{
  "prontuario_id": 3,
  "text": "01:40H: NO INÍCIO DO PLANTÃO, ESTAVA APRESENTANDO FR = 24, FC = 94, SPO2 98%, COM MELHORA DO PADRÃO RESPIRATÓRIO APÓS POSICIONAR NO LEITO  EM POSIÇÃO SEMISSENTADO E REALIZAÇÃO DE NEBULIZAÇÃO. 01:20H: CHAMADO DR VITAL BRASIL, DA NEURO, POR PACIENTE ESTAR DISPNÉICO E INSATURANDO; SPO2 88% COM SUPORTE DE OXIGÊNIO EM NÉVOA. TRANSFERIDO PARA UTI 2 ÀS 01:40H, CONFORME CONTATO PRÉVIO COM ENFERMEIRA FLORENCE. ENF. FLORENCE. TRAUMATISMO INTRACRANIANO. ENFERMAGEM MANHÃ: REALIZADO REPOSICIONAMENTO DE SNE PARA DIETOTERAPIA. INFARTO AGUDO DO MIOCÁRDIO. 03:40 h: PO de colestectomia. Comunicativa, responsiva. Com dieta liquída/pastosa. Dreno suctor em lateral de tórax com débito hemático em pouca quantidade. Eliminações presentes no período. AC Enf. PUC Florence. CALCULOSE DA VESÍCULA BILIAR SEM COLECISTITE. 10:30: Cliente alerta, orientado, comunicativo, hipocorado, aceita bem dieta VO, apresenta déficit motor em MMII e MMSS, não deambula, relata câimbras e algia em região lombar, acesso venoso periférico permeável salinizado, hemodinamicamente estável, realizou mudança de decúbito em poltrona, mantém SVD com débito satisfatório de cor amarelo claro, sem presença de grumos, evacuação presente, de aspecto normal. Enf. Florence. FRATURA DE VÉRTEBRA LOMBAR.",
  "entities": {
    "Conceito Temporal": [
      "INÍCIO",
      "PO"
    ],
    "Atividade de Assistência à Saúde": [
      "PLANTÃO"
    ],
    "Conceito Quantitativo": [
      "24",
      "94",
      "98%",
      "88%"
    ],
    "Procedimento Terapêutico ou Preventivo": [
      "NEBULIZAÇÃO",
      "DIETOTERAPIA",
      "colestectomia",
      "SVD",
      "POSICIONAR NO LEITO EM POSIÇÃO SEMISSENTADO",
      "SUPORTE DE OXIGÊNIO EM NÉVOA",
      "REPOSICIONAMENTO DE SNE",
      "dieta liquída/pastosa",
      "Dreno suctor",
      "dieta VO",
      "acesso venoso periférico",
      "mudança de decúbito"
    ],
    "Paciente ou Grupo com Deficiência": [
      "PACIENTE",
      "Cliente"
    ],
    "Sinal ou Sintoma": [
      "DISPNÉICO",
      "INSATURANDO",
      "câimbras",
      "algia"
    ],
    "Organização Relacionada à Saúde": [
      "UTI"
    ],
    "Abreviação": [
      "ENF",
      "PO",
      "AC",
      "Enf",
      "MMII",
      "MMSS",
      "SVD",
      "REPOSICIONAMENTO DE SNE"
    ],
    "Grupo Profissional ou Ocupacional": [
      "ENF",
      "Enf"
    ],
    "Achado": [
      "Comunicativa",
      "responsiva",
      "alerta",
      "orientado",
      "comunicativo",
      "hipocorado",
      "deambula",
      "permeável",
      "MELHORA DO PADRÃO RESPIRATÓRIO",
      "débito hemático em pouca quantidade",
      "Eliminações presentes",
      "déficit motor",
      "hemodinamicamente estável",
      "débito satisfatório de cor amarelo claro",
      "evacuação presente",
      "aspecto normal"
    ],
    "Localização ou Região Corporal": [
      "MMII",
      "MMSS",
      "lateral de tórax",
      "região lombar"
    ],
    "Dispositivo Médico": [
      "SVD",
      "Dreno suctor",
      "acesso venoso periférico"
    ],
    "Lesão ou Envenenamento": [
      "TRAUMATISMO INTRACRANIANO",
      "FRATURA DE VÉRTEBRA LOMBAR"
    ],
    "Doença ou Síndrome": [
      "INFARTO AGUDO DO MIOCÁRDIO",
      "CALCULOSE DA VESÍCULA BILIAR"
    ],
    "Função Fisiológica": [
      "Eliminações presentes",
      "débito satisfatório de cor amarelo claro",
      "evacuação presente"
    ]
  },
  "labels": {}
}