{
  "prontuario_id": 710,
  "text": "13:45HRS: Cliente traqueostomizado em VM nos parâmetros PSv, peep 5cmH2O, FiO2 30%, glasgow 5/6, pupilas iso / foto +, corado, mucosa oral hidratada, boa perfusão periférica, permanece sobre o leito com cabeceira elevada a 45°. Mantém com monitorização de multiparâmetros ECG, PNI, SpO2, acesso venoso periférico em MSD com srt em curso gravitacional, SNE aberta com dietoterapia em curso BI. Apresenta AC rítmica e normofonética, AP MV + com roncos esparsos, abdômen flácido e RHA +, úlcera por pressão em região sacro-coccigeana grau III com esfacelos + tecido de necrose. Faz uso de uropen + urofix com presença de débito diurético ++ de coloração amarelo claro, eliminação fecal ausente. Seguem cuidados da enfermagem. Enf° Florence, Coren 9999. EXAME GERAL E INVESTIGAÇÃO DE PESSOAS SEM QUEIXAS OU DIAGNÓSTICO RELATADO. 05:28: Paciente retorna do CC, às 23:30. POI de RMS em perna E. Mantém-se consciente, lúcida, orientada, comunicativa, normotensa, normocorada, afebril, em repouso no leito. Mantém acesso venoso em MSD com soroterapia em curso. Curativo em perna E, limpo e seco externamente. Paciente com queixa de algia leve. Segue sob cuidados. DEFEITO DE CONSOLIDAÇÃO DA FRATURA. 12H: Proveniente do POSTO 3, acordada, em jejum para procedimento cirúrgico, acesso venoso periférico em antebraço esquerdo, em uso de tipóia canadense em MSD, com tração transesquelética em MID.  Enfª Florence, COREN PR 9999. FRATURA SUBTROCANTÉRICA.",
  "entities": {
    "Paciente ou Grupo com Deficiência": [
      "Cliente",
      "Paciente"
    ],
    "Achado": [
      "traqueostomizado",
      "corado",
      "normofonética",
      "consciente",
      "lúcida",
      "orientada",
      "comunicativa",
      "normotensa",
      "normocorada",
      "afebril",
      "limpo",
      "seco",
      "acordada",
      "jejum",
      "mucosa oral hidratada",
      "perfusão periférica",
      "SNE aberta",
      "MV +",
      "RHA +",
      "com esfacelos",
      "débito diurético",
      "coloração amarelo claro",
      "repouso no leito"
    ],
    "Procedimento Terapêutico ou Preventivo": [
      "traqueostomizado",
      "VM",
      "srt",
      "dietoterapia",
      "RMS",
      "soroterapia",
      "Curativo",
      "jejum",
      "cabeceira elevada a 45°",
      "acesso venoso periférico",
      "acesso venoso",
      "procedimento cirúrgico",
      "tipóia canadense",
      "tração transesquelética"
    ],
    "Abreviação": [
      "VM",
      "peep",
      "5cmH2O",
      "FiO2",
      "ECG",
      "PNI",
      "SpO2",
      "MSD",
      "srt",
      "BI",
      "AP",
      "CC",
      "POI",
      "RMS",
      "E",
      "MID",
      "SNE aberta",
      "MV +",
      "RHA +"
    ],
    "Conceito Quantitativo": [
      "5cmH2O",
      "30%",
      "grau III"
    ],
    "Conceito Qualitativo": [
      "boa",
      "grau III",
      "coloração amarelo claro"
    ],
    "Procedimento Diagnóstico": [
      "ECG",
      "AC",
      "AP",
      "monitorização de multiparâmetros",
      "EXAME GERAL"
    ],
    "Localização ou Região Corporal": [
      "MSD",
      "abdômen",
      "MID",
      "região sacro-coccigeana"
    ],
    "Dispositivo Médico": [
      "BI",
      "uropen",
      "urofix",
      "Curativo",
      "acesso venoso periférico",
      "acesso venoso",
      "tipóia canadense"
    ],
    "Conceito Funcional": [
      "uso"
    ],
    "Grupo Populacional": [
      "PESSOAS"
    ],
    "Organização Relacionada à Saúde": [
      "CC",
      "POSTO 3"
    ],
    "Conceito Temporal": [
      "POI"
    ],
    "Parte do Corpo, Órgão ou Componente Orgânico": [
      "perna",
      "antebraço"
    ],
    "Conceito Espacial": [
      "E",
      "externamente",
      "esquerdo"
    ],
    "Negação": [
      "afebril",
      "eliminação fecal ausente"
    ],
    "Sinal ou Sintoma": [
      "algia",
      "glasgow 5/6",
      "roncos esparsos"
    ],
    "Atividade de Assistência à Saúde": [
      "cuidados",
      "cuidados da enfermagem"
    ],
    "Doença ou Síndrome": [
      "úlcera por pressão"
    ],
    "Função Fisiológica": [
      "débito diurético",
      "eliminação fecal ausente"
    ],
    "Função Patológica": [
      "DEFEITO DE CONSOLIDAÇÃO DA FRATURA"
    ],
    "Lesão ou Envenenamento": [
      "FRATURA SUBTROCANTÉRICA"
    ]
  },
  "labels": {}
}