{
  "prontuario_id": 393,
  "text": "ÀS 11:20:  REPASSADO SNE, SEM INTERCORRÊNCIA NO PROCEDIMENTO, AUSCULTA ABDOMINAL POSITIVA, RETIRO FIO GUIA. SOLICITO RAIO-X PARA AVALIAÇÃO DA POSIÇÃO. Cliente intubada com TOT n° 7.5, rima labial 22 cm DIR, VM nos parametros PCV, PI 14 cmH2O, peep 5 cmH2O, FR 11, FiO2 50%, Ramsay 6, pupilas iso / foto +, face corada, mucosa oral hidratada, boa perfusão periferica, no leito com cabeceira elevada á 45°. Mantem com monitorização de multiparametros ECG, PAM em radial ESQ oscilante, SpO2 e PVC (regua), SNG aberta narina ESQ com estase gastrica ++ de coloração biliosa, SNE aberta narina ESQ com dietoterapia em curso BI 40ml/hr, cateter venoso central duplo-lumen em subclavia DIR sem sinais flogisticos e infusão de fentanil + dormonid á 10 ml/hr + eletrolitos á 42 ml/hr em curso BI. Apresenta ausculta cardiaca ritmica e normofonetica, ausculta pulmonar MV + com roncos esparsos, abdomem flacido com RHA +, edemas MMSS e II cacifo I/II, liberação de exudato em MMSS e II, região dorsal, lesão de dermatite em dorso + escapula DIR, ctvos em região femural DIR. Faz uso de SVD aberta com debito diuretico presente ++ de coloração amarelo-claro, eliminação fecal ausente. segue cuidados. ",
  "entities": {
    "Procedimento Diagnóstico": [
      "RAIO-X",
      "AUSCULTA ABDOMINAL POSITIVA",
      "monitorização de multiparametros",
      "ausculta cardiaca",
      "ausculta pulmonar"
    ],
    "Paciente ou Grupo com Deficiência": [
      "Cliente"
    ],
    "Abreviação": [
      "DIR",
      "VM",
      "PCV",
      "PI",
      "peep",
      "FiO2",
      "ECG",
      "PAM",
      "SpO2",
      "PVC",
      "BI",
      "40ml/hr",
      "MMSS",
      "II",
      "ctvos",
      "REPASSADO SNE",
      "22 cm",
      "14 cmH2O",
      "SNG aberta",
      "narina ESQ",
      "estase gastrica",
      "SNE aberta",
      "subclavia DIR",
      "MV +",
      "RHA +",
      "cacifo I/II",
      "escapula DIR",
      "região femural DIR",
      "SVD aberta"
    ],
    "Procedimento Terapêutico ou Preventivo": [
      "VM",
      "dietoterapia",
      "infusão",
      "ctvos",
      "REPASSADO SNE",
      "RETIRO FIO GUIA",
      "cabeceira elevada á 45°",
      "SNG aberta",
      "SNE aberta",
      "cateter venoso central duplo-lumen",
      "SVD aberta"
    ],
    "Conceito Quantitativo": [
      "11",
      "50%",
      "22 cm",
      "14 cmH2O"
    ],
    "Achado": [
      "oscilante",
      "ritmica",
      "normofonetica",
      "AUSCULTA ABDOMINAL POSITIVA",
      "face corada",
      "mucosa oral hidratada",
      "boa perfusão periferica",
      "cabeceira elevada á 45°",
      "SNG aberta",
      "estase gastrica",
      "coloração biliosa",
      "SNE aberta",
      "MV +",
      "RHA +",
      "cacifo I/II",
      "SVD aberta",
      "debito diuretico presente",
      "coloração amarelo-claro"
    ],
    "Conceito Qualitativo": [
      "oscilante",
      "coloração amarelo-claro"
    ],
    "Dispositivo Médico": [
      "regua",
      "BI",
      "ctvos",
      "REPASSADO SNE",
      "RETIRO FIO GUIA",
      "SNG aberta",
      "SNE aberta",
      "cateter venoso central duplo-lumen",
      "SVD aberta"
    ],
    "Substância Farmacológica": [
      "fentanil",
      "dormonid",
      "eletrolitos"
    ],
    "Substância Química Orgânica": [
      "fentanil",
      "dormonid"
    ],
    "Localização ou Região Corporal": [
      "abdomem",
      "MMSS",
      "dorso",
      "rima labial",
      "região dorsal",
      "região femural DIR"
    ],
    "Sinal ou Sintoma": [
      "edemas",
      "Ramsay 6",
      "roncos esparsos",
      "cacifo I/II",
      "liberação de exudato"
    ],
    "Conceito Funcional": [
      "uso"
    ],
    "Atividade de Assistência à Saúde": [
      "cuidados"
    ],
    "Parte do Corpo, Órgão ou Componente Orgânico": [
      "rima labial",
      "radial ESQ",
      "narina ESQ",
      "subclavia DIR",
      "escapula DIR"
    ],
    "Lesão ou Envenenamento": [
      "lesão de dermatite"
    ],
    "Função Fisiológica": [
      "debito diuretico presente",
      "eliminação fecal ausente"
    ],
    "Negação": [
      "eliminação fecal ausente"
    ]
  },
  "labels": {}
}