{
  "prontuario_id": 942,
  "text": "Em 02/11/07, 11:50H: SEDADA, PUPILAS MIÓTICAS E ISOCÓRICAS BRADIFOTORREAGENTES. SNG ABERTA À D COM DÉBITO DE COLORAÇÃO MARROM EM GRANDE QUANTIDADE, SNG À E INFUNDINDO DIETA EM BOMBA A 50 ML/H. ACESSO VENOSO CENTRAL EM SUBCLÁVIA D INFUNDINDO EM BI DORMONID. NEOPLASIA MALIGNA DO RETO. Às 13:30h: Sedado, intubado sob ventilação mecânica. Mantém SNG para alimentação. Diurese cítrica em SVD. Apresenta moderada quantidade de secreção traqueobrônquica. Pele íntegra. Enfª Florence Nightingale. EPILEPSIA NAO ESPECIFICADA. Às 21:00, em 04/09/07: Veio de centro cirurgico de maca, consciente, comunicativo, lucido e orientado, eupneico, afebril,  hipocorado, com curativo tipo capacete de crepe com dreno de suctor com débito hemático, ausculta pulmonar com MV +, abdomen plano e fla . CONCUSSAO CEREBRAL. Sonolento, não responsivo, SNE para dieta, AVP em pé D com SRT, edema de MMII, eliminações em fralda. Segue sob cuidados. RETENCAO URINARIA. ÀS 14:59h: ALTA HOSPITALAR. VAI COM RECEITA, ORIENTAÇÕES, RESUMO DE ALTA. MARCADO RETORNO PARA CIRURGIA GERAL. ACALASIA DO CARDIA. REALIZADO DOPPLER TRANSCRANIANO ÀS 11:00 HORAS, PELA DRA MARIA (LAUDO: PERSISTE DISCRETO FLUXO NAS ARTÉRIAS VERTEBRAIS E ACM D). PIC OSCILANTE 87, 64 MMHG); CURATIVO CEFÁLICO COM EXTRAVASAMENTO DE MASSA ENCEFÁLICA A DIREITA MAIS OTORRAGIA EM TRAUMATISMOS MULTIPLOS NAO ESPECIFICADOS.",
  "entities": {
    "Procedimento Terapêutico ou Preventivo": [
      "SEDADA",
      "Sedado",
      "SVD",
      "AVP",
      "SRT",
      "SNG ABERTA",
      "ACESSO VENOSO CENTRAL",
      "ventilação mecânica",
      "SNG para alimentação",
      "curativo tipo capacete de crepe",
      "dreno de suctor",
      "SNE para dieta",
      "CURATIVO CEFÁLICO"
    ],
    "Parte do Corpo, Órgão ou Componente Orgânico": [
      "PUPILAS",
      "SUBCLÁVIA D",
      "pé D"
    ],
    "Sinal ou Sintoma": [
      "MIÓTICAS",
      "BRADIFOTORREAGENTES",
      "afebril",
      "hipocorado",
      "Sonolento",
      "edema",
      "OTORRAGIA",
      "DÉBITO DE COLORAÇÃO MARROM",
      "moderada quantidade de secreção traqueobrônquica",
      "RETENCAO URINARIA",
      "PIC OSCILANTE",
      "EXTRAVASAMENTO DE MASSA ENCEFÁLICA A DIREITA"
    ],
    "Achado": [
      "ISOCÓRICAS",
      "intubado",
      "consciente",
      "comunicativo",
      "lucido",
      "orientado",
      "eupneico",
      "plano",
      "fla",
      "responsivo",
      "Diurese cítrica",
      "Pele íntegra",
      "débito hemático",
      "MV +",
      "eliminações em fralda"
    ],
    "Conceito Espacial": [
      "D",
      "E"
    ],
    "Dispositivo Médico": [
      "SNG",
      "SVD",
      "maca",
      "AVP",
      "SNG ABERTA",
      "ACESSO VENOSO CENTRAL",
      "curativo tipo capacete de crepe",
      "dreno de suctor",
      "SNE para dieta",
      "CURATIVO CEFÁLICO"
    ],
    "Dispositivo de Administração de Medicamento": [
      "BOMBA",
      "BI"
    ],
    "Abreviação": [
      "BI",
      "SVD",
      "Enfª",
      "fla",
      "AVP",
      "SRT",
      "MMII",
      "SNG ABERTA",
      "SUBCLÁVIA D",
      "SNG para alimentação",
      "MV +",
      "SNE para dieta",
      "pé D",
      "PIC OSCILANTE"
    ],
    "Substância Farmacológica": [
      "DORMONID"
    ],
    "Substância Química Orgânica": [
      "DORMONID"
    ],
    "Grupo Profissional ou Ocupacional": [
      "Enfª",
      "CIRURGIA GERAL"
    ],
    "Doença ou Síndrome": [
      "EPILEPSIA",
      "ACALASIA DO CARDIA"
    ],
    "Negação": [
      "afebril",
      "não"
    ],
    "Localização ou Região Corporal": [
      "abdomen",
      "MMII"
    ],
    "Atividade de Assistência à Saúde": [
      "cuidados",
      "ORIENTAÇÕES",
      "RETORNO",
      "ALTA HOSPITALAR"
    ],
    "Produto Intelectual": [
      "RECEITA",
      "RESUMO DE ALTA"
    ],
    "Função Patológica": [
      "OTORRAGIA"
    ],
    "Conceito Qualitativo": [
      "GRANDE QUANTIDADE",
      "moderada quantidade de secreção traqueobrônquica"
    ],
    "Conceito Quantitativo": [
      "50 ML/H",
      "87 , 64 MMHG"
    ],
    "Processo Neoplásico": [
      "NEOPLASIA MALIGNA DO RETO"
    ],
    "Função Fisiológica": [
      "Diurese cítrica",
      "eliminações em fralda"
    ],
    "Organização Relacionada à Saúde": [
      "centro cirurgico",
      "CIRURGIA GERAL"
    ],
    "Objeto Manufaturado": [
      "centro cirurgico"
    ],
    "Procedimento Diagnóstico": [
      "ausculta pulmonar",
      "DOPPLER TRANSCRANIANO"
    ],
    "Lesão ou Envenenamento": [
      "CONCUSSAO CEREBRAL",
      "TRAUMATISMOS MULTIPLOS"
    ],
    "Resultado Laboratorial ou de Teste": [
      "PERSISTE DISCRETO FLUXO NAS ARTÉRIAS VERTEBRAIS E ACM D"
    ],
    "Atributo Clínico": [
      "PIC OSCILANTE"
    ]
  },
  "labels": {}
}