{
  "prontuario_id": 898,
  "text": "ÀS 17H16MIN: SONDA NASOENTERAL COM DIETA EM CURSO, TRAQUEOSTOMIA COM O2, ABDOMEN PLANO E FLÁCIDO, ACESSO VENOSO PERIFÉRICO EM FACE ANTERIOR DO ANTEBRAÇO E, ULCERA POR PRESSÃO GRAU II EM REGIÃO SACRA, COM SECREÇÃO EM BASTANTE QUANTIDADE E EM REGIÃO CALCÂNEA, DIURESE EM UROPEN, EVACUAÇÃO 1X. ACADÊMICA DE ENFERMAGEM DO 8ºPERÍODO FLORENCE NIGHTINGALE. ORIENTADA PELA ENFERMEIRA FLORENCE NIGHTINGALE. SINDROME DE GUILLAIN BARRE. ÀS 12:54: 4º DI, Hx ICC descompensado + has + depressão + astenia + fraqueza. Consciente, gemente, pouco comunicativa. Mantendo monitorização  P 81, PA 103/74, sat O2 97%. Mantendo O2 sob máscara 3 ml/h. BCR Hiperfonéticas com sopro sistólico, ausculta pulmonar roncos + congestão. Acesso central em subclávia à E com soroterapia + hyponor 15 ml/h em BI. Abdomen globoso, flácido, RHA hiperativos, refere algia à palpação. Lesão em região lombossacra grau II. SVD com débido de 100 ml com coloração amarelo escuro com presença de grumos. Fazendo uso de fralda, evacuação de aspecto líquido. Permancendo na sala de emergência, aguardando vaga de UTI. Segue sob os cuidados de enfermagem . Enfº Florence Nightingale, COREN XXXX. INSUFICIENCIA CARDIACA. REALIZADO TENTATIVAS DE PASSAGEM DE SNE SEM SUCESSO, COMUNICADO DRA ALICE. INSUFICIENCIA RESPIRATORIA AGUDA.",
  "entities": {
    "Alimento": [
      "DIETA"
    ],
    "Localização ou Região Corporal": [
      "ABDOMEN",
      "Abdomen",
      "REGIÃO SACRA",
      "REGIÃO CALCÂNEA",
      "região lombossacra"
    ],
    "Achado": [
      "PLANO",
      "FLÁCIDO",
      "EVACUAÇÃO",
      "Consciente",
      "BCR",
      "flácido"
    ],
    "Abreviação": [
      "E",
      "Hx",
      "has",
      "BCR",
      "BI",
      "SVD",
      "UTI",
      "Enfº",
      "ICC descompensado",
      "3 ml/h",
      "15 ml/h",
      "RHA hiperativos",
      "PASSAGEM DE SNE"
    ],
    "Conceito Espacial": [
      "E"
    ],
    "Substância Corporal": [
      "SECREÇÃO"
    ],
    "Dispositivo Médico": [
      "UROPEN",
      "BI",
      "SVD",
      "SONDA NASOENTERAL",
      "ACESSO VENOSO PERIFÉRICO",
      "Acesso central"
    ],
    "Função Fisiológica": [
      "EVACUAÇÃO"
    ],
    "Doença ou Síndrome": [
      "has",
      "depressão",
      "ULCERA POR PRESSÃO",
      "SINDROME DE GUILLAIN BARRE",
      "ICC descompensado",
      "INSUFICIENCIA CARDIACA",
      "INSUFICIENCIA RESPIRATORIA AGUDA"
    ],
    "Sinal ou Sintoma": [
      "astenia",
      "fraqueza",
      "gemente",
      "Hiperfonéticas",
      "roncos",
      "congestão",
      "globoso",
      "sopro sistólico",
      "RHA hiperativos",
      "algia à palpação",
      "presença de grumos",
      "evacuação de aspecto líquido"
    ],
    "Procedimento Diagnóstico": [
      "monitorização",
      "ausculta pulmonar"
    ],
    "Conceito Quantitativo": [
      "81",
      "103/74",
      "97%",
      "3 ml/h",
      "15 ml/h",
      "100 ml"
    ],
    "Parte do Corpo, Órgão ou Componente Orgânico": [
      "subclávia"
    ],
    "Procedimento Terapêutico ou Preventivo": [
      "soroterapia",
      "SVD",
      "SONDA NASOENTERAL",
      "TRAQUEOSTOMIA COM O2",
      "ACESSO VENOSO PERIFÉRICO",
      "O2 sob máscara",
      "Acesso central",
      "PASSAGEM DE SNE"
    ],
    "Substância Farmacológica": [
      "hyponor"
    ],
    "Lesão ou Envenenamento": [
      "Lesão"
    ],
    "Objeto Manufaturado": [
      "fralda"
    ],
    "Organização Relacionada à Saúde": [
      "UTI",
      "sala de emergência"
    ],
    "Conceito Qualitativo": [
      "BASTANTE QUANTIDADE"
    ],
    "Atividade de Assistência à Saúde": [
      "cuidados de enfermagem"
    ]
  },
  "labels": {}
}