{
  "prontuario_id": 551,
  "text": "Às 18:09 Hr: Paciente em 1º PO de fratura de fêmur esquerdo, hipotenso, suspenso medicações para hipertensão pela Dra. Alice. Aceitando bem a alimentação VO, com acesso venoso periférico em punho esquedo salinizado. Eliminação vesical espontânea. Curativo e FRATURA DO COLO DO FEMUR. ÀS 16:16: AGUARDANDO AMBULÂNCIA PARA ALTA HOSPITALAR. ABDOME AGUDO. Em 19/06/2007, 09:31 h: Paciente no centro cirúrgico em procedimento. Ausente do setor. TRAUMATISMOS MULTIPLOS NAO ESPECIFICADOS. EM 16/02/2007, 13:30 HORAS: RETORNOU DO POSTO 03 POR QUADRO DE INSUFICIÊNCIA RESPIRATÓRIA. APRESENTA-SE ACORDADO, CONSCIENTE, ORIENTADO, COM PERÍODOS DE AGITAÇÃO PSICOMOTORA, PERMANECE CONTIDO NO LEITO POR PRECAUÇÃO. COM PUPILAS ISOCÓRICAS E FOTORREAGENTES. TRAUMATISMOS MULTIPLOS NAO ESPECIFICADOS. 5º DI, abscesso cervical? TU de assoalho da boca? Lúcido, orientado, comunicativo, deambulando. Refere aceitação da dieta após \"drenagem\", sem SNE. Eupnêico, em ar ambiente, acianótico. Aumento de volume em maxilar inferior, ponto de drenagem cicatrizado. ABSCESSO RETROFARINGEO E PARAFARINGEO. ÀS 14H: PACIENTE VÍTIMA DE AGRESSÃO COM 1 PEDRA, COM FX DE FACE, CONSCIENTE, COMUNICATIVO, DEAMBULANTE, AFEBRIL, EUPNÉICO, AVP EM MSE, APRESENTOU CONVULSÃO DURANTE A MANHÃ 1 VEZ E SANGRAMENTO NO ROSTO NO LADO D, APRESENTA HEMATOMA NOS OLHOS, NEGA ALGIA, ACEI. TRAUMATISMOS MULTIPLOS NAO ESPECIFICADOS.",
  "entities": {
    "Paciente ou Grupo com Deficiência": [
      "Paciente",
      "PACIENTE",
      "VÍTIMA"
    ],
    "Conceito Temporal": [
      "PO",
      "após"
    ],
    "Abreviação": [
      "PO",
      "DI",
      "SNE",
      "AVP",
      "MSE",
      "D",
      "ACEI",
      "TU de assoalho da boca",
      "FX DE FACE"
    ],
    "Sinal ou Sintoma": [
      "hipotenso",
      "CONVULSÃO",
      "ALGIA",
      "PERÍODOS DE AGITAÇÃO PSICOMOTORA",
      "HEMATOMA NOS OLHOS"
    ],
    "Grupo Profissional ou Ocupacional": [
      "Dra"
    ],
    "Conceito Espacial": [
      "esquedo",
      "D"
    ],
    "Conceito Qualitativo": [
      "salinizado"
    ],
    "Dispositivo Médico": [
      "Curativo",
      "SNE",
      "AVP",
      "acesso venoso periférico"
    ],
    "Procedimento Terapêutico ou Preventivo": [
      "Curativo",
      "procedimento",
      "\"drenagem\"",
      "SNE",
      "AVP",
      "acesso venoso periférico",
      "CONTIDO NO LEITO POR PRECAUÇÃO",
      "aceitação da dieta"
    ],
    "Atividade de Assistência à Saúde": [
      "procedimento",
      "ALTA HOSPITALAR"
    ],
    "Organização Relacionada à Saúde": [
      "POSTO",
      "centro cirúrgico"
    ],
    "Achado": [
      "ACORDADO",
      "CONSCIENTE",
      "ORIENTADO",
      "Lúcido",
      "orientado",
      "comunicativo",
      "deambulando",
      "acianótico",
      "COMUNICATIVO",
      "DEAMBULANTE",
      "AFEBRIL",
      "EUPNÉICO",
      "SANGRAMENTO",
      "Eliminação vesical espontânea",
      "PUPILAS ISOCÓRICAS E FOTORREAGENTES",
      "Eupnêico , em ar ambiente",
      "ponto de drenagem cicatrizado"
    ],
    "Negação": [
      "sem",
      "acianótico",
      "AFEBRIL",
      "NEGA"
    ],
    "Localização ou Região Corporal": [
      "MSE",
      "ROSTO",
      "maxilar inferior"
    ],
    "Lesão ou Envenenamento": [
      "fratura de fêmur esquerdo",
      "FRATURA DO COLO DO FEMUR",
      "TRAUMATISMOS MULTIPLOS NAO ESPECIFICADOS",
      "AGRESSÃO COM 1 PEDRA",
      "FX DE FACE"
    ],
    "Substância Farmacológica": [
      "medicações para hipertensão"
    ],
    "Função Fisiológica": [
      "Eliminação vesical espontânea"
    ],
    "Doença ou Síndrome": [
      "ABDOME AGUDO",
      "INSUFICIÊNCIA RESPIRATÓRIA",
      "abscesso cervical",
      "ABSCESSO RETROFARINGEO E PARAFARINGEO"
    ],
    "Processo Neoplásico": [
      "TU de assoalho da boca"
    ],
    "Função Patológica": [
      "Aumento de volume"
    ]
  },
  "labels": {}
}