{
  "prontuario_id": 249,
  "text": "PACIENTE DE 50 ANOS: AFEBRIL, CORADA, POUCO RESPONSIVA, ACEITANDO DIETA VIA ORAL, AVP EM MSD COM SOROTERAPIA EM CURSO, SSVV ESTAVÉIS, ELIMINAÇÕES  FISIOLOGICAS DIARIAS, SEM QUEIXAS ALGICAS, SEGUE SOB CUIDADOS DE ENFERMAGEM. NEOPLASIA MALIGNA DO CEREBELO. ÀS 15:30: CONSCIENTE, LUCIDO, EUPNEICO, COMUNICATIVO, REPOUSO NO LEITO, SEM QUEIXAS ALGICAS NO MOMENTO, APRESENTA PUPILAS ISOCORICAS, PELE E MUCOSA CORADA E HIDRATADA, ABDOMEN PLANO, FLACIDO, INDOLOR A PALPAÇÃO, MANTEM ACESSO VENOSO PERIFERICO EM MSE SALINIZADO. OSTEOMIELITE CRONICA COM SEIO DRENANTE. Às 15:40: Permanece alerta e orientada. Relata bom estado geral. Nega algias. Apresenta boa aceitação de dieta. Não mantém avp, medicações VO. Relata diurese espontânea presente, de aspecto \"menos concentrado\", em quantidade moderada. Realizou raio-x durante. NEFRITE TUBULO INTERSTICIAL AGUDA. ÀS 16:30: PACIENTE RETORNOU DO HOSPITAL-DIA LÚCIDO, POREM SONOLENTO, COM CURATIVO EM COXA ESQUERDA E MIE COM ASPECTO LIMPO E SECO, ORIENTADA ENFERMAGEM A NÃO TROCAR O CURATIVO, AVP EM MSE, SEGUE SOB CUIDADOS DE ENFERMAGEM. TRAUMATISMOS MULTIPLOS NAO ESPECIFICADOS.",
  "entities": {
    "Paciente ou Grupo com Deficiência": [
      "PACIENTE"
    ],
    "Achado": [
      "AFEBRIL",
      "CORADA",
      "CONSCIENTE",
      "LUCIDO",
      "EUPNEICO",
      "COMUNICATIVO",
      "HIDRATADA",
      "PLANO",
      "FLACIDO",
      "alerta",
      "orientada",
      "LÚCIDO",
      "LIMPO",
      "SECO",
      "ACEITANDO DIETA VIA ORAL",
      "SSVV ESTAVÉIS",
      "ELIMINAÇÕES FISIOLOGICAS DIARIAS",
      "REPOUSO NO LEITO",
      "PUPILAS ISOCORICAS",
      "bom estado geral",
      "boa aceitação de dieta",
      "diurese espontânea",
      "aspecto \"menos concentrado\""
    ],
    "Negação": [
      "AFEBRIL",
      "INDOLOR",
      "Nega",
      "NÃO"
    ],
    "Abreviação": [
      "AVP",
      "MSD",
      "MSE",
      "avp",
      "MIE",
      "SSVV ESTAVÉIS",
      "medicações VO"
    ],
    "Dispositivo Médico": [
      "AVP",
      "avp",
      "CURATIVO",
      "ACESSO VENOSO PERIFERICO"
    ],
    "Procedimento Terapêutico ou Preventivo": [
      "AVP",
      "avp",
      "CURATIVO",
      "SOROTERAPIA EM CURSO",
      "REPOUSO NO LEITO",
      "ACESSO VENOSO PERIFERICO",
      "TROCAR O CURATIVO"
    ],
    "Localização ou Região Corporal": [
      "MSD",
      "ABDOMEN",
      "MSE",
      "MIE"
    ],
    "Parte do Corpo, Órgão ou Componente Orgânico": [
      "PELE",
      "COXA"
    ],
    "Procedimento Diagnóstico": [
      "PALPAÇÃO",
      "raio-x"
    ],
    "Conceito Qualitativo": [
      "SALINIZADO"
    ],
    "Sinal ou Sintoma": [
      "algias",
      "SONOLENTO",
      "QUEIXAS ALGICAS"
    ],
    "Organização Relacionada à Saúde": [
      "HOSPITAL-DIA"
    ],
    "Conceito Espacial": [
      "ESQUERDA"
    ],
    "Grupo Profissional ou Ocupacional": [
      "ENFERMAGEM"
    ],
    "Função Fisiológica": [
      "ELIMINAÇÕES FISIOLOGICAS DIARIAS",
      "diurese espontânea"
    ],
    "Atividade de Assistência à Saúde": [
      "CUIDADOS DE ENFERMAGEM"
    ],
    "Processo Neoplásico": [
      "NEOPLASIA MALIGNA DO CEREBELO"
    ],
    "Conceito Temporal": [
      "NO MOMENTO"
    ],
    "Doença ou Síndrome": [
      "OSTEOMIELITE CRONICA COM SEIO DRENANTE",
      "NEFRITE TUBULO INTERSTICIAL AGUDA"
    ],
    "Substância Farmacológica": [
      "medicações VO"
    ],
    "Lesão ou Envenenamento": [
      "TRAUMATISMOS MULTIPLOS NAO ESPECIFICADOS"
    ]
  },
  "labels": {}
}