{
  "prontuario_id": 324,
  "text": "Às 10:00 horas: Desligada sedação por determinação do Dr Vital Brasil; aguarda melhores condições para desmame ventilatório. OUTRAS FORMAS DE OBSTRUCAO INTESTINAL E AS NAO ESPECIFICADAS. PACIENTE COM LESÃO TENDINOSA EM MSE, HÁ 5 DIAS, COM VIDRO. NÃO FLEXIONA 4º QDT E. CTVO COM TALA GESSADA, USO DE TIPÓIA. PERFUSÃO DE MSE PRESERVADA. INTERNA P/ GRUPO DA MÃO. ORIENTO JEJUM APÓS 24 H. OUTRA CONTRATURA DE TENDAO BAINHA. Às 16:40: CONSCIENTE, LUCIDO, EUPNEICO, COMUNICATIVO, EM REPOUSO NO LEITO, SEM QUEIXAS ALGICAS NO MOMENTO, APRESENTA PUPILAS ISOCORICAS, PELE E MUCOSA CORADA E HIDRATADA, ABDOMEN PLANO, FLACIDO, INDOLOR A PALPAÇÃO, PLEGIA EM MID, ACEITANDO BEM A DIETA OFERECIDA. FRATURA DE VERTEBRA TORACICA. Em 28/05/2007, 08:01h: Sonolenta, torporosa, pouco responsiva, hipocorada, mucosas coradas e úmidas. Apresenta abdome flácido, RHA + . Mantém SNE para alimentação por bomba infusora. Diurese limpida em bom volume, não há relato de evacuação nas últimas 18h. SINDROME DA ARTERIA CEREBRAL MEDIA.",
  "entities": {
    "Procedimento Terapêutico ou Preventivo": [
      "sedação",
      "CTVO",
      "TIPÓIA",
      "JEJUM",
      "TALA GESSADA",
      "REPOUSO NO LEITO",
      "SNE para alimentação"
    ],
    "Paciente ou Grupo com Deficiência": [
      "PACIENTE"
    ],
    "Dispositivo Médico": [
      "CTVO",
      "TIPÓIA",
      "TALA GESSADA"
    ],
    "Abreviação": [
      "CTVO",
      "FLEXIONA",
      "4º QDT",
      "PERFUSÃO DE MSE PRESERVADA",
      "PLEGIA EM MID",
      "RHA +",
      "SNE para alimentação"
    ],
    "Conceito Funcional": [
      "USO"
    ],
    "Atividade de Assistência à Saúde": [
      "ORIENTO",
      "desmame ventilatório"
    ],
    "Achado": [
      "CONSCIENTE",
      "LUCIDO",
      "EUPNEICO",
      "COMUNICATIVO",
      "CORADA",
      "HIDRATADA",
      "PLANO",
      "FLACIDO",
      "coradas",
      "úmidas",
      "limpida",
      "evacuação",
      "FLEXIONA",
      "4º QDT",
      "PERFUSÃO DE MSE PRESERVADA",
      "REPOUSO NO LEITO",
      "PUPILAS ISOCORICAS",
      "ACEITANDO BEM",
      "RHA +",
      "bom volume"
    ],
    "Parte do Corpo, Órgão ou Componente Orgânico": [
      "PELE",
      "MUCOSA",
      "mucosas"
    ],
    "Localização ou Região Corporal": [
      "ABDOMEN",
      "abdome"
    ],
    "Negação": [
      "INDOLOR"
    ],
    "Procedimento Diagnóstico": [
      "PALPAÇÃO"
    ],
    "Sinal ou Sintoma": [
      "Sonolenta",
      "torporosa",
      "hipocorada",
      "QUEIXAS ALGICAS",
      "PLEGIA EM MID"
    ],
    "Função Fisiológica": [
      "Diurese",
      "evacuação"
    ],
    "Doença ou Síndrome": [
      "OBSTRUCAO INTESTINAL",
      "CONTRATURA DE TENDAO BAINHA",
      "SINDROME DA ARTERIA CEREBRAL MEDIA"
    ],
    "Lesão ou Envenenamento": [
      "LESÃO TENDINOSA",
      "CONTRATURA DE TENDAO BAINHA",
      "FRATURA DE VERTEBRA TORACICA"
    ],
    "Organização Relacionada à Saúde": [
      "GRUPO DA MÃO"
    ],
    "Conceito Temporal": [
      "NO MOMENTO"
    ]
  },
  "labels": {}
}