{
  "prontuario_id": 739,
  "text": "Às 02:10 H: CLIENTE MANTEM JEJUM PARA REALIZAR EXAME, ORIENTADA, AFEBRIL, EUPNEICA. SEGUE EM OBSERVAÇÃO E CUIDADOS. Às 20:00h: consciente, traqueostomizado, febril, tº 38.5º c, apresenta disfonia, mantendo oxigenioterapia sob névoa, dieta via gastro, acesso venoso periferico em região do pé esquerdo, abdomen distendido, incisão cirurgica em região cefalica seca; segue acompanhado pelos familiares e sob cuidados. Às 13:40H: PROVENIENTE DO PA, CALMA, COMUNICATIVA, EUPNEICA EM AR AMBIENTE, REFERE MELHORA DA DOR EM REGIÃO ABDOMINAL QUE IRRADIAVA PARA REGIÃO INGUINAL BILATERAL. REFERE TAMBÉM QUE APRESENTOU NAUSEAS E VOMITOS APÓS ADMINISTRAÇÃO DA MEDICAÇÃO AINDA NO PA. ACESSO VENOSO PERIFÉRICO SALINIZADO EM MSD. DIURESE PRESENTE ESPONTANEAMENTE. SEGUE CUIDADOS. Retorna do cc após realização de litotripsia, acordado, comunicativo, sem queixas algicas, mantendo avp permeável em mse com soroterapia em curso, segue sob cuidados e observação de enfermagem. EVOLUÇAO DIA 01/02/10: ACORDADO, RESPONSIVO, SEM QUEIXAS ALGICAS NO MOMENTO. AGENDADO TOMOGRAFIA DE ABDOMEN + PELVE PARA 02/02/10, AS 09:30H. E SOLICITADO ENDOSCOPIA NO SISTEMA.",
  "entities": {
    "Paciente ou Grupo com Deficiência": [
      "CLIENTE"
    ],
    "Procedimento Terapêutico ou Preventivo": [
      "JEJUM",
      "traqueostomizado",
      "litotripsia",
      "avp",
      "oxigenioterapia sob névoa",
      "dieta via gastro",
      "acesso venoso periferico",
      "ACESSO VENOSO PERIFÉRICO",
      "soroterapia em curso"
    ],
    "Achado": [
      "JEJUM",
      "ORIENTADA",
      "AFEBRIL",
      "EUPNEICA",
      "consciente",
      "traqueostomizado",
      "seca",
      "CALMA",
      "COMUNICATIVA",
      "SALINIZADO",
      "acordado",
      "comunicativo",
      "permeável",
      "ACORDADO",
      "RESPONSIVO",
      "oxigenioterapia sob névoa",
      "EUPNEICA EM AR AMBIENTE",
      "MELHORA DA DOR",
      "DIURESE PRESENTE ESPONTANEAMENTE"
    ],
    "Procedimento Diagnóstico": [
      "EXAME",
      "TOMOGRAFIA",
      "ENDOSCOPIA"
    ],
    "Negação": [
      "AFEBRIL"
    ],
    "Atividade de Assistência à Saúde": [
      "OBSERVAÇÃO",
      "CUIDADOS",
      "cuidados",
      "SOLICITADO",
      "sob cuidados",
      "observação de enfermagem"
    ],
    "Sinal ou Sintoma": [
      "febril",
      "disfonia",
      "NAUSEAS",
      "VOMITOS",
      "abdomen distendido",
      "queixas algicas",
      "QUEIXAS ALGICAS"
    ],
    "Abreviação": [
      "tº",
      "PA",
      "MSD",
      "cc",
      "avp",
      "mse",
      "dieta via gastro"
    ],
    "Atributo Clínico": [
      "tº"
    ],
    "Conceito Quantitativo": [
      "38"
    ],
    "Grupo Familiar": [
      "familiares"
    ],
    "Organização Relacionada à Saúde": [
      "PA",
      "cc"
    ],
    "Localização ou Região Corporal": [
      "MSD",
      "mse",
      "ABDOMEN",
      "região do pé esquerdo",
      "região cefalica",
      "REGIÃO ABDOMINAL",
      "INGUINAL BILATERAL"
    ],
    "Dispositivo Médico": [
      "avp",
      "acesso venoso periferico",
      "ACESSO VENOSO PERIFÉRICO"
    ],
    "Parte do Corpo, Órgão ou Componente Orgânico": [
      "PELVE"
    ],
    "Lesão ou Envenenamento": [
      "incisão cirurgica"
    ],
    "Função Fisiológica": [
      "DIURESE PRESENTE ESPONTANEAMENTE"
    ]
  },
  "labels": {}
}