{
  "prontuario_id": 131,
  "text": "Em 13/04/2010, 9H: Com Glasgow de 13, agitado, mantendo contenção no leito. Respiração espontânea sob nevoa umida a 5l, mantem com monitorização cardiaca, oximetria digital, PNI continuos. Apresenta tosse com expectoração amarelada. Mantem com sonda orogastrica aberta sem debito e sonda oroenteral recebendo nutrição enteral a 75 ml/h. Acesso venoso periferico em braço D recebendo solução salina em BI. BCRNF. Ausculta pulmonar com roncos em ápice E e murmurios vesiculares a D. RHA normoativos. Realizado os curativos das úlceras de pressão com gaze não aderente e região coccígea que apresenta esfacelos e bordos avermelhados, aplicado tambem hidrogel, ocluido com gaze e micropore, em região articular E em ulcera lacerada, aplicado gaze não aderente, ocluido com gaze e atadura e em tornozelo D, em ulcera com placa purulenta, aplicado gaze não aderente e ocluido com gaze e atadura. Sonda vesical de demora com diurese efetiva nas 24h, porem apresenta grumos. Não evacuou ate o momento.",
  "entities": {
    "Sinal ou Sintoma": [
      "agitado",
      "tosse",
      "esfacelos",
      "grumos",
      "Glasgow de 13",
      "expectoração amarelada",
      "roncos em ápice E",
      "bordos avermelhados",
      "ulcera com placa purulenta"
    ],
    "Conceito Quantitativo": [
      "5l",
      "75 ml/h"
    ],
    "Abreviação": [
      "PNI",
      "BI",
      "BCRNF",
      "braço D",
      "roncos em ápice E",
      "murmurios vesiculares a D",
      "RHA normoativos",
      "região articular E",
      "tornozelo D",
      "diurese efetiva nas 24h"
    ],
    "Achado": [
      "aberta",
      "BCRNF",
      "evacuou",
      "murmurios vesiculares a D",
      "RHA normoativos",
      "diurese efetiva nas 24h"
    ],
    "Dispositivo de Administração de Medicamento": [
      "BI"
    ],
    "Atividade de Assistência à Saúde": [
      "Realizado",
      "aplicado"
    ],
    "Procedimento Terapêutico ou Preventivo": [
      "curativos",
      "ocluido",
      "contenção no leito",
      "Respiração espontânea sob nevoa umida",
      "sonda oroenteral",
      "nutrição enteral",
      "Acesso venoso periferico",
      "solução salina",
      "aplicado gaze não aderente",
      "Sonda vesical de demora"
    ],
    "Dispositivo Médico": [
      "curativos",
      "gaze",
      "micropore",
      "atadura",
      "sonda oroenteral",
      "Acesso venoso periferico",
      "Sonda vesical de demora"
    ],
    "Substância Farmacológica": [
      "hidrogel"
    ],
    "Substância Química Orgânica": [
      "hidrogel"
    ],
    "Negação": [
      "Não"
    ],
    "Função Fisiológica": [
      "evacuou",
      "diurese efetiva nas 24h"
    ],
    "Procedimento Diagnóstico": [
      "monitorização cardiaca",
      "oximetria digital",
      "Ausculta pulmonar"
    ],
    "Substância Corporal": [
      "expectoração amarelada"
    ],
    "Parte do Corpo, Órgão ou Componente Orgânico": [
      "braço D"
    ],
    "Doença ou Síndrome": [
      "úlceras de pressão",
      "ulcera lacerada"
    ],
    "Localização ou Região Corporal": [
      "região coccígea",
      "região articular E",
      "tornozelo D"
    ]
  },
  "labels": {}
}