{
  "prontuario_id": 885,
  "text": "Às 02:38: Criança alerta, ativa, reativa, normotensa, normocorada, afebril no momento. Paciente em pré-operatório de amigdalectomia. Permanece em jejum desde 24 horas, para procedimento em CC. Segue sob cuidados. AMIGDALITE CRONICA. Às 12H: PROVENIENTE DO INTERNAMENTO ELETIVO, CALMO, COMUNICATIVO, EM CADEIRA DE RODAS, EUPNEICO EM AR AMBIENTE, REFERE DOR EM MMII. SEM ACESSO. ELIMINAÇÕES PRESENTES. ENTRO EM CONTATO COM DR VITAL BRASIL, INFORMO SOBRE O INTERNAMENTO, O MESMO CIENTE, QUESTIONO SOBRE A DIETA, PACIENTE NÃO É PORTADOR DE DIABETES, NEM HIPERTENSÃO, LIBERADO DIETA LIVRE. SEGUE SOB CUIDADOS DE ENFERMAGEM.  ENF FLORENCE NIGHTINGALE, COREN XXXX. PARAPLEGIA ESPASTICA. Às 03h: retirou SNG com infusao de dieta, sendo orientado pelo plantao que nao repassar, para nova reavaliaçao pela manha. Sendo suspenso dieta via SNG. Enfermeira Florence Nightingale. TRAUMATISMO INTRACRANIANO.",
  "entities": {
    "Grupo Etário": [
      "Criança"
    ],
    "Achado": [
      "alerta",
      "ativa",
      "reativa",
      "normotensa",
      "normocorada",
      "afebril",
      "jejum",
      "CALMO",
      "COMUNICATIVO",
      "EUPNEICO EM AR AMBIENTE",
      "ELIMINAÇÕES PRESENTES",
      "DIETA LIVRE"
    ],
    "Negação": [
      "afebril"
    ],
    "Paciente ou Grupo com Deficiência": [
      "Paciente",
      "PACIENTE"
    ],
    "Conceito Temporal": [
      "pré-operatório"
    ],
    "Procedimento Terapêutico ou Preventivo": [
      "amigdalectomia",
      "jejum",
      "procedimento",
      "ACESSO",
      "infusao de dieta"
    ],
    "Organização Relacionada à Saúde": [
      "CC"
    ],
    "Abreviação": [
      "CC",
      "ENF",
      "DOR EM MMII",
      "retirou SNG"
    ],
    "Atividade de Assistência à Saúde": [
      "cuidados",
      "INTERNAMENTO",
      "plantao",
      "INTERNAMENTO ELETIVO",
      "CUIDADOS DE ENFERMAGEM"
    ],
    "Dispositivo Médico": [
      "ACESSO",
      "CADEIRA DE RODAS"
    ],
    "Alimento": [
      "DIETA"
    ],
    "Doença ou Síndrome": [
      "DIABETES",
      "HIPERTENSÃO",
      "AMIGDALITE CRONICA",
      "PARAPLEGIA ESPASTICA"
    ],
    "Grupo Profissional ou Ocupacional": [
      "ENF",
      "Enfermeira"
    ],
    "Sinal ou Sintoma": [
      "DOR EM MMII"
    ],
    "Função Fisiológica": [
      "ELIMINAÇÕES PRESENTES"
    ],
    "Lesão ou Envenenamento": [
      "TRAUMATISMO INTRACRANIANO"
    ]
  },
  "labels": {}
}