{
  "prontuario_id": 548,
  "text": "PRÉ-OP DE RETIRADA SÍNTESE DE MID. COMUNICATIVO, CONSCIENTE, REPOUSO NO LEITO, JEJUM, AGUARDA CX PARA HOJE, DIURESE PRESENTE. TRANSTORNOS DA CONTINUIDADE DO OSSO. 16: Consciente, comunicativo, afebril, eupneico, normocardico, curativo em torax exsudativo seropurulenta, acesso hep em msd, diz aceitar bem a dieta, eliminaçoes intestinais e urinarias presentes, abdomen plano, curativo em mie limpo e seco externamente. FRATURA DA DIAFISE DA TIBIA. Às 17:55 HORAS: ACORDADA, LÚCIDA E CONTACTUANDO. PUPILAS ISOCORICAS E FOTORREAGENTES. CORADA, HIDRATADA E EUPNÉICA, RESPIRANDO EM AR AMBIENTE. SINAIS VITAIS ESTÁVEIS. PERMANECE EM REPOUSO ABSOLUTO NO LEITO DEVIDO ARTERIOGRAFIA REALIZADA NO PERÍODO DA MANHA. C HEMORRAGIA SUBARACNOIDE PROVENIENTE DA ARTERIA BASILAR. Às 18:45: ORIENTADO, COMUNICATIVO, SEM QUEIXAS ALGICAS, MANTEM ACESSO VENOSO PERIFERICO EM JUGULAR D, MANTEM CTVO EM ABD COM SECREÇÃO SANGUINOLENTO, REALIZADO JEJUNOSTOMIA COM SOROTERAPIA EM CURSO. PERMANECE EM JEJUM. OUTRAS PANCREATITES CRONICAS.",
  "entities": {
    "Conceito Temporal": [
      "PRÉ-OP"
    ],
    "Abreviação": [
      "PRÉ-OP",
      "MID",
      "CX",
      "msd",
      "mie",
      "CTVO",
      "ABD",
      "acesso hep",
      "JUGULAR D"
    ],
    "Localização ou Região Corporal": [
      "MID",
      "torax",
      "msd",
      "mie",
      "ABD"
    ],
    "Achado": [
      "COMUNICATIVO",
      "CONSCIENTE",
      "JEJUM",
      "Consciente",
      "comunicativo",
      "afebril",
      "eupneico",
      "normocardico",
      "limpo",
      "seco",
      "ACORDADA",
      "LÚCIDA",
      "CONTACTUANDO",
      "CORADA",
      "HIDRATADA",
      "EUPNÉICA",
      "ORIENTADO",
      "REPOUSO NO LEITO",
      "DIURESE PRESENTE",
      "aceitar bem a dieta",
      "eliminaçoes intestinais e urinarias presentes",
      "abdomen plano",
      "RESPIRANDO EM AR AMBIENTE",
      "SINAIS VITAIS ESTÁVEIS"
    ],
    "Procedimento Terapêutico ou Preventivo": [
      "JEJUM",
      "CX",
      "curativo",
      "CTVO",
      "JEJUNOSTOMIA",
      "RETIRADA SÍNTESE",
      "REPOUSO NO LEITO",
      "acesso hep",
      "REPOUSO ABSOLUTO",
      "ACESSO VENOSO PERIFERICO",
      "SOROTERAPIA EM CURSO"
    ],
    "Negação": [
      "afebril"
    ],
    "Dispositivo Médico": [
      "curativo",
      "CTVO",
      "acesso hep",
      "ACESSO VENOSO PERIFERICO"
    ],
    "Conceito Espacial": [
      "externamente"
    ],
    "Parte do Corpo, Órgão ou Componente Orgânico": [
      "PUPILAS",
      "JUGULAR D"
    ],
    "Objeto Manufaturado": [
      "LEITO"
    ],
    "Procedimento Diagnóstico": [
      "ARTERIOGRAFIA"
    ],
    "Função Fisiológica": [
      "DIURESE PRESENTE",
      "eliminaçoes intestinais e urinarias presentes"
    ],
    "Doença ou Síndrome": [
      "TRANSTORNOS DA CONTINUIDADE DO OSSO",
      "HEMORRAGIA SUBARACNOIDE PROVENIENTE DA ARTERIA BASILAR",
      "PANCREATITES CRONICAS"
    ],
    "Sinal ou Sintoma": [
      "exsudativo seropurulenta",
      "QUEIXAS ALGICAS"
    ],
    "Substância Corporal": [
      "exsudativo seropurulenta",
      "SECREÇÃO SANGUINOLENTO"
    ],
    "Lesão ou Envenenamento": [
      "FRATURA DA DIAFISE DA TIBIA"
    ]
  },
  "labels": {}
}