{
  "prontuario_id": 892,
  "text": "ÀS 16h: Provinda do CC, POI de coledocotomia e derivação biliodigestiva. Admissão: PA 135/77 (113), FC 73 bpm, FR 18 rpm, Sat 91%. Glasgow 14, sonolenta. Pupilas isocóricas fotorreagentes. SNG aberta com presença de 100 ml de estase biliosa. Suporte de O2 sob máscara de névoa úmida e cânula de guedel. Acesso venoso central em subclávia D com curativo oclusivo infundindo soroterapia. CPP sem RA. Abdomen globoso, flácido, doloroso à palpação. FO em região hipogástrica à flanco D, dreno de suctor com débito hemático (50 ml). Acesso venoso periférico em dorso mão D soronizado. PAM em radial E permeável. SVD nº 16 com presença de 500 ml de diurese colúrica, evacuação ausente em fralda descartável. Mantido enfaixamento para aquecer MMII. Monitorizada contínuamente com parâmetros de PA invasiva, cardioscopia e oximetria de pulso. Segue sob cuidados intensivos. Enfª Florence Nightingale. EXAME GERAL E INVESTIGACAO DE PESSOAS SEM QUEIXAS OU DIAGNOSTICO RELATADO.",
  "entities": {
    "Abreviação": [
      "CC",
      "POI",
      "PA",
      "FC",
      "bpm",
      "FR",
      "rpm",
      "Sat",
      "CPP",
      "RA",
      "FO",
      "PAM",
      "MMII",
      "Enfª",
      "SNG aberta",
      "subclávia D",
      "flanco",
      "dorso mão D",
      "radial E",
      "SVD nº 16",
      "PA invasiva"
    ],
    "Organização Relacionada à Saúde": [
      "CC"
    ],
    "Conceito Temporal": [
      "POI"
    ],
    "Procedimento Terapêutico ou Preventivo": [
      "coledocotomia",
      "soronizado",
      "derivação biliodigestiva",
      "SNG aberta",
      "Suporte de O2",
      "névoa úmida",
      "Acesso venoso central",
      "curativo oclusivo",
      "infundindo soroterapia",
      "dreno de suctor",
      "Acesso venoso periférico",
      "SVD nº 16",
      "enfaixamento para aquecer"
    ],
    "Atributo Clínico": [
      "PA",
      "FC",
      "FR",
      "Sat"
    ],
    "Conceito Quantitativo": [
      "135/77",
      "113",
      "73",
      "91%",
      "100 ml",
      "50 ml",
      "500 ml"
    ],
    "Achado": [
      "18",
      "flácido",
      "permeável",
      "SNG aberta",
      "débito hemático"
    ],
    "Sinal ou Sintoma": [
      "sonolenta",
      "RA",
      "globoso",
      "QUEIXAS",
      "Glasgow 14",
      "estase biliosa",
      "diurese colúrica"
    ],
    "Parte do Corpo, Órgão ou Componente Orgânico": [
      "Pupilas",
      "subclávia D",
      "radial E"
    ],
    "Dispositivo Médico": [
      "máscara",
      "SNG aberta",
      "cânula de guedel",
      "Acesso venoso central",
      "curativo oclusivo",
      "dreno de suctor",
      "Acesso venoso periférico",
      "SVD nº 16",
      "fralda descartável"
    ],
    "Negação": [
      "sem"
    ],
    "Localização ou Região Corporal": [
      "Abdomen",
      "MMII",
      "região hipogástrica",
      "flanco",
      "D",
      "dorso mão D"
    ],
    "Procedimento Diagnóstico": [
      "palpação",
      "PAM",
      "cardioscopia",
      "Monitorizada contínuamente",
      "PA invasiva",
      "oximetria de pulso"
    ],
    "Lesão ou Envenenamento": [
      "FO"
    ],
    "Grupo Profissional ou Ocupacional": [
      "Enfª"
    ],
    "Substância Corporal": [
      "estase biliosa",
      "débito hemático"
    ],
    "Atividade de Assistência à Saúde": [
      "cuidados intensivos"
    ]
  },
  "labels": {}
}