{
  "prontuario_id": 20,
  "text": "Às 11:11h: Acordado, alerta, responsivo, descorado, desidratado. Apresenta abdome escavado, flácido, indolor à palpação, RHA +. Mantém acesso venoso central em subclávia direita com NPT em curso por bomba infusora. Diurese limpida em bom volume, paciente refe. ABDOME AGUDO. Às 18:30: PACIENE INTERNA PARA PROCEDIMENTO CIRURGICO, ORIENTADA A REALIZAR JEJUM APOS 00:00. SEGUIMENTO ENVOLVENDO REMOCAO DE PLACA DE FRATURA E OUTROS DISPOSITIVOS DE FIXACAO INTERNA. PROVENIENTE DO PS DE MACA, CONSCIENTE, ORIENTADO, CALMO, APRESENTA HEMATOMAS EM REGIÃO PERIOCULAR BILATERAL, SUTURA EM MIE, REFERE DOR LOMBAR, SEGUE SOB CUIDADOS DE ENFERMAGEM. TRAUMATISMOS MULTIPLOS NAO ESPECIFICADOS. Pcte com cultura de Lavado Brônquico do dia 25/01/08, com crescimento de MRSA. Mantê-lo em Precaução de Contato até alta hospitalar, devido estar com Klebsiella pneumoniae MR em Urina do dia 23/01/08. HEMORRAGIA INTRACEREBRAL CEREBELAR.",
  "entities": {
    "Achado": [
      "Acordado",
      "alerta",
      "responsivo",
      "flácido",
      "limpida",
      "CONSCIENTE",
      "ORIENTADO",
      "CALMO",
      "RHA +",
      "bom volume"
    ],
    "Sinal ou Sintoma": [
      "descorado",
      "desidratado",
      "escavado",
      "HEMATOMAS",
      "DOR LOMBAR"
    ],
    "Localização ou Região Corporal": [
      "abdome",
      "MIE",
      "REGIÃO PERIOCULAR BILATERAL"
    ],
    "Procedimento Diagnóstico": [
      "palpação"
    ],
    "Procedimento Terapêutico ou Preventivo": [
      "NPT",
      "JEJUM",
      "SUTURA",
      "acesso venoso central",
      "PROCEDIMENTO CIRURGICO",
      "REMOCAO DE PLACA DE FRATURA",
      "Precaução de Contato"
    ],
    "Abreviação": [
      "NPT",
      "PS",
      "MIE",
      "Pcte",
      "RHA +"
    ],
    "Função Fisiológica": [
      "Diurese"
    ],
    "Paciente ou Grupo com Deficiência": [
      "paciente",
      "PACIENE",
      "Pcte"
    ],
    "Organização Relacionada à Saúde": [
      "PS"
    ],
    "Dispositivo Médico": [
      "MACA",
      "acesso venoso central",
      "bomba infusora",
      "DISPOSITIVOS DE FIXACAO INTERNA"
    ],
    "Função Patológica": [
      "HEMATOMAS"
    ],
    "Substância Corporal": [
      "Urina"
    ],
    "Parte do Corpo, Órgão ou Componente Orgânico": [
      "subclávia direita"
    ],
    "Dispositivo de Administração de Medicamento": [
      "bomba infusora"
    ],
    "Doença ou Síndrome": [
      "ABDOME AGUDO",
      "HEMORRAGIA INTRACEREBRAL CEREBELAR"
    ],
    "Atividade de Assistência à Saúde": [
      "CUIDADOS DE ENFERMAGEM",
      "alta hospitalar"
    ],
    "Lesão ou Envenenamento": [
      "TRAUMATISMOS MULTIPLOS"
    ],
    "Procedimento Laboratorial": [
      "cultura de Lavado Brônquico"
    ],
    "Bactéria": [
      "Klebsiella pneumoniae MR"
    ]
  },
  "labels": {}
}