{
  "prontuario_id": 415,
  "text": "À 01:00: Acordado, consciente, comunicativo, lucido e orientado, eupneico, afebril e normotenso, com ausculta pulmonar com MV +, abdomen flacido e indolor com RHA +, com diurese expontanea, com acesso venoso em msd, com fixador externo em MIE com boa perfusao. DEFEITO DE CONSOLIDACAO DA FRATURA. Em 27/05/2007, 12:00 HORAS: FOI AVALIADO PELA CIRURGIA GERAL (DR. Vital Brasil E R1 ???), E AS MESMA COM PINÇA CURATIVO REALIZARAM AFASTAMENTO DOS PONTOS EM REGIÃO DE HIPOGASTRIO. APÓS TEREM MANUSEADO, REGIÃO COMEÇOU A SANGRAR. SANGRAMENTO IMPORTANTE, NO PERÍ. ABDOME AGUDO. À 01:00h: Consciente, comunicativa, lucida e orientada, deambulando, eupneica, afebril, normontensa, apresenta curativo oclusivo limpo e seco externamente em mse e mie, com boa perfusão periférica, nega algias no periodo e relata melhora do quadro. TRAUMATISMOS MULTIPLOS NAO ESPECIFICADOS. POUCO COLABORATIVA, RUBOR FACIAL, O2 CONTINUIO, SNE COM DIETA EM CURSO, RESTRITA AO LEITO, CONTIDA NO LEITO, PERIODOS DE AGITAÇÃO DURANTE A NOITE, NÃO TEVE EPSÓDIOS DE DIARRÉIA NO PERIODO DA TARDE. PRESCRITA MEDICAÇÃO NÃO PADRÃO, CONTATO COM MÉDICO PARA P. INSUFICIENCIA CARDIACA NAO ESPECIFICADA. Às 17:26: CORADO, ALERTA, AFEBRIL, COMUNICATIVO, EM REPOUSO NO LEITO, ACEITANDO DIETA VIA ORAL, SUTURA LIMPA E SECA, AVP EM MSE SALINIZADO, SINAIS VITAIS ESTAVÉIS, NÃO REFERI ALGIA, ELIMINAÇÕES FISIOLOGICAS PRESENTES E ESPONTANEAS, SEGUE SOB CUIDADOS. HEMORRAGIA EPIDURAL.",
  "entities": {
    "Achado": [
      "Acordado",
      "consciente",
      "comunicativo",
      "lucido",
      "orientado",
      "eupneico",
      "afebril",
      "normotenso",
      "flacido",
      "indolor",
      "Consciente",
      "comunicativa",
      "lucida",
      "orientada",
      "deambulando",
      "eupneica",
      "normontensa",
      "limpo",
      "seco",
      "CORADO",
      "ALERTA",
      "AFEBRIL",
      "COMUNICATIVO",
      "LIMPA",
      "SECA",
      "SALINIZADO",
      "MV +",
      "RHA +",
      "diurese expontanea",
      "boa perfusao",
      "boa perfusão periférica",
      "RESTRITA AO LEITO",
      "REPOUSO NO LEITO",
      "ACEITANDO DIETA VIA ORAL",
      "SINAIS VITAIS ESTAVÉIS",
      "ELIMINAÇÕES FISIOLOGICAS"
    ],
    "Negação": [
      "afebril",
      "indolor",
      "NÃO",
      "AFEBRIL"
    ],
    "Localização ou Região Corporal": [
      "abdomen",
      "msd",
      "MIE",
      "REGIÃO",
      "mie",
      "MSE",
      "REGIÃO DE HIPOGASTRIO"
    ],
    "Abreviação": [
      "msd",
      "MIE",
      "mie",
      "AVP",
      "MSE",
      "MV +",
      "RHA +",
      "em mse",
      "SNE COM DIETA EM CURSO"
    ],
    "Conceito Espacial": [
      "externamente"
    ],
    "Sinal ou Sintoma": [
      "algias",
      "ALGIA",
      "RUBOR FACIAL",
      "PERIODOS DE AGITAÇÃO DURANTE A NOITE",
      "EPSÓDIOS DE DIARRÉIA"
    ],
    "Atividade de Assistência à Saúde": [
      "PRESCRITA",
      "CUIDADOS"
    ],
    "Procedimento Terapêutico ou Preventivo": [
      "SUTURA",
      "AVP",
      "SALINIZADO",
      "acesso venoso",
      "fixador externo",
      "AFASTAMENTO DOS PONTOS",
      "curativo oclusivo",
      "O2 CONTINUIO",
      "SNE COM DIETA EM CURSO",
      "RESTRITA AO LEITO",
      "CONTIDA NO LEITO"
    ],
    "Dispositivo Médico": [
      "AVP",
      "acesso venoso",
      "fixador externo",
      "PINÇA CURATIVO",
      "curativo oclusivo"
    ],
    "Procedimento Diagnóstico": [
      "ausculta pulmonar"
    ],
    "Função Fisiológica": [
      "diurese expontanea",
      "ELIMINAÇÕES FISIOLOGICAS"
    ],
    "Organização Relacionada à Saúde": [
      "CIRURGIA GERAL"
    ],
    "Doença ou Síndrome": [
      "ABDOME AGUDO",
      "INSUFICIENCIA CARDIACA",
      "HEMORRAGIA EPIDURAL"
    ],
    "Lesão ou Envenenamento": [
      "TRAUMATISMOS MULTIPLOS"
    ]
  },
  "labels": {}
}