{
  "prontuario_id": 15,
  "text": "Às 17:40hrs: Transferido para posto 3 (816), de maca, na presença da enfermagem, segue aos cuidados do posto. Às 12:30HS: ALERTA. PERIODOS DE CONFUSÃO. EUPINEICA EM AR AMBIENTE. DVE FUNCIONANTE. INSERÇÃO DVE SEM SINAIS FLOGISTICOS. ACEITOU A DIETA OFERECIDA. NÃO REFERE ALGIA. DIURESE ESPONTANEA PRESENTE. SEGUE CUIDADOS. 10 TU cerebral, 9 PO ressecção de TU, TQT 27/04/2012, SNE 2 dia, 9 SVD, Glasgow 3, pupilas iso foto, região cefalica com FO com pequena qt de secreção serohematica, realizado curativo tipo capacete, abd  globoso, porem flacido, MMSS edema, MMII sem edemas. Traqueostomizada sob VM na modalidade controlada, recebendo dieta via SNE ha 75 ml/h, cvc em jugular D com soroterapia em curso, SVD com diurese efetiva. Mantem monitorização cardiaca continua; segue sob cuidados intensivos.",
  "entities": {
    "Dispositivo Médico": [
      "maca",
      "SNE",
      "SVD",
      "cvc",
      "curativo tipo capacete"
    ],
    "Organização Relacionada à Saúde": [
      "enfermagem"
    ],
    "Grupo Profissional ou Ocupacional": [
      "enfermagem"
    ],
    "Achado": [
      "ALERTA",
      "iso",
      "foto",
      "flacido",
      "Traqueostomizada",
      "EUPINEICA EM AR AMBIENTE",
      "DVE FUNCIONANTE",
      "ACEITOU A DIETA",
      "DIURESE ESPONTANEA",
      "secreção serohematica",
      "diurese efetiva"
    ],
    "Sinal ou Sintoma": [
      "ALGIA",
      "globoso",
      "edema",
      "edemas",
      "PERIODOS DE CONFUSÃO",
      "SINAIS FLOGISTICOS",
      "Glasgow 3"
    ],
    "Atividade de Assistência à Saúde": [
      "CUIDADOS",
      "cuidados do posto",
      "cuidados intensivos"
    ],
    "Conceito Temporal": [
      "PO"
    ],
    "Abreviação": [
      "PO",
      "TQT",
      "SNE",
      "SVD",
      "iso",
      "foto",
      "FO",
      "abd",
      "MMSS",
      "MMII",
      "VM",
      "cvc",
      "DVE FUNCIONANTE",
      "INSERÇÃO DVE",
      "TU cerebral",
      "ressecção de TU",
      "dieta via SNE",
      "jugular D"
    ],
    "Procedimento Terapêutico ou Preventivo": [
      "TQT",
      "SNE",
      "SVD",
      "Traqueostomizada",
      "VM",
      "cvc",
      "ressecção de TU",
      "curativo tipo capacete",
      "modalidade controlada",
      "dieta via SNE",
      "soroterapia em curso"
    ],
    "Parte do Corpo, Órgão ou Componente Orgânico": [
      "pupilas",
      "jugular D"
    ],
    "Lesão ou Envenenamento": [
      "FO"
    ],
    "Localização ou Região Corporal": [
      "abd",
      "MMSS",
      "MMII",
      "região cefalica"
    ],
    "Função Patológica": [
      "edema",
      "edemas"
    ],
    "Função Fisiológica": [
      "DIURESE ESPONTANEA",
      "diurese efetiva"
    ],
    "Processo Neoplásico": [
      "TU cerebral"
    ],
    "Conceito Qualitativo": [
      "pequena qt"
    ],
    "Conceito Quantitativo": [
      "75 ml/h"
    ],
    "Procedimento Diagnóstico": [
      "monitorização cardiaca continua"
    ]
  },
  "labels": {}
}