{
  "prontuario_id": 47,
  "text": "Às 17:13 HS: CONSCIENTE, ORIENTADO, EUPNEICO, CORADO, HIDRATADO, ACEITA DIETA, DIURESE ESPONTANEA, SEM QUEIXAS ALGICAS DURANTE O PERIODO, MANTEM PRECAUÇÃO DE CONTATO E VIAS AÉREAS. ENF FLORENCE NIGHTINGALE,COREN XXXX. FALENCIA OU REJEICAO DE TRANSPLANTE DE RIM. NA PASSAGEM DO PLANTÃO, APRESENTADO DISCRETO ESFORÇO RESPIRATORIO. EVOLUINDO AS 20:25h ESFORÇO RESPIRATORIO ACENTUADO, DISSATURANDO, COMUNICADO PLANTONISTA, QUE AUMENTOU PARAMETROS VENTILATORIOS, ADMINISTRADO PANCURONIO, NO PRIMEIRO MOMENTO (ACM); CERCA DE 40 MINUTOS + TARDE, ADMINISTRADO HALDOL (ACM), COM POUCA RESPOSTA, PLANTONISTA OPTARÁ POR SEDAR COM PROPOFOL (aguardando prescrição medica). APRESENTANDO SECREÇÃO NASO / ORAL (rosea) EM MEDIA QUANTIDADE, PLANTONISTA CIENTE. INFECCAO BACTERIANA DE LOCAL NAO ESPECIFICADO. Às 18:50hrs: paciente torporoso, dispneico com utilização da musculatura acessoria, mantém oxigenoterapia sob máscara de névoa úmida, sne com dieta em curso, não foi retirado todos os pontos cefalico, pois ao retirar o primeiro ponto apresentou deiscencia de sutura; tentado contato com dr Vital Brasil, sem sucesso. HEMORRAGIA INTRACEREBRAL CEREBELAR.",
  "entities": {
    "Achado": [
      "CONSCIENTE",
      "ORIENTADO",
      "EUPNEICO",
      "CORADO",
      "HIDRATADO",
      "sucesso",
      "ACEITA DIETA",
      "DIURESE ESPONTANEA",
      "POUCA RESPOSTA"
    ],
    "Abreviação": [
      "ENF",
      "dr",
      "SECREÇÃO NASO / ORAL",
      "sne com dieta em curso"
    ],
    "Grupo Profissional ou Ocupacional": [
      "ENF",
      "PLANTONISTA"
    ],
    "Atividade de Assistência à Saúde": [
      "PLANTÃO",
      "ADMINISTRADO"
    ],
    "Organização Relacionada à Saúde": [
      "PLANTÃO"
    ],
    "Sinal ou Sintoma": [
      "DISSATURANDO",
      "rosea",
      "torporoso",
      "dispneico",
      "QUEIXAS ALGICAS",
      "DISCRETO ESFORÇO RESPIRATORIO",
      "ESFORÇO RESPIRATORIO ACENTUADO",
      "utilização da musculatura acessoria",
      "deiscencia de sutura"
    ],
    "Substância Farmacológica": [
      "PANCURONIO",
      "PROPOFOL"
    ],
    "Procedimento Terapêutico ou Preventivo": [
      "SEDAR",
      "PRECAUÇÃO DE CONTATO E VIAS AÉREAS",
      "AUMENTOU PARAMETROS VENTILATORIOS",
      "névoa úmida",
      "sne com dieta em curso",
      "retirado todos os pontos cefalico"
    ],
    "Substância Química Orgânica": [
      "PROPOFOL"
    ],
    "Paciente ou Grupo com Deficiência": [
      "paciente"
    ],
    "Dispositivo Médico": [
      "máscara"
    ],
    "Negação": [
      "não"
    ],
    "Função Fisiológica": [
      "DIURESE ESPONTANEA"
    ],
    "Doença ou Síndrome": [
      "FALENCIA OU REJEICAO DE TRANSPLANTE DE RIM",
      "INFECCAO BACTERIANA",
      "HEMORRAGIA INTRACEREBRAL CEREBELAR"
    ],
    "Conceito Qualitativo": [
      "ESFORÇO RESPIRATORIO ACENTUADO",
      "MEDIA QUANTIDADE"
    ],
    "Produto Intelectual": [
      "prescrição medica"
    ],
    "Substância Corporal": [
      "SECREÇÃO NASO / ORAL"
    ]
  },
  "labels": {}
}