{
  "prontuario_id": 490,
  "text": "Sedado, ainda anisocorico, D > E, presença de rinorreia acentuada, mantendo colar cervical de philadelphia, Sob VM, modo PCV, PI = 45, PEEP = 12, FIO2 = 96%, Hemodinamicamente instavel em uso de noradrenalina, AVP em MSD, Abdome distendido, estase gastrica. CONCUSSAO CEREBRAL. Em 07/08/2007, 09:59h: Acordado, alerta, responsivo, mucosas coradas e hidratadas. Mantém SNE para alimentação por bomba infusora. Apresenta abdome plano, flácido, indolor à palpação, RHA +. Diurese limpida em bom volume, não evacuou nas últimas 18h. FRATURA DA DIAFISE DA TIBIA. Às 09:42h: Acordado, alerta, responsivo, corado, hidratado. Mantém SNE para alimentação por bomba infusora. Apresenta abdome globoso, flácido, indolor à palpação, RHA +. Diurese limpida em bom volume, não evacuou (fezes pastosas). FRATURA DA DIAFISE DO FEMUR.",
  "entities": {
    "Procedimento Terapêutico ou Preventivo": [
      "Sedado",
      "VM",
      "PI",
      "PEEP",
      "FIO2",
      "AVP",
      "colar cervical de philadelphia",
      "modo PCV",
      "SNE para alimentação"
    ],
    "Sinal ou Sintoma": [
      "anisocorico",
      "globoso",
      "rinorreia acentuada",
      "Hemodinamicamente instavel",
      "Abdome distendido",
      "estase gastrica"
    ],
    "Abreviação": [
      "VM",
      "PI",
      "PEEP",
      "FIO2",
      "AVP",
      "MSD",
      "D &gt; E",
      "modo PCV",
      "SNE para alimentação",
      "RHA +"
    ],
    "Conceito Quantitativo": [
      "45",
      "12",
      "96%"
    ],
    "Hormônio": [
      "noradrenalina"
    ],
    "Substância Farmacológica": [
      "noradrenalina"
    ],
    "Substância Química Orgânica": [
      "noradrenalina"
    ],
    "Dispositivo Médico": [
      "AVP",
      "colar cervical de philadelphia"
    ],
    "Localização ou Região Corporal": [
      "MSD",
      "abdome"
    ],
    "Achado": [
      "Acordado",
      "alerta",
      "responsivo",
      "coradas",
      "hidratadas",
      "plano",
      "flácido",
      "limpida",
      "corado",
      "hidratado",
      "evacuou",
      "indolor à palpação",
      "RHA +",
      "bom volume",
      "fezes pastosas"
    ],
    "Parte do Corpo, Órgão ou Componente Orgânico": [
      "mucosas"
    ],
    "Negação": [
      "não"
    ],
    "Função Fisiológica": [
      "evacuou"
    ],
    "Lesão ou Envenenamento": [
      "CONCUSSAO CEREBRAL",
      "FRATURA DA DIAFISE DA TIBIA",
      "FRATURA DA DIAFISE DO FEMUR"
    ],
    "Dispositivo de Administração de Medicamento": [
      "bomba infusora"
    ],
    "Conceito Qualitativo": [
      "bom volume"
    ]
  },
  "labels": {}
}