{
  "prontuario_id": 462,
  "text": "Às 14:00: PACIENTE APRESENTA PICO FEBRIL DE 38,2 C, REALIZADO MEDICAÇÃO CONFORME PRESCRITO. ENF FLORENCE NIGHTINGALE. Às 10:45: REALIZADO PASSAGEM DE SNE, SEM INTERCORRÊNCIA NO RPOCEDIMENTO. RETIRO FIO-GUIA. SOLICITO RAIO-X P/ AVALIAÇÃO DA POSIÇÃO. Às 14h: Paciente refere Sindrome do Pânico, diz ter episódios de crise durante a noite por estar sozinha sem acompanhante no quarto. Libero acompanhante. Às 00:00 h: Paciente estubada pelo plantonista, respiração espontanea com auxílio de nevoa umida em mascara facial, com O2 a 4 l/m contínuo. Às 03:00 H: CLIENTE CONSCIENTE, COMUNICATIVO, REPOUSO, ORIENTADO, AFEBRIL. MANTEM JEJUM ATE 2ª ORDEM. ACESSO PERIFERICO EM MSD COM PLANO DE SORO EM CURSO. APRESENTA CURATIVO EM REGIÃO CEFÁLICA ASPECTO  SECO E LIMPO EXTERNAMENTE. SUTURA EM SUPERCÍLIO SECA E LIMPA. ESCORIAÇÕES EM OMBRO ESQUERDO. ELIMINAÇÕES NORMAIS. SEGUE EM OBSERVAÇÃO E CUIDADOS. Às 21:00 h: Responsiva a estimulos verbais e dolorosos, mantem monitorização de parametros, traqueostomizada, VM modo VCV 4870 ml, PEEP 8, FIO2 a 70%, pupilas isocoricas fotorreagentes, recebendo dieta via SNE a 75 ml/h contínuo, BCRHF s/ s, CPP com roncos bolhosos bilateral, RHA diminuidos, acesso venoso central com planos de soroterapia em curso, diurese via SVD em media quantidade de cor amarelo ouro, sem grumos, boa perfusão periférica.  ",
  "entities": {
    "Paciente ou Grupo com Deficiência": [
      "PACIENTE",
      "Paciente",
      "CLIENTE"
    ],
    "Substância Farmacológica": [
      "MEDICAÇÃO"
    ],
    "Procedimento Terapêutico ou Preventivo": [
      "MEDICAÇÃO",
      "estubada",
      "O2",
      "REPOUSO",
      "JEJUM",
      "CURATIVO",
      "SUTURA",
      "traqueostomizada",
      "VM",
      "PEEP",
      "FIO2",
      "PASSAGEM DE SNE",
      "RETIRO FIO-GUIA",
      "nevoa umida",
      "ACESSO PERIFERICO",
      "PLANO DE SORO",
      "modo VCV",
      "dieta via SNE",
      "acesso venoso central",
      "planos de soroterapia"
    ],
    "Abreviação": [
      "ENF",
      "O2",
      "MSD",
      "VM",
      "PEEP",
      "FIO2",
      "BCRHF",
      "CPP",
      "PASSAGEM DE SNE",
      "modo VCV",
      "dieta via SNE",
      "s/ s",
      "RHA diminuidos",
      "diurese via SVD"
    ],
    "Grupo Profissional ou Ocupacional": [
      "ENF",
      "plantonista"
    ],
    "Procedimento Diagnóstico": [
      "RAIO-X",
      "monitorização de parametros"
    ],
    "Negação": [
      "sem",
      "AFEBRIL",
      "s/ s"
    ],
    "Grupo Populacional": [
      "acompanhante"
    ],
    "Achado": [
      "estubada",
      "CONSCIENTE",
      "COMUNICATIVO",
      "REPOUSO",
      "ORIENTADO",
      "AFEBRIL",
      "SECO",
      "LIMPO",
      "SECA",
      "LIMPA",
      "traqueostomizada",
      "respiração espontanea",
      "ELIMINAÇÕES NORMAIS",
      "Responsiva a estimulos verbais e dolorosos",
      "diurese via SVD",
      "cor amarelo ouro",
      "boa perfusão periférica"
    ],
    "Localização ou Região Corporal": [
      "MSD",
      "SUPERCÍLIO",
      "CPP",
      "REGIÃO CEFÁLICA"
    ],
    "Dispositivo Médico": [
      "CURATIVO",
      "mascara facial",
      "ACESSO PERIFERICO",
      "acesso venoso central"
    ],
    "Lesão ou Envenenamento": [
      "ESCORIAÇÕES"
    ],
    "Atividade de Assistência à Saúde": [
      "OBSERVAÇÃO",
      "CUIDADOS"
    ],
    "Conceito Quantitativo": [
      "8",
      "70%",
      "38 , 2 C",
      "4 l/m",
      "4870 ml",
      "75 ml/h"
    ],
    "Parte do Corpo, Órgão ou Componente Orgânico": [
      "pupilas",
      "OMBRO ESQUERDO"
    ],
    "Sinal ou Sintoma": [
      "grumos",
      "PICO FEBRIL",
      "roncos bolhosos bilateral",
      "RHA diminuidos"
    ],
    "Doença ou Síndrome": [
      "Sindrome do Pânico"
    ],
    "Função Fisiológica": [
      "ELIMINAÇÕES NORMAIS"
    ]
  },
  "labels": {}
}