{
  "prontuario_id": 507,
  "text": "Às 11:25H: Retirado acesso venoso central em subclávia, encaminhado para análise ponta de cateter. Puncionado acesso venoso em dorso da mão D com soroterapia gravitacional. Retirado SVD e instalado uropen, apresenta diurese efetiva. Às 07:30H: Encaminhado para CC com suporte de O2 sob névoa úmida + monitorização. Às 01:05h: Encontra-se torporoso, responsivo apenas a estimulos dolorosos, abertura ocular espontanea, apresentou hipertermia sendo medicado conforme prescrição, demais dados vitais estáveis, traqueostomizado, fazendo uso de oxigenoterapia sob nevoa umida, sistema fechado de aspiração com média quantidade de secreção espessa, mantem SNE com infusão de dietoterapia contínua e SNG aberta com baixo débito drenado, acesso venoso periférico em msd permeavel, com infusão de venóclise, diurese via SVD de aspecto concentrado, segue em precaução de contato, sob cuidados de enfermagem. Às 02:01: Admitida no setor, proveniente do PA, deambulando com acompanhante, apresenta edema e sinais flogisticos em 3 pododactilo da mão D, interna para tratamento de celulite, realizou drenagem ontem, porem sem sucesso, refere algia intensa de escala 10, sendo medicada conforme prescrição medica, puncionado acesso venoso periferico, coletado exames laboratoriais, aguarda PC para cirurgiao da mão, segue cuidados.",
  "entities": {
    "Parte do Corpo, Órgão ou Componente Orgânico": [
      "subclávia",
      "3 pododactilo da mão D"
    ],
    "Procedimento Terapêutico ou Preventivo": [
      "Puncionado",
      "SVD",
      "medicado",
      "traqueostomizado",
      "SNE",
      "tratamento",
      "drenagem",
      "medicada",
      "puncionado",
      "Retirado acesso venoso central",
      "acesso venoso",
      "soroterapia gravitacional",
      "suporte de O2 sob névoa úmida",
      "oxigenoterapia sob nevoa umida",
      "sistema fechado de aspiração",
      "dietoterapia contínua",
      "SNG aberta",
      "acesso venoso periférico",
      "infusão de venóclise",
      "precaução de contato",
      "acesso venoso periferico"
    ],
    "Atividade de Assistência à Saúde": [
      "Retirado",
      "prescrição",
      "cuidados",
      "cuidados de enfermagem",
      "prescrição medica"
    ],
    "Abreviação": [
      "SVD",
      "CC",
      "SNE",
      "msd",
      "PA",
      "PC",
      "dorso da mão D",
      "suporte de O2 sob névoa úmida",
      "SNG aberta",
      "diurese via SVD",
      "3 pododactilo da mão D"
    ],
    "Dispositivo Médico": [
      "SVD",
      "uropen",
      "SNE",
      "Retirado acesso venoso central",
      "acesso venoso",
      "acesso venoso periférico",
      "acesso venoso periferico"
    ],
    "Organização Relacionada à Saúde": [
      "CC",
      "PA"
    ],
    "Procedimento Diagnóstico": [
      "monitorização"
    ],
    "Sinal ou Sintoma": [
      "torporoso",
      "hipertermia",
      "edema",
      "responsivo apenas a estimulos dolorosos",
      "secreção espessa",
      "sinais flogisticos",
      "algia intensa"
    ],
    "Produto Intelectual": [
      "prescrição"
    ],
    "Achado": [
      "traqueostomizado",
      "permeavel",
      "sucesso",
      "diurese efetiva",
      "abertura ocular espontanea",
      "dados vitais estáveis",
      "diurese via SVD",
      "aspecto concentrado",
      "deambulando com acompanhante"
    ],
    "Localização ou Região Corporal": [
      "msd",
      "dorso da mão D"
    ],
    "Função Patológica": [
      "edema"
    ],
    "Doença ou Síndrome": [
      "celulite"
    ],
    "Negação": [
      "sem"
    ],
    "Procedimento Laboratorial": [
      "análise ponta de cateter",
      "exames laboratoriais"
    ],
    "Função Fisiológica": [
      "diurese efetiva",
      "diurese via SVD"
    ],
    "Conceito Qualitativo": [
      "média quantidade"
    ],
    "Substância Corporal": [
      "baixo débito drenado"
    ],
    "Grupo Profissional ou Ocupacional": [
      "cirurgiao da mão"
    ]
  },
  "labels": {}
}