{
  "prontuario_id": 794,
  "text": "Às 17:44 HS: CONSCIENTE, ORIENTADA, EUPNEICA, HIPOCORADA, HIDRATADA, ACEITA DIETA, DIURESE ESPONTANEA, ABDOME GLOBOSO INDOLOR A PALPAÇÃO, MANTEM PRECAUÇÃO DE CONTATO E VIAS AÉREAS, SEM QUEIXAS ALGICAS DURANTE O PERIODO. POR VOLTA DAS 22:30H DO DIA 28/07/10, CLIENTE EVADIU-SE DA ENFERMARIA 105-3 UI-1, ONDE ESTAVA INTERNADO. COMUNICADO SEGURANÇA DO HOSPITAL E SERVIÇO SOCIAL. CLIENTE VÍTIMA DE FAF EM MÃO ESQ, POI  DE FIXAÇÃO DE FX DE 3º QD ESQ, ESTAVA COM PLANO DE ALTA PARA AMANHÃ SE TUDO OK. Às 14h: Realizada coleta de amostras de aspirado traqueal + 02 hemoculturas, encaminhadas para análise laboratorial. Sem sucesso tentativas de punção de acesso venoso periférico para retirada de acesso venoso central. Às 10:15 HS: LUCIDO, ORIENTADO, COMINICATIVO, AFEBRIL, NORMOTENSO, NORMOCORADO, EUPNEICO, BOA ACEITAÇÃO DA DIETA VO, BOA INGESTA HIDRICA, DEAMBULA COM AUXILIO, DIURESE PRESENTE, SEGUE CUIDADOS.  ",
  "entities": {
    "Achado": [
      "CONSCIENTE",
      "ORIENTADA",
      "EUPNEICA",
      "HIDRATADA",
      "sucesso",
      "LUCIDO",
      "ORIENTADO",
      "COMINICATIVO",
      "AFEBRIL",
      "NORMOTENSO",
      "NORMOCORADO",
      "EUPNEICO",
      "ACEITA DIETA",
      "DIURESE ESPONTANEA",
      "BOA ACEITAÇÃO DA DIETA VO",
      "BOA INGESTA HIDRICA",
      "DEAMBULA COM AUXILIO",
      "DIURESE PRESENTE"
    ],
    "Sinal ou Sintoma": [
      "HIPOCORADA",
      "GLOBOSO",
      "QUEIXAS ALGICAS"
    ],
    "Localização ou Região Corporal": [
      "ABDOME"
    ],
    "Negação": [
      "INDOLOR",
      "SEM",
      "Sem",
      "AFEBRIL"
    ],
    "Procedimento Diagnóstico": [
      "PALPAÇÃO"
    ],
    "Atividade de Assistência à Saúde": [
      "MANTEM",
      "COMUNICADO",
      "tentativas",
      "CUIDADOS",
      "PLANO DE ALTA",
      "coleta de amostras"
    ],
    "Paciente ou Grupo com Deficiência": [
      "CLIENTE",
      "VÍTIMA"
    ],
    "Objeto Manufaturado": [
      "ENFERMARIA"
    ],
    "Grupo Profissional ou Ocupacional": [
      "SEGURANÇA",
      "SERVIÇO SOCIAL"
    ],
    "Abreviação": [
      "POI",
      "FAF EM MÃO",
      "BOA ACEITAÇÃO DA DIETA VO"
    ],
    "Conceito Temporal": [
      "POI"
    ],
    "Procedimento Terapêutico ou Preventivo": [
      "punção",
      "PRECAUÇÃO DE CONTATO E VIAS AÉREAS",
      "acesso venoso periférico",
      "acesso venoso central"
    ],
    "Organização Relacionada à Saúde": [
      "SERVIÇO SOCIAL"
    ],
    "Parte do Corpo, Órgão ou Componente Orgânico": [
      "FAF EM MÃO"
    ],
    "Lesão ou Envenenamento": [
      "FAF EM MÃO"
    ],
    "Substância Corporal": [
      "aspirado traqueal"
    ],
    "Procedimento Laboratorial": [
      "análise laboratorial"
    ],
    "Dispositivo Médico": [
      "acesso venoso periférico",
      "acesso venoso central"
    ],
    "Função Fisiológica": [
      "DIURESE PRESENTE"
    ]
  },
  "labels": {}
}