{
  "prontuario_id": 836,
  "text": "Consciente, sonolento, comunicativo, deitado. Tala gessada e curativo em MSE. Presença de mancha de sg em QDT. Movimentação e perfusão + em 1º QDT. Florence Nightingale. FRATURA DE OUTROS DEDOS. Às 18:00HRS: CONSCIENTE, ORIENTADA, POUCO COMUNICATIVA, PERIODOS DE SONOLENCIA. ACEITANDO POUCO A DIETA VO BRANDA. MANTEM ACESSO VENOSO PERIFERICO NO MSD COM SOROTERAPIA EM CURSO. PERMANECE COM DRENO DE TORAX DIREITO E ESQUERDO COM DEBITO HEMATICO, SENDO TROC. TRAUMATISMOS MULTIPLOS NAO ESPECIFICADOS. Às 12:35: Paciente referindo algia intensa MIE, consciente, orientado, comunicativo, restrito ao leito, aceitando bem dieta VO, com sinais vitais estaveis,fazendo uso de colar cervical para mobilização, com acesso venoso periférico MSE, apresentando edema em. TRAUMATISMOS MULTIPLOS NAO ESPECIFICADOS. Às 11:42 HS: CONSCIENTE, ORIENTADA, SONOLENTA, AVP E COM SRT, RETIRADO SNG E LIBERADO DIETA PASTOSA ATÉ AMANHÃ. DEAMBULA COM AUXÍLIO, ELIMINAÇÕES PRESENTES. SEGUE CUIDADOS DE ENFERMAGEM. COM ACOMPANHANTE. INTOXICACAO POR ANTIDEPRESSIVOS TRICICLICOS E TETRACICLICOS.",
  "entities": {
    "Achado": [
      "Consciente",
      "comunicativo",
      "deitado",
      "Movimentação",
      "perfusão",
      "CONSCIENTE",
      "ORIENTADA",
      "consciente",
      "orientado",
      "DEBITO HEMATICO",
      "restrito ao leito",
      "aceitando bem dieta VO",
      "sinais vitais estaveis",
      "DEAMBULA COM AUXÍLIO",
      "ELIMINAÇÕES PRESENTES"
    ],
    "Sinal ou Sintoma": [
      "sonolento",
      "edema",
      "SONOLENTA",
      "mancha de sg",
      "PERIODOS DE SONOLENCIA",
      "DEBITO HEMATICO",
      "algia intensa"
    ],
    "Dispositivo Médico": [
      "curativo",
      "AVP",
      "Tala gessada",
      "ACESSO VENOSO PERIFERICO",
      "DRENO DE TORAX",
      "colar cervical",
      "acesso venoso periférico"
    ],
    "Procedimento Terapêutico ou Preventivo": [
      "curativo",
      "AVP",
      "SRT",
      "Tala gessada",
      "ACESSO VENOSO PERIFERICO",
      "SOROTERAPIA EM CURSO",
      "DRENO DE TORAX",
      "restrito ao leito",
      "acesso venoso periférico",
      "RETIRADO SNG",
      "DIETA PASTOSA"
    ],
    "Localização ou Região Corporal": [
      "MSE",
      "MSD",
      "MIE"
    ],
    "Abreviação": [
      "MSE",
      "MSD",
      "MIE",
      "AVP",
      "SRT",
      "mancha de sg",
      "1º QDT",
      "aceitando bem dieta VO",
      "RETIRADO SNG"
    ],
    "Conceito Espacial": [
      "DIREITO",
      "ESQUERDO"
    ],
    "Paciente ou Grupo com Deficiência": [
      "Paciente"
    ],
    "Função Patológica": [
      "edema"
    ],
    "Grupo Populacional": [
      "ACOMPANHANTE"
    ],
    "Parte do Corpo, Órgão ou Componente Orgânico": [
      "1º QDT"
    ],
    "Lesão ou Envenenamento": [
      "FRATURA DE OUTROS DEDOS",
      "TRAUMATISMOS MULTIPLOS",
      "INTOXICACAO POR ANTIDEPRESSIVOS TRICICLICOS E TETRACICLICOS"
    ],
    "Alimento": [
      "DIETA PASTOSA"
    ],
    "Função Fisiológica": [
      "ELIMINAÇÕES PRESENTES"
    ],
    "Atividade de Assistência à Saúde": [
      "CUIDADOS DE ENFERMAGEM"
    ]
  },
  "labels": {}
}