{
  "prontuario_id": 655,
  "text": "ENTUBADO, VM, MONITORIZAÇÃO CARDIACA E OXIMETRIA DE PULSO, MODO PCV, SNG EM NARINA DIREITA FECHADA, TOT COM GRANDE QUANTIDADE SECREÇÃO PURULENTA, PUPILAS MIOTICAS, ABDOMEN FLACIDO, RHA PRESENTES, ACESSO VENOSO EM MMSS COM SOROTERAPIA PERMEAVEL, SVD COM DIURESE. ISQUEMIA CEREBRAL TRANSITORIA NAO ESPECIFICADA. Noite: Chamada pelas AE, pois Dr Vital Brasil prescreveu Levomepromazina VO, que segundo farmácia não é padrão. Solicitado para Dr Vital Brasil substituição, substituído por Clorpromazina EV. Florence Nightingale. DEPLECAO DE VOLUME. Às 16:54 HS: CONSCIENTE, ORIENTADO, VERBALIZANDO, EM REPOUSO NO LEITO. SEM QUEIXAS ÁLGICAS NO MOMENTO. REFERE BOA ACEITAÇÃO DA DIETA VO. MANTÉM ACESSO VENOSO PERIFÉRICO EM MSE HEPARINIZADO. CURATIVO EM PERNA D LIMPO E SECO EXTERNAMENTE. BOA PERFUSÃO PERIFÉRICA. FRATURA DA DIAFISE DA TIBIA. Em 19/01/07, 23:10: Entubada, em VM modo PCV, Pi 32, Peep 11, Fr 14, FiO2 60%, saturando 95%. Pupilas isocóricas, fotorreagentes, reage a dor e aspiração. Ausculta pulmonar com presença de roncos E, secreção traqueobrônquica em pequena quantidade esbranquiçada. TUBERCULOSE PULMONAR COM CONFIRMACAO POR EXAME MICROSCOPICO DA EXPECTORACAO COM OU SEM CULTURA.",
  "entities": {
    "Achado": [
      "ENTUBADO",
      "FECHADA",
      "PERMEAVEL",
      "padrão",
      "CONSCIENTE",
      "ORIENTADO",
      "VERBALIZANDO",
      "LIMPO",
      "SECO",
      "Entubada",
      "fotorreagentes",
      "ABDOMEN FLACIDO",
      "RHA PRESENTES",
      "REPOUSO NO LEITO",
      "BOA PERFUSÃO PERIFÉRICA",
      "reage a dor e aspiração"
    ],
    "Procedimento Terapêutico ou Preventivo": [
      "ENTUBADO",
      "VM",
      "SNG",
      "FECHADA",
      "TOT",
      "SVD",
      "HEPARINIZADO",
      "CURATIVO",
      "Entubada",
      "Pi",
      "Peep",
      "FiO2",
      "MODO PCV",
      "ACESSO VENOSO",
      "REPOUSO NO LEITO",
      "ACESSO VENOSO PERIFÉRICO",
      "modo PCV"
    ],
    "Abreviação": [
      "VM",
      "SNG",
      "TOT",
      "MMSS",
      "Dr",
      "EV",
      "MSE",
      "Pi",
      "Peep",
      "Fr",
      "FiO2",
      "MODO PCV",
      "RHA PRESENTES",
      "PERNA D",
      "modo PCV",
      "roncos E"
    ],
    "Dispositivo Médico": [
      "SNG",
      "TOT",
      "SVD",
      "CURATIVO",
      "ACESSO VENOSO",
      "ACESSO VENOSO PERIFÉRICO"
    ],
    "Localização ou Região Corporal": [
      "MMSS",
      "MSE"
    ],
    "Substância Farmacológica": [
      "Levomepromazina",
      "Clorpromazina"
    ],
    "Negação": [
      "não",
      "SEM"
    ],
    "Conceito Espacial": [
      "EXTERNAMENTE"
    ],
    "Conceito Quantitativo": [
      "32",
      "11",
      "14",
      "60%",
      "95%"
    ],
    "Parte do Corpo, Órgão ou Componente Orgânico": [
      "Pupilas",
      "PERNA D"
    ],
    "Procedimento Diagnóstico": [
      "MONITORIZAÇÃO CARDIACA",
      "OXIMETRIA DE PULSO",
      "Ausculta pulmonar"
    ],
    "Espaço ou Junção Corporal": [
      "NARINA DIREITA"
    ],
    "Conceito Qualitativo": [
      "GRANDE QUANTIDADE",
      "BOA ACEITAÇÃO"
    ],
    "Substância Corporal": [
      "SECREÇÃO PURULENTA",
      "secreção traqueobrônquica"
    ],
    "Sinal ou Sintoma": [
      "SECREÇÃO PURULENTA",
      "PUPILAS MIOTICAS",
      "QUEIXAS ÁLGICAS",
      "roncos E"
    ],
    "Doença ou Síndrome": [
      "ISQUEMIA CEREBRAL TRANSITORIA",
      "TUBERCULOSE PULMONAR"
    ],
    "Lesão ou Envenenamento": [
      "FRATURA DA DIAFISE DA TIBIA"
    ],
    "Procedimento Laboratorial": [
      "EXAME MICROSCOPICO DA EXPECTORACAO COM OU SEM CULTURA"
    ]
  },
  "labels": {}
}