{
  "prontuario_id": 608,
  "text": "Pcte com cultura de Urina do dia 08/03/10, com crescimento de ** Klebsiella pneumoniae MR **.  ** Instaurar Precaução de Contato até alta hospitalar. ** ** Reforçar Higienização das Mãos. ** ABDOME AGUDO. Às 07:00 Horas: Abertura ocular espontânea, porém, dificuldade em responder a estímulos verbais por esforço respiratório, hipertensão e saturação 88%; solicitado pelo Dr Vital Brasil administração de Dormonid 15 mg e início de plano em bomba infusora (Dormonid 150 mg + SG5% 250 ml a 20 ml/h); evoluiu com melhora da pressão e saturação. TRAUMATISMO NAO ESPECIFICADO. Às 08:20h: Ramsay 6, pupilas isomióticas bradifotorreagentes. SNE fechada. Em VM modo PCV, Peep 7, PI 22, FiO2 100%. Entubada, rima labial de TOT em 26 cm, uso contínuo de filtro de barreira e aspiração via sistema aberto. Acesso venoso triplo-lumem em jugular interna E com curativo oclusivo infundindo dormonid 12 ml/h + noradrenalina 2 ml/h. CPP com creptantes difusos. Abdomem flácido, globoso, RHA +. PAM em radial D permeável. SVD anúrica, evacuação ausente. Edema e exudato em MMSS, importante fragilidade cutânea. Extremidades frias e má perfundidas. Uso de colchão de ar. Monitorizada contínuamente com parâmetros de PA invasiva, cardioscopia e oximetria de pulso. Segue sob cuidados intensivos. Enfª Florence Nightingale. EDEMA CEREBRAL.",
  "entities": {
    "Abreviação": [
      "Pcte",
      "Dr",
      "SG5%",
      "VM",
      "Peep",
      "PI",
      "FiO2",
      "CPP",
      "PAM",
      "MMSS",
      "Enfª",
      "SNE fechada",
      "modo PCV",
      "jugular interna E",
      "RHA +",
      "radial D",
      "SVD anúrica",
      "PA invasiva"
    ],
    "Paciente ou Grupo com Deficiência": [
      "Pcte"
    ],
    "Sinal ou Sintoma": [
      "hipertensão",
      "globoso",
      "Edema",
      "exudato",
      "frias",
      "dificuldade em responder a estímulos verbais",
      "esforço respiratório",
      "creptantes difusos",
      "SVD anúrica",
      "importante fragilidade cutânea",
      "má perfundidas"
    ],
    "Conceito Quantitativo": [
      "88%",
      "7",
      "22",
      "100%",
      "15 mg",
      "150 mg",
      "250 ml",
      "20 ml/h",
      "26 cm",
      "12 ml/h",
      "2 ml/h"
    ],
    "Substância Química Orgânica": [
      "Dormonid",
      "dormonid"
    ],
    "Substância Farmacológica": [
      "Dormonid",
      "SG5%",
      "dormonid",
      "noradrenalina"
    ],
    "Parte do Corpo, Órgão ou Componente Orgânico": [
      "pupilas",
      "rima labial",
      "jugular interna E",
      "radial D"
    ],
    "Procedimento Terapêutico ou Preventivo": [
      "VM",
      "Peep",
      "PI",
      "FiO2",
      "Entubada",
      "infundindo",
      "Precaução de Contato",
      "Higienização das Mãos",
      "SNE fechada",
      "modo PCV",
      "filtro de barreira",
      "aspiração via sistema aberto",
      "Acesso venoso triplo-lumem",
      "curativo oclusivo",
      "colchão de ar"
    ],
    "Achado": [
      "Entubada",
      "permeável",
      "evacuação",
      "Abertura ocular espontânea",
      "melhora da pressão",
      "e saturação",
      "Ramsay 6",
      "SNE fechada",
      "RHA +"
    ],
    "Dispositivo Médico": [
      "TOT",
      "bomba infusora",
      "filtro de barreira",
      "Acesso venoso triplo-lumem",
      "curativo oclusivo",
      "colchão de ar"
    ],
    "Hormônio": [
      "noradrenalina"
    ],
    "Localização ou Região Corporal": [
      "CPP",
      "Abdomem",
      "MMSS",
      "Extremidades"
    ],
    "Procedimento Diagnóstico": [
      "PAM",
      "cardioscopia",
      "Monitorizada contínuamente",
      "PA invasiva",
      "oximetria de pulso"
    ],
    "Função Fisiológica": [
      "evacuação"
    ],
    "Negação": [
      "ausente"
    ],
    "Função Patológica": [
      "Edema"
    ],
    "Grupo Profissional ou Ocupacional": [
      "Enfª"
    ],
    "Procedimento Laboratorial": [
      "cultura de Urina"
    ],
    "Bactéria": [
      "Klebsiella pneumoniae MR"
    ],
    "Resultado Laboratorial ou de Teste": [
      "Klebsiella pneumoniae MR"
    ],
    "Atividade de Assistência à Saúde": [
      "alta hospitalar",
      "cuidados intensivos"
    ],
    "Doença ou Síndrome": [
      "ABDOME AGUDO",
      "EDEMA CEREBRAL"
    ],
    "Dispositivo de Administração de Medicamento": [
      "bomba infusora"
    ],
    "Objeto Manufaturado": [
      "colchão de ar"
    ]
  },
  "labels": {}
}