{
  "prontuario_id": 403,
  "text": "Às 18:05: CLIENTE RETORNOU DO CC POR VOLTA DAS 12:30. 1º RIZOTOMIA PERCUTANEAS POR RADIOFREQUENCIA, CONSCIENTE, COMUNICATIVO, EUPNEICO, DEAMBULANDO, NEGA QUEIXAS ALGICAS, AVP EM MSD SALINIZADO, CTVO LIMPO E SECO, MICÇÃO PRESENTE, DE ALTA HOSPITALAR ÁS 18:00 A. PANICULITE ATINGINDO REGIOES DO PESCOCO E DO DORSO. Às 17:02HRS: CONSCIENTE, ORIENTADO, COMUNICATIVO. ACEITANDO BEM A DIETA VO. ACESSO VENOSO PERIFERICO NO MSD SALINIZADO. CURATIVO NO JOELHO DIREITO LIMPO E SECO EXTERNAMENTE. SEM QUEIXAS ALGICAS ATE O MOMENTO. ELIMINAÇÕES FISIOLOGICAS PRESENTES. DEAMBULANDO. FRATURA DA EXTREMIDADE SUPERIOR DO CUBITO ULNA. Às 17H: RECEPCIONADA NA UNIDADE PROVENIENTE DO CC APÓS REALIZAÇÃO DE LAPAROTOMIA EXPLORADORA (ÚLCERA DUODENAL PERFURADA), SONOLENTA, PUPILAS ISOCÓRICAS E FOTORREAGENTES, RESPIRAÇÃO ESPONTÂNEA COM SUPORTE DE O2 EM NÉVOA ÚMIDA, OXIMETRIA ACIMA DE 90%, SNG CO. ABDOME AGUDO. Às 10:00 HORAS: 3° DIA DE INTERNAMENTO, POR RUBOR E EDEMA EM MIE. ACORDADO, LÚCIDO E CONTACTUANDO. CORADO, HIDRATADO E EUPNÉICO RESPIRANDO EM AR AMBIENTE. SINAIS VITAIS ESTÁVEIS. PERMANCE EM REPOUSO NO LEITO, DEAMBULANDO. REFERE MELHORA IMPORTANTE DO QUADRO, ERISIPELOIDE NAO ESPECIFICADO.",
  "entities": {
    "Paciente ou Grupo com Deficiência": [
      "CLIENTE"
    ],
    "Abreviação": [
      "CC",
      "AVP",
      "CTVO",
      "MSD",
      "SNG",
      "MIE",
      "EM MSD",
      "ACEITANDO BEM A DIETA VO"
    ],
    "Organização Relacionada à Saúde": [
      "CC"
    ],
    "Achado": [
      "CONSCIENTE",
      "COMUNICATIVO",
      "EUPNEICO",
      "DEAMBULANDO",
      "SALINIZADO",
      "LIMPO",
      "SECO",
      "ORIENTADO",
      "ACORDADO",
      "LÚCIDO",
      "CONTACTUANDO",
      "CORADO",
      "HIDRATADO",
      "EUPNÉICO",
      "MICÇÃO PRESENTE",
      "ACEITANDO BEM A DIETA VO",
      "ELIMINAÇÕES FISIOLOGICAS PRESENTES",
      "RESPIRAÇÃO ESPONTÂNEA",
      "OXIMETRIA ACIMA DE 90%",
      "RESPIRANDO EM AR AMBIENTE",
      "SINAIS VITAIS ESTÁVEIS",
      "REPOUSO NO LEITO",
      "MELHORA IMPORTANTE DO QUADRO"
    ],
    "Negação": [
      "NEGA",
      "SEM"
    ],
    "Procedimento Terapêutico ou Preventivo": [
      "AVP",
      "SALINIZADO",
      "CTVO",
      "CURATIVO",
      "RIZOTOMIA PERCUTANEAS POR RADIOFREQUENCIA",
      "ACESSO VENOSO PERIFERICO",
      "LAPAROTOMIA EXPLORADORA",
      "SUPORTE DE O2 EM NÉVOA ÚMIDA",
      "REPOUSO NO LEITO"
    ],
    "Dispositivo Médico": [
      "AVP",
      "CTVO",
      "CURATIVO",
      "SNG",
      "ACESSO VENOSO PERIFERICO"
    ],
    "Localização ou Região Corporal": [
      "MSD",
      "MIE",
      "EM MSD"
    ],
    "Conceito Espacial": [
      "EXTERNAMENTE"
    ],
    "Sinal ou Sintoma": [
      "SONOLENTA",
      "RUBOR",
      "EDEMA",
      "QUEIXAS ALGICAS"
    ],
    "Parte do Corpo, Órgão ou Componente Orgânico": [
      "PUPILAS",
      "JOELHO DIREITO"
    ],
    "Função Patológica": [
      "EDEMA"
    ],
    "Função Fisiológica": [
      "MICÇÃO PRESENTE",
      "ELIMINAÇÕES FISIOLOGICAS PRESENTES"
    ],
    "Atividade de Assistência à Saúde": [
      "ALTA HOSPITALAR"
    ],
    "Doença ou Síndrome": [
      "PANICULITE ATINGINDO REGIOES DO PESCOCO E DO DORSO",
      "ÚLCERA DUODENAL PERFURADA",
      "ABDOME AGUDO"
    ],
    "Lesão ou Envenenamento": [
      "FRATURA DA EXTREMIDADE SUPERIOR DO CUBITO ULNA"
    ]
  },
  "labels": {}
}