{
  "prontuario_id": 758,
  "text": "Paciente Maria 80 anos, vem transferido de Curitiba (sem nota de transferência), onde esteve internada segundo familiar por dor torácica e dispnéia. Foi transferida do Hospital de origem para a Hemodinâmica, aos cuidados do Prof. Lucas a fim de realizar cateterismo cardíaco em 03/03/2006 - apresentou após procedimento Edema agudo de pulmão. Realizou ecocardiograma em 06/03/2006 - VE dilatado, FE 31%, insuficiência mitral moderada funcional, e acinesia de segmentos anterior, medio, apical e inferior.  Em 01/03/2006 realizou angioplastia com implante de stent na primeira Diagonal. Em 07/03/2006 apresentou diminuição de volume de diurese e sintomas de uremia associado a hipervolemia necessitando de suporte dialítico por cateter. Após colocação de SVD apresentou hematúria macicça com queda de HB de 12 --> 8 em 24 horas. Realizado TC de abdome que excluiu hipótese de hematoma retroperitoneal. Foi transferida à UTI em 08/03/2006 para otimização de manejo e monitorização, tendo alta para enfermaria dois dias após.  Melhora progressiva de sintomas - persistindo em insuficiência cardíaca classe 4.  Paciente é transferida hoje para Hospital de origem para seguir aos cuidados de seu médico, devendo manter acompanhamento com nefrologista também.  PRESCRIÇÃO AAS 100 mg/dia Ticlopidina 250 mg 2x/dia por 30 dias Digoxina 0,125 mg/ 48 horas Hidralazina 25 mg 3x/dia Isossorbida 20 mg 3x/dia Carbonato de Cálcio 500 mg CAJ Hemodiálise por cateter 2/4/6  Lista de problemas # Insuficiência cardíaca classe 4 # CArdiopatia isquêmica  # Doença renal crônica agudizada por nefropatia relacionada ao contraste # Hematúria a esclarecer",
  "entities": {
    "Paciente ou Grupo com Deficiência": [
      "Paciente"
    ],
    "Negação": [
      "sem"
    ],
    "Atividade de Assistência à Saúde": [
      "internada",
      "cuidados",
      "otimização",
      "manejo",
      "alta",
      "acompanhamento",
      "PRESCRIÇÃO"
    ],
    "Grupo Familiar": [
      "familiar"
    ],
    "Sinal ou Sintoma": [
      "dispnéia",
      "acinesia",
      "hipervolemia",
      "Hematúria",
      "dor torácica",
      "sintomas de uremia",
      "hematúria macicça"
    ],
    "Organização Relacionada à Saúde": [
      "Hospital",
      "Hemodinâmica",
      "UTI",
      "enfermaria"
    ],
    "Grupo Profissional ou Ocupacional": [
      "Hemodinâmica",
      "Prof",
      "médico",
      "nefrologista"
    ],
    "Abreviação": [
      "Prof",
      "FE",
      "SVD",
      "HB",
      "TC",
      "UTI",
      "AAS",
      "2x/dia",
      "3x/dia",
      "CAJ",
      "VE dilatado"
    ],
    "Conceito Temporal": [
      "após",
      "hoje",
      "2x/dia",
      "3x/dia",
      "80 anos",
      "24 horas",
      "dois dias",
      "30 dias",
      "48 horas"
    ],
    "Procedimento Terapêutico ou Preventivo": [
      "procedimento",
      "ecocardiograma",
      "angioplastia",
      "SVD",
      "manejo",
      "Hemodiálise",
      "cateterismo cardíaco",
      "implante de stent",
      "suporte dialítico"
    ],
    "Parte do Corpo, Órgão ou Componente Orgânico": [
      "pulmão",
      "primeira Diagonal"
    ],
    "Procedimento Diagnóstico": [
      "ecocardiograma",
      "monitorização"
    ],
    "Conceito Quantitativo": [
      "31%",
      "volume",
      "3x/dia",
      "12 --&gt; 8",
      "100 mg/dia",
      "250 mg",
      "0 , 125",
      "25 mg",
      "20 mg",
      "500 mg"
    ],
    "Localização ou Região Corporal": [
      "segmentos",
      "anterior",
      "medio",
      "abdome",
      "apical e inferior"
    ],
    "Conceito Qualitativo": [
      "diminuição",
      "Melhora progressiva"
    ],
    "Achado": [
      "diurese",
      "Melhora progressiva"
    ],
    "Função Fisiológica": [
      "diurese"
    ],
    "Dispositivo Médico": [
      "cateter"
    ],
    "Atributo Clínico": [
      "HB"
    ],
    "Substância Farmacológica": [
      "AAS",
      "Ticlopidina",
      "Digoxina",
      "Hidralazina",
      "Isossorbida",
      "Carbonato de Cálcio"
    ],
    "Doença ou Síndrome": [
      "Hematúria",
      "insuficiência mitral moderada funcional",
      "insuficiência cardíaca classe 4",
      "Insuficiência cardíaca classe 4",
      "CArdiopatia isquêmica",
      "Doença renal crônica agudizada",
      "nefropatia relacionada ao contraste"
    ],
    "Resultado Laboratorial ou de Teste": [
      "VE dilatado",
      "insuficiência mitral moderada funcional"
    ],
    "Função Patológica": [
      "hematoma retroperitoneal"
    ]
  },
  "labels": {}
}