{
  "prontuario_id": 776,
  "text": "18:01 SOLICITADO PSICOLOGIA DEVIDO QUADRO CLINICO DA CLIENTE, PSICOLOGA CAROLINE CIENTE. ENFª FLORENCE NIGHTINGALE XXXX. DIABETES MELLITUS NAO ESPECIFICADO COM OUTRAS COMPLICACOES ESPECIFICADAS. 21:25h: Comunico  Dr VITAL BRASIL plantão da ortopedia que o paciente esta sem prescrição médica ate o momento. Enf FLORENCE NIGHTINGALE. FRATURA DO MEMBRO INFERIOR NIVEL NAO ESPECIFICADO. 08:30 Horas. Paciente em 2 DI por atropelamento com TCE grave. Permanece em sala de emergencia com ventilação mecanica em modo PCV, FiO2 50%; FR 16; Tempo Insp.: 1.1; Pressão Limite 15; PEEP 4. Monitorizado FC 115; PA 95/45; SpO2 99%. Com curativo em fcc suturado em couro cabeludo e labios. Pupilas anisocoricas (E>D). SOG com debito. AVP em jugular esquerda com Dopamina a 10 ml/h e sedação a 30 ml/h. Ausculta pulmonar com discretos ruidos adventicios, abdomem plano, flaido e indolor a palpação. RHA+. SVD com debito concentrado e grumos laranjas. MMII com escoriações e AVP em MSE salinizado. Apresentou hipertermia, adiantado dipirona cpm. Paciente aguarda vaga em leito para UTI. TRAUMATISMO SUPERFICIAL DO PESCOCO.",
  "entities": {
    "Grupo Profissional ou Ocupacional": [
      "PSICOLOGIA",
      "PSICOLOGA",
      "ENFª",
      "Enf"
    ],
    "Organização Relacionada à Saúde": [
      "PSICOLOGIA",
      "UTI",
      "plantão da ortopedia",
      "sala de emergencia"
    ],
    "Paciente ou Grupo com Deficiência": [
      "CLIENTE",
      "paciente",
      "Paciente"
    ],
    "Abreviação": [
      "ENFª",
      "Dr",
      "Enf",
      "FiO2",
      "FR",
      "PEEP",
      "FC",
      "PA",
      "SpO2",
      "E&gt;D",
      "AVP",
      "RHA+",
      "SVD",
      "MSE",
      "cpm",
      "UTI",
      "TCE grave",
      "modo PCV",
      "fcc suturado",
      "SOG com debito",
      "MMII com escoriações"
    ],
    "Negação": [
      "sem",
      "indolor"
    ],
    "Lesão ou Envenenamento": [
      "atropelamento",
      "FRATURA DO MEMBRO INFERIOR",
      "TCE grave",
      "MMII com escoriações",
      "TRAUMATISMO SUPERFICIAL DO PESCOCO"
    ],
    "Procedimento Terapêutico ou Preventivo": [
      "FiO2",
      "PEEP",
      "curativo",
      "AVP",
      "sedação",
      "SVD",
      "salinizado",
      "ventilação mecanica",
      "modo PCV",
      "Pressão Limite",
      "fcc suturado"
    ],
    "Conceito Quantitativo": [
      "50%",
      "16",
      "15",
      "4",
      "115",
      "95/45",
      "99%",
      "10 ml/h",
      "30 ml/h"
    ],
    "Conceito Qualitativo": [
      "4"
    ],
    "Procedimento Diagnóstico": [
      "Monitorizado",
      "palpação",
      "Ausculta pulmonar"
    ],
    "Atributo Clínico": [
      "FC",
      "PA",
      "SpO2"
    ],
    "Sinal ou Sintoma": [
      "115",
      "hipertermia",
      "Pupilas anisocoricas",
      "discretos ruidos adventicios",
      "grumos laranjas"
    ],
    "Dispositivo Médico": [
      "curativo",
      "AVP",
      "SVD"
    ],
    "Parte do Corpo, Órgão ou Componente Orgânico": [
      "labios",
      "couro cabeludo",
      "jugular esquerda"
    ],
    "Substância Química Orgânica": [
      "Dopamina",
      "dipirona"
    ],
    "Substância Farmacológica": [
      "Dopamina",
      "dipirona"
    ],
    "Substância Biologicamente Ativa": [
      "Dopamina"
    ],
    "Localização ou Região Corporal": [
      "abdomem",
      "MSE"
    ],
    "Achado": [
      "plano",
      "flaido",
      "RHA+",
      "salinizado",
      "SOG com debito",
      "debito concentrado"
    ],
    "Objeto Manufaturado": [
      "leito"
    ],
    "Doença ou Síndrome": [
      "DIABETES MELLITUS"
    ],
    "Atividade de Assistência à Saúde": [
      "prescrição médica"
    ],
    "Produto Intelectual": [
      "prescrição médica"
    ]
  },
  "labels": {}
}