{
  "prontuario_id": 50,
  "text": "14:42 HS ABERTURA OCULAR, TRAQUEOSTOMIZADO , O2 CONTÍNUO, SONDA NASOENTRAL, DIETA EM BI, DIURESE EM FRALDA BOM VOLUME , EVACUAÇÃO DE ASPCETO ENDURECIDO  COM PRESENÇA DE MUCO, EDEMA GENERALIZADO , ABDOME GLOBOSO FLÁCIDO,ESCARA  EM REGIÃO GLÚTEA DE ASPCETO NECRÓTICO, ÚLCERA DE PRESSÃO  EM REGIÃO DE CALCÂNEO EM ESTÁGIO 2, APRESENTA SANGRAMENTO EM REGIÃO ORAL POUCO VOLUME,MANTÉM - SE HIPERTENSO 200/100 ,MEDICADO CONF PRESCRIÇÃO MÉDICA, MANTEM  PRECAUÇÃO DE CONTATO. ENF FLORENCE NIGHTINGALE. COREN XXXX. OBS: COM CONHECIMENTO DR LUCAS RESIDENTE DA NEUROLOGIA. ENF FLORENCE NIGHTINGALE XXXX. ENCEFALITE MIELITE E ENCEFALOMIELITE NAO ESPECIFICADA. Pupilas isofoto +; traqueostomizado, mantido sob VM PI 18, PS 17, PEEP 5, FIO2 35%, SPO2 99%, uso de filtro de barreiras e sistema aberto de aspiração, secreção traqueobrônquica amarelada emo moderada quatidade, CPP com MV diuminuidos e roncos difusos; permenece com cateter nasoenteral para diétoterapia; cateter central em JID de HD uso de 3ª via para infusão de Noradrenliana 2 ml/h em faze de desmame e Heparina 15 ml/h; abdomem globoso flácido RHA+ hipoativos; cateter vesical de demora com diurése efetiva de apecto concentrado; ÚP sacra estávi III extensa com placa de necrose, e em calcâneos bilateral; MM edemaciados cacifo III/IV, perfusão periférica preservada. INSUFICIENCIA RESPIRATORIA NAO CLASSIFICADA DE OUTRA PARTE.",
  "entities": {
    "Achado": [
      "TRAQUEOSTOMIZADO",
      "EVACUAÇÃO",
      "FLÁCIDO",
      "traqueostomizado",
      "flácido",
      "ABERTURA OCULAR",
      "DIURESE EM FRALDA",
      "BOM VOLUME",
      "ASPCETO ENDURECIDO",
      "Pupilas isofoto",
      "secreção traqueobrônquica amarelada",
      "diurése efetiva",
      "apecto concentrado",
      "perfusão periférica preservada"
    ],
    "Procedimento Terapêutico ou Preventivo": [
      "TRAQUEOSTOMIZADO",
      "traqueostomizado",
      "VM",
      "PS",
      "PEEP",
      "FIO2",
      "SPO2",
      "HD",
      "O2 CONTÍNUO",
      "SONDA NASOENTRAL",
      "DIETA EM BI",
      "PRECAUÇÃO DE CONTATO",
      "filtro de barreiras",
      "sistema aberto de aspiração",
      "cateter nasoenteral para diétoterapia",
      "cateter central",
      "faze de desmame",
      "cateter vesical de demora"
    ],
    "Função Fisiológica": [
      "EVACUAÇÃO",
      "diurése efetiva"
    ],
    "Localização ou Região Corporal": [
      "ABDOME",
      "CPP",
      "abdomem",
      "MM",
      "REGIÃO GLÚTEA",
      "REGIÃO DE CALCÂNEO",
      "REGIÃO ORAL"
    ],
    "Sinal ou Sintoma": [
      "GLOBOSO",
      "HIPERTENSO",
      "globoso",
      "PRESENÇA DE MUCO",
      "EDEMA GENERALIZADO",
      "ASPCETO NECRÓTICO",
      "POUCO VOLUME",
      "MV diuminuidos",
      "roncos difusos",
      "RHA+ hipoativos"
    ],
    "Doença ou Síndrome": [
      "ESCARA",
      "ÚLCERA DE PRESSÃO",
      "INSUFICIENCIA RESPIRATORIA"
    ],
    "Função Patológica": [
      "SANGRAMENTO"
    ],
    "Conceito Quantitativo": [
      "200/100",
      "18",
      "17",
      "5",
      "35%",
      "99%",
      "2 ml/h",
      "15 ml/h"
    ],
    "Grupo Profissional ou Ocupacional": [
      "ENF",
      "NEUROLOGIA"
    ],
    "Abreviação": [
      "ENF",
      "DR",
      "VM",
      "PI",
      "PS",
      "PEEP",
      "FIO2",
      "SPO2",
      "CPP",
      "JID",
      "HD",
      "O2 CONTÍNUO",
      "DIETA EM BI",
      "Pupilas isofoto",
      "MV diuminuidos",
      "RHA+ hipoativos"
    ],
    "Organização Relacionada à Saúde": [
      "NEUROLOGIA"
    ],
    "Parte do Corpo, Órgão ou Componente Orgânico": [
      "JID",
      "calcâneos bilateral"
    ],
    "Substância Farmacológica": [
      "Noradrenliana",
      "Heparina"
    ],
    "Hormônio": [
      "Noradrenliana"
    ],
    "Substância Química Orgânica": [
      "Noradrenliana",
      "Heparina"
    ],
    "Substância Biologicamente Ativa": [
      "Heparina"
    ],
    "Dispositivo Médico": [
      "SONDA NASOENTRAL",
      "filtro de barreiras",
      "cateter central",
      "cateter vesical de demora"
    ],
    "Conceito Qualitativo": [
      "BOM VOLUME",
      "ESTÁGIO 2",
      "moderada quatidade",
      "estávi III",
      "cacifo III/IV"
    ]
  },
  "labels": {}
}