{
  "prontuario_id": 812,
  "text": "12:30 HS ALERTA , ABERTURA OCULAR ESPONTÂNEA, PUPILAS ISOCÓRICAS FOTORREAGENTE, TRAQUEOSTOMIZADO, O2 CONTÍNUO, SECREÇÃO ESPESSA MÉDIA QUANTIDADE COLORAÇÃO AMARELA, CABECEIRA ELEVADA A 30 GRAUS, COM CATETER DE DVE EM REGIÃO CEFÁLICA, COM SECREÇÃO LICÓRICA LÍMPIDA ,FUNCIONANTE, CATETER FIXADO COM PONTOS DE SUTURA,  SOMENTE EM BORBOLETA, CATETER MALEÁVEL SEM PONTOS DE SUTURA, DIETA EM JEJUNOSTOMIA  FIXADO , APRESENTANDO PONTO DE SECREÇÃO EM VOLTA DE  ORIFÍCIO, DIURESE E UROPEN, COLORAÇÃO LÍMPIDA , MANTEM PELE INTEGRA, MANTEM PRECAUÇÃO DE CONTATO. ENF FLORENCE NIGHTINGALE, COREN XXXX. OBS: COMUNICADO DR VITAL BRASIL , REFERENTE DVE, SEM PONTOS DE SUTURA EM, CATETER MALEÁVEL . ENF FLORENCE NIGHTINGALE, COREN XXXX.  EDEMA CEREBRAL. 10H35 RETORNOU DO CENTRO CIRÚRGICO POI DE SIMPATECTOMIA TORÁCIA, ACORDADO, CORADO, PUPILAS ISOCÓRICAS, EUPNEICO EM AR AMBIENTE, COMUNICATIVO, CURATIVO PEQUENO EM REGIÃO LATERAL DE TORAX DIREITO E ESQUERDO LIMPO E SECO EXTERNAMENTE, AVP EM MÃO ESQUERDO SALINIZADO, ATÉ O MOMENTO NÃO APRESENTOU ELIMINAÇÕES FISIOLÓGICAS.  ENFª FLORENCE NIGHTINGALE, COREN XX XXXX. EXAME GERAL E INVESTIGACAO DE PESSOAS SEM QUEIXAS OU DIAGNOSTICO RELATADO.",
  "entities": {
    "Achado": [
      "ALERTA",
      "ISOCÓRICAS",
      "FOTORREAGENTE",
      "TRAQUEOSTOMIZADO",
      "FUNCIONANTE",
      "DIURESE",
      "ACORDADO",
      "CORADO",
      "COMUNICATIVO",
      "LIMPO",
      "SECO",
      "SALINIZADO",
      "ABERTURA OCULAR ESPONTÂNEA",
      "COLORAÇÃO AMARELA",
      "SECREÇÃO LICÓRICA LÍMPIDA",
      "COLORAÇÃO LÍMPIDA",
      "PELE INTEGRA",
      "PUPILAS ISOCÓRICAS",
      "EUPNEICO EM AR AMBIENTE",
      "ELIMINAÇÕES FISIOLÓGICAS"
    ],
    "Parte do Corpo, Órgão ou Componente Orgânico": [
      "PUPILAS",
      "MÃO ESQUERDO"
    ],
    "Procedimento Terapêutico ou Preventivo": [
      "TRAQUEOSTOMIZADO",
      "DVE",
      "AVP",
      "SALINIZADO",
      "O2 CONTÍNUO",
      "CABECEIRA ELEVADA A 30 GRAUS",
      "CATETER DE DVE",
      "CATETER FIXADO COM PONTOS DE SUTURA",
      "PONTOS DE SUTURA",
      "DIETA EM JEJUNOSTOMIA FIXADO",
      "PRECAUÇÃO DE CONTATO",
      "SIMPATECTOMIA TORÁCIA",
      "CURATIVO PEQUENO"
    ],
    "Negação": [
      "SEM",
      "NÃO"
    ],
    "Função Fisiológica": [
      "DIURESE",
      "ELIMINAÇÕES FISIOLÓGICAS"
    ],
    "Dispositivo Médico": [
      "UROPEN",
      "DVE",
      "AVP",
      "CATETER DE DVE",
      "CATETER MALEÁVEL",
      "CURATIVO PEQUENO"
    ],
    "Abreviação": [
      "ENF",
      "DR",
      "DVE",
      "POI",
      "AVP",
      "ENFª",
      "CATETER DE DVE"
    ],
    "Grupo Profissional ou Ocupacional": [
      "ENF",
      "ENFª"
    ],
    "Conceito Temporal": [
      "POI"
    ],
    "Conceito Espacial": [
      "EXTERNAMENTE"
    ],
    "Sinal ou Sintoma": [
      "QUEIXAS",
      "SECREÇÃO ESPESSA",
      "PONTO DE SECREÇÃO"
    ],
    "Conceito Qualitativo": [
      "MÉDIA QUANTIDADE"
    ],
    "Localização ou Região Corporal": [
      "REGIÃO CEFÁLICA",
      "REGIÃO LATERAL DE TORAX DIREITO E ESQUERDO"
    ],
    "Substância Corporal": [
      "SECREÇÃO LICÓRICA LÍMPIDA"
    ],
    "Doença ou Síndrome": [
      "EDEMA CEREBRAL"
    ],
    "Organização Relacionada à Saúde": [
      "CENTRO CIRÚRGICO"
    ]
  },
  "labels": {}
}