{
  "prontuario_id": 686,
  "text": "EVOLUÇAO DIA 02/02/10: Acordada, responsiva, eupneica, em repouso no leito e com relato de discreta algia em mie ao se mobilizar. Acesso venoso periferico MSD salinizado, relata aceitaçao alimentar e diurese presente. Enfermeira Florence Nightingale. EMBOLIA E TROMBOSE DE ARTERIAS DOS MEMBROS INFERIORES. À 01:40 H: CLIENTE CONSCIENTE, COMUNICATIVO, ANSIOSO, REPOUSO, AFEBRIL, EUPNEICO, ORIENTADO. ACEITA DIETA OFERECIDA. MANTEM ACESSO PERIFERICO EM MSE SALINIZADO. APRESENTA CURATIVO OCLUSIVO EM REGIÃO DE MIE ASPECTO SECO E LIMPO EXTERNAMENTE. ELIMINAÇÕES NORMAIS. SEGUE EM OBSERVAÇÃO E CUIDADOS. ENFª FLORENCE NIGHTINGALE, COREN XXXX. FRATURA DO PE EXCETO DO TORNOZELO. Em 07/04/2010, 12 hs: Consciente, comunicativa, corada. Sem queixas. Tosse produtiva. Refere mal estar quando administrada a medicacao (ansia). Diurese e evacuacao presentes. Visita controlada. Ac de Enfermagem Florence, sob supervisao da prof Florence Nightingale. PNEUMONIA BACTERIANA NAO ESPECIFICADA. Às 06:11 h: Paciente retirou a SNE, em teste com agua apresenta boa deglutição VO, passo em plantão a necessidade de avaliação da fonoaudiologia para verificar a permanencia da sonda. Enf Florence Nightingale. TRAUMATISMO INTRACRANIANO. Às 7h30min: Encaminhado para o Raio-X para realizar fistulografia. Enfª Florence Nightingale, COREN XX  XXXX. OSTEOMIELITE.",
  "entities": {
    "Achado": [
      "Acordada",
      "responsiva",
      "eupneica",
      "salinizado",
      "CONSCIENTE",
      "COMUNICATIVO",
      "ANSIOSO",
      "REPOUSO",
      "AFEBRIL",
      "EUPNEICO",
      "ORIENTADO",
      "SALINIZADO",
      "SECO",
      "LIMPO",
      "Consciente",
      "comunicativa",
      "corada",
      "Diurese",
      "evacuacao",
      "presentes",
      "repouso no leito",
      "Acesso venoso periferico",
      "aceitaçao alimentar",
      "diurese presente",
      "ACEITA DIETA OFERECIDA",
      "ELIMINAÇÕES NORMAIS",
      "boa deglutição VO"
    ],
    "Localização ou Região Corporal": [
      "mie",
      "MSD",
      "MSE",
      "REGIÃO DE MIE"
    ],
    "Abreviação": [
      "mie",
      "MSD",
      "MSE",
      "ENFª",
      "Enf",
      "Enfª",
      "REGIÃO DE MIE",
      "retirou a SNE",
      "boa deglutição VO"
    ],
    "Procedimento Terapêutico ou Preventivo": [
      "salinizado",
      "SALINIZADO",
      "repouso no leito",
      "Acesso venoso periferico",
      "ACESSO PERIFERICO",
      "CURATIVO OCLUSIVO",
      "Visita controlada",
      "retirou a SNE"
    ],
    "Grupo Profissional ou Ocupacional": [
      "Enfermeira",
      "ENFª",
      "Enfermagem",
      "Enf",
      "Enfª"
    ],
    "Paciente ou Grupo com Deficiência": [
      "CLIENTE",
      "Paciente"
    ],
    "Sinal ou Sintoma": [
      "ANSIOSO",
      "queixas",
      "ansia",
      "discreta algia",
      "Tosse produtiva",
      "mal estar"
    ],
    "Negação": [
      "AFEBRIL",
      "EXCETO",
      "Sem"
    ],
    "Conceito Espacial": [
      "EXTERNAMENTE"
    ],
    "Atividade de Assistência à Saúde": [
      "OBSERVAÇÃO",
      "CUIDADOS",
      "avaliação da fonoaudiologia"
    ],
    "Parte do Corpo, Órgão ou Componente Orgânico": [
      "TORNOZELO"
    ],
    "Substância Farmacológica": [
      "medicacao"
    ],
    "Função Fisiológica": [
      "Diurese",
      "evacuacao",
      "diurese presente",
      "ELIMINAÇÕES NORMAIS"
    ],
    "Organização Relacionada à Saúde": [
      "plantão"
    ],
    "Procedimento Diagnóstico": [
      "Raio-X",
      "fistulografia"
    ],
    "Doença ou Síndrome": [
      "OSTEOMIELITE",
      "PNEUMONIA BACTERIANA"
    ],
    "Dispositivo Médico": [
      "Acesso venoso periferico",
      "ACESSO PERIFERICO",
      "CURATIVO OCLUSIVO"
    ],
    "Lesão ou Envenenamento": [
      "FRATURA DO PE",
      "TRAUMATISMO INTRACRANIANO"
    ]
  },
  "labels": {}
}