{
  "prontuario_id": 802,
  "text": "ÀS 15:03 H - PROVENIENTE DA UTI 2 ÀS 14h24min, EUPNEICA, SONOLENTA, COM CATETER DE O². ACESSO VENOSO PERIFÉRICO EM FACE ANTERIOR DO ANTEBRAÇO ESQUERDO SEM SINAIS FLOGÍSTICOS. SONDA VESICAL DE DEMORA COM DÉBITO AMARELADO. ACADÊMICA DE ENFERMAGEM DO 8º PERÍODO FLORENCE NIGHTINGALE. ORIENTADA PELA ENFERMEIRA FLORENCE NIGHTINGALE. SINDROME DO DESCONFORTO RESPIRATORIO DO ADULTO. ÀS 17:30 h - Consciente, comunicativo, eupneico, em ar ambiente, deambulando sem auxilio, normotenso, normocorado, aceitando dieta oferecida, sem acesso venoso, fistula em MSE, abdomen globoso e semi-flacido, faz uso de cinta abdominal, diurese presente de coloraçao amarelo citrico, nega queixas algicas, realizada medidas de conforto, coletado exames de urina, segue sob cuidados. Enf Florence. DOENCA RENAL EM ESTADIO FINAL. Às 00:30 h: Encontra-se consciente, orientado, verbalizando, deambulando, ssvv dentro dos parametros de normalidade, mantem acesso venoso central em jugular interna D, curativo em MSE limpo e seco externamente, aguarda  curativo cirúrgico em 25/01, relata boa aceitação alimentar, eliminações fisiologicas presentes, segue sob cuidados de enfermagem. Enf Florence Nightingale, XXXX. ABSCESSO CUTANEO FURUNCULO E ANTRAZ DE LOCALIZACAO NAO ESPECIFICADA. Às 01:25 HS: CÇA ATIVA, RESPONDENDO A ESTIMULOS VERBAIS, CHOROSA, ACESSO VENOSO PERIFÉRICO SALINIZADO, BOA ACEITAÇÃO DA DIETA, PRESENÇA DE LESÃO DE PELE EM MIE, MANTENDO TRAÇÃO DE MIE, DIURESE PRESENTE, SEGUE SOB CUIDADOS. FRATURA DA DIAFISE DO FEMUR.",
  "entities": {
    "Abreviação": [
      "UTI",
      "MSE",
      "Enf",
      "MIE",
      "ssvv dentro dos parametros de normalidade",
      "jugular interna D",
      "TRAÇÃO DE MIE"
    ],
    "Organização Relacionada à Saúde": [
      "UTI"
    ],
    "Achado": [
      "EUPNEICA",
      "Consciente",
      "comunicativo",
      "eupneico",
      "deambulando",
      "normotenso",
      "normocorado",
      "consciente",
      "orientado",
      "verbalizando",
      "limpo",
      "seco",
      "ATIVA",
      "CHOROSA",
      "DÉBITO AMARELADO",
      "em ar ambiente",
      "aceitando dieta",
      "diurese presente",
      "coloraçao amarelo citrico",
      "ssvv dentro dos parametros de normalidade",
      "boa aceitação alimentar",
      "eliminações fisiologicas presentes",
      "RESPONDENDO A ESTIMULOS VERBAIS",
      "BOA ACEITAÇÃO DA DIETA",
      "DIURESE PRESENTE"
    ],
    "Sinal ou Sintoma": [
      "SONOLENTA",
      "globoso",
      "semi-flacido",
      "SINAIS FLOGÍSTICOS",
      "queixas algicas"
    ],
    "Negação": [
      "SEM",
      "sem",
      "nega"
    ],
    "Atividade de Assistência à Saúde": [
      "ORIENTADA",
      "cuidados",
      "CUIDADOS",
      "medidas de conforto",
      "cuidados de enfermagem"
    ],
    "Grupo Profissional ou Ocupacional": [
      "ENFERMEIRA",
      "Enf",
      "ACADÊMICA DE ENFERMAGEM"
    ],
    "Anormalidade Anatômica": [
      "fistula"
    ],
    "Localização ou Região Corporal": [
      "MSE",
      "abdomen",
      "MIE",
      "FACE ANTERIOR DO ANTEBRAÇO ESQUERDO"
    ],
    "Procedimento Terapêutico ou Preventivo": [
      "curativo",
      "CATETER DE O²",
      "ACESSO VENOSO PERIFÉRICO",
      "SONDA VESICAL DE DEMORA",
      "acesso venoso",
      "cinta abdominal",
      "medidas de conforto",
      "acesso venoso central",
      "curativo cirúrgico",
      "TRAÇÃO DE MIE"
    ],
    "Dispositivo Médico": [
      "curativo",
      "ACESSO VENOSO PERIFÉRICO",
      "SONDA VESICAL DE DEMORA",
      "acesso venoso",
      "cinta abdominal",
      "acesso venoso central",
      "curativo cirúrgico"
    ],
    "Conceito Espacial": [
      "externamente"
    ],
    "Doença ou Síndrome": [
      "SINDROME DO DESCONFORTO RESPIRATORIO DO ADULTO",
      "DOENCA RENAL EM ESTADIO FINAL",
      "ABSCESSO CUTANEO FURUNCULO E ANTRAZ"
    ],
    "Função Fisiológica": [
      "diurese presente",
      "eliminações fisiologicas presentes",
      "DIURESE PRESENTE"
    ],
    "Procedimento Laboratorial": [
      "exames de urina"
    ],
    "Parte do Corpo, Órgão ou Componente Orgânico": [
      "jugular interna D"
    ],
    "Lesão ou Envenenamento": [
      "FRATURA DA DIAFISE DO FEMUR"
    ]
  },
  "labels": {}
}