{
  "prontuario_id": 356,
  "text": "15:29h Paciente consciente, orientado, em repouso no leito, eupineico, hipocorado, com CVC em soroterapia, curativo oclusivo em região abdominal seco e limpo externamente, dreno de penhouse com bolsa de colostomia funcionante. Relata cefaléia intensa e parestesia em MIE.  Enf FLORENCE NIGHTINGALE, Coren XX XXXX. DOR ABDOMINAL E PELVICA. 08:30hs- Glasgow 13, pupilas isocóricas fotorreagentes, SNG aberta com pouca estase biliosa, respiração espontânea, com névoa úmida 5 l/m, SpO2 98%, acesso venoso central D com Noradrenalina 20 ml/h, monitorizada, estável hemodinamicamente, MV diminuído em bases sem R/A, abdome distendido, rígido, doloroso a palpação, presença de massa + hematoma em flanco E, RHA diminuído, SVd com diurese efetiva, evacuação ausente, extremidades quentes e bem perfundidas, higienizada e mobilizada no leito, pele íntegra. Enfª FLORENCE NIGHTINGALE, XXXX. HEMORRAGIA EPIDURAL.",
  "entities": {
    "Paciente ou Grupo com Deficiência": [
      "Paciente"
    ],
    "Achado": [
      "consciente",
      "orientado",
      "eupineico",
      "seco",
      "limpo",
      "funcionante",
      "isocóricas",
      "fotorreagentes",
      "monitorizada",
      "higienizada",
      "repouso no leito",
      "respiração espontânea",
      "estável hemodinamicamente",
      "diurese efetiva",
      "bem perfundidas",
      "pele íntegra"
    ],
    "Sinal ou Sintoma": [
      "hipocorado",
      "parestesia",
      "DOR",
      "R/A",
      "distendido",
      "rígido",
      "cefaléia intensa",
      "Glasgow 13",
      "pouca estase biliosa",
      "MV diminuído em bases",
      "doloroso a palpação",
      "RHA diminuído"
    ],
    "Dispositivo Médico": [
      "CVC",
      "SVd",
      "curativo oclusivo",
      "dreno de penhouse",
      "bolsa de colostomia",
      "acesso venoso central D"
    ],
    "Procedimento Terapêutico ou Preventivo": [
      "CVC",
      "soroterapia",
      "SVd",
      "higienizada",
      "repouso no leito",
      "curativo oclusivo",
      "dreno de penhouse",
      "SNG aberta",
      "névoa úmida",
      "acesso venoso central D",
      "mobilizada no leito"
    ],
    "Abreviação": [
      "CVC",
      "MIE",
      "Enf",
      "SpO2",
      "R/A",
      "SVd",
      "Enfª",
      "SNG aberta",
      "acesso venoso central D",
      "MV diminuído em bases",
      "flanco E",
      "RHA diminuído"
    ],
    "Conceito Espacial": [
      "externamente"
    ],
    "Localização ou Região Corporal": [
      "MIE",
      "ABDOMINAL",
      "PELVICA",
      "abdome",
      "extremidades",
      "região abdominal",
      "flanco E"
    ],
    "Grupo Profissional ou Ocupacional": [
      "Enf",
      "Enfª"
    ],
    "Parte do Corpo, Órgão ou Componente Orgânico": [
      "pupilas"
    ],
    "Atributo Clínico": [
      "SpO2"
    ],
    "Conceito Quantitativo": [
      "98%",
      "5 l/m",
      "20 ml/h"
    ],
    "Substância Química Orgânica": [
      "Noradrenalina"
    ],
    "Hormônio": [
      "Noradrenalina"
    ],
    "Substância Farmacológica": [
      "Noradrenalina"
    ],
    "Procedimento Diagnóstico": [
      "monitorizada"
    ],
    "Negação": [
      "sem",
      "ausente"
    ],
    "Função Patológica": [
      "hematoma"
    ],
    "Função Fisiológica": [
      "evacuação",
      "diurese efetiva"
    ],
    "Substância Corporal": [
      "pouca estase biliosa"
    ],
    "Doença ou Síndrome": [
      "HEMORRAGIA EPIDURAL"
    ]
  },
  "labels": {}
}