{
  "prontuario_id": 618,
  "text": "# HAS, # Tabagista, # DM, # Claudicação Prévia Msis. Paciente interna proveniente do ambulatório devido à úlceras extensas em MIE secundário a vasculopatia periférica com inviabilidade do membro. Paciente foi submetida a amputação SC MIE sob anestesia raquidiana. Não apresentou intercorrências no trans-operatório. Apresentou boa evolução pós-op e tem alta em bom estado geral, com orientações e retorno para Fisiatria e Cir vascular. Paciente portadora de carcinoma medular de tireoide internou para realização de linfadenectomia cervical bilateral. Intra e pós-operatórios sem intercorrências. Com sequelas de cirurgia prévia apresentando paralisia de prega vocal esquerda e hipoparatireoidismo que mantiveram-se inalterados com o atual procedimento. Paciente com IRC, ICC, vem ao XXXX por inapetência, tosse e escarro. Rx de tórax sem consolidações. Prescrevo amoxicilina para tratamento de infecção respiratória alta. Hidrato EV. Paciente G3 P1 A1, Tipo Sang Mãe AB -, IG de 40 sem 4 dia(s), vem com queixa de contrações fortes e dolorosas. Interna com diagnóstico de trabalho de parto e apresentação pélvica. Cesárea por apresentação pélvica em 14/06/2007, as 11:10 hs. RN APGAR 9/10, MASC, 4170 G. Puerpério evolui sem intercorrências. Solicito VDRL não reag,  TOXO IGG não reag e IGM não reag, HBsAg negativo, anti-HIV não reag ,CI negativo e TSRN B +. Administrado Rhogan. Recebe alta em bom estado geral, sinais vitais estáveis e orientações gerais.",
  "entities": {
    "Abreviação": [
      "HAS",
      "DM",
      "MIE",
      "pós-op",
      "Fisiatria",
      "IRC",
      "ICC",
      "G3",
      "P1",
      "A1",
      "IG",
      "RN",
      "MASC",
      "Cir vascular",
      "Rx de tórax",
      "Hidrato EV",
      "Tipo Sang Mãe AB -",
      "40 sem 4 dia",
      "VDRL não reag",
      "TOXO IGG não reag",
      "IGM não reag",
      "HBsAg negativo",
      "anti-HIV não reag",
      "CI negativo",
      "TSRN B +"
    ],
    "Doença ou Síndrome": [
      "HAS",
      "Tabagista",
      "DM",
      "hipoparatireoidismo",
      "IRC",
      "ICC",
      "vasculopatia periférica",
      "infecção respiratória alta"
    ],
    "Paciente ou Grupo com Deficiência": [
      "Paciente"
    ],
    "Organização Relacionada à Saúde": [
      "ambulatório",
      "Fisiatria",
      "Cir vascular"
    ],
    "Localização ou Região Corporal": [
      "MIE"
    ],
    "Procedimento Terapêutico ou Preventivo": [
      "amputação",
      "procedimento",
      "anestesia raquidiana",
      "linfadenectomia cervical bilateral",
      "Hidrato EV",
      "Cesárea por apresentação pélvica"
    ],
    "Negação": [
      "Não",
      "sem"
    ],
    "Sinal ou Sintoma": [
      "intercorrências",
      "inapetência",
      "tosse",
      "escarro",
      "queixa",
      "dolorosas",
      "Claudicação Prévia",
      "TSRN B +"
    ],
    "Conceito Temporal": [
      "trans-operatório",
      "pós-op",
      "prévia",
      "Intra e pós-operatórios"
    ],
    "Atividade de Assistência à Saúde": [
      "alta",
      "orientações",
      "retorno"
    ],
    "Grupo Profissional ou Ocupacional": [
      "Fisiatria",
      "Cir vascular"
    ],
    "Função Patológica": [
      "sequelas"
    ],
    "Substância Corporal": [
      "escarro"
    ],
    "Substância Química Orgânica": [
      "amoxicilina"
    ],
    "Antibiótico": [
      "amoxicilina"
    ],
    "Achado": [
      "G3",
      "P1",
      "A1",
      "inviabilidade do membro",
      "boa evolução",
      "bom estado geral",
      "apresentação pélvica",
      "Cesárea por apresentação pélvica",
      "sinais vitais estáveis"
    ],
    "Atributo Clínico": [
      "IG"
    ],
    "Grupo Etário": [
      "RN"
    ],
    "Atributo de Organismo": [
      "MASC"
    ],
    "Substância Farmacológica": [
      "Rhogan"
    ],
    "Processo Neoplásico": [
      "carcinoma medular de tireoide"
    ],
    "Procedimento Diagnóstico": [
      "Rx de tórax"
    ],
    "Resultado Laboratorial ou de Teste": [
      "Tipo Sang Mãe AB -",
      "VDRL não reag",
      "TOXO IGG não reag",
      "IGM não reag",
      "HBsAg negativo",
      "anti-HIV não reag",
      "CI negativo",
      "TSRN B +"
    ],
    "Conceito Quantitativo": [
      "40 sem 4 dia",
      "4170 G"
    ]
  },
  "labels": {}
}