{
  "prontuario_id": 590,
  "text": "Paciente com as seguintes comorbidades: - HAS, - Etilismo ativo, - Gota, - Dislipidemia, - Dispnéia aos esforços desde 2001, - DM tipo 2, - Ecocardio 2001 com FE 43 %,  hipocinesia difusa. Acompanhamento irregular no Ambu de Medicina Interna do XXXX com quadro de ICC. Má adesão ao tratamento. Procura Emergência do XXXX em 03/09/04 com quadro de dispnéia em repouso, ortopnéia, edema de MsIs, caracterizando quadro de INSUFICIÊNCIA CARDÍACA CONGESTIVA DESCOMPENSADA - CLASSE 4. Investigado inicialmente para TEP / TVP com Cintilografia Perfusional e Eco doppler de MsIs, sem evidências de tais comorbidades. Caracterizado sinais e sintomas por ICC descompensada, devido a MÁ ADESÃO AO TRATAMENTO (não vinha em uso regular das medicações prescritas). Iniciado tratamento com diuréticos, inicialmente EV e após VO, bem como IECA e digoxina, com melhora importante do quadro. Recebe alta com sintomas de ICC CLASSE 2, com a seguinte prescrição: 1 - AAS 100 mg ao dia. 2- Digoxina 0,125 mg ao dia. 3- Furosemida 40 mg 2x ao dia. 4- Captopril 25 mg de 8/8 horas. Recebe as seguintes orientações na alta: 1- Uso correto e regular das medicações prescritas. 2- Retorno ao Ambulatório de Cardiologia para acompanhamento --> encaminhar a posteriori para Ambu ICT. 3- Orientação de retorno à emergência se dispnéia, síncope, edema importante, bem como outros sinais de piora do estado geral. Plano: 1- Investigar isquemia miocárdica em caráter eletivo. 2- Aumentar IECA e iniciar beta-bloqueador conforme necessidade.",
  "entities": {
    "Paciente ou Grupo com Deficiência": [
      "Paciente"
    ],
    "Doença ou Síndrome": [
      "comorbidades",
      "HAS",
      "Gota",
      "Dislipidemia",
      "ICC",
      "TEP",
      "TVP",
      "DM tipo 2",
      "INSUFICIÊNCIA CARDÍACA CONGESTIVA DESCOMPENSADA - CLASSE 4",
      "ICC descompensada",
      "ICC CLASSE 2"
    ],
    "Abreviação": [
      "HAS",
      "Ecocardio",
      "ICC",
      "TEP",
      "TVP",
      "EV",
      "VO",
      "IECA",
      "AAS",
      "DM tipo 2",
      "FE 43 %",
      "Eco doppler de MsIs",
      "ICC descompensada",
      "ICC CLASSE 2",
      "Aumentar IECA"
    ],
    "Procedimento Diagnóstico": [
      "Ecocardio",
      "Investigado",
      "Cintilografia Perfusional",
      "Eco doppler de MsIs"
    ],
    "Organização Relacionada à Saúde": [
      "Emergência",
      "emergência",
      "Ambulatório de Cardiologia"
    ],
    "Sinal ou Sintoma": [
      "ortopnéia",
      "edema",
      "sintomas",
      "dispnéia",
      "síncope",
      "Dispnéia aos esforços",
      "dispnéia em repouso",
      "sinais e sintomas",
      "edema importante",
      "sinais de piora do estado geral"
    ],
    "Negação": [
      "sem",
      "não"
    ],
    "Substância Farmacológica": [
      "diuréticos",
      "IECA",
      "digoxina",
      "AAS",
      "Digoxina",
      "Furosemida",
      "Captopril",
      "medicações",
      "beta-bloqueador",
      "Aumentar IECA"
    ],
    "Substância Química Orgânica": [
      "digoxina",
      "AAS",
      "Digoxina",
      "Furosemida"
    ],
    "Atividade de Assistência à Saúde": [
      "alta",
      "prescrição",
      "orientações",
      "Retorno",
      "acompanhamento",
      "Orientação",
      "retorno"
    ],
    "Produto Intelectual": [
      "prescrição"
    ],
    "Aminoácido, Peptídeo ou Proteína": [
      "Captopril"
    ],
    "Resultado Laboratorial ou de Teste": [
      "FE 43 %",
      "hipocinesia difusa"
    ],
    "Procedimento Terapêutico ou Preventivo": [
      "uso regular das medicações",
      "Aumentar IECA"
    ],
    "Achado": [
      "melhora importante"
    ],
    "Conceito Quantitativo": [
      "100 mg",
      "0 , 125 mg ao dia",
      "40 mg",
      "25 mg"
    ],
    "Conceito Qualitativo": [
      "0 , 125 mg ao dia"
    ]
  },
  "labels": {}
}