{
  "prontuario_id": 414,
  "text": "Paciente portados de HAS, mutação do gene da protrombina em anticoagulação crônica com warfarin com IAM e AVC em 2001 com sequela (déficit motor à esquerda) com CAT de 2001 evidenciando hipertrofia de VE e coronárias normais. Ergometria de 06/04 com baixa capacidade funcional. Em 30/12/04 iniciou com dor retroesternal, em aperto, intensa sem irradiação. Veio à emergência do XXXX. ECG inalterado em relação aos prévios. Marcadores de injúria miocárdica sem alteração e com alívio da dor com isordil SL. frente ao diagnóstico de angina instável, o paciente foi internado na UTI coronariana e iniciado enoxaparina, propranolol e nitrato fixo. Evoluiu com alguns episódios de dor e após 36h sem dor, sem alteração eletrocardiográfica ou enzimática, recebeu alta para a internação na equipe de cardiologia em BEG, hemodinamicamente estável, PA controlada, com warfarin reiniciado e com plano de suspender enoxaparina após 7 dias de warfarina (INR entre 2,0 e 3,0). No andar evoluiu cardiologicamente bem. A enoxaparina foi suspense quando o INR estava em 2,38. Paciente recebe alta em BEG, anticoagulado, sem sangramentos, hemodinamicamente estável, eupnéico, afebril e com plano de retorno ambulatorial (cardiologia) com o Dr VITAL BRASIL. Sai com prescrição domiciliar de : - Propranolol 40 mg TID - AAS 100 mg / dia - Isossorbida 40 mg TID - Isossorbida 5 mg SL s/n - Varfarina 5 mg /dia.",
  "entities": {
    "Paciente ou Grupo com Deficiência": [
      "Paciente",
      "paciente"
    ],
    "Doença ou Síndrome": [
      "HAS",
      "IAM",
      "AVC",
      "mutação do gene da protrombina",
      "angina instável"
    ],
    "Abreviação": [
      "HAS",
      "IAM",
      "AVC",
      "CAT",
      "BEG",
      "Dr",
      "AAS",
      "hipertrofia de VE",
      "ECG inalterado em relação aos prévios",
      "isordil SL",
      "UTI coronariana",
      "PA controlada",
      "5 mg SL"
    ],
    "Substância Farmacológica": [
      "warfarin",
      "enoxaparina",
      "propranolol",
      "nitrato",
      "warfarina",
      "Propranolol",
      "AAS",
      "Isossorbida",
      "Varfarina",
      "isordil SL"
    ],
    "Substância Química Orgânica": [
      "warfarin",
      "enoxaparina",
      "propranolol",
      "warfarina",
      "Propranolol",
      "AAS",
      "Isossorbida",
      "Varfarina"
    ],
    "Sinal ou Sintoma": [
      "sequela",
      "intensa",
      "irradiação",
      "dor",
      "déficit motor à esquerda",
      "dor retroesternal",
      "em aperto",
      "episódios de dor"
    ],
    "Procedimento Terapêutico ou Preventivo": [
      "CAT",
      "anticoagulação crônica",
      "plano de suspender",
      "prescrição domiciliar"
    ],
    "Procedimento Diagnóstico": [
      "CAT",
      "Ergometria"
    ],
    "Conceito Qualitativo": [
      "intensa"
    ],
    "Negação": [
      "sem",
      "afebril"
    ],
    "Organização Relacionada à Saúde": [
      "emergência",
      "cardiologia",
      "UTI coronariana"
    ],
    "Conceito Funcional": [
      "diagnóstico"
    ],
    "Atividade de Assistência à Saúde": [
      "alta",
      "retorno ambulatorial"
    ],
    "Achado": [
      "BEG",
      "anticoagulado",
      "eupnéico",
      "afebril",
      "alívio da dor",
      "hemodinamicamente estável",
      "PA controlada",
      "evoluiu cardiologicamente bem"
    ],
    "Função Patológica": [
      "sangramentos"
    ],
    "Grupo Profissional ou Ocupacional": [
      "cardiologia",
      "equipe de cardiologia"
    ],
    "Resultado Laboratorial ou de Teste": [
      "mutação do gene da protrombina",
      "hipertrofia de VE",
      "coronárias normais",
      "baixa capacidade funcional",
      "ECG inalterado em relação aos prévios",
      "Marcadores de injúria miocárdica sem alteração",
      "INR entre 2 , 0 e 3 , 0"
    ],
    "Conceito Quantitativo": [
      "40 mg",
      "100 mg",
      "5 mg SL",
      "5 mg"
    ]
  },
  "labels": {}
}