{
  "prontuario_id": 66,
  "text": "Paciente com hipogamaglobulinemia em tratamento de bcp com boa evolução, recebe imunoglobulina em 14/06. Recebe alta em tratamento com antibioticos VO e retorno ao ambulatorio de Imuno. Paciente interna por pneumonia bacteriana. Iniciados antibiotícos com boa resposta clínica. Recebe alta com plano de retorno ao consultório da médica assistente Dra Maria. Familiares orientados a seguir com uso das medicações prescritas e a procurar emergência em caso intercorrências. Paciente no momento sem queixas. Vejo exames: GGT 599, FA 195, BT 2,4. RETORNAR À EMERGENCIA AMANHA PARA REAVALIAÇÃO. BIPAR GASTRO SE NECESSÁRIO. PACIENTE COM DM E IRC, COM COLECISTITE VEIO À EMERGÊNCIA POR DOR E URINA ESCURA. EVOLUIU COM MELHORA DA DOR. MELHORA DAS PFH E AUSÊNCIA DE PANCREATITE. TEM CONSULTA MARCADA PARA JULHO, NA CIRURGIA PARA ENCAMINHAMENTO DA COLECISTECTOMIA. G2 P1, Tipo Sang Mãe O -, IG de 38 sem 3 dia(s), interna em trabalho de parto. Evolui para Parto Eutócico com episiotomia em 18/06/2007, 01:10 hs, RN  APGAR 8 / 10, FEM, 2975 G, VDRL: NR, Anti-HIV: NR, HBsAg: NR, Toxo igg e igm: NR. TSRN: O -. Recebe alta em bom estado geral, sinais vitais estáveis, mamas lactantes, lóquios fisiológicos, útero contraído.",
  "entities": {
    "Paciente ou Grupo com Deficiência": [
      "Paciente",
      "PACIENTE"
    ],
    "Doença ou Síndrome": [
      "hipogamaglobulinemia",
      "bcp",
      "DM",
      "IRC",
      "COLECISTITE",
      "PANCREATITE",
      "pneumonia bacteriana"
    ],
    "Abreviação": [
      "bcp",
      "Dra",
      "GGT",
      "GASTRO",
      "DM",
      "IRC",
      "G2",
      "P1",
      "IG",
      "RN",
      "FEM",
      "TSRN",
      "antibioticos VO",
      "ambulatorio de Imuno",
      "MELHORA DAS PFH",
      "Tipo Sang Mãe O -",
      "38 sem 3 dia",
      "VDRL : NR",
      "Anti-HIV : NR",
      "HBsAg : NR",
      "Toxo igg e igm : NR"
    ],
    "Fator Imunológico": [
      "imunoglobulina"
    ],
    "Aminoácido, Peptídeo ou Proteína": [
      "imunoglobulina"
    ],
    "Substância Farmacológica": [
      "imunoglobulina",
      "antibiotícos"
    ],
    "Atividade de Assistência à Saúde": [
      "alta",
      "retorno",
      "REAVALIAÇÃO",
      "CONSULTA"
    ],
    "Antibiótico": [
      "antibiotícos",
      "antibioticos VO"
    ],
    "Organização Relacionada à Saúde": [
      "consultório",
      "emergência",
      "EMERGENCIA",
      "EMERGÊNCIA",
      "ambulatorio de Imuno"
    ],
    "Grupo Familiar": [
      "Familiares"
    ],
    "Sinal ou Sintoma": [
      "intercorrências",
      "queixas",
      "DOR",
      "URINA ESCURA",
      "MELHORA DA DOR"
    ],
    "Negação": [
      "sem",
      "AUSÊNCIA"
    ],
    "Resultado Laboratorial ou de Teste": [
      "exames",
      "Tipo Sang Mãe O -",
      "VDRL : NR",
      "Anti-HIV : NR",
      "HBsAg : NR",
      "Toxo igg e igm : NR"
    ],
    "Procedimento Laboratorial": [
      "exames"
    ],
    "Conceito Quantitativo": [
      "599",
      "195",
      "2 , 4",
      "38 sem 3 dia",
      "2975 G"
    ],
    "Grupo Profissional ou Ocupacional": [
      "GASTRO",
      "médica assistente"
    ],
    "Procedimento Terapêutico ou Preventivo": [
      "CIRURGIA",
      "COLECISTECTOMIA",
      "episiotomia",
      "em tratamento",
      "uso das medicações prescritas",
      "trabalho de parto",
      "Parto Eutócico"
    ],
    "Achado": [
      "G2",
      "boa evolução",
      "boa resposta clínica",
      "MELHORA DAS PFH",
      "bom estado geral",
      "sinais vitais estáveis",
      "mamas lactantes",
      "lóquios fisiológicos",
      "útero contraído"
    ],
    "Atributo Clínico": [
      "IG"
    ],
    "Grupo Etário": [
      "RN"
    ],
    "Atributo de Organismo": [
      "FEM"
    ]
  },
  "labels": {}
}