{
  "prontuario_id": 436,
  "text": "Paciente apresentou quadro de pancreatite aguda biliar, em 04/07. Realizada CPRE internada, com esfincterectomia (sem calculos no coledoco) e encaminhada para realização de colecistectomia. Paciente internou eletivamente e foi submetida a colecistectomia videolaparoscópica em 25/06/07, sem intercorrências. Colangiografia transoperatória não demonstrou cálculos na via biliar. Recebe alta em bom estado geral, afebril, aceitando bem dieta via oral, com orientação de retornar à emergência se piora aguda. Paciente com incontinência urinária de esforço com cistocele e retocele, interna para realização de perineoplastia anterior e posterior com Sling, procedimento sem intercorrências. Apresenta adequada evolução pós-operatória, recebe alta com diurese expontânea, afebril, com orientações quanto a cateterismo intermitente pós-miccional e retorno ambulatorial. # Tabagista (1 maço / dia), # Etilista, # HCV +. Admitido na E-XXXX dia 30/04/07 com quadro de dispnéia, tosse com escarro amarelado e emagrecimento de 3 Kg há 2 meses. RX tórax com volumoso derrame pleural à direita. Puncionado derrame com aspecto hemático - ADA 61,2 U/L; Glicose 335; LDH 223; Proteínas Totais 6,0; pesquisa de fungos e BAAR negativos; cultura sem crescimento bacteriano. Hemograma sem leucocitose. Hemoculturas sem crescimento bacteriano. Função renal normal. Realizado toracocentese com biópsia de pleura (04/05): AP: INFLAMAÇÃO CRÔNICA DE PADRÃO MORFOLÓGICO NÃO ESPECÍFICO E SEROSA. PESQUISA DE FUNGOS E BAAR NEGATIVAS. TC Tórax (05/05): Volumoso derrame pleural à direita e mínimo à esquerda. Alguns pequenos linfonodos mediastinais. Mediastino desviado para a esquerda. Material denso depositado posteriormente na cavidade pleural direita (debris?). Micronódulo subpleural na periferia do subsegmento lingular inferior. Atelectasia subtotal do pulmão direito, permanecendo insuflado o lobo superior. Raros focos de calcificação no pulmão atelectasiado. PSA (09/05): 0,12.  Realizada nova TC de tórax: Volumoso derrame pleural à direita. Formações arredondadas justa-pleurais na porção posterior da cavidade pleural à direita, a maior medindo cerca de 1,7 cm, sugestivas de implantes secundários. Atelectasia subtotal do pulmão direito comprometendo especialmente o segmento medial do lobo médio e a pirâmide basal. Atenuação em vidro fosco no lobo superior direito. Sem evidência de processo expansivo ou linfonodomegalias no mediastino. Submetido a FBC (16/05): laringe edemaciada e hiperemiada, com vascularização proeminente, cordas vocais móveis e simétricas. Brônquio LSD desviado, sem evidência de lesões. Edema de mucosa e estenose secundária à provável compressão extrínseca no brônquio lobar médio, sem evidência de lesões. Brônquio lobar inferior direito do segmento apical do LID apresentando importante estenose secundária à compressão extrínseca (derrame pleural?). Ausência de secreções patológicas. Realizado LBA do LM (segmento medial): BAAR e CP negativos. Dia 18/05, submetido a pleuroscopia com aspiração e drenagem com nova biópsia pleural (sendo colocado dreno com escape aéreo). Achados: grande volume de líquido pleural (3000 ml) de aspecto sanguinolento em cavidade pleural direita. Pleura parietal apresentando diminutas micronodularidades com eritema e neovascularização difusas. Pulmão com boa expansibilidade na cavidade torácica. AP - PEÇA CIRÚRGICA (PLEURA DIAFRAGMÁTICA DIREITA): INFLAMAÇÃO CRÔNICA EM SEROSA COM FOCOS DE HIPERPLASIA MESOTELIAL, SINAIS DE HEMORRAGIA ANTIGA E EXSUDATO FIBRINO-NEUTROCITÁRIO. Em 24/05 iniciado RHZ empírico. Solicitada nova TC de tórax após drenagem do derrame pleural. TC Tórax (30/05): Derrame pleural bilateral. Área de consolidação e atelectasia em lobo inferior direito. Observa-se infiltração e pequena quantidade de  líquido coletado em goteira parieto-cólica direita. Há espessamento das paredes do ceco e infiltração dos planos de gordura adjacentes de aspecto sugestivo de lesão inflamatória. A possibilidade de lesão neoplásica não pode ser totalmente afastada. Pequena quantidade de líquido livre na cavidade abdominal. Devido aos achados desta TC, solicitada TC de ABD complementar - (31/05): Observa-se infiltração e pequena quantidade de líquido coletado em goteira parieto-cólica direita. Há espessamento das paredes do ceco e infiltração dos planos de gordura adjacentes de aspecto sugestivo de lesão inflamatória. A possibilidade de lesão neoplásica não pode ser totalmente afastada. Pequena quantidade de líquido livre na cavidade abdominal. Submetido a colonoscopia sem evidência de lesão sugestiva de neoplasia. Permaneceu com dreno de tórax até dia 13/06 com drenagem de liquido pleural progressivamente maior. Submetido a nova biópsia de pleura a pleurodese a direita. Evoluiu com expansão relativa de pulmão direito e inicio de derrame pleural a esquerda, com necessidade  de toracocenteses de alivio diárias, com drenagem de cerca de 1500 ml. Material enviado para laboratório externo ao XXXX, que encontrou achados de inflamação, sem evidência de neoplasia ou granuloma.    Paciente evoluiu com hipoalbuminemia severa, com drenagem elevada de liquido pleural, edema generalizado e ascite. Iniciado o uso de diuréticos, com necessidade de suspensão devido a piora da função renal. Apresentou piora do padrão ventilatório, suspeita clínica de BCP ou TEP. Solicitados culturas, realizado raio-x de tórax com possível foco de consolidação em base  direita. Iniciado empiricamente Cefepime e vancomicina. Hemoculturas com crescimento de cocos gram positivos em aglomerados.    Apresentou piora clínica significativa, evoluindo para choque séptico refratário e parada cardio-respiratória em assistolia, sem resposta as medidas de reanimação cardíaca, indo a óbito.",
  "entities": {
    "Paciente ou Grupo com Deficiência": [
      "Paciente"
    ],
    "Atividade de Assistência à Saúde": [
      "Realizada",
      "encaminhada",
      "realização",
      "internou",
      "alta",
      "orientação",
      "retornar",
      "interna",
      "orientações",
      "Realizado",
      "Solicitada",
      "Iniciado",
      "suspensão",
      "Solicitados",
      "realizado",
      "retorno ambulatorial"
    ],
    "Procedimento Diagnóstico": [
      "CPRE",
      "toracocentese",
      "AP",
      "FBC",
      "pleuroscopia",
      "TC",
      "colonoscopia",
      "Colangiografia transoperatória",
      "RX tórax",
      "biópsia de pleura",
      "TC Tórax",
      "TC de tórax",
      "biópsia pleural",
      "TC de ABD",
      "raio-x de tórax"
    ],
    "Abreviação": [
      "CPRE",
      "PSA",
      "FBC",
      "LBA",
      "LM",
      "AP",
      "RHZ",
      "TC",
      "BCP",
      "TEP",
      "HCV +",
      "RX tórax",
      "TC Tórax",
      "TC de tórax",
      "BAAR e CP negativos",
      "TC de ABD"
    ],
    "Procedimento Terapêutico ou Preventivo": [
      "CPRE",
      "esfincterectomia",
      "colecistectomia",
      "procedimento",
      "Puncionado",
      "toracocentese",
      "aspiração",
      "drenagem",
      "colecistectomia videolaparoscópica",
      "perineoplastia anterior e posterior",
      "cateterismo intermitente pós-miccional",
      "dreno com escape aéreo",
      "drenagem do derrame pleural",
      "dreno de tórax",
      "toracocenteses de alivio",
      "medidas de reanimação cardíaca"
    ],
    "Negação": [
      "sem",
      "não",
      "afebril",
      "Sem",
      "Ausência"
    ],
    "Sinal ou Sintoma": [
      "intercorrências",
      "afebril",
      "dispnéia",
      "tosse",
      "emagrecimento",
      "ascite",
      "escarro amarelado",
      "drenagem elevada de liquido pleural",
      "edema generalizado",
      "piora da função renal",
      "piora do padrão ventilatório",
      "piora clínica significativa"
    ],
    "Organização Relacionada à Saúde": [
      "emergência",
      "laboratório"
    ],
    "Anormalidade Adquirida": [
      "cistocele",
      "retocele"
    ],
    "Dispositivo Médico": [
      "Sling",
      "dreno com escape aéreo",
      "dreno de tórax"
    ],
    "Conceito Temporal": [
      "pós-operatória",
      "após",
      "diárias"
    ],
    "Doença ou Síndrome": [
      "Tabagista",
      "derrame",
      "BCP",
      "TEP",
      "pancreatite aguda biliar",
      "incontinência urinária de esforço",
      "HCV +",
      "derrame pleural",
      "hipoalbuminemia severa",
      "choque séptico refratário",
      "parada cardio-respiratória"
    ],
    "Disfunção Mental ou Comportamental": [
      "Etilista"
    ],
    "Achado": [
      "hemático",
      "bom estado geral",
      "aceitando bem dieta via oral",
      "adequada evolução",
      "diurese expontânea",
      "Função renal normal",
      "pode ser totalmente afastada",
      "progressivamente maior",
      "expansão relativa de pulmão direito"
    ],
    "Procedimento Laboratorial": [
      "cultura",
      "Hemograma",
      "Hemoculturas",
      "PSA",
      "culturas"
    ],
    "Substância Farmacológica": [
      "RHZ",
      "diuréticos"
    ],
    "Conceito Qualitativo": [
      "empírico",
      "Pequena quantidade"
    ],
    "Conceito Espacial": [
      "esquerda"
    ],
    "Função Patológica": [
      "inflamação"
    ],
    "Resultado Laboratorial ou de Teste": [
      "inflamação",
      "calculos no coledoco",
      "demonstrou cálculos na via biliar",
      "volumoso derrame pleural à direita",
      "ADA 61 , 2 U/L",
      "Glicose 335",
      "LDH 223",
      "Proteínas Totais 6 , 0",
      "pesquisa de fungos e BAAR negativos",
      "crescimento bacteriano",
      "Função renal normal",
      "INFLAMAÇÃO CRÔNICA DE PADRÃO MORFOLÓGICO NÃO ESPECÍFICO E SEROSA",
      "PESQUISA DE FUNGOS E BAAR NEGATIVAS",
      "Volumoso derrame pleural à direita e mínimo à esquerda",
      "Alguns pequenos linfonodos mediastinais",
      "Mediastino desviado para a esquerda",
      "Material denso depositado posteriormente na cavidade pleural direita",
      "Micronódulo subpleural na periferia do subsegmento lingular inferior",
      "Atelectasia subtotal do pulmão direito",
      "permanecendo insuflado o lobo superior",
      "Raros focos de calcificação no pulmão atelectasiado",
      "0 , 12",
      "Volumoso derrame pleural à direita",
      "Formações arredondadas justa-pleurais",
      "porção posterior da cavidade pleural à direita",
      "maior medindo cerca de 1 , 7 cm",
      "sugestivas de implantes secundários",
      "comprometendo especialmente",
      "segmento medial do lobo médio e a pirâmide basal",
      "Atenuação em vidro fosco no lobo superior direito",
      "evidência de processo expansivo ou linfonodomegalias no mediastino",
      "laringe edemaciada e hiperemiada",
      "vascularização proeminente",
      "cordas vocais móveis e simétricas",
      "Brônquio LSD desviado",
      "evidência de lesões",
      "Edema de mucosa e estenose secundária",
      "provável compressão extrínseca no brônquio lobar médio",
      "Brônquio lobar inferior direito do segmento apical do LID",
      "importante estenose secundária à compressão extrínseca",
      "secreções patológicas",
      "BAAR e CP negativos",
      "grande volume de líquido pleural",
      "3000 ml",
      "aspecto sanguinolento em cavidade pleural direita",
      "Pleura parietal apresentando diminutas micronodularidades",
      "eritema e neovascularização difusas",
      "Pulmão com boa expansibilidade na cavidade torácica",
      "INFLAMAÇÃO CRÔNICA EM SEROSA COM FOCOS DE HIPERPLASIA MESOTELIAL",
      "SINAIS DE HEMORRAGIA ANTIGA E EXSUDATO FIBRINO-NEUTROCITÁRIO",
      "Derrame pleural bilateral",
      "Área de consolidação e atelectasia em lobo inferior direito",
      "infiltração e pequena quantidade",
      "líquido",
      "coletado em goteira parieto-cólica direita",
      "espessamento das paredes do ceco",
      "infiltração dos planos de gordura adjacentes",
      "aspecto sugestivo de lesão inflamatória",
      "líquido livre na cavidade abdominal",
      "infiltração e pequena quantidade de líquido coletado em goteira parieto-cólica",
      "Pequena quantidade de líquido livre na cavidade abdominal",
      "evidência de lesão sugestiva de neoplasia",
      "pleurodese a direita",
      "evidência de neoplasia ou granuloma",
      "possível foco de consolidação em base direita",
      "crescimento de cocos gram positivos em aglomerados"
    ],
    "Antibiótico": [
      "Cefepime",
      "vancomicina"
    ],
    "Função de Organismo": [
      "óbito",
      "diurese expontânea"
    ],
    "Conceito Quantitativo": [
      "1 maço / dia",
      "3 Kg",
      "1500 ml"
    ],
    "Vírus": [
      "HCV +"
    ],
    "Localização ou Região Corporal": [
      "segmento medial"
    ],
    "Parte do Corpo, Órgão ou Componente Orgânico": [
      "PEÇA CIRÚRGICA",
      "PLEURA DIAFRAGMÁTICA DIREITA"
    ],
    "Processo Neoplásico": [
      "lesão neoplásica"
    ]
  },
  "labels": {}
}