{
  "prontuario_id": 278,
  "text": "PACIENTE INTERNA PARA MAMOPLASTIA REDUTORA ESQUERDA E CORREÇÃO DE CICATRIZ EM REGIÃO PEITORAL DIR. PROCEDIMENTO SEM INTERCORRÊNCIAS. APRESENTA BOA EVOLUÇÃO PÓS-OP, SV ESTÁVEIS, PORTO VAC DRENAGEM ADEQUADA, EM CONDIÇÕES DE ALTA HOSPITALAR. RN MARIA  # sepse neonatal - AMPI + GENTA; # HMG infeccioso (R b/n: 0,28),  DN: 28/05/07 às 15:11 neste C.O. Parto Cesáreo por apresentação pélvica, BR no ato, LAC. APGAR 8/10 - Pn 3200 g, IG Capurro 37+1 - AIG. Mãe de 27 anos, G3 P2, IGO 38+5, PN c/ 6 consultas. Jan/07: VDRL NR, TOXO IgG R e IgM NR, HIV NR. MAIO/07: VDRL NR, HBsAg Nr, HIV NR. Internou na UCI em 30/05, por apresentar hipertermia. Triado para sepse neonatal, apresentava HMG com 1980 bastões e R: 0,28; PCr < 3,17; líquor: leuc 13 (neutr 2 %, mono 68 %, macro 30 %), eritr 172, glicorraquia 45, proteinorraquia 74. Iniciado AMPI + GENTA. Exames de controle após 48h de ATB com melhora (Ht 36,7; Hg 12,1; leuc 13900, 3/52/1/0/12/29/1/2 - R: 0,1). Evoluindo com adequado ganho de peso e sem intercorrências. Recebe alta no dia de hoje, em condições clinicas adequadas, após 10 dias de ATB, com orientações gerais e retorno ambulatorial (dia 11/06, às 13h30 - ZONA 4, sala 10).  ",
  "entities": {
    "Paciente ou Grupo com Deficiência": [
      "PACIENTE"
    ],
    "Atividade de Assistência à Saúde": [
      "INTERNA",
      "consultas",
      "Internou",
      "alta",
      "CONDIÇÕES DE ALTA HOSPITALAR",
      "orientações gerais"
    ],
    "Procedimento Terapêutico ou Preventivo": [
      "PROCEDIMENTO",
      "MAMOPLASTIA REDUTORA ESQUERDA",
      "CORREÇÃO DE CICATRIZ",
      "Parto Cesáreo"
    ],
    "Negação": [
      "SEM",
      "sem"
    ],
    "Sinal ou Sintoma": [
      "INTERCORRÊNCIAS",
      "hipertermia",
      "intercorrências",
      "HMG infeccioso"
    ],
    "Conceito Temporal": [
      "PÓS-OP",
      "anos",
      "após",
      "dia",
      "hoje",
      "dias"
    ],
    "Abreviação": [
      "PÓS-OP",
      "RN",
      "AMPI",
      "GENTA",
      "BR",
      "LAC",
      "Pn",
      "IG",
      "AIG",
      "G3",
      "P2",
      "IGO",
      "UCI",
      "HMG",
      "PCr",
      "ATB",
      "REGIÃO PEITORAL DIR",
      "SV ESTÁVEIS",
      "HMG infeccioso",
      "VDRL NR",
      "TOXO IgG R e IgM NR",
      "HIV NR",
      "HBsAg Nr",
      "leuc 13",
      "neutr 2 %",
      "mono 68 %",
      "macro 30 %",
      "eritr 172",
      "Ht 36 , 7",
      "Hg 12 , 1",
      "leuc 13900"
    ],
    "Grupo Etário": [
      "RN"
    ],
    "Grupo Populacional": [
      "RN"
    ],
    "Antibiótico": [
      "AMPI",
      "GENTA",
      "ATB"
    ],
    "Substância Química Orgânica": [
      "AMPI",
      "GENTA"
    ],
    "Atributo Clínico": [
      "Pn",
      "IG",
      "IGO"
    ],
    "Conceito Quantitativo": [
      "3200",
      "37+1",
      "38+5"
    ],
    "Atributo de Organismo": [
      "IG"
    ],
    "Produto Intelectual": [
      "Capurro"
    ],
    "Resultado Laboratorial ou de Teste": [
      "37+1",
      "VDRL NR",
      "TOXO IgG R e IgM NR",
      "HIV NR",
      "HBsAg Nr",
      "1980 bastões",
      "R : 0 , 28",
      "leuc 13",
      "neutr 2 %",
      "mono 68 %",
      "macro 30 %",
      "eritr 172",
      "glicorraquia 45",
      "proteinorraquia 74",
      "Ht 36 , 7",
      "Hg 12 , 1",
      "leuc 13900",
      "R : 0 , 1"
    ],
    "Grupo Familiar": [
      "Mãe"
    ],
    "Organização Relacionada à Saúde": [
      "UCI"
    ],
    "Procedimento Laboratorial": [
      "HMG",
      "PCr",
      "Exames de controle"
    ],
    "Substância Corporal": [
      "líquor"
    ],
    "Localização ou Região Corporal": [
      "REGIÃO PEITORAL DIR"
    ],
    "Achado": [
      "BOA EVOLUÇÃO",
      "SV ESTÁVEIS",
      "DRENAGEM ADEQUADA",
      "CONDIÇÕES DE ALTA HOSPITALAR",
      "apresentação pélvica",
      "adequado ganho de peso",
      "condições clinicas adequadas"
    ],
    "Dispositivo Médico": [
      "PORTO VAC"
    ],
    "Doença ou Síndrome": [
      "sepse neonatal"
    ],
    "Procedimento Diagnóstico": [
      "Exames de controle"
    ]
  },
  "labels": {}
}