{
  "prontuario_id": 549,
  "text": "     Paciente com diagnóstico de Linfoma de Burkitt com término de tratamento em outubro de 2005 (BFM 90). Vinha em acompanhamento ambulatorial na Zona 13, tendo sido detectados pequenos linfonodos na região cervical bilateral com cerca de 1 cm de diâmetro cada em fevereiro deste ano. ECO cervical de 28/05/2007 apresentando \"LFNs aumentados de volume na região submentoniana, o maior deles à direita com 2,4 cm e à esquerda 1,7 x 0,8 cm.  Mantendo LDH e beta2-microglobulina dentro da normalidade. Interna p/ realização de bx LFN. Realizado TC tórax e abd: normais; Tc reg cervical com LFNs na reg submentoniana < 1 cm; alguns em cadeia jugular bilateral, os maiores com 1,6 cm. Sorologias negativas (VDRL, Anti-HIV, Toxo, CMV, Herpes). Bx LFN à esquerda sem intercorrências. Recebe alta em bom estado geral, assintomático, com orientação de retornar ao Ambulatório da Zona 11 na próxima semana p/ ver resultado da bx.",
  "entities": {
    "Paciente ou Grupo com Deficiência": [
      "Paciente"
    ],
    "Procedimento Terapêutico ou Preventivo": [
      "tratamento"
    ],
    "Conceito Quantitativo": [
      "90",
      "1 cm",
      "o maior deles à direita com 2 , 4 cm",
      "à esquerda 1 , 7 x 0 , 8 cm",
      "&lt; 1 cm",
      "os maiores com 1 , 6 cm"
    ],
    "Abreviação": [
      "\"LFNs",
      "LDH",
      "VDRL",
      "Anti-HIV",
      "Toxo",
      "CMV",
      "ECO cervical",
      "bx LFN",
      "TC tórax e abd",
      "Tc reg cervical",
      "&lt; 1 cm",
      "Bx LFN à esquerda",
      "resultado da bx"
    ],
    "Localização ou Região Corporal": [
      "submentoniana",
      "região cervical bilateral"
    ],
    "Enzima": [
      "LDH"
    ],
    "Procedimento Laboratorial": [
      "LDH",
      "beta2-microglobulina",
      "VDRL",
      "Anti-HIV",
      "Toxo",
      "CMV",
      "Herpes"
    ],
    "Aminoácido, Peptídeo ou Proteína": [
      "LDH",
      "beta2-microglobulina"
    ],
    "Substância Biologicamente Ativa": [
      "beta2-microglobulina"
    ],
    "Atividade de Assistência à Saúde": [
      "Interna",
      "alta",
      "orientação",
      "retornar",
      "acompanhamento ambulatorial"
    ],
    "Resultado Laboratorial ou de Teste": [
      "normais",
      "o maior deles à direita com 2 , 4 cm",
      "à esquerda 1 , 7 x 0 , 8 cm",
      "dentro da normalidade",
      "alguns em cadeia jugular bilateral",
      "os maiores com 1 , 6 cm",
      "Sorologias negativas",
      "resultado da bx"
    ],
    "Parte do Corpo, Órgão ou Componente Orgânico": [
      "LFNs"
    ],
    "Vírus": [
      "CMV"
    ],
    "Negação": [
      "sem",
      "assintomático"
    ],
    "Sinal ou Sintoma": [
      "intercorrências"
    ],
    "Achado": [
      "assintomático",
      "bom estado geral"
    ],
    "Organização Relacionada à Saúde": [
      "Ambulatório"
    ],
    "Processo Neoplásico": [
      "Linfoma de Burkitt"
    ],
    "Procedimento Diagnóstico": [
      "ECO cervical",
      "bx LFN",
      "TC tórax e abd",
      "Tc reg cervical",
      "Bx LFN à esquerda"
    ]
  },
  "labels": {}
}