{
  "prontuario_id": 39,
  "text": "Paciente realizou Rx tórax e TC, que mostraram consolidações. Iniciado cefuroxime. Recebe alta em bom estado geral, afebril, com hemograma normal. Manter uso de cefuroxime por 7 dias. Paciente interna devido queda - tc de cranio sem evidência de hemorragia intracraniana. Sem novas lesões isquemicas. Evolui com melhora clinica neurologica progressiva. Insuficiencia renal cronica agudizada com melhora com hidratação. Hipotireoidismo, aumento dose de puran para 75, tsh de 33. Tratamento de infecçaõ respiratória com cefuroxima, com boa resposta clinica. Reinicio anticoagulaçaõ com varfarina. Tem alta em uso de Puran 75, sinvastatina 20 mg a noite. Enalapril 5 mg vo 2 x, metoprolol tartarato 25 mg vo 2 x, digoxina 1/2 cp em dias alternados. Paroxetina 20 mg vo 1 x pela manha, flunitrazepan 1 mg vo 1 x a noite, varfarina 5 mg vo 1 x ao dia. Omeprazol 20 mg vo 1 x ao dia. Carbonato de calcio 500 mg vo 2 x. Controle de tp na sexta feira. Se piora, retorno a emergência.",
  "entities": {
    "Paciente ou Grupo com Deficiência": [
      "Paciente"
    ],
    "Abreviação": [
      "TC",
      "vo",
      "Rx tórax",
      "tc de cranio"
    ],
    "Procedimento Diagnóstico": [
      "TC",
      "Rx tórax",
      "tc de cranio"
    ],
    "Resultado Laboratorial ou de Teste": [
      "consolidações",
      "hemograma normal",
      "sem evidência",
      "tsh de 33"
    ],
    "Sinal ou Sintoma": [
      "consolidações",
      "novas lesões isquemicas"
    ],
    "Substância Química Orgânica": [
      "cefuroxime",
      "cefuroxima",
      "varfarina",
      "Paroxetina",
      "flunitrazepan",
      "Omeprazol",
      "metoprolol tartarato"
    ],
    "Substância Farmacológica": [
      "cefuroxime",
      "puran",
      "cefuroxima",
      "varfarina",
      "Puran",
      "sinvastatina",
      "Enalapril",
      "digoxina",
      "Paroxetina",
      "flunitrazepan",
      "Omeprazol",
      "metoprolol tartarato",
      "Carbonato de calcio"
    ],
    "Antibiótico": [
      "cefuroxime",
      "cefuroxima"
    ],
    "Atividade de Assistência à Saúde": [
      "alta",
      "retorno"
    ],
    "Negação": [
      "afebril",
      "Sem",
      "sem evidência"
    ],
    "Achado": [
      "afebril",
      "bom estado geral",
      "hemograma normal",
      "melhora clinica neurologica progressiva",
      "melhora com hidratação",
      "boa resposta clinica"
    ],
    "Conceito Temporal": [
      "dias",
      "noite",
      "manha",
      "dia",
      "dias alternados",
      "sexta feira"
    ],
    "Lesão ou Envenenamento": [
      "queda"
    ],
    "Doença ou Síndrome": [
      "Hipotireoidismo",
      "hemorragia intracraniana",
      "Insuficiencia renal cronica agudizada",
      "infecçaõ respiratória"
    ],
    "Aminoácido, Peptídeo ou Proteína": [
      "puran",
      "Puran",
      "Enalapril"
    ],
    "Hormônio": [
      "puran",
      "Puran"
    ],
    "Procedimento Terapêutico ou Preventivo": [
      "Tratamento",
      "anticoagulaçaõ",
      "aumento dose"
    ],
    "Conceito Quantitativo": [
      "75"
    ],
    "Organização Relacionada à Saúde": [
      "emergência"
    ],
    "Substância Química Inorgânica": [
      "Carbonato de calcio"
    ],
    "Procedimento Laboratorial": [
      "Controle de tp"
    ]
  },
  "labels": {}
}