{
  "prontuario_id": 609,
  "text": "Às 23h encaminhado para clínica Nome, acompanhado pela aux. de Enfermeira Florence Nightingale para realização de RNM de crânio. Conforme passagem de plantão e orientações da própria clínica, levamos álcool 70% e luvas para desinfecção pós exame, pois o pcte é portador de MRSA + Klebsiella sp ESBL. Ao chegar na clínica foi abordado na  ambulância e negado o exame por não ter levado peresal.  Por telefone explico para o téc. de enf.  Florence Nightingale sobre a dificuldade em encaminhar pcte para exame, pois é um pcte crítico, acamado, com gastrostomia e traqueostomizado, peço a gentileza que  realize o exame, e encaminho o peresal posteriormente, o mesmo diz que não é possível e que as máquinas ja foram todas desligadas. Pcte retorna sem realizar exame e sem reagendar, explico intercorrência para familiar, mãe. Pedido de RNM anexado ao prontuário do pcte.  Enfermeira Florence Nightingale OUTRAS EPILEPSIAS",
  "entities": {
    "Organização Relacionada à Saúde": [
      "clínica"
    ],
    "Grupo Profissional ou Ocupacional": [
      "Enfermeira"
    ],
    "Atividade de Assistência à Saúde": [
      "orientações",
      "encaminhar",
      "realizar",
      "reagendar",
      "passagem de plantão"
    ],
    "Dispositivo Médico": [
      "luvas"
    ],
    "Paciente ou Grupo com Deficiência": [
      "pcte",
      "Pcte"
    ],
    "Abreviação": [
      "pcte",
      "MRSA",
      "Pcte",
      "RNM",
      "RNM de crânio",
      "Klebsiella sp"
    ],
    "Achado": [
      "portador",
      "gastrostomia",
      "traqueostomizado"
    ],
    "Bactéria": [
      "MRSA",
      "Klebsiella sp"
    ],
    "Negação": [
      "negado",
      "não",
      "sem"
    ],
    "Procedimento Diagnóstico": [
      "exame",
      "RNM",
      "RNM de crânio"
    ],
    "Substância": [
      "peresal"
    ],
    "Sinal ou Sintoma": [
      "crítico",
      "acamado"
    ],
    "Conceito Qualitativo": [
      "crítico"
    ],
    "Procedimento Terapêutico ou Preventivo": [
      "gastrostomia",
      "traqueostomizado",
      "desinfecção pós exame"
    ],
    "Grupo Familiar": [
      "familiar",
      "mãe"
    ],
    "Produto Intelectual": [
      "prontuário"
    ],
    "Doença ou Síndrome": [
      "EPILEPSIAS"
    ],
    "Substância Química Orgânica": [
      "álcool 70%"
    ],
    "Substância Farmacológica": [
      "álcool 70%"
    ]
  },
  "labels": {}
}