{
  "prontuario_id": 309,
  "text": "11:00 Horas. Paciente proveniente do CMUM Bairro trazida pela remoção Nome do SAMU. Deu entrada no CMUM ontem 11/11 por quadro de dispnéia, náuseas e mal estar. Evoluindo com insuficiência respiratória + rebaixamento de nível de consciência. História prévia de IAM em 2006, HAS, DM, Hipotireoidismo e ICC. Intubada em ventilação mecãnica modo: PCV, concentração de 02:70% e PEEP:6. Monitorização cardíaca e oximetria de pulso contínua mantendo sinais vitais estáveis, FC:66 bpm, SAT:98% e PA:140/80 mmhg. Secreção sanguinolenta durante aspiração de vias aéreas. Cabeceira do leito elevada 45°C. Pele integra. Pupilas mióticas. Acesso venoso puncionado em jugular externa D, mantendo plano de sedação em curso. Abdomen globoso e flácido com RHA+. Ausculta pulmonar com MV+ bilateral. Perfusão periférica e pulsos presentes. Extremidades aquecidas. SVD com pouco débito amarelo claro. Segue sob os cuidados da equipe multiprofissional. Aguarda vaga em UTI.  * Encaminhado novo pedido de vaga para UTI. *Realizada passagem de SNE aguarda RX para verificar posicionamento Enfermeira Florence Nightingale  EDEMA PULMONAR NÃO ESPECIFICADO DE OUTRA FORMA",
  "entities": {
    "Paciente ou Grupo com Deficiência": [
      "Paciente"
    ],
    "Sinal ou Sintoma": [
      "dispnéia",
      "náuseas",
      "globoso",
      "mal estar",
      "rebaixamento de nível de consciência",
      "Secreção sanguinolenta",
      "Pupilas mióticas",
      "pouco débito"
    ],
    "Doença ou Síndrome": [
      "IAM",
      "HAS",
      "DM",
      "Hipotireoidismo",
      "ICC",
      "EDEMA PULMONAR"
    ],
    "Abreviação": [
      "IAM",
      "HAS",
      "DM",
      "ICC",
      "PEEP",
      "FC",
      "SAT",
      "PA",
      "RHA+",
      "SVD",
      "UTI",
      "RX",
      "modo : PCV",
      "concentração de 02",
      "jugular externa D",
      "MV+ bilateral",
      "passagem de SNE"
    ],
    "Achado": [
      "Intubada",
      "flácido",
      "RHA+",
      "presentes",
      "sinais vitais estáveis",
      "Pele integra",
      "MV+ bilateral",
      "Extremidades aquecidas",
      "pouco débito",
      "amarelo claro"
    ],
    "Procedimento Terapêutico ou Preventivo": [
      "Intubada",
      "PEEP",
      "puncionado",
      "SVD",
      "ventilação mecãnica",
      "modo : PCV",
      "aspiração de vias aéreas",
      "Cabeceira do leito elevada 45°C",
      "Acesso venoso",
      "plano de sedação",
      "cuidados da equipe multiprofissional",
      "passagem de SNE"
    ],
    "Conceito Quantitativo": [
      "70%",
      "6",
      "98%",
      "66 bpm",
      "140/80 mmhg"
    ],
    "Atributo Clínico": [
      "FC",
      "SAT",
      "PA",
      "pulsos",
      "Perfusão periférica"
    ],
    "Localização ou Região Corporal": [
      "Abdomen"
    ],
    "Dispositivo Médico": [
      "SVD",
      "Acesso venoso"
    ],
    "Organização Relacionada à Saúde": [
      "UTI"
    ],
    "Procedimento Diagnóstico": [
      "RX",
      "Monitorização cardíaca",
      "oximetria de pulso contínua",
      "Ausculta pulmonar"
    ],
    "Grupo Profissional ou Ocupacional": [
      "Enfermeira"
    ],
    "Parte do Corpo, Órgão ou Componente Orgânico": [
      "jugular externa D"
    ]
  },
  "labels": {}
}