{
  "prontuario_id": 308,
  "text": "08:20hs- Glasgow 15, pupilas isocóricas fotorreagentes, SNE com dieta a 60ml/h, traqueostomizada, em ventilação mecânica modo PSV, Ps 18, PEEP 6, fiO2 35%, secreção traqueobrônquica amarela em média quantidade, monitorizada, estável hemodinamicamente, MV global diminuído com roncos difusos, acesso venoso periférico em MSD com Imunoglobulina a 21ml/h, abdome globoso, flácido, indolor a palpação, RHA+, diurese espontânea efetiva, evacuação ausente, extremidades bem perfundidas, higienizada e mobilizada no leito, pele íntegra, escala de braden: 12 (risco elevado). Enfermeira Florence Nightingale  DOR TORÁCICA NÃO ESPECIFICADA",
  "entities": {
    "Parte do Corpo, Órgão ou Componente Orgânico": [
      "pupilas"
    ],
    "Achado": [
      "isocóricas",
      "fotorreagentes",
      "traqueostomizada",
      "monitorizada",
      "flácido",
      "RHA+",
      "evacuação",
      "higienizada",
      "Glasgow 15",
      "secreção traqueobrônquica amarela",
      "estável hemodinamicamente",
      "diurese espontânea efetiva",
      "extremidades bem perfundidas",
      "pele íntegra"
    ],
    "Procedimento Terapêutico ou Preventivo": [
      "SNE",
      "dieta",
      "traqueostomizada",
      "Ps",
      "PEEP",
      "fiO2",
      "higienizada",
      "ventilação mecânica",
      "modo PSV",
      "acesso venoso periférico",
      "mobilizada no leito"
    ],
    "Abreviação": [
      "SNE",
      "60ml/h",
      "Ps",
      "PEEP",
      "fiO2",
      "MSD",
      "RHA+",
      "modo PSV",
      "MV global diminuído"
    ],
    "Dispositivo Médico": [
      "SNE",
      "acesso venoso periférico"
    ],
    "Conceito Quantitativo": [
      "60ml/h",
      "18",
      "6",
      "35%",
      "21ml/h"
    ],
    "Conceito Qualitativo": [
      "6",
      "média quantidade",
      "risco elevado"
    ],
    "Procedimento Diagnóstico": [
      "monitorizada",
      "palpação"
    ],
    "Localização ou Região Corporal": [
      "MSD",
      "abdome"
    ],
    "Aminoácido, Peptídeo ou Proteína": [
      "Imunoglobulina"
    ],
    "Substância Farmacológica": [
      "Imunoglobulina"
    ],
    "Fator Imunológico": [
      "Imunoglobulina"
    ],
    "Sinal ou Sintoma": [
      "globoso",
      "secreção traqueobrônquica amarela",
      "MV global diminuído",
      "roncos difusos",
      "escala de braden : 12",
      "DOR TORÁCICA"
    ],
    "Negação": [
      "indolor",
      "ausente"
    ],
    "Função Fisiológica": [
      "evacuação",
      "diurese espontânea efetiva"
    ],
    "Grupo Profissional ou Ocupacional": [
      "Enfermeira"
    ]
  },
  "labels": {}
}