{
  "prontuario_id": 10,
  "text": "09:33 - 2º DI Hx vítima de atropelamento com FCC em região frontal. Sonolento, choroso a tentativa de acorda-lo, corado. Face escoriações, hematoma em região ocular E, curativo limpo e seco em região frontal à D. Respiração espontânea em ar ambiente, CPP livres, BCRNF. Acessos venosos periféricos em antebraços D e E salinizado. Abdomen plano, RHA +. MMII aquecidos, pulsos pediosos palpáveis, perfusão periférica < 3s. MIE escoriações. Diurese espontânea presente, evacuação ausente. No período em repouso no leito. Aguardando internamento em UI. Segue sob os cuidados da equipe multidisciplinar. Enfermeira Florence Nightingale . OUTROS TRAUMATISMOS INTRACRANIANOS",
  "entities": {
    "Paciente ou Grupo com Deficiência": [
      "vítima"
    ],
    "Lesão ou Envenenamento": [
      "atropelamento",
      "FCC",
      "escoriações",
      "TRAUMATISMOS INTRACRANIANOS"
    ],
    "Abreviação": [
      "FCC",
      "BCRNF",
      "MIE",
      "região ocular E",
      "região frontal à D",
      "CPP livres",
      "antebraços D e E",
      "RHA +",
      "MMII aquecidos",
      "perfusão periférica &lt; 3s",
      "internamento em UI"
    ],
    "Sinal ou Sintoma": [
      "Sonolento",
      "escoriações"
    ],
    "Achado": [
      "choroso",
      "corado",
      "limpo",
      "seco",
      "BCRNF",
      "salinizado",
      "evacuação",
      "Respiração espontânea",
      "CPP livres",
      "RHA +",
      "MMII aquecidos",
      "pulsos pediosos palpáveis",
      "perfusão periférica &lt; 3s",
      "Diurese espontânea presente",
      "repouso no leito"
    ],
    "Localização ou Região Corporal": [
      "Face",
      "Abdomen",
      "MIE",
      "região frontal",
      "região ocular E",
      "região frontal à D"
    ],
    "Função Patológica": [
      "hematoma"
    ],
    "Dispositivo Médico": [
      "curativo",
      "Acessos venosos periféricos"
    ],
    "Procedimento Terapêutico ou Preventivo": [
      "curativo",
      "salinizado",
      "Acessos venosos periféricos",
      "repouso no leito"
    ],
    "Função Fisiológica": [
      "evacuação",
      "Diurese espontânea presente"
    ],
    "Negação": [
      "ausente"
    ],
    "Grupo Profissional ou Ocupacional": [
      "Enfermeira"
    ],
    "Parte do Corpo, Órgão ou Componente Orgânico": [
      "antebraços D e E"
    ],
    "Atividade de Assistência à Saúde": [
      "internamento em UI",
      "cuidados da equipe multidisciplinar"
    ]
  },
  "labels": {}
}