{
  "prontuario_id": 291,
  "text": "PACIENTE DIABÉTICA , COM IMC ELEVADO , HAS , TABAGISTA PESADA ATIVA , USUÁRIA CRONICA DE CORTICÓIDE 920MG  /DIA PREDNISONA ) POR A.REUMATÓIDE , CAR 2001 COM LESÕES 3 VASOS MODERADAS ( <30% ) , INTERNA POR DOR TORACICA ATIPICA EM REPOUSO , TRATADA COMO SINDROME CORONARIANA AGUDA PELAS VARIAVEIS CLÍNICAS ( DOENÇA CORONARIANA PRÉVIA DEMONSTRADA ) + FATORES DE RISCO MÚLTIPLOS PARA ATEROSCLEROSE . SEM ALT NOVAS ECG DA CHEGADA E SEM CURVA ENZIMATICA TÍPICA DE IAM .  FOI OPTADO POR MANEJO CONSERVADOR , SENDO QUE A PACIENTE APRESENTOU MELHORA IMPORTANTE DA DOR COM TRATAMENTO CLÍNICO OTIMIZADO , TEM ALTA EM BOM ESTADO GERAL , ASSINTOMÁTICO , COM USO DE TODAS AS INTERVENÇÕES FARMACOLÓGICAS COM BENEFÍCIO COMPROVABDO POR ENSAIOS CLÍNICOS RANDOMIZADOS E COM RETORNO AMBULATORIAL JÁ MARCADO PARA MED INTERNA/HCPA ONDE JÁ REALIZAVA ACOMPANHAMENTO . SUGERIMOS PARA MÉDICO ASSITENTE REDUZIR DOSES CORTICÓIDE ,SE POSSÍVEL .",
  "entities": {
    "Paciente ou Grupo com Deficiência": [
      "PACIENTE"
    ],
    "Doença ou Síndrome": [
      "DIABÉTICA",
      "HAS",
      "SINDROME CORONARIANA AGUDA",
      "DOENÇA CORONARIANA",
      "PARA ATEROSCLEROSE"
    ],
    "Abreviação": [
      "HAS",
      "CAR",
      "ALT",
      "ECG",
      "IMC ELEVADO",
      "CURVA ENZIMATICA TÍPICA DE IAM"
    ],
    "Substância Química Orgânica": [
      "CORTICÓIDE",
      "PREDNISONA"
    ],
    "Hormônio": [
      "CORTICÓIDE",
      "PREDNISONA"
    ],
    "Substância Farmacológica": [
      "CORTICÓIDE",
      "PREDNISONA"
    ],
    "Conceito Quantitativo": [
      "920MG",
      "&lt;30%"
    ],
    "Procedimento Diagnóstico": [
      "CAR",
      "ECG"
    ],
    "Negação": [
      "SEM",
      "ASSINTOMÁTICO"
    ],
    "Atividade de Assistência à Saúde": [
      "ALTA",
      "REDUZIR"
    ],
    "Achado": [
      "ASSINTOMÁTICO",
      "MELHORA IMPORTANTE DA DOR",
      "BOM ESTADO GERAL"
    ],
    "Resultado Laboratorial ou de Teste": [
      "LESÕES 3 VASOS MODERADAS",
      "CURVA ENZIMATICA TÍPICA DE IAM"
    ],
    "Sinal ou Sintoma": [
      "DOR TORACICA ATIPICA EM REPOUSO"
    ],
    "Procedimento Terapêutico ou Preventivo": [
      "MANEJO CONSERVADOR",
      "TRATAMENTO CLÍNICO OTIMIZADO",
      "INTERVENÇÕES FARMACOLÓGICAS"
    ],
    "Produto Intelectual": [
      "ENSAIOS CLÍNICOS RANDOMIZADOS"
    ],
    "Atividade de Pesquisa": [
      "ENSAIOS CLÍNICOS RANDOMIZADOS"
    ],
    "Grupo Profissional ou Ocupacional": [
      "MÉDICO ASSITENTE"
    ]
  },
  "labels": {}
}