{
  "prontuario_id": 578,
  "text": "PCTE TRAZIDO À EM HCPA ÀS 12H DE HOJE , POR AMBULÂNCIA , PROVENIENTE DE CARAZINHO , ONDE ESTARIA INTERNADO , DESDE 30/4 . TERIA RECEBIDO ALTA PARA CONSULTAR NO AMBULATÓRIO  ICC , CFE . RELATO DA MÃE QUE O ACOMPANHAVA .TEM DIAGNÓSTICO ESTABELECIDO DE MIOCARDIOPATIA DILATADA IDIOPÁTICA( FEJ 16% ) , COM INTERNAÇÃO PRÉVIA - 2004 - NO HCPA POR ICC DESCOMPENSADA , PARTICIPOU DO PROTOCOLO EVEREST E TEM ÚLTIMO REGISTRO DE  CONSULTA NO HCPA EM NOVEMBRO DE 2005 .  POR VOLTA DAS 11 H , NO TRANSPORTE AO HCPA ,  SEGUNDO RELATO DA MÃE , APRESENTOU EPISÓDIO COMPATÍVEL COM SÍNCOPE . CHEGOU À EMERGÊNCIA  EM PCR - ASSISTOLIA , HAVENDO RESPOSTA ÀS MANOBRAS DE RCP . TRANSFERIDO AO CTI ÀS 12H30 , EM VM C/ EVIDÊNCIA CLÍNICA DE BAIXO DÉBITO . EVOLUIU C/ QUADRO DE CHOQUE E BRADIARRITMIA >>  NOVA PCR EM FV  >> ASSISTOLIA , NÃO RESPONDENDO ÀS MANOBRAS DE RCP , DURAÇÃO DE 45 MINUTOS . ÓBITO ÀS 12H48MIN .",
  "entities": {
    "Paciente ou Grupo com Deficiência": [
      "PCTE"
    ],
    "Abreviação": [
      "PCTE",
      "EM",
      "PCR",
      "CTI",
      "VM",
      "FV",
      "AMBULATÓRIO ICC",
      "ICC DESCOMPENSADA",
      "MANOBRAS DE RCP",
      "DURAÇÃO DE 45 MINUTOS ."
    ],
    "Organização Relacionada à Saúde": [
      "EM",
      "EMERGÊNCIA",
      "CTI"
    ],
    "Dispositivo Médico": [
      "AMBULÂNCIA"
    ],
    "Atividade de Assistência à Saúde": [
      "ALTA",
      "CONSULTAR",
      "INTERNAÇÃO",
      "TRANSPORTE",
      "TRANSFERIDO",
      "AMBULATÓRIO ICC"
    ],
    "Grupo Familiar": [
      "MÃE"
    ],
    "Conceito Temporal": [
      "PRÉVIA",
      "DURAÇÃO DE 45 MINUTOS ."
    ],
    "Doença ou Síndrome": [
      "PCR",
      "ASSISTOLIA",
      "BRADIARRITMIA",
      "FV",
      "MIOCARDIOPATIA DILATADA IDIOPÁTICA",
      "ICC DESCOMPENSADA"
    ],
    "Procedimento Terapêutico ou Preventivo": [
      "VM",
      "MANOBRAS DE RCP"
    ],
    "Função Patológica": [
      "CHOQUE",
      "BAIXO DÉBITO"
    ],
    "Negação": [
      "NÃO"
    ],
    "Achado": [
      "ÓBITO"
    ],
    "Produto Intelectual": [
      "DIAGNÓSTICO ESTABELECIDO",
      "ÚLTIMO REGISTRO DE CONSULTA"
    ],
    "Resultado Laboratorial ou de Teste": [
      "FEJ 16%"
    ],
    "Atividade de Pesquisa": [
      "PROTOCOLO EVEREST"
    ],
    "Sinal ou Sintoma": [
      "EPISÓDIO COMPATÍVEL COM SÍNCOPE",
      "EVIDÊNCIA CLÍNICA"
    ]
  },
  "labels": {}
}