{
  "prontuario_id": 264,
  "text": "QP : PCTE REFERE BAV PARA PERTO EM AO , HA 1 ANO. NEGA OUTROS SINTOMAS .\nNEGA CX E TRAUMA OCULAR .\nNEGA USO DE OCLLIRIO .\nFAZ USO DE OCULOS PARA PERTO , HA 5 ANOS\nEM USO DE FLUOXETINO PARA DEPRESSAO\n\nOCULOS QUE USA :  + 1,50 ESF AO\n\nHMF : NEGA HX FAMILIAR D ECGUEIRA E GLAUCOMA\n\nEF :\n\nAV : 20/25P\n       20/20P\n\nESQ ; +0,50 - 0,25 180º\n         PL ESF \n\nTOL : +0,50 - 0,50 180º 20/20 \n        PL ESF 20/20\n        AD +2,25 J1 ( SEM CILINDRO )\n\nBIO : PTG NASAL GRAU I\n         PINGUECULA NASAL\n\nPIO : 12/14\n\nFO : PAPILA E MACULA NORMAL AO\n\nCD : PRESCREVO OCULOS PARA PERTO A PEDIDO DO PACIENTE E CONFORME TOLERANCIA\n      RETORNO ANUAL PELA UBS\n\nR1MARINA\nR2FERNANDO\n\n.\n \n \n \n ",
  "entities": {
    "Abreviação": [
      "QP",
      "PCTE",
      "AO",
      "CX",
      "ESF",
      "HMF",
      "EF",
      "AV",
      "20/25P",
      "20/20P",
      "ESQ",
      "PL",
      "TOL",
      "AD",
      "PIO",
      "FO",
      "CD",
      "HX FAMILIAR",
      "PTG NASAL GRAU I"
    ],
    "Sinal ou Sintoma": [
      "QP",
      "OUTROS SINTOMAS",
      "PINGUECULA NASAL"
    ],
    "Paciente ou Grupo com Deficiência": [
      "PCTE",
      "PACIENTE"
    ],
    "Achado": [
      "BAV",
      "HMF",
      "PARA PERTO",
      "HX FAMILIAR",
      "D ECGUEIRA"
    ],
    "Parte do Corpo, Órgão ou Componente Orgânico": [
      "AO",
      "FO",
      "PAPILA",
      "MACULA"
    ],
    "Negação": [
      "NEGA",
      "SEM"
    ],
    "Procedimento Terapêutico ou Preventivo": [
      "CX",
      "OCULOS PARA PERTO"
    ],
    "Dispositivo Médico": [
      "OCULOS",
      "OCULOS PARA PERTO"
    ],
    "Substância Farmacológica": [
      "FLUOXETINO"
    ],
    "Substância Química Orgânica": [
      "FLUOXETINO"
    ],
    "Doença ou Síndrome": [
      "DEPRESSAO",
      "GLAUCOMA",
      "PTG NASAL GRAU I",
      "PINGUECULA NASAL"
    ],
    "Atividade de Assistência à Saúde": [
      "EF",
      "CD",
      "PRESCREVO",
      "RETORNO"
    ],
    "Atributo Clínico": [
      "AV",
      "PIO"
    ],
    "Procedimento Diagnóstico": [
      "AV"
    ],
    "Resultado Laboratorial ou de Teste": [
      "20/25P",
      "20/20P",
      "180º",
      "12/14",
      "+0 , 50 - 0 , 25",
      "+0 , 50 - 0 , 50"
    ],
    "Conceito Espacial": [
      "ESQ"
    ],
    "Conceito Quantitativo": [
      "180º",
      "12/14",
      "+ 1 , 50",
      "+0 , 50 - 0 , 25",
      "+0 , 50 - 0 , 50"
    ],
    "Conceito Qualitativo": [
      "PL",
      "ESF",
      "PARA PERTO"
    ],
    "Produto Intelectual": [
      "CD"
    ],
    "Conceito Temporal": [
      "ANUAL"
    ],
    "Organização Relacionada à Saúde": [
      "UBS"
    ],
    "Lesão ou Envenenamento": [
      "TRAUMA OCULAR"
    ]
  },
  "labels": {}
}