{
  "prontuario_id": 640,
  "text": "HA 3 MESES INICIOU COM EDEMA DIFUSO , COM ASCITE SEM MOTIVO APARENTE      \nUS TV : MOSTRANDO UTERO 33ML , ENDOMETRIO MEDINDO ENTRE 3-4MM , LIQUIDO LIVRE NA CAVIDADE PELVICA , ASSIMETRIA NA SILHUETA CENTRAL HIPERECOGENICA , PODENDO CORRESPONDER A UM POLIPO\nEMAGRECIMENTO DE 3-4KG NESSES ULTIMOS 3 MESES\nQUEIXANDO SE DE CANSACO , SEM DISPNEIA , SEM ANGINA\nRELATA 1-2 EPISODIOS DE DIARREIA SEMANAIS\nEM USO DE : MONOCORDIL , ESPIRONOLACTONA , FUROSEMIDA , LOSARTANA , CARVEDILOL , METFORMINA\nCOMORBIDADES : HAS CONTROLADA , DM , \nUS DE ABDOME : MOSTRANDO ALTERACAO DIFUSA HEPATICA , PANCREAS DE TEXTURA HETEROGENEA E ASCITE\n \n \n \n ",
  "entities": {
    "Sinal ou Sintoma": [
      "ASCITE",
      "EMAGRECIMENTO",
      "QUEIXANDO",
      "CANSACO",
      "DISPNEIA",
      "ANGINA",
      "EDEMA DIFUSO",
      "MOTIVO APARENTE",
      "EPISODIOS DE DIARREIA SEMANAIS"
    ],
    "Negação": [
      "SEM"
    ],
    "Anormalidade Anatômica": [
      "POLIPO"
    ],
    "Conceito Quantitativo": [
      "3-4KG"
    ],
    "Medicamento Clínico": [
      "MONOCORDIL"
    ],
    "Substância Farmacológica": [
      "MONOCORDIL",
      "ESPIRONOLACTONA",
      "FUROSEMIDA",
      "LOSARTANA",
      "CARVEDILOL",
      "METFORMINA"
    ],
    "Substância Química Orgânica": [
      "ESPIRONOLACTONA",
      "FUROSEMIDA",
      "LOSARTANA",
      "CARVEDILOL",
      "METFORMINA"
    ],
    "Doença ou Síndrome": [
      "COMORBIDADES",
      "DM"
    ],
    "Achado": [
      "CONTROLADA",
      "UTERO 33ML",
      "ENDOMETRIO MEDINDO ENTRE 3-4MM",
      "LIQUIDO LIVRE NA CAVIDADE PELVICA",
      "ALTERACAO DIFUSA HEPATICA , PANCREAS DE TEXTURA HETEROGENEA E ASCITE"
    ],
    "Abreviação": [
      "DM",
      "US TV",
      "ENDOMETRIO MEDINDO ENTRE 3-4MM",
      "US DE ABDOME"
    ],
    "Função Patológica": [
      "EDEMA DIFUSO"
    ],
    "Conceito Funcional": [
      "MOTIVO APARENTE"
    ],
    "Procedimento Diagnóstico": [
      "US TV",
      "US DE ABDOME"
    ],
    "Resultado Laboratorial ou de Teste": [
      "UTERO 33ML",
      "ENDOMETRIO MEDINDO ENTRE 3-4MM",
      "LIQUIDO LIVRE NA CAVIDADE PELVICA",
      "ASSIMETRIA NA SILHUETA CENTRAL HIPERECOGENICA",
      "ALTERACAO DIFUSA HEPATICA , PANCREAS DE TEXTURA HETEROGENEA E ASCITE"
    ]
  },
  "labels": {}
}