{
  "prontuario_id": 272,
  "text": "Paciente , 79 anos\n\n# Erupção pruriginosa papulosa / eritemato-escamosa disseminada ( com predominio em tronco e\nmmss ) há aprox 2,5 anos.\n\n3 biopsias prévias :\n- Dermatite superficial espongiótica - Penúltima bx (08/14) : sugestiva de\nFarmacodermia .\n- Nova bx em dez/14 : Aspecto histológico favorece hipóteses clínicas de eritema\nanular centrífugo / Pitiríase Rósea. - AP 14/B05337.\n\n## AP 15/B03636 (04/8/15): FRAGMENTOS DE PELE SEMELHANTES ENTRE SI COM FOCOS DE PARACERATOSE ,\nFOCALMENTE MICROABCESSOS NA CAM CORNEA , ACANTOSE REGULAR , DISCRETA ESPONGIOSE E TENDO NA DERME\nSUPERFICIAL MOD INFILTRADO INFLAMATORIO CRONICO LINFOCITARIO PERIVASCULAR .\nDERMATITE PSORIASIFORME .\n\nS# Paciente relata prurido pela tarde , com melhora nos ultimo mês .  Está em uso de Hidroxezina pela manha e Doxepina pela noite . Está fazendo hidratação 3X/dia .\n\no# nódulos hipercromicos em região de torax anterior e poucos na região lombar , elevados , com escoriações. manchas hipercrÔmicas residuais em dorso .\n\na# Farmacodermia ?psoriase ?\n\np# mantenho hidroxezine 25mg pela manhã , doxepina 20mg pela noite . prescrevo drenison creme para os nodulos mais elevados por no máx 30 dias .\nretorno dia 27/11\nPossível plano de iniciar MTX pelo quadro clínico psoriasiformico/ap ?\n\n\nDoutor Vital Brazil ",
  "entities": {
    "Paciente ou Grupo com Deficiência": [
      "Paciente"
    ],
    "Localização ou Região Corporal": [
      "tronco",
      "mmss",
      "dorso",
      "região de torax anterior",
      "região lombar"
    ],
    "Abreviação": [
      "mmss",
      "bx",
      "AP",
      "S",
      "o",
      "a",
      "p",
      "MTX",
      "FOCALMENTE MICROABCESSOS NA CAM CORNEA , ACANTOSE REGULAR"
    ],
    "Procedimento Diagnóstico": [
      "biopsias",
      "bx",
      "AP",
      "a"
    ],
    "Conceito Temporal": [
      "prévias",
      "Penúltima",
      "3X/dia",
      "manhã",
      "noite"
    ],
    "Doença ou Síndrome": [
      "Farmacodermia",
      "psoriase",
      "psoriasiformico/ap",
      "Dermatite superficial espongiótica",
      "Aspecto histológico favorece hipóteses clínicas de eritema anular centrífugo",
      "Pitiríase Rósea",
      "DERMATITE PSORIASIFORME"
    ],
    "Procedimento Laboratorial": [
      "AP"
    ],
    "Conceito Espacial": [
      "PERIVASCULAR"
    ],
    "Achado": [
      "S",
      "melhora",
      "escoriações",
      "SEMELHANTES ENTRE SI",
      "manchas hipercrÔmicas residuais"
    ],
    "Sinal ou Sintoma": [
      "prurido",
      "elevados",
      "Erupção pruriginosa papulosa",
      "eritemato-escamosa disseminada",
      "nódulos hipercromicos"
    ],
    "Substância Química Orgânica": [
      "Hidroxezina",
      "Doxepina",
      "hidroxezine",
      "doxepina",
      "MTX"
    ],
    "Substância Farmacológica": [
      "Hidroxezina",
      "Doxepina",
      "hidroxezine",
      "doxepina",
      "MTX",
      "drenison creme"
    ],
    "Procedimento Terapêutico ou Preventivo": [
      "hidratação"
    ],
    "Atividade de Assistência à Saúde": [
      "o",
      "mantenho",
      "prescrevo",
      "retorno"
    ],
    "Conceito Qualitativo": [
      "elevados",
      "25mg"
    ],
    "Produto Intelectual": [
      "p",
      "plano"
    ],
    "Conceito Quantitativo": [
      "25mg",
      "20mg"
    ],
    "Resultado Laboratorial ou de Teste": [
      "Dermatite superficial espongiótica",
      "Aspecto histológico favorece hipóteses clínicas de eritema anular centrífugo",
      "Pitiríase Rósea",
      "SEMELHANTES ENTRE SI",
      "FOCOS DE PARACERATOSE",
      "FOCALMENTE MICROABCESSOS NA CAM CORNEA , ACANTOSE REGULAR",
      "DISCRETA ESPONGIOSE",
      "INFILTRADO INFLAMATORIO CRONICO LINFOCITARIO"
    ],
    "Parte do Corpo, Órgão ou Componente Orgânico": [
      "FRAGMENTOS DE PELE",
      "FOCALMENTE MICROABCESSOS NA CAM CORNEA , ACANTOSE REGULAR",
      "DERME SUPERFICIAL"
    ],
    "Função Patológica": [
      "FOCALMENTE MICROABCESSOS NA CAM CORNEA , ACANTOSE REGULAR",
      "DISCRETA ESPONGIOSE",
      "INFILTRADO INFLAMATORIO CRONICO LINFOCITARIO"
    ],
    "Anormalidade Adquirida": [
      "nódulos hipercromicos"
    ],
    "Medicamento Clínico": [
      "drenison creme"
    ],
    "Anormalidade Anatômica": [
      "nodulos mais elevados"
    ]
  },
  "labels": {}
}