{
  "prontuario_id": 876,
  "text": "\"retorno com exames\".  Paciente com DM diagnosticado há 8 anos. Em uso de Nesina 25mg 1 x/dia e outro ADO que não soube informar 2 x/dia; Metformina 850mg 3 x/dia. Insulina NPH 20U pela manhã e 10U após o jantar. Nega episódios recentes de hipoglicemia. Glicemia varia bastante com a alimentação (de 120 - 450). Refere \"dormência\" nos pés (fez exame do pé diabético há 6 meses). Refere disfagia frequentemente. Exames de 11/01/16: HbA1C 9,27%, Glicose 300, Creatinina 0,9 ( CL Cr  = 74 ml/ min  =  ckd-epi), CPK 233, Triglicerídeos 95, TGP 20,  TGO 19, HDL 38, CT 183,  LDL 126, TSH 1,19; Microalbuminúria 24 h 8,9. Pai falecido por AVC e mãe falecida por IAM. Retinopatia diabética há 3 anos, com perda da visão no olho direito. Nega nefropatia diabética e doenças cardiovasculares. HAS (?) - faz uso de cp sublingual quando a PA está muito alta. Nega etilismo e tabagismo. Alimentação controlada pela família (sic). Faz refeição na madrugada. HbA1C, Glicemia de jejum, Perfil lipídico.",
  "entities": {
    "Paciente ou Grupo com Deficiência": [
      "Paciente"
    ],
    "Abreviação": [
      "DM",
      "ADO",
      "AVC",
      "IAM",
      "HAS",
      "PA",
      "HbA1C",
      "HbA1C 9 , 27%",
      "CL Cr = 74 ml/ min = ckd-epi",
      "CPK 233",
      "HDL 38",
      "CT 183",
      "LDL 126"
    ],
    "Doença ou Síndrome": [
      "DM",
      "AVC",
      "IAM",
      "HAS",
      "etilismo",
      "tabagismo",
      "Retinopatia diabética",
      "nefropatia diabética",
      "doenças cardiovasculares"
    ],
    "Atividade de Assistência à Saúde": [
      "diagnosticado"
    ],
    "Substância Farmacológica": [
      "Nesina",
      "Metformina",
      "Insulina NPH"
    ],
    "Substância Química Orgânica": [
      "Nesina",
      "Metformina"
    ],
    "Conceito Quantitativo": [
      "25mg",
      "850mg",
      "20U",
      "10U",
      "120 - 450"
    ],
    "Negação": [
      "não",
      "Nega"
    ],
    "Sinal ou Sintoma": [
      "hipoglicemia",
      "disfagia",
      "\"dormência\" nos pés"
    ],
    "Alimento": [
      "alimentação",
      "Alimentação"
    ],
    "Conceito Temporal": [
      "frequentemente",
      "1 x/dia",
      "2 x/dia",
      "3 x/dia",
      "pela manhã",
      "após o jantar"
    ],
    "Grupo Familiar": [
      "Pai",
      "mãe"
    ],
    "Achado": [
      "falecido",
      "falecida"
    ],
    "Localização ou Região Corporal": [
      "sublingual"
    ],
    "Atributo Clínico": [
      "PA"
    ],
    "Procedimento Laboratorial": [
      "HbA1C",
      "Glicemia de jejum",
      "Perfil lipídico"
    ],
    "Aminoácido, Peptídeo ou Proteína": [
      "Insulina NPH"
    ],
    "Resultado Laboratorial ou de Teste": [
      "120 - 450",
      "HbA1C 9 , 27%",
      "Glicose 300",
      "Creatinina 0 , 9",
      "CL Cr = 74 ml/ min = ckd-epi",
      "CPK 233",
      "Triglicerídeos 95",
      "TGP 20",
      "TGO 19",
      "HDL 38",
      "CT 183",
      "LDL 126",
      "TSH 1 , 19",
      "Microalbuminúria 24 h 8 , 9"
    ],
    "Procedimento Diagnóstico": [
      "exame do pé diabético"
    ],
    "Parte do Corpo, Órgão ou Componente Orgânico": [
      "olho direito"
    ],
    "Conceito Qualitativo": [
      "muito alta"
    ]
  },
  "labels": {}
}