{
  "prontuario_id": 777,
  "text": "Lucas, 74 anos. Em acompanhamento no ambualtorio há 5 anos por FA, uso de marevan 5mg 1 x ao dia.  Comorbidades: DM há 10 anos em uso de metformina 850mg 3 cp/dia, acarbose 1 cp/dia e glicazida 60mg 2 cp/dia e insulina (24 - 0 - 24). HAS há 15 anos em uso de losartana 50mg /dia e digoxina 1/2 cp /dia, carvedilol 25 12/12, HCTZ. DSLP em uso de sinvastatina, marevan 1 cp/dia seg - sab para no alvo sic.  S : Assintomática. Nega dispnéia, DPN e ortopneia, palpitações e sincope. O : BEG, corada, hidtratada, afebril, fc 63, so2 97%, pa 130/80; MV presente, simétrico, sem RA. BC arritmicas, NF SS 2T. Abd globoso, flacido, indolor a palpacao, sem VCM. MMII sem edema, panturrilhas livres.  Exames -  Holter: FC controlada, media 92. Cr - 0,7;  glic - 140;   ureia - 33;  CPK - 68,  Triglerideos - 335;   HDL - 30;   CT - 216;   LDL - 119;  K - 5,1; RNI - 2,07;   Microalbuminúria 308 mg/g.  Ecocardiograma - ventrículo esquerdo com hipertrofia concentrica de grau discreto e função sistólica preservada. aumento moderado de átrio esquerdo. calcificação mitral e aórtica com refluxo leve.   A : FA.  PA - 120/80, P - 72, bulhas arritimicas, normofonéticas, sem sopros.  Abdomen flácido, indolor, sem visceromegalias. Sem alterações nos MMII. Otimizo dose da sinvastatina para 40mg /dia. Atestado para atividades físicas. Retorno na vaga.",
  "entities": {
    "Atividade de Assistência à Saúde": [
      "acompanhamento",
      "O",
      "Retorno",
      "Otimizo dose",
      "Atestado para atividades físicas"
    ],
    "Organização Relacionada à Saúde": [
      "ambualtorio"
    ],
    "Abreviação": [
      "FA",
      "DM",
      "HAS",
      "HCTZ",
      "DSLP",
      "S",
      "DPN",
      "O",
      "BEG",
      "fc",
      "so2",
      "pa",
      "RA",
      "Abd",
      "VCM",
      "MMII",
      "A",
      "PA",
      "P",
      "3 cp/dia",
      "1 cp/dia",
      "2 cp/dia",
      "1/2 cp /dia",
      "MV presente",
      "BC arritmicas",
      "NF SS 2T",
      "FC controlada",
      "Cr - 0 , 7",
      "glic - 140",
      "CPK - 68",
      "HDL - 30",
      "CT - 216",
      "LDL - 119",
      "K - 5 , 1",
      "RNI - 2 , 07"
    ],
    "Doença ou Síndrome": [
      "FA",
      "DM",
      "HAS",
      "DSLP"
    ],
    "Substância Farmacológica": [
      "marevan",
      "metformina",
      "acarbose",
      "glicazida",
      "insulina",
      "losartana",
      "digoxina",
      "carvedilol",
      "HCTZ",
      "sinvastatina"
    ],
    "Substância Química Orgânica": [
      "metformina",
      "glicazida",
      "losartana",
      "carvedilol",
      "sinvastatina"
    ],
    "Hormônio": [
      "insulina"
    ],
    "Conceito Temporal": [
      "12/12"
    ],
    "Achado": [
      "S",
      "BEG",
      "corada",
      "hidtratada",
      "simétrico",
      "flacido",
      "normofonéticas",
      "flácido",
      "MV presente",
      "NF SS 2T",
      "função sistólica preservada"
    ],
    "Negação": [
      "Assintomática",
      "Nega",
      "afebril",
      "sem",
      "indolor",
      "Sem"
    ],
    "Sinal ou Sintoma": [
      "Assintomática",
      "dispnéia",
      "DPN",
      "ortopneia",
      "palpitações",
      "sincope",
      "afebril",
      "RA",
      "globoso",
      "VCM",
      "edema",
      "sopros",
      "indolor",
      "visceromegalias",
      "alterações",
      "BC arritmicas"
    ],
    "Atributo Clínico": [
      "fc",
      "so2",
      "pa",
      "PA",
      "P"
    ],
    "Conceito Quantitativo": [
      "63",
      "97%",
      "130/80",
      "120/80",
      "72",
      "1 x ao dia",
      "3 cp/dia",
      "1 cp/dia",
      "2 cp/dia",
      "24 - 0 - 24",
      "50mg /dia",
      "1/2 cp /dia",
      "40mg /dia"
    ],
    "Localização ou Região Corporal": [
      "Abd",
      "MMII",
      "Abdomen"
    ],
    "Função Patológica": [
      "edema"
    ],
    "Parte do Corpo, Órgão ou Componente Orgânico": [
      "panturrilhas"
    ],
    "Procedimento Diagnóstico": [
      "Exames",
      "Holter",
      "Ecocardiograma",
      "A"
    ],
    "Resultado Laboratorial ou de Teste": [
      "FC controlada",
      "media 92",
      "Cr - 0 , 7",
      "glic - 140",
      "ureia - 33",
      "CPK - 68",
      "Triglerideos - 335",
      "HDL - 30",
      "CT - 216",
      "LDL - 119",
      "K - 5 , 1",
      "RNI - 2 , 07",
      "Microalbuminúria 308 mg/g",
      "ventrículo esquerdo com hipertrofia concentrica",
      "função sistólica preservada",
      "aumento moderado de átrio esquerdo",
      "calcificação mitral e aórtica com refluxo leve"
    ]
  },
  "labels": {}
}