{
  "prontuario_id": 925,
  "text": "PCTE COM HISTÓRIA DE GOTA, NEFRECTOMIA HÁ 2 ANOS E ANGINA INTERNA PARA REALIZAÇÃO DE ACTP + STENT EM ACX DISTAL COM SUCESSO ANGIOGRÁFICO. APRESENTA NO DIA POSTERIOR AO PROCEDIMENTO QUADRO DE MONOARTRITE EM JOELHO DIR. INICIADO TRATAMENTO PARA CRISE DE GOTA COM COLCHICINA E AINE COM MELHORA PARCIAL. REALIZADA PUNÇÃO ARTICULAR COM PRESENÇA DE CRISTAIS E NEUTROFILOS 80% NO DIFERENCIAL E MELHORA SIGNIFICATIVA DO QUADRO. PROVEVEL PERDA DE FUNÇÃO RENAL PRÉVIA COM PIORA COM AINE, MAS RETRONO AOS NÍVEIS BASAIS COM HIDRATAÇÃO E RETIRADA DO AINE. EXAMES NA ALTA: U: 100, CR: 2,2; K:4,2; ORIENTADO A USAR TICLOPIDINA 250MG DE 12/12 H POR 30 DIAS, JUNTAMENTE COM OUTRAS MEDICAÇÕES DE USO CORRENTE, ASSIM COMO PROCURAR SEU MÉDICO PARA MANEJO DA IRC E GOTA.",
  "entities": {
    "Abreviação": [
      "PCTE",
      "AINE",
      "ACX DISTAL",
      "JOELHO DIR",
      "PIORA COM AINE",
      "U : 100",
      "CR : 2 , 2",
      "K : 4 , 2"
    ],
    "Paciente ou Grupo com Deficiência": [
      "PCTE"
    ],
    "Doença ou Síndrome": [
      "GOTA",
      "ANGINA",
      "IRC",
      "QUADRO DE MONOARTRITE",
      "CRISE DE GOTA",
      "PERDA DE FUNÇÃO RENAL"
    ],
    "Procedimento Terapêutico ou Preventivo": [
      "NEFRECTOMIA",
      "TRATAMENTO",
      "HIDRATAÇÃO",
      "PUNÇÃO ARTICULAR"
    ],
    "Sinal ou Sintoma": [
      "ANGINA",
      "QUADRO DE MONOARTRITE"
    ],
    "Atividade de Assistência à Saúde": [
      "INTERNA",
      "ALTA",
      "ORIENTADO"
    ],
    "Substância Farmacológica": [
      "COLCHICINA",
      "AINE",
      "TICLOPIDINA",
      "MEDICAÇÕES"
    ],
    "Substância Química Orgânica": [
      "COLCHICINA",
      "TICLOPIDINA"
    ],
    "Conceito Temporal": [
      "PRÉVIA",
      "12/12 H"
    ],
    "Procedimento Laboratorial": [
      "EXAMES"
    ],
    "Conceito Quantitativo": [
      "250MG"
    ],
    "Grupo Profissional ou Ocupacional": [
      "MÉDICO"
    ],
    "Parte do Corpo, Órgão ou Componente Orgânico": [
      "ACX DISTAL",
      "JOELHO DIR"
    ],
    "Achado": [
      "SUCESSO ANGIOGRÁFICO",
      "MELHORA PARCIAL",
      "MELHORA SIGNIFICATIVA DO QUADRO",
      "PIORA COM AINE"
    ],
    "Procedimento Diagnóstico": [
      "PUNÇÃO ARTICULAR"
    ],
    "Resultado Laboratorial ou de Teste": [
      "PRESENÇA DE CRISTAIS E NEUTROFILOS 80%",
      "U : 100",
      "CR : 2 , 2",
      "K : 4 , 2"
    ]
  },
  "labels": {}
}