{
  "prontuario_id": 207,
  "text": "Paciente internou para investigar quadro de vertigem acompanhado de nauseas, vomitos, principalmente durante a madrugada. Fez avaliação da otorrino que sugeriu audiometria e eletronistagmografia que deverão ser realizados a nivel ambulatorial. Realizado holter que não evidenciou arritmias significativas. Mostrou intervalo QT prolongado. Fez tilt que foi negativo para sincope vaso vagal. Cintilografia miocardica de esforço não mostrou alterações significativas, apenas discreta hipoperfusão apical compativel com afinamento apica fisilogicol. Recebe alta hospitalar, prosseguindo investigação a nivel ambulatorial.",
  "entities": {
    "Paciente ou Grupo com Deficiência": [
      "Paciente"
    ],
    "Atividade de Assistência à Saúde": [
      "internou",
      "investigar",
      "avaliação",
      "Realizado",
      "alta hospitalar",
      "investigação a nivel ambulatorial"
    ],
    "Sinal ou Sintoma": [
      "nauseas",
      "vomitos",
      "alterações",
      "quadro de vertigem"
    ],
    "Grupo Profissional ou Ocupacional": [
      "otorrino"
    ],
    "Abreviação": [
      "otorrino",
      "tilt"
    ],
    "Procedimento Diagnóstico": [
      "audiometria",
      "eletronistagmografia",
      "holter",
      "tilt",
      "Cintilografia miocardica de esforço"
    ],
    "Negação": [
      "não",
      "negativo"
    ],
    "Doença ou Síndrome": [
      "arritmias",
      "sincope vaso vagal"
    ],
    "Resultado Laboratorial ou de Teste": [
      "arritmias",
      "negativo",
      "intervalo QT prolongado",
      "hipoperfusão apical",
      "afinamento apica fisilogicol"
    ],
    "Conceito Temporal": [
      "durante a madrugada"
    ],
    "Organização Relacionada à Saúde": [
      "nivel ambulatorial",
      "investigação a nivel ambulatorial"
    ]
  },
  "labels": {}
}