{
  "prontuario_id": 602,
  "text": "Acompanhamento Nefrologia  desde 2012 devido encaminhamento da endocrinologia por DM.  ID: Lucas, 65 anos, do lar.  QP: Consulta para analise exames laboratoriais, sem queixas. paciente refere nicturia, maior vol urinario a noite. nega disuria. paciente refere edema principalmente se aumento ingesta sal. paciente refere dor em flanco D em caso de aumento da ingesta de sal. PAciente  relata aumento de 13 Kg em 8 meses.  medicamentos em uso:  Losartana 50mg 2 x/d,  Anlodipino 5mg 2 x/d, Atenolol 50mg 2 x/d, Hidroclorotiazida 25mg 1 x/d,  AAS 1mg 1 x/d, Atorvastatina 20mg 1 x/d, Trayenta (linagliptina), Actos 15mg 1 x/d, Isordil 5mg se dor peito, Clopidogrel 75mg 1 x/d,  Exames laboratoriais 23/05/2013: HMG: Hb  12,2; VG 36,3; leucocitos 5440; eosinofilos 3%; linfocitos 28%; bastonetes 1%; plaquetas 204000; creatinina 1,2; glicose 192; ureia 38; calcio total 9,3; ac urico 5,5; TG 138; HDL 47; Sodio 138; Potassio 4,8; CT 178; Fosforo 3,9; LDL 103; microalbuminuria 24 h 11,8; clearance creatinina pelo CKD-epi 48 ml/min. cx revascularizacao miocardio, Ponte de safena 2008, angioplastia 2012, HAS,  DM ha 12 anos, nega alergias.",
  "entities": {
    "Atividade de Assistência à Saúde": [
      "Acompanhamento",
      "encaminhamento",
      "Consulta"
    ],
    "Organização Relacionada à Saúde": [
      "Nefrologia"
    ],
    "Grupo Profissional ou Ocupacional": [
      "Nefrologia",
      "endocrinologia"
    ],
    "Doença ou Síndrome": [
      "DM",
      "HAS",
      "alergias"
    ],
    "Abreviação": [
      "DM",
      "ID",
      "QP",
      "AAS",
      "HAS",
      "maior vol urinario",
      "flanco D",
      "Hb 12 , 2",
      "VG 36 , 3",
      "CT 178"
    ],
    "Achado": [
      "QP",
      "cx revascularizacao miocardio",
      "Ponte de safena"
    ],
    "Negação": [
      "sem",
      "nega"
    ],
    "Sinal ou Sintoma": [
      "queixas",
      "nicturia",
      "disuria",
      "edema",
      "dor",
      "maior vol urinario",
      "aumento de 13 Kg"
    ],
    "Paciente ou Grupo com Deficiência": [
      "paciente",
      "PAciente"
    ],
    "Função Patológica": [
      "edema"
    ],
    "Substância Farmacológica": [
      "medicamentos",
      "Losartana",
      "Anlodipino",
      "Atenolol",
      "Hidroclorotiazida",
      "AAS",
      "Atorvastatina",
      "Trayenta",
      "linagliptina",
      "Actos",
      "Isordil",
      "Clopidogrel"
    ],
    "Substância Química Orgânica": [
      "Losartana",
      "Anlodipino",
      "Atenolol",
      "Hidroclorotiazida",
      "AAS",
      "Atorvastatina",
      "Trayenta",
      "linagliptina",
      "Actos",
      "Isordil",
      "Clopidogrel"
    ],
    "Conceito Quantitativo": [
      "5mg",
      "2 x/d",
      "25mg",
      "1 x/d"
    ],
    "Procedimento Laboratorial": [
      "HMG",
      "exames laboratoriais",
      "Exames laboratoriais"
    ],
    "Procedimento Terapêutico ou Preventivo": [
      "angioplastia",
      "cx revascularizacao miocardio",
      "Ponte de safena"
    ],
    "Localização ou Região Corporal": [
      "flanco D"
    ],
    "Resultado Laboratorial ou de Teste": [
      "Hb 12 , 2",
      "VG 36 , 3",
      "leucocitos 5440",
      "eosinofilos 3%",
      "linfocitos 28%",
      "bastonetes 1%",
      "plaquetas 204000",
      "creatinina 1 , 2",
      "glicose 192",
      "ureia 38",
      "calcio total 9 , 3",
      "ac urico 5 , 5",
      "TG 138",
      "HDL 47",
      "Sodio 138",
      "Potassio 4 , 8",
      "CT 178",
      "Fosforo 3 , 9",
      "LDL 103",
      "microalbuminuria 24 h 11 , 8",
      "clearance creatinina pelo CKD-epi 48 ml/min"
    ]
  },
  "labels": {}
}