{
  "prontuario_id": 6,
  "text": "16:25h: Glasgow 11, pupilas iso  /  foto. SNE com infusão de dieta 75 ml/h. Suporte de O2 sob traqueostomia, aspiração de secreção espessa amarelada. CPP com roncos difusos. Dren de tórax D anterior e posterior com presença de drenagem purulenta com aspiração contínua. Abdomem plano e flácido, RHA +. Acesso venoso em MSD com infusão de soroterapia. MSE contido profiláticamente. SVD com diurese efetiva, evacuação ausente. Extremidades aquecidas, perfusão periférica adequada, edemaciado. Segue sentado em poltrona, sob cuidados intensivos e precaução de contato para MRSA + A. baumannii. Enfermeira Florence Nightingale. EXAME GERAL E INVESTIGACAO DE PESSOAS SEM QUEIXAS OU DIAGNOSTICO RELATADO.",
  "entities": {
    "Parte do Corpo, Órgão ou Componente Orgânico": [
      "pupilas"
    ],
    "Abreviação": [
      "iso",
      "foto",
      "SNE",
      "O2",
      "CPP",
      "MSD",
      "MSE",
      "SVD",
      "MRSA",
      "RHA +"
    ],
    "Achado": [
      "iso",
      "foto",
      "plano",
      "flácido",
      "RHA +",
      "diurese efetiva",
      "Extremidades aquecidas",
      "perfusão periférica adequada",
      "sentado em poltrona"
    ],
    "Procedimento Terapêutico ou Preventivo": [
      "SNE",
      "traqueostomia",
      "SVD",
      "Acesso venoso",
      "infusão de soroterapia"
    ],
    "Dispositivo Médico": [
      "SNE",
      "Dren",
      "SVD",
      "Acesso venoso"
    ],
    "Localização ou Região Corporal": [
      "CPP",
      "Abdomem",
      "MSD",
      "MSE"
    ],
    "Conceito Espacial": [
      "anterior",
      "posterior"
    ],
    "Sinal ou Sintoma": [
      "edemaciado",
      "QUEIXAS",
      "Glasgow 11",
      "roncos difusos"
    ],
    "Bactéria": [
      "MRSA",
      "baumannii"
    ],
    "Grupo Profissional ou Ocupacional": [
      "Enfermeira"
    ],
    "Negação": [
      "SEM"
    ],
    "Conceito Quantitativo": [
      "75 ml/h"
    ],
    "Atividade de Assistência à Saúde": [
      "cuidados intensivos",
      "EXAME GERAL"
    ],
    "Procedimento Diagnóstico": [
      "INVESTIGACAO DE PESSOAS"
    ],
    "Doença ou Síndrome": [
      "DIAGNOSTICO RELATADO"
    ]
  },
  "labels": {}
}