{
  "prontuario_id": 162,
  "text": "LUCAS, 55 ANOS, VEIO P COM SOBRINHA LUCAS, DM E HAS HÁ 10 ANOS, EX-USUARIO DE DROGAS , USO DE PSICOTROPICOS (HALDOL... USO IRREGULAR DE MEDICAÇÕES: ENALAPRIL, GLICANIL, METFORMINA, FLUOXETINA, RESPIRIDONA, AMYTRIL, HALO, LONGACTIL, SVT, DLP. NEGA ALTERAÇÃO PROSTÁTICA, IAM, AVE, UROLITIASE, GOTA NÃO SE LEMBRA DAS MEDICAÇÕES. AO EXAME: PESO 98, ALT 174, MUCOSAS CORADAS, OBESO, ABDOME GLOBOSO, SEM VCM, MEMBROS SEM EDEMA. ORIENTO OTMIZAR TTO NA UBS. INICIO INDAPEN.  NEFROPATIA LEVE. EXAMES > CR 0,88, TG 176, CT 174, HDL 33, CL CR 63, HMG NORMAL, HB GLIC 8,8. PEÇO URINA 24H. DEFINIR NEFROPATIA DIABÉTICA. RETORNO DA SOBRINHA COM EXAMES  11/11/2015: CR 1,16, GLI 87, NA 136, K 4,3, UR 23, CA 9,1, AC 4,7, P 3,7, P URINA: PROTEINA 100, HT 45, HB 15,  MICROALB 683 MG/G.",
  "entities": {
    "Doença ou Síndrome": [
      "DM",
      "HAS",
      "IAM",
      "AVE",
      "UROLITIASE",
      "GOTA",
      "OBESO",
      "NEFROPATIA",
      "NEFROPATIA DIABÉTICA"
    ],
    "Abreviação": [
      "DM",
      "HAS",
      "HALO",
      "SVT",
      "DLP",
      "IAM",
      "AVE",
      "ALT",
      "VCM",
      "UBS",
      "P URINA"
    ],
    "Substância Farmacológica": [
      "PSICOTROPICOS",
      "HALDOL",
      "MEDICAÇÕES",
      "ENALAPRIL",
      "GLICANIL",
      "METFORMINA",
      "FLUOXETINA",
      "RESPIRIDONA",
      "AMYTRIL",
      "HALO",
      "LONGACTIL",
      "SVT",
      "INDAPEN"
    ],
    "Aminoácido, Peptídeo ou Proteína": [
      "ENALAPRIL"
    ],
    "Substância Química Orgânica": [
      "GLICANIL",
      "METFORMINA",
      "FLUOXETINA",
      "RESPIRIDONA",
      "AMYTRIL",
      "HALO",
      "LONGACTIL",
      "SVT"
    ],
    "Negação": [
      "NEGA",
      "NÃO",
      "SEM"
    ],
    "Procedimento Diagnóstico": [
      "EXAME"
    ],
    "Atributo Clínico": [
      "PESO",
      "ALT"
    ],
    "Conceito Quantitativo": [
      "98",
      "174"
    ],
    "Achado": [
      "OBESO",
      "EX-USUARIO DE DROGAS",
      "MUCOSAS CORADAS",
      "HMG NORMAL"
    ],
    "Parte do Corpo, Órgão ou Componente Orgânico": [
      "ABDOME",
      "MEMBROS"
    ],
    "Sinal ou Sintoma": [
      "GLOBOSO",
      "VCM",
      "EDEMA",
      "ALTERAÇÃO PROSTÁTICA"
    ],
    "Função Patológica": [
      "EDEMA"
    ],
    "Organização Relacionada à Saúde": [
      "UBS"
    ],
    "Conceito Qualitativo": [
      "LEVE"
    ],
    "Procedimento Laboratorial": [
      "EXAMES",
      "URINA 24H",
      "P URINA"
    ],
    "Atividade de Assistência à Saúde": [
      "RETORNO",
      "ORIENTO OTMIZAR TTO"
    ],
    "Resultado Laboratorial ou de Teste": [
      "CR 0 , 88",
      "TG 176",
      "CT 174",
      "HDL 33",
      "CL CR 63",
      "HMG NORMAL",
      "HB GLIC 8 , 8",
      "CR 1 , 16",
      "GLI 87",
      "NA 136",
      "K 4 , 3",
      "UR 23",
      "CA 9 , 1",
      "AC 4 , 7",
      "P 3 , 7",
      "PROTEINA 100",
      "HT 45",
      "HB 15",
      "MICROALB 683 MG/G"
    ]
  },
  "labels": {}
}