{
  "prontuario_id": 824,
  "text": "LUCAS, 70 ANOS, APOSENTADO, CASADO.  ACOMPANHAMENTO DE HIPERTENSÃO ARTERIAL REFRETÁRIA. ACOMPANHAMENTO DE DM2. REFERE PERDA DE SENSIBILIDADE TÁTIL NOS PÉS. DORES EM DEDOS DOS PÉS.  EM USO DE LOSARTANA 50MG /DIA, ANLODIPINO 10MG /DIA, ATENOLOL 25MG /DIA, HCT 25MG /DIA, METFORMINA 850 MG 2 CP MANHÃ, GLIBENCLAMIDA 5MG 2 CP MANHÃ E 2 CP NOITE, SINVASTATINA 20MG /DIA (PAROU O USO POR CONTA).  # O : FC 72, FR 16, PA SENTADO 150/80, PA DEITADO 160/90, PA EM PÉ 170/80, CA 103 CM,  BEG, LOTE, HANN CARDIOPULMONAR SEM PARTICULARIDADES. ABDOME: PRESENÇA DE HÉRNIA ABDOMINAL MEDIANA. SEM EDEMA DE MEMBROS INFERIORES.  #,A,: ELETROCARDIOGRAMA: BLOQUEIO DE RAMO DIREITO. HEMOGRAMA OK, GLICEMIA 94, SÓDIO 137, POTÁSSIO 5,8; PROTEÍNAS OK; URÉIAS 89; CREATININA 2,27; - CLEARENCE DE CREATININA 28,2 (ESTADIO 4); HBA1C 8,2;  # P: MANTENHO PRESCRIÇÃO E ORIENTO A REALIZAÇÃO DE MAIS AFERIÇÕES DE PA. SUBSTITUO ADO POR INSULINOTERAPIA. SUBSTITUO POR INSULINA NPH 14 UNIDADES PELA MANHÃ E 7 UNIDADES A NOITE. ENCAMINHO PARA O SERVIÇO DA NEFROLOGIA DA XXX.",
  "entities": {
    "Grupo Profissional ou Ocupacional": [
      "APOSENTADO",
      "NEFROLOGIA"
    ],
    "Atividade de Assistência à Saúde": [
      "ACOMPANHAMENTO",
      "MANTENHO",
      "PRESCRIÇÃO",
      "ORIENTO",
      "SUBSTITUO",
      "ENCAMINHO"
    ],
    "Doença ou Síndrome": [
      "DM2",
      "HIPERTENSÃO ARTERIAL REFRETÁRIA",
      "BLOQUEIO DE RAMO DIREITO"
    ],
    "Abreviação": [
      "DM2",
      "HCT",
      "FC",
      "FR",
      "CA",
      "BEG",
      "LOTE",
      "ADO",
      "PA SENTADO",
      "PA DEITADO",
      "PA EM PÉ",
      "AFERIÇÕES DE PA"
    ],
    "Parte do Corpo, Órgão ou Componente Orgânico": [
      "PÉS",
      "DEDOS DOS PÉS"
    ],
    "Sinal ou Sintoma": [
      "DORES",
      "PARTICULARIDADES",
      "EDEMA",
      "PERDA DE SENSIBILIDADE TÁTIL"
    ],
    "Substância Farmacológica": [
      "LOSARTANA",
      "ANLODIPINO",
      "ATENOLOL",
      "HCT",
      "METFORMINA",
      "GLIBENCLAMIDA",
      "SINVASTATINA",
      "ADO",
      "INSULINA NPH"
    ],
    "Substância Química Orgânica": [
      "METFORMINA",
      "SINVASTATINA"
    ],
    "Atributo Clínico": [
      "FC",
      "FR",
      "CA",
      "PA SENTADO",
      "PA DEITADO",
      "PA EM PÉ"
    ],
    "Conceito Quantitativo": [
      "72",
      "16",
      "150/80",
      "160/90",
      "170/80",
      "50MG /DIA",
      "10MG /DIA",
      "25MG /DIA",
      "850 MG",
      "20MG /DIA",
      "103 CM"
    ],
    "Achado": [
      "BEG",
      "LOTE"
    ],
    "Negação": [
      "SEM"
    ],
    "Localização ou Região Corporal": [
      "ABDOME",
      "MEMBROS INFERIORES"
    ],
    "Função Patológica": [
      "EDEMA"
    ],
    "Procedimento Diagnóstico": [
      "ELETROCARDIOGRAMA",
      "AFERIÇÕES DE PA"
    ],
    "Procedimento Terapêutico ou Preventivo": [
      "INSULINOTERAPIA"
    ],
    "Resultado Laboratorial ou de Teste": [
      "BLOQUEIO DE RAMO DIREITO",
      "HEMOGRAMA OK",
      "GLICEMIA 94",
      "SÓDIO 137",
      "POTÁSSIO 5 , 8",
      "PROTEÍNAS OK",
      "URÉIAS 89",
      "CREATININA 2 , 27",
      "CLEARENCE DE CREATININA 28 , 2",
      "HBA1C 8 , 2"
    ]
  },
  "labels": {}
}