{
  "prontuario_id": 479,
  "text": "Masculino, 54 anos, internado em Bento Gonçalves por síndrome coronariana aguda sem supra ST e descompensação de ICC. Apresenta também como comorbidades HAS, DM e DPOC. Cateterismo cardíaco com lesão grave em artéria circunflexa. Interna em 15/10/04 para realização de angioplastia e implante de endoprótese nessa lesão. Procedimento realizado com sucesso e sem intercorrências pelo Doutor Vital Brazil no mesmo dia. Evoluiu bem, havendo compensação da ICC com tratamento farmacológico (diurético endovenoso). Ecografia com doppler em local de punção de artéria femoral mostra ausência de sinais de hematoma ou pseudoaneurisma. Recebe alta em bom estado geral, assintomático, sinais vitais estáveis, afebril, orientado quanto a medicações, cuidados e retorno ao seu médico.",
  "entities": {
    "Doença ou Síndrome": [
      "comorbidades",
      "HAS",
      "DM",
      "DPOC",
      "ICC",
      "síndrome coronariana aguda",
      "descompensação de ICC"
    ],
    "Abreviação": [
      "HAS",
      "DM",
      "DPOC",
      "ICC",
      "descompensação de ICC"
    ],
    "Atividade de Assistência à Saúde": [
      "Interna",
      "realizado",
      "retorno",
      "tratamento farmacológico"
    ],
    "Procedimento Terapêutico ou Preventivo": [
      "angioplastia",
      "Procedimento",
      "Cateterismo cardíaco",
      "implante de endoprótese",
      "tratamento farmacológico"
    ],
    "Achado": [
      "sucesso",
      "bem",
      "compensação",
      "assintomático",
      "afebril",
      "supra ST",
      "bom estado geral",
      "sinais vitais estáveis"
    ],
    "Negação": [
      "sem",
      "ausência",
      "assintomático",
      "afebril"
    ],
    "Sinal ou Sintoma": [
      "intercorrências",
      "sinais de hematoma"
    ],
    "Resultado Laboratorial ou de Teste": [
      "pseudoaneurisma",
      "lesão grave em artéria circunflexa",
      "sinais de hematoma"
    ],
    "Substância Farmacológica": [
      "medicações",
      "diurético endovenoso"
    ],
    "Grupo Profissional ou Ocupacional": [
      "médico"
    ],
    "Procedimento Diagnóstico": [
      "Cateterismo cardíaco",
      "Ecografia com doppler"
    ],
    "Parte do Corpo, Órgão ou Componente Orgânico": [
      "artéria femoral"
    ]
  },
  "labels": {}
}