{
  "prontuario_id": 378,
  "text": "DM HA 25 ANOS COM CONTROLE IRREGULAR - NEGA DIETA ICO - RVM HÁ 12 ANOS (2001) / 2012 - ATC EX TABAGISTA  HAS HÁ 12 ANOS CGIA DE CATARATA / RETINOPATIA (LASER) US DE LST 50MG 2X, SINVA 20MG, , AAS, ANLO 5MG 1X, INDAPAMINA SR 1,5MG, SELOZOK 100MG 2X, CLOPIDOGREL 75MG 1X, MTF 850MG 3X, OMZ 20, INSULINA NPH 50 - 0 - 30. INSULINA R 10U ANTES DO CAFÉ.  ECG 2012 - ISQUEMIA SUBEPICARDICO LAT ALTA, AREA INATIVA ANT-SEPTAL, SINUSAL FC 66 TSH 7,7 HBA1C 10,1 8/8/2013 MICROALBUMINURIA 399 CLCR 106 ( CG ) CT 185 TG 173 CR 0,7 HDL 41 LDL 109 VG 38 LEUC 4750 PQ 227  PU D 1007 PH 6,0 LEUC E HEM 0  PESO 93,5 PA 160*80 CPP LIVRE SEM RA ABDOMEN NDN MMII SEM EDEMA  HD: NEFROPATIA DIABETICA / PROTEINURIA NAO NEFROTICA DM DESCOMPENSADO  P: ENALAPRIL 10MG  DOPPLER  DIETA",
  "entities": {
    "Doença ou Síndrome": [
      "DM",
      "HAS",
      "CATARATA",
      "RETINOPATIA",
      "NEFROPATIA DIABETICA",
      "DM DESCOMPENSADO"
    ],
    "Abreviação": [
      "DM",
      "RVM",
      "HAS",
      "LST",
      "SINVA",
      "AAS",
      "ANLO",
      "MTF",
      "OMZ",
      "ECG",
      "FC",
      "CG",
      "LEUC",
      "PA",
      "RA",
      "NDN",
      "MMII",
      "HD",
      "P",
      "INSULINA R",
      "ISQUEMIA SUBEPICARDICO LAT ALTA",
      "AREA INATIVA ANT-SEPTAL",
      "CT 185",
      "TG 173",
      "CR 0 , 7",
      "VG 38",
      "LEUC 4750",
      "CPP LIVRE",
      "DM DESCOMPENSADO"
    ],
    "Negação": [
      "NEGA",
      "SEM"
    ],
    "Alimento": [
      "DIETA",
      "CAFÉ"
    ],
    "Procedimento Terapêutico ou Preventivo": [
      "RVM",
      "LASER",
      "DIETA"
    ],
    "Substância Farmacológica": [
      "LST",
      "SINVA",
      "AAS",
      "ANLO",
      "SELOZOK",
      "CLOPIDOGREL",
      "MTF",
      "OMZ",
      "ENALAPRIL",
      "INDAPAMINA SR",
      "INSULINA NPH",
      "INSULINA R"
    ],
    "Conceito Quantitativo": [
      "20MG",
      "20",
      "66",
      "160*80",
      "10MG",
      "50MG 2X",
      "5MG 1X",
      "1 , 5MG",
      "100MG 2X",
      "75MG 1X",
      "850MG 3X",
      "50 - 0 - 30",
      "93 , 5"
    ],
    "Conceito Temporal": [
      "ANTES",
      "HA 25 ANOS"
    ],
    "Procedimento Diagnóstico": [
      "ECG",
      "HD",
      "DOPPLER"
    ],
    "Resultado Laboratorial ou de Teste": [
      "SINUSAL",
      "ISQUEMIA SUBEPICARDICO LAT ALTA",
      "AREA INATIVA ANT-SEPTAL",
      "TSH 7 , 7",
      "HBA1C 10 , 1",
      "MICROALBUMINURIA 399",
      "CLCR 106",
      "CT 185",
      "TG 173",
      "CR 0 , 7",
      "HDL 41",
      "LDL 109",
      "VG 38",
      "LEUC 4750",
      "PQ 227",
      "PH 6 , 0"
    ],
    "Atributo Clínico": [
      "FC",
      "PESO",
      "PA"
    ],
    "Sinal ou Sintoma": [
      "RA",
      "EDEMA",
      "CONTROLE IRREGULAR",
      "PROTEINURIA NAO NEFROTICA"
    ],
    "Localização ou Região Corporal": [
      "ABDOMEN",
      "MMII"
    ],
    "Achado": [
      "NDN",
      "EX TABAGISTA",
      "CPP LIVRE"
    ],
    "Produto Intelectual": [
      "P"
    ],
    "Hormônio": [
      "INSULINA NPH",
      "INSULINA R"
    ]
  },
  "labels": {}
}