{
  "prontuario_id": 36,
  "text": "15:30h S: 15º DI por PO de ventriculostomia.   O : Glasgow 7, pupilas anisocóricas E > D. FO cefálica limpa e seca, DVE fechada, PIC em 10mmHg. Suporte de O2 sob TQT, aspiração de secreçãoe espessa amrelada. CPP com roncos difusos. Abdomem flácido, RHA+. Acesso venoso em MSE com infusão de soroterapia. SVD com diurese efetiva. Extremidades aquecidas, perfusão periférica adequada, edema em membros. Lesões de subcutâneo por fragilidade importenate. Uso de colchão de ar. Segue sob cuidadso intensivos.   # Realizado coleta de líquor pelo residente Ricardo, enacminhada amostra para análise.   A : Desobstrução ineficaz das vias aéreas; Integridade da pele prejudicada.   P : Conforme prescrição de enfermagem. Enfermeira Florence Nightingale. HIDROCEFALIA",
  "entities": {
    "Abreviação": [
      "S",
      "DI",
      "PO",
      "O",
      "FO",
      "PIC",
      "CPP",
      "RHA+",
      "MSE",
      "SVD",
      "A",
      "DVE fechada"
    ],
    "Achado": [
      "S",
      "limpa",
      "seca",
      "flácido",
      "RHA+",
      "diurese efetiva",
      "Extremidades aquecidas",
      "perfusão periférica adequada"
    ],
    "Conceito Temporal": [
      "DI",
      "PO"
    ],
    "Procedimento Terapêutico ou Preventivo": [
      "ventriculostomia",
      "aspiração",
      "SVD",
      "DVE fechada",
      "Suporte de O2",
      "Acesso venoso",
      "infusão de soroterapia",
      "colchão de ar"
    ],
    "Atividade de Assistência à Saúde": [
      "O",
      "Realizado",
      "enacminhada",
      "cuidadso intensivos",
      "prescrição de enfermagem"
    ],
    "Parte do Corpo, Órgão ou Componente Orgânico": [
      "pupilas",
      "CPP"
    ],
    "Lesão ou Envenenamento": [
      "FO",
      "Lesões de subcutâneo"
    ],
    "Localização ou Região Corporal": [
      "cefálica",
      "Abdomem",
      "MSE",
      "membros"
    ],
    "Atributo Clínico": [
      "PIC",
      "CPP"
    ],
    "Conceito Quantitativo": [
      "10mmHg"
    ],
    "Dispositivo Médico": [
      "SVD",
      "Acesso venoso",
      "colchão de ar"
    ],
    "Sinal ou Sintoma": [
      "edema",
      "Glasgow 7",
      "E &gt; D",
      "secreçãoe espessa amrelada",
      "roncos difusos",
      "fragilidade importenate",
      "Desobstrução ineficaz das vias aéreas",
      "Integridade da pele prejudicada"
    ],
    "Substância": [
      "amostra"
    ],
    "Procedimento Laboratorial": [
      "análise",
      "coleta de líquor"
    ],
    "Procedimento Diagnóstico": [
      "A"
    ],
    "Produto Intelectual": [
      "P"
    ],
    "Grupo Profissional ou Ocupacional": [
      "Enfermeira"
    ],
    "Doença ou Síndrome": [
      "HIDROCEFALIA"
    ],
    "Substância Corporal": [
      "secreçãoe espessa amrelada"
    ],
    "Função de Organismo": [
      "diurese efetiva"
    ],
    "Objeto Manufaturado": [
      "colchão de ar"
    ]
  },
  "labels": {}
}