{
  "prontuario_id": 808,
  "text": "07:40hs - Glasgow 8, pupilas isocóricas fotorreagentes, SNE com dieta a 50ml/h, traqueostomizada, em ventilação mecânica, modo PSV, Ps 16, PEEP 6, FiO2 45%, secreção traqueobrônquica amarela em média quantidade, acesso venoso central E com plano básico de hidratação, monitorizada, estável hemodinamicamente, MV global diminuído com roncos esparsos, MMSS edemaciados ++++/4, abdome globoso, flácido, indolor a palpação, RHA+, SVD com diurese efetiva, evacuação presente, úlcera grau III em região sacra, MMII edemaciados ++++/4, extremidades bem perfundidas, higienizada e mobilizada no leito, mantendo precauçãod e contato por Acinetobacter + Pseudomonas. Enfermeira Florence Nightingale.  EXAME GERAL E INVESTIGACAO DE PESSOAS SEM QUEIXAS OU DIAGNOSTICO RELATADO",
  "entities": {
    "Parte do Corpo, Órgão ou Componente Orgânico": [
      "pupilas"
    ],
    "Achado": [
      "isocóricas",
      "fotorreagentes",
      "traqueostomizada",
      "flácido",
      "RHA+",
      "higienizada",
      "estável hemodinamicamente",
      "indolor a palpação",
      "diurese efetiva",
      "evacuação presente",
      "extremidades bem perfundidas"
    ],
    "Dispositivo Médico": [
      "SNE",
      "SVD",
      "acesso venoso central E"
    ],
    "Procedimento Terapêutico ou Preventivo": [
      "SNE",
      "dieta",
      "traqueostomizada",
      "SVD",
      "ventilação mecânica",
      "plano básico de hidratação",
      "mobilizada no leito",
      "precauçãod e contato"
    ],
    "Abreviação": [
      "SNE",
      "Ps",
      "PEEP",
      "FiO2",
      "RHA+",
      "SVD",
      "modo PSV",
      "MV global diminuído",
      "MMSS edemaciados",
      "MMII edemaciados"
    ],
    "Alimento": [
      "dieta"
    ],
    "Conceito Quantitativo": [
      "50ml/h",
      "16",
      "6",
      "45%",
      "++++/4",
      "média quantidade"
    ],
    "Atributo Clínico": [
      "Ps",
      "PEEP",
      "FiO2",
      "modo PSV"
    ],
    "Atividade de Assistência à Saúde": [
      "monitorizada",
      "higienizada",
      "mantendo",
      "INVESTIGACAO DE PESSOAS"
    ],
    "Procedimento Diagnóstico": [
      "monitorizada",
      "EXAME GERAL",
      "INVESTIGACAO DE PESSOAS"
    ],
    "Localização ou Região Corporal": [
      "abdome",
      "região sacra"
    ],
    "Sinal ou Sintoma": [
      "globoso",
      "QUEIXAS",
      "Glasgow 8",
      "secreção traqueobrônquica amarela",
      "MV global diminuído",
      "roncos esparsos",
      "MMSS edemaciados",
      "MMII edemaciados"
    ],
    "Bactéria": [
      "Pseudomonas"
    ],
    "Grupo Profissional ou Ocupacional": [
      "Enfermeira"
    ],
    "Negação": [
      "SEM",
      "indolor a palpação"
    ],
    "Função de Organismo": [
      "diurese efetiva",
      "evacuação presente"
    ],
    "Doença ou Síndrome": [
      "úlcera grau III",
      "DIAGNOSTICO RELATADO"
    ]
  },
  "labels": {}
}