{
  "prontuario_id": 304,
  "text": "# 2 CX DE TROCA DE MITRAL + ATRIOSEPTOPLASTIA (2006)\n# FA PERMANENTE \n# 23/09/14:  PROTESE METALICA EM POSIÇÃO MITRAL NORMOFUNCIONANTE. VE APRESENTA DIMENSÕES NORMAIS COM FUNÇÃO SISTOLICA\nPRESERVADA. VENTRICULO DIREITO APRESENTA DIMENSÕES AUMENTADAS E FUNÇÃO SISTOLICA COMPROMETIDA DISCRETAMENTE.\nREGURGITAÇÃO TRICUSPIDE DISCRETA. PSAP ESTIMADA EM 45MMHG. ATRIO ESQUERDO E DIREITO DILATADOS. \n# MEDICAMENTOS EM USO:\nWARFARIM 5MG\nSELOKEN 100MG 12/12H\nPENICILINA BENZATINA 21/21 DIAS \n# PACIENTE NEGA DISPNEIA OU DOR, REFERE PALPITAÇÕES EVENTUAIS.\nSEM OUTRAS QUEIXAS NO PERIODO \n# AO EXAME :\nBEG, CORADA, HIDRATADA, LOTE, EUPNÉICA.\nMV + SEM RA. RITMO CARDÍACO IRREGULAR,\nACV : BULHAS NORMOFONÉTICAS, PRESENÇA DE ESTALIDO METÁLICO.\nFC 71\nPA 100/70\nFC : 97 \nCONDUTA : \n- retornoem 1 ano com edocardio\n \n \n \n ",
  "entities": {
    "Conceito Quantitativo": [
      "2",
      "45MMHG",
      "5MG",
      "71",
      "100/70",
      "97",
      "100MG 12/12H",
      "21/21 DIAS"
    ],
    "Procedimento Terapêutico ou Preventivo": [
      "ATRIOSEPTOPLASTIA",
      "CX DE TROCA DE MITRAL"
    ],
    "Abreviação": [
      "VE",
      "PSAP",
      "BEG",
      "LOTE",
      "RA",
      "ACV",
      "FC",
      "PA",
      "edocardio",
      "CX DE TROCA DE MITRAL",
      "FA PERMANENTE",
      "MV +"
    ],
    "Parte do Corpo, Órgão ou Componente Orgânico": [
      "VE",
      "VENTRICULO DIREITO",
      "ATRIO ESQUERDO E DIREITO"
    ],
    "Atributo Clínico": [
      "PSAP",
      "ACV",
      "FC",
      "PA"
    ],
    "Sinal ou Sintoma": [
      "DILATADOS",
      "DISPNEIA",
      "DOR",
      "QUEIXAS",
      "RA",
      "DIMENSÕES AUMENTADAS",
      "FUNÇÃO SISTOLICA COMPROMETIDA DISCRETAMENTE",
      "REGURGITAÇÃO TRICUSPIDE DISCRETA",
      "RITMO CARDÍACO IRREGULAR"
    ],
    "Substância Farmacológica": [
      "MEDICAMENTOS",
      "WARFARIM",
      "SELOKEN",
      "PENICILINA BENZATINA"
    ],
    "Paciente ou Grupo com Deficiência": [
      "PACIENTE"
    ],
    "Negação": [
      "NEGA",
      "SEM"
    ],
    "Conceito Temporal": [
      "EVENTUAIS",
      "PERIODO",
      "1 ano"
    ],
    "Atividade de Assistência à Saúde": [
      "EXAME",
      "CONDUTA",
      "retornoem"
    ],
    "Achado": [
      "BEG",
      "CORADA",
      "HIDRATADA",
      "LOTE",
      "EUPNÉICA",
      "POSIÇÃO MITRAL NORMOFUNCIONANTE",
      "DIMENSÕES NORMAIS",
      "FUNÇÃO SISTOLICA PRESERVADA",
      "MV +",
      "BULHAS NORMOFONÉTICAS",
      "PRESENÇA DE ESTALIDO METÁLICO"
    ],
    "Procedimento Diagnóstico": [
      "ACV",
      "edocardio"
    ],
    "Grupo Profissional ou Ocupacional": [
      "edocardio"
    ],
    "Doença ou Síndrome": [
      "FA PERMANENTE"
    ],
    "Dispositivo Médico": [
      "PROTESE METALICA"
    ],
    "Função Patológica": [
      "DIMENSÕES AUMENTADAS"
    ],
    "Antibiótico": [
      "PENICILINA BENZATINA"
    ]
  },
  "labels": {}
}