{
  "prontuario_id": 943,
  "text": "Lucas, 43 anos \nPaciente refere dispneia aos mínimos esforços com piora progressiva, ortopneia, roncos noturnos, edema de MMII. Relata o aparecimento de angina há mais ou menos 3 meses, aos mínimos esforços.\nCx bariátrica há 1 ano e meio, 3 episódios de internamento por edema agudo de pulmão, última sendo em Agosto de 2014. Paciente hipertenso, portador de ICC, hérnia de hiato. Em uso de enalapril 10mg 12/12h, carvedilol 12,5mg 12/12h, furosemida 40mg 12/12h, espironolactona 25mg 12/12h, apresolina 25mg, 12/12h, monocordil 20mg 12/12h, warfarina 50mg 1 comprimido por dia.\nEx fumante, fumou 27 anos em media de 2 carteiras por dia.  \nEletro 13/05/2014: fibrilação atrial, hipertrofia ventricular esquerda, alterações difusas de repolarização ventricular.\nEcocardiograma 6/05/2014: importante aumento das dimensões do ventriculo esquerdo, espessura normal, disfunção sistolica global moderada por hipocinesia difusa com FE 41%. Aumento das dimensões do atrio direito e esquerdo, estenose aortica de grau leve, insuficiencia aortica de grau leve, insuf mitral de grau leve, pressao sistolica pulmonar de 20mmHg.\nCateterismo não evidencia doença coronariana importante\nLaboratorio 13/08/2014\nCreatinina 0,98\nGlic jejum 90\nPCR nao reag\nTAP 23,6\nConduta: paciente encaminhado à UDT para compensação da ICC. Retorno após internamento\n \n \n \n ",
  "entities": {
    "Paciente ou Grupo com Deficiência": [
      "Paciente",
      "paciente"
    ],
    "Sinal ou Sintoma": [
      "ortopneia",
      "angina",
      "dispneia aos mínimos esforços",
      "piora progressiva",
      "roncos noturnos",
      "aos mínimos esforços",
      "hipertrofia ventricular esquerda"
    ],
    "Localização ou Região Corporal": [
      "MMII"
    ],
    "Conceito Quantitativo": [
      "3",
      "10mg",
      "40mg",
      "25mg",
      "20mg",
      "50mg",
      "12 , 5mg",
      "1 comprimido",
      "2 carteiras por dia"
    ],
    "Atividade de Assistência à Saúde": [
      "internamento",
      "Conduta",
      "encaminhado",
      "Retorno",
      "compensação da ICC"
    ],
    "Doença ou Síndrome": [
      "hipertenso",
      "ICC",
      "edema agudo de pulmão",
      "fibrilação atrial"
    ],
    "Abreviação": [
      "ICC",
      "Eletro",
      "UDT",
      "Cx bariátrica",
      "disfunção sistolica global moderada por hipocinesia difusa",
      "FE 41%",
      "insuf mitral de grau leve",
      "Creatinina 0 , 98",
      "Glic jejum 90",
      "PCR nao reag",
      "TAP 23 , 6",
      "compensação da ICC"
    ],
    "Aminoácido, Peptídeo ou Proteína": [
      "enalapril"
    ],
    "Substância Farmacológica": [
      "enalapril",
      "carvedilol",
      "furosemida",
      "espironolactona",
      "apresolina",
      "monocordil",
      "warfarina"
    ],
    "Conceito Temporal": [
      "12/12h",
      "dia",
      "há mais ou menos 3 meses",
      "há 1 ano e meio",
      "27 anos"
    ],
    "Substância Química Orgânica": [
      "carvedilol",
      "furosemida",
      "espironolactona",
      "apresolina",
      "monocordil",
      "warfarina"
    ],
    "Substância Perigosa ou Venenosa": [
      "warfarina"
    ],
    "Procedimento Diagnóstico": [
      "Eletro",
      "Ecocardiograma",
      "Cateterismo"
    ],
    "Procedimento Terapêutico ou Preventivo": [
      "Cateterismo",
      "Cx bariátrica",
      "compensação da ICC"
    ],
    "Negação": [
      "não"
    ],
    "Procedimento Laboratorial": [
      "Laboratorio"
    ],
    "Organização Relacionada à Saúde": [
      "UDT"
    ],
    "Anormalidade Anatômica": [
      "hérnia de hiato"
    ],
    "Achado": [
      "Ex fumante"
    ],
    "Resultado Laboratorial ou de Teste": [
      "fibrilação atrial",
      "hipertrofia ventricular esquerda",
      "alterações difusas de repolarização ventricular",
      "importante aumento das dimensões do ventriculo esquerdo",
      "espessura normal",
      "disfunção sistolica global moderada por hipocinesia difusa",
      "FE 41%",
      "Aumento das dimensões do atrio direito e esquerdo",
      "estenose aortica de grau leve",
      "insuficiencia aortica de grau leve",
      "insuf mitral de grau leve",
      "pressao sistolica pulmonar de 20mmHg",
      "evidencia doença coronariana importante",
      "Creatinina 0 , 98",
      "Glic jejum 90",
      "PCR nao reag",
      "TAP 23 , 6"
    ]
  },
  "labels": {}
}