{
  "prontuario_id": 724,
  "text": "Lucas 32 ANOS \nDM DESDE 14 ANOS\nDRC ESTAGIO FINAL , PRÉ TRS - CLEARANCE DE CR 12ML/MIN\nHAS HÁ 2 ANOS, \nNEFROPATIA DIABÉTICA E RETINOPATIA DIABÉTICA\nNEGA CARDIOPATIAS, DOENÇAS DE TIREÓIDE OU OUTRAS\nG 2 C 1 P 1 PFANESTIAL\nEM TRATAMENTO CONSERVADOR, COM PLANEJAMENTO DE TRANSPLANTE PRÉ - EMPTIVO\nEM USO DE INSULINA, EPO, LOSARTANA, ANLODIPINO, NORIPURUM\nNEGA TABAGISMO\nPESO 47 ALT 156\nPA 180/100\nMUCOSAS HIPOCORADAS\nPC > TAQUICARDIA\nCPP LIVRES\nABDOME FLACIDO, RHA+, SEM VCM\nMEMBROS EDEMA EM MIDIREITO, PULSOS PERIFERICOS PRESENTES E DIMINUIDOS A DIREITA \nPACIENTE DM , DRC TERMINAL \nTRANSPLANTE RENLA PRÉEMPTIVO \nLIBERADO PARA CIRURGIA \nRISCO ASA 2\nHOJE > AVALIAÇÃO ANESTESIO\nOBS EXAMES SERÃO REPETIDOS NO DIA ANTERIOR AO PROCEDIMENTO\nMS; PRED / FK E INDUÇÃO ATG\nABO  B PRA 76,2MM DSA ECOCARDIO DE STRESS NEGATIVO \nECOGRAFIA ABDOME RINS COM SINAIS NEFROPATIA CRONICA\nECG SINUSAL\nRX DE TORAX NORMAL\n ",
  "entities": {
    "Abreviação": [
      "DM",
      "HAS",
      "EPO",
      "ALT",
      "PA",
      "PC",
      "RHA+",
      "VCM",
      "MIDIREITO",
      "ANESTESIO",
      "MS",
      "PRED",
      "FK",
      "2MM",
      "DSA",
      "ECG",
      "DRC ESTAGIO FINAL",
      "CLEARANCE DE CR 12ML/MIN",
      "CPP LIVRES",
      "DRC TERMINAL",
      "INDUÇÃO ATG",
      "PRA 76",
      "ECOCARDIO DE STRESS",
      "RX DE TORAX"
    ],
    "Doença ou Síndrome": [
      "DM",
      "HAS",
      "CARDIOPATIAS",
      "TABAGISMO",
      "DRC ESTAGIO FINAL",
      "NEFROPATIA DIABÉTICA",
      "RETINOPATIA DIABÉTICA",
      "DOENÇAS DE TIREÓIDE",
      "DRC TERMINAL"
    ],
    "Conceito Temporal": [
      "PRÉ",
      "DIA ANTERIOR"
    ],
    "Procedimento Terapêutico ou Preventivo": [
      "TRS",
      "C",
      "P",
      "PFANESTIAL",
      "CIRURGIA",
      "PROCEDIMENTO",
      "TRATAMENTO CONSERVADOR",
      "TRANSPLANTE RENLA PRÉEMPTIVO",
      "INDUÇÃO ATG"
    ],
    "Negação": [
      "NEGA",
      "SEM"
    ],
    "Atributo Clínico": [
      "G",
      "PESO",
      "ALT",
      "PA",
      "PC",
      "PULSOS PERIFERICOS"
    ],
    "Conceito Quantitativo": [
      "2",
      "1",
      "156",
      "180/100"
    ],
    "Atividade de Assistência à Saúde": [
      "PLANEJAMENTO",
      "LIBERADO",
      "AVALIAÇÃO"
    ],
    "Aminoácido, Peptídeo ou Proteína": [
      "INSULINA"
    ],
    "Hormônio": [
      "INSULINA",
      "PRED"
    ],
    "Substância Química Orgânica": [
      "INSULINA",
      "EPO",
      "LOSARTANA",
      "ANLODIPINO",
      "MS",
      "PRED",
      "FK"
    ],
    "Substância Farmacológica": [
      "INSULINA",
      "EPO",
      "LOSARTANA",
      "ANLODIPINO",
      "NORIPURUM",
      "MS",
      "PRED",
      "FK"
    ],
    "Sinal ou Sintoma": [
      "TAQUICARDIA",
      "VCM",
      "EDEMA",
      "MUCOSAS HIPOCORADAS",
      "DIMINUIDOS A DIREITA"
    ],
    "Localização ou Região Corporal": [
      "ABDOME",
      "MEMBROS"
    ],
    "Achado": [
      "FLACIDO",
      "RHA+",
      "PRESENTES",
      "CPP LIVRES",
      "ABO B"
    ],
    "Função Patológica": [
      "EDEMA"
    ],
    "Paciente ou Grupo com Deficiência": [
      "PACIENTE"
    ],
    "Grupo Profissional ou Ocupacional": [
      "ANESTESIO"
    ],
    "Procedimento Diagnóstico": [
      "EXAMES",
      "ECG",
      "ECOCARDIO DE STRESS",
      "ECOGRAFIA ABDOME",
      "RX DE TORAX"
    ],
    "Procedimento Laboratorial": [
      "EXAMES"
    ],
    "Resultado Laboratorial ou de Teste": [
      "NEGATIVO",
      "SINUSAL",
      "NORMAL",
      "CLEARANCE DE CR 12ML/MIN",
      "PRA 76",
      "RINS COM SINAIS NEFROPATIA CRONICA"
    ],
    "Classificação": [
      "ASA 2"
    ]
  },
  "labels": {}
}