{
  "prontuario_id": 787,
  "text": "Aparecida 45 anos Natural de Goioere/PR Morou proximo a Cascavel/PR Procedente de Curitiba\nMCP dilatada de etiologia a esclarecer\nTE ALTERADO 2014\n21-5-14 ECOESTRESS NEGATIVO\n21-5-15 FE 35 EP 17 AE 38\nFÇAO SISTOLICA COMPROMETIDA HIPOCINESIA DIFUSA REG MI DISCRETA\nDOR TIPICA AOS ESFORÇOS , AOS ESTADO ANSIOSOS\nCINTILO 14-2-15 T5E POSITIVO POR ALT CLINICO ECG DE ISQUEMIA\nISQUEMIA PEQUENA EXTENSAO PAREDE INFERIOR VE FE 34-46%\nCATETERISMO CARDIACO (02/06/15): TORTUOSIDADES CORONARIANAS.\nECO TT (03/03/16): FE 66%, NORMAL\nECG (30/09/15): RS ADRV\nHDP : Nega patologias previas\nNega tabagismo\nNega etilismo\nNega uso de drogas ilicitas\nHF: PAI, avó e tios cardiopatas\nMedicamentos em uso: Carvedilol, AAS, ENALAPRIL 10 MG 12/12\nAO EXAME : FC 70 BPM PA 120/80 MMHG\nACV : RCR EM 2T\nAP : MV+ ARA\nPANTURRILHAS LIVRES, SEM EDEMAS\n\nCD : MANTENHO CARVEDILOL E ENALAPRIL. RETORNO EM 01 ANO COM NOVO ECO TT\n \n \n \n ",
  "entities": {
    "Abreviação": [
      "TE",
      "CINTILO",
      "T5E",
      "ECG",
      "RS",
      "ADRV",
      "HDP",
      "HF",
      "AAS",
      "FC",
      "PA",
      "ACV",
      "AP",
      "MV+",
      "ARA",
      "CD",
      "MCP dilatada",
      "FE 35",
      "EP 17",
      "AE 38",
      "FÇAO SISTOLICA COMPROMETIDA",
      "POSITIVO POR ALT CLINICO",
      "ECG DE ISQUEMIA",
      "ISQUEMIA PEQUENA EXTENSAO PAREDE INFERIOR VE",
      "FE 34-46%",
      "ECO TT",
      "FE 66%",
      "RCR EM 2T"
    ],
    "Procedimento Diagnóstico": [
      "TE",
      "CINTILO",
      "T5E",
      "ECG",
      "EXAME",
      "AP",
      "ECG DE ISQUEMIA",
      "CATETERISMO CARDIACO",
      "ECO TT"
    ],
    "Resultado Laboratorial ou de Teste": [
      "ALTERADO",
      "NORMAL",
      "RS",
      "ADRV",
      "ECOESTRESS NEGATIVO",
      "FE 35",
      "EP 17",
      "AE 38",
      "FÇAO SISTOLICA COMPROMETIDA",
      "HIPOCINESIA DIFUSA",
      "POSITIVO POR ALT CLINICO",
      "ISQUEMIA PEQUENA EXTENSAO PAREDE INFERIOR VE",
      "FE 34-46%",
      "TORTUOSIDADES CORONARIANAS",
      "FE 66%"
    ],
    "Sinal ou Sintoma": [
      "REG",
      "ANSIOSOS",
      "ARA",
      "EDEMAS",
      "DISCRETA DOR TIPICA AOS ESFORÇOS"
    ],
    "Localização ou Região Corporal": [
      "MI",
      "ACV",
      "AP"
    ],
    "Achado": [
      "HDP",
      "HF",
      "cardiopatas",
      "MV+",
      "ARA",
      "etiologia a esclarecer",
      "uso de drogas ilicitas",
      "RCR EM 2T",
      "PANTURRILHAS LIVRES"
    ],
    "Atividade de Assistência à Saúde": [
      "HDP",
      "RETORNO EM 01 ANO"
    ],
    "Negação": [
      "Nega",
      "ARA",
      "SEM"
    ],
    "Doença ou Síndrome": [
      "patologias",
      "tabagismo",
      "etilismo",
      "MCP dilatada",
      "uso de drogas ilicitas"
    ],
    "Conceito Temporal": [
      "previas",
      "12/12"
    ],
    "Grupo Familiar": [
      "PAI",
      "avó",
      "tios"
    ],
    "Anormalidade Adquirida": [
      "cardiopatas"
    ],
    "Substância Farmacológica": [
      "Medicamentos",
      "Carvedilol",
      "AAS",
      "ENALAPRIL",
      "CARVEDILOL"
    ],
    "Substância Química Orgânica": [
      "Carvedilol",
      "AAS",
      "ENALAPRIL"
    ],
    "Atributo Clínico": [
      "FC",
      "PA"
    ],
    "Sistema Corporal": [
      "ACV"
    ],
    "Produto Intelectual": [
      "CD"
    ],
    "Procedimento Terapêutico ou Preventivo": [
      "CATETERISMO CARDIACO"
    ],
    "Conceito Quantitativo": [
      "10 MG",
      "70 BPM",
      "120/80 MMHG"
    ]
  },
  "labels": {}
}