{
  "prontuario_id": 438,
  "text": "Lucas, 21 anos \nCx Ross 03/06/2015 ( Valva aórtica biscúspide com refluxo moderado ) \nUso: AAS 100 - 1xd; selozok 25; Enalapril 10 - 1xd.\nPaciente sem queixas. \nAguarda eco de controle \nNega dispneia; dor toracica qdo tosse,sem edema mmii. Nega ainda palpitação.\nTosee seca.\nTrouxe exames\nHb 14,5 / Leuc 10770 / Pla 274.000\ncr 0,7 / Ur 21\nK 4,5\nHaptoglobiina 165 / Cont reticulocitos 1,4%, LDH 503\nEx Fisico: BEG, eupneico, acianotico, anicterico, sem edema mmii. \nPA : 120x90mmHg, P = 83 spm, FR = 12 rpm.\nMV normodist sem ruidosd adv, RCR, 2T, BNF ss + / 6 + FA o e P.\nFerida operatorio boma specto, com torax estavel, sem creptação.\nA # PO Cx Ross\nMantenho medicações. Retorno em 2 meses com lbs. Aguardo ecocardio\nE3 cardio Doutor Vital Brazil ",
  "entities": {
    "Função Patológica": [
      "refluxo",
      "edema",
      "FA"
    ],
    "Conceito Qualitativo": [
      "moderado"
    ],
    "Abreviação": [
      "AAS",
      "mmii",
      "BEG",
      "PA",
      "P",
      "FR",
      "RCR",
      "2T",
      "BNF",
      "ss",
      "FA",
      "A",
      "PO",
      "lbs",
      "ecocardio",
      "cardio",
      "Cx Ross",
      "dor toracica qdo tosse",
      "Hb 14 , 5",
      "Leuc 10770",
      "Pla 274",
      "cr 0 , 7",
      "Ur 21",
      "K 4 , 5",
      "Cont reticulocitos 1 , 4%",
      "Ex Fisico",
      "MV normodist",
      "ruidosd adv"
    ],
    "Substância Farmacológica": [
      "AAS",
      "selozok",
      "Enalapril",
      "medicações"
    ],
    "Substância Química Orgânica": [
      "AAS",
      "Enalapril"
    ],
    "Conceito Quantitativo": [
      "100",
      "1xd",
      "25",
      "10",
      "120x90mmHg",
      "83 spm",
      "12 rpm"
    ],
    "Conceito Temporal": [
      "1xd",
      "PO"
    ],
    "Paciente ou Grupo com Deficiência": [
      "Paciente"
    ],
    "Negação": [
      "sem",
      "Nega",
      "acianotico",
      "anicterico",
      "ss"
    ],
    "Sinal ou Sintoma": [
      "queixas",
      "dispneia",
      "edema",
      "palpitação",
      "creptação",
      "dor toracica qdo tosse",
      "Tosee seca",
      "ruidosd adv"
    ],
    "Achado": [
      "Aguarda",
      "BEG",
      "eupneico",
      "acianotico",
      "anicterico",
      "RCR",
      "2T",
      "BNF",
      "ss",
      "MV normodist",
      "boma specto",
      "torax estavel"
    ],
    "Procedimento Diagnóstico": [
      "eco",
      "exames",
      "A",
      "lbs",
      "ecocardio",
      "Ex Fisico"
    ],
    "Localização ou Região Corporal": [
      "mmii"
    ],
    "Resultado Laboratorial ou de Teste": [
      "exames",
      "Hb 14 , 5",
      "Leuc 10770",
      "Pla 274",
      "cr 0 , 7",
      "Ur 21",
      "K 4 , 5",
      "Haptoglobiina 165",
      "Cont reticulocitos 1 , 4%",
      "LDH 503"
    ],
    "Atributo Clínico": [
      "PA",
      "P",
      "FR"
    ],
    "Doença ou Síndrome": [
      "FA"
    ],
    "Procedimento Terapêutico ou Preventivo": [
      "Cx Ross"
    ],
    "Parte do Corpo, Órgão ou Componente Orgânico": [
      "Valva aórtica biscúspide"
    ],
    "Atividade de Assistência à Saúde": [
      "Ex Fisico",
      "Retorno em 2 meses"
    ],
    "Lesão ou Envenenamento": [
      "Ferida operatorio"
    ]
  },
  "labels": {}
}