{
  "prontuario_id": 840,
  "text": "# sem queixas\n# chagas\n# acompanha na cardio geral e esta aguardando consulta\n# faço receita conforme já utiliza pois está com dificuldade de conseguir os medicamentos - mas não faltar cardio\nmp camara dupla\n# programado em modo ddd 60-50\n# ritmo proprio = bav com escape ventricular\n# 97% em vat\n# bat = ok \n# para eri = 10 MESES !!!!\n# A - imp = 395, sense = 5,3, cla = menor que 1,0 x 0,4\n# v - imp = 381, sense = mAIor que 10, clv = menor que 1,0 x 2,4\n# cd = programação mantida + retorno em 6 meses ( devido a bateria !!!!!! demais ok !!!! pcte ciente ) ou se intercorrencias = procura direta + não faltar cardio.\n ",
  "entities": {
    "Negação": [
      "sem",
      "não"
    ],
    "Sinal ou Sintoma": [
      "queixas",
      "dificuldade",
      "intercorrencias",
      "bav com escape ventricular"
    ],
    "Doença ou Síndrome": [
      "chagas"
    ],
    "Atividade de Assistência à Saúde": [
      "consulta",
      "receita",
      "cd"
    ],
    "Produto Intelectual": [
      "receita"
    ],
    "Substância Farmacológica": [
      "medicamentos"
    ],
    "Abreviação": [
      "cardio",
      "cd",
      "pcte",
      "cardio geral",
      "mp camara dupla",
      "bav com escape ventricular",
      "97% em vat",
      "bat = ok",
      "para eri = 10 MESES",
      "imp = 395",
      "sense = 5 , 3",
      "cla = menor que 1 , 0",
      "imp = 381",
      "sense = mAIor que 10",
      "clv = menor que 1"
    ],
    "Grupo Profissional ou Ocupacional": [
      "cardio",
      "cardio geral"
    ],
    "Paciente ou Grupo com Deficiência": [
      "pcte"
    ],
    "Organização Relacionada à Saúde": [
      "cardio geral"
    ],
    "Procedimento Terapêutico ou Preventivo": [
      "mp camara dupla"
    ],
    "Conceito Qualitativo": [
      "modo ddd 60-50"
    ],
    "Achado": [
      "ritmo proprio",
      "programação mantida",
      "procura direta"
    ],
    "Resultado Laboratorial ou de Teste": [
      "bav com escape ventricular",
      "97% em vat",
      "bat = ok",
      "para eri = 10 MESES",
      "imp = 395",
      "sense = 5 , 3",
      "imp = 381",
      "sense = mAIor que 10"
    ]
  },
  "labels": {}
}