{
  "prontuario_id": 296,
  "text": "PACIENTE COM QUEIXA DE PALPITAÇÃO, RELATA TRÊS CRISES; A PRIMEIRA FOI 1 ANO ATRÁS A ÚLTIMA HÁ DOIS MESES. A ÚLTIMA TEVE DURAÇÃO MAIOR ( DUAS HORAS ) E SINTOMAS MAIS EXACERBADOS ASSOCIADOS ( DISPNEIA, DOR RETROESTERNAL EM APERTO E NÁUSEA ); DISPNEIA AOS MÉDIOS ESFORÇOS, ASSOCIADO A QUEIMAÇÃO NO PESCOÇO.\nHAS EM USO DE ATENOLOL 25 MG (3 VEZES POR DIA ).\nGASTRITE EM USO DE DOMPERIDONA E RANITIDINA.\nEX-TABAGISTA PAROU HÁ 22 ANOS.\nMÃE FALECEU DE IAM.\nECOCARDIO 04/10/14: DENTRO DOS LIMITES DA NORMALIDADE.\nECG DE REPOUSO 12/09/14: TAQUICARDIA PAROXÍSTICA SUPRA VENTRICULAR.\nFC: 68 BPM.\nPA: 140/100 MMHG.\nAUSCULTA PULMONAR: MV PRESENTE BILATERALMENTE, SEM RA.\nAUSCULTA CARDÍACA: BCRNF.\nMMII COM EDEMA +/4+.\nSOLICITADO NOVO ECG E RETORNO EM 2 MESES.\n \n \n \n ",
  "entities": {
    "Paciente ou Grupo com Deficiência": [
      "PACIENTE"
    ],
    "Achado": [
      "ASSOCIADOS",
      "EX-TABAGISTA",
      "PAROU",
      "FALECEU",
      "BCRNF",
      "MV PRESENTE"
    ],
    "Sinal ou Sintoma": [
      "DISPNEIA",
      "NÁUSEA",
      "QUEIMAÇÃO",
      "RA",
      "EDEMA",
      "QUEIXA DE PALPITAÇÃO",
      "DURAÇÃO MAIOR",
      "SINTOMAS MAIS EXACERBADOS",
      "DOR RETROESTERNAL",
      "DISPNEIA AOS MÉDIOS ESFORÇOS"
    ],
    "Parte do Corpo, Órgão ou Componente Orgânico": [
      "PESCOÇO",
      "MMII"
    ],
    "Abreviação": [
      "HAS",
      "IAM",
      "ECOCARDIO",
      "FC",
      "PA",
      "RA",
      "BCRNF",
      "MMII",
      "ECG",
      "ECG DE REPOUSO",
      "MV PRESENTE"
    ],
    "Doença ou Síndrome": [
      "HAS",
      "GASTRITE",
      "IAM"
    ],
    "Substância Química Orgânica": [
      "ATENOLOL",
      "DOMPERIDONA",
      "RANITIDINA"
    ],
    "Substância Farmacológica": [
      "ATENOLOL",
      "DOMPERIDONA",
      "RANITIDINA"
    ],
    "Grupo Familiar": [
      "MÃE"
    ],
    "Procedimento Diagnóstico": [
      "ECOCARDIO",
      "ECG",
      "ECG DE REPOUSO",
      "AUSCULTA PULMONAR",
      "AUSCULTA CARDÍACA"
    ],
    "Atributo Clínico": [
      "FC",
      "PA"
    ],
    "Conceito Espacial": [
      "BILATERALMENTE"
    ],
    "Negação": [
      "SEM"
    ],
    "Função Patológica": [
      "EDEMA"
    ],
    "Resultado Laboratorial ou de Teste": [
      "+/4+",
      "DENTRO DOS LIMITES DA NORMALIDADE",
      "TAQUICARDIA PAROXÍSTICA SUPRA VENTRICULAR"
    ],
    "Atividade de Assistência à Saúde": [
      "SOLICITADO"
    ],
    "Conceito Quantitativo": [
      "TRÊS CRISES",
      "25 MG",
      "68 BPM",
      "140/100 MMHG"
    ],
    "Conceito Qualitativo": [
      "EM APERTO"
    ],
    "Conceito Temporal": [
      "3 VEZES POR DIA",
      "HÁ 22 ANOS"
    ]
  },
  "labels": {}
}