{
  "prontuario_id": 531,
  "text": "Lucas,57 anos\nHomoenxerto aortico ( por EAo ) + MIE - DA; RAD - CD; SAF - MG em 2006.\nHipertenso.\nEm uso de: AAS 100 mg dia, losartana 100 mg dia, atovastatina 20 mg 2 cp / dia ( prescrito 80mg / d, porém está usando somente 40mg / d por falta da medicação na saúde há 20 dias ), atenolol 25mg / dia, furosemida 40mg / dia, omeoprazol 40mg ao dia, ezatimibe 10 mg, Hidantal 100mg - por cisticercose.\nPenicilina G benzatina 1,200,000U IM a cada 21 dia - suspenso em 2013.\nExames:\nEcocardiograma - 26/06/2013: Homoenxerto em posição aórtica normofuncionante. VE hipertrofiado com dimensões normais e fumção sistólica preservada. ALteração do relaxamento do VE. AE dilatado. Homoenxerto com mobilidade adequada. FE: 66%.\n- Lab (05/02/15): Cr 0,91, CT 174, TGC 197, HDL 44, K 4,8, LDL 90, Glic 107.\nS #  Pte relata dor em ponto específico paraesternal, sem relação com esforço físico e com duração de horas, sintoma existente desde a cx, sem piora desde então. Nega dor precordial. \nAo exame:\nPte em BEG, eupneico, corado, hidratado.\nFC: 64; PA: 120/70.\nCP: sem estase jugular.\nAC: BCRNF sem sopros.\nAP: MV presente bilateralmente, sem RA.\nA # ICO crônica.\nP # Retorno em 6 meses com eco + lab  ( incluindo TTOG e Hb glicada ). Reforço MEV.\n \n \n \n ",
  "entities": {
    "Abreviação": [
      "EAo",
      "MIE",
      "DA",
      "RAD",
      "CD",
      "SAF",
      "MG",
      "AAS",
      "IM",
      "Lab",
      "Pte",
      "cx",
      "BEG",
      "FC",
      "PA",
      "CP",
      "AC",
      "BCRNF",
      "AP",
      "RA",
      "eco",
      "lab",
      "TTOG",
      "VE hipertrofiado",
      "ALteração do relaxamento do VE",
      "AE dilatado",
      "FE : 66%",
      "Cr 0 , 91",
      "CT 174",
      "TGC 197",
      "Glic 107",
      "MV presente bilateralmente",
      "ICO crônica",
      "Hb glicada"
    ],
    "Doença ou Síndrome": [
      "EAo",
      "Hipertenso",
      "cisticercose",
      "ICO crônica"
    ],
    "Parte do Corpo, Órgão ou Componente Orgânico": [
      "MIE",
      "DA",
      "RAD",
      "CD",
      "SAF",
      "MG"
    ],
    "Substância Farmacológica": [
      "AAS",
      "losartana",
      "atovastatina",
      "atenolol",
      "furosemida",
      "omeoprazol",
      "ezatimibe",
      "Hidantal"
    ],
    "Substância Química Orgânica": [
      "AAS",
      "losartana",
      "atenolol",
      "furosemida",
      "omeoprazol",
      "Penicilina G benzatina"
    ],
    "Atividade de Assistência à Saúde": [
      "prescrito",
      "suspenso",
      "Retorno"
    ],
    "Organização Relacionada à Saúde": [
      "saúde"
    ],
    "Conceito Quantitativo": [
      "100mg",
      "64",
      "120/70",
      "100 mg",
      "10 mg",
      "1 , 200 , 000U"
    ],
    "Conceito Funcional": [
      "IM"
    ],
    "Procedimento Diagnóstico": [
      "Ecocardiograma",
      "exame",
      "CP",
      "AC",
      "AP",
      "eco"
    ],
    "Achado": [
      "normofuncionante",
      "piora",
      "BEG",
      "eupneico",
      "corado",
      "hidratado",
      "BCRNF",
      "falta da medicação",
      "fumção sistólica preservada",
      "Homoenxerto com mobilidade adequada",
      "MV presente bilateralmente"
    ],
    "Resultado Laboratorial ou de Teste": [
      "Lab",
      "lab",
      "VE hipertrofiado",
      "dimensões normais",
      "fumção sistólica preservada",
      "ALteração do relaxamento do VE",
      "AE dilatado",
      "FE : 66%",
      "Cr 0 , 91",
      "CT 174",
      "TGC 197",
      "HDL 44",
      "K 4 , 8",
      "LDL 90",
      "Glic 107"
    ],
    "Procedimento Laboratorial": [
      "Lab",
      "lab",
      "TTOG",
      "Hb glicada"
    ],
    "Sinal ou Sintoma": [
      "dor",
      "sintoma",
      "sopros",
      "RA",
      "dor precordial",
      "estase jugular"
    ],
    "Negação": [
      "sem",
      "Nega"
    ],
    "Conceito Temporal": [
      "desde",
      "cada 21 dia",
      "duração de horas"
    ],
    "Procedimento Terapêutico ou Preventivo": [
      "cx",
      "Homoenxerto aortico"
    ],
    "Atributo Clínico": [
      "FC",
      "PA"
    ],
    "Antibiótico": [
      "Penicilina G benzatina"
    ],
    "Anormalidade Adquirida": [
      "VE hipertrofiado",
      "AE dilatado"
    ],
    "Localização ou Região Corporal": [
      "ponto específico paraesternal"
    ],
    "Função de Organismo": [
      "esforço físico"
    ]
  },
  "labels": {}
}