{
  "prontuario_id": 617,
  "text": "# QP: PACIENTE REFERE CEGUEIRA TOTAL DE OD E QUE ENXERGA APENAS VULTOS COM O OE ( NEGA DIMINUIÇÃO DA AV DE OE NOS ULTIMOS 6 MESES ). FAZ ACOMPANHAMENTO OFTALMOLOGICO NO HC. SOLICITA LENTE ESCLERAL PARA OD\n# HMA: QUEIXA-SE TAMBEM DE LACRIMEJAMENTO, PRURIDO E ARDENCIA EM OD. NÃO FAZ USO DE ÓCULOS NEM COLÍRIO.\n# HMP: DM HÁ 10 ANOS EM USO DE INSULINA, RENAL CRONICA AGUARDANDO TX RENAL. REFERE TRAUMA OCULAR HÁ 7 ANOS. REFERE TER REALIZADO VARIAS CIRURGIAS EM AO NO SERVIÇO OFTALMOLOGICO DO HC. \n# HMF: NEGA HISTORICO FAMILIAR DE GLAUCOMA, ESTRABISMO OU CEGUEIRA; \n# EX FISICO:\n- AV: OD: SPL\n\tOEE: 20 / 400\n- ESQ: AO: SEM REFLEXO\n- TOL: AO: NÃO MELHORA\n-  BIO: OD: MICROOFTALMIA, CATARATA BRANCA COM SINEQUIA POSTERIOR 360o; PIGMENTAÇÃO EM CRISTALINO. CA RASA E FORMADA, CÓRNE FLUOR NEGATIVA; OE: LIO TOPICA; OPACIDADE POSTERIOR E MARCAS DE YAG LASER EM EIXO CENTRAL\n- FO\tOD: DIFICIL VISUALIZAÇÃO POR OPACIDADE DE MEIOS; OE: VASOS POST VIZUALIZADA COM OPACIDADE VITREA; Doutor Vital Brazil ?\n# CONDUTA: ENTREGO SOLICITAÇÃO PARA NOVA LENTE ESCLERAL E ENCAMINHO PACIENTE PARA O SERVIÇO NO QUAL JÁ ESTA REALIZANDO ACOMPANHAMENTO. \nR1 Vital Brasil\nR2 Vital Brasil\n \n \n \n ",
  "entities": {
    "Sinal ou Sintoma": [
      "QP",
      "QUEIXA-SE",
      "LACRIMEJAMENTO",
      "PRURIDO",
      "SPL",
      "CEGUEIRA TOTAL DE OD",
      "VULTOS COM O OE",
      "ARDENCIA EM OD",
      "20 / 400"
    ],
    "Abreviação": [
      "QP",
      "DM",
      "AO",
      "AV",
      "OD",
      "SPL",
      "OEE",
      "ESQ",
      "TOL",
      "BIO",
      "OE",
      "FO",
      "R1",
      "R2",
      "CEGUEIRA TOTAL DE OD",
      "VULTOS COM O OE",
      "DIMINUIÇÃO DA AV DE OE",
      "LENTE ESCLERAL PARA OD",
      "ARDENCIA EM OD",
      "TX RENAL",
      "CA RASA E FORMADA",
      "LIO TOPICA",
      "VASOS POST VIZUALIZADA COM OPACIDADE VITREA"
    ],
    "Paciente ou Grupo com Deficiência": [
      "PACIENTE"
    ],
    "Negação": [
      "NEGA",
      "NÃO",
      "NEM",
      "SEM"
    ],
    "Atividade de Assistência à Saúde": [
      "SOLICITA",
      "CONDUTA",
      "ENTREGO",
      "SOLICITAÇÃO",
      "ENCAMINHO",
      "ACOMPANHAMENTO OFTALMOLOGICO",
      "REALIZANDO ACOMPANHAMENTO"
    ],
    "Dispositivo Médico": [
      "ÓCULOS",
      "LENTE ESCLERAL PARA OD",
      "LENTE ESCLERAL"
    ],
    "Substância Farmacológica": [
      "COLÍRIO",
      "INSULINA"
    ],
    "Substância Química Orgânica": [
      "COLÍRIO",
      "INSULINA"
    ],
    "Doença ou Síndrome": [
      "DM",
      "GLAUCOMA",
      "ESTRABISMO",
      "RENAL CRONICA"
    ],
    "Hormônio": [
      "INSULINA"
    ],
    "Sequência de Aminoácidos": [
      "INSULINA"
    ],
    "Procedimento Terapêutico ou Preventivo": [
      "CIRURGIAS",
      "LENTE ESCLERAL PARA OD",
      "TX RENAL"
    ],
    "Parte do Corpo, Órgão ou Componente Orgânico": [
      "AO",
      "OD",
      "OEE",
      "OE"
    ],
    "Achado": [
      "CEGUEIRA",
      "REFLEXO",
      "CEGUEIRA TOTAL DE OD",
      "DIMINUIÇÃO DA AV DE OE",
      "HISTORICO FAMILIAR"
    ],
    "Atributo Clínico": [
      "AV"
    ],
    "Procedimento Diagnóstico": [
      "ESQ",
      "TOL",
      "BIO",
      "FO"
    ],
    "Conceito Qualitativo": [
      "MELHORA",
      "NOVA"
    ],
    "Resultado Laboratorial ou de Teste": [
      "MICROOFTALMIA",
      "CATARATA BRANCA COM SINEQUIA POSTERIOR 360o",
      "PIGMENTAÇÃO EM CRISTALINO",
      "CA RASA E FORMADA",
      "CÓRNE FLUOR NEGATIVA",
      "LIO TOPICA",
      "OPACIDADE POSTERIOR",
      "MARCAS DE YAG LASER EM EIXO CENTRAL",
      "DIFICIL VISUALIZAÇÃO POR OPACIDADE DE MEIOS",
      "VASOS POST VIZUALIZADA COM OPACIDADE VITREA"
    ],
    "Grupo Profissional ou Ocupacional": [
      "Doutor",
      "R1",
      "R2"
    ],
    "Conceito Temporal": [
      "NOS ULTIMOS 6 MESES",
      "HÁ 10 ANOS",
      "HÁ 7 ANOS"
    ],
    "Lesão ou Envenenamento": [
      "TRAUMA OCULAR"
    ],
    "Organização Relacionada à Saúde": [
      "SERVIÇO OFTALMOLOGICO"
    ],
    "Conceito Quantitativo": [
      "20 / 400"
    ]
  },
  "labels": {}
}