{
  "prontuario_id": 372,
  "text": "Lucas, 67 ANOS, CASADO, CURITIBA\n# RM EM 2010- 3 PONTES SAFENAS\n# HAS HÁ 15 ANOS\n# DM COM USO DE INSULINA HA 4 ANOS\n# ANGIOPLASTIA HÁ 10 ANOS\n# ARRITMIA\nMEDICAÇÕES:\nLOSARTANA 100MG 1 CP PELA MANHÃ E MEIO A TARDE\nESPIRONOLACTONA 25MG 1 CP PELA MANHÃ\nCONCOR 5 MG 1 CP AO DIA\nAMIODARONA 200MG MEIO COMPRIMIDO AO DIA\nFUROSEMIDA 40 MG 1 CP PELA MANHÃ \nMAREVAN 5 MG 2 CP DIA TODOS OS DIAS\nINSULINA 30 U A NOITE\nMETFORMINA 500 MG 3 X AO DIA\nATORVASTATINA  20 MG 4 CP DIA\nQUEIXA PRINCIPAL - DISPNEIA NYHA III\nNEGA DOR ANGINOSA\nEXAMES:\nÚLTIMO RNI 31/03/2014: 1,32\nECOCARDIOGRAMA 27/09/13\nCONCLUSÃO: HIPERTROFIADE VENTRICULO ESQUERDO, COM DIMENSOESAUMENTADAS E FUNÇÃO SISTOLICA COMPROMETIDA DE GRAU MODERADO,\nACINESIA DE PAREDE INFERIOR E HIPOCINESIANOS DEMAIS SEGMENTOS, ALTERAÇÃO DO RELAXAMENTO VENTRICULAR ESQUERDO.\nREGURGITAÇÃOMITRAL MODERADA, ATRIO ESQUERDO DILATADO.\nCHV: EX TABAGISTA PAROU HÁ 5 ANOS MEIA CARTEIRA DIA\nNÃO FAZ USO DE ÁLCOOL HÁ ANOS\nSEDENTÁRIO\nNÃO CUIDA A DIETA, COMENDO POUCA GORDURA\nICC GLOBAL\nFA PAROXISTICA\nTIO CARDIOPATA\nCX: 6 CATETERISMO, 2 ANGIOSPLATIA, 3 PONTE DE SAFENA.\nNEGA ALERGIAS\nNEGA OUTRAS INTERNAMENTOS.\nFRATUROU JOELHO E PERNA ? FEZ CIRURGIA\nNEGA QUEIXAS\nRETORNO COM EXAMES QUE NÃO FORAM REALIZADOS PQ PERDERAM O PAPEL",
  "entities": {
    "Procedimento Terapêutico ou Preventivo": [
      "RM",
      "ANGIOPLASTIA",
      "MEDICAÇÕES",
      "CX",
      "CATETERISMO",
      "ANGIOSPLATIA",
      "INTERNAMENTOS",
      "CIRURGIA",
      "PONTES SAFENAS",
      "PONTE DE SAFENA"
    ],
    "Abreviação": [
      "RM",
      "HAS",
      "DM",
      "RNI",
      "CX",
      "1 CP",
      "2 CP",
      "30 U",
      "3 X",
      "ICC GLOBAL",
      "FA PAROXISTICA"
    ],
    "Procedimento Diagnóstico": [
      "RM",
      "ECOCARDIOGRAMA"
    ],
    "Conceito Quantitativo": [
      "3",
      "100MG",
      "MEIO",
      "25MG",
      "200MG",
      "6",
      "2",
      "1 CP",
      "5 MG",
      "MEIO COMPRIMIDO",
      "40 MG",
      "2 CP",
      "30 U",
      "500 MG",
      "3 X",
      "20 MG",
      "4 CP",
      "1 , 32",
      "MEIA CARTEIRA DIA"
    ],
    "Doença ou Síndrome": [
      "HAS",
      "DM",
      "ARRITMIA",
      "CARDIOPATA",
      "DISPNEIA NYHA III",
      "ICC GLOBAL",
      "FA PAROXISTICA"
    ],
    "Substância Farmacológica": [
      "INSULINA",
      "MEDICAÇÕES",
      "LOSARTANA",
      "ESPIRONOLACTONA",
      "CONCOR",
      "AMIODARONA",
      "FUROSEMIDA",
      "MAREVAN",
      "METFORMINA",
      "ATORVASTATINA"
    ],
    "Hormônio": [
      "INSULINA"
    ],
    "Substância Química Orgânica": [
      "LOSARTANA",
      "ESPIRONOLACTONA",
      "CONCOR",
      "AMIODARONA",
      "FUROSEMIDA",
      "METFORMINA",
      "ATORVASTATINA"
    ],
    "Conceito Temporal": [
      "DIA",
      "HÁ 15 ANOS",
      "HA 4 ANOS",
      "HÁ 10 ANOS",
      "PELA MANHÃ",
      "A TARDE",
      "AO DIA",
      "TODOS OS DIAS",
      "A NOITE",
      "HÁ ANOS"
    ],
    "Negação": [
      "NEGA",
      "NÃO"
    ],
    "Procedimento Laboratorial": [
      "EXAMES",
      "RNI"
    ],
    "Achado": [
      "SEDENTÁRIO",
      "EX TABAGISTA",
      "PAROU HÁ 5 ANOS",
      "COMENDO POUCA GORDURA"
    ],
    "Alimento": [
      "DIETA"
    ],
    "Grupo Familiar": [
      "TIO"
    ],
    "Função Patológica": [
      "ALERGIAS"
    ],
    "Atividade de Assistência à Saúde": [
      "INTERNAMENTOS",
      "RETORNO",
      "REALIZADOS"
    ],
    "Lesão ou Envenenamento": [
      "FRATUROU"
    ],
    "Parte do Corpo, Órgão ou Componente Orgânico": [
      "JOELHO",
      "PERNA"
    ],
    "Sinal ou Sintoma": [
      "QUEIXAS",
      "QUEIXA PRINCIPAL",
      "DOR ANGINOSA"
    ],
    "Resultado Laboratorial ou de Teste": [
      "EXAMES",
      "HIPERTROFIADE VENTRICULO ESQUERDO , COM DIMENSOESAUMENTADAS",
      "FUNÇÃO SISTOLICA COMPROMETIDA DE GRAU MODERADO",
      "ACINESIA DE PAREDE INFERIOR E HIPOCINESIANOS DEMAIS SEGMENTOS",
      "ALTERAÇÃO DO RELAXAMENTO VENTRICULAR ESQUERDO",
      "REGURGITAÇÃOMITRAL MODERADA , ATRIO ESQUERDO DILATADO"
    ]
  },
  "labels": {}
}