{
  "prontuario_id": 160,
  "text": "LUCAS, 63 ANOS\n\n# TV AO + MI = 2007\n   - PROTESE AO BRAILE 25MM\n   - PROTESE MI CARDIOPROTESE 29MM\nEM USO DE: ENALAPRIL 10MG; HCTZ 25MG /D; METOPROLOL 100MG /D; AAS 100MG /D; SVT 20MG /D.\n\nECOCARDIO 2014: RA 33, VD 47, AE 47,  SEPTO 13, PP 13, DD 57, DS 41, FE 53%.\nMI BIOL: GMAX 14, MEDIO 5, IMOD.\nPROTESE AO BIOL GMAX 40, MEDIO 20 - DLAO DISCRETA.\n\nPCTE SEM QUEIXAS, NEGA DISPNÉIA, NEGA ORTOPNÉIA. QUEIXA-SE DE IMPOTENCIA APÓS INICIAR O USO DE METOPROLOL.\nSEQUELA MOTORA ESQ - PARALISIA INFANTIL? \n\nPA 140X60, FC 64\nAP MVB+ S RA\nAC BCRNF SOPRO SISTOLICO AO E PANFOCAL +4/+6 EJETIVO; SOPRO DIASTOLICO AO E MI ASPIRATIVO +3/+6\nABD SP\nMMII SP\n\nA # TROCA DE VAO E MI HÁ 8 ANOS\nCF I => LIMITADO PELA ALTERAÇÃO MOTORA? SUBESTIMADO\n\nP # AUMENTO ENALAPRIL 10 MG 12/12H; METOPROLOL 50MG /D.\nMANTIDOS DEMAIS.\nRETORNO COM NOVO ECO EM 6 MESES.\n\nR4 CARDIO LUCAS\nDoutor Vital Brazil ",
  "entities": {
    "Parte do Corpo, Órgão ou Componente Orgânico": [
      "AO",
      "MI",
      "ABD",
      "MMII"
    ],
    "Aminoácido, Peptídeo ou Proteína": [
      "ENALAPRIL"
    ],
    "Substância Farmacológica": [
      "ENALAPRIL",
      "HCTZ",
      "METOPROLOL",
      "AAS",
      "SVT"
    ],
    "Substância Química Orgânica": [
      "ENALAPRIL",
      "HCTZ",
      "METOPROLOL",
      "AAS",
      "SVT"
    ],
    "Conceito Quantitativo": [
      "10MG",
      "140X60",
      "64",
      "50MG",
      "25MG /D",
      "10 MG"
    ],
    "Abreviação": [
      "HCTZ",
      "AAS",
      "SVT",
      "ECOCARDIO",
      "DLAO",
      "PCTE",
      "PA",
      "FC",
      "AP",
      "MVB+",
      "S",
      "RA",
      "AC",
      "BCRNF",
      "AO",
      "MI",
      "MMII",
      "SP",
      "A",
      "P",
      "ECO",
      "PROTESE AO BRAILE 25MM",
      "PROTESE MI CARDIOPROTESE 29MM",
      "RA 33",
      "VD 47",
      "AE 47",
      "PP 13",
      "DD 57",
      "DS 41",
      "FE 53%",
      "MI BIOL",
      "PROTESE AO BIOL",
      "SEQUELA MOTORA ESQ"
    ],
    "Procedimento Diagnóstico": [
      "ECOCARDIO",
      "AP",
      "AC",
      "A",
      "ECO"
    ],
    "Resultado Laboratorial ou de Teste": [
      "IMOD",
      "+3/+6",
      "RA 33",
      "VD 47",
      "AE 47",
      "SEPTO 13",
      "PP 13",
      "DD 57",
      "DS 41",
      "FE 53%",
      "GMAX 14",
      "MEDIO 5",
      "+4/+6 EJETIVO"
    ],
    "Paciente ou Grupo com Deficiência": [
      "PCTE"
    ],
    "Negação": [
      "SEM",
      "NEGA",
      "S"
    ],
    "Sinal ou Sintoma": [
      "QUEIXAS",
      "DISPNÉIA",
      "ORTOPNÉIA",
      "QUEIXA-SE",
      "RA",
      "SOPRO SISTOLICO",
      "SOPRO DIASTOLICO"
    ],
    "Doença ou Síndrome": [
      "IMPOTENCIA",
      "PARALISIA INFANTIL"
    ],
    "Atributo Clínico": [
      "PA",
      "FC"
    ],
    "Achado": [
      "MVB+",
      "BCRNF",
      "SP"
    ],
    "Localização ou Região Corporal": [
      "AO",
      "PANFOCAL",
      "MI"
    ],
    "Conceito Qualitativo": [
      "ASPIRATIVO"
    ],
    "Dispositivo Médico": [
      "VAO",
      "PROTESE AO BRAILE 25MM",
      "PROTESE MI CARDIOPROTESE 29MM",
      "PROTESE AO BIOL"
    ],
    "Produto Intelectual": [
      "P"
    ],
    "Procedimento Terapêutico ou Preventivo": [
      "AUMENTO"
    ],
    "Atividade de Assistência à Saúde": [
      "AUMENTO",
      "MANTIDOS DEMAIS"
    ],
    "Conceito Temporal": [
      "12/12H",
      "/D",
      "HÁ 8 ANOS"
    ],
    "Função Patológica": [
      "SEQUELA MOTORA ESQ",
      "SOPRO SISTOLICO",
      "SOPRO DIASTOLICO",
      "ALTERAÇÃO MOTORA"
    ]
  },
  "labels": {}
}