{
  "prontuario_id": 451,
  "text": "TRANSPLANTE RENAL EM 204.\nRM 2012.\n\nEM USO DE SELOZOK 100 / LOSARTANA 50 BID / ANLODIPINA 5 BID / ATENSINA 0,150 BID / AAS 100 / ATORVA 40 / CIPROFIBRATO 200 / PREDNISONA 15 / MICOFENOLATO / ALOPURINOL.\n\nPACIENTE QUEIXA-SE DE DISPNÉIA AOS PEQUENOS / MEDIOS ESFORÇOS, PROGRESSIVA, COM CERCA DE 06 MESES DE EVOLUÇÃO. NEGA ANGINA\nHÁBITOS FISIOLÓGICOS PRESERVADOS.\n\nERGOMÉTRICO DE 2014 > SUBMÁXIMO E SEM ALTERAÇÕES ISQUEMICA. EXTRA-SISTOLES PAREADAS E INTERROMPIDO POR EXAUSTÃO.\nTRIGLICÉRIDES 389 / CT 235 / HDL 31 / LDL 126.\n\nAO EXAME: OBESO, BEG, CORADO, HIDRATADO, ANICTÉRICO E ACIANÓTICO.\nMVF E SEM RA, FR 14 IRPM SAT.O2 98% EM AA.\nRCR BNF EM 2T, FC 72BPM ,PA 140X80 MMHG.\nABODME LIVRE, RHA PRESERVADOS E INDOLOR A PALPAÇÃO.\nMMII SEM ALTERAÇÕES.\n\nCD:\nDISPNÉIA A/E > EQUIVALENTE ANGINOSO?\n\nCD:\nORIENTAÇÕES GERAIS,\nORIENTO EMAGRECIMENTO,\nSOLICITO AVALIAÇÃO DA EQUIPE DA NUTRIÇÃO,\nSOLIICO CINTILOGRAFIA DE MIOCARDIO,\nRETORNO COM 06 MESES,\nORIENTO SINAIS DE ALERTA,\nPROCURAR O PS SE NOVAS QUEIXAS E/OU INTERCORRÊNCIAS.\n \n ",
  "entities": {
    "Abreviação": [
      "RM",
      "BID",
      "AAS",
      "ATORVA",
      "BEG",
      "MVF",
      "RA",
      "FR",
      "SAT",
      "FC",
      "72BPM",
      "PA",
      "MMII",
      "CD",
      "A/E",
      "CT 235",
      "14 IRPM",
      "RCR BNF EM 2T",
      "RHA PRESERVADOS"
    ],
    "Procedimento Terapêutico ou Preventivo": [
      "RM",
      "EMAGRECIMENTO",
      "TRANSPLANTE RENAL"
    ],
    "Substância Química Orgânica": [
      "SELOZOK",
      "LOSARTANA",
      "ANLODIPINA",
      "ATENSINA",
      "AAS",
      "ATORVA",
      "CIPROFIBRATO",
      "PREDNISONA",
      "MICOFENOLATO",
      "ALOPURINOL"
    ],
    "Substância Farmacológica": [
      "SELOZOK",
      "LOSARTANA",
      "ANLODIPINA",
      "ATENSINA",
      "AAS",
      "ATORVA",
      "CIPROFIBRATO",
      "PREDNISONA",
      "MICOFENOLATO",
      "ALOPURINOL"
    ],
    "Conceito Quantitativo": [
      "100",
      "40",
      "200",
      "15",
      "72BPM",
      "0 , 150",
      "14 IRPM",
      "98% EM AA",
      "140X80 MMHG"
    ],
    "Paciente ou Grupo com Deficiência": [
      "PACIENTE"
    ],
    "Sinal ou Sintoma": [
      "QUEIXA-SE",
      "ANGINA",
      "ANICTÉRICO",
      "ACIANÓTICO",
      "RA",
      "ALTERAÇÕES",
      "DISPNÉIA",
      "QUEIXAS",
      "INTERCORRÊNCIAS",
      "DISPNÉIA AOS PEQUENOS / MEDIOS ESFORÇOS",
      "EQUIVALENTE ANGINOSO",
      "SINAIS DE ALERTA"
    ],
    "Conceito Qualitativo": [
      "PROGRESSIVA"
    ],
    "Negação": [
      "NEGA",
      "SEM",
      "ANICTÉRICO",
      "ACIANÓTICO"
    ],
    "Procedimento Diagnóstico": [
      "ERGOMÉTRICO",
      "EXAME",
      "PALPAÇÃO",
      "CINTILOGRAFIA DE MIOCARDIO"
    ],
    "Doença ou Síndrome": [
      "OBESO"
    ],
    "Achado": [
      "OBESO",
      "BEG",
      "CORADO",
      "HIDRATADO",
      "MVF",
      "LIVRE",
      "TRANSPLANTE RENAL",
      "HÁBITOS FISIOLÓGICOS PRESERVADOS",
      "RCR BNF EM 2T",
      "RHA PRESERVADOS"
    ],
    "Atributo Clínico": [
      "FR",
      "SAT",
      "FC",
      "PA"
    ],
    "Parte do Corpo, Órgão ou Componente Orgânico": [
      "ABODME",
      "MMII"
    ],
    "Produto Intelectual": [
      "CD"
    ],
    "Atividade de Assistência à Saúde": [
      "CD",
      "SOLIICO",
      "ORIENTAÇÕES GERAIS",
      "SOLICITO AVALIAÇÃO",
      "RETORNO COM 06 MESES"
    ],
    "Organização Relacionada à Saúde": [
      "PS",
      "EQUIPE DA NUTRIÇÃO"
    ],
    "Conceito Temporal": [
      "06 MESES DE EVOLUÇÃO"
    ],
    "Resultado Laboratorial ou de Teste": [
      "ALTERAÇÕES ISQUEMICA",
      "EXTRA-SISTOLES PAREADAS E INTERROMPIDO POR EXAUSTÃO",
      "TRIGLICÉRIDES 389",
      "CT 235",
      "HDL 31",
      "LDL 126"
    ],
    "Grupo Profissional ou Ocupacional": [
      "EQUIPE DA NUTRIÇÃO"
    ]
  },
  "labels": {}
}