{
  "prontuario_id": 367,
  "text": "pos tx renal.\nTx renal dez/13.\ninternamento em maio/14 por diarreia e lesão L5-S1.\nobesidade, cadeirante por lombociatalgia, onicomicose, insônia, eosinofilia persistente.\nDM mal controlado.\nhiperTGL.\nEcodoppler: IR 0,9 em todas artérias.\nECG: ritmo sinusal, sem sinais de isq.\n \n \nMTC 5, MPS 2 / 1, FK 1 / 2, OMP 40, amiodarona (exceto FDS), AAS 100, MTF 850 x2, FSM 40 x2, ATN 50 x2, PT4 100, NPH 34 / 12 / 12 e IR 12 / 12 / 8, fluconazol semanal, lactulona, Polaramine 2mg, cilostazol.\n\nS: Refere amortecimento em face há alguns dias, sem déficit focal. Episódios de diarreia ocasional. Refere ainda precordialgia atípica. Controles mostram glicemia mal controlada. PA bem controlada.\nExames mostram ClCr 64ml/min, Hb 12,2, TGL 400, NS FK 5,0  sem ferropenia,  UC neg.",
  "entities": {
    "Atividade de Assistência à Saúde": [
      "internamento"
    ],
    "Sinal ou Sintoma": [
      "diarreia",
      "lombociatalgia",
      "insônia",
      "déficit focal",
      "precordialgia atípica"
    ],
    "Doença ou Síndrome": [
      "obesidade",
      "onicomicose",
      "hiperTGL",
      "DM mal controlado"
    ],
    "Resultado Laboratorial ou de Teste": [
      "eosinofilia",
      "Exames",
      "ferropenia",
      "IR 0 , 9 em todas artérias",
      "ritmo sinusal",
      "glicemia mal controlada",
      "ClCr 64ml/min",
      "Hb 12 , 2",
      "TGL 400",
      "NS FK 5 , 0",
      "UC neg"
    ],
    "Conceito Qualitativo": [
      "persistente"
    ],
    "Abreviação": [
      "hiperTGL",
      "ECG",
      "MTC",
      "MPS",
      "FK",
      "OMP",
      "FDS",
      "AAS",
      "MTF",
      "FSM",
      "ATN",
      "PT4",
      "NPH",
      "tx renal",
      "Tx renal",
      "DM mal controlado",
      "PA bem controlada",
      "ClCr 64ml/min",
      "TGL 400",
      "NS FK 5 , 0"
    ],
    "Procedimento Diagnóstico": [
      "Ecodoppler",
      "ECG"
    ],
    "Negação": [
      "sem",
      "exceto"
    ],
    "Substância Farmacológica": [
      "MTC",
      "MPS",
      "FK",
      "OMP",
      "amiodarona",
      "AAS",
      "MTF",
      "FSM",
      "ATN",
      "PT4",
      "NPH",
      "fluconazol",
      "lactulona",
      "Polaramine",
      "cilostazol"
    ],
    "Substância Química Orgânica": [
      "MTC",
      "FK",
      "OMP",
      "amiodarona",
      "AAS",
      "MTF",
      "FSM",
      "ATN",
      "fluconazol",
      "Polaramine",
      "cilostazol"
    ],
    "Conceito Quantitativo": [
      "5",
      "40",
      "100",
      "semanal",
      "2mg",
      "2 / 1",
      "1 / 2",
      "850 x2",
      "40 x2",
      "50 x2",
      "34 / 12 / 12",
      "12 / 12 / 8"
    ],
    "Conceito Temporal": [
      "FDS",
      "semanal",
      "Episódios",
      "ocasional"
    ],
    "Hormônio": [
      "NPH"
    ],
    "Aminoácido, Peptídeo ou Proteína": [
      "NPH"
    ],
    "Localização ou Região Corporal": [
      "face"
    ],
    "Procedimento Laboratorial": [
      "Controles"
    ],
    "Procedimento Terapêutico ou Preventivo": [
      "tx renal",
      "Tx renal"
    ],
    "Lesão ou Envenenamento": [
      "lesão L5-S1"
    ],
    "Achado": [
      "ritmo sinusal",
      "PA bem controlada"
    ]
  },
  "labels": {}
}