{
  "prontuario_id": 927,
  "text": "LUCAS 28 ANOS \nGNC, PERDA RENAL PÓS-GRAVIDEZ , BX REALIZADA > NÃO SABE LAUDO\nHAS\nDRC , EM TRS - HD JUNHO 2015\nNEGA DM, DLP, TIRÓIDE, CARDIOPATIAS, LITÍASE, OUTROS...\nG 2 A 1 C 1.\nNEGA OUTRAS CIRURGIAS, \nDIURESE DE BOM VOLUME.\nEM USO DE RENALVIT, EPO, CALCIOLIT.\n\nINTERNAÇÕES > ÚLTIMAS PÓR INFECÇÃO PERMCATH. TROCADO EM NOV HUC E RETIRADO EM DEZ POR FEBRE.\nHOJE COM DL EM JID, SEM QUEIXAS HÁ MAIS DE 1 M,êS.\n\nPESO SECO 66, ALT 160.\n\nAO EXAME :\nPA 150/90,\nMUCOSAS HIPOCORADAS, DEMAIS \nEXAME FISICO NORMAL.\n \nLIBERADA PARA TRANSPLANTE,\nESCLAREÇO RISCOS E BENEFICIOS,\nABO O,\nSOROLOGIAS CMV E EBV  REAGENTE, ANTIHBS REAGENTE, TOXO NR,\nECOCARDIOGRAMA NORMAL ,\nDOPPLER PELVICO NORMAL ,\nECOGRAFIA ABDOME TOTAL > RINS NEFROPATIA, DEMAIS SP,\nECG SINUSAL, FC 113, NORMAL ,\nTE AUSENCIA ALTERAÇÕES ISQUEMICAS,\nIMUNO : REVER MM E PRA NA REUNIÃO.\n ",
  "entities": {
    "Doença ou Síndrome": [
      "GNC",
      "HAS",
      "DRC",
      "DM",
      "DLP",
      "TIRÓIDE",
      "CARDIOPATIAS",
      "LITÍASE",
      "INFECÇÃO",
      "NEFROPATIA"
    ],
    "Abreviação": [
      "GNC",
      "HAS",
      "DRC",
      "TRS",
      "HD",
      "DM",
      "DLP",
      "EPO",
      "DL",
      "JID",
      "ALT",
      "PA",
      "CMV",
      "EBV",
      "TE",
      "G 2",
      "A 1",
      "C 1",
      "TOXO NR",
      "DEMAIS SP"
    ],
    "Conceito Temporal": [
      "PÓS-GRAVIDEZ"
    ],
    "Atividade de Assistência à Saúde": [
      "REALIZADA",
      "TROCADO",
      "RETIRADO",
      "LIBERADA",
      "ESCLAREÇO RISCOS E BENEFICIOS"
    ],
    "Negação": [
      "NÃO",
      "NEGA",
      "SEM",
      "AUSENCIA ALTERAÇÕES ISQUEMICAS"
    ],
    "Procedimento Terapêutico ou Preventivo": [
      "TRS",
      "HD",
      "TRANSPLANTE",
      "OUTRAS CIRURGIAS"
    ],
    "Substância Farmacológica": [
      "RENALVIT",
      "EPO",
      "CALCIOLIT"
    ],
    "Aminoácido, Peptídeo ou Proteína": [
      "EPO"
    ],
    "Hormônio": [
      "EPO"
    ],
    "Organização Relacionada à Saúde": [
      "INTERNAÇÕES"
    ],
    "Dispositivo Médico": [
      "PERMCATH",
      "DL"
    ],
    "Sinal ou Sintoma": [
      "FEBRE",
      "QUEIXAS",
      "MUCOSAS HIPOCORADAS"
    ],
    "Parte do Corpo, Órgão ou Componente Orgânico": [
      "JID",
      "RINS"
    ],
    "Conceito Quantitativo": [
      "66",
      "160",
      "150/90"
    ],
    "Atributo Clínico": [
      "ALT",
      "PA",
      "FC",
      "G 2",
      "A 1",
      "C 1",
      "PESO SECO"
    ],
    "Procedimento Diagnóstico": [
      "EXAME",
      "ECG",
      "TE",
      "IMUNO",
      "ECOGRAFIA ABDOME TOTAL"
    ],
    "Procedimento Laboratorial": [
      "SOROLOGIAS"
    ],
    "Vírus": [
      "CMV",
      "EBV"
    ],
    "Resultado Laboratorial ou de Teste": [
      "REAGENTE",
      "ABO O",
      "ANTIHBS REAGENTE",
      "TOXO NR",
      "DOPPLER PELVICO NORMAL",
      "AUSENCIA ALTERAÇÕES ISQUEMICAS"
    ],
    "Achado": [
      "SINUSAL",
      "NORMAL",
      "DIURESE DE BOM VOLUME",
      "EXAME FISICO NORMAL",
      "ECOCARDIOGRAMA NORMAL",
      "DEMAIS SP"
    ]
  },
  "labels": {}
}