{
  "prontuario_id": 838,
  "text": "LUCAS, 50 ANOS\n\n# HAS HÁ 10 ANOS\n# DSLP \n# HIPOTIREOIDISMO \n# DEPRESSÃO \n# OSTEOARTRITE DE MÃOS\n# CAT EM JUNHO/2011: SEM INDICAÇÃO CIRÚRGICA\n# HÉRNIA DE DISCO HÁ 3 ANOS\n# CINTILOGRAFIA MIOCÁRDICA COM DIPIRIDAMOL EM 2011: HIPOCAPTAÇÃO APICAL, DO SEGMENTO ANTERIOR (TRANSITÓRIO) E BASAL DO SEGMENTO\nANTERO-SEPTAL\n\n# EM USO: FLUOXETINA 20MG /D; ENALAPRIL 10MG 12/12H; AAS 100MG /D; CARVEDILOL 12,5MG 12/12H; HCTZ 25MG /D; SUSTRATE 10MG SN; SINVASTATINA 40MG /D; LEVOTIROXINA 25UCG /D; HIDROXICLOROQUINA 400MG /D; \n\nLAB 08/04/15: TG 144 / HDL 50 / CT 178 / LDL 99 / \n\nS # REFERE DOR TORÁCICA PRECORDIAL TIPO QUEIMAÇÃO, COM MELHORA AO USO DE NITRATO, SEM IRRADIAÇÃO, SEM RELAÇÃO COM O ESFORÇO, 2 EPISÓDIOS AO MÊS. NEGA DISPNÉIA, ORTOPNEIA OU DPN. NEGA EDEMA DE     MMII. CONTA APRESENTAR ARTRALGIAS DIFUSAS PIORES AO FRIO. \n\nO # \n BEG, CORADA, HIDRATADA, EUPNEICA, LOTE.\n PA 120/70; FC 62; SATO2 98% EM AA.\n MV PRESENTE E SIMÉTRICO SEM RA.\n BCRNF SEM SOPROS EM 2T.\n ABDOME GLOBOSO, FLÁCIDO, INDOLOR, SEM VCM OU MASSAS PALPAVEIS.\n MMII SEM EDEMA OU EMPASTAMENTO. \n\nA # \n- ANGINA INSTÁVEL? \n\nP #\n- ACRESCENTO MONOCORDIL 20MG 12/12H.\n- SOLICITO NOVA CINTILOGRAFIA DE PERFUSÃO MIOCÁRDICA.\n- SOLICITO NOVO LAB .\n- RETORNO COM EXAMES.\n\nR2 XX LUCAS\nDoutor Vital Brazil\n \n \n \n ",
  "entities": {
    "Abreviação": [
      "HAS",
      "DSLP",
      "CAT",
      "AAS",
      "HCTZ",
      "SN",
      "LAB",
      "DPN",
      "MMII",
      "BEG",
      "LOTE",
      "PA",
      "FC",
      "AA",
      "MV",
      "RA",
      "BCRNF",
      "VCM",
      "R2",
      "TG 144",
      "CT 178"
    ],
    "Doença ou Síndrome": [
      "HAS",
      "DSLP",
      "HIPOTIREOIDISMO",
      "DEPRESSÃO",
      "HÉRNIA DE DISCO",
      "ANGINA INSTÁVEL"
    ],
    "Disfunção Mental ou Comportamental": [
      "DEPRESSÃO"
    ],
    "Parte do Corpo, Órgão ou Componente Orgânico": [
      "MÃOS",
      "MMII",
      "ABDOME"
    ],
    "Procedimento Diagnóstico": [
      "CAT",
      "EXAMES",
      "CINTILOGRAFIA MIOCÁRDICA",
      "CINTILOGRAFIA DE PERFUSÃO MIOCÁRDICA"
    ],
    "Procedimento Terapêutico ou Preventivo": [
      "CAT"
    ],
    "Negação": [
      "SEM",
      "NEGA",
      "INDOLOR"
    ],
    "Substância Química Orgânica": [
      "DIPIRIDAMOL",
      "FLUOXETINA",
      "AAS",
      "CARVEDILOL",
      "HCTZ",
      "SINVASTATINA",
      "HIDROXICLOROQUINA"
    ],
    "Substância Farmacológica": [
      "DIPIRIDAMOL",
      "FLUOXETINA",
      "ENALAPRIL",
      "AAS",
      "CARVEDILOL",
      "HCTZ",
      "SUSTRATE",
      "SINVASTATINA",
      "LEVOTIROXINA",
      "HIDROXICLOROQUINA",
      "NITRATO",
      "MONOCORDIL"
    ],
    "Aminoácido, Peptídeo ou Proteína": [
      "ENALAPRIL",
      "LEVOTIROXINA"
    ],
    "Conceito Temporal": [
      "SN"
    ],
    "Hormônio": [
      "LEVOTIROXINA"
    ],
    "Resultado Laboratorial ou de Teste": [
      "LAB",
      "HIPOCAPTAÇÃO APICAL",
      "SEGMENTO ANTERIOR ( TRANSITÓRIO ) E BASAL DO SEGMENTO ANTERO-SEPTAL",
      "TG 144",
      "HDL 50",
      "CT 178",
      "LDL 99"
    ],
    "Achado": [
      "MELHORA",
      "BEG",
      "CORADA",
      "HIDRATADA",
      "EUPNEICA",
      "LOTE",
      "SIMÉTRICO",
      "BCRNF",
      "GLOBOSO",
      "FLÁCIDO",
      "PIORES AO FRIO"
    ],
    "Substância Química Inorgânica": [
      "NITRATO"
    ],
    "Sinal ou Sintoma": [
      "IRRADIAÇÃO",
      "DISPNÉIA",
      "ORTOPNEIA",
      "DPN",
      "EDEMA",
      "RA",
      "GLOBOSO",
      "INDOLOR",
      "VCM",
      "EMPASTAMENTO",
      "DOR TORÁCICA PRECORDIAL",
      "ARTRALGIAS DIFUSAS",
      "MASSAS PALPAVEIS"
    ],
    "Atributo Clínico": [
      "PA",
      "FC",
      "SATO2"
    ],
    "Conceito Quantitativo": [
      "120/70",
      "62",
      "98%",
      "20MG /D",
      "100MG /D",
      "12 , 5MG 12/12H",
      "25MG /D",
      "40MG /D",
      "25UCG /D",
      "400MG /D",
      "2 EPISÓDIOS AO MÊS",
      "20MG 12/12H"
    ],
    "Conceito Espacial": [
      "SIMÉTRICO"
    ],
    "Localização ou Região Corporal": [
      "MMII"
    ],
    "Atividade de Assistência à Saúde": [
      "ACRESCENTO",
      "SOLICITO",
      "RETORNO",
      "INDICAÇÃO CIRÚRGICA"
    ],
    "Procedimento Laboratorial": [
      "LAB"
    ],
    "Grupo Profissional ou Ocupacional": [
      "R2",
      "Doutor"
    ],
    "Conceito Qualitativo": [
      "TIPO QUEIMAÇÃO"
    ]
  },
  "labels": {}
}