{
  "prontuario_id": 8,
  "text": "PACIENTE EM ACOMPNHAMENTO POR MEGACOLON CHAGÁSICO.\nREFERE CONSTIPAÇÃO CRÔNICA TENDO QUE USAR FLEET ENEMA PARA EVACUAR. DORES ESPORÁDICAS PRINCIPALMENTE QUANDO DEMORAR MUITO PARA IR AO BANHEIRO.\nATUALMENTE HÁ 15 DIAS SEM EVACUAR.\n\nHMP: MARCAPASSO HÁ 6 ANOS POR ARRITMIA TROCADO POR CDI HÁ 3 ANOS.\nJÁ REALIZOU CIRURGIA PARA MEGACOLON 2 VEZES HÁ 10 ANOS.\n\nEM USO DE: AAS / ENALAPRIL / FUROSEMIDA / AMIODARONA / CARVEDILOL.\n\nREIOGRAFIA DE ESOFAGO/ESTOMAGO/DUODENO (25/06/2015): ALTERADO: PRESENÇA DE REFLUXO. ESOFAGO / ESTOMAGO E DUODENO DE ASPECTOS NORMAIS.\n\n# CD: SOLICITO ENEMA OPACO VIA USB.\nRETORNO COM EXAMES.\nORIENTO USO DE FLEET PARA CONSTIPAÇÃO.\n \n \n \n ",
  "entities": {
    "Paciente ou Grupo com Deficiência": [
      "PACIENTE"
    ],
    "Função de Organismo": [
      "EVACUAR"
    ],
    "Sinal ou Sintoma": [
      "DORES",
      "CONSTIPAÇÃO",
      "CONSTIPAÇÃO CRÔNICA"
    ],
    "Conceito Temporal": [
      "ESPORÁDICAS",
      "ATUALMENTE"
    ],
    "Negação": [
      "SEM"
    ],
    "Abreviação": [
      "HMP",
      "CDI",
      "AAS",
      "CD"
    ],
    "Achado": [
      "HMP",
      "ASPECTOS NORMAIS"
    ],
    "Procedimento Terapêutico ou Preventivo": [
      "MARCAPASSO",
      "CDI",
      "FLEET",
      "FLEET ENEMA"
    ],
    "Dispositivo Médico": [
      "MARCAPASSO",
      "CDI"
    ],
    "Doença ou Síndrome": [
      "ARRITMIA",
      "MEGACOLON",
      "MEGACOLON CHAGÁSICO"
    ],
    "Substância Farmacológica": [
      "AAS",
      "ENALAPRIL",
      "FUROSEMIDA",
      "AMIODARONA",
      "CARVEDILOL",
      "FLEET ENEMA"
    ],
    "Substância Química Orgânica": [
      "AAS",
      "FUROSEMIDA",
      "AMIODARONA",
      "CARVEDILOL"
    ],
    "Aminoácido, Peptídeo ou Proteína": [
      "ENALAPRIL"
    ],
    "Resultado Laboratorial ou de Teste": [
      "ALTERADO",
      "PRESENÇA DE REFLUXO"
    ],
    "Parte do Corpo, Órgão ou Componente Orgânico": [
      "ESOFAGO",
      "ESTOMAGO",
      "DUODENO"
    ],
    "Produto Intelectual": [
      "CD"
    ],
    "Atividade de Assistência à Saúde": [
      "SOLICITO",
      "RETORNO",
      "EM ACOMPNHAMENTO",
      "TROCADO POR"
    ],
    "Organização Relacionada à Saúde": [
      "USB"
    ],
    "Procedimento Diagnóstico": [
      "EXAMES",
      "REIOGRAFIA DE ESOFAGO/ESTOMAGO/DUODENO",
      "ENEMA OPACO"
    ],
    "Conceito Quantitativo": [
      "2 VEZES"
    ]
  },
  "labels": {}
}