{
  "prontuario_id": 790,
  "text": "HAS / DLP,\nPos-operatorio recente de retirada de \"Tumor\" em regtião cervical, não conseguiram controlar,\nBronquite,\nObesidade,\n# Tosse com captopril.\n\n# Losartana 50 /12h, anlodipino 5, HCTZ 25, Alenia 6/6h, AAS 100 (dias alternados).\n\nQueixa de dor em MSE e irradiação para região precordial duração de 15 minutos, com dificuldade para mexer o braço.\nDispnéia aos esforços (400 / 500 metros).\n\n\nPA 150/80,\nEF: BEG, corada, hidratada, eupneica, acinaotioca, anicterica.\ns/ sopro carotideo.\nMV + c/ sibilos expiratorios.\nBR2t s/ sopros.\nmembors perfundidos, sem edemas, dermatite ocre.\n\nCD: LAb  + Ergometrico + ETT.\nAumento anlodipina.\nUsar aradois como losartana.\nRetorno em 2 meses.\n \n \n \n ",
  "entities": {
    "Abreviação": [
      "HAS",
      "DLP",
      "HCTZ",
      "AAS",
      "MSE",
      "PA",
      "EF",
      "BEG",
      "s/",
      "CD",
      "LAb",
      "ETT",
      "MV +"
    ],
    "Doença ou Síndrome": [
      "HAS",
      "DLP",
      "Bronquite",
      "Obesidade"
    ],
    "Negação": [
      "não",
      "acinaotioca",
      "anicterica",
      "s/",
      "sem"
    ],
    "Substância Química Orgânica": [
      "Losartana",
      "anlodipino",
      "HCTZ",
      "Alenia",
      "AAS",
      "anlodipina",
      "losartana"
    ],
    "Substância Farmacológica": [
      "Losartana",
      "anlodipino",
      "HCTZ",
      "Alenia",
      "AAS",
      "anlodipina",
      "aradois",
      "losartana"
    ],
    "Conceito Temporal": [
      "/12h",
      "6/6h",
      "Pos-operatorio recente"
    ],
    "Conceito Quantitativo": [
      "5",
      "25",
      "6/6h",
      "100",
      "150/80",
      "400 / 500 metros"
    ],
    "Sinal ou Sintoma": [
      "Queixa",
      "dor",
      "irradiação",
      "acinaotioca",
      "anicterica",
      "sopros",
      "edemas",
      "dificuldade para mexer",
      "Dispnéia aos esforços",
      "sibilos expiratorios",
      "dermatite ocre"
    ],
    "Localização ou Região Corporal": [
      "MSE",
      "membors",
      "região precordial"
    ],
    "Atributo Clínico": [
      "PA"
    ],
    "Procedimento Diagnóstico": [
      "EF",
      "Ergometrico",
      "ETT"
    ],
    "Achado": [
      "BEG",
      "corada",
      "hidratada",
      "eupneica",
      "perfundidos",
      "Tosse com captopril",
      "MV +"
    ],
    "Função Patológica": [
      "edemas"
    ],
    "Produto Intelectual": [
      "CD"
    ],
    "Atividade de Assistência à Saúde": [
      "CD",
      "Aumento",
      "Retorno"
    ],
    "Procedimento Laboratorial": [
      "LAb"
    ],
    "Processo Neoplásico": [
      "\"Tumor\" em regtião cervical"
    ]
  },
  "labels": {}
}