{
  "prontuario_id": 839,
  "text": "S ) PACIENTE EM ACOMPANHAMENTO POR TUMORAÇÃO EM MANDÍBULA. \n INICIO HA CERCA DE 7  MESES, EM FACE E CORPO DE MANDIBULA DIR, INDOLOR.\n NEGA DISFAGIA, NEGA PARESIAS OU PARESTESIAS EM FACE. REFERE QUE O TUMOR DIMINUIU UM POUCO DESDE A ULTIMA CONSULTA EM NOVEMBRO.\n NEGA TABAGISMO; NEGA ALERGIAS,\n PACIENTE REFERE TER REALIZADO TC DE PESCOÇO E RX MAS NÃO TROUXE O RESULTADO.\n HMP: HAS EM TTO, TRANSPLANTADA RENAL ESQ HA 03 ANOS, EM USO DE IMUNODEPRESSORES (SIC); \n\nO ) ORO: EDENTULISMO SUP E INF; PRESENÇA DE MASSA ENDURECIDA EM CORPO E RAMO DIREITOS DE MANDIBULA , INDOLOR Á PALPAÇÃO; 8X8 CM; LINGUA E ASSOALHO LIVRES; \nC/P: LIVRE.\n\nA) tumor odontogenico (cisto dentigero, ameloblastoma, tu marrom? sarcoma de mandibula?)\n\nC) RETORNO EM UMA SEMANA PARA TRAZER EXAMES.\n\nR2 Lucas\n \n \n ",
  "entities": {
    "Achado": [
      "S",
      "HMP",
      "LIVRE",
      "EM ACOMPANHAMENTO",
      "LINGUA E ASSOALHO LIVRES"
    ],
    "Abreviação": [
      "S",
      "RX",
      "HMP",
      "SIC",
      "O",
      "ORO",
      "C/P",
      "A",
      "C",
      "CORPO DE MANDIBULA DIR",
      "TC DE PESCOÇO",
      "TRANSPLANTADA RENAL ESQ",
      "SUP E INF",
      "tu marrom"
    ],
    "Paciente ou Grupo com Deficiência": [
      "PACIENTE"
    ],
    "Parte do Corpo, Órgão ou Componente Orgânico": [
      "MANDÍBULA",
      "C/P",
      "CORPO DE MANDIBULA DIR",
      "CORPO E RAMO DIREITOS DE MANDIBULA"
    ],
    "Negação": [
      "INDOLOR",
      "NEGA",
      "NÃO"
    ],
    "Sinal ou Sintoma": [
      "INDOLOR",
      "DISFAGIA",
      "PARESIAS",
      "PARESTESIAS",
      "MASSA ENDURECIDA"
    ],
    "Localização ou Região Corporal": [
      "FACE"
    ],
    "Processo Neoplásico": [
      "TUMOR",
      "ameloblastoma",
      "tumor odontogenico",
      "cisto dentigero",
      "tu marrom",
      "sarcoma de mandibula"
    ],
    "Atividade de Assistência à Saúde": [
      "CONSULTA",
      "O"
    ],
    "Doença ou Síndrome": [
      "TABAGISMO",
      "ALERGIAS",
      "HAS",
      "EDENTULISMO",
      "ameloblastoma"
    ],
    "Procedimento Diagnóstico": [
      "RX",
      "ORO",
      "PALPAÇÃO",
      "A",
      "EXAMES",
      "TC DE PESCOÇO"
    ],
    "Procedimento Terapêutico ou Preventivo": [
      "TTO",
      "IMUNODEPRESSORES",
      "TRANSPLANTADA RENAL ESQ"
    ],
    "Substância Farmacológica": [
      "IMUNODEPRESSORES"
    ],
    "Produto Intelectual": [
      "C"
    ],
    "Conceito Temporal": [
      "INICIO HA CERCA DE 7 MESES",
      "HA 03 ANOS"
    ],
    "Conceito Espacial": [
      "SUP E INF"
    ],
    "Conceito Quantitativo": [
      "8X8 CM"
    ]
  },
  "labels": {}
}