{
  "prontuario_id": 755,
  "text": "06/03/2012 às 14:40h. 1ºDI - Hemorragia intraventricular E. 1ºDI - AVC e PAM. Puérpera. Abertura ocular espontânea, afásica, hemiplégica D e diminuição de força a E. Pupilas iso / foto. Em ar ambiente. Segue em jejum VO. Acesso venoso central em subclávia D com infusão de soroterapia. CPP sem RA. Abdomem flácido, RHA+. Presença de lactação em mamas. Diurese espontânea. Extremidades aquecidas, perfusão periférica adequada, sem edemas.  # Solicitado enfaixamento de mamas. # Aguarda conduta frente a realização de Arteriografia.  Enfermeira Florence Nightingale. EXAME GERAL E INVESTIGACAO DE PESSOAS SEM QUEIXAS OU DIAGNOSTICO RELATADO.",
  "entities": {
    "Abreviação": [
      "AVC",
      "PAM",
      "iso",
      "foto",
      "CPP",
      "RA",
      "RHA+",
      "Hemorragia intraventricular E",
      "jejum VO",
      "subclávia D"
    ],
    "Achado": [
      "Puérpera",
      "iso",
      "foto",
      "RHA+",
      "Abertura ocular espontânea",
      "Diurese espontânea",
      "Extremidades aquecidas",
      "perfusão periférica adequada"
    ],
    "Conceito Temporal": [
      "Puérpera"
    ],
    "Sinal ou Sintoma": [
      "afásica",
      "RA",
      "edemas",
      "QUEIXAS",
      "hemiplégica D",
      "diminuição de força a E"
    ],
    "Parte do Corpo, Órgão ou Componente Orgânico": [
      "Pupilas",
      "subclávia D"
    ],
    "Atividade de Assistência à Saúde": [
      "infusão",
      "Solicitado",
      "EXAME GERAL"
    ],
    "Procedimento Terapêutico ou Preventivo": [
      "soroterapia",
      "jejum VO",
      "Acesso venoso central",
      "enfaixamento de mamas"
    ],
    "Negação": [
      "sem",
      "SEM"
    ],
    "Procedimento Diagnóstico": [
      "Arteriografia",
      "INVESTIGACAO DE PESSOAS"
    ],
    "Grupo Profissional ou Ocupacional": [
      "Enfermeira"
    ],
    "Dispositivo Médico": [
      "Acesso venoso central"
    ],
    "Função Fisiológica": [
      "lactação em mamas"
    ],
    "Doença ou Síndrome": [
      "DIAGNOSTICO RELATADO"
    ]
  },
  "labels": {}
}