{
  "prontuario_id": 723,
  "text": "15:30 9º DI CRISE CONVULSIVA - PERMANECE NA SALA DE EMERGÊNCIA SOB VENTILAÇÃO MECÂNICA, DESIDRATADA, HIPOTENSA, TOT 7,5 COM RIMA LABIAL 22, FIO2 70%, MODO PCV , TEMPO DE INSPIRAÇÃO 1,0, PEEP 4, MANITORIZAÇÃO CARDÍACA COM OXIMETRIA DE PULSO CONTÍNUO COM FC 75 BMP, PA 97/59 MMHG, SPO2 96%. ACESSO VENOSO EM MSD COM SOROTERIAPIA EM CURSO E SEDAÇÃO 20 ML EM BOMBA INFUSORA. SOE EM POSIÇÃO GÁTRICA  COM DIETA EM CURSO. PRESENÇA DE SECREÇÃO PURULENTA EM TOT. AUSCULTA PULMONAR COM RONCOS, DIFUSOS.  SVD COM DÉBITO DE 100 ML COLORAÇÃO LARANJADA. ÚLCERA DE PRESSÃO EM REGIÃO SACRA GRAU II E EM REGIÃO DE CALCANHO BILATERAL GRAU II.  AGUARDA VAGA NA UTI. SEGUE AOS CUIDADOS DA EQUIPE MULTIPROFISIONAL. SEPTICEMIA NAO ESPECIFICADA.",
  "entities": {
    "Sinal ou Sintoma": [
      "DESIDRATADA",
      "HIPOTENSA",
      "RONCOS",
      "CRISE CONVULSIVA",
      "SECREÇÃO PURULENTA"
    ],
    "Procedimento Terapêutico ou Preventivo": [
      "TOT",
      "SOROTERIAPIA",
      "SEDAÇÃO",
      "SOE",
      "DIETA",
      "SVD",
      "VENTILAÇÃO MECÂNICA",
      "MANITORIZAÇÃO CARDÍACA",
      "ACESSO VENOSO"
    ],
    "Dispositivo Médico": [
      "TOT",
      "SOE",
      "SVD",
      "ACESSO VENOSO"
    ],
    "Conceito Quantitativo": [
      "22",
      "70%",
      "4",
      "96%",
      "7 , 5",
      "1 , 0",
      "75 BMP",
      "97/59 MMHG",
      "20 ML",
      "100 ML"
    ],
    "Atributo Clínico": [
      "FIO2",
      "PEEP",
      "FC",
      "PA",
      "SPO2",
      "DÉBITO",
      "TEMPO DE INSPIRAÇÃO"
    ],
    "Abreviação": [
      "FIO2",
      "PEEP",
      "FC",
      "PA",
      "SPO2",
      "MSD",
      "SOE",
      "TOT",
      "SVD",
      "MODO PCV",
      "75 BMP"
    ],
    "Parte do Corpo, Órgão ou Componente Orgânico": [
      "MSD"
    ],
    "Conceito Espacial": [
      "DIFUSOS"
    ],
    "Função de Organismo": [
      "DÉBITO"
    ],
    "Organização Relacionada à Saúde": [
      "UTI",
      "SALA DE EMERGÊNCIA"
    ],
    "Localização ou Região Corporal": [
      "RIMA LABIAL",
      "REGIÃO SACRA",
      "REGIÃO DE CALCANHO BILATERAL"
    ],
    "Procedimento Diagnóstico": [
      "MANITORIZAÇÃO CARDÍACA",
      "OXIMETRIA DE PULSO CONTÍNUO",
      "AUSCULTA PULMONAR"
    ],
    "Dispositivo de Administração de Medicamento": [
      "BOMBA INFUSORA"
    ],
    "Conceito Qualitativo": [
      "COLORAÇÃO LARANJADA"
    ],
    "Doença ou Síndrome": [
      "ÚLCERA DE PRESSÃO"
    ],
    "Classificação": [
      "GRAU II"
    ],
    "Atividade de Assistência à Saúde": [
      "CUIDADOS DA EQUIPE MULTIPROFISIONAL"
    ]
  },
  "labels": {}
}