{
  "prontuario_id": 314,
  "text": "14:00 Consciente, comunicativa, normocorada, afebril, ventilação espontânea em AA, sem esforço, relata melhora da dispnéia, Aceitação parcial de dieta branda para DM, MMSS aquecidos, sem edema, AVP em MSE com soroterapia simples em curso, apresentou episódio de náusea e hipotensão foi medicada CPM. Abdomen flácido, RHA+, diurese espontânea, MMII aquecidos, sem edema. Encaminhada para higiene por asperção em cadeira de banho. # Aguarda agendamento de Eco cardio, Eco de Stress e Dopller de MMII para amanhã 22/02/2012. Enfermeira Florence Nightingale . EXAME GERAL E INVESTIGACAO DE PESSOAS SEM QUEIXAS OU DIAGNOSTICO RELATADO.",
  "entities": {
    "Achado": [
      "Consciente",
      "comunicativa",
      "normocorada",
      "flácido",
      "RHA+",
      "aquecidos",
      "MMSS aquecidos",
      "diurese espontânea"
    ],
    "Negação": [
      "afebril",
      "sem",
      "SEM"
    ],
    "Sinal ou Sintoma": [
      "afebril",
      "esforço",
      "dispnéia",
      "edema",
      "náusea",
      "hipotensão",
      "QUEIXAS"
    ],
    "Abreviação": [
      "AA",
      "AVP",
      "MSE",
      "CPM",
      "RHA+",
      "MMII",
      "dieta branda para DM",
      "MMSS aquecidos",
      "Eco cardio",
      "Eco de Stress"
    ],
    "Dispositivo Médico": [
      "AVP"
    ],
    "Procedimento Terapêutico ou Preventivo": [
      "AVP",
      "dieta branda para DM",
      "soroterapia simples"
    ],
    "Parte do Corpo, Órgão ou Componente Orgânico": [
      "MSE",
      "Abdomen"
    ],
    "Conceito Temporal": [
      "episódio"
    ],
    "Atividade de Assistência à Saúde": [
      "medicada",
      "CPM",
      "agendamento",
      "higiene",
      "por asperção",
      "EXAME GERAL"
    ],
    "Procedimento Diagnóstico": [
      "Dopller",
      "Eco cardio",
      "Eco de Stress",
      "INVESTIGACAO DE PESSOAS"
    ],
    "Grupo Profissional ou Ocupacional": [
      "Enfermeira"
    ],
    "Conceito Qualitativo": [
      "Aceitação parcial"
    ],
    "Objeto Manufaturado": [
      "cadeira de banho"
    ],
    "Doença ou Síndrome": [
      "DIAGNOSTICO RELATADO"
    ]
  },
  "labels": {}
}