{
  "prontuario_id": 137,
  "text": "18:15h Admissão S: Glasgow 14, em névoa úmida, nega queixas álgicas.  O: POI de microcirurgia por hidrocefalia obstrutiva. PA 135/68 (87) mmHg, FC 95bpm, FR 20rpm, Sat 95%, T 36,2ºC. Pupilas isocóricas fotorreagentes. Confusa. Curativo cefálico tipo capacete de crepe limpo e seco externamente. Suporte de O2 sob máscara de névoa úmida. CPP sem RA. Abdomem flácido, sem massas palpáveis. Acesso venos em MSE com infusão de soroterapia. Diurese e evacução ausente em fralda descartável. Extremidades aquecidas, perfusão periférica adequada, sem edemas. Monitorizada contínuamente com parâmetros de PA não invasiva, cardioscopia e oximetria de pulso. Segue sob cuidados intensivos.  A: Plano de Tac de Crânio para amanhã (08/02) às 06h.  P: Conforme prescrição de enfermagem. Enfermeira Florence Nightingale. HIDROCEFALIA DE PRESSAO NORMAL.",
  "entities": {
    "Negação": [
      "nega",
      "sem",
      "ausente",
      "não"
    ],
    "Abreviação": [
      "O",
      "POI",
      "PA",
      "FC",
      "FR",
      "Sat",
      "T",
      "CPP",
      "RA",
      "MSE",
      "A",
      "P",
      "Tac de Crânio"
    ],
    "Conceito Temporal": [
      "POI"
    ],
    "Atributo Clínico": [
      "PA",
      "FC",
      "FR",
      "Sat",
      "T"
    ],
    "Conceito Quantitativo": [
      "95bpm",
      "20rpm",
      "95%",
      "135/68 ( 87 ) mmHg",
      "36 , 2ºC"
    ],
    "Parte do Corpo, Órgão ou Componente Orgânico": [
      "Pupilas",
      "MSE"
    ],
    "Achado": [
      "isocóricas",
      "fotorreagentes",
      "flácido",
      "Extremidades aquecidas",
      "perfusão periférica adequada"
    ],
    "Sinal ou Sintoma": [
      "Confusa",
      "RA",
      "edemas",
      "Glasgow 14",
      "queixas álgicas",
      "massas palpáveis"
    ],
    "Dispositivo Médico": [
      "crepe",
      "máscara de névoa úmida",
      "Acesso venos",
      "fralda descartável"
    ],
    "Conceito Qualitativo": [
      "limpo",
      "seco",
      "invasiva"
    ],
    "Localização ou Região Corporal": [
      "CPP"
    ],
    "Atividade de Assistência à Saúde": [
      "infusão",
      "Monitorizada contínuamente",
      "cuidados intensivos",
      "Conforme prescrição de enfermagem"
    ],
    "Função de Organismo": [
      "Diurese",
      "evacução"
    ],
    "Procedimento Diagnóstico": [
      "cardioscopia",
      "oximetria de pulso",
      "Tac de Crânio"
    ],
    "Grupo Profissional ou Ocupacional": [
      "Enfermeira"
    ],
    "Procedimento Terapêutico ou Preventivo": [
      "névoa úmida",
      "Suporte de O2",
      "máscara de névoa úmida",
      "Acesso venos"
    ],
    "Doença ou Síndrome": [
      "hidrocefalia obstrutiva",
      "HIDROCEFALIA DE PRESSAO NORMAL"
    ],
    "Objeto Manufaturado": [
      "fralda descartável"
    ]
  },
  "labels": {}
}