{
  "prontuario_id": 191,
  "text": "08:40hs- Glasgow 3, pupilas isomióticas, incisão cirúrgica cefálica limpa e seca, SNE com dieta a 75ml/h, traqueostmizado, em ventilação mecânica modo VCV, Vc 460ml, PEEP 10, FiO2 60%, secreção traqueobrônquica amarela em média quantidade, acesso venoso central E com Fentanil 2,5ml/h + Noradrenalina 4ml/h, monitorizado, estável hemodinamicamente, MV+ com roncos difusos, PAM em radial D, MMSS edemaciados +++/4, abdome pouco distendido, flácido, RHA+, SVD com diurese efetiva, evacuação ausente, úlcera sacra grau II, úlcera grau II em calcâneos, extremidades bem perfundidas, higienizado e mobilizado no leito. Enfermeira Florence Nightingale.  OUTROS TRAUMATISMOS INTRACRANIANOS.",
  "entities": {
    "Conceito Qualitativo": [
      "limpa",
      "seca"
    ],
    "Procedimento Terapêutico ou Preventivo": [
      "SNE",
      "traqueostmizado",
      "SVD",
      "incisão cirúrgica cefálica",
      "com dieta",
      "ventilação mecânica",
      "acesso venoso central",
      "mobilizado no leito"
    ],
    "Abreviação": [
      "SNE",
      "Vc",
      "PEEP",
      "FiO2",
      "E",
      "MV+",
      "PAM",
      "MMSS",
      "RHA+",
      "SVD",
      "modo VCV",
      "radial D"
    ],
    "Dispositivo Médico": [
      "SNE",
      "SVD",
      "acesso venoso central"
    ],
    "Conceito Quantitativo": [
      "75ml/h",
      "460ml",
      "10",
      "60%",
      "4ml/h",
      "média quantidade",
      "2 , 5ml/h"
    ],
    "Atributo Clínico": [
      "Vc",
      "PEEP",
      "FiO2"
    ],
    "Conceito Espacial": [
      "E"
    ],
    "Substância Farmacológica": [
      "Fentanil",
      "Noradrenalina"
    ],
    "Substância Química Orgânica": [
      "Fentanil",
      "Noradrenalina"
    ],
    "Hormônio": [
      "Noradrenalina"
    ],
    "Atividade de Assistência à Saúde": [
      "monitorizado"
    ],
    "Achado": [
      "MV+",
      "flácido",
      "RHA+",
      "higienizado",
      "pupilas isomióticas",
      "estável hemodinamicamente",
      "diurese efetiva",
      "extremidades bem perfundidas",
      "mobilizado no leito"
    ],
    "Procedimento Diagnóstico": [
      "PAM"
    ],
    "Parte do Corpo, Órgão ou Componente Orgânico": [
      "MMSS",
      "abdome",
      "calcâneos",
      "radial D"
    ],
    "Sinal ou Sintoma": [
      "edemaciados",
      "Glasgow 3",
      "secreção traqueobrônquica amarela",
      "roncos difusos",
      "pouco distendido"
    ],
    "Função de Organismo": [
      "evacuação",
      "diurese efetiva"
    ],
    "Negação": [
      "ausente"
    ],
    "Grupo Profissional ou Ocupacional": [
      "Enfermeira"
    ],
    "Doença ou Síndrome": [
      "úlcera sacra grau II",
      "úlcera grau II",
      "TRAUMATISMOS INTRACRANIANOS"
    ]
  },
  "labels": {}
}