{
  "prontuario_id": 225,
  "text": "11:25hs - Glasgow 15, pupilas isocóricas fotorreagentes, respiração espontânea em ar ambiente, SpO2 96%, passado SNG nº16 e mantida aberta devido a presença de vômito de aspecto bilioso em média quantidade, acesso venoso central D com NPT a 84 ml/h, monitorizado, estável hemodinamicamente, MV+ sem R/A, dreno de tórax E sem débito, abdome plano, flácido, indolor a palpação, RHA+, FO abdominal limpa e seca, SVD com diurese efetiva, evacuação presente, úlcera sacra grau II, extremidades bem perfundidas, higienizado e sentado no leito. Enfermeira Florence Nightingale.  EXAME GERAL E INVESTIGACAO DE PESSOAS SEM QUEIXAS OU DIAGNOSTICO RELATADO.",
  "entities": {
    "Parte do Corpo, Órgão ou Componente Orgânico": [
      "pupilas",
      "abdome"
    ],
    "Achado": [
      "isocóricas",
      "fotorreagentes",
      "MV+",
      "débito",
      "plano",
      "flácido",
      "RHA+",
      "higienizado",
      "Glasgow 15",
      "respiração espontânea",
      "estável hemodinamicamente",
      "evacuação presente",
      "extremidades bem perfundidas",
      "sentado no leito"
    ],
    "Abreviação": [
      "SpO2",
      "NPT",
      "MV+",
      "R/A",
      "RHA+",
      "FO",
      "SVD",
      "SNG nº16"
    ],
    "Atributo Clínico": [
      "SpO2"
    ],
    "Conceito Quantitativo": [
      "96%",
      "média quantidade",
      "84 ml/h"
    ],
    "Sinal ou Sintoma": [
      "vômito",
      "R/A",
      "indolor",
      "QUEIXAS",
      "aspecto bilioso"
    ],
    "Procedimento Terapêutico ou Preventivo": [
      "NPT",
      "SVD",
      "SNG nº16"
    ],
    "Atividade de Assistência à Saúde": [
      "monitorizado",
      "EXAME GERAL"
    ],
    "Negação": [
      "sem",
      "indolor",
      "SEM"
    ],
    "Conceito Espacial": [
      "E"
    ],
    "Função de Organismo": [
      "débito",
      "diurese efetiva",
      "evacuação presente"
    ],
    "Procedimento Diagnóstico": [
      "palpação",
      "INVESTIGACAO DE PESSOAS"
    ],
    "Lesão ou Envenenamento": [
      "FO"
    ],
    "Localização ou Região Corporal": [
      "abdominal"
    ],
    "Conceito Qualitativo": [
      "limpa",
      "seca",
      "aspecto bilioso"
    ],
    "Dispositivo Médico": [
      "SVD",
      "SNG nº16"
    ],
    "Grupo Profissional ou Ocupacional": [
      "Enfermeira"
    ],
    "Objeto Manufaturado": [
      "dreno de tórax"
    ],
    "Doença ou Síndrome": [
      "úlcera sacra grau II",
      "DIAGNOSTICO RELATADO"
    ]
  },
  "labels": {}
}