{
  "prontuario_id": 871,
  "text": "14:43h - GLASGOW 15, TRAQUEOSTOMIZADO EM VENTILAÇÃO MECÂNICA EM MODO PCV, PEEP 5 cmH²O, FIO² 60%, COM FILTRO BARREIRA, SONDA NASOGÁSTRICA COM DIETA EM CURSO DE 75ml/h, ABERTURA OCULAR ESPONTÂNEA, PUPILAS ISOCÓRICAS, RESPONDENDO À ESTÍMULOS VERBAIS ASSENTINDO COM A CABEÇA E ESBOÇANDO FALA, CORADO, ACESSO VENOSO PERIFÉRICO EM BRAÇO DIREITO COM SOROTERAPIA EM CURSO E SEM SINAIS FLOGÍSTICOS, PELE ÍNTEGRA, ABDOMEN FLÁCIDO E INDOLOR À PALPAÇÃO, EXTREMIDADES AQUECIDAS. MMII SEM EDEMA. DIURESE EM UROPEN COM COLETOR DE SISTEMA ABERTO COM DÉBITO AMARELADO DE 150 ml. ACADÊMICA DE ENFERMAGEM DO 8º PERÍODO FLORENCE, ORIENTADA PELA Enfermeira Florence Nightingale . EXPOSICAO A OUTROS FATORES AMBIENTAIS ARTIFICIAIS E AOS NAO ESPECIFICADOS LOCAL NAO ESPECIFICADO.",
  "entities": {
    "Procedimento Terapêutico ou Preventivo": [
      "TRAQUEOSTOMIZADO",
      "PCV",
      "DIETA",
      "SOROTERAPIA",
      "VENTILAÇÃO MECÂNICA",
      "FILTRO BARREIRA",
      "SONDA NASOGÁSTRICA",
      "ACESSO VENOSO PERIFÉRICO",
      "COLETOR DE SISTEMA ABERTO"
    ],
    "Abreviação": [
      "PCV",
      "PEEP",
      "FIO²",
      "MMII"
    ],
    "Atributo Clínico": [
      "PEEP",
      "FIO²"
    ],
    "Conceito Quantitativo": [
      "60%",
      "75ml/h",
      "5 cmH²O",
      "150 ml"
    ],
    "Parte do Corpo, Órgão ou Componente Orgânico": [
      "PUPILAS",
      "ABDOMEN",
      "MMII",
      "BRAÇO DIREITO"
    ],
    "Achado": [
      "ISOCÓRICAS",
      "CORADO",
      "FLÁCIDO",
      "GLASGOW 15",
      "ABERTURA OCULAR ESPONTÂNEA",
      "RESPONDENDO À ESTÍMULOS VERBAIS",
      "ASSENTINDO COM A CABEÇA",
      "ESBOÇANDO FALA",
      "PELE ÍNTEGRA",
      "EXTREMIDADES AQUECIDAS"
    ],
    "Negação": [
      "SEM",
      "INDOLOR"
    ],
    "Sinal ou Sintoma": [
      "INDOLOR",
      "EDEMA",
      "ESBOÇANDO FALA",
      "SINAIS FLOGÍSTICOS"
    ],
    "Procedimento Diagnóstico": [
      "PALPAÇÃO"
    ],
    "Função de Organismo": [
      "DIURESE",
      "DÉBITO"
    ],
    "Conceito Qualitativo": [
      "AMARELADO"
    ],
    "Organização Relacionada à Saúde": [
      "ENFERMAGEM"
    ],
    "Atividade de Assistência à Saúde": [
      "ORIENTADA"
    ],
    "Grupo Profissional ou Ocupacional": [
      "Enfermeira"
    ],
    "Dispositivo Médico": [
      "FILTRO BARREIRA",
      "SONDA NASOGÁSTRICA",
      "ACESSO VENOSO PERIFÉRICO",
      "COLETOR DE SISTEMA ABERTO"
    ],
    "Lesão ou Envenenamento": [
      "EXPOSICAO A OUTROS FATORES AMBIENTAIS ARTIFICIAIS"
    ]
  },
  "labels": {}
}