{
  "prontuario_id": 694,
  "text": "Paciente com história de HAS, obesidade, vem à emergência com quadro de dispnéia progressiva, ortopnéia, dispnéia paroxística noturna, edema de membros inferiores, ascite (NYHA classe IV). Ao exame da chegada com turgência jugular e presença de B3. ECG com bloqueio de ramo esquerdo. Realizado Ecocardiograma que evidenciou dilatação de cavidades esquerdas (AE = 5cm, DDVE = 7,1; DSVE = 6,0), VEFE = 32% por hipocinesia difusa; septo e parede posterior com 1,0 cm e massa ventricular de aproximadamente 400 g; insuficiência mitral leve a moderada e PSAP = 64-69 mmHg. Cintilografia miocárdica sugestiva de miocardiopatia dilatada (hipertensiva?). Iniciado manejo para insuficiência cardíaca, com diuréticos, inibidor da ECA, espironolactona e digoxina, com boa resposta clínica, tendo perdido aproximadamente 22Kg. Posteriormente iniciado com beta-bloqueador, tendo atingido dose alvo na internação. Devido à perda de função renal, acabou-se trocando captopril por isossorbida + nitrato e suspendido diuréticos, com plano de restituição dos mesmos a nível ambulatorial. Recebe alta em bom estado geral, afebril, com classe funcional I-II, etiologia possivelmente hipertensiva, com plano de seguir acompanhamento ambulatorial e fazer uso das medicações prescritas. Em caso de piora, retornar à emergência deste Hospital com esta nota de alta em mãos.",
  "entities": {
    "Abreviação": [
      "HAS",
      "ECG",
      "AE",
      "DDVE",
      "DSVE",
      "VEFE",
      "PSAP"
    ],
    "Doença ou Síndrome": [
      "HAS",
      "obesidade",
      "insuficiência mitral leve a moderada",
      "miocardiopatia dilatada",
      "insuficiência cardíaca"
    ],
    "Organização Relacionada à Saúde": [
      "emergência",
      "internação",
      "ambulatorial",
      "Hospital",
      "nível ambulatorial"
    ],
    "Sinal ou Sintoma": [
      "quadro",
      "ortopnéia",
      "edema",
      "ascite",
      "afebril",
      "piora",
      "dispnéia progressiva",
      "dispnéia paroxística noturna",
      "turgência jugular",
      "presença de B3"
    ],
    "Procedimento Diagnóstico": [
      "exame",
      "ECG",
      "Ecocardiograma",
      "Cintilografia miocárdica"
    ],
    "Atividade de Assistência à Saúde": [
      "Realizado",
      "Iniciado",
      "manejo",
      "iniciado",
      "internação",
      "trocando",
      "suspendido",
      "alta",
      "retornar",
      "plano de restituição dos mesmos",
      "uso das medicações prescritas"
    ],
    "Conceito Quantitativo": [
      "5cm",
      "32%",
      "7 , 1",
      "6 , 0",
      "1 , 0 cm",
      "400 g",
      "64-69 mmHg",
      "dose alvo"
    ],
    "Parte do Corpo, Órgão ou Componente Orgânico": [
      "septo",
      "mãos",
      "membros inferiores",
      "parede posterior"
    ],
    "Atributo Clínico": [
      "PSAP"
    ],
    "Substância Farmacológica": [
      "diuréticos",
      "espironolactona",
      "digoxina",
      "beta-bloqueador",
      "captopril",
      "inibidor da ECA",
      "isossorbida + nitrato"
    ],
    "Substância Química Orgânica": [
      "espironolactona",
      "digoxina",
      "isossorbida + nitrato"
    ],
    "Conceito Temporal": [
      "Posteriormente"
    ],
    "Aminoácido, Peptídeo ou Proteína": [
      "captopril"
    ],
    "Negação": [
      "afebril"
    ],
    "Resultado Laboratorial ou de Teste": [
      "bloqueio de ramo esquerdo",
      "dilatação de cavidades esquerdas",
      "hipocinesia difusa"
    ],
    "Achado": [
      "boa resposta clínica",
      "perdido aproximadamente 22Kg",
      "bom estado geral"
    ],
    "Classificação": [
      "classe funcional I-II"
    ],
    "Conceito Funcional": [
      "etiologia possivelmente hipertensiva"
    ]
  },
  "labels": {}
}