{
  "prontuario_id": 24,
  "text": "LUCAS, 57 anos.  # HAS. # DM 2.  Paciente admitido com quadro de IAM inferior com supradesnivelamento de ST sem comprometimento hemodinâmico. Submetido à angioplastia primária e implante de stent em 1/3 distal de CD na 6ª hora com resultado angiográfico satisfatório. Cateterismo de demais vasos: lesão de 70% em 1/3 médio DAE; lesão severa em Dg; lesões de 50% em Cx e 40% em Mg. Evolução clínica favorável, recebendo alta assintomático com retorno para o ambulatório de Cardiopatia Isquêmica do XXXX em uso de: - AAS 100 mg 1x /dia. - Ticlopidina 250 mg 12/12 horas até 25/06/03. - Metoprolol 25 mg 12/12 horas. - Enalapril 5 mg 12/12 horas. - Sinvastatina 20 mg à noite. - Glibenclamida 5 mg pela manhã.",
  "entities": {
    "Abreviação": [
      "HAS",
      "AAS",
      "DM 2",
      "IAM inferior com supradesnivelamento de ST",
      "1/3 distal de CD",
      "lesão de 70% em 1/3 médio DAE",
      "lesão severa em Dg",
      "lesões de 50% em Cx",
      "40% em Mg"
    ],
    "Doença ou Síndrome": [
      "HAS",
      "DM 2",
      "IAM inferior com supradesnivelamento de ST"
    ],
    "Atividade de Assistência à Saúde": [
      "admitido",
      "Submetido",
      "alta",
      "retorno"
    ],
    "Sinal ou Sintoma": [
      "quadro",
      "comprometimento hemodinâmico"
    ],
    "Negação": [
      "sem"
    ],
    "Procedimento Diagnóstico": [
      "Cateterismo"
    ],
    "Procedimento Terapêutico ou Preventivo": [
      "Cateterismo",
      "angioplastia primária",
      "implante de stent"
    ],
    "Parte do Corpo, Órgão ou Componente Orgânico": [
      "vasos",
      "1/3 distal de CD"
    ],
    "Substância Química Orgânica": [
      "AAS",
      "Ticlopidina",
      "Metoprolol",
      "Sinvastatina",
      "Glibenclamida"
    ],
    "Substância Farmacológica": [
      "AAS",
      "Ticlopidina",
      "Metoprolol",
      "Enalapril",
      "Sinvastatina",
      "Glibenclamida"
    ],
    "Aminoácido, Peptídeo ou Proteína": [
      "Enalapril"
    ],
    "Conceito Temporal": [
      "noite",
      "manhã"
    ],
    "Resultado Laboratorial ou de Teste": [
      "resultado angiográfico",
      "lesão de 70% em 1/3 médio DAE",
      "lesão severa em Dg",
      "lesões de 50% em Cx",
      "40% em Mg"
    ],
    "Achado": [
      "Evolução clínica favorável"
    ],
    "Organização Relacionada à Saúde": [
      "ambulatório de Cardiopatia Isquêmica"
    ],
    "Conceito Quantitativo": [
      "100 mg 1x /dia",
      "250 mg 12/12 horas",
      "25 mg 12/12 horas",
      "5 mg 12/12 horas",
      "20 mg",
      "5 mg"
    ]
  },
  "labels": {}
}