{
  "prontuario_id": 79,
  "text": "LUCAS, 49 anos.  # Síndrome do intestino curto há 17 anos.   - lesão da raiz do mesentério em acidente automobilístico 1990.   - diarréia crônica - vinha com boa adaptação às restrições dietéticas.   - aproximadamente 40 cm de delgado + colón esquerdo.  # IRC - instalação rápida - aproximadamente 2 anos de instalação.   - em hemodiálise desde janeiro 2007 - no XXXX.  - Bx Renal - cidade XXXX Jan/2007 - Glomerulopatia esclerosante difusa; sem depósito de imunocomplexos ou sinal de lesão imunomediada   - Previamente - aproxiamdamente 2 anos com sintoas típicos de insuficiência renal progressiva, culminando com fanca síndrome urêmica em dezembro de 2006.  # Atual: investigação de emagreciemtno involuntário em adulto - encerrado - atribuído à IRC + S intestino curto.  # Hipotireoidismo - compensado.  # Plano de otimizar manejo nutricional e vincular à nefrologia do XXXX para hemodiálise e visando Tx renal.   Pcte recebe alta em bom estado geral, encaminhada ao Hospital XXXX para dialise, enquanto aguarda ser chamada para iniciar dialise no XXXX ( esta na lista de espera). Tem retorno com a equipe da nutrologia e consulta para iniciar protocolo de transplante renal com doador vivo.",
  "entities": {
    "Abreviação": [
      "IRC",
      "Pcte",
      "Bx Renal",
      "S intestino curto",
      "Tx renal"
    ],
    "Doença ou Síndrome": [
      "IRC",
      "Hipotireoidismo",
      "Síndrome do intestino curto",
      "Glomerulopatia esclerosante difusa",
      "insuficiência renal progressiva",
      "síndrome urêmica",
      "S intestino curto"
    ],
    "Procedimento Terapêutico ou Preventivo": [
      "hemodiálise",
      "dialise",
      "restrições dietéticas",
      "Tx renal"
    ],
    "Negação": [
      "sem"
    ],
    "Conceito Temporal": [
      "Previamente",
      "instalação rápida",
      "2 anos de instalação",
      "aproxiamdamente 2 anos"
    ],
    "Atividade de Assistência à Saúde": [
      "investigação",
      "vincular",
      "alta",
      "encaminhada",
      "retorno",
      "consulta",
      "restrições dietéticas",
      "otimizar manejo nutricional"
    ],
    "Achado": [
      "compensado",
      "boa adaptação",
      "bom estado geral"
    ],
    "Grupo Profissional ou Ocupacional": [
      "nefrologia",
      "equipe da nutrologia"
    ],
    "Organização Relacionada à Saúde": [
      "nefrologia",
      "Hospital",
      "equipe da nutrologia"
    ],
    "Parte do Corpo, Órgão ou Componente Orgânico": [
      "raiz do mesentério",
      "colón esquerdo"
    ],
    "Fenômeno ou Processo": [
      "acidente automobilístico"
    ],
    "Sinal ou Sintoma": [
      "diarréia crônica",
      "sinal de lesão imunomediada",
      "sintoas típicos",
      "emagreciemtno involuntário"
    ],
    "Conceito Quantitativo": [
      "40 cm"
    ],
    "Procedimento Diagnóstico": [
      "Bx Renal"
    ],
    "Resultado Laboratorial ou de Teste": [
      "depósito de imunocomplexos",
      "sinal de lesão imunomediada"
    ],
    "Grupo Populacional": [
      "doador vivo"
    ]
  },
  "labels": {}
}