{
  "prontuario_id": 986,
  "text": "Paciente diabético e hipertenso internou para investigação de episódio único de síncope que ocorreu durante caminhada. Foi investigado com Tilt Test com resultado normal; cintilografia miocárdica sem alterações isquêmicas, hollter com ritmo sinusal, condução AV preservada, raras extrassístoles; ecodoppler de carótidas sem evidência de obstruções significativas; TC crânio normal; ecocardiograma transesofágico com os seguintes achados: AE 4,9, DD 5,5, DS 3,1, PP 1,1, S 1,1, VD 2,5, Déficit de relaxamento. Também realizou estudo eletrofisiológico que não evidenciou alterações.    Proposta Terapêutica:  Tratamento do diabetes e suas complicações, Captopril 12,5mg 8/8h, AAS 100mg /dia, Hidroclorotiazida 25mg /dia, Metformina 850mg VO 2x/dia,  Acompanhamento ambulatorial. Fará colonoscopia no dia 14-06-05 para avaliação de hábito intestinal.",
  "entities": {
    "Doença ou Síndrome": [
      "diabético",
      "hipertenso",
      "diabetes",
      "complicações",
      "raras extrassístoles"
    ],
    "Atividade de Assistência à Saúde": [
      "internou",
      "investigado",
      "realizou",
      "avaliação",
      "Proposta Terapêutica",
      "Acompanhamento ambulatorial"
    ],
    "Procedimento Diagnóstico": [
      "investigação",
      "hollter",
      "colonoscopia",
      "Tilt Test",
      "cintilografia miocárdica",
      "ecodoppler de carótidas",
      "TC crânio",
      "ecocardiograma transesofágico",
      "estudo eletrofisiológico"
    ],
    "Sinal ou Sintoma": [
      "síncope",
      "alterações",
      "alterações isquêmicas",
      "Déficit de relaxamento"
    ],
    "Atividade Diária ou Recreativa": [
      "caminhada"
    ],
    "Negação": [
      "sem",
      "não"
    ],
    "Procedimento Terapêutico ou Preventivo": [
      "Tratamento"
    ],
    "Substância Farmacológica": [
      "Captopril",
      "AAS",
      "Hidroclorotiazida",
      "Metformina"
    ],
    "Aminoácido, Peptídeo ou Proteína": [
      "Captopril"
    ],
    "Abreviação": [
      "AAS",
      "condução AV preservada",
      "AE 4 , 9",
      "DD 5 , 5",
      "DS 3 , 1",
      "PP 1",
      "VD 2 , 5"
    ],
    "Substância Química Orgânica": [
      "AAS",
      "Hidroclorotiazida",
      "Metformina"
    ],
    "Conceito Quantitativo": [
      "episódio único",
      "12 , 5mg 8/8h",
      "100mg /dia",
      "25mg /dia",
      "850mg VO 2x/dia"
    ],
    "Resultado Laboratorial ou de Teste": [
      "resultado normal",
      "ritmo sinusal",
      "condução AV preservada",
      "raras extrassístoles",
      "evidência de obstruções significativas",
      "AE 4 , 9",
      "DD 5 , 5",
      "DS 3 , 1",
      "PP 1",
      "S 1 , 1",
      "VD 2 , 5",
      "Déficit de relaxamento"
    ],
    "Achado": [
      "ritmo sinusal",
      "condução AV preservada"
    ],
    "Anormalidade Anatômica": [
      "evidência de obstruções significativas"
    ],
    "Função de Organismo": [
      "hábito intestinal"
    ]
  },
  "labels": {}
}