{
  "prontuario_id": 89,
  "text": "PACIENTE COM HAS EM USO DE HCTZ, ENXAQUECA (USO DE DERIVADOS DO ERGOT), JÁ COM PASSADO DE ANGINA E CORONARIAS NORMAIS, TEVE QUADRO DE SÍNCOPE AO ORTOSTATISMO SEGUIDO DE SUDORESE E MAL ESTAR. FOI REALIZADO ECG NO DOMICILIO QUE MOSTROU SUPRA DESNIVEL DE ST DE V1 - V4. CHEGOU AO XXXX JÁ ASSINTOMATICA COM ECG NORMAL. ENZIMAS TAMBEM NORMAIS. CONCLUIU-SE POR ANGINA VASOESPASTICA (PARA A QUAL SE ATRIBUI PROVAVEL CARDIOPATIA ISQUEMICA INCIPIENTE). NÃO SE PODE EXCLUIR 2 FATORES PRECIPITANTES: HIPOTENSAO POR CONSTRIÇÃO DE VOLUME PELA HCTZ E VASOESPASMO ASSOCIADO AO USO DE DERIVADOS DO ERGOT.  ASSIM FORAM SUSPENSOS O ORMIGREM E A HCTZ. INICIADO MONONITRATO (CEFALEIA COM DINITRATO), BLOQUEADOR DE CANAIS DE CALCIO (AMLODIPINA), AAS, ESTATINA (DOSE A SER REAJUSTADA C/ PERFIL LIPIDICO APOS ALTA). ALTA ASSINTOMATICA POR 72H.",
  "entities": {
    "Abreviação": [
      "HAS",
      "HCTZ",
      "ECG",
      "AAS",
      "ECG NORMAL"
    ],
    "Doença ou Síndrome": [
      "HAS",
      "ENXAQUECA",
      "ANGINA VASOESPASTICA",
      "CARDIOPATIA ISQUEMICA INCIPIENTE"
    ],
    "Substância Farmacológica": [
      "HCTZ",
      "ORMIGREM",
      "MONONITRATO",
      "DINITRATO",
      "AMLODIPINA",
      "AAS",
      "ESTATINA",
      "DERIVADOS DO ERGOT",
      "BLOQUEADOR DE CANAIS DE CALCIO"
    ],
    "Substância Química Orgânica": [
      "HCTZ",
      "MONONITRATO",
      "DINITRATO",
      "AMLODIPINA",
      "AAS",
      "ESTATINA"
    ],
    "Conceito Temporal": [
      "PASSADO",
      "APOS",
      "72H"
    ],
    "Sinal ou Sintoma": [
      "ANGINA",
      "QUADRO",
      "SUDORESE",
      "ASSINTOMATICA",
      "CEFALEIA",
      "SÍNCOPE AO ORTOSTATISMO",
      "MAL ESTAR"
    ],
    "Procedimento Diagnóstico": [
      "ECG"
    ],
    "Negação": [
      "ASSINTOMATICA",
      "NÃO"
    ],
    "Função Patológica": [
      "VASOESPASMO"
    ],
    "Atividade de Assistência à Saúde": [
      "SUSPENSOS",
      "INICIADO",
      "REAJUSTADA",
      "ALTA"
    ],
    "Conceito Quantitativo": [
      "DOSE"
    ],
    "Achado": [
      "CORONARIAS NORMAIS"
    ],
    "Resultado Laboratorial ou de Teste": [
      "SUPRA DESNIVEL DE ST DE V1 - V4",
      "ECG NORMAL",
      "ENZIMAS TAMBEM NORMAIS"
    ],
    "Procedimento Laboratorial": [
      "PERFIL LIPIDICO"
    ]
  },
  "labels": {}
}