{
  "prontuario_id": 355,
  "text": "          Paciente previamente hígida (história de HAS interrogada), interna neste hospital devido a quadro de forte dor precordial definido pelo ECG como IAM de parede inferior do miocárdio. Submetida a estudo hemodinâmico logo na chegada, apresentando lesão de 95% em óstio de CD + oclusão de mesma artéria em porção final do segmento proximal. Realizado ACTP + colocação de stent na região ocluída, associado a ACTP de óstio e colocação de segundo stent nesta localização; resultado final TIMI 3; procedimento sem intercorrências.  Evoluiu bem após procedimento, sem dor ou sinais de isquemia miocárdica.  Recebe alta em excelente estado geral, sinais vitais estáveis, com orientações de retorno ao ambulatório de cardiopatia isquêmica para revisão e acompanhamento posterior.  OBS: paciente apresenta ao exame radiográfico do tórax nódulo calcificado e de limites precisos em lobo superior de pulmão direito, já presente em radiografias prévias e sem alterações; como a característica e a evolução radiográfica favorecem o diagnóstico de nódulo benigno, sugere-se acompanhamento radiográfico.",
  "entities": {
    "Conceito Temporal": [
      "previamente",
      "após",
      "prévias"
    ],
    "Achado": [
      "hígida",
      "característica",
      "Evoluiu bem",
      "excelente estado geral",
      "sinais sinais vitais vitais estáveis estáveis",
      "evolução radiográfica"
    ],
    "Abreviação": [
      "HAS",
      "ECG",
      "ACTP",
      "IAM de parede inferior do miocárdio",
      "óstio de CD"
    ],
    "Doença ou Síndrome": [
      "HAS",
      "IAM de parede inferior do miocárdio"
    ],
    "Atividade de Assistência à Saúde": [
      "interna",
      "alta",
      "orientações",
      "retorno",
      "revisão",
      "acompanhamento posterior",
      "acompanhamento radiográfico"
    ],
    "Organização Relacionada à Saúde": [
      "hospital",
      "ambulatório de cardiopatia isquêmica"
    ],
    "Objeto Manufaturado": [
      "hospital"
    ],
    "Sinal ou Sintoma": [
      "quadro",
      "intercorrências",
      "dor",
      "alterações",
      "forte dor precordial",
      "sinais de isquemia miocárdica"
    ],
    "Procedimento Diagnóstico": [
      "ECG",
      "procedimento",
      "estudo hemodinâmico",
      "exame radiográfico do tórax",
      "em radiografias"
    ],
    "Procedimento Terapêutico ou Preventivo": [
      "ACTP",
      "procedimento",
      "colocação de stent",
      "ACTP de óstio",
      "colocação de segundo stent",
      "acompanhamento radiográfico"
    ],
    "Negação": [
      "sem"
    ],
    "Conceito Qualitativo": [
      "característica"
    ],
    "Lesão ou Envenenamento": [
      "lesão de 95%"
    ],
    "Resultado Laboratorial ou de Teste": [
      "lesão de 95%",
      "resultado final TIMI 3",
      "nódulo calcificado",
      "limites precisos em lobo superior de pulmão direito",
      "nódulo benigno"
    ],
    "Parte do Corpo, Órgão ou Componente Orgânico": [
      "óstio de CD"
    ],
    "Localização ou Região Corporal": [
      "região ocluída"
    ],
    "Classificação": [
      "resultado final TIMI 3"
    ],
    "Processo Neoplásico": [
      "nódulo benigno"
    ]
  },
  "labels": {}
}