{
  "prontuario_id": 907,
  "text": "# avc isquemico em bulbo lateral esquerdo - hemiparesia direita - força grau iv, disartria. discreta alteração de IX e X. # placa complexa em aorta com trombo. # sem estenose carotidea significativa. # tabagismo. # sindrome metabólica. - Dm. # ronco + apneia do sono.   Paciente interna com quadro agudo de hemiparesia direita e disartria. Tc inicial e controle sem evidência de isquemia. Realizado rnm de encefalo que mostrou isquemia bulbo - pontina a esquerda. Eco cardio transesofagico com placa complexa em aorta com trombo. Indicação de anticoagulação. Paciente apresenta melhora clinica significativa, tem alta com hemiparesia direita força grau iv, disartria leve. Paciente deseja alta. Alta em uso de  Sinvastatina 20mg vo 1x a noite. Varfarina 5mg vo 1x ao dia. AAS 300mg vo 1x até INR alvo. Metformina  850mg vo 1x antes do café.  Tem alta com plano de retorno em ambulatorio de neuovascular no dia 03/06 para ver TP. Encaminhar fisioterapia e fono. Discutir conforme evolução tempo de anticoagulação.  Se piora retorno a emergência.  ",
  "entities": {
    "Sinal ou Sintoma": [
      "disartria",
      "ronco",
      "hemiparesia direita",
      "discreta alteração",
      "quadro agudo"
    ],
    "Abreviação": [
      "IX",
      "X",
      "Dm",
      "vo",
      "AAS",
      "TP",
      "fono",
      "avc isquemico",
      "rnm de encefalo",
      "Eco cardio transesofagico"
    ],
    "Parte do Corpo, Órgão ou Componente Orgânico": [
      "aorta"
    ],
    "Função Patológica": [
      "trombo"
    ],
    "Negação": [
      "sem"
    ],
    "Doença ou Síndrome": [
      "tabagismo",
      "Dm",
      "avc isquemico",
      "estenose carotidea significativa",
      "sindrome metabólica",
      "apneia do sono"
    ],
    "Atividade de Assistência à Saúde": [
      "interna",
      "controle",
      "Indicação",
      "alta",
      "Alta",
      "Encaminhar",
      "Discutir",
      "retorno",
      "plano de retorno"
    ],
    "Conceito Temporal": [
      "inicial",
      "noite",
      "até",
      "evolução",
      "tempo",
      "quadro agudo",
      "antes do café"
    ],
    "Procedimento Terapêutico ou Preventivo": [
      "anticoagulação"
    ],
    "Substância Química Orgânica": [
      "Sinvastatina",
      "Varfarina",
      "AAS",
      "Metformina"
    ],
    "Substância Farmacológica": [
      "Sinvastatina",
      "Varfarina",
      "AAS",
      "Metformina"
    ],
    "Substância Perigosa ou Venenosa": [
      "Varfarina"
    ],
    "Resultado Laboratorial ou de Teste": [
      "TP",
      "força grau iv",
      "evidência de isquemia",
      "isquemia bulbo - pontina a esquerda",
      "placa complexa em aorta com trombo",
      "INR alvo"
    ],
    "Organização Relacionada à Saúde": [
      "fisioterapia",
      "fono",
      "emergência",
      "ambulatorio de neuovascular"
    ],
    "Localização ou Região Corporal": [
      "bulbo lateral esquerdo"
    ],
    "Procedimento Diagnóstico": [
      "rnm de encefalo",
      "Eco cardio transesofagico"
    ],
    "Achado": [
      "melhora clinica significativa"
    ],
    "Conceito Quantitativo": [
      "1x",
      "1x ao dia"
    ]
  },
  "labels": {}
}