{
  "prontuario_id": 143,
  "text": "PACIENTE COM FIBRILAÇÃO ATRIAL, ICC FE 40%, DUPLA LESÃO AÓRTICA COM PREDOMÍNIO DE ESTENOSE (GDTE MAX 73), SINTOMÁTICA, C/ INDICAÇÃO CIRÚRGICA. INSUFICIÊNCIA MITRAL LEVE / MOD. CAT COM CORONÁRIAS NORMAIS. PACIENTE PROCURA EMERGÊNCIA COM QUADRO DE TROMBOSE VENOSA PROFUNDA EM MEMBRO INFERIOR DIREITO, ATÉ ILÍACAS. DISCUTIDO EM EQUIPE, OPTADO POR ANTICOAGULAÇÃO ORAL A MÉDIO PRAZO, PARA REDUZIR ELEVADO RISCO CIRÚRGICO NO MOMENTO. SE DESCOMPENSAÇÃO REFRATÁRIA A TRATAMENTO CLÍNICO, CONSIDERAR IMPLANTE DE FILTRO DE VEIA CAVA VIA FEM ESQUERDA E TROCA VALVULA. SE BOA EVOLUÇÃO, CIRURGIA ELETIVA APÓS PERÍODO DE MAIOR RISCO. RECEBE ALTA EM USO DAS MEDICAÇÕES ABAIXO RELACIONADAS E RETORNO AMBULATORIAL PARA SEGUIMENTO.",
  "entities": {
    "Abreviação": [
      "ICC",
      "CAT",
      "FE 40%",
      "INSUFICIÊNCIA MITRAL LEVE / MOD",
      "FEM ESQUERDA"
    ],
    "Doença ou Síndrome": [
      "ICC",
      "FIBRILAÇÃO ATRIAL",
      "INSUFICIÊNCIA MITRAL LEVE / MOD",
      "TROMBOSE VENOSA PROFUNDA",
      "DESCOMPENSAÇÃO REFRATÁRIA"
    ],
    "Sinal ou Sintoma": [
      "SINTOMÁTICA",
      "QUADRO"
    ],
    "Procedimento Terapêutico ou Preventivo": [
      "CAT",
      "REDUZIR",
      "MEDICAÇÕES",
      "INDICAÇÃO CIRÚRGICA",
      "ANTICOAGULAÇÃO ORAL",
      "TRATAMENTO CLÍNICO",
      "IMPLANTE DE FILTRO DE VEIA CAVA",
      "TROCA VALVULA",
      "CIRURGIA ELETIVA"
    ],
    "Procedimento Diagnóstico": [
      "CAT"
    ],
    "Organização Relacionada à Saúde": [
      "EMERGÊNCIA",
      "EQUIPE"
    ],
    "Parte do Corpo, Órgão ou Componente Orgânico": [
      "ILÍACAS",
      "MEMBRO INFERIOR DIREITO",
      "FEM ESQUERDA"
    ],
    "Conceito Temporal": [
      "APÓS",
      "MÉDIO PRAZO",
      "NO MOMENTO"
    ],
    "Atividade de Assistência à Saúde": [
      "ALTA",
      "SEGUIMENTO",
      "RETORNO AMBULATORIAL"
    ],
    "Substância Farmacológica": [
      "MEDICAÇÕES"
    ],
    "Resultado Laboratorial ou de Teste": [
      "FE 40%",
      "DUPLA LESÃO AÓRTICA COM PREDOMÍNIO DE ESTENOSE",
      "GDTE MAX 73",
      "CORONÁRIAS NORMAIS"
    ],
    "Achado": [
      "BOA BOA EVOLUÇÃO EVOLUÇÃO"
    ]
  },
  "labels": {}
}