{
  "prontuario_id": 265,
  "text": "PACIENTE COM PROTESE VALVULAR MECANICA AORTICA EM 1995 POR ESTENOSE AORTICA, REOPERAÇAO EM 1996 POR LEAK PARAVALVULAR, EM ANTICOAGULAÇAO DESDE ENTAO, EM ACOMPANHAMENTO COM MEDICO EXTERNO.  VEIO À XXXX EM 09/08/03 POR DISPNEIA + CANSAÇO, APRESENTANDO BRADICARDIA IMPORTANTE (FC EM TORNO DE 40 bpm), ECG COM BRADICARDIA E BLOQUEIO TRIFASCICULAR. COMO USAVA DIGOXINA, AGUARDOU-SE NIVEL SÉRICO PARA DECISÃO SOBRE NECESSIDADE DE MARCAPASSO. EM 14/08, ENTRETANTO,  APRESENTOU PIORA DOS SINTOMAS E FOI ENTÃO COLOCADO MP DEFINITIVO. O PACIENTE APRESENTOU BOA EVOLUÇÃO APÓS A COLOCAÇÃO DO MP, APENAS COM 2 EPISÓDIOS DE EPISTAXE NÃO VOLUMOSAS, COM INR = 2. COMO DEVE PERSISTIR ANTICOAGULADO, FOI REALIZADA AVALIAÇÃO PELA CONSULTORIA DA OTORRINO, COM LESÃO DA MUCOSA SEPTAL POR MANIPULAÇÃO, SENDO FEITO TTO E SERÁ REAVALIADO AMBULATORIALMENTE.  RECEBE ALTA EM BOAS CONDIÇÕES, COM MP COM BOM FUNCIONAMENTO, RETORNO AMBULATORIAL RPECOCE COM OTORRINO PARA REAVALIAÇÃO E RETORNO EM DEZEMBRO PARA REIVSÃO DO MP COM CIRURGIA CARDIACA. DEVE MANTER MEDICAÇÕES EM USO PRÉVIO E ACOMPANHAMENTO COM SEU MÉDICO ASSISTENTE.",
  "entities": {
    "Procedimento Terapêutico ou Preventivo": [
      "REOPERAÇAO",
      "ANTICOAGULAÇAO",
      "MARCAPASSO",
      "TTO",
      "MP",
      "PROTESE VALVULAR MECANICA AORTICA",
      "MP DEFINITIVO",
      "COLOCAÇÃO DO MP",
      "PERSISTIR ANTICOAGULADO",
      "CIRURGIA CARDIACA"
    ],
    "Atividade de Assistência à Saúde": [
      "ACOMPANHAMENTO",
      "DECISÃO",
      "AVALIAÇÃO",
      "ALTA",
      "REAVALIAÇÃO",
      "RETORNO",
      "REAVALIADO AMBULATORIALMENTE",
      "RETORNO AMBULATORIAL",
      "REIVSÃO DO MP",
      "MANTER MEDICAÇÕES"
    ],
    "Sinal ou Sintoma": [
      "DISPNEIA",
      "CANSAÇO",
      "BRADICARDIA",
      "DE EPISTAXE"
    ],
    "Conceito Qualitativo": [
      "IMPORTANTE",
      "PIORA"
    ],
    "Abreviação": [
      "FC",
      "ECG",
      "TTO",
      "MP",
      "OTORRINO",
      "MP DEFINITIVO",
      "COLOCAÇÃO DO MP",
      "CONSULTORIA DA OTORRINO",
      "REIVSÃO DO MP"
    ],
    "Atributo Clínico": [
      "FC"
    ],
    "Procedimento Diagnóstico": [
      "ECG"
    ],
    "Substância Farmacológica": [
      "DIGOXINA"
    ],
    "Substância Química Orgânica": [
      "DIGOXINA"
    ],
    "Dispositivo Médico": [
      "MARCAPASSO",
      "MP",
      "PROTESE VALVULAR MECANICA AORTICA",
      "MP DEFINITIVO",
      "COLOCAÇÃO DO MP"
    ],
    "Conceito Temporal": [
      "APÓS",
      "EPISÓDIOS",
      "RPECOCE",
      "PRÉVIO"
    ],
    "Negação": [
      "NÃO"
    ],
    "Conceito Quantitativo": [
      "VOLUMOSAS",
      "40 bpm"
    ],
    "Organização Relacionada à Saúde": [
      "OTORRINO",
      "CONSULTORIA DA OTORRINO",
      "MÉDICO ASSISTENTE"
    ],
    "Grupo Profissional ou Ocupacional": [
      "OTORRINO",
      "MEDICO EXTERNO",
      "MÉDICO MÉDICO ASSISTENTE ASSISTENTE"
    ],
    "Doença ou Síndrome": [
      "ESTENOSE AORTICA",
      "LEAK PARAVALVULAR"
    ],
    "Função Patológica": [
      "LEAK PARAVALVULAR"
    ],
    "Resultado Laboratorial ou de Teste": [
      "BRADICARDIA E BLOQUEIO TRIFASCICULAR",
      "NIVEL SÉRICO",
      "INR = 2"
    ],
    "Procedimento Laboratorial": [
      "NIVEL SÉRICO"
    ],
    "Achado": [
      "BOA BOA EVOLUÇÃO EVOLUÇÃO",
      "BOAS CONDIÇÕES",
      "BOM FUNCIONAMENTO"
    ],
    "Lesão ou Envenenamento": [
      "LESÃO DA MUCOSA SEPTAL POR MANIPULAÇÃO"
    ],
    "Atividade de Máquina": [
      "BOM FUNCIONAMENTO"
    ]
  },
  "labels": {}
}