{
  "prontuario_id": 376,
  "text": "PACIENTE COM: - DM 2. - OBESIDADE. - HAS. - DISLIPIDEMIA. - CARDIOPATIA ISQUEMICA ( STENT ADAE 1/3 PROXIMAL 03/2004 , STENT AMgCx 1/3 DISTAL 09/2004). APRESENTANDO ANGINA, REALIZOU ERGOMETRIA POSITIVA, TENDO FEITO CATETERISMO DIA 11/02 QUE DEMONSTROU REESTENOSE GRAVE INTRA-STENT DA AMgCx, INTERNOU PARA REALIZAÇÃO DE ANGIOPLASTIA INTRA-STENT, COM SUCESSO ANGIOGRÁFICO E FLUXO TIMI 3, SEM IMPLANTE DE STENT. RECEBE ALTA EM BOM ESTADO GERAL, COM OS SEGUINTES: - TICLOPIDINA 250 MG 1 CP 12/12 HORAS, CONTÍNUO. - AAS 100 MG 1 CP CONTÍNUO. - MANTER USO DAS MEDICAÇÕES HABITUAIS E ACOMPANHAR COM SEU MÉDICO.",
  "entities": {
    "Doença ou Síndrome": [
      "OBESIDADE",
      "HAS",
      "DISLIPIDEMIA",
      "DM 2",
      "CARDIOPATIA ISQUEMICA",
      "REESTENOSE GRAVE"
    ],
    "Abreviação": [
      "HAS",
      "AAS",
      "DM 2",
      "DA AMgCx"
    ],
    "Dispositivo Médico": [
      "STENT"
    ],
    "Parte do Corpo, Órgão ou Componente Orgânico": [
      "ADAE",
      "DA AMgCx"
    ],
    "Sinal ou Sintoma": [
      "ANGINA"
    ],
    "Grupo Profissional ou Ocupacional": [
      "MÉDICO"
    ],
    "Conceito Espacial": [
      "INTRA-STENT"
    ],
    "Atividade de Assistência à Saúde": [
      "INTERNOU",
      "ALTA",
      "ACOMPANHAR"
    ],
    "Negação": [
      "SEM"
    ],
    "Substância Farmacológica": [
      "TICLOPIDINA",
      "AAS",
      "MEDICAÇÕES HABITUAIS"
    ],
    "Substância Química Orgânica": [
      "TICLOPIDINA",
      "AAS"
    ],
    "Conceito Temporal": [
      "CONTÍNUO",
      "12/12 HORAS"
    ],
    "Procedimento Terapêutico ou Preventivo": [
      "ANGIOPLASTIA INTRA-STENT",
      "IMPLANTE IMPLANTE DE DE STENT STENT",
      "MEDICAÇÕES HABITUAIS"
    ],
    "Achado": [
      "SUCESSO ANGIOGRÁFICO",
      "BOM BOM ESTADO ESTADO GERAL GERAL"
    ],
    "Resultado Laboratorial ou de Teste": [
      "FLUXO TIMI 3"
    ],
    "Conceito Quantitativo": [
      "100 MG 1 CP"
    ]
  },
  "labels": {}
}