{
  "prontuario_id": 2,
  "text": "Paciente de 75 anos, cardiopata isquêmico (IAM inf mar/02 - ACTP + stent em Cx; SCA s/ ST em dez/03) hipertenso prévio, dislipidêmico, portador de Insuficiência Renal Crônica e gota. Vem transferido ao CTI / XXXX no dia 28/02/2004 por dispnéia progressiva e angina. Iniciado tratamento clínico para SCA e Edema Agudo de Pulmão, obtendo-se boa resposta. Apresentou elevação discreta de CK-MB (32), sem alterações compatíveis com isquemia recente ao ECG.  Submetido, em 02/03/2004, a avaliação angiográfica, que evidenciou restenose intra-stent e proximal ao stent em DAE e lesão em 1a diagonal. Realizada angioplastia de artéria diagonal e ACTP + stent em DA, com bom resultado angiografico. O paciente teve boa evoluçao após o procedimento, recebe alta em boas condições clínicas, estável. Orientaçao de manter medicações acima relacionadas, e utilizar ticlopidina 250 mg 12/12 h por 30 dias. Retorna ao ambulatório da cardio (previamente já em acompanhamento).",
  "entities": {
    "Doença ou Síndrome": [
      "dislipidêmico",
      "gota",
      "SCA",
      "cardiopata cardiopata isquêmico isquêmico",
      "IAM inf",
      "SCA s/ ST",
      "hipertenso prévio",
      "Insuficiência Renal Crônica",
      "Edema Agudo de Pulmão"
    ],
    "Atividade de Assistência à Saúde": [
      "transferido",
      "Iniciado",
      "Submetido",
      "recebe",
      "alta",
      "Retorna",
      "acompanhamento",
      "Orientaçao de manter medicações"
    ],
    "Organização Relacionada à Saúde": [
      "CTI",
      "ambulatório da cardio"
    ],
    "Abreviação": [
      "CTI",
      "SCA",
      "ECG",
      "IAM inf",
      "stent",
      "SCA s/ ST",
      "ambulatório da cardio"
    ],
    "Sinal ou Sintoma": [
      "angina",
      "alterações",
      "dispnéia progressiva"
    ],
    "Conceito Quantitativo": [
      "32",
      "250 mg 12/12"
    ],
    "Negação": [
      "sem"
    ],
    "Procedimento Diagnóstico": [
      "ECG",
      "procedimento",
      "avaliação angiográfica"
    ],
    "Lesão ou Envenenamento": [
      "lesão"
    ],
    "Parte do Corpo, Órgão ou Componente Orgânico": [
      "DA",
      "angioplastia de artéria diagonal"
    ],
    "Conceito Temporal": [
      "após",
      "previamente",
      "30 dias"
    ],
    "Procedimento Terapêutico ou Preventivo": [
      "procedimento",
      "stent",
      "tratamento clínico",
      "angioplastia de artéria diagonal"
    ],
    "Achado": [
      "estável",
      "boa resposta",
      "bom resultado angiografico",
      "boa evoluçao",
      "boas condições clínicas"
    ],
    "Substância Química Orgânica": [
      "ticlopidina"
    ],
    "Substância Farmacológica": [
      "ticlopidina"
    ],
    "Resultado Laboratorial ou de Teste": [
      "CK-MB",
      "restenose intra-stent",
      "bom resultado angiografico"
    ],
    "Função Patológica": [
      "isquemia recente"
    ]
  },
  "labels": {}
}