{
  "prontuario_id": 994,
  "text": "   PACIENTE MASCULINO, DE 75 ANOS, PORTADOR DE HAS, DM II. APRESNTOU AVC EM SET/03, REALIZANDO ENDARTERECTOMIA CAROTÍDEA EM SET/03. CHEGA À EMERGÊNCIA NO DIA 16/06/04 COM ANGINA. FETIO DIAGNÓSTICO DE ANGINA INSTÁVEL. NO DIA 17/06/04, APRESENTOU NOVAMENTE DOR COM ALTERAÇÃO EM ECG E ENZIMAS (IAM COM SUPRA DE ST). PACIENTE FOI ENCAMINHADO PARA ANGIOPLASTIA PRIMARIA 17/06/04: ADAE APRESENTA UMA LESÃO SEGMENTAR E SEVERA NO TERÇO PROXIMAL, LESÃO DISCRETA NO TERÇO MÉDIO, LESÃO DE APROXIMADAMENTE 80% NO TERÇO DISTAL; ACX ISENTA DE LESÕES ATEROMATOSAS SIGNIFICATIVAS; RAMO DESCENDENTE POSTERIOR DA ARTÉRIA CORONÁRIA DIREITA DE FINO CALIBRE E COM LESÃO SEVERA NO TERÇO MÉDIO. REALIZADO ANGIOPLASTIA COM IMPLANTE DE STENT NOS TERÇOS PROXIMAL E MÉDIO DA ADAE COM SUCESSO (TIMI III). PACIENTE FOI INCLUIDO NO ESTUDO XXXX - 6. ECO ABDÔMEN TOTAL 17/06/04: SEM EVIDÊNCIA DE ANEURISMA NA AORTA ABDOMINAL. EVOLUI BEM DURANTE A INTERNAÇÃO. ECOCARDIO 23/06/04: AORTOESCLEROSE COM ACOMETIMENTO VALVULAR NÃO OBSTRUTIVO. VE COM DÉFICIT RELAXAMENTO, FUNÇÃO SISTÓLICA GLOBAL E SEGMENTAR PRESERVADAS. CALCIFICAÇÃO DO ANEL MITRAL; FE: 66%. PACIENTE APRESENTOU BOA EVOLUÇAO CLINICA, SEM DOR APÓS O PROCDIMENTO E SEM EVIDENCIA DE CONGESTAO. APRESENTOU TAMBÉM MELHORA DO QUADRO NEUROLOGICO DURANTE A INTERNAÇAO. RECEBE ALTA EM BOAS CONDIÇOES, COM ORIENTAÇAO DE MANTER AS MEDICAÇOES ACIMA DESCRITAS E RETORNO AMBULATORIAL PRECOCE.",
  "entities": {
    "Abreviação": [
      "HAS",
      "AVC",
      "ECG",
      "ADAE",
      "ACX",
      "ECOCARDIO",
      "VE",
      "DM II",
      "IAM COM SUPRA DE ST",
      "TERÇOS PROXIMAL E MÉDIO DA ADAE",
      "ECO ABDÔMEN TOTAL",
      "FE : 66%"
    ],
    "Doença ou Síndrome": [
      "HAS",
      "AVC",
      "DM II",
      "ANGINA INSTÁVEL",
      "IAM COM SUPRA DE ST",
      "ANEURISMA NA AORTA ABDOMINAL"
    ],
    "Organização Relacionada à Saúde": [
      "EMERGÊNCIA",
      "INTERNAÇÃO",
      "INTERNAÇAO"
    ],
    "Sinal ou Sintoma": [
      "ANGINA",
      "DOR",
      "EVIDÊNCIA",
      "EVIDENCIA",
      "QUADRO NEUROLOGICO"
    ],
    "Produto Intelectual": [
      "DIAGNÓSTICO"
    ],
    "Resultado Laboratorial ou de Teste": [
      "ALTERAÇÃO",
      "AORTOESCLEROSE",
      "LESÃO SEGMENTAR",
      "LESÃO DISCRETA",
      "TIMI III",
      "ACOMETIMENTO VALVULAR",
      "DÉFICIT RELAXAMENTO",
      "FUNÇÃO SISTÓLICA GLOBAL E SEGMENTAR PRESERVADAS",
      "CALCIFICAÇÃO DO ANEL MITRAL",
      "FE : 66%"
    ],
    "Procedimento Diagnóstico": [
      "ECG",
      "ECOCARDIO",
      "ECO ABDÔMEN TOTAL"
    ],
    "Atividade de Assistência à Saúde": [
      "ENCAMINHADO",
      "ALTA",
      "ORIENTAÇAO"
    ],
    "Procedimento Terapêutico ou Preventivo": [
      "ANGIOPLASTIA",
      "ENDARTERECTOMIA CAROTÍDEA",
      "ANGIOPLASTIA COM IMPLANTE DE STENT"
    ],
    "Parte do Corpo, Órgão ou Componente Orgânico": [
      "ADAE",
      "ACX",
      "VE",
      "TERÇOS PROXIMAL E MÉDIO DA ADAE"
    ],
    "Conceito Qualitativo": [
      "SEVERA",
      "FINO CALIBRE"
    ],
    "Lesão ou Envenenamento": [
      "LESÃO",
      "LESÃO SEVERA"
    ],
    "Achado": [
      "SUCESSO",
      "MELHORA",
      "BOA EVOLUÇAO CLINICA",
      "BOAS CONDIÇOES"
    ],
    "Atividade de Pesquisa": [
      "ESTUDO"
    ],
    "Negação": [
      "SEM",
      "NÃO"
    ],
    "Conceito Temporal": [
      "EVOLUI",
      "APÓS",
      "PRECOCE"
    ],
    "Função Patológica": [
      "CONGESTAO",
      "DÉFICIT RELAXAMENTO"
    ],
    "Conceito Espacial": [
      "TERÇO PROXIMAL",
      "TERÇO MÉDIO",
      "TERÇO DISTAL"
    ]
  },
  "labels": {}
}