{
  "prontuario_id": 945,
  "text": "                PACIENTE COM HISTÓRIA DE DOR PRECORDIAL EM APERTO COM IRRADIAÇÃO PARA MEMBROS SUPERIORES, ACOMPANHADA DE PARESTESIAS E TONTURAS. RECEBEU DICLOFENACO INTRAMUSCULAR. QUADRO CLÍNICO INICIADO DIA 07-08-06. PROCURA ATENDIMENTO HOSPITALAR EM SAPUCAIA DO SUL DIA 08-08-06 PELAS MESMAS QUEIXAS: ECG SEM ALTERAÇÕES, CK 3429 E CK-MB 62. É TRANSFERIDO PARA PARA O CTI DO XXXX. NA CHEGADA, ECG E RX SEM ALTERAÇÕES, CK 1671 E TROPONINA MENOR QUE 0,01. EVOLUI COM RESOLUÇÃO DA DOR (ALTERAÇÕES DE MARCADORES DE INJÚRIA CARDIACA PROVAVELMENTE SECUNDÁRIA A INJEÇÕES IM DE AINE).  RECEBE ALTA EM ÓTIMAS CONDIÇÕES CLÍNICAS E COM PLANO DE MANTER ACOMPANHAMENTO EM POSTO DE SAÚDE POR DOR TORÁCICA NÃO CARDIOGÊNICA.",
  "entities": {
    "Sinal ou Sintoma": [
      "IRRADIAÇÃO",
      "TONTURAS",
      "QUEIXAS",
      "ALTERAÇÕES",
      "DOR",
      "DOR PRECORDIAL",
      "QUADRO CLÍNICO",
      "DOR TORÁCICA"
    ],
    "Atividade de Assistência à Saúde": [
      "RECEBEU",
      "TRANSFERIDO",
      "ALTA",
      "ATENDIMENTO HOSPITALAR",
      "PLANO DE MANTER ACOMPANHAMENTO"
    ],
    "Procedimento Diagnóstico": [
      "ECG",
      "RX"
    ],
    "Abreviação": [
      "ECG",
      "CTI",
      "RX"
    ],
    "Negação": [
      "SEM",
      "NÃO"
    ],
    "Organização Relacionada à Saúde": [
      "CTI",
      "ATENDIMENTO HOSPITALAR",
      "POSTO DE SAÚDE"
    ],
    "Conceito Temporal": [
      "EVOLUI"
    ],
    "Substância Farmacológica": [
      "AINE",
      "DICLOFENACO INTRAMUSCULAR"
    ],
    "Conceito Qualitativo": [
      "EM APERTO"
    ],
    "Parte do Corpo, Órgão ou Componente Orgânico": [
      "MEMBROS SUPERIORES"
    ],
    "Procedimento Terapêutico ou Preventivo": [
      "DICLOFENACO INTRAMUSCULAR"
    ],
    "Resultado Laboratorial ou de Teste": [
      "CK 3429",
      "CK-MB 62",
      "CK 1671",
      "TROPONINA MENOR QUE 0 , 01",
      "ALTERAÇÕES DE MARCADORES DE INJÚRIA CARDIACA"
    ],
    "Achado": [
      "ÓTIMAS CONDIÇÕES CLÍNICAS"
    ]
  },
  "labels": {}
}