{
  "prontuario_id": 475,
  "text": "LUCAS\n\nCMD APÓS GESTAÇÃO.\nIMPLANTOU RESSINC E CDI EM NOV DE 15.\nNÃO REALIZOU CONSULTA EM NOSSO AMBU DO MP.\n\nHOJE VEIO COMO PROCURA DIRETA - ENCAIXE.\nSENTE-SE MELHOR POREM NÃO ESTA 100%.\nANTES SENTIA-SE MAL ATÉ EM PENTEAR O CABELO, TOMAR BANHO (ESTAVA PRATICAMENTE EM CADEIRA DE RODAS), TINHA DPN E ORTOPNEIA.\nAGORA CONSEGUE CAMINHAR EMPURRANDO CARRINHO POR MEIA QUADRA.\n \n \n# mp MULTISSITIO.\n# programado em BIV 70 70.\n# operando MAIS DE 95% EM BIV.\n# ritmo proprio = BRADI SINUSAL.\n# a - imp = 537, sense = 2,6, cla = 1,2 x 0,5.\n# v - imp = 522, sense = 17, clv = 0,7 x 0,5.\nVE COM 609, 19,6 E 11 X 0,5.\n# bat ok.\n\n# programado em FC DE 60 - 50, mantido demais, retorno em 30 DIAS  + NÃO FALTAR CONSULTA COM Doutor Vital Brazil. ",
  "entities": {
    "Abreviação": [
      "CMD",
      "DPN",
      "VE",
      "FC",
      "AMBU DO MP",
      "mp MULTISSITIO"
    ],
    "Doença ou Síndrome": [
      "CMD"
    ],
    "Conceito Temporal": [
      "APÓS",
      "HOJE",
      "ANTES",
      "30 DIAS"
    ],
    "Função de Organismo": [
      "GESTAÇÃO"
    ],
    "Dispositivo Médico": [
      "RESSINC",
      "CDI",
      "CADEIRA DE RODAS"
    ],
    "Negação": [
      "NÃO"
    ],
    "Atividade de Assistência à Saúde": [
      "CONSULTA",
      "ENCAIXE",
      "programado",
      "retorno",
      "PROCURA DIRETA",
      "FALTAR CONSULTA"
    ],
    "Achado": [
      "100%",
      "SENTE-SE MELHOR",
      "CAMINHAR EMPURRANDO CARRINHO",
      "ritmo proprio"
    ],
    "Sinal ou Sintoma": [
      "DPN",
      "ORTOPNEIA",
      "SENTIA-SE MAL"
    ],
    "Atributo Clínico": [
      "BIV",
      "imp",
      "sense",
      "cla",
      "clv",
      "FC"
    ],
    "Atividade de Máquina": [
      "operando",
      "ritmo proprio"
    ],
    "Conceito Quantitativo": [
      "95%",
      "537",
      "522",
      "17",
      "MEIA QUADRA",
      "70 70",
      "2 , 6",
      "1 , 2 x 0 , 5",
      "0 , 7 x 0 , 5",
      "11 X 0 , 5",
      "60 - 50"
    ],
    "Parte do Corpo, Órgão ou Componente Orgânico": [
      "VE"
    ],
    "Grupo Profissional ou Ocupacional": [
      "Doutor"
    ],
    "Organização Relacionada à Saúde": [
      "AMBU DO MP"
    ],
    "Atividade Diária ou Recreativa": [
      "PENTEAR O CABELO",
      "TOMAR BANHO"
    ],
    "Procedimento Terapêutico ou Preventivo": [
      "mp MULTISSITIO"
    ]
  },
  "labels": {}
}