{
  "prontuario_id": 477,
  "text": "Lucas 79 ANOS\n\n# ACOMPANHAMENTO DEVIDO A FIBRILAÇÃO ATRIAL 4 ANOS \n# FA \n# HAS\n# DISLIPIDEMIA\n# DM\n# CA DE INTESTINO GROSSO 2010 - ACOMPANHAMENTO REGULAR\n# PACIENTE REFERE QUE EM ABRIL APRESENTOU QUADRO DE PALPITAÇÃO ASSOCIADO A MAL ESTAR, TONTURA. NO MOMENTO DA CONSULTA PACIENTE SEM QUEIXAS.\n# MUC:\nMARCOMAR 1,5MG - MEIO COMPRIMIDO\nANLODIPINO 2,5MG - 1X AO DIA\nATENOLOL 50MG - 1X AO DIA\nHIDROCLOROTIAZIDA 25MG - 1X AO DIA\nMETFORMINA 850MG - 1/2 AO DIA\nSINVASTATINA 20MG - 1X AO DIA\nRNI\n02/03 - 2,7\n04/05 - 2,3\n08/06 - 1,5\nEF\nSAT O2 94\nFC 73 BPM\nPA: 125/75 MMHG\nCP JUGULARES INGURGITADAS\nACV: BULHAS ARRITMICAS HIPOFONETICAS SEM SS\nMV PRESENTE BILATERAL SRA\nABDOME FLACIDO INDOLOR A PALPACAO\nMMII: EDEMA BILATERAL ++/4+\n# C\nRETIRADO ANLODIPINO DEVIDO A EDEMA EM MMII\nRETORNO NA VAGA EM 6 MESES\nORIENTAÇÕES SOBRE SINAIS DE ALARME DA FA\nDoutor Vital Brazil ",
  "entities": {
    "Atividade de Assistência à Saúde": [
      "ACOMPANHAMENTO",
      "CONSULTA",
      "C",
      "RETIRADO",
      "RETORNO",
      "ORIENTAÇÕES"
    ],
    "Doença ou Síndrome": [
      "FA",
      "HAS",
      "DISLIPIDEMIA",
      "DM",
      "FIBRILAÇÃO ATRIAL",
      "CA DE INTESTINO GROSSO"
    ],
    "Abreviação": [
      "FA",
      "HAS",
      "DM",
      "MUC",
      "RNI",
      "EF",
      "CP",
      "ACV",
      "SS",
      "SRA",
      "MMII",
      "C",
      "CA DE INTESTINO GROSSO",
      "1X AO DIA",
      "SAT O2 94"
    ],
    "Conceito Quantitativo": [
      "REGULAR",
      "850MG",
      "20MG",
      "6",
      "1X AO DIA",
      "2 , 7",
      "2 , 3",
      "1 , 5",
      "73 BPM"
    ],
    "Paciente ou Grupo com Deficiência": [
      "PACIENTE"
    ],
    "Conceito Temporal": [
      "ABRIL",
      "MESES"
    ],
    "Sinal ou Sintoma": [
      "PALPITAÇÃO",
      "TONTURA",
      "QUEIXAS",
      "SS",
      "INDOLOR",
      "EDEMA",
      "MAL ESTAR",
      "JUGULARES INGURGITADAS",
      "BULHAS ARRITMICAS HIPOFONETICAS"
    ],
    "Negação": [
      "SEM",
      "INDOLOR"
    ],
    "Achado": [
      "MUC",
      "SRA"
    ],
    "Substância Química Orgânica": [
      "HIDROCLOROTIAZIDA",
      "METFORMINA",
      "ANLODIPINO",
      "MARCOMAR 1 , 5MG",
      "ANLODIPINO 2 , 5MG"
    ],
    "Substância Farmacológica": [
      "HIDROCLOROTIAZIDA",
      "METFORMINA",
      "ANLODIPINO",
      "MARCOMAR 1 , 5MG",
      "ANLODIPINO 2 , 5MG"
    ],
    "Resultado Laboratorial ou de Teste": [
      "RNI",
      "SAT O2 94"
    ],
    "Parte do Corpo, Órgão ou Componente Orgânico": [
      "CP",
      "MMII"
    ],
    "Atributo Clínico": [
      "ACV"
    ],
    "Conceito Espacial": [
      "BILATERAL"
    ],
    "Localização ou Região Corporal": [
      "MMII"
    ],
    "Grupo Profissional ou Ocupacional": [
      "Doutor"
    ]
  },
  "labels": {}
}