{
  "prontuario_id": 220,
  "text": "Lucas, 29 ANOS\nS # Segunda consulta.Paciente veio acompanhado da mãe. Refere melhora do tremor de MMSS com a retirada do Haldol, no entanto refere piora da acatisia e discinesia com a introdução da risperidona 02 mg (0-0-1).Refere sono não reparador, insonia intermediaria. Nega sintomas de hiperativaçao, nega alteraçoes de sensopercepçao, nega sintomas depressivos. Mantem sintomas negativos - lentificaçao psicomotora e de pensamento, embotamento afetivo, apatia.\nTrouxe exames lab:\nLitemia 0,4 (nao tomou remedio na noite anterior).\nEM USO: RISPERIDONA 02 MG (0-0-1)\n             CITALOPRAM 20 MG (1-0-0)\n              CARBOLITIUM 300 MG (1-0-2)\n               CLONAZEPAM 0,5 MG (0-0-1)\nA # TAB ? PERSONALIDADE ESQUIZOIDE ??\nP # Conforme orientaçoes Doutor Vital Brazil mantenho prescrição médica, aumento clonazepam 0,5 para (2-0-1) para melhhora de acatisia e discinesia. Retorno em 30 dias.\nO # Asseado, cooperativo, orientado alo e auto, normovigil, normotenaz, humor hipotimico afeto embotado, critica e insght parciais.\n ",
  "entities": {
    "Atividade de Assistência à Saúde": [
      "consulta",
      "acompanhado",
      "retirada",
      "introdução",
      "orientaçoes",
      "mantenho",
      "aumento",
      "Retorno",
      "prescrição médica"
    ],
    "Paciente ou Grupo com Deficiência": [
      "Paciente"
    ],
    "Grupo Familiar": [
      "mãe"
    ],
    "Abreviação": [
      "MMSS",
      "TAB",
      "alo",
      "auto"
    ],
    "Substância Química Orgânica": [
      "Haldol",
      "risperidona",
      "RISPERIDONA",
      "CITALOPRAM",
      "CARBOLITIUM",
      "CLONAZEPAM",
      "clonazepam"
    ],
    "Substância Farmacológica": [
      "Haldol",
      "risperidona",
      "RISPERIDONA",
      "CITALOPRAM",
      "CARBOLITIUM",
      "CLONAZEPAM",
      "clonazepam"
    ],
    "Negação": [
      "Nega",
      "nega"
    ],
    "Sinal ou Sintoma": [
      "sintomas",
      "hiperativaçao",
      "apatia",
      "acatisia",
      "discinesia",
      "piora da acatisia e discinesia",
      "sono não reparador",
      "alteraçoes de sensopercepçao",
      "sintomas depressivos",
      "lentificaçao psicomotora e de pensamento",
      "embotamento afetivo",
      "humor hipotimico afeto embotado",
      "critica e insght parciais"
    ],
    "Disfunção Mental ou Comportamental": [
      "apatia"
    ],
    "Elemento, Íon ou Isótopo": [
      "CARBOLITIUM"
    ],
    "Doença ou Síndrome": [
      "TAB",
      "insonia intermediaria",
      "PERSONALIDADE ESQUIZOIDE"
    ],
    "Grupo Profissional ou Ocupacional": [
      "Doutor"
    ],
    "Achado": [
      "Asseado",
      "cooperativo",
      "orientado",
      "normovigil",
      "normotenaz"
    ],
    "Conceito Quantitativo": [
      "02 mg",
      "02 MG",
      "20 MG",
      "300 MG",
      "0 , 5 MG"
    ],
    "Procedimento Laboratorial": [
      "exames lab"
    ],
    "Resultado Laboratorial ou de Teste": [
      "Litemia 0 , 4"
    ],
    "Conceito Qualitativo": [
      "0 , 5 para ( 2-0-1 )"
    ]
  },
  "labels": {}
}