{
  "prontuario_id": 209,
  "text": "S # Lucas 43 anos\nRetorno trazendo exames.\nHMA # Crise de dor em pontada em hipocondrio direito, irradiaçao para dorso direito, de forte intensidade, há aprox 2 meses. Nao relacionada com alimentaçao.\nRefere febre e pneumonia junto com a crise de dor.\n21/08/13: USG abdome: colelitiase biliar com coledoco dilatado..\nHMP #\n - DM, HAS, bronquite e rinite\n - Faz uso metformina 850mg 3x / dia, glicazida 30mg , sinvastatina 20mg, hctz 25mg, enalapril 10mg 12/12h, histamin 2mg 12/12h, prednisona 20mg, omeprazol 20mg.\n - Tabagista\n - AGO: G 4 P 2 C 1 A 1. Usa ACHO injetável (depoprovera)\nO #\nBEG\nA #\nColecistolitiase\nP #\nEncaminhada para cirurgia.\nEXAMES PRÉ - OP:\nECG: Taqui sinusal, Gli j: 149 - outros sp.\n \n \n \n ",
  "entities": {
    "Atividade de Assistência à Saúde": [
      "Retorno",
      "Encaminhada"
    ],
    "Procedimento Laboratorial": [
      "exames",
      "EXAMES"
    ],
    "Procedimento Diagnóstico": [
      "exames",
      "USG",
      "EXAMES",
      "ECG"
    ],
    "Sinal ou Sintoma": [
      "Crise",
      "febre",
      "dor em pontada",
      "relacionada com alimentaçao",
      "crise de dor"
    ],
    "Negação": [
      "Nao"
    ],
    "Doença ou Síndrome": [
      "pneumonia",
      "DM",
      "HAS",
      "bronquite",
      "rinite",
      "Tabagista",
      "Colecistolitiase",
      "Taqui sinusal"
    ],
    "Abreviação": [
      "USG",
      "HMP",
      "DM",
      "HAS",
      "hctz",
      "AGO",
      "ACHO",
      "BEG",
      "ECG",
      "sp",
      "Taqui sinusal",
      "Gli j : 149"
    ],
    "Localização ou Região Corporal": [
      "abdome",
      "hipocondrio direito",
      "dorso direito"
    ],
    "Substância Farmacológica": [
      "metformina",
      "glicazida",
      "sinvastatina",
      "hctz",
      "enalapril",
      "histamin",
      "prednisona",
      "omeprazol",
      "depoprovera"
    ],
    "Substância Química Orgânica": [
      "metformina",
      "glicazida",
      "sinvastatina",
      "hctz",
      "histamin",
      "prednisona",
      "omeprazol",
      "depoprovera"
    ],
    "Conceito Quantitativo": [
      "30mg",
      "20mg",
      "25mg",
      "4",
      "2",
      "1",
      "850mg 3x / dia",
      "10mg 12/12h",
      "2mg 12/12h"
    ],
    "Aminoácido, Peptídeo ou Proteína": [
      "enalapril"
    ],
    "Substância Biologicamente Ativa": [
      "histamin"
    ],
    "Hormônio": [
      "prednisona",
      "depoprovera"
    ],
    "Atributo Clínico": [
      "AGO"
    ],
    "Função de Organismo": [
      "G",
      "P"
    ],
    "Procedimento Terapêutico ou Preventivo": [
      "C",
      "cirurgia"
    ],
    "Achado": [
      "A",
      "BEG",
      "sp"
    ],
    "Conceito Qualitativo": [
      "forte intensidade"
    ],
    "Conceito Temporal": [
      "2 meses"
    ],
    "Resultado Laboratorial ou de Teste": [
      "colelitiase biliar com coledoco dilatado",
      "Gli j : 149"
    ]
  },
  "labels": {}
}