{
  "prontuario_id": 238,
  "text": "Paciente 72 anos, parou de trabalhar há 8 meses - cuidadora e do lar. \nComorbidades: nega DM e HAS, problema na coluna - hx de fratura em região lombar - dor somente quando se esforça\nMed uso: medicação para infecção na perna (não sabe o nome, mas nega ser atb), nega analgesicos\ncx de hernia umbilical e inguinal E há 8 meses.\nRx lombar: espondilose, listese de L5, redução espaço discal L4 / L5 e L5 / S1.\nhá 2 meses apresentou infecção na perna (úlcera varicosa) - antibioticoterapia porem não sabe o nome, queixa de dores episódicas\nnão dorme bem, não tem sono reparador - há 1 mês perdeu filho\nEF: BEG, LOTE, sem linfonodomegalia \nnega perda de peso recentemente\nP:\nPA 120x80mmHg\n98 Sat\n62 bpm \nAP sp\nACV sp\nABD sp\nmembros: curativo em MID - úlcera varicosa\nHemograma 02/09\nHb 11\nleuco 5640 \nbast 0\neosi 2\nlinf 29\ntsh 5,08\nt4 livre 0,85\n \n \n \n ",
  "entities": {
    "Paciente ou Grupo com Deficiência": [
      "Paciente"
    ],
    "Negação": [
      "nega",
      "não",
      "sem"
    ],
    "Doença ou Síndrome": [
      "DM",
      "HAS",
      "espondilose",
      "listese de L5",
      "úlcera varicosa"
    ],
    "Abreviação": [
      "DM",
      "HAS",
      "Med",
      "atb",
      "cx",
      "EF",
      "BEG",
      "LOTE",
      "AP",
      "sp",
      "ACV",
      "ABD",
      "MID",
      "inguinal E",
      "Rx lombar",
      "98 Sat",
      "leuco 5640",
      "bast 0",
      "eosi 2",
      "linf 29"
    ],
    "Parte do Corpo, Órgão ou Componente Orgânico": [
      "coluna",
      "perna",
      "membros",
      "MID"
    ],
    "Sinal ou Sintoma": [
      "dor",
      "queixa",
      "linfonodomegalia",
      "dores episódicas",
      "perda de peso"
    ],
    "Antibiótico": [
      "atb",
      "antibioticoterapia"
    ],
    "Substância Farmacológica": [
      "analgesicos",
      "antibioticoterapia"
    ],
    "Procedimento Terapêutico ou Preventivo": [
      "cx",
      "antibioticoterapia",
      "curativo"
    ],
    "Achado": [
      "BEG",
      "LOTE",
      "sp",
      "dorme bem",
      "sono reparador"
    ],
    "Conceito Temporal": [
      "recentemente",
      "8 meses",
      "há 2 meses"
    ],
    "Atributo Clínico": [
      "PA",
      "AP",
      "ACV",
      "98 Sat"
    ],
    "Conceito Quantitativo": [
      "120x80mmHg",
      "62 bpm"
    ],
    "Localização ou Região Corporal": [
      "ABD",
      "inguinal E"
    ],
    "Procedimento Laboratorial": [
      "Hemograma"
    ],
    "Lesão ou Envenenamento": [
      "fratura em região lombar"
    ],
    "Procedimento Diagnóstico": [
      "Rx lombar"
    ],
    "Resultado Laboratorial ou de Teste": [
      "Hb 11",
      "leuco 5640",
      "bast 0",
      "eosi 2",
      "linf 29",
      "tsh 5 , 08",
      "t4 livre 0 , 85"
    ]
  },
  "labels": {}
}