{
  "prontuario_id": 979,
  "text": "PACIENTE EM PRIMEIRA CONSULTA REFERE BAV PARA PERTO HÁ ANOS LONGE HÁ ANOS \nREFERE DM TIPO 1 EM TTO DESCONTROLADA  HÁ 8 ANOS \nNEGA HAS\nHF DE CEGUEIRA E GLAUCOMA \nNEGA CX E TRAUMA OCULAR AO \nAV: 20 / 70// 20 / 200 \nESQ: -1,00 ESF AO \nTOL: -1,25 ESF VV 20 / 40 // -0,75 ESF VV 20 / 70  \nFO: PAPILA E MACULA NROMAIS AO SEM OUTRAS ALTERAÇÕES EVIDENTES AO \nPIO: 14/13\nBIO: CA CALMA E BEM FORMADA COM PUPILAS FOTOREAGNMETS BILATERAL E SIMETRICAMENTE AO \nMR AO E BIO DE FUNDO SEM ALTERAÇÕES EVIDENTES AO \nCDTA: SOLICITO ANGIO  E QUANDO CONSEGUIR DATA PARA EXAME BATER NA PORTA PARA MARCAR RETORNO \nR1 Doutor Vital Brazil\nR2 Doutor Vital Brazil\n \n \n ",
  "entities": {
    "Paciente ou Grupo com Deficiência": [
      "PACIENTE"
    ],
    "Atividade de Assistência à Saúde": [
      "CONSULTA",
      "CDTA",
      "SOLICITO",
      "RETORNO"
    ],
    "Abreviação": [
      "BAV",
      "TTO",
      "HAS",
      "HF",
      "CX",
      "AO",
      "VV",
      "ESF",
      "FO",
      "PIO",
      "BIO",
      "CA",
      "MR",
      "CDTA",
      "ANGIO",
      "R1",
      "R2",
      "DM TIPO 1",
      "AV : 20 / 70// 20 / 200",
      "ESQ : -1 , 00 ESF",
      "TOL : -1 , 25 ESF",
      "BIO DE FUNDO"
    ],
    "Sinal ou Sintoma": [
      "BAV",
      "CEGUEIRA",
      "ALTERAÇÕES",
      "AV : 20 / 70// 20 / 200",
      "ESQ : -1 , 00 ESF",
      "TOL : -1 , 25 ESF",
      "OUTRAS ALTERAÇÕES"
    ],
    "Procedimento Terapêutico ou Preventivo": [
      "TTO",
      "CX"
    ],
    "Conceito Qualitativo": [
      "DESCONTROLADA",
      "SIMETRICAMENTE"
    ],
    "Negação": [
      "NEGA",
      "SEM"
    ],
    "Doença ou Síndrome": [
      "HAS",
      "GLAUCOMA",
      "DM TIPO 1"
    ],
    "Parte do Corpo, Órgão ou Componente Orgânico": [
      "AO",
      "CA",
      "PUPILAS"
    ],
    "Procedimento Diagnóstico": [
      "FO",
      "PIO",
      "BIO",
      "MR",
      "ANGIO",
      "EXAME",
      "BIO DE FUNDO"
    ],
    "Conceito Quantitativo": [
      "14/13",
      "20 / 70"
    ],
    "Achado": [
      "CALMA",
      "PAPILA E MACULA NROMAIS",
      "BEM FORMADA"
    ],
    "Grupo Profissional ou Ocupacional": [
      "R1",
      "Doutor",
      "R2"
    ],
    "Conceito Temporal": [
      "HÁ ANOS",
      "HÁ 8 ANOS"
    ],
    "Lesão ou Envenenamento": [
      "TRAUMA OCULAR"
    ]
  },
  "labels": {}
}