{
  "prontuario_id": 626,
  "text": "R1 Doutor Vital Brazil\nR2 Doutor Vital Brazil\nLucas, 19 ANOS\n# PACIENTE COM QUEIXA DE BAV OD HA 1 MES, APOS EPISODIO DE CONJUNTIVITE (SIC). \n     REFERE QUE POSSUI LESAO CORNEANA PERIFERICA DESDE INFANCIA. , COM PIORA TAMBEM APOS PROVAVEL CONJUNTIVITE (SIC)\n# HMP: NEGA CX OU TRAUMA OCULAR\n             NEGA COMORBIDADES\n# HMF: NEGA\n# AVSC:\n20/200\n20/20\n# ESQ:\nREFLEXO DIMINUIDO\n+0,50 ESF\n# TOLERA:\nSEM MELHORA 20/200\nPL ESF 20/20\n# BIO:\nOD - OPACIDADE CORNEANA (ESTROMAL) ACOMETENDO EIXO, VH4, PFR, CERATITE PUNTATA INFERIOR, SEM REAÇÃO DE CAMARA, PIGMENTO DE IRIS EM CRISTALINO, NEOVASOS FINOS CORNEANOS 4H\n# BIO DE FUNDO //  FO:\nOD - IMPOSSIVEL DEVIDO A OPACIDADE DE MEIOS\nOE - MACULA E PAPILA NORMAIS\n# MR OD:\nOPACIDADE DE MEIOS\n# PIO:\n10/10\n# A: BAV OD (LEUCOMA ACOMETENDO EIXO VISUAL)\n# CD: AGENDO RETORNO DIA 15/09/16 PARA AVALIAÇÃO COM Doutor Vital Brazil PRESCREVO VIDISIC 6/6H + SYSTANE 4/4H\n \n \n \n ",
  "entities": {
    "Abreviação": [
      "R1",
      "R2",
      "BAV",
      "OD",
      "CX",
      "HMF",
      "ESQ",
      "ESF",
      "TOLERA",
      "PL",
      "BIO",
      "VH4",
      "PFR",
      "FO",
      "OE",
      "MR",
      "PIO",
      "CD",
      "BIO DE FUNDO"
    ],
    "Grupo Profissional ou Ocupacional": [
      "R1",
      "Doutor",
      "R2"
    ],
    "Paciente ou Grupo com Deficiência": [
      "PACIENTE"
    ],
    "Sinal ou Sintoma": [
      "QUEIXA",
      "BAV",
      "REFLEXO DIMINUIDO",
      "OPACIDADE CORNEANA",
      "REAÇÃO DE CAMARA",
      "NEOVASOS FINOS CORNEANOS",
      "IMPOSSIVEL DEVIDO A OPACIDADE DE MEIOS",
      "OPACIDADE DE MEIOS"
    ],
    "Parte do Corpo, Órgão ou Componente Orgânico": [
      "OD",
      "ESTROMAL",
      "OE"
    ],
    "Doença ou Síndrome": [
      "CONJUNTIVITE",
      "CERATITE PUNTATA INFERIOR"
    ],
    "Conceito Temporal": [
      "APOS",
      "HA 1 MES",
      "DESDE INFANCIA"
    ],
    "Negação": [
      "NEGA",
      "SEM"
    ],
    "Procedimento Terapêutico ou Preventivo": [
      "CX"
    ],
    "Procedimento Diagnóstico": [
      "ESQ",
      "BIO",
      "PFR",
      "FO",
      "MR",
      "PIO",
      "BIO DE FUNDO"
    ],
    "Conceito Qualitativo": [
      "MELHORA"
    ],
    "Conceito Quantitativo": [
      "20/200",
      "20/20",
      "10/10",
      "+0 , 50"
    ],
    "Atividade de Assistência à Saúde": [
      "CD",
      "AGENDO",
      "RETORNO",
      "AVALIAÇÃO",
      "PRESCREVO"
    ],
    "Substância Química Orgânica": [
      "VIDISIC"
    ],
    "Substância Farmacológica": [
      "VIDISIC",
      "SYSTANE"
    ],
    "Lesão ou Envenenamento": [
      "LESAO CORNEANA PERIFERICA",
      "TRAUMA OCULAR"
    ],
    "Achado": [
      "REAÇÃO DE CAMARA",
      "PIGMENTO DE IRIS EM CRISTALINO",
      "MACULA E PAPILA NORMAIS"
    ]
  },
  "labels": {}
}