{
  "prontuario_id": 134,
  "text": "ID: Lucas.\nHMA: PACIENTE RELATA ARDÊNCIA EM ESOFAGO AO SE ALIMENTAR, DISFAGIA E ODINOFAGIA,  VOMITOS LOGO APOS AS REFEIÇÕES, INCLUSIVE SEM PODER BEBER ÁGUA DESDE ENTRAR NA DIETA SOLIDA (HÁ PRATICAMENTE 1 MÊS). QUEIXA-SE DE DOR EM HIPOCONDRIO DIREITO\nHMP: REALIZOU BYPASS HÁ 2 MESES. RELATA TER PERDIO 16 KG. IMC 32.68 KG/M². \nLAUDO EDA (15/06/16): ESOFAGITE EROSIVA GRAU B DE LOS ANGELES; SINAIS DE GASTROPLASIA REDUTORA EM Y DE ROUX, GASTRITE EROSIVA PLANA EM COTO DISCRETA, SUBESTENOSE  DA ANASTOMOSE GASTROENTERAL COM BALÃO DILATADOR.\nCONDUTA: PROGRAMA DILATAÇÃO COM BALÃO E RETORNO 22/08/16 COM EXAMES\n \n \n \n ",
  "entities": {
    "Paciente ou Grupo com Deficiência": [
      "PACIENTE"
    ],
    "Sinal ou Sintoma": [
      "DISFAGIA",
      "ODINOFAGIA",
      "VOMITOS",
      "QUEIXA-SE",
      "ARDÊNCIA EM ESOFAGO",
      "GASTRITE EROSIVA PLANA EM COTO DISCRETA"
    ],
    "Conceito Temporal": [
      "APOS",
      "HÁ 2 MESES"
    ],
    "Alimento": [
      "REFEIÇÕES"
    ],
    "Negação": [
      "SEM"
    ],
    "Substância": [
      "ÁGUA"
    ],
    "Procedimento Terapêutico ou Preventivo": [
      "BYPASS",
      "GASTROPLASIA REDUTORA EM Y DE ROUX",
      "DILATAÇÃO COM BALÃO"
    ],
    "Atributo Clínico": [
      "IMC"
    ],
    "Conceito Quantitativo": [
      "32",
      "16 KG"
    ],
    "Abreviação": [
      "EDA"
    ],
    "Procedimento Diagnóstico": [
      "EDA"
    ],
    "Atividade de Assistência à Saúde": [
      "CONDUTA",
      "RETORNO"
    ],
    "Procedimento Laboratorial": [
      "EXAMES"
    ],
    "Localização ou Região Corporal": [
      "HIPOCONDRIO DIREITO"
    ],
    "Doença ou Síndrome": [
      "ESOFAGITE EROSIVA GRAU B DE LOS ANGELES"
    ],
    "Resultado Laboratorial ou de Teste": [
      "GASTROPLASIA REDUTORA EM Y DE ROUX",
      "GASTRITE EROSIVA PLANA EM COTO DISCRETA",
      "SUBESTENOSE DA ANASTOMOSE GASTROENTERAL COM BALÃO DILATADOR"
    ]
  },
  "labels": {}
}