{
  "prontuario_id": 195,
  "text": "# Lucas\n# CBC sólido malar D - jan/2016\n# CBC sólido asa nasal E - jan/2016\n# Bx excisional infra-orbitária E - jan/2016\n# CEC mento E - jan 2016\n# S: Vem para resultado de AP \nAP n 16/B00149\n1- malar D = Fragmento de pele com focos de inflamação crônica linfocitária e fibrose dérmica cicatricial. \nHá também ceratose actínica. Margens livres de neoplasia.\n2 - Asa nasal E= CBC superficial. Há também focos de inflamação crônica linfocitária e fibrose. Uma dar margens laterais está comprometida. \n3 - Infra orbitária E = Fragmento de pele com focos de inflamação crônica linfocitária e fibrose dérmica cicatricial. Margens livres de neoplasia. \n4 - Mento a E = CEC bem diferenciado grau I, invasivo de pele. Margens livres. \n# O: Múltiplas QAS em face e pavilhao auricular E, intenso fotodano\nLesão infrauricular com vasos arboriformes\n# A: Fotodano seguimeto pos CA\n# P: Devido a margem comprometida em asa nasal e intenso fotodano optamos por efurix para tratar campo\nDoutor Vital Brazil orienta fazer 28 noites se tolerância\nNo retorno reavaliar lesôes residuais se há necessidade de bx. \nRetorno em 3 meses.\nR3 Doutor Vital Brazil ",
  "entities": {
    "Doença ou Síndrome": [
      "CBC",
      "CEC",
      "QAS",
      "CA",
      "ceratose actínica"
    ],
    "Procedimento Diagnóstico": [
      "AP",
      "bx",
      "Bx excisional"
    ],
    "Abreviação": [
      "AP",
      "QAS",
      "bx",
      "R3",
      "malar D",
      "asa nasal E",
      "Bx excisional",
      "infra-orbitária E",
      "mento E",
      "Asa nasal E",
      "Infra orbitária E",
      "Mento a E",
      "pavilhao auricular E"
    ],
    "Processo Neoplásico": [
      "neoplasia"
    ],
    "Conceito Espacial": [
      "focos"
    ],
    "Localização ou Região Corporal": [
      "face",
      "infrauricular",
      "malar D",
      "asa nasal E",
      "infra-orbitária E",
      "mento E",
      "Asa nasal E",
      "Infra orbitária E",
      "Mento a E",
      "pavilhao auricular E",
      "asa nasal"
    ],
    "Conceito Qualitativo": [
      "intenso"
    ],
    "Sinal ou Sintoma": [
      "fotodano",
      "Lesão",
      "Fotodano",
      "inflamação crônica linfocitária",
      "vasos arboriformes"
    ],
    "Substância Farmacológica": [
      "efurix"
    ],
    "Ácido Nucleico, Nucleosídeo ou Nucleotídeo": [
      "efurix"
    ],
    "Grupo Profissional ou Ocupacional": [
      "Doutor",
      "R3"
    ],
    "Atividade de Assistência à Saúde": [
      "orienta",
      "retorno",
      "reavaliar",
      "Retorno"
    ],
    "Atributo de Organismo": [
      "tolerância"
    ],
    "Parte do Corpo, Órgão ou Componente Orgânico": [
      "malar D",
      "Asa nasal E",
      "Infra orbitária E",
      "Mento a E",
      "pavilhao auricular E",
      "asa nasal"
    ],
    "Resultado Laboratorial ou de Teste": [
      "malar D",
      "Fragmento de pele com focos de inflamação crônica linfocitária",
      "fibrose dérmica cicatricial",
      "ceratose actínica",
      "margens laterais está comprometida",
      "focos de inflamação crônica linfocitária e fibrose dérmica cicatricial",
      "Mento a E",
      "grau I",
      "invasivo de pele",
      "Margens livres"
    ],
    "Classificação": [
      "grau I"
    ],
    "Conceito Temporal": [
      "28 noites",
      "3 meses"
    ]
  },
  "labels": {}
}