{
  "prontuario_id": 474,
  "text": "# QP: PTERÍGIO AO + LACRIMEJAMENTO OE\n# HMA: BAV PARA LONGE. USA ÓCULOS PARA DESCANSO\n# HMP: NEGA TRAUMA OU CIRURGIAS OFTALMOLÓGICAS. SEM COMORBIDADES; \n# HMF: PAI COM CATARATA\nExame Físico: \n# Avis: OD: 20/25\n            OE: 20/25\n# Esq: OD -0,25 A 180 // -0,25 A 90; OE: +0,75 A 180 // -0,5 A 90\n# Tol: OD: pl esf; OE: +0,75-1,00 180 // 20/20\n# FO: AO DISCO ÓPICO COM ESCAVAÇÃO FISIOLÓGICA, SIMÉTRICO E RESPEITANDO A REGRA ISNT. APRESENTA REGIÃO MACULAR SEM ALTERAÇÕES\n# BIO: AO CA CALMA E BEM FORMADA, PUPILAS FOTORREAGENTES, CÓRNEA CLARA; OD PT GRAU 1; OE PT GRAU 3\n# PIO: 12/12\nCONDUTA: PRESCREVO LACRIFILM COLÍREO E AGENDO PACIENTE PARA CIRURGIA PARA REMOÇÃO DE PTERÍGIO. ORIENTAMOS PACIENTE Á DIRIGIR-SE AO HUC CASO APRESENTE QUALQUER ALTERAÇÃO DA SAÚDE OCULAR. RETORNO ANUAL VIA UBS \n\nR1 Doutor Vital Btazil\n\n \n \n ",
  "entities": {
    "Sinal ou Sintoma": [
      "QP",
      "LACRIMEJAMENTO",
      "20/25",
      "ALTERAÇÕES",
      "ALTERAÇÃO",
      "BAV PARA LONGE",
      "-0 , 25 A 90",
      "+0 , 75 A 180",
      "-0 , 5 A 90"
    ],
    "Abreviação": [
      "QP",
      "OE",
      "HMF",
      "Avis",
      "OD",
      "Esq",
      "Tol",
      "pl",
      "esf",
      "FO",
      "BIO",
      "PIO",
      "UBS",
      "R1",
      "BAV PARA LONGE",
      "RESPEITANDO A REGRA ISNT",
      "CA CALMA E BEM FORMADA",
      "PT GRAU 1",
      "PT GRAU 3"
    ],
    "Doença ou Síndrome": [
      "PTERÍGIO",
      "COMORBIDADES",
      "CATARATA",
      "PT GRAU 1",
      "PT GRAU 3"
    ],
    "Parte do Corpo, Órgão ou Componente Orgânico": [
      "OE",
      "OD",
      "PUPILAS"
    ],
    "Dispositivo Médico": [
      "ÓCULOS"
    ],
    "Negação": [
      "NEGA",
      "SEM"
    ],
    "Lesão ou Envenenamento": [
      "TRAUMA"
    ],
    "Grupo Familiar": [
      "PAI"
    ],
    "Atributo Clínico": [
      "Avis"
    ],
    "Conceito Quantitativo": [
      "20/25",
      "180",
      "20/20",
      "12/12",
      "-0 , 25",
      "+0 , 75-1 , 00"
    ],
    "Procedimento Diagnóstico": [
      "Esq",
      "Tol",
      "FO",
      "BIO",
      "PIO"
    ],
    "Achado": [
      "20/20",
      "FOTORREAGENTES",
      "CÓRNEA CLARA",
      "SAÚDE OCULAR"
    ],
    "Resultado Laboratorial ou de Teste": [
      "SIMÉTRICO",
      "DISCO ÓPICO COM ESCAVAÇÃO FISIOLÓGICA",
      "RESPEITANDO A REGRA ISNT",
      "CA CALMA E BEM FORMADA"
    ],
    "Atividade de Assistência à Saúde": [
      "CONDUTA",
      "PRESCREVO",
      "AGENDO",
      "ORIENTAMOS",
      "RETORNO"
    ],
    "Paciente ou Grupo com Deficiência": [
      "PACIENTE"
    ],
    "Procedimento Terapêutico ou Preventivo": [
      "CIRURGIA",
      "CIRURGIAS OFTALMOLÓGICAS"
    ],
    "Conceito Temporal": [
      "ANUAL"
    ],
    "Organização Relacionada à Saúde": [
      "UBS"
    ],
    "Grupo Profissional ou Ocupacional": [
      "R1",
      "Doutor"
    ],
    "Localização ou Região Corporal": [
      "REGIÃO MACULAR"
    ],
    "Classificação": [
      "PT GRAU 1",
      "PT GRAU 3"
    ],
    "Medicamento Clínico": [
      "LACRIFILM COLÍREO"
    ],
    "Substância Farmacológica": [
      "LACRIFILM COLÍREO"
    ]
  },
  "labels": {}
}