{
  "prontuario_id": 844,
  "text": "Lucas, 54 ANOS, DO LAR\n\nDOR EM COLUNA LOMBAR DE LONGA DATA, NEGA TRAUMA\n\nDOR INCIDIOSA, NEGA USO DE ANALGESICO\n\nJÁ REALIZOU FST, NO MOMENTO REALIZANDO HIDROGINÁSTICA, REFERE MELHORA COM OS EXERCICIOS\n\nQUEIXA-SE DE DOR LOMBAR SEM IRRADIAÇOES\n\nPACIENTE COM PROTESE DE QUADRIL A ESQUERDA REALIZADA EM 2007.\n\nNEGA HAS / DM, REFRE ESTRA TRATANDO PARA HIPOTIREOIDISMO, PACIENTE OBESA\n\nPACIENTE NÃO PERDEU PESO ATÉ A PRESENTE CONSULTA\n\nAO EXAME\n\nDEAMBULANDO SEM DIFICULDADE\n\nCOLUNA APARENTEMENTE NO EIXO\n\nNEGA DOR A FLEXO-EXTENSÃO E ROTAÇÕES\n\nSEM DOR A PALPAÇAO EM COLUNA LOMBAR\n\nLASEGUE NEGATIVO\n\nREFLEXOS PRESENTES E SIMETRICOS\n\nFORÇA MUSCULAR GRAU 5\n\nSENSIBILIDADE PRESERVADA\n\nCD: MANTER HIDRO\n\nORIENTO PERDA DE PESO\n\nANALGESIA QUANDO NECESSARIO\n\nORIENTO NOVAMENTE A NECESSIDADE DE PERDA DE PESO \n\nORIENTO A IMPORTANCIA DESTA CONDUTA \n\nSOLICITO RADIOGRAFIA PARA PROXIMA CONSULTA \n\nHAVENDO POSSIBILIDADE DE ALTA NO RETORNO\n \n \n \n ",
  "entities": {
    "Negação": [
      "NEGA",
      "SEM",
      "NÃO"
    ],
    "Lesão ou Envenenamento": [
      "TRAUMA"
    ],
    "Substância Farmacológica": [
      "ANALGESICO",
      "ANALGESIA"
    ],
    "Substância Química Orgânica": [
      "ANALGESICO"
    ],
    "Atividade de Assistência à Saúde": [
      "REALIZOU",
      "FST",
      "EXERCICIOS",
      "TRATANDO",
      "CONSULTA",
      "CD",
      "MANTER",
      "ORIENTO",
      "SOLICITO",
      "ALTA",
      "RETORNO"
    ],
    "Abreviação": [
      "FST",
      "HAS",
      "DM",
      "CD",
      "HIDRO"
    ],
    "Procedimento Terapêutico ou Preventivo": [
      "FST",
      "HIDROGINÁSTICA",
      "HIDRO",
      "PERDA DE PESO"
    ],
    "Achado": [
      "MELHORA",
      "PERDEU PESO",
      "LASEGUE NEGATIVO",
      "REFLEXOS PRESENTES",
      "FORÇA MUSCULAR GRAU 5",
      "SENSIBILIDADE PRESERVADA"
    ],
    "Sinal ou Sintoma": [
      "QUEIXA-SE",
      "IRRADIAÇOES",
      "DIFICULDADE",
      "DOR INCIDIOSA"
    ],
    "Localização ou Região Corporal": [
      "LOMBAR"
    ],
    "Paciente ou Grupo com Deficiência": [
      "PACIENTE"
    ],
    "Doença ou Síndrome": [
      "HAS",
      "DM",
      "HIPOTIREOIDISMO",
      "OBESA"
    ],
    "Parte do Corpo, Órgão ou Componente Orgânico": [
      "COLUNA",
      "COLUNA LOMBAR"
    ],
    "Conceito Funcional": [
      "FLEXO-EXTENSÃO",
      "ROTAÇÕES"
    ],
    "Procedimento Diagnóstico": [
      "PALPAÇAO",
      "RADIOGRAFIA"
    ],
    "Atividade Ocupacional": [
      "DO LAR"
    ],
    "Conceito Temporal": [
      "LONGA DATA",
      "QUANDO NECESSARIO"
    ],
    "Dispositivo Médico": [
      "PROTESE DE QUADRIL A ESQUERDA"
    ]
  },
  "labels": {}
}