{
  "prontuario_id": 326,
  "text": "Lucas, 59 anos\n\nDIH: 03/06/2016\nTrazido pelo SIATE por queda de altura de 3m, com trauma em dorso e crânio. Cervicodorsalgia. NEfa perda de sconsciência ou vômitos\nAMP: HAS\nMUC: hidroclorotiazida e losartana. Ao exame inicial Sinais Vitais estáveis e controlados. Colar cervical. \n\nGCS 15, pupilas isocóricas e fotorreagentes, mobiliza os 4 membros. OBS: Coluna a/c ortopedia. Fratura de C7\n\nPrincipais exames\n1 - TC de Crânio: fratura esfenotemporal e de processo zigomática, ambas lineares e à direita.\n2 - TAC do craânio (04/06/2016): Sem particularidades evolutivas\n\nPaciente em GCS 15, PIFR, sem déficts neurológicos focais. \n\nEm uso de colar cervical de espuma prescrito pela equipe da ortopedia.\nAssintomático, nega náuseas ou vômitos.\n\nCD: Solicito TAC de crânio de controle.\nRetorno com exame.\n \n \n \n ",
  "entities": {
    "Conceito Temporal": [
      "DIH"
    ],
    "Abreviação": [
      "DIH",
      "SIATE",
      "HAS",
      "MUC",
      "a/c",
      "PIFR",
      "CD",
      "GCS 15",
      "Fratura de C7",
      "TC de Crânio",
      "TAC do craânio",
      "TAC de crânio"
    ],
    "Atividade de Assistência à Saúde": [
      "Trazido",
      "a/c",
      "prescrito",
      "CD",
      "Solicito",
      "Retorno"
    ],
    "Organização Relacionada à Saúde": [
      "SIATE"
    ],
    "Conceito Quantitativo": [
      "3m"
    ],
    "Sinal ou Sintoma": [
      "Cervicodorsalgia",
      "vômitos",
      "Assintomático",
      "náuseas",
      "perda de sconsciência",
      "particularidades evolutivas",
      "déficts neurológicos focais"
    ],
    "Negação": [
      "NEfa",
      "Sem",
      "sem",
      "Assintomático",
      "nega"
    ],
    "Doença ou Síndrome": [
      "HAS"
    ],
    "Substância Farmacológica": [
      "hidroclorotiazida",
      "losartana"
    ],
    "Substância Química Orgânica": [
      "hidroclorotiazida",
      "losartana"
    ],
    "Parte do Corpo, Órgão ou Componente Orgânico": [
      "pupilas",
      "Coluna"
    ],
    "Achado": [
      "isocóricas",
      "fotorreagentes",
      "PIFR",
      "Assintomático",
      "Sinais Vitais estáveis",
      "GCS 15",
      "mobiliza os 4 membros"
    ],
    "Grupo Profissional ou Ocupacional": [
      "ortopedia",
      "equipe da ortopedia"
    ],
    "Paciente ou Grupo com Deficiência": [
      "Paciente"
    ],
    "Procedimento Laboratorial": [
      "exame"
    ],
    "Lesão ou Envenenamento": [
      "trauma em dorso e crânio",
      "Fratura de C7",
      "fratura esfenotemporal e de processo zigomática"
    ],
    "Dispositivo Médico": [
      "Colar cervical",
      "colar cervical"
    ],
    "Procedimento Diagnóstico": [
      "TC de Crânio",
      "TAC do craânio",
      "TAC de crânio"
    ],
    "Resultado Laboratorial ou de Teste": [
      "fratura esfenotemporal e de processo zigomática",
      "lineares e à direita"
    ]
  },
  "labels": {}
}