{
  "prontuario_id": 61,
  "text": "R1 Doutor Vital Brazil PCT VEIO PORQUE FEZ 4 INJEÇÕES EM OD EM CIANORTE EM SERVIÇO PARTICULAR E QUER AVALIAR A POSSIBILIDADE DE FAZER PELO SUS.\nREFERE DOR OE.\nUSA ÓCULOS, ÚLTIMO HÁ 3M.\nCX DE CATARATA AO EM CIANORTE EM SERVIÇO PARTICULAR, HÁ 10A E LASER OE APÓS A CX DE CATARATA.\nHAS HÁ 5A EM USO DE ENALAPRIL. DLP EM USO DE SINVASTATINA. USO DE IOMBINA E AAS\nNEGA HMF DE CEGUEIRA OU GLAUCOMA.\n\nAV C/C    \n20/60 P\n20/30 P\nJ1\n\nÓCULOS QUE USA\n-1,00 -1,00 105º\n-2,25 -4,25 90º\nAD +3,00\n\nTOLERA\n-0,50 -1,00 120º  20/40 P\n-2,75 -4,25 90º   20/30 P\nAD +3,00 J1\n\nFO\nESC 0,3, DRUSAS PERIMACULARES E ATROFIA EPR AO\n\nBIO\nAO BLEFARITE, LIO TÓPICA, CORECTOPIA, PUPILA FOTORREAGENTE, VH4, CÓRNEA CLARA, CA CALMA E BEM FORMADA\n\nPIO APLAN\nOD 14 16\nOE 23 23\n\nA # HIPERTENSÃO OCULAR\nP # PRESCREVO AZOPT 1X À NOITE AO.\nRETORNO ANUAL\n \n \n \n ",
  "entities": {
    "Abreviação": [
      "R1",
      "PCT",
      "SUS",
      "AO",
      "OE",
      "HAS",
      "DLP",
      "AAS",
      "HMF",
      "AV",
      "J1",
      "TOLERA",
      "FO",
      "BIO",
      "VH4",
      "PIO",
      "OD",
      "1X",
      "INJEÇÕES EM OD",
      "HÁ 10A",
      "CX DE CATARATA",
      "AD +3 , 00",
      "ATROFIA EPR",
      "LIO TÓPICA",
      "CA CALMA E BEM FORMADA"
    ],
    "Grupo Profissional ou Ocupacional": [
      "R1",
      "Doutor"
    ],
    "Paciente ou Grupo com Deficiência": [
      "PCT"
    ],
    "Organização Relacionada à Saúde": [
      "SUS",
      "SERVIÇO PARTICULAR"
    ],
    "Parte do Corpo, Órgão ou Componente Orgânico": [
      "OE",
      "OD"
    ],
    "Dispositivo Médico": [
      "ÓCULOS"
    ],
    "Doença ou Síndrome": [
      "CATARATA",
      "HAS",
      "DLP",
      "GLAUCOMA",
      "BLEFARITE",
      "DRUSAS PERIMACULARES",
      "HIPERTENSÃO OCULAR"
    ],
    "Procedimento Terapêutico ou Preventivo": [
      "LASER",
      "INJEÇÕES EM OD",
      "CX DE CATARATA"
    ],
    "Conceito Temporal": [
      "APÓS",
      "NOITE",
      "ANUAL",
      "HÁ 10A"
    ],
    "Aminoácido, Peptídeo ou Proteína": [
      "ENALAPRIL"
    ],
    "Substância Química Orgânica": [
      "ENALAPRIL",
      "SINVASTATINA",
      "IOMBINA",
      "AAS",
      "AZOPT"
    ],
    "Substância Farmacológica": [
      "ENALAPRIL",
      "SINVASTATINA",
      "IOMBINA",
      "AAS",
      "AZOPT"
    ],
    "Negação": [
      "NEGA"
    ],
    "Achado": [
      "CEGUEIRA",
      "J1",
      "PUPILA FOTORREAGENTE"
    ],
    "Procedimento Diagnóstico": [
      "AV",
      "TOLERA",
      "FO",
      "BIO",
      "PIO"
    ],
    "Conceito Qualitativo": [
      "C/C"
    ],
    "Resultado Laboratorial ou de Teste": [
      "BLEFARITE",
      "CORECTOPIA",
      "VH4",
      "APLAN",
      "ESC 0 , 3",
      "DRUSAS PERIMACULARES",
      "ATROFIA EPR",
      "LIO TÓPICA",
      "CÓRNEA CLARA",
      "CA CALMA E BEM FORMADA"
    ],
    "Atividade de Assistência à Saúde": [
      "PRESCREVO",
      "RETORNO"
    ],
    "Conceito Quantitativo": [
      "1X",
      "-1 , 00 -1 , 00 105º",
      "-2 , 25 -4 , 25 90º",
      "AD +3 , 00",
      "-0 , 50 -1 , 00 120º 20/40 P",
      "-2 , 75 -4 , 25 90º 20/30 P",
      "14 16",
      "23 23"
    ]
  },
  "labels": {}
}