{
  "prontuario_id": 395,
  "text": "# Lucas,35 ANOS\n\n# QP: METRORRAGIA, HA 10 DIAS,\n\n# METRORRAGIA ASSOCIADA  DESDE ONTEM A LESOES DE PELE E DORES ARTICULARES EM IFD E IFP PREDOMINANTEMENTE EM MÃO DIREITA  SEM FATORES DE MELHORA E PIORA, ALEM DE DOR EM REGIAO POSTERIOR DO OUVIDO (PROCESSO MASTOISE?) ESQUERDO, ASSOCIADA A FEBRE DE 38 \nPCT REFERE OUTRO CASO SIMILAR COM REATIVAÇÃO DO LES\n\n# HMP: DX DE les HA 3 ANOS\nNEGA OUTRAS COMORBIDADES\n\n# EM USO DE:\nAZATIPRINA\nPREDINIZONA 10MG\nMETROREXATE\nCLOROQUINA HÁ 2M\n\nGINECOLOGICO: CICLO MESNTRUAL REGULAR, 5 DIAS, FLUXO MEDIO, \nSEM USO DE ACHO\nG 1 P 1 A 0 HA 15 ANOS\nEM ACOMPANHAMENTO COM GNECOLOGIA E EXAMES SEM ALTERAÇOES (SIC)\nNEGA DISPAREUNIA , CORRIMENTO, COLICA\n\nEF: LESOSE DE PELE MACULO-VESICULAR LACALIZADAS EM REGIAO CERVICAL ANTERIOR-ESQUERDA, POSTERIOR , REGIAO DE FURCULA ESTERNAL E DELTODE ESQUERDO, \nLESOES HIPEREMIADA, SEM PRURIDO SEM HIPERTEMIA LOCAL\nMAOS: EDEMA DE ARTICULAÇOES IFD E IFP PRINCIPALMENTE EM 2O E 3O DEMOS DIREITO E LIMITAÇAO ARTICULAR, SEM FATORES DE MELHORA E PIORA\n\n# CONDUTA: SUSPENDER MEDICAMENTOS IMUNOSSUPRESSORES PELA SUSPEITA DE ZOSTER\nDEIXO PRESCRITO ACICLOVIR 200MG\n \n \n \n ",
  "entities": {
    "Sinal ou Sintoma": [
      "QP",
      "LESOES",
      "FEBRE",
      "ALTERAÇOES",
      "DISPAREUNIA",
      "CORRIMENTO",
      "COLICA",
      "PRURIDO",
      "HIPERTEMIA",
      "DORES ARTICULARES",
      "LESOSE DE PELE MACULO-VESICULAR",
      "LESOES HIPEREMIADA",
      "LIMITAÇAO ARTICULAR"
    ],
    "Abreviação": [
      "QP",
      "PCT",
      "DX",
      "les",
      "ACHO",
      "EF",
      "ARTICULAÇOES IFD E IFP",
      "2O E 3O DEMOS DIREITO"
    ],
    "Função Patológica": [
      "METRORRAGIA"
    ],
    "Conceito Qualitativo": [
      "ASSOCIADA"
    ],
    "Parte do Corpo, Órgão ou Componente Orgânico": [
      "PELE",
      "OUVIDO",
      "MAOS",
      "MÃO DIREITA",
      "PROCESSO MASTOISE",
      "2O E 3O DEMOS DIREITO"
    ],
    "Espaço ou Junção Corporal": [
      "IFD",
      "IFP",
      "ARTICULAÇOES IFD E IFP"
    ],
    "Negação": [
      "SEM",
      "NEGA"
    ],
    "Conceito Espacial": [
      "POSTERIOR",
      "ESQUERDO"
    ],
    "Conceito Quantitativo": [
      "38",
      "10MG",
      "1",
      "0",
      "200MG",
      "FLUXO MEDIO"
    ],
    "Paciente ou Grupo com Deficiência": [
      "PCT"
    ],
    "Doença ou Síndrome": [
      "LES",
      "les",
      "ZOSTER"
    ],
    "Atividade de Assistência à Saúde": [
      "DX",
      "ACOMPANHAMENTO",
      "CONDUTA",
      "SUSPENDER",
      "PRESCRITO"
    ],
    "Substância Farmacológica": [
      "AZATIPRINA",
      "PREDINIZONA",
      "METROREXATE",
      "CLOROQUINA",
      "ACHO",
      "ACICLOVIR",
      "MEDICAMENTOS IMUNOSSUPRESSORES"
    ],
    "Substância Química Orgânica": [
      "AZATIPRINA",
      "PREDINIZONA",
      "METROREXATE",
      "CLOROQUINA",
      "ACICLOVIR"
    ],
    "Substância Perigosa ou Venenosa": [
      "AZATIPRINA"
    ],
    "Hormônio": [
      "PREDINIZONA"
    ],
    "Função de Organismo": [
      "G"
    ],
    "Procedimento Terapêutico ou Preventivo": [
      "P"
    ],
    "Grupo Profissional ou Ocupacional": [
      "GNECOLOGIA"
    ],
    "Procedimento Laboratorial": [
      "EXAMES"
    ],
    "Ácido Nucleico, Nucleosídeo ou Nucleotídeo": [
      "ACICLOVIR"
    ],
    "Conceito Temporal": [
      "HA 10 DIAS",
      "HA 3 ANOS",
      "HÁ 2M",
      "5 DIAS",
      "HA 15 ANOS"
    ],
    "Produto Intelectual": [
      "FATORES DE MELHORA E PIORA"
    ],
    "Achado": [
      "CICLO MESNTRUAL REGULAR"
    ],
    "Função Fisiológica": [
      "CICLO MESNTRUAL REGULAR"
    ],
    "Localização ou Região Corporal": [
      "CERVICAL ANTERIOR-ESQUERDA , POSTERIOR",
      "FURCULA ESTERNAL",
      "DELTODE ESQUERDO"
    ],
    "Fator Imunológico": [
      "MEDICAMENTOS IMUNOSSUPRESSORES"
    ]
  },
  "labels": {}
}