{
  "prontuario_id": 11,
  "text": "POI DE LAVAGEM + CURETA DE TECIDO NECRÓTICO. 18:00: PACIENTE RETORNOU DO CC LÚCIDO, ORIENTADO, COMUNICATIVO; MANTEM AVP COM STP. REFERE TER APRESENTADO 01 EPISÓDIO DE EMESE NO CC. CURATIVO COM ASPECTO LIMPO E SECO. SEGUE EM OBSERVAÇÃO. OSTEOMIELITE NÃO ESPECIFICADA. INTUBADO, SOB VENTILAÇÃO MECÂNICA, MONITORIZAÇÃO CARDÍACA E OXIMETRIA DE PULSO, JUGULAR COM SOROTERAPIA EM CURSO, SNG ABERTA COM ESTASE BORRA DE CAFÉ. REALIZADO MUDANÇA DE DECÚBITO, ASPIRADO TOT COM GRANDE QUANTIDADE DE SECREÇÃO ESPESSA E PURULENTA, SVD L. INFARTO CEREBRAL DEVIDO A TROMBOSE DE ARTÉRIAS PRÉ-CEREBRAIS. 18:30: DESACORDADO, FAZ ABERTURA OCULAR ESPONTÂNEA, AGITADO. REALIZADO BANHO DE LEITO E HIGIENE ORAL, APÓS CONTIDO NO LEITO NOVAMENTE DEVIDO A AGITAÇÃO. COM HEMATOMA E EDEMA DISCRETO EM REGIÃO OCULAR À D. MEIA TALA GESSADA EM MIE E REALIZADA NOVA PUNÇÃO V. TRAUMATISMOS MÚLTIPLOS NÃO ESPECIFICADOS. 13/10/2006, 15:40 HORAS: PERMANECE EM COMA, COM PUPILAS MÉDIO-FIXAS, MANTENDO CATETER DE DVE. VM VIA TOT COM FIO2-50%, PCV, PP 25cmH20, PEEP 2cmH20, F15mrpm, SPO2 99%. AUSCULTA PULMONAR COM MV LIVRES. HEMODINAMICAMENTE ESTÁVEL. CVP EM MSD COM PLANO BÁSICO D. OUTRAS HEMORRAGIAS INTRACEREBRAIS",
  "entities": {
    "Conceito Temporal": [
      "POI"
    ],
    "Abreviação": [
      "POI",
      "CC",
      "AVP",
      "STP",
      "SNG",
      "TOT",
      "SVD",
      "L",
      "D",
      "MIE",
      "VM",
      "FIO2-50%",
      "PCV",
      "PP",
      "25cmH20",
      "PEEP",
      "2cmH20",
      "F15mrpm",
      "SPO2",
      "CVP",
      "MSD",
      "PUNÇÃO V",
      "MV LIVRES"
    ],
    "Procedimento Terapêutico ou Preventivo": [
      "LAVAGEM",
      "CURETA",
      "STP",
      "CURATIVO",
      "SOROTERAPIA",
      "SNG",
      "ASPIRADO",
      "SVD",
      "VM",
      "FIO2-50%",
      "PCV",
      "VENTILAÇÃO MECÂNICA",
      "MUDANÇA DE DECÚBITO",
      "BANHO DE LEITO",
      "HIGIENE ORAL",
      "CONTIDO NO LEITO",
      "MEIA TALA GESSADA",
      "PUNÇÃO V"
    ],
    "Paciente ou Grupo com Deficiência": [
      "PACIENTE"
    ],
    "Organização Relacionada à Saúde": [
      "CC"
    ],
    "Achado": [
      "LÚCIDO",
      "ORIENTADO",
      "COMUNICATIVO",
      "AVP",
      "LIMPO",
      "SECO",
      "INTUBADO",
      "ESPESSA",
      "L",
      "F15mrpm",
      "ABERTURA OCULAR ESPONTÂNEA",
      "MV LIVRES",
      "HEMODINAMICAMENTE ESTÁVEL"
    ],
    "Dispositivo Médico": [
      "AVP",
      "CURATIVO",
      "SNG",
      "TOT",
      "SVD",
      "CATETER",
      "CVP"
    ],
    "Sinal ou Sintoma": [
      "EMESE",
      "PURULENTA",
      "DESACORDADO",
      "AGITADO",
      "AGITAÇÃO",
      "HEMATOMA",
      "EDEMA",
      "COMA",
      "ESTASE BORRA DE CAFÉ",
      "PUPILAS MÉDIO-FIXAS"
    ],
    "Doença ou Síndrome": [
      "OSTEOMIELITE",
      "COMA",
      "INFARTO CEREBRAL",
      "TROMBOSE DE ARTÉRIAS PRÉ-CEREBRAIS",
      "HEMORRAGIAS INTRACEREBRAIS"
    ],
    "Parte do Corpo, Órgão ou Componente Orgânico": [
      "JUGULAR"
    ],
    "Substância Corporal": [
      "SECREÇÃO"
    ],
    "Conceito Qualitativo": [
      "DISCRETO"
    ],
    "Conceito Espacial": [
      "D"
    ],
    "Localização ou Região Corporal": [
      "MIE",
      "MSD",
      "REGIÃO OCULAR"
    ],
    "Conceito Quantitativo": [
      "FIO2-50%",
      "25cmH20",
      "2cmH20",
      "99%"
    ],
    "Disfunção Celular ou Molecular": [
      "TECIDO NECRÓTICO"
    ],
    "Negação": [
      "NÃO ESPECIFICADA",
      "NÃO ESPECIFICADOS"
    ],
    "Procedimento Diagnóstico": [
      "MONITORIZAÇÃO CARDÍACA",
      "OXIMETRIA DE PULSO",
      "AUSCULTA PULMONAR"
    ],
    "Lesão ou Envenenamento": [
      "TRAUMATISMOS MÚLTIPLOS"
    ]
  },
  "labels": {
    "orientado": {
      "capitulo": "06"
    },
    "espessa": {
      "capitulo": "13"
    },
    "hemodinamicamente estável": {
      "capitulo": "11"
    },
    "osteomielite": {
      "capitulo": "03"
    },
    "pupilas médio-fixas": {
      "capitulo": "08"
    },
    "estase borra de café": {
      "capitulo": "09"
    },
    "f15mrpm": {
      "capitulo": "07"
    },
    "hematoma": {
      "capitulo": "14"
    },
    "seco": {
      "capitulo": "13"
    },
    "comunicativo": {
      "capitulo": "06"
    },
    "limpo": {
      "capitulo": "13"
    },
    "intubado": {
      "capitulo": "11"
    },
    "agitação": {
      "capitulo": "06"
    },
    "emese": {
      "capitulo": "01"
    },
    "trombose de artérias pré-cerebrais": {
      "capitulo": "08"
    },
    "abertura ocular espontânea": {
      "capitulo": "09"
    },
    "lúcido": {
      "capitulo": "06"
    },
    "traumatismos múltiplos": {
      "capitulo": "22"
    },
    "coma": {
      "capitulo": "08"
    },
    "purulenta": {
      "capitulo": "13"
    },
    "edema": {
      "capitulo": "14"
    },
    "mv livres": {
      "capitulo": "12"
    },
    "infarto cerebral": {
      "capitulo": "08"
    },
    "hemorragias intracerebrais": {
      "capitulo": "08"
    },
    "agitado": {
      "capitulo": "06"
    },
    "tecido necrótico": {
      "capitulo": "15"
    }
  }
}