{
  "prontuario_id": 233,
  "text": "Paciente em Pré-operatório de FX fêmur E, consciente, orientado, comunicativo, ansioso, em jejum para realização de procedimento cirúrgico hoje, com acesso venoso periférico heparinizado MSE, com tração transesquelética MIE, eliminações fisiológicas pres. FRATURA DO COLO DO FÊMUR. 18:24: PROVENIENTE DO CC LÚCIDA, COMUNICATIVA, MANTÉM ACESSO VENOSO PERIFÉRICO EM MMSS, MANTÉM CTVO EM ABD, SEM DIURESE ATÉ O MOMENTO, PERMANECE EM JEJUM. CALCULOSE DA VESÍCULA BILIAR SEM COLECISTITE. 12:30h: Consciente, comunicativo, acamado, afebril, eupnéico, SNE com dieta em BI, acesso venoso periférico em MSD, foi trocada trach care pela cânula de metal, tração transesquelética em MIE, apresentou dor em MIE, realizado troca de fralda com micção. TRAUMATISMOS MÚLTIPLOS NÃO ESPECIFICADOS. 09:00: RECEBEU ALTA E ORIENTAÇÕES PELO Dr. VITAL BRASIL, SEM QUEIXAS ÁLGICAS NO MOMENTO, DEAMBULANDO, AGUARDA FAMÍLIA VIR BUSCÁ-LA. TRANSTORNOS DA CONTINUIDADE DO OSSO. 12:56 Hr: 4º PO de fratura luxação de cotovelo direito, segue com algia moderada no local, mantém tala gessada e fixador externo em MSD com edema local, boa perfusão distal e pulso periférico preservado. Mantém gesso em perna direita com boa perfusão distal. FRATURA DA EXTREMIDADE DISTAL DO RÁDIO. 15:45HRS: CONSCIENTE, ORIENTADA, ALERTA, DISARTRIA. EUPNÉICA E AFEBRIL. ACEITANDO POUCO A DIETA VO. AVP EM MSE PERMEÁVEL. APRESENTOU ESPASMO FACIAL À DIREITA NO PERÍODO DA MANHÃ. HEMIPARESIA À ESQUERDA. FAZ USO DE FRALDA, COM DIURESE E EVACUAÇÃO PRESENTES. OUTRAS HEMORRAGIAS INTRACEREBRAIS.",
  "entities": {
    "Paciente ou Grupo com Deficiência": [
      "Paciente"
    ],
    "Conceito Temporal": [
      "Pré-operatório",
      "PO",
      "PERÍODO DA MANHÃ"
    ],
    "Abreviação": [
      "E",
      "MSE",
      "CC",
      "MMSS",
      "CTVO",
      "ABD",
      "SNE",
      "MSD",
      "PO",
      "AVP",
      "eliminações fisiológicas",
      "dieta em BI"
    ],
    "Conceito Espacial": [
      "E",
      "direito",
      "direita",
      "DIREITA",
      "ESQUERDA"
    ],
    "Achado": [
      "consciente",
      "orientado",
      "comunicativo",
      "jejum",
      "LÚCIDA",
      "COMUNICATIVA",
      "Consciente",
      "afebril",
      "eupnéico",
      "DEAMBULANDO",
      "CONSCIENTE",
      "ORIENTADA",
      "ALERTA",
      "EUPNÉICA",
      "AFEBRIL",
      "acesso venoso periférico",
      "pulso periférico preservado"
    ],
    "Sinal ou Sintoma": [
      "ansioso",
      "dor",
      "edema",
      "HEMIPARESIA",
      "algia moderada",
      "ESPASMO FACIAL"
    ],
    "Localização ou Região Corporal": [
      "MSE",
      "MIE",
      "MMSS",
      "MSD"
    ],
    "Organização Relacionada à Saúde": [
      "CC"
    ],
    "Negação": [
      "afebril",
      "AFEBRIL"
    ],
    "Função de Organismo": [
      "micção"
    ],
    "Atividade de Assistência à Saúde": [
      "ALTA",
      "procedimento cirúrgico"
    ],
    "Grupo Familiar": [
      "FAMÍLIA"
    ],
    "Conceito Qualitativo": [
      "boa",
      "ACEITANDO POUCO"
    ],
    "Procedimento Terapêutico ou Preventivo": [
      "gesso",
      "AVP",
      "acesso venoso periférico",
      "tração transesquelética",
      "ACESSO VENOSO PERIFÉRICO",
      "dieta em BI",
      "tala gessada",
      "fixador externo",
      "DIETA VO"
    ],
    "Parte do Corpo, Órgão ou Componente Orgânico": [
      "perna"
    ],
    "Disfunção Mental ou Comportamental": [
      "DISARTRIA"
    ],
    "Dispositivo Médico": [
      "AVP",
      "acesso venoso periférico",
      "ACESSO VENOSO PERIFÉRICO",
      "trach care",
      "cânula de metal",
      "tala gessada",
      "fixador externo"
    ],
    "Função Fisiológica": [
      "eliminações fisiológicas"
    ],
    "Lesão ou Envenenamento": [
      "FRATURA DO COLO DO FÊMUR",
      "fratura luxação de cotovelo",
      "FRATURA DA EXTREMIDADE DISTAL DO RÁDIO"
    ],
    "Doença ou Síndrome": [
      "CALCULOSE DA VESÍCULA BILIAR",
      "TRANSTORNOS DA CONTINUIDADE DO OSSO",
      "HEMORRAGIAS INTRACEREBRAIS"
    ],
    "Anormalidade Adquirida": [
      "TRANSTORNOS DA CONTINUIDADE DO OSSO"
    ]
  },
  "labels": {
    "fratura do colo do fêmur": {
      "capitulo": "15"
    },
    "calculose da vesícula biliar": {
      "capitulo": "13"
    },
    "transtornos da continuidade do osso": {
      "capitulo": "15"
    },
    "hemiparesia": {
      "capitulo": "08"
    },
    "disartria": {
      "capitulo": "06"
    },
    "fratura luxação de cotovelo": {
      "capitulo": "15"
    },
    "algia moderada": {
      "capitulo": "15"
    },
    "espasmo facial": {
      "capitulo": "21"
    },
    "edema": {
      "capitulo": "21"
    },
    "ansioso": {
      "capitulo": "06"
    },
    "hemorragias intracerebrais": {
      "capitulo": "08"
    },
    "fratura da extremidade distal do rádio": {
      "capitulo": "15"
    },
    "dor": {
      "capitulo": "21"
    }
  }
}