{
  "prontuario_id": 404,
  "text": "10:30hs: 34° dia de UTI por ICC, obesidade mórbida e HAS, glasglow 15, pupilas isocóricas e fotorreativas, TQt em névoa úmida 5l/min, SVD com diurese efetiva e alaranjada, AVP MIE com nipride a 5ml/h. Monitorizada com PNI: 85mmHg, FC: 94bpm, SPO2: 95%, lesões em proeminêcias gordurosas na região do dorso em processo de cicatrização, mucosas coradas, pele hidratada, extremidades aquecidas e bem perfundidas. 19:16 HS: PROVENIENTE DO PS ÀS 16:00, CONSCIENTE ,ORIENTADA, EUPNÉICA, TAQUICÁRDICA, CADEIRANTE, EMAGRECIDA, FÍSTULA MSE, ACEITA DIETA, COM ACESSO VENOSO PERIFÉRICO COM SOROTERAPIA, ACEITA DIETA, SEM QUEIXAS ÁLGICAS DURANTE O PERÍODO. 22:40h: Admitida nesta unidade proveniente do CC após realizar POI Ponte Ilíaco-Femoral E com prótese PTFE, HX: DM + HAS + Tabagismo. Na admissão, PA 230/90mmhg,FC 152bpm, Sat. 94%, face hipocorada, pupilas isocóricas / fotorreagentes, apresentando tremores + pele fria. Respiração espontânea com suporte de névoa úmida 4L/min, ausculta pulmonar com roncos difusos. Acesso periférico MSD + MSE iniciado com nipride 10ml/hr + medicação para algia em reg. abdominal. FO reg. abdominal + ilíaca E aparentemente limpa. PAM radial E permeável, mas perfusão periférica em extremidades diminuídas. Diurese por SVD presente em coletor, amarelo cítrico. 2° e 3° quirodáctilos com extremidades escurecidas. Monitorizada continuamente com cardioscópio + oximetria de pulso + pam não invasiva.    ",
  "entities": {
    "Organização Relacionada à Saúde": [
      "UTI",
      "unidade",
      "CC"
    ],
    "Abreviação": [
      "ICC",
      "HAS",
      "TQt",
      "5l/min",
      "SVD",
      "AVP",
      "MIE",
      "5ml/h",
      "PNI",
      "85mmHg",
      "SPO2",
      "PS",
      "MSE",
      "CC",
      "POI",
      "E",
      "HX",
      "DM",
      "Sat",
      "4L/min",
      "MSD",
      "10ml/hr",
      "reg",
      "FO",
      "PAM",
      "prótese PTFE",
      "ilíaca E",
      "pam não invasiva"
    ],
    "Doença ou Síndrome": [
      "ICC",
      "HAS",
      "DM",
      "Tabagismo",
      "obesidade mórbida"
    ],
    "Procedimento Terapêutico ou Preventivo": [
      "TQt",
      "SVD",
      "AVP",
      "Monitorizada",
      "SOROTERAPIA",
      "névoa úmida",
      "ACESSO VENOSO PERIFÉRICO",
      "Ponte Ilíaco-Femoral",
      "Acesso periférico",
      "medicação para algia"
    ],
    "Conceito Quantitativo": [
      "5l/min",
      "5ml/h",
      "85mmHg",
      "94bpm",
      "95%",
      "230/90mmhg",
      "152bpm",
      "94%",
      "4L/min",
      "10ml/hr"
    ],
    "Dispositivo Médico": [
      "SVD",
      "AVP",
      "coletor",
      "cardioscópio",
      "ACESSO VENOSO PERIFÉRICO",
      "prótese PTFE",
      "Acesso periférico",
      "oximetria de pulso"
    ],
    "Função Fisiológica": [
      "diurese",
      "Diurese"
    ],
    "Localização ou Região Corporal": [
      "MIE",
      "MSE",
      "MSD",
      "abdominal",
      "reg",
      "região do dorso"
    ],
    "Substância Farmacológica": [
      "nipride"
    ],
    "Substância Química Inorgânica": [
      "nipride"
    ],
    "Procedimento Diagnóstico": [
      "Monitorizada",
      "ausculta pulmonar",
      "oximetria de pulso"
    ],
    "Achado": [
      "Monitorizada",
      "CONSCIENTE",
      "ORIENTADA",
      "EUPNÉICA",
      "CADEIRANTE",
      "EMAGRECIDA",
      "limpa",
      "permeável",
      "glasglow 15",
      "pupilas isocóricas e fotorreativas",
      "efetiva e alaranjada",
      "mucosas coradas",
      "pele hidratada",
      "bem perfundidas",
      "SEM QUEIXAS ÁLGICAS",
      "Respiração espontânea",
      "perfusão periférica em extremidades diminuídas",
      "amarelo cítrico"
    ],
    "Sinal ou Sintoma": [
      "TAQUICÁRDICA",
      "tremores",
      "face hipocorada",
      "pele fria",
      "roncos difusos"
    ],
    "Função Patológica": [
      "TAQUICÁRDICA",
      "processo de cicatrização"
    ],
    "Paciente ou Grupo com Deficiência": [
      "CADEIRANTE"
    ],
    "Anormalidade Anatômica": [
      "FÍSTULA"
    ],
    "Alimento": [
      "DIETA"
    ],
    "Conceito Temporal": [
      "POI",
      "continuamente"
    ],
    "Conceito Espacial": [
      "E"
    ],
    "Comportamento Individual": [
      "Tabagismo"
    ],
    "Atributo Clínico": [
      "Sat"
    ],
    "Parte do Corpo, Órgão ou Componente Orgânico": [
      "radial",
      "quirodáctilos",
      "ilíaca E"
    ],
    "Conceito Qualitativo": [
      "permeável",
      "amarelo cítrico"
    ],
    "Negação": [
      "SEM QUEIXAS ÁLGICAS"
    ]
  },
  "labels": {
    "perfusão periférica em extremidades diminuídas": {
      "capitulo": "11"
    },
    "taquicárdica": {
      "capitulo": "06"
    },
    "monitorizada": {
      "capitulo": "21"
    },
    "cadeirante": {
      "capitulo": "06"
    },
    "tabagismo": {
      "capitulo": "05"
    },
    "eupnéica": {
      "capitulo": "06"
    },
    "face hipocorada": {
      "capitulo": "08"
    },
    "amarelo cítrico": {
      "capitulo": "14"
    },
    "pupilas isocóricas e fotorreativas": {
      "capitulo": "08"
    },
    "icc": {
      "capitulo": "11"
    },
    "pele fria": {
      "capitulo": "21"
    },
    "tremores": {
      "capitulo": "06"
    },
    "roncos difusos": {
      "capitulo": "12"
    },
    "obesidade mórbida": {
      "capitulo": "05"
    },
    "fístula": {
      "capitulo": "16"
    },
    "permeável": {
      "capitulo": "21"
    },
    "mucosas coradas": {
      "capitulo": "14"
    },
    "has": {
      "capitulo": "05"
    },
    "processo de cicatrização": {
      "capitulo": "21"
    },
    "dm": {
      "capitulo": "05"
    }
  }
}