{
  "prontuario_id": 157,
  "text": "11:40: CONSCIENTE, ALERTA E COMUNICATIVO, RELATA TONTURA E NÁUSEA, SEM QUEIXAS DE DOR. AVPD COM SRT. MANTÉM JEJUM E REPOUSO NO LEITO. SEGUEM CUIDADOS DE ENFERMAGEM. CONCUSSÃO CEREBRAL. 8H: 1º PO DE FX DE ÚMERO ESQ. CONSCIENTE, VERBALIZANDO, AFEBRIL, EUPNÉICA, DEAMBULANTE, AVP EM MSD, ACEITA DIETA VO, REALIZOU HIGIENE CORPORAL, MICÇÃO PRESENTE E EVACUAÇÃO AUSENTE, SEM QUEIXAS ÁLGICAS E CURATIVO EM MSE COM EXSUDATO SANGUINOLENTO. FRATURA DA CINTURA ESCAPULAR PARTE NÃO ESPECIFICADA. 07/11/2007: Abertura ocular ao chamado. Púpilas isocóricas e fotorreagentes. Responsiva a estímulos dolorosos e aspirativos. Obedece a comandos verbais simples. Traqueostomizado em ventilação mecânica com sistema fechado de sucção e filtro bacteriológico/v. HEMORRAGIA SUBARACNÓIDE. 15:26: ALERTA, COMUNICATIVA, PRIMEIRO P.O.  DE APENDICECTOMIA, BOA ACEITAÇÃO DA DIETA OFERECIDA, MANTÉM ACESSO VENOSO SALINIZADO EM MSE, DEAMBULA, NÃO REFERE ALGIAS, DIURESE ESPONTÂNEA, EVACUAÇÃO AUSENTE. SEGUE SOB CUIDADOS DE ENFERMAGEM. APENDICITE AGUDA SEM OUTRA ESPECIFICAÇÃO. 01:00: DM + Anemia. # precaução por MRSA. # Consciente, confuso, pouco comunicativo. SNE com dieta em BI, acesso venoso em MSD, curativo con exsudato serossanguinolento em coto IE e curativo limpo e seco externamente em MID. Evacuação ausente há 5 dias. OUTRAS PNEUMONIAS BACTERIANAS.",
  "entities": {
    "Achado": [
      "CONSCIENTE",
      "ALERTA",
      "COMUNICATIVO",
      "JEJUM",
      "VERBALIZANDO",
      "AFEBRIL",
      "EUPNÉICA",
      "DEAMBULANTE",
      "Traqueostomizado",
      "COMUNICATIVA",
      "DEAMBULA",
      "Consciente",
      "limpo",
      "seco",
      "REPOUSO NO LEITO",
      "MICÇÃO PRESENTE",
      "SEM QUEIXAS ÁLGICAS",
      "EXSUDATO SANGUINOLENTO",
      "Púpilas isocóricas e fotorreagentes",
      "Responsiva a estímulos dolorosos e aspirativos",
      "Obedece a comandos verbais simples",
      "BOA ACEITAÇÃO",
      "DIURESE ESPONTÂNEA",
      "exsudato serossanguinolento"
    ],
    "Sinal ou Sintoma": [
      "TONTURA",
      "NÁUSEA",
      "DOR",
      "confuso",
      "Abertura ocular ao chamado",
      "pouco comunicativo"
    ],
    "Conceito Espacial": [
      "AVPD",
      "ESQ"
    ],
    "Procedimento Terapêutico ou Preventivo": [
      "AVPD",
      "SRT",
      "JEJUM",
      "AVP",
      "CURATIVO",
      "APENDICECTOMIA",
      "SALINIZADO",
      "SNE",
      "curativo",
      "REPOUSO NO LEITO",
      "DIETA VO",
      "HIGIENE CORPORAL",
      "ventilação mecânica",
      "sistema fechado de sucção",
      "filtro bacteriológico/v",
      "ACESSO VENOSO",
      "precaução por MRSA",
      "dieta em BI",
      "acesso venoso"
    ],
    "Abreviação": [
      "AVPD",
      "SRT",
      "PO",
      "AVP",
      "MSD",
      "MSE",
      "DM",
      "SNE",
      "MID",
      "filtro bacteriológico/v",
      "PRIMEIRO P",
      "precaução por MRSA",
      "dieta em BI",
      "coto IE"
    ],
    "Conceito Temporal": [
      "PO"
    ],
    "Negação": [
      "AFEBRIL",
      "SEM QUEIXAS",
      "EVACUAÇÃO AUSENTE",
      "SEM QUEIXAS ÁLGICAS",
      "Evacuação ausente"
    ],
    "Dispositivo Médico": [
      "AVP",
      "CURATIVO",
      "SNE",
      "curativo",
      "sistema fechado de sucção",
      "filtro bacteriológico/v",
      "ACESSO VENOSO",
      "acesso venoso"
    ],
    "Localização ou Região Corporal": [
      "MSD",
      "MSE",
      "MID",
      "coto IE"
    ],
    "Conceito Qualitativo": [
      "SALINIZADO",
      "BOA ACEITAÇÃO",
      "pouco comunicativo"
    ],
    "Doença ou Síndrome": [
      "DM",
      "Anemia",
      "HEMORRAGIA SUBARACNÓIDE",
      "APENDICITE AGUDA",
      "PNEUMONIAS BACTERIANAS"
    ],
    "Disfunção Mental ou Comportamental": [
      "confuso"
    ],
    "Atividade de Assistência à Saúde": [
      "CUIDADOS DE ENFERMAGEM"
    ],
    "Lesão ou Envenenamento": [
      "CONCUSSÃO CEREBRAL",
      "FRATURA DA CINTURA ESCAPULAR"
    ],
    "Função Fisiológica": [
      "MICÇÃO PRESENTE",
      "EVACUAÇÃO AUSENTE",
      "DIURESE ESPONTÂNEA",
      "Evacuação ausente"
    ]
  },
  "labels": {
    "boa aceitação": {
      "capitulo": "13"
    },
    "obedece a comandos verbais simples": {
      "capitulo": "06"
    },
    "púpilas isocóricas e fotorreagentes": {
      "capitulo": "09"
    },
    "traqueostomizado": {
      "capitulo": "22"
    },
    "exsudato sanguinolento": {
      "capitulo": "14"
    },
    "responsiva a estímulos dolorosos e aspirativos": {
      "capitulo": "06"
    },
    "comunicativo": {
      "capitulo": "06"
    },
    "verbalizando": {
      "capitulo": "06"
    },
    "anemia": {
      "capitulo": "03"
    },
    "alerta": {
      "capitulo": "06"
    },
    "confuso": {
      "capitulo": "06"
    },
    "fratura da cintura escapular": {
      "capitulo": "15"
    },
    "abertura ocular ao chamado": {
      "capitulo": "09"
    },
    "comunicativa": {
      "capitulo": "06"
    },
    "concussão cerebral": {
      "capitulo": "08"
    },
    "consciente": {
      "capitulo": "06"
    },
    "náusea": {
      "capitulo": "13"
    },
    "hemorragia subaracnóide": {
      "capitulo": "08"
    },
    "pouco comunicativo": {
      "capitulo": "06"
    },
    "exsudato serossanguinolento": {
      "capitulo": "14"
    },
    "pneumonias bacterianas": {
      "capitulo": "12"
    },
    "dm": {
      "capitulo": "05"
    },
    "tontura": {
      "capitulo": "13"
    },
    "apendicite aguda": {
      "capitulo": "13"
    }
  }
}