{
  "prontuario_id": 854,
  "text": "9:45Hrs: Cliente em Ramsay 6, pupilas iso / foto +, intubado em TOT n° 8.0 rima labial 24cm DIR, VM nos parâmetros CMV, VC 540ml, peep 5cmH2O, FR 20, FiO2 40%, face corada, mucosa oral hidratada, boa perfusão periférica, no leito com cabeceira elevada a 45°. Jejum até 2° ordem. Mantém com monitorização de multiparâmetros: ECG, PAM em radial ESQ (oxilante), SpO2, SNG aberta em narina ESQ com estase gástrica ++ de aspecto biliosa, catéter venoso central duplo-lúmen em subclávia ESQ com noradrenalina 14ml/hr, dormonid 35ml/hr (planos dobrados) em curso BI, acesso venoso periférico em MSE com fentanil 20ml/hr (plano dobrado) em curso BI, DTF D anterior com débito seroso e posterior sero-hemático, DTF E com débito seroso, ctvos em regiões toracoabdominal + dorsal com presença de secreção serosa em pouca quantidade. Apresenta ausculta cardíaca rítmica e normofonética, ausculta pulmonar MV + sem R/A, abdômen plano e flácido com RHA hipoativos, edemas em MMSS cacifo I. Faz uso de SVD aberta com débito diurético presente + de coloração amarelo claro, eliminação fecal ausente. Seguem cuidados intensivos de enfermagem.  Enf° Florence, Coren 9999. FERIMENTOS MÚLTIPLOS DA PAREDE TORÁCICA.",
  "entities": {
    "Paciente ou Grupo com Deficiência": [
      "Cliente"
    ],
    "Achado": [
      "intubado",
      "sero-hemático",
      "rítmica",
      "normofonética",
      "flácido",
      "edemas",
      "pupilas iso / foto +",
      "face corada",
      "mucosa oral hidratada",
      "boa perfusão periférica",
      "débito seroso",
      "secreção serosa",
      "MV +",
      "sem R/A",
      "débito diurético presente",
      "coloração amarelo claro"
    ],
    "Abreviação": [
      "24cm",
      "DIR",
      "VM",
      "VC",
      "540ml",
      "peep",
      "5cmH2O",
      "FiO2",
      "ECG",
      "PAM",
      "SpO2",
      "14ml/hr",
      "35ml/hr",
      "BI",
      "MSE",
      "20ml/hr",
      "DTF",
      "D",
      "E",
      "ctvos",
      "MMSS",
      "Enf°",
      "pupilas iso / foto +",
      "parâmetros CMV",
      "SNG aberta",
      "MV +",
      "sem R/A",
      "RHA hipoativos",
      "SVD aberta"
    ],
    "Conceito Quantitativo": [
      "24cm",
      "540ml",
      "5cmH2O",
      "20",
      "40%",
      "14ml/hr",
      "35ml/hr",
      "20ml/hr",
      "n° 8",
      "pouca quantidade"
    ],
    "Procedimento Terapêutico ou Preventivo": [
      "VM",
      "Jejum",
      "ctvos",
      "leito com cabeceira elevada a 45°",
      "SNG aberta",
      "catéter venoso central duplo-lúmen",
      "acesso venoso periférico",
      "SVD aberta"
    ],
    "Procedimento Diagnóstico": [
      "ECG",
      "monitorização de multiparâmetros",
      "ausculta cardíaca",
      "ausculta pulmonar"
    ],
    "Parte do Corpo, Órgão ou Componente Orgânico": [
      "radial",
      "subclávia",
      "rima labial",
      "PAREDE TORÁCICA"
    ],
    "Conceito Espacial": [
      "ESQ",
      "anterior",
      "posterior",
      "E"
    ],
    "Conceito Qualitativo": [
      "oxilante",
      "biliosa",
      "pouca quantidade",
      "cacifo I"
    ],
    "Substância Farmacológica": [
      "noradrenalina",
      "dormonid",
      "fentanil"
    ],
    "Hormônio": [
      "noradrenalina"
    ],
    "Substância Química Orgânica": [
      "dormonid",
      "fentanil"
    ],
    "Dispositivo Médico": [
      "BI",
      "ctvos",
      "catéter venoso central duplo-lúmen",
      "acesso venoso periférico",
      "SVD aberta"
    ],
    "Localização ou Região Corporal": [
      "MSE",
      "abdômen",
      "MMSS",
      "regiões toracoabdominal"
    ],
    "Conceito Funcional": [
      "uso"
    ],
    "Sinal ou Sintoma": [
      "Ramsay 6",
      "RHA hipoativos",
      "cacifo I",
      "eliminação fecal ausente"
    ],
    "Doença ou Síndrome": [
      "estase gástrica"
    ],
    "Substância Corporal": [
      "secreção serosa"
    ],
    "Negação": [
      "sem R/A",
      "eliminação fecal ausente"
    ],
    "Função Fisiológica": [
      "débito diurético presente",
      "eliminação fecal ausente"
    ],
    "Atividade de Assistência à Saúde": [
      "cuidados intensivos de enfermagem"
    ],
    "Lesão ou Envenenamento": [
      "FERIMENTOS MÚLTIPLOS"
    ]
  },
  "labels": {
    "rha hipoativos": {
      "capitulo": "11"
    },
    "estase gástrica": {
      "capitulo": "13"
    },
    "flácido": {
      "capitulo": "15"
    },
    "ferimentos múltiplos": {
      "capitulo": "22"
    },
    "edemas": {
      "capitulo": "11"
    },
    "normofonética": {
      "capitulo": "21"
    },
    "débito seroso": {
      "capitulo": "21"
    },
    "sero-hemático": {
      "capitulo": "21"
    },
    "intubado": {
      "capitulo": "12"
    },
    "secreção serosa": {
      "capitulo": "21"
    },
    "mv +": {
      "capitulo": "21"
    },
    "sem r/a": {
      "capitulo": "21"
    },
    "coloração amarelo claro": {
      "capitulo": "21"
    },
    "rítmica": {
      "capitulo": "21"
    },
    "face corada": {
      "capitulo": "21"
    },
    "débito diurético presente": {
      "capitulo": "21"
    },
    "eliminação fecal ausente": {
      "capitulo": "21"
    }
  }
}