{
  "prontuario_id": 568,
  "text": "00:27hs: Estável, consciente, comunicativo; deambulando, corado, eupnéico; mantém tala gessada em membro superior direito; apresenta boa perfusão periférica; refere algia moderada; segue sob cuidados de enfermagem. CONCUSSÃO CEREBRAL. 15:55 HORAS: 3° DIA DE INTERNAMENTO, COM HISTÓRIA DE QUEDA DE NÍVEL. MANTENDO COLAR CERVICAL CONFORME RECOMENDAÇÕES MÉDICAS. PERMANECE EM REPOUSO NO LEITO, DEAMBULANDO. CORADA, HIDRATADA E EUPNÉICA RESPIRANDO EM AR AMBIENTE. SINAIS VITAIS ESTÁVEIS. APRESENTA FRATURA DA PRIMEIRA VÉRTEBRA CERVICAL. PCTE POT CIR COLUNA CERVICAL. RETIRADO SVD + DRENO DE SUCTOR, AVP MSE SRT, MANTENDO COLAR CERVICAL C/ QUEIXAS DE DOR, MED CPM. AGUARDA LIBERAÇÃO DO CONVÊNIO. RESTRITO AO LEITO, ELIMINAÇÕES PRESENTES, ALIMENTANDO-SE BEM. REALIZADO CTVO EM REGIÃO DO CRÂNIO. FRATURA DO PESCOÇO PARTE NÃO ESPECIFICADA.",
  "entities": {
    "Achado": [
      "Estável",
      "consciente",
      "comunicativo",
      "deambulando",
      "corado",
      "eupnéico",
      "DEAMBULANDO",
      "CORADA",
      "HIDRATADA",
      "EUPNÉICA",
      "perfusão periférica",
      "REPOUSO NO LEITO",
      "RESPIRANDO EM AR AMBIENTE",
      "SINAIS VITAIS ESTÁVEIS",
      "RESTRITO AO LEITO",
      "ELIMINAÇÕES PRESENTES",
      "ALIMENTANDO-SE BEM"
    ],
    "Conceito Espacial": [
      "direito"
    ],
    "Conceito Qualitativo": [
      "boa"
    ],
    "Sinal ou Sintoma": [
      "algia",
      "QUEIXAS DE DOR"
    ],
    "Atividade de Assistência à Saúde": [
      "INTERNAMENTO",
      "cuidados de enfermagem",
      "RECOMENDAÇÕES MÉDICAS"
    ],
    "Abreviação": [
      "PCTE",
      "POT",
      "SVD",
      "AVP",
      "MSE",
      "SRT",
      "MED",
      "CPM",
      "CTVO",
      "CIR COLUNA CERVICAL"
    ],
    "Paciente ou Grupo com Deficiência": [
      "PCTE"
    ],
    "Conceito Temporal": [
      "POT"
    ],
    "Procedimento Terapêutico ou Preventivo": [
      "SVD",
      "AVP",
      "SRT",
      "CTVO",
      "tala gessada",
      "COLAR CERVICAL",
      "REPOUSO NO LEITO",
      "CIR COLUNA CERVICAL"
    ],
    "Dispositivo Médico": [
      "SVD",
      "AVP",
      "CTVO",
      "tala gessada",
      "COLAR CERVICAL",
      "DRENO DE SUCTOR"
    ],
    "Localização ou Região Corporal": [
      "MSE",
      "REGIÃO DO CRÂNIO"
    ],
    "Organização Relacionada à Saúde": [
      "CONVÊNIO"
    ],
    "Parte do Corpo, Órgão ou Componente Orgânico": [
      "membro superior"
    ],
    "Lesão ou Envenenamento": [
      "CONCUSSÃO CEREBRAL",
      "HISTÓRIA DE QUEDA DE NÍVEL",
      "FRATURA DA PRIMEIRA VÉRTEBRA CERVICAL",
      "FRATURA DO PESCOÇO"
    ],
    "Função Fisiológica": [
      "ELIMINAÇÕES PRESENTES"
    ]
  },
  "labels": {
    "eupnéico": {
      "capitulo": "11"
    },
    "perfusão periférica": {
      "capitulo": "11"
    },
    "restrito ao leito": {
      "capitulo": "22"
    },
    "corado": {
      "capitulo": "15"
    },
    "eupnéica": {
      "capitulo": "11"
    },
    "fratura do pescoço": {
      "capitulo": "15"
    },
    "comunicativo": {
      "capitulo": "06"
    },
    "deambulando": {
      "capitulo": "15"
    },
    "respirando em ar ambiente": {
      "capitulo": "12"
    },
    "queixas de dor": {
      "capitulo": "21"
    },
    "história de queda de nível": {
      "capitulo": "22"
    },
    "concussão cerebral": {
      "capitulo": "08"
    },
    "corada": {
      "capitulo": "15"
    },
    "consciente": {
      "capitulo": "06"
    },
    "algia": {
      "capitulo": "21"
    },
    "eliminações presentes": {
      "capitulo": "22"
    },
    "fratura da primeira vértebra cervical": {
      "capitulo": "15"
    }
  }
}