{
  "prontuario_id": 476,
  "text": "18h: Realização de hemodiálise com duração de 03h e UF de 500ml. 21/03/2012,10:00hs: 8° DI por CA Biliar 5º PO, de Hepatectomia à D + Linfadenectomia + Derivação Biliodigestiva Hepatojejunal, 6º D de TOT + VM, 6º D de acesso venoso central em jugular interna D - curativo trocado em 20/03/12, 5º D de catéter de hemodiálise em subclávia D - curativo trocado em 21/03/12, 6º D de PAM em radial E, 6º D de dreno suctor em flanco D, 6º D de SVD. PA: 108/65, P: 67, FR: 15, T: 35,7ºC, SpO2: 96%, Ramsay 6, pupilas isomióticas, SNG com dieta a 20ml/h, intubada com TOT 7.5, rima 24, em ventilação mecânica modo VCV, Vc 420ml, PEEP 5, FiO2 30%, secreção traqueobrônquica mucosa em média quantidade, acesso venoso central em jugular D com Propofol a 2ml/h + Fentanil 10ml/h, acesso venoso central com catéter de hemodiálise em subclávia D heparinizado, monitorizada, estável hemodinamicamente, MV+ com roncos e bolhosos, PAM em radial E, abdome globoso, flácido, RHA+, FO abdominal limpa e seca, dreno suctor em flanco D com pouca drenagem de secreção hemática, SVD com diurese efetiva, evacuação ausente, extremidades bem perfundidas, higienizada e sentada no leito, pele íntegra. ",
  "entities": {
    "Procedimento Terapêutico ou Preventivo": [
      "hemodiálise",
      "Hepatectomia",
      "Linfadenectomia",
      "TOT",
      "VM",
      "curativo",
      "PAM",
      "SVD",
      "SNG",
      "heparinizado",
      "Derivação Biliodigestiva Hepatojejunal",
      "acesso venoso central",
      "catéter de hemodiálise",
      "dreno suctor",
      "ventilação mecânica modo VCV"
    ],
    "Abreviação": [
      "03h",
      "UF",
      "500ml",
      "DI",
      "PO",
      "D",
      "TOT",
      "VM",
      "PAM",
      "SVD",
      "SpO2",
      "SNG",
      "20ml/h",
      "Vc",
      "420ml",
      "PEEP",
      "FiO2",
      "2ml/h",
      "10ml/h",
      "MV+",
      "RHA+",
      "FO",
      "CA Biliar",
      "jugular interna",
      "subclávia D",
      "radial E",
      "ventilação mecânica modo VCV",
      "jugular D"
    ],
    "Conceito Quantitativo": [
      "500ml",
      "108/65",
      "67",
      "15",
      "96%",
      "20ml/h",
      "7",
      "24",
      "420ml",
      "5",
      "30%",
      "2ml/h",
      "10ml/h",
      "35 , 7ºC",
      "média quantidade"
    ],
    "Conceito Temporal": [
      "PO"
    ],
    "Dispositivo Médico": [
      "TOT",
      "curativo",
      "SVD",
      "SNG",
      "acesso venoso central",
      "catéter de hemodiálise",
      "dreno suctor"
    ],
    "Localização ou Região Corporal": [
      "flanco",
      "abdome",
      "abdominal"
    ],
    "Conceito Espacial": [
      "D"
    ],
    "Alimento": [
      "dieta"
    ],
    "Parte do Corpo, Órgão ou Componente Orgânico": [
      "rima",
      "jugular interna",
      "subclávia D",
      "radial E",
      "jugular D"
    ],
    "Substância Química Orgânica": [
      "Propofol",
      "Fentanil"
    ],
    "Substância Farmacológica": [
      "Propofol",
      "Fentanil"
    ],
    "Conceito Qualitativo": [
      "heparinizado",
      "bolhosos",
      "pouca drenagem"
    ],
    "Procedimento Diagnóstico": [
      "monitorizada"
    ],
    "Achado": [
      "monitorizada",
      "MV+",
      "flácido",
      "RHA+",
      "limpa",
      "seca",
      "higienizada",
      "secreção traqueobrônquica mucosa",
      "estável hemodinamicamente",
      "pouca drenagem",
      "diurese efetiva",
      "evacuação ausente",
      "extremidades bem perfundidas",
      "sentada no leito",
      "pele íntegra"
    ],
    "Sinal ou Sintoma": [
      "globoso",
      "Ramsay 6",
      "pupilas isomióticas",
      "secreção hemática"
    ],
    "Processo Neoplásico": [
      "CA Biliar"
    ],
    "Substância Corporal": [
      "secreção traqueobrônquica mucosa"
    ],
    "Função Fisiológica": [
      "diurese efetiva",
      "evacuação ausente"
    ],
    "Negação": [
      "evacuação ausente"
    ]
  },
  "labels": {
    "pele íntegra": {
      "capitulo": "14"
    },
    "flácido": {
      "capitulo": "15"
    },
    "secreção traqueobrônquica mucosa": {
      "capitulo": "12"
    },
    "evacuação ausente": {
      "capitulo": "21"
    },
    "ca biliar": {
      "capitulo": "13"
    },
    "secreção hemática": {
      "capitulo": "12"
    },
    "estável hemodinamicamente": {
      "capitulo": "11"
    },
    "mv+": {
      "capitulo": "21"
    },
    "ramsay 6": {
      "capitulo": "06"
    },
    "pupilas isomióticas": {
      "capitulo": "08"
    },
    "diurese efetiva": {
      "capitulo": "16"
    },
    "pouca drenagem": {
      "capitulo": "12"
    },
    "limpa": {
      "capitulo": "14"
    },
    "globoso": {
      "capitulo": "15"
    },
    "seca": {
      "capitulo": "14"
    }
  }
}