{
  "prontuario_id": 757,
  "text": "16:22: CLIENTE FOI ENCAMINHADO AO HOSPITAL DO EXÉRCITO  ÀS 15:15, FOI TRANSFERIDO PELO ECO SALVA. ENFª FLORENCE XXXXX. EXAME GERAL E INVESTIGAÇÃO DE PESSOAS SEM QUEIXAS OU DIAGNÓSTICO. RELATADO EM TEMPO: Paciente encaminhado ao CC, por volta das 06:30. TRAUMATISMO DO MÚSCULO FLEXOR E TENDÃO DE OUTRO DEDO AO NÍVEL DO PUNHO E DA MÃO. 11:34 HS: CONSCIENTE, ORIENTADO, EUPNÉICO, EMAGRECIDO, COM DIETA EM SONDA ENTERAL, EM BI A 60ML/H, ACESSO VENOSO CENTRAL EM SUBCLÁVIA D, PERMEÁVEL PARA HD, CURATIVO EM REGIÃO ABDOMINAL SANGUINOLENTO, COM BOLSA ESCROTAL EDEMACIADA, CURATIVO COM CARVÃO ATIVADO, REALIZADO PELA ENF FLORENCE. ORIENTO REALIZAR TROCA DE CURATIVO SECUNDÁRIO. REFERIU CEFALÉIA, MEDICADO CONF PRESCRIÇÃO MÉDICA, MANTÉM PRECAUÇÃO DE CONTATO E VIAS AÉREAS. ENF FLORENCE, COREN 9999. SEPTICEMIA NÃO ESPECIFICADA.",
  "entities": {
    "Paciente ou Grupo com Deficiência": [
      "CLIENTE",
      "Paciente"
    ],
    "Abreviação": [
      "ENFª",
      "CC",
      "BI",
      "60ML/H",
      "HD",
      "ENF",
      "SUBCLÁVIA D"
    ],
    "Grupo Populacional": [
      "PESSOAS"
    ],
    "Conceito Temporal": [
      "TEMPO"
    ],
    "Organização Relacionada à Saúde": [
      "CC",
      "ECO SALVA"
    ],
    "Achado": [
      "CONSCIENTE",
      "ORIENTADO",
      "EUPNÉICO",
      "PERMEÁVEL",
      "SANGUINOLENTO",
      "BOLSA ESCROTAL EDEMACIADA"
    ],
    "Sinal ou Sintoma": [
      "EMAGRECIDO",
      "CEFALÉIA"
    ],
    "Dispositivo Médico": [
      "BI",
      "CURATIVO",
      "ACESSO VENOSO CENTRAL",
      "CURATIVO COM CARVÃO ATIVADO"
    ],
    "Conceito Quantitativo": [
      "60ML/H"
    ],
    "Conceito Qualitativo": [
      "PERMEÁVEL",
      "SANGUINOLENTO"
    ],
    "Procedimento Terapêutico ou Preventivo": [
      "HD",
      "CURATIVO",
      "MEDICADO",
      "DIETA EM SONDA ENTERAL",
      "ACESSO VENOSO CENTRAL",
      "CURATIVO COM CARVÃO ATIVADO",
      "TROCA DE CURATIVO SECUNDÁRIO",
      "PRECAUÇÃO DE CONTATO",
      "VIAS AÉREAS"
    ],
    "Atividade de Assistência à Saúde": [
      "MEDICADO",
      "EXAME GERAL"
    ],
    "Parte do Corpo, Órgão ou Componente Orgânico": [
      "SUBCLÁVIA D"
    ],
    "Localização ou Região Corporal": [
      "REGIÃO ABDOMINAL"
    ],
    "Produto Intelectual": [
      "PRESCRIÇÃO MÉDICA"
    ]
  },
  "labels": {
    "cefaléia": {
      "capitulo": "06"
    },
    "bolsa escrotal edemaciada": {
      "capitulo": "15"
    },
    "sanguinolento": {
      "capitulo": "22"
    },
    "permeável": {
      "capitulo": "21"
    },
    "emagrecido": {
      "capitulo": "05"
    }
  }
}