{
  "prontuario_id": 759,
  "text": "Às 16:10: paciente em jejum, aguardando cx herniorrafia, inicia com queixa toracica, chamado plantao da clinica médica para avaliar, realizado eletrocardigrama. Às 08:35hs: Ramsay 6, pupilas isocóricas bradifotorreagentes, incisão cirúrgica cefálica limpa e seca, SNE fechada, SNG aberta com presença de grande quantidade de estase tipo borra de café, traqueostomizado, em ventilação mecânica modo PCV, Pi 18, PEEP 13, fio2 60%, secreção traqueobrônquica amarela em média quantidade, acesso venoso central D com Dormonid 15 ml/h + Propofol 5 ml/h + Fentanil 20 ml/h + Noradrenalina 50 ml/h, monitorizado, instável hemodinamicamente, taquicárdico, hipotenso, MMSS edemaciados +++/4, abdome distendido, rígido, RHA -, calota craniana alojada em flanco E, edema peniano + bolsa escrotal, SVD, em oligúria, evacuação ausente, úlcera sacra grau III, PAM em MIE, extremidades frias e mal perfundidas, MMII edemaciados ++/4, higienizado, mantendo precaução de contato por Klebsiella + Acinetobacter. SEDADO, SOB INTUBAÇÃO OROTRAQUEAL, RIMA 26, EM VENTILAÇÃO MECANICA, EM MODALIDADE PVC, VOLUME CORRENTE DE 155, FREQUÊNCIA VENTILATORIA 18 MRPM, PEEP 7, FIO2 40%, PRESSÃO LIMITE 28, CANULA DE GUEDEL. HEMATOMA EM REGIÃO ORBITAL SUPERCILIO ESQUERDO, ESCORIAÇÕES EM REGIÃO ZIGOMÁTICA E AURICULAR ESQUERDA, SNG COM DÉBITO PRESENTE E SNE FECHADA, AGUARDANDO RAIO-X. AUSCULTA PULMONAR COM CREPITAÇÕES FINAS A ESQUERDA, BCRNF, RHA AUSENTES, ACESSO VENOSO PERIFERICO EM BRAÇO DIREITO COM CATETER DE HASTE FLEXIVEL 14 , COM SEDAÇÃO EM CURSO 15 ML/H EM BOMBA INFUSORA. ESCORIAÇÕES EM MÃOS, SVD ABERTA COM DEBITO PRESENTE DE COR LARANJA, FAZ USO DE FRALDA. ULCERA POR PRESSÃOEM REGIAO SACRA EM ESTAGIO 2. ESCORIAÇÕES EM MEMBROS INFERIORES. REALIZADO HIGIENE ORAL E CORPORAL, TROCADO FIXAÇÕES PELA EQUIPE DE ENFERMAGEM. PUNCIONADO NOVO ACESSO VENOSO PERIFÉRICO EM BRAÇO ESQUERDO COM CATETER DE HASTE FLEXIVEL 14, CONTIDO MEMBRO SUPERIOR ESQUERDO. SEGUE MONITORADO COM OXIMETRO, MONITOR CARDIACO E CONTROLE DE PRESSAO ARTERIAL.",
  "entities": {
    "Paciente ou Grupo com Deficiência": [
      "paciente"
    ],
    "Achado": [
      "jejum",
      "seca",
      "traqueostomizado",
      "18",
      "monitorizado",
      "higienizado",
      "SEDADO",
      "BCRNF",
      "RHA",
      "DÉBITO PRESENTE",
      "DEBITO PRESENTE",
      "COR LARANJA"
    ],
    "Procedimento Terapêutico ou Preventivo": [
      "jejum",
      "traqueostomizado",
      "PCV",
      "SVD",
      "higienizado",
      "SEDADO",
      "PVC",
      "SNG",
      "SEDAÇÃO",
      "PUNCIONADO",
      "CONTIDO",
      "cx herniorrafia",
      "SNE fechada",
      "SNG aberta",
      "ventilação mecânica",
      "acesso venoso central",
      "precaução de contato",
      "INTUBAÇÃO OROTRAQUEAL",
      "VENTILAÇÃO MECANICA",
      "CANULA DE GUEDEL",
      "SNE FECHADA",
      "ACESSO VENOSO PERIFERICO",
      "SVD ABERTA",
      "HIGIENE ORAL E CORPORAL",
      "TROCADO FIXAÇÕES",
      "ACESSO VENOSO PERIFÉRICO"
    ],
    "Atividade de Assistência à Saúde": [
      "plantao"
    ],
    "Procedimento Diagnóstico": [
      "eletrocardigrama",
      "monitorizado",
      "RAIO-X",
      "AUSCULTA PULMONAR",
      "MONITOR CARDIACO",
      "CONTROLE DE PRESSAO ARTERIAL"
    ],
    "Abreviação": [
      "PCV",
      "Pi",
      "PEEP",
      "fio2",
      "D",
      "MMSS",
      "+++/4",
      "SVD",
      "PAM",
      "MIE",
      "MMII",
      "PVC",
      "MRPM",
      "FIO2",
      "SNG",
      "BCRNF",
      "RHA",
      "cx herniorrafia",
      "SNE fechada",
      "SNG aberta",
      "15 ml/h",
      "5 ml/h",
      "20 ml/h",
      "50 ml/h",
      "SNE FECHADA",
      "15 ML/H",
      "SVD ABERTA"
    ],
    "Conceito Quantitativo": [
      "18",
      "60%",
      "155",
      "MRPM",
      "7",
      "40%",
      "28",
      "grande quantidade",
      "média quantidade",
      "15 ml/h",
      "5 ml/h",
      "20 ml/h",
      "50 ml/h",
      "15 ML/H"
    ],
    "Conceito Espacial": [
      "D",
      "ESQUERDA"
    ],
    "Substância Química Orgânica": [
      "Dormonid",
      "Propofol",
      "Fentanil",
      "Noradrenalina"
    ],
    "Substância Farmacológica": [
      "Dormonid",
      "Propofol",
      "Fentanil",
      "Noradrenalina"
    ],
    "Hormônio": [
      "Noradrenalina"
    ],
    "Sinal ou Sintoma": [
      "taquicárdico",
      "hipotenso",
      "edemaciados",
      "rígido",
      "edema",
      "oligúria",
      "HEMATOMA",
      "queixa toracica",
      "Ramsay 6",
      "pupilas isocóricas bradifotorreagentes",
      "estase tipo borra de café",
      "instável hemodinamicamente",
      "mal perfundidas",
      "edemaciados ++/4"
    ],
    "Localização ou Região Corporal": [
      "MMSS",
      "abdome",
      "peniano",
      "sacra",
      "MIE",
      "extremidades",
      "MMII",
      "REGIÃO ZIGOMÁTICA",
      "AURICULAR ESQUERDA",
      "REGIAO SACRA",
      "MEMBROS INFERIORES",
      "MEMBRO SUPERIOR ESQUERDO"
    ],
    "Função Patológica": [
      "edemaciados",
      "edema",
      "HEMATOMA"
    ],
    "Parte do Corpo, Órgão ou Componente Orgânico": [
      "peniano",
      "MÃOS",
      "calota craniana",
      "bolsa escrotal",
      "BRAÇO DIREITO",
      "BRAÇO ESQUERDO"
    ],
    "Dispositivo Médico": [
      "SVD",
      "SNG",
      "FRALDA",
      "OXIMETRO",
      "SNE fechada",
      "SNG aberta",
      "acesso venoso central",
      "CANULA DE GUEDEL",
      "SNE FECHADA",
      "ACESSO VENOSO PERIFERICO",
      "CATETER DE HASTE FLEXIVEL 14",
      "SVD ABERTA",
      "ACESSO VENOSO PERIFÉRICO",
      "MONITOR CARDIACO"
    ],
    "Doença ou Síndrome": [
      "oligúria",
      "úlcera",
      "ULCERA POR PRESSÃOEM"
    ],
    "Bactéria": [
      "Klebsiella",
      "Acinetobacter"
    ],
    "Lesão ou Envenenamento": [
      "ESCORIAÇÕES"
    ],
    "Conceito Funcional": [
      "USO"
    ],
    "Objeto Manufaturado": [
      "FRALDA"
    ],
    "Organização Relacionada à Saúde": [
      "clinica médica"
    ],
    "Conceito Qualitativo": [
      "grau III"
    ],
    "Função Fisiológica": [
      "DÉBITO PRESENTE",
      "DEBITO PRESENTE"
    ],
    "Grupo Profissional ou Ocupacional": [
      "EQUIPE DE ENFERMAGEM"
    ]
  },
  "labels": {
    "oligúria": {
      "capitulo": "11"
    },
    "edemaciados ++/4": {
      "capitulo": "15"
    },
    "pupilas isocóricas bradifotorreagentes": {
      "capitulo": "21"
    },
    "ulcera por pressãoem": {
      "capitulo": "14"
    },
    "rígido": {
      "capitulo": "21"
    },
    "traqueostomizado": {
      "capitulo": "12"
    },
    "estase tipo borra de café": {
      "capitulo": "21"
    },
    "cor laranja": {
      "capitulo": "21"
    },
    "instável hemodinamicamente": {
      "capitulo": "11"
    },
    "acinetobacter": {
      "capitulo": "01"
    },
    "hematoma": {
      "capitulo": "15"
    },
    "klebsiella": {
      "capitulo": "01"
    },
    "débito presente": {
      "capitulo": "21"
    },
    "ramsay 6": {
      "capitulo": "21"
    },
    "mal perfundidas": {
      "capitulo": "21"
    },
    "edemaciados": {
      "capitulo": "15"
    },
    "queixa toracica": {
      "capitulo": "21"
    },
    "escoriações": {
      "capitulo": "22"
    },
    "bcrnf": {
      "capitulo": "21"
    },
    "monitorizado": {
      "capitulo": "21"
    },
    "úlcera": {
      "capitulo": "14"
    },
    "hipotenso": {
      "capitulo": "11"
    },
    "higienizado": {
      "capitulo": "21"
    },
    "edema": {
      "capitulo": "15"
    },
    "taquicárdico": {
      "capitulo": "11"
    },
    "seca": {
      "capitulo": "21"
    },
    "sedado": {
      "capitulo": "21"
    }
  }
}