{
  "prontuario_id": 281,
  "text": "Às 12:31: CLIENTE ACORDADA, PUPILAS ISOCORICAS FOTORREAGENTES, RESPONSIVA A ESTIMULOS DOLOROSOS, EUPNEICA, REPOUSO NO LEITO, DIETA VIA GASTROSTOMIA A 50 ML/H EM BI, ABDOMEN PLANO E FLÁCIDO, PERFUSÃO DISTAL PRESERVADA, MICÇÃO PRESENTE (FAZ USO DE FRALDA). ENFª FLORENCE NIGHTINGALE XXXX. DOR CRONICA INTRATAVEL. ÀS 9h: DESLIGADA SEDAÇÃO POR DRA ALICE. HEMORRAGIA SUBDURAL DEVIDA A TRAUMATISMO. ÀS 17:30: INICIA COM NPT 42 ML/H, EM ACESSO VENOSO CENTRAL. MANTENDO GASTROSTOMIA FECHADA E JEJUM POR VIA ORAL. SEPTICEMIA NAO ESPECIFICADA. 22º PO de colecistectomia, 1º dia de reinternação por febre associada a taquicardia. Às 11:00h: Consciente, comunicativo, pupilas isocóricas e fotorreagentes, jejum até segunda ordem, apresentando ictericia generalizada. AP livre, mv + bilateral, expansão torácica simétrica. Mantém acesso venoso periférico salinizado em fossa cubital esquerda. Abdomen plano, flácido e indolor a palpação, RHA +, incisão cirurgica de região abdominal em fase de cicatrização de aspecto limpo e seco. Apresenta boa perfusão periférica. Diurese presente e espontânea. Relatando flatulências, sem queixas algicas no momento.  Enfº Florence Nightingale, COREN XXXX. EXAME GERAL E INVESTIGACAO DE PESSOAS SEM QUEIXAS OU DIAGNOSTICO RELATADO.",
  "entities": {
    "Paciente ou Grupo com Deficiência": [
      "CLIENTE"
    ],
    "Achado": [
      "ACORDADA",
      "EUPNEICA",
      "PLANO",
      "FLÁCIDO",
      "Consciente",
      "comunicativo",
      "livre",
      "plano",
      "flácido",
      "seco",
      "PUPILAS ISOCORICAS FOTORREAGENTES",
      "RESPONSIVA A ESTIMULOS DOLOROSOS",
      "REPOUSO NO LEITO",
      "PERFUSÃO DISTAL PRESERVADA",
      "MICÇÃO PRESENTE",
      "pupilas isocóricas e fotorreagentes",
      "mv + bilateral",
      "expansão torácica simétrica",
      "RHA +",
      "aspecto limpo",
      "perfusão periférica",
      "Diurese presente e espontânea"
    ],
    "Dispositivo Médico": [
      "BI",
      "ACESSO VENOSO CENTRAL",
      "acesso venoso periférico"
    ],
    "Abreviação": [
      "BI",
      "ENFª",
      "NPT",
      "PO",
      "AP",
      "Enfº",
      "50 ML/H",
      "42 ML/H",
      "mv + bilateral",
      "RHA +"
    ],
    "Localização ou Região Corporal": [
      "ABDOMEN",
      "Abdomen",
      "fossa cubital esquerda",
      "região abdominal"
    ],
    "Objeto Manufaturado": [
      "FRALDA"
    ],
    "Procedimento Terapêutico ou Preventivo": [
      "SEDAÇÃO",
      "NPT",
      "colecistectomia",
      "jejum",
      "salinizado",
      "DIETA VIA GASTROSTOMIA",
      "ACESSO VENOSO CENTRAL",
      "GASTROSTOMIA FECHADA",
      "acesso venoso periférico",
      "incisão cirurgica"
    ],
    "Conceito Temporal": [
      "PO",
      "no momento"
    ],
    "Atividade de Assistência à Saúde": [
      "reinternação",
      "DIAGNOSTICO",
      "EXAME GERAL"
    ],
    "Procedimento Diagnóstico": [
      "AP",
      "palpação",
      "EXAME GERAL"
    ],
    "Conceito Qualitativo": [
      "salinizado",
      "boa"
    ],
    "Negação": [
      "indolor"
    ],
    "Função de Organismo": [
      "cicatrização"
    ],
    "Sinal ou Sintoma": [
      "flatulências",
      "ictericia generalizada",
      "queixas algicas"
    ],
    "Conceito Quantitativo": [
      "50 ML/H",
      "42 ML/H"
    ],
    "Função Fisiológica": [
      "MICÇÃO PRESENTE",
      "Diurese presente e espontânea"
    ],
    "Doença ou Síndrome": [
      "DOR CRONICA INTRATAVEL",
      "SEPTICEMIA NAO ESPECIFICADA"
    ],
    "Função Patológica": [
      "HEMORRAGIA SUBDURAL"
    ],
    "Parte do Corpo, Órgão ou Componente Orgânico": [
      "VIA ORAL"
    ]
  },
  "labels": {
    "perfusão periférica": {
      "capitulo": "11"
    },
    "perfusão distal preservada": {
      "capitulo": "11"
    },
    "flácido": {
      "capitulo": "15"
    },
    "queixas algicas": {
      "capitulo": "21"
    },
    "hemorragia subdural": {
      "capitulo": "08"
    },
    "ictericia generalizada": {
      "capitulo": "05"
    },
    "comunicativo": {
      "capitulo": "06"
    },
    "livre": {
      "capitulo": "21"
    },
    "septicemia nao especificada": {
      "capitulo": "01"
    },
    "responsiva a estimulos dolorosos": {
      "capitulo": "21"
    },
    "plano": {
      "capitulo": "15"
    },
    "flatulências": {
      "capitulo": "13"
    },
    "dor cronica intratavel": {
      "capitulo": "06"
    },
    "mv + bilateral": {
      "capitulo": "21"
    },
    "micção presente": {
      "capitulo": "16"
    },
    "pupilas isocoricas fotorreagentes": {
      "capitulo": "21"
    },
    "pupilas isocóricas e fotorreagentes": {
      "capitulo": "21"
    }
  }
}