{
  "prontuario_id": 771,
  "text": "ÀS 10:20 HS: ADMITIDO NO SETOR ÀS 09:45 HS, PROVENIENTE DO CC, POI DE RETIRADA DE MATERIAL DE SINTESE EM OMBRO D, CONSCIENTE, ORIENTADO, CTVO LIMPO E SECO, ACESSO VENOSO EM MSE COM SRT EM CURSO. LIBERADO DIETA LIVRE. SEGUE CUIDADOS. FRATURA DA OMOPLATA ESCAPULA. ÀS 18:10 HS: POI DE ARTROSCOPIA DE JOELHO E, SOB ANESTESIA RAQUIDIANA, RETORNOU DO CENTRO CIRÚRGICO ÁS 17:30HS, COMUNICATIVO, LÚCIDO, MIE ENFAIXADO COM COMPRESSA GELADA CONTÍNUA, ACESSO VENOSO PERIFÉRICO EM MSE COM SOROTERAPIA EM CURSO, SEM QUEIXAS ÁLGICAS, DIETA L. OUTROS TRANSTORNOS DO MENISCO. Às 11:20h: Alerta, orientado, verbalizando, deambulando. Sem queixas. Nega lombalgia. Enfª Florence Nightingale. INFECCAO PIOGENICA DO DISCO INTERVERTEBRAL. PROVENIENTE DO CC ÀS 15:20, CONSCIENTE, POUCO SONOLENTA, EUPNÉICA, SEM QUEIXAS ÁLGICAS, EM JEJUM. APRESENTA CURATIVO EM REGIÃO ABDOMINAL DE ASPECTO SECO EXTERNAMENTE. MANTÉM ACESSO VENOSO EM MSE COM SOROTERAPIA EM CURSO E SVD COM DÉBITO COLÚRICO. ENFª FLORENCE NIGHTINGALE. TRAUMATISMOS MULTIPLOS NAO ESPECIFICADOS. ÀS 02:00: POI de curativo em ombro E. Veio do Cc as 22:00, consciente, orientada, comunicativa. Acesso venoso em MSD, curativo limpo e seco em ombro E, com tipóia canadense. Boa aceitação da dieta oferecida. Eliminações presentes. Nega algia. FRATURA DA EXTREMIDADE SUPERIOR DO UMERO.",
  "entities": {
    "Organização Relacionada à Saúde": [
      "CC",
      "Cc",
      "CENTRO CIRÚRGICO"
    ],
    "Abreviação": [
      "CC",
      "POI",
      "CTVO",
      "MSE",
      "SRT",
      "MIE",
      "Enfª",
      "SVD",
      "ENFª",
      "Cc",
      "MSD",
      "OMBRO D",
      "JOELHO E",
      "DIETA L",
      "ombro E"
    ],
    "Conceito Temporal": [
      "POI",
      "CONTÍNUA"
    ],
    "Achado": [
      "CONSCIENTE",
      "ORIENTADO",
      "LIMPO",
      "SECO",
      "COMUNICATIVO",
      "LÚCIDO",
      "Alerta",
      "orientado",
      "verbalizando",
      "deambulando",
      "EUPNÉICA",
      "JEJUM",
      "consciente",
      "orientada",
      "comunicativa",
      "limpo",
      "seco",
      "aceitação da dieta",
      "Eliminações presentes"
    ],
    "Procedimento Terapêutico ou Preventivo": [
      "CTVO",
      "SRT",
      "JEJUM",
      "CURATIVO",
      "SVD",
      "curativo",
      "RETIRADA DE MATERIAL DE SINTESE",
      "ACESSO VENOSO",
      "DIETA LIVRE",
      "ANESTESIA RAQUIDIANA",
      "COMPRESSA GELADA",
      "ACESSO VENOSO PERIFÉRICO",
      "SOROTERAPIA EM CURSO",
      "DIETA L",
      "Acesso venoso",
      "tipóia canadense"
    ],
    "Dispositivo Médico": [
      "CTVO",
      "CURATIVO",
      "SVD",
      "curativo",
      "ACESSO VENOSO",
      "COMPRESSA GELADA",
      "ACESSO VENOSO PERIFÉRICO",
      "Acesso venoso",
      "tipóia canadense"
    ],
    "Localização ou Região Corporal": [
      "MSE",
      "MIE",
      "MSD",
      "REGIÃO ABDOMINAL"
    ],
    "Atividade de Assistência à Saúde": [
      "CUIDADOS"
    ],
    "Procedimento Diagnóstico": [
      "ARTROSCOPIA"
    ],
    "Negação": [
      "Nega"
    ],
    "Sinal ou Sintoma": [
      "lombalgia",
      "SONOLENTA",
      "algia",
      "QUEIXAS ÁLGICAS",
      "DÉBITO COLÚRICO"
    ],
    "Conceito Espacial": [
      "EXTERNAMENTE"
    ],
    "Parte do Corpo, Órgão ou Componente Orgânico": [
      "OMBRO D",
      "JOELHO E",
      "ombro E"
    ],
    "Lesão ou Envenenamento": [
      "FRATURA DA OMOPLATA ESCAPULA",
      "TRAUMATISMOS MULTIPLOS NAO ESPECIFICADOS",
      "FRATURA DA EXTREMIDADE SUPERIOR DO UMERO"
    ],
    "Doença ou Síndrome": [
      "TRANSTORNOS DO MENISCO",
      "INFECCAO PIOGENICA DO DISCO INTERVERTEBRAL"
    ],
    "Função Fisiológica": [
      "Eliminações presentes"
    ]
  },
  "labels": {
    "transtornos do menisco": {
      "capitulo": "15"
    },
    "infeccao piogenica do disco intervertebral": {
      "capitulo": "01"
    },
    "débito colúrico": {
      "capitulo": "X"
    },
    "lombalgia": {
      "capitulo": "15"
    },
    "algia": {
      "capitulo": "15"
    },
    "fratura da omoplata escapula": {
      "capitulo": "15"
    },
    "fratura da extremidade superior do umero": {
      "capitulo": "15"
    },
    "queixas álgicas": {
      "capitulo": "15"
    },
    "traumatismos multiplos nao especificados": {
      "capitulo": "22"
    }
  }
}