{
  "prontuario_id": 908,
  "text": "Às 08:15H: Glasgow 6. Afebril, porém apresentando sudorese. Traqueostomizado, uso contínuo de sistema fechado de aspiração, suporte de O2 sob névoa úmida. Acesso central em subclávia E com curativo de filme transparente infundindo plano de hidratação gravitacional. CPP com roncos e bolhosos difusos. Gastrostomia funcionante infundindo dieta. Abdomen pouco distendido, RHA diminuídos. FO com presença de curativo oclusivo limpo e seco externamente. MMSS contidos. SVD com diurese efetiva, não apresentou evacuação até o momento. Monitorizado contínuamente com parâmetros de Pa não invasiva, cardioscopia e oximetria de pulso. Segue sob cuidados intensivos e precaução de contato para MRSA. Às 08:30hs: Ramsay 5, pupilas isocóricas fotorreagentes, curativo cefálico tipo capacete limpo e seco, DVE fechada + PIC (1-2 mmHg), SOG aberta sem débito, intubada com TOT 8, rima 24, em VM modo VCV, Vc 420 ml, PEEP 5, FiO2 60%, secreção traqueobrônquica sanguinolenta em média quantidade, puncionado acesso venoso central D, com Dormonid 30 ml/h + Propofol 20 ml/h + Noradrenalina 3 ml/h, monitorizada, estável hemodinamicamente, MV + com roncos e bolhosos difusos, PAM em radial D, abdome plano, flácido, RHA +, SVD com diurese efetiva, evacuação ausente, extremidades quentes e bem perfundidas, higienizada, pele íntegra. ",
  "entities": {
    "Negação": [
      "Afebril",
      "sem"
    ],
    "Achado": [
      "Afebril",
      "Traqueostomizado",
      "limpo",
      "seco",
      "evacuação",
      "débito",
      "intubada",
      "monitorizada",
      "plano",
      "flácido",
      "higienizada",
      "Gastrostomia funcionante",
      "diurese efetiva",
      "pupilas isocóricas fotorreagentes",
      "estável hemodinamicamente",
      "MV +",
      "RHA +",
      "bem perfundidas",
      "pele íntegra"
    ],
    "Sinal ou Sintoma": [
      "Afebril",
      "sudorese",
      "distendido",
      "Glasgow 6",
      "roncos e bolhosos difusos",
      "RHA diminuídos",
      "Ramsay 5",
      "secreção traqueobrônquica sanguinolenta"
    ],
    "Procedimento Terapêutico ou Preventivo": [
      "Traqueostomizado",
      "dieta",
      "SVD",
      "VM",
      "sistema fechado de aspiração",
      "névoa úmida",
      "Acesso central",
      "curativo de filme transparente",
      "plano de hidratação gravitacional",
      "Gastrostomia funcionante",
      "curativo oclusivo",
      "MMSS contidos",
      "precaução de contato",
      "curativo cefálico tipo capacete",
      "DVE fechada",
      "SOG aberta",
      "acesso venoso central"
    ],
    "Conceito Funcional": [
      "uso"
    ],
    "Parte do Corpo, Órgão ou Componente Orgânico": [
      "subclávia",
      "rima",
      "radial"
    ],
    "Conceito Espacial": [
      "E",
      "externamente",
      "D"
    ],
    "Abreviação": [
      "E",
      "CPP",
      "FO",
      "SVD",
      "VM",
      "Vc",
      "PEEP",
      "FiO2",
      "PAM",
      "RHA diminuídos",
      "MMSS contidos",
      "DVE fechada",
      "1-2 mmHg",
      "SOG aberta",
      "modo VCV",
      "420 ml",
      "30 ml/h",
      "20 ml/h",
      "3 ml/h",
      "MV +",
      "RHA +"
    ],
    "Localização ou Região Corporal": [
      "CPP",
      "Abdomen",
      "abdome",
      "extremidades"
    ],
    "Alimento": [
      "dieta"
    ],
    "Dispositivo Médico": [
      "SVD",
      "Acesso central",
      "curativo de filme transparente",
      "curativo oclusivo",
      "oximetria de pulso",
      "curativo cefálico tipo capacete",
      "DVE fechada",
      "acesso venoso central"
    ],
    "Função Fisiológica": [
      "evacuação",
      "diurese efetiva"
    ],
    "Procedimento Diagnóstico": [
      "cardioscopia",
      "PAM",
      "Monitorizado contínuamente",
      "oximetria de pulso"
    ],
    "Bactéria": [
      "MRSA"
    ],
    "Conceito Quantitativo": [
      "8",
      "24",
      "5",
      "60%",
      "1-2 mmHg",
      "420 ml",
      "média quantidade",
      "30 ml/h",
      "20 ml/h",
      "3 ml/h"
    ],
    "Substância Química Orgânica": [
      "Dormonid",
      "Propofol"
    ],
    "Substância Farmacológica": [
      "Dormonid",
      "Propofol",
      "Noradrenalina"
    ],
    "Hormônio": [
      "Noradrenalina"
    ],
    "Atividade de Assistência à Saúde": [
      "cuidados intensivos"
    ],
    "Substância Corporal": [
      "secreção traqueobrônquica sanguinolenta"
    ],
    "Conceito Qualitativo": [
      "bem perfundidas"
    ]
  },
  "labels": {
    "pele íntegra": {
      "capitulo": "14"
    },
    "flácido": {
      "capitulo": "15"
    },
    "mrsa": {
      "capitulo": "24"
    },
    "monitorizada": {
      "capitulo": "21"
    },
    "distendido": {
      "capitulo": "13"
    },
    "gastrostomia funcionante": {
      "capitulo": "13"
    },
    "traqueostomizado": {
      "capitulo": "12"
    },
    "ramsay 5": {
      "capitulo": "06"
    },
    "débito": {
      "capitulo": "21"
    },
    "evacuação": {
      "capitulo": "21"
    },
    "seco": {
      "capitulo": "14"
    },
    "intubada": {
      "capitulo": "12"
    },
    "estável hemodinamicamente": {
      "capitulo": "21"
    },
    "sudorese": {
      "capitulo": "21"
    },
    "limpo": {
      "capitulo": "14"
    },
    "pupilas isocóricas fotorreagentes": {
      "capitulo": "06"
    },
    "mv +": {
      "capitulo": "21"
    },
    "higienizada": {
      "capitulo": "14"
    },
    "plano": {
      "capitulo": "15"
    },
    "roncos e bolhosos difusos": {
      "capitulo": "12"
    },
    "glasgow 6": {
      "capitulo": "06"
    },
    "secreção traqueobrônquica sanguinolenta": {
      "capitulo": "21"
    }
  }
}