{
  "prontuario_id": 274,
  "text": "Às 18:07h: Paciente orientado, comunicativo, em repouso no leito, afebril, em ar ambiente, AVP em MSE salinizado, com edema de face e hematomas, tala gessada em MSD, fazendo uso de tipóia, aceitando dieta oferecida, diurese presente. Orientado quanto ao jejum a partir das 24h. Aguardando procedimento cirurgico, provável amanhã. Em 26/10/11, 9:20h: Comatosa, pupilas isocóricas fotorreagentes, SNE com dieta Jevity Plus a 75 ml/h, traqueostomizada, 02 em névoa úmida a 1 L/min. Curativo em subclávia D, hematomas em MMSS, curativo em punho E, ausculta pulmonar MV difusos, BCANF, dreno de tórax E com débito seroso, abdômen globoso, flácido, AVP pé D com SF 0,9% a 10 ml/h. Realizado banho no leito, grades e cabeceira elevadas. ",
  "entities": {
    "Paciente ou Grupo com Deficiência": [
      "Paciente"
    ],
    "Achado": [
      "orientado",
      "comunicativo",
      "afebril",
      "traqueostomizada",
      "flácido",
      "repouso no leito",
      "diurese presente",
      "pupilas isocóricas fotorreagentes",
      "débito seroso"
    ],
    "Sinal ou Sintoma": [
      "afebril",
      "hematomas",
      "Comatosa",
      "BCANF",
      "globoso",
      "edema de face"
    ],
    "Negação": [
      "afebril"
    ],
    "Procedimento Terapêutico ou Preventivo": [
      "AVP",
      "tipóia",
      "jejum",
      "SNE",
      "traqueostomizada",
      "Curativo",
      "curativo",
      "repouso no leito",
      "tala gessada",
      "procedimento cirurgico",
      "02 em névoa úmida",
      "dreno de tórax",
      "SF 0 , 9%",
      "banho no leito",
      "grades e cabeceira elevadas"
    ],
    "Abreviação": [
      "AVP",
      "MSE",
      "MSD",
      "SNE",
      "MMSS",
      "E",
      "BCANF",
      "subclávia D",
      "MV difusos",
      "pé D",
      "SF 0 , 9%"
    ],
    "Dispositivo Médico": [
      "AVP",
      "tipóia",
      "SNE",
      "Curativo",
      "curativo",
      "tala gessada",
      "dreno de tórax"
    ],
    "Localização ou Região Corporal": [
      "MSE",
      "MSD",
      "MMSS",
      "abdômen"
    ],
    "Conceito Qualitativo": [
      "salinizado"
    ],
    "Conceito Funcional": [
      "uso"
    ],
    "Alimento": [
      "dieta"
    ],
    "Conceito Temporal": [
      "amanhã"
    ],
    "Função Patológica": [
      "hematomas"
    ],
    "Conceito Espacial": [
      "E"
    ],
    "Função Fisiológica": [
      "diurese presente"
    ],
    "Conceito Quantitativo": [
      "75 ml/h",
      "1 L/min",
      "10 ml/h"
    ],
    "Parte do Corpo, Órgão ou Componente Orgânico": [
      "subclávia D",
      "pé D"
    ],
    "Procedimento Diagnóstico": [
      "ausculta pulmonar"
    ],
    "Substância Farmacológica": [
      "SF 0 , 9%"
    ]
  },
  "labels": {
    "orientado": {
      "capitulo": "06"
    },
    "débito seroso": {
      "capitulo": "12"
    },
    "flácido": {
      "capitulo": "15"
    },
    "bcanf": {
      "capitulo": "21"
    },
    "edema de face": {
      "capitulo": "14"
    },
    "comunicativo": {
      "capitulo": "06"
    },
    "globoso": {
      "capitulo": "21"
    },
    "repouso no leito": {
      "capitulo": "21"
    },
    "traqueostomizada": {
      "capitulo": "12"
    },
    "pupilas isocóricas fotorreagentes": {
      "capitulo": "08"
    },
    "comatosa": {
      "capitulo": "08"
    },
    "hematomas": {
      "capitulo": "14"
    }
  }
}