{
  "prontuario_id": 525,
  "text": "Às 00:45HS: PACIENTE APRESENTANDO SECREÇÃO TRAQUEAL COM ESTRIAS DE SANGUE EM GRANDE QUANTIDADE NO INICIO DO PLANTÃO. APÓS ASPIRAÇÃO, INICIOU COM SANGRAMENTO ATIVO PELA TRAQUEOSTOMIA E COÁGULOS DE SANGUE. ENTRO EM CONTATO COM O PLANTÃO NA NEUROCX - VITAL BRASIL - PARA AVALIAÇÃO DO PACIENTE, PORÉM NÃO PODERIA AVALIAR NO MOMENTO E ORIENTOU SOLICITAR AVALIAÇÃO DA CX GERAL. CHAMO O PLANTÃO DA CX GERAL - VITAL BRASIL - PARA AVALIAÇÃO DO PACIENTE. ENF. FLORENCE NIGHTINGALE, COREN XXXX. OUTROS TRANSTORNOS RESPIRATORIOS POS-PROCEDIMENTOS. Às 10:50: acordada, hipocorada, eupneica em ar ambiente, curativo limpo e seco em MIE, nega algias, ansiosa pela alta, chorosa, solicita falar com médico, aviso Dr VITAL BRASIL. Enf. Florence Nightingale. FRATURA DA EXTREMIDADE DISTAL DO FEMUR.",
  "entities": {
    "Paciente ou Grupo com Deficiência": [
      "PACIENTE"
    ],
    "Atividade de Assistência à Saúde": [
      "PLANTÃO",
      "AVALIAR",
      "AVALIAÇÃO DO PACIENTE",
      "AVALIAÇÃO DA CX GERAL"
    ],
    "Conceito Temporal": [
      "APÓS",
      "NO MOMENTO"
    ],
    "Procedimento Terapêutico ou Preventivo": [
      "ASPIRAÇÃO",
      "TRAQUEOSTOMIA",
      "curativo"
    ],
    "Negação": [
      "NÃO",
      "nega"
    ],
    "Abreviação": [
      "ENF",
      "MIE",
      "Enf",
      "PLANTÃO NA NEUROCX",
      "AVALIAÇÃO DA CX GERAL",
      "PLANTÃO DA CX GERAL"
    ],
    "Grupo Profissional ou Ocupacional": [
      "ENF",
      "médico",
      "Enf"
    ],
    "Achado": [
      "acordada",
      "limpo",
      "seco",
      "chorosa",
      "ESTRIAS DE SANGUE",
      "eupneica em ar ambiente",
      "ansiosa pela alta"
    ],
    "Sinal ou Sintoma": [
      "hipocorada",
      "algias",
      "SANGRAMENTO ATIVO",
      "COÁGULOS DE SANGUE"
    ],
    "Dispositivo Médico": [
      "curativo"
    ],
    "Localização ou Região Corporal": [
      "MIE"
    ],
    "Conceito Qualitativo": [
      "GRANDE QUANTIDADE"
    ],
    "Organização Relacionada à Saúde": [
      "PLANTÃO NA NEUROCX",
      "PLANTÃO DA CX GERAL"
    ],
    "Doença ou Síndrome": [
      "TRANSTORNOS RESPIRATORIOS POS-PROCEDIMENTOS"
    ],
    "Lesão ou Envenenamento": [
      "FRATURA DA EXTREMIDADE DISTAL DO FEMUR"
    ]
  },
  "labels": {
    "fratura da extremidade distal do femur": {
      "capitulo": "15"
    },
    "chorosa": {
      "capitulo": "21"
    },
    "hipocorada": {
      "capitulo": "08"
    },
    "sangramento ativo": {
      "capitulo": "12"
    },
    "ansiosa pela alta": {
      "capitulo": "06"
    },
    "transtornos respiratorios pos-procedimentos": {
      "capitulo": "12"
    },
    "estrias de sangue": {
      "capitulo": "21"
    },
    "coágulos de sangue": {
      "capitulo": "03"
    }
  }
}