{
  "prontuario_id": 587,
  "text": "ÀS 16:30: PACIENTE PROVENIENTE DO PRONTO SOCORRO, VITIMA DE QUEDA DE NIVEL + FAF, MANTEM ESCOLTA POLICIAL, LUCIDO, ORIENTADO, COMUNICATIVO, TALA EM MSE COM BOA PERFUSÃO PERIFERICA, FORÇA MUSCULAR PRESERVADA, ACEITANDO BEM A DIETA, REFERE ALGIA MODERADA, SEGUE FRATURA DA DIAFISE DO UMERO. Às 01h50min: CONSCIENTE, COMUNICATIVO, EM REPOUSO NO LEITO, EUPNEICO, MANTEM COLAR CERVICAL, COM CURATIVO EM OMBRO DIREITO E ESQUERDO LIMPO E SECO EXTERNAMENTE, NEGA ALGIA, NEGA DIETA VIA ORAL, ELIMINACAO VESICAL PRESENTE, INTESTINAL AUSENTE NO PERIODO, REFER. FERIMENTO ENVOLVENDO A LARINGE E A TRAQUEIA. ÀS 14:20 HORAS: ACORDADA, LÚCIDA E CONTACTUANDO. DEAMBULANDO, HIDRATADA E HIPOCORADA. PACIENTE PERMANECE EM ISOLAMENTO PRECAUÇÃO DE CONTATO PARA GOTÍCULAS. SUSPEITA DE TB ??? AGUARDA RESULTADO DE EXAMES. REFERE PERÍODOS DE DISPNÉIA, FAZENDO USO DE 02 EM MÁSCARA. DOENCA CARDIACA HIPERTENSIVA COM INSUFICIENCIA CARDIACA CONGESTIVA. Em 25/07/2007, 12:25h: Sonolento, responsivo aos estímulos, mucosas descoradas e úmidas. Apresenta abdome plano, flácido, indolor à palpação, RHA + . Realizado passagem de SNE em narina direita, procedimento realizado sem intercorrência. Solicito RX de abdome si. INFARTO CEREBRAL DEVIDO A TROMBOSE DE ARTERIAS PRE-CEREBRAIS.",
  "entities": {
    "Paciente ou Grupo com Deficiência": [
      "PACIENTE",
      "VITIMA"
    ],
    "Abreviação": [
      "FAF",
      "MSE",
      "SNE",
      "SUSPEITA DE TB",
      "RHA +",
      "RX de abdome"
    ],
    "Lesão ou Envenenamento": [
      "FAF",
      "FERIMENTO",
      "QUEDA DE NIVEL",
      "FRATURA DA DIAFISE DO UMERO"
    ],
    "Achado": [
      "LUCIDO",
      "ORIENTADO",
      "COMUNICATIVO",
      "CONSCIENTE",
      "EUPNEICO",
      "LIMPO",
      "SECO",
      "ACORDADA",
      "LÚCIDA",
      "CONTACTUANDO",
      "DEAMBULANDO",
      "HIDRATADA",
      "Sonolento",
      "úmidas",
      "plano",
      "flácido",
      "BOA PERFUSÃO PERIFERICA",
      "FORÇA MUSCULAR PRESERVADA",
      "REPOUSO NO LEITO",
      "ELIMINACAO VESICAL PRESENTE",
      "responsivo aos estímulos",
      "indolor à palpação",
      "RHA +"
    ],
    "Dispositivo Médico": [
      "TALA",
      "CURATIVO",
      "SNE",
      "COLAR CERVICAL"
    ],
    "Procedimento Terapêutico ou Preventivo": [
      "TALA",
      "CURATIVO",
      "SNE",
      "procedimento",
      "REPOUSO NO LEITO",
      "COLAR CERVICAL",
      "DIETA VIA ORAL",
      "ISOLAMENTO PRECAUÇÃO DE CONTATO PARA GOTÍCULAS",
      "02 EM MÁSCARA"
    ],
    "Localização ou Região Corporal": [
      "MSE",
      "abdome"
    ],
    "Alimento": [
      "DIETA"
    ],
    "Conceito Espacial": [
      "DIREITO",
      "ESQUERDO",
      "EXTERNAMENTE",
      "direita"
    ],
    "Sinal ou Sintoma": [
      "ALGIA",
      "HIPOCORADA",
      "DISPNÉIA",
      "descoradas",
      "intercorrência",
      "ALGIA MODERADA"
    ],
    "Negação": [
      "NEGA",
      "AUSENTE"
    ],
    "Parte do Corpo, Órgão ou Componente Orgânico": [
      "LARINGE",
      "TRAQUEIA",
      "mucosas"
    ],
    "Procedimento Diagnóstico": [
      "EXAMES",
      "RX de abdome"
    ],
    "Conceito Funcional": [
      "USO"
    ],
    "Espaço ou Junção Corporal": [
      "narina"
    ],
    "Atividade de Assistência à Saúde": [
      "procedimento"
    ],
    "Organização Relacionada à Saúde": [
      "PRONTO SOCORRO"
    ],
    "Função Fisiológica": [
      "ELIMINACAO VESICAL PRESENTE"
    ],
    "Conceito Temporal": [
      "NO PERIODO"
    ],
    "Doença ou Síndrome": [
      "SUSPEITA DE TB",
      "DOENCA CARDIACA HIPERTENSIVA",
      "INSUFICIENCIA CARDIACA CONGESTIVA",
      "INFARTO CEREBRAL",
      "TROMBOSE DE ARTERIAS PRE-CEREBRAIS"
    ]
  },
  "labels": {
    "flácido": {
      "capitulo": "15"
    },
    "hipocorada": {
      "capitulo": "11"
    },
    "trombose de arterias pre-cerebrais": {
      "capitulo": "08"
    },
    "queda de nivel": {
      "capitulo": "22"
    },
    "doenca cardiaca hipertensiva": {
      "capitulo": "11"
    },
    "seco": {
      "capitulo": "14"
    },
    "deambulando": {
      "capitulo": "15"
    },
    "úmidas": {
      "capitulo": "14"
    },
    "limpo": {
      "capitulo": "14"
    },
    "insuficiencia cardiaca congestiva": {
      "capitulo": "11"
    },
    "faf": {
      "capitulo": "22"
    },
    "algia moderada": {
      "capitulo": "21"
    },
    "plano": {
      "capitulo": "15"
    },
    "repouso no leito": {
      "capitulo": "22"
    },
    "sonolento": {
      "capitulo": "21"
    },
    "algia": {
      "capitulo": "21"
    },
    "ferimento": {
      "capitulo": "08"
    },
    "descoradas": {
      "capitulo": "14"
    },
    "suspeita de tb": {
      "capitulo": "01"
    },
    "intercorrência": {
      "capitulo": "22"
    },
    "dispnéia": {
      "capitulo": "12"
    },
    "infarto cerebral": {
      "capitulo": "08"
    },
    "fratura da diafise do umero": {
      "capitulo": "15"
    }
  }
}