{
  "prontuario_id": 446,
  "text": "ÀS 12:15 HS: PROVENIENTE DA UTI 3 DE CADEIRA DE RODAS, COMUNICATIVA, ORIENTADA, AFEBRIL, NORMOTENSA, NORMOCORADA, EUPNEICA. BOA ACEITAÇÃO DA DIETA VO, BOA INGESTA HIDRICA. DEAMBULA COM AUXILIO, COM ACOMPANHANTE. MEDICAÇÃO DE USO CONTINUO COM FAMILIAR. SEGUE CUIDADOS DE ENFERMAGEM. ENF FLORENCE NIGHTINGALE, COREN XXXX. NEOPLASIA DE COMPORTAMENTO INCERTO OU DESCONHECIDO DO ENCEFALO E DO SISTEMA NERVOSO CENTRAL. Às 8:40h: pcte vitima de acidente de moto, fratura exposta de MID, lucido, comunicativo, deambula com auxilio, acesso venoso periferico em MSD salinizado, fixador externo em MID com ctvo limpo e seco externamente, membro edemaciado, refere eliminaçoes presentes. Enf Florence Nightingale (coren XXXX). LESAO POR ESMAGAMENTO DO TORNOZELO. Às 01:26: Lucido, comunicativo, orientado, deambulando, mobiliza 4 membros, referindo tontura, mal-estar gastrico, cefaleia, PA 110/80, presenta rubor + edema em face, aceita dieta oferecida, sem apresentar nauseas e ou emese, diurese presente, segue cuidados. TRAUMATISMO INTRACRANIANO. Às 08:00hs: Autorizada traqueostomia pela filha (Maria), termo de consentimento assinado e arquivado no prontuário. Enfª Florence Nightingale, XXXX. OUTROS TRANSTORNOS RESPIRATORIOS POS-PROCEDIMENTOS.",
  "entities": {
    "Abreviação": [
      "UTI",
      "ENF",
      "pcte",
      "MID",
      "MSD",
      "ctvo",
      "Enf",
      "PA",
      "Enfª",
      "BOA ACEITAÇÃO DA DIETA VO"
    ],
    "Organização Relacionada à Saúde": [
      "UTI"
    ],
    "Achado": [
      "COMUNICATIVA",
      "ORIENTADA",
      "AFEBRIL",
      "NORMOTENSA",
      "NORMOCORADA",
      "EUPNEICA",
      "lucido",
      "comunicativo",
      "limpo",
      "seco",
      "Lucido",
      "orientado",
      "deambulando",
      "BOA ACEITAÇÃO DA DIETA VO",
      "BOA INGESTA HIDRICA",
      "DEAMBULA COM AUXILIO",
      "deambula com auxilio",
      "eliminaçoes presentes",
      "mobiliza 4 membros",
      "aceita dieta",
      "diurese presente"
    ],
    "Negação": [
      "AFEBRIL",
      "sem"
    ],
    "Grupo Populacional": [
      "ACOMPANHANTE"
    ],
    "Grupo Familiar": [
      "FAMILIAR",
      "filha"
    ],
    "Paciente ou Grupo com Deficiência": [
      "pcte",
      "vitima"
    ],
    "Localização ou Região Corporal": [
      "MID",
      "MSD",
      "face"
    ],
    "Conceito Qualitativo": [
      "salinizado"
    ],
    "Procedimento Terapêutico ou Preventivo": [
      "ctvo",
      "traqueostomia",
      "acesso venoso periferico"
    ],
    "Dispositivo Médico": [
      "ctvo",
      "CADEIRA DE RODAS",
      "acesso venoso periferico",
      "fixador externo"
    ],
    "Conceito Espacial": [
      "externamente"
    ],
    "Sinal ou Sintoma": [
      "tontura",
      "cefaleia",
      "rubor",
      "edema",
      "nauseas",
      "emese",
      "membro edemaciado",
      "mal-estar gastrico"
    ],
    "Atributo Clínico": [
      "PA"
    ],
    "Conceito Quantitativo": [
      "110/80"
    ],
    "Atividade de Assistência à Saúde": [
      "cuidados",
      "CUIDADOS DE ENFERMAGEM"
    ],
    "Substância Farmacológica": [
      "MEDICAÇÃO DE USO CONTINUO"
    ],
    "Parte do Corpo, Órgão ou Componente Orgânico": [
      "ENCEFALO E DO SISTEMA NERVOSO CENTRAL"
    ],
    "Lesão ou Envenenamento": [
      "acidente de moto",
      "fratura exposta",
      "LESAO POR ESMAGAMENTO DO TORNOZELO",
      "TRAUMATISMO INTRACRANIANO"
    ],
    "Função Fisiológica": [
      "eliminaçoes presentes",
      "diurese presente"
    ],
    "Doença ou Síndrome": [
      "TRANSTORNOS RESPIRATORIOS POS-PROCEDIMENTOS"
    ]
  },
  "labels": {
    "acidente de moto": {
      "capitulo": "22"
    },
    "transtornos respiratorios pos-procedimentos": {
      "capitulo": "12"
    },
    "mal-estar gastrico": {
      "capitulo": "13"
    },
    "normotensa": {
      "capitulo": "11"
    },
    "rubor": {
      "capitulo": "21"
    },
    "traumatismo intracraniano": {
      "capitulo": "08"
    },
    "emese": {
      "capitulo": "21"
    },
    "nauseas": {
      "capitulo": "21"
    },
    "lesao por esmagamento do tornozelo": {
      "capitulo": "15"
    },
    "eliminaçoes presentes": {
      "capitulo": "21"
    },
    "membro edemaciado": {
      "capitulo": "15"
    },
    "fratura exposta": {
      "capitulo": "15"
    },
    "edema": {
      "capitulo": "21"
    },
    "normocorada": {
      "capitulo": "11"
    },
    "cefaleia": {
      "capitulo": "21"
    },
    "tontura": {
      "capitulo": "21"
    }
  }
}