{
  "prontuario_id": 734,
  "text": "Às 23:12 hs: Traqueostomizado, em VM modo CMV, VC 510, Peep 3, Fr 18, FiO2 35%, saturando 99%. Pupilas isocóricas, fotorreagentes, acordado, comunicativo, períodos de agitação. Ausculta pulmonar com MV diminuídos, com presença de roncos, secreção traqueobrônq. INSUFICIENCIA CARDIACA. 15:28: PACIENTE: CORADO, ALERTA, RESPONSIVO, APRESENTA-SE EM REPOUSO NO LEITO, DIETA VIA SNE EM BOMBA INFUSORA, AVP EM MSE SALINIZADO, NÃO REFERIU ALGIA, ELIMINAÇÕES FISIOLOGICAS PRESENTES E ESPONTANÊOS, SEGUE SOB CUIDADOS DE ENFERMAGEM. EPILEPSIA E SINDROMES EPILEPTICAS IDIOPATICAS DEFINIDAS POR SUA LOCALIZACAO FOCAL PARCIAL COM CRISES DE INICIO FOCAL. RECEBEU PAPA DE HEMÁCIAS 1 UNIDADE. ABDOME AGUDO. ÀS 16:00: PACIENTE EM REPOUSO NO LEITO, VERBALIZANDO E BEM COMUNICATIVA, QUEIXANDO-SE DE MUITA DOR NO ABDOME. DEIXO COMO OBS PARA SER SEGUIDO SOMENTE A PRESCRIÇÃO DE DR VITAL BRASIL, A PEDIDO MÉDICO. SEGUE OBS DE ENFERMAGEM. DOR ABDOMINAL E PELVICA.",
  "entities": {
    "Achado": [
      "Traqueostomizado",
      "fotorreagentes",
      "acordado",
      "comunicativo",
      "CORADO",
      "ALERTA",
      "RESPONSIVO",
      "VERBALIZANDO",
      "Pupilas isocóricas",
      "secreção traqueobrônq",
      "REPOUSO NO LEITO",
      "BEM COMUNICATIVA"
    ],
    "Procedimento Terapêutico ou Preventivo": [
      "Traqueostomizado",
      "VM",
      "CMV",
      "SNE",
      "AVP",
      "SALINIZADO",
      "REPOUSO NO LEITO"
    ],
    "Abreviação": [
      "VM",
      "CMV",
      "VC",
      "Peep",
      "Fr",
      "FiO2",
      "SNE",
      "AVP",
      "MSE",
      "MV diminuídos",
      "secreção traqueobrônq"
    ],
    "Atributo Clínico": [
      "VC",
      "Peep",
      "Fr",
      "FiO2",
      "saturando"
    ],
    "Conceito Quantitativo": [
      "510",
      "3",
      "18",
      "35%",
      "99%",
      "1 UNIDADE"
    ],
    "Sinal ou Sintoma": [
      "agitação",
      "roncos",
      "ALGIA",
      "DOR",
      "MV diminuídos",
      "MUITA DOR"
    ],
    "Paciente ou Grupo com Deficiência": [
      "PACIENTE"
    ],
    "Alimento": [
      "DIETA"
    ],
    "Dispositivo Médico": [
      "SNE",
      "AVP",
      "BOMBA INFUSORA"
    ],
    "Localização ou Região Corporal": [
      "MSE",
      "ABDOME",
      "ABDOMINAL",
      "PELVICA"
    ],
    "Parte do Corpo, Órgão ou Componente Orgânico": [
      "MSE"
    ],
    "Atividade de Assistência à Saúde": [
      "RECEBEU",
      "PRESCRIÇÃO",
      "CUIDADOS DE ENFERMAGEM"
    ],
    "Substância Farmacológica": [
      "HEMÁCIAS"
    ],
    "Produto Intelectual": [
      "PRESCRIÇÃO"
    ],
    "Grupo Profissional ou Ocupacional": [
      "ENFERMAGEM"
    ],
    "Procedimento Diagnóstico": [
      "Ausculta pulmonar"
    ],
    "Substância Corporal": [
      "secreção traqueobrônq"
    ],
    "Doença ou Síndrome": [
      "INSUFICIENCIA CARDIACA",
      "EPILEPSIA E SINDROMES EPILEPTICAS IDIOPATICAS",
      "ABDOME AGUDO"
    ]
  },
  "labels": {
    "acordado": {
      "capitulo": "06"
    },
    "secreção traqueobrônq": {
      "capitulo": "12"
    },
    "traqueostomizado": {
      "capitulo": "12"
    },
    "mv diminuídos": {
      "capitulo": "21"
    },
    "epilepsia e sindromes epilepticas idiopaticas": {
      "capitulo": "06"
    },
    "muita dor": {
      "capitulo": "13"
    },
    "comunicativo": {
      "capitulo": "06"
    },
    "verbalizando": {
      "capitulo": "06"
    },
    "agitação": {
      "capitulo": "21"
    },
    "insuficiencia cardiaca": {
      "capitulo": "11"
    },
    "abdome agudo": {
      "capitulo": "13"
    },
    "roncos": {
      "capitulo": "12"
    },
    "dor": {
      "capitulo": "21"
    }
  }
}