{
  "prontuario_id": 72,
  "text": "Às 6h: Paciente com queixa de dor de moderada intensidade, apresentou discreto sangramento. Segue sob cuidados da enfermagem. HIPERTROFIA DA MAMA. Às 7:30: 2º DI COM HX DE DERRAME PLEURAL A D. EM REPOUSO NO LEITO, MONITORIZADO FC 80, SAT O2 100%, PA 249/123, GEMENTE, HIPOCORADO, PUPILAS ISOCORICAS FOTORREAGENTES, MANTEM SNG ABERTA COM 10 ml DEBITO BILIOSO, MANTEM O2 EM NEVOA UMIDA 10 L/M, MUCOSAS SECAS, E DE PNEUMOCISTOSE. Em 13/10/2006, 15:40 HORAS: PERMANECE EM COMA, COM PUPILAS MÉDIO-FIXAS, MANTENDO CATETER DE DVE. VM VIA TOT COM FiO2 50%, PCV, PP 25 cmH20, PEEP 2 cmH20,F 15 mrpm, SPO2 99%. AUSCULTA PULMONAR COM MV LIVRES. HEMODINAMICAMENTE ESTÁVEL. CVP EM MSD COM PLANO BÁSICO D. OUTRAS HEMORRAGIAS INTRACEREBRAIS. Às 05:23: Paciente retornou do CC por volta das 04:00 horas, POI de drenagem de abscesso em mao esquerda. Lucido, comunicativo, apresenta curativo em MSE limpo e seco externamente, referindo algia moderada no local, segue cuidados. ABSCESSO CUTANEO FURUNCULO E ANTRAZ DOS MEMBROS. PCTE PROVENIENTE DO CC, POI DE FRATURA DE MMSS, VÍTIMA DE MÚLTIPLAS FOIÇADAS, SEDADO EM TOT, VM PCV PI = 22 + PEEP = 3 + FIO2 = 60%, SATURAÇÃO = 98%, PUPILAS ISOCÓRICAS FOTORREAGENTES, AUSCULTA PULMONAR MV +, NÃO REAGINDO A ESTÍMULOS VERBAIS, CTVO CIRÚRGICO EM MMSS C/ FRATURA DA EXTREMIDADE SUPERIOR DO CUBITO ULNA.",
  "entities": {
    "Paciente ou Grupo com Deficiência": [
      "Paciente",
      "PCTE",
      "VÍTIMA"
    ],
    "Sinal ou Sintoma": [
      "dor",
      "GEMENTE",
      "HIPOCORADO",
      "COMA",
      "DEBITO BILIOSO",
      "PUPILAS MÉDIO-FIXAS",
      "algia moderada"
    ],
    "Abreviação": [
      "HX",
      "D",
      "FC",
      "SAT",
      "O2",
      "PA",
      "DVE",
      "VM",
      "TOT",
      "FiO2",
      "PCV",
      "PP",
      "PEEP",
      "F",
      "SPO2",
      "CVP",
      "MSD",
      "CC",
      "POI",
      "MSE",
      "PCTE",
      "MMSS",
      "PI",
      "FIO2",
      "SNG ABERTA",
      "MV +",
      "CTVO CIRÚRGICO",
      "EM MMSS"
    ],
    "Conceito Espacial": [
      "D",
      "externamente"
    ],
    "Procedimento Diagnóstico": [
      "MONITORIZADO",
      "AUSCULTA PULMONAR"
    ],
    "Atributo Clínico": [
      "FC",
      "SAT",
      "PA",
      "FiO2",
      "PEEP",
      "F",
      "SPO2",
      "PI",
      "FIO2",
      "SATURAÇÃO"
    ],
    "Conceito Quantitativo": [
      "80",
      "100%",
      "249/123",
      "50%",
      "99%",
      "22",
      "3",
      "60%",
      "98%",
      "10 ml",
      "10 L/M",
      "25 cmH20",
      "2 cmH20",
      "15 mrpm"
    ],
    "Substância Farmacológica": [
      "O2"
    ],
    "Procedimento Terapêutico ou Preventivo": [
      "O2",
      "DVE",
      "VM",
      "TOT",
      "PCV",
      "CVP",
      "drenagem",
      "curativo",
      "SEDADO",
      "SNG ABERTA",
      "NEVOA UMIDA",
      "PLANO BÁSICO",
      "CTVO CIRÚRGICO"
    ],
    "Doença ou Síndrome": [
      "PNEUMOCISTOSE",
      "HIPERTROFIA DA MAMA",
      "DERRAME PLEURAL",
      "HEMORRAGIAS INTRACEREBRAIS",
      "ABSCESSO CUTANEO FURUNCULO E ANTRAZ DOS MEMBROS"
    ],
    "Dispositivo Médico": [
      "CATETER",
      "TOT",
      "curativo",
      "SNG ABERTA",
      "CTVO CIRÚRGICO"
    ],
    "Parte do Corpo, Órgão ou Componente Orgânico": [
      "MSD",
      "MSE",
      "mao esquerda"
    ],
    "Organização Relacionada à Saúde": [
      "CC"
    ],
    "Conceito Temporal": [
      "POI"
    ],
    "Achado": [
      "Lucido",
      "comunicativo",
      "limpo",
      "seco",
      "SEDADO",
      "REPOUSO NO LEITO",
      "PUPILAS ISOCORICAS FOTORREAGENTES",
      "SNG ABERTA",
      "MV LIVRES",
      "HEMODINAMICAMENTE ESTÁVEL",
      "PUPILAS ISOCÓRICAS FOTORREAGENTES",
      "MV +"
    ],
    "Atividade de Assistência à Saúde": [
      "cuidados",
      "cuidados da enfermagem"
    ],
    "Lesão ou Envenenamento": [
      "FRATURA",
      "MÚLTIPLAS FOIÇADAS",
      "FRATURA DA EXTREMIDADE SUPERIOR DO CUBITO ULNA"
    ],
    "Localização ou Região Corporal": [
      "MMSS"
    ],
    "Conceito Qualitativo": [
      "moderada intensidade"
    ],
    "Substância Corporal": [
      "DEBITO BILIOSO"
    ]
  },
  "labels": {
    "hemodinamicamente estável": {
      "capitulo": "11"
    },
    "hipertrofia da mama": {
      "capitulo": "14"
    },
    "pupilas médio-fixas": {
      "capitulo": "21"
    },
    "derrame pleural": {
      "capitulo": "12"
    },
    "pneumocistose": {
      "capitulo": "12"
    },
    "fratura": {
      "capitulo": "15"
    },
    "pupilas isocóricas fotorreagentes": {
      "capitulo": "21"
    },
    "algia moderada": {
      "capitulo": "21"
    },
    "múltiplas foiçadas": {
      "capitulo": "15"
    },
    "mv +": {
      "capitulo": "21"
    },
    "debito bilioso": {
      "capitulo": "12"
    },
    "coma": {
      "capitulo": "21"
    },
    "hipocorado": {
      "capitulo": "21"
    },
    "fratura da extremidade superior do cubito ulna": {
      "capitulo": "15"
    },
    "mv livres": {
      "capitulo": "21"
    },
    "gemente": {
      "capitulo": "21"
    },
    "hemorragias intracerebrais": {
      "capitulo": "08"
    },
    "abscesso cutaneo furunculo e antraz dos membros": {
      "capitulo": "14"
    },
    "dor": {
      "capitulo": "21"
    },
    "pupilas isocoricas fotorreagentes": {
      "capitulo": "21"
    },
    "sng aberta": {
      "capitulo": "12"
    }
  }
}