{
  "prontuario_id": 493,
  "text": "Às 12HS: ENTRO EM CONTATO COM OTORRINOLARINGOLOGIA PARA AVISA-LA DO PEDIDO DE CONSULTA A PEDIDO DO DR NEURO. Às 14;25h: Segue mantendo repouso relativo ao leito sem queixas, lúcido, orientado, colaborativo. Mantem AVP MSD, aguarda infusão da Terceira bolsa de CH não administrada ontem por falta de prescrição, curativo sacral limpo e seco no momento, mas exalando odor fétido; refere boa aceitação da dieta VO, diurese presente por uropen débito claro. Segue aos cuidados de Enfermagem. ESQUEMA DE SUPERVISÃO NOTURNA:  04:00h APRESENTANDO PUPILAS MEDIO-FIXAS, EVOLUINDO PARA MIDRIATICA, COMUNICADO PLANTONISTA. Às 06:20h: APRESENTANDO SANGRAMENTO ABDOMINAL INTENSO, PLANTONISTA VEIO AVALIAR, SEM ALTERAÇÕES NA CONDUTA ATÉ O MOMENTO, AGUARDANDO RESULTADO DE EXAMES. MANTENDO DOPAMINA EM 56 ML/H, NORADRENALINA EM 80 ML/H. OBS: PROGNÓSTICO RESERVADO. Consciente, comunicativa, glasgow 15, monitorizado com multiparâmetros, PA, ECG e Oximetria não invasivos; tendendo a hipotensão; mantem cateter nasoenteral para diétoterapia; traqueostomizada, mantida sob VM modo espontãneo, PS 18, PEEP 5, FIO2 40%, SPO2 96%, uso de filtro de barreiras e sistema de aspiração aberto, secreção trauqueobrônquica amarelada com estrias de sangue em média quantidade; CPP com MV diminuidos e roncos esparsos; cateter venoso em dorso da mão \"D\" com plano básico de hidratação; curativo oclusivo em HTE; enfisema subcutâneo difuso diminuido; cateter vesical de demora com diurése efetiva de cor clara sem grumos; hiperemia intensa em sacra; extremidades aquecidas e perfundidas, MM discretamente edemaciados sem cacifo.",
  "entities": {
    "Organização Relacionada à Saúde": [
      "OTORRINOLARINGOLOGIA"
    ],
    "Sinal ou Sintoma": [
      "queixas",
      "MIDRIATICA",
      "hipotensão",
      "grumos",
      "cacifo",
      "exalando odor fétido",
      "estrias de sangue",
      "MV diminuidos",
      "roncos esparsos",
      "enfisema subcutâneo difuso diminuido",
      "hiperemia intensa"
    ],
    "Achado": [
      "lúcido",
      "orientado",
      "colaborativo",
      "limpo",
      "seco",
      "Consciente",
      "comunicativa",
      "traqueostomizada",
      "amarelada",
      "aquecidas",
      "perfundidas",
      "repouso relativo ao leito",
      "boa aceitação da dieta VO",
      "diurese presente",
      "débito claro",
      "glasgow 15",
      "diurése efetiva",
      "cor clara"
    ],
    "Dispositivo Médico": [
      "AVP",
      "curativo",
      "uropen",
      "cateter nasoenteral",
      "filtro de barreiras",
      "cateter venoso",
      "curativo oclusivo",
      "cateter vesical de demora"
    ],
    "Procedimento Terapêutico ou Preventivo": [
      "AVP",
      "infusão",
      "CH",
      "curativo",
      "diétoterapia",
      "traqueostomizada",
      "VM",
      "PS",
      "PEEP",
      "FIO2",
      "SPO2",
      "cateter nasoenteral",
      "modo espontãneo",
      "filtro de barreiras",
      "sistema de aspiração aberto",
      "cateter venoso",
      "plano básico de hidratação",
      "curativo oclusivo",
      "cateter vesical de demora"
    ],
    "Abreviação": [
      "AVP",
      "MSD",
      "CH",
      "PA",
      "ECG",
      "VM",
      "PS",
      "PEEP",
      "FIO2",
      "SPO2",
      "CPP",
      "HTE",
      "MM",
      "boa aceitação da dieta VO"
    ],
    "Parte do Corpo, Órgão ou Componente Orgânico": [
      "MSD"
    ],
    "Produto Intelectual": [
      "prescrição"
    ],
    "Localização ou Região Corporal": [
      "sacral",
      "sacra",
      "extremidades",
      "dorso da mão \"D\""
    ],
    "Grupo Profissional ou Ocupacional": [
      "PLANTONISTA"
    ],
    "Substância Química Orgânica": [
      "DOPAMINA"
    ],
    "Substância Farmacológica": [
      "DOPAMINA",
      "NORADRENALINA"
    ],
    "Hormônio": [
      "NORADRENALINA"
    ],
    "Atributo Clínico": [
      "PA"
    ],
    "Procedimento Diagnóstico": [
      "ECG",
      "Oximetria",
      "monitorizado com multiparâmetros"
    ],
    "Conceito Quantitativo": [
      "18",
      "5",
      "40%",
      "96%",
      "56 ML/H",
      "80 ML/H"
    ],
    "Negação": [
      "sem"
    ],
    "Função Fisiológica": [
      "diurese presente"
    ],
    "Atividade de Assistência à Saúde": [
      "cuidados de Enfermagem",
      "ALTERAÇÕES NA CONDUTA"
    ],
    "Substância Corporal": [
      "secreção trauqueobrônquica"
    ],
    "Conceito Qualitativo": [
      "média quantidade"
    ]
  },
  "labels": {
    "cacifo": {
      "capitulo": "15"
    },
    "aquecidas": {
      "capitulo": "15"
    },
    "repouso relativo ao leito": {
      "capitulo": "21"
    },
    "enfisema subcutâneo difuso diminuido": {
      "capitulo": "14"
    },
    "queixas": {
      "capitulo": "21"
    },
    "perfundidas": {
      "capitulo": "15"
    },
    "grumos": {
      "capitulo": "16"
    },
    "seco": {
      "capitulo": "14"
    },
    "exalando odor fétido": {
      "capitulo": "14"
    },
    "limpo": {
      "capitulo": "14"
    },
    "traqueostomizada": {
      "capitulo": "10"
    },
    "roncos esparsos": {
      "capitulo": "21"
    },
    "amarelada": {
      "capitulo": "21"
    },
    "mv diminuidos": {
      "capitulo": "08"
    },
    "estrias de sangue": {
      "capitulo": "10"
    },
    "midriatica": {
      "capitulo": "21"
    },
    "hipotensão": {
      "capitulo": "11"
    },
    "hiperemia intensa": {
      "capitulo": "15"
    }
  }
}