{
  "prontuario_id": 707,
  "text": "Às 00:51: Lucida, comunicativa, orientada, em repouso na poltrona, apresenta curativo limpo e seco externamente + fixador externo em  MIE, edema em MIE cacifo +++/+4, referindo algia moderada no local, aceita dieta oferecida, eliminaçoes fisiologicas presentes, segue cuidados. Recebido plantao com paciente sem prescriçao medica, entrado em contato com plantao da ortopedia as 20:30 horas, entrado novamente em contato as 23:00 horas, aguardamos... FRATURA DA DIAFISE DA TIBIA. ÀS 13 H: APRESENTOU HIPOTENSÃO, COMUNICADO DR VITAL BRASIL, MEDICADO CONFORME ORIENTAÇÃO. EDEMA CEREBRAL. Às 13:10hs: Paciente intubado em VM modo contolado com peep 5 Fio2 30, pupilas isocoricas fotorreagentes, SNE fechada sem debito biliar, ausculta pulmonar com roncos difusos, torax simetrico, abdomen globoso, flácido a palpação. SVD com diurese presente, concentrada, com grumos, AVP em jugular D com plano basico de hidratação, AVC com NPT 63 ml/h e noradrenalina 5, monitorização multiparametros com ECG, PAM 113/98, FR 15, FC 107 e Spo2 93%. Enfermeira Florence Nightingale, XXXX. EXAME GERAL E INVESTIGACAO DE PESSOAS SEM QUEIXAS OU DIAGNOSTICO RELATADO. Às 16:43: 2° di com hx de atropelamento + tce. No momento, consciente, orientada, com periodos de sonolencia, eupneica, respirando em ar ambiente, comunicativa, em repouso no leito, acompanhada de familiar, acesso venoso em msd salinizado, apresenta escoriações em face, refere cefaléia e algia em ombro esquerdo, não está aceitando a dieta, apresenta náuseas e vômito, diurese presente, evacuação ausente, sem queixas álgicas, segue sob cuidados. enf Florence Nightingale. TRAUMATISMO INTRACRANIANO.",
  "entities": {
    "Achado": [
      "Lucida",
      "comunicativa",
      "orientada",
      "limpo",
      "seco",
      "intubado",
      "concentrada",
      "consciente",
      "eupneica",
      "aceita dieta oferecida",
      "eliminaçoes fisiologicas presentes",
      "pupilas isocoricas fotorreagentes",
      "debito biliar",
      "torax simetrico",
      "flácido a palpação",
      "diurese presente",
      "respirando em ar ambiente",
      "repouso no leito",
      "aceitando a dieta"
    ],
    "Procedimento Terapêutico ou Preventivo": [
      "curativo",
      "MEDICADO",
      "peep",
      "Fio2",
      "SVD",
      "AVP",
      "AVC",
      "NPT",
      "salinizado",
      "repouso na poltrona",
      "fixador externo",
      "modo contolado",
      "SNE fechada",
      "plano basico de hidratação",
      "repouso no leito",
      "acesso venoso"
    ],
    "Dispositivo Médico": [
      "curativo",
      "SVD",
      "AVP",
      "AVC",
      "fixador externo",
      "acesso venoso"
    ],
    "Conceito Espacial": [
      "externamente"
    ],
    "Localização ou Região Corporal": [
      "MIE",
      "abdomen",
      "msd",
      "face"
    ],
    "Abreviação": [
      "MIE",
      "peep",
      "Fio2",
      "SVD",
      "AVP",
      "AVC",
      "NPT",
      "ECG",
      "PAM",
      "FR",
      "FC",
      "Spo2",
      "hx",
      "tce",
      "msd",
      "enf",
      "SNE fechada",
      "jugular D"
    ],
    "Função Patológica": [
      "edema"
    ],
    "Sinal ou Sintoma": [
      "edema",
      "HIPOTENSÃO",
      "globoso",
      "grumos",
      "cefaléia",
      "algia",
      "náuseas",
      "vômito",
      "cacifo +++/+4",
      "algia moderada",
      "roncos difusos",
      "periodos de sonolencia",
      "queixas álgicas"
    ],
    "Atividade de Assistência à Saúde": [
      "cuidados",
      "plantao",
      "MEDICADO",
      "ORIENTAÇÃO",
      "prescriçao medica"
    ],
    "Paciente ou Grupo com Deficiência": [
      "paciente",
      "Paciente"
    ],
    "Negação": [
      "sem"
    ],
    "Conceito Quantitativo": [
      "5",
      "30",
      "113/98",
      "15",
      "107",
      "93%",
      "63 ml/h"
    ],
    "Hormônio": [
      "noradrenalina"
    ],
    "Substância Farmacológica": [
      "noradrenalina"
    ],
    "Conceito Qualitativo": [
      "5",
      "salinizado"
    ],
    "Procedimento Diagnóstico": [
      "ECG",
      "ausculta pulmonar",
      "monitorização multiparametros"
    ],
    "Atributo Clínico": [
      "PAM",
      "FR",
      "FC",
      "Spo2"
    ],
    "Grupo Profissional ou Ocupacional": [
      "Enfermeira",
      "enf"
    ],
    "Lesão ou Envenenamento": [
      "atropelamento",
      "tce",
      "escoriações",
      "FRATURA DA DIAFISE DA TIBIA",
      "TRAUMATISMO INTRACRANIANO"
    ],
    "Grupo Familiar": [
      "familiar"
    ],
    "Função Fisiológica": [
      "eliminaçoes fisiologicas presentes",
      "diurese presente"
    ],
    "Organização Relacionada à Saúde": [
      "plantao da ortopedia"
    ],
    "Doença ou Síndrome": [
      "EDEMA CEREBRAL"
    ],
    "Substância Corporal": [
      "debito biliar"
    ],
    "Parte do Corpo, Órgão ou Componente Orgânico": [
      "jugular D",
      "ombro esquerdo"
    ]
  },
  "labels": {
    "edema cerebral": {
      "capitulo": "08"
    },
    "periodos de sonolencia": {
      "capitulo": "06"
    },
    "grumos": {
      "capitulo": "13"
    },
    "cefaléia": {
      "capitulo": "21"
    },
    "traumatismo intracraniano": {
      "capitulo": "08"
    },
    "concentrada": {
      "capitulo": "13"
    },
    "náuseas": {
      "capitulo": "13"
    },
    "fratura da diafise da tibia": {
      "capitulo": "15"
    },
    "flácido a palpação": {
      "capitulo": "21"
    },
    "intubado": {
      "capitulo": "22"
    },
    "algia moderada": {
      "capitulo": "21"
    },
    "roncos difusos": {
      "capitulo": "21"
    },
    "cacifo +++/+4": {
      "capitulo": "21"
    },
    "escoriações": {
      "capitulo": "14"
    },
    "vômito": {
      "capitulo": "13"
    },
    "tce": {
      "capitulo": "22"
    },
    "algia": {
      "capitulo": "21"
    },
    "atropelamento": {
      "capitulo": "22"
    },
    "edema": {
      "capitulo": "15"
    },
    "hipotensão": {
      "capitulo": "11"
    },
    "globoso": {
      "capitulo": "21"
    },
    "queixas álgicas": {
      "capitulo": "21"
    },
    "pupilas isocoricas fotorreagentes": {
      "capitulo": "21"
    }
  }
}