{
  "prontuario_id": 448,
  "text": "DRENO DE PENROSE COM DÉBITO SERO-HEMÁTICO, COLOSTOMIA SEM DÉBITO, FOI SUSPENSO BANHO E DIETA DEVIDO A INSTABILIDADE HEMODINAMICA. DOENCA DIVERTICULAR DO INTESTINO DE LOCALIZACAO NAO ESPECIFICADA SEM PERFURACAO OU ABSCESSO. Às 15:47: ORIENTADO, COMUNICATIVO, SEM QUEIXAS ALGICAS, DEAMBULANDO, MANTEM CTVO EM ABD, MANTEM ACESSO VENOSO PERIFERICO EM MSE, ACEITANDO DIETA, ELIMINAÇÕES FISIOLÓGICAS PRESENTES. OUTRAS FORMAS DE APENDICITE. Às 16:47 Hr: Segue sem queixas álgicas, com acesso venoso periférico em braço esquerdo salinizado. Mantendo tala gessada em MSE com boa perfusão periférica e edema distal. Eliminações vesical e intestinal presentes. TRAUMATISMOS MULTIPLOS NAO ESPECIFICADOS. Em 07/01/2008, 16 HORAS: PERMANECE SEDADO, COM ABERTURA OCULAR ESPONTÂNEA, PUPILAS ISOCÓRICAS E FOTORREAGENTES, REAGINDO DISCRETAMENTE AOS ESTÍMULOS VERBAIS. VM VIA TRAQUEO COM FiO2 30%, PCV, PI 27 cmH2O, PEEP 7 cmH2O, F 16 mrpm, SPO2 100%. AUSCULTA PULMONAR COM INSUFICIENCIA RESPIRATORIA AGUDA. Às 16:07h: POI CCVL. Consciente, orientada, tranquila, comunicativa e mantendo repouso. Mantendo acesso venoso periférico em MSE medial e articular com boa perfusão e soroterapia em curso, curativos oclusivos abdominais limpo e seco externamente. Enf Florence Nightingale. OUTRAS COLELITIASES.",
  "entities": {
    "Procedimento Terapêutico ou Preventivo": [
      "COLOSTOMIA",
      "BANHO",
      "DIETA",
      "CTVO",
      "SEDADO",
      "PCV",
      "PI",
      "PEEP",
      "SPO2",
      "DRENO DE PENROSE",
      "ACESSO VENOSO PERIFERICO",
      "acesso venoso periférico",
      "tala gessada",
      "VM VIA TRAQUEO"
    ],
    "Atividade de Assistência à Saúde": [
      "SUSPENSO"
    ],
    "Alimento": [
      "DIETA"
    ],
    "Achado": [
      "ORIENTADO",
      "COMUNICATIVO",
      "DEAMBULANDO",
      "salinizado",
      "Consciente",
      "orientada",
      "tranquila",
      "comunicativa",
      "repouso",
      "limpo",
      "seco",
      "DÉBITO SERO-HEMÁTICO",
      "ACEITANDO DIETA",
      "ELIMINAÇÕES FISIOLÓGICAS PRESENTES",
      "boa perfusão periférica",
      "ABERTURA OCULAR ESPONTÂNEA",
      "PUPILAS ISOCÓRICAS E FOTORREAGENTES"
    ],
    "Abreviação": [
      "CTVO",
      "ABD",
      "MSE",
      "PCV",
      "PI",
      "PEEP",
      "F",
      "SPO2",
      "POI",
      "CCVL",
      "Enf",
      "VM VIA TRAQUEO"
    ],
    "Dispositivo Médico": [
      "CTVO",
      "DRENO DE PENROSE",
      "ACESSO VENOSO PERIFERICO",
      "acesso venoso periférico",
      "tala gessada",
      "curativos oclusivos"
    ],
    "Localização ou Região Corporal": [
      "ABD",
      "MSE",
      "abdominais"
    ],
    "Doença ou Síndrome": [
      "APENDICITE",
      "COLELITIASES",
      "DOENCA DIVERTICULAR DO INTESTINO",
      "INSUFICIENCIA RESPIRATORIA AGUDA"
    ],
    "Conceito Quantitativo": [
      "30%",
      "100%",
      "27 cmH2O",
      "7 cmH2O",
      "16 mrpm"
    ],
    "Conceito Temporal": [
      "POI"
    ],
    "Conceito Espacial": [
      "externamente"
    ],
    "Grupo Profissional ou Ocupacional": [
      "Enf"
    ],
    "Substância Corporal": [
      "DÉBITO SERO-HEMÁTICO"
    ],
    "Sinal ou Sintoma": [
      "INSTABILIDADE HEMODINAMICA",
      "QUEIXAS ALGICAS",
      "queixas álgicas",
      "edema distal",
      "REAGINDO DISCRETAMENTE AOS ESTÍMULOS VERBAIS"
    ],
    "Função Fisiológica": [
      "ELIMINAÇÕES FISIOLÓGICAS PRESENTES"
    ],
    "Parte do Corpo, Órgão ou Componente Orgânico": [
      "braço esquerdo"
    ],
    "Função Patológica": [
      "edema distal"
    ],
    "Lesão ou Envenenamento": [
      "TRAUMATISMOS MULTIPLOS"
    ],
    "Procedimento Diagnóstico": [
      "AUSCULTA PULMONAR"
    ]
  },
  "labels": {
    "orientado": {
      "capitulo": "06"
    },
    "queixas algicas": {
      "capitulo": "21"
    },
    "instabilidade hemodinamica": {
      "capitulo": "11"
    },
    "apendicite": {
      "capitulo": "13"
    },
    "comunicativo": {
      "capitulo": "06"
    },
    "deambulando": {
      "capitulo": "15"
    },
    "seco": {
      "capitulo": "14"
    },
    "limpo": {
      "capitulo": "14"
    },
    "traumatismos multiplos": {
      "capitulo": "22"
    },
    "insuficiencia respiratoria aguda": {
      "capitulo": "12"
    },
    "abertura ocular espontânea": {
      "capitulo": "09"
    },
    "comunicativa": {
      "capitulo": "06"
    },
    "reagindo discretamente aos estímulos verbais": {
      "capitulo": "06"
    },
    "consciente": {
      "capitulo": "06"
    },
    "tranquila": {
      "capitulo": "06"
    },
    "salinizado": {
      "capitulo": "14"
    },
    "colelitiases": {
      "capitulo": "16"
    },
    "débito sero-hemático": {
      "capitulo": "03"
    },
    "edema distal": {
      "capitulo": "15"
    },
    "orientada": {
      "capitulo": "06"
    },
    "queixas álgicas": {
      "capitulo": "21"
    },
    "pupilas isocóricas e fotorreagentes": {
      "capitulo": "09"
    },
    "doenca diverticular do intestino": {
      "capitulo": "13"
    }
  }
}