{
  "prontuario_id": 368,
  "text": "Às 05:30: ENCAMINHADO PARA TAC DE CRÂNIO, MONITORIZADA, PROCEDIMENTO E TRAJETO REALIZADOS SEM INTERCORRÊNCIAS. EXAME GERAL E INVESTIGACAO DE PESSOAS SEM QUEIXAS OU DIAGNOSTICO RELATADO. Às 11:52 HS: LUCIDO, ORIENTADO, COMUNICATIVO, AFEBRIL, NORMOTENSO, NORMOCORADO, EUPNEICO. ACESSO VENOSO PERIFERICO EM MSE SALINIZADO. CURATIVO EM MS LIMPO E SECO EXTERNAMENTE. DIURESE PRESENTE, REPOUSO NO LEITO. MANTÉM JEJUM PARA PROCEDIMENTO CIRURGICO HOJE A TARDE. SEGUE CUIDADOS DE ENFERMAGEM. ENF FLORENCE NIGHTINGALE, COREN XXXX. TRANSTORNOS DA CONTINUIDADE DO OSSO. Às 14:30: 2ª DI - FAB REGIÃO GLUTEA DIREITA - CONSCIENTE, LUCIDO, EUPNEICO, COMUNICATIVO, DEAMBULA COM AUXILIO, SEM QUEIXAS ALGICAS NO MOMENTO, APRESENTA PUPILAS ISOCORICAS, PELE E MUCOSA CORADA E HIDRATADA, AUSCULTA PULMONAR COM MV +, MANTEM ACESSO VENOSO PERIFERICO SALINIZADO, RELATA BOA ACEITAÇAO DA DIETA OFERECIDA, DIURESE ESPONTANEA PRESENTE; TRAUMATISMO DE NERVOS DE REGIAO NAO ESPECIFICADA DO CORPO.",
  "entities": {
    "Procedimento Diagnóstico": [
      "MONITORIZADA",
      "TAC DE CRÂNIO",
      "AUSCULTA PULMONAR"
    ],
    "Achado": [
      "MONITORIZADA",
      "LUCIDO",
      "ORIENTADO",
      "COMUNICATIVO",
      "AFEBRIL",
      "NORMOTENSO",
      "NORMOCORADO",
      "EUPNEICO",
      "SALINIZADO",
      "LIMPO",
      "SECO",
      "CONSCIENTE",
      "CORADA",
      "HIDRATADA",
      "DIURESE PRESENTE",
      "REPOUSO NO LEITO",
      "DEAMBULA COM AUXILIO",
      "PUPILAS ISOCORICAS",
      "MV +",
      "ACESSO VENOSO PERIFERICO",
      "ACEITAÇAO DA DIETA",
      "DIURESE ESPONTANEA"
    ],
    "Procedimento Terapêutico ou Preventivo": [
      "PROCEDIMENTO",
      "CURATIVO",
      "JEJUM",
      "ACESSO VENOSO PERIFERICO",
      "REPOUSO NO LEITO",
      "PROCEDIMENTO CIRURGICO"
    ],
    "Negação": [
      "AFEBRIL"
    ],
    "Localização ou Região Corporal": [
      "MSE",
      "MS",
      "REGIÃO GLUTEA DIREITA"
    ],
    "Abreviação": [
      "MSE",
      "MS",
      "ENF",
      "FAB",
      "TAC DE CRÂNIO",
      "MV +"
    ],
    "Conceito Qualitativo": [
      "SALINIZADO"
    ],
    "Dispositivo Médico": [
      "CURATIVO",
      "ACESSO VENOSO PERIFERICO"
    ],
    "Conceito Espacial": [
      "EXTERNAMENTE"
    ],
    "Grupo Profissional ou Ocupacional": [
      "ENF"
    ],
    "Lesão ou Envenenamento": [
      "FAB",
      "TRAUMATISMO DE NERVOS"
    ],
    "Parte do Corpo, Órgão ou Componente Orgânico": [
      "PELE",
      "MUCOSA"
    ],
    "Função Fisiológica": [
      "DIURESE PRESENTE",
      "DIURESE ESPONTANEA"
    ],
    "Atividade de Assistência à Saúde": [
      "CUIDADOS DE ENFERMAGEM"
    ],
    "Doença ou Síndrome": [
      "TRANSTORNOS DA CONTINUIDADE DO OSSO"
    ],
    "Sinal ou Sintoma": [
      "QUEIXAS ALGICAS"
    ]
  },
  "labels": {
    "orientado": {
      "capitulo": "06"
    },
    "queixas algicas": {
      "capitulo": "21"
    },
    "monitorizada": {
      "capitulo": "22"
    },
    "acesso venoso periferico": {
      "capitulo": "X"
    },
    "deambula com auxilio": {
      "capitulo": "15"
    },
    "transtornos da continuidade do osso": {
      "capitulo": "15"
    },
    "seco": {
      "capitulo": "X"
    },
    "comunicativo": {
      "capitulo": "06"
    },
    "limpo": {
      "capitulo": "X"
    },
    "traumatismo de nervos": {
      "capitulo": "22"
    },
    "aceitaçao da dieta": {
      "capitulo": "24"
    },
    "mv +": {
      "capitulo": "21"
    },
    "corada": {
      "capitulo": "X"
    },
    "consciente": {
      "capitulo": "06"
    },
    "hidratada": {
      "capitulo": "X"
    },
    "repouso no leito": {
      "capitulo": "24"
    },
    "salinizado": {
      "capitulo": "X"
    },
    "fab": {
      "capitulo": "21"
    },
    "pupilas isocoricas": {
      "capitulo": "21"
    }
  }
}