{
  "prontuario_id": 954,
  "text": "Às 20H: RECEPCIONADA DO CC EM POI DE RESSECÇÃO DE TUMOR DE MEDIASTINO POSTERIOR + ESOFAGORRAFIAS. PERMANECE EM RESPIRAÇÃO ESPONTÂNEA COM SUPLEMENTAÇÃO DE O2 VIA MÁSCARA A 5 L/MIN, PUPILAS ISOCÓRICAS E FOTORREAGENTES, GLASGOW 11-12, MUCOSAS DESCORADAS, SNE FECHADA, ACESSOS VENOSOS PERIFÉRICOS EM MMSS COM PLANO BÁSICO DE HIDRATAÇÃO, AUSCULTA PULMONAR COM RONCOS ESPARSOS E MV DIMINUÍDOS EM BASES, DRENO DE TÓRAX Á DIREITA SUPERIOR COM DISCRETA OSCILAÇÃO E 50 ML DE DÉBITO HEMÁTICO, DRENO DE TÓRAX DIREITO INFERIOR COM 200 ML DE DÉBITO HEMÁTICO E OSCILANTE, ABDOME GLOBOSO E FLÁCIDO, RHA HIPOATIVOS, CATÉTER PARA ANALGESIA OCLUÍDO, 200 ML DE DIURESE DE ASPECTO AMARELO CLARO. MONITORADO COM PNI, CARDIOSCOPIA E OXIMETRIA DE PULSO. EXAME GERAL E INVESTIGACAO DE PESSOAS SEM QUEIXAS OU DIAGNOSTICO RELATADO. Às 01:42H: CLIENTE SERIA REMOVIDO PARA HOSPITAL EVANGÉLICO, PORÉM FOI SUSPENSO. FOI REMOVIDO PARA HOSPITAL DE CLÍNICAS PARA CONTINUIDADE NO TRATAMENTO, CONTATO REALIZADO PELA CLÍNICA MÉDICA COM PLANTONISTA DO HC. ENF FLORENCE NIGHTINGALE, COREN XXXX. OUTRAS DOENCAS ESPECIFICADAS DO SANGUE E DOS ORGAOS HEMATOPOETICOS.",
  "entities": {
    "Abreviação": [
      "CC",
      "POI",
      "MMSS",
      "PNI",
      "ENF",
      "SNE FECHADA",
      "MV DIMINUÍDOS EM BASES",
      "RHA HIPOATIVOS"
    ],
    "Organização Relacionada à Saúde": [
      "CC",
      "CLÍNICA MÉDICA"
    ],
    "Conceito Temporal": [
      "POI"
    ],
    "Procedimento Terapêutico ou Preventivo": [
      "ESOFAGORRAFIAS",
      "RESSECÇÃO DE TUMOR DE MEDIASTINO POSTERIOR",
      "SUPLEMENTAÇÃO DE O2",
      "SNE FECHADA",
      "ACESSOS VENOSOS PERIFÉRICOS",
      "PLANO BÁSICO DE HIDRATAÇÃO",
      "DRENO DE TÓRAX"
    ],
    "Dispositivo Médico": [
      "MÁSCARA",
      "SNE FECHADA",
      "ACESSOS VENOSOS PERIFÉRICOS",
      "DRENO DE TÓRAX"
    ],
    "Parte do Corpo, Órgão ou Componente Orgânico": [
      "PUPILAS"
    ],
    "Localização ou Região Corporal": [
      "MMSS",
      "ABDOME"
    ],
    "Sinal ou Sintoma": [
      "OSCILANTE",
      "GLOBOSO",
      "GLASGOW 11-12",
      "MUCOSAS DESCORADAS",
      "RONCOS ESPARSOS",
      "MV DIMINUÍDOS EM BASES",
      "DISCRETA OSCILAÇÃO",
      "DÉBITO HEMÁTICO",
      "RHA HIPOATIVOS"
    ],
    "Achado": [
      "FLÁCIDO",
      "OCLUÍDO",
      "MONITORADO",
      "RESPIRAÇÃO ESPONTÂNEA",
      "SNE FECHADA",
      "AMARELO CLARO"
    ],
    "Procedimento Diagnóstico": [
      "MONITORADO",
      "PNI",
      "CARDIOSCOPIA",
      "AUSCULTA PULMONAR",
      "OXIMETRIA DE PULSO"
    ],
    "Grupo Populacional": [
      "PESSOAS"
    ],
    "Negação": [
      "SEM"
    ],
    "Paciente ou Grupo com Deficiência": [
      "CLIENTE"
    ],
    "Grupo Profissional ou Ocupacional": [
      "PLANTONISTA",
      "ENF"
    ],
    "Conceito Quantitativo": [
      "5 L/MIN",
      "50 ML",
      "200 ML"
    ],
    "Conceito Espacial": [
      "DIREITA SUPERIOR",
      "DIREITO INFERIOR"
    ],
    "Substância Corporal": [
      "DÉBITO HEMÁTICO"
    ],
    "Doença ou Síndrome": [
      "DOENCAS ESPECIFICADAS DO SANGUE E DOS ORGAOS HEMATOPOETICOS"
    ]
  },
  "labels": {
    "rha hipoativos": {
      "capitulo": "03"
    },
    "glasgow 11-12": {
      "capitulo": "06"
    },
    "mv diminuídos em bases": {
      "capitulo": "08"
    },
    "débito hemático": {
      "capitulo": "22"
    },
    "flácido": {
      "capitulo": "15"
    },
    "doencas especificadas do sangue e dos orgaos hematopoeticos": {
      "capitulo": "03"
    },
    "globoso": {
      "capitulo": "15"
    },
    "mucosas descoradas": {
      "capitulo": "14"
    },
    "discreta oscilação": {
      "capitulo": "08"
    },
    "roncos esparsos": {
      "capitulo": "12"
    },
    "oscilante": {
      "capitulo": "22"
    },
    "respiração espontânea": {
      "capitulo": "12"
    },
    "sne fechada": {
      "capitulo": "16"
    },
    "amarelo claro": {
      "capitulo": "21"
    },
    "ocluído": {
      "capitulo": "09"
    },
    "monitorado": {
      "capitulo": "24"
    }
  }
}