{
  "prontuario_id": 313,
  "text": "Às 11:15HRS: Cliente acordado, glasgow 12, pupilas iso / foto +. TQT, respiração espontânea em aa, com auxilio de oxigenoterapia em névoa úmida, em máscara á 4 l/min, eupneico, mucosa corada e hidratada, boa perfusão periferica, com cabeceira elevada á 60°. Mantem monitorização de multiparâmetros - ECG, PNI, SpO2, SNG aberta com estase gastrica ++, CVC em subclávia ESQ, sem sinais flogisticos, com infusão de srt em curso gravitacional, dreno de suctor em FID com debito seroso +, FO em região abdominal com presença de secreção ++ de aspecto seroso. Faz uso de SVD aberta com debito diuretico presente, eliminação fecal ausente. Apresenta AP ritmica e normofonetica, AP MV + com roncos difusos, abdomen com RHA +. Segue cuidados intensivos da enfermagem. Enf° Florence Nightingale, Coren XXXX. INFECCAO SUBSEQUENTE A PROCEDIMENTO NAO CLASSIFICADA EM OUTRA PARTE. Às 03:04: Por volta das 22:00 horas, paciente apresentando sonolencia, sudorese, tremores, rigidez de nuca, PA 130/ 80, dextro 153, afebril, chamado plantao da neuro, suspenso diazepam. No momento, acordada, nao verbalizando, responsiva à estimulos, PA 120/70, dextro 137, afebril, edema em regiao frontal à esquerda aumentado, segue cuidados e observaçao. Aguarda cx para proxima semana. Com acompanhante. FRATURA DA PRIMEIRA VERTEBRA CERVICAL.",
  "entities": {
    "Paciente ou Grupo com Deficiência": [
      "Cliente",
      "paciente"
    ],
    "Achado": [
      "acordado",
      "eupneico",
      "corada",
      "hidratada",
      "ritmica",
      "normofonetica",
      "afebril",
      "acordada",
      "verbalizando",
      "aumentado",
      "boa perfusão periferica",
      "SNG aberta",
      "debito seroso",
      "debito diuretico presente",
      "eliminação fecal",
      "MV +",
      "abdomen com RHA +",
      "responsiva à estimulos"
    ],
    "Parte do Corpo, Órgão ou Componente Orgânico": [
      "pupilas",
      "mucosa",
      "subclávia ESQ"
    ],
    "Procedimento Terapêutico ou Preventivo": [
      "TQT",
      "CVC",
      "infusão",
      "cx",
      "oxigenoterapia em névoa úmida",
      "cabeceira elevada á 60°",
      "SNG aberta",
      "srt em curso gravitacional",
      "dreno de suctor",
      "SVD aberta"
    ],
    "Abreviação": [
      "TQT",
      "ECG",
      "PNI",
      "SpO2",
      "CVC",
      "FID",
      "FO",
      "AP",
      "Enf°",
      "PA",
      "cx",
      "respiração espontânea em aa",
      "SNG aberta",
      "subclávia ESQ",
      "srt em curso gravitacional",
      "SVD aberta",
      "MV +",
      "abdomen com RHA +"
    ],
    "Dispositivo Médico": [
      "máscara",
      "CVC",
      "SNG aberta",
      "dreno de suctor",
      "SVD aberta"
    ],
    "Procedimento Diagnóstico": [
      "ECG",
      "PNI",
      "AP",
      "monitorização de multiparâmetros"
    ],
    "Negação": [
      "sem",
      "ausente",
      "afebril",
      "nao"
    ],
    "Localização ou Região Corporal": [
      "FID",
      "região abdominal",
      "regiao frontal à esquerda"
    ],
    "Lesão ou Envenenamento": [
      "FO",
      "FRATURA DA PRIMEIRA VERTEBRA CERVICAL"
    ],
    "Grupo Profissional ou Ocupacional": [
      "Enf°"
    ],
    "Sinal ou Sintoma": [
      "sonolencia",
      "sudorese",
      "tremores",
      "edema",
      "glasgow 12",
      "estase gastrica",
      "sinais flogisticos",
      "presença de secreção",
      "aspecto seroso",
      "roncos difusos",
      "rigidez de nuca"
    ],
    "Atributo Clínico": [
      "PA"
    ],
    "Conceito Quantitativo": [
      "153",
      "120/70",
      "4 l/min",
      "130/ 80"
    ],
    "Atividade de Assistência à Saúde": [
      "plantao",
      "cuidados",
      "cuidados intensivos da enfermagem",
      "e observaçao"
    ],
    "Substância Farmacológica": [
      "diazepam"
    ],
    "Substância Química Orgânica": [
      "diazepam"
    ],
    "Função Patológica": [
      "edema"
    ],
    "Conceito Qualitativo": [
      "aumentado"
    ],
    "Grupo Populacional": [
      "acompanhante"
    ],
    "Função Fisiológica": [
      "debito diuretico presente",
      "eliminação fecal"
    ],
    "Doença ou Síndrome": [
      "INFECCAO SUBSEQUENTE A PROCEDIMENTO"
    ]
  },
  "labels": {
    "aumentado": {
      "capitulo": "11"
    },
    "rigidez de nuca": {
      "capitulo": "08"
    },
    "sudorese": {
      "capitulo": "21"
    },
    "glasgow 12": {
      "capitulo": "08"
    },
    "debito diuretico presente": {
      "capitulo": "11"
    },
    "mv +": {
      "capitulo": "21"
    },
    "fratura da primeira vertebra cervical": {
      "capitulo": "15"
    },
    "sinais flogisticos": {
      "capitulo": "21"
    },
    "aspecto seroso": {
      "capitulo": "21"
    },
    "presença de secreção": {
      "capitulo": "21"
    },
    "tremores": {
      "capitulo": "08"
    },
    "roncos difusos": {
      "capitulo": "21"
    },
    "sonolencia": {
      "capitulo": "07"
    },
    "abdomen com rha +": {
      "capitulo": "13"
    },
    "estase gastrica": {
      "capitulo": "21"
    },
    "fo": {
      "capitulo": "21"
    },
    "edema": {
      "capitulo": "21"
    },
    "infeccao subsequente a procedimento": {
      "capitulo": "01"
    },
    "sng aberta": {
      "capitulo": "21"
    },
    "debito seroso": {
      "capitulo": "21"
    }
  }
}