{
  "prontuario_id": 172,
  "text": "Em 30/07/2007, 09:00h: Acordado, alerta, descorado, pouco responsivo aos estímulos, mucosas coradas e hidratadas. Traqueostomizado, apresentando secreção espessa em grande quantidade. Apresenta abdome plano, flácido, indolor à palpação, RHA +. Mantém SNE para a. TRAUMATISMOS MULTIPLOS NAO ESPECIFICADOS. Às 01:40: Paciente alerta, ativo, reativo. Apresenta-se choroso no momento. Mantém acesso venoso em MSE salinizado. Segundo acompanhante, paciente relata algia lombar moderada. Mantém jejum desde 00 horas, para procedimento cirurgico. Segue sob cuidados. TRAUMATISMOS MULTIPLOS NAO ESPECIFICADOS. Às 14:35 Hr: 3º PO de enxerto em MIE, segue referindo algia intensa em perna esquerda, mantém acesso venoso periférico em antebraço direito com soroterapia em curso. Curativo em tórax, coxa direita e perna esquerda com aspecto limpo e seco externamente, mante. FRATURA DA ROTULA PATELA. Às 10H: CONSCIENTE, ALERTA, ABERTURA OCULAR ESPONTANEA, ATENDE AS SOLICITAÇÕES VERBAIS, AFÁSICO, NÃO DEAMBULA, EM REPOUSO NA POLTRONA. TRAQUEOSTOMIZADO COM NÉVOA ÚMIDA CONTÍNUA. FOI ASPIRADO. APRESENTA GRANDE QUANTIDADE DE SECREÇÃO TRAQUEOBRONQUICA FLUIDIFICAD. NEOPLASIA MALIGNA DA BASE DA LINGUA.",
  "entities": {
    "Achado": [
      "Acordado",
      "alerta",
      "Traqueostomizado",
      "flácido",
      "ativo",
      "reativo",
      "choroso",
      "salinizado",
      "jejum",
      "CONSCIENTE",
      "ALERTA",
      "DEAMBULA",
      "TRAQUEOSTOMIZADO",
      "pouco responsivo aos estímulos",
      "mucosas coradas e hidratadas",
      "indolor à palpação",
      "RHA +",
      "ABERTURA OCULAR ESPONTANEA",
      "ATENDE AS SOLICITAÇÕES VERBAIS",
      "SECREÇÃO TRAQUEOBRONQUICA FLUIDIFICAD"
    ],
    "Sinal ou Sintoma": [
      "descorado",
      "AFÁSICO",
      "pouco responsivo aos estímulos",
      "secreção espessa em grande quantidade",
      "algia lombar moderada",
      "algia intensa"
    ],
    "Procedimento Terapêutico ou Preventivo": [
      "Traqueostomizado",
      "SNE",
      "salinizado",
      "jejum",
      "enxerto",
      "Curativo",
      "TRAQUEOSTOMIZADO",
      "ASPIRADO",
      "acesso venoso",
      "procedimento cirurgico",
      "acesso venoso periférico",
      "soroterapia em curso",
      "REPOUSO NA POLTRONA",
      "NÉVOA ÚMIDA CONTÍNUA"
    ],
    "Localização ou Região Corporal": [
      "abdome",
      "MSE",
      "MIE",
      "tórax"
    ],
    "Dispositivo Médico": [
      "SNE",
      "Curativo",
      "acesso venoso",
      "acesso venoso periférico"
    ],
    "Abreviação": [
      "SNE",
      "MSE",
      "PO",
      "MIE",
      "RHA +",
      "SECREÇÃO TRAQUEOBRONQUICA FLUIDIFICAD"
    ],
    "Paciente ou Grupo com Deficiência": [
      "Paciente",
      "paciente"
    ],
    "Grupo Populacional": [
      "acompanhante"
    ],
    "Atividade de Assistência à Saúde": [
      "cuidados"
    ],
    "Conceito Temporal": [
      "PO"
    ],
    "Conceito Espacial": [
      "externamente"
    ],
    "Negação": [
      "NÃO"
    ],
    "Conceito Qualitativo": [
      "secreção espessa em grande quantidade",
      "GRANDE QUANTIDADE"
    ],
    "Lesão ou Envenenamento": [
      "TRAUMATISMOS MULTIPLOS",
      "FRATURA DA ROTULA PATELA"
    ],
    "Parte do Corpo, Órgão ou Componente Orgânico": [
      "antebraço direito",
      "coxa direita"
    ],
    "Processo Neoplásico": [
      "NEOPLASIA MALIGNA DA BASE DA LINGUA"
    ]
  },
  "labels": {
    "mucosas coradas e hidratadas": {
      "capitulo": "12"
    },
    "flácido": {
      "capitulo": "15"
    },
    "fratura da rotula patela": {
      "capitulo": "15"
    },
    "traqueostomizado": {
      "capitulo": "22"
    },
    "choroso": {
      "capitulo": "21"
    },
    "secreção espessa em grande quantidade": {
      "capitulo": "12"
    },
    "traumatismos multiplos": {
      "capitulo": "22"
    },
    "algia lombar moderada": {
      "capitulo": "15"
    },
    "afásico": {
      "capitulo": "21"
    },
    "algia intensa": {
      "capitulo": "15"
    },
    "jejum": {
      "capitulo": "24"
    },
    "secreção traqueobronquica fluidificad": {
      "capitulo": "12"
    },
    "salinizado": {
      "capitulo": "22"
    },
    "abertura ocular espontanea": {
      "capitulo": "21"
    },
    "neoplasia maligna da base da lingua": {
      "capitulo": "02"
    },
    "pouco responsivo aos estímulos": {
      "capitulo": "21"
    }
  }
}