{
  "prontuario_id": 814,
  "text": "Em 05/10/2006, 14 HORAS: PERMANECE SEDADO, COM PUPILAS ISOMIÓTICAS E FOTORREAGENTES, COM DISCRETO EDEMA PERIPALPEBRAL BILATERAL. VM VIA TRAQUEO COM FO2 50%, PCV, PI 23 cmH20, PEEP 10cm H2O, F 14 mrpm, SPO2 99%. AUSCULTA PULMONAR COM RONCOS DIFUSOS E DISCRETAMEN. TRAUMATISMO DO BACO. Em 26/07/2007, 08:36h: Acordada, alerta, responsiva, mucosas coradas e hidratadas. Apresenta abdome plano, flácido, RHA +, indolor à palpação. Mantém SNE para alimentação por bomba infusora, em jejum no momento para procedimento cirúrgico (gastrostomia). Diures. ACIDENTES VASCULARES CEREBRAIS ISQUEMICOS TRANSITORIOS E SINDROMES CORRELATAS. CONSCIENTE, LÚCIDO, ORIENTADO, VERBALIZA, DEAMBULA, REFERE BOA ACEITAÇÃO DA DIETA HOSPITALAR, PORÉM MANTÉM JEJUM PARA PROCEDIMENTO NO CENTRO CIRÚRGICO HOJE. NEGA ALGIA, APRESENTA TALA GESSADA EM MSD, CURATIVO LOCAL DE ASPECTO LIMPO E SECO EXTERNAMENTE, BO. FRATURA DE OUTROS OSSOS DO METACARPO. Às 10:00: Paciente consciente, orientado, comunicativo, refere boa aceitação da dieta, paraplegia em MMII, realizado mudança de decúbito de 2/2hrs, refere não evacuar há 3 dias, algia em abdomen. Ao exame físico: ausculta pulmonar livre, ausculta abdominal com. OUTROS TRANSTORNOS DO TRATO URINARIO.",
  "entities": {
    "Achado": [
      "SEDADO",
      "ISOMIÓTICAS",
      "FOTORREAGENTES",
      "Acordada",
      "alerta",
      "responsiva",
      "flácido",
      "jejum",
      "CONSCIENTE",
      "LÚCIDO",
      "ORIENTADO",
      "VERBALIZA",
      "DEAMBULA",
      "consciente",
      "orientado",
      "comunicativo",
      "RHA +",
      "indolor à palpação",
      "BOA ACEITAÇÃO DA DIETA",
      "boa aceitação da dieta",
      "ausculta pulmonar livre"
    ],
    "Procedimento Terapêutico ou Preventivo": [
      "SEDADO",
      "FO2",
      "PCV",
      "PI",
      "PEEP",
      "SPO2",
      "jejum",
      "gastrostomia",
      "JEJUM",
      "CURATIVO",
      "VM VIA TRAQUEO",
      "SNE para alimentação",
      "procedimento cirúrgico",
      "PARA PROCEDIMENTO",
      "TALA GESSADA",
      "mudança de decúbito"
    ],
    "Parte do Corpo, Órgão ou Componente Orgânico": [
      "PUPILAS",
      "mucosas"
    ],
    "Abreviação": [
      "FO2",
      "PCV",
      "PI",
      "PEEP",
      "F",
      "SPO2",
      "MSD",
      "VM VIA TRAQUEO",
      "RHA +",
      "SNE para alimentação",
      "paraplegia em MMII",
      "mudança de decúbito"
    ],
    "Conceito Quantitativo": [
      "50%",
      "99%",
      "23 cmH20",
      "14 mrpm"
    ],
    "Localização ou Região Corporal": [
      "abdome",
      "MSD",
      "abdomen"
    ],
    "Negação": [
      "NEGA",
      "não"
    ],
    "Sinal ou Sintoma": [
      "ALGIA",
      "algia",
      "DISCRETO EDEMA PERIPALPEBRAL BILATERAL",
      "RONCOS DIFUSOS",
      "paraplegia em MMII"
    ],
    "Dispositivo Médico": [
      "CURATIVO",
      "TALA GESSADA"
    ],
    "Conceito Espacial": [
      "EXTERNAMENTE"
    ],
    "Paciente ou Grupo com Deficiência": [
      "Paciente"
    ],
    "Função Fisiológica": [
      "evacuar"
    ],
    "Procedimento Diagnóstico": [
      "AUSCULTA PULMONAR",
      "exame físico",
      "ausculta pulmonar livre",
      "ausculta abdominal"
    ],
    "Lesão ou Envenenamento": [
      "TRAUMATISMO DO BACO",
      "FRATURA DE OUTROS OSSOS DO METACARPO"
    ],
    "Dispositivo de Administração de Medicamento": [
      "bomba infusora"
    ],
    "Doença ou Síndrome": [
      "ACIDENTES VASCULARES CEREBRAIS ISQUEMICOS TRANSITORIOS",
      "FRATURA DE OUTROS OSSOS DO METACARPO",
      "TRANSTORNOS DO TRATO URINARIO"
    ],
    "Organização Relacionada à Saúde": [
      "CENTRO CIRÚRGICO"
    ]
  },
  "labels": {
    "orientado": {
      "capitulo": "06"
    },
    "flácido": {
      "capitulo": "15"
    },
    "fratura de outros ossos do metacarpo": {
      "capitulo": "15"
    },
    "isomióticas": {
      "capitulo": "08"
    },
    "verbaliza": {
      "capitulo": "06"
    },
    "transtornos do trato urinario": {
      "capitulo": "16"
    },
    "paraplegia em mmii": {
      "capitulo": "08"
    },
    "acidentes vasculares cerebrais isquemicos transitorios": {
      "capitulo": "08"
    },
    "comunicativo": {
      "capitulo": "06"
    },
    "alerta": {
      "capitulo": "06"
    },
    "acordada": {
      "capitulo": "06"
    },
    "responsiva": {
      "capitulo": "06"
    },
    "discreto edema peripalpebral bilateral": {
      "capitulo": "09"
    },
    "fotorreagentes": {
      "capitulo": "09"
    },
    "roncos difusos": {
      "capitulo": "12"
    },
    "lúcido": {
      "capitulo": "06"
    },
    "consciente": {
      "capitulo": "06"
    },
    "traumatismo do baco": {
      "capitulo": "15"
    },
    "deambula": {
      "capitulo": "06"
    },
    "sedado": {
      "capitulo": "08"
    }
  }
}