{
  "prontuario_id": 140,
  "text": "Às 7:28hs: Paciente ramsay 5, entubado em VM modo CMV, com peep 8, Fio2 42%, pupilas isocoricas fotorreagentes, SNG fechada, SNE com dieta 30 ml/h, curativo em carotida com dreno de penrose, ausculta pulmonar com roncos difusos, torax simetrico, abdomem plano com RHA+, diurese em uropen, AVP em MSE com propofol 10 ml/h e fentanil 10 ml/h, monitorização multiparametros com ECG, FC 90, FR 19, PA 168/92 e Spo2 95%. Boa perfusão periferica sem edemas e cianoses. Em 03/04/12, 20:05H: PACIENTE COM GLASGOW = 15, PUPILAS ISOCÓRICAS E FOTORREATIVAS, HEMODINAMICAMENTE ESTÁVEL, RESPIRAÇÃO ESPONTANEA EM AR AMBIENTE, MANTENDO BOA SPO2 = 98%, APRESENTA HEMATOMA E EDEMA EM FACE ESQ E ORBITAL ESQ. MANTÉM ACESSO VENOSO PERIFÉRICO PERMEÁVEL, RETIRADO SVD NO PERÍODO DA TARDE, NÃO APRESENTOU DIURESE ESPONTÂNEA ATÉ O MOMENTO.  # ALTA DA UTI-2, ENCAMINHADA PARA UI-2, LEITO-206-2. PASSADO PLANTÃO PARA ENFERMEIRA. Às 08:30hs: Glasgow 15, pupilas isocóricas fotorreagentes, respiração espontânea com névoa úmida 4 l/m, SpO2 96%, boa aceitação de dieta hipossódica VO, monitorizada, estável hemodinamicamente, MV diminuído em base D, sem R/A, dreno de tórax D com pouca drenagem, serohemática, incisão cirúrgica torácica D com curativo limpo e seco, abdome globoso, flácido, indolor a palpação, RHA +, diurese espontânea efetiva, evacuação ausente, extremidades bem perfundidas, higienizada e sentada na poltrona, pele íntegra. ",
  "entities": {
    "Paciente ou Grupo com Deficiência": [
      "Paciente",
      "PACIENTE"
    ],
    "Procedimento Terapêutico ou Preventivo": [
      "entubado",
      "VM",
      "peep",
      "Fio2",
      "curativo",
      "AVP",
      "higienizada",
      "modo CMV",
      "SNG fechada",
      "SNE com dieta",
      "dreno de penrose",
      "ACESSO VENOSO PERIFÉRICO",
      "RETIRADO SVD",
      "respiração espontânea",
      "névoa úmida",
      "dreno de tórax",
      "com curativo",
      "sentada na poltrona"
    ],
    "Achado": [
      "entubado",
      "RHA+",
      "diurese",
      "monitorizada",
      "R/A",
      "limpo",
      "seco",
      "flácido",
      "evacuação",
      "higienizada",
      "SNG fechada",
      "dreno de penrose",
      "torax simetrico",
      "Boa perfusão periferica",
      "GLASGOW = 15",
      "HEMODINAMICAMENTE ESTÁVEL",
      "RESPIRAÇÃO ESPONTANEA EM AR AMBIENTE",
      "ACESSO VENOSO PERIFÉRICO",
      "DIURESE ESPONTÂNEA",
      "Glasgow 15",
      "respiração espontânea",
      "boa aceitação de dieta hipossódica VO",
      "estável hemodinamicamente",
      "pouca drenagem",
      "RHA +",
      "diurese espontânea efetiva",
      "extremidades bem perfundidas",
      "sentada na poltrona",
      "pele íntegra"
    ],
    "Abreviação": [
      "VM",
      "peep",
      "Fio2",
      "RHA+",
      "AVP",
      "MSE",
      "ECG",
      "FC",
      "FR",
      "PA",
      "Spo2",
      "UTI-2",
      "UI-2",
      "SpO2",
      "R/A",
      "modo CMV",
      "SNG fechada",
      "SNE com dieta",
      "FACE ESQ",
      "ORBITAL ESQ",
      "RETIRADO SVD",
      "boa aceitação de dieta hipossódica VO",
      "MV diminuído em base D",
      "incisão cirúrgica torácica D",
      "RHA +"
    ],
    "Conceito Quantitativo": [
      "8",
      "42%",
      "90",
      "19",
      "168/92",
      "95%",
      "98%",
      "96%",
      "30 ml/h",
      "10 ml/h",
      "4 l/m"
    ],
    "Parte do Corpo, Órgão ou Componente Orgânico": [
      "pupilas",
      "carotida",
      "PUPILAS"
    ],
    "Dispositivo Médico": [
      "curativo",
      "uropen",
      "AVP",
      "dreno de penrose",
      "ACESSO VENOSO PERIFÉRICO",
      "dreno de tórax",
      "com curativo"
    ],
    "Função Fisiológica": [
      "diurese",
      "evacuação",
      "DIURESE ESPONTÂNEA",
      "diurese espontânea efetiva"
    ],
    "Localização ou Região Corporal": [
      "MSE",
      "abdome",
      "FACE ESQ",
      "ORBITAL ESQ"
    ],
    "Substância Química Orgânica": [
      "propofol",
      "fentanil"
    ],
    "Substância Farmacológica": [
      "fentanil"
    ],
    "Procedimento Diagnóstico": [
      "ECG",
      "monitorizada",
      "palpação",
      "ausculta pulmonar",
      "monitorização multiparametros"
    ],
    "Atributo Clínico": [
      "FC",
      "FR",
      "PA",
      "Spo2",
      "SpO2"
    ],
    "Negação": [
      "sem",
      "indolor",
      "ausente"
    ],
    "Função Patológica": [
      "edemas",
      "HEMATOMA",
      "EDEMA"
    ],
    "Sinal ou Sintoma": [
      "edemas",
      "cianoses",
      "HEMATOMA",
      "EDEMA",
      "serohemática",
      "globoso",
      "ramsay 5",
      "roncos difusos",
      "MV diminuído em base D"
    ],
    "Conceito Qualitativo": [
      "BOA",
      "pouca drenagem"
    ],
    "Atividade de Assistência à Saúde": [
      "ALTA",
      "PLANTÃO"
    ],
    "Grupo Profissional ou Ocupacional": [
      "ENFERMEIRA"
    ],
    "Conceito Espacial": [
      "D"
    ],
    "Lesão ou Envenenamento": [
      "incisão cirúrgica torácica D"
    ]
  },
  "labels": {
    "sng fechada": {
      "capitulo": "11"
    },
    "flácido": {
      "capitulo": "15"
    },
    "sentada na poltrona": {
      "capitulo": "V"
    },
    "monitorizada": {
      "capitulo": "21"
    },
    "entubado": {
      "capitulo": "12"
    },
    "edemas": {
      "capitulo": "14"
    },
    "mv diminuído em base d": {
      "capitulo": "11"
    },
    "ramsay 5": {
      "capitulo": "06"
    },
    "respiração espontanea em ar ambiente": {
      "capitulo": "12"
    },
    "hematoma": {
      "capitulo": "14"
    },
    "evacuação": {
      "capitulo": "21"
    },
    "cianoses": {
      "capitulo": "12"
    },
    "dreno de penrose": {
      "capitulo": "14"
    },
    "torax simetrico": {
      "capitulo": "21"
    },
    "respiração espontânea": {
      "capitulo": "12"
    },
    "glasgow = 15": {
      "capitulo": "06"
    },
    "higienizada": {
      "capitulo": "V"
    },
    "glasgow 15": {
      "capitulo": "06"
    },
    "boa aceitação de dieta hipossódica vo": {
      "capitulo": "21"
    },
    "roncos difusos": {
      "capitulo": "12"
    },
    "diurese": {
      "capitulo": "21"
    },
    "incisão cirúrgica torácica d": {
      "capitulo": "14"
    },
    "edema": {
      "capitulo": "14"
    },
    "pouca drenagem": {
      "capitulo": "21"
    },
    "serohemática": {
      "capitulo": "12"
    },
    "globoso": {
      "capitulo": "15"
    },
    "extremidades bem perfundidas": {
      "capitulo": "V"
    },
    "r/a": {
      "capitulo": "21"
    },
    "acesso venoso periférico": {
      "capitulo": "X"
    }
  }
}