{
  "prontuario_id": 592,
  "text": "2º DI, HX DOR ABDOMINAL + EMAGRECIMENTO + EMESES. NO MOMENTO, CONSCIENTE, POUCO COMUNICATIVO, APÁTICO, HEMARECIDO, HIPOCORADO, COM ACESSO VENOSO EM MSE SALINIZADO, ABDOMEM FLÁCIDO, COM MASSA PALPAVEL EM REGIÃO EPIGASTRICA, REFERE DIURESE PRESENTE, EVACUAÇÃO. PERITONITE AGUDA. Às 11:10: Paciente não referindo queixas, consciente, orientado, calmo, comunicativo, em repouso no leito, aceitando dieta VO, acesso venoso periférico MSE, tala gessada antebraço D. boa perfusão periférica, eliminações fisiológicas presentes. FRATURA DE OUTRAS PARTES E DE PARTES NAO ESPECIFICADAS DO PUNHO E DA MAO. Em 06-09-2007, 16:00: Transferido da UTI 2 para o posto 2. Hemodinamicamente Estável. Conversado com a enfermeira  da importância do controle do Balanço. OUTROS TRAUMATISMOS INTRACRANIANOS. Às 9:00: Permanece apática, com abertura ocular espontânea, responsiva à estímulos dolorosos e aspirativos, pupilas isocóricas e fotorreagentes, afebril, hipocorada, taquicárdica, traqueostomizada com suporte de névoa úmida contínua saturando 98%. Apresenta. HEMORRAGIA SUBARACNOIDE PROVENIENTE DO SIFAO E DA BIFURCACAO DA CAROTIDA.",
  "entities": {
    "Abreviação": [
      "HX",
      "MSE",
      "UTI",
      "aceitando dieta VO",
      "antebraço D"
    ],
    "Sinal ou Sintoma": [
      "EMAGRECIMENTO",
      "EMESES",
      "APÁTICO",
      "HEMARECIDO",
      "HIPOCORADO",
      "queixas",
      "apática",
      "hipocorada",
      "taquicárdica",
      "DOR ABDOMINAL",
      "POUCO COMUNICATIVO"
    ],
    "Achado": [
      "CONSCIENTE",
      "SALINIZADO",
      "EVACUAÇÃO",
      "consciente",
      "orientado",
      "calmo",
      "comunicativo",
      "afebril",
      "traqueostomizada",
      "MASSA PALPAVEL",
      "DIURESE PRESENTE",
      "repouso no leito",
      "aceitando dieta VO",
      "boa perfusão periférica",
      "eliminações fisiológicas presentes",
      "Hemodinamicamente Estável",
      "abertura ocular espontânea",
      "responsiva à estímulos dolorosos e aspirativos"
    ],
    "Localização ou Região Corporal": [
      "MSE",
      "REGIÃO EPIGASTRICA"
    ],
    "Procedimento Terapêutico ou Preventivo": [
      "SALINIZADO",
      "traqueostomizada",
      "ACESSO VENOSO",
      "repouso no leito",
      "acesso venoso periférico",
      "tala gessada",
      "controle do Balanço",
      "suporte de névoa úmida contínua"
    ],
    "Função Fisiológica": [
      "EVACUAÇÃO",
      "DIURESE PRESENTE",
      "eliminações fisiológicas presentes"
    ],
    "Paciente ou Grupo com Deficiência": [
      "Paciente"
    ],
    "Negação": [
      "não",
      "afebril"
    ],
    "Lesão ou Envenenamento": [
      "FRATURA",
      "OUTROS TRAUMATISMOS INTRACRANIANOS"
    ],
    "Organização Relacionada à Saúde": [
      "UTI"
    ],
    "Grupo Profissional ou Ocupacional": [
      "enfermeira"
    ],
    "Parte do Corpo, Órgão ou Componente Orgânico": [
      "pupilas",
      "antebraço D"
    ],
    "Conceito Quantitativo": [
      "98%"
    ],
    "Dispositivo Médico": [
      "ACESSO VENOSO",
      "acesso venoso periférico",
      "tala gessada"
    ],
    "Doença ou Síndrome": [
      "PERITONITE AGUDA",
      "HEMORRAGIA SUBARACNOIDE PROVENIENTE DO SIFAO E DA BIFURCACAO DA CAROTIDA"
    ]
  },
  "labels": {
    "massa palpavel": {
      "capitulo": "13"
    },
    "taquicárdica": {
      "capitulo": "11"
    },
    "hipocorada": {
      "capitulo": "21"
    },
    "hemodinamicamente estável": {
      "capitulo": "11"
    },
    "queixas": {
      "capitulo": "21"
    },
    "evacuação": {
      "capitulo": "13"
    },
    "fratura": {
      "capitulo": "15"
    },
    "emagrecimento": {
      "capitulo": "05"
    },
    "traqueostomizada": {
      "capitulo": "21"
    },
    "peritonite aguda": {
      "capitulo": "13"
    },
    "abertura ocular espontânea": {
      "capitulo": "08"
    },
    "boa perfusão periférica": {
      "capitulo": "11"
    },
    "outros traumatismos intracranianos": {
      "capitulo": "08"
    },
    "emeses": {
      "capitulo": "13"
    },
    "hipocorado": {
      "capitulo": "21"
    },
    "salinizado": {
      "capitulo": "11"
    },
    "dor abdominal": {
      "capitulo": "13"
    },
    "hemorragia subaracnoide proveniente do sifao e da bifurcacao da carotida": {
      "capitulo": "08"
    },
    "pouco comunicativo": {
      "capitulo": "21"
    },
    "apático": {
      "capitulo": "21"
    },
    "hemarecido": {
      "capitulo": "21"
    },
    "responsiva à estímulos dolorosos e aspirativos": {
      "capitulo": "21"
    }
  }
}