{
  "prontuario_id": 878,
  "text": "Às 17:25 HS: PROVENIENTE DO PA, CONSCIENTE, ORIENTADO, EUPNEICO, SEM QUEIXAS ALGICAS, AGUARDA TRATAMENTO CIRURGICO. ENF FLORENCE NIGHTINGALE, COREN XXXX. ATEROSCLEROSE DAS ARTERIAS DAS EXTREMIDADES. EVOLUÇAO DIA 25/01/10: RETORNOU DO CC AS 15:30H, ACORDADA, RESPONSIVA, EUPNEICA, EM REPOUSO NO LEITO  E COM RELATO DE ALGIA EM REG ABDOMINAL, APRESENTANDO INCISOES CIRURGICAS LIMPA E ACESSO VENOSO PERIFERICO MSD SALINIZADO. DIURESE ESPÓNTANEA PRESENTE. APRESENTA COTO MIE. ENFERMEIRA FLORENCE NIGHTINGALE, COREN XXX. COLELITIASE. Às 01:40: Paciente retorna do centro cirúrgico as 22h no POI de FX fêmur, encontra-se consciente, orientada, verbalizando, em repouso no leito, ssvv dentro dos parametros de normalidade, mantendo acesso venoso periférico em MSD permeavel salinizado no momento, curativo em fêmur D com presença de secreção hemática em grande quantidade, medicada conforme prescrição, segue sob cuidados de enfermagem. Enf FLORENCE NIGHTINGALE. FRATURA PERTROCANTERICA.",
  "entities": {
    "Organização Relacionada à Saúde": [
      "PA",
      "CC",
      "centro cirúrgico"
    ],
    "Abreviação": [
      "PA",
      "ENF",
      "CC",
      "MSD",
      "MIE",
      "POI",
      "Enf",
      "REG ABDOMINAL",
      "ssvv dentro dos parametros de normalidade",
      "fêmur D"
    ],
    "Achado": [
      "CONSCIENTE",
      "ORIENTADO",
      "EUPNEICO",
      "ACORDADA",
      "RESPONSIVA",
      "EUPNEICA",
      "SALINIZADO",
      "consciente",
      "orientada",
      "verbalizando",
      "permeavel",
      "salinizado",
      "QUEIXAS ALGICAS",
      "REPOUSO NO LEITO",
      "INCISOES CIRURGICAS LIMPA",
      "DIURESE ESPÓNTANEA",
      "repouso no leito",
      "ssvv dentro dos parametros de normalidade"
    ],
    "Negação": [
      "SEM"
    ],
    "Grupo Profissional ou Ocupacional": [
      "ENF",
      "ENFERMEIRA",
      "Enf"
    ],
    "Sinal ou Sintoma": [
      "ALGIA",
      "secreção hemática"
    ],
    "Localização ou Região Corporal": [
      "MSD",
      "COTO",
      "MIE",
      "REG ABDOMINAL"
    ],
    "Procedimento Terapêutico ou Preventivo": [
      "SALINIZADO",
      "salinizado",
      "curativo",
      "medicada",
      "TRATAMENTO CIRURGICO",
      "REPOUSO NO LEITO",
      "ACESSO VENOSO PERIFERICO",
      "repouso no leito",
      "acesso venoso periférico"
    ],
    "Doença ou Síndrome": [
      "COLELITIASE",
      "ATEROSCLEROSE DAS ARTERIAS DAS EXTREMIDADES"
    ],
    "Paciente ou Grupo com Deficiência": [
      "Paciente"
    ],
    "Conceito Temporal": [
      "POI"
    ],
    "Dispositivo Médico": [
      "curativo",
      "ACESSO VENOSO PERIFERICO",
      "acesso venoso periférico"
    ],
    "Produto Intelectual": [
      "prescrição"
    ],
    "Lesão ou Envenenamento": [
      "INCISOES CIRURGICAS LIMPA",
      "FRATURA PERTROCANTERICA"
    ],
    "Função Fisiológica": [
      "DIURESE ESPÓNTANEA"
    ],
    "Parte do Corpo, Órgão ou Componente Orgânico": [
      "fêmur D",
      "secreção hemática"
    ],
    "Conceito Qualitativo": [
      "grande quantidade"
    ],
    "Atividade de Assistência à Saúde": [
      "cuidados de enfermagem"
    ]
  },
  "labels": {
    "aterosclerose das arterias das extremidades": {
      "capitulo": "11"
    },
    "queixas algicas": {
      "capitulo": "21"
    },
    "incisoes cirurgicas limpa": {
      "capitulo": "22"
    },
    "secreção hemática": {
      "capitulo": "21"
    },
    "colelitiase": {
      "capitulo": "13"
    },
    "fratura pertrocanterica": {
      "capitulo": "15"
    },
    "algia": {
      "capitulo": "21"
    }
  }
}