{
  "prontuario_id": 984,
  "text": "Às 17:52: CONSCIENTE, ORIENTADA, EM REPOUSO NO LEITO, AINDA REFERE TONTURAS E ALGIA EM FLANCO ESQ, ACEITA DIETA OFERECIDA. MANTÉM ACESSO VENOSO EM MSE SALINIZADO, SVD COM DÉBITO. ENCAMINHADA PARA TOMOGRAFIA E ENTREGUE PC PARA OFTALMO. ENFª FLORENCE NIGHTINGALE, XXXX. TRAUMATISMOS MULTIPLOS NAO ESPECIFICADOS. Em 17/03/2008, 18 HORAS: SOLICITADO PELO DR VITAL BRASIL ECOCARDIOGRAMA. PORÉM, NÃO CONSEGUIMOS AGENDAR POR ESTAR FECHADO. FICANDO ASSIM PARA AMANHÃ CEDO AGENDAR. ENFERMEIRA FLORENCE NIGHTINGALE. SINDROME DE GUILLAIN BARRE. Às 15:37:  CORADO, ALERTA, AFEBRIL, COMUNICATIVO, APRESENTA-SE EM REPOUSO NO LEITO, ACEITANDO DIETA VIA ORAL, AVP EM MSD SALINIZADO, MANTÉM SINAIS VITAIS ESTAVÉIS, NÃO REFERI ALGIA, ELIMINAÇÕES FISIOLOGICAS PRESENTES E ESPONTANEAS, SEGUE SOB CUIDADOS DE ENFERMAGEM. HEMORRAGIA INTRACEREBRAL CEREBELAR. Às 11:30: ACORDADO, ABERTURA OCULAR ESPONTANEA, NAO RESPONSIVO. O2 COM NEVOA UMIDA EM TRAQUEO COM 6 L/MIN. ACESSO EM DORSO DE MAO ESQ, SALINIZANDO. SNE EM BI E NAO EM CURSO. UP EM COXINS. SEM UROPEN. MANTER PRECAUCAO DE CONTATO. AC ENF FLORENCE NIGHTINGALE. ABDOME AGUDO. Às 12:05h: Suspendo retirada de SVD, pois paciente inicia com hematúria, tracionou a sonda no período, mantenho exercício vesical para retirar sonda amanhã. Retiro acesso central em subclávia D. Enfª FLORENCE NIGHTINGALE. Coren XXXX. CISTICERCOSE DO SISTEMA NERVOSO CENTRAL. Às 10:30 hs: Afebril, normotenso, pupilas isocóricas, reagindo a estímulos de aspiração; monitorização cardíaca, pressão arterial, saturação e respiração; recebendo, por acesso venoso periférico em MMSE, Noradrenalina a 10 ml/h, Dormonid + Fentanil a 20 ml/h. TRAUMATISMOS MULTIPLOS NAO ESPECIFICADOS.",
  "entities": {
    "Achado": [
      "CONSCIENTE",
      "ORIENTADA",
      "SALINIZADO",
      "CORADO",
      "ALERTA",
      "AFEBRIL",
      "COMUNICATIVO",
      "ACORDADO",
      "RESPONSIVO",
      "SALINIZANDO",
      "Afebril",
      "normotenso",
      "REPOUSO NO LEITO",
      "ACEITA DIETA",
      "SVD COM DÉBITO",
      "ACEITANDO DIETA VIA ORAL",
      "SINAIS VITAIS ESTAVÉIS",
      "ELIMINAÇÕES FISIOLOGICAS PRESENTES E ESPONTANEAS",
      "ABERTURA OCULAR ESPONTANEA",
      "tracionou a sonda",
      "pupilas isocóricas",
      "reagindo a estímulos de aspiração"
    ],
    "Sinal ou Sintoma": [
      "TONTURAS",
      "ALGIA",
      "hematúria"
    ],
    "Abreviação": [
      "MSE",
      "PC",
      "OFTALMO",
      "ENFª",
      "DR",
      "AVP",
      "MSD",
      "TRAQUEO",
      "UP",
      "ENF",
      "Enfª",
      "MMSE",
      "FLANCO ESQ",
      "SVD COM DÉBITO",
      "DORSO DE MAO ESQ",
      "retirada de SVD",
      "subclávia D"
    ],
    "Localização ou Região Corporal": [
      "MSE",
      "MSD",
      "MMSE",
      "FLANCO ESQ",
      "DORSO DE MAO ESQ"
    ],
    "Procedimento Terapêutico ou Preventivo": [
      "SALINIZADO",
      "AVP",
      "ACESSO",
      "SALINIZANDO",
      "REPOUSO NO LEITO",
      "ACESSO VENOSO",
      "O2 COM NEVOA UMIDA",
      "PRECAUCAO DE CONTATO",
      "retirada de SVD",
      "exercício vesical",
      "acesso central",
      "acesso venoso periférico"
    ],
    "Procedimento Diagnóstico": [
      "TOMOGRAFIA",
      "ECOCARDIOGRAMA",
      "monitorização cardíaca"
    ],
    "Grupo Profissional ou Ocupacional": [
      "OFTALMO",
      "ENFª",
      "ENFERMEIRA",
      "ENF",
      "Enfª"
    ],
    "Negação": [
      "AFEBRIL",
      "NÃO",
      "NAO",
      "SEM",
      "Afebril"
    ],
    "Dispositivo Médico": [
      "AVP",
      "ACESSO",
      "SNE",
      "UROPEN",
      "ACESSO VENOSO",
      "acesso central",
      "acesso venoso periférico"
    ],
    "Doença ou Síndrome": [
      "UP",
      "SINDROME DE GUILLAIN BARRE",
      "HEMORRAGIA INTRACEREBRAL CEREBELAR",
      "ABDOME AGUDO",
      "CISTICERCOSE DO SISTEMA NERVOSO CENTRAL"
    ],
    "Paciente ou Grupo com Deficiência": [
      "paciente"
    ],
    "Função de Organismo": [
      "respiração",
      "pressão arterial"
    ],
    "Substância Farmacológica": [
      "Noradrenalina",
      "Dormonid",
      "Fentanil"
    ],
    "Hormônio": [
      "Noradrenalina"
    ],
    "Substância Química Orgânica": [
      "Dormonid",
      "Fentanil"
    ],
    "Lesão ou Envenenamento": [
      "TRAUMATISMOS MULTIPLOS"
    ],
    "Função Fisiológica": [
      "ELIMINAÇÕES FISIOLOGICAS PRESENTES E ESPONTANEAS"
    ],
    "Atividade de Assistência à Saúde": [
      "CUIDADOS DE ENFERMAGEM"
    ],
    "Conceito Quantitativo": [
      "6 L/MIN",
      "10 ml/h",
      "20 ml/h"
    ],
    "Parte do Corpo, Órgão ou Componente Orgânico": [
      "subclávia D"
    ]
  },
  "labels": {
    "sindrome de guillain barre": {
      "capitulo": "08"
    },
    "cisticercose do sistema nervoso central": {
      "capitulo": "08"
    },
    "svd com débito": {
      "capitulo": "11"
    },
    "tonturas": {
      "capitulo": "21"
    },
    "hemorragia intracerebral cerebelar": {
      "capitulo": "08"
    },
    "traumatismos multiplos": {
      "capitulo": "22"
    },
    "tracionou a sonda": {
      "capitulo": "21"
    },
    "algia": {
      "capitulo": "21"
    },
    "hematúria": {
      "capitulo": "08"
    },
    "abdome agudo": {
      "capitulo": "22"
    },
    "abertura ocular espontanea": {
      "capitulo": "21"
    }
  }
}