{
  "prontuario_id": 699,
  "text": "Às 08:00, 18/03/2010: Refere estar bem. Sem queixas álgicas. Diurese presente. Evacuação ausente. Comunicativo, confuso, não deambulando. Abcesso em região cervical com secreção purulenta. Permanece com curativo oclusivo. Permanece com uropen e fralda. Apresenta hiperemia em região sacra. Acesso venoso periférico em MSD com soroterapia. Ac de enfermagem Florence Nightingale. ABSCESSO RETROFARINGEO E PARAFARINGEO. Às 18h: Paciente consciente, orientado, comunicativo, em repouso no leito, POI de RMS, afebril, eupneico, AVP em MSE salinizado, curativo oclusivo em MIE seco e limpo externamente, segue permanecendo em jejum, diurese e evacuação ausentes. Sem queixas. Segue sob os cuidados da enfermagem.  Enf Florence Nightingale, Coren XXXX. FRATURA DA DIAFISE DA TIBIA. EVOLUÇAO DIA 17/02/10: Acordado, responsivo, eupneico, em repouso no leito e com relato de algia em reg mid com tala gessada aparentemente limpa. Acesso venoso periferico MSD salinizado, relata aceitaçao alimentar e diurese presente. Enfermeira Florence Nightingale. FRATURA DA EXTREMIDADE DISTAL DO RADIO.",
  "entities": {
    "Negação": [
      "Sem",
      "ausente",
      "não",
      "afebril",
      "ausentes"
    ],
    "Achado": [
      "Evacuação",
      "Comunicativo",
      "deambulando",
      "consciente",
      "orientado",
      "comunicativo",
      "afebril",
      "eupneico",
      "salinizado",
      "seco",
      "evacuação",
      "Acordado",
      "responsivo",
      "limpa",
      "Diurese presente",
      "repouso no leito",
      "e limpo",
      "aceitaçao alimentar",
      "diurese presente"
    ],
    "Função Fisiológica": [
      "Evacuação",
      "diurese",
      "evacuação",
      "Diurese presente",
      "diurese presente"
    ],
    "Sinal ou Sintoma": [
      "confuso",
      "hiperemia",
      "queixas",
      "algia",
      "queixas álgicas",
      "secreção purulenta"
    ],
    "Doença ou Síndrome": [
      "Abcesso",
      "ABSCESSO RETROFARINGEO E PARAFARINGEO"
    ],
    "Dispositivo Médico": [
      "uropen",
      "fralda",
      "AVP",
      "curativo oclusivo",
      "Acesso venoso periférico",
      "tala gessada",
      "Acesso venoso periferico"
    ],
    "Objeto Manufaturado": [
      "fralda"
    ],
    "Abreviação": [
      "MSD",
      "POI",
      "RMS",
      "AVP",
      "MSE",
      "MIE",
      "Enf",
      "reg mid"
    ],
    "Localização ou Região Corporal": [
      "MSD",
      "MSE",
      "MIE",
      "região cervical",
      "região sacra",
      "reg mid"
    ],
    "Procedimento Terapêutico ou Preventivo": [
      "soroterapia",
      "RMS",
      "AVP",
      "salinizado",
      "jejum",
      "curativo oclusivo",
      "Acesso venoso periférico",
      "repouso no leito",
      "tala gessada",
      "Acesso venoso periferico"
    ],
    "Grupo Profissional ou Ocupacional": [
      "enfermagem",
      "Enf",
      "Enfermeira"
    ],
    "Organização Relacionada à Saúde": [
      "enfermagem"
    ],
    "Paciente ou Grupo com Deficiência": [
      "Paciente"
    ],
    "Conceito Temporal": [
      "POI"
    ],
    "Conceito Espacial": [
      "externamente"
    ],
    "Substância Corporal": [
      "secreção purulenta"
    ],
    "Atividade de Assistência à Saúde": [
      "cuidados da enfermagem"
    ],
    "Lesão ou Envenenamento": [
      "FRATURA DA DIAFISE DA TIBIA",
      "FRATURA DA EXTREMIDADE DISTAL DO RADIO"
    ]
  },
  "labels": {
    "orientado": {
      "capitulo": "06"
    },
    "abscesso retrofaringeo e parafaringeo": {
      "capitulo": "01"
    },
    "acordado": {
      "capitulo": "06"
    },
    "fratura da extremidade distal do radio": {
      "capitulo": "15"
    },
    "queixas": {
      "capitulo": "21"
    },
    "evacuação": {
      "capitulo": "21"
    },
    "comunicativo": {
      "capitulo": "06"
    },
    "deambulando": {
      "capitulo": "06"
    },
    "fratura da diafise da tibia": {
      "capitulo": "15"
    },
    "confuso": {
      "capitulo": "06"
    },
    "eupneico": {
      "capitulo": "08"
    },
    "responsivo": {
      "capitulo": "06"
    },
    "consciente": {
      "capitulo": "06"
    },
    "repouso no leito": {
      "capitulo": "21"
    },
    "algia": {
      "capitulo": "21"
    },
    "secreção purulenta": {
      "capitulo": "01"
    },
    "abcesso": {
      "capitulo": "01"
    },
    "queixas álgicas": {
      "capitulo": "21"
    },
    "hiperemia": {
      "capitulo": "21"
    }
  }
}