{
  "prontuario_id": 318,
  "text": "À 01:00h: Apatico, sonolento, não verbalizando, com pupilas isocoricas fotorreagentes, com SNE em narina esquerda dieta 75 ml/h,  com traqueostomia secreção expessa com ausculta pulmonar com roncos difusos, abdomen plano e flacido com RHA +, com coletor urinár. TRAUMATISMOS MULTIPLOS NAO ESPECIFICADOS. Às 17:47: ORIENTADO, COMUNICATIVO, SEM QUEIXAS ALGICAS, MANTEM ACESSO VENOSO PERIFERICO EM MSD, ACEITANDO DIETA, DIURESE PRESENTE, AGUARDANDO CC. OUTRAS DOENCAS ESPECIFICADAS DO APARELHO DIGESTIVO. À 00:42hs: Paciente estável, consciênte, comunicativo; em repouso no leito, corado, eupneico; curativo em membro inferior direito apresentando pouca secreção purulenta; região do coto apresenta escará + epiremia moderada; não refere queixas algicas; sem inte. ERISIPELA. Às 18:32: PACIENTE APRESENTOU-SE FEBRIL NO INICIO DO PLANTAO DE 38.4, SENDO MEDICADO E COM MELHORA APOS, REALIZADO HEMOTRANSFUSAO DE 1 HEMOCOMPONENTE CONCENTRADO DE HEMACIAS, SEM INTERCORRENCIAS, SEM QUEIXAS. SEGUE SOB CUIDADOS. NEFRITE TUBULO INTERSTICIAL AGUDA. Às 10:59h: Acordado, alerta, responsivo, descorado, mucosas coradas e hidratadas. Apresenta abdome plano, flácido, indolor à palpação, RHA +. Mantém jejum para ecografia. Apresenta SNE tracionada e com o fio-guia, e segundo auxiliar de enfermagem, foi colocad. FRATURA SUBTROCANTERICA. Em 16/05/2007, 08:14h: Acordado, responsivo, hipocorado. Apresenta abdome escavado, flácido, RHA +. Mantém gastrostomia para alimentação. Diurese limpida em bom volume, não evacuou nas últimas 48h. NEOPLASIA MALIGNA DO ENCEFALO.",
  "entities": {
    "Sinal ou Sintoma": [
      "Apatico",
      "sonolento",
      "FEBRIL",
      "QUEIXAS",
      "descorado",
      "hipocorado",
      "escavado",
      "secreção expessa",
      "roncos difusos",
      "QUEIXAS ALGICAS",
      "pouca secreção purulenta",
      "epiremia moderada",
      "queixas algicas"
    ],
    "Negação": [
      "não",
      "SEM",
      "sem",
      "indolor",
      "não refere"
    ],
    "Achado": [
      "verbalizando",
      "ORIENTADO",
      "COMUNICATIVO",
      "estável",
      "consciênte",
      "comunicativo",
      "corado",
      "eupneico",
      "inte",
      "INTERCORRENCIAS",
      "Acordado",
      "alerta",
      "responsivo",
      "flácido",
      "evacuou",
      "RHA +",
      "ACEITANDO DIETA",
      "DIURESE PRESENTE",
      "repouso no leito",
      "pouca secreção purulenta",
      "Diurese limpida",
      "bom volume"
    ],
    "Parte do Corpo, Órgão ou Componente Orgânico": [
      "pupilas",
      "mucosas",
      "abdome"
    ],
    "Dispositivo Médico": [
      "SNE",
      "curativo",
      "fio-guia",
      "coletor urinár",
      "ACESSO VENOSO PERIFERICO"
    ],
    "Procedimento Terapêutico ou Preventivo": [
      "SNE",
      "dieta",
      "traqueostomia",
      "curativo",
      "MEDICADO",
      "HEMOTRANSFUSAO",
      "jejum",
      "coletor urinár",
      "ACESSO VENOSO PERIFERICO",
      "repouso no leito",
      "SNE tracionada",
      "gastrostomia para alimentação"
    ],
    "Abreviação": [
      "SNE",
      "MSD",
      "CC",
      "inte",
      "RHA +",
      "coletor urinár",
      "SNE tracionada"
    ],
    "Localização ou Região Corporal": [
      "abdomen",
      "MSD",
      "abdome",
      "membro inferior direito",
      "região do coto"
    ],
    "Paciente ou Grupo com Deficiência": [
      "Paciente",
      "PACIENTE"
    ],
    "Doença ou Síndrome": [
      "escará",
      "ERISIPELA",
      "DOENCAS ESPECIFICADAS DO APARELHO DIGESTIVO",
      "NEFRITE TUBULO INTERSTICIAL AGUDA"
    ],
    "Organização Relacionada à Saúde": [
      "PLANTAO"
    ],
    "Atividade de Assistência à Saúde": [
      "PLANTAO",
      "CUIDADOS"
    ],
    "Procedimento Diagnóstico": [
      "palpação",
      "ecografia",
      "ausculta pulmonar"
    ],
    "Função Fisiológica": [
      "evacuou",
      "DIURESE PRESENTE",
      "Diurese limpida"
    ],
    "Espaço ou Junção Corporal": [
      "narina esquerda"
    ],
    "Conceito Quantitativo": [
      "75 ml/h"
    ],
    "Substância Corporal": [
      "secreção expessa",
      "pouca secreção purulenta"
    ],
    "Lesão ou Envenenamento": [
      "TRAUMATISMOS MULTIPLOS",
      "FRATURA SUBTROCANTERICA"
    ],
    "Grupo Profissional ou Ocupacional": [
      "auxiliar de enfermagem"
    ],
    "Conceito Qualitativo": [
      "bom volume"
    ],
    "Processo Neoplásico": [
      "NEOPLASIA MALIGNA DO ENCEFALO"
    ]
  },
  "labels": {
    "orientado": {
      "capitulo": "06"
    },
    "flácido": {
      "capitulo": "15"
    },
    "neoplasia maligna do encefalo": {
      "capitulo": "02"
    },
    "acordado": {
      "capitulo": "06"
    },
    "nefrite tubulo intersticial aguda": {
      "capitulo": "03"
    },
    "epiremia moderada": {
      "capitulo": "15"
    },
    "escará": {
      "capitulo": "15"
    },
    "fratura subtrocanterica": {
      "capitulo": "15"
    },
    "comunicativo": {
      "capitulo": "06"
    },
    "escavado": {
      "capitulo": "15"
    },
    "doencas especificadas do aparelho digestivo": {
      "capitulo": "13"
    },
    "pouca secreção purulenta": {
      "capitulo": "21"
    },
    "traumatismos multiplos": {
      "capitulo": "22"
    },
    "alerta": {
      "capitulo": "06"
    },
    "responsivo": {
      "capitulo": "06"
    },
    "roncos difusos": {
      "capitulo": "12"
    },
    "descorado": {
      "capitulo": "15"
    },
    "sonolento": {
      "capitulo": "07"
    },
    "hipocorado": {
      "capitulo": "06"
    },
    "secreção expessa": {
      "capitulo": "21"
    },
    "erisipela": {
      "capitulo": "14"
    },
    "apatico": {
      "capitulo": "07"
    }
  }
}