{
  "prontuario_id": 923,
  "text": "Às 11:30Hrs: Cliente encaminhado ao centro de dx para exame de traqueoscopia, realizado troca de canula de TQT (metal), procedimento sem intercorrencia.  Enf° Florence Nightingale, Coren XXXX. SINDROME DO DESCONFORTO RESPIRATORIO DO ADULTO. Às 18:30: REPASSADO SNE SEM INTECORRÊNCIA NO PROCEDIMENTO, AGUARDA RAIO-X PARA VISUALIZAÇÃO  DA MESMA. SEPTICEMIA NAO ESPECIFICADA. Às 02HS: PCTE RETORNA DO CC, POI DE AMPUTAÇÃO DE 2º PDE, LUCIDO, COMUNICATIVO, EUPNEICO S/ QUEIXAS ALGICAS NO MOMENTO, ACESSO VENOSO PERIFÉRICO C/ SOROTERAPIA EM CURSO, MANTENDO CTVO EM PÉ ESQUERDO LIMPO E SECO EXTERNAMENTE, SEGUE SOB CUIDADOS. DIABETES MELLITUS INSULINO DEPENDENTE COM COMPLICACOES CIRCULATORIAS PERIFERICAS. Às 15h: Agitado, periodos de confusao, pouco responsivo e colaborativo, nao permite que se aproxime para realizar exame fisico, refere algia abdominal, na presença de familiares. Enf Florence Nightingale. TRAUMATISMO INTRACRANIANO. Às 22:30h: Ramsay 6, em VM modo controlado, PEEP 5, VC 460 ml, FiO2 a 60%, TOT nº 7,5 em rima 23, AVC em subclavia a direita com soroterapia + drogas vasoativas e sedação em curso (dormo, fenta, dopa, nora), repassada SNE e solicitado RX para avaliação, UP em grau lV em região de trocanter a direita + maleolos. diurese via SVD em media quantidade amarelo ouro. Enf Florence Nightingale, XXXX. PNEUMONIA BACTERIANA NAO ESPECIFICADA.",
  "entities": {
    "Paciente ou Grupo com Deficiência": [
      "Cliente",
      "PCTE"
    ],
    "Abreviação": [
      "metal",
      "Enf°",
      "PCTE",
      "CC",
      "POI",
      "S/",
      "CTVO",
      "Enf",
      "VM",
      "PEEP",
      "VC",
      "FiO2",
      "AVC",
      "dormo",
      "fenta",
      "dopa",
      "nora",
      "RX",
      "UP",
      "troca de canula de TQT",
      "REPASSADO SNE",
      "2º PDE",
      "TOT nº 7",
      "repassada SNE",
      "via SVD"
    ],
    "Procedimento Terapêutico ou Preventivo": [
      "procedimento",
      "SOROTERAPIA",
      "CTVO",
      "VM",
      "PEEP",
      "FiO2",
      "AVC",
      "soroterapia",
      "sedação",
      "troca de canula de TQT",
      "REPASSADO SNE",
      "ACESSO VENOSO PERIFÉRICO",
      "modo controlado",
      "drogas vasoativas",
      "repassada SNE"
    ],
    "Negação": [
      "sem",
      "SEM",
      "S/",
      "nao"
    ],
    "Achado": [
      "intercorrencia",
      "INTECORRÊNCIA",
      "LUCIDO",
      "COMUNICATIVO",
      "EUPNEICO",
      "LIMPO",
      "SECO",
      "diurese",
      "COMPLICACOES CIRCULATORIAS PERIFERICAS",
      "Ramsay 6",
      "amarelo ouro"
    ],
    "Grupo Profissional ou Ocupacional": [
      "Enf°",
      "Enf"
    ],
    "Procedimento Diagnóstico": [
      "RAIO-X",
      "RX",
      "exame de traqueoscopia",
      "exame fisico"
    ],
    "Organização Relacionada à Saúde": [
      "CC",
      "centro de dx"
    ],
    "Conceito Temporal": [
      "POI"
    ],
    "Dispositivo Médico": [
      "CTVO",
      "AVC",
      "ACESSO VENOSO PERIFÉRICO",
      "TOT nº 7",
      "via SVD"
    ],
    "Conceito Espacial": [
      "EXTERNAMENTE"
    ],
    "Atividade de Assistência à Saúde": [
      "CUIDADOS"
    ],
    "Sinal ou Sintoma": [
      "Agitado",
      "QUEIXAS ALGICAS",
      "periodos de confusao",
      "pouco responsivo e colaborativo",
      "algia abdominal"
    ],
    "Conceito Quantitativo": [
      "5",
      "60%",
      "23",
      "460 ml"
    ],
    "Parte do Corpo, Órgão ou Componente Orgânico": [
      "rima",
      "2º PDE",
      "PÉ ESQUERDO",
      "subclavia a direita"
    ],
    "Substância Farmacológica": [
      "dormo",
      "fenta",
      "dopa",
      "nora",
      "drogas vasoativas"
    ],
    "Substância Química Orgânica": [
      "dormo",
      "fenta",
      "dopa"
    ],
    "Doença ou Síndrome": [
      "UP",
      "SINDROME DO DESCONFORTO RESPIRATORIO DO ADULTO",
      "DIABETES MELLITUS INSULINO DEPENDENTE",
      "PNEUMONIA BACTERIANA"
    ],
    "Localização ou Região Corporal": [
      "maleolos",
      "região de trocanter a direita"
    ],
    "Função Fisiológica": [
      "diurese"
    ],
    "Grupo Familiar": [
      "de familiares"
    ],
    "Lesão ou Envenenamento": [
      "TRAUMATISMO INTRACRANIANO"
    ],
    "Conceito Qualitativo": [
      "grau lV",
      "media quantidade"
    ]
  },
  "labels": {
    "queixas algicas": {
      "capitulo": "06"
    },
    "traumatismo intracraniano": {
      "capitulo": "08"
    },
    "intecorrência": {
      "capitulo": "22"
    },
    "algia abdominal": {
      "capitulo": "13"
    },
    "periodos de confusao": {
      "capitulo": "06"
    },
    "amarelo ouro": {
      "capitulo": "21"
    },
    "ramsay 6": {
      "capitulo": "22"
    },
    "up": {
      "capitulo": "22"
    },
    "diabetes mellitus insulino dependente": {
      "capitulo": "05"
    },
    "complicacoes circulatorias perifericas": {
      "capitulo": "11"
    },
    "agitado": {
      "capitulo": "06"
    },
    "pneumonia bacteriana": {
      "capitulo": "12"
    },
    "sindrome do desconforto respiratorio do adulto": {
      "capitulo": "12"
    },
    "diurese": {
      "capitulo": "21"
    },
    "intercorrencia": {
      "capitulo": "22"
    },
    "pouco responsivo e colaborativo": {
      "capitulo": "06"
    }
  }
}