{
  "prontuario_id": 696,
  "text": "01HS PCTE LUCIDO, COMUNICATIVO, EUPNEICO EM AR AMBIENTE, S/ QUEIXAS ALGICAS, BOA ACEITAÇÃO DE DIETA, MANTENDO REPOUSO NO LEITO, MMII ELEVADOS MANTENDO ENFAIXADOS, ACESSO VENOSO PERIFÉRICO SALINIZADO, CTVO LIMPO E SECO EXTERNAMENTE, DIURESE PRESENTE, SEGUE SOB CUIDADOS VARIZES DOS MEMBROS INFERIORES COM ULCERA E INFLAMACAO. 22:30 PERMANECE EM RESPIRAÇÃO ESPONTÂNEA COM SUPORTE DE O2 EM NÉVOÁ ÚMIDA CONTÍNUA A 5L/MIN, GLASGOW 15, PUPILAS DISCRETAMENTE ANISOCÓRICAS D>E, CVC EM SUBCLÁVIA D COM TRIDIL 40ML/H, AUSCULTA PULMONAR COM RONCOS ESPARSOS, FAV EM MSE COM FRÊMITO, ABDOME GLOBOS E FLÁCIDO, RHA PRESENTES, SVD COM ANÚRIA. PRECAUÇÃO DE CONTATO PROFILATICAMENTE. MONITORADO COM PNI, CARDIOSCOPIA E OXIMETRIA DE PULSO. APRESENTA PERÍODOS DE AGRESSIVIDADE E AGITAÇÃO PSICOMOTORA (O CLIENTE TENTA INTIMIDAR E AGREDIR VERBALMENTE  A EQUIPE MULTIDISCIPLINAR) - DISCRETA MELHORA APÓS SEDATIVOS INTERMITENTES. CONCUSSAO CEREBRAL.",
  "entities": {
    "Abreviação": [
      "PCTE",
      "S/",
      "CTVO",
      "D&gt;E",
      "CVC",
      "FAV",
      "MSE",
      "GLOBOS",
      "SVD",
      "PNI",
      "SUBCLÁVIA D",
      "RHA PRESENTES"
    ],
    "Paciente ou Grupo com Deficiência": [
      "PCTE",
      "CLIENTE"
    ],
    "Achado": [
      "LUCIDO",
      "COMUNICATIVO",
      "LIMPO",
      "SECO",
      "FLÁCIDO",
      "EUPNEICO EM AR AMBIENTE",
      "BOA ACEITAÇÃO DE DIETA",
      "REPOUSO NO LEITO",
      "DIURESE PRESENTE",
      "RESPIRAÇÃO ESPONTÂNEA",
      "GLASGOW 15",
      "RHA PRESENTES",
      "DISCRETA MELHORA"
    ],
    "Negação": [
      "S/"
    ],
    "Localização ou Região Corporal": [
      "MMII",
      "MSE",
      "ABDOME",
      "MEMBROS INFERIORES"
    ],
    "Procedimento Terapêutico ou Preventivo": [
      "ENFAIXADOS",
      "CTVO",
      "CVC",
      "FAV",
      "SVD",
      "SEDATIVOS",
      "REPOUSO NO LEITO",
      "ACESSO VENOSO PERIFÉRICO SALINIZADO",
      "SUPORTE DE O2 EM NÉVOÁ ÚMIDA CONTÍNUA",
      "PRECAUÇÃO DE CONTATO PROFILATICAMENTE"
    ],
    "Dispositivo Médico": [
      "CTVO",
      "CVC",
      "SVD",
      "ACESSO VENOSO PERIFÉRICO SALINIZADO"
    ],
    "Conceito Espacial": [
      "EXTERNAMENTE"
    ],
    "Organização Relacionada à Saúde": [
      "CUIDADOS"
    ],
    "Atividade de Assistência à Saúde": [
      "CUIDADOS"
    ],
    "Doença ou Síndrome": [
      "ULCERA"
    ],
    "Função Patológica": [
      "INFLAMACAO"
    ],
    "Conceito Quantitativo": [
      "5L/MIN",
      "40ML/H"
    ],
    "Conceito Qualitativo": [
      "5L/MIN"
    ],
    "Substância Farmacológica": [
      "TRIDIL",
      "SEDATIVOS"
    ],
    "Sinal ou Sintoma": [
      "FRÊMITO",
      "GLOBOS",
      "ANÚRIA",
      "QUEIXAS ALGICAS",
      "PUPILAS DISCRETAMENTE ANISOCÓRICAS",
      "RONCOS ESPARSOS",
      "PERÍODOS DE AGRESSIVIDADE",
      "AGITAÇÃO PSICOMOTORA"
    ],
    "Procedimento Diagnóstico": [
      "MONITORADO",
      "PNI",
      "CARDIOSCOPIA",
      "AUSCULTA PULMONAR",
      "OXIMETRIA DE PULSO"
    ],
    "Conceito Temporal": [
      "INTERMITENTES"
    ],
    "Função Fisiológica": [
      "DIURESE PRESENTE"
    ],
    "Parte do Corpo, Órgão ou Componente Orgânico": [
      "SUBCLÁVIA D"
    ],
    "Grupo Profissional ou Ocupacional": [
      "EQUIPE MULTIDISCIPLINAR"
    ],
    "Lesão ou Envenenamento": [
      "CONCUSSAO CEREBRAL"
    ]
  },
  "labels": {
    "flácido": {
      "capitulo": "13"
    },
    "inflamacao": {
      "capitulo": "04"
    },
    "concussao cerebral": {
      "capitulo": "08"
    },
    "ulcera": {
      "capitulo": "14"
    },
    "comunicativo": {
      "capitulo": "06"
    },
    "anúria": {
      "capitulo": "16"
    },
    "roncos esparsos": {
      "capitulo": "12"
    },
    "frêmito": {
      "capitulo": "08"
    },
    "glasgow 15": {
      "capitulo": "V"
    },
    "períodos de agressividade": {
      "capitulo": "06"
    },
    "globos": {
      "capitulo": "13"
    },
    "pupilas discretamente anisocóricas": {
      "capitulo": "08"
    },
    "agitação psicomotora": {
      "capitulo": "06"
    }
  }
}