{
  "prontuario_id": 708,
  "text": "MANHÃ- A PEDIDO DE DR VITAL BRASIL, PACIENTE PERMANECE EM JEJUM, POR VOLTA DE 8:40 A FUNCIONÁRIA XXXX DA CENTRAL DE GUIAS ME INFORMA QUE OS MATERIAIS E CIRURGIA ESTÃO LIBERADO PELO CONVENIO. PORÉM PACIENTE NÃO ESTÁ NO MAPA CIRURGICO NEM NO MAPA CIRURGICO DE EMERGENCIA. TENTO CONTATO  VARIAS VEZES COM DR VITAL BRASIL DA ORTO E DR VITAL BRASIL SEM SUCESSO. POR VOLTA DE 12H ENTRO EM CONTATO COM O CC, DR VITAL BRASIL ESTÁ EM PROCEDIMENTO CIRURGICO, PEDE QUE ENTRE EM CONTATO COM DRA MARIA. ENTRO EM CONTATO COM DRA MARIA E INFORMO DA LIBERAÇÃO DOS MATERIAIS E CX A MESMA CIENTE. INFORMA QUE ENTRARA EM CONTATO COM DR VITAL BRASIL E SOLICITA QUE O PACIENTE PERMANEÇA EM JEJUM. ORIENTO PACIENTE QUANTO AO JEJUM. PASSO EM PLANTÃO.  ENFA FLORENCE NIGHTINGALE COREN XX XXXX. TRAUMATISMOS MULTIPLOS NAO ESPECIFICADOS.",
  "entities": {
    "Abreviação": [
      "DR",
      "ORTO",
      "CC",
      "DRA",
      "CX",
      "ENFA"
    ],
    "Paciente ou Grupo com Deficiência": [
      "PACIENTE"
    ],
    "Procedimento Terapêutico ou Preventivo": [
      "JEJUM",
      "CIRURGIA",
      "CX",
      "PROCEDIMENTO CIRURGICO"
    ],
    "Dispositivo Médico": [
      "MATERIAIS"
    ],
    "Organização Relacionada à Saúde": [
      "CONVENIO",
      "ORTO",
      "CC",
      "PLANTÃO"
    ],
    "Negação": [
      "NÃO",
      "NEM",
      "SEM"
    ],
    "Grupo Profissional ou Ocupacional": [
      "ORTO",
      "ENFA"
    ],
    "Achado": [
      "SUCESSO"
    ],
    "Atividade de Assistência à Saúde": [
      "ORIENTO",
      "PLANTÃO"
    ],
    "Lesão ou Envenenamento": [
      "TRAUMATISMOS MULTIPLOS"
    ]
  },
  "labels": {
    "traumatismos multiplos": {
      "capitulo": "22"
    }
  }
}