{
  "prontuario_id": 433,
  "text": "9:30 - Hx DIMINUIÇAO DA FORÇA MUSCULAR + DISARTRIA - ACOMPANHADA DO FILHO, CONSCIENTE, LUCIDA, EUPNEICA, COMUNICATIVA, DEAMBULA COM AUXILIO, SEM QUEIXAS ALGICAS NO MOMENTO, APRESENTA PUPILAS ISOCORICAS, PELE E MUCOSA CORADA E HIDRATADA, AUSCULTA PULMONAR COM MV +, RUIDOS DIFUSOS, ABDOMEM FLACIDO, RHA +, MANTEM ACESSO VENOSO PERIFERICO SALINIZADO EM MSD, RELATA BOA ACEITAÇAO DA DIETA OFERECIDA, DIURESE ESPONTANEA PRESENTE;  COMORBIDADES: HAS + DM; DESCONHECE ALERGIA A MEDICAÇÕES; AGUARDA CONDUTA MEDICA; OUTRAS HEMORRAGIAS INTRACEREBRAIS. 10H - DR VITAL BRASIL SOLICITA OXIMETRIA DE PULSO, ENTRO EM CONTATO COM SETORES DO HOSPITAL, PORÉM NÃO HÁ OXIMETRO , INFORMO DR VITAL BRASIL O MESMO CIENTE, INFORMOU QUE SOLICITARÁ GASOMETRIA ARTERIAL.  ENFA FLORENCE NIGHTINGALE, COREN XX XXXX. INSUFICIENCIA RESPIRATORIA AGUDA. 17h - 4º PO tx renal, acordado, lucido, comunicativo, eupneico, em ar ambiente, normotenso, normocorado, deambulando sem auxilio, aceitando dieta oferecida, abdomen flacido, curativo abdominal limpo e seco externamente, uso de cinta abdominal, diurese presente de coloração clara, nega queixas algicas, realizada medidas de conforto, segue sob cuidados.  Enf FLORENCE NIGHTINGALE, RIM TRANSPLANTADO. 15:45hrs paciente consciente, comunicativo, eupneico em aa, deambulando sem queixas algicas aceitando bem dieta oferecida via oral, apresenta leve edema em região maxilar á d. eliminações fisiologicas presentes TRAUMATISMO INTRACRANIANO.",
  "entities": {
    "Sinal ou Sintoma": [
      "DISARTRIA",
      "DIMINUIÇAO DA FORÇA MUSCULAR",
      "QUEIXAS ALGICAS",
      "RUIDOS DIFUSOS",
      "queixas algicas",
      "leve edema"
    ],
    "Grupo Familiar": [
      "FILHO"
    ],
    "Achado": [
      "CONSCIENTE",
      "LUCIDA",
      "EUPNEICA",
      "COMUNICATIVA",
      "CORADA",
      "HIDRATADA",
      "SALINIZADO",
      "acordado",
      "lucido",
      "comunicativo",
      "eupneico",
      "normotenso",
      "normocorado",
      "deambulando",
      "limpo",
      "seco",
      "consciente",
      "DEAMBULA COM AUXILIO",
      "PUPILAS ISOCORICAS",
      "MV +",
      "ABDOMEM FLACIDO",
      "RHA +",
      "BOA ACEITAÇAO DA DIETA",
      "DIURESE ESPONTANEA",
      "DESCONHECE ALERGIA A MEDICAÇÕES",
      "em ar ambiente",
      "aceitando dieta",
      "abdomen flacido",
      "diurese presente",
      "coloração clara",
      "eupneico em aa",
      "aceitando bem dieta oferecida via oral",
      "eliminações fisiologicas presentes"
    ],
    "Negação": [
      "SEM",
      "NÃO",
      "sem",
      "nega"
    ],
    "Parte do Corpo, Órgão ou Componente Orgânico": [
      "PELE",
      "MUCOSA"
    ],
    "Abreviação": [
      "MSD",
      "HAS",
      "DM",
      "DR",
      "ENFA",
      "Enf",
      "MV +",
      "RHA +",
      "4º PO",
      "tx renal",
      "eupneico em aa",
      "região maxilar á d"
    ],
    "Localização ou Região Corporal": [
      "MSD",
      "região maxilar á d"
    ],
    "Doença ou Síndrome": [
      "COMORBIDADES",
      "HAS",
      "DM",
      "HEMORRAGIAS INTRACEREBRAIS",
      "INSUFICIENCIA RESPIRATORIA AGUDA"
    ],
    "Organização Relacionada à Saúde": [
      "HOSPITAL"
    ],
    "Dispositivo Médico": [
      "OXIMETRO",
      "ACESSO VENOSO PERIFERICO",
      "curativo abdominal",
      "cinta abdominal"
    ],
    "Grupo Profissional ou Ocupacional": [
      "ENFA",
      "Enf"
    ],
    "Atividade de Assistência à Saúde": [
      "auxilio",
      "cuidados"
    ],
    "Conceito Espacial": [
      "externamente"
    ],
    "Paciente ou Grupo com Deficiência": [
      "paciente"
    ],
    "Procedimento Diagnóstico": [
      "AUSCULTA PULMONAR",
      "OXIMETRIA DE PULSO"
    ],
    "Procedimento Terapêutico ou Preventivo": [
      "ACESSO VENOSO PERIFERICO",
      "tx renal",
      "curativo abdominal",
      "cinta abdominal",
      "medidas de conforto"
    ],
    "Função Fisiológica": [
      "DIURESE ESPONTANEA",
      "diurese presente",
      "eliminações fisiologicas presentes"
    ],
    "Procedimento Laboratorial": [
      "GASOMETRIA ARTERIAL"
    ],
    "Conceito Temporal": [
      "4º PO"
    ],
    "Função Patológica": [
      "leve edema"
    ],
    "Lesão ou Envenenamento": [
      "TRAUMATISMO INTRACRANIANO"
    ]
  },
  "labels": {
    "boa aceitaçao da dieta": {
      "capitulo": "V"
    },
    "deambula com auxilio": {
      "capitulo": "15"
    },
    "leve edema": {
      "capitulo": "14"
    },
    "traumatismo intracraniano": {
      "capitulo": "08"
    },
    "ruidos difusos": {
      "capitulo": "12"
    },
    "abdomem flacido": {
      "capitulo": "15"
    },
    "insuficiencia respiratoria aguda": {
      "capitulo": "12"
    },
    "corada": {
      "capitulo": "14"
    },
    "normotenso": {
      "capitulo": "11"
    },
    "comorbidades": {
      "capitulo": "04"
    },
    "diminuiçao da força muscular": {
      "capitulo": "15"
    },
    "em ar ambiente": {
      "capitulo": "12"
    },
    "abdomen flacido": {
      "capitulo": "15"
    },
    "has": {
      "capitulo": "04"
    },
    "hemorragias intracerebrais": {
      "capitulo": "08"
    },
    "desconhece alergia a medicações": {
      "capitulo": "24"
    },
    "disartria": {
      "capitulo": "06"
    },
    "dm": {
      "capitulo": "05"
    }
  }
}