{
  "prontuario_id": 486,
  "text": "EVOLUÇAO DIA 08/02/10 Acordada, pouco responsiva, eupneica, apresentando sudorese, abdomen distendido  e tenso com incisao aberta e limpa, cuidadora refere ter alimentado pela manha e apresentou vomito apos, chamado para CC as 16h, informado DR VITAL BRASIL que veio e avaliou e comunicou que manter em jejum e ira realizar uma video a noite a seguir de ouitra cirurgia.Contida em MMSS para proteçao. Enfermeira FLORENCE NIGHTINGALE. SEPTICEMIA NAO ESPECIFICADA. 18:40h Paciente alerta, orientado, comunicativo, em repouso no leito, afebril, em ar ambiente, demais SSVV estáveis, AVP em MSD salinizado, curativo oclusivo em região abdominal limpo e seco externamente, curativo oclusivo em região inguinal limpo e seco externamente com dreno de suctor funcionante com pouca secreção sanguinolenta, curativo oclusivo em região femural esquerda limpo e seco externamente, curativo oclusivo em região dorsal do pé esquerdo limpo e seco externamente, mantendo jejum conforme orientação médica, SVD com 300 ml. Segue sob cuidados. FERIMENTO DO DORSO E DA PELVE.",
  "entities": {
    "Achado": [
      "Acordada",
      "eupneica",
      "limpa",
      "alerta",
      "orientado",
      "comunicativo",
      "afebril",
      "salinizado",
      "limpo",
      "seco",
      "repouso no leito",
      "em ar ambiente",
      "SSVV estáveis",
      "dreno de suctor",
      "secreção sanguinolenta"
    ],
    "Sinal ou Sintoma": [
      "sudorese",
      "tenso",
      "vomito",
      "pouco responsiva"
    ],
    "Localização ou Região Corporal": [
      "abdomen",
      "MSD",
      "DORSO",
      "região abdominal",
      "região inguinal",
      "região femural esquerda",
      "região dorsal do pé esquerdo"
    ],
    "Grupo Profissional ou Ocupacional": [
      "cuidadora",
      "Enfermeira"
    ],
    "Organização Relacionada à Saúde": [
      "CC"
    ],
    "Abreviação": [
      "CC",
      "DR",
      "AVP",
      "MSD",
      "SVD",
      "Contida em MMSS para proteçao",
      "SSVV estáveis"
    ],
    "Atividade de Assistência à Saúde": [
      "manter",
      "cuidados"
    ],
    "Procedimento Terapêutico ou Preventivo": [
      "jejum",
      "cirurgia",
      "AVP",
      "salinizado",
      "SVD",
      "repouso no leito",
      "curativo oclusivo",
      "dreno de suctor"
    ],
    "Paciente ou Grupo com Deficiência": [
      "Paciente"
    ],
    "Negação": [
      "afebril"
    ],
    "Dispositivo Médico": [
      "AVP",
      "SVD",
      "curativo oclusivo",
      "dreno de suctor"
    ],
    "Conceito Espacial": [
      "externamente"
    ],
    "Lesão ou Envenenamento": [
      "FERIMENTO",
      "incisao aberta"
    ],
    "Conceito Quantitativo": [
      "300 ml"
    ]
  },
  "labels": {
    "orientado": {
      "capitulo": "06"
    },
    "incisao aberta": {
      "capitulo": "22"
    },
    "vomito": {
      "capitulo": "13"
    },
    "seco": {
      "capitulo": "14"
    },
    "comunicativo": {
      "capitulo": "06"
    },
    "sudorese": {
      "capitulo": "21"
    },
    "pouco responsiva": {
      "capitulo": "06"
    },
    "limpo": {
      "capitulo": "14"
    },
    "alerta": {
      "capitulo": "06"
    },
    "salinizado": {
      "capitulo": "21"
    },
    "tenso": {
      "capitulo": "22"
    },
    "ferimento": {
      "capitulo": "22"
    },
    "secreção sanguinolenta": {
      "capitulo": "22"
    },
    "limpa": {
      "capitulo": "14"
    },
    "dreno de suctor": {
      "capitulo": "22"
    },
    "acordada": {
      "capitulo": "06"
    }
  }
}