{
  "prontuario_id": 629,
  "text": "PACIENTE INTERNA PARA TIMPANOPLASTIA EM ORELHA DIREITA. PROCEDIMENTO SEM INTERCORRÊNCIAS. RECEBE ALTA EM BOAS CONDIÇÕES. Paciente interna para tratamento cirúrgico fratura maléolo lateral. Procedimento realizado sem intercorrências. Boa evolução no pós operatório. Recebe alta em bom estado geral, com orientações, analgesia e retorno em ambulatório. Paciente com ICC, vem ao XXXX por dispnéia + tosse com escarro amarelado. Tratada para ICC com melhora da dispnéia. Rx de tórax sem BCP. Iniciado tratamento com amoxicilina para infecção respiratória. Recebe alta com plano de tratamento dociliar com amoxi VO. # DPOC --> ex-tabagista (parou há 4 meses) Veio à emergência por dispneía + tosse com escarro amarelado + febre. Realizado Rx de tórax sem consolidação. Iniciado manejo com nebulizações, hidrocortisona e bactrin. Paciente apresentou melhora do quadro. Recebe alta em bom estado geral, com plano de seguimento ambulatorial com seu médico.",
  "entities": {
    "Paciente ou Grupo com Deficiência": [
      "PACIENTE",
      "Paciente"
    ],
    "Procedimento Terapêutico ou Preventivo": [
      "TIMPANOPLASTIA",
      "PROCEDIMENTO",
      "Procedimento",
      "analgesia",
      "nebulizações",
      "tratamento cirúrgico",
      "Tratada para ICC",
      "plano de tratamento dociliar"
    ],
    "Negação": [
      "SEM",
      "sem"
    ],
    "Sinal ou Sintoma": [
      "INTERCORRÊNCIAS",
      "intercorrências",
      "dispnéia",
      "dispneía",
      "febre",
      "tosse com escarro amarelado"
    ],
    "Atividade de Assistência à Saúde": [
      "ALTA",
      "alta",
      "orientações"
    ],
    "Organização Relacionada à Saúde": [
      "ambulatório",
      "emergência"
    ],
    "Abreviação": [
      "ICC",
      "DPOC",
      "Tratada para ICC",
      "Rx de tórax",
      "amoxi VO"
    ],
    "Doença ou Síndrome": [
      "ICC",
      "DPOC",
      "infecção respiratória"
    ],
    "Antibiótico": [
      "amoxicilina",
      "amoxi VO"
    ],
    "Substância Química Orgânica": [
      "amoxicilina",
      "hidrocortisona"
    ],
    "Achado": [
      "ex-tabagista",
      "BOAS CONDIÇÕES",
      "Boa evolução",
      "bom estado geral",
      "melhora da dispnéia",
      "melhora do quadro"
    ],
    "Substância Farmacológica": [
      "hidrocortisona"
    ],
    "Hormônio": [
      "hidrocortisona"
    ],
    "Grupo Profissional ou Ocupacional": [
      "médico"
    ],
    "Parte do Corpo, Órgão ou Componente Orgânico": [
      "ORELHA DIREITA"
    ],
    "Lesão ou Envenenamento": [
      "fratura maléolo lateral"
    ],
    "Conceito Temporal": [
      "pós operatório"
    ],
    "Procedimento Diagnóstico": [
      "Rx de tórax"
    ],
    "Resultado Laboratorial ou de Teste": [
      "Rx de tórax"
    ]
  },
  "labels": {
    "febre": {
      "capitulo": "22"
    },
    "tosse com escarro amarelado": {
      "capitulo": "12"
    },
    "icc": {
      "capitulo": "04"
    },
    "dispneía": {
      "capitulo": "12"
    },
    "dispnéia": {
      "capitulo": "12"
    },
    "intercorrências": {
      "capitulo": "22"
    },
    "dpoc": {
      "capitulo": "24"
    },
    "infecção respiratória": {
      "capitulo": "12"
    },
    "ex-tabagista": {
      "capitulo": "24"
    },
    "fratura maléolo lateral": {
      "capitulo": "15"
    }
  }
}