{
  "prontuario_id": 243,
  "text": "     PACIENTE DE CONVÊNIO DO DR VITAL BRASIL, INTERNA PARA ESTUDO ELETROFISIOLÓGICO.      OBTEVE ALTA HOSPITALAR SOB ORIENTAÇÃO DO MÉDICO ASSISTENTE. PACIENTE COM CRM PRÉVIA, 4 SAFENAS HÁ 9 ANOS, COM ICC CLASSE III, DM2, HAS. INTERNA COM SÍNDROME CORONARIANA AGUDA SEM SUPRA ST, TIMI 4. REALIZADO CAT QUE EVIDENCIOU LESÃO CRÍTICA EM PONTE DE SAFENA SEQUENCIAL P/ DAE E DIAGONAL, DERRADEIRA. REALIZADO IMPLANTE DE STENT 3 X13 COM SUCESSO ANGIOGRÁFICO. PULSO FEM DIREITO SEM ALTERAÇÕES PACIENTE APRESENTOU BOA EVOLUÇÃO, EM CONDIÇÕES DE ALTA EM USO DAS MEDICAÇÕES ABAIXO E RETORNO AO SEU MÉDICO PARA SEGUIMENTO. Pcte internou para realização de estudo eletrofisiológico. Procedimento sem intercorrências. NOTA DE ALTA DA CTI   LIRIO, 59 ANOS # HAS - TTO IRREGULAR COM CAPTOPRIL # DISLIPIDEMICO SEM TTO PRÉVIO # HISTORIA FAMILIAR POSITIVA PARA CARDIOPATIA ISQUEMICA.  PACIENTE TEVE IAM COM SUPRADESNÍVEL SEGMENTO ST EM PARADE INFERIOR NO DIA 09/12/05  FOI ATENDIDO EM XXXX ONDE FEZ ESTREPTOQUINASE COM CRITÉRIOS DE REPERFUSÃO (MELHORA DA DOR , DESAPARECIMENTO DO SUPRA). NO DIA 23/12/05 O PACIENTE TEVE NOVO EPISÓDIO DE DOR RETROESTERNAL EM REPOUSO FOI LEVADO NOVAMENTE AO HOSPITAL ONDE O ECG MOSTROU NOVO SUPRA NO MESMO TERRITÓRIO COM SUPRA DE NO MÍNIMO 1 mm EM V5 E V6. NESTE OCASIÃO FOI TENTADO NOVEMENTE TROMBOLÍTICO ( ESTREPTOQUINASE) SEM CRITÉRIOS DE REPERFUSÃO E COM PERSISTENCIA DA ANGINA. FOI TRANSFERIDO PARA O XXXX NA MADRUGADA DO DIA 26/12/05. NA CHEGADA O ECG MOSTRAVA ONDA Q PAREDE INFERIOR + INVERSÃO ONDA T NAS MESMAS DERIVAÇÕES COM DISCRETO SUPRA EM V5 E V6. NA TENTATIVA DE DESLIGAR NITROGLICERIDA PACIENTE VOLTOU A TER ANGINA EM REPOUSO. REALIZADO CATETERISMO CARDIACO NO DIA 27/12/05  --> QUE MOSTROU OCLUSÃO TROMBÓTICA  DA CORONÁRIA DIREITA . FEITO ANGIOPLASTIA + STENT COM TIMI 3. TEM ALTA HOSPITALAR EM BOM ESTADO GERAL,  SEM DOR TORÁCICA,  EM USO DE METOPROLOL 50 MG 2X/DIA + CAPTOPRIL 50 3X/DIA PRAVASTATINA 40 MG + AAS 100 MG + TICLOPIDINA 250 MG 2X/DIA.   ORIENTAÇÕES NA ALTA PROCURAR ATENDIMENTO MÉDICO SE NOVOS EPISÓDIOS DE DOR NO PEITO FAZER USO DAS MEDICAÇÕES CONFORME PRESCRITO REVISÃO COM SEU CARDIOLOGISTA DENTRO DE 30 DIAS.",
  "entities": {
    "Paciente ou Grupo com Deficiência": [
      "PACIENTE",
      "Pcte"
    ],
    "Organização Relacionada à Saúde": [
      "CONVÊNIO",
      "CTI",
      "HOSPITAL"
    ],
    "Abreviação": [
      "DR",
      "CRM",
      "DM2",
      "HAS",
      "Pcte",
      "ECG",
      "AAS",
      "ICC CLASSE III",
      "SEQUENCIAL P/ DAE E DIAGONAL",
      "PULSO FEM DIREITO",
      "TTO IRREGULAR",
      "TTO PRÉVIO",
      "IAM COM SUPRADESNÍVEL SEGMENTO ST"
    ],
    "Atividade de Assistência à Saúde": [
      "ORIENTAÇÃO",
      "ALTA",
      "ORIENTAÇÕES",
      "ALTA HOSPITALAR",
      "ATENDIMENTO MÉDICO"
    ],
    "Procedimento Terapêutico ou Preventivo": [
      "CRM",
      "SAFENAS",
      "Procedimento",
      "TROMBOLÍTICO",
      "ANGIOPLASTIA",
      "STENT",
      "IMPLANTE DE STENT",
      "TTO PRÉVIO",
      "TENTATIVA DE DESLIGAR NITROGLICERIDA"
    ],
    "Conceito Temporal": [
      "PRÉVIA"
    ],
    "Conceito Quantitativo": [
      "4",
      "50",
      "50 MG",
      "40 MG",
      "100 MG",
      "250 MG"
    ],
    "Parte do Corpo, Órgão ou Componente Orgânico": [
      "SAFENAS",
      "PARADE INFERIOR"
    ],
    "Doença ou Síndrome": [
      "DM2",
      "HAS",
      "DISLIPIDEMICO",
      "ICC CLASSE III",
      "SÍNDROME CORONARIANA AGUDA SEM SUPRA ST",
      "CARDIOPATIA ISQUEMICA",
      "IAM COM SUPRADESNÍVEL SEGMENTO ST"
    ],
    "Procedimento Diagnóstico": [
      "CAT",
      "ECG",
      "ESTUDO ELETROFISIOLÓGICO",
      "estudo eletrofisiológico",
      "CATETERISMO CARDIACO"
    ],
    "Negação": [
      "SEM",
      "sem"
    ],
    "Sinal ou Sintoma": [
      "ALTERAÇÕES",
      "intercorrências",
      "EPISÓDIO DE DOR RETROESTERNAL",
      "EM REPOUSO",
      "PERSISTENCIA DA ANGINA",
      "ANGINA EM REPOUSO",
      "DOR TORÁCICA",
      "DOR NO PEITO"
    ],
    "Substância Farmacológica": [
      "MEDICAÇÕES",
      "CAPTOPRIL",
      "ESTREPTOQUINASE",
      "METOPROLOL",
      "PRAVASTATINA",
      "AAS",
      "TICLOPIDINA"
    ],
    "Grupo Profissional ou Ocupacional": [
      "MÉDICO",
      "CARDIOLOGISTA",
      "MÉDICO ASSISTENTE"
    ],
    "Aminoácido, Peptídeo ou Proteína": [
      "CAPTOPRIL",
      "ESTREPTOQUINASE"
    ],
    "Enzima": [
      "ESTREPTOQUINASE"
    ],
    "Dispositivo Médico": [
      "STENT",
      "IMPLANTE DE STENT"
    ],
    "Substância Química Orgânica": [
      "METOPROLOL",
      "PRAVASTATINA",
      "AAS",
      "TICLOPIDINA"
    ],
    "Resultado Laboratorial ou de Teste": [
      "TIMI 4",
      "SEQUENCIAL P/ DAE E DIAGONAL",
      "NOVO SUPRA",
      "MESMO TERRITÓRIO",
      "SUPRA DE NO MÍNIMO 1 mm EM V5 E V6",
      "ONDA Q PAREDE INFERIOR",
      "INVERSÃO ONDA T NAS MESMAS DERIVAÇÕES",
      "DISCRETO SUPRA EM V5 E V6",
      "OCLUSÃO TROMBÓTICA DA CORONÁRIA DIREITA",
      "TIMI 3"
    ],
    "Achado": [
      "SUCESSO ANGIOGRÁFICO",
      "BOA EVOLUÇÃO",
      "MELHORA DA DOR",
      "DESAPARECIMENTO DO SUPRA",
      "CRITÉRIOS DE REPERFUSÃO",
      "BOM ESTADO GERAL"
    ],
    "Atributo Clínico": [
      "PULSO FEM DIREITO"
    ]
  },
  "labels": {
    "icc classe iii": {
      "capitulo": "11"
    },
    "alterações": {
      "capitulo": "21"
    },
    "iam com supradesnível segmento st": {
      "capitulo": "11"
    },
    "sucesso angiográfico": {
      "capitulo": "11"
    },
    "critérios de reperfusão": {
      "capitulo": "11"
    },
    "síndrome coronariana aguda sem supra st": {
      "capitulo": "11"
    },
    "cardiopatia isquemica": {
      "capitulo": "11"
    },
    "angina em repouso": {
      "capitulo": "11"
    },
    "desaparecimento do supra": {
      "capitulo": "11"
    },
    "dor no peito": {
      "capitulo": "21"
    },
    "dm2": {
      "capitulo": "11"
    },
    "episódio de dor retroesternal": {
      "capitulo": "11"
    },
    "has": {
      "capitulo": "11"
    },
    "dislipidemico": {
      "capitulo": "11"
    },
    "intercorrências": {
      "capitulo": "21"
    },
    "persistencia da angina": {
      "capitulo": "11"
    },
    "dor torácica": {
      "capitulo": "21"
    }
  }
}