{
  "prontuario_id": 806,
  "text": "PTE PROCUROU EMERGENCIA DO XXXX POR DISPNEIA, ORTOPNEIA, DPN, EDEMA DE MMINFS QUE JA A AFLIGIAM HA MAIS DE 1 SEMANA. TEM TROCA DE V. MITRAL POR ESTENOSE EM 1997 (H XXXX), MARCAPASSO POR BAVT EM 1998 E EPISODIO DE ICC ASSOCIADA A BCP DA COMUNIDADE GRAVE COM PASSAGEM EM UTI HA CERCA DE 4 MESES. OBTEVE MELHORA RAPIDA DA DESCOMPENSAÇAO DA ICC (NAO ADERENCIA A MEDICAÇOES NO DOMICILIO?) SEM INTERCORRENCIAS. EM ESTUDO ECOCARDIOGRAFICO (ANEXO) MOSTROU ESTENOSE DE PROTESE MITRAL COM AREA VALVAR ESTIMADA EM 1 CM, GRADIENTE TRANSVALVAR MITRAL MAX DE 27 E MEDIO DE 12 COM PSAP DE 39 MMHG. PLANO: AVALIAÇÃO PARA TROCA DE PROTESE MITRAL NO HOSPITAL DE ORIGEM (XXXX). PACIENTE DIABÉTICO - HIPOGLICEMIANTE ORAL, HIPERTENSO, EX-TABAGISTA, IAM ANTERIOR 3/04 - ACTP SIC. INTERNA COM ANGINA REFRATÁRIA. REALIZADO CAT - LESÃO CD, VASO FINO CALIBRE, LESÃO CX E DAE SEM ALTERAÇÕES. SUBMETIDO A CIRURGIA DE REVASCULARIZAÇÃO MIOCÁRDICA - SAF PARA MARGINAL 1 E 2 E DP (ESTA COM POUCO FLUXO APÓS IMPLANTE). PACIENTE APRESENTA BOA EVOLUÇÃO NO PO, SEM INTERCORRÊNCIAS. APRESENTOU EPISÓDIO DE SANGRAMENTO ORIFICIAL - PEQUENO, SENDO AVALIADO PELA GASTRO E INDICADA AVALIAÇÃO AMBULATORIAL COM PROCTOLOGIA. RECEBE ALTA EM USO DAS MEDICAÇÕES ABAIXO E RETORNO PARA SEGUIMENTO. A PROCTO PARA INVESTIGAÇÃO.",
  "entities": {
    "Abreviação": [
      "PTE",
      "DPN",
      "MMINFS",
      "BAVT",
      "UTI",
      "IAM",
      "ACTP",
      "CAT",
      "CX",
      "DAE",
      "SAF",
      "PO",
      "GASTRO",
      "PROCTO",
      "EPISODIO DE ICC",
      "BCP DA COMUNIDADE",
      "MELHORA RAPIDA DA DESCOMPENSAÇAO DA ICC",
      "LESÃO CD"
    ],
    "Paciente ou Grupo com Deficiência": [
      "PTE",
      "PACIENTE"
    ],
    "Organização Relacionada à Saúde": [
      "EMERGENCIA",
      "UTI",
      "HOSPITAL"
    ],
    "Sinal ou Sintoma": [
      "DISPNEIA",
      "ORTOPNEIA",
      "DPN",
      "EDEMA",
      "INTERCORRENCIAS",
      "ALTERAÇÕES",
      "INTERCORRÊNCIAS",
      "ANGINA REFRATÁRIA"
    ],
    "Localização ou Região Corporal": [
      "MMINFS"
    ],
    "Função Patológica": [
      "ESTENOSE"
    ],
    "Doença ou Síndrome": [
      "ESTENOSE",
      "BAVT",
      "DIABÉTICO",
      "HIPERTENSO",
      "IAM",
      "BCP DA COMUNIDADE",
      "ESTENOSE DE PROTESE MITRAL"
    ],
    "Dispositivo Médico": [
      "MARCAPASSO"
    ],
    "Procedimento Terapêutico ou Preventivo": [
      "MARCAPASSO",
      "ACTP",
      "CAT",
      "IMPLANTE",
      "TROCA DE PROTESE MITRAL",
      "CIRURGIA DE REVASCULARIZAÇÃO MIOCÁRDICA",
      "AVALIAÇÃO AMBULATORIAL"
    ],
    "Negação": [
      "SEM"
    ],
    "Achado": [
      "EX-TABAGISTA",
      "MELHORA RAPIDA DA DESCOMPENSAÇAO DA ICC",
      "BOA EVOLUÇÃO"
    ],
    "Procedimento Diagnóstico": [
      "CAT",
      "ESTUDO ECOCARDIOGRAFICO"
    ],
    "Parte do Corpo, Órgão ou Componente Orgânico": [
      "CX",
      "SAF"
    ],
    "Conceito Temporal": [
      "PO"
    ],
    "Conceito Qualitativo": [
      "PEQUENO"
    ],
    "Grupo Profissional ou Ocupacional": [
      "GASTRO",
      "PROCTOLOGIA",
      "PROCTO"
    ],
    "Atividade de Assistência à Saúde": [
      "ALTA"
    ],
    "Substância Farmacológica": [
      "MEDICAÇÕES",
      "HIPOGLICEMIANTE ORAL"
    ],
    "Resultado Laboratorial ou de Teste": [
      "ESTENOSE DE PROTESE MITRAL",
      "AREA VALVAR ESTIMADA EM 1 CM",
      "LESÃO CD",
      "VASO FINO CALIBRE"
    ],
    "Conceito Quantitativo": [
      "AREA VALVAR ESTIMADA EM 1 CM"
    ]
  },
  "labels": {
    "melhora rapida da descompensaçao da icc": {
      "capitulo": "06"
    },
    "ortopneia": {
      "capitulo": "11"
    },
    "alterações": {
      "capitulo": "21"
    },
    "edema": {
      "capitulo": "12"
    },
    "hipertenso": {
      "capitulo": "11"
    },
    "angina refratária": {
      "capitulo": "11"
    },
    "dpn": {
      "capitulo": "11"
    },
    "intercorrências": {
      "capitulo": "21"
    },
    "iam": {
      "capitulo": "11"
    },
    "bcp da comunidade": {
      "capitulo": "06"
    },
    "diabético": {
      "capitulo": "05"
    },
    "estenose de protese mitral": {
      "capitulo": "11"
    },
    "intercorrencias": {
      "capitulo": "21"
    },
    "bavt": {
      "capitulo": "23"
    },
    "dispneia": {
      "capitulo": "12"
    },
    "estenose": {
      "capitulo": "11"
    }
  }
}