{
  "prontuario_id": 340,
  "text": "Paciente proveniente de XXXX, em acompanhamento no ambulatório de ICC do XXXX, internado na CTI desde 08/03 com quadro de insuficiência cardiaca refratária ao tratamento clínico e choque cardiogênico. Apesar das medidas terapêuticas adotadas, inserção de cateter de Swan-Ganz e uso de drogas vasoativas ( Dobutamina e Milrinona ), não apresentou melhora clinica. Foram tomadas medidas para inclusão do paciente em lista de transplante cardiaco, o qual não foi concretizado por falta de condições clínicas do mesmo. Complicou durante a internação com perda progressiva de função renal e infecção no local de introdução do cateter ( septicemia não especificada ). Dia 18/03 apresentou piora importante do quadro, necessitando de ventilação mecânica. Apesar das medidas instituidas em vigência da piora clínica, evoluiu para obito às 08:00 h de 19/03. PACIENTE COM CARDIOPATIA ISQUEMICA INTERNA PARA REALIZAÇÃO DE ANGIOPLASTIA COM IMPLANTE DE STENT EM ARTÉRIA DESCENDENTE ANTERIOR ESQUERDA REALIZADA COM SUCESSO, SEM INTERCORRÊNCIAS. RECEBE ALTA EM BOM ESTADO GERAL, COM RECOMENDAÇÕES.",
  "entities": {
    "Paciente ou Grupo com Deficiência": [
      "Paciente",
      "paciente",
      "PACIENTE"
    ],
    "Atividade de Assistência à Saúde": [
      "internado",
      "internação",
      "INTERNA",
      "ALTA",
      "RECOMENDAÇÕES"
    ],
    "Organização Relacionada à Saúde": [
      "CTI"
    ],
    "Abreviação": [
      "CTI",
      "ambulatório de ICC"
    ],
    "Substância Química Orgânica": [
      "Dobutamina",
      "Milrinona"
    ],
    "Substância Farmacológica": [
      "Dobutamina",
      "Milrinona",
      "drogas vasoativas"
    ],
    "Negação": [
      "não",
      "SEM"
    ],
    "Função Patológica": [
      "infecção",
      "choque cardiogênico"
    ],
    "Função de Organismo": [
      "obito"
    ],
    "Achado": [
      "SUCESSO",
      "melhora clinica",
      "piora clínica",
      "BOM ESTADO GERAL"
    ],
    "Sinal ou Sintoma": [
      "INTERCORRÊNCIAS"
    ],
    "Doença ou Síndrome": [
      "insuficiência cardiaca refratária",
      "choque cardiogênico",
      "CARDIOPATIA ISQUEMICA"
    ],
    "Procedimento Terapêutico ou Preventivo": [
      "inserção de cateter de Swan-Ganz",
      "transplante cardiaco",
      "ventilação mecânica",
      "ANGIOPLASTIA COM IMPLANTE DE"
    ],
    "Localização ou Região Corporal": [
      "local de introdução do cateter"
    ],
    "Parte do Corpo, Órgão ou Componente Orgânico": [
      "ARTÉRIA DESCENDENTE ANTERIOR ESQUERDA"
    ]
  },
  "labels": {
    "choque cardiogênico": {
      "capitulo": "11"
    },
    "piora clínica": {
      "capitulo": "21"
    },
    "insuficiência cardiaca refratária": {
      "capitulo": "11"
    },
    "infecção": {
      "capitulo": "22"
    },
    "cardiopatia isquemica": {
      "capitulo": "11"
    },
    "intercorrências": {
      "capitulo": "21"
    },
    "melhora clinica": {
      "capitulo": "21"
    }
  }
}