{
  "prontuario_id": 385,
  "text": "Paciente com estenose aórtica grave com colocação de prótese metálica em 15/08/02 e HAS, veio à E - XXXX com quadro de dor torácica e dispneia no dia 04/02/05 solicitada cintilografia miocárdica que demonstrou uma perfusão miocárdica normal e uma FE = 46 %. Paciente não apresentou novos sintomas durante a internação. Apresentou INR = 4,65, sendo ajustada anticoagulação. Recebe alta em bom estado geral, seguindo acompanhamento ambulatorial. Medicamentos na alta: 1) AAS 100 mg; 2) Enalapril 5 mg 1 x/dia; 3) Varfarina 2,5 mg 1 x/dia; Masculino, 75 anos, hipertenso, diabético, vasculopata periférico (amputação supracondiliana em membro inferior esquerdo), ex-tabagista, infarto do miocárdio em parede ântero-lateral extenso em 1999 com cateterismo cardíaco na época mostrando descendente anterior ocluída em terço médio, coronária direita com lesão de 70 % em terço médio, circunflexa sem lesões significativas e segundo ramo marginal com lesão de 80 % na origem, procura emergência do XXXX por apresentar há cerca de 48 horas vômitos e diarréia aquosa em grande quantidade. Durante episódios de vômito apresentou dor torácica atípica de curta duração sem alterações de eletrocardiograma e enzimas cardíacas. Refere que desde o infarto não apresentava dor torácica nem em repouso e nem aos esforços. Realizou cintilografia miocárdica que mostrou os mesmos resultados da anteriormente realizada em 1999 --- necrose em parede ântero-septo-apical com pequena área de isquemia perinecrose. Após resolução do quadro de gastroenterite que regrediu espontaneamente e com hidratação endovenosa, não apresentou novos episódios de dor. Dessa forma, recebe alta em bom estado geral, assintomático, sinais vitais estáveis, afebril, orientado quanto a cuidados, retorno ao seu médico e uso das medicações prescritas.",
  "entities": {
    "Paciente ou Grupo com Deficiência": [
      "Paciente"
    ],
    "Conceito Qualitativo": [
      "grave",
      "extenso",
      "grande quantidade"
    ],
    "Abreviação": [
      "HAS",
      "AAS",
      "FE = 46 %",
      "INR = 4 , 65"
    ],
    "Doença ou Síndrome": [
      "HAS",
      "hipertenso",
      "diabético",
      "infarto",
      "gastroenterite",
      "estenose aórtica",
      "vasculopata periférico",
      "infarto do miocárdio"
    ],
    "Sinal ou Sintoma": [
      "dispneia",
      "vômitos",
      "dor",
      "dor torácica",
      "apresentou novos sintomas",
      "diarréia aquosa",
      "em repouso",
      "aos esforços"
    ],
    "Negação": [
      "não",
      "sem",
      "nem",
      "assintomático",
      "afebril"
    ],
    "Conceito Temporal": [
      "durante",
      "x/dia",
      "anos",
      "Durante"
    ],
    "Atividade de Assistência à Saúde": [
      "internação",
      "alta",
      "retorno",
      "orientado quanto a cuidados"
    ],
    "Substância Farmacológica": [
      "Medicamentos",
      "AAS",
      "Enalapril",
      "Varfarina",
      "medicações"
    ],
    "Substância Química Orgânica": [
      "AAS",
      "Varfarina"
    ],
    "Aminoácido, Peptídeo ou Proteína": [
      "Enalapril"
    ],
    "Atributo Clínico": [
      "Masculino"
    ],
    "Achado": [
      "ex-tabagista",
      "assintomático",
      "afebril",
      "bom estado geral",
      "resolução do quadro",
      "sinais vitais estáveis"
    ],
    "Parte do Corpo, Órgão ou Componente Orgânico": [
      "circunflexa",
      "coronária direita",
      "segundo ramo marginal",
      "parede ântero-septo-apical"
    ],
    "Organização Relacionada à Saúde": [
      "emergência"
    ],
    "Procedimento Diagnóstico": [
      "eletrocardiograma",
      "cintilografia miocárdica",
      "cateterismo cardíaco"
    ],
    "Função de Órgão ou Tecido": [
      "necrose"
    ],
    "Grupo Profissional ou Ocupacional": [
      "médico"
    ],
    "Dispositivo Médico": [
      "colocação de prótese metálica"
    ],
    "Procedimento Terapêutico ou Preventivo": [
      "colocação de prótese metálica",
      "ajustada anticoagulação",
      "amputação supracondiliana",
      "cateterismo cardíaco",
      "hidratação endovenosa"
    ],
    "Resultado Laboratorial ou de Teste": [
      "perfusão miocárdica normal",
      "FE = 46 %",
      "INR = 4 , 65",
      "descendente anterior ocluída em terço médio",
      "coronária direita",
      "segundo ramo marginal",
      "mesmos resultados da anteriormente"
    ],
    "Conceito Quantitativo": [
      "100 mg",
      "5 mg",
      "2 , 5 mg",
      "70 %",
      "80 %"
    ],
    "Localização ou Região Corporal": [
      "membro inferior esquerdo",
      "parede ântero-lateral",
      "descendente anterior ocluída em terço médio"
    ],
    "Conceito Espacial": [
      "descendente anterior ocluída em terço médio",
      "terço médio"
    ],
    "Procedimento Laboratorial": [
      "enzimas cardíacas"
    ]
  },
  "labels": {
    "aos esforços": {
      "capitulo": "11"
    },
    "resolução do quadro": {
      "capitulo": "21"
    },
    "gastroenterite": {
      "capitulo": "13"
    },
    "ex-tabagista": {
      "capitulo": "24"
    },
    "diabético": {
      "capitulo": "5"
    },
    "estenose aórtica": {
      "capitulo": "11"
    },
    "apresentou novos sintomas": {
      "capitulo": "21"
    },
    "diarréia aquosa": {
      "capitulo": "13"
    },
    "infarto": {
      "capitulo": "11"
    },
    "vômitos": {
      "capitulo": "13"
    },
    "infarto do miocárdio": {
      "capitulo": "11"
    },
    "dispneia": {
      "capitulo": "12"
    },
    "hipertenso": {
      "capitulo": "5"
    },
    "has": {
      "capitulo": "24"
    },
    "vasculopata periférico": {
      "capitulo": "15"
    },
    "dor": {
      "capitulo": "21"
    },
    "dor torácica": {
      "capitulo": "21"
    }
  }
}