{
  "prontuario_id": 70,
  "text": "G1, SEM PRE-NATAL. INTERNA POR RUPTURA PREMATURA DE MEMBRANAS. EVOLUI PARA Parto Eutócico COM EPISIOTOMIA em 17/06/2007, 07:44 hs, RN APGAR 9/10, MASC, 3110 G, TS: O+, plaquetas: 223000, Ht: 38,6 %,  Hb:13,1; leuc: 13800, 2% bastões, VDRL: nr, HBSAG: nr, ANTI-HIV: nr, TOXO IGG e IGM: nr. RECEBE ALTA EM BOM ESTADO GERAL, SINAIS VITAIS ESTÁVEIS, MAMAS LACTANTES, LÓQUIOS FISIOLÓGICOS, ÚTERO CONTRAÍDO. # HIV+ 1991 (CD4 = 433 jun/07). # Bio + EFZ desde mar/03. # HCV gen 1 - Riba + PEG INF por 48 sem a partir de dez/04 - PCR negativo em jul/06. # Neurolues abr/03. Paciente vem encaminhado do ambulatório da zona 7 para realizar Eco de abdômen por suspeita de ascite, a qual não se confirmou, e Eco de joelho esquerdo para investigação de tendinite. Nas eco de abdômen se evidenciou hemangioma hepático e cálculo na pelve renal. Na Eco de joelho esquerdo há pequena quantidade de derrame coletado, não foi evidenciado alterações nos tendões. Plano pós-alta: retornar ao ambulatório da zona 7, manter tratamento com cloroquina e ibuprofeno, Betametasona IM 2 doses com intervalo de 10 dias.",
  "entities": {
    "Abreviação": [
      "G1",
      "RN",
      "MASC",
      "TS",
      "HIV+",
      "IM",
      "Ht : 38 , 6 %",
      "Hb : 13 , 1",
      "leuc : 13800",
      "VDRL : nr",
      "HBSAG : nr",
      "ANTI-HIV : nr",
      "TOXO IGG e IGM : nr",
      "HCV gen 1",
      "PEG INF",
      "PCR negativo",
      "Eco de abdômen",
      "Eco de joelho esquerdo",
      "eco de abdômen",
      "Eco de joelho"
    ],
    "Negação": [
      "SEM",
      "não",
      "não se confirmou"
    ],
    "Atividade de Assistência à Saúde": [
      "PRE-NATAL",
      "INTERNA",
      "ALTA",
      "retornar",
      "Plano pós-alta"
    ],
    "Grupo Etário": [
      "RN"
    ],
    "Atributo Clínico": [
      "MASC",
      "TS",
      "3110 G"
    ],
    "Atributo de Organismo": [
      "MASC"
    ],
    "Resultado Laboratorial ou de Teste": [
      "HIV+",
      "plaquetas : 223000",
      "Ht : 38 , 6 %",
      "Hb : 13 , 1",
      "leuc : 13800",
      "2% bastões",
      "VDRL : nr",
      "HBSAG : nr",
      "ANTI-HIV : nr",
      "TOXO IGG e IGM : nr",
      "CD4 = 433",
      "PCR negativo",
      "não se confirmou",
      "hemangioma hepático",
      "cálculo na pelve renal",
      "pequena quantidade de derrame coletado"
    ],
    "Doença ou Síndrome": [
      "Neurolues",
      "cálculo na pelve renal"
    ],
    "Paciente ou Grupo com Deficiência": [
      "Paciente"
    ],
    "Organização Relacionada à Saúde": [
      "ambulatório"
    ],
    "Substância Química Orgânica": [
      "cloroquina",
      "ibuprofeno",
      "Betametasona"
    ],
    "Substância Farmacológica": [
      "cloroquina",
      "ibuprofeno",
      "Betametasona"
    ],
    "Hormônio": [
      "Betametasona"
    ],
    "Procedimento Terapêutico ou Preventivo": [
      "IM",
      "Parto Eutócico"
    ],
    "Conceito Qualitativo": [
      "IM"
    ],
    "Função Patológica": [
      "RUPTURA PREMATURA DE MEMBRANAS"
    ],
    "Conceito Quantitativo": [
      "3110 G"
    ],
    "Achado": [
      "BOM ESTADO GERAL",
      "SINAIS VITAIS ESTÁVEIS",
      "MAMAS LACTANTES",
      "LÓQUIOS FISIOLÓGICOS",
      "ÚTERO CONTRAÍDO"
    ],
    "Vírus": [
      "HCV gen 1"
    ],
    "Procedimento Diagnóstico": [
      "Eco de abdômen",
      "Eco de joelho esquerdo",
      "eco de abdômen",
      "Eco de joelho"
    ],
    "Processo Neoplásico": [
      "hemangioma hepático"
    ]
  },
  "labels": {
    "lóquios fisiológicos": {
      "capitulo": "18"
    },
    "cálculo na pelve renal": {
      "capitulo": "13"
    },
    "útero contraído": {
      "capitulo": "18"
    },
    "neurolues": {
      "capitulo": "08"
    },
    "ruptura prematura de membranas": {
      "capitulo": "19"
    },
    "hcv gen 1": {
      "capitulo": "04"
    },
    "hemangioma hepático": {
      "capitulo": "13"
    }
  }
}