{
  "prontuario_id": 847,
  "text": "PACIENTE HIPERTENSA, VEIO AO HCPA ENCAMINHADA POR SEU MEDICO ASSISTENTE POR BRADICARDIA SINTOMATICA. NA CHEGADA, ECG COM BAV DE SEGUNDO GRAU 2:1 COM FREQUENCIA CARDIACA EM TORNO DE 40 bpm. REALIZADA COLOCAÇÃO DE MARCAPASSO DEFINITIVO EM 19/08/03, COM BOA EVOLUÇÃO APÓS. MARCAPASSO COM BOM FUNCIONAMENTO. RECEBE ALTA EM BOAS CONDIÇOES, COM ORIENTAÇAO DE MANTER ACOMPANHAMENTO COM SEU MEDICO E COM RETORNO EM DEZEMBRO/03 PARA REVISAO DO MARCAPASSO. # EX-TABAGISTA. # DPOC - ASMA. # HAS # DISLIPIDEMIA. # ACTP + STENT ACD SEG. MEDIO PROXIMAL FEV/2004. # CAT (08/2004): ADA 60 % SEG MEDIO; ACX OK; ACD 65 % SEG MEDIO. - - -  TRATAMENTO CLINICO NESTA INTERNAÇÃO. # SCA - AI. # ACTP + STENT ADA + 1a ADG. # REOPRO PE VEM A E-HCPA POR ANGINA INSTAVEL, TENDO SIDO SUBMETIDO A CATT. COM VISUALIZAÇÃO DE IMAGEM COMPATIVEL COM TROMBO EM ADA, SENDO SUBMETIDA A ACTP + STENT DE ADA E DIAGONAL. APOS A PASSAGEM DA GUIA APRESENTOU LINHA DE DISSECÇÃO RETROGRADA DA ADA ATÉ RAIZ DA AORTA, TENDO SIDO IMPLANTADOS OUTROS STENTS EM ADA, E ACX. O CONTROLE ECOCARDIO TE NAO EVIDENCIOU PROGRESSÃO DA DISSECÇÃO EM AORTA. POS-CONTROLE APOS 4 DIAS, TBEM NAO EVIDENCIOU PROGRESSÃO. TEM ALTA EM BOAS CONDIÇÕES, COM RETORNO AO AMBULATORIO DE ORIGEM (CPI) COM DRS VITAL BRASIL/VITAL BRASIL2. DEVE FAZER USO CONTINUADO DE TICLOPIDINA 1 MES.",
  "entities": {
    "Paciente ou Grupo com Deficiência": [
      "PACIENTE"
    ],
    "Doença ou Síndrome": [
      "HIPERTENSA",
      "DPOC",
      "ASMA",
      "HAS",
      "DISLIPIDEMIA",
      "SCA",
      "AI",
      "BAV DE SEGUNDO GRAU 2 : 1",
      "ANGINA INSTAVEL"
    ],
    "Abreviação": [
      "ECG",
      "DPOC",
      "HAS",
      "ACTP",
      "ACD",
      "CAT",
      "SCA",
      "AI",
      "ADA",
      "CATT",
      "ACX",
      "BAV DE SEGUNDO GRAU 2 : 1",
      "ADA 60 % SEG MEDIO",
      "ACX OK",
      "ACD 65 % SEG MEDIO",
      "1a ADG",
      "TROMBO EM ADA",
      "LINHA DE DISSECÇÃO RETROGRADA DA ADA ATÉ RAIZ DA AORTA",
      "ECOCARDIO TE"
    ],
    "Procedimento Diagnóstico": [
      "ECG",
      "CAT",
      "CATT",
      "ECOCARDIO TE"
    ],
    "Atividade de Assistência à Saúde": [
      "ALTA",
      "ORIENTAÇAO",
      "RETORNO",
      "INTERNAÇÃO",
      "POS-CONTROLE",
      "MANTER ACOMPANHAMENTO"
    ],
    "Grupo Profissional ou Ocupacional": [
      "MEDICO",
      "MEDICO ASSISTENTE"
    ],
    "Achado": [
      "EX-TABAGISTA",
      "PROGRESSÃO",
      "BOA EVOLUÇÃO",
      "MARCAPASSO COM BOM FUNCIONAMENTO",
      "BOAS CONDIÇOES",
      "LINHA DE DISSECÇÃO RETROGRADA DA ADA ATÉ RAIZ DA AORTA",
      "BOAS CONDIÇÕES"
    ],
    "Procedimento Terapêutico ou Preventivo": [
      "ACTP",
      "STENT",
      "CAT",
      "CATT",
      "COLOCAÇÃO DE MARCAPASSO DEFINITIVO",
      "REVISAO DO MARCAPASSO",
      "TRATAMENTO CLINICO",
      "IMPLANTADOS OUTROS STENTS"
    ],
    "Dispositivo Médico": [
      "STENT"
    ],
    "Parte do Corpo, Órgão ou Componente Orgânico": [
      "ACD",
      "ADA",
      "DIAGONAL",
      "ACX"
    ],
    "Conceito Espacial": [
      "DIAGONAL"
    ],
    "Negação": [
      "NAO"
    ],
    "Organização Relacionada à Saúde": [
      "AMBULATORIO"
    ],
    "Substância Química Orgânica": [
      "TICLOPIDINA"
    ],
    "Substância Farmacológica": [
      "TICLOPIDINA"
    ],
    "Resultado Laboratorial ou de Teste": [
      "BAV DE SEGUNDO GRAU 2 : 1",
      "FREQUENCIA CARDIACA EM TORNO DE 40 bpm",
      "ADA 60 % SEG MEDIO",
      "ACX OK",
      "ACD 65 % SEG MEDIO",
      "TROMBO EM ADA",
      "PROGRESSÃO DA DISSECÇÃO EM AORTA"
    ],
    "Atributo Clínico": [
      "FREQUENCIA CARDIACA EM TORNO DE 40 bpm"
    ],
    "Conceito Quantitativo": [
      "FREQUENCIA CARDIACA EM TORNO DE 40 bpm"
    ]
  },
  "labels": {
    "bav de segundo grau 2 : 1": {
      "capitulo": "08"
    },
    "has": {
      "capitulo": "11"
    },
    "dpoc": {
      "capitulo": "14"
    },
    "hipertensa": {
      "capitulo": "11"
    },
    "ai": {
      "capitulo": "04"
    },
    "ex-tabagista": {
      "capitulo": "24"
    },
    "progressão": {
      "capitulo": "21"
    },
    "linha de dissecção retrograda da ada até raiz da aorta": {
      "capitulo": "08"
    },
    "asma": {
      "capitulo": "12"
    },
    "angina instavel": {
      "capitulo": "11"
    },
    "sca": {
      "capitulo": "04"
    },
    "dislipidemia": {
      "capitulo": "05"
    },
    "actp + stent a cd seg. medio proximal fev/2004": {
      "capitulo": "11"
    }
  }
}