{
  "prontuario_id": 793,
  "text": "10:30 Horas. Paciente em internamento por quadro de dor abdominal - suspeita de de oclusão intestinal. História prévia de HAS, FA crônica, hipotireoidismo e RVM em 1994 - 3 safenas. Acordada, respondendo quando questionada, bastante gemente. Hipocorada e apática. SNG aberta sem débito. Permanece em monitorização cardíaca e oximetria de pulso contínua com PA: 1150/90 mmhg, FC:80 bpm. Perfusão periférica bastante diminuída. Apresentou pico de hipoglicemia sendo medicada conforme prescrição médica. Acesso em jugular externa D mantendo plano de soroterapia em curso. Lesão em MSD. Ulcera em MID grau III com presença de secreção serosanguinolenta e odor fétido. Relata algia abdominal- abdomen distendido e bastante doloroso á palpação.  Confecção de botas de algodão. Ausculta pulmonar com presença de MV+ e roncos difusos. SVD com baixo débito concentrado. * Encaminhada para Tomografia de abdomen e pelve- transporte sem intercorrências. às 10:49 paciente apresentou PCR iniciadas medidas de reanimação. Intubação + massagem cardíaca + droga.  2° parada ás 11:03 horas novamente realizada medidas de reanimação. 3° PCR ás 11:16 horas com sucesso. Segue em ventilação mecânica e monitorização cardíaca. Iniciada dopamina em BI, no momento mantendo 50ml/h. Aguarda vaga de UTI. Segue na sala de emergência. NEFRITE TÚBULO INTERSTICIAL AGUDA",
  "entities": {
    "Paciente ou Grupo com Deficiência": [
      "Paciente",
      "paciente"
    ],
    "Abreviação": [
      "HAS",
      "RVM",
      "PA",
      "FC",
      "MSD",
      "MID",
      "MV+",
      "SVD",
      "PCR",
      "BI",
      "UTI",
      "FA crônica",
      "SNG aberta",
      "jugular externa D"
    ],
    "Doença ou Síndrome": [
      "HAS",
      "hipotireoidismo",
      "hipoglicemia",
      "Ulcera",
      "PCR",
      "parada",
      "FA crônica",
      "NEFRITE TÚBULO INTERSTICIAL AGUDA"
    ],
    "Procedimento Terapêutico ou Preventivo": [
      "RVM",
      "medicada",
      "Acesso",
      "soroterapia",
      "SVD",
      "Intubação",
      "droga",
      "SNG aberta",
      "botas de algodão",
      "medidas de reanimação",
      "massagem cardíaca",
      "ventilação mecânica"
    ],
    "Conceito Quantitativo": [
      "3",
      "50ml/h",
      "1150/90 mmhg",
      "80 bpm"
    ],
    "Achado": [
      "Acordada",
      "débito",
      "MV+",
      "sucesso",
      "respondendo quando questionada"
    ],
    "Sinal ou Sintoma": [
      "Hipocorada",
      "apática",
      "intercorrências",
      "dor abdominal",
      "bastante gemente",
      "Perfusão periférica bastante diminuída",
      "secreção serosanguinolenta",
      "odor fétido",
      "algia abdominal-",
      "abdomen distendido",
      "bastante doloroso á palpação",
      "roncos difusos",
      "baixo débito concentrado"
    ],
    "Negação": [
      "sem"
    ],
    "Atributo Clínico": [
      "PA",
      "FC"
    ],
    "Atividade de Assistência à Saúde": [
      "medicada",
      "Encaminhada",
      "prescrição médica"
    ],
    "Dispositivo Médico": [
      "Acesso",
      "SVD"
    ],
    "Lesão ou Envenenamento": [
      "Lesão"
    ],
    "Localização ou Região Corporal": [
      "MSD",
      "MID",
      "abdomen",
      "pelve-"
    ],
    "Procedimento Diagnóstico": [
      "Tomografia",
      "monitorização cardíaca",
      "oximetria de pulso contínua",
      "Ausculta pulmonar"
    ],
    "Substância Farmacológica": [
      "droga",
      "dopamina"
    ],
    "Substância Biologicamente Ativa": [
      "dopamina"
    ],
    "Substância Química Orgânica": [
      "dopamina"
    ],
    "Dispositivo de Administração de Medicamento": [
      "BI"
    ],
    "Organização Relacionada à Saúde": [
      "UTI",
      "sala de emergência"
    ],
    "Produto Intelectual": [
      "prescrição médica"
    ],
    "Parte do Corpo, Órgão ou Componente Orgânico": [
      "jugular externa D"
    ],
    "Classificação": [
      "grau III"
    ],
    "Conceito Qualitativo": [
      "grau III"
    ],
    "Substância Corporal": [
      "secreção serosanguinolenta"
    ]
  },
  "labels": {
    "perfusão periférica bastante diminuída": {
      "capitulo": "11"
    },
    "hipocorada": {
      "capitulo": "06"
    },
    "pcr": {
      "capitulo": "22"
    },
    "hipotireoidismo": {
      "capitulo": "05"
    },
    "débito": {
      "capitulo": "12"
    },
    "secreção serosanguinolenta": {
      "capitulo": "13"
    },
    "lesão": {
      "capitulo": "15"
    },
    "ulcera": {
      "capitulo": "13"
    },
    "nefrite túbulo intersticial aguda": {
      "capitulo": "16"
    },
    "baixo débito concentrado": {
      "capitulo": "12"
    },
    "bastante gemente": {
      "capitulo": "06"
    },
    "mv+": {
      "capitulo": "09"
    },
    "parada": {
      "capitulo": "22"
    },
    "fa crônica": {
      "capitulo": "13"
    },
    "roncos difusos": {
      "capitulo": "09"
    },
    "bastante doloroso á palpação": {
      "capitulo": "13"
    },
    "dor abdominal": {
      "capitulo": "13"
    },
    "algia abdominal-": {
      "capitulo": "13"
    },
    "has": {
      "capitulo": "05"
    },
    "odor fétido": {
      "capitulo": "14"
    },
    "abdomen distendido": {
      "capitulo": "13"
    },
    "hipoglicemia": {
      "capitulo": "05"
    },
    "apática": {
      "capitulo": "06"
    }
  }
}