{
  "prontuario_id": 519,
  "text": "13:41 Hrs Cliente em glasgow 15, pupilas iso/foto +, respiração espontânea em aa, eupneica, face corada, mucosa oral hidratada, boa perfusão periférica, no leito com cabeceira elevada á 30°. Jejum por VO até 2° ordem. Mantem com monitorização de multiparametros ECG, PNI, SpO2, DVE aberta com debito presente ++ de aspecto seroso,   SNG aberta sem debito gástrico,  acesso venoso central duplo-lumen em sub-clavia ESQ com srt em curso gravitacional. Apresenta FO em região craniana limpa e seca, ausculta cardíaca rítmica e normofonética, ausculta pulmonar MV + sem R/A, abdomen plano e flácido com RHA +. Faz uso de SVD aberta com debito diurético presente ++ de coloração amarelo-claro, eliminação fecal ausente. Segue cuidados intensivos de enfermagem.  Enfermeira Florence Nightingale . DOENÇA PELO HIV RESULTANDO EM INFECÇÕES MÚLTIPLAS",
  "entities": {
    "Paciente ou Grupo com Deficiência": [
      "Cliente"
    ],
    "Parte do Corpo, Órgão ou Componente Orgânico": [
      "pupilas",
      "sub-clavia ESQ"
    ],
    "Achado": [
      "eupneica",
      "limpa",
      "seca",
      "rítmica",
      "normofonética",
      "plano",
      "flácido",
      "glasgow 15",
      "iso/foto +",
      "respiração espontânea em aa",
      "face corada",
      "mucosa oral hidratada",
      "boa perfusão periférica",
      "debito presente",
      "SNG aberta",
      "debito gástrico",
      "MV +",
      "RHA +",
      "debito diurético presente",
      "coloração amarelo-claro",
      "eliminação fecal"
    ],
    "Procedimento Diagnóstico": [
      "ECG",
      "monitorização de multiparametros",
      "ausculta cardíaca",
      "ausculta pulmonar"
    ],
    "Abreviação": [
      "ECG",
      "PNI",
      "SpO2",
      "FO",
      "R/A",
      "HIV",
      "iso/foto +",
      "respiração espontânea em aa",
      "Jejum por VO",
      "DVE aberta",
      "SNG aberta",
      "sub-clavia ESQ",
      "srt em curso gravitacional",
      "MV +",
      "RHA +",
      "SVD aberta"
    ],
    "Procedimento Terapêutico ou Preventivo": [
      "PNI",
      "SpO2",
      "cabeceira elevada á 30°",
      "Jejum por VO",
      "DVE aberta",
      "SNG aberta",
      "acesso venoso central duplo-lumen",
      "srt em curso gravitacional",
      "SVD aberta"
    ],
    "Negação": [
      "sem",
      "ausente"
    ],
    "Lesão ou Envenenamento": [
      "FO"
    ],
    "Sinal ou Sintoma": [
      "R/A",
      "aspecto seroso"
    ],
    "Localização ou Região Corporal": [
      "abdomen",
      "região craniana"
    ],
    "Grupo Profissional ou Ocupacional": [
      "Enfermeira"
    ],
    "Vírus": [
      "HIV"
    ],
    "Dispositivo Médico": [
      "SNG aberta",
      "acesso venoso central duplo-lumen"
    ],
    "Função Fisiológica": [
      "debito diurético presente",
      "eliminação fecal"
    ],
    "Atividade de Assistência à Saúde": [
      "cuidados intensivos de enfermagem"
    ],
    "Doença ou Síndrome": [
      "INFECÇÕES MÚLTIPLAS"
    ]
  },
  "labels": {
    "flácido": {
      "capitulo": "15"
    },
    "rha +": {
      "capitulo": "13"
    },
    "normofonética": {
      "capitulo": "08"
    },
    "iso/foto +": {
      "capitulo": "09"
    },
    "debito presente": {
      "capitulo": "21"
    },
    "debito gástrico": {
      "capitulo": "21"
    },
    "mv +": {
      "capitulo": "12"
    },
    "aspecto seroso": {
      "capitulo": "13"
    },
    "coloração amarelo-claro": {
      "capitulo": "14"
    },
    "hiv": {
      "capitulo": "04"
    },
    "plano": {
      "capitulo": "15"
    },
    "boa perfusão periférica": {
      "capitulo": "11"
    },
    "glasgow 15": {
      "capitulo": "22"
    },
    "rítmica": {
      "capitulo": "08"
    },
    "eupneica": {
      "capitulo": "12"
    },
    "infecções múltiplas": {
      "capitulo": "01"
    },
    "eliminação fecal": {
      "capitulo": "13"
    },
    "face corada": {
      "capitulo": "21"
    },
    "fo": {
      "capitulo": "09"
    },
    "debito diurético presente": {
      "capitulo": "21"
    },
    "limpa": {
      "capitulo": "14"
    },
    "respiração espontânea em aa": {
      "capitulo": "12"
    },
    "mucosa oral hidratada": {
      "capitulo": "21"
    },
    "sng aberta": {
      "capitulo": "13"
    },
    "r/a": {
      "capitulo": "21"
    },
    "seca": {
      "capitulo": "14"
    }
  }
}