{
  "prontuario_id": 933,
  "text": "15H RAMSAY 06, DEPENDENTE DE DVA, NORMOTÉRMICO (35,6c), NORMOCÁRDICO (97bpm), CURATIVO CEFÁLICO LIMPO E SECO,MANTEM CURATIVO COM COMPRESSA DE GAZE, ANISOCÓRICO D >  E, TRAQUEOSTOMIZADO EM VM MODO CMV, VC 540,FREQ 15, PEEP 5, FIO2 30, SPO2 95%, AUSCUTA PULMONAR COM RONCOS DIFUSOS, SECREÇÃO SEROHEMÁTICA AO REDOR DA INSERÇÃO DA TRAQUEOSTOMIA, CATETER VENOSO CENTRAL DUPLO LUME VIA SUBCLAVIA DIREITA INFUNDINDO NORADRENALINA 10ML/H, FENTANIL 5ML/H,MIDAZOLAN 20ML/H, ABDOMEN FLÁCIDO, RHA PRESENTES, SNE COM DIETATERAPIA, CURATIVO DE ALOJAMENTO DE CALOTA A DIREITA,LIMPO E SECO, SVD COM DIURESE EM AMARELO TENDENDO A COR LARANJA, ELIMINAÇÕES INTESTINAIS AUSENTES, REALIZADO MEDIDAS DE HIGIENE E CONFORTO, SEGUE EM REPOUSO NO LEITO COM CABECEIRA ELEVADA A 45º MONITORADO COM OXIMETRIA DE PULSO,AM EM RADIAL DIREITA,ECG E PVC SOB CUIDADOS INTENSIVOS.  # RETIRADO CURATIVO TIPO CAPACETE POR Doutor Vital Brazil (NEUROCIRURGIA), MANTEM CURATIVO COM COMPRESSA DE GAZE CONFORME ORIENTAÇÃO DO MESMO. # IRÁ TRANSFUNDIR TRÊS CONCENTRADOS DE HEMÁCIAS, CONFORME PRESCRIÇÃO.  Enfermeira Florence Nightingale  TRAUMATISMOS SUPERFICIAIS ENVOLVENDO A CABEÇA COM O PESCOÇO",
  "entities": {
    "Achado": [
      "NORMOTÉRMICO",
      "NORMOCÁRDICO",
      "LIMPO",
      "SECO",
      "TRAQUEOSTOMIZADO",
      "AMARELO",
      "MONITORADO",
      "RAMSAY 06",
      "DEPENDENTE DE DVA",
      "RHA PRESENTES",
      "ELIMINAÇÕES INTESTINAIS",
      "REPOUSO NO LEITO"
    ],
    "Conceito Quantitativo": [
      "97bpm",
      "540",
      "15",
      "5",
      "95%",
      "10ML/H",
      "5ML/H",
      "20ML/H",
      "35 , 6c"
    ],
    "Procedimento Terapêutico ou Preventivo": [
      "TRAQUEOSTOMIZADO",
      "VM",
      "PEEP",
      "FIO2",
      "SPO2",
      "TRAQUEOSTOMIA",
      "SVD",
      "CURATIVO CEFÁLICO",
      "CURATIVO COM COMPRESSA DE GAZE",
      "CATETER VENOSO CENTRAL DUPLO LUME",
      "SNE COM DIETATERAPIA",
      "CURATIVO DE ALOJAMENTO",
      "MEDIDAS DE HIGIENE E CONFORTO",
      "REPOUSO NO LEITO",
      "CABECEIRA ELEVADA A 45º",
      "CURATIVO TIPO CAPACETE",
      "TRANSFUNDIR TRÊS CONCENTRADOS DE HEMÁCIAS"
    ],
    "Abreviação": [
      "VM",
      "VC",
      "FREQ",
      "PEEP",
      "FIO2",
      "SPO2",
      "10ML/H",
      "20ML/H",
      "SVD",
      "ECG",
      "PVC",
      "DEPENDENTE DE DVA",
      "ANISOCÓRICO D &gt; E",
      "RHA PRESENTES",
      "SNE COM DIETATERAPIA"
    ],
    "Atributo Clínico": [
      "FREQ"
    ],
    "Substância Farmacológica": [
      "NORADRENALINA",
      "FENTANIL",
      "MIDAZOLAN"
    ],
    "Hormônio": [
      "NORADRENALINA"
    ],
    "Substância Química Orgânica": [
      "NORADRENALINA",
      "FENTANIL",
      "MIDAZOLAN"
    ],
    "Localização ou Região Corporal": [
      "ABDOMEN"
    ],
    "Dispositivo Médico": [
      "SVD",
      "CURATIVO CEFÁLICO",
      "CURATIVO COM COMPRESSA DE GAZE",
      "CATETER VENOSO CENTRAL DUPLO LUME",
      "CURATIVO DE ALOJAMENTO",
      "CURATIVO TIPO CAPACETE"
    ],
    "Função Fisiológica": [
      "DIURESE",
      "ELIMINAÇÕES INTESTINAIS"
    ],
    "Negação": [
      "AUSENTES"
    ],
    "Procedimento Diagnóstico": [
      "MONITORADO",
      "ECG",
      "PVC",
      "AUSCUTA PULMONAR",
      "OXIMETRIA DE PULSO"
    ],
    "Atividade de Assistência à Saúde": [
      "RETIRADO",
      "PRESCRIÇÃO",
      "CUIDADOS INTENSIVOS"
    ],
    "Grupo Profissional ou Ocupacional": [
      "NEUROCIRURGIA",
      "Enfermeira"
    ],
    "Organização Relacionada à Saúde": [
      "NEUROCIRURGIA"
    ],
    "Produto Intelectual": [
      "PRESCRIÇÃO"
    ],
    "Sinal ou Sintoma": [
      "ANISOCÓRICO D &gt; E",
      "RONCOS DIFUSOS",
      "TENDENDO A COR LARANJA"
    ],
    "Substância Corporal": [
      "SECREÇÃO SEROHEMÁTICA"
    ],
    "Parte do Corpo, Órgão ou Componente Orgânico": [
      "SUBCLAVIA DIREITA",
      "RADIAL DIREITA"
    ],
    "Lesão ou Envenenamento": [
      "TRAUMATISMOS SUPERFICIAIS ENVOLVENDO A CABEÇA COM O PESCOÇO"
    ]
  },
  "labels": {
    "tendendo a cor laranja": {
      "capitulo": "V"
    },
    "anisocórico d > e": {
      "capitulo": "08"
    },
    "traumatismos superficiais envolvendo a cabeça com o pescoço": {
      "capitulo": "22"
    },
    "monitorado": {
      "capitulo": "21"
    },
    "roncos difusos": {
      "capitulo": "12"
    },
    "repouso no leito": {
      "capitulo": "V"
    },
    "traqueostomizado": {
      "capitulo": "22"
    },
    "eliminações intestinais": {
      "capitulo": "13"
    },
    "amarelo": {
      "capitulo": "21"
    }
  }
}