{
  "prontuario_id": 279,
  "text": "PTE CI COM LESAO EM CAT PREVIO OBSERVANDO ESTENOSE SEGMENTAR PROXIMAL DE ADA. RETORNA PARA SER SUBMETIDA A ACTP + STENT EM ADA PROXIMAL EM PROCEDIMENTO COM SUCESSO ANGIOGRAFICO E LIVRE DE INTERCORRENCIAS . REALIZAMOS TBEM INVESTIGAÇÃO COMPLEMENTAR DE DOR LOMBAR E ABDOMINAL PREDOMINANTE A ESQUERDA PRESENTA COMO QUEIXA HA 2 MESES. REALIZOU TC DE COLUNA LOMBAR COM VISUALIZAÇÃO DE PROLAPSO DE DISCOS INTERVERTREBRAIS E REDUÇÃO DO CANAL MEDULAR  CENTRAL  E DE RECESSOS LATERAIS DE L4-L5. SEGUE INVESTIGAÇÃO E TRATAMENTO COM AMULATORIO DE ORIGEM. ALTA EM BOAS CONDICOES. DEVE FAZER USO DE TICLOPIDINA 250 MG DE 12/12H DURANTE 30 DIAS .",
  "entities": {
    "Paciente ou Grupo com Deficiência": [
      "PTE"
    ],
    "Abreviação": [
      "PTE",
      "CI",
      "CAT",
      "ACTP",
      "ESTENOSE SEGMENTAR PROXIMAL DE ADA",
      "ADA PROXIMAL",
      "TC DE COLUNA LOMBAR"
    ],
    "Doença ou Síndrome": [
      "CI"
    ],
    "Resultado Laboratorial ou de Teste": [
      "LESAO",
      "ESTENOSE SEGMENTAR PROXIMAL DE ADA",
      "VISUALIZAÇÃO DE PROLAPSO DE DISCOS INTERVERTREBRAIS",
      "REDUÇÃO DO CANAL MEDULAR CENTRAL",
      "RECESSOS LATERAIS DE L4-L5"
    ],
    "Procedimento Diagnóstico": [
      "CAT",
      "ACTP",
      "INVESTIGAÇÃO",
      "INVESTIGAÇÃO COMPLEMENTAR",
      "TC DE COLUNA LOMBAR"
    ],
    "Procedimento Terapêutico ou Preventivo": [
      "CAT",
      "ACTP",
      "PROCEDIMENTO",
      "TRATAMENTO"
    ],
    "Dispositivo Médico": [
      "STENT"
    ],
    "Atividade de Assistência à Saúde": [
      "PROCEDIMENTO",
      "INVESTIGAÇÃO",
      "ALTA"
    ],
    "Sinal ou Sintoma": [
      "DOR"
    ],
    "Localização ou Região Corporal": [
      "LOMBAR",
      "ABDOMINAL"
    ],
    "Substância Farmacológica": [
      "TICLOPIDINA"
    ],
    "Substância Química Orgânica": [
      "TICLOPIDINA"
    ],
    "Parte do Corpo, Órgão ou Componente Orgânico": [
      "ADA PROXIMAL"
    ],
    "Achado": [
      "SUCESSO ANGIOGRAFICO",
      "LIVRE DE INTERCORRENCIAS",
      "BOAS CONDICOES"
    ],
    "Conceito Espacial": [
      "A ESQUERDA"
    ],
    "Conceito Qualitativo": [
      "250 MG"
    ],
    "Conceito Quantitativo": [
      "250 MG"
    ]
  },
  "labels": {
    "livre de intercorrencias": {
      "capitulo": "11"
    },
    "ci": {
      "capitulo": "22"
    },
    "sucesso angiografico": {
      "capitulo": "11"
    },
    "dor": {
      "capitulo": "21"
    }
  }
}