{
  "prontuario_id": 816,
  "text": "PACIENTE HIPERTENSO DE LONGA DATA INTERNA POR QUADRO DE INSUFICIÊNCIA CARDÍACA DESCOMPENSADA , COM CONGESTÃO PULMONAR , ASSOCIADA A TAQUIARRITMIA ( FIBRILAÇÃO E FLUTTER ATRIAL ) COM RESPOSTA VENTRICULAR PERSISTENTEMENTE ELEVADA . REALIZADAS MEDIDAS PARA MANEJO DE IC COM BOA RESPOSTA AO TRATAMENTO , MELHORA IMPORTANTE DA CONGESTÃO . DEVIDO À ALTA RV E INSUFICIENCIA CARDÍACA COM PLANO DE CVE , FOI INICIADA ANTICOAGULAÇAO E  REALIZADO ECOCARDIOGRAMA TE QUE EVIDENCIOU FE 46% , HVE , COM HIPOCINESIA DIFUSA E ACINESIA ANTERO-SEPTA MÉDIO-APICAL , SEM TROMBOS INTRACAVITARIOS E COM AUMENTO DO AE ( 5,1CM )  .  NA EVOLUÇÃO , PORÉM , O PACIENTE APRESENTOU MELHORA REDUÇAO DA RESPOSTA VENTRICULAR COM BOM CONTROLE SEM NECESSIDADE DE CVE .  DEVIDO A SE TRATAR DE PRIMEIRO EPISÓDIO DE IC COM ECOCARDIO DO ULTIMO ANO SEM DISFUNÇAO VENTRICUALR E COM ACHADO SEGMENTAR NA ECOCARDIO , REALIZADA INVESTIGAÇAO PARA CARDIOPATIA ISQUEMICA COM CINTILO MIOCARDICA COM DIPIRIDAMOL . ESTE EXAME NÃO EVIDENCIOU ÁREA ISQUEMICA IMPORTANTE , COM POSSIVEL PEQUENA ÁREA ISQUEMICA ANTERIOR APENAS . COM MELHORA CLÍNICA E SEM ACHADOS SUGESTIVOS DE SUBSTRATO ISQUEMICO SIGNIFICATIVO , OPTADO POR OTIMIZAR TTO CLÍNICO E MANTER O PACIENTE ANTICOAGULADO . INICIADA ANTICOAGUAÇAO ORAL NO HOSPITAL , E O PACIENTE FARÁ AJUSTE EM REGIME AMBULATORIAL . RECEBE ALTA EM BOAS CONDIÇOES , COM MELHORA CLÍNICA IMPORTANTE DA IC E RV CONTROLADA .",
  "entities": {
    "Paciente ou Grupo com Deficiência": [
      "PACIENTE",
      "O PACIENTE"
    ],
    "Doença ou Síndrome": [
      "HIPERTENSO",
      "FIBRILAÇÃO",
      "IC",
      "INSUFICIÊNCIA CARDÍACA DESCOMPENSADA",
      "CONGESTÃO PULMONAR",
      "INSUFICIENCIA CARDÍACA",
      "CARDIOPATIA ISQUEMICA"
    ],
    "Atividade de Assistência à Saúde": [
      "INTERNA",
      "INVESTIGAÇAO",
      "MANTER",
      "ALTA"
    ],
    "Sinal ou Sintoma": [
      "TAQUIARRITMIA"
    ],
    "Abreviação": [
      "CVE",
      "HVE",
      "ECOCARDIO",
      "MANEJO DE IC",
      "ALTA RV",
      "ECOCARDIOGRAMA TE",
      "FE 46%",
      "NECESSIDADE DE CVE",
      "NA ECOCARDIO",
      "CINTILO MIOCARDICA",
      "OTIMIZAR TTO CLÍNICO",
      "MELHORA CLÍNICA IMPORTANTE DA IC",
      "RV CONTROLADA"
    ],
    "Procedimento Terapêutico ou Preventivo": [
      "ANTICOAGULAÇAO",
      "ANTICOAGULADO",
      "MANEJO DE IC",
      "OTIMIZAR TTO CLÍNICO",
      "ANTICOAGUAÇAO ORAL"
    ],
    "Resultado Laboratorial ou de Teste": [
      "HVE",
      "FE 46%",
      "HIPOCINESIA DIFUSA E ACINESIA ANTERO-SEPTA MÉDIO-APICAL",
      "5 , 1CM",
      "DISFUNÇAO VENTRICUALR E COM ACHADO SEGMENTAR",
      "EVIDENCIOU ÁREA ISQUEMICA IMPORTANTE",
      "POSSIVEL PEQUENA ÁREA ISQUEMICA ANTERIOR"
    ],
    "Negação": [
      "SEM",
      "NÃO"
    ],
    "Procedimento Diagnóstico": [
      "ECOCARDIO",
      "INVESTIGAÇAO",
      "EXAME",
      "ECOCARDIOGRAMA TE",
      "NA ECOCARDIO",
      "CINTILO MIOCARDICA"
    ],
    "Substância Farmacológica": [
      "DIPIRIDAMOL"
    ],
    "Substância Química Orgânica": [
      "DIPIRIDAMOL"
    ],
    "Organização Relacionada à Saúde": [
      "HOSPITAL"
    ],
    "Função Patológica": [
      "FLUTTER ATRIAL"
    ],
    "Achado": [
      "RESPOSTA VENTRICULAR PERSISTENTEMENTE ELEVADA",
      "BOA RESPOSTA AO TRATAMENTO",
      "MELHORA IMPORTANTE DA CONGESTÃO",
      "MELHORA REDUÇAO DA RESPOSTA VENTRICULAR",
      "BOM CONTROLE",
      "MELHORA CLÍNICA",
      "BOAS CONDIÇOES",
      "MELHORA CLÍNICA IMPORTANTE DA IC",
      "RV CONTROLADA"
    ],
    "Conceito Quantitativo": [
      "5 , 1CM"
    ]
  },
  "labels": {
    "taquiarritmia": {
      "capitulo": "11"
    },
    "hipertenso": {
      "capitulo": "11"
    },
    "cardiopatia isquemica": {
      "capitulo": "11"
    },
    "melhora reduçao da resposta ventricular": {
      "capitulo": "21"
    },
    "fibrilação": {
      "capitulo": "11"
    },
    "flutter atrial": {
      "capitulo": "11"
    },
    "melhora clínica importante da ic": {
      "capitulo": "21"
    },
    "insuficiência cardíaca descompensada": {
      "capitulo": "11"
    },
    "insuficiencia cardíaca": {
      "capitulo": "11"
    },
    "resposta ventricular persistentemente elevada": {
      "capitulo": "11"
    },
    "ic": {
      "capitulo": "11"
    },
    "congestão pulmonar": {
      "capitulo": "12"
    },
    "melhora importante da congestão": {
      "capitulo": "21"
    }
  }
}