{
  "prontuario_id": 833,
  "text": "Paciente com história de  HAS . Parada cardiorrespiratória em 1997 - Implante de CDI / marcapasso - trocou gerador em 2001 e 2004 .  Cateterismo 1997  coronárias normais .  Taquicardia ventricular de repetição  ablação em 07/2003 . ICC miocardiopatia dilatada  Chagas positivo .  ECO 2003 fe 40% , acinesia inferior . Insuficiência renal crônica  tto conservador  Hipotireoidismo / Impregnação cutânea / Alteração da difusão pulmonar - Secundário a Amiodarona .  Colelitíase sintomática - internação em 09/2004 . Interna por quadro clínico sugestivo de sindrome coronariana aguda - angina instável . ECG com ritmo de marcapasso / Enzimas e troponina normais . Realizou cintilografia miocardica : VE com grande aumento dos volumes sistólico e diastólico finais , acinesia infero-basal , latero-basal e apical , hipocinesia severa dos demais segmentos , com FE < 20% após estresse. Conclusão : necrose infero-latero-basal ( CD / CX ?) , sem evidencia de isquemia residual . Devido a importante hipocinesia , optou-se por realizar cateterismo diagnóstico , que demonstrou coronárias normais . Recebe alta em bom estado geral , compensado, com os seguintes :  Retorno ambulatorial com cardiologia e cirurgia .  Manter uso correto das medicações .  Retornar a emergência se necessário , trazendo sempre esta nota de alta .",
  "entities": {
    "Paciente ou Grupo com Deficiência": [
      "Paciente"
    ],
    "Abreviação": [
      "HAS",
      "ICC",
      "ECO",
      "ECG",
      "CD",
      "CX",
      "Implante de CDI",
      "fe 40%",
      "tto conservador",
      "VE com grande aumento dos volumes sistólico e diastólico finais",
      "FE &lt; 20% após estresse"
    ],
    "Doença ou Síndrome": [
      "HAS",
      "ICC",
      "Hipotireoidismo",
      "Parada cardiorrespiratória",
      "miocardiopatia dilatada",
      "Insuficiência renal crônica",
      "Colelitíase sintomática",
      "sindrome coronariana aguda",
      "angina instável"
    ],
    "Dispositivo Médico": [
      "marcapasso"
    ],
    "Procedimento Diagnóstico": [
      "Cateterismo",
      "ECO",
      "ECG",
      "cintilografia miocardica",
      "cateterismo diagnóstico"
    ],
    "Procedimento Terapêutico ou Preventivo": [
      "Cateterismo",
      "Implante de CDI",
      "trocou gerador",
      "tto conservador"
    ],
    "Parte do Corpo, Órgão ou Componente Orgânico": [
      "CD"
    ],
    "Negação": [
      "sem"
    ],
    "Atividade de Assistência à Saúde": [
      "alta",
      "Retorno",
      "Manter",
      "Retornar"
    ],
    "Achado": [
      "compensado",
      "coronárias normais",
      "Impregnação cutânea",
      "bom estado geral"
    ],
    "Organização Relacionada à Saúde": [
      "ambulatorial",
      "cardiologia",
      "cirurgia",
      "emergência"
    ],
    "Grupo Profissional ou Ocupacional": [
      "cardiologia",
      "cirurgia"
    ],
    "Substância Farmacológica": [
      "medicações"
    ],
    "Resultado Laboratorial ou de Teste": [
      "coronárias normais",
      "fe 40%",
      "acinesia inferior",
      "ritmo de marcapasso",
      "Enzimas e troponina normais",
      "VE com grande aumento dos volumes sistólico e diastólico finais",
      "hipocinesia severa dos demais segmentos",
      "FE &lt; 20% após estresse",
      "necrose infero-latero-basal"
    ],
    "Sinal ou Sintoma": [
      "Alteração da difusão pulmonar"
    ]
  },
  "labels": {
    "impregnação cutânea": {
      "capitulo": "14"
    },
    "alteração da difusão pulmonar": {
      "capitulo": "12"
    },
    "icc": {
      "capitulo": "03"
    },
    "sindrome coronariana aguda": {
      "capitulo": "11"
    },
    "has": {
      "capitulo": "21"
    },
    "angina instável": {
      "capitulo": "11"
    },
    "miocardiopatia dilatada": {
      "capitulo": "11"
    },
    "coronárias normais": {
      "capitulo": "11"
    },
    "hipotireoidismo": {
      "capitulo": "05"
    },
    "colelitíase sintomática": {
      "capitulo": "13"
    },
    "parada cardiorrespiratória": {
      "capitulo": "11"
    },
    "insuficiência renal crônica": {
      "capitulo": "16"
    }
  }
}