{
  "prontuario_id": 999,
  "text": "PACIENTE , 90 ANOS\n\n# NATURAL E PROCEDENTE DE CURITIBA . \n# APOSENTADA - EMPREGADA DOMESTICA\n\nHMA # PCTE REFERE HX DE NÓDULO ULCERADO EM ASA NASAL A ESQ , COM CRESCIMENTO RAPIDO E PROGRESSIVO HÁ 6 MESES. REFERE SANGRAMENTO LOCAL . \n\nHMP # NEGA COMORBIDADES . NEGA USO DE MEDICAMENTOS CONTINUOS .\nDEFICIENTE VISUAL .\n\nCHV # NEGA VICIOS .\n\nE . F # NÓDULO ULCERADO EM ASA NASAL ESQ , COM APROXIMADAMENTE 5 CM DE DIAMETRO .\n\nA # CBC ULCERADO ?? CEC ??\n\nP # ENCAIXO PUNCH PARA HOJE  R1 VITAL BRAZIL . \nRETORNO EM 45 DIAS NO AMBULATORIO DO CANCER DE PELE .\n\n\nR1 VITAL BRAZIL .\nDoutor Vital Brazil .\n \n \n \n ",
  "entities": {
    "Paciente ou Grupo com Deficiência": [
      "PACIENTE",
      "PCTE"
    ],
    "Grupo Profissional ou Ocupacional": [
      "APOSENTADA",
      "R1",
      "EMPREGADA DOMESTICA"
    ],
    "Abreviação": [
      "PCTE",
      "HMP",
      "CHV",
      "A",
      "CEC",
      "P",
      "R1",
      "ASA NASAL ESQ",
      "CBC ULCERADO"
    ],
    "Conceito Temporal": [
      "MESES",
      "HOJE",
      "CRESCIMENTO RAPIDO"
    ],
    "Achado": [
      "HMP",
      "CHV"
    ],
    "Negação": [
      "NEGA"
    ],
    "Doença ou Síndrome": [
      "COMORBIDADES",
      "VICIOS",
      "DEFICIENTE VISUAL"
    ],
    "Disfunção Mental ou Comportamental": [
      "VICIOS"
    ],
    "Procedimento Diagnóstico": [
      "A",
      "PUNCH"
    ],
    "Processo Neoplásico": [
      "CEC",
      "CBC ULCERADO"
    ],
    "Produto Intelectual": [
      "P"
    ],
    "Atividade de Assistência à Saúde": [
      "ENCAIXO",
      "PUNCH",
      "RETORNO"
    ],
    "Atividade Ocupacional": [
      "EMPREGADA DOMESTICA"
    ],
    "Função Patológica": [
      "NÓDULO ULCERADO",
      "SANGRAMENTO LOCAL"
    ],
    "Sinal ou Sintoma": [
      "NÓDULO ULCERADO",
      "CRESCIMENTO RAPIDO",
      "SANGRAMENTO LOCAL",
      "5 CM DE DIAMETRO"
    ],
    "Parte do Corpo, Órgão ou Componente Orgânico": [
      "ASA NASAL A ESQ",
      "ASA NASAL ESQ"
    ],
    "Conceito Qualitativo": [
      "CRESCIMENTO RAPIDO"
    ],
    "Procedimento Terapêutico ou Preventivo": [
      "MEDICAMENTOS CONTINUOS"
    ],
    "Substância Farmacológica": [
      "MEDICAMENTOS CONTINUOS"
    ],
    "Organização Relacionada à Saúde": [
      "AMBULATORIO DO CANCER DE PELE"
    ]
  },
  "labels": {
    "5 cm de diametro": {
      "capitulo": "09"
    },
    "crescimento rapido": {
      "capitulo": "02"
    },
    "sangramento local": {
      "capitulo": "21"
    },
    "nódulo ulcerado": {
      "capitulo": "14"
    },
    "cbc ulcerado": {
      "capitulo": "21"
    }
  }
}