{
  "prontuario_id": 546,
  "text": "S # angioplastia, implante de marcapasso (pacte assintomatico, ecg de repouso com bav de 2 grau mobitz 2), cat em agosto desse ano. Permaneceu em UTI por 10 dias. DM, HAS, DAC (rvm há 4 anos), dislipidemia. Em uso de insulina nph, metformina, sinvastatina 40mg 2 cp, carvedilol 6,25mg, losartana 50mg 2 x dia, AAS 100mg, clopidogrel 75mg. Tabagista há mais de 40 anos. Hoje fuma 8 cigarros por dia. Antes 2 carteiras/dia. Nega queixas.  O # LAboratorial 07/08/2013: HB: 12,9; Hematocrito 37,5; glicemia: 144; microalbuminuria: 2030,7 mg.  Cintilografia de perfusao miocardica agosto/13: Sem evidencias de isquemia miocardica, fç do VE preservada com hipocinesia septal. DIlatação do VE, FE VE em repouso 61%, FE VE apos estresse 60%.  CAt agosto 2013: reestenose de stent 70% em cd, Oclusao total de stent em ramo diagonalis, *angioplastia de agosto 2013 de cornoaria direita com stent.  O # EF cardiaco e abdominal sp. Pulmonar: ? em base E, PA: 150/75 mmhg.  P # retorno em 6 meses com exames prescrito, anlodipino e enalapril para tto de microalbuminuria.",
  "entities": {
    "Abreviação": [
      "S",
      "pacte",
      "cat",
      "UTI",
      "DM",
      "HAS",
      "DAC",
      "rvm",
      "AAS",
      "O",
      "CAt",
      "PA",
      "P",
      "2 cp",
      "HB : 12 , 9",
      "DIlatação do VE",
      "FE VE em repouso 61%",
      "FE VE apos estresse 60%",
      "reestenose de stent 70% em cd",
      "base E"
    ],
    "Achado": [
      "S",
      "assintomatico",
      "cornoaria direita com stent"
    ],
    "Procedimento Terapêutico ou Preventivo": [
      "angioplastia",
      "cat",
      "rvm",
      "CAt",
      "*angioplastia",
      "implante de marcapasso"
    ],
    "Paciente ou Grupo com Deficiência": [
      "pacte"
    ],
    "Negação": [
      "assintomatico",
      "Nega",
      "Sem"
    ],
    "Organização Relacionada à Saúde": [
      "UTI"
    ],
    "Doença ou Síndrome": [
      "DM",
      "HAS",
      "DAC",
      "dislipidemia",
      "microalbuminuria"
    ],
    "Substância Química Orgânica": [
      "metformina",
      "sinvastatina",
      "carvedilol",
      "AAS",
      "clopidogrel",
      "anlodipino"
    ],
    "Substância Farmacológica": [
      "metformina",
      "sinvastatina",
      "carvedilol",
      "losartana",
      "AAS",
      "clopidogrel",
      "anlodipino",
      "enalapril",
      "insulina nph"
    ],
    "Conceito Quantitativo": [
      "40mg",
      "50mg",
      "100mg",
      "75mg",
      "2 cp",
      "6 , 25mg",
      "8 cigarros por dia",
      "2 carteiras/dia",
      "150/75 mmhg"
    ],
    "Disfunção Mental ou Comportamental": [
      "Tabagista"
    ],
    "Comportamento Social": [
      "fuma"
    ],
    "Sinal ou Sintoma": [
      "queixas"
    ],
    "Atividade de Assistência à Saúde": [
      "O",
      "retorno",
      "exames prescrito"
    ],
    "Localização ou Região Corporal": [
      "abdominal",
      "base E"
    ],
    "Atributo Clínico": [
      "PA"
    ],
    "Produto Intelectual": [
      "P"
    ],
    "Procedimento Diagnóstico": [
      "ecg de repouso",
      "Cintilografia de perfusao miocardica"
    ],
    "Resultado Laboratorial ou de Teste": [
      "bav de 2 grau mobitz 2",
      "HB : 12 , 9",
      "Hematocrito 37 , 5",
      "glicemia : 144",
      "microalbuminuria : 2030 , 7 mg",
      "evidencias de isquemia miocardica",
      "DIlatação do VE",
      "FE VE em repouso 61%",
      "FE VE apos estresse 60%",
      "reestenose de stent 70% em cd",
      "Oclusao total de stent em ramo diagonalis"
    ],
    "Aminoácido, Peptídeo ou Proteína": [
      "insulina nph"
    ],
    "Conceito Temporal": [
      "2 x dia"
    ]
  },
  "labels": {
    "dac": {
      "capitulo": "11"
    },
    "tabagista": {
      "capitulo": "24"
    },
    "has": {
      "capitulo": "11"
    },
    "cornoaria direita com stent": {
      "capitulo": "11"
    },
    "microalbuminuria": {
      "capitulo": "05"
    },
    "dm": {
      "capitulo": "05"
    },
    "dislipidemia": {
      "capitulo": "05"
    }
  }
}