{
  "prontuario_id": 449,
  "text": "PACIENTE ENCAMINHADA PARA SALA DE EMERGÊNCIA APÓS APRESENTAR EPISTAXE VOLUMOSA E PICO HIPOTENSIVO. COMUNICADO PLANTÃO DA OTORRINO. CONFECÇÃO DE NOVO TAMPÃO. EVOLUIU PARA PCR ÁS  11:30 HORAS, INICIADA MANOBRAS DE REANIMAÇÃO E ENTUBAÇÃO OROTRAQUEAL - RETORNA APÓS 10 MINUTOS. HIPOCORADA. SEGUE EM VENTILAÇÃO MECÂNICA MODO: PCV, CONCENTRAÇÃO DE 02: 100% E PEEP: 5. MONITORIZAÇÃO CARDÍACA E OXIMETRIA DE PULSO CONTÍNUA, MANTENDO FC: 95 BPM, SAT: 95% E PA: 88/50 MMHG. ACESSO VENOSO PERÍFERICO MANTENDO PLANO DE SOROTERAPIA EM CURSO. INICIADO PLANO DE SEDAÇÃO EM BI. REALIZADA PASSAGEM DE SVD FOLEY N°16. PROCEDIMENTO REALIZADO SEM INTERCORRÊNCIAS - DÉBITO AMARELO CLARO. ENCAMINHADO PEDIDO DE SANGUE PARA BANCO DE SANGUE. ENCAMINHADO PEDIDO DE VAGA PARA UTI. SEGUE SOB OS CUIDADOS DA EQUIPE MULTIPROFISSIONAL. AGUARDA VAGA EM UTI. CHOQUE HIPOVOLEMICO.",
  "entities": {
    "Paciente ou Grupo com Deficiência": [
      "PACIENTE"
    ],
    "Atividade de Assistência à Saúde": [
      "ENCAMINHADA",
      "ENCAMINHADO",
      "CUIDADOS",
      "PEDIDO DE SANGUE"
    ],
    "Dispositivo Médico": [
      "TAMPÃO",
      "ACESSO VENOSO PERÍFERICO",
      "SVD FOLEY N°16"
    ],
    "Função Patológica": [
      "PCR"
    ],
    "Abreviação": [
      "PCR",
      "PCV",
      "FC",
      "SAT",
      "PA",
      "BI",
      "UTI",
      "95 BPM",
      "SVD FOLEY N°16"
    ],
    "Sinal ou Sintoma": [
      "HIPOCORADA",
      "INTERCORRÊNCIAS",
      "EPISTAXE VOLUMOSA",
      "PICO HIPOTENSIVO"
    ],
    "Procedimento Terapêutico ou Preventivo": [
      "PCV",
      "SEDAÇÃO",
      "MANOBRAS DE REANIMAÇÃO",
      "ENTUBAÇÃO OROTRAQUEAL",
      "VENTILAÇÃO MECÂNICA",
      "MONITORIZAÇÃO CARDÍACA",
      "OXIMETRIA DE PULSO CONTÍNUA",
      "ACESSO VENOSO PERÍFERICO",
      "SOROTERAPIA EM CURSO"
    ],
    "Atributo Clínico": [
      "FC",
      "SAT",
      "PA"
    ],
    "Conceito Quantitativo": [
      "95%",
      "PEEP : 5",
      "95 BPM",
      "88/50 MMHG"
    ],
    "Dispositivo de Administração de Medicamento": [
      "BI"
    ],
    "Negação": [
      "SEM"
    ],
    "Função de Organismo": [
      "DÉBITO"
    ],
    "Organização Relacionada à Saúde": [
      "UTI",
      "SALA DE EMERGÊNCIA",
      "PLANTÃO DA OTORRINO",
      "BANCO DE SANGUE",
      "EQUIPE MULTIPROFISSIONAL"
    ],
    "Procedimento Diagnóstico": [
      "MONITORIZAÇÃO CARDÍACA",
      "OXIMETRIA DE PULSO CONTÍNUA"
    ],
    "Achado": [
      "AMARELO CLARO"
    ],
    "Grupo Profissional ou Ocupacional": [
      "EQUIPE MULTIPROFISSIONAL"
    ],
    "Doença ou Síndrome": [
      "CHOQUE HIPOVOLEMICO"
    ]
  },
  "labels": {
    "choque hipovolemico": {
      "capitulo": "22"
    },
    "hipocorada": {
      "capitulo": "11"
    },
    "pico hipotensivo": {
      "capitulo": "11"
    },
    "intercorrências": {
      "capitulo": "21"
    },
    "pcr": {
      "capitulo": "21"
    },
    "epistaxe volumosa": {
      "capitulo": "10"
    },
    "amarelo claro": {
      "capitulo": "21"
    }
  }
}