{
  "prontuario_id": 382,
  "text": "LUCAS, 57 ANOS  # DM,  # HAS # DAC - iam em 2009 --> atc. # RVM em 2009. # ATC EM 2013 DE CD + IMPLANTE DE MP (bav de 2 grau mobitz 2) # Dislipidemia. # Tabagista há mais de 40 anos (10 CIGARROS /DIA).  # Em uso de insulina nph 26UI / 10UI, metformina 850MG CAFÉ / ALMOÇO / JANTA, ARADOIS 50MG /DIA, ANLODIPINA 5MG 12/12 HS, ENALAPRIL 20MG 12/12 HS, sinvastatina 80mg , SELOZOK 50MG /DIA, AAS 100mg,   S # NEGA PRECORDIALGIA, NEGA DISPNEIA, ORTOPNEIA, DPN. REFERE CLAUDICAÇÃO INTERMITENTE PARA MODERADOS ESFORÇOS.  O #  BEG, LOTE, CORADO, HIDRATADO, EUPNEICO, AFEBRIL, PA 150/80, FC 74, CP: SP, ACV: BCRNF 2T SS, AP: MV+ REDUZIDO DIFUSAMENTE, SEM RA, ABD: SP, MMII: PULSOS REDUZIDOS BILAT, SEM EDEMA OU EMPASTAMENTO,  LAB 13/01/14: GLICOSE 304; GLICOSE PÓS-PRANDIAL 309; CT 119; HDL 21; TG 214; TGO 19; HBA1C 6,70; CPK 72; CR 1,00; K 4,7; UR 30; MICROALBUMINURIA 24 HS (2114 MG); PU (GLICOSE ++; LEUC 2).  A #  DAC, HAS, DM.  P # AUMENTO SELOZOK PARA 100MG /DIA.  DEMAIS MANTIDO.  R3 CARDIO LUCAS, DR VITAL BRASIL.",
  "entities": {
    "Doença ou Síndrome": [
      "DM",
      "HAS",
      "DAC",
      "iam",
      "Dislipidemia",
      "bav de 2 grau mobitz 2"
    ],
    "Abreviação": [
      "DM",
      "HAS",
      "DAC",
      "iam",
      "atc",
      "RVM",
      "ATC",
      "CD",
      "AAS",
      "S",
      "DPN",
      "O",
      "BEG",
      "LOTE",
      "PA",
      "FC",
      "CP",
      "SP",
      "ACV",
      "AP",
      "RA",
      "ABD",
      "MMII",
      "LAB",
      "PU",
      "A",
      "P",
      "IMPLANTE DE MP",
      "bav de 2 grau mobitz 2",
      "MV+ REDUZIDO DIFUSAMENTE",
      "PULSOS REDUZIDOS BILAT",
      "CT 119",
      "HDL 21",
      "TG 214",
      "HBA1C 6 , 70",
      "CR 1 , 00",
      "K 4 , 7",
      "UR 30",
      "LEUC 2"
    ],
    "Procedimento Terapêutico ou Preventivo": [
      "atc",
      "RVM",
      "ATC",
      "IMPLANTE DE MP"
    ],
    "Parte do Corpo, Órgão ou Componente Orgânico": [
      "CD"
    ],
    "Disfunção Mental ou Comportamental": [
      "Tabagista"
    ],
    "Substância Química Orgânica": [
      "metformina",
      "ANLODIPINA",
      "sinvastatina",
      "AAS"
    ],
    "Substância Farmacológica": [
      "metformina",
      "ARADOIS",
      "ANLODIPINA",
      "ENALAPRIL",
      "sinvastatina",
      "SELOZOK",
      "AAS",
      "insulina nph"
    ],
    "Conceito Quantitativo": [
      "850MG",
      "5MG",
      "20MG",
      "80mg",
      "100mg",
      "150/80",
      "74",
      "10 CIGARROS /DIA",
      "26UI / 10UI"
    ],
    "Aminoácido, Peptídeo ou Proteína": [
      "ENALAPRIL",
      "insulina nph"
    ],
    "Achado": [
      "S",
      "BEG",
      "LOTE",
      "CORADO",
      "HIDRATADO",
      "EUPNEICO",
      "SP"
    ],
    "Negação": [
      "NEGA",
      "AFEBRIL",
      "SP",
      "SEM"
    ],
    "Sinal ou Sintoma": [
      "PRECORDIALGIA",
      "DISPNEIA",
      "ORTOPNEIA",
      "DPN",
      "AFEBRIL",
      "RA",
      "EDEMA",
      "EMPASTAMENTO",
      "CLAUDICAÇÃO INTERMITENTE",
      "MV+ REDUZIDO DIFUSAMENTE",
      "PULSOS REDUZIDOS BILAT"
    ],
    "Atividade de Assistência à Saúde": [
      "O",
      "AUMENTO SELOZOK"
    ],
    "Atributo Clínico": [
      "PA",
      "FC"
    ],
    "Localização ou Região Corporal": [
      "CP",
      "ACV",
      "AP",
      "ABD",
      "MMII"
    ],
    "Função Patológica": [
      "EDEMA"
    ],
    "Procedimento Diagnóstico": [
      "A"
    ],
    "Produto Intelectual": [
      "P"
    ],
    "Conceito Temporal": [
      "há mais de 40 anos",
      "12/12 HS"
    ],
    "Conceito Qualitativo": [
      "PARA MODERADOS ESFORÇOS"
    ],
    "Resultado Laboratorial ou de Teste": [
      "GLICOSE 304",
      "GLICOSE PÓS-PRANDIAL 309",
      "CT 119",
      "HDL 21",
      "TG 214",
      "TGO 19",
      "HBA1C 6 , 70",
      "CPK 72",
      "CR 1 , 00",
      "K 4 , 7",
      "UR 30",
      "MICROALBUMINURIA 24 HS ( 2114 MG",
      "GLICOSE ++",
      "LEUC 2"
    ],
    "Grupo Profissional ou Ocupacional": [
      "R3 CARDIO"
    ]
  },
  "labels": {
    "mv+ reduzido difusamente": {
      "capitulo": "11"
    },
    "ortopneia": {
      "capitulo": "12"
    },
    "tabagista": {
      "capitulo": "24"
    },
    "pulsos reduzidos bilat": {
      "capitulo": "08"
    },
    "precordialgia": {
      "capitulo": "21"
    },
    "dac": {
      "capitulo": "11"
    },
    "claudicação intermitente": {
      "capitulo": "15"
    },
    "iam": {
      "capitulo": "21"
    },
    "dispneia": {
      "capitulo": "12"
    },
    "dislipidemia": {
      "capitulo": "11"
    },
    "edema": {
      "capitulo": "21"
    },
    "has": {
      "capitulo": "11"
    },
    "bav de 2 grau mobitz 2": {
      "capitulo": "08"
    },
    "dm": {
      "capitulo": "11"
    },
    "empastamento": {
      "capitulo": "21"
    },
    "dpn": {
      "capitulo": "15"
    }
  }
}