{
  "prontuario_id": 762,
  "text": "AVALIAÇÃO NEFROLOGIA:  VEIO COM SR LUCAS > ESPOSO,  62 ANOS, DM COM DX HÁ POUCO MAIS DE 5 ANOS,  HAS CONCOMITANTE, HIPOTIREOIDISMO, DLP, AVE HÁ 2 ANOS (SIC), NEGA CARDIOPATIAS, IAM, GOTA, ACIDO ÚRICO, ITUS, AINES, EM USO DE M ENALAPRIL, METFORMINA, LEVOTIROXINA, OMEPRAZOL, SINVASTATINA, ANLODIPINO, CARVEDILOL, HCTZ, INSULINA.  ENCAMINHADA POR DRC.  PESO 66, ALT 160, PA 180/100.  MUCOSAS CORADAS. CPP LIVRES. PC SOPRO SISTOLICO, AREA MITRAL E AO, ABDOME GLOBOSO, RHA +, SEM VCM, SEM DOR, MEMBROS SEM EDEMA. DRC ESTAGIO 3. ORIENTAÇÕES GERAIS:  MELHOR CONTROLE DO DM E DA HAS. TROUXE EXAMES >>> 23/06/2015>> UREIA 56, GLICOSE 79, CR 1,22; K 5,3; RELAÇAO CRE/ALB 518; B NEG, HB GLIC 7,8; TFG ESTIMADA 46 ckd epi.",
  "entities": {
    "Atividade de Assistência à Saúde": [
      "AVALIAÇÃO",
      "ENCAMINHADA",
      "ORIENTAÇÕES GERAIS"
    ],
    "Grupo Profissional ou Ocupacional": [
      "NEFROLOGIA"
    ],
    "Organização Relacionada à Saúde": [
      "NEFROLOGIA"
    ],
    "Grupo Familiar": [
      "ESPOSO"
    ],
    "Abreviação": [
      "DM",
      "HAS",
      "DLP",
      "AVE",
      "IAM",
      "ITUS",
      "AINES",
      "HCTZ",
      "DRC",
      "PA",
      "PC",
      "VCM",
      "CPP LIVRES",
      "AREA MITRAL E AO",
      "RHA +",
      "DRC ESTAGIO 3",
      "CR 1 , 22",
      "K 5 , 3",
      "CRE/ALB 518",
      "B NEG",
      "HB GLIC 7 , 8"
    ],
    "Doença ou Síndrome": [
      "DM",
      "HAS",
      "HIPOTIREOIDISMO",
      "DLP",
      "AVE",
      "CARDIOPATIAS",
      "IAM",
      "GOTA",
      "ITUS",
      "DRC",
      "ACIDO ÚRICO",
      "DRC ESTAGIO 3"
    ],
    "Negação": [
      "NEGA",
      "SEM"
    ],
    "Substância Farmacológica": [
      "AINES",
      "ENALAPRIL",
      "METFORMINA",
      "LEVOTIROXINA",
      "OMEPRAZOL",
      "SINVASTATINA",
      "ANLODIPINO",
      "CARVEDILOL",
      "HCTZ",
      "INSULINA"
    ],
    "Aminoácido, Peptídeo ou Proteína": [
      "ENALAPRIL",
      "INSULINA"
    ],
    "Substância Química Orgânica": [
      "METFORMINA",
      "LEVOTIROXINA",
      "OMEPRAZOL",
      "SINVASTATINA",
      "ANLODIPINO",
      "CARVEDILOL"
    ],
    "Hormônio": [
      "INSULINA"
    ],
    "Atributo Clínico": [
      "PESO",
      "PA"
    ],
    "Conceito Quantitativo": [
      "66",
      "160",
      "180/100"
    ],
    "Localização ou Região Corporal": [
      "PC",
      "ABDOME",
      "MEMBROS",
      "AREA MITRAL E AO"
    ],
    "Sinal ou Sintoma": [
      "GLOBOSO",
      "VCM",
      "DOR",
      "EDEMA",
      "SOPRO SISTOLICO"
    ],
    "Função Patológica": [
      "EDEMA"
    ],
    "Procedimento Laboratorial": [
      "EXAMES"
    ],
    "Achado": [
      "MUCOSAS CORADAS",
      "CPP LIVRES",
      "RHA +"
    ],
    "Resultado Laboratorial ou de Teste": [
      "UREIA 56",
      "GLICOSE 79",
      "CR 1 , 22",
      "K 5 , 3",
      "CRE/ALB 518",
      "B NEG",
      "HB GLIC 7 , 8",
      "TFG ESTIMADA 46 ckd epi"
    ]
  },
  "labels": {
    "drc estagio 3": {
      "capitulo": "11"
    },
    "sopro sistolico": {
      "capitulo": "11"
    },
    "itus": {
      "capitulo": "21"
    },
    "hipotireoidismo": {
      "capitulo": "05"
    },
    "gota": {
      "capitulo": "17"
    },
    "acido úrico": {
      "capitulo": "21"
    },
    "cardiopatias": {
      "capitulo": "11"
    },
    "iam": {
      "capitulo": "21"
    },
    "ave": {
      "capitulo": "21"
    },
    "mucosas coradas": {
      "capitulo": "21"
    },
    "dlp": {
      "capitulo": "05"
    },
    "edema": {
      "capitulo": "15"
    },
    "has": {
      "capitulo": "05"
    },
    "globoso": {
      "capitulo": "16"
    },
    "dor": {
      "capitulo": "21"
    },
    "dm": {
      "capitulo": "05"
    }
  }
}