{
  "prontuario_id": 946,
  "text": "Lucas , 69 anos,  acompanhamento DM 2. Diagnostico de Dm 2 há 16 anos - inciou o uso da insulina há 10 anos - esta bem adaptada a droga.  Nega poliuria, polidipsia, polifagia.  Nega outras queixas.  Medicamentos :  sinvastatina 20 mg - um cp a noite, espironolactona 25 mg : 1 cp pela manha,  furosemida - 40 mg,  AAS  - 100 mg - 1 cp apos o almoço,  Insulina NPH : 30 U pela manha e 30 U a noite,  Levotiroxina 100 mcg : 1 cp pela manha,  Glibenclamida 5 mg : 1 cp apos cafe, almoço e jantar,  Metformina 850 : 1 cp apos cafe, almoço e jantar, Losartana 50 mg ( 1 cp pela manha e 1 cp a noite).    Exames LAb ( 18/08):  potassio : 4,8;  CT : 184; HDL : 52; LDL : 90; Cr : 0,9; glicose : 159, Hemoglobina glicosilada : 8, 17%;  TSH : 5, 61;  Microalbuminuria 24 horas : 15,6;  Transaminase piruvica : 37;  Transaminase oxalacetica : 23. Obesidade grau III;  DM  2.",
  "entities": {
    "Atividade de Assistência à Saúde": [
      "acompanhamento"
    ],
    "Produto Intelectual": [
      "Diagnostico"
    ],
    "Aminoácido, Peptídeo ou Proteína": [
      "insulina",
      "Insulina NPH"
    ],
    "Substância Farmacológica": [
      "insulina",
      "Medicamentos",
      "sinvastatina",
      "espironolactona",
      "furosemida",
      "AAS",
      "Levotiroxina",
      "Glibenclamida",
      "Metformina",
      "Losartana",
      "Insulina NPH"
    ],
    "Hormônio": [
      "insulina"
    ],
    "Negação": [
      "Nega"
    ],
    "Sinal ou Sintoma": [
      "poliuria",
      "polidipsia",
      "polifagia",
      "queixas"
    ],
    "Substância Química Orgânica": [
      "sinvastatina",
      "espironolactona",
      "furosemida",
      "AAS",
      "Levotiroxina",
      "Glibenclamida",
      "Metformina",
      "Losartana"
    ],
    "Abreviação": [
      "AAS",
      "DM 2",
      "Dm 2",
      "um cp",
      "1 cp",
      "Exames LAb",
      "CT : 184",
      "Cr : 0 , 9"
    ],
    "Doença ou Síndrome": [
      "DM 2",
      "Dm 2",
      "Obesidade grau III"
    ],
    "Achado": [
      "bem adaptada a droga"
    ],
    "Conceito Quantitativo": [
      "20 mg",
      "um cp",
      "25 mg",
      "1 cp",
      "40 mg",
      "100 mg",
      "30 U",
      "100 mcg",
      "5 mg",
      "50 mg"
    ],
    "Conceito Temporal": [
      "a noite",
      "pela manha",
      "apos o almoço",
      "apos cafe , almoço e jantar"
    ],
    "Resultado Laboratorial ou de Teste": [
      "potassio : 4 , 8",
      "CT : 184",
      "HDL : 52",
      "LDL : 90",
      "Cr : 0 , 9",
      "glicose : 159",
      "Hemoglobina glicosilada : 8 , 17%",
      "TSH : 5 , 61",
      "Microalbuminuria 24 horas : 15 , 6",
      "Transaminase piruvica : 37",
      "Transaminase oxalacetica : 23"
    ]
  },
  "labels": {
    "polidipsia": {
      "capitulo": "11"
    },
    "obesidade grau iii": {
      "capitulo": "15"
    },
    "poliuria": {
      "capitulo": "11"
    },
    "queixas": {
      "capitulo": "21"
    },
    "dm 2": {
      "capitulo": "05"
    },
    "polifagia": {
      "capitulo": "11"
    }
  }
}