{
  "prontuario_id": 181,
  "text": "# Lucas, 78 anos  * HAS, * Gota, * DAC - IAM + ATC em 2012 (angina instavel)  - Ecocardiograma mar/14: FE 42% / comprometimento difuso do VE grau moderado, insuf Mi discreta, insuf Tri discreta, hipetensao pulmonar discreta.  Paciente refere fraqueza intermitente em MMII, associada a tontura, turvação visual e epigastralgia. Nega dor toracica associada ou dispneia.  Nega DPN. Nega sincope.  Nega edema de MMII. Alimenta-se bem. Nega queixas urinarias e gastrointestinais.  Nega tabagismo atual e pregresso.  - Laboratorio Cr 1,5 / glicose 85 / ureia 70 / CPK 161 / acido urico 5,3 / TG 107 / TGP 23 / HDL 38 / Na 143 / TGO 26 / CT 103 / LDL 44 / K 5,1 / HB 16,1 / leucocitos 6800 / plaquetas 116000 / - Albumina/Cr isolada = 174,3 *** CKD 44; Paciente encaminhado via UBS para nefrologia - aguarda consulta.  Em uso de: alopurinol 150mg /dia, anlodipino 5mg /noite, enalapril 10mg 12/12 h, selozok 100mg /dia, AAS 100mg /dia, clopidogrel 75mg /dia, sinvastatina 40mg /dia, colecalciferol 10 gotas /semana.  Ao exame: PA: 90/60 mmHg / FC 55 bpm, BCRNF, SS, MV + bilateralmente, sem RA, MMII edema +/IV bilateral.  ##  Reduzimos anlodipino para 2,5mg /dia. Suspendemos clopidogrel. Mantemos demais medicações. Retorno em 10 meses com a cardio com novos exames. Encaminhado à nefrologia.  R1 CM Lucas, Dr Fortes. * HAS * Gota * DAC - IAM + ATC em 2012 (angina instavel).",
  "entities": {
    "Doença ou Síndrome": [
      "HAS",
      "Gota",
      "DAC",
      "IAM",
      "tabagismo",
      "angina instavel"
    ],
    "Abreviação": [
      "HAS",
      "DAC",
      "IAM",
      "ATC",
      "MMII",
      "DPN",
      "UBS",
      "AAS",
      "PA",
      "FC",
      "BCRNF",
      "SS",
      "cardio",
      "FE 42%",
      "comprometimento difuso do VE grau moderado",
      "insuf Mi discreta",
      "insuf Tri discreta",
      "MV + bilateralmente"
    ],
    "Procedimento Terapêutico ou Preventivo": [
      "ATC"
    ],
    "Procedimento Diagnóstico": [
      "Ecocardiograma",
      "exame"
    ],
    "Paciente ou Grupo com Deficiência": [
      "Paciente"
    ],
    "Localização ou Região Corporal": [
      "MMII"
    ],
    "Sinal ou Sintoma": [
      "epigastralgia",
      "dispneia",
      "DPN",
      "sincope",
      "edema",
      "queixas",
      "RA",
      "fraqueza intermitente",
      "associada a tontura",
      "turvação visual",
      "dor toracica associada"
    ],
    "Negação": [
      "Nega",
      "sem"
    ],
    "Função Patológica": [
      "edema"
    ],
    "Sistema Corporal": [
      "urinarias",
      "gastrointestinais"
    ],
    "Procedimento Laboratorial": [
      "Laboratorio"
    ],
    "Atividade de Assistência à Saúde": [
      "encaminhado",
      "Retorno",
      "Encaminhado",
      "Suspendemos clopidogrel"
    ],
    "Organização Relacionada à Saúde": [
      "UBS"
    ],
    "Grupo Profissional ou Ocupacional": [
      "nefrologia"
    ],
    "Substância Química Orgânica": [
      "alopurinol",
      "anlodipino",
      "AAS",
      "clopidogrel",
      "sinvastatina",
      "colecalciferol"
    ],
    "Substância Farmacológica": [
      "alopurinol",
      "anlodipino",
      "enalapril",
      "selozok",
      "AAS",
      "clopidogrel",
      "sinvastatina",
      "colecalciferol",
      "medicações"
    ],
    "Aminoácido, Peptídeo ou Proteína": [
      "enalapril"
    ],
    "Vitamina": [
      "colecalciferol"
    ],
    "Atributo Clínico": [
      "PA",
      "FC"
    ],
    "Achado": [
      "BCRNF",
      "SS",
      "Alimenta-se bem",
      "aguarda consulta",
      "MV + bilateralmente"
    ],
    "Conceito Espacial": [
      "bilateral"
    ],
    "Resultado Laboratorial ou de Teste": [
      "FE 42%",
      "comprometimento difuso do VE grau moderado",
      "insuf Mi discreta",
      "insuf Tri discreta",
      "hipetensao pulmonar discreta",
      "Cr 1 , 5",
      "glicose 85",
      "ureia 70",
      "CPK 161",
      "acido urico 5 , 3",
      "TG 107",
      "TGP 23",
      "HDL 38",
      "Na 143",
      "TGO 26",
      "CT 103",
      "LDL 44",
      "K 5 , 1",
      "HB 16 , 1",
      "leucocitos 6800",
      "plaquetas 116000",
      "Albumina/Cr isolada = 174 , 3",
      "CKD 44"
    ],
    "Conceito Temporal": [
      "atual e pregresso",
      "12/12 h",
      "10 gotas /semana"
    ],
    "Conceito Quantitativo": [
      "150mg /dia",
      "5mg /noite",
      "12/12 h",
      "10 gotas /semana",
      "90/60 mmHg",
      "55 bpm"
    ]
  },
  "labels": {
    "ra": {
      "capitulo": "11"
    },
    "associada a tontura": {
      "capitulo": "06"
    },
    "queixas": {
      "capitulo": "21"
    },
    "aguarda consulta": {
      "capitulo": "24"
    },
    "turvação visual": {
      "capitulo": "09"
    },
    "mv + bilateralmente": {
      "capitulo": "15"
    },
    "gota": {
      "capitulo": "11"
    },
    "ss": {
      "capitulo": "11"
    },
    "dac": {
      "capitulo": "11"
    },
    "epigastralgia": {
      "capitulo": "13"
    },
    "fraqueza intermitente": {
      "capitulo": "21"
    },
    "iam": {
      "capitulo": "11"
    },
    "angina instavel": {
      "capitulo": "11"
    },
    "dispneia": {
      "capitulo": "12"
    },
    "edema": {
      "capitulo": "15"
    },
    "has": {
      "capitulo": "11"
    },
    "sincope": {
      "capitulo": "21"
    },
    "dor toracica associada": {
      "capitulo": "21"
    }
  }
}