{
  "prontuario_id": 289,
  "text": "ID # Lucas, 60 anos.  QP # sem queixas.  HMA # Nega dispneia, palpitações, dor toracica ou outros sintomas cardíacos. Edema matinal. Acompanha no ambulatório por cardiomiopatia dilatada idiopatica e fibrilação atrial.  Comorbidades: HAS, DM e gota. Atualmente em uso furosemida 40mg 1 cp ao dia, digoxina 0,25mg 1 cp/dia, carvedilol 25mg 2 cp/dia, monocordil 20mg 2 cp/dia, hidralazina 25mg 2 cp/dia, alopurinol 300mg 1 cp/dia, colchicina 0,5mg  se dor, marevan 5mg 2 cp seg, qua e sex, sab e 1 cp nos demais, metformina 850mg 1 cp após almoço.  HMP # Já esteve na fila para transplante - mretirado por melhora clinica. CATE há aprox 2 anos - sem evidência de doença coronariana. Internado por insuficiência renal??? (inicio 2014).  Herniorrafia de parede abdominal (sangramento retroperitoneal por discrasia sanguinea) há 1 ano.  CHV # nega tabagismo e etilismo, sedentário.  HMF # mãe falecida por trombose aos 64 anos e pai falecida nefropatia com 78 anos; filhos saudáveis.  Exames: Leucocitose discreta - 10800; - segmentados 65,4; Ureia: 92; Cr: 2,1; Acido urico: 7,3; Sodio: 138; K: 5,7;  TFG (CKD-EPI): 33.",
  "entities": {
    "Abreviação": [
      "ID",
      "QP",
      "HMA",
      "HAS",
      "DM",
      "HMP",
      "CATE",
      "CHV",
      "HMF",
      "1 cp ao dia",
      "1 cp/dia",
      "2 cp/dia",
      "2 cp",
      "seg , qua e sex , sab",
      "1 cp"
    ],
    "Achado": [
      "QP",
      "HMA",
      "HMP",
      "CHV",
      "HMF",
      "melhora clinica",
      "filhos saudáveis ."
    ],
    "Negação": [
      "sem",
      "Nega",
      "nega"
    ],
    "Sinal ou Sintoma": [
      "queixas",
      "dispneia",
      "palpitações",
      "dor",
      "dor toracica",
      "sintomas cardíacos",
      "Edema matinal"
    ],
    "Organização Relacionada à Saúde": [
      "ambulatório"
    ],
    "Doença ou Síndrome": [
      "HAS",
      "DM",
      "gota",
      "tabagismo",
      "etilismo",
      "sedentário",
      "trombose",
      "nefropatia",
      "cardiomiopatia dilatada idiopatica",
      "fibrilação atrial",
      "doença coronariana",
      "insuficiência renal"
    ],
    "Substância Química Orgânica": [
      "furosemida",
      "digoxina",
      "carvedilol",
      "monocordil",
      "hidralazina",
      "alopurinol",
      "colchicina",
      "marevan",
      "metformina"
    ],
    "Substância Farmacológica": [
      "furosemida",
      "digoxina",
      "carvedilol",
      "monocordil",
      "hidralazina",
      "alopurinol",
      "colchicina",
      "marevan",
      "metformina"
    ],
    "Procedimento Terapêutico ou Preventivo": [
      "transplante",
      "CATE"
    ],
    "Atividade de Assistência à Saúde": [
      "Internado"
    ],
    "Procedimento Laboratorial": [
      "Exames"
    ],
    "Conceito Quantitativo": [
      "1 cp ao dia",
      "0 , 25mg",
      "1 cp/dia",
      "2 cp/dia",
      "0 , 5mg",
      "2 cp",
      "1 cp"
    ],
    "Conceito Temporal": [
      "seg , qua e sex , sab",
      "após almoço"
    ],
    "Resultado Laboratorial ou de Teste": [
      "Leucocitose discreta - 10800",
      "segmentados 65 , 4",
      "Ureia : 92",
      "Cr",
      "K : 5 , 7",
      "TFG ( CKD-EPI ) : 33"
    ]
  },
  "labels": {
    "sintomas cardíacos": {
      "capitulo": "11"
    },
    "fibrilação atrial": {
      "capitulo": "11"
    },
    "cardiomiopatia dilatada idiopatica": {
      "capitulo": "11"
    },
    "dor toracica": {
      "capitulo": "11"
    },
    "insuficiência renal": {
      "capitulo": "16"
    },
    "gota": {
      "capitulo": "05"
    },
    "doença coronariana": {
      "capitulo": "11"
    },
    "nefropatia": {
      "capitulo": "16"
    },
    "palpitações": {
      "capitulo": "11"
    },
    "dispneia": {
      "capitulo": "11"
    },
    "has": {
      "capitulo": "05"
    },
    "trombose": {
      "capitulo": "16"
    },
    "edema matinal": {
      "capitulo": "21"
    },
    "dor": {
      "capitulo": "21"
    },
    "dm": {
      "capitulo": "05"
    }
  }
}