{
  "prontuario_id": 666,
  "text": "Paciente em tratamento para ICC diastólica há cerca de  com melhora importante dos sintomas após início do tratamento. Hoje relata dispneia aos moderados esforços, nega disnpneía paroxística notrna, dorme com apenas 1 travesseiro. Nega precordialgia aos moderados esforços. Nega episódios anginosos. Nega outras queixas. Relata disúria associada à dor supra púbica. Faz 2 horas de caminhada / semana.   Ao EF: PA 130x78mmHg (relata PA normal quando em ambiente não hospitalar), FC 60bpm AR: mv sem RA ACV : rcr em 2T sem sopros, com hipofonese de bulhas AD: abdome globos, normotenso, indolor, ausência de massas ou visceromegalias Giordano - MMII sem edema  ex lab (04/11/14): - Cr: 1,1   Ur: 61 - Na: 140    K: 4,8  HBa1C: 6,59%  Clearence Cr: 49.9 CKD-EPI 51,7  MDRD   HD : - ICC diastólica classe I - HAS - DMII - Dislipidemia  CD : - Mantenho medicação. - Retorno em 6 meses - Solicito Ecocardio (retorno com exame). ICC classe I NYHA HAS, em uso de atenolol 100mg / dia, AAS 100mg / dia, furosemida 40mg 1cp / dia, losartana 50mg 12/12h DMII, metformina 850mg 1cp / dia Dislipidemia, faz uso de sinvastatina 20mg 02 cp à noite",
  "entities": {
    "Paciente ou Grupo com Deficiência": [
      "Paciente"
    ],
    "Procedimento Terapêutico ou Preventivo": [
      "tratamento",
      "medicação"
    ],
    "Negação": [
      "nega",
      "Nega",
      "sem",
      "indolor",
      "ausência",
      "-"
    ],
    "Sinal ou Sintoma": [
      "queixas",
      "disúria",
      "dor",
      "RA",
      "sopros",
      "globos",
      "massas",
      "visceromegalias",
      "edema",
      "dispneia aos moderados esforços",
      "precordialgia aos moderados esforços",
      "episódios anginosos",
      "hipofonese de bulhas"
    ],
    "Conceito Temporal": [
      "semana",
      "noite"
    ],
    "Abreviação": [
      "EF",
      "PA",
      "FC",
      "AR",
      "mv",
      "RA",
      "ACV",
      "AD",
      "MMII",
      "HD",
      "HAS",
      "DMII",
      "CD",
      "Ecocardio",
      "AAS",
      "ICC diastólica",
      "rcr em 2T",
      "ex lab",
      "Cr : 1 , 1",
      "Ur : 61",
      "Na : 140",
      "K : 4 , 8",
      "HBa1C : 6 , 59%",
      "Clearence Cr : 49",
      "CKD-EPI 51",
      "ICC diastólica classe I",
      "ICC classe I NYHA"
    ],
    "Atributo Clínico": [
      "PA",
      "FC",
      "AR",
      "ACV",
      "AD"
    ],
    "Conceito Quantitativo": [
      "130x78mmHg",
      "60bpm",
      "100mg / dia",
      "40mg 1cp / dia",
      "50mg 12/12h",
      "850mg 1cp / dia",
      "20mg 02 cp"
    ],
    "Sistema Corporal": [
      "AR",
      "ACV",
      "AD"
    ],
    "Achado": [
      "mv",
      "normotenso",
      "indolor",
      "melhora importante dos sintomas",
      "rcr em 2T"
    ],
    "Localização ou Região Corporal": [
      "abdome",
      "MMII",
      "supra púbica"
    ],
    "Doença ou Síndrome": [
      "HAS",
      "DMII",
      "Dislipidemia",
      "ICC diastólica",
      "ICC diastólica classe I",
      "ICC classe I NYHA"
    ],
    "Produto Intelectual": [
      "CD"
    ],
    "Atividade de Assistência à Saúde": [
      "Mantenho",
      "Retorno",
      "Solicito"
    ],
    "Substância Farmacológica": [
      "medicação",
      "atenolol",
      "AAS",
      "furosemida",
      "losartana",
      "metformina",
      "sinvastatina"
    ],
    "Procedimento Diagnóstico": [
      "Ecocardio",
      "exame",
      "ex lab"
    ],
    "Procedimento Laboratorial": [
      "ex lab"
    ],
    "Resultado Laboratorial ou de Teste": [
      "Cr : 1 , 1",
      "Ur : 61",
      "Na : 140",
      "K : 4 , 8",
      "HBa1C : 6 , 59%",
      "Clearence Cr : 49",
      "CKD-EPI 51",
      "7 MDRD"
    ]
  },
  "labels": {
    "ra": {
      "capitulo": "08"
    },
    "episódios anginosos": {
      "capitulo": "11"
    },
    "dmii": {
      "capitulo": "05"
    },
    "disúria": {
      "capitulo": "13"
    },
    "icc diastólica": {
      "capitulo": "11"
    },
    "queixas": {
      "capitulo": "21"
    },
    "icc diastólica classe i": {
      "capitulo": "11"
    },
    "massas": {
      "capitulo": "16"
    },
    "mv": {
      "capitulo": "08"
    },
    "rcr em 2t": {
      "capitulo": "08"
    },
    "icc classe i nyha": {
      "capitulo": "11"
    },
    "precordialgia aos moderados esforços": {
      "capitulo": "11"
    },
    "dispneia aos moderados esforços": {
      "capitulo": "12"
    },
    "globos": {
      "capitulo": "15"
    },
    "visceromegalias": {
      "capitulo": "16"
    },
    "dislipidemia": {
      "capitulo": "05"
    },
    "edema": {
      "capitulo": "14"
    },
    "has": {
      "capitulo": "11"
    },
    "sopros": {
      "capitulo": "08"
    },
    "dor": {
      "capitulo": "13"
    },
    "hipofonese de bulhas": {
      "capitulo": "08"
    }
  }
}