{
  "prontuario_id": 360,
  "text": "LUCAS  60 ANOS COMORBIDADES: IAM HÁ 5 ANOS - CATETERIZAÇÃO, ICC, DISLIPIDEMIA, HAS, DM MUC: AAS 100MG 1CP, ENALAPRIL 10MG 1CP 12/12HRS, SELOZOK 100MG 1CP 12/12HRS, ESPIRONOLACTONA 25MG 1CP, SINVASTATINA 20MG 2CP, FLUOXETINA 10MG 1CP  GLIFAGE 500MG 1CP NOITE, INSULINA NPH 28U M 24U N, INSULINA REGULAR 12U N  #S - EM ACOMPANHAMENTO AMBULATORIAL POR DM TIPO 2 HÁ 5 ANOS, DX DE DM HÁ 23 ANOS - PACIENTE VAI FAZER O LASER PARA CORREÃO DA VISÃO - NEGA ALTERAÇÕES DE HABITO URINARIO E INTESTINAL - NÃO FAZ ACOMPANHAMENTO NUTRICIONAL - PRATICA CAMINHADAS DE 1 HORA PELA MANHA E A ATARDE TODO DIA   # O - BEG , LOTE, ANICTERICA, ACIANOTICA, CORADA E HIDRATADA - CV : BRNF 2T SS - CPP : spp - ABS : spp - MMII : PES BEM CUIDADOS, COM TROFISMO PRESERVADO, SEM EVIDENCIA DE ONICOMICOSE  EXAMES LABORATORIAIS - Cr 1,2 TFG CKD EPI 48.9 ml/min/1.73 m2- GLICOSE 155 - HBAC1 7,86% - MICROALBUMINURIA 24 HRS 10,8MG / 24HRS  # A - DM TIPO 2 EM ACOMPANHAMENTO - SEM EVIDENCIA DE IRC  # P - PACIENTE ORIENTADA QUANDO AO CONTROLE DA GLICEMIA CAPILAR - ORIENTAÇAO PARA PEGA FITAS  E FAZER CADASTRO EM CURITIBA",
  "entities": {
    "Doença ou Síndrome": [
      "COMORBIDADES",
      "IAM",
      "ICC",
      "DISLIPIDEMIA",
      "HAS",
      "DM",
      "ONICOMICOSE",
      "IRC",
      "DM TIPO 2"
    ],
    "Abreviação": [
      "IAM",
      "ICC",
      "HAS",
      "DM",
      "MUC",
      "AAS",
      "1CP",
      "2CP",
      "M",
      "N",
      "S",
      "DX",
      "O",
      "BEG",
      "LOTE",
      "CV",
      "SS",
      "CPP",
      "spp",
      "ABS",
      "MMII",
      "A",
      "IRC",
      "P",
      "DM TIPO 2",
      "BRNF 2T",
      "Cr 1 , 2"
    ],
    "Procedimento Terapêutico ou Preventivo": [
      "CATETERIZAÇÃO",
      "LASER",
      "CORREÃO DA VISÃO",
      "CONTROLE DA GLICEMIA CAPILAR"
    ],
    "Achado": [
      "MUC",
      "S",
      "BEG",
      "LOTE",
      "ANICTERICA",
      "ACIANOTICA",
      "CORADA",
      "HIDRATADA",
      "SS",
      "spp",
      "BRNF 2T",
      "BEM CUIDADOS",
      "TROFISMO PRESERVADO"
    ],
    "Substância Farmacológica": [
      "AAS",
      "ENALAPRIL",
      "SELOZOK",
      "ESPIRONOLACTONA",
      "SINVASTATINA",
      "FLUOXETINA",
      "GLIFAGE",
      "INSULINA NPH",
      "INSULINA REGULAR"
    ],
    "Conceito Temporal": [
      "12/12HRS",
      "NOITE",
      "M",
      "N",
      "MANHA",
      "HÁ 5 ANOS",
      "HÁ 23 ANOS",
      "1 HORA",
      "TODO DIA"
    ],
    "Organização Relacionada à Saúde": [
      "AMBULATORIAL"
    ],
    "Atividade de Assistência à Saúde": [
      "DX",
      "O",
      "ACOMPANHAMENTO",
      "ORIENTADA",
      "ORIENTAÇAO",
      "ACOMPANHAMENTO NUTRICIONAL"
    ],
    "Paciente ou Grupo com Deficiência": [
      "PACIENTE"
    ],
    "Negação": [
      "NEGA",
      "NÃO",
      "ANICTERICA",
      "ACIANOTICA",
      "SS",
      "spp",
      "SEM"
    ],
    "Função de Organismo": [
      "INTESTINAL",
      "HABITO URINARIO"
    ],
    "Sistema Corporal": [
      "CV",
      "CPP"
    ],
    "Localização ou Região Corporal": [
      "ABS",
      "MMII"
    ],
    "Parte do Corpo, Órgão ou Componente Orgânico": [
      "PES"
    ],
    "Procedimento Diagnóstico": [
      "A"
    ],
    "Produto Intelectual": [
      "P"
    ],
    "Dispositivo Médico": [
      "FITAS"
    ],
    "Aminoácido, Peptídeo ou Proteína": [
      "INSULINA NPH",
      "INSULINA REGULAR"
    ],
    "Hormônio": [
      "INSULINA NPH",
      "INSULINA REGULAR"
    ],
    "Procedimento Laboratorial": [
      "EXAMES LABORATORIAIS"
    ],
    "Resultado Laboratorial ou de Teste": [
      "Cr 1 , 2",
      "TFG CKD EPI 48",
      "GLICOSE 155",
      "HBAC1 7 , 86%",
      "MICROALBUMINURIA 24 HRS 10 , 8MG / 24HRS"
    ]
  },
  "labels": {
    "irc": {
      "capitulo": "04"
    },
    "anicterica": {
      "capitulo": "05"
    },
    "muc": {
      "capitulo": "05"
    },
    "onicomicose": {
      "capitulo": "14"
    },
    "acianotica": {
      "capitulo": "09"
    },
    "brnf 2t": {
      "capitulo": "11"
    },
    "ss": {
      "capitulo": "11"
    },
    "corada": {
      "capitulo": "09"
    },
    "icc": {
      "capitulo": "11"
    },
    "iam": {
      "capitulo": "11"
    },
    "dm tipo 2": {
      "capitulo": "05"
    },
    "dislipidemia": {
      "capitulo": "11"
    },
    "spp": {
      "capitulo": "09"
    },
    "has": {
      "capitulo": "11"
    }
  }
}