{
  "prontuario_id": 222,
  "text": "feminino, 75 anos acompanhamento da diabetes e da creatinina  parcial de urina : nitrito positivo, leucocitos 57, cor castanha, traços de proteinas creatinina 1.9 CKD/EPI 25 ml/min Hb glicada 8,5 % glicose durante o dia : de manha controlada e no inicio e fim da noite sempre mais alta  HMF : DM 2 e HAS há 30 anos dislipidemia doença renal estagio 4 obesidade e sedentarismo cx previas : platina no braço e perna  em uso de : losartana 30 mg 2x dia sinvastatina 20 mg 1 x dia omeprazol 20 mg 1 x ao dia hidroclorotiazida 25 mg 1 x dia fluoxetina 20 mg 1 x dia insulina : NPH 50U de manha e 30U de noite, regular apenas de meio dia quando esta alta , usa 5 U uso de metformina apenas quando glicose maior que 300  PA : 117/64 mmHg FC : 67 bpm MMII edema 1+/4+ peso : 108 kg diurese mais de 3 x ao dia evacuaçoes : 1 x na semana  conduta : retirar metformina NPH 50 de manha, 10 no almoço e 30U de noite  atb com macrodantina 100 mg 2x ao dia",
  "entities": {
    "Atributo Clínico": [
      "feminino",
      "PA",
      "FC",
      "peso"
    ],
    "Atividade de Assistência à Saúde": [
      "acompanhamento",
      "conduta",
      "retirar"
    ],
    "Doença ou Síndrome": [
      "diabetes",
      "HAS",
      "dislipidemia",
      "obesidade",
      "DM 2",
      "doença renal estagio 4"
    ],
    "Substância Biologicamente Ativa": [
      "creatinina",
      "glicose"
    ],
    "Substância Química Orgânica": [
      "glicose",
      "macrodantina"
    ],
    "Substância Farmacológica": [
      "glicose",
      "losartana",
      "sinvastatina",
      "omeprazol",
      "hidroclorotiazida",
      "fluoxetina",
      "insulina",
      "NPH",
      "regular",
      "metformina",
      "macrodantina"
    ],
    "Conceito Temporal": [
      "manha",
      "previas",
      "noite",
      "durante o dia",
      "inicio e fim da noite",
      "há 30 anos",
      "meio dia",
      "1 x na semana"
    ],
    "Abreviação": [
      "HMF",
      "HAS",
      "cx",
      "NPH",
      "PA",
      "FC",
      "MMII",
      "atb",
      "DM 2"
    ],
    "Achado": [
      "HMF"
    ],
    "Sinal ou Sintoma": [
      "sedentarismo",
      "edema"
    ],
    "Comportamento Individual": [
      "sedentarismo"
    ],
    "Procedimento Terapêutico ou Preventivo": [
      "cx",
      "platina"
    ],
    "Elemento, Íon ou Isótopo": [
      "platina"
    ],
    "Localização ou Região Corporal": [
      "braço",
      "perna",
      "MMII"
    ],
    "Aminoácido, Peptídeo ou Proteína": [
      "insulina",
      "NPH",
      "regular"
    ],
    "Hormônio": [
      "insulina",
      "NPH",
      "regular"
    ],
    "Resultado Laboratorial ou de Teste": [
      "1+/4+",
      "nitrito positivo",
      "leucocitos 57",
      "cor castanha",
      "traços de proteinas",
      "creatinina 1",
      "CKD/EPI 25 ml/min",
      "Hb glicada 8 , 5 %"
    ],
    "Conceito Quantitativo": [
      "1+/4+",
      "30 mg",
      "2x dia",
      "20 mg",
      "1 x dia",
      "1 x ao dia",
      "25 mg",
      "5 U",
      "maior que 300",
      "117/64 mmHg",
      "67 bpm",
      "108 kg",
      "3 x ao dia",
      "1 x na semana",
      "100 mg",
      "2x ao dia"
    ],
    "Função de Organismo": [
      "diurese",
      "evacuaçoes"
    ],
    "Produto Intelectual": [
      "conduta"
    ],
    "Antibiótico": [
      "atb"
    ],
    "Grupo Etário": [
      "75 anos"
    ],
    "Procedimento Laboratorial": [
      "parcial de urina"
    ]
  },
  "labels": {
    "sedentarismo": {
      "capitulo": "05"
    },
    "edema": {
      "capitulo": "11"
    },
    "has": {
      "capitulo": "05"
    },
    "diabetes": {
      "capitulo": "05"
    },
    "doença renal estagio 4": {
      "capitulo": "16"
    },
    "hmf": {
      "capitulo": "05"
    },
    "dm 2": {
      "capitulo": "05"
    },
    "obesidade": {
      "capitulo": "15"
    },
    "dislipidemia": {
      "capitulo": "13"
    }
  }
}