{
  "prontuario_id": 126,
  "text": "LUCAS , 59 A.  QP : DOR NAS PERNAS.  HMA : REFERE INICIO DO QUADRO HÁ 2 MESES, BILATERAL, DOR CANSADA, COM PREDOMÍNIO EM TORNOZELO. NEGA FATORES DE MELHORAS E PIORA COM DEAMBULAÇÃO. USO DE AMITRIPTILINA 75MG POR 1 MÊS, SEM MELHORAS.  HMP : - DM2 - HAS - CX DE AMPUTAÇÃO DE PODODACTILO DO PÉ DIREITO - CX PARA DRENAGEM DE HEMATOMA APÓS TRAUMA CRANIOENCEFALICO.  MUC : - INSULINA NPH ( 35U DE MANHA E 10 A NOITE ). - METFORMINA 850MG 2X AO DIA. - SINVASTATINA 20MG / DIA - AAS 100MG / DIA - LOSARTANA 100MG / DIA. - AMITRIPTILINA 25MG / DIA.  RS: TONTURA DESDE O PÓS OPERATORIO.  EXAMES (01/04) - HMG ( HB 13.3, HT 38.3, LEUC 8530, BASTAO 2%, PLAQUETAS 283000 ) - NA 147 - UR 57 - HDL 34 - LDL 69 - CR 1.03 - K 4.9 - CT 122 - TG 115 - HBA1C 8.6% - GLICEMIA 67 - MICROALBUMINURIA ( 38 ). DM2 NEUROPATIA DIABETICA ?",
  "entities": {
    "Sinal ou Sintoma": [
      "DOR",
      "TONTURA",
      "DOR CANSADA",
      "PIORA COM DEAMBULAÇÃO"
    ],
    "Parte do Corpo, Órgão ou Componente Orgânico": [
      "PERNAS",
      "TORNOZELO",
      "PODODACTILO DO PÉ DIREITO"
    ],
    "Conceito Espacial": [
      "BILATERAL"
    ],
    "Negação": [
      "NEGA",
      "SEM"
    ],
    "Substância Química Orgânica": [
      "AMITRIPTILINA",
      "METFORMINA",
      "SINVASTATINA"
    ],
    "Substância Farmacológica": [
      "AMITRIPTILINA",
      "METFORMINA",
      "SINVASTATINA",
      "AAS",
      "LOSARTANA",
      "INSULINA NPH"
    ],
    "Achado": [
      "MELHORAS",
      "FATORES DE MELHORAS"
    ],
    "Abreviação": [
      "HMP",
      "DM2",
      "HAS",
      "CX",
      "MUC",
      "AAS",
      "HMG",
      "CR",
      "K",
      "CX DE AMPUTAÇÃO",
      "HT 38",
      "LEUC 8530",
      "NA 147",
      "UR 57",
      "CT 122",
      "TG 115"
    ],
    "Doença ou Síndrome": [
      "DM2",
      "HAS",
      "NEUROPATIA DIABETICA"
    ],
    "Procedimento Terapêutico ou Preventivo": [
      "CX",
      "CX DE AMPUTAÇÃO",
      "DRENAGEM DE HEMATOMA"
    ],
    "Conceito Temporal": [
      "APÓS",
      "MANHA",
      "NOITE",
      "HÁ 2 MESES",
      "1 MÊS",
      "PÓS OPERATORIO"
    ],
    "Procedimento Laboratorial": [
      "EXAMES",
      "HMG",
      "CR",
      "K",
      "HBA1C"
    ],
    "Procedimento Diagnóstico": [
      "EXAMES",
      "NEUROPATIA DIABETICA"
    ],
    "Lesão ou Envenenamento": [
      "TRAUMA CRANIOENCEFALICO"
    ],
    "Conceito Quantitativo": [
      "20MG / DIA",
      "100MG / DIA",
      "25MG / DIA"
    ],
    "Resultado Laboratorial ou de Teste": [
      "HT 38",
      "LEUC 8530",
      "BASTAO 2%",
      "PLAQUETAS 283000",
      "NA 147",
      "UR 57",
      "HDL 34",
      "LDL 69",
      "CT 122",
      "TG 115",
      "GLICEMIA 67",
      "MICROALBUMINURIA ( 38 )"
    ]
  },
  "labels": {
    "dor": {
      "capitulo": "15"
    },
    "neuropatia diabetica": {
      "capitulo": "05"
    },
    "piora com deambulação": {
      "capitulo": "15"
    },
    "tontura": {
      "capitulo": "21"
    }
  }
}