{
  "prontuario_id": 129,
  "text": "# ESTENOSE MITRAL - VALVULOPLASTIA 1993 # ACFA / FLUTTER - CARDIOVERSÃO HÁ 2 ANOS # HIPOTIREOIDISMO  Paciente internou por quadro de dispnéia associada a palpitações, tendo sido relacionado este quadro a fibrilação atrial aguda com exacerbação de ICC. Houve melhora progressiva durante a internação. Em 31/1/2007, foi submetida a cardioversão elétrica eletiva para reversão para ritmo sinusal. Procedimento sem intercorrências com ritmo sinusal documentado desde então. Antes do procedimento foi afastado trombos por ecocardiografia transesofágico. Ao exame apresenta apenas leve hiperemia em local do choque, sem dor. Tem alta em boas condições, com frequência em torno de 70 / minuto, regular, hemodinamicamente estável, com INR no alvo com plano de retorno ao consultório do Doutor Vital Brazil , seu médico assistente. Orientações gerais. ",
  "entities": {
    "Procedimento Terapêutico ou Preventivo": [
      "VALVULOPLASTIA",
      "CARDIOVERSÃO",
      "Procedimento",
      "procedimento",
      "choque",
      "cardioversão elétrica eletiva",
      "reversão para ritmo sinusal"
    ],
    "Abreviação": [
      "ACFA",
      "INR",
      "exacerbação de ICC"
    ],
    "Doença ou Síndrome": [
      "ACFA",
      "FLUTTER",
      "HIPOTIREOIDISMO",
      "ESTENOSE MITRAL",
      "fibrilação atrial aguda",
      "exacerbação de ICC"
    ],
    "Paciente ou Grupo com Deficiência": [
      "Paciente"
    ],
    "Atividade de Assistência à Saúde": [
      "internou",
      "internação",
      "submetida",
      "alta",
      "Orientações gerais"
    ],
    "Sinal ou Sintoma": [
      "dispnéia",
      "palpitações",
      "intercorrências",
      "trombos",
      "hiperemia",
      "dor",
      "boas condições"
    ],
    "Negação": [
      "sem"
    ],
    "Conceito Temporal": [
      "Antes",
      "HÁ 2 ANOS"
    ],
    "Procedimento Diagnóstico": [
      "exame",
      "INR",
      "ecocardiografia transesofágico"
    ],
    "Conceito Qualitativo": [
      "leve",
      "regular"
    ],
    "Atributo Clínico": [
      "frequência"
    ],
    "Achado": [
      "regular",
      "melhora progressiva",
      "ritmo sinusal",
      "boas condições",
      "hemodinamicamente estável"
    ],
    "Produto Intelectual": [
      "plano"
    ],
    "Organização Relacionada à Saúde": [
      "consultório"
    ],
    "Grupo Profissional ou Ocupacional": [
      "Doutor",
      "médico assistente"
    ],
    "Conceito Quantitativo": [
      "70 / minuto"
    ]
  },
  "labels": {
    "flutter": {
      "capitulo": "11"
    },
    "melhora progressiva": {
      "capitulo": "21"
    },
    "exacerbação de icc": {
      "capitulo": "05"
    },
    "ritmo sinusal": {
      "capitulo": "11"
    },
    "trombos": {
      "capitulo": "23"
    },
    "dispnéia": {
      "capitulo": "12"
    },
    "fibrilação atrial aguda": {
      "capitulo": "11"
    },
    "intercorrências": {
      "capitulo": "22"
    },
    "hemodinamicamente estável": {
      "capitulo": "21"
    },
    "dor": {
      "capitulo": "14"
    },
    "palpitações": {
      "capitulo": "11"
    },
    "hiperemia": {
      "capitulo": "14"
    },
    "hipotireoidismo": {
      "capitulo": "05"
    },
    "estenose mitral": {
      "capitulo": "11"
    },
    "acfa": {
      "capitulo": "26"
    }
  }
}