{
  "prontuario_id": 144,
  "text": "LUCAS , 68 ANOS.  QP: ACOMPANHAMENTO POS RM HMA : PACIENTE RELATA TOSSE SECA, FREQUENTES, MAIS A NOITE. RM COM 2 SAFENAS E 1 MAMARIA, CIRURGIA REALIZADA EM JULHO DE 2015.  NEGA DISPNEIA.NEGA SINCOPE.  RELATA DOR TIPO QUEIMAÇÃO EM HEMITORAX ESQUERDO, COM DURAÇÃO MENOR QUE 1 MINUTO, SEM RELÇAO COM EXERCICIIOS FISICOS, ALIVIANDO COM PARACETAMOL.  HMP : HAS, DM.  MEDICAMENTOS DE USO CONTINUO :  -  AAS 100 MG -CLOPIDROGEL 75 MG -SINVASTATINA 40 MG -CAPTOPRIL 25 MG -CARVEDILOL 12,5 -OMEPRAZOL 20 MG -PARACETAMOL 500 MG - METFORMINA 850 MG - INSULINA NPH 16 UI PELA MANHA E 12 UI A TARDE.   EXAMES :  - ECG : ALTERAÇÃO DA REPOLARIZAÇÃO VENTRICULAR LATERAL E ALTA. RITMO SINUSAL. FC : 70 BPM . - SODIO : 135 - CREATININA : 1,6 ( CLEARENCE 44 ) - GLICOSE : 188 - UREIA : 71 - POTASSIO : 5,4 - HDL : 27 - TG : 187 - HB1AC : 9,42% - RX : SEM ANORMALIDADES  EXAME FISICO : - FC : 74 BPM - FR : 18 - PA : 120/70   PLANO :  - ENCAMINHO PACIENTE PARA AMBULATORIO DE ENDOCRINOLOGIA PARA CONTROLE DE DIABETES MAL CONTROLADA - ENCAMINHO PACIENTE PARA AMBULATORIO DE NEFROLOGIA PARA ACOMPANHAMENTO DE IRC - TROCO CAPTOPRIL POR LOSARTANA.",
  "entities": {
    "Atividade de Assistência à Saúde": [
      "ACOMPANHAMENTO",
      "REALIZADA",
      "PLANO",
      "ENCAMINHO",
      "TROCO"
    ],
    "Conceito Temporal": [
      "POS",
      "FREQUENTES",
      "NOITE",
      "DURAÇÃO",
      "CONTINUO",
      "MANHA",
      "TARDE"
    ],
    "Abreviação": [
      "RM",
      "HAS",
      "DM",
      "AAS",
      "ECG",
      "FC",
      "RX",
      "FR",
      "PA",
      "IRC",
      "70 BPM",
      "TG : 187",
      "74 BPM"
    ],
    "Procedimento Terapêutico ou Preventivo": [
      "RM",
      "CIRURGIA"
    ],
    "Paciente ou Grupo com Deficiência": [
      "PACIENTE"
    ],
    "Conceito Quantitativo": [
      "2",
      "1",
      "18",
      "120/70",
      "100 MG",
      "75 MG",
      "40 MG",
      "25 MG",
      "12 , 5",
      "20 MG",
      "500 MG",
      "850 MG",
      "16 UI",
      "12 UI",
      "70 BPM",
      "74 BPM"
    ],
    "Parte do Corpo, Órgão ou Componente Orgânico": [
      "SAFENAS",
      "MAMARIA"
    ],
    "Negação": [
      "NEGA",
      "SEM",
      "ANORMALIDADES"
    ],
    "Sinal ou Sintoma": [
      "DISPNEIA",
      "SINCOPE",
      "ANORMALIDADES",
      "TOSSE SECA",
      "DOR TIPO QUEIMAÇÃO",
      "MENOR QUE 1 MINUTO",
      "RELÇAO COM EXERCICIIOS FISICOS"
    ],
    "Achado": [
      "ALIVIANDO",
      "RITMO SINUSAL"
    ],
    "Substância Química Orgânica": [
      "PARACETAMOL",
      "AAS",
      "-CLOPIDROGEL",
      "-SINVASTATINA",
      "-CARVEDILOL",
      "-OMEPRAZOL",
      "-PARACETAMOL",
      "METFORMINA",
      "INSULINA",
      "LOSARTANA"
    ],
    "Substância Farmacológica": [
      "PARACETAMOL",
      "MEDICAMENTOS",
      "AAS",
      "-CLOPIDROGEL",
      "-SINVASTATINA",
      "-CAPTOPRIL",
      "-CARVEDILOL",
      "-OMEPRAZOL",
      "-PARACETAMOL",
      "METFORMINA",
      "CAPTOPRIL",
      "LOSARTANA"
    ],
    "Doença ou Síndrome": [
      "HAS",
      "DM",
      "IRC",
      "DIABETES MAL CONTROLADA"
    ],
    "Aminoácido, Peptídeo ou Proteína": [
      "-CAPTOPRIL",
      "INSULINA",
      "NPH",
      "CAPTOPRIL"
    ],
    "Hormônio": [
      "INSULINA",
      "NPH"
    ],
    "Resultado Laboratorial ou de Teste": [
      "EXAMES",
      "ANORMALIDADES",
      "ALTERAÇÃO DA REPOLARIZAÇÃO VENTRICULAR LATERAL E ALTA",
      "RITMO SINUSAL",
      "SODIO : 135",
      "CREATININA : 1 , 6",
      "CLEARENCE 44",
      "GLICOSE : 188",
      "UREIA : 71",
      "POTASSIO : 5 , 4",
      "HDL : 27",
      "TG : 187",
      "HB1AC : 9 , 42%"
    ],
    "Procedimento Diagnóstico": [
      "EXAMES",
      "ECG",
      "RX",
      "EXAME FISICO"
    ],
    "Atributo Clínico": [
      "FC",
      "FR",
      "PA"
    ],
    "Localização ou Região Corporal": [
      "HEMITORAX ESQUERDO"
    ],
    "Organização Relacionada à Saúde": [
      "AMBULATORIO DE ENDOCRINOLOGIA",
      "AMBULATORIO DE NEFROLOGIA"
    ]
  },
  "labels": {
    "tosse seca": {
      "capitulo": "12"
    },
    "dor tipo queimação": {
      "capitulo": "08"
    },
    "irc": {
      "capitulo": "11"
    },
    "diabetes mal controlada": {
      "capitulo": "05"
    },
    "has": {
      "capitulo": "04"
    },
    "dm": {
      "capitulo": "05"
    },
    "aliviando": {
      "capitulo": "21"
    },
    "menor que 1 minuto": {
      "capitulo": "21"
    },
    "relçao com exerciciios fisicos": {
      "capitulo": "21"
    },
    "anormalidades": {
      "capitulo": "21"
    }
  }
}