{
  "prontuario_id": 43,
  "text": "PACIENTE INTERNA COM QUADRO DE DOR ABDOMINAL, NÁUSEAS E VÔMITOS. SEM FEBRE NA INTERNAÇÃO. ECO DE AB COM VESÍCULA DE PEQUENAS PROPORÇÕES E CÁLCULO NO INFUNDÍBULO ). SEM CÁLCULOS NO COLÉDOCO. PELO MENOS DOIS CISTOS NA TRANSIÇÃO ENTRE O CORPO E A CAUDA DO PÂNCREAS, O MAIOR COM 1 CM DE DIÂMETRO. PRÓSTATA COM AUMENTO DE VOLUME. LABORATÓRIO COM AUMENTO DE BILIRRUBINAS TOTAIS, TGO, TGP E FOSFATASE ALCALINA, JÁ COM DIMINUIÇÃO DOS VALORES NA SEGUNDA MEDIDA.  PERMANECEU ASSINTOMÁTICO NA INTERNAÇÃO. EXAMES PROGRESSIVAMENTE MELHORES. RECEBE ALTA EM BOM ESTADO GERAL E MANTERÁ ACOMPANHAMENTO MEDICO NO CONSULTÓRIO DO SEU MÉDICO ASSISTENTE.",
  "entities": {
    "Paciente ou Grupo com Deficiência": [
      "PACIENTE"
    ],
    "Atividade de Assistência à Saúde": [
      "INTERNA",
      "INTERNAÇÃO",
      "ALTA",
      "ACOMPANHAMENTO MEDICO"
    ],
    "Sinal ou Sintoma": [
      "QUADRO",
      "NÁUSEAS",
      "VÔMITOS",
      "FEBRE",
      "DOR ABDOMINAL",
      "PRÓSTATA COM AUMENTO DE VOLUME",
      "AUMENTO DE BILIRRUBINAS TOTAIS",
      "DIMINUIÇÃO DOS VALORES"
    ],
    "Negação": [
      "SEM",
      "ASSINTOMÁTICO"
    ],
    "Conceito Quantitativo": [
      "DOIS"
    ],
    "Resultado Laboratorial ou de Teste": [
      "LABORATÓRIO",
      "TGO",
      "TGP",
      "VESÍCULA DE PEQUENAS PROPORÇÕES E CÁLCULO NO INFUNDÍBULO",
      "CÁLCULOS NO COLÉDOCO",
      "CISTOS NA TRANSIÇÃO",
      "CORPO E A CAUDA DO PÂNCREAS",
      "MAIOR COM 1 CM DE DIÂMETRO",
      "AUMENTO DE BILIRRUBINAS TOTAIS",
      "FOSFATASE ALCALINA",
      "EXAMES PROGRESSIVAMENTE MELHORES"
    ],
    "Procedimento Laboratorial": [
      "LABORATÓRIO"
    ],
    "Achado": [
      "ASSINTOMÁTICO",
      "EXAMES PROGRESSIVAMENTE MELHORES",
      "BOM ESTADO GERAL"
    ],
    "Organização Relacionada à Saúde": [
      "CONSULTÓRIO"
    ],
    "Procedimento Diagnóstico": [
      "ECO DE AB"
    ],
    "Abreviação": [
      "ECO DE AB"
    ],
    "Grupo Profissional ou Ocupacional": [
      "MÉDICO ASSISTENTE"
    ]
  },
  "labels": {
    "febre": {
      "capitulo": "01"
    },
    "próstata com aumento de volume": {
      "capitulo": "16"
    },
    "náuseas": {
      "capitulo": "13"
    },
    "quadro": {
      "capitulo": "21"
    },
    "vômitos": {
      "capitulo": "13"
    },
    "dor abdominal": {
      "capitulo": "13"
    }
  }
}