{
  "prontuario_id": 736,
  "text": "Cx bariatrica 2x ( ultima ha 1,5a ).Valva aortica bicúspide com gra no cate de 38 mmHg..Uso: Enalapril 10 - 12/12h; Monocordil ?mg - 2xd ; FSM - 1/2cp ao dia; Espironolactona 25 - 1xd; Apresolina 25 - 12/12h; Carvedilol 12.5 - 12/12h.\nDispnéia de longa data, progressiva,aos moderados esforços. Ardencia retoresternal aos grandes esforços vespertino\nBEG, eupneico, acianotico, anictrico, PA (sentado): 130x90mmHg, P = 68 spm, FR = 12 rpm. MV normodist sem ruidoa adv. RCR, 2T, BNFss++ / 6+ FAO e Ao ac. \nCate (18/09/2014): sem coronariopatia obstrutiva, VE disfunção de grau moderado, estenose aortica grau moderado.\nCD; mantida e retorno amanha com Doutor Vital Brazil e vamos discutir a situação.\n \n \n \n ",
  "entities": {
    "Conceito Quantitativo": [
      "2x",
      "10",
      "2xd",
      "25",
      "1xd",
      "130x90mmHg",
      "38 mmHg",
      "68 spm",
      "12 rpm"
    ],
    "Procedimento Diagnóstico": [
      "cate",
      "Cate"
    ],
    "Aminoácido, Peptídeo ou Proteína": [
      "Enalapril"
    ],
    "Substância Farmacológica": [
      "Enalapril",
      "Monocordil",
      "FSM",
      "Espironolactona",
      "Apresolina",
      "Carvedilol"
    ],
    "Conceito Temporal": [
      "12/12h",
      "2xd",
      "dia",
      "1xd",
      "amanha",
      "longa data"
    ],
    "Substância Química Orgânica": [
      "Monocordil",
      "FSM",
      "Espironolactona",
      "Apresolina",
      "Carvedilol"
    ],
    "Abreviação": [
      "FSM",
      "BEG",
      "PA",
      "P",
      "FR",
      "Cate",
      "CD",
      "Cx bariatrica",
      "MV normodist",
      "ruidoa adv",
      "RCR , 2T",
      "VE disfunção de grau moderado"
    ],
    "Sinal ou Sintoma": [
      "Dispnéia",
      "progressiva",
      "moderados esforços",
      "Ardencia retoresternal aos grandes esforços",
      "ruidoa adv"
    ],
    "Conceito Qualitativo": [
      "progressiva"
    ],
    "Achado": [
      "BEG",
      "eupneico",
      "acianotico",
      "anictrico",
      "MV normodist",
      "RCR , 2T"
    ],
    "Negação": [
      "acianotico",
      "anictrico",
      "sem",
      "BNFss++"
    ],
    "Atributo Clínico": [
      "PA",
      "P",
      "FR"
    ],
    "Atividade de Assistência à Saúde": [
      "CD",
      "mantida",
      "retorno",
      "discutir"
    ],
    "Grupo Profissional ou Ocupacional": [
      "Doutor"
    ],
    "Procedimento Terapêutico ou Preventivo": [
      "Cx bariatrica"
    ],
    "Parte do Corpo, Órgão ou Componente Orgânico": [
      "Valva aortica bicúspide"
    ],
    "Resultado Laboratorial ou de Teste": [
      "coronariopatia obstrutiva",
      "VE disfunção de grau moderado",
      "estenose aortica grau moderado"
    ]
  },
  "labels": {
    "moderados esforços": {
      "capitulo": "11"
    },
    "rcr , 2t": {
      "capitulo": "11"
    },
    "anictrico": {
      "capitulo": "06"
    },
    "progressiva": {
      "capitulo": "21"
    },
    "beg": {
      "capitulo": "21"
    },
    "ardencia retoresternal aos grandes esforços": {
      "capitulo": "12"
    },
    "dispnéia": {
      "capitulo": "12"
    },
    "acianotico": {
      "capitulo": "21"
    },
    "ruidoa adv": {
      "capitulo": "11"
    }
  }
}