{
  "prontuario_id": 716,
  "text": "Lucas, 44 anos\nQP : Hérnia incisional. Retorno com exames pré - operatórios\nGastroplastia Sleeve. Re-sleeve Santoro modificada. Reoperado  ( bariátrica ) há 2 anos\nPaciente retornou com solicitação da cardiologia para descrição da intervenção cirúrgica para avaliação cardiológica. \nEcocardiograma: VE hipertrófico e comprometimento discreto da função sistólica, aumento importante de AD, aumento de AD, insuficiencia mitral de grau discreto, dupla lesão aórtica com estenose moderada e refluxo discreto, \naumento discreto da aorta ascendente, hipertensão pulmonar de grau discreto.\nConduta : enviamos carta descrevendo o tipo de intervenção cirúrgica para cardiologia. Aguardando avaliação da cardiologia.\n \n \n \n ",
  "entities": {
    "Atividade de Assistência à Saúde": [
      "QP",
      "Retorno",
      "retornou",
      "Conduta",
      "enviamos",
      "solicitação da cardiologia",
      "avaliação cardiológica",
      "Aguardando avaliação"
    ],
    "Abreviação": [
      "QP",
      "VE hipertrófico e comprometimento discreto da função sistólica",
      "aumento importante de AD",
      "aumento de AD"
    ],
    "Achado": [
      "Retorno",
      "Reoperado"
    ],
    "Paciente ou Grupo com Deficiência": [
      "Paciente"
    ],
    "Procedimento Diagnóstico": [
      "Ecocardiograma",
      "exames pré - operatórios"
    ],
    "Grupo Profissional ou Ocupacional": [
      "cardiologia"
    ],
    "Anormalidade Anatômica": [
      "Hérnia incisional"
    ],
    "Procedimento Laboratorial": [
      "exames pré - operatórios"
    ],
    "Procedimento Terapêutico ou Preventivo": [
      "Gastroplastia Sleeve",
      "Re-sleeve Santoro modificada",
      "intervenção cirúrgica"
    ],
    "Conceito Temporal": [
      "há 2 anos"
    ],
    "Resultado Laboratorial ou de Teste": [
      "VE hipertrófico e comprometimento discreto da função sistólica",
      "aumento importante de AD",
      "aumento de AD",
      "insuficiencia mitral de grau discreto",
      "dupla lesão aórtica com estenose moderada e refluxo discreto",
      "aumento discreto da aorta ascendente",
      "hipertensão pulmonar de grau discreto"
    ]
  },
  "labels": {
    "retorno": {
      "capitulo": "22"
    },
    "reoperado": {
      "capitulo": "22"
    },
    "hérnia incisional": {
      "capitulo": "13"
    }
  }
}