{
  "prontuario_id": 169,
  "text": "Retorno para analise de exames laboratoriais\nTTO para cirurgia bariatrica há 1 ano\nRelata diarreia esporadica, 4-5x ao dia, fezes pastosas. Tenesmo\nDM descompensado\nHAS controlada\nDLP às custas de Trig\nHipot controlado\nObesidade grau 2\nAnsiedade não controlada\nVarizes em MMII\nDiarréia crônica a esclarecer\nMãe falecida por AVC com 65 anos e pai por IAM com 69 anos\nIrmã hipertensa e diabética\nPaciente diabética, acompanhada com medicação há 4 anos. Metformina 850 mg 3x / dia e gliclazida 60 mg 1cp antes do almoço ( não usa ).\nHipertensa, tratada \nHipotireoidismo, tratada com Puran 100mcg \nPrednisona 5mg 2 cp por dia,  para Sarcoidose há 4 anos\nFluoxetina há 2 anos\nDexclorfeniramina 2 mg / 5 ml solução oral, tomar 5 ml a cada 12h\nAAS 100 mg, 1x ao dia\nEnalapril 10 mg, 1cp a cada 12h\n** Ainda mto ansiosa e comendo demais\n** Sedentária ( parou academia por varizes )\nInternamento para Biopsia de pulmão e Cesarea\nG 5 P 3 C 1 A 1\nMenopausa há 2 anos, faz preventivo todo ano.\n ",
  "entities": {
    "Atividade de Assistência à Saúde": [
      "analise",
      "tratada",
      "Internamento",
      "preventivo"
    ],
    "Procedimento Terapêutico ou Preventivo": [
      "TTO",
      "tratada",
      "tomar",
      "Cesarea",
      "P",
      "C",
      "cirurgia bariatrica"
    ],
    "Abreviação": [
      "TTO",
      "DLP",
      "MMII",
      "AVC",
      "IAM",
      "1cp",
      "AAS",
      "G",
      "P",
      "C",
      "A",
      "DM descompensado",
      "HAS controlada",
      "2 cp",
      "mto ansiosa"
    ],
    "Sinal ou Sintoma": [
      "Tenesmo",
      "Ansiedade",
      "hipertensa",
      "Sedentária",
      "diarreia esporadica",
      "fezes pastosas",
      "DM descompensado",
      "Diarréia crônica",
      "mto ansiosa"
    ],
    "Doença ou Síndrome": [
      "DLP",
      "Varizes",
      "AVC",
      "IAM",
      "Hipotireoidismo",
      "Sarcoidose",
      "varizes",
      "DM descompensado",
      "HAS controlada",
      "Obesidade grau 2",
      "Diarréia crônica"
    ],
    "Substância Química Orgânica": [
      "Trig",
      "Metformina",
      "gliclazida",
      "Prednisona",
      "Fluoxetina",
      "Dexclorfeniramina",
      "AAS",
      "Enalapril"
    ],
    "Substância Biologicamente Ativa": [
      "Trig"
    ],
    "Achado": [
      "controlado",
      "controlada",
      "diabética",
      "Hipertensa",
      "tratada",
      "Sedentária"
    ],
    "Negação": [
      "não"
    ],
    "Localização ou Região Corporal": [
      "MMII"
    ],
    "Grupo Familiar": [
      "Mãe",
      "pai",
      "Irmã"
    ],
    "Paciente ou Grupo com Deficiência": [
      "Paciente"
    ],
    "Substância Farmacológica": [
      "medicação",
      "Metformina",
      "gliclazida",
      "Puran",
      "Prednisona",
      "Fluoxetina",
      "Dexclorfeniramina",
      "AAS",
      "Enalapril"
    ],
    "Conceito Quantitativo": [
      "1cp",
      "100mcg",
      "5mg",
      "5",
      "3",
      "1",
      "4-5x ao dia",
      "850 mg",
      "3x / dia",
      "60 mg",
      "2 cp",
      "2 mg",
      "5 ml",
      "100 mg",
      "10 mg"
    ],
    "Conceito Funcional": [
      "usa"
    ],
    "Hormônio": [
      "Puran"
    ],
    "Conceito Temporal": [
      "dia",
      "há 1 ano",
      "há 4 anos",
      "antes do almoço",
      "há 2 anos",
      "a cada 12h",
      "todo ano"
    ],
    "Evento": [
      "parou"
    ],
    "Organização Relacionada à Saúde": [
      "Internamento"
    ],
    "Função de Organismo": [
      "G",
      "P"
    ],
    "Atributo Clínico": [
      "G",
      "A"
    ],
    "Função Fisiológica": [
      "Menopausa"
    ],
    "Procedimento Diagnóstico": [
      "preventivo",
      "Biopsia de pulmão"
    ],
    "Procedimento Laboratorial": [
      "exames laboratoriais"
    ],
    "Produto Intelectual": [
      "a esclarecer"
    ]
  },
  "labels": {
    "sarcoidose": {
      "capitulo": "04"
    },
    "diarréia crônica": {
      "capitulo": "13"
    },
    "hipotireoidismo": {
      "capitulo": "05"
    },
    "tenesmo": {
      "capitulo": "21"
    },
    "diabética": {
      "capitulo": "11"
    },
    "obesidade grau 2": {
      "capitulo": "15"
    },
    "fezes pastosas": {
      "capitulo": "13"
    },
    "iam": {
      "capitulo": "19"
    },
    "dm descompensado": {
      "capitulo": "11"
    },
    "dlp": {
      "capitulo": "21"
    },
    "varizes": {
      "capitulo": "15"
    },
    "avc": {
      "capitulo": "19"
    },
    "ansiedade": {
      "capitulo": "06"
    },
    "sedentária": {
      "capitulo": "21"
    },
    "diarreia esporadica": {
      "capitulo": "13"
    },
    "mto ansiosa": {
      "capitulo": "06"
    }
  }
}