{
  "prontuario_id": 335,
  "text": "Luca, 76\n# MP desde 2002 - hx de síncope >> revisão em julho/2012\n# FA em anticoagulação\n# hipotireoidismo\n# Ex tabagista, parou há 12 anos, CT alta\n# Em uso de marevan - não sabe as outras medicações que usa\nLab 26/01/2013 - Cr 1,2 / Glic 89/ Ur 35 / TGP 41 / TGO 43 / Na 136 / K 4,7 / CT 170 / TSH 9,41 / PSA 3,73 / HDL 58 / LDL 101 / TG 56 / t4 l 1,43\nS # Pct refere que há 3 meses inciou com tontura pela manhãque melhora no decorrer do dia.\nO # mv presente, simétrico, sem ra\nbcrnfss\nabdome sp\nmmii sem edema\np # solicito que retorne semana que vem com as medicações de uso contínuo para ajustes + retorno em 3 meses\ne2 cardioDoutor Vital Brazil ",
  "entities": {
    "Abreviação": [
      "MP",
      "hx",
      "FA",
      "Lab",
      "Pct",
      "ra",
      "bcrnfss",
      "sp",
      "mmii",
      "CT alta",
      "Cr 1 , 2",
      "Glic 89/",
      "Ur 35",
      "Na 136",
      "K 4 , 7",
      "CT 170",
      "TG 56",
      "t4 l 1 , 43",
      "mv presente"
    ],
    "Sinal ou Sintoma": [
      "síncope",
      "tontura",
      "ra",
      "edema"
    ],
    "Função Patológica": [
      "FA"
    ],
    "Doença ou Síndrome": [
      "FA",
      "hipotireoidismo",
      "CT alta"
    ],
    "Procedimento Terapêutico ou Preventivo": [
      "anticoagulação"
    ],
    "Negação": [
      "não",
      "sem",
      "sp"
    ],
    "Substância Farmacológica": [
      "medicações",
      "de marevan"
    ],
    "Procedimento Laboratorial": [
      "Lab"
    ],
    "Paciente ou Grupo com Deficiência": [
      "Pct"
    ],
    "Achado": [
      "simétrico",
      "bcrnfss",
      "sp",
      "Ex tabagista",
      "mv presente"
    ],
    "Localização ou Região Corporal": [
      "abdome",
      "mmii"
    ],
    "Atividade de Assistência à Saúde": [
      "solicito",
      "ajustes",
      "retorno"
    ],
    "Resultado Laboratorial ou de Teste": [
      "Cr 1 , 2",
      "Glic 89/",
      "Ur 35",
      "TGP 41",
      "TGO 43",
      "Na 136",
      "K 4 , 7",
      "CT 170",
      "TSH 9 , 41",
      "PSA 3 , 73",
      "HDL 58",
      "LDL 101",
      "TG 56",
      "t4 l 1 , 43"
    ]
  },
  "labels": {
    "ra": {
      "capitulo": "09"
    },
    "edema": {
      "capitulo": "14"
    },
    "fa": {
      "capitulo": "11"
    },
    "ct alta": {
      "capitulo": "15"
    },
    "síncope": {
      "capitulo": "21"
    },
    "sp": {
      "capitulo": "09"
    },
    "hipotireoidismo": {
      "capitulo": "05"
    },
    "tontura": {
      "capitulo": "21"
    }
  }
}