{
  "prontuario_id": 362,
  "text": "Lucas, 63 anos\n# PO Tx cardíaco 06/10/2015 / Miocardiopatia chagásica\n# IRC agudizada no pós-operatório com necessidade de HD - com melhora após\n# Cateterismo hemodinamico em 2014 - PSAP 44 mmhg\n# Marca-passo há 7 anos // HAS // Dislipidemia // Ex-tabagista - parou há 7 anos - 19 maços/ano // IRC\n# Medicamentos: furosemida 40mg 2x / dia, azatioprina 50mg 12/12h, prednisona 20mg e everolimus 0,75mg 8/8h\n# S: SEM QUEIXAS. \nO # BEG, hipocorado 2+ / 4+, eupneico, afebril\nPA: 140X90 // FC:92\nCP: sp\nBRNF SS\nCPP: MV+ bilateral, REDUZIDO EM BASES\nABD: globoso, flacido, sem VCM ou massas palpáveis\nMMII: edema 2+ / 4+\nA # POT DE TX CARDIACO\nP # SOLICITO ECOCARDIO TT\nREDUZO PDN PARA 10MG / DIA.\nINICIO CILOSPORINA 50\nRETONRO EM DEZ\n \n \n \n ",
  "entities": {
    "Abreviação": [
      "PO",
      "IRC",
      "HD",
      "HAS",
      "BEG",
      "PA",
      "FC",
      "CP",
      "sp",
      "CPP",
      "ABD",
      "VCM",
      "MMII",
      "POT",
      "PDN",
      "Tx cardíaco",
      "MV+ bilateral",
      "TX CARDIACO",
      "ECOCARDIO TT"
    ],
    "Conceito Temporal": [
      "PO",
      "pós-operatório",
      "após",
      "12/12h",
      "8/8h",
      "POT",
      "2x / dia"
    ],
    "Doença ou Síndrome": [
      "IRC",
      "HAS",
      "Dislipidemia",
      "Miocardiopatia chagásica"
    ],
    "Sinal ou Sintoma": [
      "agudizada",
      "QUEIXAS",
      "hipocorado",
      "afebril",
      "globoso",
      "VCM",
      "edema",
      "REDUZIDO EM BASES",
      "massas palpáveis"
    ],
    "Procedimento Terapêutico ou Preventivo": [
      "HD",
      "Marca-passo",
      "Tx cardíaco",
      "Cateterismo hemodinamico",
      "TX CARDIACO"
    ],
    "Achado": [
      "melhora",
      "Ex-tabagista",
      "BEG",
      "eupneico",
      "sp",
      "flacido",
      "MV+ bilateral"
    ],
    "Atributo Clínico": [
      "PSAP",
      "PA",
      "FC",
      "CP",
      "CPP"
    ],
    "Dispositivo Médico": [
      "Marca-passo"
    ],
    "Substância Farmacológica": [
      "Medicamentos",
      "furosemida",
      "azatioprina",
      "prednisona",
      "everolimus",
      "PDN",
      "CILOSPORINA"
    ],
    "Substância Química Orgânica": [
      "furosemida",
      "PDN"
    ],
    "Conceito Quantitativo": [
      "40mg",
      "50mg",
      "20mg",
      "140X90",
      "92",
      "50",
      "44 mmhg",
      "19 maços/ano",
      "2x / dia",
      "0 , 75mg",
      "2+ / 4+",
      "10MG / DIA"
    ],
    "Negação": [
      "SEM",
      "afebril",
      "sp",
      "SS",
      "sem"
    ],
    "Localização ou Região Corporal": [
      "CP",
      "CPP",
      "ABD",
      "MMII"
    ],
    "Atividade de Assistência à Saúde": [
      "SOLICITO",
      "REDUZO",
      "INICIO"
    ],
    "Hormônio": [
      "PDN"
    ],
    "Procedimento Diagnóstico": [
      "Cateterismo hemodinamico",
      "ECOCARDIO TT"
    ],
    "Resultado Laboratorial ou de Teste": [
      "2+ / 4+"
    ]
  },
  "labels": {
    "irc": {
      "capitulo": "11"
    },
    "reduzido em bases": {
      "capitulo": "15"
    },
    "sp": {
      "capitulo": "21"
    },
    "miocardiopatia chagásica": {
      "capitulo": "11"
    },
    "mv+ bilateral": {
      "capitulo": "15"
    },
    "ex-tabagista": {
      "capitulo": "24"
    },
    "vcm": {
      "capitulo": "21"
    },
    "flacido": {
      "capitulo": "21"
    },
    "massas palpáveis": {
      "capitulo": "21"
    },
    "hipocorado": {
      "capitulo": "09"
    },
    "dislipidemia": {
      "capitulo": "05"
    },
    "edema": {
      "capitulo": "15"
    }
  }
}