{
  "prontuario_id": 651,
  "text": "Protese Metalica Aortica em 2004.\nUso: Enalapril 10 - 2cp - 12/12 / Atenolol 50 - 1cp = 12/12; Espironolactona 25 - 1xd; Sinvastatina 20 - 1x noite; Calcio 500 - 3x d;Marevan 5 - amb da ACXO; Trazodona 25 1x d.\nDispnia esporadica, edema mmii eventual, sem palpitação, dor toracica quando epigastralgia que melhoram com paracetamol.\nLab (21/01/16): Hbglic 6,34; TSH 2,15; Hb 13,5; VG 42% leuco 9610; plaq 234000; Urina I ok;  K 4,4; Cr 1,1; Gli 71; U 69; Tri 67; HDL- C 77; ColT 160; LDL- C 70;\nEcocardio (04/12/15): AE 42; DDVE 39; DSVE 23; FE 73%; VMi area 1,65; calcificada, refluxo discreto. VAo protese metalica com espessamento, e relfuxo discreto.Grad medio de 16 e max de 30. ARea de 1,12. VTri = refluxo discreto com PSAP 56mmHg. VP refluxo minimo. VE hipertrofiado., SIv 13. PPVE 14.\nPA ( sentada ): 140x60mmHg, P 76. EM pé 2 idem.\nMV normodist sem ruidos adsventicios. RCR, 2T, BNF ss++ / 6+ FAo e Mi ( +/6+.\nBEG, eupneica, acianotica, orientada, Sem edema mmii.\nHD:protese Metalica AOrtoca normofuncionante.Disfunbção diastolica.\nCD:Suspendo Espironolactona.Reduzo Sinvastatina para 10mg / noite. ACrescento Omeprazol 20 -1x d. Retonro em 6m com lab.\n \n \n \n ",
  "entities": {
    "Aminoácido, Peptídeo ou Proteína": [
      "Enalapril"
    ],
    "Substância Farmacológica": [
      "Enalapril",
      "Atenolol",
      "Espironolactona",
      "Sinvastatina",
      "Calcio",
      "Marevan",
      "Trazodona",
      "paracetamol",
      "Omeprazol"
    ],
    "Conceito Quantitativo": [
      "10",
      "2cp",
      "50",
      "1cp",
      "25",
      "1xd",
      "20",
      "1x",
      "5",
      "140x60mmHg",
      "76",
      "+/6+",
      "3x d",
      "-1x d"
    ],
    "Abreviação": [
      "2cp",
      "1cp",
      "1x",
      "mmii",
      "Lab",
      "Ecocardio",
      "PA",
      "P",
      "RCR",
      "2T",
      "BNF",
      "FAo",
      "Mi",
      "BEG",
      "HD",
      "CD",
      "lab",
      "amb da ACXO",
      "Hbglic 6 , 34",
      "Hb 13 , 5",
      "VG 42%",
      "leuco 9610",
      "plaq 234000",
      "I ok",
      "K 4 , 4",
      "Cr 1 , 1",
      "Gli 71",
      "U 69",
      "Tri 67",
      "ColT 160",
      "AE 42",
      "DDVE 39",
      "DSVE 23",
      "FE 73%",
      "VMi area 1 , 65",
      "VAo protese metalica com espessamento , e relfuxo discreto",
      "Grad medio de 16 e max de 30",
      "VTri = refluxo discreto com PSAP 56mmHg",
      "VP refluxo minimo",
      "VE hipertrofiado",
      "SIv 13",
      "PPVE 14",
      "MV normodist"
    ],
    "Conceito Temporal": [
      "12/12",
      "1xd",
      "noite",
      "eventual"
    ],
    "Substância Química Orgânica": [
      "Espironolactona",
      "Sinvastatina",
      "paracetamol"
    ],
    "Substância Biologicamente Ativa": [
      "Calcio"
    ],
    "Sinal ou Sintoma": [
      "edema",
      "palpitação",
      "epigastralgia",
      "acianotica",
      "Dispnia esporadica",
      "ruidos adsventicios",
      "Disfunbção diastolica"
    ],
    "Localização ou Região Corporal": [
      "mmii",
      "toracica"
    ],
    "Negação": [
      "sem",
      "acianotica",
      "Sem"
    ],
    "Achado": [
      "melhoram",
      "2T",
      "BNF",
      "BEG",
      "eupneica",
      "orientada",
      "MV normodist",
      "protese Metalica AOrtoca normofuncionante"
    ],
    "Procedimento Laboratorial": [
      "Lab",
      "Urina",
      "lab"
    ],
    "Procedimento Diagnóstico": [
      "Ecocardio"
    ],
    "Resultado Laboratorial ou de Teste": [
      "calcificada",
      "+/6+",
      "Hbglic 6 , 34",
      "TSH 2 , 15",
      "Hb 13 , 5",
      "VG 42%",
      "leuco 9610",
      "plaq 234000",
      "I ok",
      "K 4 , 4",
      "Cr 1 , 1",
      "Gli 71",
      "U 69",
      "Tri 67",
      "HDL- C 77",
      "ColT 160",
      "LDL- C 70",
      "AE 42",
      "DDVE 39",
      "DSVE 23",
      "FE 73%",
      "VMi area 1 , 65",
      "refluxo discreto",
      "VAo protese metalica com espessamento , e relfuxo discreto",
      "Grad medio de 16 e max de 30",
      "ARea de 1 , 12",
      "VTri = refluxo discreto com PSAP 56mmHg",
      "VP refluxo minimo",
      "VE hipertrofiado",
      "SIv 13",
      "PPVE 14",
      "Disfunbção diastolica"
    ],
    "Atributo Clínico": [
      "PA",
      "P"
    ],
    "Conceito Qualitativo": [
      "sentada"
    ],
    "Atividade de Assistência à Saúde": [
      "CD",
      "Suspendo",
      "Reduzo",
      "ACrescento"
    ],
    "Procedimento Terapêutico ou Preventivo": [
      "Reduzo",
      "ACrescento",
      "Protese Metalica Aortica"
    ],
    "Dispositivo Médico": [
      "Protese Metalica Aortica"
    ]
  },
  "labels": {
    "protese metalica aortoca normofuncionante": {
      "capitulo": "11"
    },
    "edema": {
      "capitulo": "12"
    },
    "epigastralgia": {
      "capitulo": "13"
    },
    "disfunbção diastolica": {
      "capitulo": "11"
    },
    "dispnia esporadica": {
      "capitulo": "12"
    },
    "ruidos adsventicios": {
      "capitulo": "21"
    },
    "mv normodist": {
      "capitulo": "15"
    },
    "palpitação": {
      "capitulo": "21"
    }
  }
}