{
  "prontuario_id": 924,
  "text": "TX RENAL 6 MESES DC.\nDM INSULINO DEPENDENTE > AGUARDANDO AUDITORIA PARA LANTUS SOLICITADA PELO ENDO.\nNEUROPATIA DIABÉTICA.\nMTC 5, FK 3 / 4, MS 2 / 2, BO, CVD 3CP 6,25 X2, ANLO 10, NPH 30 / 0 / 20 E R 0 / 5 / 5, CBZ 200\nS : HÁ 1 SEMANA COM DISPNEIA, TOSSE MAS SEM CONSEGUIR EXPECTORAR. NEGA FEBRE. SEM MELHORA COM SINTOMATICOS + BERTEC / ATROVENT\nSEM HX ASMA / BRONQUITE PREVIA.\nMELHORA DAS PARESTESIAS COM CBZ.\nO : PA 160/100 D,  140/100 S,   P 100,  T NR,  PESO 76KG ( GANHO PONDERAL 30 DIAS DE 3 KG).\nCORADA E HIDRATADA.\nCPP SIBILOS INS E EXPIRATORIOS, BOLHOSOS MEDIOS ATÉ APICE BILATERALMENTE.\nPC RITMO REGULAR, TAQUICARDICO.\nABD RHA+, FLÁCIDO, ENXERTO FIE SP.\nMMII EDEMA +/IV, DISCRETAMENTE MAIOR A D\nTX RENAL 6 MESES DC: CR 0,38 / 0,9 COM NS FK 8,5.\nDM INSULINO DEPENDENTE > AGUARDANDO AUDITORIA PARA LANTUS SOLICITADA PELO ENDO : HBA1C 8,5.\nNEUROPATIA DIABÉTICA.\nBRONCOESPASMO.\n* DOPPLER MMII NORMAL.\n* DOPPLER CAROTIDAS / VERTEBRAIS SEM ESTENOSES.",
  "entities": {
    "Grupo Populacional": [
      "DC"
    ],
    "Abreviação": [
      "DC",
      "ENDO",
      "MTC",
      "FK",
      "MS",
      "BO",
      "CVD",
      "ANLO",
      "NPH",
      "R",
      "CBZ",
      "BERTEC",
      "HX",
      "O",
      "PA",
      "D",
      "S",
      "P",
      "T",
      "NR",
      "CPP",
      "INS",
      "ABD",
      "RHA+",
      "FIE",
      "SP",
      "MMII",
      "DOPPLER",
      "CAROTIDAS",
      "VERTEBRAIS",
      "TX RENAL",
      "DM INSULINO DEPENDENTE",
      "3CP 6 , 25 X2",
      "NS FK 8 , 5"
    ],
    "Aminoácido, Peptídeo ou Proteína": [
      "LANTUS",
      "NPH"
    ],
    "Substância Farmacológica": [
      "LANTUS",
      "MTC",
      "FK",
      "BO",
      "CVD",
      "ANLO",
      "NPH",
      "R",
      "CBZ",
      "SINTOMATICOS",
      "BERTEC",
      "ATROVENT"
    ],
    "Atividade de Assistência à Saúde": [
      "SOLICITADA",
      "NR"
    ],
    "Organização Relacionada à Saúde": [
      "ENDO"
    ],
    "Grupo Profissional ou Ocupacional": [
      "ENDO"
    ],
    "Substância Química Orgânica": [
      "MTC",
      "FK",
      "MS",
      "CVD",
      "ANLO",
      "ATROVENT",
      "CBZ"
    ],
    "Conceito Quantitativo": [
      "5",
      "10",
      "200",
      "160/100",
      "140/100",
      "100",
      "76KG",
      "3 / 4",
      "2 / 2",
      "3CP 6 , 25 X2",
      "30 / 0 / 20",
      "0 / 5 / 5",
      "3 KG"
    ],
    "Antibiótico": [
      "MS"
    ],
    "Hormônio": [
      "NPH",
      "R"
    ],
    "Sinal ou Sintoma": [
      "DISPNEIA",
      "TOSSE",
      "EXPECTORAR",
      "FEBRE",
      "PARESTESIAS",
      "SIBILOS",
      "TAQUICARDICO",
      "EDEMA",
      "BOLHOSOS MEDIOS"
    ],
    "Negação": [
      "SEM",
      "NEGA",
      "NR"
    ],
    "Achado": [
      "MELHORA",
      "CORADA",
      "HIDRATADA",
      "RHA+",
      "FLÁCIDO",
      "SP",
      "NORMAL",
      "GANHO PONDERAL",
      "RITMO REGULAR",
      "DISCRETAMENTE MAIOR"
    ],
    "Doença ou Síndrome": [
      "ASMA",
      "BRONQUITE",
      "BRONCOESPASMO",
      "DM INSULINO DEPENDENTE",
      "NEUROPATIA DIABÉTICA"
    ],
    "Conceito Temporal": [
      "PREVIA"
    ],
    "Atributo Clínico": [
      "PA",
      "P",
      "T",
      "PESO",
      "INS",
      "EXPIRATORIOS",
      "PC"
    ],
    "Localização ou Região Corporal": [
      "CPP",
      "FIE",
      "APICE BILATERALMENTE"
    ],
    "Parte do Corpo, Órgão ou Componente Orgânico": [
      "ABD",
      "MMII",
      "CAROTIDAS",
      "VERTEBRAIS"
    ],
    "Procedimento Terapêutico ou Preventivo": [
      "ENXERTO",
      "TX RENAL"
    ],
    "Conceito Espacial": [
      "D"
    ],
    "Procedimento Diagnóstico": [
      "DOPPLER"
    ],
    "Função Patológica": [
      "ESTENOSES"
    ],
    "Resultado Laboratorial ou de Teste": [
      "ESTENOSES",
      "CR 0 , 38 / 0 , 9",
      "NS FK 8 , 5",
      "HBA1C 8 ,"
    ]
  },
  "labels": {
    "parestesias": {
      "capitulo": "08"
    },
    "flácido": {
      "capitulo": "15"
    },
    "ganho ponderal": {
      "capitulo": "05"
    },
    "bolhosos medios": {
      "capitulo": "12"
    },
    "bronquite": {
      "capitulo": "12"
    },
    "estenoses": {
      "capitulo": "23"
    },
    "discretamente maior": {
      "capitulo": "15"
    },
    "broncoespasmo": {
      "capitulo": "12"
    },
    "sibilos": {
      "capitulo": "12"
    },
    "corada": {
      "capitulo": "11"
    },
    "ritmo regular": {
      "capitulo": "08"
    },
    "dm insulino dependente": {
      "capitulo": "05"
    },
    "taquicardico": {
      "capitulo": "11"
    },
    "expectorar": {
      "capitulo": "12"
    },
    "asma": {
      "capitulo": "12"
    },
    "dispneia": {
      "capitulo": "12"
    },
    "neuropatia diabética": {
      "capitulo": "08"
    },
    "edema": {
      "capitulo": "15"
    }
  }
}