{
  "prontuario_id": 311,
  "text": "Lucas, 56 anos\n# HAS\n# ABLAÇÃO DE TAQUICARDIA ATRIAL 2009 E A SEGUNDA EM 2010\n# CATETERISMO COM AUSENCIA DE CORONARIOPATIA\n# ANALFABETISMO\nFAZ USO DE ATENOLOL 100MG 12/12H, DILTIAZEN 60MG 8/8H, ENALAPRIL 10MG 12/12H, HCTZ 25MG, MAREVAN 7,5MG.\nS # última consulta em Março/15. Mantendo-se assintomático. Traz exames.\nLab 13/5/15: PU sp,  HG sp,  Hb1AC 5%,  Cr 1,0;  HDL 50,  Ur 22,  TG 82,  LDL 202,  Glic 88,  CT 268,  AU 4,1;  T4l 1,02;  TSH 1,19;  PSA total 0,8.\nHolter 11/5/15: normal.\nETT 12/5/15: AE 36,  FE 64%,  Disfunção diastólica grau I.\nO # BEG, normocorado, hidratado, FC 64, PA 110X80.\nAC 2t ss.\nConforme discutido com Doutor Vital Brazil : Suspenso marevan, demais medicamentos mantidos.\nRetorno em 1 ano.\n\n \n \n \n ",
  "entities": {
    "Abreviação": [
      "HAS",
      "HCTZ",
      "S",
      "Lab",
      "ETT",
      "O",
      "BEG",
      "FC",
      "PA",
      "AC",
      "Hb1AC 5%",
      "Cr 1 , 0",
      "Ur 22",
      "TG 82",
      "Glic 88",
      "CT 268",
      "AE 36",
      "FE 64%"
    ],
    "Doença ou Síndrome": [
      "HAS",
      "CORONARIOPATIA",
      "Disfunção diastólica grau I"
    ],
    "Conceito Temporal": [
      "2009",
      "2010",
      "12/12H",
      "8/8H",
      "última"
    ],
    "Conceito Quantitativo": [
      "SEGUNDA",
      "100MG",
      "60MG",
      "10MG",
      "25MG",
      "64",
      "110X80",
      "7 , 5MG"
    ],
    "Procedimento Diagnóstico": [
      "CATETERISMO",
      "exames",
      "Holter",
      "ETT",
      "AC"
    ],
    "Procedimento Terapêutico ou Preventivo": [
      "CATETERISMO",
      "ABLAÇÃO DE TAQUICARDIA ATRIAL"
    ],
    "Negação": [
      "AUSENCIA",
      "assintomático",
      "sp",
      "ss"
    ],
    "Achado": [
      "ANALFABETISMO",
      "S",
      "normal",
      "BEG",
      "normocorado",
      "hidratado"
    ],
    "Substância Química Orgânica": [
      "ATENOLOL",
      "DILTIAZEN",
      "HCTZ",
      "MAREVAN",
      "marevan"
    ],
    "Substância Farmacológica": [
      "ATENOLOL",
      "DILTIAZEN",
      "ENALAPRIL",
      "HCTZ",
      "MAREVAN",
      "marevan",
      "medicamentos"
    ],
    "Atividade de Assistência à Saúde": [
      "consulta",
      "O",
      "Suspenso"
    ],
    "Sinal ou Sintoma": [
      "assintomático",
      "sp",
      "ss"
    ],
    "Procedimento Laboratorial": [
      "Lab",
      "PU"
    ],
    "Resultado Laboratorial ou de Teste": [
      "normal",
      "Hb1AC 5%",
      "Cr 1 , 0",
      "HDL 50",
      "Ur 22",
      "TG 82",
      "LDL 202",
      "Glic 88",
      "CT 268",
      "AU 4 , 1",
      "T4l 1 , 02",
      "TSH 1 , 19",
      "PSA total 0 , 8",
      "AE 36",
      "FE 64%",
      "Disfunção diastólica grau I"
    ],
    "Atributo Clínico": [
      "FC",
      "PA"
    ]
  },
  "labels": {
    "disfunção diastólica grau i": {
      "capitulo": "11"
    },
    "analfabetismo": {
      "capitulo": "V"
    },
    "coronariopatia": {
      "capitulo": "11"
    }
  }
}