{
  "prontuario_id": 103,
  "text": "LUCAS, 56,  procedente Curitiba, aposentado, casado, 4 filhos.\nAcompanhamento pela cardio após 3 pontes de safena e troca valvar na mesma operação (5/5/06).\nHMA: \" quando esquenta demais, os pés incham \".\nHMP: em 2006 desmaiou após sentir um \" sufoco \", falta de ar; após avaliação médica foi encaminhado para cateterismo;\nja ficou internado por 21 dias por cisticercose (1987); fraturou 2 costelas em 1986;\nHAS em uso de losartana 50 mg 2x / dia, atenolol 25 mg, furosemida 40 mg, atorvastatina 20 mg 2 cps, ezetimibe 10 mg, AAS 100 mg\ntambém em uso de omeprazol 20 mg 2 cps e fenitoina 100 mg.\nHMF: irmãos com HAS, mãe teve 3 IAM, irmãos com DM, irmão câncer intestino e prostata e cistolitiase, \nCHV: não fuma, não bebe, \nROS: sem queixas, somente quando está para chover, sente dor nos grampos da esternotomia mediana.\nEF: PA 100/60, FC 68, FR 20, \nAC: desdobramento de B1 (?).\nAR: MV + bilateralmente sem RA;\n \n \n \n ",
  "entities": {
    "Achado": [
      "aposentado",
      "casado",
      "bebe",
      "4 filhos",
      "MV +"
    ],
    "Atividade de Assistência à Saúde": [
      "Acompanhamento",
      "encaminhado",
      "internado",
      "avaliação médica"
    ],
    "Grupo Profissional ou Ocupacional": [
      "cardio"
    ],
    "Organização Relacionada à Saúde": [
      "cardio"
    ],
    "Abreviação": [
      "cardio",
      "HMA",
      "HAS",
      "AAS",
      "IAM",
      "DM",
      "EF",
      "PA",
      "FC",
      "FR",
      "AC",
      "AR",
      "RA",
      "MV +"
    ],
    "Conceito Temporal": [
      "após"
    ],
    "Procedimento Terapêutico ou Preventivo": [
      "operação",
      "cateterismo",
      "pontes de safena",
      "troca valvar",
      "esternotomia mediana"
    ],
    "Parte do Corpo, Órgão ou Componente Orgânico": [
      "pés",
      "costelas",
      "intestino"
    ],
    "Sinal ou Sintoma": [
      "desmaiou",
      "sufoco",
      "fuma",
      "queixas",
      "dor",
      "RA",
      "falta de ar",
      "desdobramento de B1"
    ],
    "Procedimento Diagnóstico": [
      "cateterismo",
      "EF",
      "AC",
      "AR",
      "avaliação médica"
    ],
    "Doença ou Síndrome": [
      "cisticercose",
      "HAS",
      "IAM",
      "DM",
      "cistolitiase"
    ],
    "Lesão ou Envenenamento": [
      "fraturou"
    ],
    "Conceito Quantitativo": [
      "2",
      "100/60",
      "68",
      "20",
      "50 mg 2x / dia",
      "25 mg",
      "40 mg",
      "20 mg 2 cps",
      "10 mg",
      "100 mg"
    ],
    "Substância Química Orgânica": [
      "losartana",
      "atenolol",
      "furosemida",
      "ezetimibe",
      "AAS",
      "omeprazol",
      "fenitoina"
    ],
    "Substância Farmacológica": [
      "losartana",
      "atenolol",
      "furosemida",
      "atorvastatina",
      "ezetimibe",
      "AAS",
      "omeprazol",
      "fenitoina"
    ],
    "Grupo Familiar": [
      "irmãos",
      "mãe",
      "irmão"
    ],
    "Processo Neoplásico": [
      "câncer"
    ],
    "Negação": [
      "não",
      "sem"
    ],
    "Dispositivo Médico": [
      "grampos"
    ],
    "Atributo Clínico": [
      "PA",
      "FC",
      "FR"
    ],
    "Conceito Espacial": [
      "bilateralmente"
    ]
  },
  "labels": {
    "ra": {
      "capitulo": "11"
    },
    "queixas": {
      "capitulo": "21"
    },
    "cisticercose": {
      "capitulo": "01"
    },
    "falta de ar": {
      "capitulo": "11"
    },
    "sufoco": {
      "capitulo": "11"
    },
    "mv +": {
      "capitulo": "11"
    },
    "câncer": {
      "capitulo": "02"
    },
    "fraturou": {
      "capitulo": "15"
    },
    "desdobramento de b1": {
      "capitulo": "21"
    },
    "iam": {
      "capitulo": "02"
    },
    "desmaiou": {
      "capitulo": "11"
    },
    "has": {
      "capitulo": "11"
    },
    "dor": {
      "capitulo": "21"
    },
    "cistolitiase": {
      "capitulo": "14"
    },
    "dm": {
      "capitulo": "05"
    }
  }
}