{
  "prontuario_id": 973,
  "text": "Lucas, 60 ANOS\n# HAS\n# DSLP\n# MIOCARDIOPATIA ISQUEMICA\n# 06/2013: IAMCSST - KILLIP I => ATC DA COM STENT COM SUCESSO\n# EX-TABAGISTA: 45MAÇOS/ANO PAROU QUANDO INFARTOU\n# EM USO DE: AAS 100MG, ENALAPRIL 10MG 12/12H; BRILINTA 90MG 12/12H; SELOZOK 150MG; SINVASTATINA 40MG / D; ESPIRONOLACTONA 25MG / D\n# ECOCARDIO 24/10/13: AE 44 // VD 25 // SEPTO 10 // VE 64 // FE 40% *\nVE AUMENTADO EM GRAU DISCRETO, PADRÃO DE HIPERTROFIA EXCENTRICA, DISFUNÇÃO SISTOLICA MODERADA. CONTRAÇÃO SEGMENTAR DO VE\nALTERADA. DISFUNÇÃO DIASTÓLICA GRAU II DO VE - RESTRITIVO.AE AUMENTADO EM GRAU DISCRETO. INSUFICIENCIA MITRAL DISCRETA\nS # DISPNEIA EM REPOUSO, PRINCIPALMENTE AO DEITAR. DORME COM 2 TRAVESSEIROS, REFERE DISPNEIA PAROXISTICA.\nDOR TORACICA CONTINUA DIARIAMENTE, TIPO FISGADA,DURAÇAO DE ATÉ UM MINUTO. SEM IRRADIAÇAO. SEM RELAÇAO COM ESFORÇO FISICO OU REPOUSO. \nNAO CONSEGIU REALIZAR NOVO ECOCARDIO POR FALTA DE VAGA.\nAO EXAME:\nBEG, LOTE\nPA 140X80 MMHG   FC 65\nAP MVB+, DIFUSAMENTE DIMINUIDO, S RA\nAC BCRNF SS\nMMII SP\nEX LAB:\nHBA1C 5,1%  K 5,3\nA #  DAC  IC ETIOLOGIA  ISQUEMICA\nP # SUSPENDO BRILINTA CARVEDILOL 25MG  E SUSPENDO SELOZOK\nPRESCREVO FUROSEMIDA \nAGUARDA ECOCARDIO\nR2 CM Doutor Vital Brazil ",
  "entities": {
    "Abreviação": [
      "HAS",
      "DSLP",
      "IAMCSST",
      "AAS",
      "12/12H",
      "D",
      "ECOCARDIO",
      "BEG",
      "LOTE",
      "PA",
      "FC",
      "AP",
      "MVB+",
      "S",
      "RA",
      "AC",
      "BCRNF",
      "SS",
      "MMII",
      "SP",
      "DAC",
      "R2",
      "ATC DA COM STENT",
      "AE 44",
      "VD 25",
      "VE 64",
      "FE 40%",
      "VE AUMENTADO EM GRAU DISCRETO",
      "CONTRAÇÃO SEGMENTAR DO VE ALTERADA",
      "DISFUNÇÃO DIASTÓLICA GRAU II DO VE - RESTRITIVO",
      "AE AUMENTADO EM GRAU DISCRETO",
      "EX LAB",
      "HBA1C 5 , 1%",
      "K 5 , 3",
      "IC ETIOLOGIA ISQUEMICA"
    ],
    "Doença ou Síndrome": [
      "HAS",
      "DSLP",
      "IAMCSST",
      "DAC",
      "MIOCARDIOPATIA ISQUEMICA",
      "INSUFICIENCIA MITRAL DISCRETA",
      "DISPNEIA PAROXISTICA",
      "IC ETIOLOGIA ISQUEMICA"
    ],
    "Achado": [
      "EX-TABAGISTA",
      "BEG",
      "LOTE",
      "MVB+",
      "BCRNF",
      "SP",
      "PAROU QUANDO INFARTOU",
      "DORME COM 2 TRAVESSEIROS"
    ],
    "Conceito Quantitativo": [
      "45MAÇOS/ANO",
      "100MG",
      "90MG",
      "12/12H",
      "150MG",
      "40MG",
      "25MG",
      "65",
      "140X80 MMHG"
    ],
    "Substância Farmacológica": [
      "AAS",
      "ENALAPRIL",
      "BRILINTA",
      "SELOZOK",
      "SINVASTATINA",
      "ESPIRONOLACTONA",
      "CARVEDILOL",
      "FUROSEMIDA"
    ],
    "Substância Química Orgânica": [
      "AAS",
      "ENALAPRIL",
      "BRILINTA",
      "SELOZOK",
      "SINVASTATINA",
      "ESPIRONOLACTONA",
      "CARVEDILOL",
      "FUROSEMIDA"
    ],
    "Aminoácido, Peptídeo ou Proteína": [
      "ENALAPRIL"
    ],
    "Ácido Nucleico, Nucleosídeo ou Nucleotídeo": [
      "BRILINTA"
    ],
    "Conceito Temporal": [
      "D",
      "DIARIAMENTE",
      "DURAÇAO DE ATÉ UM MINUTO"
    ],
    "Procedimento Diagnóstico": [
      "ECOCARDIO"
    ],
    "Negação": [
      "SEM",
      "NAO",
      "S",
      "SS"
    ],
    "Fenômeno ou Processo Natural": [
      "IRRADIAÇAO"
    ],
    "Sinal ou Sintoma": [
      "IRRADIAÇAO",
      "RA",
      "SS",
      "DISPNEIA EM REPOUSO",
      "DISPNEIA PAROXISTICA",
      "DOR TORACICA CONTINUA",
      "DIFUSAMENTE DIMINUIDO"
    ],
    "Conceito Qualitativo": [
      "RELAÇAO",
      "PRINCIPALMENTE AO DEITAR",
      "TIPO FISGADA"
    ],
    "Atividade Diária ou Recreativa": [
      "REPOUSO"
    ],
    "Atributo Clínico": [
      "PA",
      "FC",
      "AP",
      "AC"
    ],
    "Parte do Corpo, Órgão ou Componente Orgânico": [
      "MMII"
    ],
    "Localização ou Região Corporal": [
      "MMII"
    ],
    "Atividade de Assistência à Saúde": [
      "SUSPENDO",
      "PRESCREVO"
    ],
    "Grupo Profissional ou Ocupacional": [
      "R2"
    ],
    "Classificação": [
      "KILLIP I"
    ],
    "Procedimento Terapêutico ou Preventivo": [
      "ATC DA COM STENT"
    ],
    "Resultado Laboratorial ou de Teste": [
      "AE 44",
      "VD 25",
      "SEPTO 10",
      "VE 64",
      "FE 40%",
      "VE AUMENTADO EM GRAU DISCRETO",
      "PADRÃO DE HIPERTROFIA EXCENTRICA",
      "DISFUNÇÃO SISTOLICA MODERADA",
      "CONTRAÇÃO SEGMENTAR DO VE ALTERADA",
      "DISFUNÇÃO DIASTÓLICA GRAU II DO VE - RESTRITIVO",
      "AE AUMENTADO EM GRAU DISCRETO",
      "INSUFICIENCIA MITRAL DISCRETA",
      "HBA1C 5 , 1%",
      "K 5 , 3"
    ],
    "Procedimento Laboratorial": [
      "EX LAB"
    ]
  },
  "labels": {
    "ra": {
      "capitulo": "11"
    },
    "mvb+": {
      "capitulo": "11"
    },
    "dor toracica continua": {
      "capitulo": "21"
    },
    "sp": {
      "capitulo": "08"
    },
    "insuficiencia mitral discreta": {
      "capitulo": "11"
    },
    "dslp": {
      "capitulo": "06"
    },
    "ex-tabagista": {
      "capitulo": "24"
    },
    "ic etiologia isquemica": {
      "capitulo": "11"
    },
    "ss": {
      "capitulo": "11"
    },
    "dac": {
      "capitulo": "11"
    },
    "difusamente diminuido": {
      "capitulo": "21"
    },
    "dispneia em repouso": {
      "capitulo": "12"
    },
    "bcrnf": {
      "capitulo": "08"
    },
    "dispneia paroxistica": {
      "capitulo": "12"
    },
    "iamcsst": {
      "capitulo": "24"
    },
    "has": {
      "capitulo": "06"
    },
    "miocardiopatia isquemica": {
      "capitulo": "11"
    },
    "beg": {
      "capitulo": "21"
    },
    "dorme com 2 travesseiros": {
      "capitulo": "21"
    },
    "parou quando infartou": {
      "capitulo": "24"
    }
  }
}