{
  "prontuario_id": 712,
  "text": "Lucas, 68 anos, natural de Colombro e mora em Barreirinha há 66 anos, casada, do lar, dois filhos\nQP Dor retroesternal, em repouso, em pontada, sem irradiação, com duração de 10 min, escala 3, acorda a noite por causa da dor, desde a angioplastia\nHMA Ao realizar um ECG para realizaçõa de cirurgia de catarata, foi encaminhada um teste ergométrico (30/09/15) que revelou a presença de um IAM, uma semana depois realizou angioplasta (05/10/15).\nHMP Episódio de infarto no dia 05 de outubro, realizaçõa de cateterismo cardíaco esquerdo, coronariografia com ventriculografia esquerda\nHipotireoidismo há 5 anos\nHMF Pai falecido por trombose\nmãe falecida \nIrmão com câncer de próstata \nCHV\nAlimentação saudável\nNega etilismo e tabagismo \nAlergia a penicilina\nRS\nObstipação há 1 mês, chegando a ficar 5 dias sem ir ao banheiro\nAmnésia recente\nSente muito desânimo, angústia, humor deprimido\nInsônia terminal\nMuito cansaço\nMedicação\nClopidogrel 75mg, AAs 100mg, Enalapril 10mg, Omeprazol 20mg, Levotiroxina 50 microgramas, Sinvastatina 40mg\n \n \n \n ",
  "entities": {
    "Sinal ou Sintoma": [
      "QP",
      "irradiação",
      "Obstipação",
      "angústia",
      "Dor retroesternal",
      "Amnésia recente",
      "humor deprimido",
      "Insônia terminal"
    ],
    "Abreviação": [
      "QP",
      "ECG",
      "IAM",
      "RS",
      "AAs",
      "10 min"
    ],
    "Conceito Qualitativo": [
      "pontada"
    ],
    "Negação": [
      "sem",
      "Nega"
    ],
    "Fenômeno ou Processo Natural": [
      "irradiação"
    ],
    "Procedimento Terapêutico ou Preventivo": [
      "angioplastia",
      "angioplasta",
      "Medicação",
      "cirurgia de catarata",
      "cateterismo cardíaco esquerdo",
      "coronariografia com ventriculografia esquerda"
    ],
    "Procedimento Diagnóstico": [
      "ECG",
      "teste ergométrico",
      "coronariografia com ventriculografia esquerda"
    ],
    "Atividade de Assistência à Saúde": [
      "realizaçõa",
      "encaminhada"
    ],
    "Doença ou Síndrome": [
      "IAM",
      "infarto",
      "Hipotireoidismo",
      "trombose",
      "etilismo",
      "tabagismo",
      "câncer de próstata"
    ],
    "Resultado Laboratorial ou de Teste": [
      "IAM"
    ],
    "Grupo Familiar": [
      "Pai",
      "mãe",
      "Irmão"
    ],
    "Função Patológica": [
      "trombose"
    ],
    "Substância Farmacológica": [
      "penicilina",
      "Medicação",
      "Clopidogrel",
      "AAs",
      "Enalapril",
      "Omeprazol",
      "Levotiroxina",
      "Sinvastatina"
    ],
    "Antibiótico": [
      "penicilina"
    ],
    "Atributo Clínico": [
      "RS"
    ],
    "Achado": [
      "desânimo",
      "cansaço",
      "Alimentação saudável"
    ],
    "Substância Química Orgânica": [
      "Clopidogrel",
      "AAs",
      "Enalapril",
      "Omeprazol",
      "Levotiroxina",
      "Sinvastatina"
    ],
    "Conceito Quantitativo": [
      "75mg",
      "100mg",
      "10mg",
      "20mg",
      "40mg",
      "10 min",
      "50 microgramas"
    ],
    "Aminoácido, Peptídeo ou Proteína": [
      "Enalapril",
      "Levotiroxina"
    ],
    "Hormônio": [
      "Levotiroxina"
    ],
    "Classificação": [
      "escala 3"
    ],
    "Conceito Temporal": [
      "há 5 anos",
      "há 1 mês"
    ],
    "Processo Neoplásico": [
      "câncer de próstata"
    ],
    "Disfunção Mental ou Comportamental": [
      "Amnésia recente",
      "humor deprimido",
      "Insônia terminal"
    ]
  },
  "labels": {
    "insônia terminal": {
      "capitulo": "07"
    },
    "humor deprimido": {
      "capitulo": "06"
    },
    "infarto": {
      "capitulo": "11"
    },
    "amnésia recente": {
      "capitulo": "21"
    },
    "trombose": {
      "capitulo": "11"
    },
    "iam": {
      "capitulo": "11"
    },
    "obstipação": {
      "capitulo": "13"
    },
    "desânimo": {
      "capitulo": "06"
    },
    "qp": {
      "capitulo": "21"
    },
    "dor retroesternal": {
      "capitulo": "09"
    },
    "irradiação": {
      "capitulo": "09"
    },
    "cansaço": {
      "capitulo": "06"
    },
    "hipotireoidismo": {
      "capitulo": "05"
    },
    "câncer de próstata": {
      "capitulo": "02"
    },
    "angústia": {
      "capitulo": "06"
    }
  }
}