{
  "prontuario_id": 444,
  "text": "HAS.\nUso: Atenol 50 - 1xd. Enalapril 5 - 12/12h.\nSem queixas cardiovasculares.\nNa ultima consulta foi solictado ecocardio porque tinha estenose aortica discreta somente e cardiomiopatia hipertensiva.\nEcocardio (13/02/15): AE = 45; SIV = PPVE = 14mm; DDVE = 48; DSVE = 29; FE = 69%. VMi = folhetos espessados, abertura preservada, refluxo discreto, fluxo diastólico com padrão E< A VAo = cúspides calcificadas, com dupla lesão; Grad max de 54 e medio de 28mmHg. VP = ok; Vtri = folhetos espessados, abertura preservada, insuficiente, PSAP = 39mmHg. VE = hipertrofiado, cavidade, função sistólica e contração preservadas, alt de relaxamento. AD = aumentado.\nBEG, eupneico, acianotico, anicterico, sem edema mmii. PA ( sentado ) : 160x80mmHg, P = 100 spm, Fr = 12 rpm. MV normodist sem ruidos . RCR, 2T, taquicardico, ss ++/6+, crsec / decres, FAO, irradiação para todo o precórdio.\nObs ? paciente ansioso duarnte a constulta; refere PA normal fora da consulta.\nCD: mantida. Retorno 12m com novo ecocardio.\n \n \n \n ",
  "entities": {
    "Abreviação": [
      "HAS",
      "1xd",
      "12/12h",
      "ecocardio",
      "Ecocardio",
      "BEG",
      "mmii",
      "PA",
      "P",
      "Fr",
      "FAO",
      "CD",
      "12m",
      "AE = 45",
      "SIV = PPVE = 14mm",
      "DDVE = 48",
      "DSVE = 29",
      "FE = 69%",
      "Grad max de 54 e medio de 28mmHg",
      "VP = ok",
      "Vtri = folhetos espessados , abertura preservada , insuficiente",
      "PSAP = 39mmHg",
      "alt de relaxamento",
      "AD = aumentado",
      "100 spm",
      "12 rpm",
      "MV normodist",
      "RCR , 2T",
      "ss ++/6+ , crsec / decres"
    ],
    "Doença ou Síndrome": [
      "HAS",
      "cardiomiopatia hipertensiva"
    ],
    "Substância Química Orgânica": [
      "Atenol",
      "Enalapril"
    ],
    "Substância Farmacológica": [
      "Atenol",
      "Enalapril"
    ],
    "Conceito Quantitativo": [
      "50",
      "1xd",
      "5",
      "12/12h",
      "160x80mmHg",
      "100 spm",
      "12 rpm"
    ],
    "Aminoácido, Peptídeo ou Proteína": [
      "Enalapril"
    ],
    "Conceito Temporal": [
      "12/12h",
      "12m"
    ],
    "Negação": [
      "Sem",
      "acianotico",
      "anicterico",
      "sem"
    ],
    "Sistema Corporal": [
      "cardiovasculares"
    ],
    "Atividade de Assistência à Saúde": [
      "consulta",
      "solictado",
      "constulta",
      "CD",
      "mantida",
      "Retorno"
    ],
    "Procedimento Diagnóstico": [
      "ecocardio",
      "Ecocardio"
    ],
    "Achado": [
      "BEG",
      "eupneico",
      "MV normodist",
      "RCR , 2T"
    ],
    "Sinal ou Sintoma": [
      "acianotico",
      "anicterico",
      "edema",
      "ruidos",
      "taquicardico",
      "ansioso",
      "ss ++/6+ , crsec / decres"
    ],
    "Parte do Corpo, Órgão ou Componente Orgânico": [
      "mmii"
    ],
    "Atributo Clínico": [
      "PA",
      "P",
      "Fr"
    ],
    "Localização ou Região Corporal": [
      "FAO",
      "precórdio"
    ],
    "Paciente ou Grupo com Deficiência": [
      "paciente"
    ],
    "Resultado Laboratorial ou de Teste": [
      "estenose aortica discreta",
      "AE = 45",
      "SIV = PPVE = 14mm",
      "DDVE = 48",
      "DSVE = 29",
      "FE = 69%",
      "folhetos espessados , abertura preservada",
      "refluxo discreto , fluxo diastólico com padrão E&lt; A",
      "cúspides calcificadas , com dupla lesão",
      "Grad max de 54 e medio de 28mmHg",
      "VP = ok",
      "Vtri = folhetos espessados , abertura preservada , insuficiente",
      "PSAP = 39mmHg",
      "hipertrofiado , cavidade , função sistólica e contração preservadas",
      "alt de relaxamento",
      "AD = aumentado"
    ]
  },
  "labels": {
    "rcr, 2t": {
      "capitulo": "08"
    },
    "edema": {
      "capitulo": "14"
    },
    "has": {
      "capitulo": "11"
    },
    "ansioso": {
      "capitulo": "06"
    },
    "taquicardico": {
      "capitulo": "11"
    },
    "cardiomiopatia hipertensiva": {
      "capitulo": "11"
    },
    "ss ++/6+, crsec / decres": {
      "capitulo": "08"
    },
    "ruidos": {
      "capitulo": "09"
    }
  }
}