{
  "prontuario_id": 750,
  "text": "Lucas, 65 anos\n# MCP dilatada - IDIOPÁTICA\nCF II-III OSCILANTE.\n** PROTOCOLO DE TX CARDIACO - INDICE CARDIACO 3,44 **\n*** Em uso de: Omeprazol 20mg / d, AAS 100mg / d, Losartan 50mg 12/12hs, Espironolactona 25mg / d, Hidralazina 50mg 12/12hs, Carvedilol 12,5mg 12/12hs\n# Exames:\nCAT 09/06/2014: ausência de coronariopatia obstrutiva crítica\nIC 3,449 pré / 3,602 pós\nRVP em woods 0,217 pré / 0,147 pós\nS # Não coletou laboratoriais devido à greve de ônibus. Apresentou episodio de dor torácica há 2 dias - retroesternal e em MSE, em queimação, duração de várias horas, pior de acordo com movimentação do tronco. Dispneia para moderados esforços CF II, às vezes para pequenos esforços. Sem ortopneia. Às vezes apresenta dor torácica associada à caminhada mais rápida. Nega sincope e palpitações. Edema de MMII esporadicamente.\nO # Pte em BEG, eupneico, corado, hidratado\nPA 106/60 FC 60\nSEM TURGÊNCIA JUGULAR\nCPP - MV + BILATERAL, CREPITANTES EM BASE DIREITA\nPC - BC HIPOFONETICAS, SEM SOPROS, ICTUS DESVIADO\nABDOME - SEM VCM, DOR A PALPAÇÃO DE FLANCO E FIE\nMMII - SEM EDEMA\nA # MCP dilatada CF II / III\nP # MEDICAÇÕES MANTIDAS. RETORNO EM 2 MESES COM NOVO LAB\nR4 Doutor Vital Brazil ",
  "entities": {
    "Substância Farmacológica": [
      "Omeprazol",
      "AAS",
      "Losartan",
      "Espironolactona",
      "Hidralazina",
      "Carvedilol",
      "MEDICAÇÕES"
    ],
    "Substância Química Orgânica": [
      "Omeprazol",
      "AAS",
      "Losartan",
      "Espironolactona",
      "Hidralazina",
      "Carvedilol"
    ],
    "Conceito Quantitativo": [
      "20mg",
      "100mg",
      "50mg",
      "25mg",
      "106/60",
      "60",
      "12 , 5mg"
    ],
    "Conceito Temporal": [
      "d",
      "12/12hs",
      "esporadicamente",
      "há 2 dias",
      "duração de várias horas",
      "2 MESES"
    ],
    "Abreviação": [
      "d",
      "AAS",
      "12/12hs",
      "CAT",
      "MSE",
      "MMII",
      "Pte",
      "BEG",
      "PA",
      "FC",
      "CPP",
      "PC",
      "VCM",
      "LAB",
      "R4",
      "MCP dilatada - IDIOPÁTICA CF II-III OSCILANTE",
      "PROTOCOLO DE TX CARDIACO",
      "IC 3 , 449 pré / 3 , 602 pós",
      "RVP em woods",
      "CF II",
      "MV + BILATERAL",
      "BC HIPOFONETICAS",
      "MCP dilatada CF II / III"
    ],
    "Resultado Laboratorial ou de Teste": [
      "Exames",
      "LAB",
      "INDICE CARDIACO 3 , 44",
      "ausência de coronariopatia obstrutiva crítica",
      "IC 3 , 449 pré / 3 , 602 pós",
      "RVP em woods",
      "0 , 217 pré / 0 , 147 pós"
    ],
    "Procedimento Diagnóstico": [
      "CAT",
      "PALPAÇÃO"
    ],
    "Negação": [
      "Não",
      "Sem",
      "Nega",
      "SEM"
    ],
    "Atividade de Assistência à Saúde": [
      "coletou",
      "MANTIDAS",
      "RETORNO"
    ],
    "Procedimento Laboratorial": [
      "laboratoriais"
    ],
    "Localização ou Região Corporal": [
      "retroesternal",
      "FLANCO",
      "FIE"
    ],
    "Parte do Corpo, Órgão ou Componente Orgânico": [
      "MSE",
      "MMII",
      "ABDOME"
    ],
    "Sinal ou Sintoma": [
      "queimação",
      "Dispneia",
      "ortopneia",
      "sincope",
      "palpitações",
      "Edema",
      "SOPROS",
      "VCM",
      "EDEMA",
      "dor torácica",
      "TURGÊNCIA JUGULAR",
      "CREPITANTES EM BASE DIREITA",
      "BC HIPOFONETICAS",
      "ICTUS DESVIADO"
    ],
    "Paciente ou Grupo com Deficiência": [
      "Pte"
    ],
    "Achado": [
      "BEG",
      "eupneico",
      "corado",
      "hidratado",
      "MV + BILATERAL"
    ],
    "Atributo Clínico": [
      "PA",
      "FC",
      "CPP",
      "PC"
    ],
    "Procedimento Terapêutico ou Preventivo": [
      "MEDICAÇÕES"
    ],
    "Grupo Profissional ou Ocupacional": [
      "R4",
      "Doutor"
    ],
    "Doença ou Síndrome": [
      "MCP dilatada - IDIOPÁTICA CF II-III OSCILANTE",
      "MCP dilatada CF II / III"
    ],
    "Produto Intelectual": [
      "PROTOCOLO DE TX CARDIACO"
    ],
    "Atividade Diária ou Recreativa": [
      "moderados esforços",
      "pequenos esforços",
      "caminhada mais rápida"
    ],
    "Classificação": [
      "CF II"
    ]
  },
  "labels": {
    "ortopneia": {
      "capitulo": "12"
    },
    "mcp dilatada - idiopática cf ii-iii oscilante": {
      "capitulo": "11"
    },
    "crepitantes em base direita": {
      "capitulo": "21"
    },
    "mcp dilatada cf ii / iii": {
      "capitulo": "11"
    },
    "vcm": {
      "capitulo": "13"
    },
    "queimação": {
      "capitulo": "21"
    },
    "palpitações": {
      "capitulo": "21"
    },
    "dispneia": {
      "capitulo": "12"
    },
    "mv + bilateral": {
      "capitulo": "21"
    },
    "edema": {
      "capitulo": "15"
    },
    "turgência jugular": {
      "capitulo": "11"
    },
    "sopros": {
      "capitulo": "21"
    },
    "sincope": {
      "capitulo": "21"
    },
    "ictus desviado": {
      "capitulo": "08"
    },
    "bc hipofoneticas": {
      "capitulo": "21"
    },
    "dor torácica": {
      "capitulo": "12"
    }
  }
}