{
  "prontuario_id": 804,
  "text": "Ecocardio (17/11/14): AE = 50; SIV = PPVE = 12; DDVE = 57; DSVE = 43; FE = 48%; VMi = protese biologica com espessamentoi de seus folhetos;mobioidade adequada e rgurgitação moderada a importante. Gra max de 25  e medio de 13 Area de 2.\nVAo = cuspides calcificadas com mobilidade comprometida. Grad max de 55  e medio de 33. Regurgitação moderada. VTri = abertura adequada coim refluxo disreto. PSAP = 40mmHg.\nAssintomático. Não trouxe receita.\nEx Fisico: BEG, eupneico, acianotico, anicterico, sem edema mmii. PA ( sentado ): 120x70mmHg, P = 56. MV OK. RCR 2T, BNF ss++/6+ FAo e Mi e SD +/6+.\nCD: mantida 6m.\n \n \n \n ",
  "entities": {
    "Abreviação": [
      "Ecocardio",
      "BEG",
      "mmii",
      "PA",
      "P",
      "BNF",
      "CD",
      "AE = 50",
      "SIV = PPVE = 12",
      "DDVE = 57",
      "DSVE = 43",
      "FE = 48%",
      "VMi = protese biologica com espessamentoi de seus folhetos",
      "Gra max de 25 e medio de 13",
      "VAo = cuspides calcificadas com mobilidade comprometida",
      "Grad max de 55 e medio de 33",
      "VTri = abertura adequada coim refluxo disreto",
      "PSAP = 40mmHg",
      "Ex Fisico",
      "MV OK",
      "RCR 2T",
      "SD +/6+"
    ],
    "Procedimento Diagnóstico": [
      "Ecocardio"
    ],
    "Negação": [
      "Assintomático",
      "Não",
      "acianotico",
      "anicterico",
      "sem"
    ],
    "Sinal ou Sintoma": [
      "Assintomático",
      "acianotico",
      "anicterico",
      "edema",
      "SD +/6+"
    ],
    "Atividade de Assistência à Saúde": [
      "receita",
      "CD",
      "mantida"
    ],
    "Achado": [
      "BEG",
      "eupneico",
      "BNF",
      "MV OK",
      "RCR 2T"
    ],
    "Localização ou Região Corporal": [
      "mmii"
    ],
    "Parte do Corpo, Órgão ou Componente Orgânico": [
      "mmii"
    ],
    "Atributo Clínico": [
      "PA",
      "P"
    ],
    "Conceito Quantitativo": [
      "120x70mmHg",
      "56"
    ],
    "Resultado Laboratorial ou de Teste": [
      "AE = 50",
      "SIV = PPVE = 12",
      "DDVE = 57",
      "DSVE = 43",
      "FE = 48%",
      "VMi = protese biologica com espessamentoi de seus folhetos",
      "mobioidade adequada e rgurgitação moderada a importante",
      "Gra max de 25 e medio de 13",
      "Area de 2",
      "VAo = cuspides calcificadas com mobilidade comprometida",
      "Grad max de 55 e medio de 33",
      "Regurgitação moderada",
      "VTri = abertura adequada coim refluxo disreto",
      "PSAP = 40mmHg"
    ]
  },
  "labels": {
    "edema": {
      "capitulo": "12"
    },
    "beg": {
      "capitulo": "09"
    },
    "bnf": {
      "capitulo": "V"
    },
    "rcr 2t": {
      "capitulo": "21"
    },
    "sd +/6+": {
      "capitulo": "15"
    }
  }
}