{
  "prontuario_id": 128,
  "text": "# IAM 2013 + ATC\n# HAS\n#  DM\n#  TBG ATIVA\n\n# ECG FC 50 BS ZEI AS IS AL.\n#  CINTILO: FIBROSE PERSISTENTE APICE E MEDIO APICAL DA P ANTERIOR E ANTERO SEPTAL DISCRETA ISQUEMIA ASSOCIADA,\nFE 23-28%.\n# CINTILOGRAFIA 16/01/15: HIPOPERFUSÃO ACENTUADA E PERSISTENTE NO APICE E MEDIO APICAL PAREDE ANTERIOR E ANTERO SEPTAL VE. HIPOCINESIA DIFUSA DAS PAREDES DO VE, ANTERIOR E APICAL. FE 23---28%.\n# TESTE ESFORÇO 16/01/15: AUSENCIA DE MANIFESTAÇÕES ELETROCARDIOGRAFICAS SUJESTIVAS DE ISQUEMIA MIOCARDICA.\n\nEM USO DE: AAS 100MG DIA, CARVEDILOL 25MG DIA, ENALAPRIL 10MG 1/2CP 1X DIA, METFORMINA 850MG 1CP AO DIA, SINVASTATINA 80MG A NOITE.\n\nS: PACIENTE REFERE CONSEGUIR REALIZAR AS ATIVIDADES DIARIAS SEM LIMITAÇÕES, APRESENTANDO APENAS QUADRO DE DISPNEIA AOS GRANDES ESFORÇOS.\nNEGA DISPNEIA PAROXISTICA NOTURNA OU ORTOPNEIA.\nREFERE EPISOIDOS ESPORADICOS DE PALPITAÇÃO, SEM SINTOMAS ASSOCIADOS.\nNEGA DOR TORACICA.\n\n\nEXAME FISICO:\nBEG, HIDRATADA, NORMOCORADA, ACIANOTICA.\nFC 64, PA 130/80, SAT 97%, P: 61KG.\nAFEBRIL,\nACV: BRNF2T SEM SOPRO AUDIVEL.\n\nP: oTIMIZADO TRATAMENTO COM CARVEDILOL 12,5MG 12/12 H, ENALAPRIL 5 MG 12/12H E INICIADO ESPIRONOLACTONA 25MG DE MANHA.\nSOLICITADO EXAMES LABORATORIAIS DE CONTROLE.\nSOLICITADO ECOCARDIO DE CONTROLE.\nORIENTADA A CESSAR O TABAGISMO E ENCAMINHADA AO PROGRAMA DE ABANDONO AO TABAGISMO.\nRETORNO COM EXAMES.\n\nR3 CARDIO LUCAS\nDoutor Vital Brazil ",
  "entities": {
    "Abreviação": [
      "IAM",
      "ATC",
      "HAS",
      "DM",
      "ECG",
      "BS",
      "ZEI",
      "AS",
      "IS",
      "AL",
      "CINTILO",
      "AAS",
      "S",
      "BEG",
      "FC",
      "PA",
      "P",
      "ACV",
      "ECOCARDIO",
      "TBG ATIVA",
      "FE 23-28%",
      "PAREDE ANTERIOR E ANTERO SEPTAL VE",
      "HIPOCINESIA DIFUSA DAS PAREDES DO VE",
      "FE 23---28%",
      "SAT 97%"
    ],
    "Doença ou Síndrome": [
      "IAM",
      "HAS",
      "DM",
      "TBG ATIVA",
      "DISPNEIA PAROXISTICA NOTURNA"
    ],
    "Achado": [
      "IAM",
      "DM",
      "S",
      "BEG",
      "HIDRATADA",
      "NORMOCORADA",
      "REFERE CONSEGUIR REALIZAR AS ATIVIDADES DIARIAS"
    ],
    "Conceito Temporal": [
      "2013",
      "DIA",
      "12/12H",
      "MANHA",
      "1/2CP 1X DIA",
      "1CP AO DIA",
      "A NOITE",
      "12/12 H"
    ],
    "Procedimento Terapêutico ou Preventivo": [
      "ATC",
      "CESSAR O TABAGISMO"
    ],
    "Procedimento Diagnóstico": [
      "ECG",
      "CINTILO",
      "CINTILOGRAFIA",
      "ACV",
      "ECOCARDIO",
      "TESTE ESFORÇO",
      "EXAME FISICO"
    ],
    "Resultado Laboratorial ou de Teste": [
      "BS",
      "ZEI",
      "AS",
      "IS",
      "AL",
      "FC 50",
      "FIBROSE PERSISTENTE APICE E MEDIO APICAL DA P ANTERIOR",
      "ANTERO SEPTAL DISCRETA ISQUEMIA ASSOCIADA",
      "FE 23-28%",
      "HIPOPERFUSÃO ACENTUADA E PERSISTENTE NO APICE E MEDIO APICAL",
      "PAREDE ANTERIOR E ANTERO SEPTAL VE",
      "HIPOCINESIA DIFUSA DAS PAREDES DO VE",
      "ANTERIOR E APICAL",
      "FE 23---28%",
      "AUSENCIA DE MANIFESTAÇÕES ELETROCARDIOGRAFICAS SUJESTIVAS DE ISQUEMIA MIOCARDICA"
    ],
    "Substância Química Orgânica": [
      "AAS",
      "CARVEDILOL",
      "ENALAPRIL",
      "METFORMINA",
      "SINVASTATINA",
      "ESPIRONOLACTONA"
    ],
    "Substância Farmacológica": [
      "AAS",
      "CARVEDILOL",
      "ENALAPRIL",
      "METFORMINA",
      "SINVASTATINA",
      "ESPIRONOLACTONA"
    ],
    "Conceito Quantitativo": [
      "100MG",
      "25MG",
      "10MG",
      "850MG",
      "80MG",
      "64",
      "130/80",
      "61KG",
      "12 , 5MG",
      "5 MG"
    ],
    "Aminoácido, Peptídeo ou Proteína": [
      "ENALAPRIL"
    ],
    "Paciente ou Grupo com Deficiência": [
      "PACIENTE"
    ],
    "Negação": [
      "SEM",
      "NEGA",
      "ACIANOTICA",
      "AFEBRIL"
    ],
    "Sinal ou Sintoma": [
      "LIMITAÇÕES",
      "ORTOPNEIA",
      "ACIANOTICA",
      "AFEBRIL",
      "DISPNEIA AOS GRANDES ESFORÇOS",
      "DISPNEIA PAROXISTICA NOTURNA",
      "EPISOIDOS ESPORADICOS DE PALPITAÇÃO",
      "SINTOMAS ASSOCIADOS",
      "DOR TORACICA",
      "SOPRO AUDIVEL"
    ],
    "Atributo Clínico": [
      "FC",
      "PA",
      "P",
      "SAT 97%"
    ],
    "Atributo de Organismo": [
      "P"
    ],
    "Produto Intelectual": [
      "P"
    ],
    "Atividade de Assistência à Saúde": [
      "INICIADO",
      "SOLICITADO",
      "oTIMIZADO TRATAMENTO"
    ],
    "Procedimento Laboratorial": [
      "EXAMES LABORATORIAIS"
    ],
    "Organização Relacionada à Saúde": [
      "PROGRAMA DE ABANDONO AO TABAGISMO"
    ]
  },
  "labels": {
    "ortopneia": {
      "capitulo": "12"
    },
    "tbg ativa": {
      "capitulo": "11"
    },
    "dor toracica": {
      "capitulo": "21"
    },
    "acianotica": {
      "capitulo": "14"
    },
    "dispneia aos grandes esforços": {
      "capitulo": "12"
    },
    "episoidos esporadicos de palpitação": {
      "capitulo": "11"
    },
    "iam": {
      "capitulo": "11"
    },
    "sintomas associados": {
      "capitulo": "21"
    },
    "has": {
      "capitulo": "11"
    },
    "dm": {
      "capitulo": "11"
    },
    "limitações": {
      "capitulo": "V"
    },
    "sopro audivel": {
      "capitulo": "10"
    }
  }
}