{
  "prontuario_id": 1,
  "text": "has / 10 anos/maço.\naas 100 / carvedilol 25 1x/d / sinva 40 mg 1 x/d / enalapril 1 cp 12/12 hs / furo 40 mg 1 x/d.\nfez cat + angioplastia 2013.\nECOCARDIO 25/11/13 - VE HIPERTROFIADO COM DIMENSÃO INTERNA AUMENTADA E FUNÇÃO GLOBAL MODERADAMENTE DIMINUIDA POR ACINESIA\nMEDIO APICAL PAREDE ANTERO SEPTAL. AUMENTO DE AE. REFLUXO MITRAL DISCRETO. ECTASIA DA RAIZ AÓRTICA. REFLUXO AÓRTICO DISCRETO.\nFEVE: 47%.\n01/03/11: ECODOPPLER ARTERIAR MMII ESQ: ESTENOSE APROX DE 75% DA BIFURCAÇÃO DOS VASOS FEMORAIS.\nLESOES SUBSEGMENTARES DAS ART, TIBIAL ANTERIOR E FIBULAR.\nOCLUSÃO DA ARTERIA POPLITEA MEDIO DISTAL.\nESTENOSE > A OCLUSAO DA ARTERIA TIBIAL POSTERIOR.\nquadro de disfunção sistólica após iam, perdeu seguimento.\n \n \n ",
  "entities": {
    "Abreviação": [
      "has",
      "aas",
      "1x/d",
      "sinva",
      "furo",
      "cat",
      "ECOCARDIO",
      "iam",
      "1 x/d",
      "1 cp",
      "VE HIPERTROFIADO COM DIMENSÃO INTERNA AUMENTADA",
      "AUMENTO DE AE",
      "FEVE : 47%",
      "ECODOPPLER ARTERIAR MMII ESQ",
      "ESTENOSE APROX DE 75% DA BIFURCAÇÃO DOS VASOS FEMORAIS",
      "LESOES SUBSEGMENTARES DAS ART"
    ],
    "Doença ou Síndrome": [
      "has",
      "iam"
    ],
    "Achado": [
      "has",
      "perdeu seguimento"
    ],
    "Substância Farmacológica": [
      "aas",
      "carvedilol",
      "sinva",
      "enalapril",
      "furo"
    ],
    "Substância Química Orgânica": [
      "aas",
      "carvedilol",
      "sinva",
      "furo"
    ],
    "Conceito Quantitativo": [
      "100",
      "25",
      "1x/d",
      "10 anos/maço",
      "40 mg",
      "1 x/d",
      "1 cp"
    ],
    "Conceito Temporal": [
      "1x/d",
      "após",
      "1 x/d",
      "12/12 hs"
    ],
    "Aminoácido, Peptídeo ou Proteína": [
      "enalapril"
    ],
    "Procedimento Terapêutico ou Preventivo": [
      "cat",
      "angioplastia"
    ],
    "Procedimento Diagnóstico": [
      "ECOCARDIO",
      "ECODOPPLER ARTERIAR MMII ESQ"
    ],
    "Resultado Laboratorial ou de Teste": [
      "VE HIPERTROFIADO COM DIMENSÃO INTERNA AUMENTADA",
      "E FUNÇÃO GLOBAL MODERADAMENTE DIMINUIDA",
      "POR ACINESIA MEDIO APICAL PAREDE ANTERO SEPTAL",
      "AUMENTO DE AE",
      "REFLUXO MITRAL",
      "ECTASIA DA RAIZ AÓRTICA",
      "REFLUXO AÓRTICO DISCRETO",
      "FEVE : 47%",
      "ESTENOSE APROX DE 75% DA BIFURCAÇÃO DOS VASOS FEMORAIS",
      "LESOES SUBSEGMENTARES DAS ART",
      "TIBIAL ANTERIOR E FIBULAR",
      "OCLUSÃO DA ARTERIA POPLITEA MEDIO DISTAL",
      "ESTENOSE &gt; A OCLUSAO DA ARTERIA TIBIAL POSTERIOR"
    ],
    "Função Patológica": [
      "disfunção sistólica"
    ]
  },
  "labels": {
    "disfunção sistólica": {
      "capitulo": "11"
    },
    "perdeu seguimento": {
      "capitulo": "24"
    },
    "iam": {
      "capitulo": "22"
    }
  }
}