{
  "prontuario_id": 639,
  "text": "TX RENAL CADAVERICO EM 24/12/2013, CIT 19H SEM INDUÇÃO.\nHIPERSENSIBILIZADA.\nMTC 10, TAC 3 / 3, MYF 2 / 2, BON, AMIODARONA 200, ANLO 10 2X, MTF 850 2X, LEVOTIROXINA 25, INSULINA NPH 45 - 0 - 10.\n\nS: REFERE FRAQUEZA, EDEMA DE MMII, TREMORES, DEISCENCIA DE SUTURA.\n\nO: BEG, LOTE, HIPOCORADA.\nPESO 66,5; PA 120*80;\nCPP LIVRE.\nABDOMEN DEISCENCIA DE 2 PONTOS DE SUTURA COM CURATIVO ESPECIAL.\nMMII EDEMA++/4.\n\nA: CR 1,2 - 1,3.\nUROCULTURA NEG.\nTAC PENDENTE.\nLDH 600 (EM QUEDA).\nGJ 106 - 161.\nNAO TROUXE O CONTROLE GLICEMICO.\nCONTROLE DE PA DOMICILIAR - ADEQUADO.\n\nP: SUSPENSO A ANLODIPINA.\nFAÇO O ATENOLOL.\nMANTIDO DEMAIS ATÉ NIVEL DE TAC.\n \n \n \n ",
  "entities": {
    "Abreviação": [
      "CIT",
      "MTC",
      "TAC",
      "MYF",
      "BON",
      "ANLO",
      "MTF",
      "MMII",
      "BEG",
      "LOTE",
      "PA",
      "TX RENAL CADAVERICO",
      "CPP LIVRE",
      "CR 1 , 2 - 1 , 3",
      "UROCULTURA NEG",
      "GJ 106 - 161",
      "CONTROLE DE PA DOMICILIAR"
    ],
    "Negação": [
      "SEM",
      "NAO"
    ],
    "Procedimento Terapêutico ou Preventivo": [
      "INDUÇÃO",
      "TX RENAL CADAVERICO",
      "CURATIVO ESPECIAL",
      "CONTROLE GLICEMICO",
      "CONTROLE DE PA DOMICILIAR"
    ],
    "Substância Química Orgânica": [
      "MTC",
      "MYF",
      "AMIODARONA",
      "ANLO",
      "MTF",
      "ANLODIPINA",
      "ATENOLOL"
    ],
    "Substância Farmacológica": [
      "MTC",
      "TAC",
      "MYF",
      "BON",
      "AMIODARONA",
      "ANLO",
      "MTF",
      "LEVOTIROXINA",
      "ANLODIPINA",
      "ATENOLOL",
      "INSULINA NPH"
    ],
    "Conceito Quantitativo": [
      "10",
      "200",
      "25",
      "120*80",
      "3 / 3",
      "2 / 2",
      "10 2X",
      "850 2X",
      "45 - 0 - 10",
      "66 , 5",
      "2 PONTOS"
    ],
    "Aminoácido, Peptídeo ou Proteína": [
      "LEVOTIROXINA",
      "INSULINA NPH"
    ],
    "Hormônio": [
      "LEVOTIROXINA",
      "INSULINA NPH"
    ],
    "Sinal ou Sintoma": [
      "FRAQUEZA",
      "EDEMA",
      "TREMORES",
      "HIPOCORADA",
      "DEISCENCIA",
      "EDEMA++/4",
      "DEISCENCIA DE SUTURA"
    ],
    "Parte do Corpo, Órgão ou Componente Orgânico": [
      "MMII",
      "ABDOMEN"
    ],
    "Achado": [
      "BEG",
      "LOTE",
      "CPP LIVRE",
      "EM QUEDA"
    ],
    "Atributo Clínico": [
      "PESO",
      "PA"
    ],
    "Dispositivo Médico": [
      "SUTURA",
      "CURATIVO ESPECIAL"
    ],
    "Resultado Laboratorial ou de Teste": [
      "EDEMA++/4",
      "CR 1 , 2 - 1 , 3",
      "UROCULTURA NEG",
      "LDH 600",
      "GJ 106 - 161"
    ],
    "Procedimento Diagnóstico": [
      "TAC",
      "CONTROLE GLICEMICO",
      "CONTROLE DE PA DOMICILIAR"
    ],
    "Atividade de Assistência à Saúde": [
      "SUSPENSO",
      "CONTROLE GLICEMICO"
    ]
  },
  "labels": {
    "deiscencia de sutura": {
      "capitulo": "22"
    },
    "edema": {
      "capitulo": "11"
    },
    "deiscencia": {
      "capitulo": "22"
    },
    "tremores": {
      "capitulo": "06"
    },
    "hipocorada": {
      "capitulo": "08"
    },
    "em queda": {
      "capitulo": "21"
    },
    "fraqueza": {
      "capitulo": "06"
    },
    "edema++/4": {
      "capitulo": "11"
    }
  }
}