{
  "prontuario_id": 346,
  "text": "TX RENAL EM 24/12/2013.\n\nUSO DE MTC 10, TAC 3 / 2, MYF 2 / 2.\nBON, ATN 100, MTF 850 2X, LEVO 25 NPH 50 / 10 / 10 R 0 - 10 - 4, AMIODARONA.\n\n\nS: PT FEZ EXAMES NA CIDADE DE ORIGEM POREM NÃO TEM RESULTADO DO NIVEL DE TACROLIMO.\nREFERE FRAQUEZA.\n\nO: BEG, LOTE, HIPOCORADA, AFEBRIL.\nPA 120*60.\nEF NORMAL.\nCICATRIZAÇÃO OK - FECHAMENTO DA FO.\n\nA: CR 1,1 - 1,3.\nVG 31%, LEUC 10700, E 8-12%, PQ 395.\nURP +  E COLI 10 6 S A MACRODANTINA.\nDM DESCOMPENSADO.\nTSH 8,4.\nPRA 98 % COM DSA  MIF > 2000.\n\nP: LEVO 50.\nMACRODANTINA.\nINSULINA 55 / 11 / 10. R 0 - 15 - 4.\nRETIRADA DOS PONTOS.\nRETORNO EM 3 SEMANAS COM EXAMES SEMANAIS.\n \n \n \n ",
  "entities": {
    "Substância Farmacológica": [
      "MTC",
      "TAC",
      "MYF",
      "BON",
      "ATN",
      "MTF",
      "LEVO",
      "NPH",
      "R",
      "AMIODARONA",
      "MACRODANTINA"
    ],
    "Substância Química Orgânica": [
      "MTC",
      "MYF",
      "ATN",
      "MTF",
      "LEVO",
      "AMIODARONA",
      "MACRODANTINA"
    ],
    "Abreviação": [
      "MTC",
      "TAC",
      "MYF",
      "BON",
      "ATN",
      "MTF",
      "LEVO",
      "NPH",
      "R",
      "BEG",
      "LOTE",
      "PA",
      "FO",
      "PRA",
      "CR 1 , 1 - 1 , 3",
      "VG 31%",
      "LEUC 10700",
      "E 8-12%",
      "PQ 395",
      "URP +",
      "&gt; 2000"
    ],
    "Conceito Quantitativo": [
      "10",
      "100",
      "25",
      "120*60",
      "50",
      "/ 2",
      "2 /",
      "- 10 - 4",
      "CR 1 , 1 - 1 , 3",
      "10 6",
      "%",
      "55 / 11 / 10",
      "0 - 15 - 4"
    ],
    "Hormônio": [
      "NPH",
      "R"
    ],
    "Procedimento Diagnóstico": [
      "EXAMES"
    ],
    "Negação": [
      "NÃO",
      "AFEBRIL"
    ],
    "Sinal ou Sintoma": [
      "FRAQUEZA",
      "HIPOCORADA",
      "AFEBRIL"
    ],
    "Achado": [
      "BEG",
      "LOTE",
      "CICATRIZAÇÃO OK"
    ],
    "Atributo Clínico": [
      "PA"
    ],
    "Função de Organismo": [
      "FECHAMENTO"
    ],
    "Lesão ou Envenenamento": [
      "FO"
    ],
    "Procedimento Laboratorial": [
      "PRA",
      "DSA"
    ],
    "Aminoácido, Peptídeo ou Proteína": [
      "INSULINA"
    ],
    "Atividade de Assistência à Saúde": [
      "RETORNO",
      "RETIRADA DOS PONTOS"
    ],
    "Conceito Qualitativo": [
      "10 - 4"
    ],
    "Resultado Laboratorial ou de Teste": [
      "NIVEL DE TACROLIMO",
      "CR 1 , 1 - 1 , 3",
      "VG 31%",
      "LEUC 10700",
      "E 8-12%",
      "PQ 395",
      "URP +",
      "TSH 8 ,",
      "MIF 2000"
    ],
    "Bactéria": [
      "E COLI"
    ],
    "Doença ou Síndrome": [
      "DM DESCOMPENSADO"
    ],
    "Procedimento Terapêutico ou Preventivo": [
      "EXAMES SEMANAIS"
    ]
  },
  "labels": {
    "fo": {
      "capitulo": "X"
    },
    "hipocorada": {
      "capitulo": "03"
    },
    "e coli": {
      "capitulo": "01"
    },
    "dm descompensado": {
      "capitulo": "05"
    },
    "fraqueza": {
      "capitulo": "21"
    }
  }
}