{
  "prontuario_id": 620,
  "text": "DRC ESTAGIO 5 EM TRATAMENTO CONSERVADOR.\nDRC ESTAGIO 5.\nCANDIDATO A TX RENAL.\n \n \nDRC ESTAGIO 5 EM TRATAMENTO CONSERVADOR.\nD. BASE: DOENÇA POLICISTICA HEPATORRENAL.\nEM ATUAL CONSERVADOR COM Doutor Vital Brazil , EM PREPARO PARA TRS - OPÇÃO SERIA CAPD PELO TRABALHO (Professor MÉDIO / ALUNO MESTRADO).\nNEGA TABAGISMO E ETILISMO.\n3 FAMILIARES TRANSPLANTADOS DE RIM.\nAO EXAME PA 130/70,  P 78,  AFEBRIL,  DIURESE 2L,   NORMOLINEO.\nCORADO E HIDRATADO,\nCPP LIVRES,\nPC RITMO REGULAR,\nABD RINS PALPÁVEIS, MAS FOSSAS ILÍACAS LIVRES,\nMMII SEM EDEMA,\n* AVALIAÇÃO LAB, CARDIOLOGICA E DEMAIS EXAMES IMAGEM ADEQUADOS AO TRATAMENTO PROPOSTO.",
  "entities": {
    "Grupo Populacional": [
      "CANDIDATO"
    ],
    "Grupo Profissional ou Ocupacional": [
      "Doutor",
      "Professor",
      "ALUNO MESTRADO"
    ],
    "Atividade de Assistência à Saúde": [
      "PREPARO",
      "EXAME"
    ],
    "Procedimento Terapêutico ou Preventivo": [
      "TRS",
      "CAPD",
      "TRATAMENTO CONSERVADOR",
      "TX RENAL",
      "ATUAL CONSERVADOR",
      "TRATAMENTO PROPOSTO"
    ],
    "Abreviação": [
      "TRS",
      "CAPD",
      "PA",
      "P",
      "PC",
      "ABD",
      "MMII",
      "DRC ESTAGIO 5",
      "TX RENAL",
      "CPP LIVRES",
      "AVALIAÇÃO LAB"
    ],
    "Atividade Ocupacional": [
      "TRABALHO"
    ],
    "Negação": [
      "NEGA",
      "AFEBRIL",
      "SEM"
    ],
    "Doença ou Síndrome": [
      "TABAGISMO",
      "ETILISMO",
      "DRC ESTAGIO 5",
      "DOENÇA POLICISTICA HEPATORRENAL"
    ],
    "Achado": [
      "TRANSPLANTADOS",
      "NORMOLINEO",
      "CORADO",
      "HIDRATADO",
      "ADEQUADOS",
      "CPP LIVRES",
      "RITMO REGULAR",
      "FOSSAS ILÍACAS LIVRES"
    ],
    "Parte do Corpo, Órgão ou Componente Orgânico": [
      "RIM",
      "ABD",
      "MMII"
    ],
    "Atributo Clínico": [
      "PA",
      "P",
      "PC"
    ],
    "Conceito Quantitativo": [
      "130/70",
      "78",
      "2L"
    ],
    "Sinal ou Sintoma": [
      "AFEBRIL",
      "EDEMA",
      "RINS PALPÁVEIS"
    ],
    "Função de Organismo": [
      "DIURESE"
    ],
    "Procedimento Diagnóstico": [
      "CARDIOLOGICA",
      "EXAMES IMAGEM"
    ],
    "Grupo Familiar": [
      "3 FAMILIARES"
    ],
    "Resultado Laboratorial ou de Teste": [
      "AVALIAÇÃO LAB"
    ],
    "Procedimento Laboratorial": [
      "AVALIAÇÃO LAB"
    ]
  },
  "labels": {
    "ritmo regular": {
      "capitulo": "11"
    },
    "cpp livres": {
      "capitulo": "13"
    },
    "edema": {
      "capitulo": "15"
    },
    "doença policistica hepatorrenal": {
      "capitulo": "16"
    },
    "etilismo": {
      "capitulo": "24"
    },
    "drc estagio 5": {
      "capitulo": "11"
    },
    "transplantados": {
      "capitulo": "16"
    },
    "rins palpáveis": {
      "capitulo": "21"
    },
    "fossas ilíacas livres": {
      "capitulo": "15"
    },
    "tabagismo": {
      "capitulo": "24"
    },
    "adequados": {
      "capitulo": "11"
    }
  }
}