{
  "prontuario_id": 219,
  "text": "Lucas, 70 anos.\n\n# Troca de valva aórtica biológica por EAo em 2008,\n# FA paroxística,\n# HAS,\n# DM tipo 2,\n# Ex-tabagista, parou há 9 anos, carga tabágica de 40 maços/ano.\n\nMUC: Carvedilol 25mg de 12/12h.\nOmeprazol 20mg /dia,\nAtorvastatina 40mg /dia,\nMaraven 5mg /dia,\nMetformina 850mg de 12/12h,\nGliclazida 30mg /dia.\n\n# Ecocardio TT (10/07/15): VE com hipetrofia excentrica importante, função sistolica preservada (FE: 65%) e disfunção diastólica grau I. AE e câmeras D normais.\nInsuficiência mitral discreta. Prótese biológica com gradientes sugestivos de possível estenose.\n# ECG (09/07/15): eixo de QRS desviado para a esquerda, BRD, bradicardia sinusal.\n\nS: Paciente oligossintomatico, relata esporadicamente episódios de tontura ao fazer esforço, porém não atrapalha suas atividades diárias. Relata melhora importante dos sintomas com medicação.\n\nO: BEG, LOTE, corado, hidrado, acianótico e anictérico,\nPA: 140/70, FC: 48, FR: 16, SatO2 em AA: 93%,\nAP: MV+ bilateral, mas difusamente diminuído, S RA.\nAC: RCR em 2T, BNF, sopro sistólico em foco Ao de 2+/6+.\nAbdome: flácido, RHA+, indolor a palpação, sem massas palpáveis.\nMMII: sem edema, boa perfusão periférica.\n\nA: Válvula aórtica biológica + FA paroxística no momento em ritmo sinusal.\n\nP: Diminuo carvedilol para 25mg de manha e 12,5mg a noite devido a bradicardia.\nRetorno em 6 meses.\n\nE3 CARDIO LUCAS,\nDoutor Vital Brazil.",
  "entities": {
    "Doença ou Síndrome": [
      "EAo",
      "HAS",
      "FA paroxística",
      "DM tipo 2"
    ],
    "Abreviação": [
      "EAo",
      "HAS",
      "MUC",
      "ECG",
      "BRD",
      "S",
      "O",
      "BEG",
      "LOTE",
      "PA",
      "FC",
      "FR",
      "AP",
      "RA",
      "AC",
      "BNF",
      "RHA+",
      "MMII",
      "A",
      "P",
      "FA paroxística",
      "DM tipo 2",
      "Ecocardio TT",
      "VE com hipetrofia excentrica importante",
      "AE e câmeras D normais",
      "SatO2 em AA",
      "MV+ bilateral",
      "RCR em 2T",
      "foco Ao"
    ],
    "Achado": [
      "Ex-tabagista",
      "S",
      "BEG",
      "LOTE",
      "corado",
      "hidrado",
      "BNF",
      "flácido",
      "RHA+",
      "Troca de valva aórtica biológica",
      "MV+ bilateral",
      "RCR em 2T",
      "boa perfusão periférica",
      "ritmo sinusal"
    ],
    "Atributo Clínico": [
      "MUC",
      "PA",
      "FC",
      "FR",
      "carga tabágica",
      "SatO2 em AA"
    ],
    "Substância Química Orgânica": [
      "Carvedilol",
      "Omeprazol",
      "Atorvastatina",
      "Maraven",
      "Metformina",
      "Gliclazida",
      "carvedilol"
    ],
    "Substância Farmacológica": [
      "Carvedilol",
      "Omeprazol",
      "Atorvastatina",
      "Maraven",
      "Metformina",
      "Gliclazida",
      "carvedilol"
    ],
    "Conceito Quantitativo": [
      "25mg",
      "850mg",
      "140/70",
      "48",
      "16",
      "93%",
      "2+/6+",
      "40 maços/ano",
      "40mg /dia",
      "5mg /dia",
      "12 , 5mg"
    ],
    "Conceito Temporal": [
      "12/12h",
      "/dia",
      "esporadicamente",
      "manha",
      "no momento",
      "a noite"
    ],
    "Procedimento Diagnóstico": [
      "ECG",
      "AP",
      "AC",
      "palpação",
      "A",
      "Ecocardio TT"
    ],
    "Resultado Laboratorial ou de Teste": [
      "BRD",
      "VE com hipetrofia excentrica importante",
      "função sistolica preservada ( FE : 65% )",
      "disfunção diastólica grau I",
      "AE e câmeras D normais",
      "Insuficiência mitral discreta",
      "gradientes sugestivos de possível estenose",
      "eixo de QRS desviado para a esquerda",
      "bradicardia sinusal"
    ],
    "Paciente ou Grupo com Deficiência": [
      "Paciente"
    ],
    "Sinal ou Sintoma": [
      "oligossintomatico",
      "acianótico",
      "anictérico",
      "RA",
      "edema",
      "bradicardia",
      "episódios de tontura ao fazer esforço",
      "atrapalha suas atividades diárias",
      "difusamente diminuído",
      "sopro sistólico",
      "massas palpáveis"
    ],
    "Negação": [
      "não",
      "acianótico",
      "anictérico",
      "S",
      "sem"
    ],
    "Atividade de Assistência à Saúde": [
      "O",
      "Diminuo"
    ],
    "Parte do Corpo, Órgão ou Componente Orgânico": [
      "Abdome",
      "MMII"
    ],
    "Função Patológica": [
      "edema",
      "FA paroxística"
    ],
    "Produto Intelectual": [
      "P"
    ],
    "Procedimento Terapêutico ou Preventivo": [
      "Troca de valva aórtica biológica"
    ],
    "Dispositivo Médico": [
      "Prótese biológica",
      "Válvula aórtica biológica"
    ],
    "Localização ou Região Corporal": [
      "foco Ao"
    ]
  },
  "labels": {
    "ra": {
      "capitulo": "11"
    },
    "flácido": {
      "capitulo": "21"
    },
    "ritmo sinusal": {
      "capitulo": "21"
    },
    "sopro sistólico": {
      "capitulo": "11"
    },
    "troca de valva aórtica": {
      "capitulo": "11"
    },
    "mv+ bilateral": {
      "capitulo": "11"
    },
    "difusamente diminuído": {
      "capitulo": "21"
    },
    "rcr em 2t": {
      "capitulo": "11"
    },
    "fa paroxística": {
      "capitulo": "11"
    },
    "bradicardia": {
      "capitulo": "11"
    },
    "oligossintomatico": {
      "capitulo": "21"
    },
    "dm tipo 2": {
      "capitulo": "5"
    },
    "bnf": {
      "capitulo": "11"
    },
    "edema": {
      "capitulo": "21"
    },
    "has": {
      "capitulo": "5"
    },
    "eao": {
      "capitulo": "11"
    },
    "episódios de tontura ao fazer esforço": {
      "capitulo": "21"
    }
  }
}