{
  "prontuario_id": 941,
  "text": "Nefro Geral.\n \n \n \nLucas, 78 anos.\n\nHAS, em uso de ENL 20 x2, ATN 50 x2, HCTZ.\nHPB, episodio de obstrução urinária há 6 anos.\nnega cirurgias abdominais, ex-tabagista (parou há 30 anos).\nAVC em 2013, sem sequelas.\nexames agosto/2014: pH 7, 29;  Bic 22;  PU 1,015; leuc 6M, hem 1M, GJ 93, Na 143,  CT 165,  Cr 2,02;  K 5,8,  Ur 101,  Ca 9,2,  Fe 91,   P 3,6 , HDL 23 , TGL 161,  acido urico 9,4 , LDL 110,  UC neg.\nRx com ectasia da aorta.\nUS: cistos renais simples bilaterais, espessura cortical normal, sem litiase, sem dilatação, próstata 44g, com resíduo vesical pós-miccional (139ml).\nAo exame: 147 cm, 69 kg, IMC 31.\nCorado, hidratado, PA 150 x 70 (MSD e MSE), FC 80, crepitantes bibasais, abdomen globoso sem VCM, edema periférico.",
  "entities": {
    "Abreviação": [
      "HAS",
      "ENL",
      "ATN",
      "HCTZ",
      "HPB",
      "AVC",
      "Rx",
      "US",
      "PA",
      "MSD",
      "MSE",
      "FC",
      "VCM",
      "Nefro Geral",
      "Bic 22",
      "PU 1 , 015",
      "leuc 6M",
      "hem 1M",
      "GJ 93",
      "CT 165",
      "Cr 2 , 02",
      "K 5 , 8",
      "Ur 101",
      "Ca 9 , 2",
      "Fe 91",
      "próstata 44g"
    ],
    "Doença ou Síndrome": [
      "HAS",
      "HPB",
      "AVC",
      "ectasia da aorta"
    ],
    "Substância Farmacológica": [
      "ENL",
      "ATN",
      "HCTZ"
    ],
    "Aminoácido, Peptídeo ou Proteína": [
      "ENL"
    ],
    "Substância Química Orgânica": [
      "ATN",
      "HCTZ"
    ],
    "Negação": [
      "nega",
      "sem"
    ],
    "Achado": [
      "ex-tabagista",
      "Corado",
      "hidratado",
      "globoso"
    ],
    "Procedimento Laboratorial": [
      "exames"
    ],
    "Procedimento Diagnóstico": [
      "Rx",
      "US",
      "exame"
    ],
    "Resultado Laboratorial ou de Teste": [
      "litiase",
      "dilatação",
      "pH 7 , 29",
      "Bic 22",
      "PU 1 , 015",
      "leuc 6M",
      "hem 1M",
      "GJ 93",
      "Na 143",
      "CT 165",
      "Cr 2 , 02",
      "K 5 , 8",
      "Ur 101",
      "Ca 9 , 2",
      "Fe 91",
      "P 3 , 6",
      "HDL 23",
      "TGL 161",
      "acido urico 9 , 4",
      "LDL 110",
      "UC neg",
      "ectasia da aorta",
      "cistos renais simples bilaterais",
      "espessura cortical normal",
      "próstata 44g",
      "com resíduo vesical pós-miccional ( 139ml )",
      "IMC 31"
    ],
    "Atributo Clínico": [
      "PA",
      "FC"
    ],
    "Parte do Corpo, Órgão ou Componente Orgânico": [
      "MSD",
      "MSE",
      "abdomen"
    ],
    "Conceito Quantitativo": [
      "80",
      "147 cm",
      "69 kg",
      "150 x 70"
    ],
    "Sinal ou Sintoma": [
      "VCM",
      "obstrução urinária",
      "crepitantes bibasais",
      "edema periférico"
    ],
    "Conceito Temporal": [
      "há 6 anos",
      "há 30 anos"
    ],
    "Procedimento Terapêutico ou Preventivo": [
      "cirurgias abdominais"
    ]
  },
  "labels": {
    "obstrução urinária": {
      "capitulo": "16"
    },
    "ectasia da aorta": {
      "capitulo": "11"
    },
    "crepitantes bibasais": {
      "capitulo": "21"
    },
    "edema periférico": {
      "capitulo": "15"
    },
    "avc": {
      "capitulo": "08"
    },
    "hpb": {
      "capitulo": "16"
    }
  }
}