{
  "prontuario_id": 377,
  "text": "Lucas, 80 anos.\n\n# HAS, HPB\n# Em uso de Losartan 50mg 12/12 horas e furosemida 40mg 12/12 horas. Também faz uso de medicação para HPB, não lembra o nome\n# Nega cirurgias\n# Ex-tabagista, parou há 20 anos, 20 maços/ano.\n\nS: Paciente nega sintomas. Diurese presente, boa quantidade, alguns dias refere sintomas de LUTS ( Dificuldade para urinar, Jato fraco, Noctúria).\nQueixa-se ainda de edema articular e artralgia em punhos e tornozelos, sempre monoarticular.\n\nPaciente nega hx de obstrução urinária prévia.\n\nAo exame:\n \nBEG, LOTE, normocorado, hidratado,\nPA 216/100, FC 64, FR 16, Sat 98% em AA.\nMV+ bilateralmente sem RA.\nBCRNF em 2 tempos com sopro sistólico +/6+ em foco pulmonar,\nAbdome flácido, indolor, RHA+, sem sinais de IP,\nMMII edema +/4+ bilateralmente, panturrilhas livres.\n\nCKD EPI 38,3;\n\nP # Inicio BBQ e Anlodipino,\nRetorno em 6 meses.\nSolicito exames laboratoriais.\nPU +  Cultura de Urina.\nSolicito que traga medicação na próxima consulta.\nInicio estatina + AAS.\n \n \n \n ",
  "entities": {
    "Abreviação": [
      "HAS",
      "HPB",
      "S",
      "hx",
      "BEG",
      "LOTE",
      "PA",
      "FC",
      "FR",
      "MV+",
      "RA",
      "RHA+",
      "MMII",
      "P",
      "BBQ",
      "PU",
      "AAS",
      "sintomas de LUTS",
      "sinais de IP"
    ],
    "Doença ou Síndrome": [
      "HAS",
      "HPB"
    ],
    "Substância Química Orgânica": [
      "Losartan",
      "furosemida",
      "BBQ",
      "Anlodipino",
      "AAS"
    ],
    "Substância Farmacológica": [
      "Losartan",
      "furosemida",
      "medicação",
      "BBQ",
      "Anlodipino",
      "estatina",
      "AAS"
    ],
    "Conceito Quantitativo": [
      "40mg",
      "216/100",
      "64",
      "16",
      "20 maços/ano"
    ],
    "Negação": [
      "não",
      "Nega",
      "nega",
      "sem",
      "indolor"
    ],
    "Procedimento Terapêutico ou Preventivo": [
      "cirurgias"
    ],
    "Achado": [
      "Ex-tabagista",
      "S",
      "BEG",
      "LOTE",
      "normocorado",
      "hidratado",
      "MV+",
      "flácido",
      "indolor",
      "RHA+",
      "Diurese presente",
      "boa quantidade",
      "em 2 tempos",
      "panturrilhas livres"
    ],
    "Paciente ou Grupo com Deficiência": [
      "Paciente"
    ],
    "Sinal ou Sintoma": [
      "sintomas",
      "Noctúria",
      "Queixa-se",
      "artralgia",
      "RA",
      "indolor",
      "sintomas de LUTS",
      "Dificuldade para urinar",
      "Jato fraco",
      "edema articular",
      "obstrução urinária",
      "sopro sistólico +/6+",
      "sinais de IP"
    ],
    "Parte do Corpo, Órgão ou Componente Orgânico": [
      "punhos",
      "tornozelos",
      "Abdome",
      "MMII"
    ],
    "Conceito Temporal": [
      "prévia",
      "12/12 horas",
      "há 20 anos",
      "alguns dias"
    ],
    "Procedimento Diagnóstico": [
      "exame"
    ],
    "Atributo Clínico": [
      "PA",
      "FC",
      "FR",
      "Sat"
    ],
    "Conceito Espacial": [
      "bilateralmente"
    ],
    "Resultado Laboratorial ou de Teste": [
      "+/4+",
      "CKD EPI 38 , 3"
    ],
    "Produto Intelectual": [
      "P"
    ],
    "Atividade de Assistência à Saúde": [
      "Inicio",
      "Solicito"
    ],
    "Procedimento Laboratorial": [
      "PU",
      "exames laboratoriais",
      "Cultura de Urina"
    ]
  },
  "labels": {
    "panturrilhas livres": {
      "capitulo": "15"
    },
    "obstrução urinária": {
      "capitulo": "21"
    },
    "ra": {
      "capitulo": "04"
    },
    "flácido": {
      "capitulo": "21"
    },
    "jato fraco": {
      "capitulo": "21"
    },
    "artralgia": {
      "capitulo": "15"
    },
    "sinais de ip": {
      "capitulo": "21"
    },
    "noctúria": {
      "capitulo": "16"
    },
    "queixa-se": {
      "capitulo": "21"
    },
    "hpb": {
      "capitulo": "11"
    },
    "mv+": {
      "capitulo": "21"
    },
    "sintomas": {
      "capitulo": "21"
    },
    "sopro sistólico +/6+": {
      "capitulo": "08"
    },
    "dificuldade para urinar": {
      "capitulo": "21"
    },
    "sintomas de luts": {
      "capitulo": "21"
    },
    "edema articular": {
      "capitulo": "15"
    },
    "has": {
      "capitulo": "11"
    },
    "beg": {
      "capitulo": "21"
    },
    "em 2 tempos": {
      "capitulo": "21"
    },
    "lote": {
      "capitulo": "21"
    },
    "s": {
      "capitulo": "21"
    }
  }
}