{
  "prontuario_id": 366,
  "text": "# QP: PACIENTE ENCAMINHADO PARA AVALIAÇÃO DE FUNDO DE OLHO DEVIDO À USO DE HIDROXICLOROQUINA PARA AR.\n\n# HMA: PACIENTE NEGA HIPEREMIA CONJUNTIVAL, PRURIDO OU LACRIMEJAMENTO. FAZ USO DE ÓCULOS PARA LEITURA (NÃO TROUXE).  FAZ USO DE  COLÍRIO LUBRIFICANTE; \n\n# HMP: COMORBIDADES: HAS E ARTRITE REUMATÓIDE EM USO DE HIDROXICLOROQUINA 400MG /DIA HÁ 2 MESES. NEGA CIRURGIAS OU TRAUMAS OCULARES.\n\n# HMF: NEGA HISTÓRICO FAMILIAR DE GLAUCOMA OU CEGUEIRA.\n\n# EXAME FÍSICO:\n\n-AV:\tOD 20/30,\n\tOE 20/40,\n\tJ1.\n\n-TOL:\tOD -1,00 ESF//20/20;\n\tOE -2,00 ESF//20/20;\n\tAD+3,00//J1.\n\n-BIO:\tAO CA CALMA E BEM FORMADA. PUPILAS FOTORREAGENTES. CÓRNEA CLARA. CATARATA AO.\n\n-PIO:\t18/18.\n\n-FO:\tAO PAPILA E MACULA APARENTEMENTE NORMAIS, APESAR DA OPACIDADE DE MEIOS.\n\n# CONDUTA: ORIENTO PACIENTE A DIRIGIR-SE AO HUC CASO APRESENTE QUALQUER ALTERAÇÃO AGUDA DA SAÚDE OCULAR. RETORNO ANUAL VIA UBS.\n\nR1 Lucas\nR3 Lucas\n \n \n \n ",
  "entities": {
    "Sinal ou Sintoma": [
      "QP",
      "PRURIDO",
      "LACRIMEJAMENTO",
      "COMORBIDADES",
      "HIPEREMIA CONJUNTIVAL",
      "OPACIDADE DE MEIOS",
      "ALTERAÇÃO AGUDA"
    ],
    "Abreviação": [
      "QP",
      "AR",
      "HMA",
      "HMP",
      "HAS",
      "HMF",
      "-AV",
      "-TOL",
      "ESF//20/20",
      "-BIO",
      "AO",
      "CA",
      "-PIO",
      "-FO",
      "UBS",
      "OD 20/30",
      "OE 20/40",
      "OD -1 , 00",
      "OE -2 , 00",
      "AD+3 , 00//J1"
    ],
    "Paciente ou Grupo com Deficiência": [
      "PACIENTE"
    ],
    "Atividade de Assistência à Saúde": [
      "ENCAMINHADO",
      "AVALIAÇÃO",
      "CONDUTA",
      "RETORNO",
      "ORIENTO PACIENTE"
    ],
    "Substância Farmacológica": [
      "HIDROXICLOROQUINA",
      "COLÍRIO LUBRIFICANTE"
    ],
    "Doença ou Síndrome": [
      "AR",
      "HAS",
      "GLAUCOMA",
      "CEGUEIRA",
      "CATARATA",
      "ARTRITE REUMATÓIDE"
    ],
    "Achado": [
      "HMA",
      "HMP",
      "HMF",
      "USO DE ÓCULOS PARA LEITURA",
      "HISTÓRICO FAMILIAR",
      "BEM FORMADA",
      "PUPILAS FOTORREAGENTES",
      "CÓRNEA CLARA",
      "APARENTEMENTE NORMAIS"
    ],
    "Negação": [
      "NEGA",
      "NÃO"
    ],
    "Substância Química Orgânica": [
      "HIDROXICLOROQUINA"
    ],
    "Conceito Temporal": [
      "/DIA",
      "ANUAL",
      "HÁ 2 MESES"
    ],
    "Procedimento Terapêutico ou Preventivo": [
      "CIRURGIAS"
    ],
    "Lesão ou Envenenamento": [
      "TRAUMAS"
    ],
    "Procedimento Diagnóstico": [
      "-TOL",
      "-BIO",
      "-PIO",
      "-FO",
      "FUNDO DE OLHO",
      "EXAME FÍSICO"
    ],
    "Resultado Laboratorial ou de Teste": [
      "ESF//20/20",
      "18/18",
      "OD 20/30",
      "OE 20/40",
      "OD -1 , 00",
      "OE -2 , 00",
      "AD+3 , 00//J1"
    ],
    "Parte do Corpo, Órgão ou Componente Orgânico": [
      "AO",
      "CA",
      "PAPILA",
      "MACULA"
    ],
    "Conceito Quantitativo": [
      "18/18"
    ],
    "Produto Intelectual": [
      "CONDUTA"
    ],
    "Organização Relacionada à Saúde": [
      "UBS"
    ]
  },
  "labels": {
    "bem formada": {
      "capitulo": "09"
    },
    "aparentemente normais": {
      "capitulo": "09"
    },
    "traumas": {
      "capitulo": "22"
    },
    "qp": {
      "capitulo": "24"
    },
    "córnea clara": {
      "capitulo": "09"
    },
    "hma": {
      "capitulo": "24"
    },
    "cegueira": {
      "capitulo": "09"
    },
    "opacidade de meios": {
      "capitulo": "09"
    },
    "ar": {
      "capitulo": "05"
    },
    "hmp": {
      "capitulo": "24"
    },
    "comorbidades": {
      "capitulo": "24"
    },
    "lacrimejamento": {
      "capitulo": "09"
    },
    "alteração aguda": {
      "capitulo": "22"
    },
    "catarata": {
      "capitulo": "09"
    },
    "hmf": {
      "capitulo": "24"
    },
    "histórico familiar": {
      "capitulo": "24"
    },
    "glaucoma": {
      "capitulo": "09"
    },
    "hiperemia conjuntival": {
      "capitulo": "09"
    },
    "has": {
      "capitulo": "04"
    },
    "artrite reumatóide": {
      "capitulo": "15"
    }
  }
}