{
  "prontuario_id": 714,
  "text": "joão, 68 anos.\n\n# IAM 2009 - ATC.\n# CA de Laringe, fez QT e RT - TERMINO TTO 2002,\n# HAS,\n# HPB,\n# DLP,\n# ARTRITE REUMATÓIDE.\n\n# Em um uso de:\n- Enalapril 20 mg, 2 cp de 12/12 hr.\n- CARVEDILOL 12,5MG, 1 cp de 12/12 hr,\n- AAS 100 mg, 1/dia;\n- Sinvastatina 20mg, 4 cp de noite;\n- Omeprazol 20m mg, 2 cp de 12/12hr;\n- PREDNISONA 5 MG;\n- COMBODART.\n\n***Teste de esforço 10/2013:  eficaz, submáximo, sem alterações. Clínicas ou eletrocardiográficas de iesquemia miocardica. Resposta cronotrópica adequada. Resposta tensional fisiológica. Decréscimo normal da FC no 1° minuto de recuperação.\n*** ECOCARDIO 11/06/2014: VE COM DIMENSÃO INTERNA , CONTRATILIDADE MIOCARDICA E FUNÇÃO SISTOLICA GLOBAL NORMAIS, DISFUNÇÃO DIASTOLICA TIPO ALTERAÇÃO DE RELAXAMENTO, AE E CAVIDADES DIREITAS NORMAIS,\nFLUXOS VALVARES SEM ANORMALIDADES MORFOFUNCIONAIS SIGNIFICATIVAS. AE 31, VDC 21, DDDV 44, DSVE 30, FE 60.\n\nS # SEM QUEIXAS. NEGA DISPNEIA E DOR NO PEITO. ESTÁVEL.\n\nO # \nBEG, LOTE, CORADO, HIDRATADO, EUPNEICO.\nPA 120/80, FC 80;\nACV: BCRNF2TSS;\nAP: MV+ BILAT, SEM RA;\nABD: SP;\nMMII: SP;\n\n\nA # DAC.\n\nP # CONDUTA MANTIDA,\n      EX DE CONTROLE.\n\nR3 CARDIO Lucas,\nDoutor Lucas.",
  "entities": {
    "Abreviação": [
      "IAM",
      "ATC",
      "QT",
      "RT",
      "HAS",
      "HPB",
      "DLP",
      "AAS",
      "ECOCARDIO",
      "S",
      "O",
      "BEG",
      "LOTE",
      "PA",
      "FC",
      "ACV",
      "BCRNF2TSS",
      "AP",
      "RA",
      "ABD",
      "SP",
      "MMII",
      "A",
      "DAC",
      "P",
      "CA de Laringe",
      "2 cp",
      "1 cp",
      "4 cp",
      "Decréscimo normal da FC no 1° minuto de recuperação",
      "VE COM DIMENSÃO INTERNA",
      "AE E CAVIDADES DIREITAS NORMAIS",
      "AE 31",
      "VDC 21",
      "FE 60",
      "EX DE CONTROLE"
    ],
    "Doença ou Síndrome": [
      "IAM",
      "HAS",
      "HPB",
      "DLP",
      "DAC",
      "ARTRITE REUMATÓIDE",
      "iesquemia miocardica"
    ],
    "Procedimento Terapêutico ou Preventivo": [
      "QT",
      "RT"
    ],
    "Conceito Temporal": [
      "2002",
      "1/dia",
      "noite",
      "12/12hr",
      "12/12 hr"
    ],
    "Substância Farmacológica": [
      "Enalapril",
      "CARVEDILOL",
      "AAS",
      "Sinvastatina",
      "Omeprazol",
      "PREDNISONA",
      "COMBODART"
    ],
    "Aminoácido, Peptídeo ou Proteína": [
      "Enalapril"
    ],
    "Substância Química Orgânica": [
      "CARVEDILOL",
      "AAS",
      "Sinvastatina",
      "Omeprazol",
      "PREDNISONA",
      "COMBODART"
    ],
    "Resultado Laboratorial ou de Teste": [
      "eficaz",
      "submáximo",
      "alterações",
      "eletrocardiográficas",
      "Resposta cronotrópica adequada",
      "Resposta tensional fisiológica",
      "Decréscimo normal da FC no 1° minuto de recuperação",
      "VE COM DIMENSÃO INTERNA",
      "CONTRATILIDADE MIOCARDICA E FUNÇÃO SISTOLICA GLOBAL NORMAIS",
      "DISFUNÇÃO DIASTOLICA TIPO ALTERAÇÃO DE RELAXAMENTO",
      "AE E CAVIDADES DIREITAS NORMAIS",
      "FLUXOS VALVARES SEM",
      "ANORMALIDADES MORFOFUNCIONAIS SIGNIFICATIVAS",
      "AE 31",
      "VDC 21",
      "DDDV 44",
      "DSVE 30",
      "FE 60"
    ],
    "Negação": [
      "sem",
      "SEM",
      "NEGA",
      "SP"
    ],
    "Procedimento Diagnóstico": [
      "ECOCARDIO",
      "ACV",
      "AP",
      "A",
      "***Teste de esforço",
      "EX DE CONTROLE"
    ],
    "Achado": [
      "S",
      "ESTÁVEL",
      "BEG",
      "LOTE",
      "CORADO",
      "HIDRATADO",
      "EUPNEICO",
      "BCRNF2TSS",
      "SP",
      "TERMINO TTO"
    ],
    "Sinal ou Sintoma": [
      "QUEIXAS",
      "DISPNEIA",
      "RA",
      "DOR NO PEITO"
    ],
    "Atividade de Assistência à Saúde": [
      "O",
      "CONDUTA MANTIDA"
    ],
    "Atributo Clínico": [
      "PA",
      "FC"
    ],
    "Conceito Quantitativo": [
      "120/80",
      "80",
      "20 mg",
      "2 cp",
      "12 , 5MG",
      "1 cp",
      "100 mg",
      "4 cp",
      "20m mg",
      "5 MG"
    ],
    "Conceito Espacial": [
      "BILAT"
    ],
    "Parte do Corpo, Órgão ou Componente Orgânico": [
      "ABD",
      "MMII"
    ],
    "Produto Intelectual": [
      "P"
    ],
    "Processo Neoplásico": [
      "CA de Laringe"
    ]
  },
  "labels": {
    "ra": {
      "capitulo": "11"
    },
    "sp": {
      "capitulo": "15"
    },
    "ca de laringe": {
      "capitulo": "10"
    },
    "iesquemia miocardica": {
      "capitulo": "11"
    },
    "hpb": {
      "capitulo": "13"
    },
    "dac": {
      "capitulo": "22"
    },
    "iam": {
      "capitulo": "11"
    },
    "dor no peito": {
      "capitulo": "11"
    },
    "dispneia": {
      "capitulo": "12"
    },
    "dlp": {
      "capitulo": "13"
    },
    "has": {
      "capitulo": "04"
    },
    "bcrnf2tss": {
      "capitulo": "X"
    },
    "beg": {
      "capitulo": "24"
    },
    "artrite reumatóide": {
      "capitulo": "15"
    }
  }
}