{
  "prontuario_id": 934,
  "text": "# 12º PO BX LESAO MANDIBULA À DIREITA + BX PERFURAÇÃO NASAL (VER AP).\n\nS # FEZ USO DE ANTIBIOTICO ( AMOXI+ CLAV) E CORTICOIDE ORAL COM MELHORA IMPORTANTE DOS SINTOMAS. REFERE REDUÇÃO QUASE COMPLETA DO EDEMA ENDURECIDO EM MANDIBULA À DIREITA.\n# HMP: TRANSPLANTE RENAL À DIREITA HÁ 5 ANOS - EM ACOMPANHAMENTO COM NEFROLOGIA.\n\nO # ORO: FO BOM ASPECTO.\nC/P: EDEMA ENDURECIDO EM MANDIBULA APROX 5CM.\nRINO: PERF NASAL ANTERIOR GRANDE CROSTAS C/ CROSTAS AO REDOR. \n\nCD # RETORNO EM 2 SEMANAS PARA VER AP ! (CONSULTA EM 1 SEMANA COINCIDIRIA COM CONSULTA DA NEFRO).\nORIENTAÇÕES GERAIS.\nMANUTENÇÃO DE MEDICAÇÃO ANALGÉSICA SE DOR.\n\nR2 Lucas\n \n \n \n ",
  "entities": {
    "Abreviação": [
      "PO",
      "AP",
      "S",
      "HMP",
      "O",
      "ORO",
      "C/P",
      "RINO",
      "CD",
      "BX PERFURAÇÃO NASAL",
      "AMOXI+ CLAV",
      "FO BOM ASPECTO",
      "APROX 5CM",
      "PERF NASAL ANTERIOR GRANDE CROSTAS C/ CROSTAS AO REDOR",
      "CONSULTA DA NEFRO"
    ],
    "Conceito Temporal": [
      "PO"
    ],
    "Procedimento Diagnóstico": [
      "AP",
      "ORO",
      "RINO"
    ],
    "Achado": [
      "S",
      "HMP",
      "MELHORA IMPORTANTE DOS SINTOMAS",
      "FO BOM ASPECTO"
    ],
    "Sinal ou Sintoma": [
      "DOR"
    ],
    "Grupo Profissional ou Ocupacional": [
      "R2",
      "NEFROLOGIA"
    ],
    "Atividade de Assistência à Saúde": [
      "ACOMPANHAMENTO",
      "RETORNO",
      "CONSULTA",
      "CONSULTA DA NEFRO",
      "ORIENTAÇÕES GERAIS"
    ],
    "Parte do Corpo, Órgão ou Componente Orgânico": [
      "C/P",
      "MANDIBULA",
      "MANDIBULA À DIREITA"
    ],
    "Produto Intelectual": [
      "CD"
    ],
    "Procedimento Terapêutico ou Preventivo": [
      "BX PERFURAÇÃO NASAL",
      "MEDICAÇÃO ANALGÉSICA"
    ],
    "Substância Farmacológica": [
      "AMOXI+ CLAV",
      "CORTICOIDE ORAL",
      "MEDICAÇÃO ANALGÉSICA"
    ],
    "Substância Química Orgânica": [
      "CORTICOIDE ORAL"
    ],
    "Localização ou Região Corporal": [
      "MANDIBULA À DIREITA"
    ],
    "Conceito Quantitativo": [
      "APROX 5CM"
    ]
  },
  "labels": {
    "melhora importante dos sintomas": {
      "capitulo": "21"
    },
    "dor": {
      "capitulo": "22"
    },
    "hmp": {
      "capitulo": "16"
    }
  }
}