{
  "prontuario_id": 974,
  "text": "11:25Hrs Cliente em glw 5, pupilas iso / foto +, IOT + VM nos parametros PSv ( 14 ),   peep 5cmh2O,   FR 10,   FiO2 37%, face corada, mucosa oral hidratada, boa perfusão periferica, no leito com cabeceira elevada á 45°. Mantem com monitorização de multiparametros: ECG, PNI, SpO2,   SNE fechada ( aguarda infusão de dieta enteral por BI ),  acesso venoso periferico em MSD com srt em curso gravitacional. Apresenta ausculta cardiaca ritmica e normofonetica, ausculta pulmonar MV + com roncos, DTF DIR com debito serohematico ++, abdomem globoso e flacido com RHA +, edemas em MMSS e II cacifo ++, FO de região coxo-femural ESQ limpo e seco. Faz uso de SVD aberta com debito diuretico presente + de coloração amarelo-claro, eliminação fecal ausente. Segue cuidados intensivos de enfermagem em precaução de contato.   Enfermeira Florence Nightingale . FRATURA DO FEMUR.",
  "entities": {
    "Parte do Corpo, Órgão ou Componente Orgânico": [
      "pupilas",
      "MSD",
      "abdomem",
      "MMSS"
    ],
    "Achado": [
      "iso",
      "ritmica",
      "normofonetica",
      "flacido",
      "limpo",
      "seco",
      "foto +",
      "face corada",
      "mucosa oral hidratada",
      "boa perfusão periferica",
      "MV +",
      "RHA +",
      "debito diuretico presente",
      "coloração amarelo-claro"
    ],
    "Abreviação": [
      "iso",
      "IOT",
      "VM",
      "PSv",
      "peep",
      "FR",
      "FiO2",
      "ECG",
      "PNI",
      "SpO2",
      "BI",
      "MSD",
      "srt",
      "FO",
      "glw 5",
      "foto +",
      "SNE fechada",
      "DTF DIR",
      "RHA +",
      "coxo-femural ESQ",
      "SVD aberta"
    ],
    "Dispositivo Médico": [
      "IOT",
      "SNE fechada",
      "acesso venoso periferico"
    ],
    "Procedimento Terapêutico ou Preventivo": [
      "IOT",
      "VM",
      "PSv",
      "srt",
      "cabeceira elevada á 45°",
      "SNE fechada",
      "dieta enteral",
      "acesso venoso periferico",
      "DTF DIR",
      "SVD aberta",
      "precaução de contato"
    ],
    "Conceito Quantitativo": [
      "14",
      "5cmh2O",
      "10",
      "37%"
    ],
    "Atributo Clínico": [
      "peep",
      "FR",
      "FiO2"
    ],
    "Procedimento Diagnóstico": [
      "ECG",
      "PNI",
      "SpO2",
      "ausculta cardiaca",
      "ausculta pulmonar"
    ],
    "Dispositivo de Administração de Medicamento": [
      "BI"
    ],
    "Sinal ou Sintoma": [
      "roncos",
      "globoso",
      "edemas",
      "glw 5"
    ],
    "Lesão ou Envenenamento": [
      "FO"
    ],
    "Conceito Qualitativo": [
      "limpo",
      "seco",
      "coloração amarelo-claro"
    ],
    "Negação": [
      "ausente"
    ],
    "Organização Relacionada à Saúde": [
      "enfermagem"
    ],
    "Grupo Profissional ou Ocupacional": [
      "enfermagem",
      "Enfermeira"
    ],
    "Atividade de Assistência à Saúde": [
      "monitorização de multiparametros",
      "cuidados intensivos"
    ],
    "Resultado Laboratorial ou de Teste": [
      "debito serohematico ++",
      "cacifo ++"
    ],
    "Localização ou Região Corporal": [
      "coxo-femural ESQ"
    ],
    "Função de Organismo": [
      "eliminação fecal"
    ],
    "Doença ou Síndrome": [
      "FRATURA DO FEMUR"
    ]
  },
  "labels": {
    "rha +": {
      "capitulo": "15"
    },
    "edemas": {
      "capitulo": "12"
    },
    "iso": {
      "capitulo": "11"
    },
    "seco": {
      "capitulo": "14"
    },
    "limpo": {
      "capitulo": "10"
    },
    "normofonetica": {
      "capitulo": "21"
    },
    "debito diuretico presente": {
      "capitulo": "13"
    },
    "mv +": {
      "capitulo": "12"
    },
    "coloração amarelo-claro": {
      "capitulo": "14"
    },
    "flacido": {
      "capitulo": "15"
    },
    "foto +": {
      "capitulo": "21"
    },
    "fratura do femur": {
      "capitulo": "15"
    },
    "face corada": {
      "capitulo": "21"
    },
    "fo": {
      "capitulo": "10"
    },
    "mucosa oral hidratada": {
      "capitulo": "21"
    },
    "roncos": {
      "capitulo": "12"
    },
    "globoso": {
      "capitulo": "15"
    },
    "boa perfusão periferica": {
      "capitulo": "21"
    },
    "glw 5": {
      "capitulo": "11"
    },
    "ritmica": {
      "capitulo": "21"
    }
  }
}