{
  "prontuario_id": 447,
  "text": "07:40H Ramsay 6, pupilas isomióticas. Curativo cefálico tipo capacete de crepe limpo e seco, PIC com média de 22 com DVE fechada. SNG aberta com discreto débito biliosa, SNE com infusão de dieta. Em ventilação mecânica modo PCV, Peep 3, PI 16cmH2O, FiO2 30%. Entubado, rima labial de TOT em 23cm, uso contínuo de filtro de barreira e sistema fechado de aspiração. Acesso central em subclavia D com curativo oclusivo infundindo noradrenalina 10ml/h + sedação 40ml/h. CPP com roncos difusos. Abdomem flácido, RHA+. PAM em inguinal D permeável. SVD com diurese efetiva, pele íntegra em região sacra. Extremidades aquecidase bem perfundidas, sem edemas.  Monitorizado contínuamente com parâmetros de PA invasiva, cardioscopia e oximetria de pulso. Segue sob cuidados intensivos e precaução de contato profilático. Enfermeira Florence Nightingale . DISPARO DE OUTRA ARMA DE FOGO E DE ARMA DE FOGO NAO ESPECIFICADA INTENCAO NAO DETERMINADA AREAS INDUSTRIAIS E EM CONSTRUCAO.",
  "entities": {
    "Dispositivo Médico": [
      "crepe",
      "SNE",
      "TOT",
      "SVD",
      "SNG aberta",
      "filtro de barreira",
      "Acesso central",
      "curativo oclusivo"
    ],
    "Abreviação": [
      "PIC",
      "SNE",
      "Peep",
      "PI",
      "FiO2",
      "TOT",
      "CPP",
      "RHA+",
      "PAM",
      "SVD",
      "DVE fechada",
      "SNG aberta",
      "subclavia D",
      "inguinal D"
    ],
    "Atributo Clínico": [
      "PIC",
      "Peep",
      "FiO2"
    ],
    "Procedimento Terapêutico ou Preventivo": [
      "SNE",
      "PCV",
      "Entubado",
      "TOT",
      "sedação",
      "SVD",
      "DVE fechada",
      "SNG aberta",
      "ventilação mecânica",
      "filtro de barreira",
      "sistema fechado de aspiração",
      "Acesso central",
      "curativo oclusivo",
      "precaução de contato profilático"
    ],
    "Atividade de Assistência à Saúde": [
      "infusão",
      "infundindo",
      "Monitorizado contínuamente",
      "cuidados intensivos"
    ],
    "Conceito Quantitativo": [
      "3",
      "16cmH2O",
      "30%",
      "23cm",
      "10ml/h",
      "40ml/h"
    ],
    "Conceito Temporal": [
      "contínuo"
    ],
    "Substância Farmacológica": [
      "noradrenalina"
    ],
    "Substância Química Orgânica": [
      "noradrenalina"
    ],
    "Hormônio": [
      "noradrenalina"
    ],
    "Localização ou Região Corporal": [
      "CPP",
      "Extremidades",
      "rima labial",
      "inguinal D",
      "região sacra"
    ],
    "Achado": [
      "flácido",
      "RHA+",
      "aquecidase",
      "pupilas isomióticas",
      "diurese efetiva",
      "bem perfundidas"
    ],
    "Procedimento Diagnóstico": [
      "PAM",
      "cardioscopia",
      "PA invasiva",
      "oximetria de pulso"
    ],
    "Conceito Qualitativo": [
      "permeável"
    ],
    "Negação": [
      "sem"
    ],
    "Sinal ou Sintoma": [
      "edemas",
      "Ramsay 6",
      "débito biliosa",
      "roncos difusos"
    ],
    "Grupo Profissional ou Ocupacional": [
      "Enfermeira"
    ],
    "Resultado Laboratorial ou de Teste": [
      "média de 22"
    ],
    "Parte do Corpo, Órgão ou Componente Orgânico": [
      "subclavia D",
      "pele íntegra"
    ],
    "Objeto Manufaturado": [
      "ARMA DE FOGO"
    ]
  },
  "labels": {
    "flácido": {
      "capitulo": "12"
    },
    "roncos difusos": {
      "capitulo": "08"
    },
    "pupilas isomióticas": {
      "capitulo": "09"
    },
    "edemas": {
      "capitulo": "15"
    },
    "débito biliosa": {
      "capitulo": "12"
    },
    "ramsay 6": {
      "capitulo": "21"
    }
  }
}