{
  "prontuario_id": 277,
  "text": "03:45 H CLIENTE PROVENIENTE DO PRONTO ATENDIMENTO NO PERIODO DA TARDE, PARA TRATAMENTO DE ESCARA SACRAL, INTERNA PARA REALIZAR DEBRIDAMENTO. ACAMADA, ALERTA, EUPNEICA, AFEBRIL, ORIENTADA, EMAGRECIDA, HEMATOMA EM FACE ESQUERDA. ACEITA DIETA OFERECIDA. MANTEM ACESSO PERIFERICO EM MSD SALINIZADO. ABDOMEM GLOBOSO E FLACIDO. APRESENTA CURATIVO REGIÃO DE ÚLCERA SACRA COM ODOR FÉTIDO E PRESENÇA DE NECROSE. ELIMINAÇÕES EM FRALDA. REALIZADO MEDIDAS DE CONFORTO E MUDANÇA DE DECUBITO. SEGUE EM OBSERVAÇÃO E CUIDADOS. Enfermeira Florence Nightingale . EXAME GERAL E INVESTIGACAO DE PESSOAS SEM QUEIXAS OU DIAGNOSTICO RELATADO.",
  "entities": {
    "Atividade de Assistência à Saúde": [
      "TRATAMENTO",
      "OBSERVAÇÃO",
      "CUIDADOS",
      "MEDIDAS DE CONFORTO",
      "EXAME GERAL"
    ],
    "Procedimento Terapêutico ou Preventivo": [
      "TRATAMENTO",
      "DEBRIDAMENTO",
      "DIETA",
      "CURATIVO",
      "ACESSO PERIFERICO",
      "MUDANÇA DE DECUBITO"
    ],
    "Sinal ou Sintoma": [
      "ACAMADA",
      "AFEBRIL",
      "EMAGRECIDA",
      "HEMATOMA",
      "NECROSE",
      "QUEIXAS",
      "ODOR FÉTIDO"
    ],
    "Achado": [
      "ALERTA",
      "EUPNEICA",
      "ORIENTADA",
      "GLOBOSO",
      "FLACIDO"
    ],
    "Negação": [
      "AFEBRIL",
      "SEM"
    ],
    "Parte do Corpo, Órgão ou Componente Orgânico": [
      "MSD",
      "ABDOMEM"
    ],
    "Abreviação": [
      "MSD"
    ],
    "Dispositivo Médico": [
      "CURATIVO",
      "FRALDA",
      "ACESSO PERIFERICO"
    ],
    "Função de Órgão ou Tecido": [
      "NECROSE"
    ],
    "Objeto Manufaturado": [
      "FRALDA"
    ],
    "Grupo Profissional ou Ocupacional": [
      "Enfermeira"
    ],
    "Organização Relacionada à Saúde": [
      "PRONTO ATENDIMENTO"
    ],
    "Conceito Temporal": [
      "PERIODO DA TARDE"
    ],
    "Doença ou Síndrome": [
      "ESCARA SACRAL",
      "DIAGNOSTICO RELATADO ."
    ],
    "Localização ou Região Corporal": [
      "FACE ESQUERDA",
      "REGIÃO DE ÚLCERA SACRA"
    ],
    "Conceito Qualitativo": [
      "ODOR FÉTIDO"
    ],
    "Procedimento Diagnóstico": [
      "INVESTIGACAO DE PESSOAS"
    ]
  },
  "labels": {
    "acamada": {
      "capitulo": "22"
    },
    "flacido": {
      "capitulo": "15"
    },
    "hematoma": {
      "capitulo": "14"
    },
    "escara sacral": {
      "capitulo": "14"
    },
    "necrose": {
      "capitulo": "14"
    },
    "alerta": {
      "capitulo": "21"
    },
    "odor fétido": {
      "capitulo": "14"
    },
    "globoso": {
      "capitulo": "15"
    },
    "queixas": {
      "capitulo": "21"
    },
    "diagnostico relatado": {
      "capitulo": "21"
    }
  }
}