{
  "prontuario_id": 12,
  "text": "02:20H PACIENTE PROVENIENTE DO CC, HX DE QUEDA DE NÍVEL COM TCE LEVE, POI DE DRENAGEM DE HSA TEMPORAL ESQ. NO MOMENTO SEDADA COM RAMSAY=6, PUPILAS ISOCORICAS E FOTORREATIVAS, ESTÁVEL HEMODINAMICAMENTE, IOT TUBO 7.5 RIMA 23, VM PCV, PEEP = 5, FIO2 = 40%, HIPOCORADA, HIDRATADA, ESTÁVEL HEMODINAMICAMENTE, APRESENTA CURATIVO CEFÁLICO LIMPO E SECO EXTERNAMENTE, CVC EM SUBCLÁVIA D. ACESSO VENOSO PERIFÉRICO EM MSE E PÉ D. * FAV EM MSD, ORIENTADO EQUIPE PARA NÃO PUNCIONAR E NÃO AFERIR PA EM MSD. CHEGOU DO CC COM HEMOTRASFUSÃO EM CURSO. SVD COM DIURESE EFETIVA.  # TAC DE CRÂNIO LIBERADA E AGENDADA PARA ÀS 06H. Enfermeira Florence Nightingale .   ACIDENTE VASCULAR CEREBRAL NAO ESPECIFICADO COMO HEMORRAGICO OU ISQUEMICO.",
  "entities": {
    "Abreviação": [
      "CC",
      "HX",
      "POI",
      "VM",
      "PCV",
      "PEEP",
      "FIO2",
      "CVC",
      "MSE",
      "FAV",
      "MSD",
      "SVD",
      "TAC",
      "TCE LEVE",
      "DRENAGEM DE HSA",
      "TEMPORAL ESQ",
      "IOT TUBO 7",
      "SUBCLÁVIA D",
      "PÉ D",
      "AFERIR PA"
    ],
    "Organização Relacionada à Saúde": [
      "CC",
      "EQUIPE"
    ],
    "Conceito Temporal": [
      "POI",
      "MOMENTO",
      "EM CURSO"
    ],
    "Procedimento Terapêutico ou Preventivo": [
      "SEDADA",
      "VM",
      "PCV",
      "CVC",
      "HEMOTRASFUSÃO",
      "SVD",
      "DRENAGEM DE HSA",
      "IOT TUBO 7",
      "CURATIVO CEFÁLICO",
      "ACESSO VENOSO PERIFÉRICO"
    ],
    "Achado": [
      "SEDADA",
      "ISOCORICAS",
      "FOTORREATIVAS",
      "HIDRATADA",
      "LIMPO",
      "SECO",
      "QUEDA DE NÍVEL",
      "ESTÁVEL HEMODINAMICAMENTE",
      "DIURESE EFETIVA"
    ],
    "Parte do Corpo, Órgão ou Componente Orgânico": [
      "PUPILAS",
      "MSE",
      "MSD",
      "CRÂNIO",
      "SUBCLÁVIA D",
      "PÉ D"
    ],
    "Atributo Clínico": [
      "PEEP",
      "FIO2"
    ],
    "Conceito Quantitativo": [
      "5",
      "40%"
    ],
    "Sinal ou Sintoma": [
      "HIPOCORADA",
      "RAMSAY = 6"
    ],
    "Conceito Qualitativo": [
      "LIMPO",
      "SECO"
    ],
    "Conceito Espacial": [
      "EXTERNAMENTE"
    ],
    "Dispositivo Médico": [
      "CVC",
      "SVD",
      "CURATIVO CEFÁLICO",
      "ACESSO VENOSO PERIFÉRICO"
    ],
    "Anormalidade Adquirida": [
      "FAV"
    ],
    "Negação": [
      "NÃO",
      "NAO"
    ],
    "Atividade de Assistência à Saúde": [
      "PUNCIONAR",
      "LIBERADA",
      "AGENDADA",
      "AFERIR PA"
    ],
    "Procedimento Diagnóstico": [
      "TAC"
    ],
    "Grupo Profissional ou Ocupacional": [
      "Enfermeira"
    ],
    "Doença ou Síndrome": [
      "TCE LEVE",
      "ACIDENTE VASCULAR CEREBRAL"
    ],
    "Localização ou Região Corporal": [
      "TEMPORAL ESQ"
    ],
    "Função de Organismo": [
      "DIURESE EFETIVA"
    ]
  },
  "labels": {
    "isocoricas": {
      "capitulo": "08"
    },
    "hipocorada": {
      "capitulo": "11"
    },
    "fav": {
      "capitulo": "22"
    },
    "seco": {
      "capitulo": "14"
    },
    "limpo": {
      "capitulo": "14"
    },
    "fotorreativas": {
      "capitulo": "09"
    },
    "acidente vascular cerebral": {
      "capitulo": "08"
    },
    "queda de nível": {
      "capitulo": "22"
    },
    "sedada": {
      "capitulo": "22"
    },
    "tce leve": {
      "capitulo": "22"
    }
  }
}