{
  "prontuario_id": 990,
  "text": "05/06/2012 às 16:30h. Vítima de atropelamento, trauma torácico, Fx de pelve em livro aberto e Fx exposta de MID.  Recebido do CC às 14:30h.  POI de toracostomia com drenagem pleural fechada, correção de fratura de pelve e MID. Ramsay 06, pupilas isomióticas. SNG aberta sem débito. Entubada, TOT em rima labial de 24cm, em VM modalidade CMV, VC 520ml, FiO2 60%, Peep 5. Acesso venoso em subclávia e com infusão de noradrenalina 100 ml/h, vasopressina 12 ml/h + dopamina 35 ml/h + insulina 10 ml/h. Acesso venoso em MSD com infusão de dormonid 15 ml/h + fentanil 20 ml/h. PAM em radial D pérvia. CPP com rocnos esparsos. Dreno de tórax D com débito hemático. SVD com débito colúrico. Presença de fixador externo em pelve em MID. Extremidades aquecidas, perfusão periférica adequada, sem edemas.   # Recebeu 03 U de CH na chagada a UTI. Enfermeira Florence Nightingale. CHOQUE HIPOVOLEMICO.",
  "entities": {
    "Parte do Corpo, Órgão ou Componente Orgânico": [
      "MID",
      "pelve",
      "pupilas",
      "subclávia",
      "MSD",
      "radial D"
    ],
    "Abreviação": [
      "MID",
      "CC",
      "POI",
      "TOT",
      "VM",
      "VC",
      "FiO2",
      "Peep",
      "MSD",
      "PAM",
      "CPP",
      "SVD",
      "CH",
      "UTI",
      "Fx de pelve em livro aberto",
      "Fx exposta",
      "SNG aberta",
      "radial D"
    ],
    "Atividade de Assistência à Saúde": [
      "Recebido",
      "infusão",
      "Recebeu"
    ],
    "Organização Relacionada à Saúde": [
      "CC",
      "UTI"
    ],
    "Conceito Temporal": [
      "POI"
    ],
    "Negação": [
      "sem"
    ],
    "Função de Organismo": [
      "débito"
    ],
    "Procedimento Terapêutico ou Preventivo": [
      "Entubada",
      "TOT",
      "VM",
      "CMV",
      "infusão",
      "SVD",
      "toracostomia com drenagem pleural fechada",
      "correção de fratura",
      "SNG aberta",
      "Acesso venoso",
      "fixador externo"
    ],
    "Dispositivo Médico": [
      "TOT",
      "SVD",
      "SNG aberta",
      "Acesso venoso",
      "fixador externo"
    ],
    "Conceito Quantitativo": [
      "24cm",
      "520ml",
      "60%",
      "5",
      "100 ml/h",
      "12 ml/h",
      "35 ml/h",
      "10 ml/h",
      "15 ml/h",
      "20 ml/h",
      "03 U"
    ],
    "Atributo Clínico": [
      "VC",
      "FiO2",
      "Peep"
    ],
    "Substância Farmacológica": [
      "noradrenalina",
      "vasopressina",
      "dopamina",
      "insulina",
      "dormonid",
      "fentanil"
    ],
    "Substância Química Orgânica": [
      "noradrenalina",
      "dopamina",
      "dormonid",
      "fentanil"
    ],
    "Hormônio": [
      "noradrenalina",
      "vasopressina",
      "insulina"
    ],
    "Aminoácido, Peptídeo ou Proteína": [
      "vasopressina",
      "insulina"
    ],
    "Substância Biologicamente Ativa": [
      "dopamina"
    ],
    "Procedimento Diagnóstico": [
      "PAM"
    ],
    "Conceito Qualitativo": [
      "pérvia"
    ],
    "Sinal ou Sintoma": [
      "edemas",
      "Ramsay 06",
      "rocnos esparsos",
      "débito hemático",
      "débito colúrico"
    ],
    "Grupo Profissional ou Ocupacional": [
      "Enfermeira"
    ],
    "Achado": [
      "Vítima de atropelamento",
      "Extremidades aquecidas",
      "perfusão periférica adequada"
    ],
    "Lesão ou Envenenamento": [
      "trauma torácico",
      "Fx exposta"
    ],
    "Localização ou Região Corporal": [
      "rima labial"
    ],
    "Doença ou Síndrome": [
      "CHOQUE HIPOVOLEMICO"
    ]
  },
  "labels": {
    "débito hemático": {
      "capitulo": "12"
    },
    "choque hipovolemico": {
      "capitulo": "11"
    },
    "edemas": {
      "capitulo": "15"
    },
    "rocnos esparsos": {
      "capitulo": "21"
    },
    "débito colúrico": {
      "capitulo": "12"
    },
    "fx exposta": {
      "capitulo": "22"
    },
    "ramsay 06": {
      "capitulo": "21"
    },
    "trauma torácico": {
      "capitulo": "22"
    },
    "vítima de atropelamento": {
      "capitulo": "23"
    }
  }
}