{
  "prontuario_id": 263,
  "text": "22:17 HS - GLASGOW 14, AGITADO, CONFUSO, MANTENDO SUPORTE NÉVOA-ÚMIDA 5 LITROS,  SNE DIETA ENTERAL EM CURSO, CATETER CENTRAL (D) NORA 30 ML/H E DOBUTA 30 ML/H, PVC 12 MMHG, ABDOMEM GLOBOSO, FLÁCIDO, RHA +,  SVD DIURESE VOLUME EFICAZ COLORAÇÃO CONCENTRADO, APRESENTA FISSURAS EM BOLSA ESCROTAL, ÚLCERA POR PRESSÃO SACRA GRAU II COM PRESENÇA NECROSE, PASADO KOLLAGENASE,  TROCADO CURATICO COTO MID BORDAS AFASTADAS, COM SECREÇÃO SANGUINOLENTA, EDEMA MIE EXTREMIDADES FRIAS, COMUNICADO PLANTONISATA VERIFICADO GLICEMIA  CAPILAR 165 MG/DL, SEGUE CUIDADOS PRECAUÇÃO CONTATO. (Enfermeira Florence Nightingale ). EXAME GERAL E INVESTIGACAO DE PESSOAS SEM QUEIXAS OU DIAGNOSTICO RELATADO.",
  "entities": {
    "Sinal ou Sintoma": [
      "AGITADO",
      "CONFUSO",
      "SANGUINOLENTA",
      "EDEMA",
      "QUEIXAS",
      "GLASGOW 14",
      "COLORAÇÃO CONCENTRADO",
      "EXTREMIDADES FRIAS"
    ],
    "Dispositivo Médico": [
      "SNE",
      "SVD"
    ],
    "Abreviação": [
      "SNE",
      "NORA",
      "DOBUTA",
      "PVC",
      "SVD",
      "MIE",
      "RHA +"
    ],
    "Procedimento Terapêutico ou Preventivo": [
      "SNE",
      "SVD",
      "SUPORTE NÉVOA-ÚMIDA",
      "DIETA ENTERAL",
      "CUIDADOS PRECAUÇÃO CONTATO"
    ],
    "Hormônio": [
      "NORA"
    ],
    "Substância Química Orgânica": [
      "NORA",
      "DOBUTA"
    ],
    "Substância Farmacológica": [
      "NORA",
      "DOBUTA"
    ],
    "Parte do Corpo, Órgão ou Componente Orgânico": [
      "ABDOMEM",
      "MIE",
      "BOLSA ESCROTAL"
    ],
    "Achado": [
      "GLOBOSO",
      "FLÁCIDO",
      "RHA +"
    ],
    "Função de Organismo": [
      "DIURESE"
    ],
    "Função de Órgão ou Tecido": [
      "NECROSE"
    ],
    "Conceito Qualitativo": [
      "SANGUINOLENTA",
      "VOLUME EFICAZ",
      "COLORAÇÃO CONCENTRADO",
      "BORDAS AFASTADAS"
    ],
    "Grupo Profissional ou Ocupacional": [
      "PLANTONISATA"
    ],
    "Negação": [
      "SEM"
    ],
    "Conceito Quantitativo": [
      "5 LITROS",
      "30 ML/H",
      "12 MMHG"
    ],
    "Conceito Espacial": [
      "D"
    ],
    "Resultado Laboratorial ou de Teste": [
      "GLICEMIA CAPILAR 165 MG/DL"
    ],
    "Atividade de Assistência à Saúde": [
      "EXAME GERAL"
    ],
    "Procedimento Diagnóstico": [
      "INVESTIGACAO DE PESSOAS"
    ],
    "Doença ou Síndrome": [
      "DIAGNOSTICO RELATADO"
    ]
  },
  "labels": {
    "diagnostico relatado": {
      "capitulo": "21"
    },
    "extremidades frias": {
      "capitulo": "22"
    },
    "edema": {
      "capitulo": "15"
    },
    "flácido": {
      "capitulo": "15"
    },
    "glasgow 14": {
      "capitulo": "06"
    },
    "globoso": {
      "capitulo": "15"
    },
    "sanguinolenta": {
      "capitulo": "21"
    },
    "agitado": {
      "capitulo": "06"
    },
    "queixas": {
      "capitulo": "21"
    },
    "confuso": {
      "capitulo": "06"
    },
    "coloração concentrado": {
      "capitulo": "21"
    }
  }
}