{
  "prontuario_id": 550,
  "text": "00:30h: Paciente apresentando rebaixamento de  nível de consciência, glasgow 13, disfásico, referindo forte cefaléia, comunico plantão da neurocirurgia que solicita Tomografia de crânio de emergência, libero e exame e paciente é encaminhado as 23h com  ambulância do hospital mas auxiliar de enfermagem, retornando as 23:30h com filme de imagem do exame, realizo ECG conforme solicitação médica. Encaminhado pedido de vaga de UTI na UTI 2  para Enfermeira Florence Nightingale . Segue sob cuidados de enfermagem. Solicito instação de oxigenioterapia. Enfermeira Florence Nightingale . TRAUMATISMO INTRACRANIANO.",
  "entities": {
    "Sinal ou Sintoma": [
      "disfásico",
      "rebaixamento de nível de consciência",
      "glasgow 13",
      "forte cefaléia"
    ],
    "Organização Relacionada à Saúde": [
      "neurocirurgia",
      "emergência",
      "UTI",
      "enfermagem"
    ],
    "Grupo Profissional ou Ocupacional": [
      "neurocirurgia",
      "Enfermeira",
      "enfermagem"
    ],
    "Atividade de Assistência à Saúde": [
      "solicita",
      "encaminhado",
      "retornando",
      "Encaminhado",
      "cuidados",
      "Solicito",
      "comunico plantão",
      "solicitação médica"
    ],
    "Procedimento Diagnóstico": [
      "exame",
      "ECG",
      "Tomografia de crânio"
    ],
    "Abreviação": [
      "ECG",
      "UTI"
    ],
    "Procedimento Terapêutico ou Preventivo": [
      "oxigenioterapia"
    ],
    "Resultado Laboratorial ou de Teste": [
      "filme de imagem"
    ],
    "Doença ou Síndrome": [
      "TRAUMATISMO INTRACRANIANO"
    ]
  },
  "labels": {
    "glasgow 13": {
      "capitulo": "06"
    },
    "traumatismo intracraniano": {
      "capitulo": "08"
    },
    "forte cefaléia": {
      "capitulo": "21"
    },
    "disfásico": {
      "capitulo": "06"
    },
    "rebaixamento de nível de consciência": {
      "capitulo": "08"
    }
  }
}