{
  "prontuario_id": 947,
  "text": "Paciente com história de Tx renal com falência do enxerto em outubro / 2006, há 3 meses com hematúria e prostração. Refere por +- 4 semanas antes da internação eletiva para nefrectomia, queixa de tosse paroxística, sendo admitida para internação previamente na instituição de origem, sendo afastadas causas infecciosas para o quadro. Admitida afebril e sem alterações no leucograma, sendo manejada com sintomáticos, com boa evolução do quadro. Nefrectomia de enxerto sem intercorrências, com boa evolução pós-operatória. Alta em 3o PO em boas condições, com retorno para reavaliação com urologia em 12/07/2007.",
  "entities": {
    "Sinal ou Sintoma": [
      "hematúria",
      "prostração",
      "queixa",
      "quadro",
      "afebril",
      "intercorrências",
      "tosse paroxística"
    ],
    "Procedimento Terapêutico ou Preventivo": [
      "nefrectomia",
      "Tx renal",
      "Nefrectomia de enxerto"
    ],
    "Atividade de Assistência à Saúde": [
      "admitida",
      "internação",
      "afastadas",
      "Admitida",
      "manejada",
      "Alta",
      "internação eletiva",
      "retorno para reavaliação"
    ],
    "Negação": [
      "afebril",
      "sem"
    ],
    "Substância Farmacológica": [
      "sintomáticos"
    ],
    "Conceito Temporal": [
      "pós-operatória",
      "3o PO"
    ],
    "Organização Relacionada à Saúde": [
      "urologia",
      "instituição de origem"
    ],
    "Grupo Profissional ou Ocupacional": [
      "urologia"
    ],
    "Abreviação": [
      "Tx renal",
      "3o PO"
    ],
    "Função Patológica": [
      "causas infecciosas"
    ],
    "Resultado Laboratorial ou de Teste": [
      "alterações no leucograma"
    ],
    "Achado": [
      "boa evolução do quadro",
      "boas condições"
    ]
  },
  "labels": {
    "causas infecciosas": {
      "capitulo": "01"
    },
    "quadro": {
      "capitulo": "21"
    },
    "intercorrências": {
      "capitulo": "22"
    },
    "prostração": {
      "capitulo": "06"
    },
    "queixa": {
      "capitulo": "21"
    },
    "tosse paroxística": {
      "capitulo": "12"
    },
    "hematúria": {
      "capitulo": "16"
    }
  }
}