{
  "prontuario_id": 4,
  "text": "LUCAS, 43a # HAS - diagnóstico recente. # Tabagismo. # Obesidade. # Dislipidemia. # HF + para cardiopatia isquêmica. # IAM 25/02. Paciente encaminhado do interior para cateterismo cardíaco pós-IAM. Realizada ACTP + 3 stents na ACD, proximal, média e distal. Procedimento feito sem intercorrências, com sucesso angiográfico. Vinha já em uso de clopidogrel.  Recebe alta após 48 em bom estado geral, assintomático, com recomendação de: - manter uso de clopidogrel por 3 meses. - AAS 200 mg /dia. - sinvastatina 20 mg /dia. Retorno breve ao seu médico assistente. Procurar a emergência em caso de intercorrências.",
  "entities": {
    "Abreviação": [
      "HAS",
      "IAM",
      "pós-IAM",
      "ACTP",
      "ACD",
      "AAS",
      "HF +"
    ],
    "Doença ou Síndrome": [
      "HAS",
      "diagnóstico",
      "Tabagismo",
      "Obesidade",
      "Dislipidemia",
      "IAM",
      "cardiopatia isquêmica"
    ],
    "Atividade de Assistência à Saúde": [
      "encaminhado",
      "alta",
      "recomendação",
      "Retorno",
      "Procurar"
    ],
    "Procedimento Terapêutico ou Preventivo": [
      "ACTP",
      "Procedimento",
      "cateterismo cardíaco"
    ],
    "Conceito Quantitativo": [
      "3",
      "200 mg /dia",
      "20 mg /dia"
    ],
    "Dispositivo Médico": [
      "stents"
    ],
    "Parte do Corpo, Órgão ou Componente Orgânico": [
      "ACD"
    ],
    "Localização ou Região Corporal": [
      "proximal",
      "média",
      "distal"
    ],
    "Negação": [
      "sem",
      "assintomático"
    ],
    "Sinal ou Sintoma": [
      "intercorrências",
      "assintomático"
    ],
    "Substância Química Orgânica": [
      "clopidogrel",
      "AAS",
      "sinvastatina"
    ],
    "Substância Farmacológica": [
      "clopidogrel",
      "AAS",
      "sinvastatina"
    ],
    "Organização Relacionada à Saúde": [
      "emergência"
    ],
    "Achado": [
      "HF +",
      "bom estado geral"
    ],
    "Conceito Qualitativo": [
      "sucesso angiográfico"
    ],
    "Conceito Temporal": [
      "após 48",
      "3 meses"
    ],
    "Grupo Profissional ou Ocupacional": [
      "médico assistente"
    ]
  },
  "labels": {
    "diagnóstico": {
      "capitulo": "21"
    },
    "has": {
      "capitulo": "21"
    },
    "cardiopatia isquêmica": {
      "capitulo": "11"
    },
    "intercorrências": {
      "capitulo": "22"
    },
    "iam": {
      "capitulo": "11"
    },
    "hf+": {
      "capitulo": "11"
    },
    "tabagismo": {
      "capitulo": "21"
    },
    "obesidade": {
      "capitulo": "15"
    },
    "dislipidemia": {
      "capitulo": "11"
    }
  }
}