{
  "prontuario_id": 599,
  "text": "# TRANSTORNO AFETIVO BIPOLAR TIPO 1, # HAS. # AVC ISQUEMICO PRÉVIO. # AVC HEMORRAGICO TEMPORAL ESQUERDO.\n09/06 Paciente procura emergência 09/06/07 por cefaléia, afasia de compreensão, perda de força em hemicorpo D. Previamente hipertensa e transtorno bipolar, usava risperidona 6mg /dia,  ácido valpróico 500, 500 e 1000mg à noite, além bupropiona 300mg e clonazepam 2 mg. Realizou TC de crânio que mostrou AVC hemorrágico temporal esq, ressonância magnéticoa com hemorragia e suspeita de vaso dentro do hematoma.  Arteriografia não mostrou alterações maiores. TEm alta após recuperação de força em hemicorpo D, com plano de consulta com neurocirurgia (neuro mal formações vasculares quinta-feira, após 16:30 em 2 meses) e neurologia doenças vasculares. Palno de repetir  arteriografia em 3 meses. REtorno com psiquiatria e uso de suas medicações.",
  "entities": {
    "Doença ou Síndrome": [
      "HAS",
      "hipertensa",
      "AVC ISQUEMICO",
      "AVC HEMORRAGICO TEMPORAL ESQUERDO",
      "AVC hemorrágico temporal esq"
    ],
    "Abreviação": [
      "HAS",
      "AVC ISQUEMICO",
      "AVC HEMORRAGICO TEMPORAL ESQUERDO",
      "hemicorpo D",
      "TC de crânio",
      "AVC hemorrágico temporal esq"
    ],
    "Conceito Temporal": [
      "PRÉVIO",
      "Previamente"
    ],
    "Organização Relacionada à Saúde": [
      "emergência",
      "neurocirurgia",
      "psiquiatria"
    ],
    "Sinal ou Sintoma": [
      "cefaléia",
      "afasia de compreensão",
      "perda de força",
      "alterações maiores"
    ],
    "Substância Farmacológica": [
      "risperidona",
      "bupropiona",
      "clonazepam",
      "ácido valpróico"
    ],
    "Substância Química Orgânica": [
      "risperidona",
      "bupropiona",
      "clonazepam",
      "ácido valpróico"
    ],
    "Conceito Quantitativo": [
      "300mg",
      "6mg /dia",
      "2 mg"
    ],
    "Resultado Laboratorial ou de Teste": [
      "hemorragia",
      "vaso dentro do hematoma"
    ],
    "Procedimento Diagnóstico": [
      "Arteriografia",
      "arteriografia",
      "TC de crânio",
      "ressonância magnéticoa"
    ],
    "Negação": [
      "não"
    ],
    "Atividade de Assistência à Saúde": [
      "alta",
      "Palno",
      "repetir",
      "REtorno",
      "plano de consulta",
      "uso de suas medicações"
    ],
    "Grupo Profissional ou Ocupacional": [
      "psiquiatria",
      "neuro mal formações vasculares",
      "neurologia doenças vasculares"
    ],
    "Disfunção Mental ou Comportamental": [
      "TRANSTORNO AFETIVO BIPOLAR TIPO 1",
      "transtorno bipolar"
    ],
    "Localização ou Região Corporal": [
      "hemicorpo D"
    ]
  },
  "labels": {
    "transtorno bipolar": {
      "capitulo": "06"
    },
    "avc isquemico": {
      "capitulo": "11"
    },
    "afasia de compreensão": {
      "capitulo": "21"
    },
    "perda de força": {
      "capitulo": "15"
    },
    "avc hemorrágico temporal esq": {
      "capitulo": "08"
    },
    "transtorno afetivo bipolar tipo 1": {
      "capitulo": "06"
    },
    "cefaléia": {
      "capitulo": "21"
    },
    "alterações maiores": {
      "capitulo": "21"
    },
    "avc hemorragico temporal esquerdo": {
      "capitulo": "08"
    }
  }
}