{
  "prontuario_id": 657,
  "text": "LUCAS, 66 A.\n# EX-TABAGISTA. # CARDIOPATA ISQUÊMICA (IAM 2001- ACTP 1ª DAE) => OCLUSÃO AGUDA DE STENT - DILATAÇÃO POR BALÃO. # ACTP 2005 COM 2 STENT EM ACD # INTERNAÇÃO (18/04/06): ANGINA INSTÁVEL COM PADRÃO EM CRESCENDO. # CAT (19/04/06):  => GRANDE RAMO MARGINAL DA ARTÉRIA CIRCUNFLEXA COM LESÃO EXCÊNTRICA E SEVERA NO 1/3 PROXIMAL; => DAE COM STENT ENVOLVENDO NOS 1/3 PROXIMAL E INÍCIO DO 1/3 MÉDIO, SEM LESÕES SIGNIFICATIVAS. => CD COM STENT NOS 1/3 PROXIMAL E MÉDIO, APRESENTANDO LESÃO DE APROX 65 - 70% NO SEU INTERIOR.  PACIENTE INTERNA COM QUADRO DE ANGINA TÍPICA PADRÃO EM CRESCENDO, RELACIONADA AOS PEQUENOS ESFORÇOS, DE INÍCIO HÁ 1 MÊS. NA INTERNAÇÃO NÃO APRESENTOU ALTERAÇÕES DE MARCADORES DE NECROSE. FOI SUBMETIDA A ACTP E IMPLANTE DE STENT NO SEGMENTO MÉDIO DA ARTÉRIA CX. EVOLUIU BEM, SEM INTERCORRÊNCIAS. APRESENTA - SE BEM, SEM DOR TORÁCICA E SEM DISPNÉIA. TEM CONDIÇÕES DE RECEBER ALTA HOSPITALAR E MANTER MEDICAÇÕES EM CASA. SE APRESENTAR ALTERAÇÕES, RETORNAR A EMERGÊNCIA DESTE HOSPITAL, SEMPRE PORTANDO EM MÃOS ESTA NOTA DE ALTA HOSPITALAR.",
  "entities": {
    "Achado": [
      "EX-TABAGISTA",
      "PEQUENOS ESFORÇOS",
      "EVOLUIU BEM",
      "APRESENTA - SE BEM"
    ],
    "Doença ou Síndrome": [
      "IAM",
      "CARDIOPATA ISQUÊMICA",
      "OCLUSÃO AGUDA DE STENT",
      "ANGINA INSTÁVEL",
      "ANGINA TÍPICA"
    ],
    "Abreviação": [
      "IAM",
      "ACTP",
      "ACD",
      "CAT",
      "DAE",
      "CD",
      "SEGMENTO MÉDIO DA ARTÉRIA CX"
    ],
    "Procedimento Terapêutico ou Preventivo": [
      "ACTP",
      "CAT",
      "STENT",
      "DILATAÇÃO POR BALÃO",
      "IMPLANTE DE STENT"
    ],
    "Dispositivo Médico": [
      "STENT"
    ],
    "Parte do Corpo, Órgão ou Componente Orgânico": [
      "ACD",
      "DAE",
      "CD",
      "MÃOS"
    ],
    "Atividade de Assistência à Saúde": [
      "INTERNAÇÃO",
      "INTERNA",
      "SUBMETIDA",
      "RETORNAR",
      "ALTA HOSPITALAR",
      "MANTER MEDICAÇÕES EM CASA"
    ],
    "Procedimento Diagnóstico": [
      "CAT"
    ],
    "Conceito Qualitativo": [
      "SEVERA",
      "PADRÃO EM CRESCENDO"
    ],
    "Negação": [
      "SEM",
      "NÃO"
    ],
    "Lesão ou Envenenamento": [
      "LESÃO",
      "LESÕES SIGNIFICATIVAS"
    ],
    "Conceito Espacial": [
      "INTERIOR",
      "1/3 PROXIMAL",
      "INÍCIO DO 1/3 MÉDIO",
      "1/3 PROXIMAL E MÉDIO"
    ],
    "Sinal ou Sintoma": [
      "QUADRO",
      "ALTERAÇÕES",
      "INTERCORRÊNCIAS",
      "DISPNÉIA",
      "ANGINA TÍPICA",
      "DOR TORÁCICA"
    ],
    "Organização Relacionada à Saúde": [
      "INTERNAÇÃO",
      "HOSPITAL",
      "A EMERGÊNCIA"
    ],
    "Objeto Manufaturado": [
      "HOSPITAL"
    ],
    "Localização ou Região Corporal": [
      "RAMO MARGINAL DA ARTÉRIA CIRCUNFLEXA",
      "SEGMENTO MÉDIO DA ARTÉRIA CX"
    ],
    "Conceito Quantitativo": [
      "65 - 70%"
    ],
    "Conceito Temporal": [
      "INÍCIO HÁ 1 MÊS"
    ],
    "Resultado Laboratorial ou de Teste": [
      "MARCADORES DE NECROSE"
    ],
    "Procedimento Laboratorial": [
      "MARCADORES DE NECROSE"
    ]
  },
  "labels": {
    "evoluiu bem": {
      "capitulo": "11"
    },
    "alterações": {
      "capitulo": "21"
    },
    "cardiopata isquêmica": {
      "capitulo": "11"
    },
    "lesões significativas": {
      "capitulo": "22"
    },
    "quadro": {
      "capitulo": "21"
    },
    "intercorrências": {
      "capitulo": "22"
    },
    "iam": {
      "capitulo": "11"
    },
    "ex-tabagista": {
      "capitulo": "24"
    },
    "angina instável": {
      "capitulo": "11"
    },
    "dispnéia": {
      "capitulo": "12"
    },
    "dor torácica": {
      "capitulo": "21"
    },
    "angina típica": {
      "capitulo": "11"
    },
    "lesão": {
      "capitulo": "22"
    },
    "oclusão aguda de stent": {
      "capitulo": "11"
    }
  }
}