{
  "prontuario_id": 419,
  "text": "PACIENTE G 2  C 1, Tipo Sang Mãe O -, IG de 40 sem 6 dia(s), INTERNA PARA INDUÇÃO DE PARTO. INICIADA INDUÇÃO COM OCITOCINA, EVOLUI PARA Cesárea POR FALHA DE INDUÇÃO em 02/06/2007 19:55 hs, RN APGAR 8 / 9, MASC, 3245 G. EXAMES XXXX: VDRL: NR, CI: NEGATIVO, TSRN: O NEGATIVO, CI NEGATIVO, TOXO IGG E IGM: NR E NR. EVOLUI COM CONSTIPAÇÃO E FECALOMA NO PUERPÉRIO, SENDO REALIZADO ENEMA, COM BOA RESPOSTA. RECEBE ALTA EM BOM ESTADO GERAL, SINAIS VITAIS ESTÁVEIS, LÓQUIOS FISIOLÓGICOS, MAMAS LACTANTES, FERIDA OPERATÓRIA SEM SINAIS INFLAMATÓRIOS, COM AS ORIENTAÇÕES ABAIXO LISTADAS.  ORIENTAÇÕES:  # AMAMENTAÇÕES ECLUSIVA ATÉ OS 6 MESES. # TOMAR AS MEDICAÇÕES PRESCRITAS. # RETORNAR À EMERGÊNCIA DESTE HOSPITAL SE SANGRAMENTO AUMENTADO, FEBRE OU OUTRAS INETRCORRÊNCIAS. # REVISÃO GINECOLÓGICA EM 30 DIAS.",
  "entities": {
    "Abreviação": [
      "IG",
      "RN",
      "TSRN",
      "G 2",
      "C 1",
      "VDRL : NR",
      "CI : NEGATIVO",
      "CI NEGATIVO",
      "TOXO IGG E IGM : NR E NR"
    ],
    "Atributo Clínico": [
      "IG",
      "G 2",
      "C 1"
    ],
    "Atividade de Assistência à Saúde": [
      "INTERNA",
      "REALIZADO",
      "ORIENTAÇÕES",
      "RETORNAR",
      "TOMAR AS MEDICAÇÕES PRESCRITAS",
      "REVISÃO GINECOLÓGICA"
    ],
    "Procedimento Terapêutico ou Preventivo": [
      "INDUÇÃO",
      "Cesárea",
      "ENEMA",
      "AMAMENTAÇÕES ECLUSIVA"
    ],
    "Substância Farmacológica": [
      "OCITOCINA"
    ],
    "Aminoácido, Peptídeo ou Proteína": [
      "OCITOCINA"
    ],
    "Hormônio": [
      "OCITOCINA"
    ],
    "Conceito Temporal": [
      "EVOLUI",
      "PUERPÉRIO",
      "40 sem 6 dia ( s )",
      "ATÉ OS 6 MESES"
    ],
    "Grupo Etário": [
      "RN"
    ],
    "Achado": [
      "MASC",
      "Tipo Sang Mãe O -",
      "3245 G",
      "BOA RESPOSTA",
      "BOM BOM ESTADO ESTADO GERAL GERAL",
      "SINAIS VITAIS ESTÁVEIS",
      "LÓQUIOS FISIOLÓGICOS",
      "MAMAS LACTANTES"
    ],
    "Resultado Laboratorial ou de Teste": [
      "EXAMES",
      "APGAR 8 / 9",
      "VDRL : NR",
      "CI : NEGATIVO",
      "O NEGATIVO",
      "CI NEGATIVO",
      "TOXO IGG E IGM : NR E NR"
    ],
    "Procedimento Laboratorial": [
      "TSRN"
    ],
    "Sinal ou Sintoma": [
      "CONSTIPAÇÃO",
      "FECALOMA",
      "FEBRE",
      "INETRCORRÊNCIAS",
      "SINAIS INFLAMATÓRIOS",
      "SANGRAMENTO AUMENTADO"
    ],
    "Negação": [
      "SEM"
    ],
    "Organização Relacionada à Saúde": [
      "EMERGÊNCIA",
      "HOSPITAL"
    ],
    "Objeto Manufaturado": [
      "HOSPITAL"
    ],
    "Função de Organismo": [
      "MAMAS LACTANTES"
    ],
    "Lesão ou Envenenamento": [
      "FERIDA OPERATÓRIA"
    ]
  },
  "labels": {
    "masc": {
      "capitulo": "18"
    },
    "febre": {
      "capitulo": "12"
    },
    "sangramento aumentado": {
      "capitulo": "22"
    },
    "ferida operatória": {
      "capitulo": "21"
    },
    "sinais inflamatórios": {
      "capitulo": "21"
    },
    "inetrcorrências": {
      "capitulo": "21"
    },
    "constipação": {
      "capitulo": "13"
    },
    "fecaloma": {
      "capitulo": "13"
    }
  }
}