{
  "prontuario_id": 743,
  "text": "# IAM ínfero-lateral distal com acometimento de VD. # HAS . # Osteoartrose de joelho D.  Paciente encaminhada de XXXX, chega à EME - XXXX com quadro de IAM com supra de ST em 26/set/06. Foi submetida à ACTP primária e stent (tempo de evolução 9h) com recanalização da CD em seu treço prox, com sucesso angiográfico. Evolui de forma satisfatória e recebe alta com as seguintes medicações:  1) Ticlopidina 250mg VO 12/12h durante 30 dias, 2) AAS 100mg 1cp VO no almoço - contínuo 3), Metoprolol tartarato 25mg VO 1cp de 12/12h - contínuo 4), HCTZ 25mg VO 1 cp pela manhã - contínuo 5), Sinvastatina 40mg VO 1cp à noite.  Plano: - Retorno ao ambulatório de Cardiologia - XXXX - Otimizar tratamento para CI e prevenção secundária. - Solicito TSH para ser visto em consulta ambulatorial. - Avaliar necessidade de uso de anti-depressivo. - Retorno à Emergência de necessário. ",
  "entities": {
    "Abreviação": [
      "IAM",
      "HAS",
      "EME",
      "ACTP",
      "CD",
      "VO",
      "AAS",
      "HCTZ",
      "1cp",
      "TSH",
      "acometimento de VD",
      "joelho D",
      "1 cp"
    ],
    "Doença ou Síndrome": [
      "IAM",
      "HAS",
      "Osteoartrose"
    ],
    "Paciente ou Grupo com Deficiência": [
      "Paciente"
    ],
    "Atividade de Assistência à Saúde": [
      "encaminhada",
      "alta",
      "Plano",
      "Retorno",
      "Solicito",
      "consulta ambulatorial"
    ],
    "Organização Relacionada à Saúde": [
      "EME",
      "ambulatório de Cardiologia"
    ],
    "Procedimento Diagnóstico": [
      "ACTP"
    ],
    "Procedimento Terapêutico ou Preventivo": [
      "ACTP",
      "stent",
      "recanalização",
      "prevenção secundária"
    ],
    "Conceito Qualitativo": [
      "primária"
    ],
    "Dispositivo Médico": [
      "stent"
    ],
    "Parte do Corpo, Órgão ou Componente Orgânico": [
      "CD"
    ],
    "Substância Farmacológica": [
      "medicações",
      "Ticlopidina",
      "AAS",
      "HCTZ",
      "Sinvastatina",
      "Metoprolol tartarato"
    ],
    "Substância Química Orgânica": [
      "Ticlopidina",
      "AAS",
      "HCTZ",
      "Sinvastatina"
    ],
    "Conceito Quantitativo": [
      "250mg",
      "25mg",
      "1cp",
      "40mg",
      "1 cp"
    ],
    "Conceito Temporal": [
      "12/12h",
      "almoço",
      "contínuo",
      "manhã",
      "noite",
      "tempo de evolução 9h",
      "30 dias"
    ],
    "Produto Intelectual": [
      "Plano"
    ],
    "Achado": [
      "Plano",
      "sucesso angiográfico",
      "Evolui de forma satisfatória"
    ],
    "Procedimento Laboratorial": [
      "TSH"
    ],
    "Localização ou Região Corporal": [
      "ínfero-lateral distal"
    ],
    "Sinal ou Sintoma": [
      "acometimento de VD"
    ],
    "Espaço ou Junção Corporal": [
      "joelho D"
    ]
  },
  "labels": {
    "osteoartrose": {
      "capitulo": "15"
    },
    "sucesso angiográfico": {
      "capitulo": "11"
    },
    "plano": {
      "capitulo": "24"
    },
    "iam": {
      "capitulo": "11"
    },
    "acometimento de vd": {
      "capitulo": "11"
    }
  }
}