{
  "prontuario_id": 34,
  "text": "PACIENTE DE 69 ANOS COM ICC DE ETIOLOGIA ISQUÊMICA (CRM 06/01 C/ SAFENA PARA DA, MARGINAL E CD), HAS, DM2, DISLIPIDEMIA, TABAGISTA PESADO NO PASSADO, COM CAT DE 08/02 COM OCLUSÃO TOTAL DE DA E PONTE DE SAFENA ASSOCIADO A GRAVE COMPROMETIMENTO DO VE (FE 20%). ESTAVA EM USO DE FUROSEMIDA 40 BID, DIGOXINA 0,25 /D, SINVASTATINA 40 /NOITE, CAPTOPRIL 50 TID, ISOSSORBIDA 20 TID, AAS 100 /D E ESPIRONOLACTONA 25 /D. PROCUROU A EA - XXXX EM 05-11-02 DEVIDO À DISPNÉIA, DPN, ORTOPNÉIA E DOR TORÁCICA OPRESSIVA SEM IRRADIAÇÃO. RECEBEU NITRATO, APRESENTANDO HIPOTENSÃO E PIORA DO ESTADO GERAL. FOI RECEBIDO NO CTI NO MESMO DIA COM TA 100/60, FC 87, FR 33, TAX 35,5ºC E SAT 97%. ECG E ENZIMAS CARDÍACAS SEM ALTERAÇÕES. APRESENTOU BOA EVOLUÇÃO CLÍNICA APÓS OTIMIZAÇÃO DO TTO DA ICC. DEVIDO AO FATO DE TER DPOC E APRESENTADO DISFUNÇÃO RESPIRATÓRIA AGUDA COM INFILTRADO PULMONAR EM BASE DIREITA, FOI REALIZADO CURSO DE ATB COM LEVOFLOXACINA POR 7 DIAS. EM 07-11 TEVE ALTA PARA O ANDAR CLÍNICO, ONDE EVOLUIU BEM, COM MELHORA DA DISPNÉIA E DIMINUIÇÃO DO EDEMA EM MSIS. RECEBE ALTA EM BOM ESTADO GERAL, COM PLANO DE ACOMPANHAR  NO AMBULATÓRIO DE ICC. COMO ESQUEMA DE MEDICAÇÃO PARA ICC PRESCRITO NO ALTA, RECEBE FUROSEMIDA 40 BID, ISOSSORBIDA 40 TID, DIGOXINA 0,25 /D, CAPTOPRIL 50 TID E ESPIRONOLACTONA 25 /D.",
  "entities": {
    "Abreviação": [
      "CRM",
      "SAFENA",
      "DA",
      "MARGINAL",
      "CD",
      "HAS",
      "DM2",
      "CAT",
      "BID",
      "TID",
      "AAS",
      "EA",
      "DPN",
      "CTI",
      "TA",
      "FC",
      "FR",
      "TAX",
      "SAT",
      "ECG",
      "ICC",
      "DPOC",
      "MSIS",
      "ICC DE ETIOLOGIA ISQUÊMICA",
      "OCLUSÃO TOTAL DE DA",
      "GRAVE COMPROMETIMENTO DO VE",
      "FE 20%",
      "OTIMIZAÇÃO DO TTO",
      "CURSO DE ATB",
      "AMBULATÓRIO DE ICC"
    ],
    "Procedimento Terapêutico ou Preventivo": [
      "CRM",
      "CAT",
      "CURSO DE ATB",
      "ESQUEMA DE MEDICAÇÃO"
    ],
    "Parte do Corpo, Órgão ou Componente Orgânico": [
      "SAFENA",
      "DA",
      "MARGINAL",
      "CD",
      "MSIS"
    ],
    "Doença ou Síndrome": [
      "HAS",
      "DM2",
      "DISLIPIDEMIA",
      "ICC",
      "DPOC",
      "ICC DE ETIOLOGIA ISQUÊMICA"
    ],
    "Procedimento Diagnóstico": [
      "CAT",
      "ECG"
    ],
    "Substância Química Orgânica": [
      "FUROSEMIDA",
      "DIGOXINA",
      "SINVASTATINA",
      "ISOSSORBIDA",
      "AAS",
      "ESPIRONOLACTONA",
      "LEVOFLOXACINA"
    ],
    "Substância Farmacológica": [
      "FUROSEMIDA",
      "DIGOXINA",
      "SINVASTATINA",
      "CAPTOPRIL",
      "ISOSSORBIDA",
      "AAS",
      "ESPIRONOLACTONA",
      "NITRATO"
    ],
    "Conceito Quantitativo": [
      "40",
      "BID",
      "50",
      "TID",
      "20",
      "100/60",
      "87",
      "33",
      "97%",
      "0 , 25 /D",
      "35 , 5ºC",
      "25 /D"
    ],
    "Aminoácido, Peptídeo ou Proteína": [
      "CAPTOPRIL"
    ],
    "Organização Relacionada à Saúde": [
      "EA",
      "CTI",
      "ANDAR CLÍNICO",
      "AMBULATÓRIO DE ICC"
    ],
    "Sinal ou Sintoma": [
      "DISPNÉIA",
      "DPN",
      "ORTOPNÉIA",
      "IRRADIAÇÃO",
      "HIPOTENSÃO",
      "ALTERAÇÕES",
      "DOR TORÁCICA OPRESSIVA",
      "PIORA DO ESTADO GERAL",
      "DISFUNÇÃO RESPIRATÓRIA AGUDA"
    ],
    "Negação": [
      "SEM"
    ],
    "Atividade de Assistência à Saúde": [
      "RECEBEU",
      "RECEBIDO",
      "REALIZADO",
      "ALTA",
      "PLANO DE ACOMPANHAR",
      "PRESCRITO NO ALTA"
    ],
    "Atributo Clínico": [
      "TA",
      "FC",
      "FR",
      "TAX",
      "SAT"
    ],
    "Conceito Qualitativo": [
      "87"
    ],
    "Conceito Temporal": [
      "APÓS",
      "NO PASSADO",
      "7 DIAS"
    ],
    "Resultado Laboratorial ou de Teste": [
      "OCLUSÃO TOTAL DE DA",
      "PONTE DE SAFENA",
      "GRAVE COMPROMETIMENTO DO VE",
      "FE 20%",
      "INFILTRADO PULMONAR EM BASE DIREITA"
    ],
    "Procedimento Laboratorial": [
      "ENZIMAS CARDÍACAS"
    ],
    "Achado": [
      "BOA EVOLUÇÃO CLÍNICA",
      "EVOLUIU BEM",
      "MELHORA DA DISPNÉIA",
      "DIMINUIÇÃO DO EDEMA",
      "BOM ESTADO GERAL"
    ],
    "Objeto Manufaturado": [
      "ANDAR CLÍNICO"
    ]
  },
  "labels": {
    "alterações": {
      "capitulo": "08"
    },
    "dpoc": {
      "capitulo": "22"
    },
    "diminuição do edema": {
      "capitulo": "15"
    },
    "disfunção respiratória aguda": {
      "capitulo": "12"
    },
    "ortopnéia": {
      "capitulo": "15"
    },
    "icc de etiologia isquêmica": {
      "capitulo": "11"
    },
    "dor torácica opressiva": {
      "capitulo": "08"
    },
    "irradiação": {
      "capitulo": "22"
    },
    "icc": {
      "capitulo": "11"
    },
    "dm2": {
      "capitulo": "05"
    },
    "dislipidemia": {
      "capitulo": "05"
    },
    "has": {
      "capitulo": "11"
    },
    "hipotensão": {
      "capitulo": "11"
    },
    "dispnéia": {
      "capitulo": "12"
    },
    "dpn": {
      "capitulo": "22"
    }
  }
}