{
  "prontuario_id": 850,
  "text": "LUCAS, 5 anos  Paciente com epilepsia de difícil controle, RDNPM, em uso de topiramato e VPA, iniciou com crises convulsivas, além de queixa de febre, tosse e rinorréia. Realizado Rx Tx: FC em LIE. Iniciado amoxicilina. Em 20/06, iniciado beta-2 1/1h, O2 1l/min e CTC VO, por tempo expiratório aumentado e sibilância; à noite, espaçado beta-2 para de 2/2h. Neuro avaliou caso; aumentou topiramato para 75mg 2x/dia e manteve dose do valproato (impressão: escape? dose inadequada de anticonvulsivantes?). Evoluiu afebril, com melhora do ponto de vista respiratório, sendo retirado O2 em 21/06 pela manhã. Afebril há 24h. Paciente mantém tempo expiratório levemente aumentado, saturando 95% em ar ambiente, nebulizando de 2/2h, caminhando, em bom estado geral. Mãe insiste em ir embora e refere ter recursos para recorrer se piora do quadro. Explico que seria mais prudente aguardar melhora completa. Alta hospitalar com beta-2 de 3/3 horas, CTC VO e amoxicilina, além de anticonvulsivantes. Retornar se necessário.",
  "entities": {
    "Doença ou Síndrome": [
      "epilepsia",
      "RDNPM"
    ],
    "Abreviação": [
      "RDNPM",
      "FC",
      "LIE",
      "O2",
      "Neuro",
      "Rx Tx",
      "CTC VO"
    ],
    "Substância Química Orgânica": [
      "topiramato",
      "amoxicilina",
      "valproato"
    ],
    "Substância Farmacológica": [
      "topiramato",
      "beta-2",
      "valproato",
      "anticonvulsivantes",
      "CTC VO"
    ],
    "Sinal ou Sintoma": [
      "queixa",
      "febre",
      "tosse",
      "rinorréia",
      "afebril",
      "Afebril",
      "quadro",
      "crises convulsivas"
    ],
    "Parte do Corpo, Órgão ou Componente Orgânico": [
      "LIE"
    ],
    "Atividade de Assistência à Saúde": [
      "Iniciado",
      "iniciado",
      "avaliou",
      "aumentou",
      "Evoluiu",
      "retirado",
      "Explico",
      "aguardar",
      "Retornar",
      "Alta hospitalar"
    ],
    "Antibiótico": [
      "amoxicilina"
    ],
    "Conceito Quantitativo": [
      "1/1h",
      "1l/min",
      "2/2h",
      "95%",
      "75mg 2x/dia",
      "dose inadequada",
      "3/3 horas"
    ],
    "Procedimento Terapêutico ou Preventivo": [
      "O2",
      "nebulizando",
      "CTC VO",
      "manteve dose"
    ],
    "Grupo Profissional ou Ocupacional": [
      "Neuro"
    ],
    "Conceito Temporal": [
      "Evoluiu",
      "manhã",
      "à noite"
    ],
    "Negação": [
      "afebril",
      "Afebril"
    ],
    "Atributo Clínico": [
      "saturando"
    ],
    "Achado": [
      "caminhando",
      "melhora do ponto de vista respiratório",
      "bom bom estado estado geral geral",
      "melhora completa"
    ],
    "Grupo Familiar": [
      "Mãe"
    ],
    "Conceito Qualitativo": [
      "piora",
      "difícil controle",
      "dose inadequada"
    ],
    "Procedimento Diagnóstico": [
      "Rx Tx"
    ],
    "Resultado Laboratorial ou de Teste": [
      "tempo expiratório aumentado",
      "tempo expiratório levemente aumentado"
    ]
  },
  "labels": {
    "caminhando": {
      "capitulo": "V"
    },
    "febre": {
      "capitulo": "12"
    },
    "tosse": {
      "capitulo": "12"
    },
    "melhora completa": {
      "capitulo": "21"
    },
    "quadro": {
      "capitulo": "21"
    },
    "epilepsia": {
      "capitulo": "08"
    },
    "queixa": {
      "capitulo": "21"
    },
    "melhora do ponto de vista respiratório": {
      "capitulo": "12"
    },
    "rdnpm": {
      "capitulo": "08"
    },
    "crises convulsivas": {
      "capitulo": "08"
    },
    "rinorréia": {
      "capitulo": "12"
    }
  }
}