{
  "prontuario_id": 68,
  "text": "LUCAS, 59 anos\n\nHIP em setembro 2015.\n# 03/06 - PO de cranioplastia com flap autólogo e correção de fístula liquórica identificada no intra-operatório com uso de pericárdio bovino.\ndrenagem de hematoma epidural parietal esquerdo 06/06.\n\nPaciente em retrono pós operatório com melhora importante da disartria e da hemiparesia esquerada.\n \n\nNega alergias. HAS, em uso de Losartan 50mg 12/12h. Realizou Cirurgia para Varizes em MID, há 12 anos, e Hemorroidectomia, há 14 anos. Dois irmãos falecidos por AVC (sic).\nEx-etilista social e ex-tabagista social (sic).\n\nAo exame: GCS 15, pupilas iso foto, mobiliza 4 membros. Fala e marcha preservados. Paresia de flexão de 1°, 2° e 3° quirodáctilos D.\nSem alteração de sensibilidade. Reflexos Grau II universais.\nFO sem sinais de flogose com flap ósseo em região parietal E.\n\nCD: retorno com nova Tc cranio, manter fisioterapia.\n \n \n \n ",
  "entities": {
    "Função Patológica": [
      "HIP",
      "hematoma epidural parietal esquerdo"
    ],
    "Abreviação": [
      "HIP",
      "PO",
      "HAS",
      "MID",
      "AVC",
      "sic",
      "iso",
      "foto",
      "FO",
      "GCS 15",
      "região parietal E",
      "Tc cranio"
    ],
    "Conceito Temporal": [
      "PO",
      "intra-operatório",
      "pós operatório"
    ],
    "Atividade de Assistência à Saúde": [
      "drenagem",
      "retrono",
      "Realizou",
      "retorno"
    ],
    "Achado": [
      "melhora",
      "iso",
      "foto",
      "Ex-etilista social",
      "ex-tabagista social",
      "GCS 15",
      "mobiliza 4 membros"
    ],
    "Conceito Qualitativo": [
      "importante"
    ],
    "Sinal ou Sintoma": [
      "disartria",
      "hemiparesia esquerada",
      "Paresia de flexão",
      "alteração de sensibilidade",
      "Reflexos Grau II",
      "sinais de flogose"
    ],
    "Negação": [
      "Nega",
      "Sem",
      "sem"
    ],
    "Doença ou Síndrome": [
      "alergias",
      "HAS",
      "Varizes",
      "AVC"
    ],
    "Substância Química Orgânica": [
      "Losartan"
    ],
    "Substância Farmacológica": [
      "Losartan"
    ],
    "Procedimento Terapêutico ou Preventivo": [
      "Cirurgia",
      "Hemorroidectomia",
      "fisioterapia",
      "correção de fístula liquórica"
    ],
    "Parte do Corpo, Órgão ou Componente Orgânico": [
      "MID",
      "pupilas",
      "flap autólogo",
      "1° , 2° e 3° quirodáctilos D"
    ],
    "Grupo Familiar": [
      "irmãos"
    ],
    "Procedimento Diagnóstico": [
      "exame",
      "Tc cranio"
    ],
    "Lesão ou Envenenamento": [
      "FO"
    ],
    "Tecido": [
      "pericárdio bovino"
    ],
    "Dispositivo Médico": [
      "pericárdio bovino"
    ],
    "Conceito Quantitativo": [
      "50mg 12/12h"
    ],
    "Localização ou Região Corporal": [
      "região parietal E"
    ]
  },
  "labels": {
    "melhora": {
      "capitulo": "06"
    },
    "hip": {
      "capitulo": "11"
    },
    "hemiparesia esquerada": {
      "capitulo": "08"
    },
    "sinais de flogose": {
      "capitulo": "21"
    },
    "hematoma epidural parietal esquerdo": {
      "capitulo": "22"
    },
    "reflexos grau ii": {
      "capitulo": "08"
    },
    "fo": {
      "capitulo": "09"
    },
    "alteração de sensibilidade": {
      "capitulo": "21"
    },
    "varizes": {
      "capitulo": "13"
    },
    "has": {
      "capitulo": "11"
    },
    "avc": {
      "capitulo": "08"
    },
    "paresia de flexão": {
      "capitulo": "08"
    },
    "disartria": {
      "capitulo": "06"
    }
  }
}