{
  "prontuario_id": 78,
  "text": "Lucas, 52 ANOS\nIC ISQUEMICA (RVM EM 2008, ATC EM 2009 E IAM + PCR + ATC DA EM 2011)\nDEFICT NEUROLÓGICO PÓS PCR EM 2011 (PERDA MEMÓRIA RECENTE)\nEM USO DE: ENALAPRIL 10MG 12/12HS, CARVEDILOL 25MG 12/12HS, ESPIRONOLACTONA 25MG / D, AAS 200MG / D,monocordil 20mg 2x,SINVASTATINA 40MG / D, LEVOTIROXINA 50MCG / D +25MCG / DIA, QUETRUSe lamitor e exodus\nTROUXE LAB HB 13,1 , LEUC 7730,  NA 141, K 4,3, CRAET 0,8, , GLIC 94, UREIA 72, CPK 126, TGP 27, TGO 23, CT 101, TSH 3,44, HB GLICADA 5,87, TG 120, HDL 28, LDL 50\nECOCARDIO 028/05/16 AE 44 , VD 23, VE 52/38, FEVE 52% VE HIPERTROFIACDO. ACINESIA MEDIO BASAL INFERO DORSAL, ALTERACAO RELAXAMENTO\nS # \nEXCETO PELA PERDADA MEMORIA . REFER ESTAR ASSINTYOMATICO R\nsem estase jugular\nAC: BCRNf sem sopros B2 DESDOBRADA FIXA\nMV+ e simétrico, sem RA.\nAbd: sp\nMMII: sem edema\nBoa perfusão periférica\nA # IC isquemica CF II - E REMODELAMENTO REVERSO\nP # SUSPENDO  MONOCORDIL E ESPIRONOLACTONA.\n     REDUZO AAS PARA 100MG\n     SOLICITO LAB + ECOTT DE CONTROLE\n     RETORNO EM 3 MESES\n \n \n \n ",
  "entities": {
    "Abreviação": [
      "RVM",
      "ATC",
      "IAM",
      "PCR",
      "AAS",
      "D",
      "LAB",
      "ECOCARDIO",
      "AC",
      "BCRNf",
      "MV+",
      "RA",
      "MMII",
      "ECOTT",
      "IC ISQUEMICA",
      "HB 13 , 1",
      "LEUC 7730",
      "NA 141",
      "K 4 , 3",
      "CRAET 0 , 8",
      "GLIC 94",
      "CPK 126",
      "TGP 27",
      "TGO 23",
      "CT 101",
      "TSH 3 , 44",
      "HB GLICADA 5 , 87",
      "TG 120",
      "HDL 28",
      "LDL 50",
      "AE 44",
      "VD 23",
      "VE 52/38",
      "FEVE 52%",
      "VE HIPERTROFIACDO",
      "IC isquemica CF II"
    ],
    "Procedimento Terapêutico ou Preventivo": [
      "RVM",
      "ATC"
    ],
    "Doença ou Síndrome": [
      "IAM",
      "IC ISQUEMICA",
      "VE HIPERTROFIACDO",
      "IC isquemica CF II",
      "REMODELAMENTO REVERSO"
    ],
    "Conceito Temporal": [
      "PÓS",
      "D",
      "MESES"
    ],
    "Substância Química Orgânica": [
      "AAS",
      "LEVOTIROXINA",
      "QUETRUSe",
      "lamitor",
      "exodus",
      "MONOCORDIL",
      "ESPIRONOLACTONA"
    ],
    "Substância Farmacológica": [
      "AAS",
      "QUETRUSe",
      "lamitor",
      "exodus",
      "MONOCORDIL",
      "ESPIRONOLACTONA"
    ],
    "Procedimento Laboratorial": [
      "LAB"
    ],
    "Procedimento Diagnóstico": [
      "ECOCARDIO",
      "ECOTT"
    ],
    "Achado": [
      "ASSINTYOMATICO",
      "BCRNf",
      "MV+",
      "simétrico",
      "Boa perfusão periférica"
    ],
    "Sinal ou Sintoma": [
      "ASSINTYOMATICO",
      "sopros",
      "edema",
      "DEFICT NEUROLÓGICO",
      "PERDA MEMÓRIA RECENTE",
      "PERDADA MEMORIA",
      "estase jugular",
      "B2 DESDOBRADA FIXA"
    ],
    "Negação": [
      "ASSINTYOMATICO",
      "sem"
    ],
    "Atributo Clínico": [
      "AC",
      "MV+"
    ],
    "Localização ou Região Corporal": [
      "Abd"
    ],
    "Parte do Corpo, Órgão ou Componente Orgânico": [
      "MMII"
    ],
    "Atividade de Assistência à Saúde": [
      "SUSPENDO",
      "REDUZO",
      "SOLICITO",
      "RETORNO"
    ],
    "Conceito Quantitativo": [
      "100MG",
      "3"
    ],
    "Resultado Laboratorial ou de Teste": [
      "HB 13 , 1",
      "LEUC 7730",
      "NA 141",
      "K 4 , 3",
      "CRAET 0 , 8",
      "GLIC 94",
      "UREIA 72",
      "CPK 126",
      "TGP 27",
      "TGO 23",
      "CT 101",
      "TSH 3 , 44",
      "HB GLICADA 5 , 87",
      "TG 120",
      "HDL 28",
      "LDL 50",
      "AE 44",
      "VD 23",
      "VE 52/38",
      "FEVE 52%",
      "VE HIPERTROFIACDO"
    ]
  },
  "labels": {
    "ic isquemica cf ii": {
      "capitulo": "11"
    },
    "ve hipertrofiacdo": {
      "capitulo": "11"
    },
    "edema": {
      "capitulo": "21"
    },
    "perda memória recente": {
      "capitulo": "06"
    },
    "b2 desdobrada fixa": {
      "capitulo": "11"
    },
    "sopros": {
      "capitulo": "11"
    },
    "iam": {
      "capitulo": "11"
    },
    "bcrnf": {
      "capitulo": "11"
    },
    "defict neurológico": {
      "capitulo": "08"
    },
    "remodelamento reverso": {
      "capitulo": "11"
    },
    "estase jugular": {
      "capitulo": "21"
    },
    "ic isquemica": {
      "capitulo": "11"
    },
    "mv+": {
      "capitulo": "11"
    }
  }
}