{
  "prontuario_id": 605,
  "text": "PRIMEIRA CONSULTA\nS # PACIENTE REFERE TONTURA DO TIPO VERTIGINOSA, COM PIORA AO MOVIMENTAR A CABEÇA, ASSOCIADO A NAUSEA - COM CRISE DE DURAÇÃO DE 1 HORA. COM MLEHORA PARCIAL. AMNTENDO COM INSTABILIDADE POR 5 DIAS. EM USO DE VERTIX E LABIRIN POR 3 MESES. NEGA HIPOACUSIA OU OUTRAS QUEIXAS EM  ORL. \nREFERE TAMBEM RONCOS E ENGASGOS DURANTE A NOITE, AINDA NAO REALIZOU POLISSONOGRAFIA.\nHMP: HAS\nO # \nOT: SP\nRNF: PM, HHCCII\nORF: MALAPATI 3, AMIGDALA GII\nAUSENCIA DE NISTAGMO\nHEAD TRUST NEGATIVO\nP #\nROTINA OTONEURO\nCICLO DE MECLIN\nFAÇO DECLARAÇÃO SOLICITANDO MUDANÇA DE POSTO DE TRABALHO (TRABALHA EM ALTURAS)\nRETORNO COM EXAMES\nR1 Doutor Vital Bazil\nR2 Doutor Vital Bazil\n \n \n \n ",
  "entities": {
    "Atividade de Assistência à Saúde": [
      "CONSULTA",
      "RETORNO"
    ],
    "Paciente ou Grupo com Deficiência": [
      "PACIENTE"
    ],
    "Sinal ou Sintoma": [
      "TONTURA",
      "NAUSEA",
      "CRISE",
      "INSTABILIDADE",
      "HIPOACUSIA",
      "QUEIXAS",
      "RONCOS",
      "ENGASGOS",
      "HHCCII",
      "NISTAGMO",
      "PIORA AO MOVIMENTAR A CABEÇA",
      "AMIGDALA GII"
    ],
    "Substância Química Orgânica": [
      "VERTIX",
      "LABIRIN",
      "MECLIN"
    ],
    "Substância Farmacológica": [
      "VERTIX",
      "LABIRIN",
      "MECLIN"
    ],
    "Conceito Quantitativo": [
      "3"
    ],
    "Negação": [
      "NEGA",
      "NAO",
      "AUSENCIA"
    ],
    "Abreviação": [
      "ORL",
      "HMP",
      "HAS",
      "OT",
      "SP",
      "RNF",
      "PM",
      "HHCCII",
      "ORF",
      "OTONEURO",
      "R1",
      "R2"
    ],
    "Grupo Profissional ou Ocupacional": [
      "ORL",
      "R1",
      "Doutor",
      "R2"
    ],
    "Procedimento Diagnóstico": [
      "POLISSONOGRAFIA",
      "EXAMES"
    ],
    "Atributo Clínico": [
      "HMP"
    ],
    "Doença ou Síndrome": [
      "HAS"
    ],
    "Achado": [
      "SP",
      "MALAPATI 3"
    ],
    "Localização ou Região Corporal": [
      "ORF"
    ],
    "Procedimento Laboratorial": [
      "EXAMES"
    ],
    "Conceito Temporal": [
      "DURAÇÃO DE 1 HORA",
      "5 DIAS",
      "DURANTE A NOITE"
    ],
    "Classificação": [
      "MALAPATI 3"
    ],
    "Resultado Laboratorial ou de Teste": [
      "HEAD TRUST NEGATIVO"
    ],
    "Atividade Ocupacional": [
      "POSTO DE TRABALHO",
      "TRABALHA EM ALTURAS"
    ]
  },
  "labels": {
    "tontura": {
      "capitulo": "08"
    },
    "piora ao movimentar a cabeça": {
      "capitulo": "08"
    },
    "nausea": {
      "capitulo": "08"
    },
    "crise": {
      "capitulo": "21"
    },
    "nistagmo": {
      "capitulo": "08"
    },
    "instabilidade": {
      "capitulo": "08"
    },
    "roncos": {
      "capitulo": "10"
    },
    "engasgos": {
      "capitulo": "10"
    },
    "amigdala gii": {
      "capitulo": "10"
    },
    "malapati 3": {
      "capitulo": "10"
    }
  }
}