{
  "prontuario_id": 863,
  "text": "# QP: SANGRAMENTO INTESTINAL\n# HMA: HÁ 15 ANOS COM QUADRO DE HEMATOQUEZIA  INTERMITENTE ATÉ 5 X / DIA NAS CRISES. REFERE QUE SEMPRE TEVE FEZES DIARRÉICAS ATÉ 10 VEZES / DIA. REFERE MUCORRÉIA E PUXO. NEGA EMAGRECIMENTO. NEGA HIPOREXIA. NEGA QUEIXAS ORIFICIAIS\n# HPP:\nHAS EM USO DE ENALAPRIL\nDM II METFORMINA E GLIBECLAMIDA\nFLUOXETINA\nSINVASTATINA\nG I V P III (EPISIOTOMIA ) C I ( 3250 G) + LAQUEADURA\n# HF: HX DE CCR NA FAMÍLIA (TIO)\n# CHV: EX-TABAGISTA HÁ 15 ANOS 30 ANOS / MAÇO\n# O: BEG, LOTE, AAA\n        ABDOME GLOBOSO, FLÁCIDO, INDOLOR, SEM MASSAS PALPÁVEIS\n        PROCTO: INSPEÇÃO: MAMILO HEMORROIDÁRIO EXTERNO ANTERIOR DIREITO, PLICOMA POSTERIOR\n                         TR: ESFINCTER NORMOTÔNICO, SEM MASSAS PALPÁVEIS, SEM SANGUE EM LUVA\n                        ANUSCOPIA: MUCOSA NORMOCORADA, SEM SANGRAMENTO\n # A: HEMATOQUEZIA A/E\n # C: SOLICITO COLONO. RETORNO COM EXAME.\n \n \n \n ",
  "entities": {
    "Sinal ou Sintoma": [
      "QP",
      "HEMATOQUEZIA",
      "CRISES",
      "MUCORRÉIA",
      "PUXO",
      "EMAGRECIMENTO",
      "HIPOREXIA",
      "INDOLOR",
      "SANGRAMENTO",
      "SANGRAMENTO INTESTINAL",
      "FEZES DIARRÉICAS",
      "QUEIXAS ORIFICIAIS",
      "MASSAS PALPÁVEIS"
    ],
    "Abreviação": [
      "QP",
      "HMA",
      "HPP",
      "HAS",
      "HF",
      "CCR",
      "CHV",
      "BEG",
      "LOTE",
      "PROCTO",
      "TR",
      "COLONO",
      "DM II"
    ],
    "Conceito Temporal": [
      "INTERMITENTE",
      "HÁ 15 ANOS"
    ],
    "Negação": [
      "NEGA",
      "INDOLOR",
      "SEM"
    ],
    "Doença ou Síndrome": [
      "HAS",
      "CCR",
      "DM II",
      "MAMILO HEMORROIDÁRIO",
      "PLICOMA POSTERIOR"
    ],
    "Substância Farmacológica": [
      "ENALAPRIL",
      "METFORMINA",
      "GLIBECLAMIDA",
      "FLUOXETINA",
      "SINVASTATINA"
    ],
    "Aminoácido, Peptídeo ou Proteína": [
      "ENALAPRIL"
    ],
    "Substância Química Orgânica": [
      "ENALAPRIL",
      "METFORMINA",
      "GLIBECLAMIDA",
      "FLUOXETINA",
      "SINVASTATINA"
    ],
    "Função de Organismo": [
      "G",
      "P"
    ],
    "Conceito Quantitativo": [
      "III",
      "I",
      "5 X / DIA",
      "10 VEZES / DIA"
    ],
    "Procedimento Terapêutico ou Preventivo": [
      "EPISIOTOMIA",
      "C",
      "LAQUEADURA"
    ],
    "Grupo Familiar": [
      "FAMÍLIA"
    ],
    "Achado": [
      "EX-TABAGISTA",
      "BEG",
      "LOTE",
      "GLOBOSO",
      "FLÁCIDO",
      "ESFINCTER NORMOTÔNICO",
      "MUCOSA NORMOCORADA"
    ],
    "Parte do Corpo, Órgão ou Componente Orgânico": [
      "ABDOME"
    ],
    "Procedimento Diagnóstico": [
      "TR",
      "ANUSCOPIA",
      "COLONO"
    ],
    "Substância Corporal": [
      "SANGUE"
    ],
    "Atividade de Assistência à Saúde": [
      "SOLICITO",
      "RETORNO"
    ],
    "Função Patológica": [
      "SANGRAMENTO INTESTINAL"
    ],
    "Localização ou Região Corporal": [
      "EXTERNO ANTERIOR DIREITO"
    ]
  },
  "labels": {
    "mucorréia": {
      "capitulo": "13"
    },
    "flácido": {
      "capitulo": "15"
    },
    "crises": {
      "capitulo": "13"
    },
    "qp": {
      "capitulo": "13"
    },
    "sangramento intestinal": {
      "capitulo": "13"
    },
    "ccr": {
      "capitulo": "21"
    },
    "sangramento": {
      "capitulo": "13"
    },
    "mamilo hemorroidário": {
      "capitulo": "13"
    },
    "ex-tabagista": {
      "capitulo": "24"
    },
    "hematoquezia": {
      "capitulo": "13"
    },
    "dm ii": {
      "capitulo": "5"
    },
    "puxo": {
      "capitulo": "13"
    },
    "mucosa normocorada": {
      "capitulo": "21"
    },
    "massas palpáveis": {
      "capitulo": "21"
    },
    "fezes diarréicas": {
      "capitulo": "13"
    },
    "has": {
      "capitulo": "5"
    },
    "esfincter normotônico": {
      "capitulo": "21"
    },
    "beg": {
      "capitulo": "24"
    },
    "globoso": {
      "capitulo": "15"
    },
    "plicoma posterior": {
      "capitulo": "21"
    },
    "lote": {
      "capitulo": "24"
    }
  }
}