{
  "prontuario_id": 922,
  "text": "Lucas, 63\n# DM, em uso de metformina\n# Relata arritmia, em uso de amiodarona, digoxina e furosemida\n# Nega tabagismo e etilismo.\n# Em uso de gabapentina \n# Relata \" mancha no pulmao \" dx em nov/14, associado a intoxicaçao por organofosfardo  ( Foi agricultor, usava radiatox 60 )\nRelata inícuio de quadro de dispneia há 7 meses, relata dispneia ao repouso associado a tosse e rouquidao. Relata ter ficado depressivo apos a visualização das \" manchas no pulmao \", sendo encaminhado ao psiquiarta e começou uma medicaçao que nao sabe o nome mas apresentou melhora do quadro de dispneia, sem queixas no momento.\nRx de torax 21/10/14: Opacidades pulmonares interstício-alveolares bilaterais, confluentes, algumas de aspecto nodular ( inflamatório-infeccioso )?\nEspirometria 21/05/15:\nCVF: pre-72% pos-76%\nVEF1: pre 89% - pós 95\nVEF1/CVF: pre -124% e pós -124% \nO # BEG, hidratadom corado, eupneico afebril\nSat: 98% em AA FC: 97\nAP: MV bilat sem RA\nACV: BCRNF sem sopro\nAbd: sp\nA # Pneumonia intersticial provocada por amiodarona\nP # Escrevo carta para cardiologia para remanejar medicação\nPara a próxima consulta, solicitar espirometria e TC  de torax\nR2 Doutor Vital Brazil ",
  "entities": {
    "Abreviação": [
      "DM",
      "dx",
      "CVF",
      "pre-72%",
      "pos-76%",
      "VEF1",
      "VEF1/CVF",
      "BEG",
      "AP",
      "RA",
      "ACV",
      "BCRNF",
      "Abd",
      "sp",
      "R2",
      "98%",
      "MV bilat",
      "TC de torax"
    ],
    "Doença ou Síndrome": [
      "DM",
      "tabagismo",
      "etilismo",
      "Pneumonia intersticial"
    ],
    "Substância Farmacológica": [
      "metformina",
      "amiodarona",
      "digoxina",
      "furosemida",
      "gabapentina",
      "medicaçao",
      "medicação"
    ],
    "Substância Química Orgânica": [
      "metformina",
      "amiodarona",
      "digoxina",
      "furosemida",
      "gabapentina",
      "organofosfardo"
    ],
    "Achado": [
      "arritmia",
      "BEG",
      "hidratadom",
      "corado",
      "eupneico",
      "BCRNF",
      "sp",
      "MV bilat"
    ],
    "Negação": [
      "Nega",
      "sem",
      "afebril"
    ],
    "Substância Perigosa ou Venenosa": [
      "organofosfardo"
    ],
    "Sinal ou Sintoma": [
      "dispneia",
      "tosse",
      "rouquidao",
      "depressivo",
      "queixas",
      "inflamatório-infeccioso",
      "afebril",
      "RA",
      "sopro",
      "mancha no pulmao",
      "dispneia ao repouso",
      "manchas no pulmao"
    ],
    "Atividade de Assistência à Saúde": [
      "encaminhado",
      "Escrevo",
      "consulta",
      "solicitar"
    ],
    "Grupo Profissional ou Ocupacional": [
      "psiquiarta",
      "cardiologia",
      "R2",
      "Doutor"
    ],
    "Procedimento Terapêutico ou Preventivo": [
      "medicaçao",
      "medicação"
    ],
    "Resultado Laboratorial ou de Teste": [
      "confluentes",
      "CVF",
      "pre-72%",
      "pos-76%",
      "VEF1",
      "VEF1/CVF",
      "Opacidades pulmonares interstício-alveolares bilaterais",
      "aspecto nodular",
      "pre 89%",
      "pós 95",
      "pre -124%",
      "pós -124%"
    ],
    "Procedimento Diagnóstico": [
      "Espirometria",
      "espirometria",
      "Rx de torax",
      "TC de torax"
    ],
    "Atributo Clínico": [
      "Sat",
      "AP",
      "ACV"
    ],
    "Conceito Quantitativo": [
      "97"
    ],
    "Conceito Temporal": [
      "próxima",
      "há 7 meses"
    ]
  },
  "labels": {
    "ra": {
      "capitulo": "11"
    },
    "rouquidao": {
      "capitulo": "09"
    },
    "arritmia": {
      "capitulo": "11"
    },
    "queixas": {
      "capitulo": "21"
    },
    "manchas no pulmao": {
      "capitulo": "12"
    },
    "inflamatório-infeccioso": {
      "capitulo": "12"
    },
    "depressivo": {
      "capitulo": "06"
    },
    "dispneia": {
      "capitulo": "12"
    },
    "tosse": {
      "capitulo": "09"
    },
    "dispneia ao repouso": {
      "capitulo": "12"
    },
    "mancha no pulmao": {
      "capitulo": "12"
    },
    "pneumonia intersticial": {
      "capitulo": "12"
    },
    "dm": {
      "capitulo": "11"
    }
  }
}