{
  "prontuario_id": 849,
  "text": "85 anos.\nlombalgia de longa data, sem historia de trauma.\napresentando melhora parcial leve com fst\ndor em ombro dir de longa data.\nrx de coluna lombo sacra ( 07/12): dextroescoliose, espondilolistese grau 1 L5, redução espaço discais L3-L4 e L5-S1, redução da altura do corpo vertebral de T12 e L1\nUs de ombro dir (03/11): tendão do supra rotura completa\nEF: lasegue negativo bilateral, fm graus 5 universal, sensibildaide preservada bilateral, hiporreflexia patelar e aquiliana bilateral.\nA: hernia disco L5-S1 + lesão do supra.\nCD: fst, analgesico, retorno em 1 mes. após termino da fst.\nencaminho ao amb. do ombro para discussõ de cx\n \n \n \n ",
  "entities": {
    "Sinal ou Sintoma": [
      "lombalgia",
      "hiporreflexia patelar e aquiliana bilateral"
    ],
    "Negação": [
      "sem"
    ],
    "Procedimento Terapêutico ou Preventivo": [
      "fst",
      "cx"
    ],
    "Abreviação": [
      "fst",
      "EF",
      "CD",
      "amb",
      "cx",
      "ombro dir",
      "rx de coluna lombo sacra",
      "Us de ombro dir",
      "fm graus 5 universal"
    ],
    "Atividade de Assistência à Saúde": [
      "fst",
      "CD",
      "retorno",
      "encaminho",
      "discussõ"
    ],
    "Anormalidade Anatômica": [
      "dextroescoliose"
    ],
    "Resultado Laboratorial ou de Teste": [
      "dextroescoliose",
      "espondilolistese grau 1 L5",
      "redução espaço discais L3-L4 e L5-S1",
      "redução da altura do corpo vertebral de T12 e L1",
      "tendão do supra rotura completa"
    ],
    "Substância Farmacológica": [
      "analgesico"
    ],
    "Substância Química Orgânica": [
      "analgesico"
    ],
    "Substância Perigosa ou Venenosa": [
      "analgesico"
    ],
    "Organização Relacionada à Saúde": [
      "amb"
    ],
    "Parte do Corpo, Órgão ou Componente Orgânico": [
      "ombro",
      "ombro dir"
    ],
    "Conceito Temporal": [
      "longa data",
      "1 mes",
      "após termino"
    ],
    "Lesão ou Envenenamento": [
      "historia de trauma",
      "lesão do supra"
    ],
    "Conceito Qualitativo": [
      "melhora parcial leve"
    ],
    "Procedimento Diagnóstico": [
      "rx de coluna lombo sacra",
      "Us de ombro dir"
    ],
    "Doença ou Síndrome": [
      "espondilolistese grau 1 L5",
      "hernia disco L5-S1"
    ],
    "Achado": [
      "lasegue negativo bilateral",
      "fm graus 5 universal",
      "sensibildaide preservada bilateral"
    ]
  },
  "labels": {
    "espondilolistese grau 1 l5": {
      "capitulo": "15"
    },
    "lesão do supra": {
      "capitulo": "22"
    },
    "hiporreflexia patelar e aquiliana bilateral": {
      "capitulo": "21"
    },
    "hernia disco l5-s1": {
      "capitulo": "15"
    },
    "lombalgia": {
      "capitulo": "15"
    },
    "dextroescoliose": {
      "capitulo": "15"
    },
    "historia de trauma": {
      "capitulo": "22"
    }
  }
}