{
  "prontuario_id": 697,
  "text": "# Lucas, 74 ANOS\n# QP: RETORNO COM EXAME ( ACOMPANHA DESDE 2014 POR DRC );\nNA ÚLTIMA CONSULTA (07/15) FOI RELATADO POLACIURIA E SOLICITADO PARCIAL DE URINA;\nPACIENTE RELATA QUEDA E HEMATÚRIA  (SOLICITADO US. DE VIAS URINÁRIAS );\n# HMA: RELATA FRAQUEZA AO FICAR POR TEMPO PROLONGADO (1 HORA) EM PÉ; INICIOU HÁ 03 MESES;\n- HAS HÁ 20 ANOS;\n- HIPOTIREOIDISMO;\n- FA;\n# MEDICAMENTOS: EM USO DE LOSARTANA 50MG 2X / DIA,  HIDROCLOROTIAZIDA 25MG, LEVOTIROXINA 100MCG, METOPROLOL 50MG, MARCOUMAR 3MG.\n# S: NEGA DISURIA E HEMATURIA, NEGA INCONTINENCIA. \n# O: BEG, LOTE, ANICTERICA, ACIANOTICA, HIDRATADA;\nDV: PA 130/90, FC 88, PESO 103;\nCPP: MV PRESENTE BILATERALMENTE S/RA;\nACV: B ARRITMICAS NFSS; \nABD: GLOBOSO, RHA +, INDOLOR A PALPAÇÃO;\nMMII SEM EDEMA;\n# LAB 19/07/2016: \nCR 1,0\nPARCIAL DE URINA HEMOGLUBINA ++;\n# A: DRC POR NEFROESCLEROSE HIPERTENSIVA, CLEREANCE DE CREATININA 56 ML/MIN\n# P: SOLICITO US. VIAS URINÁRIAS; PARCIAL DE URINA  (2X - UM EM AGOSTO/SETEMBRO);\n- RETORNO 02 MESES;\n \n \n \n ",
  "entities": {
    "Sinal ou Sintoma": [
      "QP",
      "POLACIURIA",
      "HEMATÚRIA",
      "FRAQUEZA",
      "DISURIA",
      "HEMATURIA",
      "INCONTINENCIA",
      "ANICTERICA",
      "ACIANOTICA",
      "GLOBOSO",
      "INDOLOR",
      "EDEMA",
      "B ARRITMICAS"
    ],
    "Abreviação": [
      "QP",
      "DRC",
      "US",
      "HAS",
      "FA",
      "2X",
      "BEG",
      "LOTE",
      "DV",
      "PA",
      "FC",
      "CPP",
      "S/RA",
      "MMII",
      "LAB",
      "MV PRESENTE BILATERALMENTE",
      "B ARRITMICAS",
      "RHA +",
      "CR 1 , 0"
    ],
    "Atividade de Assistência à Saúde": [
      "RETORNO",
      "CONSULTA",
      "SOLICITADO",
      "SOLICITO"
    ],
    "Procedimento Laboratorial": [
      "EXAME",
      "LAB",
      "PARCIAL DE URINA"
    ],
    "Procedimento Diagnóstico": [
      "EXAME",
      "US",
      "PALPAÇÃO"
    ],
    "Doença ou Síndrome": [
      "DRC",
      "HAS",
      "HIPOTIREOIDISMO",
      "FA",
      "NEFROESCLEROSE HIPERTENSIVA"
    ],
    "Conceito Temporal": [
      "ÚLTIMA",
      "DIA",
      "HÁ 03 MESES",
      "HÁ 20 ANOS"
    ],
    "Paciente ou Grupo com Deficiência": [
      "PACIENTE"
    ],
    "Lesão ou Envenenamento": [
      "QUEDA"
    ],
    "Substância Farmacológica": [
      "MEDICAMENTOS",
      "LOSARTANA",
      "HIDROCLOROTIAZIDA",
      "LEVOTIROXINA",
      "METOPROLOL",
      "MARCOUMAR"
    ],
    "Substância Química Orgânica": [
      "LOSARTANA",
      "HIDROCLOROTIAZIDA",
      "METOPROLOL",
      "MARCOUMAR"
    ],
    "Conceito Quantitativo": [
      "50MG",
      "2X",
      "25MG",
      "100MCG",
      "3MG",
      "130/90",
      "88",
      "103"
    ],
    "Aminoácido, Peptídeo ou Proteína": [
      "LEVOTIROXINA"
    ],
    "Hormônio": [
      "LEVOTIROXINA"
    ],
    "Negação": [
      "NEGA",
      "ANICTERICA",
      "ACIANOTICA",
      "S/RA",
      "INDOLOR",
      "SEM"
    ],
    "Achado": [
      "BEG",
      "LOTE",
      "HIDRATADA",
      "S/RA",
      "MV PRESENTE BILATERALMENTE",
      "B ARRITMICAS",
      "RHA +"
    ],
    "Atributo Clínico": [
      "DV",
      "PA",
      "FC",
      "PESO",
      "CPP"
    ],
    "Localização ou Região Corporal": [
      "MMII"
    ],
    "Parte do Corpo, Órgão ou Componente Orgânico": [
      "MMII",
      "VIAS URINÁRIAS"
    ],
    "Resultado Laboratorial ou de Teste": [
      "CR 1 , 0",
      "PARCIAL DE URINA",
      "HEMOGLUBINA ++",
      "CLEREANCE DE CREATININA 56 ML/MIN"
    ]
  },
  "labels": {
    "queda": {
      "capitulo": "11"
    },
    "incontinencia": {
      "capitulo": "16"
    },
    "anicterica": {
      "capitulo": "09"
    },
    "s/ra": {
      "capitulo": "08"
    },
    "qp": {
      "capitulo": "16"
    },
    "hipotireoidismo": {
      "capitulo": "05"
    },
    "fraqueza": {
      "capitulo": "15"
    },
    "nefroesclerose hipertensiva": {
      "capitulo": "11"
    },
    "acianotica": {
      "capitulo": "09"
    },
    "b arritmicas": {
      "capitulo": "08"
    },
    "disuria": {
      "capitulo": "16"
    },
    "polaciuria": {
      "capitulo": "16"
    },
    "drc": {
      "capitulo": "11"
    },
    "hematúria": {
      "capitulo": "16"
    },
    "edema": {
      "capitulo": "15"
    },
    "hematuria": {
      "capitulo": "16"
    }
  }
}