{
  "prontuario_id": 559,
  "text": "Lucas, 4 anos\n\n# Tinea Capitis?\n\ns: Usou griseofulvina 250 mg dia por 3 semanas e cessou devido à queixa da criança de ardência na boca (sem lesões locais).\nMelhora subjetiva segundo relato da mãe de 90% do quadro.\n\nNega familiares e contatos com lesões semelhantes. Criança frequenta creche.\n\no: lesões eritemato descamativas em cc sem exudação, indolores no momento, com repilação imporante das areas previamente alopecicas.\n\nmicológico direto negativo\nCultura em andamento.\n\na: Tinea capitis (quadro clinico compativel e melhora importante com 3 semanas de antifungico oral)\np: Mantenho griseofulvina 250 mg dia (peso atual 16 kg - porém Doutor Vital Brazil sugere não aumentar dose) por 30 dias e retorno para reavaliação.\nmantenho xampu ceto 2%.\n\nr1 Doutor Vital Brazil ",
  "entities": {
    "Substância Farmacológica": [
      "griseofulvina",
      "antifungico oral",
      "xampu ceto"
    ],
    "Substância Química Orgânica": [
      "griseofulvina"
    ],
    "Conceito Temporal": [
      "dia"
    ],
    "Conceito Quantitativo": [
      "3",
      "30",
      "2%",
      "250 mg",
      "16 kg"
    ],
    "Sinal ou Sintoma": [
      "queixa",
      "lesões",
      "exudação",
      "indolores",
      "lesões eritemato descamativas"
    ],
    "Paciente ou Grupo com Deficiência": [
      "criança",
      "Criança"
    ],
    "Parte do Corpo, Órgão ou Componente Orgânico": [
      "boca"
    ],
    "Negação": [
      "sem",
      "Nega",
      "indolores",
      "não"
    ],
    "Grupo Familiar": [
      "familiares"
    ],
    "Organização": [
      "creche"
    ],
    "Localização ou Região Corporal": [
      "cc"
    ],
    "Função Fisiológica": [
      "repilação"
    ],
    "Procedimento Laboratorial": [
      "Cultura"
    ],
    "Atividade de Assistência à Saúde": [
      "Mantenho",
      "retorno",
      "reavaliação",
      "mantenho"
    ],
    "Grupo Profissional ou Ocupacional": [
      "Doutor",
      "r1"
    ],
    "Abreviação": [
      "r1",
      "16 kg",
      "xampu ceto"
    ],
    "Doença ou Síndrome": [
      "Tinea Capitis",
      "Tinea capitis"
    ],
    "Lesão ou Envenenamento": [
      "lesões locais"
    ],
    "Achado": [
      "Melhora subjetiva segundo relato da mãe",
      "micológico direto negativo",
      "quadro clinico compativel"
    ],
    "Resultado Laboratorial ou de Teste": [
      "micológico direto negativo"
    ],
    "Atributo Clínico": [
      "peso atual"
    ],
    "Procedimento Terapêutico ou Preventivo": [
      "aumentar dose"
    ]
  },
  "labels": {
    "tinea capitis": {
      "capitulo": "14"
    },
    "micológico direto negativo": {
      "capitulo": "21"
    },
    "lesões locais": {
      "capitulo": "21"
    },
    "queixa": {
      "capitulo": "21"
    },
    "quadro clinico compativel": {
      "capitulo": "21"
    },
    "lesões": {
      "capitulo": "21"
    },
    "lesões eritemato descamativas": {
      "capitulo": "21"
    }
  }
}