{
  "prontuario_id": 589,
  "text": "POT FAF POR FX DE UMERO ESQ COM LESÃO DE NERVO RADIAL EM 2011\n\nREFERE DOR RECORRENTE EM OMBRO E BRAÇO\nMÃO CAÍDA AO EXAME FÍSICO (LESAO RADIAL), PLANO DE TRANSFERENCIA TENDINOSA POSTERIOR COM O GRUPO DA MÃO\n\nAO RX, FX CONSOLIDADA COM DESVIO ROTACIONAL\nRETORNA COM RX PANORAMICO SOLICITADO EM ULT CONSULTA QUE INDICA DESVIO EM ROTAÇÃO EXTERNA DO ÚMERO + ENCURTAMENTO DE 4CM\n\nAGENDO OSTEOTOMIA DERROTADORA + ALONGAMENTO ÓSSEO DE 4CM PARA DIA 29/07/2016\nORIENTO PACIENTE SOBRE RISCOS, COMPLICAÇÕES COMO PSEUDOARTROSE, INFECÇÃO, RETARDO DE CONSOLIDAÇÃO PERDA FUNCIONAL E ATÉ MORTE\nPACIENTE DIZ ENTENDER SITUAÇÃO\n\nR1 Doutor Vital Brazil ",
  "entities": {
    "Conceito Temporal": [
      "POT"
    ],
    "Abreviação": [
      "POT",
      "FAF",
      "RX",
      "R1",
      "FX DE UMERO ESQ",
      "RX PANORAMICO"
    ],
    "Lesão ou Envenenamento": [
      "FAF",
      "FX DE UMERO ESQ",
      "LESÃO DE NERVO RADIAL",
      "LESAO RADIAL"
    ],
    "Parte do Corpo, Órgão ou Componente Orgânico": [
      "OMBRO",
      "BRAÇO"
    ],
    "Atividade de Assistência à Saúde": [
      "PLANO",
      "RETORNA",
      "SOLICITADO",
      "CONSULTA",
      "AGENDO",
      "ORIENTO"
    ],
    "Procedimento Diagnóstico": [
      "RX",
      "RX PANORAMICO"
    ],
    "Resultado Laboratorial ou de Teste": [
      "ENCURTAMENTO",
      "DESVIO EM ROTAÇÃO EXTERNA DO ÚMERO"
    ],
    "Conceito Quantitativo": [
      "4CM"
    ],
    "Paciente ou Grupo com Deficiência": [
      "PACIENTE"
    ],
    "Função Patológica": [
      "PSEUDOARTROSE"
    ],
    "Sinal ou Sintoma": [
      "INFECÇÃO",
      "MÃO CAÍDA",
      "DESVIO ROTACIONAL",
      "PERDA FUNCIONAL"
    ],
    "Grupo Profissional ou Ocupacional": [
      "R1",
      "Doutor",
      "GRUPO DA MÃO"
    ],
    "Procedimento Terapêutico ou Preventivo": [
      "TRANSFERENCIA TENDINOSA POSTERIOR",
      "OSTEOTOMIA DERROTADORA",
      "ALONGAMENTO ÓSSEO"
    ],
    "Achado": [
      "RETARDO DE CONSOLIDAÇÃO"
    ]
  },
  "labels": {
    "infecção": {
      "capitulo": "22"
    },
    "fx de umero esq": {
      "capitulo": "15"
    },
    "mão caída": {
      "capitulo": "15"
    },
    "desvio rotacional": {
      "capitulo": "15"
    },
    "faf": {
      "capitulo": "21"
    },
    "pseudoartrose": {
      "capitulo": "15"
    },
    "lesão de nervo radial": {
      "capitulo": "15"
    },
    "lesao radial": {
      "capitulo": "15"
    },
    "retardo de consolidação": {
      "capitulo": "15"
    },
    "perda funcional": {
      "capitulo": "V"
    }
  }
}