{
  "prontuario_id": 118,
  "text": "S # PACIENTE VEIO SOZINHA A CONSULTA. Refere melhora importante dos sintomas ansiosos com uso do REMILEV \" passou aquela angustia \" (sic). Refere sono reparador. Relata ter perdido cerca de 10kg desde ultima consulta (ha 01 mes) com uso de topiramato 50 mg (1/2-0/1-2). Esta cogitando não fazer a cx bariatrica desde então. Nega queixas, nega sintomas depressivos, nega sintomas ansisosos.\n \nA # HIPERTIMIA??\nP # AUMENTO TOPIRAMATO PARA 50 MG 1-0-1/2, ORIENTO MANTER REMILEV. ORIENTO PACIENTE SOBRE PROCESSO DE EMAGRECIMENTO, A MESMA DIZ QUE PREFERE ESPERAR MAIS TEMPO PARA DAR CONTINUIDADE A BARIATRICA.\nO # asseada, cooperativa, orientada, humor hipertimico afeto congruente, critica e insght parciais.\n ",
  "entities": {
    "Paciente ou Grupo com Deficiência": [
      "PACIENTE"
    ],
    "Atividade de Assistência à Saúde": [
      "CONSULTA",
      "AUMENTO",
      "ORIENTO",
      "MANTER"
    ],
    "Conceito Qualitativo": [
      "melhora",
      "parciais"
    ],
    "Conceito Quantitativo": [
      "10kg",
      "50 mg",
      "50 MG"
    ],
    "Abreviação": [
      "10kg",
      "BARIATRICA",
      "cx bariatrica"
    ],
    "Substância Química Orgânica": [
      "topiramato",
      "TOPIRAMATO",
      "REMILEV"
    ],
    "Substância Farmacológica": [
      "topiramato",
      "TOPIRAMATO",
      "REMILEV"
    ],
    "Negação": [
      "não",
      "Nega",
      "nega"
    ],
    "Sinal ou Sintoma": [
      "queixas",
      "HIPERTIMIA",
      "sintomas ansiosos",
      "sintomas depressivos",
      "sintomas ansisosos",
      "humor hipertimico"
    ],
    "Procedimento Terapêutico ou Preventivo": [
      "BARIATRICA",
      "cx bariatrica"
    ],
    "Achado": [
      "asseada",
      "cooperativa",
      "orientada",
      "passou aquela angustia",
      "PROCESSO DE EMAGRECIMENTO",
      "afeto congruente"
    ],
    "Processo Mental": [
      "critica",
      "insght",
      "afeto congruente"
    ],
    "Função Fisiológica": [
      "sono reparador"
    ],
    "Conceito Temporal": [
      "desde ultima consulta",
      "ha 01 mes",
      "desde então"
    ],
    "Disfunção Mental ou Comportamental": [
      "humor hipertimico"
    ]
  },
  "labels": {
    "humor hipertimico": {
      "capitulo": "06"
    },
    "passou aquela angustia": {
      "capitulo": "21"
    },
    "hipertimia": {
      "capitulo": "06"
    }
  }
}