{
  "prontuario_id": 127,
  "text": "Às 10:20: Retirado cateter central duplo-lumen + cateter p hemodialise, encaminhado ponta para cultura + coleta hemocultura. Puncionado cateter central em sub D tres vias p hemodialise, puncionado acesso venoso periferico. Às 13:00hs: Realizado TAC de crânio, sem intercorrências durante o exame e transporte. Acamada, torporosa, traqueostomizada com suporte em nevoa, dieta via SNE, mantem cabeceira elevada, sem AVP, UP em região sacra e em calcaneos, diurese presente em fralda, realizando mudança de decubito. Às 21:00 h: Paciente retorna do CC, trajeto de volta sem intercorrencias. Às 07:30hrs: Ramsay 6, pupilas iso / foto + , traqueostomizado, aspirado media quantidade de secreção de aspecto espesso, em VM modo VC (530), PEEP 5, FiO2 40%, PA 137x75 mmHg, FC 97 bpm, FR 18 mpm, sat 100%, SNE fechada, acesso venoso central em subclavia D com curativo oclusivo limpo e seco, recebendo dormonid a 20 ml/h + fentanil a 10 ml/h e noradrenalina a 12 ml/h, PAM radial D, incisao cirurgica em regiao dorsal apresentando odor fetido e exsudato piossanguinolento, dreno de torax a D sem debito no momento e com fuga aerea, curativo em local de inserção de dreno com aspecto seroso, AP diminuida em base D e roncos difusos, abdomen globoso e flacido, RHA hipoativos, UP sacra, SVD diurese em pequena quantidade concentrada e com grumos, extremidades aquecidas, perfusao periferica <3s, mantem monitorização cardiaca, PAM, oximetria de pulso e cabeceira elevada a 45°, segue sob cuidados e observação. Precaução por contato. # aguarda procedimento cirurgico com grupo da coluna. ",
  "entities": {
    "Procedimento Laboratorial": [
      "hemocultura",
      "ponta para cultura"
    ],
    "Procedimento Terapêutico ou Preventivo": [
      "Puncionado",
      "hemodialise",
      "puncionado",
      "traqueostomizada",
      "AVP",
      "traqueostomizado",
      "aspirado",
      "VM",
      "curativo",
      "dreno",
      "SVD",
      "cateter central duplo-lumen",
      "cateter p hemodialise",
      "cateter central",
      "acesso venoso periferico",
      "suporte em nevoa",
      "dieta via SNE",
      "cabeceira elevada",
      "mudança de decubito",
      "SNE fechada",
      "acesso venoso central",
      "curativo oclusivo",
      "dreno de torax",
      "cabeceira elevada a 45°",
      "Precaução por contato",
      "procedimento cirurgico"
    ],
    "Abreviação": [
      "sub",
      "D",
      "AVP",
      "UP",
      "CC",
      "VM",
      "PEEP",
      "FiO2",
      "PA",
      "mmHg",
      "FC",
      "bpm",
      "FR",
      "mpm",
      "sat",
      "PAM",
      "SVD",
      "TAC de crânio",
      "dieta via SNE",
      "pupilas iso / foto +",
      "modo VC",
      "SNE fechada",
      "RHA hipoativos"
    ],
    "Parte do Corpo, Órgão ou Componente Orgânico": [
      "sub",
      "subclavia",
      "radial"
    ],
    "Conceito Espacial": [
      "D"
    ],
    "Sinal ou Sintoma": [
      "intercorrências",
      "torporosa",
      "intercorrencias",
      "globoso",
      "grumos",
      "Ramsay 6",
      "secreção de aspecto espesso",
      "odor fetido",
      "exsudato piossanguinolento",
      "fuga aerea",
      "aspecto seroso",
      "roncos difusos",
      "RHA hipoativos"
    ],
    "Procedimento Diagnóstico": [
      "exame",
      "PAM",
      "TAC de crânio",
      "monitorização cardiaca",
      "oximetria de pulso"
    ],
    "Atividade de Assistência à Saúde": [
      "exame",
      "cuidados",
      "observação"
    ],
    "Achado": [
      "Acamada",
      "traqueostomizada",
      "traqueostomizado",
      "FC",
      "limpo",
      "seco",
      "debito",
      "flacido",
      "concentrada",
      "diurese presente em fralda",
      "pupilas iso / foto +"
    ],
    "Negação": [
      "sem"
    ],
    "Dispositivo Médico": [
      "AVP",
      "curativo",
      "dreno",
      "SVD",
      "cateter central duplo-lumen",
      "cateter p hemodialise",
      "cateter central",
      "acesso venoso periferico",
      "SNE fechada",
      "acesso venoso central",
      "curativo oclusivo",
      "dreno de torax"
    ],
    "Doença ou Síndrome": [
      "UP"
    ],
    "Localização ou Região Corporal": [
      "calcaneos",
      "abdomen",
      "sacra",
      "região sacra",
      "regiao dorsal"
    ],
    "Paciente ou Grupo com Deficiência": [
      "Paciente"
    ],
    "Organização Relacionada à Saúde": [
      "CC",
      "grupo da coluna"
    ],
    "Conceito Quantitativo": [
      "530",
      "5",
      "40%",
      "mmHg",
      "97",
      "bpm",
      "18",
      "mpm",
      "100%",
      "20 ml/h",
      "10 ml/h",
      "12 ml/h"
    ],
    "Atributo Clínico": [
      "PA",
      "FC",
      "sat"
    ],
    "Substância Química Orgânica": [
      "dormonid",
      "fentanil",
      "noradrenalina"
    ],
    "Substância Farmacológica": [
      "dormonid",
      "fentanil",
      "noradrenalina"
    ],
    "Hormônio": [
      "noradrenalina"
    ],
    "Função Fisiológica": [
      "debito",
      "diurese",
      "diurese presente em fralda"
    ],
    "Conceito Qualitativo": [
      "media quantidade",
      "pequena quantidade"
    ],
    "Substância Corporal": [
      "secreção de aspecto espesso",
      "exsudato piossanguinolento"
    ],
    "Lesão ou Envenenamento": [
      "incisao cirurgica"
    ],
    "Conceito Temporal": [
      "no momento"
    ]
  },
  "labels": {
    "rha hipoativos": {
      "capitulo": "08",
      "opcoes": []
    },
    "exsudato piossanguinolento": {
      "capitulo": "13",
      "opcoes": []
    },
    "debito": {
      "capitulo": "22",
      "opcoes": []
    },
    "torporosa": {
      "capitulo": "06",
      "opcoes": []
    },
    "traqueostomizado": {
      "capitulo": "12",
      "opcoes": []
    },
    "fuga aerea": {
      "capitulo": "22",
      "opcoes": []
    },
    "grumos": {
      "capitulo": "21",
      "opcoes": []
    },
    "traqueostomizada": {
      "capitulo": "12",
      "opcoes": []
    },
    "aspecto seroso": {
      "capitulo": "13",
      "opcoes": []
    },
    "ramsay 6": {
      "capitulo": "06",
      "opcoes": []
    },
    "flacido": {
      "capitulo": "15",
      "opcoes": []
    },
    "roncos difusos": {
      "capitulo": "12",
      "opcoes": []
    },
    "secreção de aspecto espesso": {
      "capitulo": "21",
      "opcoes": []
    },
    "incisao cirurgica": {
      "capitulo": "22",
      "opcoes": []
    },
    "odor fetido": {
      "capitulo": "13",
      "opcoes": []
    },
    "acamada": {
      "capitulo": "06",
      "opcoes": []
    },
    "pupilas iso / foto +": {
      "capitulo": "08",
      "opcoes": []
    },
    "globoso": {
      "capitulo": "15",
      "opcoes": []
    },
    "intercorrências": {
      "capitulo": "22",
      "opcoes": []
    },
    "intercorrencias": {
      "capitulo": "22",
      "opcoes": []
    }
  }
}