{
  "prontuario_id": 672,
  "text": "PUPILAS ISOCORICAS FOTORREAGENTES, CALMO, VERBALIZANDO COM DIFICULDADE, ORIENTADO, CORADO, VITIMAS DE QUEDA DE MOTO, LESÕES DE FACE, ESCORIAÇÕES EM MMSS E MMII, VENOCLISE SALINIZADO EM MSE. REFERE ALGIA EM LESÕES DE FACE E DE MMII. SEGUE EM OBSERVAÇÃO E CUI. TRAUMATISMOS MULTIPLOS NAO ESPECIFICADOS. Às 00:59h: intubado, em VM PCV com 65% FIO2, 12 FR, 12 PEEP, saturando acima de 90%, TOT com com pouca quantidade de secreção traqueobrônquica flúida esbranquiçada. Abertura ocular ao estímulo, púpilas mióticas, fotorreagentes e discretamente anisocórica com. DIARREIA E GASTROENTERITE DE ORIGEM INFECCIOSA PRESUMIVEL. Púpila discoria à D e miotica E, fotorreagentes. Responsivo durante a aspiração. Traqueostomizado, em ventilação mecânica, PSV, PS 30, Peep 3 e FiO2 30%. Ausculta Pulmonar MV presente bilateral, com presença de roncos difusos. Secreção traqueobrÔnquica es. NEOPLASIA MALIGNA DA BASE DA LINGUA. Em 21/07/2007, 12:30 HORAS: APRESENTA-SE ACORDADO, ATENDENDO AOS COMANDOS VERBAIS, PTOSE Á DIREITA, COM PUPILAS ISOCÓRICAS E FOTORREAGENTES. EM VM VIA TRAQUEO COM FIO2 30% PSV, PS 14 cmH2O, PEEP 3 cmH2O, F 10 cmH2O, SPO2 100%. AUSCULTA PULMONAR COM MV LIVRES. TRAUMATISMOS MULTIPLOS NAO ESPECIFICADOS. Às 18:00: PACIENTE ACAMADO, NAO RESPONDE A ESTIMULOS VERBAIS, REALIZADA AVALIAÇÃO DE ULCERA DE PRESSAO EM REGIAO SACRA, APRESENTANDO SECREÇÃO PURULENTA EM MEDIA QUANTIDADE, SEM PRESENÇA DE TECIDO NECROSADO OU ESFACELO, COM TECIDO DE GRANULAÇÃO EM TODA A FERIDA. FRATURA DE OUTRAS PARTES DA PERNA.",
  "entities": {
    "Achado": [
      "CALMO",
      "ORIENTADO",
      "CORADO",
      "intubado",
      "saturando",
      "fotorreagentes",
      "Traqueostomizado",
      "ACORDADO",
      "ACAMADO",
      "PUPILAS ISOCORICAS FOTORREAGENTES",
      "flúida esbranquiçada",
      "Responsivo durante a aspiração",
      "MV presente bilateral",
      "ATENDENDO AOS COMANDOS VERBAIS",
      "PUPILAS ISOCÓRICAS E FOTORREAGENTES",
      "MV LIVRES",
      "RESPONDE A ESTIMULOS VERBAIS",
      "OU ESFACELO",
      "TECIDO DE GRANULAÇÃO"
    ],
    "Paciente ou Grupo com Deficiência": [
      "VITIMAS",
      "PACIENTE"
    ],
    "Lesão ou Envenenamento": [
      "ESCORIAÇÕES",
      "LESÕES",
      "FERIDA",
      "QUEDA DE MOTO",
      "LESÕES DE FACE",
      "TRAUMATISMOS MULTIPLOS NAO ESPECIFICADOS",
      "FRATURA DE OUTRAS PARTES DA PERNA"
    ],
    "Abreviação": [
      "MMSS",
      "MMII",
      "MSE",
      "VM",
      "PCV",
      "FIO2",
      "FR",
      "PEEP",
      "TOT",
      "D",
      "E",
      "PSV",
      "PS",
      "Peep",
      "FiO2",
      "TRAQUEO",
      "F",
      "SPO2",
      "MV presente bilateral",
      "MV LIVRES"
    ],
    "Localização ou Região Corporal": [
      "MMSS",
      "MMII",
      "MSE",
      "FACE",
      "REGIAO SACRA"
    ],
    "Sinal ou Sintoma": [
      "ALGIA",
      "discoria",
      "miotica",
      "PTOSE",
      "VERBALIZANDO COM DIFICULDADE",
      "Abertura ocular ao estímulo",
      "discretamente anisocórica",
      "roncos difusos",
      "SECREÇÃO PURULENTA",
      "TECIDO NECROSADO"
    ],
    "Atividade de Assistência à Saúde": [
      "OBSERVAÇÃO"
    ],
    "Procedimento Terapêutico ou Preventivo": [
      "intubado",
      "VM",
      "PCV",
      "Traqueostomizado",
      "PSV",
      "TRAQUEO",
      "SPO2",
      "VENOCLISE SALINIZADO",
      "ventilação mecânica"
    ],
    "Conceito Quantitativo": [
      "65%",
      "12",
      "30",
      "3",
      "30%",
      "100%",
      "acima de 90%",
      "14 cmH2O",
      "3 cmH2O",
      "10 cmH2O"
    ],
    "Dispositivo Médico": [
      "TOT"
    ],
    "Parte do Corpo, Órgão ou Componente Orgânico": [
      "púpilas",
      "Púpila"
    ],
    "Conceito Espacial": [
      "D",
      "E",
      "DIREITA"
    ],
    "Negação": [
      "NAO",
      "SEM"
    ],
    "Conceito Qualitativo": [
      "pouca quantidade",
      "MEDIA QUANTIDADE"
    ],
    "Substância Corporal": [
      "secreção traqueobrônquica",
      "Secreção traqueobrÔnquica",
      "SECREÇÃO PURULENTA"
    ],
    "Doença ou Síndrome": [
      "DIARREIA E GASTROENTERITE DE ORIGEM INFECCIOSA PRESUMIVEL",
      "ULCERA DE PRESSAO"
    ],
    "Procedimento Diagnóstico": [
      "Ausculta Pulmonar",
      "AUSCULTA PULMONAR"
    ],
    "Processo Neoplásico": [
      "NEOPLASIA MALIGNA DA BASE DA LINGUA"
    ],
    "Função Patológica": [
      "TECIDO NECROSADO"
    ]
  },
  "labels": {
    "orientado": {
      "capitulo": "06",
      "opcoes": []
    },
    "queda de moto": {
      "capitulo": "22",
      "opcoes": []
    },
    "saturando": {
      "capitulo": "12",
      "opcoes": []
    },
    "discretamente anisocórica": {
      "capitulo": "08",
      "opcoes": []
    },
    "lesões de face": {
      "capitulo": "22",
      "opcoes": []
    },
    "traqueostomizado": {
      "capitulo": "12",
      "opcoes": []
    },
    "ptose": {
      "capitulo": "15",
      "opcoes": []
    },
    "lesões": {
      "capitulo": "22",
      "opcoes": []
    },
    "discoria": {
      "capitulo": "08",
      "opcoes": []
    },
    "ulcera de pressao": {
      "capitulo": "19",
      "opcoes": []
    },
    "flúida esbranquiçada": {
      "capitulo": "13",
      "opcoes": []
    },
    "intubado": {
      "capitulo": "12",
      "opcoes": []
    },
    "tecido necrosado": {
      "capitulo": "22",
      "opcoes": []
    },
    "ferida": {
      "capitulo": "22",
      "opcoes": []
    },
    "miotica": {
      "capitulo": "08",
      "opcoes": []
    },
    "fotorreagentes": {
      "capitulo": "09",
      "opcoes": []
    },
    "fratura de outras partes da perna": {
      "capitulo": "15",
      "opcoes": []
    },
    "roncos difusos": {
      "capitulo": "12",
      "opcoes": []
    },
    "escoriações": {
      "capitulo": "22",
      "opcoes": []
    },
    "diarreia e gastroenterite de origem infecciosa presumivel": {
      "capitulo": "01",
      "opcoes": []
    },
    "algia": {
      "capitulo": "21",
      "opcoes": []
    },
    "verbalizando com dificuldade": {
      "capitulo": "06",
      "opcoes": []
    },
    "tecido de granulação": {
      "capitulo": "19",
      "opcoes": []
    },
    "secreção purulenta": {
      "capitulo": "13",
      "opcoes": []
    },
    "neoplasia maligna da base da lingua": {
      "capitulo": "02",
      "opcoes": []
    },
    "pupilas isocoricas fotorreagentes": {
      "capitulo": "09",
      "opcoes": []
    },
    "pupilas isocóricas e fotorreagentes": {
      "capitulo": "09",
      "opcoes": []
    },
    "traumatismos multiplos nao especificados": {
      "capitulo": "22",
      "opcoes": []
    }
  }
}