{
  "prontuario_id": 321,
  "text": "Às 15:16: CLIENTE CONSCIENTE, COMUNICATIVA, EUPNEICA, REPOUSO NA POLTRONA, FOI SUSPENSO A ECOGRAFIA E AGENDADA PARA AMANHA 16/05, LIBERADO DIETA CONFORME PRESCRIÇÃO, ACESSO PERIFÉRICO EM MSE SALINIZADO, ABDOMEN PLANO E FLÁCIDO, MICÇÃO PRESENTE. ORIENTADA A ENTRAR EM JEJUM A PARTIR DAS 24:00 PARA REALIZAR ECOGRAFIA AMANHA . ENFª FLORENCE NIGHTINGALE, XXXX. DERRAME PLEURAL NAO CLASSIFICADO EM OUTRA PARTE. Às 15:50: POT PTJ A DIREITA EM 27/01/2010. RETORNA COM DOR + EDEMA + EMPASTAMENTO EM PERNA DO MID. CONSCIENTE, LUCIDA, EUPNEICA, COMUNICATIVA, EM REPOUSO NO LEITO, SEM QUEIXAS ALGICAS NO MOMENTO, APRESENTA PUPILAS ISOCORICAS, PELE E MUCOSA CORADA E HIDRATADA, AUSCULTA PULMONAR COM MV +, SEM RUIDOS, SUTURA EM JOELHO DO MID SEM PRESENÇA DE SINAIS FLOGISTICO, MANTEM MEDICAÇOES VIA ORAL, COMPRESSAS MORNAS EM MID, RELATA BOA ACEITAÇAO DA DIETA OFERECIDA, DIURESE ESPONTANEA PRESENTE. RELATA FAZER USO DE CEFALEXINA EM CASA; TENTO CONTATO COM Dra ALICE DA VASCULAR PARA AVISA-LA, SEM SUCESSO. FLEBITE E TROMBOFLEBITE DE OUTROS VASOS PROFUNDOS DOS MEMBROS INFERIORES. Às 04:00h: Encontra-se consciente, orientado, verbalizando, em repouso no leito, ssvv dentro dos parametros de normalidade, mantendo acesso venoso periférico em MSE permeavel salinizado no momento, curativo em região perianal limpo e seco externamente, refere boa aceitação alimentar, diurese presente, relata evacuação ausente a 7 dias, segue sob cuidados de enfermagem. Enf Florence Nightingale. ABSCESSO DAS REGIOES ANAL E RETAL.",
  "entities": {
    "Paciente ou Grupo com Deficiência": [
      "CLIENTE"
    ],
    "Achado": [
      "CONSCIENTE",
      "COMUNICATIVA",
      "EUPNEICA",
      "SALINIZADO",
      "PLANO",
      "FLÁCIDO",
      "LUCIDA",
      "CORADA",
      "HIDRATADA",
      "consciente",
      "orientado",
      "verbalizando",
      "permeavel",
      "salinizado",
      "limpo",
      "seco",
      "MICÇÃO PRESENTE",
      "REPOUSO NO LEITO",
      "PUPILAS ISOCORICAS",
      "MV +",
      "BOA ACEITAÇAO DA DIETA OFERECIDA",
      "DIURESE ESPONTANEA",
      "repouso no leito",
      "ssvv dentro dos parametros de normalidade",
      "boa aceitação alimentar",
      "diurese presente"
    ],
    "Procedimento Diagnóstico": [
      "ECOGRAFIA",
      "AUSCULTA PULMONAR"
    ],
    "Alimento": [
      "DIETA"
    ],
    "Atividade de Assistência à Saúde": [
      "PRESCRIÇÃO",
      "cuidados de enfermagem"
    ],
    "Produto Intelectual": [
      "PRESCRIÇÃO"
    ],
    "Localização ou Região Corporal": [
      "MSE",
      "ABDOMEN",
      "MID",
      "região perianal"
    ],
    "Abreviação": [
      "MSE",
      "ENFª",
      "POT",
      "PTJ",
      "MID",
      "Dra",
      "Enf",
      "MV +",
      "ssvv dentro dos parametros de normalidade"
    ],
    "Procedimento Terapêutico ou Preventivo": [
      "SALINIZADO",
      "JEJUM",
      "PTJ",
      "SUTURA",
      "salinizado",
      "curativo",
      "REPOUSO NA POLTRONA",
      "ACESSO PERIFÉRICO",
      "REPOUSO NO LEITO",
      "MEDICAÇOES VIA ORAL",
      "COMPRESSAS MORNAS",
      "repouso no leito",
      "acesso venoso periférico"
    ],
    "Grupo Profissional ou Ocupacional": [
      "ENFª",
      "Enf"
    ],
    "Conceito Temporal": [
      "POT"
    ],
    "Sinal ou Sintoma": [
      "DOR",
      "EDEMA",
      "RUIDOS",
      "EMPASTAMENTO EM PERNA",
      "QUEIXAS ALGICAS",
      "SINAIS FLOGISTICO"
    ],
    "Função Patológica": [
      "EDEMA"
    ],
    "Parte do Corpo, Órgão ou Componente Orgânico": [
      "PELE",
      "MUCOSA",
      "JOELHO"
    ],
    "Antibiótico": [
      "CEFALEXINA"
    ],
    "Dispositivo Médico": [
      "curativo",
      "ACESSO PERIFÉRICO",
      "acesso venoso periférico"
    ],
    "Conceito Espacial": [
      "externamente"
    ],
    "Função Fisiológica": [
      "evacuação",
      "MICÇÃO PRESENTE",
      "DIURESE ESPONTANEA",
      "diurese presente"
    ],
    "Negação": [
      "ausente"
    ],
    "Doença ou Síndrome": [
      "DERRAME PLEURAL",
      "FLEBITE E TROMBOFLEBITE DE OUTROS VASOS PROFUNDOS DOS MEMBROS INFERIORES",
      "ABSCESSO DAS REGIOES ANAL E RETAL"
    ]
  },
  "labels": {
    "flácido": {
      "capitulo": "15",
      "opcoes": []
    },
    "queixas algicas": {
      "capitulo": "21",
      "opcoes": []
    },
    "ruidos": {
      "capitulo": "12",
      "opcoes": []
    },
    "derrame pleural": {
      "capitulo": "12",
      "opcoes": []
    },
    "seco": {
      "capitulo": "14",
      "opcoes": []
    },
    "limpo": {
      "capitulo": "14",
      "opcoes": []
    },
    "sinais flogistico": {
      "capitulo": "21",
      "opcoes": []
    },
    "abscesso das regioes anal e retal": {
      "capitulo": "14",
      "opcoes": []
    },
    "mv +": {
      "capitulo": "08",
      "opcoes": []
    },
    "corada": {
      "capitulo": "14",
      "opcoes": []
    },
    "permeavel": {
      "capitulo": "11",
      "opcoes": []
    },
    "plano": {
      "capitulo": "15",
      "opcoes": []
    },
    "hidratada": {
      "capitulo": "14",
      "opcoes": []
    },
    "empastamento em perna": {
      "capitulo": "15",
      "opcoes": []
    },
    "salinizado": {
      "capitulo": "11",
      "opcoes": []
    },
    "edema": {
      "capitulo": "15",
      "opcoes": []
    },
    "micção presente": {
      "capitulo": "16",
      "opcoes": []
    },
    "flebite e tromboflebite de outros vasos profundos dos membros inferiores": {
      "capitulo": "22",
      "opcoes": []
    },
    "dor": {
      "capitulo": "21",
      "opcoes": []
    },
    "pupilas isocoricas": {
      "capitulo": "08",
      "opcoes": []
    }
  }
}