{
  "prontuario_id": 799,
  "text": "Continuando evolução anterior. Finalizado controle de diurese as 08:00hs. LEPTOPIROSE ICTEROHEMORRAGICA. Às 15:00: AGENDADO RESSONANCIA DE CRANIO PARA HOJE, 20/10/2010,  AS 22:00, CLINICA X-LEME. ENCAMINHO PC PARA OFTALMO, CONTATO COM DRA TARSILA. ENF FLORENCE NIGHINGALE, XXXX. EPILEPSIA E SINDROMES EPILEPTICAS GENERALIZADAS IDIOPATICAS. Às 15:33HS: GLASGOW 15, TRANQUILA, COLABORATIVA, SEM QUEIXAS ALGICAS OU DESCONFORTO. O: 3º PO POR SEGMENTECTOMIA A DIREITA, DPOC DESCOMPENSADO, EUPNEICA SOB MASCARA DE OXIGENIO A 2 L/M, SPO2 93%, NORMOTERMICA (37 c), NORMOCARDICA (81 bpm), HIPOTENSA (83/38 MMhg), COMUNICO DRA ALICE, QUE ME INFORMA SER O BASAL DA PACIENTE, CATETER VENOSO CENTRAL DUPLO-LUMEN, VIA SUBCLAVIA DIREITA, INFUNDINDO PLANO BASICO DE HIDRATAÇÃO, AUSCULTA PULMONAR LIVRE, DRENOS DE TORAX A DIREITA COM DEBITO SEROHEMATICO EM MEDIA QUANTIDADE, SINAIS DE HEMATOMA EM MAMA DIREITA PROXIMO LOCAL DA INSERÇÃO DOS DRENOS, MANTEM CATETER PARA ANALGESIA, ABDOMEN FLACIDO, RHA PRESENTES, POUCA ACEITAÇÃO ALIMENTAR POR DIETA BRANDA, EXTREMIDADES AQUECIDAS E BEM PERFUNIDAS, SVD COM DIURESE AMARELO CLARO, SEM PRESENÇA DE GRUMOS, ELIMINAÇÕES INTESTINAIS AUSENTES DURANTE O DIA, REPOUSOU NA POLTRONA PELA MANHA, APRESENTA FORÇA MOTORA PRESERVADA, SE MANTEM EM PÉ SEM DESCONFORTO RESPIRATORIO, REALIZADO MEDIDAS DE HIGIENE E CONFORTO, SEGUE MONITORADA EM CUIDADOS INTENSIVOS.  A: DESLIGADO NORADRENALINA E RETIRADO PAM PELA MANHA, OBSERVAR SATURAÇÃO, MANTEM OXIGENIO NO MAXIMO EM 2 L/M, MONITORAR SINAIS DE HIPOTENSÃO E SONOLENCIA E COMUNICAR ENFERMEIRO.  P: CONFORME PRESCRIÇÃO. ENF FLORENCE NIGHTINGALE, COREN XXXX. EXAME GERAL E INVESTIGACAO DE PESSOAS SEM QUEIXAS OU DIAGNOSTICO RELATADO.",
  "entities": {
    "Abreviação": [
      "PC",
      "OFTALMO",
      "DRA",
      "ENF",
      "PO",
      "SPO2",
      "bpm",
      "MMhg",
      "SVD",
      "PAM",
      "RHA PRESENTES"
    ],
    "Grupo Profissional ou Ocupacional": [
      "OFTALMO",
      "ENF",
      "ENFERMEIRO"
    ],
    "Achado": [
      "TRANQUILA",
      "COLABORATIVA",
      "EUPNEICA",
      "NORMOTERMICA",
      "NORMOCARDICA",
      "AQUECIDAS",
      "DIURESE",
      "GLASGOW 15",
      "AUSCULTA PULMONAR LIVRE",
      "DEBITO SEROHEMATICO",
      "RHA PRESENTES",
      "BEM PERFUNIDAS",
      "AMARELO CLARO",
      "REPOUSOU NA POLTRONA",
      "FORÇA MOTORA PRESERVADA",
      "SE MANTEM EM PÉ"
    ],
    "Sinal ou Sintoma": [
      "DESCONFORTO",
      "HIPOTENSA",
      "GRUMOS",
      "SONOLENCIA",
      "QUEIXAS",
      "QUEIXAS ALGICAS",
      "SINAIS DE HEMATOMA",
      "POUCA ACEITAÇÃO ALIMENTAR POR DIETA BRANDA",
      "SINAIS DE HIPOTENSÃO"
    ],
    "Conceito Temporal": [
      "PO"
    ],
    "Atributo Clínico": [
      "SPO2"
    ],
    "Conceito Quantitativo": [
      "93%",
      "81",
      "83/38",
      "2 L/M",
      "37 c"
    ],
    "Paciente ou Grupo com Deficiência": [
      "PACIENTE"
    ],
    "Localização ou Região Corporal": [
      "ABDOMEN",
      "EXTREMIDADES"
    ],
    "Dispositivo Médico": [
      "SVD",
      "CATETER VENOSO CENTRAL DUPLO-LUMEN",
      "DRENOS DE TORAX"
    ],
    "Procedimento Terapêutico ou Preventivo": [
      "SVD",
      "PAM",
      "SEGMENTECTOMIA A DIREITA",
      "SOB MASCARA DE OXIGENIO",
      "CATETER VENOSO CENTRAL DUPLO-LUMEN",
      "PLANO BASICO DE HIDRATAÇÃO",
      "DRENOS DE TORAX",
      "CATETER PARA ANALGESIA",
      "REPOUSOU NA POLTRONA",
      "MEDIDAS DE HIGIENE E CONFORTO",
      "OXIGENIO NO MAXIMO"
    ],
    "Função Fisiológica": [
      "DIURESE",
      "ELIMINAÇÕES INTESTINAIS"
    ],
    "Negação": [
      "AUSENTES"
    ],
    "Procedimento Diagnóstico": [
      "MONITORADA",
      "RESSONANCIA DE CRANIO"
    ],
    "Atividade de Assistência à Saúde": [
      "DESLIGADO",
      "MONITORAR",
      "PRESCRIÇÃO",
      "CUIDADOS INTENSIVOS",
      "OBSERVAR SATURAÇÃO"
    ],
    "Substância Farmacológica": [
      "NORADRENALINA"
    ],
    "Produto Intelectual": [
      "PRESCRIÇÃO"
    ],
    "Doença ou Síndrome": [
      "LEPTOPIROSE ICTEROHEMORRAGICA",
      "EPILEPSIA E SINDROMES EPILEPTICAS GENERALIZADAS IDIOPATICAS",
      "DPOC DESCOMPENSADO"
    ],
    "Parte do Corpo, Órgão ou Componente Orgânico": [
      "SUBCLAVIA DIREITA",
      "MAMA DIREITA"
    ],
    "Conceito Espacial": [
      "A DIREITA"
    ],
    "Substância Corporal": [
      "DEBITO SEROHEMATICO"
    ],
    "Conceito Qualitativo": [
      "MEDIA QUANTIDADE",
      "BEM PERFUNIDAS"
    ]
  },
  "labels": {
    "normocardica": {
      "capitulo": "11",
      "opcoes": []
    },
    "queixas algicas": {
      "capitulo": "06",
      "opcoes": []
    },
    "sinais de hematoma": {
      "capitulo": "14",
      "opcoes": []
    },
    "pouca aceitação alimentar por dieta branda": {
      "capitulo": "05",
      "opcoes": []
    },
    "hipotensa": {
      "capitulo": "11",
      "opcoes": []
    },
    "queixas": {
      "capitulo": "06",
      "opcoes": []
    },
    "grumos": {
      "capitulo": "21",
      "opcoes": []
    },
    "debito serohematico": {
      "capitulo": "12",
      "opcoes": []
    },
    "desconforto": {
      "capitulo": "06",
      "opcoes": []
    },
    "leptopirose icterohemorragica": {
      "capitulo": "01",
      "opcoes": []
    },
    "colaborativa": {
      "capitulo": "06",
      "opcoes": []
    },
    "sinais de hipotensão": {
      "capitulo": "11",
      "opcoes": []
    },
    "glasgow 15": {
      "capitulo": "06",
      "opcoes": []
    },
    "eupneica": {
      "capitulo": "12",
      "opcoes": []
    },
    "sonolencia": {
      "capitulo": "07",
      "opcoes": []
    },
    "tranquila": {
      "capitulo": "06",
      "opcoes": []
    },
    "dpoc descompensado": {
      "capitulo": "11",
      "opcoes": []
    },
    "epilepsia e sindromes epilepticas generalizadas idiopaticas": {
      "capitulo": "08",
      "opcoes": []
    }
  }
}