{
  "prontuario_id": 708,
  "text": "MANHÃ- A PEDIDO DE DR VITAL BRASIL, PACIENTE PERMANECE EM JEJUM, POR VOLTA DE 8:40 A FUNCIONÁRIA XXXX DA CENTRAL DE GUIAS ME INFORMA QUE OS MATERIAIS E CIRURGIA ESTÃO LIBERADO PELO CONVENIO. PORÉM PACIENTE NÃO ESTÁ NO MAPA CIRURGICO NEM NO MAPA CIRURGICO DE EMERGENCIA. TENTO CONTATO  VARIAS VEZES COM DR VITAL BRASIL DA ORTO E DR VITAL BRASIL SEM SUCESSO. POR VOLTA DE 12H ENTRO EM CONTATO COM O CC, DR VITAL BRASIL ESTÁ EM PROCEDIMENTO CIRURGICO, PEDE QUE ENTRE EM CONTATO COM DRA MARIA. ENTRO EM CONTATO COM DRA MARIA E INFORMO DA LIBERAÇÃO DOS MATERIAIS E CX A MESMA CIENTE. INFORMA QUE ENTRARA EM CONTATO COM DR VITAL BRASIL E SOLICITA QUE O PACIENTE PERMANEÇA EM JEJUM. ORIENTO PACIENTE QUANTO AO JEJUM. PASSO EM PLANTÃO.  ENFA FLORENCE NIGHTINGALE COREN XX XXXX. TRAUMATISMOS MULTIPLOS NAO ESPECIFICADOS.",
  "entities": {
    "Abreviação": [
      "DR",
      "ORTO",
      "CC",
      "DRA",
      "CX",
      "ENFA"
    ],
    "Paciente ou Grupo com Deficiência": [
      "PACIENTE"
    ],
    "Procedimento Terapêutico ou Preventivo": [
      "JEJUM",
      "CIRURGIA",
      "CX",
      "PROCEDIMENTO CIRURGICO"
    ],
    "Dispositivo Médico": [
      "MATERIAIS"
    ],
    "Organização Relacionada à Saúde": [
      "CONVENIO",
      "ORTO",
      "CC",
      "PLANTÃO"
    ],
    "Negação": [
      "NÃO",
      "NEM",
      "SEM"
    ],
    "Grupo Profissional ou Ocupacional": [
      "ORTO",
      "ENFA"
    ],
    "Achado": [
      "SUCESSO"
    ],
    "Atividade de Assistência à Saúde": [
      "ORIENTO",
      "PLANTÃO"
    ],
    "Lesão ou Envenenamento": [
      "TRAUMATISMOS MULTIPLOS"
    ]
  },
  "labels": {
    "traumatismos multiplos": {
      "capitulo": "22",
      "opcoes": [
        {
          "NA06.00": {
            "confidence_embedding": 0.8159,
            "text": "Representação de doença CID-11: Avulsão da pálpebra. Definição: Lesão em que uma estrutura corporal é forçadamente destacada do seu ponto normal de inserção por traumatismo ou cirurgia. O termo mais comumente se refere a um traumatismo de superfície em que todas as camadas da pele foram laceradas, expondo estruturas subjacentes (isto é, tecido subcutâneo, músculo, tendões ou osso). É semelhante a uma abrasão, mas mais grave, em que a pálpebra pode estar parcial ou completamente destacada do corpo."
          }
        },
        {
          "ND36": {
            "confidence_embedding": 0.7925,
            "text": "Representação de doença CID-11: Outros traumatismos envolvendo regiões múltiplas do corpo, não classificados em outra parte. Definição: "
          }
        },
        {
          "ND34": {
            "confidence_embedding": 0.7923,
            "text": "Representação de doença CID-11: Traumatismos por esmagamento envolvendo múltiplas regiões do corpo. Definição: "
          }
        },
        {
          "NA07": {
            "confidence_embedding": 0.79,
            "text": "Representação de doença CID-11: Traumatismo intracraniano. Definição: Dano infligido aos tecidos do cérebro como o resultado direto ou indireto de uma força externa, com ou sem interrupção da continuidade estrutural."
          }
        },
        {
          "ND56.Z": {
            "confidence_embedding": 0.7831,
            "text": "Representação de doença CID-11: Traumatismo de região não especificada do corpo, não especificado. Definição: "
          }
        }
      ]
    }
  }
}