{
  "prontuario_id": 215,
  "text": "Lucas , 78 anos, natural e residente de RS, casado, 2 filhos, aposentado.  S #  QP : Acompanhamento da DM, retorno com exames. Sem queixas.  HMP : DM e HAS há 20 anos. Realizou 2 angioplastias (1996 e 1999) - na segunda colocou um stent.  Faz uso de Metformina 850 mg ( 1x/d ), Glibenclamida 5mg (1x/d ), Sinvastatina 20mg (1x/d ), Diltiazem 60 mg  ( 2x/d ), Enalapril 10 mg ( 2x/d ), AAS 100mg ( 1x/d ). Faz acompanhamento com serviço de oftalmologista e cardiologista.  HMF: Pai faleceu por Ca de próstata, mãe com Alzheimer, também falecida.  CHV : Ex tabagista ( 60 maços / ano, parou há 20 anos), ex etilista há 20 anos. Refere alimentação saudável (2 refeiçoes por dia - café da manhã e janta). Realiza caminhada todos os dias ( mínimo 30 minutos ).  RS: Sem particularidades. Nega queixas urinárias e gastrointestinais.   Exames Laboratoriais :15/01/2015 Cr 0.8 Triglicerideos 74 Transaminase Piruvica 24 HDL 48 Sodio 137 Potassio 5.1 Transaminase oxalacetica 27 Colesterol total 123 LDL 60 Glicose 80 A1C 6.49%  Oftalmo = 08 /2014 =  tudo normal  ( angiografia )  Exame do Pé = 12/2014 =  normal   12/11/2014 = Relação albumina / creatinina 54.32 mg/g  O #  EF BEG, normocorado, hidratado, anictérico, acianótico, afebril. 150/80 mmHg BRNFSS MV + bilateralmente Abdome plano, flacido, indolor a palpação. MMII sem edema ou empastamento. Pulsos perifericos presentes.  A # DM2 + HAS  P # Retorno com exames em 6 meses.",
  "entities": {
    "Grupo Profissional ou Ocupacional": [
      "aposentado",
      "cardiologista",
      "serviço de oftalmologista"
    ],
    "Abreviação": [
      "S",
      "DM",
      "HMP",
      "HAS",
      "AAS",
      "HMF",
      "EF",
      "BEG",
      "BRNFSS",
      "MMII",
      "A",
      "DM2",
      "P",
      "Ca de próstata",
      "MV + bilateralmente"
    ],
    "Achado": [
      "S",
      "HMP",
      "HMF",
      "CHV",
      "normal",
      "BEG",
      "normocorado",
      "hidratado",
      "anictérico",
      "acianótico",
      "afebril",
      "BRNFSS",
      "plano",
      "flacido",
      "Ex tabagista",
      "ex etilista",
      "alimentação saudável",
      "MV + bilateralmente",
      "indolor a palpação",
      "Pulsos perifericos presentes"
    ],
    "Atividade de Assistência à Saúde": [
      "Acompanhamento",
      "retorno",
      "Realizou",
      "acompanhamento",
      "Retorno"
    ],
    "Doença ou Síndrome": [
      "DM",
      "HAS",
      "Alzheimer",
      "DM2"
    ],
    "Procedimento Laboratorial": [
      "exames",
      "Exames Laboratoriais"
    ],
    "Procedimento Diagnóstico": [
      "exames",
      "angiografia",
      "EF",
      "A",
      "Exames Laboratoriais"
    ],
    "Negação": [
      "Sem",
      "Nega",
      "anictérico",
      "acianótico",
      "afebril",
      "sem",
      "indolor a palpação"
    ],
    "Sinal ou Sintoma": [
      "queixas",
      "particularidades",
      "edema",
      "empastamento",
      "queixas urinárias",
      "150/80 mmHg"
    ],
    "Procedimento Terapêutico ou Preventivo": [
      "angioplastias"
    ],
    "Dispositivo Médico": [
      "stent"
    ],
    "Substância Farmacológica": [
      "Metformina",
      "Glibenclamida",
      "Sinvastatina",
      "Diltiazem",
      "Enalapril",
      "AAS"
    ],
    "Grupo Familiar": [
      "Pai",
      "mãe"
    ],
    "Evento": [
      "faleceu"
    ],
    "Alimento": [
      "janta",
      "café da manhã"
    ],
    "Sistema Corporal": [
      "gastrointestinais"
    ],
    "Parte do Corpo, Órgão ou Componente Orgânico": [
      "Pé"
    ],
    "Localização ou Região Corporal": [
      "Abdome",
      "MMII"
    ],
    "Produto Intelectual": [
      "P"
    ],
    "Grupo Etário": [
      "78 anos"
    ],
    "Conceito Temporal": [
      "20 anos",
      "há 20 anos",
      "30 minutos",
      "6 meses"
    ],
    "Conceito Quantitativo": [
      "850 mg",
      "60 mg",
      "10 mg",
      "60 maços / ano",
      "150/80 mmHg"
    ],
    "Organização Relacionada à Saúde": [
      "serviço de oftalmologista"
    ],
    "Processo Neoplásico": [
      "Ca de próstata"
    ],
    "Resultado Laboratorial ou de Teste": [
      "Cr 0",
      "Triglicerideos 74",
      "Transaminase Piruvica 24",
      "HDL 48",
      "Sodio 137",
      "Potassio 5",
      "Transaminase oxalacetica 27",
      "Colesterol total 123",
      "LDL 60",
      "Glicose 80",
      "A1C 6",
      "Relação albumina / creatinina 54"
    ]
  },
  "labels": {
    "normocorado": {
      "capitulo": "11",
      "opcoes": []
    },
    "ca de próstata": {
      "capitulo": "02",
      "opcoes": []
    },
    "queixas": {
      "capitulo": "21",
      "opcoes": []
    },
    "150/80 mmhg": {
      "capitulo": "11",
      "opcoes": []
    },
    "chv": {
      "capitulo": "24",
      "opcoes": []
    },
    "mv + bilateralmente": {
      "capitulo": "15",
      "opcoes": []
    },
    "ex tabagista": {
      "capitulo": "24",
      "opcoes": []
    },
    "hmp": {
      "capitulo": "05",
      "opcoes": []
    },
    "acianótico": {
      "capitulo": "11",
      "opcoes": []
    },
    "plano": {
      "capitulo": "15",
      "opcoes": []
    },
    "flacido": {
      "capitulo": "15",
      "opcoes": []
    },
    "alimentação saudável": {
      "capitulo": "24",
      "opcoes": []
    },
    "alzheimer": {
      "capitulo": "02",
      "opcoes": []
    },
    "queixas urinárias": {
      "capitulo": "21",
      "opcoes": []
    },
    "dm2": {
      "capitulo": "05",
      "opcoes": []
    },
    "ex etilista": {
      "capitulo": "24",
      "opcoes": []
    },
    "anictérico": {
      "capitulo": "11",
      "opcoes": []
    },
    "hmf": {
      "capitulo": "04",
      "opcoes": []
    },
    "indolor a palpação": {
      "capitulo": "15",
      "opcoes": []
    },
    "edema": {
      "capitulo": "15",
      "opcoes": []
    },
    "has": {
      "capitulo": "05",
      "opcoes": []
    },
    "beg": {
      "capitulo": "V",
      "opcoes": []
    },
    "dm": {
      "capitulo": "05",
      "opcoes": []
    },
    "empastamento": {
      "capitulo": "15",
      "opcoes": []
    },
    "brnfss": {
      "capitulo": "X",
      "opcoes": []
    }
  }
}