{
  "prontuario_id": 400,
  "text": "LUCAS, 61 ANOS\nACOMPANHAMENTO HÁ 1 ANO\n\n# HAS\n# IC\n# HIPOTIREOIDISMO\n# MIOCARDIOPATIA DILATADA\n# IMPLANTE DE RESSINCRONIZADOR / DESFIBRILADOR EM MAIO/2012\n# DEPRESSÃO\n\nEM USO: CARVEDILOL 50 MG 2X/D + MONONITRATO DE ISOSSORBITA 20 MG 2X/D + ANCORON (AMIODARONA) 200 MG 2X/D + ESPIRONOLACTONA 25 MG /D + FUROSEMIDA 40 MG 2X/D + LOSARTAN 50 MG 2X/D + DIGOXINA 0,25 MG /D + SINVASTATINA 40 MG /D + LEVOTIROXINA 50 MCG /D + RIVOTRIL 2 MG /D + CITALOPRAM 20MG 3X/DIA.\n\nREFERE DOR PRECORDIAL LEVE A MODERADA DO TIPO QUEIMAÇÃO, SEM IRRADIAÇÃO, SEM PIORA AOS ESFORÇOS.\nDISPNEIA, MAL ESTAR E FADIGA AO SUBIR ESCADAS, ANDAR RÁPIDO. NEGA ORTOPNEIA E DPN.\nNEGA TOSSE E EDEMA.\n\nHÁ 2 ANOS NÃO FAZ REVISÃO DO MP.\n\n# HMP: \n1 CESAREA PRÉVIA, LIPOASPIRAÇÃO.\nNEGA ALERGIAS.\nJÁ REALIZOU 3 CATETERISMOS, CINTILOGRAFIA E EXAMES PARA DOENÇA DE CHAGAS.\n\n# HMA:\nAVÓ TEVE IAM.\n\n# CHDV\nNEGA TABAGISMO, NEGA ETILISMO, NEGA EXERCÍCIO FÍSICO.\n\nEXAMES:\nHB 14,7.\nHT 43,9%.\nCREATININA 0,8.\nGLICOSE 87.\nUREIA 48 48.\nHDL 28.\nSODIO 139.\nPOTASSIO 4,8.\nCOLESTEROL TOTAL 268.\nTSH 5,87.\nT4 LIVRE 0,86.\nTRIGLICERIDEOS 626.\n\nSTRESS FARMACOLOGICO COM DIPIRIDAMOL: ECOCARDIOGRAMA DE STRESS FARMACOLOGICO SEM EVIDENCIA DE ISQUEMIA MIOCÁRDICA.\n\nCONDUTA: AUMENTO DA DOSE DE LEVOTIROXINA PARA 100 MCG, CIPROFIBRATO 100MG 1X/DIA, FUROSEMIDA SE FALTA DE AR, SINVASTATINA PARA 40MG, HIDRALAZINA 25MG DE 8/8H.\nEXAMES DE TSH, T4 LIVRE, CK, TGO E TGP E PERFIL LIPIDICO. \n \n \n ",
  "entities": {
    "Atividade de Assistência à Saúde": [
      "ACOMPANHAMENTO",
      "REVISÃO",
      "CONDUTA",
      "EXERCÍCIO FÍSICO",
      "AUMENTO DA DOSE"
    ],
    "Doença ou Síndrome": [
      "HAS",
      "IC",
      "HIPOTIREOIDISMO",
      "DEPRESSÃO",
      "ALERGIAS",
      "IAM",
      "TABAGISMO",
      "ETILISMO",
      "MIOCARDIOPATIA DILATADA",
      "DOENÇA DE CHAGAS"
    ],
    "Abreviação": [
      "HAS",
      "IC",
      "DPN",
      "MP",
      "HMP",
      "HMA",
      "IAM",
      "CHDV",
      "HB 14 , 7",
      "HT 43 , 9%"
    ],
    "Procedimento Terapêutico ou Preventivo": [
      "DESFIBRILADOR",
      "CESAREA",
      "LIPOASPIRAÇÃO",
      "CATETERISMOS",
      "IMPLANTE DE RESSINCRONIZADOR"
    ],
    "Dispositivo Médico": [
      "DESFIBRILADOR"
    ],
    "Substância Química Orgânica": [
      "CARVEDILOL",
      "ANCORON",
      "AMIODARONA",
      "ESPIRONOLACTONA",
      "FUROSEMIDA",
      "LOSARTAN",
      "DIGOXINA",
      "SINVASTATINA",
      "LEVOTIROXINA",
      "RIVOTRIL",
      "CITALOPRAM",
      "DIPIRIDAMOL",
      "CIPROFIBRATO",
      "HIDRALAZINA",
      "MONONITRATO DE ISOSSORBITA"
    ],
    "Substância Farmacológica": [
      "CARVEDILOL",
      "ESPIRONOLACTONA",
      "FUROSEMIDA",
      "LOSARTAN",
      "DIGOXINA",
      "SINVASTATINA",
      "LEVOTIROXINA",
      "RIVOTRIL",
      "CITALOPRAM",
      "DIPIRIDAMOL",
      "CIPROFIBRATO",
      "HIDRALAZINA",
      "MONONITRATO DE ISOSSORBITA"
    ],
    "Conceito Temporal": [
      "2X/D",
      "/D",
      "3X/DIA",
      "PRÉVIA",
      "1X/DIA",
      "8/8H",
      "HÁ 1 ANO",
      "HÁ 2 ANOS"
    ],
    "Conceito Quantitativo": [
      "2X/D",
      "20MG",
      "3X/DIA",
      "1",
      "3",
      "100MG",
      "40MG",
      "25MG",
      "50 MG",
      "20 MG",
      "200 MG",
      "25 MG",
      "40 MG",
      "0 , 25 MG",
      "50 MCG",
      "2 MG",
      "100 MCG"
    ],
    "Conceito Qualitativo": [
      "LEVE",
      "MODERADA",
      "TIPO QUEIMAÇÃO"
    ],
    "Negação": [
      "SEM",
      "NEGA",
      "NÃO"
    ],
    "Sinal ou Sintoma": [
      "IRRADIAÇÃO",
      "DISPNEIA",
      "ORTOPNEIA",
      "DPN",
      "TOSSE",
      "EDEMA",
      "DOR PRECORDIAL",
      "PIORA AOS ESFORÇOS",
      "MAL ESTAR",
      "FADIGA AO SUBIR ESCADAS",
      "FALTA DE AR"
    ],
    "Função Patológica": [
      "EDEMA"
    ],
    "Achado": [
      "HMP",
      "HMA",
      "IMPLANTE DE RESSINCRONIZADOR",
      "ANDAR RÁPIDO",
      "EXERCÍCIO FÍSICO"
    ],
    "Procedimento Diagnóstico": [
      "CINTILOGRAFIA",
      "EXAMES",
      "STRESS FARMACOLOGICO",
      "ECOCARDIOGRAMA DE STRESS FARMACOLOGICO"
    ],
    "Grupo Familiar": [
      "AVÓ"
    ],
    "Procedimento Laboratorial": [
      "EXAMES",
      "CK",
      "TGO",
      "TGP",
      "EXAMES DE TSH",
      "T4 LIVRE",
      "PERFIL LIPIDICO"
    ],
    "Produto Intelectual": [
      "CONDUTA"
    ],
    "Resultado Laboratorial ou de Teste": [
      "HB 14 , 7",
      "HT 43 , 9%",
      "CREATININA 0 , 8",
      "GLICOSE 87",
      "UREIA 48 48",
      "HDL 28",
      "SODIO 139",
      "POTASSIO 4 , 8",
      "COLESTEROL TOTAL 268",
      "TSH 5 , 87",
      "T4 LIVRE 0 , 86",
      "TRIGLICERIDEOS 626",
      "EVIDENCIA DE ISQUEMIA MIOCÁRDICA"
    ]
  },
  "labels": {
    "ortopneia": {
      "capitulo": "12",
      "opcoes": []
    },
    "doença de chagas": {
      "capitulo": "01",
      "opcoes": []
    },
    "ic": {
      "capitulo": "04",
      "opcoes": []
    },
    "hipotireoidismo": {
      "capitulo": "05",
      "opcoes": []
    },
    "piora aos esforços": {
      "capitulo": "21",
      "opcoes": []
    },
    "mal estar": {
      "capitulo": "06",
      "opcoes": []
    },
    "hma": {
      "capitulo": "18",
      "opcoes": []
    },
    "implante de ressincronizador": {
      "capitulo": "11",
      "opcoes": []
    },
    "falta de ar": {
      "capitulo": "12",
      "opcoes": []
    },
    "miocardiopatia dilatada": {
      "capitulo": "11",
      "opcoes": []
    },
    "depressão": {
      "capitulo": "06",
      "opcoes": []
    },
    "hmp": {
      "capitulo": "18",
      "opcoes": []
    },
    "fadiga ao subir escadas": {
      "capitulo": "21",
      "opcoes": []
    },
    "iam": {
      "capitulo": "20",
      "opcoes": []
    },
    "dor precordial": {
      "capitulo": "08",
      "opcoes": []
    },
    "dispneia": {
      "capitulo": "12",
      "opcoes": []
    },
    "edema": {
      "capitulo": "14",
      "opcoes": []
    },
    "has": {
      "capitulo": "04",
      "opcoes": []
    },
    "andar rápido": {
      "capitulo": "21",
      "opcoes": []
    },
    "dpn": {
      "capitulo": "12",
      "opcoes": []
    }
  }
}