{
  "prontuario_id": 771,
  "text": "ÀS 10:20 HS: ADMITIDO NO SETOR ÀS 09:45 HS, PROVENIENTE DO CC, POI DE RETIRADA DE MATERIAL DE SINTESE EM OMBRO D, CONSCIENTE, ORIENTADO, CTVO LIMPO E SECO, ACESSO VENOSO EM MSE COM SRT EM CURSO. LIBERADO DIETA LIVRE. SEGUE CUIDADOS. FRATURA DA OMOPLATA ESCAPULA. ÀS 18:10 HS: POI DE ARTROSCOPIA DE JOELHO E, SOB ANESTESIA RAQUIDIANA, RETORNOU DO CENTRO CIRÚRGICO ÁS 17:30HS, COMUNICATIVO, LÚCIDO, MIE ENFAIXADO COM COMPRESSA GELADA CONTÍNUA, ACESSO VENOSO PERIFÉRICO EM MSE COM SOROTERAPIA EM CURSO, SEM QUEIXAS ÁLGICAS, DIETA L. OUTROS TRANSTORNOS DO MENISCO. Às 11:20h: Alerta, orientado, verbalizando, deambulando. Sem queixas. Nega lombalgia. Enfª Florence Nightingale. INFECCAO PIOGENICA DO DISCO INTERVERTEBRAL. PROVENIENTE DO CC ÀS 15:20, CONSCIENTE, POUCO SONOLENTA, EUPNÉICA, SEM QUEIXAS ÁLGICAS, EM JEJUM. APRESENTA CURATIVO EM REGIÃO ABDOMINAL DE ASPECTO SECO EXTERNAMENTE. MANTÉM ACESSO VENOSO EM MSE COM SOROTERAPIA EM CURSO E SVD COM DÉBITO COLÚRICO. ENFª FLORENCE NIGHTINGALE. TRAUMATISMOS MULTIPLOS NAO ESPECIFICADOS. ÀS 02:00: POI de curativo em ombro E. Veio do Cc as 22:00, consciente, orientada, comunicativa. Acesso venoso em MSD, curativo limpo e seco em ombro E, com tipóia canadense. Boa aceitação da dieta oferecida. Eliminações presentes. Nega algia. FRATURA DA EXTREMIDADE SUPERIOR DO UMERO.",
  "entities": {
    "Organização Relacionada à Saúde": [
      "CC",
      "Cc",
      "CENTRO CIRÚRGICO"
    ],
    "Abreviação": [
      "CC",
      "POI",
      "CTVO",
      "MSE",
      "SRT",
      "MIE",
      "Enfª",
      "SVD",
      "ENFª",
      "Cc",
      "MSD",
      "OMBRO D",
      "JOELHO E",
      "DIETA L",
      "ombro E"
    ],
    "Conceito Temporal": [
      "POI",
      "CONTÍNUA"
    ],
    "Achado": [
      "CONSCIENTE",
      "ORIENTADO",
      "LIMPO",
      "SECO",
      "COMUNICATIVO",
      "LÚCIDO",
      "Alerta",
      "orientado",
      "verbalizando",
      "deambulando",
      "EUPNÉICA",
      "JEJUM",
      "consciente",
      "orientada",
      "comunicativa",
      "limpo",
      "seco",
      "aceitação da dieta",
      "Eliminações presentes"
    ],
    "Procedimento Terapêutico ou Preventivo": [
      "CTVO",
      "SRT",
      "JEJUM",
      "CURATIVO",
      "SVD",
      "curativo",
      "RETIRADA DE MATERIAL DE SINTESE",
      "ACESSO VENOSO",
      "DIETA LIVRE",
      "ANESTESIA RAQUIDIANA",
      "COMPRESSA GELADA",
      "ACESSO VENOSO PERIFÉRICO",
      "SOROTERAPIA EM CURSO",
      "DIETA L",
      "Acesso venoso",
      "tipóia canadense"
    ],
    "Dispositivo Médico": [
      "CTVO",
      "CURATIVO",
      "SVD",
      "curativo",
      "ACESSO VENOSO",
      "COMPRESSA GELADA",
      "ACESSO VENOSO PERIFÉRICO",
      "Acesso venoso",
      "tipóia canadense"
    ],
    "Localização ou Região Corporal": [
      "MSE",
      "MIE",
      "MSD",
      "REGIÃO ABDOMINAL"
    ],
    "Atividade de Assistência à Saúde": [
      "CUIDADOS"
    ],
    "Procedimento Diagnóstico": [
      "ARTROSCOPIA"
    ],
    "Negação": [
      "Nega"
    ],
    "Sinal ou Sintoma": [
      "lombalgia",
      "SONOLENTA",
      "algia",
      "QUEIXAS ÁLGICAS",
      "DÉBITO COLÚRICO"
    ],
    "Conceito Espacial": [
      "EXTERNAMENTE"
    ],
    "Parte do Corpo, Órgão ou Componente Orgânico": [
      "OMBRO D",
      "JOELHO E",
      "ombro E"
    ],
    "Lesão ou Envenenamento": [
      "FRATURA DA OMOPLATA ESCAPULA",
      "TRAUMATISMOS MULTIPLOS NAO ESPECIFICADOS",
      "FRATURA DA EXTREMIDADE SUPERIOR DO UMERO"
    ],
    "Doença ou Síndrome": [
      "TRANSTORNOS DO MENISCO",
      "INFECCAO PIOGENICA DO DISCO INTERVERTEBRAL"
    ],
    "Função Fisiológica": [
      "Eliminações presentes"
    ]
  },
  "labels": {
    "FA33.2": {
      "term_original": "transtornos do menisco",
      "capitulo": "15",
      "confidence_embedding": 0.7564,
      "descricao_cid": "Representação de doença CID-11: Transtorno do menisco devido à ruptura ou lesão antiga. Definição: ",
      "classification_reasoning": "A opção mais precisa é o Transtorno do menisco devido à ruptura ou lesão antiga (FA33.2), pois o contexto clínico menciona a presença de fratura na omoplata escapula e artroscopia no joelho, sugerindo lesão ou traumatismo nos ligamentos cruzados e menisco."
    },
    "1D01": {
      "term_original": "infeccao piogenica do disco intervertebral",
      "capitulo": "01",
      "confidence_embedding": 0.7464,
      "descricao_cid": "Representação de doença CID-11: Meningite infecciosa, não classificada em outra parte. Definição: Doença das meninges, causada por uma infecção.",
      "classification_reasoning": "A escolha do código 1D01, Meningite infecciosa, não classificada em outra parte, é mais precisa para o termo 'infeccao piogenica do disco intervertebral' dentro do contexto clínico, pois menciona a presença de infecção e meniscos, o que está relacionado à meningite. As outras opções, embora envolvam processos infecciosos, não se aplicam ao contexto específico da fratura da omoplata escapula e infeccao piogenica do disco intervertebral."
    },
    "XE2EZ": {
      "term_original": "débito colúrico",
      "capitulo": "X",
      "confidence_embedding": 0.762,
      "descricao_cid": "Representação de doença CID-11: Sendo cuidado por pessoa que não é da área da saúde. Definição: ",
      "classification_reasoning": "A escolha do código XE2EZ se baseia na menção 'ENFª Florence Nightingale' que indica a presença de um profissional de saúde responsável pelo cuidado ao paciente, o que é descrito pela definição do código como 'Sendo cuidado por pessoa que não é da área da saúde'. Isso está alinhado com o contexto clínico do prontuário."
    },
    "FA80.8": {
      "term_original": "lombalgia",
      "capitulo": "15",
      "confidence_embedding": 0.7595,
      "descricao_cid": "Representação de doença CID-11: Degeneração de disco intervertebral da coluna lombar sem prolapso de disco. Definição: ",
      "classification_reasoning": "A presença de dor lombar (lombalgia) no contexto clínico e a infecção piojénica do disco intervertebral sugerem degeneração de disco intervertebral da coluna lombar sem prolapso de disco, o que justifica a escolha do código FA80.8."
    },
    "FA80.A": {
      "term_original": "algia",
      "capitulo": "15",
      "confidence_embedding": 0.7675,
      "descricao_cid": "Representação de doença CID-11: Degeneração de disco intervertebral da coluna lombar com esporão ósseo na vértebra. Definição: ",
      "classification_reasoning": "A escolha foi baseada na presença de infeção piojênica do disco intervertebral mencionada no contexto clínico, o que corresponde à definição de degeneração de disco intervertebral da coluna lombar com esporão ósseo na vértebra."
    },
    "FA38.1": {
      "term_original": "queixas álgicas",
      "capitulo": "15",
      "confidence_embedding": 0.7316,
      "descricao_cid": "Representação de doença CID-11: Artropatia neuropática. Definição: A artropatia neuropática é uma artrite progressiva, destrutiva, associada à perda da sensibilidade dolorosa, da propriocepção, ou de ambas. Os reflexos musculares normais que modulam os movimentos articulares também estão diminuídos. Sem estes mecanismos de proteção, as articulações ficam sujeitas ao trauma repetitivo, o que resulta no dano cartilaginoso e ósseo progressivo. Os sintomas adicionais incluem alterações cutâneas, tais como eritema, edema, hiperpigmentação ou púrpura, e úlceras de tecidos moles sobre as áreas afetadas, bem como afrouxamento ou instabilidade das articulações e deformidades articulares.",
      "classification_reasoning": "A opção mais precisa para o termo 'queixas álgicas' é a Artropatia neuropática (FA38.1), pois essa condição caracteriza-se por dor e desconforto articular, o que se relaciona às 'queixas álgicas' mencionadas no contexto clínico."
    },
    "ND36": {
      "term_original": "traumatismos multiplos nao especificados",
      "capitulo": "22",
      "confidence_embedding": 0.7909,
      "descricao_cid": "Representação de doença CID-11: Outros traumatismos envolvendo regiões múltiplas do corpo, não classificados em outra parte. Definição: ",
      "classification_reasoning": "A escolha pelo código ND36 se baseia na ausência de especificidade sobre a natureza dos traumatismos múltiplos. A descrição do código ND36 se ajusta melhor ao contexto clínico, que não apresenta detalhes específicos sobre o tipo de lesão ou a área afetada."
    }
  }
}