{
  "prontuario_id": 904,
  "text": "14:30 PROVINIENTE DA UTI-1 COMUNICATIVA, RESPIRANDO COM AUXILIO DE CATETER DE O2, EUPNEICA NOMOTENSA, NORMOCARDICA, HEMATOMAS EM MMSS, ACESSO VENOSO NO ANTEBRAÇO D CO SOROTERAPIA , SVD COM DÉBITO COLURICO, COM PELE INTEGRA, MANTEM CABECEIRA ELEVA.  ENFª FLORENCE NIGHTINGALE XXXX. DOENCA HEPATICA SEM OUTRA ESPECIFICACAO. 21:00 PELO ENFERMEIRO - NOITE  S - RAMSAY = 05 - SEDADO, TRAQUEOSTOMIZADO EM VENTILAÇÃO MECÂNICA, SUPORTADO POR DVA. O - 15º DI VÍTIMA ATROPELAMENTO POR ÔNIBUS, POI DRENAGEM HED + HSDA FRONTAL + FIXAÇÃO EXTERNA DE MSE, CRÂNIO ASSIMÉTRICO, INCISÃO CEFÁLICA COM DISCRETO DÉBITO SEROSO + DISCRETA DEISCÊNCIA DE SUTURA A DIREITA, FACE CORADA, PUPILAS ISOFOTOREAGENTES, D7 SNE COM DIETOTERAPIA EM CURSO 75 ML/H EM BI, TRAQUESOTOMIZADO EM SUPORTE DE VENTILAÇÃO MECÂNICA MODALIDADE CMV PEEP = 6 cmH2O, FIO2 = 35%, SPO2 = 98%, SECREÇÃO TRAQUEOBRÔNQUICA PURULENTA EM MÉDIA QUANTIDADE, ASPIRAÇÃO COM SISTEMA ABERTO, APRESENTANDO DISCRETA ESTÍMULO A ASPIRAÇÃO, CABECEIRA ELEVADA 45º, D 15 ACESSO CENTRAL CATETER DUPLO LÚMEM EM SUBCLÁVIA DIREITA, RECEBENDO NORADRENALINA 10 ML/H, MIDAZOLAN 20 ML/H, FENTANIL 10 ML/H EM BI, MSE COM EDEMA + FIXADOR EXTERNO EM MÃO + PUNHO, COM INCISÃO COM DISCRETO DÉBITO SEROSO, MANTENDO CURATIVO SIMPLES, MSD EDEMACIADO CACIFO III, TÓRAX SIMÉTRICO, AUSCULTA PULMONAR MV DIMINUÍDO Á DIREITA, RONCOS DIFUSOS E BOLHOSOS ACENTUADOS A ESQUERDA, ABDOMEM FLÁCIDO SEM MASSA PALPÁVEL, RHA ++, REGIÃO SACRA COM HIPEREMIA, ELIMINAÇÕES INTESTINAIS AUSENTES NO MOMENTO, DIURESE PRESENTE EM SISTEMA ABERTO, MMII LIVRES, PERFUSÃO PERIFÉRICA PRESERVADA, HEMODINÂMICAMENTE INSTÁVEL, MONITORIZADO COM ECG, PA E OXIMETRIA DE PULSO, EM PRECAUÇÃO DE CONTATO PARA ACINETO BAUMANNII + KLEBSIELA PNEUMONIAE, SEGUE EM CUIDADOS DE ENFERMAGEM.  SSVV - PA = 112/60, FC = 110 bpm, FR = 28 RPM,  Tº = 37.1º C.  A - REALIZAR ELETROENCÊFALO DIA 22/11/10 ÀS 15:30 H.  P - CONFORME PRESCRIÇÃO DE ENFERMAGEM HEMORRAGIA SUBDURAL DEVIDA A TRAUMATISMO.",
  "entities": {
    "Achado": [
      "COMUNICATIVA",
      "EUPNEICA",
      "NOMOTENSA",
      "NORMOCARDICA",
      "TRAQUESOTOMIZADO",
      "PELE INTEGRA",
      "FACE CORADA",
      "PUPILAS ISOFOTOREAGENTES",
      "TÓRAX SIMÉTRICO",
      "MASSA PALPÁVEL",
      "RHA ++",
      "DIURESE PRESENTE EM SISTEMA ABERTO",
      "MMII LIVRES",
      "PERFUSÃO PERIFÉRICA PRESERVADA"
    ],
    "Função Patológica": [
      "HEMATOMAS",
      "EDEMA"
    ],
    "Procedimento Terapêutico ou Preventivo": [
      "SOROTERAPIA",
      "SVD",
      "SEDADO",
      "TRAQUEOSTOMIZADO",
      "DVA",
      "TRAQUESOTOMIZADO",
      "PEEP",
      "FIO2",
      "SPO2",
      "ACESSO VENOSO",
      "CABECEIRA ELEVA",
      "VENTILAÇÃO MECÂNICA",
      "DRENAGEM HED",
      "FIXAÇÃO EXTERNA",
      "MODALIDADE CMV",
      "ASPIRAÇÃO COM SISTEMA ABERTO",
      "CABECEIRA ELEVADA 45º",
      "ACESSO CENTRAL CATETER DUPLO LÚMEM",
      "FIXADOR EXTERNO",
      "CURATIVO SIMPLES",
      "PRECAUÇÃO DE CONTATO"
    ],
    "Abreviação": [
      "SVD",
      "ENFª",
      "DVA",
      "POI",
      "MSE",
      "BI",
      "PEEP",
      "FIO2",
      "SPO2",
      "MSD",
      "ECG",
      "PA",
      "SSVV",
      "FC",
      "FR",
      "Tº",
      "ELETROENCÊFALO",
      "EM MMSS",
      "ANTEBRAÇO D",
      "DRENAGEM HED",
      "HSDA FRONTAL",
      "MODALIDADE CMV",
      "MV DIMINUÍDO Á DIREITA",
      "RHA ++",
      "MMII LIVRES"
    ],
    "Dispositivo Médico": [
      "SVD",
      "SNE",
      "ACESSO VENOSO",
      "ACESSO CENTRAL CATETER DUPLO LÚMEM",
      "FIXADOR EXTERNO",
      "CURATIVO SIMPLES"
    ],
    "Grupo Profissional ou Ocupacional": [
      "ENFª",
      "ENFERMEIRO"
    ],
    "Paciente ou Grupo com Deficiência": [
      "VÍTIMA"
    ],
    "Conceito Temporal": [
      "POI"
    ],
    "Localização ou Região Corporal": [
      "MSE",
      "MSD",
      "ABDOMEM",
      "REGIÃO SACRA"
    ],
    "Dispositivo de Administração de Medicamento": [
      "BI"
    ],
    "Conceito Quantitativo": [
      "35%",
      "98%",
      "112/60",
      "37",
      "75 ML/H",
      "6 cmH2O",
      "10 ML/H",
      "20 ML/H",
      "110 bpm",
      "28 RPM"
    ],
    "Substância Farmacológica": [
      "NORADRENALINA",
      "MIDAZOLAN",
      "FENTANIL"
    ],
    "Substância Química Orgânica": [
      "NORADRENALINA",
      "MIDAZOLAN",
      "FENTANIL"
    ],
    "Hormônio": [
      "NORADRENALINA"
    ],
    "Sinal ou Sintoma": [
      "EDEMA",
      "RESPIRANDO COM AUXILIO",
      "DÉBITO COLURICO",
      "RAMSAY = 05",
      "CRÂNIO ASSIMÉTRICO",
      "EDEMACIADO CACIFO III",
      "MV DIMINUÍDO Á DIREITA",
      "RONCOS DIFUSOS",
      "BOLHOSOS ACENTUADOS",
      "COM HIPEREMIA",
      "HEMODINÂMICAMENTE INSTÁVEL"
    ],
    "Parte do Corpo, Órgão ou Componente Orgânico": [
      "MÃO",
      "PUNHO",
      "ANTEBRAÇO D",
      "SUBCLÁVIA DIREITA"
    ],
    "Lesão ou Envenenamento": [
      "INCISÃO",
      "ATROPELAMENTO POR ÔNIBUS",
      "INCISÃO CEFÁLICA",
      "HEMORRAGIA SUBDURAL"
    ],
    "Negação": [
      "SEM",
      "AUSENTES"
    ],
    "Procedimento Diagnóstico": [
      "MONITORIZADO",
      "ECG",
      "PA",
      "ELETROENCÊFALO",
      "AUSCULTA PULMONAR",
      "OXIMETRIA DE PULSO"
    ],
    "Atributo Clínico": [
      "SSVV",
      "FC",
      "FR",
      "Tº"
    ],
    "Doença ou Síndrome": [
      "DOENCA HEPATICA",
      "HSDA FRONTAL",
      "HEMORRAGIA SUBDURAL"
    ],
    "Resultado Laboratorial ou de Teste": [
      "RAMSAY = 05"
    ],
    "Conceito Qualitativo": [
      "MÉDIA QUANTIDADE"
    ],
    "Função Fisiológica": [
      "ELIMINAÇÕES INTESTINAIS",
      "DIURESE PRESENTE EM SISTEMA ABERTO"
    ],
    "Bactéria": [
      "ACINETO BAUMANNII",
      "KLEBSIELA PNEUMONIAE"
    ],
    "Atividade de Assistência à Saúde": [
      "CUIDADOS DE ENFERMAGEM"
    ],
    "Produto Intelectual": [
      "PRESCRIÇÃO DE ENFERMAGEM"
    ]
  },
  "labels": {}
}