{
  "prontuario_id": 98,
  "text": "19/03/12: Colocada em névoa úmida no período, sem intercorrências. 10:54Hrs: Cliente encaminhado ao CC para procedimento com neurocx. 10hrs: Glasgow 14, pupilas iso / foto +, suporte de O2 sob névoa a 2l/min, solicito material para instalar catéter nasal, dieta VO líquida-pastosa com boa aceitação, PA 166x89mmHg, FC 94bpm, FR 20mpm, sat 95%, acesso venoso central em subclávia D com curativo oclusivo limpo e seco externamente, recebendo nipride a 16ml/h e eletrólitos a 42ml/h, ambos em BI, PAM em radial D, AP apresentando MV+ e sem ruídos adventícios, abdômen globoso e flácido, RHA+, SVD diurese efetiva, pele íntegra em região sacra, mantém monitorização cardíaca, oximetria de pulso e cabeceira elevada a 45°, realizadas medidas de conforto e higiene, segue sob cuidados e observação. 00:23: paciente POI de cx de fx rádio distal, lúcido, verbalizando, eupnéico, com boa perfusão distal, mantém tala com enfaixamento em MSE. 00:08h: Paciente encaminhado à clínica X-leme para realização de complemento da ressonância, já realizada anteriormente.  ",
  "entities": {
    "Paciente ou Grupo com Deficiência": [
      "Cliente",
      "paciente",
      "Paciente"
    ],
    "Abreviação": [
      "CC",
      "neurocx",
      "2l/min",
      "D",
      "16ml/h",
      "42ml/h",
      "BI",
      "PAM",
      "AP",
      "MV+",
      "RHA+",
      "SVD",
      "POI",
      "MSE",
      "dieta VO líquida-pastosa"
    ],
    "Organização Relacionada à Saúde": [
      "CC",
      "clínica X-leme"
    ],
    "Atividade de Assistência à Saúde": [
      "procedimento",
      "cuidados",
      "observação",
      "medidas de conforto e higiene"
    ],
    "Grupo Profissional ou Ocupacional": [
      "neurocx"
    ],
    "Dispositivo Médico": [
      "material",
      "BI",
      "SVD",
      "catéter nasal",
      "acesso venoso central",
      "curativo oclusivo",
      "tala com enfaixamento"
    ],
    "Conceito Quantitativo": [
      "166x89mmHg",
      "94bpm",
      "20mpm",
      "95%",
      "16ml/h",
      "42ml/h"
    ],
    "Parte do Corpo, Órgão ou Componente Orgânico": [
      "subclávia",
      "radial",
      "pele"
    ],
    "Achado": [
      "limpo",
      "seco",
      "MV+",
      "flácido",
      "RHA+",
      "lúcido",
      "verbalizando",
      "eupnéico",
      "boa aceitação",
      "sem ruídos adventícios",
      "diurese efetiva",
      "cabeceira elevada a 45°",
      "perfusão distal"
    ],
    "Conceito Espacial": [
      "externamente"
    ],
    "Substância Química Inorgânica": [
      "nipride"
    ],
    "Substância Farmacológica": [
      "nipride",
      "eletrólitos"
    ],
    "Procedimento Diagnóstico": [
      "AP",
      "ressonância",
      "monitorização cardíaca",
      "oximetria de pulso"
    ],
    "Localização ou Região Corporal": [
      "abdômen",
      "MSE",
      "região sacra"
    ],
    "Sinal ou Sintoma": [
      "globoso",
      "Glasgow 14"
    ],
    "Procedimento Terapêutico ou Preventivo": [
      "SVD",
      "névoa úmida",
      "suporte de",
      "O2 sob névoa",
      "dieta VO líquida-pastosa",
      "acesso venoso central",
      "curativo oclusivo",
      "cabeceira elevada a 45°",
      "medidas de conforto e higiene",
      "tala com enfaixamento"
    ],
    "Conceito Temporal": [
      "POI"
    ],
    "Conceito Qualitativo": [
      "boa",
      "boa aceitação"
    ],
    "Negação": [
      "sem ruídos adventícios"
    ],
    "Função Fisiológica": [
      "diurese efetiva"
    ],
    "Lesão ou Envenenamento": [
      "fx rádio distal"
    ]
  },
  "labels": {}
}