{
  "prontuario_id": 416,
  "text": "Às 00:03: Paciente referindo dificuldade para respirar, consciente, orientado, calmo, comunicativo, em repouso no leito, recebendo oxigênio por catéter nasal a 4 l/min, aceitando pouco dieta VO, acesso venoso periférico MSE salinizado, eliminações fisiológicas. ENFISEMA. Consciente, orientada, ansiosa pela alta, refere lombalgia e algia em MID. Segue sob cuidados de enfermagem. DOR LOMBAR BAIXA. Às 20:00h: Consciente, comunicativo, lucido , orientado, eupneico, afebril, mantêm repouso, até momento sem prescrição médica, comunicado plantão ortopedia. TRAUMATISMOS MULTIPLOS NAO ESPECIFICADOS. Às 10:54 HS: CONSCIENTE, ORIENTADO, LÚCIDO E COMUNICATIVO, POUCO DISPNEICO, PASSOU PARTE DA NOITE EM AR AMBIENTE, SEGUNDO A ESPOSA, SEM ALTERAÇÕES, O2 CONTÍNUO EM CATETER NASAL. AVP EM MSD COM SRT, BOA ACEITAÇÃO ALIMENTAR, RETIRADO SVD. BANHO DE ASPERSÃO E RE. OUTRAS DOENCAS PULMONARES OBSTRUTIVAS CRONICAS.",
  "entities": {
    "Paciente ou Grupo com Deficiência": [
      "Paciente"
    ],
    "Achado": [
      "consciente",
      "orientado",
      "calmo",
      "comunicativo",
      "Consciente",
      "orientada",
      "lucido",
      "eupneico",
      "afebril",
      "repouso",
      "CONSCIENTE",
      "ORIENTADO",
      "LÚCIDO",
      "COMUNICATIVO",
      "AVP",
      "repouso no leito",
      "eliminações fisiológicas",
      "ACEITAÇÃO ALIMENTAR"
    ],
    "Substância Farmacológica": [
      "oxigênio"
    ],
    "Localização ou Região Corporal": [
      "MSE",
      "MID",
      "MSD"
    ],
    "Abreviação": [
      "MSE",
      "MID",
      "AVP",
      "MSD",
      "SRT",
      "4 l/min",
      "dieta VO",
      "RETIRADO SVD"
    ],
    "Procedimento Terapêutico ou Preventivo": [
      "salinizado",
      "AVP",
      "SRT",
      "dieta VO",
      "acesso venoso periférico",
      "O2 CONTÍNUO",
      "RETIRADO SVD",
      "BANHO DE ASPERSÃO E RE"
    ],
    "Conceito Qualitativo": [
      "salinizado",
      "BOA"
    ],
    "Função Patológica": [
      "ENFISEMA"
    ],
    "Doença ou Síndrome": [
      "ENFISEMA",
      "DOENCAS PULMONARES OBSTRUTIVAS CRONICAS"
    ],
    "Atividade de Assistência à Saúde": [
      "alta",
      "cuidados de enfermagem",
      "prescrição médica"
    ],
    "Sinal ou Sintoma": [
      "lombalgia",
      "algia",
      "afebril",
      "DISPNEICO",
      "ALTERAÇÕES",
      "dificuldade para respirar",
      "DOR LOMBAR BAIXA"
    ],
    "Negação": [
      "afebril",
      "sem"
    ],
    "Conceito Quantitativo": [
      "POUCO",
      "4 l/min"
    ],
    "Grupo Familiar": [
      "ESPOSA"
    ],
    "Dispositivo Médico": [
      "AVP",
      "acesso venoso periférico"
    ],
    "Função Fisiológica": [
      "eliminações fisiológicas"
    ],
    "Produto Intelectual": [
      "prescrição médica"
    ],
    "Lesão ou Envenenamento": [
      "TRAUMATISMOS MULTIPLOS"
    ]
  },
  "labels": {}
}