{
  "prontuario_id": 499,
  "text": "Às 15:54 HS: CLIENTE INTERNADO POR INTOXICAÇÃO EXÓGENA + REBAIXAMENTO NÍVEL CONSCIÊNCIA: GLASGOW 11 ESTIMADO 15, PUPILAS ISOCÓRICAS, SEGUE VENTILAÇÃO MECÂNICA MODALIDADE A/C, FIO2 40%, SNG FECHADA, MV CREPITANTES, CATETER CENTRAL (D) PVC 13,  PLANO HIDRATAÇÃO EM CURSO, ABDOMEN GLOBOSO, FLÁCIDO, RHA + , SVD DIURESE COLORAÇÃO CONCENTRADO. FOI SUSPENSO TC CRÂNIO. ÀS 12:13HS: PACIENTE TRAQUEOSTOMIZADA COM CANULA DE METAL, COM SAIDA DE POUCA SECREÇÃO, MANTEM SUPORTE DE O2 SOB NEVOA UMIDA. ABERTURA OCULAR ESPONTANEA. ABDOMEM PLANO E FLACIDO COM RHA + , DIURESE ESPONTANEA PRESENTE EM FRALDAS. EDEMA DE MMII. APRESENTOU TEMPERATURA DE 38. FOI MEDICADA CONFORME PRESCRIÇÃO. AGUARDA RX DE ABD PARA VISUALIZAÇÃO DE SONDA NASOENTERAL. SEGUE SOB OBSERVAÇÃO E CUIDADOS ENFER .",
  "entities": {
    "Paciente ou Grupo com Deficiência": [
      "CLIENTE",
      "PACIENTE"
    ],
    "Abreviação": [
      "FIO2",
      "D",
      "PVC",
      "SVD",
      "MMII",
      "MODALIDADE A/C",
      "SNG FECHADA",
      "MV CREPITANTES",
      "RHA +",
      "TC CRÂNIO",
      "RX DE ABD"
    ],
    "Conceito Quantitativo": [
      "40%",
      "13"
    ],
    "Conceito Espacial": [
      "D"
    ],
    "Localização ou Região Corporal": [
      "ABDOMEN",
      "ABDOMEM",
      "MMII"
    ],
    "Sinal ou Sintoma": [
      "GLOBOSO",
      "EDEMA",
      "REBAIXAMENTO NÍVEL CONSCIÊNCIA",
      "GLASGOW 11",
      "MV CREPITANTES",
      "TEMPERATURA DE 38"
    ],
    "Achado": [
      "FLÁCIDO",
      "DIURESE",
      "TRAQUEOSTOMIZADA",
      "PLANO",
      "FLACIDO",
      "ESTIMADO 15",
      "PUPILAS ISOCÓRICAS",
      "RHA +",
      "COLORAÇÃO CONCENTRADO",
      "ABERTURA OCULAR ESPONTANEA",
      "DIURESE ESPONTANEA"
    ],
    "Dispositivo Médico": [
      "SVD",
      "SNG FECHADA",
      "CATETER CENTRAL",
      "CANULA DE METAL",
      "SONDA NASOENTERAL"
    ],
    "Procedimento Terapêutico ou Preventivo": [
      "SVD",
      "TRAQUEOSTOMIZADA",
      "MEDICADA",
      "VENTILAÇÃO MECÂNICA",
      "SNG FECHADA",
      "CATETER CENTRAL",
      "SUPORTE DE O2 SOB NEVOA UMIDA"
    ],
    "Função Fisiológica": [
      "DIURESE",
      "DIURESE ESPONTANEA"
    ],
    "Substância Corporal": [
      "SECREÇÃO"
    ],
    "Objeto Manufaturado": [
      "FRALDAS"
    ],
    "Função Patológica": [
      "EDEMA"
    ],
    "Atividade de Assistência à Saúde": [
      "MEDICADA",
      "PRESCRIÇÃO",
      "OBSERVAÇÃO",
      "CUIDADOS ENFER"
    ],
    "Lesão ou Envenenamento": [
      "INTOXICAÇÃO EXÓGENA"
    ],
    "Procedimento Diagnóstico": [
      "TC CRÂNIO",
      "RX DE ABD"
    ]
  },
  "labels": {}
}