{
  "prontuario_id": 636,
  "text": "ÀS 15:45h: CONSCIENTE, LUCIDA, EUPNEICA, COMUNICATIVA, EM REPOUSO NO LEITO, NÃO REFERE ALGIA, APRESENTA PUPILAS ISOCORICAS, PELE E MUCOSA CORADA E HIDRATADA, ABDOMEN PLANO, FLACIDO, POUCO DOLOROSO A PALPAÇÃO, MANTEM ACESSO VENOSO PERIFERICO COM SOROTERAPIA, ABDOME AGUDO. PAC SOB NEVOA, TENTATIVA DE SUICIDIO POR INTOXICAÇÃO EXOGENA. ACESSO VENOSO COM SOROTERAPIA PERMEAVEL, REPOUSO NO LEITO, SEGUE SOB CUIDADOS DE ENFERMAGEM. OUTRAS PNEUMONIAS DEVIDAS A MICROORGANISMOS NAO ESPECIFICADOS. ÀS 18:00H: CLIENTE CONSCIENTE, RECUSOU A PASSAGEM DA SONDA, A MESMA ACEITOU BEM A DIETA OFERECIDA , DEGLUTINDO SEM DIFICULDADES, TENTO CONTATO COM A FONO AUGUSTA, SEM SUCESSO. NEOPLASIA MALIGNA DO CEREBRO, EXCETO LOBOS E VENTRICULOS. Às 18:06: corada, alerta, afebril, comunicativa, em repouso no leito, aceitando dieta via oral, avp em mse com soroterapia em curso, ssvv estavéis, eliminações fisiologicas presentes e espontaneas, não refere algia, incisão cirurgica limpa e seca, segue sob cuidados de. FRATURA DA COLUNA LOMBAR E DA PELVE.",
  "entities": {
    "Achado": [
      "CONSCIENTE",
      "LUCIDA",
      "EUPNEICA",
      "COMUNICATIVA",
      "CORADA",
      "HIDRATADA",
      "PLANO",
      "FLACIDO",
      "corada",
      "alerta",
      "afebril",
      "comunicativa",
      "limpa",
      "seca",
      "REPOUSO NO LEITO",
      "PUPILAS ISOCORICAS",
      "repouso no leito",
      "ssvv estavéis"
    ],
    "Sinal ou Sintoma": [
      "ALGIA",
      "afebril",
      "algia"
    ],
    "Parte do Corpo, Órgão ou Componente Orgânico": [
      "PELE",
      "LOBOS",
      "VENTRICULOS"
    ],
    "Localização ou Região Corporal": [
      "ABDOMEN",
      "mse"
    ],
    "Procedimento Diagnóstico": [
      "PALPAÇÃO"
    ],
    "Procedimento Terapêutico ou Preventivo": [
      "SOROTERAPIA",
      "NEVOA",
      "avp",
      "REPOUSO NO LEITO",
      "ACESSO VENOSO PERIFERICO",
      "ACESSO VENOSO",
      "SOROTERAPIA PERMEAVEL",
      "PASSAGEM DA SONDA",
      "repouso no leito",
      "dieta via oral",
      "soroterapia em curso"
    ],
    "Paciente ou Grupo com Deficiência": [
      "CLIENTE"
    ],
    "Alimento": [
      "DIETA"
    ],
    "Negação": [
      "EXCETO",
      "afebril"
    ],
    "Abreviação": [
      "avp",
      "mse",
      "ssvv estavéis"
    ],
    "Dispositivo Médico": [
      "avp",
      "ACESSO VENOSO PERIFERICO",
      "ACESSO VENOSO"
    ],
    "Atividade de Assistência à Saúde": [
      "cuidados",
      "CUIDADOS DE ENFERMAGEM"
    ],
    "Doença ou Síndrome": [
      "ABDOME AGUDO"
    ],
    "Lesão ou Envenenamento": [
      "TENTATIVA DE SUICIDIO POR INTOXICAÇÃO EXOGENA",
      "FRATURA DA COLUNA LOMBAR E DA PELVE"
    ],
    "Processo Neoplásico": [
      "NEOPLASIA MALIGNA DO CEREBRO"
    ]
  },
  "labels": {}
}