{
  "prontuario_id": 80,
  "text": "Em 30/01/2008: Púpilas isocóricas, mióticas, responsiva a estímulos dolorosos e aspirativos. Permanece em ventilação ventilação mecânica, PCV, Pi 36, Peep 8 e FiO2 80%. Hemodinamicamente instavel, taquicárdica, mantendo no momento saturação de 92% e hipotensão. NEOPLASIA MALIGNA DA BASE DA LINGUA. Às 09:57h: PO PONTE FEM-FEM. CONSCIENTE, ORIENTADO, TRANQUILO, NÃO VERBALIZANDO E RESTRITO AO LEITO. MANTENDO CURATIVO EM MIE. SNE COM DIETA EM BI. EMBOLIA E TROMBOSE DE ARTERIAS DOS MEMBROS SUPERIORES. Às 14:339hrs: Consciente, comunicativa, alerta, orientada. Eupneica, afebril, corada e hidratada. Aceitando bem a dieta VO branda. Mantem dreno de penrose na reg abdominal, ausente de debito. Incisao cirurgica em reg abdominal permanece limpo e seco. Nao re. ABDOME AGUDO. Às 18:01h: TRAQUEOSTOMIZADA, EM VM PCV COM 20 PI, 14 FR, 5 PEEP, 50% FIO2, INSTÁVEL HEMODINAMICAMENTE, APRESENTANDO HIPOTENSÃO, INICIADO DVA COM BOA RESPOSTA E NECESSIDADE DE AJUSTE POR ELEVAÇÃO DE PA, REAGE A DOSE E ASPIRAÇÃO, PÚPILAS ISOCÓRICAS E FOTORREAGENTES. NEOPLASIA MALIGNA DO RETO.",
  "entities": {
    "Parte do Corpo, Órgão ou Componente Orgânico": [
      "Púpilas"
    ],
    "Sinal ou Sintoma": [
      "mióticas",
      "taquicárdica",
      "hipotensão",
      "afebril",
      "HIPOTENSÃO",
      "Hemodinamicamente instavel",
      "INSTÁVEL HEMODINAMICAMENTE"
    ],
    "Abreviação": [
      "PCV",
      "Pi",
      "Peep",
      "FiO2",
      "PO",
      "MIE",
      "SNE",
      "VM",
      "PI",
      "FR",
      "PEEP",
      "FIO2",
      "DVA",
      "PONTE FEM-FEM",
      "dieta VO branda",
      "reg abdominal",
      "ELEVAÇÃO DE PA"
    ],
    "Procedimento Terapêutico ou Preventivo": [
      "PCV",
      "CURATIVO",
      "SNE",
      "TRAQUEOSTOMIZADA",
      "VM",
      "DVA",
      "ASPIRAÇÃO",
      "ventilação mecânica",
      "PONTE FEM-FEM",
      "RESTRITO AO LEITO",
      "dieta VO branda",
      "dreno de penrose"
    ],
    "Conceito Quantitativo": [
      "36",
      "8",
      "80%",
      "92%",
      "20",
      "14",
      "5",
      "50%"
    ],
    "Conceito Temporal": [
      "PO",
      "no momento"
    ],
    "Achado": [
      "CONSCIENTE",
      "ORIENTADO",
      "TRANQUILO",
      "VERBALIZANDO",
      "Consciente",
      "comunicativa",
      "alerta",
      "orientada",
      "Eupneica",
      "afebril",
      "corada",
      "hidratada",
      "debito",
      "limpo",
      "seco",
      "TRAQUEOSTOMIZADA",
      "responsiva a estímulos dolorosos e aspirativos",
      "RESTRITO AO LEITO",
      "ELEVAÇÃO DE PA",
      "PÚPILAS ISOCÓRICAS E FOTORREAGENTES"
    ],
    "Negação": [
      "NÃO",
      "afebril",
      "ausente",
      "Nao"
    ],
    "Dispositivo Médico": [
      "CURATIVO",
      "SNE",
      "dreno de penrose"
    ],
    "Localização ou Região Corporal": [
      "MIE",
      "reg abdominal"
    ],
    "Função Fisiológica": [
      "debito"
    ],
    "Processo Neoplásico": [
      "NEOPLASIA MALIGNA DA BASE DA LINGUA",
      "NEOPLASIA MALIGNA DO RETO"
    ],
    "Doença ou Síndrome": [
      "EMBOLIA E TROMBOSE DE ARTERIAS DOS MEMBROS SUPERIORES",
      "ABDOME AGUDO"
    ]
  },
  "labels": {}
}