{
  "prontuario_id": 544,
  "text": "Às 07:40hs: Glasgow 15, pupilas isocóricas fotorreagentes, SNG aberta sem débito, respiração espontânea, em névoa úmida a 4 l/m, SpO2 99%, curativo de região cervical anterior limpo e seco, monitorizado, estável hemodinamicamente, MV + com roncos esparsos, acesso venoso periférico em MSE com plano básico de hidratação, curativo em antebraço D limpo e seco, abdome plano, flácido, indolor a palpação, RHA diminuído, SVD com diurese efetiva, evacuação ausente, tala gessada em MIE, extremidades quentes e bem perfundidas, higienizado e sentado na poltrona, pele íntegra. ÀS 18:41: CLIENTE SONOLENTA, CONSCIENTE, POUCO COMUNICATIVA, EUPNEICA, REPOUSO NO LEITO, ACEITANDO POUCO  A DIETA, APRESENTOU HIPERGLICEMIA E FOI COMUNICADO DRº LUCAS, E FOI MEDICADA, CTVO LIMPO E SECO EM OMBRO D + TIPOIA CANADENSE, ABDOMEN GLOBOSO E FLÁCIDO, MICÇÃO PRESENTE. Às 20h: Glasgow 15, face corada, pupilas iso / foto. FO reg frontal D aberta, limpa e seca. Respiraçao espontanea em ar ambiente, ausculta pulmonar com MV +, S/ RA. SNE em narina E fechada no momento. Mantem cabeceira 45 graus, no momento nao relata queixas algicas. Acesso central D com infusao de sf 0,9% gravitacional. Extremidades aquecidas, perfusao periferica preservada, PAM radial E permeavel. Abdomen flacido palpaçao, rha + . Diurese por SVD presente em coletor, amarelo citrico. Balanço negativo em -122 ml, comunicado plantao, feito 500 ml sf 0,9% em bolus. Monitorizado continuamente com cardioscopio + oximetria de pulso + pam nao invasiva.",
  "entities": {
    "Função Fisiológica": [
      "débito",
      "Diurese",
      "diurese efetiva",
      "MICÇÃO PRESENTE"
    ],
    "Procedimento Terapêutico ou Preventivo": [
      "SpO2",
      "curativo",
      "SVD",
      "higienizado",
      "CTVO",
      "SNE",
      "PAM",
      "pam",
      "invasiva",
      "SNG aberta",
      "névoa úmida",
      "acesso venoso periférico",
      "plano básico de hidratação",
      "tala gessada",
      "sentado na poltrona",
      "REPOUSO NO LEITO",
      "TIPOIA CANADENSE",
      "cabeceira 45 graus",
      "Acesso central",
      "sf 0 , 9%"
    ],
    "Abreviação": [
      "SpO2",
      "MSE",
      "D",
      "SVD",
      "MIE",
      "CTVO",
      "FO",
      "S/",
      "RA",
      "SNE",
      "E",
      "SNG aberta",
      "MV +",
      "RHA diminuído",
      "pupilas iso / foto",
      "rha +",
      "sf 0 , 9%"
    ],
    "Conceito Quantitativo": [
      "99%",
      "4 l/m",
      "Balanço negativo",
      "-122 ml",
      "500 ml",
      "sf 0 , 9%"
    ],
    "Dispositivo Médico": [
      "curativo",
      "SVD",
      "CTVO",
      "SNE",
      "coletor",
      "cardioscopio",
      "SNG aberta",
      "acesso venoso periférico",
      "tala gessada",
      "TIPOIA CANADENSE",
      "Acesso central"
    ],
    "Achado": [
      "limpo",
      "seco",
      "monitorizado",
      "plano",
      "flácido",
      "quentes",
      "higienizado",
      "CONSCIENTE",
      "EUPNEICA",
      "LIMPO",
      "SECO",
      "FLÁCIDO",
      "aberta",
      "limpa",
      "seca",
      "flacido",
      "Monitorizado",
      "Glasgow 15",
      "pupilas isocóricas fotorreagentes",
      "SNG aberta",
      "respiração espontânea",
      "estável hemodinamicamente",
      "MV +",
      "diurese efetiva",
      "bem perfundidas",
      "sentado na poltrona",
      "pele íntegra",
      "REPOUSO NO LEITO",
      "MICÇÃO PRESENTE",
      "face corada",
      "pupilas iso / foto",
      "Respiraçao espontanea em ar ambiente",
      "Extremidades aquecidas",
      "perfusao periferica preservada",
      "rha +",
      "amarelo citrico"
    ],
    "Procedimento Diagnóstico": [
      "monitorizado",
      "palpação",
      "palpaçao",
      "Monitorizado",
      "cardioscopio",
      "ausculta pulmonar",
      "oximetria de pulso"
    ],
    "Localização ou Região Corporal": [
      "MSE",
      "abdome",
      "MIE",
      "extremidades",
      "ABDOMEN",
      "Abdomen",
      "cervical anterior"
    ],
    "Conceito Espacial": [
      "D",
      "E"
    ],
    "Negação": [
      "indolor",
      "S/",
      "nao"
    ],
    "Paciente ou Grupo com Deficiência": [
      "CLIENTE"
    ],
    "Sinal ou Sintoma": [
      "SONOLENTA",
      "GLOBOSO",
      "RA",
      "roncos esparsos",
      "RHA diminuído",
      "queixas algicas"
    ],
    "Alimento": [
      "DIETA"
    ],
    "Atividade de Assistência à Saúde": [
      "MEDICADA",
      "plantao"
    ],
    "Conceito Temporal": [
      "continuamente",
      "no momento"
    ],
    "Conceito Qualitativo": [
      "bem perfundidas"
    ],
    "Substância Farmacológica": [
      "sf 0 , 9%"
    ]
  },
  "labels": {}
}