{
  "prontuario_id": 161,
  "text": "Às 13:30: REALIZADA INTUBAÇÃO OROTRAQUEAL POR MEDICO, SEM INTERCORRÊNCIAS. SEGUE EM VM, TOT Nº 7,5, RIMA: 23, PARÂMETROS: A/C, FR: 16, FIO2: 40%, VOL: 482 ML. PUNÇÃO DE CVC EM SUBCLÁVIA ESQUERDA. AGUARDA RX. PAM SEM SUCESSO, AMBOS POR MEDICO. MANTÉM INFUSÃO DE PROPOFOL 15 ML/H, NORA 10 ML/H E ELETRÓLITO 21 ML/H. ÀS 16:00: NÃO CONTACTUA,  ICTERICA, RESPIRANDO COM AUXILIO DE O2, PA = 70/40, PULSO 91 BPM, RESP = 30 RPM, SAT = ACIMA DE 90%. SNE LIBERADO DIETA CONFORME ORIENTAÇÃO Drª ALICE, ACESSO VENOSO NO ANTEBRAÇO DIREITO SEM SINAIS FLOGISTICOS. DIURESE PRESENTE, MANTEM CABECEIRA ELEVADA. Às 00:36h: Orientada a manter jejum após as 24h para procedimento cirúrgico em 30/06, as 07h, conforme evolução médica. Encaminhada para realização de RX. À 01:00 H: CLIENTE PROVENIENTE DO PA, VITIMA DE COLISÃO MOTO X AUTO, TRATAMENTO OMBRO DIREITO, CONSCIENTE, AFEBRIL, EUPNEICO, REPOUSO, ORIENTADO, NORMOTENSO 130X70, NORMOCARDICO 75, REFERE ALGIA EM OMBRO DIREITO, SENDO MEDICADO CPM. ELIMINAÇOES NORMAIS. SEGUE EM OBSERVAÇÃO E CUIDADOS. Paciente lúcido, orientado, deambula sem auxílio, aceita bem a dieta. Hidratado, corado, afebril, eupneico. Sem queixas álgicas no momento. MID com edema +1/+4. Aguarda avaliação da hematologia, Dra Alice ciente, virá amanhã. SEGUE CUIDADOS.",
  "entities": {
    "Grupo Profissional ou Ocupacional": [
      "MEDICO"
    ],
    "Sinal ou Sintoma": [
      "INTERCORRÊNCIAS",
      "ICTERICA",
      "ALGIA",
      "edema",
      "RESPIRANDO COM AUXILIO DE O2",
      "SINAIS FLOGISTICOS",
      "queixas álgicas"
    ],
    "Abreviação": [
      "VM",
      "TOT",
      "FR",
      "FIO2",
      "VOL",
      "CVC",
      "RX",
      "PAM",
      "NORA",
      "PA",
      "BPM",
      "RPM",
      "SAT",
      "SNE",
      "CPM",
      "MID",
      "+1/+4"
    ],
    "Procedimento Terapêutico ou Preventivo": [
      "VM",
      "CVC",
      "INFUSÃO",
      "SNE",
      "jejum",
      "TRATAMENTO",
      "REPOUSO",
      "dieta",
      "INTUBAÇÃO OROTRAQUEAL",
      "ACESSO VENOSO",
      "CABECEIRA ELEVADA",
      "procedimento cirúrgico"
    ],
    "Dispositivo Médico": [
      "TOT",
      "CVC",
      "SNE",
      "ACESSO VENOSO"
    ],
    "Parte do Corpo, Órgão ou Componente Orgânico": [
      "RIMA",
      "SUBCLÁVIA"
    ],
    "Conceito Quantitativo": [
      "23",
      "16",
      "40%",
      "70/40",
      "BPM",
      "30",
      "RPM",
      "130X70",
      "75",
      "7 , 5",
      "482 ML",
      "15 ML/H",
      "10 ML/H",
      "21 ML/H",
      "ACIMA DE 90%"
    ],
    "Conceito Espacial": [
      "ESQUERDA",
      "DIREITO"
    ],
    "Procedimento Diagnóstico": [
      "RX",
      "PAM"
    ],
    "Achado": [
      "SUCESSO",
      "CONTACTUA",
      "CONSCIENTE",
      "AFEBRIL",
      "EUPNEICO",
      "REPOUSO",
      "ORIENTADO",
      "NORMOTENSO",
      "NORMOCARDICO",
      "lúcido",
      "orientado",
      "deambula",
      "Hidratado",
      "corado",
      "afebril",
      "eupneico",
      "DIURESE PRESENTE",
      "ELIMINAÇOES NORMAIS"
    ],
    "Substância Farmacológica": [
      "PROPOFOL",
      "NORA",
      "ELETRÓLITO"
    ],
    "Substância Química Orgânica": [
      "PROPOFOL"
    ],
    "Atributo Clínico": [
      "PA",
      "SAT",
      "PULSO 91"
    ],
    "Alimento": [
      "DIETA",
      "dieta"
    ],
    "Conceito Temporal": [
      "após",
      "amanhã",
      "no momento"
    ],
    "Paciente ou Grupo com Deficiência": [
      "CLIENTE",
      "VITIMA",
      "Paciente"
    ],
    "Organização Relacionada à Saúde": [
      "PA"
    ],
    "Negação": [
      "AFEBRIL",
      "afebril"
    ],
    "Atividade de Assistência à Saúde": [
      "MEDICADO",
      "OBSERVAÇÃO",
      "CUIDADOS",
      "avaliação da hematologia"
    ],
    "Localização ou Região Corporal": [
      "MID"
    ],
    "Função Patológica": [
      "edema"
    ],
    "Função Fisiológica": [
      "DIURESE PRESENTE",
      "ELIMINAÇOES NORMAIS"
    ],
    "Produto Intelectual": [
      "evolução médica"
    ]
  },
  "labels": {}
}