{
  "prontuario_id": 112,
  "text": "Às 17:00: Dra Alice realizou troca de cânula de traqueostomia mudando modo para PSV. Florence Nightingale. HEMANGIOMA DE QUALQUER LOCALIZACAO. Consciente, orientado, edema + hematoma orbital bilateral, escoriações, AVPE com SRT, gesso em MSD com boa perfusão, nega algias, deambula com auxílio. Boa aceitação alimentar, eliminações presentes. Segue sob cuidados de enfermagem. TRAUMATISMO CEREBRAL FOCAL. DR VITAL BRASIL SOLICITA RNM DE COLUNA CERVICAL. ENCAMINHO PARA REVISÃO DE CONTAS E AGENDAMENTO COM MARIA. AGUARDO RETORNO DO HORÁRIO AGENDADO. ENCEFALITE AGUDA DISSEMINADA. ÀS 02:45HS: PACIENTE CONFUSA, AGITADA, AGRESSIVA, CONTIDA, NÃO ACEITA MEDICAÇÃO VO, CONTIDA NO LEITO. COMUNICADO DRA ALICE SOBRE A NÃO ACEITAÇÃO DA MEDICAÇAÕ VO PELA PACIENTE QUE PERMANECE AGITADA E CONFUSA. HEMORRAGIA SUBARACNOIDE PROVENIENTE DE ARTERIA INTRACRANIANA NAO ESPECIFICADA. Às 12:22: Paciente não referindo queixas, consciente, orientado, calmo, comunicativo, em repouso no leito, aceitando bem dieta VO, com edema em coxa D, boa perfusão periférica, eliminações fisiológicas presentes. CONCUSSAO CEREBRAL. ÀS 12:21 HS: CONSCIENTE, ORIENTADA, COMUNICATIVA, ACESSO VENOSO SALINIZADO, RELATA DOR LOMBAR COM IRRADIAÇÃO PARA MID. ONTEM REALIZOU ECG, HOJE RAIO-X E TOMO. CX AGENDADA PARA 21/02 PELA MANHÃ. SEGUE CUIDADOS. TRANSTORNOS DE DISCOS LOMBARES E DE OUTROS DISCOS INTERVERTEBRAIS COM RADICULOPATIA.",
  "entities": {
    "Procedimento Terapêutico ou Preventivo": [
      "PSV",
      "AVPE",
      "SRT",
      "gesso",
      "CONTIDA",
      "CX",
      "troca de cânula de traqueostomia",
      "CONTIDA NO LEITO",
      "repouso no leito",
      "ACESSO VENOSO"
    ],
    "Abreviação": [
      "PSV",
      "AVPE",
      "SRT",
      "MSD",
      "D",
      "ECG",
      "TOMO",
      "CX",
      "RNM DE COLUNA CERVICAL",
      "ACEITA MEDICAÇÃO VO",
      "ACEITAÇÃO DA MEDICAÇAÕ VO",
      "aceitando bem dieta VO",
      "IRRADIAÇÃO PARA MID"
    ],
    "Achado": [
      "Consciente",
      "orientado",
      "consciente",
      "calmo",
      "comunicativo",
      "CONSCIENTE",
      "ORIENTADA",
      "COMUNICATIVA",
      "boa perfusão",
      "deambula com auxílio",
      "Boa aceitação alimentar",
      "eliminações presentes",
      "ACEITA MEDICAÇÃO VO",
      "ACEITAÇÃO DA MEDICAÇAÕ VO",
      "repouso no leito",
      "aceitando bem dieta VO",
      "boa perfusão periférica"
    ],
    "Função Patológica": [
      "edema"
    ],
    "Sinal ou Sintoma": [
      "edema",
      "algias",
      "CONFUSA",
      "AGITADA",
      "AGRESSIVA",
      "queixas",
      "DOR LOMBAR",
      "IRRADIAÇÃO PARA MID"
    ],
    "Lesão ou Envenenamento": [
      "escoriações",
      "TRAUMATISMO CEREBRAL FOCAL",
      "CONCUSSAO CEREBRAL"
    ],
    "Dispositivo Médico": [
      "AVPE",
      "gesso",
      "ACESSO VENOSO"
    ],
    "Localização ou Região Corporal": [
      "MSD"
    ],
    "Paciente ou Grupo com Deficiência": [
      "PACIENTE",
      "Paciente"
    ],
    "Parte do Corpo, Órgão ou Componente Orgânico": [
      "coxa"
    ],
    "Conceito Espacial": [
      "D"
    ],
    "Procedimento Diagnóstico": [
      "ECG",
      "RAIO-X",
      "TOMO",
      "RNM DE COLUNA CERVICAL"
    ],
    "Conceito Temporal": [
      "MANHÃ"
    ],
    "Atividade de Assistência à Saúde": [
      "CUIDADOS",
      "cuidados de enfermagem"
    ],
    "Doença ou Síndrome": [
      "HEMANGIOMA DE QUALQUER LOCALIZACAO",
      "ENCEFALITE AGUDA DISSEMINADA"
    ],
    "Processo Neoplásico": [
      "HEMANGIOMA DE QUALQUER LOCALIZACAO"
    ],
    "Função Fisiológica": [
      "eliminações presentes"
    ]
  },
  "labels": {}
}