{
  "prontuario_id": 782,
  "text": "ÀS 15:30HRS: PACIENTE EM REPOUSO NO LEITO, CONTIDA AO LEITO, COM GRADES ELEVADAS PARA PROTEÇÃO, COM LUVAS EM MMSS, DE CREPE. CORADA E HIDRATADA, COM SNE, COM DIETA EM CURSO 75 ML/HR. NÃO VERBALIZA. SSVVS ESTAVEIS, BOM PADRÃO CARDIACO E RESPIRATORIO. EM USO DE FRALDAS, DIURESE E EVACUAÇÃO PRESENTES E NORMAIS. ENFª FLORENCE NIGHTINGALE, COREN XXXX. EPILEPSIA E SINDROMES EPILEPTICAS IDIOPATICAS DEFINIDAS POR SUA LOCALIZACAO FOCAL PARCIAL COM CRISES DE INICIO FOCAL. Às 20:00h: EM TEMPO: Ulcera por Pressão estagio I. TRAUMATISMO CEREBRAL DIFUSO. ÀS 15:15: ENCAMINHADO AO RAIO-X COM SUCESSO, SEM INTERCORRENCIA NO TRANSPORTE. TRAUMATISMOS MULTIPLOS NAO ESPECIFICADOS. ÀS 12:45: REALIZO PASSAGEM SVD COM PEQUENA QUANTIDADE DE DIURESE CONCENTRADA. ENF FLORENCE NIGHTINGALE. SEPTICEMIA NAO ESPECIFICADA. ÀS 12H: DESLIGADO FENTANIL CONFORME ORIENTAÇÃO DR VITAL BRASIL, INICIARA COM ANALGESIA DE HORARIO. ENF FLORENCE NIGHTINGALE, COREN XXXX. SEPTICEMIA NAO ESPECIFICADA.",
  "entities": {
    "Paciente ou Grupo com Deficiência": [
      "PACIENTE"
    ],
    "Dispositivo Médico": [
      "CREPE",
      "SNE",
      "FRALDAS",
      "SVD",
      "LUVAS EM MMSS"
    ],
    "Achado": [
      "CORADA",
      "HIDRATADA",
      "EVACUAÇÃO",
      "PRESENTES",
      "NORMAIS",
      "REPOUSO NO LEITO",
      "CONTIDA AO LEITO",
      "SSVVS ESTAVEIS"
    ],
    "Abreviação": [
      "SNE",
      "ML/HR",
      "ENFª",
      "SVD",
      "ENF",
      "LUVAS EM MMSS",
      "SSVVS ESTAVEIS"
    ],
    "Procedimento Terapêutico ou Preventivo": [
      "SNE",
      "SVD",
      "ANALGESIA",
      "REPOUSO NO LEITO",
      "CONTIDA AO LEITO",
      "GRADES ELEVADAS PARA PROTEÇÃO",
      "LUVAS EM MMSS",
      "DIETA EM CURSO"
    ],
    "Conceito Funcional": [
      "USO"
    ],
    "Objeto Manufaturado": [
      "FRALDAS"
    ],
    "Função Fisiológica": [
      "DIURESE",
      "EVACUAÇÃO",
      "DIURESE CONCENTRADA"
    ],
    "Procedimento Diagnóstico": [
      "RAIO-X"
    ],
    "Sinal ou Sintoma": [
      "INTERCORRENCIA"
    ],
    "Substância Química Orgânica": [
      "FENTANIL"
    ],
    "Substância Farmacológica": [
      "FENTANIL"
    ],
    "Conceito Qualitativo": [
      "BOM PADRÃO",
      "PEQUENA QUANTIDADE"
    ],
    "Doença ou Síndrome": [
      "EPILEPSIA E SINDROMES EPILEPTICAS IDIOPATICAS",
      "Ulcera por Pressão",
      "SEPTICEMIA NAO ESPECIFICADA"
    ],
    "Lesão ou Envenenamento": [
      "TRAUMATISMO CEREBRAL DIFUSO",
      "TRAUMATISMOS MULTIPLOS NAO ESPECIFICADOS"
    ]
  },
  "labels": {}
}