{
  "prontuario_id": 456,
  "text": "Cliente em glasgow 7, pupilas iso / foto +, traqueostomizado com cânula de metal, respiração espontânea em aa com auxilio de oxigenoterapia em nevoa umida á 4 L/min, eupneico, face corada, mucosa oral hidratada, boa perfusão periferica, no leito com cabeceira elevada á 45°. Mantem com monitorização de multiparametros, ECG, PNI, SpO2, SNE aberta com dietoterapia em curso BI á 75 ml/hr, cateter venoso central duplo-lumen em subclavia ESQ com infusão de insulina BI com vazão conforme valor glicemico, srt em curso gravitacional. Apresenta ausculta cardiaca ritmica e normofonetica, ausculta pulmonar MV + com roncos esparsos, abdomen flacido e RHA +, edemas em MMSS e II cacifo II/III, UP em região sacra-coccigeana estagio III/IV, com placa de necrose. Faz uso de uropen com debito diuretico ++ de coloração amarelo claro, eliminação fecal presente +++ de aspecto pastoso. segue cuidados em precaução de contato por MRSA + Acinetobacter baumannii. Às 22:24h: Paciente com medicação Staficilin prescrita, porém com ficha de solicitação vencida, comunico plantão da ortopedia.",
  "entities": {
    "Paciente ou Grupo com Deficiência": [
      "Cliente",
      "Paciente"
    ],
    "Procedimento Terapêutico ou Preventivo": [
      "traqueostomizado",
      "oxigenoterapia",
      "infusão",
      "nevoa umida",
      "leito com cabeceira elevada á 45°",
      "SNE aberta",
      "com dietoterapia",
      "cateter venoso central duplo-lumen",
      "srt em curso gravitacional",
      "precaução de contato"
    ],
    "Achado": [
      "traqueostomizado",
      "eupneico",
      "ritmica",
      "normofonetica",
      "pupilas iso / foto",
      "respiração espontânea",
      "face corada",
      "mucosa oral hidratada",
      "boa perfusão periferica",
      "SNE aberta",
      "MV +",
      "RHA +",
      "debito diuretico ++",
      "coloração amarelo claro",
      "eliminação fecal presente"
    ],
    "Abreviação": [
      "ECG",
      "PNI",
      "SpO2",
      "BI",
      "MMSS",
      "UP",
      "MRSA",
      "pupilas iso / foto",
      "SNE aberta",
      "subclavia ESQ",
      "srt em curso gravitacional",
      "MV +",
      "RHA +",
      "debito diuretico ++"
    ],
    "Procedimento Diagnóstico": [
      "ECG",
      "PNI",
      "monitorização de multiparametros",
      "ausculta cardiaca",
      "ausculta pulmonar"
    ],
    "Dispositivo Médico": [
      "BI",
      "uropen",
      "cânula de metal",
      "SNE aberta",
      "cateter venoso central duplo-lumen"
    ],
    "Substância Farmacológica": [
      "insulina",
      "Staficilin",
      "nevoa umida"
    ],
    "Localização ou Região Corporal": [
      "abdomen",
      "MMSS",
      "região sacra-coccigeana"
    ],
    "Sinal ou Sintoma": [
      "edemas",
      "roncos esparsos",
      "placa de necrose",
      "aspecto pastoso"
    ],
    "Função Patológica": [
      "edemas"
    ],
    "Doença ou Síndrome": [
      "UP"
    ],
    "Atividade de Assistência à Saúde": [
      "cuidados",
      "plantão"
    ],
    "Bactéria": [
      "MRSA",
      "Acinetobacter baumannii"
    ],
    "Antibiótico": [
      "Staficilin"
    ],
    "Organização Relacionada à Saúde": [
      "ortopedia"
    ],
    "Conceito Quantitativo": [
      "4 L/min",
      "75 ml/hr"
    ],
    "Parte do Corpo, Órgão ou Componente Orgânico": [
      "subclavia ESQ"
    ],
    "Conceito Qualitativo": [
      "cacifo II/III",
      "estagio III/IV"
    ]
  },
  "labels": {}
}