{
  "prontuario_id": 189,
  "text": "Às 08:30, 28-09-2007: Abertura ocular espontânea, púpilas isocóricas e fotorreagentes. Não contactua. Grande quantidade de secreção de VAS com aspiração contínua. Responsivo a estímulos dolorosos e aspirativos. SNG aberta com débito bilioso em média quantidade. INTOXICACAO POR OUTRAS DROGAS MEDICAMENTOS E SUBSTANCIAS BIOLOGICAS E AS NAO ESPECIFICADAS. Paciente aguardando procedimento cirúrgico em joelho E. Refere ser hipertensa e faz tratamento com captopril (SIC). Consciente, orientada, verbalizando. COXARTROSE ARTROSE DO QUADRIL. Às 4h30: PO Bypass: Comunicativo, orientado, mantendo repouso no leito, aceitando dieta oferecida (sic), mantendo curativo limpo e seco em MID e curativo com secreção sanguinolenta em pé direito, com dor de pouca intensidade, mantendo membro elevado; perfus. TROMBOFLEBITE MIGRATORIA. ÀS 15:00: PACIENTE LÚCIDO, ORIENTADO, COMUNICATIVO, MANTEM COLAR CERVICAL, CURATIVO COM ASPECTO LIMPO E SECO, MOBILIZA OS 4 MEMBROS, ACEITA BEM A DIETA, NEGA QUEIXAS ALGICAS, SEGUE SOB CUIDADOS DE ENFERMAGEM. TRAUMATISMOS MULTIPLOS NAO ESPECIFICADOS. Afebril, normotenso, em ventilação mecânica, PCV, FIO2 90%, PEEP = 20 cm h2o; PVC = acima de 40 cmh2o; PIA = 28 cmh2o; pupilas com discreta anisocoria D > E; períodos de dessaturação; curativo nasal seco e limpo; recebendo por acesso venoso central a direi. ABDOME AGUDO.",
  "entities": {
    "Conceito Qualitativo": [
      "dolorosos",
      "aspirativos",
      "Grande quantidade",
      "média quantidade"
    ],
    "Paciente ou Grupo com Deficiência": [
      "Paciente",
      "PACIENTE"
    ],
    "Doença ou Síndrome": [
      "hipertensa",
      "COXARTROSE ARTROSE DO QUADRIL",
      "TROMBOFLEBITE MIGRATORIA"
    ],
    "Procedimento Terapêutico ou Preventivo": [
      "tratamento",
      "Bypass",
      "curativo",
      "CURATIVO",
      "PCV",
      "FIO2",
      "PEEP",
      "PVC",
      "aspiração contínua",
      "SNG aberta",
      "procedimento cirúrgico",
      "repouso no leito",
      "membro elevado",
      "MANTEM COLAR CERVICAL",
      "MOBILIZA OS 4 MEMBROS",
      "ventilação mecânica",
      "acesso venoso central"
    ],
    "Aminoácido, Peptídeo ou Proteína": [
      "captopril"
    ],
    "Substância Farmacológica": [
      "captopril"
    ],
    "Achado": [
      "Consciente",
      "orientada",
      "verbalizando",
      "Comunicativo",
      "orientado",
      "limpo",
      "seco",
      "LÚCIDO",
      "ORIENTADO",
      "COMUNICATIVO",
      "LIMPO",
      "SECO",
      "Afebril",
      "normotenso",
      "Abertura ocular espontânea",
      "púpilas isocóricas e fotorreagentes",
      "Responsivo a estímulos",
      "SNG aberta",
      "repouso no leito",
      "aceitando dieta",
      "MOBILIZA OS 4 MEMBROS",
      "ACEITA BEM A DIETA"
    ],
    "Abreviação": [
      "PO",
      "MID",
      "PCV",
      "FIO2",
      "PEEP",
      "PVC",
      "PIA",
      "secreção de VAS",
      "SNG aberta",
      "joelho E",
      "D &gt; E"
    ],
    "Conceito Temporal": [
      "PO"
    ],
    "Dispositivo Médico": [
      "curativo",
      "CURATIVO",
      "SNG aberta",
      "acesso venoso central"
    ],
    "Localização ou Região Corporal": [
      "MID"
    ],
    "Negação": [
      "Afebril"
    ],
    "Conceito Quantitativo": [
      "90%",
      "20 cm h2o",
      "acima de 40 cmh2o",
      "28 cmh2o"
    ],
    "Parte do Corpo, Órgão ou Componente Orgânico": [
      "pupilas",
      "nasal",
      "joelho E",
      "pé direito"
    ],
    "Substância Corporal": [
      "secreção de VAS",
      "débito bilioso",
      "secreção sanguinolenta"
    ],
    "Sinal ou Sintoma": [
      "débito bilioso",
      "dor de pouca intensidade",
      "QUEIXAS ALGICAS",
      "discreta anisocoria"
    ],
    "Lesão ou Envenenamento": [
      "INTOXICACAO POR OUTRAS DROGAS MEDICAMENTOS E SUBSTANCIAS BIOLOGICAS",
      "TRAUMATISMOS MULTIPLOS"
    ],
    "Atividade de Assistência à Saúde": [
      "CUIDADOS DE ENFERMAGEM"
    ],
    "Conceito Espacial": [
      "D &gt; E"
    ]
  },
  "labels": {}
}