{
  "prontuario_id": 491,
  "text": "Às 18:00: CORADA, ALERTA, AFEBRIL, COMUNICATIVA, EM REPOUSO NO LEITO, ACEITANDO BEM DIETA VIA ORAL, AVP EM MSD SALINIZADO, SINAIS VITAIS ESTAVÉIS, NÃO REFERIU ALGIA NO MOMENTO, ELIMINAÇÕES FISIOLOGICAS PRESENTES E ESPONTANEAS, SEGUE SOB CUIDADOS. TRAUMATISMO DE MEDULA ESPINHAL NIVEL NAO ESPECIFICADO. Às 12:05: LUCIDO, ORIENTADO, COMUNICATIVO, EUPNÉICO, AFEBRIL, SEM QUEIXAS ÁLGICAS, ACEITANDO DIETA OFERECIDA. APRESENTA CURATIVO EM OMBRO DIR DE ASPECTO SECO EXTERNAMENTE E CURATIVO EM MSE DE ASPECTO SECO EXTERNAMENTE. MANTÉM ACESSO VENOSO EM MSD SALINIZADO. TRAUMATISMOS MULTIPLOS NAO ESPECIFICADOS. Às 16:00: Paciente agitado, confuso, deambulando, agrediu a esposa e ameaça agredir a equipe de enfermagem, administrada medicação prescrita, porém a agitação e a agressividade não diminuiram. Contato com Dr Vital Brasil, que orientou chamar plantão da psiquiatria, tent.  INSUFICIENCIA RENAL CRONICA.",
  "entities": {
    "Achado": [
      "CORADA",
      "ALERTA",
      "AFEBRIL",
      "COMUNICATIVA",
      "SALINIZADO",
      "PRESENTES",
      "ESPONTANEAS",
      "LUCIDO",
      "ORIENTADO",
      "COMUNICATIVO",
      "EUPNÉICO",
      "agitado",
      "deambulando",
      "REPOUSO NO LEITO",
      "ACEITANDO BEM DIETA VIA ORAL",
      "SINAIS VITAIS ESTAVÉIS",
      "ACEITANDO DIETA",
      "ASPECTO SECO"
    ],
    "Negação": [
      "AFEBRIL"
    ],
    "Dispositivo Médico": [
      "AVP",
      "CURATIVO",
      "ACESSO VENOSO"
    ],
    "Procedimento Terapêutico ou Preventivo": [
      "AVP",
      "SALINIZADO",
      "CURATIVO",
      "REPOUSO NO LEITO",
      "ACESSO VENOSO"
    ],
    "Abreviação": [
      "AVP",
      "MSD",
      "MSE",
      "Dr",
      "OMBRO DIR"
    ],
    "Localização ou Região Corporal": [
      "MSD",
      "MSE"
    ],
    "Sinal ou Sintoma": [
      "ALGIA",
      "confuso",
      "agitação",
      "agressividade",
      "QUEIXAS ÁLGICAS"
    ],
    "Atividade de Assistência à Saúde": [
      "CUIDADOS",
      "administrada"
    ],
    "Conceito Espacial": [
      "EXTERNAMENTE"
    ],
    "Paciente ou Grupo com Deficiência": [
      "Paciente"
    ],
    "Função Fisiológica": [
      "ELIMINAÇÕES FISIOLOGICAS"
    ],
    "Lesão ou Envenenamento": [
      "TRAUMATISMO DE MEDULA ESPINHAL",
      "TRAUMATISMOS MULTIPLOS"
    ],
    "Parte do Corpo, Órgão ou Componente Orgânico": [
      "OMBRO DIR"
    ],
    "Organização Relacionada à Saúde": [
      "equipe de enfermagem",
      "plantão da psiquiatria"
    ],
    "Grupo Profissional ou Ocupacional": [
      "equipe de enfermagem"
    ],
    "Doença ou Síndrome": [
      "INSUFICIENCIA RENAL CRONICA"
    ]
  },
  "labels": {}
}