{
  "prontuario_id": 741,
  "text": "Púpilas isocóricas e fotorreagentes. Responsiva a estímulos dolorosos e aspirativos. Abertura ocular espontânea, obedece a comandos verbais simples. Traqueostomizado, em ventilação mecânica PCV, PI 24, Peep 5, FiO2 43%. Hemodinamicamente estável, normocá. SINDROME DE GUILLAIN BARRE. Em 08/10/2006, 08:45 HORAS: EM PRIMEIRO PO DE RESSECÇÃO DE TU CEREBRAL, APRESENTA-SE ACORDADA, ATENDENDO AOS COMANDOS VERBAIS SIMPLES, COM PERÍODOS DE AGITAÇÃO INTENSA, CHOROSA. PRESENÇA DE EDEMA PERIPALPEBRAL BILATERAL. RESPIRAÇÃO ESPONTÂNEA EM AR AMBIENTE. HIDROCEFALIA. Às 15:55HRS: SEGUE CONSCIENTE, ORIENTADO, COMUNICATIVO. EUPNEICO COM SUPORTE DE O2 SOB NEVOA UMIDA, AFEBRIL, NORMOTENSO, NORMOCARDICO. ACEITANDO BEM A DIETA VO. APRESENTA HIPEREMIA MODERADA GENERALIZADA. REFERE CEFALEIA. MANTEM REPOUSO NO LEITO. ELIMINAÇÕES. FRATURA DE COSTELA. Às 13:00: Permanece sonolento, com abertura ocular espontânea, pupilas isocóricas e fotorreagentes, responsivo a estímulos aspirativos e dolorosos, afebril, corado, traqueostomizado com suporte de névoa úmida contínua saturando a 98%. Apresenta média quantid. FRATURA DA DIAFISE DO FEMUR.",
  "entities": {
    "Parte do Corpo, Órgão ou Componente Orgânico": [
      "Púpilas",
      "pupilas"
    ],
    "Achado": [
      "isocóricas",
      "fotorreagentes",
      "Traqueostomizado",
      "normocá",
      "ACORDADA",
      "CHOROSA",
      "CONSCIENTE",
      "ORIENTADO",
      "COMUNICATIVO",
      "EUPNEICO",
      "AFEBRIL",
      "NORMOTENSO",
      "NORMOCARDICO",
      "ELIMINAÇÕES",
      "afebril",
      "corado",
      "traqueostomizado",
      "Responsiva a estímulos dolorosos e aspirativos",
      "Abertura ocular espontânea",
      "obedece a comandos verbais simples",
      "Hemodinamicamente estável",
      "ATENDENDO AOS COMANDOS VERBAIS SIMPLES",
      "RESPIRAÇÃO ESPONTÂNEA EM AR AMBIENTE",
      "ACEITANDO BEM A DIETA VO",
      "REPOUSO NO LEITO",
      "abertura ocular espontânea",
      "responsivo a estímulos aspirativos e dolorosos"
    ],
    "Procedimento Terapêutico ou Preventivo": [
      "Traqueostomizado",
      "PCV",
      "PI",
      "Peep",
      "FiO2",
      "traqueostomizado",
      "ventilação mecânica",
      "RESSECÇÃO DE TU CEREBRAL",
      "SUPORTE DE O2 SOB NEVOA UMIDA",
      "REPOUSO NO LEITO",
      "suporte de névoa úmida contínua"
    ],
    "Abreviação": [
      "PCV",
      "PI",
      "Peep",
      "FiO2",
      "normocá",
      "PO",
      "RESSECÇÃO DE TU CEREBRAL",
      "ACEITANDO BEM A DIETA VO"
    ],
    "Conceito Quantitativo": [
      "24",
      "5",
      "43%",
      "98%"
    ],
    "Conceito Temporal": [
      "PO"
    ],
    "Doença ou Síndrome": [
      "HIDROCEFALIA",
      "SINDROME DE GUILLAIN BARRE"
    ],
    "Negação": [
      "AFEBRIL",
      "afebril"
    ],
    "Sinal ou Sintoma": [
      "CEFALEIA",
      "sonolento",
      "PERÍODOS DE AGITAÇÃO INTENSA",
      "EDEMA PERIPALPEBRAL BILATERAL",
      "HIPEREMIA MODERADA GENERALIZADA"
    ],
    "Função Fisiológica": [
      "ELIMINAÇÕES"
    ],
    "Lesão ou Envenenamento": [
      "FRATURA DE COSTELA",
      "FRATURA DA DIAFISE DO FEMUR"
    ],
    "Conceito Qualitativo": [
      "média quantid"
    ]
  },
  "labels": {}
}