{
  "prontuario_id": 732,
  "text": "Às 22:00H: CLIENTE PROVENIENTE DO PS. CONSCIENTE, VERBALIZANDO, EUPNEICA EM AR AMBIENTE, REFERE DOR EM HEMITÓRAX ESQ, COM AUMENTO DE INTENSIDADE AO INSPIRAR. # DERRAME PLEURAL ESQ. # ACOMPANHADO PELA PNEUMOLOGIA. Às 15:40h: Paciente consciente, comunicativo, em repouso no leito, AVP em MSE, com curativo oclusivo em face, apresentando secreção sanguinolenta. Sem queixas algicas. Paciente ancioso por alta. Às 16:30hs: Encaminhado para arteriografia na companhia da enfermeira e auxiliar, monitorizado e em Vm, VCV com VC: 450 ml, PEEP: 5, FiO2: 40%, sat: 98%, AVCSD com propofol a 10 ml/h e dopamina a 10 ml/h, entrego nas mãos da Enf a liberação assinada pela familia e pedido liberado da arterio. Às 12:24 hs: Abertura ocular espontânea, traqueostomizado, ar ambiente, em jejum para cirurgia, gastrostomia permeável, úlcera de pressão região sacra, bom aspecto, sem intercorrência durante o periodo, mantem precaução de contato.    ",
  "entities": {
    "Paciente ou Grupo com Deficiência": [
      "CLIENTE",
      "Paciente"
    ],
    "Organização Relacionada à Saúde": [
      "PS",
      "PNEUMOLOGIA"
    ],
    "Abreviação": [
      "PS",
      "AVP",
      "MSE",
      "Vm",
      "VCV",
      "VC",
      "PEEP",
      "FiO2",
      "sat",
      "AVCSD",
      "Enf",
      "arterio",
      "HEMITÓRAX ESQ",
      "DERRAME PLEURAL ESQ"
    ],
    "Achado": [
      "CONSCIENTE",
      "VERBALIZANDO",
      "consciente",
      "comunicativo",
      "traqueostomizado",
      "jejum",
      "EUPNEICA EM AR AMBIENTE",
      "repouso no leito",
      "Abertura ocular espontânea",
      "gastrostomia permeável",
      "bom aspecto"
    ],
    "Sinal ou Sintoma": [
      "DOR",
      "ancioso",
      "AUMENTO DE INTENSIDADE AO INSPIRAR",
      "queixas algicas"
    ],
    "Dispositivo Médico": [
      "AVP",
      "curativo oclusivo"
    ],
    "Procedimento Terapêutico ou Preventivo": [
      "AVP",
      "Vm",
      "VCV",
      "PEEP",
      "FiO2",
      "AVCSD",
      "traqueostomizado",
      "jejum",
      "cirurgia",
      "repouso no leito",
      "curativo oclusivo",
      "precaução de contato"
    ],
    "Localização ou Região Corporal": [
      "MSE",
      "face",
      "HEMITÓRAX ESQ",
      "região sacra"
    ],
    "Negação": [
      "Sem"
    ],
    "Atividade de Assistência à Saúde": [
      "alta"
    ],
    "Procedimento Diagnóstico": [
      "arteriografia",
      "monitorizado",
      "arterio"
    ],
    "Grupo Profissional ou Ocupacional": [
      "enfermeira",
      "auxiliar",
      "Enf"
    ],
    "Conceito Quantitativo": [
      "5",
      "40%",
      "98%",
      "450 ml",
      "10 ml/h"
    ],
    "Substância Farmacológica": [
      "propofol",
      "dopamina"
    ],
    "Substância Química Orgânica": [
      "propofol",
      "dopamina"
    ],
    "Parte do Corpo, Órgão ou Componente Orgânico": [
      "mãos"
    ],
    "Grupo Familiar": [
      "familia"
    ],
    "Doença ou Síndrome": [
      "DERRAME PLEURAL ESQ",
      "úlcera de pressão"
    ]
  },
  "labels": {}
}