{
  "prontuario_id": 972,
  "text": "Às 09:33: 2º DI Hx vítima de atropelamento com FCC em região frontal. Sonolento, choroso a tentativa de acorda-lo, corado. Face escoriações, hematoma em região ocular E, curativo limpo e seco em região frontal à D. Respiração espontânea em ar ambiente, CPP livres, BCRNF. Acessos venosos periféricos em antebraços D e E salinizado. Abdomen plano, RHA +. MMII aquecidos, pulsos pediosos palpáveis, perfusão periférica < 3 s. MIE escoriações. Diurese espontânea presente, evacuação ausente. No período em repouso no leito. Aguardando internamento em UI. Segue sob os cuidados da equipe multidisciplinar. Enfº Florence Nightingale, COREN XXXX. OUTROS TRAUMATISMOS INTRACRANIANOS. Às 15:30 h: Encaminhado para análise 02 hemoculturas + aspirado traqueal + cultura de líquor + urocultura + swab retal. Enfª Florence Nightingale. EXAME GERAL E INVESTIGACAO DE PESSOAS SEM QUEIXAS OU DIAGNOSTICO RELATADO. Às 03:18: paciente referindo forte algia, recusou sair do leito para realizar RX por motivo de dor intensa, apos contato telefonico com DR Vital Brasil orientou não realizar RX. Florence Nightingale, XXXX. DOR CRONICA INTRATAVEL. Às 15:30 H: COLOCADA EM OXIGENIO POR TUBO \"T\" PELA FISIOTERAPEUTA MARIA, SE MANTEM RESPONSIVA E COLABORATIVA, COM SATURAÇÃO SATISFATORIA, EXTUBADA AS 16:30 H PELA MESMA FISIOTERAPUTA. SEGUE COM PERIODOS DE CONFUSÃO EM MASCARA DE OXIGENIO A 3 L/M, SPO2 98 %, EM OBSERVAÇÃO. ENF FLORENCE NIGHTINGALE, COREN XX XXXX. EXAME GERAL E INVESTIGACAO DE PESSOAS SEM QUEIXAS OU DIAGNOSTICO RELATADO.",
  "entities": {
    "Paciente ou Grupo com Deficiência": [
      "vítima",
      "paciente"
    ],
    "Lesão ou Envenenamento": [
      "atropelamento",
      "FCC",
      "Face escoriações",
      "MIE escoriações",
      "TRAUMATISMOS INTRACRANIANOS"
    ],
    "Abreviação": [
      "FCC",
      "BCRNF",
      "UI",
      "Enfº",
      "Enfª",
      "RX",
      "SPO2",
      "ENF",
      "região ocular E",
      "região frontal à D",
      "CPP livres",
      "antebraços D e E",
      "RHA +",
      "3 s",
      "MIE escoriações",
      "realizar RX"
    ],
    "Sinal ou Sintoma": [
      "Sonolento",
      "QUEIXAS",
      "forte algia",
      "dor intensa",
      "PERIODOS DE CONFUSÃO"
    ],
    "Achado": [
      "choroso",
      "corado",
      "limpo",
      "seco",
      "BCRNF",
      "aquecidos",
      "RESPONSIVA",
      "COLABORATIVA",
      "Respiração espontânea em ar ambiente",
      "CPP livres",
      "RHA +",
      "pulsos pediosos palpáveis",
      "Diurese espontânea presente",
      "repouso no leito",
      "SATURAÇÃO SATISFATORIA"
    ],
    "Função Patológica": [
      "hematoma"
    ],
    "Procedimento Terapêutico ou Preventivo": [
      "curativo",
      "salinizado",
      "EXTUBADA",
      "Acessos venosos periféricos",
      "repouso no leito",
      "OXIGENIO POR",
      "TUBO \"T\"",
      "MASCARA DE OXIGENIO"
    ],
    "Dispositivo Médico": [
      "curativo",
      "Acessos venosos periféricos",
      "TUBO \"T\""
    ],
    "Localização ou Região Corporal": [
      "Abdomen",
      "região frontal",
      "região ocular E",
      "região frontal à D"
    ],
    "Função Fisiológica": [
      "evacuação",
      "Diurese espontânea presente"
    ],
    "Negação": [
      "ausente",
      "SEM",
      "não"
    ],
    "Organização Relacionada à Saúde": [
      "UI"
    ],
    "Grupo Profissional ou Ocupacional": [
      "Enfº",
      "Enfª",
      "FISIOTERAPEUTA",
      "FISIOTERAPUTA",
      "ENF"
    ],
    "Conceito Quantitativo": [
      "02",
      "3 L/M",
      "98 %"
    ],
    "Procedimento Laboratorial": [
      "hemoculturas",
      "urocultura",
      "cultura de líquor",
      "swab retal"
    ],
    "Objeto Manufaturado": [
      "leito"
    ],
    "Procedimento Diagnóstico": [
      "RX"
    ],
    "Atividade de Assistência à Saúde": [
      "OBSERVAÇÃO",
      "cuidados da equipe multidisciplinar"
    ],
    "Parte do Corpo, Órgão ou Componente Orgânico": [
      "antebraços D e E"
    ],
    "Atributo Clínico": [
      "perfusão periférica"
    ],
    "Substância Corporal": [
      "aspirado traqueal"
    ],
    "Doença ou Síndrome": [
      "DOR CRONICA INTRATAVEL"
    ]
  },
  "labels": {}
}