{
  "prontuario_id": 51,
  "text": "17:41 CLIENTE REFERE DOR MODERADA EM MID, CONSCIENTE, COMUNICATIVA, EUPNEICA, REPOUSO NO LEITO, ACEITANDO BEM A DIETA, ACESSO PERIFÉRICO EM MSE SALINIZADO, CTVO LIMPO E SECO EM MID + FIXADOR EXTERNO, APRESENTANDO MELHORA NO EDEMA, PERFUSÃO DSITAL PRESERVADA, ELIMINAÇÕES PRESENTES. ENFª FLORENCE NIGHTINGALE XXXX. FRATURA DO PE EXCETO DO TORNOZELO. 8:00hrs Cliente em Glasgow 14, pupilas iso / foto +, traqueostomizado, respiração espontânea em aa com auxilio de oxigenotarapia em nevoa umida á 4 l/min, eupneico, face corada, mucosa oral hidratata, boa perfusão periferica, no leeito com cabeceira elevada á 45°. Mantem com monitorização de multiparametros ECG, PNI, SpO2, com SNE fechada e jejum até 2° ordem aguardando provavel procedimento de traqueoscopia, acesso venoso periferico em MSE com SRT em curso gravitacuional. Apresenta ausculta cardiaca ritmica e normofonetica, ausculta pulmonar MV + com roncos difusos, abdopmem globoso e flacido com RHA +, edemas em MMSS cacifo I/II. Faz uso de uropem + urofix com debito diuretico ++ de coloração amarelo-claro, eliminalção fecal ausente. Segue cuidados intensivos de enfermagem em precaução de contato por VRE. Enf° FLORENCE NIGHTINGALE, Coren XXXX. OUTRAS HEMORRAGIAS INTRACEREBRAIS.",
  "entities": {
    "Paciente ou Grupo com Deficiência": [
      "CLIENTE",
      "Cliente"
    ],
    "Localização ou Região Corporal": [
      "MID",
      "MSE",
      "abdopmem",
      "MMSS"
    ],
    "Abreviação": [
      "MID",
      "MSE",
      "CTVO",
      "ENFª",
      "iso",
      "ECG",
      "PNI",
      "SpO2",
      "MMSS",
      "Enf°",
      "foto +",
      "respiração espontânea em aa",
      "SNE fechada",
      "SRT em curso gravitacuional",
      "MV +",
      "RHA +",
      "debito diuretico ++"
    ],
    "Achado": [
      "CONSCIENTE",
      "COMUNICATIVA",
      "EUPNEICA",
      "SALINIZADO",
      "LIMPO",
      "SECO",
      "iso",
      "traqueostomizado",
      "eupneico",
      "flacido",
      "REPOUSO NO LEITO",
      "ACEITANDO BEM A DIETA",
      "MELHORA NO EDEMA",
      "PERFUSÃO DSITAL PRESERVADA",
      "ELIMINAÇÕES PRESENTES",
      "foto +",
      "respiração espontânea em aa",
      "face corada",
      "mucosa oral hidratata",
      "boa perfusão periferica",
      "ausculta cardiaca ritmica e normofonetica",
      "MV +",
      "RHA +",
      "cacifo I/II",
      "debito diuretico ++",
      "coloração amarelo-claro"
    ],
    "Procedimento Terapêutico ou Preventivo": [
      "SALINIZADO",
      "CTVO",
      "traqueostomizado",
      "jejum",
      "traqueoscopia",
      "REPOUSO NO LEITO",
      "ACESSO PERIFÉRICO",
      "FIXADOR EXTERNO",
      "oxigenotarapia em",
      "nevoa umida",
      "cabeceira elevada á 45°",
      "SNE fechada",
      "acesso venoso periferico",
      "SRT em curso gravitacuional",
      "precaução de contato"
    ],
    "Dispositivo Médico": [
      "CTVO",
      "uropem",
      "urofix",
      "ACESSO PERIFÉRICO",
      "FIXADOR EXTERNO",
      "acesso venoso periferico"
    ],
    "Grupo Profissional ou Ocupacional": [
      "ENFª",
      "Enf°"
    ],
    "Parte do Corpo, Órgão ou Componente Orgânico": [
      "pupilas"
    ],
    "Objeto Manufaturado": [
      "leeito"
    ],
    "Procedimento Diagnóstico": [
      "ECG",
      "PNI",
      "monitorização de multiparametros",
      "ausculta pulmonar"
    ],
    "Sinal ou Sintoma": [
      "globoso",
      "edemas",
      "DOR MODERADA",
      "Glasgow 14",
      "roncos difusos"
    ],
    "Função Patológica": [
      "edemas"
    ],
    "Negação": [
      "ausente"
    ],
    "Função Fisiológica": [
      "ELIMINAÇÕES PRESENTES",
      "eliminalção fecal"
    ],
    "Lesão ou Envenenamento": [
      "FRATURA DO PE"
    ],
    "Conceito Quantitativo": [
      "4 l/min"
    ],
    "Atividade de Assistência à Saúde": [
      "cuidados intensivos de enfermagem"
    ],
    "Doença ou Síndrome": [
      "HEMORRAGIAS INTRACEREBRAIS"
    ]
  },
  "labels": {}
}