{
  "prontuario_id": 17,
  "text": "Às 23:30, 26/12/10: REALIZEI PUNÇÃO PERIFÉRICA COM CATETER Nº 20 EM REGIÃO DE TÓRAX À DIREITA, PROCEDIMENTO REALIZADO SEM INTERCORRÊNCIAS. SOROMA DO ACESSO ANTERIOR. BRONCOPNEUMONIA NAO ESPECIFICADA. Às 05:30: Retornou do CC POI cx herniorrafia. Lucida, comunicativa, apresenta curativo abdominal pouco sanguinolento + dreno de suctor no local, com debito hematico, abdomem globoso, SVD debito efetivo, segue cuidados. HERNIA VENTRAL SEM OBSTRUCAO OU GANGRENA. Às 18:45 H - NOVO CONTATO COM DR VITAL BRASIL PNEUMO PARA INFORMAR SOBRE A REAÇÃO POSSIVELMENTE CAUSADA PELO AVALOX VO, PORÉM SEM SUCESSO, CELULAR NA CAIXA DE MENSAGENS, PASSO EM PLANTÃO. ENFA FLORENCE NIGHTINGALE, COREN XX XXXX. EXAME GERAL E INVESTIGACAO DE PESSOAS SEM QUEIXAS OU DIAGNOSTICO RELATADO. ÀS 18:00 HS: ENTRO EM CONTATO COM NUTRICIONISTA MARIA PARA SOLICITAR LIBERAÇÃO DE DIETA VIA SNE. PACIENTE RETIRA SONDA VARIAS VEZES. SEGUINDO ORIENTAÇÕES DA NUTRICIONISTA IRA COMEÇAR ESQUEMA DE SUPLEMENTAÇÃO AMANHA. ENF FLORENCE NIGHTINGALE - COREN XXXX. DESNUTRICAO PROTEICO CALORICA NAO ESPECIFICADA.",
  "entities": {
    "Procedimento Terapêutico ou Preventivo": [
      "PROCEDIMENTO",
      "cx",
      "herniorrafia",
      "curativo",
      "PUNÇÃO PERIFÉRICA",
      "dreno de suctor",
      "LIBERAÇÃO DE DIETA VIA SNE",
      "ESQUEMA DE SUPLEMENTAÇÃO"
    ],
    "Negação": [
      "SEM",
      "NAO ESPECIFICADA"
    ],
    "Sinal ou Sintoma": [
      "INTERCORRÊNCIAS",
      "GANGRENA",
      "QUEIXAS",
      "debito hematico",
      "abdomem globoso"
    ],
    "Organização Relacionada à Saúde": [
      "CC",
      "PLANTÃO"
    ],
    "Abreviação": [
      "CC",
      "POI",
      "cx",
      "DR",
      "PNEUMO",
      "ENFA",
      "ENF",
      "SVD debito efetivo",
      "AVALOX VO",
      "LIBERAÇÃO DE DIETA VIA SNE"
    ],
    "Conceito Temporal": [
      "POI"
    ],
    "Achado": [
      "Lucida",
      "comunicativa",
      "SVD debito efetivo"
    ],
    "Dispositivo Médico": [
      "curativo",
      "CATETER Nº 20",
      "dreno de suctor"
    ],
    "Localização ou Região Corporal": [
      "abdominal"
    ],
    "Função Patológica": [
      "OBSTRUCAO",
      "REAÇÃO"
    ],
    "Doença ou Síndrome": [
      "GANGRENA",
      "DESNUTRICAO PROTEICO CALORICA"
    ],
    "Grupo Profissional ou Ocupacional": [
      "PNEUMO",
      "ENFA",
      "NUTRICIONISTA",
      "ENF"
    ],
    "Paciente ou Grupo com Deficiência": [
      "PACIENTE"
    ],
    "Atividade de Assistência à Saúde": [
      "ORIENTAÇÕES",
      "segue cuidados"
    ],
    "Anormalidade Anatômica": [
      "HERNIA VENTRAL"
    ]
  },
  "labels": {}
}