{
  "prontuario_id": 564,
  "text": "Às 02:30 H: CLIENTE CONSCIENTE, EUPNEICO, AFEBRIL, REPOUSO, ORIENTADO. ACEITA DIETA OFERECIDA. MANTEM ACESSO PERIFERICO EM MSD SALINIZADO. ABDOMEM GLOBOSO E FLÁCIDO. APRESENTA CURATIVO  EM REGIÃO DE MIE ASPECTO SECO E LIMPO EXTERNAMENTE, SENDO TROCADO NO PERIODO. ELIMINAÇÕES NORMAIS. SEGUE EM OBSERVAÇÃO E CUIDADOS. ENFª FLORENCE NIGHTINGALE, COREN XXXX. ATEROSCLEROSE DAS ARTERIAS DAS EXTREMIDADES. ÀS 12:20 HR: Restrito no leito devido 1 Po de PTQ, estavel hemodinamicamente, refere bom sono e repouso, sem queixas algicas, aceitando a dieta oferecida. Pele integra e hidratada, perfusão periferica menor 3 seg. Pupilas Iso \\ Foto, escleras e conjuntivas normocoradas, boca higienizada. Respiração Toracica, amplitude superficial, CPP livres sem RA. BCRNF s\\ s. Abdome flacido, RHA +, indolor a palpação, curativo em região de quadril limpo, restirado Dreno de Suctor pelo Dr Vital Brasil. Cateter venoso em MSD com plano basico de hidratação, Cateter vesical de demora com diurese efetiva cor amarela citrina. Segue cuidados da Enfermagem. Enfº Florence Nightingale, Coren XX XXXX. EXAME GERAL E INVESTIGACAO DE PESSOAS SEM QUEIXAS OU DIAGNOSTICO RELATADO",
  "entities": {
    "Paciente ou Grupo com Deficiência": [
      "CLIENTE"
    ],
    "Achado": [
      "CONSCIENTE",
      "EUPNEICO",
      "AFEBRIL",
      "REPOUSO",
      "ORIENTADO",
      "SALINIZADO",
      "FLÁCIDO",
      "SECO",
      "LIMPO",
      "repouso",
      "integra",
      "hidratada",
      "Iso",
      "Foto",
      "livres",
      "flacido",
      "limpo",
      "ELIMINAÇÕES NORMAIS",
      "Restrito no leito",
      "estavel hemodinamicamente",
      "bom sono",
      "conjuntivas normocoradas",
      "boca higienizada",
      "RHA +",
      "diurese efetiva",
      "cor amarela citrina"
    ],
    "Negação": [
      "AFEBRIL",
      "sem",
      "s\\",
      "indolor",
      "SEM"
    ],
    "Procedimento Terapêutico ou Preventivo": [
      "REPOUSO",
      "SALINIZADO",
      "CURATIVO",
      "TROCADO",
      "PTQ",
      "repouso",
      "curativo",
      "ACESSO PERIFERICO",
      "Restrito no leito",
      "restirado Dreno de Suctor",
      "Cateter venoso",
      "plano basico de hidratação",
      "Cateter vesical de demora"
    ],
    "Localização ou Região Corporal": [
      "MSD",
      "ABDOMEM",
      "CPP",
      "Abdome",
      "REGIÃO DE MIE",
      "região de quadril"
    ],
    "Abreviação": [
      "MSD",
      "ENFª",
      "Po",
      "PTQ",
      "Iso",
      "Foto",
      "CPP",
      "RA",
      "Enfº",
      "REGIÃO DE MIE",
      "menor 3 seg",
      "RHA +"
    ],
    "Sinal ou Sintoma": [
      "GLOBOSO",
      "RA",
      "s",
      "QUEIXAS",
      "queixas algicas",
      "amplitude superficial"
    ],
    "Dispositivo Médico": [
      "CURATIVO",
      "curativo",
      "ACESSO PERIFERICO",
      "restirado Dreno de Suctor",
      "Cateter venoso",
      "Cateter vesical de demora"
    ],
    "Conceito Espacial": [
      "EXTERNAMENTE"
    ],
    "Atividade de Assistência à Saúde": [
      "OBSERVAÇÃO",
      "CUIDADOS",
      "INVESTIGACAO",
      "cuidados da Enfermagem"
    ],
    "Grupo Profissional ou Ocupacional": [
      "ENFª",
      "Enfº"
    ],
    "Conceito Temporal": [
      "Po"
    ],
    "Parte do Corpo, Órgão ou Componente Orgânico": [
      "Pele",
      "Pupilas",
      "escleras"
    ],
    "Procedimento Diagnóstico": [
      "palpação"
    ],
    "Função Fisiológica": [
      "ELIMINAÇÕES NORMAIS",
      "diurese efetiva"
    ],
    "Doença ou Síndrome": [
      "ATEROSCLEROSE DAS ARTERIAS DAS EXTREMIDADES"
    ],
    "Atributo Clínico": [
      "perfusão periferica"
    ]
  },
  "labels": {}
}