{
  "prontuario_id": 772,
  "text": "01:30HRS CLIENTE ACORDADA, ABERTURAS OCULARES BILATERAIS ESPONTÂNEAS E POUCO CONTACTUANTES, PUPILAS ANISOCORICAS D>E BRADIFOTORREAGENTES. TQT COM PRESENÇA DE SECREÇÃO TRAQUEOBRONQUICA ++ DE ASPECTO SERO-PURULENTA, REALIZADAS ASPIRAÇÃO EM VAS + VAI, RESPIRAÇÃO ESPONTÂNEA EM AA COM AUXILIO DE OXIGENOTERAPIA EM NÉVOA ÚMIDA Á 4 L/MIN, EUPNEICA, BOA PERFUSÃO PERIFERICA, EM REPOUSO SOBRE O LEITO COM CABECEIRA ELEVADA Á 45°. MANTEM SNE ABERTA COM DIETATERAPIA EM CURSO BI, ACESSO VENOSO PERIFERICO EM JUGULAR EXT ESQ COM SRT EM CURSO GRAVITACIONAL, CTVOS EM REGIÕES : LOMBAR + AFETADAS POR UP, AMBOS COM PRESENÇA DE EXUDATO +++, TODOS TROCADOS 2 VEZES DURANTE O PLANTÃO. FAZ USO SVD ABERTA COM PRESENÇA DE DÉBITO DIURÉTICO ++ DE COLORAÇÃO AMARELO-CLARO. SEGUE CUIDADOS DA ENFERMAGEM EM PRECAUÇÃO DE CONTATO. ENF° FLORENCE NIGHTINGALE, COREN XXXX. SEPTICEMIA POR STAPHYLOCOCCUS AUREUS. 18:50hs- Coletado 2 amostras de hemocultura + ponta de cateter central e enviado ao laboratório. Enfª FLORENCE NIGHTINGALE XXXX. OUTROS TIPOS ESPECIFICADOS DE DIABETES MELLITUS COM COMPLICACOES CIRCULATORIAS PERIFERICAS. 06:10h: Paciente apresentando rebaixamento de nível de consciencia, dados vitais inaferíveis, parada cárdio-respiratória, comunico plantão da Cx Geral + Vascular para confirmação de óbito. Enf FLORENCE NIGHTINGALE, EDEMA CEREBRAL.",
  "entities": {
    "Paciente ou Grupo com Deficiência": [
      "CLIENTE",
      "Paciente"
    ],
    "Achado": [
      "ACORDADA",
      "EUPNEICA",
      "ABERTURAS OCULARES BILATERAIS ESPONTÂNEAS",
      "RESPIRAÇÃO ESPONTÂNEA EM AA",
      "BOA PERFUSÃO PERIFERICA",
      "REPOUSO SOBRE O LEITO",
      "DÉBITO DIURÉTICO",
      "COLORAÇÃO AMARELO-CLARO"
    ],
    "Parte do Corpo, Órgão ou Componente Orgânico": [
      "PUPILAS",
      "VAS",
      "VAI",
      "JUGULAR EXT ESQ"
    ],
    "Procedimento Terapêutico ou Preventivo": [
      "TQT",
      "ASPIRAÇÃO",
      "CTVOS",
      "OXIGENOTERAPIA EM NÉVOA ÚMIDA",
      "REPOUSO SOBRE O LEITO",
      "CABECEIRA ELEVADA Á 45°",
      "SNE ABERTA",
      "ACESSO VENOSO PERIFERICO",
      "SRT EM CURSO GRAVITACIONAL",
      "SVD ABERTA",
      "PRECAUÇÃO DE CONTATO"
    ],
    "Abreviação": [
      "TQT",
      "VAS",
      "VAI",
      "BI",
      "CTVOS",
      "UP",
      "ENF°",
      "Enfª",
      "Enf",
      "RESPIRAÇÃO ESPONTÂNEA EM AA",
      "SNE ABERTA",
      "JUGULAR EXT ESQ",
      "SRT EM CURSO GRAVITACIONAL",
      "SVD ABERTA",
      "Cx Geral"
    ],
    "Dispositivo de Administração de Medicamento": [
      "BI"
    ],
    "Dispositivo Médico": [
      "CTVOS",
      "ACESSO VENOSO PERIFERICO",
      "ponta de cateter central"
    ],
    "Localização ou Região Corporal": [
      "LOMBAR"
    ],
    "Doença ou Síndrome": [
      "UP",
      "SEPTICEMIA POR STAPHYLOCOCCUS AUREUS",
      "DIABETES MELLITUS COM COMPLICACOES CIRCULATORIAS PERIFERICAS",
      "EDEMA CEREBRAL"
    ],
    "Substância Corporal": [
      "EXUDATO",
      "SECREÇÃO TRAQUEOBRONQUICA"
    ],
    "Organização Relacionada à Saúde": [
      "PLANTÃO",
      "laboratório"
    ],
    "Grupo Profissional ou Ocupacional": [
      "ENF°",
      "Enfª",
      "Vascular",
      "Enf",
      "Cx Geral"
    ],
    "Procedimento Laboratorial": [
      "hemocultura"
    ],
    "Função de Organismo": [
      "óbito"
    ],
    "Sinal ou Sintoma": [
      "POUCO CONTACTUANTES",
      "D&gt;E BRADIFOTORREAGENTES",
      "ASPECTO SERO-PURULENTA",
      "rebaixamento de nível de consciencia",
      "dados vitais inaferíveis"
    ],
    "Conceito Quantitativo": [
      "4 L/MIN"
    ],
    "Função Fisiológica": [
      "DÉBITO DIURÉTICO"
    ],
    "Atividade de Assistência à Saúde": [
      "CUIDADOS DA ENFERMAGEM"
    ]
  },
  "labels": {}
}