{
  "prontuario_id": 656,
  "text": "Paciente com IRC e DM, veio à emergência após episódio de hipoglicemia com queda ao solo. Apresentando dor lombar. Realizada TC de coluna lombossacra e Rx de arcos costais sem fraturas. Recebe alta com analgesia e orientação para evitar hipoglicemias. PACIENTE INTERNA PARA COMPLETAR ESTADIAMENTO E INICIAR TRATAMENTO DE LINFOMA HODGKIN. MEDULA ÓSSEA NEGATIVA E AUSÊNCIA DE DOENÇA ABAIXO DO DIAFRAGMA. COMPROMETIMENTO DE CADEIAS LINFONODAIS CERVICAIS BILATERALMENTE E AXILARES BILATERALMENTE, BEM COMO DE LINFONODOS MEDIASTINAIS E DERRAME PERICÁRDICO. EC IIB REALIZADA COLETA DE ESPERMA PARA CONGELAÇÃO ANTES DA QT. ECOCARDIO COM BOA FUNÇÃO SISTÓLICA. CINTILOGRAFIA COM GÁLIO EM PROCESSO DE CAPTAÇÃO - 29/06/07 PACIENTE RECEBE ALTA APÓS 1 DOSE DO PRIMEIRO CICLO DE ABVD EM 27/06/07, COM BOA TOLERÂNCIA. RECEBE ALTA COM AS DEVIDAS ORIENTAÇÕES. PRÓXIMA QT EM 11/06/07.",
  "entities": {
    "Paciente ou Grupo com Deficiência": [
      "Paciente",
      "PACIENTE"
    ],
    "Doença ou Síndrome": [
      "IRC",
      "DM",
      "DERRAME PERICÁRDICO"
    ],
    "Abreviação": [
      "IRC",
      "DM",
      "QT",
      "ECOCARDIO",
      "TC de coluna lombossacra",
      "Rx de arcos costais",
      "EC IIB",
      "CICLO DE ABVD"
    ],
    "Organização Relacionada à Saúde": [
      "emergência"
    ],
    "Sinal ou Sintoma": [
      "hipoglicemia",
      "dor lombar"
    ],
    "Atividade de Assistência à Saúde": [
      "alta",
      "orientação",
      "ALTA",
      "ORIENTAÇÕES"
    ],
    "Procedimento Terapêutico ou Preventivo": [
      "analgesia",
      "QT",
      "evitar hipoglicemias",
      "TRATAMENTO DE LINFOMA HODGKIN",
      "CICLO DE ABVD"
    ],
    "Procedimento Diagnóstico": [
      "ESTADIAMENTO",
      "ECOCARDIO",
      "TC de coluna lombossacra",
      "Rx de arcos costais",
      "CINTILOGRAFIA COM GÁLIO EM PROCESSO DE CAPTAÇÃO"
    ],
    "Negação": [
      "AUSÊNCIA"
    ],
    "Conceito Quantitativo": [
      "DOSE"
    ],
    "Lesão ou Envenenamento": [
      "queda ao solo"
    ],
    "Resultado Laboratorial ou de Teste": [
      "sem fraturas",
      "MEDULA ÓSSEA NEGATIVA",
      "BOA FUNÇÃO SISTÓLICA"
    ],
    "Processo Neoplásico": [
      "TRATAMENTO DE LINFOMA HODGKIN"
    ],
    "Localização ou Região Corporal": [
      "CERVICAIS BILATERALMENTE",
      "AXILARES BILATERALMENTE",
      "LINFONODOS MEDIASTINAIS"
    ],
    "Parte do Corpo, Órgão ou Componente Orgânico": [
      "LINFONODOS MEDIASTINAIS"
    ],
    "Procedimento Laboratorial": [
      "COLETA DE ESPERMA PARA CONGELAÇÃO"
    ],
    "Substância Farmacológica": [
      "CICLO DE ABVD"
    ],
    "Achado": [
      "BOA TOLERÂNCIA"
    ]
  },
  "labels": {}
}