{
  "prontuario_id": 85,
  "text": "Paciente com neurofibromatose com acometimento em hemiface D interna para realizar ritidoplastia e suspensão de face média à direita. O procedimento ocorreu sem intercorrências e a paciente recebe alta hospitlar com orientações e retorno ambulatorial. PACIENTE COM HAS E IRC EM HD INTERNA ELETIVAMENTE PARA REALIZAÇÃO DE ACTP + STENT EM ADA, SEGMENTO MÉDIO. PROCEDIMENTO REALIZADO SEM INTERCORRÊNCIAS, COM SUCESSO ANGIOGRÁFICO. VINHA EM USO DE TICLOPIDINA. RECEBE ALTA COM ORIENTAÇÃO DE: - RETORNO BREVE AO SEU MÉDICO ASSISTENTE, - MANTER USO DE: TICLOPIDINA 250 MG 12/12 H POR 30 DIAS, AAS 100 MG, SINVASTATINA 40 MG, PROCURAR A EMERGÊNCIA EM CASO DE INTERCORRÊNCIAS. G1, IG de 38 sem 4 dia(s), RN1 Parto Eutócico com episiotomia em 10/06/2007, 03:21 hs, APGAR 7/10, Masculino, 3230 Gr. Apresentou boa evolução puerperal com lóquios fisiológicos, mamas sem ingurgitamento e útero contraído abaixo da cicatriz umbilical. Paciente evolui com dor intensa na área da episio com edema local. Realizadas medidas de analgesia e solicitada eco TV para avaliação da área. Eco TV em 16/06/07: Bexiga urinária com conteúdo denso. Útero aumentado de volume, heterogêneo, com pequena quantidade de líquido na cavidade endometrial. Não se identifica líquido livre ou coleção líquida na pelve. Não se identifica coleção líquida na avaliação do períneo. Recebe alta em bom estado geral, afebril, orientada e medicada. EXAMES: - VDRL: não reag. ",
  "entities": {
    "Paciente ou Grupo com Deficiência": [
      "Paciente",
      "paciente",
      "PACIENTE"
    ],
    "Doença ou Síndrome": [
      "neurofibromatose",
      "HAS",
      "IRC"
    ],
    "Procedimento Terapêutico ou Preventivo": [
      "ritidoplastia",
      "suspensão",
      "procedimento",
      "HD",
      "ACTP",
      "STENT",
      "PROCEDIMENTO",
      "episiotomia",
      "medicada",
      "medidas de analgesia"
    ],
    "Negação": [
      "sem",
      "SEM",
      "Não",
      "afebril"
    ],
    "Sinal ou Sintoma": [
      "intercorrências",
      "INTERCORRÊNCIAS",
      "ingurgitamento",
      "CASO DE INTERCORRÊNCIAS",
      "dor intensa",
      "edema local",
      "líquido livre",
      "coleção líquida"
    ],
    "Atividade de Assistência à Saúde": [
      "orientações",
      "retorno",
      "ALTA",
      "ORIENTAÇÃO",
      "RETORNO",
      "alta",
      "orientada",
      "medicada",
      "alta hospitlar"
    ],
    "Organização Relacionada à Saúde": [
      "ambulatorial",
      "EMERGÊNCIA"
    ],
    "Abreviação": [
      "HAS",
      "IRC",
      "HD",
      "ACTP",
      "ADA",
      "AAS",
      "G1",
      "IG",
      "RN1",
      "hemiface D",
      "38 sem 4 dia",
      "área da episio",
      "eco TV",
      "Eco TV",
      "VDRL : não reag"
    ],
    "Dispositivo Médico": [
      "STENT"
    ],
    "Parte do Corpo, Órgão ou Componente Orgânico": [
      "ADA",
      "mamas",
      "períneo"
    ],
    "Substância Química Orgânica": [
      "TICLOPIDINA",
      "AAS",
      "SINVASTATINA"
    ],
    "Substância Farmacológica": [
      "TICLOPIDINA",
      "AAS",
      "SINVASTATINA"
    ],
    "Atributo Clínico": [
      "IG",
      "Masculino"
    ],
    "Atributo de Organismo": [
      "Masculino"
    ],
    "Achado": [
      "heterogêneo",
      "afebril",
      "SUCESSO ANGIOGRÁFICO",
      "boa evolução puerperal",
      "lóquios fisiológicos",
      "útero contraído abaixo da cicatriz umbilical",
      "bom estado geral",
      "VDRL : não reag"
    ],
    "Resultado Laboratorial ou de Teste": [
      "heterogêneo",
      "Bexiga urinária com conteúdo denso",
      "Útero aumentado de volume",
      "VDRL : não reag"
    ],
    "Procedimento Laboratorial": [
      "EXAMES"
    ],
    "Localização ou Região Corporal": [
      "hemiface D",
      "face média à direita",
      "área da episio"
    ],
    "Conceito Espacial": [
      "SEGMENTO MÉDIO"
    ],
    "Grupo Profissional ou Ocupacional": [
      "MÉDICO ASSISTENTE"
    ],
    "Conceito Quantitativo": [
      "250 MG",
      "100 MG",
      "40 MG",
      "38 sem 4 dia",
      "3230 Gr"
    ],
    "Procedimento Diagnóstico": [
      "eco TV",
      "Eco TV"
    ],
    "Espaço ou Junção Corporal": [
      "cavidade endometrial"
    ]
  },
  "labels": {}
}