{
  "prontuario_id": 18,
  "text": "Paciente internada para artroscopia do joelho esquerdo. Procedimento sem intercorrências, persistiu com queixa de dor intensa no joelho. Recebe alta afebril, em bom estado geral. João, 39 anos.  # Síndrome de Kallmann, # Osteoporose =>  Acido Zoledrônico 4 mg em 14/06/07, # Rins Policísticos, # Hepatite crônica por HCV,  # Lombalgia => secundária alterações vertebrais pela osteoporose + protusão discal L4-L5. Paciente interna para investigar queixas de dor lombar com irradiação para MID, ausência de pêlos e anosmia. Há 8 meses, realizou investigação na cidade de XXXX, sendo diagnosticado Hepatite C e rins policísticos, além de ser observado ausência de caracteres sexuais secundários. Devido à suspeita, pela equipe médica daquela cidade, de hipogonadismo, recebeu encaminhamento para o XXXX  afim de completar investigação. Paciente sem pilificação corpórea, pequena quantidade de pêlos pubianos (P2). Refere ter tido ereções muito poucas vezes e nunca teve ejaculação. Apresenta pênis 4 cm e testículos 3 ml bilateral, além de envergadura maior que altura. Hipo/anosmia testada. Apresenta também distribuição ginecóide de gordura corporal. Devido ao quadro síndromico de hipogonadismo hipogonadotrófico associado à anosmia, iniciou-se investigação para Síndrome de Kallmann, sendo realizado exames laboratoriais e de imagem: Laboratoriais: 23/05/07: Testo Total: 0,31;  02/06/07: Anti-HCV: reagente, Cortisol: 12,6; FSH: 1,7; LH: 0,5; PTH: 21,6; Prolactina: 5,7; TSH: 2,2; T4: 8,82; 06/06/07: Anti-HIV: não reagente. HBSAg: negativo; Anti-HBS: não reagente. Anti-TPO: negativo. Imagem: Eco Tireóide: O lobo direito mede 4,2 x 1,1 x 1,7 cm e o esquerdo 4,4 x 1,2 x 1,8 cm. Ambos apresentam contornos regulares e ecogenicidade homogênea. Istmo homogêneo, com morfologia usual, com espessura de 0,4 cm. RNM Cranio Áreas sugestivas de heterotopia. Presença de assimetria do tamanho dos ventrículos cerebrais laterais, maior à esquerda. A hipófise apresenta dimensões normais, com padrão de impregnação homogêneo, sem sinal de lesão expansiva. O estudo com cortes finos da região frontal, não demonstra alteração do giro pré-olfatório, bilateralmente. RNM Lombo-sacra: Observa-se extrusão lateral direita a nível de L4-L5, que oblitera os planos gordurosos e indefine a raiz descendente de L5 no  recesso lateral direito. Há protrusão discal central entre L2-L3 e em menor grau entre L3-L4, sendo que entre L2-L3 há leve redução da amplitude do canal medular.       Exames antigos: eco abdominal em 13/12/2006 com rins policísticos (RD 14,5 x 7,2 e RE 12,8 x 7,2), biópsia hepática de 18/12/2006 com hepatite crônica A1 F2, hemossiderina neg. DENSITOMETRIA ÓSSEA DA COLUNA E FÊMUR: Há osteoporose da coluna. O paciente apresenta osteoporose no fêmur proximal total. Os valores encontrados para o exame de coluna foram: 0,530 g/cm² de densidade mineral óssea, a qual corresponde ao score T de -5,1 desvio-padrão em relação a massa óssea da população controle jovem. Para o exame de fêmur, a densidade mineral óssea encontrada foi 0,564 g/cm² correspondendo a um score T de -3,1 desvio-padrão em relação a massa óssea da população controle jovem. Frente ao quadro de dor lombar com irradiação para MID, paciente realizou RNM de coluna lombossacra, sendo avaliado pela neurocirurgia, que indicou tratamento conservador com analgesia, sem indicação cirúrgica no momento. Foi então solicitado consultoria à Fisiatria, que optou por realizar um acompanhamento ambulatorial. Devido à confirmação dos baixos níveis de gonadotrofinas e de testosterona, a equipe optou por iniciar o tratamento com testosterona até aquisição do HCG pela Secretaria da Saúde. Solicitou-se então consultoria à Gastrologia, a fim de esclarecer possíveis interações entre testosterona e sua doença hepática. A gastro confirmou hepatite viral cronica C em atividade, com indicação de tratamento com interferon, sendo que não contra-indicaram o uso de testosterona em tais situações. Fora também realizado uma densitometria óssea, que confirmou osteoporose importante, sendo iniciado tratamento de reposição de cálcio, além de receber dose de acido zoledronico durante a internação. Paciente também fora submetido à teste de estímulo com GnRh, apresentando resposta, o que corrobora com a hipótese prévia de hipogonadismo central de origem hipotalâmica. Paciente recebe alta com diagnóstico de Síndrome de Kallmann, com planos de iniciar tratamento do hipogonadismo com testosterona IM até aquisição de HCG e seguir acompanhamento ambulatorial pela Endocrinologia, além de seguir acompanhamento ambulatorial com a Gastrologia e Fisiatria.",
  "entities": {
    "Paciente ou Grupo com Deficiência": [
      "Paciente",
      "paciente"
    ],
    "Atividade de Assistência à Saúde": [
      "internada",
      "alta",
      "interna",
      "investigar",
      "encaminhamento",
      "investigação",
      "realizado",
      "avaliado",
      "solicitado",
      "consultoria",
      "realizar",
      "iniciar",
      "internação",
      "acompanhamento ambulatorial"
    ],
    "Procedimento Terapêutico ou Preventivo": [
      "artroscopia",
      "Procedimento",
      "analgesia",
      "tratamento",
      "tratamento conservador",
      "indicação cirúrgica",
      "reposição de cálcio"
    ],
    "Procedimento Diagnóstico": [
      "artroscopia",
      "investigação",
      "imagem",
      "Imagem",
      "Exames",
      "Eco Tireóide",
      "RNM Cranio",
      "RNM Lombo-sacra",
      "eco abdominal",
      "biópsia hepática",
      "DENSITOMETRIA ÓSSEA DA COLUNA E FÊMUR",
      "exame de coluna",
      "exame de fêmur",
      "RNM de coluna lombossacra",
      "densitometria óssea"
    ],
    "Negação": [
      "sem",
      "afebril",
      "ausência",
      "nunca",
      "não"
    ],
    "Sinal ou Sintoma": [
      "intercorrências",
      "queixa",
      "afebril",
      "Lombalgia",
      "queixas",
      "irradiação",
      "anosmia",
      "dor intensa",
      "secundária alterações vertebrais",
      "protusão discal L4-L5",
      "dor lombar",
      "Hipo/anosmia testada",
      "distribuição ginecóide de gordura corporal"
    ],
    "Espaço ou Junção Corporal": [
      "joelho",
      "joelho esquerdo"
    ],
    "Doença ou Síndrome": [
      "Osteoporose",
      "osteoporose",
      "hipogonadismo",
      "Síndrome de Kallmann",
      "Rins Policísticos",
      "Hepatite crônica",
      "Hepatite C",
      "rins policísticos",
      "quadro síndromico",
      "hipogonadismo hipogonadotrófico",
      "hepatite crônica A1 F2",
      "doença hepática",
      "hepatite viral cronica C",
      "hipogonadismo central"
    ],
    "Vírus": [
      "HCV"
    ],
    "Localização ou Região Corporal": [
      "MID"
    ],
    "Abreviação": [
      "MID",
      "HCG",
      "gastro",
      "Testo Total : 0 , 31",
      "Eco Tireóide",
      "RNM Cranio",
      "RNM Lombo-sacra",
      "eco abdominal",
      "hemossiderina neg"
    ],
    "Parte do Corpo, Órgão ou Componente Orgânico": [
      "pêlos",
      "pênis",
      "testículos",
      "pêlos pubianos",
      "fêmur proximal",
      "origem hipotalâmica"
    ],
    "Função de Órgão ou Tecido": [
      "ereções"
    ],
    "Função de Organismo": [
      "ejaculação"
    ],
    "Conceito Espacial": [
      "bilateral"
    ],
    "Procedimento Laboratorial": [
      "Laboratoriais",
      "exames laboratoriais"
    ],
    "Resultado Laboratorial ou de Teste": [
      "Laboratoriais",
      "Testo Total : 0 , 31",
      "Anti-HCV : reagente",
      "Cortisol : 12 , 6",
      "FSH : 1 , 7",
      "LH : 0 , 5",
      "PTH : 21 , 6",
      "Prolactina : 5 , 7",
      "TSH : 2 , 2",
      "T4 : 8 , 82",
      "Anti-HIV : não reagente",
      "HBSAg : negativo",
      "Anti-HBS : não reagente",
      "Anti-TPO : negativo",
      "lobo direito",
      "Ambos apresentam contornos regulares e ecogenicidade homogênea",
      "Istmo homogêneo",
      "com morfologia usual",
      "com espessura de 0 , 4 cm",
      "Áreas sugestivas de heterotopia",
      "Presença de assimetria do tamanho dos ventrículos cerebrais laterais",
      "maior à esquerda",
      "A hipófise apresenta dimensões normais",
      "com padrão de impregnação homogêneo",
      "sinal de lesão expansiva",
      "O estudo com cortes finos da região frontal",
      "demonstra alteração do giro pré-olfatório",
      "Observa-se extrusão lateral direita a nível de L4-L5",
      "que oblitera os planos gordurosos",
      "indefine a raiz descendente de L5 no recesso lateral direito",
      "Há protrusão discal central entre L2-L3",
      "em menor grau entre L3-L4",
      "entre L2-L3 há leve redução da amplitude do canal medular",
      "com rins policísticos",
      "RD 14 , 5 x 7 , 2",
      "RE 12 , 8 x 7 , 2",
      "hepatite crônica A1 F2",
      "hemossiderina neg",
      "Há osteoporose da coluna",
      "0 , 530 g/cm² de densidade mineral óssea",
      "desvio-padrão em relação a massa óssea da população controle jovem",
      "densidade mineral óssea encontrada foi 0 , 564 g/cm²",
      "desvio-padrão",
      "em relação a massa óssea da população controle jovem",
      "baixos níveis de gonadotrofinas e de testosterona",
      "osteoporose importante"
    ],
    "Grupo Profissional ou Ocupacional": [
      "neurocirurgia",
      "Fisiatria",
      "equipe",
      "Gastrologia",
      "gastro",
      "Endocrinologia",
      "equipe médica"
    ],
    "Organização Relacionada à Saúde": [
      "neurocirurgia",
      "Gastrologia",
      "gastro",
      "Endocrinologia",
      "Fisiatria"
    ],
    "Hormônio": [
      "testosterona",
      "HCG",
      "GnRh"
    ],
    "Substância Química Orgânica": [
      "testosterona"
    ],
    "Substância Farmacológica": [
      "testosterona",
      "HCG",
      "interferon",
      "GnRh",
      "Acido Zoledrônico",
      "acido zoledronico",
      "testosterona IM"
    ],
    "Aminoácido, Peptídeo ou Proteína": [
      "HCG",
      "interferon",
      "GnRh"
    ],
    "Função Molecular": [
      "interações"
    ],
    "Fator Imunológico": [
      "interferon"
    ],
    "Conceito Quantitativo": [
      "dose",
      "4 mg",
      "4 cm",
      "3 ml"
    ],
    "Conceito Temporal": [
      "durante",
      "no momento"
    ],
    "Achado": [
      "bom estado geral",
      "pilificação corpórea",
      "envergadura maior que altura",
      "em atividade",
      "apresentando resposta"
    ],
    "Atributo Clínico": [
      "caracteres sexuais secundários"
    ],
    "Conceito Qualitativo": [
      "pequena quantidade",
      "muito poucas vezes"
    ]
  },
  "labels": {}
}