{
  "prontuario_id": 978,
  "text": "05/05/2012 às 10:10h. 22º DI - colelitíase crônica + PO CCVP revertida. 18ºUTI - PO de LE por abdomen agudo. 18ºDI - SVD. 11ºDI - SNE. 10º DI - TQT. 4º DI - PAM. 1º DI - AVC femural. Ramsay 06, pupilas isomióticas. SNE com infusão de dieta a 60ml/h. Traqueostomizada, em VM modalidade PCV, Peep 10, PI 24, FiO2 60%. CPP com roncos difusos. Abdomen pouco distendido, RHA+. FO abdominal com exsudação serosa, uso de cinta elástica. PAM em radial E pérvia. Acesso venoso em femural D com infusão de propofol  a 30ml/h e plano dobrados de dormonid 30ml/h + fentanil 15ml/h + noradrenalina 15ml/h. SVD com débito efetivo, evacuação ausente. Extremidades frias, perfusão periférica diminuída, edemaciada. Uso de colchão de ar. *Precaução de contato para ESBL.* Enfermeira Florence Nightingale SÍNDROME DO CHOQUE TOXICO",
  "entities": {
    "Conceito Temporal": [
      "PO"
    ],
    "Abreviação": [
      "PO",
      "LE",
      "SVD",
      "SNE",
      "TQT",
      "PAM",
      "60ml/h",
      "VM",
      "Peep",
      "PI",
      "FiO2",
      "CPP",
      "RHA+",
      "FO",
      "30ml/h",
      "CCVP revertida",
      "AVC femural",
      "modalidade PCV",
      "radial E",
      "femural D"
    ],
    "Procedimento Terapêutico ou Preventivo": [
      "LE",
      "SVD",
      "SNE",
      "TQT",
      "Traqueostomizada",
      "VM",
      "Peep",
      "PI",
      "FiO2",
      "PAM",
      "infusão",
      "CCVP revertida",
      "AVC femural",
      "infusão de dieta",
      "modalidade PCV",
      "cinta elástica",
      "Acesso venoso",
      "colchão de ar",
      "*Precaução de contato"
    ],
    "Dispositivo Médico": [
      "SVD",
      "SNE",
      "AVC femural",
      "cinta elástica",
      "Acesso venoso",
      "colchão de ar"
    ],
    "Procedimento Diagnóstico": [
      "PAM"
    ],
    "Conceito Quantitativo": [
      "60ml/h",
      "10",
      "24",
      "60%",
      "30ml/h",
      "15ml/h"
    ],
    "Achado": [
      "Traqueostomizada",
      "RHA+",
      "pérvia",
      "débito efetivo"
    ],
    "Localização ou Região Corporal": [
      "CPP",
      "Abdomen",
      "abdominal"
    ],
    "Lesão ou Envenenamento": [
      "FO"
    ],
    "Substância Farmacológica": [
      "propofol",
      "dormonid",
      "fentanil",
      "noradrenalina"
    ],
    "Substância Química Orgânica": [
      "propofol",
      "dormonid",
      "fentanil",
      "noradrenalina"
    ],
    "Conceito Qualitativo": [
      "30ml/h"
    ],
    "Hormônio": [
      "noradrenalina"
    ],
    "Função Fisiológica": [
      "evacuação",
      "débito efetivo"
    ],
    "Negação": [
      "ausente"
    ],
    "Sinal ou Sintoma": [
      "edemaciada",
      "Ramsay 06",
      "pupilas isomióticas",
      "roncos difusos",
      "pouco distendido",
      "Extremidades frias",
      "perfusão periférica diminuída"
    ],
    "Bactéria": [
      "ESBL"
    ],
    "Grupo Profissional ou Ocupacional": [
      "Enfermeira"
    ],
    "Doença ou Síndrome": [
      "colelitíase crônica",
      "abdomen agudo",
      "SÍNDROME DO CHOQUE TOXICO"
    ],
    "Substância Corporal": [
      "exsudação serosa"
    ],
    "Parte do Corpo, Órgão ou Componente Orgânico": [
      "radial E",
      "femural D"
    ]
  },
  "labels": {}
}