{
  "prontuario_id": 301,
  "text": "PACIENTE HAS , DPOC , TABAGISTA , EX-ETILISTA , INTERNA COM QUADRO CLÍNICO DE DOR TORÁCICA IRRADIADA PARA COTOVELO DIREITO , EM REPOUSO , CARACTERÍSTICA DE APERTO , DURAÇÃO DE 4 HORAS , A QUAL TERIA INICADO HÁ 4 SEMANAS AOS ESFORÇOS .  INTERNA NO CTI-HCPA COM SUSPEITA DIAGNÓSTICA DE ANGINA PROGRESSIVA . NA INVESTIGAÇÃO , REALIZOU CATETERISMO CARDÍACO , O QUAL DEMONSTROU CORONÁRIAS SEM LESÕES OBSTRUTIVAS SIGNIFICATIVAS , E ECOCARDIOGRAMA COM AE = 50 , VE = 56/37 ,  FE = 65% , S = 16 , PP = 12  E ESTENOSE AÓRTICA LEVE-MODERADA COM GRADIENTE MÉDIO DE 31 MMHG . TERÁ ALTA HOSPITALAR ASSINTOMÁTICA , COM MEDICAÇÃO ANTIHIPERTENSIVA E COM PROFILAXIA PARA ENDOCARDITE .",
  "entities": {
    "Paciente ou Grupo com Deficiência": [
      "PACIENTE"
    ],
    "Abreviação": [
      "HAS",
      "DPOC",
      "AE = 50",
      "VE = 56/37",
      "FE = 65%",
      "S = 16",
      "PP = 12"
    ],
    "Doença ou Síndrome": [
      "HAS",
      "DPOC",
      "TABAGISTA",
      "ANGINA PROGRESSIVA"
    ],
    "Achado": [
      "EX-ETILISTA"
    ],
    "Procedimento Diagnóstico": [
      "INVESTIGAÇÃO",
      "CATETERISMO CARDÍACO",
      "E ECOCARDIOGRAMA"
    ],
    "Negação": [
      "SEM",
      "ASSINTOMÁTICA"
    ],
    "Sinal ou Sintoma": [
      "ASSINTOMÁTICA",
      "DOR TORÁCICA",
      "IRRADIADA PARA COTOVELO DIREITO",
      "EM REPOUSO",
      "CARACTERÍSTICA DE APERTO",
      "ANGINA PROGRESSIVA"
    ],
    "Procedimento Terapêutico ou Preventivo": [
      "CATETERISMO CARDÍACO",
      "PROFILAXIA PARA ENDOCARDITE"
    ],
    "Resultado Laboratorial ou de Teste": [
      "LESÕES OBSTRUTIVAS SIGNIFICATIVAS",
      "AE = 50",
      "VE = 56/37",
      "FE = 65%",
      "S = 16",
      "PP = 12",
      "ESTENOSE AÓRTICA LEVE-MODERADA COM GRADIENTE MÉDIO DE 31 MMHG"
    ],
    "Atividade de Assistência à Saúde": [
      "ALTA HOSPITALAR"
    ],
    "Substância Farmacológica": [
      "MEDICAÇÃO ANTIHIPERTENSIVA"
    ]
  },
  "labels": {}
}