{
  "prontuario_id": 176,
  "text": "pACIENTE ENCAMINHADA PELA endocrinologia devido a diabestes de longa data, paciente relata muito inchaço em MMII, relata litiase renal.  hma: INCHAÇO, principalmente no peridodo da manha e em MMII (++++/++++), piora do quadro ha 15 dias, estagio II de IRC. HMP: 3 CATE e 1 RM ( 3 safenas e 1 mamaria),  catarata, 2 cesareas (ultima ha 30 anos) ,colecistectomia,  parcial de urina: bacteriuria inensa.  CCR 0,9; UREIA 47, CKD/EP 90, HB 10,95; HEMATÓCRITO 33,4; GLICEMIA 70, HB GLICADA 7,51; COLESTEROL T 145; HDL 48; LDL 68; TRIGLI 146; PTH 115; K 4,1; PU PROT AUSENTES; HB AUSENTES; LEUCO 37,  MEDICAMENTOS: ANLODIPINO ( 5MG 1 X DIA), SINVASTATINA (20MG 1 X DIA), CARVEDILOL (12,5 (1 X DIA), LOSARTANA (50MG 1 X DIA), ALDACTONE (25MG 1 X DIA),  METFORMINA ( 850MG 1 X DIA), MONOCORDIL RETARD (150 MG), INSULINA (nph 30 D MANHA E 25 A NOITE), MEDICaMeNtO DE ESTUDO E INJEÇÃO SEMANAL, FUROSEMIDA 40MG ( 2 PELA MANHA), CALCITRIOL ( 0,25 ).  eX FISICO: pa 125/53, fc 72 BPM, imc 36,6.  conduta: realizar ecocrdiorama, hemograma, Cr, parcial de urina, pth, retorno em 6 meses. DM2, HAS, RVM.",
  "entities": {
    "Paciente ou Grupo com Deficiência": [
      "pACIENTE",
      "paciente"
    ],
    "Atividade de Assistência à Saúde": [
      "ENCAMINHADA",
      "conduta",
      "retorno"
    ],
    "Grupo Profissional ou Ocupacional": [
      "endocrinologia"
    ],
    "Organização Relacionada à Saúde": [
      "endocrinologia"
    ],
    "Doença ou Síndrome": [
      "diabestes",
      "catarata",
      "DM2",
      "HAS",
      "litiase renal",
      "estagio II de IRC"
    ],
    "Abreviação": [
      "hma",
      "MMII",
      "HMP",
      "CATE",
      "RM",
      "pa",
      "fc",
      "imc",
      "Cr",
      "pth",
      "DM2",
      "HAS",
      "RVM",
      "inchaço em MMII",
      "estagio II de IRC",
      "CCR 0 , 9",
      "CKD/EP 90",
      "HB 10 , 95",
      "HB GLICADA 7 , 51",
      "COLESTEROL T 145",
      "HDL 48",
      "LDL 68",
      "TRIGLI 146",
      "K 4 , 1",
      "HB AUSENTES",
      "LEUCO 37",
      "eX FISICO"
    ],
    "Sinal ou Sintoma": [
      "INCHAÇO",
      "inchaço em MMII",
      "piora do quadro"
    ],
    "Conceito Quantitativo": [
      "3",
      "1",
      "2",
      "125/53",
      "5MG 1 X DIA",
      "20MG 1 X DIA",
      "25MG 1 X DIA",
      "850MG 1 X DIA",
      "150 MG",
      "0 , 25",
      "72 BPM",
      "36 , 6"
    ],
    "Procedimento Terapêutico ou Preventivo": [
      "CATE",
      "RM",
      "cesareas",
      "colecistectomia"
    ],
    "Parte do Corpo, Órgão ou Componente Orgânico": [
      "safenas",
      "mamaria"
    ],
    "Substância Farmacológica": [
      "MEDICAMENTOS",
      "ANLODIPINO",
      "SINVASTATINA",
      "CARVEDILOL",
      "LOSARTANA",
      "ALDACTONE",
      "METFORMINA",
      "INSULINA",
      "nph",
      "FUROSEMIDA",
      "CALCITRIOL",
      "MONOCORDIL RETARD"
    ],
    "Substância Química Orgânica": [
      "ANLODIPINO",
      "SINVASTATINA",
      "CARVEDILOL",
      "LOSARTANA",
      "METFORMINA",
      "FUROSEMIDA",
      "CALCITRIOL",
      "MONOCORDIL RETARD"
    ],
    "Hormônio": [
      "INSULINA"
    ],
    "Atributo Clínico": [
      "pa",
      "fc",
      "imc"
    ],
    "Procedimento Diagnóstico": [
      "ecocrdiorama",
      "eX FISICO"
    ],
    "Procedimento Laboratorial": [
      "hemograma",
      "Cr",
      "pth",
      "parcial de urina"
    ],
    "Conceito Temporal": [
      "de longa data",
      "peridodo da manha",
      "D MANHA",
      "A NOITE",
      "PELA MANHA"
    ],
    "Resultado Laboratorial ou de Teste": [
      "bacteriuria inensa",
      "CCR 0 , 9",
      "UREIA 47",
      "CKD/EP 90",
      "HB 10 , 95",
      "HEMATÓCRITO 33 , 4",
      "GLICEMIA 70",
      "HB GLICADA 7 , 51",
      "COLESTEROL T 145",
      "HDL 48",
      "LDL 68",
      "TRIGLI 146",
      "PTH 115",
      "K 4 , 1",
      "HB AUSENTES",
      "LEUCO 37"
    ]
  },
  "labels": {}
}