{
  "prontuario_id": 92,
  "text": "43 ANOS HAS DESDE OS 17 ANOS, DM TIPO 2 , HÁ 5 ANOS G 4 C 4 A0 LAQUEADURA CATETERISMO CARDÍACO HÁ 2 ANOS , EM PONTA GROSSA. SEM INDICAÇÃO ANGIOPLASTIA ARRITMIA DLP MISTA EX TABAGISTA , ,PAROU HÁ 6 MESES (FUMAVA DESDE 9 ANOS) NEGA ALTERAÇÃO TIRÓIDE, IAM, AVE  EM USO DE LST 50 2X, AAS, ATENOLOL 50 2X, FUROSEMIDA 40, metformina 850   hoje  PESO 82 PA 170/100 MUCOSAS HIPOCORADAS CPP LIVRES ABDOME SP MEMBROS EDEMA +/4. Suspenso metformina  aumento furosemida e associo calcio como quelante. ECOGRAFIA 28/05/2014 > SINAIS DE NEFROPATIA CRONICA BILATERAL 15/04/2014>: CR 3,2 31/03/2015: CR 2,47, CL CR 42 12/06/2015: glico 79 , na 140 , ca 9,5 , ac urico 6,5 , cr 2,92 , k 5,2 , ureia 98 , p 5,5 , ht 41 , hb 14 , ph 7,23 , bic 21 p urina l 13mil, prot 100   A# DRC  > MDRD 28     ACIDOSE : METFORMINA?  ANEMIA DISCRETA  CAXP 52,5.",
  "entities": {
    "Doença ou Síndrome": [
      "HAS",
      "ARRITMIA",
      "IAM",
      "AVE",
      "DRC",
      "DM TIPO 2",
      "DLP MISTA"
    ],
    "Abreviação": [
      "HAS",
      "A0",
      "IAM",
      "AVE",
      "LST",
      "AAS",
      "PA",
      "CPP",
      "SP",
      "DRC",
      "DM TIPO 2",
      "DLP MISTA",
      "CR 3 , 2",
      "CR 2 , 47",
      "glico 79",
      "na 140",
      "ca 9 , 5",
      "ac urico 6 , 5",
      "cr 2 , 92",
      "k 5 , 2",
      "ht 41",
      "hb 14",
      "bic 21",
      "p urina",
      "prot 100"
    ],
    "Atributo Clínico": [
      "G",
      "PESO",
      "PA"
    ],
    "Conceito Quantitativo": [
      "4",
      "40",
      "850",
      "82",
      "170/100",
      "50 2X"
    ],
    "Procedimento Terapêutico ou Preventivo": [
      "C",
      "LAQUEADURA",
      "ANGIOPLASTIA",
      "CATETERISMO CARDÍACO"
    ],
    "Negação": [
      "SEM",
      "NEGA"
    ],
    "Atividade de Assistência à Saúde": [
      "INDICAÇÃO",
      "Suspenso",
      "aumento",
      "associo"
    ],
    "Sinal ou Sintoma": [
      "ARRITMIA",
      "ALTERAÇÃO",
      "EDEMA",
      "MUCOSAS HIPOCORADAS"
    ],
    "Parte do Corpo, Órgão ou Componente Orgânico": [
      "TIRÓIDE"
    ],
    "Substância Farmacológica": [
      "LST",
      "AAS",
      "ATENOLOL",
      "FUROSEMIDA",
      "metformina",
      "furosemida",
      "calcio",
      "quelante",
      "METFORMINA"
    ],
    "Localização ou Região Corporal": [
      "CPP",
      "ABDOME",
      "MEMBROS"
    ],
    "Achado": [
      "LIVRES",
      "SP",
      "EX TABAGISTA"
    ],
    "Resultado Laboratorial ou de Teste": [
      "+/4",
      "SINAIS DE NEFROPATIA CRONICA BILATERAL",
      "CR 3 , 2",
      "CR 2 , 47",
      "CL CR 42",
      "glico 79",
      "na 140",
      "ca 9 , 5",
      "ac urico 6 , 5",
      "cr 2 , 92",
      "k 5 , 2",
      "ureia 98",
      "p 5 , 5",
      "ht 41",
      "hb 14",
      "ph 7 , 23",
      "bic 21",
      "prot 100",
      "MDRD 28",
      "CAXP 52 , 5"
    ],
    "Substância Biologicamente Ativa": [
      "calcio"
    ],
    "Procedimento Diagnóstico": [
      "ECOGRAFIA"
    ],
    "Conceito Temporal": [
      "DESDE OS 17 ANOS",
      "HÁ 5 ANOS"
    ]
  },
  "labels": {}
}