{
  "prontuario_id": 616,
  "text": "09:00 CONSCIENTE, ORIENTADO, VERBALIZA, EM REPOUSO NO LEITO, AFEBRIL, EUPNEICO EM AR AMBIENTE, SEM QUEIXAS ALGICAS, RELATA DIFICULDADE A MASTIGAÇÃO DEVIDO A SECREÇÃO ESBRANQUIÇADA EM REGIÃO DE GENGIVA, ODOR FETIDO, ACESSO VENOSO PERIFERICO EM MSE SALINIZADO SEM SINAIS FLOGISTICOS, HEMATOMA EM REGIÃO ORBITAL ESQUERDA, TALA + CURATIVO EXTERNAMENTE SECO E LIMPO EM MIE, PERFUSÃO DISTAL PRESERVADA, PULSO PALPAVEL, DIURESE ESPONTANEA. Doutor Vital Brazil MAEDA SOLICITOU AVALIAÇÃO DA CX. FACE, Doutor Vital Brazil AVALIOU E SOLICITOU AVALIAÇÃO CX. PLASTICA  O MESMO ORIENTOU APENAS HIGIENE ORAL, AGUARDA RESULTADO TAC DE JOELHO PARA AVALIAÇÃO ORTO. Enfermeira Florence Nightingale. TRAUMATISMO INTRACRANIANO NAO ESPECIFICADO",
  "entities": {
    "Achado": [
      "CONSCIENTE",
      "ORIENTADO",
      "VERBALIZA",
      "AFEBRIL",
      "SECO",
      "LIMPO",
      "EUPNEICO EM AR AMBIENTE",
      "PERFUSÃO DISTAL PRESERVADA",
      "PULSO PALPAVEL",
      "DIURESE ESPONTANEA"
    ],
    "Negação": [
      "AFEBRIL",
      "SEM"
    ],
    "Localização ou Região Corporal": [
      "MSE",
      "MIE",
      "REGIÃO DE GENGIVA",
      "REGIÃO ORBITAL ESQUERDA"
    ],
    "Abreviação": [
      "MSE",
      "MIE",
      "ORTO"
    ],
    "Procedimento Terapêutico ou Preventivo": [
      "SALINIZADO",
      "TALA",
      "CURATIVO",
      "REPOUSO NO LEITO",
      "ACESSO VENOSO PERIFERICO",
      "HIGIENE ORAL"
    ],
    "Sinal ou Sintoma": [
      "HEMATOMA",
      "QUEIXAS ALGICAS",
      "DIFICULDADE A MASTIGAÇÃO",
      "ODOR FETIDO",
      "SINAIS FLOGISTICOS"
    ],
    "Dispositivo Médico": [
      "TALA",
      "CURATIVO",
      "ACESSO VENOSO PERIFERICO"
    ],
    "Conceito Espacial": [
      "EXTERNAMENTE"
    ],
    "Atividade de Assistência à Saúde": [
      "AVALIOU",
      "ORIENTOU",
      "AVALIAÇÃO",
      "SOLICITOU AVALIAÇÃO"
    ],
    "Parte do Corpo, Órgão ou Componente Orgânico": [
      "JOELHO"
    ],
    "Grupo Profissional ou Ocupacional": [
      "ORTO"
    ],
    "Substância Corporal": [
      "SECREÇÃO ESBRANQUIÇADA"
    ],
    "Atributo Clínico": [
      "PERFUSÃO DISTAL PRESERVADA"
    ],
    "Função de Organismo": [
      "DIURESE ESPONTANEA"
    ],
    "Lesão ou Envenenamento": [
      "TRAUMATISMO INTRACRANIANO"
    ]
  },
  "labels": {}
}