{
  "prontuario_id": 842,
  "text": "# 2 CX DE TROCA DE MITRAL + ATRIOSEPTOPLASTIA (2006)\n# FA PERMANENTE \n# 23/09/14 PROTESE METALICA EM POSIÇÃO MITRAL NORMOFUNCIONANTE. VE APRESENTA DIMENSÕES NORMAIS COM FUNÇÃO SISTOLICA\nPRESERVADA. VENTRICULO DIREITO APRESENTA DIMENSÕES AUMENTADAS E FUNÇÃO SISTOLICA COMPROMETIDA DISCRETAMENTE.\nREGURGITAÇÃO TRICUSPIDE DISCRETA. PSAP ESTIMADA EM 45MMHG. ATRIO ESQUERDO E DIREITO DILATADOS. \n# MEDICAMENTOS EM USO:\nWARFARIM 5MG\nSELOKEN 100MG \n# PACIENTE VEM PARA CONSULTA DE ROTINA. NEGA QUAISQUER SINTOMAS. NEGA INTERCORRÊNCIAS DA ÚLTIMA CONSULTA PRA CÁ. \n# AO EXAME :  \nBEG, CORADA, HIDRATADA, LOTE, EUPNÉICA.\nMV + SEM RA. RITMO CARDÍACO IRREGULAR, BULHAS NORMOFONÉTICAS, PRESENÇA DE ESTALIDO METÁLICO.   \nFC 60 \nPA 110X60 MMHG \nCONDUTA : MANTEMOS SELOKEM.\nENCAMINHAMOS A PACIENTE PARA AMBULATÓRIO DE VALVOPATIAS.\n \n \n \n ",
  "entities": {
    "Conceito Quantitativo": [
      "2",
      "45MMHG",
      "5MG",
      "100MG",
      "60",
      "110X60 MMHG"
    ],
    "Procedimento Terapêutico ou Preventivo": [
      "ATRIOSEPTOPLASTIA",
      "CX DE TROCA DE MITRAL"
    ],
    "Abreviação": [
      "VE",
      "PSAP",
      "BEG",
      "LOTE",
      "RA",
      "FC",
      "PA",
      "CX DE TROCA DE MITRAL",
      "FA PERMANENTE",
      "MV +"
    ],
    "Parte do Corpo, Órgão ou Componente Orgânico": [
      "VE",
      "VENTRICULO DIREITO"
    ],
    "Atributo Clínico": [
      "PSAP",
      "FC",
      "PA"
    ],
    "Conceito Espacial": [
      "ESQUERDO",
      "DIREITO"
    ],
    "Anormalidade Adquirida": [
      "DILATADOS",
      "REGURGITAÇÃO TRICUSPIDE DISCRETA"
    ],
    "Sinal ou Sintoma": [
      "DILATADOS",
      "SINTOMAS",
      "INTERCORRÊNCIAS",
      "RA",
      "DIMENSÕES AUMENTADAS",
      "FUNÇÃO SISTOLICA COMPROMETIDA DISCRETAMENTE",
      "REGURGITAÇÃO TRICUSPIDE DISCRETA",
      "RITMO CARDÍACO IRREGULAR"
    ],
    "Substância Farmacológica": [
      "MEDICAMENTOS",
      "WARFARIM",
      "SELOKEN",
      "SELOKEM"
    ],
    "Medicamento Clínico": [
      "MEDICAMENTOS"
    ],
    "Paciente ou Grupo com Deficiência": [
      "PACIENTE"
    ],
    "Negação": [
      "NEGA",
      "SEM"
    ],
    "Atividade de Assistência à Saúde": [
      "CONSULTA",
      "CONDUTA",
      "MANTEMOS",
      "ENCAMINHAMOS",
      "CONSULTA DE ROTINA"
    ],
    "Achado": [
      "BEG",
      "CORADA",
      "HIDRATADA",
      "LOTE",
      "EUPNÉICA",
      "POSIÇÃO MITRAL NORMOFUNCIONANTE",
      "DIMENSÕES NORMAIS",
      "FUNÇÃO SISTOLICA PRESERVADA",
      "MV +",
      "BULHAS NORMOFONÉTICAS",
      "PRESENÇA DE ESTALIDO METÁLICO"
    ],
    "Doença ou Síndrome": [
      "FA PERMANENTE"
    ],
    "Dispositivo Médico": [
      "PROTESE METALICA"
    ],
    "Função Patológica": [
      "DIMENSÕES AUMENTADAS",
      "FUNÇÃO SISTOLICA COMPROMETIDA DISCRETAMENTE"
    ],
    "Organização Relacionada à Saúde": [
      "AMBULATÓRIO DE VALVOPATIAS"
    ]
  },
  "labels": {}
}