{
  "prontuario_id": 223,
  "text": "# 2 CX DE TROCA DE MITRAL + ATRIOSEPTOPLASTIA (2006)\n# FA PERMANENTE \n# 23/09/14:  PROTESE METALICA EM POSIÇÃO MITRAL NORMOFUNCIONANTE. VE APRESENTA DIMENSÕES NORMAIS COM FUNÇÃO SISTOLICA\nPRESERVADA. VENTRICULO DIREITO APRESENTA DIMENSÕES AUMENTADAS E FUNÇÃO SISTOLICA COMPROMETIDA DISCRETAMENTE.\nREGURGITAÇÃO TRICUSPIDE DISCRETA. PSAP ESTIMADA EM 45MMHG. ATRIO ESQUERDO E DIREITO DILATADOS. \n# MEDICAMENTOS EM USO: \nWARFARIM 5MG\nSELOKEN 100MG 12/12H\nPENICILINA BENZATINA 21/21DIAS \n# PACIENTE VEM PARA COPNSULTA REFERINDO APENAS DOR INFRAMAMARIA TIPO MESMO EM REPOUSO, TIPO FISGADA, CONTINUA, SEM RELAÇÃO COM ATIVIDADE.\nNEGA DISPNEIA OU OUTROS SINTOMAS\nSEM OUTRAS QUEIXAS NO PERIODO \n# AO EXAME :\nBEG, CORADA, HIDRATADA, LOTE, EUPNÉICA.\nMV + SEM RA. RITMO CARDÍACO IRREGULAR,\nACV : BULHAS NORMOFONÉTICAS, PRESENÇA DE ESTALIDO METÁLICO.\nFC 71\nPA 100X60 MMHG \nCONDUTA: MANTIDO MEDICAÇÕES\nRAIOX DE TORAX CONTROLE\nRETORNO EM 1 ANO\n \n \n \n ",
  "entities": {
    "Conceito Quantitativo": [
      "2",
      "45MMHG",
      "5MG",
      "21/21DIAS",
      "71",
      "100MG 12/12H",
      "100X60 MMHG"
    ],
    "Procedimento Terapêutico ou Preventivo": [
      "ATRIOSEPTOPLASTIA",
      "CX DE TROCA DE MITRAL"
    ],
    "Abreviação": [
      "VE",
      "PSAP",
      "BEG",
      "LOTE",
      "RA",
      "ACV",
      "FC",
      "PA",
      "CX DE TROCA DE MITRAL",
      "FA PERMANENTE",
      "MV +"
    ],
    "Parte do Corpo, Órgão ou Componente Orgânico": [
      "VE",
      "VENTRICULO DIREITO"
    ],
    "Atributo Clínico": [
      "PSAP",
      "FC",
      "PA"
    ],
    "Conceito Espacial": [
      "ESQUERDO",
      "DIREITO"
    ],
    "Sinal ou Sintoma": [
      "DILATADOS",
      "FISGADA",
      "DISPNEIA",
      "RA",
      "DIMENSÕES AUMENTADAS",
      "FUNÇÃO SISTOLICA COMPROMETIDA DISCRETAMENTE",
      "REGURGITAÇÃO TRICUSPIDE DISCRETA",
      "DOR INFRAMAMARIA",
      "EM REPOUSO",
      "OUTROS SINTOMAS",
      "OUTRAS QUEIXAS",
      "RITMO CARDÍACO IRREGULAR",
      "ESTALIDO METÁLICO"
    ],
    "Medicamento Clínico": [
      "MEDICAMENTOS",
      "MEDICAÇÕES"
    ],
    "Substância Farmacológica": [
      "MEDICAMENTOS",
      "WARFARIM",
      "SELOKEN",
      "MEDICAÇÕES",
      "PENICILINA BENZATINA"
    ],
    "Paciente ou Grupo com Deficiência": [
      "PACIENTE"
    ],
    "Atividade de Assistência à Saúde": [
      "COPNSULTA",
      "CONDUTA",
      "MANTIDO",
      "RETORNO"
    ],
    "Conceito Qualitativo": [
      "CONTINUA"
    ],
    "Negação": [
      "SEM",
      "NEGA"
    ],
    "Achado": [
      "BEG",
      "CORADA",
      "HIDRATADA",
      "LOTE",
      "EUPNÉICA",
      "POSIÇÃO MITRAL NORMOFUNCIONANTE",
      "DIMENSÕES NORMAIS",
      "FUNÇÃO SISTOLICA PRESERVADA",
      "RELAÇÃO COM ATIVIDADE",
      "MV +",
      "BULHAS NORMOFONÉTICAS"
    ],
    "Procedimento Diagnóstico": [
      "ACV",
      "RAIOX DE TORAX"
    ],
    "Sistema Corporal": [
      "ACV"
    ],
    "Doença ou Síndrome": [
      "FA PERMANENTE"
    ],
    "Dispositivo Médico": [
      "PROTESE METALICA"
    ],
    "Função Patológica": [
      "DIMENSÕES AUMENTADAS"
    ],
    "Anormalidade Adquirida": [
      "REGURGITAÇÃO TRICUSPIDE DISCRETA"
    ],
    "Antibiótico": [
      "PENICILINA BENZATINA"
    ],
    "Conceito Temporal": [
      "NO PERIODO",
      "1 ANO"
    ]
  },
  "labels": {}
}