{
  "prontuario_id": 266,
  "text": "1ª CONSULTA \nLucas, 43 ANOS\nNATURAL E PROCEDENTE DE UNIÃO DA VITÓRIA \n# CIRURGIA BARIÁTRICA EM 2010 E 2013\n# HAS\n# EX-TABAGISTA - PAROU HÁ 04 ANOS\n# NEGA IAM, ETILISMO\n# ICC COM DIAGNÓSTICO HÁ 04 ANOS\n# MEDICAÇÕES : ENALAPRIL 10MG 12/12H, CARVEDILOL 6,25 MG 12/12H, ESPIRONOLACTONA 25MG / D, FUROSEMIDA 40MG / D, MONOCORDIL 20MG 2X/D \n* ECOCARDIOGRAMA DEZ/2013 Ao 34 / AE 62 / VD 21 / DDVE 83 / DSVE 63 / SEPTO 12 / PPVE 08 / FE 45% \nREFLUXO MITRAL DISCRETO / PRESENÇA DE FIBRILAÇÃO ATRIAL \nPACIENTE REFERE DISPNEIA AO SUBIR UM LANCE DE ESCADAS, ESTÁ DORMINDO COM 05 TRAVESSEIROS E APRESENTA D.P.N.\nRELATA EDEMA EM MMII DE LEVE INTENSIDADE.\nNEGA DOR TORÁCICA, SÍNCOPE OU PALPITAÇÕES. \nPA 120/80 MMHG, FC 88 BPM\nMV+ BILATERAL SEM RA\nRC IRREGULAR, SOPRO SISTÓLICO MITRAL 3+ / 6+\nBOA PERFUSÃO PERIFÉRICA\nEDEMA MMII 1+ / 4+ \nGLICOSE 92 / URÉIA 24 / CREATININA 0,96 \nA # ICC + INSUF MITRAL 2ª + FA ? \nP # SOLICITO ECG + NOVO ECOCARDIOGRAMA TRANSTORÁCICO\nAUMENTO CARVEDILOL 12,5 MG 12/12H E ENALAPRIL 20MG 12/12H\nORIENTO INICIO DE ANTICOAGULAÇÃO\nORIENTO PEGAR O LAUDO DO CATETERISMO NA SANTA CASA \n\n \n \n \n ",
  "entities": {
    "Atividade de Assistência à Saúde": [
      "CONSULTA",
      "DIAGNÓSTICO",
      "SOLICITO",
      "AUMENTO",
      "ORIENTO"
    ],
    "Doença ou Síndrome": [
      "HAS",
      "IAM",
      "ETILISMO",
      "ICC",
      "FA",
      "FIBRILAÇÃO ATRIAL",
      "INSUF MITRAL 2ª"
    ],
    "Abreviação": [
      "HAS",
      "IAM",
      "ICC",
      "D",
      "MMII",
      "PA",
      "FC",
      "RA",
      "FA",
      "ECG",
      "Ao 34",
      "AE 62",
      "VD 21",
      "DDVE 83",
      "DSVE 63",
      "PPVE 08",
      "FE 45%",
      "MV+ BILATERAL",
      "RC IRREGULAR",
      "INSUF MITRAL 2ª"
    ],
    "Achado": [
      "EX-TABAGISTA",
      "DORMINDO COM 05 TRAVESSEIROS",
      "MV+ BILATERAL",
      "BOA PERFUSÃO PERIFÉRICA"
    ],
    "Negação": [
      "NEGA",
      "SEM"
    ],
    "Produto Intelectual": [
      "DIAGNÓSTICO"
    ],
    "Substância Farmacológica": [
      "MEDICAÇÕES",
      "ENALAPRIL",
      "CARVEDILOL",
      "ESPIRONOLACTONA",
      "FUROSEMIDA",
      "MONOCORDIL"
    ],
    "Aminoácido, Peptídeo ou Proteína": [
      "ENALAPRIL"
    ],
    "Conceito Quantitativo": [
      "10MG",
      "20MG",
      "2X/D",
      "6 , 25 MG",
      "120/80 MMHG",
      "88 BPM",
      "3+ / 6+",
      "12 , 5 MG"
    ],
    "Conceito Temporal": [
      "12/12H",
      "D",
      "2X/D",
      "HÁ 04 ANOS"
    ],
    "Substância Química Orgânica": [
      "CARVEDILOL",
      "ESPIRONOLACTONA",
      "FUROSEMIDA",
      "MONOCORDIL"
    ],
    "Procedimento Diagnóstico": [
      "ECOCARDIOGRAMA",
      "ECG",
      "ECOCARDIOGRAMA TRANSTORÁCICO"
    ],
    "Paciente ou Grupo com Deficiência": [
      "PACIENTE"
    ],
    "Sinal ou Sintoma": [
      "EDEMA",
      "SÍNCOPE",
      "PALPITAÇÕES",
      "RA",
      "REFLUXO MITRAL DISCRETO",
      "DISPNEIA AO SUBIR UM LANCE DE ESCADAS",
      "LEVE INTENSIDADE",
      "DOR TORÁCICA",
      "RC IRREGULAR",
      "SOPRO SISTÓLICO MITRAL"
    ],
    "Localização ou Região Corporal": [
      "MMII"
    ],
    "Atributo Clínico": [
      "PA",
      "FC"
    ],
    "Procedimento Terapêutico ou Preventivo": [
      "CATETERISMO",
      "CIRURGIA BARIÁTRICA"
    ],
    "Resultado Laboratorial ou de Teste": [
      "Ao 34",
      "AE 62",
      "VD 21",
      "DDVE 83",
      "DSVE 63",
      "SEPTO 12",
      "PPVE 08",
      "FE 45%",
      "REFLUXO MITRAL DISCRETO",
      "FIBRILAÇÃO ATRIAL",
      "GLICOSE 92",
      "URÉIA 24",
      "CREATININA 0 , 96"
    ],
    "Conceito Qualitativo": [
      "LEVE INTENSIDADE"
    ],
    "Organização Relacionada à Saúde": [
      "SANTA CASA"
    ]
  },
  "labels": {}
}