{
  "prontuario_id": 911,
  "text": "# IC ETIOLOGIA ISQUEMICA\n# IAM EM 27/08/2010\n# POT ATC C STENT\n# POT RVM 2011 MIE - DA /  SF - DIAG\nEM USO DE CARVEDILOL 50 / DIA + ROSUVA 10 + VALSARTAN 320 + FURO 40  + APRESOLINA 100 / DIA + ESPIRO 25 + AAS 100 + MONOC 20 / DIA + MTF 850 3X + LEVOTIROX 50 + INDAPAMIDA 1,5\nS # ESTÁVEL, NEGA PRECORDIALGIA, REFERE DISPNEIA AOS GRANDES ESFORÇOS.\nSEM EDEMA DE MMII, MANTEM USO REGULAR DE MEDICAÇÕES.\nREFERE SOMENTE PERDA DA POTENCIA SEXUAL\nTROUXE NOVA CINTILO (06/10/14): HIPOPERFUSÃO PERSISTENTE ( FIBROSE ) DE GRANDE EXTENSÃO, NO SEGMENTO MEIO APICAL DA PAREDE ANTERIOR E ÁPICE DE VE, EM GRAU DISCRETO NA PAREDE ANTEROSSEPTAL FE REPOUSO 49%\nO # PA 110X70    FC 79  SAT 98%\nCORADO, HIDRATADO, EUVOLEMICO, EUPNEICO\nBCRNF SS 2T\nMV+ SIM BILART SRA\nABD SP\nMMII S EDEMA\nA # IC ISQUEMICA\nP # MANTENHO MEDICAÇÕES\nRETORNO EM 6 MESES COM ECOTT\nORIENTO DIMINUIR GRADATIVAMENTE O MONOCORDIL, CASO SUPORTE SEM DISPNEIA, VER POSSIBILIDADE DO USO DE CIALIS / VIAGRA.\n \n \n \n ",
  "entities": {
    "Abreviação": [
      "IAM",
      "MIE",
      "DA",
      "SF",
      "DIAG",
      "ROSUVA",
      "FURO",
      "ESPIRO",
      "AAS",
      "MONOC",
      "MTF",
      "MMII",
      "CINTILO",
      "PA",
      "FC",
      "SAT",
      "BCRNF",
      "SS",
      "2T",
      "MV+",
      "SIM",
      "BILART",
      "SRA",
      "ABD",
      "SP",
      "S",
      "ECOTT",
      "SEGMENTO MEIO APICAL DA PAREDE ANTERIOR E ÁPICE DE VE",
      "FE REPOUSO 49%",
      "IC ISQUEMICA"
    ],
    "Doença ou Síndrome": [
      "IAM",
      "IC ISQUEMICA"
    ],
    "Conceito Temporal": [
      "POT",
      "DIA",
      "3X",
      "2T",
      "6 MESES"
    ],
    "Procedimento Terapêutico ou Preventivo": [
      "ATC",
      "STENT",
      "RVM"
    ],
    "Dispositivo Médico": [
      "STENT"
    ],
    "Localização ou Região Corporal": [
      "MIE",
      "MMII",
      "ABD"
    ],
    "Parte do Corpo, Órgão ou Componente Orgânico": [
      "DA",
      "SF",
      "DIAG"
    ],
    "Substância Farmacológica": [
      "CARVEDILOL",
      "ROSUVA",
      "VALSARTAN",
      "FURO",
      "APRESOLINA",
      "ESPIRO",
      "AAS",
      "MONOC",
      "MTF",
      "LEVOTIROX",
      "INDAPAMIDA",
      "MEDICAÇÕES",
      "MONOCORDIL",
      "CIALIS",
      "VIAGRA"
    ],
    "Substância Química Orgânica": [
      "CARVEDILOL",
      "ROSUVA",
      "VALSARTAN",
      "FURO",
      "APRESOLINA",
      "ESPIRO",
      "AAS",
      "MONOC",
      "MTF",
      "INDAPAMIDA",
      "MONOCORDIL",
      "CIALIS",
      "VIAGRA"
    ],
    "Conceito Quantitativo": [
      "10",
      "320",
      "40",
      "25",
      "100",
      "850",
      "3X",
      "50",
      "110X70",
      "79",
      "98%",
      "1 , 5"
    ],
    "Aminoácido, Peptídeo ou Proteína": [
      "LEVOTIROX"
    ],
    "Hormônio": [
      "LEVOTIROX"
    ],
    "Achado": [
      "ESTÁVEL",
      "CORADO",
      "HIDRATADO",
      "EUVOLEMICO",
      "EUPNEICO",
      "BCRNF",
      "2T",
      "MV+",
      "SIM",
      "SRA",
      "SP",
      "USO REGULAR"
    ],
    "Negação": [
      "NEGA",
      "SEM",
      "SS",
      "SRA",
      "SP",
      "S"
    ],
    "Sinal ou Sintoma": [
      "PRECORDIALGIA",
      "EDEMA",
      "SS",
      "DISPNEIA",
      "ETIOLOGIA ISQUEMICA",
      "DISPNEIA AOS GRANDES ESFORÇOS",
      "PERDA DA POTENCIA SEXUAL"
    ],
    "Procedimento Diagnóstico": [
      "CINTILO",
      "ECOTT"
    ],
    "Atributo Clínico": [
      "PA",
      "FC",
      "SAT"
    ],
    "Conceito Qualitativo": [
      "SIM",
      "DIMINUIR GRADATIVAMENTE"
    ],
    "Conceito Espacial": [
      "BILART"
    ],
    "Atividade de Assistência à Saúde": [
      "MANTENHO",
      "RETORNO",
      "ORIENTO"
    ],
    "Resultado Laboratorial ou de Teste": [
      "HIPOPERFUSÃO PERSISTENTE ( FIBROSE ) DE GRANDE EXTENSÃO",
      "SEGMENTO MEIO APICAL DA PAREDE ANTERIOR E ÁPICE DE VE",
      "GRAU DISCRETO NA PAREDE ANTEROSSEPTAL",
      "FE REPOUSO 49%"
    ]
  },
  "labels": {}
}