{
  "prontuario_id": 464,
  "text": "Lucas, 60 ANOS\n# IC ETIOLOGIA ISQUEMICA\n# IAM EM 27/08/2010\n# POT ATC C STENT\n# POT RVM 2011 MIE - DA / SF - DIAG\n# EM USO DE:\n- CARVEDILOL 25MG 12/12HS\n- ROSUVA 10 \n- VALSARTAN 320 \n- FURO 40\n- APRESOLINA 50MG 12/12HS \n- ESPIRO 25 \n- AAS 100 \n- MONOC 20MG NOITE\n- MTF 850 3X\n- LEVOTIROX 50 \n- INDAPAMIDA 1,5\nS # RELATA DISPNEIA PARA MODERADOS ESFORÇOS. NEGA DOR PRECORDIAL, EDEMA DE MMII, ORTOPNEIA E DPN. \n- CINTILO (06/10/14): HIPOPERFUSÃO PERSISTENTE ( FIBROSE ) DE GRANDE EXTENSÃO, NO SEGMENTO MEDIOAPICAL DA PAREDE ANTERIOR E ÁPICE DE VE, EM GRAU DISCRETO NA PAREDE ANTEROSSEPTAL. FE REPOUSO 49%\n- ECO 17/09/15: AE 42, VD 26, SE 10, PP 9, DD 55, DS 46, FE 34%, PSAP 49 MMHG. VE ACINESIA ANTERO-SEPTAL E ANTERIOR MEDIO-APICAL E APICAL.\n- LAB : 23/04/15: K 5,1, CR 1,03, T4 LIVRE 2,26 ( 1,74 )\nO # \nPA 100/60, FC 72 SAT 98%\nCORADO, HIDRATADO, EUPNEICO\nBCRNF SS 2T\nMV+ SIM BILART SRA\nABD SP\nMMII S EDEMA\nA # IC ISQUEMICA\nP # MANTENHO MEDICAÇÕES\n- SOLICITO NOVOS EXAMES LABORATORIAIS ( AVALIAR FUNÇÃO DA TIREOIDE - T4 ACIMA DO VALOR DE REFERENCIA E FUNÇÃO RENAL K 5,1)\n- DEMAIS MANTIDO\n- RETORNO EM 4 MESES\n \n \n \n ",
  "entities": {
    "Abreviação": [
      "IAM",
      "POT",
      "ATC",
      "RVM",
      "MIE",
      "DA",
      "SF",
      "DIAG",
      "12/12HS",
      "ROSUVA",
      "FURO",
      "ESPIRO",
      "AAS",
      "MONOC",
      "MTF",
      "3X",
      "LEVOTIROX",
      "MMII",
      "DPN",
      "CINTILO",
      "ECO",
      "LAB",
      "PA",
      "FC",
      "SRA",
      "S",
      "SEGMENTO MEDIOAPICAL DA PAREDE ANTERIOR E ÁPICE DE VE",
      "FE REPOUSO 49%",
      "AE 42",
      "VD 26",
      "SE 10",
      "PP 9",
      "DD 55",
      "DS 46",
      "FE 34%",
      "PSAP 49 MMHG",
      "VE ACINESIA ANTERO-SEPTAL E ANTERIOR MEDIO-APICAL E APICAL",
      "K 5 , 1",
      "CR 1 , 03",
      "MV+ SIM BILART",
      "IC ISQUEMICA"
    ],
    "Doença ou Síndrome": [
      "IAM",
      "IC ISQUEMICA"
    ],
    "Conceito Temporal": [
      "POT",
      "12/12HS",
      "NOITE"
    ],
    "Procedimento Terapêutico ou Preventivo": [
      "ATC",
      "STENT",
      "RVM"
    ],
    "Dispositivo Médico": [
      "STENT"
    ],
    "Localização ou Região Corporal": [
      "MIE",
      "MMII",
      "ABD"
    ],
    "Parte do Corpo, Órgão ou Componente Orgânico": [
      "DA",
      "SF",
      "DIAG"
    ],
    "Substância Química Orgânica": [
      "CARVEDILOL",
      "ROSUVA",
      "VALSARTAN",
      "FURO",
      "APRESOLINA",
      "ESPIRO",
      "AAS",
      "MONOC",
      "MTF",
      "LEVOTIROX",
      "INDAPAMIDA"
    ],
    "Substância Farmacológica": [
      "CARVEDILOL",
      "ROSUVA",
      "VALSARTAN",
      "FURO",
      "APRESOLINA",
      "ESPIRO",
      "AAS",
      "MONOC",
      "MTF",
      "LEVOTIROX",
      "INDAPAMIDA",
      "MEDICAÇÕES"
    ],
    "Conceito Quantitativo": [
      "25MG",
      "12/12HS",
      "10",
      "320",
      "40",
      "50MG",
      "25",
      "100",
      "20MG",
      "850",
      "3X",
      "50",
      "100/60",
      "72",
      "98%",
      "1 , 5"
    ],
    "Hormônio": [
      "LEVOTIROX"
    ],
    "Negação": [
      "NEGA",
      "SS",
      "SRA",
      "SP",
      "S"
    ],
    "Sinal ou Sintoma": [
      "EDEMA",
      "ORTOPNEIA",
      "DPN",
      "ETIOLOGIA ISQUEMICA",
      "DISPNEIA PARA MODERADOS ESFORÇOS",
      "DOR PRECORDIAL",
      "T4 ACIMA DO VALOR DE REFERENCIA"
    ],
    "Procedimento Diagnóstico": [
      "CINTILO",
      "ECO"
    ],
    "Procedimento Laboratorial": [
      "LAB",
      "EXAMES LABORATORIAIS",
      "FUNÇÃO DA TIREOIDE",
      "FUNÇÃO RENAL"
    ],
    "Atributo Clínico": [
      "PA",
      "FC",
      "SAT"
    ],
    "Achado": [
      "CORADO",
      "HIDRATADO",
      "EUPNEICO",
      "SRA",
      "MV+ SIM BILART"
    ],
    "Atividade de Assistência à Saúde": [
      "MANTENHO",
      "SOLICITO",
      "AVALIAR",
      "MANTIDO"
    ],
    "Resultado Laboratorial ou de Teste": [
      "HIPOPERFUSÃO PERSISTENTE ( FIBROSE ) DE GRANDE EXTENSÃO",
      "SEGMENTO MEDIOAPICAL DA PAREDE ANTERIOR E ÁPICE DE VE",
      "GRAU DISCRETO NA PAREDE ANTEROSSEPTAL",
      "FE REPOUSO 49%",
      "AE 42",
      "VD 26",
      "SE 10",
      "PP 9",
      "DD 55",
      "DS 46",
      "FE 34%",
      "PSAP 49 MMHG",
      "VE ACINESIA ANTERO-SEPTAL E ANTERIOR MEDIO-APICAL E APICAL",
      "K 5 , 1",
      "CR 1 , 03",
      "T4 LIVRE 2 , 26"
    ]
  },
  "labels": {}
}