{
  "prontuario_id": 962,
  "text": "Lucas 42 ANOS\nCANDIDATA A DOAÇÃO PARA SUA IRMÃ > Lucas\nNEGA HAS, DM, UROLITÍASE, ITU, CARDIOPATIAS, ACIDO ÚRICO, GOTA, USO DE AINES\nTABAGISTA HÁ 30 ANOS\nG3 P2 \nNEGA CIRURGIA ABDOMINAL \nEM USO DE ANTICONCEPCIONAL \nALT 172\nPESO 81KG\nPA 120/80\nMUCOSAS CORADAS\nCPP RONCOS \nABDOME GLOBOSO, RHA+, SEM VCM\nPC BULHAS RITMICAS SEM SOPROS\nMEBROS SEM EDEMA \nORIENTO SOBRE RISCOS INERENTES AO PROCEDIMENTO\nLIBERADO PRA CIRURGIA\nASA 2\nABO O \nSOROLOGIAS CMV +, EBV +\nANGIOTC CALCULO 2MM ( ACHADO ) NO POS LO SUPERIOR RIM ESQUERDO\nESTUDO METABÓLICO NORMAL \nECOCARDIO NORMAL \nRX DE TORAX NORMAL \nECG E TE NORMAIS \nECOGRAFIA ABDOME NORMAL\n ",
  "entities": {
    "Paciente ou Grupo com Deficiência": [
      "CANDIDATA"
    ],
    "Procedimento Terapêutico ou Preventivo": [
      "DOAÇÃO",
      "P2",
      "PROCEDIMENTO",
      "CIRURGIA",
      "CIRURGIA ABDOMINAL"
    ],
    "Grupo Familiar": [
      "IRMÃ"
    ],
    "Negação": [
      "NEGA",
      "SEM"
    ],
    "Abreviação": [
      "HAS",
      "DM",
      "ITU",
      "AINES",
      "ALT",
      "PA",
      "RHA+",
      "VCM",
      "PC",
      "ANGIOTC",
      "ECOCARDIO",
      "ECG",
      "TE",
      "CMV +",
      "EBV +",
      "POS LO SUPERIOR RIM ESQUERDO",
      "RX DE TORAX"
    ],
    "Doença ou Síndrome": [
      "HAS",
      "DM",
      "UROLITÍASE",
      "ITU",
      "CARDIOPATIAS",
      "GOTA",
      "TABAGISTA"
    ],
    "Substância Farmacológica": [
      "AINES",
      "ANTICONCEPCIONAL"
    ],
    "Atributo Clínico": [
      "ALT",
      "PESO",
      "PA",
      "PC"
    ],
    "Conceito Quantitativo": [
      "172",
      "120/80"
    ],
    "Localização ou Região Corporal": [
      "CPP",
      "ABDOME",
      "MEBROS"
    ],
    "Sinal ou Sintoma": [
      "GLOBOSO",
      "VCM",
      "SOPROS",
      "EDEMA"
    ],
    "Achado": [
      "RHA+",
      "MUCOSAS CORADAS",
      "BULHAS RITMICAS",
      "ASA 2",
      "ABO O"
    ],
    "Função Patológica": [
      "EDEMA"
    ],
    "Atividade de Assistência à Saúde": [
      "ORIENTO"
    ],
    "Ideia ou Conceito": [
      "RISCOS"
    ],
    "Procedimento Laboratorial": [
      "SOROLOGIAS",
      "ACIDO ÚRICO",
      "ESTUDO METABÓLICO"
    ],
    "Procedimento Diagnóstico": [
      "ANGIOTC",
      "ECOCARDIO",
      "ECG",
      "TE",
      "ESTUDO METABÓLICO",
      "RX DE TORAX",
      "ECOGRAFIA ABDOME"
    ],
    "Resultado Laboratorial ou de Teste": [
      "NORMAL",
      "NORMAIS",
      "CMV +",
      "EBV +",
      "CALCULO 2MM",
      "POS LO SUPERIOR RIM ESQUERDO",
      "RX DE TORAX"
    ],
    "Classificação": [
      "ASA 2"
    ]
  },
  "labels": {}
}