{
  "prontuario_id": 428,
  "text": "ID: Lucas, 21 anos, natural de curitiba-PR, procedente de curitiba-PR, estoquista, solteiro\nQP: cicatriz no peito \nHMA: Paciente relata cirurgia para troca valvar há 4 meses sem complicações,relatando cicatriz em região esternal .Nega prurido ou aumento de tamanho ou dor.Relata usar hidratande no local\nHMP: Relata cateterismo há 12 anos. Nega internamentos prévios. nega transfusões. Nega alergias. Nega doenças de infância. Nega diabetes. Nega hipertensão. Nega cicatrizes hipetróficas prévias\nEm uso de AAS e Enalapril há 4 meses \nHMF: sem paricularidades, nega histórico de queloide na família\nCHV: nega etilismo. Nega tabagismo. Relata atividade aeróbia diária há 2 meses\nEXAME FISICO: BEG, LOTE. ANICTÉRICO,ACIANÓTICO\nPA: 140x90mmhg\nFC: 75bpm\nFR: 15rpm\nEXAME DERMATOLÓGICO: \nCicatriz hipertrófica em região esternal  de aproximadamente 20 cm, progredindo desde a fúrcula esternal até 2 cm abaixo do processo xifóide ,com diâmetro na metade superior de aproximadamente 3 cm e metade inferior de aproximadamente 1 cm, eritematosa e brilhante.Sensibilidade preservada. lesã papulosa em região do processo xifoide de aproximadanete 1cmx1cm com crostas. Não pruriginosa,não dolorosa. \n2 lesões em região epigástrica de aproximadamente 3cm x 3cm hiperemiadas, hipertróficas\nLesões em máculas hiperemiadas e pústulas difusas em região de tórax,dorso e face\nManchas hipercrômicas difusas em região de dorso e tórax\nExame cardiológico: BRNF 2T SS em focos aórtico, pulmonar, tricúspede a aórtico acessório. Hipofonese de bulha em foco mitral\nExame pulmonar: sp\nExame abdominal: sp\ncicatriz hipetrófica imatura\n \n \n ",
  "entities": {
    "Achado": [
      "QP",
      "HMA",
      "HMP",
      "HMF",
      "CHV",
      "BEG",
      "LOTE",
      "ANICTÉRICO",
      "ACIANÓTICO",
      "BRNF",
      "2T",
      "SS",
      "sp",
      "Sensibilidade preservada"
    ],
    "Abreviação": [
      "QP",
      "HMA",
      "HMP",
      "AAS",
      "HMF",
      "CHV",
      "BEG",
      "LOTE",
      "PA",
      "FC",
      "FR",
      "BRNF",
      "2T",
      "SS",
      "sp"
    ],
    "Função Patológica": [
      "cicatriz",
      "Cicatriz"
    ],
    "Paciente ou Grupo com Deficiência": [
      "Paciente"
    ],
    "Negação": [
      "sem",
      "Nega",
      "nega",
      "ANICTÉRICO",
      "ACIANÓTICO",
      "Não",
      "não",
      "SS",
      "sp"
    ],
    "Sinal ou Sintoma": [
      "complicações",
      "prurido",
      "dor",
      "paricularidades",
      "eritematosa",
      "brilhante",
      "crostas",
      "pruriginosa",
      "dolorosa",
      "lesões",
      "hiperemiadas",
      "hipertróficas",
      "máculas",
      "aumento de tamanho",
      "cicatrizes hipetróficas",
      "lesã papulosa",
      "pústulas difusas",
      "Manchas hipercrômicas difusas",
      "Hipofonese de bulha",
      "cicatriz hipetrófica imatura"
    ],
    "Substância Farmacológica": [
      "hidratande",
      "AAS",
      "Enalapril"
    ],
    "Localização ou Região Corporal": [
      "local",
      "dorso",
      "face",
      "tórax",
      "pulmonar",
      "tricúspede",
      "no peito",
      "região esternal",
      "2 cm abaixo do processo xifóide",
      "processo xifoide",
      "região epigástrica",
      "região de tórax",
      "região de dorso",
      "focos aórtico",
      "aórtico acessório",
      "foco mitral"
    ],
    "Procedimento Diagnóstico": [
      "cateterismo",
      "EXAME FISICO",
      "EXAME DERMATOLÓGICO",
      "Exame cardiológico",
      "Exame pulmonar",
      "Exame abdominal"
    ],
    "Procedimento Terapêutico ou Preventivo": [
      "cateterismo",
      "transfusões",
      "cirurgia para troca valvar"
    ],
    "Atividade de Assistência à Saúde": [
      "internamentos",
      "atividade aeróbia",
      "EXAME FISICO",
      "EXAME DERMATOLÓGICO",
      "Exame cardiológico",
      "Exame pulmonar",
      "Exame abdominal"
    ],
    "Conceito Temporal": [
      "prévios",
      "prévias",
      "diária",
      "há 4 meses",
      "há 12 anos",
      "há 2 meses"
    ],
    "Doença ou Síndrome": [
      "alergias",
      "diabetes",
      "hipertensão",
      "etilismo",
      "tabagismo",
      "doenças de infância"
    ],
    "Substância Química Orgânica": [
      "AAS",
      "Enalapril"
    ],
    "Anormalidade Adquirida": [
      "queloide"
    ],
    "Grupo Familiar": [
      "família"
    ],
    "Atributo Clínico": [
      "PA",
      "FC",
      "FR"
    ],
    "Conceito Quantitativo": [
      "140x90mmhg",
      "75bpm",
      "15rpm",
      "1cmx1cm",
      "2",
      "20 cm",
      "3cm x 3cm"
    ],
    "Conceito Qualitativo": [
      "hipertrófica",
      "progredindo",
      "eritematosa",
      "brilhante",
      "hipertróficas",
      "hiperemiadas",
      "Sensibilidade preservada"
    ],
    "Lesão ou Envenenamento": [
      "lesões",
      "Lesões"
    ],
    "Parte do Corpo, Órgão ou Componente Orgânico": [
      "fúrcula esternal"
    ]
  },
  "labels": {}
}