{
  "prontuario_id": 290,
  "text": "COMORBIDADES:\n# MCP DILATADA / CHAGAS\n# HAS, DISLIPIDEMIA, DAC FAMILIAR\n# MARCA-PASSO HÁ 5 ANOS --> 11 MESES DE BATERIA\n# CHV: EX-TABAGISTA DE 38 MAÇOS-ANO PAROU HA 7 ANOS.\nCATE DO DIA 29/07/2014: PROTOCOLO PRÉ - TRANSPLANTE CARDÍACO REALIZADO COM SUCESSO; RVP WOOD POSITIVA: CANDIDATO A TRANSPLANTE\nMEDICAMENTOS:\n# APRESOLINA 50 MG 1 CP DE 12/12 HORAS\n# MONOCORDL 20 MG 1 CP AS 8 E OUTRO AS 14 HORAS\n# ESPIRONOLACTONA 25 MG 1 CP AO DIA\n# FUROSEMIDA 40 MG 2 CP AS 8 E OUTRO AS 14 HORAS\n# CARVEDILOL 25 MG 1 CP DE 12/12 HORAS\n# SINVASTATINA 20 MG 1 CP A NOITE\nEXAMES LAB: CREAT 1,9 // UR 81 // K 5,6\nS # SEM QUEIXSA \no :  PA 100/70 // FC 70\nACV BCRNF CPP LIVRE\nMMII S/P\nP : SUSPENDO ESPIRONO; REDUZO FURO.   RETORNO EM 2 MESES NO AMBU DE ICC\n \n \n \n ",
  "entities": {
    "Doença ou Síndrome": [
      "COMORBIDADES",
      "CHAGAS",
      "HAS",
      "DISLIPIDEMIA",
      "DAC",
      "ICC",
      "MCP DILATADA"
    ],
    "Abreviação": [
      "HAS",
      "DAC",
      "CHV",
      "CATE",
      "PA",
      "FC",
      "ACV",
      "BCRNF",
      "MMII",
      "S/P",
      "ESPIRONO",
      "FURO",
      "MCP DILATADA",
      "1 CP",
      "EXAMES LAB",
      "CREAT 1 , 9",
      "UR 81",
      "K 5 , 6"
    ],
    "Grupo Familiar": [
      "FAMILIAR"
    ],
    "Procedimento Terapêutico ou Preventivo": [
      "MARCA-PASSO",
      "CATE",
      "TRANSPLANTE CARDÍACO"
    ],
    "Dispositivo Médico": [
      "MARCA-PASSO"
    ],
    "Achado": [
      "CHV",
      "EX-TABAGISTA",
      "SUCESSO",
      "BCRNF",
      "S/P"
    ],
    "Procedimento Diagnóstico": [
      "CATE"
    ],
    "Conceito Temporal": [
      "PRÉ",
      "12/12 HORAS",
      "A NOITE"
    ],
    "Atividade de Assistência à Saúde": [
      "REALIZADO",
      "SUSPENDO",
      "REDUZO",
      "RETORNO"
    ],
    "Substância Farmacológica": [
      "MEDICAMENTOS",
      "APRESOLINA",
      "MONOCORDL",
      "ESPIRONOLACTONA",
      "FUROSEMIDA",
      "CARVEDILOL",
      "SINVASTATINA",
      "ESPIRONO",
      "FURO"
    ],
    "Substância Química Orgânica": [
      "CARVEDILOL",
      "SINVASTATINA"
    ],
    "Negação": [
      "SEM",
      "S/P"
    ],
    "Sinal ou Sintoma": [
      "QUEIXSA"
    ],
    "Atributo Clínico": [
      "PA",
      "FC",
      "CPP"
    ],
    "Conceito Quantitativo": [
      "100/70",
      "70",
      "38 MAÇOS-ANO",
      "50 MG",
      "1 CP",
      "20 MG",
      "25 MG",
      "40 MG",
      "2 CP"
    ],
    "Localização ou Região Corporal": [
      "MMII"
    ],
    "Resultado Laboratorial ou de Teste": [
      "CANDIDATO A TRANSPLANTE",
      "CREAT 1 , 9",
      "UR 81",
      "K 5 , 6"
    ],
    "Procedimento Laboratorial": [
      "EXAMES LAB"
    ]
  },
  "labels": {}
}