{
  "prontuario_id": 791,
  "text": "Lucas, 57 anos\nHomoenxerto aortico ( por EAo ) + MIE - DA; RAD - CD; SAF - MG em 2006 - Doutor Vital Brazil. Hipertenso,\nEm uso de: AAS 100 mg dia, losartana 100 mg dia, atovastatina 20 mg 4CP / DIA, atenolol 25mg / dia, furosemida 40mg / dia, omeoprazol 40mg ao dia, ezatimibe 10 mg, Hidantal 100mg - por cisticercose.\nPenicilina G benzatina 1,200,000U IM a cada 21 dia - suspenso em 2013\nDOR REGIAO ESTERNAL, EM FO, LOCAL FIOS AÇO, EM QUEIMAÇÃO. \n- Labs: tg 221 / ct 166 / ldl 76, demais ok \n- Ecocardio 12/08/15: A0 / VD 22 / Septo 11 / FE 66. Homoenxerto aortico com mobilidade ampla folhetps. grad pressao 4mmHg. Regurgitacao grau leve a moderada com jato dirigido valva mitral (?). \nExames:\nEcocardiograma - 26/06/2013: Homoenxerto em posição aórtica normofuncionante. VE hipertrofiado com dimensões normais e fumção sistólica preservada. ALteração\ndo relaxamento do VE AE dilatado. Homoenxerto com mobilidade adequada. FE: 66%\n- Lab (05/02/15): Cr 0,91, CT 174, TGC 197, HDL 44, K 4,8, LDL 90, Glic 107\nAo exame:\nPte em BEG, eupneico, corado, hidratado.\nFC79  PA: 130/80\nCP: sem estase jugular\nAC: BCRNF sem sopros\nAP: MV presente bilateralmente, sem RA.\nmantenho medicações\nencaminho para cir cardiaca para retirada pontos suttura esterno\nretorno 6 meses\ne3 cardio Doutor Vital Brazil \n \n \n \n ",
  "entities": {
    "Abreviação": [
      "EAo",
      "AAS",
      "4CP",
      "IM",
      "FO",
      "Labs",
      "Ecocardio",
      "A0",
      "Lab",
      "Pte",
      "BEG",
      "FC79",
      "PA",
      "CP",
      "AC",
      "AP",
      "RA",
      "MIE - DA",
      "RAD - CD",
      "SAF - MG",
      "tg 221",
      "ct 166",
      "ldl 76",
      "VD 22",
      "FE 66",
      "grad pressao 4mmHg",
      "VE hipertrofiado com dimensões normais e fumção sistólica preservada",
      "ALteração do relaxamento do VE AE dilatado",
      "FE : 66%",
      "Cr 0 , 91",
      "CT 174",
      "TGC 197",
      "HDL 44",
      "K 4 , 8",
      "LDL 90",
      "Glic 107",
      "MV presente bilateralmente",
      "cir cardiaca"
    ],
    "Doença ou Síndrome": [
      "EAo",
      "Hipertenso",
      "cisticercose"
    ],
    "Substância Química Orgânica": [
      "AAS",
      "losartana",
      "atovastatina",
      "atenolol",
      "furosemida",
      "omeoprazol",
      "ezatimibe",
      "Hidantal",
      "Penicilina G benzatina"
    ],
    "Substância Farmacológica": [
      "AAS",
      "losartana",
      "atovastatina",
      "atenolol",
      "furosemida",
      "omeoprazol",
      "ezatimibe",
      "Hidantal",
      "medicações"
    ],
    "Conceito Temporal": [
      "dia",
      "DIA",
      "a cada 21 dia",
      "6 meses"
    ],
    "Conceito Quantitativo": [
      "4CP",
      "25mg",
      "40mg",
      "100mg",
      "130/80",
      "100 mg",
      "20 mg",
      "10 mg",
      "1 , 200 , 000U"
    ],
    "Atividade de Assistência à Saúde": [
      "suspenso",
      "mantenho",
      "encaminho",
      "retirada",
      "retorno"
    ],
    "Localização ou Região Corporal": [
      "ESTERNAL"
    ],
    "Lesão ou Envenenamento": [
      "FO"
    ],
    "Conceito Qualitativo": [
      "QUEIMAÇÃO"
    ],
    "Resultado Laboratorial ou de Teste": [
      "Labs",
      "A0",
      "tg 221",
      "ct 166",
      "ldl 76",
      "demais ok",
      "VD 22",
      "Septo 11",
      "FE 66",
      "Homoenxerto aortico com mobilidade ampla folhetps",
      "grad pressao 4mmHg",
      "Regurgitacao grau leve a moderada com jato dirigido valva mitral",
      "Homoenxerto em posição aórtica normofuncionante",
      "VE hipertrofiado com dimensões normais e fumção sistólica preservada",
      "ALteração do relaxamento do VE AE dilatado",
      "Homoenxerto com mobilidade adequada",
      "FE : 66%",
      "Cr 0 , 91",
      "CT 174",
      "TGC 197",
      "HDL 44",
      "K 4 , 8",
      "LDL 90",
      "Glic 107"
    ],
    "Procedimento Laboratorial": [
      "Labs",
      "Lab"
    ],
    "Procedimento Diagnóstico": [
      "Ecocardio",
      "Ecocardiograma"
    ],
    "Paciente ou Grupo com Deficiência": [
      "Pte"
    ],
    "Achado": [
      "BEG",
      "eupneico",
      "corado",
      "hidratado",
      "MV presente bilateralmente"
    ],
    "Atributo Clínico": [
      "FC79",
      "PA",
      "CP",
      "AC",
      "AP"
    ],
    "Parte do Corpo, Órgão ou Componente Orgânico": [
      "CP",
      "MIE - DA",
      "RAD - CD",
      "SAF - MG"
    ],
    "Negação": [
      "sem"
    ],
    "Sinal ou Sintoma": [
      "sopros",
      "RA",
      "estase jugular"
    ],
    "Procedimento Terapêutico ou Preventivo": [
      "medicações",
      "pontos",
      "Homoenxerto aortico"
    ],
    "Grupo Profissional ou Ocupacional": [
      "cardio",
      "Doutor",
      "cir cardiaca"
    ],
    "Antibiótico": [
      "Penicilina G benzatina"
    ],
    "Dispositivo Médico": [
      "FIOS AÇO"
    ]
  },
  "labels": {}
}