{
  "prontuario_id": 552,
  "text": "Lucas, 58 anos, dona de casa, casada, 1 filha.\nRefere arritmia descoberta há 2 anos. Traz exames\nNega palpitações.\nFaz caminhada 1h dia 3x / semana ( iniciou há um mês )\nRefere dores por artrose, toma dipirona apenas com muita dor\nMãe falecida com problemas cardíacos (?). Pai, 90anos, hipertenso. Sem casos de cancer na família.\nHipertensa há 15 anos. Hipotireoidismo; refere queda de cabelo.\nMenopausa há 4 anos. G 1 P 1 C 1 A 0\nNunca fumou nem bebeu.\nAtenolol 50 mg 2x / dia\nEnalapril 10 mg 2x / dia\nWarfarina 25 mg 2x / dia durante a semana e 1x / dia nos sábados e domingos\nLevotiroxina 25 mcg\nHolter: FA durante toda a gravação com frequencia ventricular média de 87 bpm, variando entre 55 e 135\nRNI:  mês 9: 1,94; 10: 2,31; 12: 3,01\nHAS e FA",
  "entities": {
    "Doença ou Síndrome": [
      "arritmia",
      "artrose",
      "hipertenso",
      "Hipertensa",
      "Hipotireoidismo",
      "FA",
      "HAS"
    ],
    "Procedimento Laboratorial": [
      "exames",
      "RNI"
    ],
    "Resultado Laboratorial ou de Teste": [
      "exames",
      "RNI",
      "frequencia ventricular média de 87 bpm",
      "variando entre 55 e 135",
      "1 , 94",
      "2 , 31",
      "3 , 01"
    ],
    "Negação": [
      "Nega",
      "Sem",
      "Nunca",
      "nem"
    ],
    "Sinal ou Sintoma": [
      "palpitações",
      "dores",
      "dor",
      "queda de cabelo"
    ],
    "Atividade Diária ou Recreativa": [
      "caminhada"
    ],
    "Atividade": [
      "caminhada"
    ],
    "Abreviação": [
      "1h",
      "3x",
      "2x",
      "1x",
      "RNI",
      "HAS",
      "FA",
      "frequencia ventricular média de 87 bpm"
    ],
    "Conceito Temporal": [
      "dia",
      "semana",
      "10",
      "12",
      "há 2 anos",
      "há um mês",
      "há 15 anos",
      "há 4 anos",
      "sábados e domingos",
      "mês 9"
    ],
    "Conceito Quantitativo": [
      "3x",
      "1",
      "0",
      "2x",
      "1x",
      "50 mg",
      "10 mg",
      "25 mg",
      "25 mcg",
      "1 , 94",
      "2 , 31",
      "3 , 01"
    ],
    "Substância Química Orgânica": [
      "dipirona",
      "Atenolol",
      "Enalapril",
      "Warfarina",
      "Levotiroxina"
    ],
    "Substância Farmacológica": [
      "dipirona",
      "Atenolol",
      "Enalapril",
      "Warfarina",
      "Levotiroxina"
    ],
    "Grupo Familiar": [
      "Mãe",
      "Pai",
      "família"
    ],
    "Processo Neoplásico": [
      "cancer"
    ],
    "Função Fisiológica": [
      "Menopausa"
    ],
    "Função de Organismo": [
      "G"
    ],
    "Procedimento Terapêutico ou Preventivo": [
      "P",
      "C"
    ],
    "Comportamento Individual": [
      "fumou",
      "bebeu"
    ],
    "Aminoácido, Peptídeo ou Proteína": [
      "Enalapril",
      "Levotiroxina"
    ],
    "Substância Perigosa ou Venenosa": [
      "Warfarina"
    ],
    "Hormônio": [
      "Levotiroxina"
    ],
    "Procedimento Diagnóstico": [
      "Holter"
    ],
    "Achado": [
      "problemas cardíacos"
    ]
  },
  "labels": {}
}