{
  "prontuario_id": 320,
  "text": "Lucas, 59\n# HAS\n# FA em Anticoagulação\n# Hipotireoidismo\n# Dislipidemia\n# Obesidade\n# Nega HF para DAC\n# Nega tabagismo/etilismo\n# Sem alergias\n# Med em Uso: Atenolol 50mg 12/12h; enalapril  10mg 12/12h; marevan 1 1/2cp todos dias ( seg a sábado ) + 01cp aos domingos LT4 50mcg + SVT 20mg;\n# traz exames lab: \n   - Triglicerídeos 304;\n   - Cr 0,8; U 22; CT 168; HDL 30; HMG normal; TGO e TGp normais;\nS # Sem queixas; nega dispnéia ou palpitação;\nO # Euneica em AA, FC 85; Sp02 96%; Ac B. Arrítmicas; Ap CPP livres; abd sp MMII sem edema; P 90Kg; IMC 31,88\nA # Oriento atividade física; Solicito novos exames; Verificar Triglicerídeos na próxima consulta;\n      Solicito novo Ecocardio ( Há mais de 1 ano q não faz ); mantenho medicamentos; retorno em 3 meses\n \n \n \n ",
  "entities": {
    "Abreviação": [
      "HAS",
      "FA",
      "HF",
      "DAC",
      "12/12h",
      "seg",
      "01cp",
      "LT4",
      "SVT",
      "FC",
      "Sp02",
      "Ac",
      "B",
      "Ap",
      "MMII",
      "Ecocardio",
      "1 1/2cp",
      "exames lab",
      "Cr 0 , 8",
      "U 22",
      "CT 168",
      "HDL 30",
      "HMG normal",
      "TGO e TGp normais",
      "Euneica em AA",
      "CPP livres"
    ],
    "Doença ou Síndrome": [
      "HAS",
      "FA",
      "Hipotireoidismo",
      "Dislipidemia",
      "Obesidade",
      "DAC",
      "tabagismo/etilismo"
    ],
    "Procedimento Terapêutico ou Preventivo": [
      "Anticoagulação",
      "Med",
      "medicamentos"
    ],
    "Negação": [
      "Nega",
      "Sem",
      "nega",
      "sem"
    ],
    "Achado": [
      "HF",
      "B",
      "Euneica em AA",
      "CPP livres"
    ],
    "Função Patológica": [
      "alergias"
    ],
    "Substância Farmacológica": [
      "Atenolol",
      "enalapril",
      "marevan",
      "LT4",
      "SVT",
      "medicamentos"
    ],
    "Substância Química Orgânica": [
      "Atenolol",
      "enalapril",
      "marevan",
      "LT4",
      "SVT"
    ],
    "Conceito Quantitativo": [
      "50mg",
      "10mg",
      "12/12h",
      "01cp",
      "50mcg",
      "20mg",
      "85",
      "96%",
      "1 1/2cp",
      "31 , 88"
    ],
    "Conceito Temporal": [
      "12/12h",
      "domingos",
      "todos dias",
      "3 meses"
    ],
    "Aminoácido, Peptídeo ou Proteína": [
      "enalapril",
      "LT4"
    ],
    "Hormônio": [
      "LT4"
    ],
    "Sinal ou Sintoma": [
      "queixas",
      "dispnéia",
      "palpitação",
      "Arrítmicas",
      "edema"
    ],
    "Atributo Clínico": [
      "FC",
      "Sp02",
      "Ac",
      "Ap",
      "P"
    ],
    "Parte do Corpo, Órgão ou Componente Orgânico": [
      "MMII"
    ],
    "Procedimento Diagnóstico": [
      "IMC",
      "Ecocardio"
    ],
    "Atividade de Assistência à Saúde": [
      "Oriento",
      "Solicito",
      "Verificar",
      "consulta",
      "mantenho",
      "retorno"
    ],
    "Procedimento Laboratorial": [
      "exames",
      "exames lab"
    ],
    "Resultado Laboratorial ou de Teste": [
      "Triglicerídeos",
      "Triglicerídeos 304",
      "Cr 0 , 8",
      "U 22",
      "CT 168",
      "HDL 30",
      "HMG normal",
      "TGO e TGp normais"
    ],
    "Atividade Diária ou Recreativa": [
      "atividade física"
    ]
  },
  "labels": {}
}