{
  "prontuario_id": 23,
  "text": "Lucas, 62 anos\n# EAo \n# HAS\n# Uso: Atenol 50 - 1xd. Enalapril 5 - 12/12h.\n# Sem queixas cardiovasculares.\nEcocardio (13/02/15): AE = 45; SIV = PPVE = 14mm; DDVE = 48; DSVE = 29; FE = 69%. VMi = folhetos espessados, abertura preservada, refluxo discreto, fluxo diastólico com padrão E<A  VAo = cúspides calcificadas, com dupla lesão; Grad max de 54 e medio de 28mmHg. VP = ok; Vtri = folhetos espessados, abertura preservada, insuficiente, PSAP = 39mmHg. VE = hipertrofiado, cavidade, função sistólica e contração preservadas,alt de relaxamento. AD = aumentado.\nEco (14/04/16) RA: 38 AE: 45  VD: 20 S: 14 PP: 14 VE: 50 / 30 FE: 70% \nAO: CUSPIDES CALCIFICADAS, COM DUPLA LESAO. GRAD MAX = 43  MEDIO 25.\nINSUF TRICU DISCRETA ( PSAP 39 )\nREFLUXO MITRAL DISCRETO. \nAO ASC: 41MM\nS. Nega dispneia, dor toracica, sincope. Nega edema de MMII. Refere controle pressorico bom em casa, porem nas consultas sempre apresenta elevação de PA. Sd Jaleco Branco ?)\nBEG, eupneico, acianotico, anicterico\nPA: 170/100 mmHg, P = 99 spm\nMV normodist sem ruidos . \nRCR, 2T, taquicardico, ss ++/6+,\ncrsec / decres, FAO, irradiação para todo o precórdio.\nA # DUPLA LESAO AO ESTENOSE MOD + INSUF DISCRETA\nP # aumento Enalapril 20mg 2x d e inicio HCTZ 25mg / dia . retorno em 1 ano com novo eco\nR4 cardio Doutor Vital Brazil ",
  "entities": {
    "Abreviação": [
      "EAo",
      "HAS",
      "1xd",
      "12/12h",
      "Ecocardio",
      "Eco",
      "MMII",
      "BEG",
      "PA",
      "P",
      "RCR",
      "2T",
      "FAO",
      "d",
      "HCTZ",
      "eco",
      "R4",
      "AE = 45",
      "SIV = PPVE = 14mm",
      "DDVE = 48",
      "DSVE = 29",
      "FE = 69%",
      "Grad max de 54 e medio de 28mmHg",
      "VP = ok",
      "Vtri = folhetos espessados , abertura preservada , insuficiente",
      "PSAP = 39mmHg",
      "VE = hipertrofiado , cavidade",
      "alt de relaxamento",
      "AD = aumentado",
      "RA : 38",
      "AE : 45",
      "VD : 20",
      "S : 14",
      "PP : 14",
      "VE : 50 / 30",
      "FE : 70%",
      "AO : CUSPIDES CALCIFICADAS , COM DUPLA LESAO",
      "GRAD MAX = 43 MEDIO 25",
      "INSUF TRICU DISCRETA ( PSAP 39 )",
      "AO ASC : 41MM S",
      "elevação de PA",
      "Sd Jaleco Branco",
      "MV normodist",
      "crsec / decres",
      "DUPLA LESAO AO ESTENOSE MOD",
      "INSUF DISCRETA"
    ],
    "Doença ou Síndrome": [
      "EAo",
      "HAS",
      "Sd Jaleco Branco"
    ],
    "Substância Farmacológica": [
      "Atenol",
      "Enalapril",
      "HCTZ"
    ],
    "Substância Química Orgânica": [
      "Atenol",
      "Enalapril",
      "HCTZ"
    ],
    "Conceito Quantitativo": [
      "50",
      "1xd",
      "5",
      "20mg",
      "2x",
      "25mg",
      "170/100 mmHg",
      "99 spm"
    ],
    "Aminoácido, Peptídeo ou Proteína": [
      "Enalapril"
    ],
    "Conceito Temporal": [
      "12/12h",
      "d",
      "dia",
      "1 ano"
    ],
    "Negação": [
      "Sem",
      "Nega",
      "sem"
    ],
    "Sistema Corporal": [
      "cardiovasculares"
    ],
    "Procedimento Diagnóstico": [
      "Ecocardio",
      "Eco",
      "eco"
    ],
    "Sinal ou Sintoma": [
      "dispneia",
      "sincope",
      "edema",
      "ruidos",
      "dor toracica",
      "irradiação para todo o precórdio"
    ],
    "Localização ou Região Corporal": [
      "MMII",
      "FAO"
    ],
    "Atividade de Assistência à Saúde": [
      "consultas",
      "aumento",
      "inicio",
      "retorno"
    ],
    "Achado": [
      "BEG",
      "eupneico",
      "acianotico",
      "anicterico",
      "RCR",
      "2T",
      "controle pressorico bom em casa",
      "elevação de PA",
      "MV normodist",
      "crsec / decres",
      "DUPLA LESAO AO ESTENOSE MOD",
      "INSUF DISCRETA"
    ],
    "Atributo Clínico": [
      "PA",
      "P"
    ],
    "Grupo Profissional ou Ocupacional": [
      "R4",
      "cardio",
      "Doutor"
    ],
    "Resultado Laboratorial ou de Teste": [
      "AE = 45",
      "SIV = PPVE = 14mm",
      "DDVE = 48",
      "DSVE = 29",
      "FE = 69%",
      "folhetos espessados , abertura preservada , refluxo discreto",
      "fluxo diastólico com padrão",
      "cúspides calcificadas , com dupla lesão",
      "Grad max de 54 e medio de 28mmHg",
      "VP = ok",
      "Vtri = folhetos espessados , abertura preservada , insuficiente",
      "PSAP = 39mmHg",
      "VE = hipertrofiado , cavidade",
      "função sistólica e contração preservadas",
      "alt de relaxamento",
      "AD = aumentado",
      "RA : 38",
      "AE : 45",
      "VD : 20",
      "S : 14",
      "PP : 14",
      "VE : 50 / 30",
      "FE : 70%",
      "AO : CUSPIDES CALCIFICADAS , COM DUPLA LESAO",
      "GRAD MAX = 43 MEDIO 25",
      "INSUF TRICU DISCRETA ( PSAP 39 )",
      "REFLUXO MITRAL DISCRETO",
      "AO ASC : 41MM S"
    ]
  },
  "labels": {}
}