{
  "prontuario_id": 55,
  "text": "LUCAS, MASC, 86 ANOS.\n\nQP: CONSULTA DE ROTINA.\n\nHMA: INICIO DE 2013 IAM COM CAT E ANGIOPLASTIA. PACIENTE SEM QUEIXAS CARDIOLOGICAS. RELATA DOR A DEAMBULACAO. \n\nEM USO DE: AAS 100 MG / CARVEDILOL 25 MG / HCTZ 25 MG / SINVASTATINA 20 MG.\n\nECOCARDIO 25/11/13 - VE HIPERTROFIADO COM DIMENSÃO INTERNA AUMENTADA E FUNÇÃO  GLOBAL MODERADAMENTE DIMINUIDA POR ACINESIA MEDIO APICAL PAREDE ANTERO SEPTAL. AUMENTO DE AE. REFLUXO MITRAL DISCRETO. ECTASIA DA RAIZ AÓRTICA. REFLUXO AÓRTICO DISCRETO.\nFEVE: 47%.\n\nEX:\nPA 120/60,\nFC: 73,\nSAT: 98,\nPC: BC HIPOFONETICAS SEM SORPOS COM EXTRASSISTOLES.\nEDEMA EM MMII ++/4.\n\nCONDUTA: A MEDICAÇAO FOI MANTIDA. RETONRO EM 1  MESES.\n \n \n \n ",
  "entities": {
    "Achado": [
      "MASC",
      "QP",
      "HMA",
      "CONSULTA DE ROTINA"
    ],
    "Abreviação": [
      "MASC",
      "QP",
      "HMA",
      "IAM",
      "CAT",
      "AAS",
      "HCTZ",
      "ECOCARDIO",
      "EX",
      "PA",
      "FC",
      "SAT",
      "PC",
      "MMII",
      "VE HIPERTROFIADO COM DIMENSÃO INTERNA AUMENTADA",
      "AUMENTO DE AE",
      "FEVE : 47%"
    ],
    "Atributo Clínico": [
      "MASC",
      "PA",
      "FC",
      "SAT"
    ],
    "Doença ou Síndrome": [
      "IAM"
    ],
    "Procedimento Terapêutico ou Preventivo": [
      "CAT",
      "ANGIOPLASTIA",
      "MANTIDA"
    ],
    "Paciente ou Grupo com Deficiência": [
      "PACIENTE"
    ],
    "Negação": [
      "SEM"
    ],
    "Substância Química Orgânica": [
      "AAS",
      "CARVEDILOL",
      "HCTZ",
      "SINVASTATINA"
    ],
    "Substância Farmacológica": [
      "AAS",
      "CARVEDILOL",
      "HCTZ",
      "SINVASTATINA",
      "MEDICAÇAO"
    ],
    "Procedimento Diagnóstico": [
      "ECOCARDIO",
      "EX"
    ],
    "Conceito Quantitativo": [
      "120/60",
      "73",
      "98",
      "100 MG",
      "25 MG",
      "20 MG"
    ],
    "Função de Órgão ou Tecido": [
      "BC"
    ],
    "Sinal ou Sintoma": [
      "HIPOFONETICAS",
      "SORPOS",
      "EXTRASSISTOLES",
      "EDEMA",
      "QUEIXAS CARDIOLOGICAS",
      "DOR A DEAMBULACAO"
    ],
    "Função Patológica": [
      "EDEMA"
    ],
    "Parte do Corpo, Órgão ou Componente Orgânico": [
      "MMII"
    ],
    "Resultado Laboratorial ou de Teste": [
      "++/4",
      "VE HIPERTROFIADO COM DIMENSÃO INTERNA AUMENTADA",
      "FUNÇÃO GLOBAL MODERADAMENTE DIMINUIDA",
      "POR ACINESIA MEDIO APICAL PAREDE ANTERO SEPTAL",
      "AUMENTO DE AE",
      "REFLUXO MITRAL DISCRETO",
      "ECTASIA DA RAIZ AÓRTICA",
      "REFLUXO AÓRTICO DISCRETO",
      "FEVE : 47%"
    ],
    "Atividade de Assistência à Saúde": [
      "CONDUTA"
    ],
    "Produto Intelectual": [
      "CONDUTA"
    ]
  },
  "labels": {}
}