{
  "prontuario_id": 154,
  "text": "# Tx Renal Intervivos há 11 anos.\n- Imunossupressores: Myfortic 360 mg 2 x/dia + Prednisosna 15 mg dia.\n- Medicações de uso continuo: Anlodipino 5 mg 1x / Selozok 100 1x / Furosemida 40 mg 1x /  Atorvastatina 40 mg 1x / Omeprazol 20 mg 1x / Atensina 0,150 2x / Ciprofibrato 200 1x / Alopurinol 150 2x.\n\nPaciente retorna com exames periódicos, apresentando pico hipertensivo na triagem, segundo ele após caminhada sem repouso antes da aferiçao. Relata PA em casa em torno de 140 x 90 diariamente.\nExames sem alterações relevantes. Creatinina de 1,9 ( 2,2 >>> 2,1 >>> 1,9).\n\nConduta: Retorno em 3 meses com exames periódicos.\n \n \n \n ",
  "entities": {
    "Substância Farmacológica": [
      "Imunossupressores",
      "Myfortic",
      "Prednisosna",
      "Anlodipino",
      "Selozok",
      "Furosemida",
      "Atorvastatina",
      "Omeprazol",
      "Atensina",
      "Ciprofibrato",
      "Alopurinol",
      "Medicações de uso continuo"
    ],
    "Substância Química Orgânica": [
      "Myfortic",
      "Prednisosna",
      "Anlodipino",
      "Furosemida",
      "Atorvastatina",
      "Omeprazol",
      "Atensina",
      "Ciprofibrato",
      "Alopurinol"
    ],
    "Conceito Temporal": [
      "dia",
      "1x",
      "2x",
      "após",
      "diariamente",
      "2 x/dia"
    ],
    "Conceito Quantitativo": [
      "1x",
      "100",
      "2x",
      "200",
      "150",
      "360 mg",
      "2 x/dia",
      "15 mg",
      "5 mg",
      "40 mg",
      "20 mg",
      "0 , 150",
      "140 x 90"
    ],
    "Abreviação": [
      "1x",
      "2x",
      "PA",
      "Tx Renal Intervivos",
      "2 x/dia"
    ],
    "Atividade de Assistência à Saúde": [
      "triagem",
      "Conduta",
      "Retorno"
    ],
    "Procedimento Terapêutico ou Preventivo": [
      "caminhada",
      "Tx Renal Intervivos"
    ],
    "Negação": [
      "sem"
    ],
    "Função de Organismo": [
      "repouso"
    ],
    "Atributo Clínico": [
      "PA"
    ],
    "Procedimento Diagnóstico": [
      "Exames",
      "exames"
    ],
    "Produto Intelectual": [
      "Conduta"
    ],
    "Achado": [
      "Tx Renal Intervivos"
    ],
    "Conceito Espacial": [
      "em casa"
    ],
    "Sinal ou Sintoma": [
      "alterações relevantes"
    ],
    "Resultado Laboratorial ou de Teste": [
      "Creatinina de 1 , 9",
      "2 , 2",
      "2 , 1",
      "1 , 9"
    ]
  },
  "labels": {}
}