{
  "prontuario_id": 87,
  "text": "LUCAS, 69 anos.\n\nHMA: paciente relata cansaço, dor precordial quando tosse. Nega dispneia, ortopneia e DNP. Paciente relata apenas um episodio no momento de gripe.\nHAS, ICC, nega DM.\ncarvedilol 1 cp 12/12, furosemida 20mg 2 cp de 12/12, sinvastatina 1cp a noite, AAS 100mg apos almoço e Omeprazol 20mg 1 xdia.\n\nHMP: paciente relata 4 angioplastia, ultima em 2012.\n\nCHV: tabagista de mais de maço dia ha 3 anos. etilista de moderado de cerveja.\n\nS # paciente relata cansaço.\n\nO # BEG, orientado, anicterico, afebril.\nCardiaco: sp, FC: 74bpm. \nPulmonar: sp.\nMMII: sem edema e sem empastamento.\nAbdome: flacido, indolor, RHA+.\n\n# C: solicito exames laboratoriais e encaminho para Doutor Vital Brazil.",
  "entities": {
    "Abreviação": [
      "HMA",
      "DNP",
      "HAS",
      "ICC",
      "DM",
      "AAS",
      "HMP",
      "CHV",
      "S",
      "O",
      "BEG",
      "sp",
      "FC",
      "MMII",
      "RHA+"
    ],
    "Achado": [
      "HMA",
      "HMP",
      "CHV",
      "S",
      "BEG",
      "orientado",
      "sp",
      "flacido",
      "RHA+"
    ],
    "Paciente ou Grupo com Deficiência": [
      "paciente",
      "Paciente"
    ],
    "Sinal ou Sintoma": [
      "cansaço",
      "tosse",
      "dispneia",
      "ortopneia",
      "DNP",
      "anicterico",
      "afebril",
      "edema",
      "empastamento",
      "indolor",
      "dor precordial"
    ],
    "Negação": [
      "Nega",
      "nega",
      "anicterico",
      "afebril",
      "sem",
      "indolor"
    ],
    "Doença ou Síndrome": [
      "HAS",
      "ICC",
      "DM"
    ],
    "Substância Química Orgânica": [
      "carvedilol",
      "furosemida",
      "sinvastatina",
      "AAS",
      "Omeprazol"
    ],
    "Substância Farmacológica": [
      "carvedilol",
      "furosemida",
      "sinvastatina",
      "AAS",
      "Omeprazol"
    ],
    "Conceito Temporal": [
      "12/12",
      "no momento de gripe",
      "1cp a noite",
      "apos almoço",
      "1 xdia"
    ],
    "Conceito Quantitativo": [
      "20mg",
      "100mg",
      "74bpm",
      "um episodio",
      "1 xdia",
      "mais de maço dia"
    ],
    "Procedimento Terapêutico ou Preventivo": [
      "angioplastia"
    ],
    "Disfunção Mental ou Comportamental": [
      "tabagista"
    ],
    "Alimento": [
      "cerveja"
    ],
    "Atividade de Assistência à Saúde": [
      "O",
      "solicito",
      "encaminho"
    ],
    "Localização ou Região Corporal": [
      "Cardiaco",
      "Pulmonar"
    ],
    "Atributo Clínico": [
      "FC"
    ],
    "Parte do Corpo, Órgão ou Componente Orgânico": [
      "Pulmonar",
      "MMII",
      "Abdome"
    ],
    "Função Patológica": [
      "edema"
    ],
    "Produto Intelectual": [
      "C"
    ],
    "Procedimento Laboratorial": [
      "exames laboratoriais"
    ]
  },
  "labels": {}
}