{
  "prontuario_id": 888,
  "text": "LUCAS, 52 ANOS\n\nS # ENCAMINHADA PARA ACOMPANHAMENTO GINECOLÓGICO DE ROTINA PELA NEFROLOGIA. SEM COLETA DE CITOLOGIA ONCÓTICA HA 2 ANOS. QUEIXA-SE DE CORRIMENTO HÁ 3 MESES, DE COLORAÇAO BRANCO AMARELADA DE PEQUENA QUANTIDADE E ODOR FORTE. REFERE APARECIMENTO DE PEQUENOS NÓDULOS EM MAMAS HÁ 2 MESES, ASSOCIADO À MASTALGIA À PALPAÇÃO. QUEIXA DE PERDA URINÁRIA AOS PEQUENOS ESFORÇOS (TOSSIR), DISÚRIA E  SECURA VAGINAL COM DIFICULDADES NA RELAÇÃO SEXUAL. NEGA QUEIXAS INTESTINAIS. \nG 3  P 0  C 3  A 0.\nTRANSPLANTE RENAL HÁ 13 ANOS, EM USO DE MICOFENOLATO E PREDNISONA.\nNEGA OUTRAS COMORBIDADES.\n\nO # \nVULVA  DE ASPECTO NORMAL PARA IDADE E SEXO, VAGINA PÁLIDA, HIPOTRÓFICA.\nCOLO DO ÚTERO DE PEQUENO VOLUME, ORIFÍCIO CIRCULAR.\nKOH NEGATIVO.\nMAMAS DE MÉDIO VOLUME, COM PARÊNQUIMA ESPESSO, SEM NÓDULOS MPALPÁVEIS, DERRAME PAPILAR NEGATIVO E AXILAS LIVRES.\n\nA # ROTINA GINECOLÓGICA. \n\nP # COLETO CITOLOGIA ONCOTICA E RETORNO EM 4 MESES PARA RESULTADO DE EXAMES E SOLICITO MAMOGRAFIA.\nPRESCREVO STELE CREME VAGINAL.\n \n \n \n ",
  "entities": {
    "Atividade de Assistência à Saúde": [
      "ENCAMINHADA",
      "COLETA",
      "COLETO",
      "RETORNO",
      "SOLICITO",
      "PRESCREVO",
      "ACOMPANHAMENTO GINECOLÓGICO DE ROTINA",
      "ROTINA GINECOLÓGICA"
    ],
    "Negação": [
      "SEM",
      "NEGA"
    ],
    "Sinal ou Sintoma": [
      "CORRIMENTO",
      "QUEIXA",
      "DISÚRIA",
      "PÁLIDA",
      "HIPOTRÓFICA",
      "COLORAÇAO BRANCO AMARELADA",
      "ODOR FORTE",
      "PEQUENOS NÓDULOS",
      "PERDA URINÁRIA AOS PEQUENOS ESFORÇOS",
      "SECURA VAGINAL",
      "DIFICULDADES NA RELAÇÃO SEXUAL",
      "QUEIXAS INTESTINAIS",
      "NÓDULOS MPALPÁVEIS"
    ],
    "Parte do Corpo, Órgão ou Componente Orgânico": [
      "MAMAS",
      "VULVA",
      "VAGINA",
      "COLO DO ÚTERO"
    ],
    "Procedimento Diagnóstico": [
      "PALPAÇÃO",
      "MAMOGRAFIA",
      "CITOLOGIA ONCÓTICA",
      "ROTINA GINECOLÓGICA"
    ],
    "Substância Farmacológica": [
      "MICOFENOLATO",
      "PREDNISONA",
      "STELE CREME VAGINAL"
    ],
    "Substância Química Orgânica": [
      "MICOFENOLATO",
      "PREDNISONA"
    ],
    "Hormônio": [
      "PREDNISONA"
    ],
    "Doença ou Síndrome": [
      "COMORBIDADES"
    ],
    "Atributo Clínico": [
      "IDADE",
      "SEXO",
      "G 3",
      "P 0",
      "C 3",
      "A 0"
    ],
    "Procedimento Laboratorial": [
      "CITOLOGIA ONCÓTICA",
      "CITOLOGIA ONCOTICA"
    ],
    "Conceito Qualitativo": [
      "COLORAÇAO BRANCO AMARELADA"
    ],
    "Conceito Quantitativo": [
      "PEQUENA QUANTIDADE",
      "PEQUENO VOLUME"
    ],
    "Abreviação": [
      "G 3",
      "P 0",
      "C 3",
      "A 0"
    ],
    "Procedimento Terapêutico ou Preventivo": [
      "TRANSPLANTE RENAL"
    ],
    "Achado": [
      "ASPECTO NORMAL",
      "ORIFÍCIO CIRCULAR",
      "DERRAME PAPILAR NEGATIVO",
      "AXILAS LIVRES"
    ],
    "Resultado Laboratorial ou de Teste": [
      "KOH NEGATIVO",
      "DERRAME PAPILAR NEGATIVO",
      "RESULTADO DE EXAMES"
    ]
  },
  "labels": {}
}