{
  "prontuario_id": 558,
  "text": "Lucas, 68A\n\n# CAT EM 2008.\nVALVOPLASTIA AÓRTICA EM 2008. VALVA BIOLÓGICA - 40 DIAS DEPOIS DA CX CARDIOVERSÃO.\n\n# PACIENTE ASSINTOMÁTICO HÁ BASTANTE TEMPO (APROX 1 ANO), A CAMINHO DO TRABALHO NO DIA 16/08 COMEÇOU A SENTIR TONTURA.\nPROCUROU ATENDIMENTO NO XXXX E PERMANECEU INTERNADO ATÉ DIA 21/08.\nHOJE PACIENTE ESTÁ ASSINTOMÁTICO, NEGA QUEIXAS, VOLTOU AS ATIVIDADES NORMAIS (FRENTISTA). \nRELATA EMAGRECIMENTO DE 7 KG EM 10 DIAS.\n\n# EX-TABAGISTA 40 MAÇOS-ANO - EM ABSTINÊNCIA HÁ 7 ANOS.\n\n# EM USO DE: ENALAPRIL 10MG 2X/DIA, CARVEDILOL 12,5 MG 2X/DIA, ATORVASTATINA 40 MG, CLOPIDOGREL E MAREVAN.\n\n\n# EXAME FÍSICO: \nLOTE, BEG, NORMOCORADO, HIDRATADO, ANICTÉRICO, ACIANÓTICO.\nFC 80 BPM,    PA 120/80 MMHG.\nBCRNF - HIPOFONESE DE BULHAS EM FOCO AÓRTICO.\nMV+ SIM BILATERAL, S/ RA.\nRHA+, ABDOME NÃO DOLOROSO A PALPAÇÃO, SEM VISCEROMEGALIAS. HERNIA UMBILICAL REDUTÍVEL.\nMMII EDEMA +/4+, PANTURRILHAS LIVRES.\n\n# ECG 19/08: FLUTTER ATRIAL PROVAVELMENTE ANTI-HORÁRIO 2/3:1, EXTRASSÍSTOLES VENTRICULARES.\n\n# CD: CONTROLE DO TAP.\n          PRECISA DE 4 TAP ENTRE 2 E 3.\n          RETORNO EM 30 DIAS.\n \n \n \n ",
  "entities": {
    "Abreviação": [
      "CAT",
      "APROX",
      "LOTE",
      "BEG",
      "FC",
      "PA",
      "BCRNF",
      "S/",
      "RA",
      "RHA+",
      "MMII",
      "ECG",
      "CD",
      "TAP",
      "CX CARDIOVERSÃO",
      "80 BPM",
      "MV+ SIM BILATERAL"
    ],
    "Procedimento Terapêutico ou Preventivo": [
      "CAT",
      "ABSTINÊNCIA",
      "VALVOPLASTIA AÓRTICA",
      "CX CARDIOVERSÃO"
    ],
    "Paciente ou Grupo com Deficiência": [
      "PACIENTE"
    ],
    "Negação": [
      "ASSINTOMÁTICO",
      "NEGA",
      "ANICTÉRICO",
      "ACIANÓTICO",
      "S/",
      "NÃO",
      "SEM"
    ],
    "Sinal ou Sintoma": [
      "ASSINTOMÁTICO",
      "TONTURA",
      "QUEIXAS",
      "ANICTÉRICO",
      "ACIANÓTICO",
      "RA",
      "VISCEROMEGALIAS",
      "EDEMA",
      "EMAGRECIMENTO DE 7 KG",
      "HIPOFONESE DE BULHAS"
    ],
    "Atividade de Assistência à Saúde": [
      "ATENDIMENTO",
      "INTERNADO",
      "CD",
      "CONTROLE",
      "RETORNO EM 30 DIAS"
    ],
    "Conceito Temporal": [
      "HOJE",
      "2X/DIA",
      "40 DIAS DEPOIS",
      "10 DIAS",
      "HÁ 7 ANOS"
    ],
    "Grupo Profissional ou Ocupacional": [
      "FRENTISTA"
    ],
    "Achado": [
      "EX-TABAGISTA",
      "LOTE",
      "BEG",
      "NORMOCORADO",
      "HIDRATADO",
      "BCRNF",
      "RHA+",
      "VALVOPLASTIA AÓRTICA",
      "MV+ SIM BILATERAL",
      "PANTURRILHAS LIVRES"
    ],
    "Comportamento": [
      "ABSTINÊNCIA"
    ],
    "Substância Farmacológica": [
      "ENALAPRIL",
      "CARVEDILOL",
      "ATORVASTATINA",
      "CLOPIDOGREL",
      "MAREVAN"
    ],
    "Aminoácido, Peptídeo ou Proteína": [
      "ENALAPRIL"
    ],
    "Conceito Quantitativo": [
      "10MG",
      "2X/DIA",
      "12",
      "40 MAÇOS-ANO",
      "5 MG",
      "40 MG",
      "80 BPM",
      "120/80 MMHG"
    ],
    "Substância Química Orgânica": [
      "CARVEDILOL",
      "ATORVASTATINA",
      "CLOPIDOGREL",
      "MAREVAN"
    ],
    "Atributo Clínico": [
      "FC",
      "PA"
    ],
    "Parte do Corpo, Órgão ou Componente Orgânico": [
      "ABDOME",
      "MMII"
    ],
    "Procedimento Diagnóstico": [
      "PALPAÇÃO",
      "ECG",
      "EXAME FÍSICO"
    ],
    "Conceito Qualitativo": [
      "REDUTÍVEL"
    ],
    "Função Patológica": [
      "EDEMA"
    ],
    "Resultado Laboratorial ou de Teste": [
      "+/4+",
      "FLUTTER ATRIAL PROVAVELMENTE ANTI-HORÁRIO 2/3 : 1",
      "EXTRASSÍSTOLES VENTRICULARES"
    ],
    "Produto Intelectual": [
      "CD"
    ],
    "Procedimento Laboratorial": [
      "TAP"
    ],
    "Dispositivo Médico": [
      "VALVA BIOLÓGICA"
    ],
    "Localização ou Região Corporal": [
      "FOCO AÓRTICO"
    ],
    "Anormalidade Anatômica": [
      "HERNIA UMBILICAL"
    ]
  },
  "labels": {}
}