{
  "prontuario_id": 147,
  "text": "Humberto, 65anos.\n\n# DAC - IAM 2007 + RVM // ATC 2010,\n# Hipertireoidismo ?? - em acompanhamento com endocrinologia ,\n# FA paroxistica ,\n# Internamento em jan/15 por taquicardia atrial com aberrância  - - DESCARTADO ISQUEMIA MIOCÁRDICA COMO CAUSA, PROVÁVEL FATOR DESCOMPENSADOR SERIA O HIPERTIREOIDISMO QUE AINDA APRESENTA-SE DESCOMPENSADO (TSH < 0,01).\n\nMedicamentos: tapazol 10 mg, enalapril 10 mg 12/12h, selozok 50 mg, sinvastatina 40 mg, xarelto 20 mg, AAS100mg .\n\nS # Nega palpitações, dispneia, dor torácica. Epigastralgia. \nConsuçta com endocrino amanhã. \n\n\nTraz exames:\n- Holter 28/04/15: ritmo sinusal, FC media 53, Intervalo PR normal, QRS normais, extra-sistole ventricular unica, extra-sistole supra-ventricular rara, ausencia de pausas, ST sem alterações\n- TSH 47 / t4l 0,55.\n- Ecocardiograma out/14 (externo): AE 43 / VD 23 / septo 10 / VE 52-26 / FE 81%. VE com contração segmentar e função sistólica adequadas. \n\nAo exame:  \nPA130/70,  FC 55. \nCV: BRNF, sem sopros.\nCPP livres.\n\nA # FA paroxística.\n      CHADS = 1 / CHADS Vasc = 3. \n     \nP # Retorno precoce na endocrino para ajuste medicação. Suspendemos selozok. prescrevemos propafenona 300mg 12/12h. Retorno com ecocardio em 3 meses. Demais medicações mantidas. \n\nE3 cardio Lucas\nDoutor Vital Brasil\n \n \n \n ",
  "entities": {
    "Abreviação": [
      "DAC",
      "IAM",
      "RVM",
      "ATC",
      "AAS100mg",
      "S",
      "PA130/70",
      "FC",
      "CV",
      "BRNF",
      "A",
      "P",
      "endocrino",
      "ecocardio",
      "FA paroxistica",
      "FC media 53",
      "t4l 0 , 55",
      "AE 43",
      "VD 23",
      "VE 52-26",
      "FE 81%",
      "VE com contração segmentar",
      "CPP livres",
      "FA paroxística"
    ],
    "Doença ou Síndrome": [
      "DAC",
      "IAM",
      "Hipertireoidismo",
      "HIPERTIREOIDISMO",
      "FA paroxistica",
      "taquicardia atrial com aberrância",
      "ISQUEMIA MIOCÁRDICA",
      "FA paroxística"
    ],
    "Procedimento Terapêutico ou Preventivo": [
      "RVM",
      "ATC"
    ],
    "Grupo Profissional ou Ocupacional": [
      "endocrinologia",
      "endocrino"
    ],
    "Atividade de Assistência à Saúde": [
      "Internamento",
      "Suspendemos",
      "prescrevemos",
      "Retorno",
      "em acompanhamento",
      "Demais medicações mantidas"
    ],
    "Produto Intelectual": [
      "DESCARTADO",
      "P"
    ],
    "Sinal ou Sintoma": [
      "DESCOMPENSADO",
      "palpitações",
      "dispneia",
      "Epigastralgia",
      "sopros",
      "dor torácica"
    ],
    "Substância Farmacológica": [
      "tapazol",
      "enalapril",
      "selozok",
      "sinvastatina",
      "xarelto",
      "AAS100mg",
      "propafenona"
    ],
    "Substância Química Orgânica": [
      "tapazol",
      "selozok",
      "sinvastatina",
      "xarelto",
      "propafenona"
    ],
    "Aminoácido, Peptídeo ou Proteína": [
      "enalapril"
    ],
    "Conceito Temporal": [
      "12/12h",
      "3 meses"
    ],
    "Achado": [
      "S",
      "BRNF",
      "CPP livres"
    ],
    "Negação": [
      "Nega",
      "sem"
    ],
    "Procedimento Diagnóstico": [
      "exames",
      "Holter",
      "Ecocardiograma",
      "exame",
      "A",
      "ecocardio"
    ],
    "Conceito Quantitativo": [
      "PA130/70",
      "55",
      "300mg",
      "10 mg",
      "50 mg",
      "40 mg",
      "20 mg"
    ],
    "Atributo Clínico": [
      "PA130/70",
      "FC"
    ],
    "Localização ou Região Corporal": [
      "CV"
    ],
    "Função Patológica": [
      "taquicardia atrial com aberrância"
    ],
    "Resultado Laboratorial ou de Teste": [
      "TSH &lt; 0 , 01",
      "ritmo sinusal",
      "FC media 53",
      "Intervalo PR normal",
      "QRS normais",
      "extra-sistole ventricular unica",
      "extra-sistole supra-ventricular rara",
      "ausencia de pausas",
      "ST sem alterações",
      "TSH 47",
      "t4l 0 , 55",
      "AE 43",
      "VD 23",
      "septo 10",
      "VE 52-26",
      "FE 81%",
      "VE com contração segmentar",
      "função sistólica adequadas",
      "CHADS = 1",
      "CHADS Vasc = 3"
    ]
  },
  "labels": {}
}