{
  "prontuario_id": 594,
  "text": "01:25 horas. Paciente em 1º dia de Internamento. Proveniente do XXXX por suspeita de abdomem agudo. Apresentou broncoespasamo, suspeita de PNM. História prévia de AVC. Acamada, pouco comunicativa, apatica, hipocorada, desidratada e emagrecida. Pele fina e frágil. Equimoses em MMSS. Cabeceira elevada 45ºC. Dispnéica com suporte de 02 sob máscara de venturi em 4l/min. Taquidispnéica. Monitorização cardíaca e oxímetria de pulso contínua, FC: 120 bpm, sat: 96% e PA: 120/80 mmhg. Acesso venoso períferico mantendo soroterapia fravitacional. Tórax simétrico, apresentando esforço respiratório importante, ausculta pulmonar com presença de roncos e sibilos difusos. Abdomem levemente distendido, doloroso á palpação com rha diminuídos. SVD com débito citrico, evacuações ausentes até o momento. Segue sob os cuidados da equipe multiprofissional. Permanece em sala de emergência conforme ordem médica. PNEUMONIA NAO ESPECIFICADA.",
  "entities": {
    "Atividade de Assistência à Saúde": [
      "Internamento",
      "Permanece",
      "cuidados da equipe multiprofissional",
      "ordem médica"
    ],
    "Sinal ou Sintoma": [
      "broncoespasamo",
      "Acamada",
      "apatica",
      "hipocorada",
      "desidratada",
      "emagrecida",
      "Equimoses",
      "Dispnéica",
      "Taquidispnéica",
      "roncos",
      "doloroso",
      "pouco comunicativa",
      "esforço respiratório importante",
      "sibilos difusos",
      "levemente distendido",
      "rha diminuídos"
    ],
    "Abreviação": [
      "PNM",
      "AVC",
      "MMSS",
      "FC",
      "sat",
      "PA",
      "SVD",
      "rha diminuídos"
    ],
    "Doença ou Síndrome": [
      "PNM",
      "AVC",
      "abdomem agudo"
    ],
    "Parte do Corpo, Órgão ou Componente Orgânico": [
      "Pele",
      "MMSS"
    ],
    "Conceito Qualitativo": [
      "fina",
      "frágil"
    ],
    "Conceito Quantitativo": [
      "4l/min",
      "96%",
      "120 bpm",
      "120/80 mmhg"
    ],
    "Atributo Clínico": [
      "FC",
      "sat",
      "PA"
    ],
    "Localização ou Região Corporal": [
      "Abdomem"
    ],
    "Procedimento Diagnóstico": [
      "palpação",
      "Monitorização cardíaca",
      "oxímetria de pulso contínua",
      "ausculta pulmonar"
    ],
    "Dispositivo Médico": [
      "SVD",
      "máscara de venturi",
      "Acesso venoso períferico"
    ],
    "Procedimento Terapêutico ou Preventivo": [
      "SVD",
      "suporte de 02",
      "soroterapia fravitacional"
    ],
    "Função Fisiológica": [
      "evacuações"
    ],
    "Negação": [
      "ausentes"
    ],
    "Conceito Temporal": [
      "momento"
    ],
    "Achado": [
      "Tórax simétrico"
    ],
    "Organização Relacionada à Saúde": [
      "sala de emergência"
    ]
  },
  "labels": {}
}