{
  "prontuario_id": 218,
  "text": "OBESO, CORADO, SEDADO, RAMSEY 6, PUPILAS ISOMIÓTICAS FOTOREAGENTES, DVE ABERTA COM DÉBITO SANGUINOLENTO EM MODERADA QUANTIDADE, CURATIVO LIMPO E SECO EXTERNAMENTE EM CRÂNIO, SNG  EM NARINA D,  20 ML/H, VENTILAÇÃO MECANICA EM MODO ASSISTIDO CONTROLADO, PEEP 6, FIO2 60, FR 16, MONITORIZAÇÃO MULTIPARAMÉTRICA INVASIVA E NÃO INVASIVA, CPP LIVRES, BCRNF S/S, ABDOMEN  GLOBOSO RIGIDO A PALPAÇÃO, RHA HIPOATIVOS, SVD DIURESE AMARELO ESCURO, FRALDA GERIATRICA  SEM EVACUAÇÃO NO PERÍÓDO,  ACESSO VENOSO EM REGIÃO CUBITAL D E E  COM SOROTERAPIA EM CURSO, COM NIPRIDE A 20ML/H; DORMINID A 30 ML/H. FENTANIL A 20ML/H. CACIFO I/ IV EM MMSS E MMII,  ENCHIMENTO CAPILAR < 3 SEGUNDOS. AC DE ENFERMAGEM Florence Nightingale, SOB SUPERVISÃO DA PROFª FLORENCE (XXXXX) ACIDENTE VASCULAR CEREBRAL NAO ESPECIFICADO COMO HEMORRAGICO OU ISQUEMICO.",
  "entities": {
    "Doença ou Síndrome": [
      "OBESO",
      "ACIDENTE VASCULAR CEREBRAL"
    ],
    "Achado": [
      "CORADO",
      "SEDADO",
      "ISOMIÓTICAS",
      "FOTOREAGENTES",
      "BCRNF",
      "GLOBOSO",
      "CPP LIVRES"
    ],
    "Procedimento Terapêutico ou Preventivo": [
      "SEDADO",
      "SNG",
      "SVD",
      "SOROTERAPIA",
      "VENTILAÇÃO MECANICA EM MODO ASSISTIDO CONTROLADO",
      "ACESSO VENOSO"
    ],
    "Parte do Corpo, Órgão ou Componente Orgânico": [
      "PUPILAS",
      "CRÂNIO",
      "ABDOMEN",
      "MMSS",
      "MMII"
    ],
    "Dispositivo Médico": [
      "CURATIVO",
      "SNG",
      "SVD",
      "FRALDA GERIATRICA",
      "ACESSO VENOSO"
    ],
    "Conceito Qualitativo": [
      "LIMPO",
      "SECO",
      "INVASIVA"
    ],
    "Abreviação": [
      "SNG",
      "PEEP",
      "FIO2",
      "FR",
      "BCRNF",
      "S/S",
      "SVD",
      "MMSS",
      "MMII",
      "AC",
      "DVE ABERTA",
      "NARINA D",
      "CPP LIVRES",
      "RHA HIPOATIVOS",
      "REGIÃO CUBITAL"
    ],
    "Atributo Clínico": [
      "PEEP",
      "FIO2",
      "FR"
    ],
    "Conceito Quantitativo": [
      "6",
      "60",
      "16",
      "20ML/H",
      "MODERADA QUANTIDADE",
      "20 ML/H",
      "30 ML/H"
    ],
    "Negação": [
      "NÃO",
      "S/S",
      "SEM"
    ],
    "Sinal ou Sintoma": [
      "S/S",
      "RAMSEY 6",
      "DÉBITO SANGUINOLENTO",
      "RHA HIPOATIVOS"
    ],
    "Procedimento Diagnóstico": [
      "PALPAÇÃO"
    ],
    "Função de Organismo": [
      "EVACUAÇÃO"
    ],
    "Conceito Temporal": [
      "PERÍÓDO"
    ],
    "Substância Química Orgânica": [
      "DORMINID",
      "FENTANIL"
    ],
    "Substância Farmacológica": [
      "DORMINID",
      "FENTANIL"
    ],
    "Atividade de Assistência à Saúde": [
      "AC",
      "MONITORIZAÇÃO MULTIPARAMÉTRICA"
    ],
    "Organização Relacionada à Saúde": [
      "ENFERMAGEM"
    ],
    "Grupo Profissional ou Ocupacional": [
      "ENFERMAGEM"
    ],
    "Objeto Manufaturado": [
      "FRALDA GERIATRICA"
    ],
    "Localização ou Região Corporal": [
      "REGIÃO CUBITAL"
    ],
    "Resultado Laboratorial ou de Teste": [
      "CACIFO I/ IV",
      "&lt; 3 SEGUNDOS"
    ]
  },
  "labels": {}
}