{
  "prontuario_id": 704,
  "text": "11:39Hrs Cliente em ramsay 6, pupilas iso / foto +, IOT + VM nos parametros PCV,   peep 5 cmh2o,   FR 12,   FiO2 50%, face corada, mucosa oral hidratada, boa perfusão periferica, no leito com cabeceira elevada á 45°. Mantem com monitorização de multiparametros ECG, PNI, SpO2,   SNG aberta com dietaterapia em curso BI 75 ml/hr, acesso venoso central duplo-lumem em sub-clavia DIR com fentanil 15 ml/hr, dormonid 20 ml/hr em curso BI. Apresenta ausculta cardiaca ritmica e normofonetica, ausculta pulmonar MV + com roncos difusos, abdomem globoso e flacido com RHA +, edemas em MMSS e II cacifo ++. Faz uso de SVD com debito diuretico presente ++ de coloração amarelo-claro, eliminação fecal ausente. Segue cuidados intensivos de enfermagem.  Enfermeira Florence Nightingale . TRAUMATISMO CEREBRAL DIFUSO.",
  "entities": {
    "Parte do Corpo, Órgão ou Componente Orgânico": [
      "pupilas",
      "abdomem",
      "MMSS",
      "II",
      "sub-clavia DIR"
    ],
    "Achado": [
      "iso",
      "globoso",
      "flacido",
      "foto +",
      "face corada",
      "mucosa oral hidratada",
      "boa perfusão periferica",
      "ritmica e normofonetica",
      "MV +",
      "RHA +",
      "presente ++"
    ],
    "Abreviação": [
      "iso",
      "IOT",
      "VM",
      "peep",
      "FR",
      "FiO2",
      "ECG",
      "PNI",
      "SpO2",
      "BI",
      "MMSS",
      "II",
      "SVD",
      "foto +",
      "SNG aberta",
      "sub-clavia DIR",
      "MV +",
      "RHA +"
    ],
    "Dispositivo Médico": [
      "IOT",
      "SVD",
      "SNG aberta",
      "acesso venoso central duplo-lumem"
    ],
    "Procedimento Terapêutico ou Preventivo": [
      "IOT",
      "VM",
      "PCV",
      "PNI",
      "SpO2",
      "dietaterapia",
      "SVD",
      "leito com cabeceira elevada á 45°",
      "acesso venoso central duplo-lumem"
    ],
    "Atributo Clínico": [
      "peep",
      "FR",
      "FiO2"
    ],
    "Conceito Quantitativo": [
      "12",
      "50%",
      "5 cmh2o",
      "75 ml/hr",
      "15 ml/hr",
      "20 ml/hr"
    ],
    "Procedimento Diagnóstico": [
      "ECG",
      "PNI",
      "SpO2",
      "ausculta cardiaca",
      "ausculta pulmonar"
    ],
    "Dispositivo de Administração de Medicamento": [
      "BI"
    ],
    "Substância Farmacológica": [
      "fentanil",
      "dormonid"
    ],
    "Substância Química Orgânica": [
      "fentanil",
      "dormonid"
    ],
    "Sinal ou Sintoma": [
      "edemas",
      "ramsay 6",
      "roncos difusos"
    ],
    "Negação": [
      "ausente"
    ],
    "Grupo Profissional ou Ocupacional": [
      "enfermagem",
      "Enfermeira"
    ],
    "Organização Relacionada à Saúde": [
      "enfermagem"
    ],
    "Atividade de Assistência à Saúde": [
      "monitorização de multiparametros",
      "cuidados intensivos"
    ],
    "Resultado Laboratorial ou de Teste": [
      "cacifo ++"
    ],
    "Função de Organismo": [
      "debito diuretico",
      "eliminação fecal"
    ],
    "Conceito Qualitativo": [
      "coloração amarelo-claro"
    ],
    "Doença ou Síndrome": [
      "TRAUMATISMO CEREBRAL DIFUSO"
    ]
  },
  "labels": {}
}