{
  "prontuario_id": 730,
  "text": "PACIENTE RECEBIDO NA UTI COM HISTÓRIA DE ERISIPELA EM MID, COM FERIDA APRESENTANDO GANGRENA E INFECÇÃO, ALÉM DE PERDA DA SENSIBILIDADE, TEMPERATURA E MOVIMENTO.  AOR RECEBIMENTO: ACORDADO, VERBALIZANDO, COMUNICATIVO, NEGA DORES NO MOMENTO. PUPILAS ISOCORICAS, FOTORREAGENTES. PELE NORMOCORADA, AFEBRIL, PREENCHIMENTO CAPILAR SATISFATÓRIO. JUGULARES ENGURGITADAS. MONITORIZADO, NORMOCARDICO, HIPERTENSO, EUPNEICO EM AR AMBIENTE COM SATURAÇÃO PERIFÉRICA DE 97%, EXPANSIBILIDADE PULMONAR SATISFATÓRIA, MV+, SONS CLARO PULMONARES. ABDOME GLOBOSO, SEM PRESENÇA DE MASSAS PALPAVEIS, EVACUAÇÕES AUSENTES NO PERÍODO. DIURESE ESPONTÂNEA, SEM DÉBITO NO MOMENTO. MMII COM EDEMAS, CACIFO +++/4, FERIDA EM MID DE INICIO NA PORÇÃO DE CALCANEO ESTENDENDO-SE ATÉ A PORÇÃO MEDIAL DA TIBIA ANTEROLATERO POSTERIOR, FERIDA COM PONTOS DE TECIDO DESVITALIZADOS , PAPULAS PURULENTAS. AGUARDANDO DISCUSSÃO MÉDICA EM RELAÇÃO AO TRATAMENTO.  EM ACOMPANHAMENTO PELA CARDIOLOGIA, INFECTOLOGIA E CX VASCULAR.  EXAME GERAL E INVESTIGACAO DE PESSOAS SEM QUEIXAS OU DIAGNOSTICO RELATADO.",
  "entities": {
    "Atividade de Assistência à Saúde": [
      "RECEBIDO",
      "MONITORIZADO",
      "ACOMPANHAMENTO",
      "DISCUSSÃO MÉDICA",
      "EXAME GERAL"
    ],
    "Organização Relacionada à Saúde": [
      "UTI",
      "CARDIOLOGIA",
      "INFECTOLOGIA",
      "CX VASCULAR"
    ],
    "Abreviação": [
      "UTI",
      "MID",
      "MV+",
      "MMII",
      "CX VASCULAR"
    ],
    "Doença ou Síndrome": [
      "ERISIPELA",
      "DIAGNOSTICO RELATADO"
    ],
    "Parte do Corpo, Órgão ou Componente Orgânico": [
      "MID",
      "PUPILAS",
      "ABDOME",
      "MMII"
    ],
    "Lesão ou Envenenamento": [
      "FERIDA"
    ],
    "Sinal ou Sintoma": [
      "GANGRENA",
      "DORES",
      "AFEBRIL",
      "HIPERTENSO",
      "EDEMAS",
      "QUEIXAS",
      "JUGULARES ENGURGITADAS",
      "MASSAS PALPAVEIS",
      "TECIDO DESVITALIZADOS",
      "PAPULAS PURULENTAS"
    ],
    "Função Patológica": [
      "INFECÇÃO"
    ],
    "Negação": [
      "PERDA",
      "NEGA",
      "AFEBRIL",
      "SEM",
      "AUSENTES"
    ],
    "Achado": [
      "SENSIBILIDADE",
      "TEMPERATURA",
      "MOVIMENTO",
      "ACORDADO",
      "VERBALIZANDO",
      "COMUNICATIVO",
      "ISOCORICAS",
      "FOTORREAGENTES",
      "NORMOCARDICO",
      "MV+",
      "GLOBOSO",
      "PELE NORMOCORADA",
      "PREENCHIMENTO CAPILAR SATISFATÓRIO",
      "EUPNEICO EM AR AMBIENTE",
      "EXPANSIBILIDADE PULMONAR SATISFATÓRIA",
      "SONS CLARO PULMONARES",
      "DIURESE ESPONTÂNEA"
    ],
    "Conceito Quantitativo": [
      "97%"
    ],
    "Função de Organismo": [
      "EVACUAÇÕES",
      "DÉBITO",
      "DIURESE ESPONTÂNEA"
    ],
    "Procedimento Terapêutico ou Preventivo": [
      "TRATAMENTO"
    ],
    "Grupo Profissional ou Ocupacional": [
      "CARDIOLOGIA",
      "INFECTOLOGIA",
      "CX VASCULAR"
    ],
    "Conceito Temporal": [
      "NO MOMENTO",
      "NO PERÍODO"
    ],
    "Atributo Clínico": [
      "SATURAÇÃO PERIFÉRICA"
    ],
    "Resultado Laboratorial ou de Teste": [
      "CACIFO +++/4"
    ],
    "Localização ou Região Corporal": [
      "PORÇÃO DE CALCANEO",
      "PORÇÃO MEDIAL DA TIBIA ANTEROLATERO POSTERIOR"
    ],
    "Procedimento Diagnóstico": [
      "INVESTIGACAO DE PESSOAS"
    ]
  },
  "labels": {}
}