{
  "prontuario_id": 421,
  "text": "Paciente com diagnostico de LMA - M4 em maio de 2006 em remissao completa apos 2 ciclos de intensificacao , sem cariograma e sem doador aparentado compativel , interna para realizacao de TMO autologo. Internacao para colocacao de cateter de Hickmann, condicionamento com BUCY, infusao de 8,6 x 106 CD34 /Kg no D0 (07/05/07), ficou neutropenica no D+2, iniciou com neutropenia febril no D+6, sem foco estabelecido , iniciado com cefepime apos coleta de culturais, permanecendo febril apos 72 h, acrescentado ao esquema vancomicina apos nova coleta de culturais , manteve-se febril por 72h, solicitado entao, CT torax e seios da face, nova coleta de culturais e iniciado com pipe+tazo. As tomografias nao evidenciaram lesoes sugestivas de infeccao fungica, porem iniciou-se com anfotericina, pois a paciente persistia febril. Fez uso de anfotericina por 5 dias e pipe+tazo por 10 dias, permanecendo afebril desde as primeiras 24h  de anfotericina. Cuturais negativos. A paciente apresesntou ainda nesta internacao, quadro de mucosite severa com resolucao completa do quadro. Apresentou pega do TMO no D+19.",
  "entities": {
    "Conceito Temporal": [
      "apos",
      "D0",
      "D+2",
      "D+6",
      "D+19",
      "5 dias",
      "10 dias"
    ],
    "Negação": [
      "sem",
      "nao",
      "afebril"
    ],
    "Procedimento Laboratorial": [
      "cariograma",
      "coleta de culturais",
      "nova coleta de culturais"
    ],
    "Atividade de Assistência à Saúde": [
      "interna",
      "Internacao",
      "colocacao",
      "infusao",
      "solicitado",
      "iniciado",
      "iniciou-se",
      "internacao"
    ],
    "Doença ou Síndrome": [
      "neutropenica",
      "LMA - M4",
      "neutropenia febril",
      "mucosite severa"
    ],
    "Substância Química Orgânica": [
      "cefepime",
      "anfotericina"
    ],
    "Antibiótico": [
      "cefepime",
      "vancomicina",
      "anfotericina"
    ],
    "Sinal ou Sintoma": [
      "febril",
      "afebril",
      "quadro",
      "persistia febril"
    ],
    "Procedimento Terapêutico ou Preventivo": [
      "esquema",
      "2 ciclos de intensificacao",
      "TMO autologo",
      "condicionamento com BUCY"
    ],
    "Aminoácido, Peptídeo ou Proteína": [
      "vancomicina"
    ],
    "Procedimento Diagnóstico": [
      "CT",
      "tomografias"
    ],
    "Abreviação": [
      "CT",
      "pipe+tazo",
      "LMA - M4",
      "TMO autologo",
      "condicionamento com BUCY"
    ],
    "Localização ou Região Corporal": [
      "torax"
    ],
    "Substância Farmacológica": [
      "pipe+tazo"
    ],
    "Achado": [
      "remissao completa",
      "resolucao completa"
    ],
    "Grupo Populacional": [
      "doador aparentado compativel"
    ],
    "Dispositivo Médico": [
      "cateter de Hickmann"
    ],
    "Conceito Quantitativo": [
      "8 , 6 x 106 CD34 /Kg"
    ],
    "Conceito Espacial": [
      "foco estabelecido"
    ],
    "Resultado Laboratorial ou de Teste": [
      "Cuturais negativos"
    ]
  },
  "labels": {}
}