{
  "prontuario_id": 73,
  "text": "PACIENTE INTERNA COM IAM ANTERIOR KILIIP II COM SUPRA ST, REALIZADO ACTP PRIMARIA NA SETIMA HORA + IMPLANTE DE STENT, COM CRITERIOS PARA REPERFUSÃO PORÉM COM FORMAÇÃO DE ONDA Q E EVOLUÇÃO PARA QUADRO TRANSITORIO DE BAIXO DEBITO, CONGESTÃO PULMONAR, ACFA, BRE INTERMITENTE, TODOS TRATADOS CLINICAMENTE. MELHORA SINTOMATICA EM 48H COM TTO CLINICO, JÁ SEM CONGESTÃO, CLASSE FUNCIONAL II / III. PRESENÇA DE TAQUICARDIA CONSTANTE E PRESENÇA DE B3, PREDITORAS DE ICE POS IAM. ECOCARDIO POS IAM MOSTROU FE 44% COM ACINESIA TOTAL DA PAREDE ANTEROSEPTAL, SEM COMPLICAÇÕES MECANICAS. INICIADO BETABLOQUEADOR NA INTERNAÇÃO COM BOA TOLERANCIA. ALTA COM TTO OTIMIZADO DE ICC, EM CLASSE FUNCIONAL II, B3 PERSISTENTE, SEM SINAIS DE CONGESTÃO AO EXAME FISICO E RX. MORTALIDADE CALCULADA EM 30 DIAS PELOS CRITERIOS TIMI EM 27%, MESMO COM TODO TTO OFERECIDO, RISCO QUE FOI EXPLICADO A FAMILIA E ORIENTADO O PACIENTE PARA PROCURAR ATENDIMENTO SE NECESSARIO.",
  "entities": {
    "Atividade de Assistência à Saúde": [
      "INTERNA",
      "INICIADO",
      "INTERNAÇÃO",
      "ALTA",
      "ORIENTADO",
      "PROCURAR ATENDIMENTO"
    ],
    "Conceito Temporal": [
      "EVOLUÇÃO",
      "SETIMA HORA",
      "POS IAM",
      "30 DIAS"
    ],
    "Doença ou Síndrome": [
      "ACFA",
      "CONGESTÃO",
      "ICC",
      "IAM ANTERIOR KILIIP II COM SUPRA ST",
      "CONGESTÃO PULMONAR",
      "BRE INTERMITENTE",
      "ICE POS IAM",
      "ACINESIA TOTAL DA PAREDE ANTEROSEPTAL"
    ],
    "Resultado Laboratorial ou de Teste": [
      "ACFA",
      "FORMAÇÃO DE ONDA Q",
      "BRE INTERMITENTE",
      "CLASSE FUNCIONAL II / III",
      "PRESENÇA DE B3",
      "FE 44%",
      "ACINESIA TOTAL DA PAREDE ANTEROSEPTAL",
      "B3 PERSISTENTE"
    ],
    "Abreviação": [
      "ACFA",
      "ECOCARDIO",
      "ICC",
      "RX",
      "IAM ANTERIOR KILIIP II COM SUPRA ST",
      "ACTP PRIMARIA",
      "BRE INTERMITENTE",
      "TTO CLINICO",
      "ICE POS IAM",
      "POS IAM",
      "FE 44%",
      "TTO OTIMIZADO",
      "TTO OFERECIDO"
    ],
    "Negação": [
      "SEM"
    ],
    "Procedimento Diagnóstico": [
      "ECOCARDIO",
      "RX",
      "EXAME FISICO"
    ],
    "Substância Química Orgânica": [
      "BETABLOQUEADOR"
    ],
    "Substância Farmacológica": [
      "BETABLOQUEADOR"
    ],
    "Organização Relacionada à Saúde": [
      "INTERNAÇÃO"
    ],
    "Conceito Quantitativo": [
      "27%",
      "MORTALIDADE CALCULADA"
    ],
    "Ideia ou Conceito": [
      "RISCO"
    ],
    "Grupo Familiar": [
      "FAMILIA"
    ],
    "Procedimento Terapêutico ou Preventivo": [
      "ACTP PRIMARIA",
      "IMPLANTE IMPLANTE DE DE STENT STENT",
      "TRATADOS CLINICAMENTE",
      "TTO CLINICO",
      "TTO OTIMIZADO",
      "TTO OFERECIDO"
    ],
    "Sinal ou Sintoma": [
      "QUADRO TRANSITORIO",
      "BAIXO DEBITO",
      "TAQUICARDIA CONSTANTE",
      "PRESENÇA DE B3",
      "B3 PERSISTENTE",
      "SINAIS DE CONGESTÃO"
    ],
    "Achado": [
      "MELHORA SINTOMATICA",
      "BOA TOLERANCIA"
    ],
    "Função Patológica": [
      "COMPLICAÇÕES MECANICAS"
    ],
    "Classificação": [
      "CRITERIOS TIMI"
    ]
  },
  "labels": {}
}