{
  "prontuario_id": 872,
  "text": "Paciente com diagnóstico de cardiopatia reumática, internou com quadro de dor torácica e dispnéia. Ecocardiograma Válvula aórtica com características de envolvimento reumático com estenose leve (gradiente máx/méd de 46/26 mmHg) e jato regurgitante central leve. Ventrículo esquerdo com diâmetros e espessuras parietais normais, déficit de relaxamento, função sistólica global e segmentar preservadas. Válvula mitral com características de acometimento reumático com regurgitação leve e área valvular estimada em 2,6 - 2,8 cm2. Átrio esquerdo e cavidades direitas de tamanho normal. Regurgitação tricúspide leve com gradiente VD/AD de 25mmHg, estimando-se a pressão sistólica na artéria pulmonar em 30 - 35mmHg.  Ergometria: sem evidência de isquemia.  Plano: profilaxia de endocardite e seguir acompanhamento no ambulatório da Cardio.",
  "entities": {
    "Produto Intelectual": [
      "diagnóstico"
    ],
    "Atividade de Assistência à Saúde": [
      "internou",
      "Plano",
      "acompanhamento"
    ],
    "Sinal ou Sintoma": [
      "quadro",
      "dispnéia",
      "dor torácica"
    ],
    "Procedimento Diagnóstico": [
      "Ecocardiograma",
      "Ergometria"
    ],
    "Negação": [
      "sem"
    ],
    "Função Patológica": [
      "isquemia",
      "jato regurgitante central leve",
      "déficit de relaxamento",
      "regurgitação leve",
      "Regurgitação tricúspide leve"
    ],
    "Resultado Laboratorial ou de Teste": [
      "isquemia",
      "características de envolvimento reumático",
      "estenose leve",
      "gradiente máx/méd de 46/26 mmHg",
      "jato regurgitante central leve",
      "diâmetros e espessuras parietais normais",
      "déficit de relaxamento",
      "função sistólica global e segmentar preservadas",
      "características de acometimento reumático",
      "regurgitação leve",
      "tamanho normal",
      "Regurgitação tricúspide leve",
      "gradiente VD/AD de 25mmHg",
      "pressão sistólica na artéria pulmonar em 30 - 35mmHg"
    ],
    "Doença ou Síndrome": [
      "cardiopatia reumática"
    ],
    "Parte do Corpo, Órgão ou Componente Orgânico": [
      "Válvula aórtica",
      "Ventrículo esquerdo",
      "Válvula mitral",
      "Átrio esquerdo",
      "cavidades direitas"
    ],
    "Abreviação": [
      "gradiente máx/méd de 46/26 mmHg",
      "gradiente VD/AD de 25mmHg",
      "ambulatório da Cardio"
    ],
    "Achado": [
      "tamanho normal"
    ],
    "Procedimento Terapêutico ou Preventivo": [
      "profilaxia de endocardite"
    ],
    "Organização Relacionada à Saúde": [
      "ambulatório da Cardio"
    ]
  },
  "labels": {}
}