{
  "prontuario_id": 862,
  "text": "Lucas, 79 ANOS\n# CBC EM DORSO NASAL EM 2010.\n# ONICOMICOSE\n- ITRACONAZOL 100 MG 3 MESES.\n- EM USO DE CICLOPIROX 8%\n# HAS, DM EM USO DE ENALAPRIL, METFORMINA, GLIBENCLAMIDA, FLUOXETINA.\nS # REFERE MELHORA PROGRESSIVA DO QUADRO.\nO # HIPERCERATOSE EM UNHAS DE HALUX BILATERAL, 2°, 3° E 4° PD A DIR.\nONICÓLISE DISTAL EM HÁLUX À DIREITA\nVARIZES BILATERALMENTE\nFOTODANO E MELANOSES SOLARES EM FACE E MMSS\nCERATOSE SEBORREICA EM FACE E TRONCO\nXEROSE\nSEM LESÕES SUSPEITAS DE CA\nA # ONICOMICOSE\nHIPERCERATOSE DEVIDO INSUFICIENCIA VENOSA ?\nFOTODANO.\nCBC EM DORSO NASAL 2010 - SEGUIMENTO\nP #\nMANTENHO ESMALTE CICLOPIROX 8%\nORIENTO MANTER HIDRATAÇÃO DA PELE\nREFORÇO USO DE FPS\nRETORNO EMOUT / 16 PARA SEGUIMENTO\nR2 Dr Vital Brasil\n \n \n \n ",
  "entities": {
    "Abreviação": [
      "CBC",
      "HAS",
      "DM",
      "MMSS",
      "FPS",
      "R2",
      "2° , 3° E 4° PD A DIR"
    ],
    "Doença ou Síndrome": [
      "CBC",
      "ONICOMICOSE",
      "HAS",
      "DM",
      "HIPERCERATOSE",
      "XEROSE",
      "ONICÓLISE DISTAL",
      "VARIZES BILATERALMENTE",
      "MELANOSES SOLARES",
      "CERATOSE SEBORREICA",
      "INSUFICIENCIA VENOSA"
    ],
    "Conceito Quantitativo": [
      "3",
      "100 MG"
    ],
    "Conceito Temporal": [
      "MESES"
    ],
    "Substância Farmacológica": [
      "ENALAPRIL",
      "METFORMINA",
      "GLIBENCLAMIDA",
      "FLUOXETINA",
      "CICLOPIROX 8%"
    ],
    "Aminoácido, Peptídeo ou Proteína": [
      "ENALAPRIL"
    ],
    "Substância Química Orgânica": [
      "METFORMINA",
      "GLIBENCLAMIDA",
      "FLUOXETINA",
      "CICLOPIROX 8%"
    ],
    "Conceito Espacial": [
      "BILATERAL"
    ],
    "Sinal ou Sintoma": [
      "FOTODANO",
      "XEROSE",
      "LESÕES SUSPEITAS DE CA"
    ],
    "Localização ou Região Corporal": [
      "FACE",
      "DORSO NASAL"
    ],
    "Parte do Corpo, Órgão ou Componente Orgânico": [
      "MMSS",
      "TRONCO",
      "UNHAS DE HALUX",
      "2° , 3° E 4° PD A DIR",
      "HÁLUX À DIREITA"
    ],
    "Negação": [
      "SEM"
    ],
    "Atividade de Assistência à Saúde": [
      "SEGUIMENTO",
      "MANTENHO",
      "ORIENTO",
      "MANTER",
      "REFORÇO",
      "RETORNO"
    ],
    "Grupo Profissional ou Ocupacional": [
      "R2"
    ],
    "Achado": [
      "HIDRATAÇÃO DA PELE"
    ],
    "Procedimento Terapêutico ou Preventivo": [
      "HIDRATAÇÃO DA PELE"
    ]
  },
  "labels": {}
}