{
  "prontuario_id": 212,
  "text": "QP: Herniorrafia Inguinal E\nHMA\n- Cx no dia 19/06/2015\n- Dor na região inguinal ao esforço\n- Urina normalmente\n- Paciente constipado de longo prazo, sente dor no local da cirurgia no ato evacuatorio\n- Sem dificuldade de se alimentar\nHMP\n- Hiperplasia Prostatica\n- Colecistectomia e Heniorrafia anterior a atual\n- Nega uso de medicações\nHMF\n- 1 irmão com DM\nCHV\n- Nega tabagsmo e etilismo atualmente, ja fez uso social anteriormente\nExame Fisico\nBEG, LOTE, anicterico, acianotico, corado e hidratado\n- Cicatriz cirurgica em região inguinal (E) sem sinais de inflamação / infecção ou sinais de secreção, não houve evidencia de abaulamente à manobra de Valsalva\nPlano\n- Retorno em 30 dias para reavaliação\n \n \n \n ",
  "entities": {
    "Sinal ou Sintoma": [
      "QP",
      "constipado",
      "anicterico",
      "abaulamente",
      "dificuldade de se alimentar",
      "sinais de inflamação",
      "sinais de secreção"
    ],
    "Abreviação": [
      "QP",
      "HMA",
      "Cx",
      "HMP",
      "HMF",
      "DM",
      "CHV",
      "BEG",
      "LOTE",
      "Herniorrafia Inguinal E"
    ],
    "Procedimento Terapêutico ou Preventivo": [
      "Cx",
      "cirurgia",
      "Colecistectomia",
      "Heniorrafia",
      "Herniorrafia Inguinal E"
    ],
    "Localização ou Região Corporal": [
      "inguinal"
    ],
    "Paciente ou Grupo com Deficiência": [
      "Paciente"
    ],
    "Negação": [
      "Sem",
      "Nega",
      "anicterico",
      "acianotico",
      "sem",
      "não"
    ],
    "Substância Farmacológica": [
      "medicações"
    ],
    "Doença ou Síndrome": [
      "DM",
      "tabagsmo",
      "etilismo",
      "Hiperplasia Prostatica"
    ],
    "Conceito Temporal": [
      "anteriormente",
      "longo prazo",
      "30 dias"
    ],
    "Achado": [
      "BEG",
      "LOTE",
      "anicterico",
      "acianotico",
      "corado",
      "hidratado"
    ],
    "Atividade de Assistência à Saúde": [
      "Plano",
      "Retorno",
      "reavaliação"
    ],
    "Função Fisiológica": [
      "ato evacuatorio"
    ],
    "Lesão ou Envenenamento": [
      "Cicatriz cirurgica"
    ],
    "Procedimento Diagnóstico": [
      "manobra de Valsalva"
    ]
  },
  "labels": {}
}