{
  "prontuario_id": 740,
  "text": "Lucas, 37 anos\nPrimeira consulta, encaminhada da ortpedia\nPaciente vítima de PAF em antebaço direito 25/06, com fratura em rádio (distal e cabeça) sob tratamento conservador com tala gessada. \nQueixa de parestesia e hipostesia em V quirodáctilo, dor em queimação e choque  e face dorsal proximal do I e II quirodáctilos. \nDesfazemos curativo de tala para avaliação:\nFM = 3 para oponência polegar-mínimo (limitação antálgica?)\nFM - 4 para abdução dos dedos, adução do polegar, flexão distal do II ao iV quirodáctilos \nFM = 5 para flexão distal do polegar, flexão e extensão do unho \nhipoestesia em toda face dorsal da mao , principalmente em IV e V quirodáctilos. \nOE em face radial do antebraço direto e OS em  face ventral do antebraço em linha média\nOE em superfície lateral do antebraço direito e OS face medial do cotovelo \nHD: lesão de radial superficial e ulnar. \nCD: Solciito ENMG por rota 3.  Retorno com exame. Se inidcação ortopédica, avisar neurocirurgia (programar possível abordagem conjunta)\n \n \n \n ",
  "entities": {
    "Atividade de Assistência à Saúde": [
      "consulta",
      "encaminhada",
      "Desfazemos",
      "avaliação",
      "CD",
      "Solciito",
      "Retorno",
      "abordagem conjunta"
    ],
    "Grupo Profissional ou Ocupacional": [
      "ortpedia",
      "neurocirurgia"
    ],
    "Paciente ou Grupo com Deficiência": [
      "Paciente",
      "vítima"
    ],
    "Lesão ou Envenenamento": [
      "PAF",
      "fratura",
      "lesão"
    ],
    "Abreviação": [
      "PAF",
      "OE",
      "OS",
      "HD",
      "CD",
      "ENMG",
      "FM = 3",
      "FM = 5"
    ],
    "Parte do Corpo, Órgão ou Componente Orgânico": [
      "rádio",
      "ulnar",
      "antebaço direito",
      "V quirodáctilo",
      "face dorsal proximal do I e II quirodáctilos",
      "IV e V quirodáctilos",
      "radial superficial"
    ],
    "Localização ou Região Corporal": [
      "cabeça",
      "face radial do antebraço direto",
      "face ventral do antebraço em linha média",
      "superfície lateral do antebraço direito",
      "face medial do cotovelo"
    ],
    "Sinal ou Sintoma": [
      "Queixa",
      "parestesia",
      "hipostesia",
      "choque",
      "hipoestesia",
      "dor em queimação",
      "FM = 3",
      "limitação antálgica"
    ],
    "Procedimento Diagnóstico": [
      "ENMG"
    ],
    "Resultado Laboratorial ou de Teste": [
      "exame"
    ],
    "Procedimento Terapêutico ou Preventivo": [
      "tratamento conservador",
      "tala gessada",
      "curativo de tala"
    ],
    "Achado": [
      "oponência polegar-mínimo",
      "adução do polegar",
      "flexão distal do II ao iV quirodáctilos",
      "FM = 5",
      "flexão distal do polegar",
      "flexão e extensão do unho"
    ],
    "Conceito Funcional": [
      "abdução dos dedos",
      "adução do polegar",
      "flexão distal do II ao iV quirodáctilos",
      "flexão distal do polegar",
      "flexão e extensão do unho"
    ]
  },
  "labels": {}
}