{
  "prontuario_id": 713,
  "text": "Lucas, 59\n- PO de Microcirurgia p/ tumor cerebral com tec. complementar (maio/2015)\n- Ressecção >90% pelo aspecto macroscópico - Glioma de alto grau.\n- Anatomo-patologico: Glioblastoma Multiforme ( grau IV-OMS )\n- Finalizou RT com 30 sessões em junho ( 60 Gys no total ) e QT em curso ( 10 de 12 sessões )\nPaciente com história de tratamento cirúrgico de tumor cerebral ( LOE fissura silviana esquerda 5x5x5 cm ), inicialmente e GCS 15 sem déficts neurológicos. \nQueixa-se de episódios de disfasia transitória e esporádica. Nega cefaleia.\nMUC: Fenitoina, lisador, omeprazol.\nAo exame: REG, euneico, hidratado e norocorado\nGCS 15 PIFR\nSem déficts neurológicos focais\nRNM de crânio (20/02/2016): Status PO de  ressecçao de LOE temporal esquerda, com lesões residuais que não apresentam alterações significativas, em comparaçao ao exame anterior (11/11/2015).\nCD: Mantemos acompanhamento ambulatorial.\nSolicito nova RNM de crânio.\n \n \n \n ",
  "entities": {
    "Conceito Temporal": [
      "PO",
      "esporádica"
    ],
    "Abreviação": [
      "PO",
      "tec",
      "RT",
      "QT",
      "MUC",
      "REG",
      "PIFR",
      "CD",
      "grau IV-OMS",
      "LOE fissura silviana esquerda",
      "GCS 15",
      "RNM de crânio",
      "ressecçao de LOE temporal esquerda"
    ],
    "Procedimento Terapêutico ou Preventivo": [
      "Ressecção",
      "RT",
      "QT",
      "Microcirurgia p/ tumor cerebral",
      "tratamento cirúrgico",
      "ressecçao de LOE temporal esquerda"
    ],
    "Conceito Quantitativo": [
      "&gt;90%",
      "30 sessões",
      "10 de 12 sessões",
      "5x5x5 cm"
    ],
    "Procedimento Laboratorial": [
      "Anatomo-patologico"
    ],
    "Paciente ou Grupo com Deficiência": [
      "Paciente"
    ],
    "Negação": [
      "sem",
      "Nega",
      "Sem",
      "não"
    ],
    "Doença ou Síndrome": [
      "cefaleia",
      "Glioblastoma Multiforme"
    ],
    "Sinal ou Sintoma": [
      "cefaleia",
      "LOE fissura silviana esquerda",
      "déficts neurológicos",
      "alterações significativas"
    ],
    "Substância Farmacológica": [
      "Fenitoina",
      "lisador",
      "omeprazol"
    ],
    "Substância Química Orgânica": [
      "Fenitoina",
      "lisador",
      "omeprazol"
    ],
    "Achado": [
      "REG",
      "euneico",
      "hidratado",
      "norocorado",
      "PIFR",
      "GCS 15"
    ],
    "Atividade de Assistência à Saúde": [
      "CD",
      "Mantemos",
      "acompanhamento",
      "Solicito"
    ],
    "Organização Relacionada à Saúde": [
      "ambulatorial"
    ],
    "Resultado Laboratorial ou de Teste": [
      "aspecto macroscópico"
    ],
    "Processo Neoplásico": [
      "Glioma de alto grau",
      "Glioblastoma Multiforme"
    ],
    "Classificação": [
      "grau IV-OMS"
    ],
    "Procedimento Diagnóstico": [
      "RNM de crânio"
    ],
    "Lesão ou Envenenamento": [
      "lesões residuais"
    ],
    "Conceito Qualitativo": [
      "comparaçao ao exame anterior"
    ]
  },
  "labels": {}
}