{
  "prontuario_id": 504,
  "text": "PRIMEIRA CONSULTA\nIRC - NEFROESCLEROSE HIPERTENSIVA? COM GESF SECUNDÁRIA? TGF ESTIMADA EM 20\nHEMATURIA - COM HISTÓRIA DE TABAGISMO\n  \nLucas, 53 ANOS\n\n- PACIENTE ENCAMINHADA POR PIORA DE FUNÇÃO RENAL - QUEIXA DE ASTENIA\n- PORTADORA DE HAS COM DIAGNÓSTICO HÁ CERCA DE 4 ANOS, COM CONTROLE REGULAR\n- HIPOTIREOIDISMO COM DX HÁ UM ANO.\n- NEGA CIRURGIAS PRÉVIAS\n- ITUS  PRÉVIAS\nUSO DE: LOSARTAN 50MG 12/12H, FUROSEMIDA 40MG, LEVOTIROXINA 100MCG, OMEPRAZOL 20MG.\n\n- EX TABAGISTA 40 ANOS MAÇO, PAROU HÁ 5 ANOS\n- SEDENTÁRIA\n- NEGA HISTÓRIA DE DOENÇA RENAL NA FAMÍLIA\n\nTROUXE EXAMES LABORATORIAIS:\n- HB 12\n- CREATININA 2,7 (TFG ESTIMADA 20ML/MIN)\n- HEMATURIA\n- US - RINS 9,2 E 9,4, COM CISTOS SIMPLES ( 3 NO TOTAL ), BEXIGA NORMAL\n- 2012 - PROTEINURIA DE 500MG\n\nAO EXAME:\nCORADA, HIDRATADA, AFEBRIL\nPA 140/90\nMV POSITIVO, SIMETRICO\nABDOMEN SP",
  "entities": {
    "Atividade de Assistência à Saúde": [
      "CONSULTA",
      "ENCAMINHADA",
      "DX"
    ],
    "Doença ou Síndrome": [
      "IRC",
      "TABAGISMO",
      "HAS",
      "HIPOTIREOIDISMO",
      "NEFROESCLEROSE HIPERTENSIVA",
      "GESF SECUNDÁRIA",
      "DOENÇA RENAL"
    ],
    "Abreviação": [
      "IRC",
      "HAS",
      "DX",
      "12/12H",
      "US",
      "PA",
      "GESF SECUNDÁRIA",
      "TGF ESTIMADA",
      "ITUS PRÉVIAS",
      "HB 12",
      "TFG ESTIMADA",
      "MV POSITIVO"
    ],
    "Sinal ou Sintoma": [
      "HEMATURIA",
      "QUEIXA",
      "AFEBRIL",
      "PIORA DE FUNÇÃO RENAL"
    ],
    "Paciente ou Grupo com Deficiência": [
      "PACIENTE"
    ],
    "Negação": [
      "NEGA",
      "AFEBRIL"
    ],
    "Substância Química Orgânica": [
      "LOSARTAN",
      "FUROSEMIDA",
      "OMEPRAZOL"
    ],
    "Substância Farmacológica": [
      "LOSARTAN",
      "FUROSEMIDA",
      "LEVOTIROXINA",
      "OMEPRAZOL"
    ],
    "Conceito Quantitativo": [
      "50MG",
      "40MG",
      "100MCG",
      "20MG",
      "20ML/MIN",
      "140/90",
      "40 ANOS MAÇO"
    ],
    "Aminoácido, Peptídeo ou Proteína": [
      "LEVOTIROXINA"
    ],
    "Hormônio": [
      "LEVOTIROXINA"
    ],
    "Achado": [
      "SEDENTÁRIA",
      "CORADA",
      "HIDRATADA",
      "SIMETRICO",
      "EX TABAGISTA",
      "MV POSITIVO"
    ],
    "Grupo Familiar": [
      "FAMÍLIA"
    ],
    "Resultado Laboratorial ou de Teste": [
      "HEMATURIA",
      "TGF ESTIMADA",
      "HB 12",
      "CREATININA 2 , 7",
      "TFG ESTIMADA",
      "RINS 9 , 2 E 9 , 4",
      "CISTOS SIMPLES",
      "BEXIGA NORMAL",
      "PROTEINURIA DE 500MG"
    ],
    "Procedimento Diagnóstico": [
      "US"
    ],
    "Atributo Clínico": [
      "PA"
    ],
    "Conceito Temporal": [
      "HÁ CERCA DE 4 ANOS",
      "HÁ UM ANO"
    ],
    "Procedimento Terapêutico ou Preventivo": [
      "CIRURGIAS PRÉVIAS"
    ],
    "Procedimento Laboratorial": [
      "EXAMES LABORATORIAIS"
    ]
  },
  "labels": {}
}