{
  "prontuario_id": 717,
  "text": "Lucas, 56 anos\n\n# CA colorretal ( sigmóide ) há 4 anos ( CX + QTX )\n# HAS em uso de atenol\n# DSLP em uso de svt\n# Prurido generalizado\n# Ex tabagista há 7 anos ( fumou por aprox 30 anos).\n\nTraz exames 03/11/14: hmg, cr, ureia, glicose, tgo, tgp, fa, ggt, Bt e frações, albumina, CEA: normais.\n\nS: Paciente com prurido generalizado após QT há 4 anos por Ca colorretal.\nCom uso de hidroxizine 25 mg dia paciente permanece assintomatica.\n\nnega hx de atopia.\n\no: Ausência de lesões elementares.\n\na: prurido generalizado idiopático\n\np: mantemos hidroxizine 25 mg / dia e hidratante ( EA 8% + MK 5 + OAD 5 + alantoina 1 ).\nRetorno em 6 meses.\n\nDoutor Vital Brazil ",
  "entities": {
    "Parte do Corpo, Órgão ou Componente Orgânico": [
      "sigmóide"
    ],
    "Procedimento Terapêutico ou Preventivo": [
      "CX",
      "QTX",
      "QT"
    ],
    "Abreviação": [
      "CX",
      "QTX",
      "HAS",
      "DSLP",
      "svt",
      "hmg",
      "cr",
      "fa",
      "ggt",
      "CEA",
      "QT",
      "EA",
      "MK",
      "OAD",
      "CA colorretal",
      "Bt e frações",
      "Ca colorretal"
    ],
    "Doença ou Síndrome": [
      "HAS",
      "DSLP"
    ],
    "Substância Farmacológica": [
      "atenol",
      "svt",
      "hidroxizine",
      "hidratante",
      "EA",
      "MK",
      "OAD"
    ],
    "Substância Química Orgânica": [
      "atenol",
      "svt",
      "hidroxizine"
    ],
    "Sinal ou Sintoma": [
      "Prurido",
      "assintomatica",
      "lesões",
      "prurido generalizado",
      "prurido generalizado idiopático"
    ],
    "Conceito Espacial": [
      "generalizado"
    ],
    "Conceito Quantitativo": [
      "7",
      "8%",
      "5",
      "1",
      "25 mg"
    ],
    "Conceito Temporal": [
      "anos",
      "após",
      "dia",
      "há 4 anos",
      "6 meses"
    ],
    "Procedimento Laboratorial": [
      "exames",
      "hmg",
      "cr",
      "ureia",
      "glicose",
      "tgo",
      "tgp",
      "fa",
      "ggt",
      "albumina",
      "CEA",
      "Bt e frações"
    ],
    "Resultado Laboratorial ou de Teste": [
      "normais"
    ],
    "Paciente ou Grupo com Deficiência": [
      "Paciente",
      "paciente"
    ],
    "Negação": [
      "assintomatica",
      "nega",
      "Ausência"
    ],
    "Atividade de Assistência à Saúde": [
      "mantemos",
      "Retorno"
    ],
    "Grupo Profissional ou Ocupacional": [
      "Doutor"
    ],
    "Processo Neoplásico": [
      "CA colorretal",
      "Ca colorretal"
    ],
    "Achado": [
      "Ex tabagista"
    ]
  },
  "labels": {}
}