{
  "prontuario_id": 735,
  "text": "RETORNO\n\nPaciente em primeira consulta com queixa de dor em punho e antebraço em queimação de forte intenidade.\nTrabalha como zeladora no CAPS e suas atividades laborais piora significativamente a dor, principalmente ao torcer pano.\nApresenta ainda quadro de transtorno depressivo maior em tratamento irregular.\nEsteve afastatada e internada em hospital psquiátrico.\nHá 2 meses retornou ao serviço e evoluiu com piora da queixa álgica.\nRelata que a dor é mais intensa no período frio e piora a queimação a noite. Parestesia em dorso de todos os dedos se, trajeto do mediano ou radicular.\nGCS 15.\nForça preservada.\nTinel presente bilateral, mais marcado a direita.\nPhalen ausente.\n\nFR não reagente 10,8\nT4 Livre 0,89 (normal)\nTSH 3,4 (Normal)\nFAN não reagente\nVHS 3mm\nPCR 1,1\n\nCD: Aguarda consulta com Doutor Vital Brazil Fila para ENMG - solicito urgencia. Aguardo exame. Prescrevo amitriptilina.\n \n \n \n ",
  "entities": {
    "Atividade de Assistência à Saúde": [
      "RETORNO",
      "consulta",
      "internada",
      "CD",
      "solicito",
      "Aguardo",
      "Prescrevo"
    ],
    "Paciente ou Grupo com Deficiência": [
      "Paciente"
    ],
    "Sinal ou Sintoma": [
      "queixa",
      "dor",
      "queimação",
      "Parestesia",
      "queixa álgica",
      "Tinel presente bilateral"
    ],
    "Parte do Corpo, Órgão ou Componente Orgânico": [
      "antebraço"
    ],
    "Conceito Qualitativo": [
      "queimação",
      "piora",
      "intensa",
      "forte intenidade"
    ],
    "Atividade Ocupacional": [
      "zeladora",
      "atividades laborais"
    ],
    "Abreviação": [
      "CAPS",
      "CD",
      "ENMG",
      "GCS 15",
      "FR não reagente 10 , 8",
      "VHS 3mm",
      "PCR 1 , 1"
    ],
    "Organização Relacionada à Saúde": [
      "CAPS",
      "hospital psquiátrico"
    ],
    "Conceito Temporal": [
      "noite",
      "Há 2 meses"
    ],
    "Localização ou Região Corporal": [
      "dorso",
      "mediano",
      "radicular"
    ],
    "Grupo Profissional ou Ocupacional": [
      "Doutor"
    ],
    "Procedimento Diagnóstico": [
      "ENMG"
    ],
    "Substância Farmacológica": [
      "amitriptilina"
    ],
    "Substância Química Orgânica": [
      "amitriptilina"
    ],
    "Doença ou Síndrome": [
      "transtorno depressivo maior"
    ],
    "Procedimento Terapêutico ou Preventivo": [
      "tratamento irregular"
    ],
    "Achado": [
      "GCS 15",
      "Força preservada",
      "Phalen ausente"
    ],
    "Resultado Laboratorial ou de Teste": [
      "FR não reagente 10 , 8",
      "T4 Livre 0 , 89",
      "TSH 3 , 4",
      "FAN não reagente",
      "VHS 3mm",
      "PCR 1 , 1"
    ]
  },
  "labels": {}
}