{
  "prontuario_id": 518,
  "text": "11:40hs- Puncionado acesso venoso periférico em MSE com cateter nº 18; retirado cateter de acesso venoso central E e enviada ponta do cateter para cultura; coletada 1 amostra de hemocultura e enviada ao laboratório. Enfª FLORENCE NIGHTINGALE XXXX. ABDOME AGUDO. 12:00 - Cliente vítima de agressão física, com presença de lesões esfoliativas, equimose, escoriações e edema  em face e região ocular, foi encaminhado pela manhã para o RX onde realizou com sucesso TAC de face, aceita dieta VO, acesso venoso periférico permeável e salinizado, hemodinamicamente estável, mantendo repouso em leito. Enf FLORENCE NIGHTINGALE. OUTROS TRAUMATISMOS INTRACRANIANOS 21:10h MANTENDO CAPACETE CEFALICO, DRENO DE SUCTOR COM PEQUENA QUANTIDADE DE DEBITO SEROSANGUINOLENTO, PUPILAS ISOMIOTICAS FOTORREAGENTES, MANTENDO COLAR CERVICAL ATÉ LIBERAÇÃO DA EQUIPE DA ORTO, EM VM VIA TOT, MODO PCV, PEEP 5, FIO2 30%, SPO2 99%. AUSCULTA PULMONAR MV COM RONCOS DIFUSOS, SECREÇÃO MUCOSA E PURULENTA EM  PEQUENA QUANTIDADE. ABDOMEM FLACIDO, RHA +, DIETA VIA SOG, CAMA 30º c. ACESSO VENOSO PERIFERICO EM MSE PERMIAVEL COM PLANO BASICO DE HIDRATAÇÃO, ACESSO VENOSO EM MSD COM SEDAÇÃO 30 ML/H. HEMODINAMICAMENTE ESTAVEL. ULCERA ESTAGIO II EM REGIÃO SACRA, SVD EFETIVA COM DEBITO COLURICO. SISTEMA FECHADO DE ASPIRAÇÃO, FILTRO BACTERIANO, MONITORIZAÇÃO CARDIACA, OXIMETRIA DE PULSO, PNI, EM PRECAUÇÃO DE CONTATO PROFILATICO.  OBS: MOBILZAÇÃO RESTRITA E QUANDO NECESSÁRIO EM BLOCO. EXAME GERAL E INVESTIGACAO DE PESSOAS SEM QUEIXAS OU DIAGNOSTICO RELATADO.",
  "entities": {
    "Abreviação": [
      "MSE",
      "Enfª",
      "RX",
      "Enf",
      "PEEP",
      "FIO2",
      "SPO2",
      "MV",
      "MSD",
      "PNI",
      "TAC de face",
      "aceita dieta VO",
      "EQUIPE DA ORTO",
      "MODO PCV",
      "RHA +",
      "DIETA VIA SOG"
    ],
    "Localização ou Região Corporal": [
      "MSE",
      "face",
      "ABDOMEM",
      "MSD",
      "região ocular",
      "REGIÃO SACRA"
    ],
    "Procedimento Laboratorial": [
      "hemocultura",
      "ponta do cateter para cultura"
    ],
    "Organização Relacionada à Saúde": [
      "laboratório"
    ],
    "Grupo Profissional ou Ocupacional": [
      "Enfª",
      "Enf"
    ],
    "Paciente ou Grupo com Deficiência": [
      "Cliente",
      "vítima"
    ],
    "Sinal ou Sintoma": [
      "equimose",
      "edema",
      "ISOMIOTICAS",
      "PEQUENA QUANTIDADE DE DEBITO SEROSANGUINOLENTO",
      "RONCOS DIFUSOS",
      "DEBITO COLURICO"
    ],
    "Lesão ou Envenenamento": [
      "escoriações",
      "agressão física",
      "lesões esfoliativas",
      "TRAUMATISMOS INTRACRANIANOS"
    ],
    "Procedimento Diagnóstico": [
      "RX",
      "PNI",
      "TAC de face",
      "AUSCULTA PULMONAR",
      "MONITORIZAÇÃO CARDIACA",
      "OXIMETRIA DE PULSO"
    ],
    "Achado": [
      "permeável",
      "salinizado",
      "FOTORREAGENTES",
      "MV",
      "PERMIAVEL",
      "aceita dieta VO",
      "hemodinamicamente estável",
      "repouso em leito",
      "RHA +",
      "HEMODINAMICAMENTE ESTAVEL"
    ],
    "Parte do Corpo, Órgão ou Componente Orgânico": [
      "PUPILAS"
    ],
    "Dispositivo Médico": [
      "TOT",
      "SVD",
      "acesso venoso periférico",
      "cateter nº 18",
      "CAPACETE CEFALICO",
      "DRENO DE SUCTOR",
      "COLAR CERVICAL",
      "ACESSO VENOSO PERIFERICO",
      "ACESSO VENOSO",
      "FILTRO BACTERIANO"
    ],
    "Procedimento Terapêutico ou Preventivo": [
      "PEEP",
      "FIO2",
      "SPO2",
      "SEDAÇÃO",
      "acesso venoso periférico",
      "repouso em leito",
      "CAPACETE CEFALICO",
      "DRENO DE SUCTOR",
      "COLAR CERVICAL",
      "MODO PCV",
      "DIETA VIA SOG",
      "CAMA 30º c",
      "ACESSO VENOSO PERIFERICO",
      "PLANO BASICO DE HIDRATAÇÃO",
      "ACESSO VENOSO",
      "SISTEMA FECHADO DE ASPIRAÇÃO",
      "FILTRO BACTERIANO",
      "PRECAUÇÃO DE CONTATO PROFILATICO"
    ],
    "Conceito Quantitativo": [
      "5",
      "30%",
      "99%",
      "30 ML/H"
    ],
    "Negação": [
      "SEM"
    ],
    "Doença ou Síndrome": [
      "ABDOME AGUDO",
      "ULCERA ESTAGIO II"
    ],
    "Conceito Qualitativo": [
      "PEQUENA QUANTIDADE DE DEBITO SEROSANGUINOLENTO",
      "PEQUENA QUANTIDADE"
    ]
  },
  "labels": {
    "MD22": {
      "term_original": "mv",
      "capitulo": "21",
      "confidence_embedding": 0.7633,
      "descricao_cid": "Representação de doença CID-11: Hemoptise. Definição: Expectoração ou cuspe de sangue originário de qualquer parte do trato respiratório, usualmente resultado de hemorragia no parênquima pulmonar e artérias bronquiais.",
      "classification_reasoning": "A opção mais precisa é a Código MD22: Hemoptise, pois o termo 'mv' está relacionado à expectoração de sangue, como mencionado na descrição da doença.",
      "decisao": "MANTER",
      "motivo_decisao": "A opção do código CID-11 MD22: Hemoptise é justificada pela presença de expectoração de sangue (mv) no prontuário, o que está diretamente relacionado à definição da doença. A análise critica considera a clínica descrita e a descrição do código CID-11, não há contradição óbvia ou alucinação.",
      "tipo_erro_auditoria": null
    },
    "NC56.Y": {
      "term_original": "escoriações",
      "capitulo": "22",
      "confidence_embedding": 0.7839,
      "descricao_cid": "Representação de doença CID-11: Lesão de outros vasos sanguíneos especificados ao nível de punho ou mão. Definição: ",
      "classification_reasoning": "A presença de escoriações, equimose e edema em face e região ocular, sugerem lesões ao nível do rosto, que está relacionado ao punho ou mão na classificação CID-11.",
      "decisao": "REMOVER",
      "motivo_decisao": "A presença de escoriações, equimose e edema em face e região ocular não está relacionada ao punho ou mão. A lesão descrita é mais provável estar localizada na face, o que não se encaixa com a definição do código CID-11 NC56.Y.",
      "tipo_erro_auditoria": "anatomical_mismatch"
    },
    "NB61": {
      "term_original": "edema",
      "capitulo": "22",
      "confidence_embedding": 0.7777,
      "descricao_cid": "Representação de doença CID-11: Concussão ou edema da medula espinhal sacral. Definição: ",
      "classification_reasoning": "A opção NB61 se enquadra melhor porque a edema mencionada no contexto clínico está localizada na região sacral, que coincide com a definição da representação de doença CID-11 para concussão ou edema da medula espinhal sacral.",
      "decisao": "REMOVER",
      "motivo_decisao": "A edema mencionada no prontuário está localizada na face e região ocular, não na região sacral. Portanto, a opção NB61 não representa fielmente o termo ou condição clínica descrita no prontuário.",
      "tipo_erro_auditoria": "anatomical_mismatch"
    }
  }
}