{
  "prontuario_id": 369,
  "text": "# ANGIOPLASTIA + IMPLANTE DE STENT NA PONTE DE SAFENA PARA ACD. PCT, 61 ANOS, COM HISTORIA DE HIPERTENSÃO ARTERIAL, DM E CRM PREVIOS  INTERNA PARA REALIZAÇÃO DE ANGIOPLASTIA NA PONTE DE SAFENA PARA ARTERIA CORONARIA DIREITA. PROCEDIMENTO OCORRE SEM INTERCORRENCIAS E O PCT RECEBE ALTA EM BOAS CONDIÇÕES CLINICAS PARA  ACOMPANHAMENTO AMBULATORIAL.  # RECOMENDAÇÕES PÓS-ALTA: ,- RETORNO PARA EMERGENCIA EM CASO DE QUALQUER INTERCORRENCIA; - USO DE TICLOPIDINA POR 30 DIAS, - RETORNO AO MEDICO ASSISTENTE. Paciente com DM, HAS, IC, CI grave (vide laudo de CAT), HBP com retenção urinária. Vem à emergência por edema agudo de pulmão + dor torácica em 04/06/2003. Apresentando angina aos mínimos esforços (classe IV). Foi manejado inicialmente com êxito, mas apresentou bradicardia sintomática na emergência com uso de B-bloqueador sendo, então, transferido ao CTI e tentado otimização de tratamento antianginoso, após resolução de bradicardia. Seguiu com angina classe III - IV, sendo revisado cintilografia prévia com isquemia, optou-se pela realização de CAT em 18/06/2003 para tentativa posterior de tratamento cirurgico para controle de sintomas. Realizado cateterismo Tronco da coronária esquerda com lesão de aproximadamente 60 % no terço proximal para médio. Artéria descendente anterior esquerda ocluida no terço médio. Presença de circulação colateral intercoronariana.   Artéria circunflexa com lesão de aproximadamente 50 % no óstio e lesão de aproximadamente 50 % no segmento proximal. Grande ramo marginal com lesão de 70 % no terço médio. Artéria coronária direita com lesão de aproximadamente 45 a 50 % no terço proximal para médio. Ramo descendente posterior com lesão severa na origem, oclusão no terço proximal para médio. Ramo ventricular posterior com lesão severa (mais ou menos 90 %) no terço médio. Realizou-se angioplastia de RVP. SEM LEITO DISTAL. Apresentou infarto inferior durante o procedimento e dois dias após FA c/ alta resposta ventricular. Decidiu-se otimização de tratamento antianginoso com terapia farmacológica e, para tanto, definiu-se pelo implante de Marca-Passo definitivo DDI em 23/06/2003. Passou a apresentar melhora sintomática e recebeu alta do CTI em 24/06/2003. Permaneceu sem angina (realizou pequenos esforços durante internação). Recebe alta com tratamento otimizado e foi iniciado anticoagulação INR chegou a 8,5 após 3 dias de ATC. Permaneceu sem warfarin por três dias e INR 3,6. Recebe alta em melhores condições clínicas com plano de seguir acompanhamento no ambulatório de CI. PRESCRIÇÃO: AAS 100 mg no almoço, Sinvastatina 40 mg às 22:00, Amlodipina 5 mg /dia, Isossorbida 40 mg às 8:00, às 16:00 e às 20:00, Atenolol 50 mg /dia, Insulina NPH 30 UI SC antes do café e 8 UI SC.",
  "entities": {
    "Procedimento Terapêutico ou Preventivo": [
      "ANGIOPLASTIA",
      "CRM",
      "PROCEDIMENTO",
      "RECOMENDAÇÕES",
      "CAT",
      "cateterismo",
      "anticoagulação",
      "ATC",
      "IMPLANTE DE STENT",
      "ACOMPANHAMENTO AMBULATORIAL",
      "transferido ao CTI",
      "otimização de tratamento antianginoso",
      "tratamento cirurgico",
      "angioplastia de RVP",
      "terapia farmacológica",
      "implante de Marca-Passo definitivo",
      "tratamento otimizado"
    ],
    "Parte do Corpo, Órgão ou Componente Orgânico": [
      "ACD",
      "PONTE DE SAFENA",
      "ARTERIA CORONARIA DIREITA",
      "Tronco da coronária esquerda",
      "Artéria descendente anterior esquerda",
      "Artéria circunflexa",
      "Grande ramo marginal",
      "Artéria coronária direita",
      "Ramo descendente posterior",
      "Ramo ventricular posterior"
    ],
    "Abreviação": [
      "ACD",
      "PCT",
      "DM",
      "CRM",
      "HAS",
      "IC",
      "HBP",
      "B-bloqueador",
      "CAT",
      "CTI",
      "ATC",
      "AAS",
      "SC",
      "CI grave",
      "laudo de CAT",
      "transferido ao CTI",
      "angioplastia de RVP",
      "Insulina NPH"
    ],
    "Paciente ou Grupo com Deficiência": [
      "PCT",
      "Paciente"
    ],
    "Doença ou Síndrome": [
      "DM",
      "HAS",
      "IC",
      "HBP",
      "HIPERTENSÃO ARTERIAL",
      "CI grave",
      "edema agudo de pulmão"
    ],
    "Negação": [
      "SEM",
      "sem"
    ],
    "Sinal ou Sintoma": [
      "INTERCORRENCIAS",
      "INTERCORRENCIA",
      "sintomas",
      "angina",
      "retenção urinária",
      "dor torácica",
      "angina aos mínimos esforços",
      "bradicardia sintomática",
      "angina classe III - IV"
    ],
    "Atividade de Assistência à Saúde": [
      "RECOMENDAÇÕES",
      "RETORNO",
      "alta",
      "acompanhamento",
      "PRESCRIÇÃO",
      "RECEBE ALTA"
    ],
    "Conceito Temporal": [
      "PÓS-ALTA",
      "por três dias"
    ],
    "Organização Relacionada à Saúde": [
      "EMERGENCIA",
      "emergência",
      "CTI"
    ],
    "Substância Química Orgânica": [
      "TICLOPIDINA",
      "warfarin",
      "AAS",
      "Amlodipina",
      "Isossorbida",
      "Atenolol"
    ],
    "Substância Farmacológica": [
      "TICLOPIDINA",
      "B-bloqueador",
      "warfarin",
      "AAS",
      "Sinvastatina",
      "Amlodipina",
      "Isossorbida",
      "Atenolol",
      "Insulina NPH"
    ],
    "Processo Neoplásico": [
      "HBP"
    ],
    "Procedimento Diagnóstico": [
      "CAT",
      "cateterismo"
    ],
    "Função Patológica": [
      "ocluida",
      "oclusão"
    ],
    "Produto Intelectual": [
      "PRESCRIÇÃO"
    ],
    "Achado": [
      "BOAS CONDIÇÕES CLINICAS",
      "manejado inicialmente com êxito",
      "resolução de bradicardia",
      "melhora sintomática",
      "realizou pequenos esforços",
      "melhores condições clínicas"
    ],
    "Grupo Profissional ou Ocupacional": [
      "MEDICO ASSISTENTE"
    ],
    "Resultado Laboratorial ou de Teste": [
      "laudo de CAT",
      "cintilografia prévia com isquemia",
      "terço proximal para médio",
      "circulação colateral intercoronariana",
      "INR chegou a 8 , 5",
      "INR 3 , 6"
    ],
    "Classificação": [
      "classe IV"
    ],
    "Conceito Qualitativo": [
      "classe IV"
    ],
    "Conceito Quantitativo": [
      "mais ou menos 90 %",
      "100 mg",
      "40 mg",
      "5 mg",
      "50 mg",
      "30 UI",
      "8 UI"
    ],
    "Dispositivo Médico": [
      "implante de Marca-Passo definitivo"
    ],
    "Aminoácido, Peptídeo ou Proteína": [
      "Insulina NPH"
    ],
    "Hormônio": [
      "Insulina NPH"
    ]
  },
  "labels": {}
}