{
  "prontuario_id": 421,
  "text": "Paciente com diagnostico de LMA - M4 em maio de 2006 em remissao completa apos 2 ciclos de intensificacao , sem cariograma e sem doador aparentado compativel , interna para realizacao de TMO autologo. Internacao para colocacao de cateter de Hickmann, condicionamento com BUCY, infusao de 8,6 x 106 CD34 /Kg no D0 (07/05/07), ficou neutropenica no D+2, iniciou com neutropenia febril no D+6, sem foco estabelecido , iniciado com cefepime apos coleta de culturais, permanecendo febril apos 72 h, acrescentado ao esquema vancomicina apos nova coleta de culturais , manteve-se febril por 72h, solicitado entao, CT torax e seios da face, nova coleta de culturais e iniciado com pipe+tazo. As tomografias nao evidenciaram lesoes sugestivas de infeccao fungica, porem iniciou-se com anfotericina, pois a paciente persistia febril. Fez uso de anfotericina por 5 dias e pipe+tazo por 10 dias, permanecendo afebril desde as primeiras 24h  de anfotericina. Cuturais negativos. A paciente apresesntou ainda nesta internacao, quadro de mucosite severa com resolucao completa do quadro. Apresentou pega do TMO no D+19.",
  "entities": {
    "Conceito Temporal": [
      "apos",
      "D0",
      "D+2",
      "D+6",
      "D+19",
      "5 dias",
      "10 dias"
    ],
    "Negação": [
      "sem",
      "nao",
      "afebril"
    ],
    "Procedimento Laboratorial": [
      "cariograma",
      "coleta de culturais",
      "nova coleta de culturais"
    ],
    "Atividade de Assistência à Saúde": [
      "interna",
      "Internacao",
      "colocacao",
      "infusao",
      "solicitado",
      "iniciado",
      "iniciou-se",
      "internacao"
    ],
    "Doença ou Síndrome": [
      "neutropenica",
      "LMA - M4",
      "neutropenia febril",
      "mucosite severa"
    ],
    "Substância Química Orgânica": [
      "cefepime",
      "anfotericina"
    ],
    "Antibiótico": [
      "cefepime",
      "vancomicina",
      "anfotericina"
    ],
    "Sinal ou Sintoma": [
      "febril",
      "afebril",
      "quadro",
      "persistia febril"
    ],
    "Procedimento Terapêutico ou Preventivo": [
      "esquema",
      "2 ciclos de intensificacao",
      "TMO autologo",
      "condicionamento com BUCY"
    ],
    "Aminoácido, Peptídeo ou Proteína": [
      "vancomicina"
    ],
    "Procedimento Diagnóstico": [
      "CT",
      "tomografias"
    ],
    "Abreviação": [
      "CT",
      "pipe+tazo",
      "LMA - M4",
      "TMO autologo",
      "condicionamento com BUCY"
    ],
    "Localização ou Região Corporal": [
      "torax"
    ],
    "Substância Farmacológica": [
      "pipe+tazo"
    ],
    "Achado": [
      "remissao completa",
      "resolucao completa"
    ],
    "Grupo Populacional": [
      "doador aparentado compativel"
    ],
    "Dispositivo Médico": [
      "cateter de Hickmann"
    ],
    "Conceito Quantitativo": [
      "8 , 6 x 106 CD34 /Kg"
    ],
    "Conceito Espacial": [
      "foco estabelecido"
    ],
    "Resultado Laboratorial ou de Teste": [
      "Cuturais negativos"
    ]
  },
  "labels": {
    "2.6": {
      "term_original": "lma - m4",
      "capitulo": "02",
      "confidence_embedding": 0.0,
      "descricao_cid": "",
      "classification_reasoning": "Escolhemos o código 2A60.30 (outras opções foram descartadas) porque o termo 'LMA - M4' é um diagnóstico de Leucemia mieloide aguda com diferenciação mínima, que é uma das subcategorias da LMA (Leucemia mieloide aguda). A definição do código 2A60.30 se encaixa perfeitamente no contexto clínico descrito na internação para realizacao de TMO autologo e internacao para colocacao de cateter de Hickmann, condicionamento com BUCY, infusao de 8,6 x 106 CD34 /Kg no D0, entre outros procedimentos e medicamentos utilizados. O diagnóstico foi feito em maio de 2006 e o paciente apresentou remissão completa após 2 ciclos de intensificacao.",
      "decisao": "MANTER",
      "motivo_decisao": "O termo 'LMA - M4' é um diagnóstico de Leucemia mieloide aguda com diferenciação mínima, que é uma das subcategorias da LMA (Leucemia mieloide aguada). A definição do código 2A60.30 se encaixa perfeitamente no contexto clínico descrito na internação para realizacao de TMO autologo e internacao para colocacao de cateter de Hickmann, condicionamento com BUCY, infusao de 8,6 x 106 CD34 /Kg no D0, entre outros procedimentos e medicamentos utilizados. O diagnóstico foi feito em maio de 2006 e o paciente apresentou remissão completa após 2 ciclos de intensificacao.",
      "tipo_erro_auditoria": null
    },
    "MG30.66": {
      "term_original": "mucosite severa",
      "capitulo": "21",
      "confidence_embedding": 0.6987,
      "descricao_cid": "Representação de doença CID-11: Cefaleia ou dor orofacial crônicas associadas a transtorno intracraniano não vascular. Definição: Cefaleia ou dor orofacial crônicas associadas a transtorno intracraniano não vascular são causadas por transtornos intracranianos não vasculares, e têm duração de mais de três meses. A dor ocorre em pelo menos 50% dos dias durante pelo menos três meses. A duração diária da dor é de pelo menos 2 horas.",
      "classification_reasoning": "A paciente apresentou quadro de mucosite severa, o que sugere uma inflamação crônica e persistente na mucosa oral e/ou faringeana. A opção MG30.66 é a mais precisa porque relaciona cefaleia ou dor orofacial crônicas com transtornos intracranianos não vasculares, o que pode estar associado à mucosite severa.",
      "decisao": "REMOVER",
      "motivo_decisao": "A opção MG30.66 não se aplica ao quadro de mucosite severa descrito no prontuário, pois a definição do código CID-11 refere-se a cefaleia ou dor orofacial crônicas associadas a transtornos intracranianos não vasculares, e não há evidência clínica de que isso esteja relacionado à mucosite severa. A classificação é demasiado genérica e não captura o quadro específico da paciente.",
      "tipo_erro_auditoria": "overly_generic_entity"
    },
    "MA15.0": {
      "term_original": "febril",
      "capitulo": "21",
      "confidence_embedding": 0.7192,
      "descricao_cid": "Representação de doença CID-11: Bacteremia. Definição: Presença de bactérias no sangue. Isto pode ser detectado, por exemplo, por uma hemocultura positiva.",
      "classification_reasoning": "A paciente apresentou febre após coleta de culturais e persistiu com febre apesar do tratamento com cefepime, vancomicina e anfotericina. Isso sugere a presença de bactérias no sangue (bacteremia), justificando a escolha do código MA15.0.",
      "decisao": "REMOVER",
      "motivo_decisao": "A febre não é um diagnóstico de bacteremia. A paciente apresentou febre após coleta de culturais e persistiu com febre apesar do tratamento, mas isso não significa que haja bactérias no sangue. É necessário mais informações para confirmar a presença de bacteremia.",
      "tipo_erro_auditoria": "wrong_entity_type"
    }
  }
}