{
  "prontuario_id": 516,
  "text": "GLASGOW 15, PUPILAS ISOCÓRICAS FOTORREAGENTES, EM NÉVOA ÚMIDA, SATURANDO 97% NO MOMENTO. AUSCULTA PULMONAR MV COM RONCOS DIFUSOS, SECREÇÃO SEROSA EM MÉDIA QUANTIDADE. ABDÔMEN FLÁCIDO, RHA +. SNE COM DIETA, SNG COM DÉBITO MARRON EM MÉDIA QUANTIDADE. ACESSO VENOSO PERIFÉRICO EM MSD COM FENTANIL 5 ML/H, ELETRÓLITOS 12 ML/H, HEMODINAMICAMENTE ESTÁVEL. MONITORIZAÇÃO CARDIOSCOPICA + OXIMETRIA + PNI. SVD EFETIVA COM DÉBITO COLÚRICO.    LACERAÇÃO E RUPTURA OCULAR COM PROLAPSO OU PERDA DE TECIDO INTRAOCULAR. 8H: Realizado aspiração, observado aspecto parecido com a dieta. Desligo a dieta para verificar posicionamento de SNE; a mesma estava apenas fixada e a ponta da sonda estava no nariz. Às 12h30min, a Enfermeira Florence veio e realizou nova passagem de sonda. Enfª Florence, COREN PR XXXX. EDEMA CEREBRAL. 18:45h: Contato com dr. Juliano da clínica cirúrgica, que fará o pedido do raio-X para verificar posicionamento de SNE. Enf. Florence, Coren PR XXXXXX. EXAME GERAL E INVESTIGAÇÃO DE PESSOAS SEM QUEIXAS OU DIAGNÓSTICO RELATADO. 17:30: paciente relata mal-estar após retornar da colonoscopia, PA = 160/100, Temp = 38, FC = 100, FR = 23, apresentou 1 episódio de vômito + diarréia, apresentou melhora após ser medicado cpm. Enf. Florence. ABDOME AGUDO.",
  "entities": {
    "Conceito Quantitativo": [
      "97%",
      "ML/H",
      "160/100",
      "38",
      "100",
      "23",
      "MÉDIA QUANTIDADE .",
      "MÉDIA QUANTIDADE"
    ],
    "Localização ou Região Corporal": [
      "ABDÔMEN",
      "MSD"
    ],
    "Abreviação": [
      "SNE",
      "SNG",
      "MSD",
      "ML/H",
      "PNI",
      "Enfª",
      "Enf",
      "cpm",
      "RHA +",
      "SVD EFETIVA"
    ],
    "Dispositivo Médico": [
      "SNE",
      "SNG",
      "ACESSO VENOSO PERIFÉRICO",
      "SVD EFETIVA"
    ],
    "Alimento": [
      "DIETA",
      "dieta"
    ],
    "Substância Química Orgânica": [
      "FENTANIL"
    ],
    "Substância Farmacológica": [
      "FENTANIL",
      "ELETRÓLITOS"
    ],
    "Procedimento Diagnóstico": [
      "OXIMETRIA",
      "raio-X",
      "colonoscopia",
      "AUSCULTA PULMONAR",
      "MONITORIZAÇÃO CARDIOSCOPICA"
    ],
    "Lesão ou Envenenamento": [
      "LACERAÇÃO",
      "RUPTURA OCULAR"
    ],
    "Anormalidade Anatômica": [
      "PROLAPSO"
    ],
    "Procedimento Terapêutico ou Preventivo": [
      "aspiração",
      "SNE",
      "medicado",
      "NÉVOA ÚMIDA",
      "ACESSO VENOSO PERIFÉRICO",
      "passagem de sonda"
    ],
    "Parte do Corpo, Órgão ou Componente Orgânico": [
      "nariz"
    ],
    "Grupo Profissional ou Ocupacional": [
      "dr",
      "Enf"
    ],
    "Paciente ou Grupo com Deficiência": [
      "paciente"
    ],
    "Sinal ou Sintoma": [
      "mal-estar",
      "vômito",
      "diarréia",
      "MV COM RONCOS DIFUSOS",
      "DÉBITO MARRON",
      "DÉBITO COLÚRICO",
      "ABDOME AGUDO"
    ],
    "Atividade de Assistência à Saúde": [
      "medicado",
      "EXAME GERAL",
      "INVESTIGAÇÃO DE PESSOAS"
    ],
    "Achado": [
      "GLASGOW 15",
      "PUPILAS ISOCÓRICAS FOTORREAGENTES",
      "RHA +",
      "DÉBITO MARRON",
      "HEMODINAMICAMENTE ESTÁVEL"
    ],
    "Substância Corporal": [
      "SECREÇÃO SEROSA"
    ],
    "Tecido": [
      "TECIDO INTRAOCULAR"
    ],
    "Função Patológica": [
      "EDEMA CEREBRAL"
    ]
  },
  "labels": {
    "edema cerebral": {
      "capitulo": "08"
    },
    "glasgow 15": {
      "capitulo": "09"
    },
    "ruptura ocular": {
      "capitulo": "09"
    },
    "laceração": {
      "capitulo": "22"
    },
    "prolapso": {
      "capitulo": "09"
    },
    "débito colúrico": {
      "capitulo": "11"
    },
    "mal-estar": {
      "capitulo": "21"
    },
    "vômito": {
      "capitulo": "13"
    },
    "mv com roncos difusos": {
      "capitulo": "12"
    },
    "débito marron": {
      "capitulo": "13"
    },
    "diarréia": {
      "capitulo": "13"
    },
    "pupilas isocóricas fotorreagentes": {
      "capitulo": "09"
    },
    "abdome agudo": {
      "capitulo": "13"
    }
  }
}