{
  "prontuario_id": 966,
  "text": "16:06: 2° di com hx de sepse de foco urinário? intoxicação exógena? No momento, consciente, orientada, calma, eupnéica, respirando em ar ambiente, comunicativa, em repouso no leito, monitorizada, fc 99, pa 121/75, sato2 95, acesso  venoso central à direita com dopamina a 25ml/h e soroterapia em curso, uso de fralda com evacuação ausente, svd com débito amarelo claro, sem queixas álgicas, liberado dieta pela residente Florence, segue sob cuidados. 15:20h: S: Glasgow 15, em ar ambiente, EC 0. O: 2º PO de reconstrução intestinal. Pupilas iso/foto. CPP sem RA. Abdômen flácido, globoso, RHA+. FO limpa e seca, região infra-abdominal com presença de dreno de penrose D e dreno de waterman E, sem débito em bolsas de colostomia descartáveis. Acesso venoso em MSD com infusão de soroterapia. Mantém cateter epidural para analgesia. SVD com presença de diurese efetiva, evacuação ausente. Pele íntegra em região dorsal e sacra. Extremidades aquecidas, perfusão periférica adequada, sem edemas. Monitorizada continuamente com parâmetros de PA não invasiva, cardioscopia e oximetria de pulso. Segue sob cuidados intensivos. A: Aguarda agendamento de Doppler de MID. P: Conforme prescrição de enfermagem.   ",
  "entities": {
    "Achado": [
      "consciente",
      "orientada",
      "calma",
      "eupnéica",
      "comunicativa",
      "monitorizada",
      "RHA+",
      "limpa",
      "seca",
      "respirando em ar ambiente",
      "repouso no leito",
      "débito amarelo claro",
      "Glasgow 15",
      "Pupilas iso/foto",
      "diurese efetiva",
      "Pele íntegra",
      "perfusão periférica adequada"
    ],
    "Conceito Espacial": [
      "direita",
      "D",
      "E"
    ],
    "Substância Química Orgânica": [
      "dopamina"
    ],
    "Substância Farmacológica": [
      "dopamina"
    ],
    "Conceito Funcional": [
      "uso"
    ],
    "Objeto Manufaturado": [
      "fralda"
    ],
    "Dispositivo Médico": [
      "fralda",
      "svd",
      "SVD",
      "acesso venoso central",
      "dreno de penrose",
      "dreno de waterman",
      "bolsas de colostomia descartáveis .",
      "Acesso venoso",
      "cateter epidural"
    ],
    "Procedimento Terapêutico ou Preventivo": [
      "svd",
      "analgesia",
      "SVD",
      "acesso venoso central",
      "soroterapia em curso",
      "reconstrução intestinal",
      "Acesso venoso",
      "infusão de soroterapia",
      "cateter epidural"
    ],
    "Abreviação": [
      "svd",
      "EC",
      "PO",
      "CPP",
      "RHA+",
      "FO",
      "D",
      "E",
      "MSD",
      "SVD",
      "MID",
      "fc 99",
      "pa 121/75",
      "sato2 95",
      "Pupilas iso/foto",
      "PA não invasiva"
    ],
    "Alimento": [
      "dieta"
    ],
    "Grupo Profissional ou Ocupacional": [
      "residente"
    ],
    "Atividade de Assistência à Saúde": [
      "cuidados",
      "cuidados intensivos",
      "prescrição de enfermagem"
    ],
    "Conceito Temporal": [
      "PO",
      "continuamente"
    ],
    "Localização ou Região Corporal": [
      "Abdômen",
      "MSD",
      "sacra",
      "MID",
      "região infra-abdominal",
      "região dorsal"
    ],
    "Sinal ou Sintoma": [
      "globoso",
      "evacuação ausente"
    ],
    "Lesão ou Envenenamento": [
      "FO",
      "intoxicação exógena"
    ],
    "Parte do Corpo, Órgão ou Componente Orgânico": [
      "Extremidades"
    ],
    "Procedimento Diagnóstico": [
      "Monitorizada",
      "cardioscopia",
      "Doppler",
      "PA não invasiva",
      "oximetria de pulso"
    ],
    "Doença ou Síndrome": [
      "sepse de foco urinário"
    ],
    "Negação": [
      "evacuação ausente"
    ]
  },
  "labels": {
    "pele íntegra": {
      "capitulo": "14"
    },
    "débito amarelo claro": {
      "capitulo": "11"
    },
    "evacuação ausente": {
      "capitulo": "21"
    },
    "pupilas iso/foto": {
      "capitulo": "08"
    },
    "rha+": {
      "capitulo": "16"
    },
    "glasgow 15": {
      "capitulo": "06"
    },
    "fo": {
      "capitulo": "21"
    },
    "sepse de foco urinário": {
      "capitulo": "16"
    },
    "globoso": {
      "capitulo": "21"
    },
    "intoxicação exógena": {
      "capitulo": "22"
    }
  }
}