{
  "prontuario_id": 545,
  "text": "Paciente com mesmo quadro neurológico, com abertura ocular espontânea, não contactuante, em uso de SNE com dieta, permanece aguardando familiares para orientações, pois já encontra-se de alta. NEOPLASIA MALIGNA DA BASE DA LÍNGUA. 18:08: TENTADO AGENDAR ECOCARDIO HOJE NA SANTA CASA COMO DE COSTUME, E FUI INFORMADA PELO SETOR DE RX QUE REALIZA O CONTATO QUE O EXAME NÃO TEM COMO SER REALIZADO DEVIDO A PACIENTE ESTAR EM PRECAUÇÃO DE CONTATO. ÚLCERA GÁSTRICA AGUDA COM HEMORRAGIA. 17:19HRS: RETORNOU DO CC ÀS 14:30HRS. CONSCIENTE, ORIENTADA, ALERTA, VERBALIZANDO. LIBERADO DIETA VO. AVP EM MSD COM SRT EM CURSO. NÃO REFERE ALGIA. CURATIVO NO MIE LIMPO E SECO EXTERNAMENTE COM FIXADOR EXTERNO. MANTÉM REPOUSO NO LEITO. PERMANECE COM SVD. NEOPLASIA MALIGNA DOS OSSOS LONGOS DOS MEMBROS INFERIORES. 11:20 hs: Lúcida, orientada, comunicativa, sinais vitais estáveis, acesso venoso periférico em membro superior esquerdo salinizado, curativo em flanco direito limpo e seco externamente, diurese presente, evacução ausente no período, seguem cuidados de enferm. APENDICITE AGUDA SEM OUTRA ESPECIFICAÇÃO. 13:45: 40º DI, EVOLUI REFERINDO CEFALÉIA DE CARÁTER LEVE. MANTÉM-SE ALERTA, ORIENTADO E COMUNICATIVO. HIPOCORADO, ACEITANDO BEM DIETA VO. AVC EM JUGULAR ESQUERDA, SEM SINAIS FLOGÍSTICOS, COM SOROTERAPIA EM CURSO. RELATA ELIMINAÇÕES VESICAIS E INTESTINAIS. RIM TRANSPLANTADO.",
  "entities": {
    "Paciente ou Grupo com Deficiência": [
      "Paciente",
      "PACIENTE"
    ],
    "Conceito Funcional": [
      "uso"
    ],
    "Dispositivo Médico": [
      "SNE",
      "AVP",
      "CURATIVO",
      "SVD",
      "curativo",
      "AVC",
      "FIXADOR EXTERNO",
      "acesso venoso periférico"
    ],
    "Procedimento Terapêutico ou Preventivo": [
      "SNE",
      "AVP",
      "SRT",
      "CURATIVO",
      "SVD",
      "curativo",
      "AVC",
      "SOROTERAPIA",
      "PRECAUÇÃO DE CONTATO",
      "DIETA VO",
      "FIXADOR EXTERNO",
      "REPOUSO NO LEITO",
      "acesso venoso periférico"
    ],
    "Abreviação": [
      "SNE",
      "CC",
      "AVP",
      "MSD",
      "SRT",
      "MIE",
      "SVD",
      "enferm",
      "DI",
      "AVC",
      "DIETA VO"
    ],
    "Alimento": [
      "dieta"
    ],
    "Grupo Familiar": [
      "familiares"
    ],
    "Atividade de Assistência à Saúde": [
      "orientações",
      "alta",
      "EXAME",
      "LIBERADO",
      "cuidados",
      "enferm"
    ],
    "Procedimento Diagnóstico": [
      "ECOCARDIO"
    ],
    "Organização Relacionada à Saúde": [
      "CC",
      "SANTA CASA",
      "SETOR DE RX"
    ],
    "Achado": [
      "CONSCIENTE",
      "ORIENTADA",
      "ALERTA",
      "VERBALIZANDO",
      "LIMPO",
      "SECO",
      "Lúcida",
      "orientada",
      "comunicativa",
      "limpo",
      "seco",
      "ORIENTADO",
      "COMUNICATIVO",
      "HIPOCORADO",
      "INTESTINAIS",
      "abertura ocular espontânea",
      "REPOUSO NO LEITO",
      "sinais vitais estáveis",
      "diurese presente"
    ],
    "Localização ou Região Corporal": [
      "MSD",
      "MIE",
      "MEMBROS INFERIORES",
      "flanco direito"
    ],
    "Sinal ou Sintoma": [
      "ALGIA",
      "CEFALÉIA",
      "quadro neurológico",
      "não contactuante"
    ],
    "Conceito Espacial": [
      "EXTERNAMENTE",
      "esquerdo",
      "externamente",
      "ESQUERDA"
    ],
    "Conceito Qualitativo": [
      "salinizado",
      "CARÁTER LEVE"
    ],
    "Grupo Profissional ou Ocupacional": [
      "enferm"
    ],
    "Parte do Corpo, Órgão ou Componente Orgânico": [
      "JUGULAR",
      "membro superior"
    ],
    "Negação": [
      "não contactuante",
      "NÃO TEM COMO SER REALIZADO",
      "NÃO REFERE",
      "evacução ausente",
      "SEM OUTRA ESPECIFICAÇÃO",
      "SEM SINAIS FLOGÍSTICOS"
    ],
    "Processo Neoplásico": [
      "NEOPLASIA MALIGNA DA BASE DA LÍNGUA",
      "NEOPLASIA MALIGNA DOS OSSOS LONGOS"
    ],
    "Doença ou Síndrome": [
      "ÚLCERA GÁSTRICA AGUDA COM HEMORRAGIA",
      "APENDICITE AGUDA"
    ]
  },
  "labels": {
    "orientado": {
      "capitulo": "06"
    },
    "intestinais": {
      "capitulo": "13"
    },
    "cefaléia": {
      "capitulo": "21"
    },
    "seco": {
      "capitulo": "14"
    },
    "comunicativo": {
      "capitulo": "06"
    },
    "neoplasia maligna dos ossos longos": {
      "capitulo": "02"
    },
    "limpo": {
      "capitulo": "14"
    },
    "sinais vitais estáveis": {
      "capitulo": "08"
    },
    "verbalizando": {
      "capitulo": "06"
    },
    "úlcera gástrica aguda com hemorragia": {
      "capitulo": "13"
    },
    "quadro neurológico": {
      "capitulo": "08"
    },
    "alerta": {
      "capitulo": "06"
    },
    "abertura ocular espontânea": {
      "capitulo": "09"
    },
    "comunicativa": {
      "capitulo": "06"
    },
    "lúcida": {
      "capitulo": "06"
    },
    "consciente": {
      "capitulo": "06"
    },
    "repouso no leito": {
      "capitulo": "24"
    },
    "neoplasia maligna da base da língua": {
      "capitulo": "02"
    },
    "algia": {
      "capitulo": "21"
    },
    "hipocorado": {
      "capitulo": "14"
    },
    "diurese presente": {
      "capitulo": "13"
    },
    "orientada": {
      "capitulo": "06"
    },
    "não contactuante": {
      "capitulo": "24"
    },
    "apendicite aguda": {
      "capitulo": "13"
    }
  }
}