{
  "prontuario_id": 180,
  "text": "02:00: Veio do PA de maca, acordado, consciente, comunicativo, lúcido e orientado, eupnéico, afebril, com curativo tipo capacete de crepe, relata leve cefaléia, com punção venosa em mse. NEOPLASIA MALIGNA DO ENCÉFALO. 14:10: REALIZADO TROCA DE CURATIVO, PRESENÇA DE POUCO SANGRAMENTO, POIS O MESMO ESTAVA PREJUDICANDO A CIRCULAÇÃO, COM FIXADOR EXTERNO E REFERIU ALGIA MODERADA, SINAIS VITAIS ESTÁVEIS, SEGUE SOB CUIDADOS DE ENFERMAGEM. FRATURA DA EXTREMIDADE DISTAL DO RÁDIO. 23:00 hs: Traqueostomizado, em VM modo PCV, Pi 25, Peep 5, Fr 12, FiO2 35%, saturando 96%. Pupilas anisocóricas E>D, fotorreagentes, reage a estímulos. Ausculta pulmonar com presença de crepitações e roncos difusos, secreção traqueobrônquica purulenta em CONCUSSÃO CEREBRAL. 11:10h: TCE + PNM + ITU + SEPSE. Alerta, não responsivo, eupnéico, febril, hipotenso, gastrostomia funcionante com dieta em BI, acesso venoso central subclávia à D, traqueostomia com névoa úmida contínua, foi aspirado. Realizado troca da fralda; evacuação ausente, CONCUSSÃO CEREBRAL.",
  "entities": {
    "Organização Relacionada à Saúde": [
      "PA"
    ],
    "Abreviação": [
      "PA",
      "mse",
      "Pi",
      "Peep",
      "FiO2",
      "TCE",
      "PNM",
      "ITU",
      "VM modo PCV",
      "Pupilas anisocóricas E&gt;D",
      "dieta em BI",
      "subclávia à D"
    ],
    "Dispositivo Médico": [
      "maca",
      "curativo tipo capacete de crepe",
      "punção venosa",
      "FIXADOR EXTERNO",
      "acesso venoso central"
    ],
    "Achado": [
      "acordado",
      "consciente",
      "comunicativo",
      "lúcido",
      "orientado",
      "eupnéico",
      "afebril",
      "Traqueostomizado",
      "saturando",
      "fotorreagentes",
      "Alerta",
      "POUCO SANGRAMENTO",
      "SINAIS VITAIS ESTÁVEIS",
      "reage a estímulos",
      "gastrostomia funcionante"
    ],
    "Negação": [
      "afebril",
      "não responsivo",
      "evacuação ausente"
    ],
    "Sinal ou Sintoma": [
      "cefaléia",
      "ALGIA",
      "febril",
      "hipotenso",
      "Pupilas anisocóricas E&gt;D",
      "crepitações e roncos difusos",
      "secreção traqueobrônquica purulenta",
      "não responsivo"
    ],
    "Localização ou Região Corporal": [
      "mse"
    ],
    "Função Fisiológica": [
      "CIRCULAÇÃO",
      "evacuação ausente"
    ],
    "Procedimento Terapêutico ou Preventivo": [
      "Traqueostomizado",
      "aspirado",
      "curativo tipo capacete de crepe",
      "punção venosa",
      "TROCA DE CURATIVO",
      "FIXADOR EXTERNO",
      "VM modo PCV",
      "dieta em BI",
      "acesso venoso central",
      "névoa úmida contínua",
      "troca da fralda"
    ],
    "Conceito Quantitativo": [
      "25",
      "5",
      "12",
      "35%",
      "96%"
    ],
    "Atributo Clínico": [
      "saturando"
    ],
    "Lesão ou Envenenamento": [
      "TCE",
      "FRATURA DA EXTREMIDADE DISTAL DO RÁDIO",
      "CONCUSSÃO CEREBRAL"
    ],
    "Doença ou Síndrome": [
      "PNM",
      "ITU",
      "SEPSE"
    ],
    "Processo Neoplásico": [
      "NEOPLASIA MALIGNA DO ENCÉFALO"
    ],
    "Atividade de Assistência à Saúde": [
      "CUIDADOS DE ENFERMAGEM"
    ],
    "Procedimento Diagnóstico": [
      "Ausculta pulmonar"
    ],
    "Parte do Corpo, Órgão ou Componente Orgânico": [
      "subclávia à D"
    ]
  },
  "labels": {
    "pnm": {
      "capitulo": "02"
    },
    "traqueostomizado": {
      "capitulo": "22"
    },
    "neoplasia maligna do encéfalo": {
      "capitulo": "02"
    },
    "cefaléia": {
      "capitulo": "21"
    },
    "não responsivo": {
      "capitulo": "06"
    },
    "crepitações e roncos difusos": {
      "capitulo": "12"
    },
    "pouco sangramento": {
      "capitulo": "22"
    },
    "itu": {
      "capitulo": "02"
    },
    "alerta": {
      "capitulo": "06"
    },
    "concussão cerebral": {
      "capitulo": "08"
    },
    "secreção traqueobrônquica purulenta": {
      "capitulo": "12"
    },
    "pupilas anisocóricas e>d": {
      "capitulo": "08"
    },
    "tce": {
      "capitulo": "02"
    },
    "algia": {
      "capitulo": "21"
    },
    "hipotenso": {
      "capitulo": "11"
    },
    "fratura da extremidade distal do rádio": {
      "capitulo": "15"
    },
    "sepse": {
      "capitulo": "22"
    }
  }
}