{
  "prontuario_id": 841,
  "text": "Às 18:30h: Paciente referiu surdez, apresentou sudorese, está sonolento em todo o período, verificado SSVV, PA 100x50, comunicado plantão da clinica médica. SEGUE CUIDADOS. Às 16:00: Paciente apresentou no periodo episodios de calafrios e pico febril de 39º. checado PA = 140/70, FR = 18. Medicado conforme prescrição medica, realizado compressas frias. Às 09:55hs: Apresentou nova PCR , realizada manobras de reanimação com sucesso. ÀS 15:28: CLIENTE RETORNOU DO CC ÁS 14:45, POI DE ARTROPLASTIA JOELHO D, CONSCIENTE, PUPILAS ISOCORICAS FOTORRREAGENTES, COMUNICATIVA, LIBERADO DIETA HIPOSSODICA, SOROTERAPIA EM MSE, ABDOMEN GLOBOSO E FLÁCIDO, CTVO LIMPO E SECO EM MID, PERFUSÃO DISTAL PRESERVADA, MICÇÃO AUSENTE NO MOMENTO. Em 08/01/12, Às 12:30h: Recebeu alta da UTI-I, para 303-1. Orientada a equipe de enfermagem que o mesmo esta em jejum até 2º ordem, conforme orientação medica. ENFER FLORENCE NIGHTINGALE. ADMISSÃO: 21:00H. PCNT proveniente do PS por crise convulsiva e queda de proprio nivel, apos apresentou mais 3 episodios de convulsões seguida de agitação e confusão mental. Admitido em RAMSAY 6, PUPILAS ISOCÓRICAS E  FOTORREAGENTES, CTVO TIPO CEFALICO, SONDA OROGASTRICA ABERTA SEM DEBITO, VM EM TOT, MODO CMV, VC 530, PEEP 5 E FIO2 50%, AUSCULTA PULMONAR; MV +, RONCOS DIFUSOS EM BASES, ABDOME PLANO E FLÁCIDO A PALPAÇÃO, AVPs BILATERAIS MSE SRT E MSD DORMO + FENTA, RECEBIDO JÁ HIDANTALIZADO NO PS. SVD COM DIURESE + EM ASPECTO CITRICO EM MEDIA QUANTIDADE, SUGIDADES E ODOR CORPORAL. EM IMEDIATO APOS ESTABILIDADE DE SSVV, REALIZADO HIGIENIZAÇÃO CORPORAL E TRICOTOMIOA FACIAL, SEGUE SOB CUIDADOS INTENSIVOS DE ENFERMAGEM.",
  "entities": {
    "Paciente ou Grupo com Deficiência": [
      "Paciente",
      "CLIENTE",
      "PCNT"
    ],
    "Sinal ou Sintoma": [
      "sudorese",
      "sonolento",
      "calafrios",
      "GLOBOSO",
      "convulsões",
      "agitação",
      "referiu surdez",
      "pico febril",
      "crise convulsiva",
      "confusão mental",
      "RAMSAY 6",
      "RONCOS DIFUSOS"
    ],
    "Conceito Temporal": [
      "período",
      "POI",
      "apos",
      "NO MOMENTO"
    ],
    "Abreviação": [
      "SSVV",
      "PCR",
      "CC",
      "POI",
      "MSE",
      "CTVO",
      "MID",
      "ENFER",
      "PCNT",
      "PS",
      "VC",
      "PEEP",
      "FIO2",
      "SRT",
      "MSD",
      "DORMO",
      "FENTA",
      "SVD",
      "alta da UTI-I",
      "CTVO TIPO CEFALICO",
      "MV +"
    ],
    "Atributo Clínico": [
      "SSVV"
    ],
    "Conceito Quantitativo": [
      "100x50",
      "39º",
      "140/70",
      "18",
      "530",
      "5",
      "50%",
      "MEDIA QUANTIDADE"
    ],
    "Atividade de Assistência à Saúde": [
      "plantão",
      "CUIDADOS",
      "Medicado",
      "prescrição medica",
      "alta da UTI-I",
      "orientação medica",
      "TRICOTOMIOA FACIAL",
      "CUIDADOS INTENSIVOS DE ENFERMAGEM"
    ],
    "Procedimento Terapêutico ou Preventivo": [
      "Medicado",
      "SOROTERAPIA",
      "CTVO",
      "CMV",
      "SRT",
      "HIDANTALIZADO",
      "SVD",
      "compressas frias",
      "manobras de reanimação",
      "DIETA HIPOSSODICA",
      "CTVO TIPO CEFALICO",
      "SONDA OROGASTRICA ABERTA",
      "HIGIENIZAÇÃO CORPORAL",
      "TRICOTOMIOA FACIAL"
    ],
    "Função Patológica": [
      "PCR"
    ],
    "Conceito Qualitativo": [
      "sucesso"
    ],
    "Organização Relacionada à Saúde": [
      "CC",
      "PS",
      "clinica médica"
    ],
    "Achado": [
      "CONSCIENTE",
      "COMUNICATIVA",
      "FLÁCIDO",
      "LIMPO",
      "SECO",
      "MICÇÃO",
      "jejum",
      "DIURESE",
      "SUGIDADES",
      "PUPILAS ISOCORICAS FOTORRREAGENTES",
      "PERFUSÃO DISTAL PRESERVADA",
      "PUPILAS ISOCÓRICAS E FOTORREAGENTES",
      "MV +",
      "ASPECTO CITRICO",
      "ODOR CORPORAL"
    ],
    "Localização ou Região Corporal": [
      "MSE",
      "ABDOMEN",
      "MID",
      "BASES",
      "ABDOME",
      "MSD"
    ],
    "Dispositivo Médico": [
      "CTVO",
      "TOT",
      "SVD",
      "CTVO TIPO CEFALICO",
      "SONDA OROGASTRICA ABERTA"
    ],
    "Função Fisiológica": [
      "DEBITO"
    ],
    "Procedimento Diagnóstico": [
      "PALPAÇÃO",
      "AUSCULTA PULMONAR"
    ],
    "Conceito Espacial": [
      "BILATERAIS"
    ],
    "Substância Farmacológica": [
      "DORMO",
      "FENTA"
    ],
    "Substância Química Orgânica": [
      "DORMO",
      "FENTA"
    ],
    "Função de Organismo": [
      "DIURESE"
    ],
    "Grupo Profissional ou Ocupacional": [
      "equipe de enfermagem"
    ],
    "Lesão ou Envenenamento": [
      "queda de proprio nivel"
    ]
  },
  "labels": {
    "perfusão distal preservada": {
      "capitulo": "11"
    },
    "flácido": {
      "capitulo": "15"
    },
    "pico febril": {
      "capitulo": "12"
    },
    "calafrios": {
      "capitulo": "21"
    },
    "confusão mental": {
      "capitulo": "06"
    },
    "pcr": {
      "capitulo": "22"
    },
    "referiu surdez": {
      "capitulo": "10"
    },
    "sugidades": {
      "capitulo": "14"
    },
    "aspecto citrico": {
      "capitulo": "21"
    },
    "seco": {
      "capitulo": "14"
    },
    "sudorese": {
      "capitulo": "21"
    },
    "limpo": {
      "capitulo": "14"
    },
    "agitação": {
      "capitulo": "06"
    },
    "crise convulsiva": {
      "capitulo": "06"
    },
    "queda de proprio nivel": {
      "capitulo": "22"
    },
    "mv +": {
      "capitulo": "11"
    },
    "pupilas isocoricas fotorrreagentes": {
      "capitulo": "08"
    },
    "roncos difusos": {
      "capitulo": "12"
    },
    "pupilas isocóricas e fotorreagentes": {
      "capitulo": "08"
    },
    "sonolento": {
      "capitulo": "21"
    },
    "convulsões": {
      "capitulo": "06"
    },
    "odor corporal": {
      "capitulo": "14"
    },
    "micção": {
      "capitulo": "16"
    },
    "globoso": {
      "capitulo": "15"
    }
  }
}