{
  "prontuario_id": 341,
  "text": "ÀS 16:20: PROVENIENTE DO PS: CORADO, ALERTA, AFEBRIL, ORIENTADO, COMUNICATIVO, EM REPOUSO NO LEITO, HEMATOMA E ESCORIAÇÕES EM FACE, ACEITANDO BEM DIETA VIA ORAL, AVP EM MSE SALINIZADO, SINAIS VITAIS ESTAVÉIS, REFERE ALGIA MODERADA, ELIMINAÇÕES FISIOLOGICAS: DIURESE PRESENTE. CONCUSSAO CEREBRAL. Às 18:20 Hr: Segue sem queixas álgicas, mantendo tala gessada em antebraço esquerdo com curativo de aspecto limpo e seco externamente, acesso venoso periférico em antebraço direito salinizado. Eliminação vesical espontânea. Curativos em coxa bilateral sem pre. FRATURA DA DIAFISE DO FEMUR. ÀS 10:06 HRS: 1° PO COLECISTECTOMIA. CONSCIENTE, ORIENTADA, VERBALIZANDO, ALERTA. CORADA E HIDRATADA. AFEBRIL. LIBERADO DIETA LIQUIDA, ACEITANDO BEM. ESTA COM AVP EM MSE PERMEAVEL. NEGA ALGIA. CURATIVO REALIZADO PELO PERIODO DA MANHA, PERMANECENDO LIMPO E. CALCULOSE DA VESICULA BILIAR SEM COLECISTITE. ÀS 18:17: ORIENTADA, COMUNICATIVA, RESTRITA AO LEITO, MANTEM ACESSO VENOSO PERIFERICO EM MSD, ACEITANDO DIETA. TRAUMATISMO DE NERVOS DE REGIAO NAO ESPECIFICADA DO CORPO. ÀS 18:50h: TRAQUEOSTOMIZADO, REAGE A ESTÍMULOS VERBAIS SIMPLES, DOR E ASPIRAÇÃO, PÚPILAS ISOCÓRICAS E FOTORREAGENTES, PTOSE PALPEBRAL ESQ . PICOS FEBRIS, ESTÁVEL HEMODINAMICAMENTE SEM USO DE DVA. AUSCULTA PULMONAR COM MV PRESENTE E RONCOS DIFUSOS, GRANDE Q . CONCUSSAO CEREBRAL. ",
  "entities": {
    "Abreviação": [
      "PS",
      "AVP",
      "MSE",
      "pre",
      "PO",
      "MSD",
      "GRANDE Q"
    ],
    "Organização Relacionada à Saúde": [
      "PS"
    ],
    "Achado": [
      "CORADO",
      "ALERTA",
      "AFEBRIL",
      "ORIENTADO",
      "COMUNICATIVO",
      "limpo",
      "seco",
      "CONSCIENTE",
      "ORIENTADA",
      "VERBALIZANDO",
      "CORADA",
      "HIDRATADA",
      "AVP",
      "PERMEAVEL",
      "LIMPO",
      "COMUNICATIVA",
      "TRAQUEOSTOMIZADO",
      "REPOUSO NO LEITO",
      "SINAIS VITAIS ESTAVÉIS",
      "DIURESE PRESENTE",
      "Eliminação vesical espontânea",
      "RESTRITA AO LEITO",
      "REAGE A ESTÍMULOS VERBAIS SIMPLES",
      "PÚPILAS ISOCÓRICAS E FOTORREAGENTES",
      "ESTÁVEL HEMODINAMICAMENTE",
      "MV PRESENTE"
    ],
    "Negação": [
      "AFEBRIL",
      "sem",
      "SEM"
    ],
    "Função Patológica": [
      "HEMATOMA"
    ],
    "Sinal ou Sintoma": [
      "HEMATOMA",
      "ALGIA",
      "DOR",
      "ALGIA MODERADA",
      "PTOSE PALPEBRAL ESQ",
      "PICOS FEBRIS",
      "RONCOS DIFUSOS"
    ],
    "Localização ou Região Corporal": [
      "FACE",
      "MSE",
      "MSD"
    ],
    "Procedimento Terapêutico ou Preventivo": [
      "AVP",
      "SALINIZADO",
      "curativo",
      "salinizado",
      "Curativos",
      "COLECISTECTOMIA",
      "CURATIVO",
      "TRAQUEOSTOMIZADO",
      "ASPIRAÇÃO",
      "REPOUSO NO LEITO",
      "DIETA VIA ORAL",
      "tala gessada",
      "acesso venoso periférico",
      "DIETA LIQUIDA",
      "RESTRITA AO LEITO",
      "ACESSO VENOSO PERIFERICO"
    ],
    "Dispositivo Médico": [
      "AVP",
      "curativo",
      "Curativos",
      "CURATIVO",
      "tala gessada",
      "acesso venoso periférico",
      "ACESSO VENOSO PERIFERICO"
    ],
    "Conceito Qualitativo": [
      "SALINIZADO",
      "salinizado",
      "PERMEAVEL",
      "ACEITANDO BEM"
    ],
    "Conceito Espacial": [
      "externamente"
    ],
    "Conceito Temporal": [
      "PO",
      "PERIODO DA MANHA"
    ],
    "Atividade de Assistência à Saúde": [
      "LIBERADO"
    ],
    "Alimento": [
      "DIETA",
      "DIETA LIQUIDA"
    ],
    "Conceito Funcional": [
      "USO"
    ],
    "Função Fisiológica": [
      "ELIMINAÇÕES FISIOLOGICAS",
      "DIURESE PRESENTE",
      "Eliminação vesical espontânea"
    ],
    "Lesão ou Envenenamento": [
      "CONCUSSAO CEREBRAL",
      "FRATURA DA DIAFISE DO FEMUR",
      "TRAUMATISMO DE NERVOS"
    ],
    "Parte do Corpo, Órgão ou Componente Orgânico": [
      "antebraço esquerdo",
      "antebraço direito"
    ],
    "Doença ou Síndrome": [
      "CALCULOSE DA VESICULA BILIAR"
    ],
    "Procedimento Diagnóstico": [
      "AUSCULTA PULMONAR"
    ],
    "Conceito Quantitativo": [
      "GRANDE Q"
    ]
  },
  "labels": {
    "calculose da vesicula biliar": {
      "capitulo": "13"
    },
    "eliminação vesical espontânea": {
      "capitulo": "16"
    },
    "concussao cerebral": {
      "capitulo": "08"
    },
    "reage a estímulos verbais simples": {
      "capitulo": "06"
    },
    "púpilas isocóricas e fotorreagentes": {
      "capitulo": "08"
    },
    "traqueostomizado": {
      "capitulo": "22"
    },
    "fratura da diafise do femur": {
      "capitulo": "15"
    },
    "hematoma": {
      "capitulo": "15"
    },
    "picos febris": {
      "capitulo": "11"
    },
    "avp": {
      "capitulo": "X"
    },
    "traumatismo de nervos": {
      "capitulo": "08"
    },
    "algia moderada": {
      "capitulo": "21"
    },
    "ptose palpebral esq": {
      "capitulo": "09"
    },
    "permeavel": {
      "capitulo": "X"
    },
    "roncos difusos": {
      "capitulo": "12"
    },
    "algia": {
      "capitulo": "21"
    },
    "mv presente": {
      "capitulo": "12"
    },
    "dor": {
      "capitulo": "21"
    }
  }
}