{
  "prontuario_id": 964,
  "text": "Às 04:58: lucido, colaborativo, AVP em MSE salinizado, tala gessada MID, diurese presente, aceita dieta oferecida, ansioso pela falta do cigarro. Segue sob cuidados multiprofissionais. Florence Nighingale XXXX. FRATURA DA EXTREMIDADE DISTAL DA TIBIA. Às 11:19h: Realizo passagem de SNE em narina esquerda, procedimento realizado sem intercorrência. Ausculta positiva em região gástrica; Libero administração da dieta via sonda. OUTROS TRAUMATISMOS INTRACRANIANOS. Às 01:38: Lucido, nao verbalizando, traqueostomizado, eupneico em aa, afebril, apresenta fixador externo em MMSS, edema em MSD, mobilidade diminuida, curativo sanguinolento + fixador externo em MIE, odor fetido, mantendo acesso venoso central à direita, sem sinais flogisticos, aceita dieta via oral oferecida, SVD bom volume, mantendo precauçao de contato, segue cuidados. TRAUMATISMOS MULTIPLOS NAO ESPECIFICADOS. Às 07:30h: Glasgow 15, pupilas isocóricas, RFM +. Tranquila, nega queixas. Em ar ambiente, boa aceitação de dieta VO. CPP sem RA. Abdomen flácido, plano, RHA+. Acesso venoso em MSE com infusão de soroterapia gravitacional. Relata diurese espontânea, evacuação ausente. Extremidades aquecidas e bem perfundidas, sem edemas. Monitorizada contínuamente com parâmetros de PA não invasiva, cardioscopia e oximetria de pulso. Segue sob cuidados intensivos. Enfermeira Florence Nightingale. # Solicitada transferência para UI, aguarda liberação de leito para encaminhamento. NEFRITE TUBULO INTERSTICIAL AGUDA.",
  "entities": {
    "Achado": [
      "lucido",
      "colaborativo",
      "Lucido",
      "traqueostomizado",
      "eupneico",
      "afebril",
      "Tranquila",
      "flácido",
      "plano",
      "RHA+",
      "diurese presente",
      "Ausculta positiva",
      "Glasgow 15",
      "pupilas isocóricas",
      "diurese espontânea",
      "bem perfundidas"
    ],
    "Dispositivo Médico": [
      "AVP",
      "SNE",
      "SVD",
      "tala gessada",
      "fixador externo",
      "acesso venoso central",
      "Acesso venoso",
      "oximetria de pulso"
    ],
    "Procedimento Terapêutico ou Preventivo": [
      "AVP",
      "salinizado",
      "SNE",
      "procedimento",
      "traqueostomizado",
      "SVD",
      "tala gessada",
      "dieta via sonda",
      "fixador externo",
      "acesso venoso central",
      "dieta via oral",
      "precauçao de contato",
      "Acesso venoso",
      "infusão de soroterapia gravitacional"
    ],
    "Abreviação": [
      "AVP",
      "MSE",
      "MID",
      "SNE",
      "aa",
      "MMSS",
      "MSD",
      "MIE",
      "SVD",
      "CPP",
      "RA",
      "RHA+",
      "UI",
      "RFM +",
      "dieta VO",
      "PA não invasiva"
    ],
    "Localização ou Região Corporal": [
      "MSE",
      "MID",
      "MMSS",
      "MSD",
      "MIE",
      "Abdomen",
      "Extremidades",
      "região gástrica"
    ],
    "Conceito Qualitativo": [
      "salinizado",
      "sanguinolento",
      "bem perfundidas"
    ],
    "Alimento": [
      "dieta"
    ],
    "Atividade de Assistência à Saúde": [
      "administração",
      "cuidados",
      "cuidados multiprofissionais",
      "cuidados intensivos"
    ],
    "Negação": [
      "afebril",
      "sem"
    ],
    "Sinal ou Sintoma": [
      "edema",
      "edemas",
      "mobilidade diminuida",
      "odor fetido"
    ],
    "Função Patológica": [
      "edema",
      "edemas"
    ],
    "Conceito Espacial": [
      "direita"
    ],
    "Procedimento Diagnóstico": [
      "cardioscopia",
      "PA não invasiva",
      "oximetria de pulso"
    ],
    "Organização Relacionada à Saúde": [
      "UI"
    ],
    "Função Fisiológica": [
      "diurese presente",
      "diurese espontânea"
    ],
    "Lesão ou Envenenamento": [
      "FRATURA DA EXTREMIDADE DISTAL DA TIBIA",
      "TRAUMATISMOS INTRACRANIANOS",
      "TRAUMATISMOS MULTIPLOS"
    ],
    "Doença ou Síndrome": [
      "NEFRITE TUBULO INTERSTICIAL AGUDA"
    ]
  },
  "labels": {
    "flácido": {
      "capitulo": "13"
    },
    "edemas": {
      "capitulo": "15"
    },
    "nefrite tubulo intersticial aguda": {
      "capitulo": "11"
    },
    "traqueostomizado": {
      "capitulo": "21"
    },
    "ausculta positiva": {
      "capitulo": "21"
    },
    "fratura da extremidade distal da tibia": {
      "capitulo": "15"
    },
    "mobilidade diminuida": {
      "capitulo": "15"
    },
    "rha+": {
      "capitulo": "13"
    },
    "traumatismos multiplos": {
      "capitulo": "22"
    },
    "eupneico": {
      "capitulo": "12"
    },
    "traumatismos intracranianos": {
      "capitulo": "08"
    },
    "plano": {
      "capitulo": "21"
    },
    "odor fetido": {
      "capitulo": "14"
    },
    "edema": {
      "capitulo": "15"
    },
    "pupilas isocóricas": {
      "capitulo": "21"
    }
  }
}