{
  "prontuario_id": 386,
  "text": "Às 14:20 hrs: paciente consciente, comunicativo, eupneico em aa, em repouso no leito, sem queixas algicas. Aguarda marcar cx. seguem cuidados de enfermagem. OUTRA DEGENERACAO ESPECIFICADA DE DISCO INTERVERTEBRAL. ÀS 18:00: 2º DI POR ICTERÍCIA DE EMERGÊNCIA SOB VM EM MODO PCV, COM FIO2 50 %, FR 14, PEEP 5, PRESSÃO LIMITE 22 E MONITORIZAÇÃO CARDÍACA NÃO INVASIVA COM 97 bpM, 97% SAT O2, 97/57 mmHg. PUPILAS ISOMIÓTICAS. SNG ABERTA COM PEQUENA QUANTIDADE DE ESTASE GÁSTRICA. TOT Nº 7.5 EM RIMA 20. CVC EM SUBCLÁVIA DIREITA COM SEDAÇÃO EM CURSO (FENTANIL E DORMONID À 15 ML/H). BCRNF. AP LIVRE DE RUÍDOS ADVENTÍCIOS. ABDOMEN GLOBOSO FLÁCIDO E COM RHA +. SVD COM DÉBITO URINÁRIO PRESENTE DE COLORAÇÃO AMBAR COM GRUMOS. SEGUE SOB CUIDADOS DA EQUIPE MULTIPROFISSIONAL. AGUARDA VAGA DE UTI. FIGADO GORDUROSO ALCOOLICO.",
  "entities": {
    "Paciente ou Grupo com Deficiência": [
      "paciente"
    ],
    "Achado": [
      "consciente",
      "comunicativo",
      "BCRNF",
      "FLÁCIDO",
      "eupneico em aa",
      "repouso no leito",
      "LIVRE DE RUÍDOS ADVENTÍCIOS",
      "RHA +",
      "DÉBITO URINÁRIO PRESENTE"
    ],
    "Procedimento Terapêutico ou Preventivo": [
      "cx",
      "VM",
      "CVC",
      "SVD",
      "repouso no leito",
      "SNG ABERTA",
      "SEDAÇÃO EM CURSO"
    ],
    "Abreviação": [
      "cx",
      "DI",
      "VM",
      "FIO2",
      "FR",
      "PEEP",
      "bpM",
      "CVC",
      "BCRNF",
      "AP",
      "SVD",
      "UTI",
      "eupneico em aa",
      "MODO PCV",
      "SAT O2",
      "97/57 mmHg",
      "SNG ABERTA",
      "TOT Nº",
      "15 ML/H",
      "RHA +"
    ],
    "Conceito Quantitativo": [
      "14",
      "5",
      "22",
      "97",
      "97%",
      "7",
      "20",
      "50 %",
      "15 ML/H"
    ],
    "Parte do Corpo, Órgão ou Componente Orgânico": [
      "RIMA",
      "SUBCLÁVIA DIREITA"
    ],
    "Dispositivo Médico": [
      "CVC",
      "SVD",
      "SNG ABERTA",
      "TOT Nº"
    ],
    "Substância Farmacológica": [
      "FENTANIL",
      "DORMONID"
    ],
    "Substância Química Orgânica": [
      "FENTANIL",
      "DORMONID"
    ],
    "Procedimento Diagnóstico": [
      "AP",
      "MONITORIZAÇÃO CARDÍACA"
    ],
    "Localização ou Região Corporal": [
      "ABDOMEN"
    ],
    "Sinal ou Sintoma": [
      "GLOBOSO",
      "GRUMOS",
      "queixas algicas",
      "ICTERÍCIA DE EMERGÊNCIA",
      "PUPILAS ISOMIÓTICAS",
      "ESTASE GÁSTRICA"
    ],
    "Organização Relacionada à Saúde": [
      "UTI"
    ],
    "Atividade de Assistência à Saúde": [
      "cuidados de enfermagem",
      "CUIDADOS DA EQUIPE MULTIPROFISSIONAL"
    ],
    "Doença ou Síndrome": [
      "DEGENERACAO ESPECIFICADA DE DISCO INTERVERTEBRAL",
      "FIGADO GORDUROSO ALCOOLICO"
    ],
    "Conceito Qualitativo": [
      "PEQUENA QUANTIDADE"
    ],
    "Substância Corporal": [
      "ESTASE GÁSTRICA"
    ],
    "Função Fisiológica": [
      "DÉBITO URINÁRIO PRESENTE"
    ]
  },
  "labels": {
    "estase gástrica": {
      "capitulo": "13"
    },
    "figado gorduroso alcoolico": {
      "capitulo": "05"
    },
    "débito urinário presente": {
      "capitulo": "16"
    },
    "queixas algicas": {
      "capitulo": "21"
    },
    "globoso": {
      "capitulo": "13"
    },
    "pupilas isomióticas": {
      "capitulo": "08"
    },
    "livre de ruídos adventícios": {
      "capitulo": "09"
    },
    "icterícia de emergência": {
      "capitulo": "11"
    },
    "degeneracao especificada de disco intervertebral": {
      "capitulo": "15"
    },
    "grumos": {
      "capitulo": "13"
    }
  }
}