{
  "prontuario_id": 638,
  "text": "ÀS 06:00 HORAS: PACIENTE ARRANCOU SNE. REALIZADA NOVA PASSAGEM, SEM INTERCORRÊNCIAS, AUSCULTA GÁSTRICA POSITIVA. AGUARDA SOLICITAÇÃO DE RX PARA VERIFICAR POSICIONAMENTO. ÀS 01:30HS: PACIENTE COM SNE OBSTRUIDA. REALIZADA LAVAGEM EXAUSTIVA, REALIZADA NOVA PASSAGEM EM NARINA DIREITA SEM INTERCORRÊNCIAS, AUSCULTA GÁSTRICA POSITIVA. AGUARDO REALIZAÇÃO DE RX PARA VISUALIZAÇÃO DE POSICIONAMENTO. ÀS 16:00: ALERTA, VERBALIZANDO, DEAMBULANDO. NO MOMENTO, REPOUSO NA POLTRONA, AFEBRIL, EUPNEICO EM AR AMBIENTE, NORMOCORADO, REFERE ALGIA EM REGIÃO DE MANDIBULA A MASTIGAÇÃO, APRESENTA ESCORIAÇÕES EM FACE E OMBRO ESQUERDO, TIPOIA EM MSE, ACESSO VENOSO PERIFERICO EM MSD SALINIZADO, SEM SINAIS FLOGISTICOS, DIURESE ESPONTANEA. ÀS 12:48: REALIZADO PASSAGEM DE SNE JUNTO COM A ENFª FLORENCE NIGHTINGALE, SEM INTERCORRÊNCIA NO PROCEDIMENTO. AUSCULTA ABDOMINAL POSITIVA. RETIRO FIO GUIA. SOLICITO RAIO-X PARA AVALIAÇÕA DA POSIÇÃO. Às 11:30hs: Realizado endoscopia digestiva + broncoscopia, sem intercorrência durante o exame e transporte.  Responsivo a estimulos dolorosos, TOT nº 8 em rima 22, VM modo PCV 23, peep 5, fio2 a 40%, pupilas isocoricas fotorreagentes, SNE aberta com pequena quantidade de debito bilioso, acesso venoso central em jugular interna a direita com plano de fentanil a 10 ml/h + NPT em acesso exclusivo a 42 ml/h contínuo, mantem monitorização de parametros, PAM em radial a direita, diurese via SVD de cor amarelo ouro sem grumos, mantem fixador externo de MID + tala gessada em MIE, evacuação ausente no período.  ",
  "entities": {
    "Paciente ou Grupo com Deficiência": [
      "PACIENTE"
    ],
    "Procedimento Terapêutico ou Preventivo": [
      "SNE",
      "TIPOIA",
      "VM",
      "PCV",
      "NPT",
      "LAVAGEM EXAUSTIVA",
      "REPOUSO NA POLTRONA",
      "ACESSO VENOSO PERIFERICO",
      "PASSAGEM DE SNE",
      "RETIRO FIO GUIA",
      "SNE aberta",
      "acesso venoso central",
      "fixador externo",
      "tala gessada"
    ],
    "Abreviação": [
      "SNE",
      "RX",
      "MSE",
      "MSD",
      "ENFª",
      "TOT",
      "VM",
      "PCV",
      "peep",
      "fio2",
      "NPT",
      "PAM",
      "MID",
      "MIE",
      "SNE OBSTRUIDA",
      "PASSAGEM DE SNE",
      "SNE aberta",
      "diurese via SVD"
    ],
    "Dispositivo Médico": [
      "SNE",
      "TIPOIA",
      "TOT",
      "ACESSO VENOSO PERIFERICO",
      "SNE aberta",
      "acesso venoso central",
      "acesso exclusivo",
      "fixador externo",
      "tala gessada"
    ],
    "Sinal ou Sintoma": [
      "INTERCORRÊNCIAS",
      "ALGIA",
      "intercorrência",
      "grumos",
      "SNE OBSTRUIDA",
      "SINAIS FLOGISTICOS",
      "INTERCORRÊNCIA NO PROCEDIMENTO",
      "Responsivo a estimulos dolorosos",
      "debito bilioso"
    ],
    "Procedimento Diagnóstico": [
      "RX",
      "RAIO-X",
      "broncoscopia",
      "monitorização",
      "PAM",
      "endoscopia digestiva"
    ],
    "Conceito Espacial": [
      "DIREITA",
      "ESQUERDO",
      "direita"
    ],
    "Achado": [
      "ALERTA",
      "VERBALIZANDO",
      "DEAMBULANDO",
      "AFEBRIL",
      "NORMOCORADO",
      "evacuação",
      "AUSCULTA GÁSTRICA POSITIVA",
      "EUPNEICO EM AR AMBIENTE",
      "DIURESE ESPONTANEA",
      "pupilas isocoricas fotorreagentes",
      "SNE aberta",
      "cor amarelo ouro"
    ],
    "Negação": [
      "AFEBRIL",
      "SEM",
      "ausente"
    ],
    "Lesão ou Envenenamento": [
      "ESCORIAÇÕES"
    ],
    "Localização ou Região Corporal": [
      "FACE",
      "MSE",
      "MSD",
      "MID",
      "MIE",
      "REGIÃO DE MANDIBULA"
    ],
    "Atividade de Assistência à Saúde": [
      "SOLICITO",
      "exame"
    ],
    "Conceito Quantitativo": [
      "8",
      "22",
      "23",
      "5",
      "40%",
      "10 ml/h",
      "42 ml/h"
    ],
    "Parte do Corpo, Órgão ou Componente Orgânico": [
      "rima",
      "radial",
      "jugular interna"
    ],
    "Substância Química Orgânica": [
      "fentanil"
    ],
    "Substância Farmacológica": [
      "fentanil"
    ],
    "Conceito Temporal": [
      "contínuo",
      "NO MOMENTO",
      "no período"
    ],
    "Função Fisiológica": [
      "evacuação",
      "DIURESE ESPONTANEA",
      "diurese via SVD"
    ],
    "Conceito Qualitativo": [
      "pequena quantidade"
    ]
  },
  "labels": {
    "sne obstruida": {
      "capitulo": "13"
    },
    "ausculta gástrica positiva": {
      "capitulo": "13"
    },
    "grumos": {
      "capitulo": "21"
    },
    "evacuação": {
      "capitulo": "21"
    },
    "responsivo a estimulos dolorosos": {
      "capitulo": "21"
    },
    "deambulando": {
      "capitulo": "21"
    },
    "verbalizando": {
      "capitulo": "21"
    },
    "alerta": {
      "capitulo": "21"
    },
    "sinais flogisticos": {
      "capitulo": "21"
    },
    "escoriações": {
      "capitulo": "14"
    },
    "debito bilioso": {
      "capitulo": "13"
    },
    "algia": {
      "capitulo": "21"
    },
    "intercorrência no procedimento": {
      "capitulo": "21"
    },
    "sne aberta": {
      "capitulo": "13"
    },
    "intercorrência": {
      "capitulo": "21"
    },
    "intercorrências": {
      "capitulo": "21"
    },
    "pupilas isocoricas fotorreagentes": {
      "capitulo": "21"
    }
  }
}