{
  "prontuario_id": 623,
  "text": "Às 07:38h: 3º DI queda de mesmo nível, com fratura escalonada de costelas. Consciente, orientada, tranquila, comunicativa e mantendo repouso. Refere dor em hemitórax D, ausculta pulmonar com movimentos ventilatórios positivos bilateralmente, abdomên flácido, in. FRATURA DE COSTELA. ÀS 16H: ALERTA E CONTACTUANTE, PUPILAS ISOCÓRICAS E FOTORREAGENTES, FOI EXTUBADA NO PERÍODO DA MANHÃ, MANTENDO NÉVOA ÚMIDA, CONTÍNUA, OXIMETRIA ACIMA DE 95%, ACESSO VENOSO EM JUGULAR INTERNA D COM PLANO BÁSICO DE HIDRATAÇÃO, SNG COM ESTASE EM BAIXO DÉBITO, AUSC. TRANSTORNOS MENTAIS E COMPORTAMENTAIS DEVIDOS AO USO DA COCAINA. INTOXICACAO AGUDA. Às 00:00: POI de fratura de femur E. Consciente, orientada, comunicativa. Acesso venoso em MSD, curativo limpo e seco em MIE, apresenta boa perfusão distal e mobilidade preservada. Relata boa aceitação da dieta oferecida. Eliminações presentes. FRATURA DO FEMUR. 2° DI COM HX DE QUEDA DO ESTADO GERAL. PROVENIENTE DO ASILO DE IDOSOS. COM MIIASE EM CAVIDADE ORAL. ABERTURA OCULAR ESPONTÂNEA, RESPONDENDO A COMANDOS. PERIODOS GEMENTE. PUPILAS ISO E FOTO. ACESSO EM MSE. HIGIENE ORAL PRECÁRIA. RESPIRAÇÃO ESPONTÂNEA EM AR. OUTRAS PNEUMONIAS VIRAIS.",
  "entities": {
    "Abreviação": [
      "DI",
      "D",
      "SNG",
      "AUSC",
      "POI",
      "E",
      "MSD",
      "MIE",
      "HX",
      "MSE",
      "PUPILAS ISO E FOTO"
    ],
    "Achado": [
      "Consciente",
      "orientada",
      "tranquila",
      "comunicativa",
      "repouso",
      "flácido",
      "ALERTA",
      "CONTACTUANTE",
      "limpo",
      "seco",
      "movimentos ventilatórios positivos bilateralmente",
      "PUPILAS ISOCÓRICAS E FOTORREAGENTES",
      "boa perfusão distal",
      "mobilidade preservada",
      "aceitação da dieta",
      "Eliminações presentes",
      "ABERTURA OCULAR ESPONTÂNEA",
      "RESPONDENDO A COMANDOS",
      "PUPILAS ISO E FOTO",
      "RESPIRAÇÃO ESPONTÂNEA EM AR"
    ],
    "Procedimento Terapêutico ou Preventivo": [
      "repouso",
      "EXTUBADA",
      "SNG",
      "MSD",
      "curativo",
      "ACESSO",
      "NÉVOA ÚMIDA",
      "ACESSO VENOSO",
      "PLANO BÁSICO DE HIDRATAÇÃO",
      "Acesso venoso"
    ],
    "Sinal ou Sintoma": [
      "dor",
      "QUEDA DO ESTADO GERAL",
      "PERIODOS GEMENTE"
    ],
    "Conceito Espacial": [
      "D",
      "E"
    ],
    "Localização ou Região Corporal": [
      "abdomên",
      "MSD",
      "MIE",
      "MSE"
    ],
    "Conceito Quantitativo": [
      "95%"
    ],
    "Dispositivo Médico": [
      "SNG",
      "curativo",
      "ACESSO",
      "ACESSO VENOSO",
      "Acesso venoso"
    ],
    "Procedimento Diagnóstico": [
      "AUSC",
      "ausculta pulmonar"
    ],
    "Conceito Temporal": [
      "POI",
      "PERÍODO DA MANHÃ"
    ],
    "Doença ou Síndrome": [
      "MIIASE",
      "PNEUMONIAS VIRAIS"
    ],
    "Lesão ou Envenenamento": [
      "queda de mesmo nível",
      "fratura escalonada de costelas",
      "FRATURA DE COSTELA",
      "INTOXICACAO AGUDA",
      "fratura de femur",
      "FRATURA DO FEMUR"
    ],
    "Parte do Corpo, Órgão ou Componente Orgânico": [
      "JUGULAR INTERNA"
    ],
    "Disfunção Mental ou Comportamental": [
      "TRANSTORNOS MENTAIS E COMPORTAMENTAIS DEVIDOS AO USO DA COCAINA"
    ],
    "Função Fisiológica": [
      "Eliminações presentes"
    ],
    "Organização Relacionada à Saúde": [
      "ASILO DE IDOSOS"
    ]
  },
  "labels": {
    "flácido": {
      "capitulo": "12"
    },
    "miiase": {
      "capitulo": "14"
    },
    "queda do estado geral": {
      "capitulo": "22"
    },
    "pneumonias virais": {
      "capitulo": "01"
    },
    "movimentos ventilatórios positivos bilateralmente": {
      "capitulo": "21"
    },
    "fratura de costela": {
      "capitulo": "15"
    },
    "alerta": {
      "capitulo": "22"
    },
    "fratura escalonada de costelas": {
      "capitulo": "15"
    },
    "abertura ocular espontânea": {
      "capitulo": "21"
    },
    "periodos gemente": {
      "capitulo": "06"
    },
    "transtornos mentais e comportamentais devidos ao uso da cocaina": {
      "capitulo": "06"
    },
    "fratura do femur": {
      "capitulo": "15"
    },
    "respondendo a comandos": {
      "capitulo": "21"
    },
    "fratura de femur": {
      "capitulo": "15"
    },
    "pupilas iso e foto": {
      "capitulo": "08"
    },
    "intoxicacao aguda": {
      "capitulo": "22"
    },
    "contactuante": {
      "capitulo": "22"
    },
    "dor": {
      "capitulo": "21"
    },
    "pupilas isocóricas e fotorreagentes": {
      "capitulo": "08"
    },
    "queda de mesmo nível": {
      "capitulo": "22"
    }
  }
}