{
  "prontuario_id": 115,
  "text": "Em 19/04/2010, 09:00H: Com Glasgow de 9, com abertura ocular a estimulos verbais e pupilas isocoricas e fotorreagentes. Com ferida cirurgica em região cefalica, com incisão limpa e seca. Sob nevoa umida a 8 l, mantem com monitorização cardiaca, oximetria digital, PNI continuos. Apresenta tosse produtiva sem expectoração. Acesso venoso central em subclavia D duplo-lumen recebendo solução salina e glicosada em BI. Sonda nasoenteral recebendo nutrição a 50 ml em BI e sonda nasogastrica aberta com pouco debito bilioso. Com incisão cirurgica em flanco D limpa a seca externamente e sem exsudação na incisão. Ao exame fisico: Ausculta pulmonar com roncos difusos, BCANF, RHA ausentes. Com coto distal a D próximo a articulação do punho. Com curativo especial na região da tibia E sem sujidade, trocado apenas o secundário e ocluido com atadura. Sonda vesical de demora com debito pouco concentrado, efetiva nas 24h. Não evacuou ate o momento. Ac de enf Florence Nightingale. ACIDENTE VASCULAR CEREBRAL NAO ESPECIFICADO COMO HEMORRAGICO OU ISQUEMICO.",
  "entities": {
    "Lesão ou Envenenamento": [
      "incisão",
      "ferida cirurgica"
    ],
    "Achado": [
      "limpa",
      "seca",
      "continuos",
      "RHA",
      "sujidade",
      "evacuou",
      "pupilas isocoricas e fotorreagentes",
      "debito pouco concentrado",
      "efetiva nas 24h"
    ],
    "Abreviação": [
      "PNI",
      "D",
      "BI",
      "BCANF",
      "RHA",
      "E",
      "Ac",
      "enf"
    ],
    "Procedimento Diagnóstico": [
      "PNI",
      "monitorização cardiaca",
      "oximetria digital",
      "exame fisico",
      "Ausculta pulmonar"
    ],
    "Conceito Temporal": [
      "continuos",
      "momento"
    ],
    "Negação": [
      "sem",
      "Não",
      "NAO"
    ],
    "Substância Corporal": [
      "expectoração",
      "exsudação"
    ],
    "Parte do Corpo, Órgão ou Componente Orgânico": [
      "subclavia"
    ],
    "Conceito Espacial": [
      "D",
      "externamente",
      "próximo",
      "E"
    ],
    "Dispositivo Médico": [
      "duplo-lumen",
      "BI",
      "Acesso venoso central",
      "Sonda nasoenteral",
      "sonda nasogastrica aberta",
      "curativo especial",
      "Sonda vesical de demora"
    ],
    "Conceito Qualitativo": [
      "duplo-lumen"
    ],
    "Alimento": [
      "nutrição"
    ],
    "Procedimento Terapêutico ou Preventivo": [
      "nutrição",
      "nevoa umida",
      "Acesso venoso central",
      "solução salina e glicosada",
      "Sonda nasoenteral",
      "sonda nasogastrica aberta",
      "curativo especial",
      "ocluido com atadura",
      "Sonda vesical de demora"
    ],
    "Localização ou Região Corporal": [
      "flanco",
      "região cefalica"
    ],
    "Sinal ou Sintoma": [
      "BCANF",
      "Glasgow de 9",
      "abertura ocular a estimulos verbais",
      "tosse produtiva",
      "pouco debito bilioso",
      "roncos difusos"
    ],
    "Função Fisiológica": [
      "evacuou"
    ],
    "Conceito Quantitativo": [
      "8 l",
      "50 ml"
    ],
    "Substância Farmacológica": [
      "solução salina e glicosada"
    ],
    "Espaço ou Junção Corporal": [
      "articulação do punho"
    ],
    "Doença ou Síndrome": [
      "ACIDENTE VASCULAR CEREBRAL"
    ]
  },
  "labels": {
    "glasgow de 9": {
      "capitulo": "06"
    },
    "tosse produtiva": {
      "capitulo": "12"
    },
    "incisão": {
      "capitulo": "13"
    },
    "roncos difusos": {
      "capitulo": "21"
    },
    "abertura ocular a estimulos verbais": {
      "capitulo": "09"
    },
    "ferida cirurgica": {
      "capitulo": "15"
    },
    "debito pouco concentrado": {
      "capitulo": "16"
    },
    "pouco debito bilioso": {
      "capitulo": "13"
    },
    "continuos": {
      "capitulo": "21"
    },
    "acidente vascular cerebral": {
      "capitulo": "11"
    },
    "pupilas isocoricas e fotorreagentes": {
      "capitulo": "09"
    }
  }
}