{
  "prontuario_id": 926,
  "text": "Às 17:45: Retorna do CC de maca, 1° PO Gastroplastia + POI reinserção dreno penrose, acordada, consciente, orientada, respirando em ar ambiente, mantem acesso venoso MSD permeavel, curativo abdominal limpo e seco externamente com dreno em flanco E, diurese ausente, orientado deambulação, mantem jejum ate 2° ordem, segue cuidados enfermagem. ÀS 05:20H: CLIENTE CONSCIENTE, RESPONSIVO, HIPOCORADO, HIDRATADO, SINAIS VITAIS ESTÁVEIS. ÁS 23H, PA = 130/70, PVC = 10, FC = 106, FR = 16, TEMP = 37,6 ºC, SPO2 97% COM 02 EM NÉVOA CONTÍNUA, MANTÉM CVC EM SUBCLÁVIA D PERMEÁVEL COM SOROTERAPIA E NPT EM VIA EXCLUSIVA À 84 ML/H, CPP = MV DIMINUIDO BIBASAL SEM RA. ABD = GLOBOSO, FLÁCIDO, DOLOROSO A PALPAÇÃO, INCISÃO CIRÚRGICA ABDOMINAL COM PRESENÇA DE SECREÇÃO SANGUINOLENTA, DRENO DE SUCTOR COM DÉBITO MARRON CLARO, COM ODOR FÉTIDO, SVD COM DIURESE EFETIVA AMARELO CLARA, SEGUE EM REPOUSO NO LEITO. S: PROVENIENTE CC ÀS 04h00. # POI DESBRIDAMENTO CIRÚRGICO. SINDROME DE FOURNIER. O: CHEGA SONOLENTA, CONFUSA (ECG 14), PUPILAS ISOMIOTICAS RFM+, RESPIRAÇÃO ESPONTÂNEA SOB CATETER DE O2 TIPO ÓCULOS, AC: BCRNF, AP: CPL, ABD: RHA +, PLANO E FLACIDO, CATETER VENOSO PERIFÉRICO EM PÉ DIREITO COM SF 0,9% EM CURSO. MONITORIZAÇÃO MULTIPARAMETRICO. A: RISCO PARA INFECÇÃO; TROCAS DE GAZES PREJUDICADA; INTEGRIDADE DA PELE PREJUDICADA. P: SEGUE PRESCRIÇÃO DE ENFERMAGEM EM ANEXO.",
  "entities": {
    "Abreviação": [
      "CC",
      "PO",
      "POI",
      "MSD",
      "E",
      "PA",
      "PVC",
      "CVC",
      "D",
      "NPT",
      "CPP",
      "RA",
      "ABD",
      "SVD",
      "S",
      "O",
      "AC",
      "BCRNF",
      "AP",
      "CPL",
      "MV DIMINUIDO BIBASAL",
      "ECG 14",
      "RHA +",
      "SF 0 , 9%"
    ],
    "Organização Relacionada à Saúde": [
      "CC"
    ],
    "Dispositivo Médico": [
      "maca",
      "curativo",
      "dreno",
      "CVC",
      "SVD",
      "acesso venoso",
      "DRENO DE SUCTOR",
      "CATETER VENOSO PERIFÉRICO"
    ],
    "Conceito Temporal": [
      "PO",
      "POI"
    ],
    "Procedimento Terapêutico ou Preventivo": [
      "Gastroplastia",
      "curativo",
      "dreno",
      "deambulação",
      "jejum",
      "PVC",
      "CVC",
      "SOROTERAPIA",
      "NPT",
      "SVD",
      "reinserção dreno penrose",
      "acesso venoso",
      "02 EM NÉVOA CONTÍNUA",
      "DRENO DE SUCTOR",
      "REPOUSO NO LEITO",
      "DESBRIDAMENTO CIRÚRGICO",
      "CATETER VENOSO PERIFÉRICO"
    ],
    "Achado": [
      "acordada",
      "consciente",
      "orientada",
      "permeavel",
      "limpo",
      "seco",
      "CONSCIENTE",
      "RESPONSIVO",
      "HIDRATADO",
      "PERMEÁVEL",
      "FLÁCIDO",
      "RFM+",
      "BCRNF",
      "CPL",
      "PLANO",
      "FLACIDO",
      "respirando em ar ambiente",
      "SINAIS VITAIS ESTÁVEIS",
      "SPO2 97%",
      "DIURESE EFETIVA",
      "AMARELO CLARA",
      "REPOUSO NO LEITO",
      "RESPIRAÇÃO ESPONTÂNEA",
      "RHA +",
      "RISCO PARA INFECÇÃO",
      "TROCAS DE GAZES PREJUDICADA",
      "INTEGRIDADE DA PELE PREJUDICADA"
    ],
    "Localização ou Região Corporal": [
      "MSD",
      "abdominal",
      "flanco",
      "CPP",
      "ABD",
      "ABDOMINAL"
    ],
    "Conceito Qualitativo": [
      "permeavel",
      "PERMEÁVEL"
    ],
    "Conceito Espacial": [
      "externamente",
      "E",
      "D",
      "DIREITO"
    ],
    "Função Fisiológica": [
      "diurese",
      "DIURESE EFETIVA"
    ],
    "Negação": [
      "ausente",
      "SEM"
    ],
    "Atividade de Assistência à Saúde": [
      "orientado",
      "cuidados enfermagem"
    ],
    "Paciente ou Grupo com Deficiência": [
      "CLIENTE"
    ],
    "Sinal ou Sintoma": [
      "HIPOCORADO",
      "RA",
      "GLOBOSO",
      "SONOLENTA",
      "CONFUSA",
      "MV DIMINUIDO BIBASAL",
      "DÉBITO MARRON CLARO",
      "ODOR FÉTIDO",
      "ECG 14"
    ],
    "Atributo Clínico": [
      "PA"
    ],
    "Conceito Quantitativo": [
      "130/70",
      "10",
      "106",
      "16",
      "37 , 6 ºC",
      "84 ML/H"
    ],
    "Parte do Corpo, Órgão ou Componente Orgânico": [
      "SUBCLÁVIA",
      "PÉ"
    ],
    "Procedimento Diagnóstico": [
      "PALPAÇÃO",
      "AC",
      "AP",
      "MONITORIZAÇÃO MULTIPARAMETRICO"
    ],
    "Lesão ou Envenenamento": [
      "INCISÃO CIRÚRGICA"
    ],
    "Substância Corporal": [
      "SECREÇÃO SANGUINOLENTA",
      "DÉBITO MARRON CLARO"
    ],
    "Doença ou Síndrome": [
      "SINDROME DE FOURNIER"
    ],
    "Substância Farmacológica": [
      "SF 0 , 9%"
    ],
    "Produto Intelectual": [
      "PRESCRIÇÃO DE ENFERMAGEM"
    ]
  },
  "labels": {
    "flácido": {
      "capitulo": "15"
    },
    "incisão cirúrgica": {
      "capitulo": "13"
    },
    "ecg 14": {
      "capitulo": "21"
    },
    "débito marron claro": {
      "capitulo": "22"
    },
    "sindrome de fournier": {
      "capitulo": "22"
    },
    "integridade da pele prejudicada": {
      "capitulo": "14"
    },
    "sinais vitais estáveis": {
      "capitulo": "21"
    },
    "cpl": {
      "capitulo": "21"
    },
    "respiração espontânea": {
      "capitulo": "21"
    },
    "plano": {
      "capitulo": "15"
    },
    "flacido": {
      "capitulo": "15"
    },
    "confusa": {
      "capitulo": "21"
    },
    "bcrnf": {
      "capitulo": "21"
    },
    "trocas de gazes prejudicada": {
      "capitulo": "22"
    },
    "risco para infecção": {
      "capitulo": "22"
    },
    "mv diminuido bibasal": {
      "capitulo": "21"
    },
    "sonolenta": {
      "capitulo": "21"
    },
    "globoso": {
      "capitulo": "15"
    },
    "odor fétido": {
      "capitulo": "14"
    },
    "rfm+": {
      "capitulo": "21"
    }
  }
}