{
  "prontuario_id": 375,
  "text": "ÀS 17:40: QUEIXA DE DOR ABDOMINAL. HX DE CAPOTAMENTO DE AUTO EM 07/036, COM ATENDIMENTO NESSE SERVIÇO, COM TRAUMA EM CERVICAL DE TTO CIRURGICO (DR VITAL BRASIL). BCRNF. ABDOMEN GLOBOSO, FLÁCIDO E DOLORIDO A PALPAÇÃO EM HIPOCONDRIO DIR. DIURESE ESPONTÂNEA PRESENTE. REFERE ALGIA EM ABDOMEN INTENSA NO PERÍODO DA NOITE. ESCARRO SANGUINOLENTO EM MODERADA QUANTIDADE NO PERÍODO DA TARDE. COMUNICO DR VITAL BRASIL SOBRE ESCARRO. SEGUE SOB CUIDADOS DA EQUIPE MULTIPROFISSIONAL. AGUARDA VAGA EM UI. DOR ABDOMINAL E PELVICA. Às 14:30h: Glasgow 15, pupilas isocóricas fotorreagentes. SNE com infusão de dieta 75 ml/h. Traqueostomizada, suporte de O2 sob névoa úmida, presença de secreção espessa hemática em média quantidade. CPP com roncos esparsos. Abdomen flácido, RHA + . Acesso venoso em MSD com infusão de soroterapia. SVD com diurese efetiva, evacuação ausente. Lesão em região sacra estágio II. Uso de colchão de ar. Extremidades aquecidas e bem perfundidas, anasarcada. Monitorizada contínuamente com parâmetros de PA não invasiva, cardioscopia e oximetria de pulso. Segue sob cuidados intensivos. Enfª Florence Nightingale. INSUFICIENCIA PULMONAR AGUDA SUBSEQUENTE A CIRURGIA TORACICA. Às 01:13: ERRATA: desconsiderar evoluçao anterior. FRATURA DO MEMBRO INFERIOR NIVEL NAO ESPECIFICADO. Às 18:50hs: Realizado cateterismo vesical de demora. Enfermeira Florence Nightingale XXXX. OUTRAS DOENCAS DO APARELHO DIGESTIVO.",
  "entities": {
    "Abreviação": [
      "HX",
      "BCRNF",
      "DIR",
      "UI",
      "SNE",
      "CPP",
      "MSD",
      "SVD",
      "PA",
      "Enfª",
      "TTO CIRURGICO",
      "RHA +"
    ],
    "Organização Relacionada à Saúde": [
      "SERVIÇO",
      "UI"
    ],
    "Achado": [
      "BCRNF",
      "FLÁCIDO",
      "Traqueostomizada",
      "flácido",
      "evacuação",
      "DIURESE ESPONTÂNEA",
      "Glasgow 15",
      "pupilas isocóricas fotorreagentes",
      "RHA +",
      "diurese efetiva",
      "Extremidades aquecidas",
      "bem perfundidas"
    ],
    "Localização ou Região Corporal": [
      "ABDOMEN",
      "HIPOCONDRIO",
      "ABDOMINAL",
      "PELVICA",
      "CPP",
      "Abdomen",
      "MSD",
      "região sacra"
    ],
    "Sinal ou Sintoma": [
      "GLOBOSO",
      "ALGIA",
      "ESCARRO",
      "DOR",
      "anasarcada",
      "DOR ABDOMINAL",
      "ESCARRO SANGUINOLENTO",
      "roncos esparsos"
    ],
    "Procedimento Diagnóstico": [
      "PALPAÇÃO",
      "PA",
      "cardioscopia",
      "Monitorizada contínuamente",
      "oximetria de pulso"
    ],
    "Conceito Espacial": [
      "DIR"
    ],
    "Substância Corporal": [
      "ESCARRO",
      "ESCARRO SANGUINOLENTO"
    ],
    "Dispositivo Médico": [
      "SNE",
      "SVD",
      "Acesso venoso",
      "colchão de ar"
    ],
    "Procedimento Terapêutico ou Preventivo": [
      "SNE",
      "infusão",
      "Traqueostomizada",
      "SVD",
      "TTO CIRURGICO",
      "névoa úmida",
      "Acesso venoso",
      "infusão de soroterapia",
      "cateterismo vesical de demora"
    ],
    "Alimento": [
      "dieta"
    ],
    "Função Fisiológica": [
      "evacuação",
      "DIURESE ESPONTÂNEA",
      "diurese efetiva"
    ],
    "Negação": [
      "ausente",
      "não"
    ],
    "Lesão ou Envenenamento": [
      "Lesão",
      "CAPOTAMENTO DE AUTO",
      "TRAUMA EM CERVICAL",
      "FRATURA DO MEMBRO INFERIOR NIVEL NAO ESPECIFICADO"
    ],
    "Conceito Funcional": [
      "Uso"
    ],
    "Conceito Temporal": [
      "PERÍODO DA NOITE",
      "PERÍODO DA TARDE"
    ],
    "Conceito Qualitativo": [
      "MODERADA QUANTIDADE",
      "média quantidade",
      "estágio II"
    ],
    "Atividade de Assistência à Saúde": [
      "CUIDADOS DA EQUIPE MULTIPROFISSIONAL",
      "cuidados intensivos"
    ],
    "Conceito Quantitativo": [
      "75 ml/h"
    ],
    "Objeto Manufaturado": [
      "colchão de ar"
    ],
    "Doença ou Síndrome": [
      "INSUFICIENCIA PULMONAR AGUDA SUBSEQUENTE A CIRURGIA TORACICA",
      "DOENCAS DO APARELHO DIGESTIVO"
    ]
  },
  "labels": {
    "flácido": {
      "capitulo": "13"
    },
    "trauma em cervical": {
      "capitulo": "22"
    },
    "lesão": {
      "capitulo": "22"
    },
    "doencas do aparelho digestivo": {
      "capitulo": "13"
    },
    "evacuação": {
      "capitulo": "21"
    },
    "fratura do membro inferior nivel nao especificado": {
      "capitulo": "15"
    },
    "roncos esparsos": {
      "capitulo": "12"
    },
    "escarro sanguinolento": {
      "capitulo": "13"
    },
    "pupilas isocóricas fotorreagentes": {
      "capitulo": "21"
    },
    "escarro": {
      "capitulo": "13"
    },
    "capotamento de auto": {
      "capitulo": "22"
    },
    "algia": {
      "capitulo": "13"
    },
    "dor abdominal": {
      "capitulo": "13"
    },
    "globoso": {
      "capitulo": "13"
    },
    "insuficiencia pulmonar aguda subsequente a cirurgia toracica": {
      "capitulo": "12"
    },
    "dor": {
      "capitulo": "21"
    },
    "anasarcada": {
      "capitulo": "15"
    }
  }
}