{
  "prontuario_id": 315,
  "text": "ÀS 10:00: CONSCIENTE, ORIENTADA, VERBALIZA, DEAMBULA, NO MOMENTO REPOUSO NO LEITO, AFEBRIL, EUPNEICA, NORMOCORADA, SEM QUEIXAS ALGICAS, ACEITANDO DIETA OFERECIDA, FERIDA OPERATORIA SECA E LIMPA, DIURESE ESPONTANEA. ENF FLORENCE NIGHTINGALE XXXX. MELANOMA MALIGNO DA PALPEBRA INCLUINDO AS COMISSURAS PALPEBRAIS. Às 15:20: Acordado, deambulando, SSVV dentro da normalidade, pouco colaborativo, respirando em ar ambiente, aceita bem a dieta, diurese presente, evacuações ausentes. Realizou EDA - nao realizou  ecografia (paciente comeu) - Remarcado ecografia para dia 10/05, as 10:30. Enf Florence Nightingale. HEMORRAGIA GASTROINTESTINAL SEM OUTRA ESPECIFICACAO. 04:40H: CLIENTE CONSCIENTE, EUPNEICO EM AR A, NO MOMENTO ENCONTRA-SE SONOLENTO, SINAIS VITAIS ESTÁVEIS, EM REPOUSO NO LEITO. NEGA ALGIA, MANTÉM DRENO DE TÓRAX BILATERAL, SENDO QUE O DRENO LADO D APRESENTA DÉBITO SANGUINOLENTO EM POUCA QUANTIDADE, LADO ESQ SEM DÉBITO ATÉ O MOMENTO, ACESSO VENOSO PERIFÉRICO EM MSE COM SOROTERAPIA, INCISÃO ABDOMINAL LIMPA E SECA EXTERNAMENTE COM BOA CICATRIZAÇÃO E SEM SINAIS FLOGISTICOS, SVD COM BOM VOLUME DE DIURESE DE ASPECTO CARACTERISTICO, NÃO EVACUOU NO PERÍODO. SEGUE SOB CUIDADOS DE ENFERMAGEM. ENF FLORENCE NIGHTINGALE, COREN XXXX. TRAUMATISMOS MULTIPLOS NAO ESPECIFICADOS.",
  "entities": {
    "Achado": [
      "CONSCIENTE",
      "ORIENTADA",
      "VERBALIZA",
      "DEAMBULA",
      "AFEBRIL",
      "EUPNEICA",
      "NORMOCORADA",
      "SECA",
      "LIMPA",
      "Acordado",
      "deambulando",
      "SONOLENTO",
      "EVACUOU",
      "REPOUSO NO LEITO",
      "DIURESE ESPONTANEA",
      "SSVV dentro da normalidade",
      "respirando em ar ambiente",
      "aceita bem a dieta",
      "diurese presente",
      "SINAIS VITAIS ESTÁVEIS",
      "BOA CICATRIZAÇÃO",
      "BOM VOLUME",
      "DIURESE DE ASPECTO CARACTERISTICO"
    ],
    "Negação": [
      "AFEBRIL",
      "nao",
      "SEM",
      "NÃO"
    ],
    "Abreviação": [
      "ENF",
      "EDA",
      "Enf",
      "MSE",
      "SVD",
      "SSVV dentro da normalidade",
      "LADO D",
      "LADO ESQ"
    ],
    "Procedimento Diagnóstico": [
      "EDA",
      "ecografia"
    ],
    "Paciente ou Grupo com Deficiência": [
      "paciente",
      "CLIENTE"
    ],
    "Conceito Qualitativo": [
      "ESPECIFICACAO",
      "POUCA QUANTIDADE",
      "BOM VOLUME"
    ],
    "Sinal ou Sintoma": [
      "ALGIA",
      "QUEIXAS ALGICAS",
      "DÉBITO SANGUINOLENTO",
      "SINAIS FLOGISTICOS"
    ],
    "Conceito Espacial": [
      "BILATERAL",
      "EXTERNAMENTE",
      "LADO D",
      "LADO ESQ"
    ],
    "Procedimento Terapêutico ou Preventivo": [
      "DRENO",
      "SOROTERAPIA",
      "SVD",
      "REPOUSO NO LEITO",
      "DRENO DE TÓRAX",
      "ACESSO VENOSO PERIFÉRICO"
    ],
    "Dispositivo Médico": [
      "DRENO",
      "SVD",
      "DRENO DE TÓRAX",
      "ACESSO VENOSO PERIFÉRICO"
    ],
    "Localização ou Região Corporal": [
      "MSE"
    ],
    "Função Fisiológica": [
      "EVACUOU",
      "DIURESE ESPONTANEA",
      "diurese presente",
      "DIURESE DE ASPECTO CARACTERISTICO"
    ],
    "Conceito Temporal": [
      "NO MOMENTO",
      "NO PERÍODO"
    ],
    "Lesão ou Envenenamento": [
      "FERIDA OPERATORIA",
      "INCISÃO ABDOMINAL",
      "TRAUMATISMOS MULTIPLOS NAO ESPECIFICADOS"
    ],
    "Processo Neoplásico": [
      "MELANOMA MALIGNO DA PALPEBRA INCLUINDO AS COMISSURAS PALPEBRAIS"
    ],
    "Função Patológica": [
      "HEMORRAGIA GASTROINTESTINAL"
    ],
    "Atividade de Assistência à Saúde": [
      "CUIDADOS DE ENFERMAGEM"
    ]
  },
  "labels": {
    "melanoma maligno da palpebra incluindo as comissuras palpebrais": {
      "capitulo": "02"
    },
    "ferida operatoria": {
      "capitulo": "22"
    },
    "queixas algicas": {
      "capitulo": "21"
    },
    "hemorragia gastrointestinal": {
      "capitulo": "13"
    },
    "débito sanguinolento": {
      "capitulo": "21"
    },
    "sinais flogisticos": {
      "capitulo": "21"
    },
    "incisão abdominal": {
      "capitulo": "22"
    },
    "sonolento": {
      "capitulo": "21"
    },
    "algia": {
      "capitulo": "21"
    },
    "traumatismos multiplos nao especificados": {
      "capitulo": "22"
    }
  }
}