{
  "prontuario_id": 105,
  "text": "Às 22:10h: Avaliado pela medica, segue sob cuidados. Às 22:53h: Responsiva a estimulos dolorosos, face corada, mas de dor, principalmente em mobilizaçao, pupilas isomioticas / fotorreagentes. SNE em narina E com infusao de dieta. Traqueostomizada, sob suporte de nevoa umida 4 L/min, Saturando 98%, PA 153/90 mmhg, FC 104 bpm, ausculta pulmonar com roncos esparsos em apice, aspirada com media quantidade de secreçao. Acesso periferico Jugular E com infusao de sf 0,9%. Extremidades edemaciadas, perfusao periferica diminuida, liberaçao de exsudato. Abdomen flacido palpaçao, rha + . Lesao reg sacra sendo solicitado oleo mineral para plantao para curativo. MMII com cianose periferica + lesoes bolhosas sendo deixado abertos com odor fetido. Diurese por SVD presente em coletor amarelo concentrado. Monitorizada com cardioscopio + oximetria de pulso + Pam nao invasiva. Em precauçao por MRSA. ÀS 8:30: REALIZADO AUSCUTA ABDOMINAL, SNE POSICIONADA, FIXADA NA NARINA DIREITA. NARINA SEM SINAL DE LESÃO.  ",
  "entities": {
    "Atividade de Assistência à Saúde": [
      "Avaliado",
      "cuidados",
      "solicitado",
      "REALIZADO"
    ],
    "Grupo Profissional ou Ocupacional": [
      "medica"
    ],
    "Achado": [
      "corada",
      "fotorreagentes",
      "Traqueostomizada",
      "Saturando",
      "Monitorizada",
      "Responsiva a estimulos dolorosos",
      "rha +",
      "Diurese por SVD presente",
      "amarelo concentrado"
    ],
    "Sinal ou Sintoma": [
      "dor",
      "secreçao",
      "exsudato",
      "roncos esparsos",
      "Extremidades edemaciadas",
      "perfusao periferica diminuida",
      "cianose periferica",
      "odor fetido",
      "SINAL DE LESÃO"
    ],
    "Procedimento Terapêutico ou Preventivo": [
      "mobilizaçao",
      "SNE",
      "infusao",
      "Traqueostomizada",
      "suporte",
      "aspirada",
      "curativo",
      "Monitorizada",
      "precauçao",
      "nevoa umida",
      "Acesso periferico",
      "deixado abertos"
    ],
    "Parte do Corpo, Órgão ou Componente Orgânico": [
      "pupilas",
      "MMII",
      "Jugular E"
    ],
    "Abreviação": [
      "SNE",
      "PA",
      "FC",
      "bpm",
      "MMII",
      "MRSA",
      "narina E",
      "Jugular E",
      "sf 0 , 9%",
      "rha +",
      "reg sacra",
      "Diurese por SVD presente"
    ],
    "Dispositivo Médico": [
      "SNE",
      "curativo",
      "coletor",
      "cardioscopio",
      "Acesso periferico"
    ],
    "Alimento": [
      "dieta"
    ],
    "Atributo Clínico": [
      "Saturando",
      "PA",
      "FC"
    ],
    "Conceito Quantitativo": [
      "98%",
      "104",
      "4 L/min",
      "153/90 mmhg"
    ],
    "Substância Corporal": [
      "secreçao",
      "exsudato"
    ],
    "Localização ou Região Corporal": [
      "Abdomen",
      "reg sacra"
    ],
    "Procedimento Diagnóstico": [
      "palpaçao",
      "Monitorizada",
      "cardioscopio",
      "ausculta pulmonar",
      "oximetria de pulso",
      "AUSCUTA ABDOMINAL"
    ],
    "Lesão ou Envenenamento": [
      "Lesao"
    ],
    "Organização Relacionada à Saúde": [
      "plantao"
    ],
    "Bactéria": [
      "MRSA"
    ],
    "Espaço ou Junção Corporal": [
      "NARINA",
      "narina E",
      "NARINA DIREITA"
    ],
    "Negação": [
      "SEM"
    ],
    "Substância Farmacológica": [
      "nevoa umida",
      "sf 0 , 9%",
      "oleo mineral"
    ],
    "Função Fisiológica": [
      "Diurese por SVD presente"
    ]
  },
  "labels": {
    "mrsa": {
      "capitulo": "23"
    },
    "cianose periferica": {
      "capitulo": "22"
    },
    "monitorizada": {
      "capitulo": "21"
    },
    "amarelo concentrado": {
      "capitulo": "21"
    },
    "traqueostomizada": {
      "capitulo": "12"
    },
    "roncos esparsos": {
      "capitulo": "12"
    },
    "secreçao": {
      "capitulo": "21"
    },
    "corada": {
      "capitulo": "21"
    },
    "responsiva a estimulos dolorosos": {
      "capitulo": "21"
    },
    "fotorreagentes": {
      "capitulo": "21"
    },
    "extremidades edemaciadas": {
      "capitulo": "22"
    },
    "exsudato": {
      "capitulo": "21"
    },
    "odor fetido": {
      "capitulo": "21"
    },
    "lesao": {
      "capitulo": "22"
    },
    "perfusao periferica diminuida": {
      "capitulo": "22"
    },
    "sinal de lesão": {
      "capitulo": "22"
    },
    "dor": {
      "capitulo": "21"
    }
  }
}