{
  "prontuario_id": 526,
  "text": "Às 14:30hrs: paciente consciente, comunicativa, eupneica em aa, em repouso no leito, aceitando bem dieta oferecida via oral, apresenta edema + hematoma em ombro e, com boa perfusão e mobilidade distal, diurese presente, seguem cuidados de enfermagem. FRATURA DA EXTREMIDADE SUPERIOR DO UMERO. Às 02:24: Lucido, comunicativo, orientado, em repouso no leito, apresenta curativo em regiao femur direito com presença de secreçao serossanguinolenta, sem queixas algicas no momento, aceita dieta oferecida, diurese presente, segue cuidados. CELULITE NAO ESPECIFICADA. Encaminhada às 15:30h ao CC. Entregue às 17h os pertences para esposo após conferência na presença do mesmo (continham em 02 sacolas roupas, chinelo, aparelho celular, carregador de celular, cerca de R$ 10, materias de higiene não utilizados na unidade). CISTOS CEREBRAIS.",
  "entities": {
    "Paciente ou Grupo com Deficiência": [
      "paciente"
    ],
    "Achado": [
      "consciente",
      "comunicativa",
      "eupneica",
      "Lucido",
      "comunicativo",
      "orientado",
      "repouso no leito",
      "aceitando bem dieta oferecida via oral",
      "boa perfusão",
      "mobilidade distal",
      "diurese presente",
      "aceita dieta oferecida"
    ],
    "Função Patológica": [
      "edema",
      "hematoma"
    ],
    "Sinal ou Sintoma": [
      "edema",
      "hematoma",
      "secreçao serossanguinolenta",
      "queixas algicas"
    ],
    "Parte do Corpo, Órgão ou Componente Orgânico": [
      "ombro"
    ],
    "Dispositivo Médico": [
      "curativo"
    ],
    "Procedimento Terapêutico ou Preventivo": [
      "curativo",
      "repouso no leito"
    ],
    "Conceito Temporal": [
      "momento",
      "após"
    ],
    "Atividade de Assistência à Saúde": [
      "cuidados",
      "Encaminhada",
      "Entregue",
      "cuidados de enfermagem"
    ],
    "Abreviação": [
      "CC"
    ],
    "Organização Relacionada à Saúde": [
      "CC"
    ],
    "Grupo Familiar": [
      "esposo"
    ],
    "Função Fisiológica": [
      "diurese presente"
    ],
    "Lesão ou Envenenamento": [
      "FRATURA DA EXTREMIDADE SUPERIOR DO UMERO"
    ],
    "Localização ou Região Corporal": [
      "regiao femur direito"
    ],
    "Substância Corporal": [
      "secreçao serossanguinolenta"
    ],
    "Doença ou Síndrome": [
      "CELULITE NAO ESPECIFICADA",
      "CISTOS CEREBRAIS"
    ]
  },
  "labels": {
    "queixas algicas": {
      "capitulo": "21"
    },
    "mobilidade distal": {
      "capitulo": "15"
    },
    "hematoma": {
      "capitulo": "22"
    },
    "secreçao serossanguinolenta": {
      "capitulo": "22"
    },
    "celulite nao especificada": {
      "capitulo": "21"
    },
    "edema": {
      "capitulo": "22"
    },
    "fratura da extremidade superior do umero": {
      "capitulo": "15"
    },
    "cistos cerebrais": {
      "capitulo": "08"
    }
  }
}