{
  "prontuario_id": 383,
  "text": "ÀS 18:20: 2ª DI - QUEDA DE CAMA + Hx CRISE CONVULSIVA - PERMANECE EM VENTILAÇÃO MECANICA, SOB MODALIDADE PVC, FiO2: 70% - Peep: 5 - PL: 26 - FR: 15 - MONITORIZAÇAO CONTINUA, NO MOMENTO, PA: 124/81 mm/hg - FC: 73 bpm - SatO2. APRESENTA PUPILAS ISOCORICAS, PELE E MUCOSA CORADA E HIDRATADA, AUSCULTA PULMONAR COM MV +, SEM RUIDOS, ABDOMEN FLACIDO, RHA +, MANTEM TOT 8,0 A 23 cm, ACESSO VENOSO PERIFERICO EM MSE INFUNDINDO DORMONID + FENTANIL A 20 ml/h, SOG COM ESTASE EM MÉDIA QUANTIDADE DE COLORAÇAO ESCURA, SVD ABERTA FUNCIONANTE COM DÉBITO DISCRETO (OLIGURICO). Dr VITAL BRASIL CIENTE, FAZ USO DE FRALDA SEM PRESENÇA DE EVACUAÇÕES NO MOMENTO; AGUARDA VAGA DE UTI; TRAUMATISMO INTRACRANIANO. OBS: Cliente apresenta-se com anisocoria desde a admissão e não isocórica como dito anteriormente. Realizado punção de PAM pelo Dr Vital Brasil em arteria radial \"E\"; Encaminhada para TAC de crânio para controle as 06:00, exame e transporte realizados sem intercorrências. NEOPLASIA BENIGNA DO ENCEFALO NAO ESPECIFICADO.",
  "entities": {
    "Abreviação": [
      "Hx",
      "FiO2",
      "Peep",
      "PL",
      "FR",
      "PA",
      "FC",
      "bpm",
      "SatO2",
      "MSE",
      "SOG",
      "SVD",
      "UTI",
      "MODALIDADE PVC",
      "MV +",
      "RHA +",
      "punção de PAM",
      "arteria radial \"E\"",
      "TAC de crânio"
    ],
    "Procedimento Terapêutico ou Preventivo": [
      "FiO2",
      "Peep",
      "SOG",
      "SVD",
      "VENTILAÇÃO MECANICA",
      "MODALIDADE PVC",
      "TOT 8 , 0 A 23 cm",
      "ACESSO VENOSO PERIFERICO",
      "punção de PAM"
    ],
    "Conceito Quantitativo": [
      "70%",
      "5",
      "26",
      "15",
      "73",
      "124/81 mm/hg",
      "20 ml/h"
    ],
    "Atributo Clínico": [
      "PA",
      "FC",
      "SatO2"
    ],
    "Parte do Corpo, Órgão ou Componente Orgânico": [
      "PELE",
      "MUCOSA",
      "arteria radial \"E\""
    ],
    "Achado": [
      "CORADA",
      "HIDRATADA",
      "PUPILAS ISOCORICAS",
      "MV +",
      "RHA +",
      "PRESENÇA DE EVACUAÇÕES"
    ],
    "Sinal ou Sintoma": [
      "RUIDOS",
      "ESTASE",
      "OLIGURICO",
      "anisocoria",
      "intercorrências",
      "CRISE CONVULSIVA",
      "COLORAÇAO ESCURA"
    ],
    "Localização ou Região Corporal": [
      "ABDOMEN",
      "MSE"
    ],
    "Substância Química Orgânica": [
      "DORMONID",
      "FENTANIL"
    ],
    "Substância Farmacológica": [
      "DORMONID",
      "FENTANIL"
    ],
    "Dispositivo Médico": [
      "SOG",
      "TOT 8 , 0 A 23 cm",
      "ACESSO VENOSO PERIFERICO"
    ],
    "Conceito Qualitativo": [
      "FUNCIONANTE",
      "MÉDIA QUANTIDADE"
    ],
    "Objeto Manufaturado": [
      "FRALDA"
    ],
    "Negação": [
      "SEM"
    ],
    "Organização Relacionada à Saúde": [
      "UTI"
    ],
    "Paciente ou Grupo com Deficiência": [
      "Cliente"
    ],
    "Atividade de Assistência à Saúde": [
      "Realizado",
      "Encaminhada"
    ],
    "Procedimento Diagnóstico": [
      "exame",
      "MONITORIZAÇAO CONTINUA",
      "AUSCULTA PULMONAR",
      "TAC de crânio"
    ],
    "Lesão ou Envenenamento": [
      "QUEDA DE CAMA",
      "TRAUMATISMO INTRACRANIANO"
    ],
    "Função Fisiológica": [
      "DÉBITO DISCRETO",
      "PRESENÇA DE EVACUAÇÕES"
    ],
    "Processo Neoplásico": [
      "NEOPLASIA BENIGNA DO ENCEFALO"
    ]
  },
  "labels": {
    "coloraçao escura": {
      "capitulo": "22"
    },
    "ruidos": {
      "capitulo": "21"
    },
    "traumatismo intracraniano": {
      "capitulo": "08"
    },
    "queda de cama": {
      "capitulo": "22"
    },
    "intercorrências": {
      "capitulo": "22"
    },
    "anisocoria": {
      "capitulo": "08"
    },
    "neoplasia benigna do encefalo": {
      "capitulo": "02"
    },
    "estase": {
      "capitulo": "21"
    },
    "oligurico": {
      "capitulo": "21"
    },
    "crise convulsiva": {
      "capitulo": "08"
    }
  }
}