{
  "prontuario_id": 961,
  "text": "Em 17/07/2007, 16 HORAS: PUNCIONADO CATETER VENOSO CENTRAL DUPLO-LUMEN EM JID PELA DR VITAL BRASIL. INSTALADO CONTROLE DE PVC. ENFERMEIRA FLORENCE NIGHTINGALE, XXXX. HEMORRAGIA INTRACEREBRAL HEMISFERICA SUBCORTICAL. Às 18:00 HR: CONSCIENTE, ORIENTADO, VERBALIZANDO, EM REPOUSO NO LEITO. SEM QUEIXAS ÁLGICAS NO MOMENTO. REFERE BOA ACEITAÇÃO DA DIETA VO. MANTÉM ACESSO VENOSO PERIFÉRICO EM MSE HEPARINIZADO. ELIMINAÇÃO VESICAL ESPONTÂNEA. MID COM TALA GESSADA E CURATIVO LIMPO. OSTEOMIELITE AGUDA HEMATOGENICA. Às 17:49 hr: Segue consciente, orientado, verbalizando, restrito ao leito, mantém colar cervical, aceitando bem a dieta oferecida. Eliminação vesical espontânea. FRATURA DA PRIMEIRA VERTEBRA CERVICAL. Às 18:40: Permanece sem sedação, responsivo a estímulos dolorosos e aspirativos, com abertura ocular aos movimentos, pupilas anisocóricas E>D e fotorreagentes, afebril, corado, traqueostomizado em ventilação mecânica modo PCV, a 70% FIO2, PI 24, PEEP 5, FR 14. TRAUMATISMOS MULTIPLOS NAO ESPECIFICADOS. Às 16:36 Hr: 1º PO de retirada de material de síntese em tornozelo esquerdo, segue consciente, orientado, verbalizando, em repouso no leito. Algia moderada no local, com acesso venoso periférico em antebraço esquerdo salinizado. Eliminação vesical espontânea. FRATURA DO PERONIO FIBULA.",
  "entities": {
    "Abreviação": [
      "JID",
      "MSE",
      "MID",
      "FIO2",
      "PI",
      "PEEP",
      "FR",
      "PO",
      "INSTALADO CONTROLE DE PVC",
      "BOA ACEITAÇÃO DA DIETA VO",
      "modo PCV"
    ],
    "Parte do Corpo, Órgão ou Componente Orgânico": [
      "JID",
      "pupilas",
      "tornozelo esquerdo"
    ],
    "Grupo Profissional ou Ocupacional": [
      "ENFERMEIRA"
    ],
    "Achado": [
      "CONSCIENTE",
      "ORIENTADO",
      "VERBALIZANDO",
      "consciente",
      "orientado",
      "verbalizando",
      "fotorreagentes",
      "afebril",
      "corado",
      "traqueostomizado",
      "salinizado",
      "REPOUSO NO LEITO",
      "BOA ACEITAÇÃO DA DIETA VO",
      "ELIMINAÇÃO VESICAL ESPONTÂNEA",
      "CURATIVO LIMPO",
      "restrito ao leito",
      "aceitando bem",
      "Eliminação vesical espontânea",
      "responsivo a estímulos dolorosos e aspirativos",
      "repouso no leito"
    ],
    "Localização ou Região Corporal": [
      "MSE",
      "MID"
    ],
    "Procedimento Terapêutico ou Preventivo": [
      "HEPARINIZADO",
      "sedação",
      "FIO2",
      "PI",
      "PEEP",
      "CATETER VENOSO CENTRAL DUPLO-LUMEN EM",
      "INSTALADO CONTROLE DE PVC",
      "ACESSO VENOSO PERIFÉRICO",
      "TALA GESSADA",
      "colar cervical",
      "ventilação mecânica",
      "modo PCV",
      "retirada de material de síntese",
      "acesso venoso periférico"
    ],
    "Negação": [
      "sem",
      "afebril"
    ],
    "Conceito Quantitativo": [
      "70%",
      "24",
      "5",
      "14"
    ],
    "Conceito Temporal": [
      "PO"
    ],
    "Dispositivo Médico": [
      "CATETER VENOSO CENTRAL DUPLO-LUMEN EM",
      "ACESSO VENOSO PERIFÉRICO",
      "TALA GESSADA",
      "colar cervical",
      "acesso venoso periférico"
    ],
    "Doença ou Síndrome": [
      "HEMORRAGIA INTRACEREBRAL HEMISFERICA SUBCORTICAL",
      "OSTEOMIELITE AGUDA HEMATOGENICA"
    ],
    "Sinal ou Sintoma": [
      "QUEIXAS ÁLGICAS",
      "abertura ocular aos movimentos",
      "Algia moderada"
    ],
    "Função Fisiológica": [
      "ELIMINAÇÃO VESICAL ESPONTÂNEA",
      "Eliminação vesical espontânea"
    ],
    "Lesão ou Envenenamento": [
      "FRATURA DA PRIMEIRA VERTEBRA CERVICAL",
      "TRAUMATISMOS MULTIPLOS",
      "FRATURA DO PERONIO FIBULA"
    ]
  },
  "labels": {
    "eliminação vesical espontânea": {
      "capitulo": "16"
    },
    "abertura ocular aos movimentos": {
      "capitulo": "21"
    },
    "restrito ao leito": {
      "capitulo": "22"
    },
    "traqueostomizado": {
      "capitulo": "12"
    },
    "traumatismos multiplos": {
      "capitulo": "22"
    },
    "osteomielite aguda hematogenica": {
      "capitulo": "15"
    },
    "algia moderada": {
      "capitulo": "21"
    },
    "fratura da primeira vertebra cervical": {
      "capitulo": "15"
    },
    "fotorreagentes": {
      "capitulo": "21"
    },
    "hemorragia intracerebral hemisferica subcortical": {
      "capitulo": "08"
    },
    "responsivo a estímulos dolorosos e aspirativos": {
      "capitulo": "21"
    },
    "fratura do peronio fibula": {
      "capitulo": "15"
    },
    "salinizado": {
      "capitulo": "X"
    },
    "curativo limpo": {
      "capitulo": "21"
    },
    "queixas álgicas": {
      "capitulo": "21"
    }
  }
}