{
  "prontuario_id": 271,
  "text": "Às 11:00HR: REALIZADO CATETERISMO VESICAL DE DEMORA, SEM INTERCORRENCIAS. Às 05:49: paciente apresentou 242 mg/dl, medicado conforme prescrição. Às 06h00: REALIZADO TC CRÂNIO, SEM INTECORRÊNCIAS. Às 06:30 H: CLIENTE APRESENTOU PERIODO DE AGITAÇÃO, ARRANCOU SNE, SOLICITADO NOVO MATERIAL PARA REPASSAR. EM 26/05/2012, ÁS 00H40: João, # PO CORREÇÃO HÉRNIA DIAFRAGMÁTICA. # 3º DI UTI. # 3º DIA SVD. # 3º DIA DRENO TÓRAX E. # 3º DIA CATETER PERIDURAL. # 3º DIA PAM RADIAL E. AO EXAME: GSW14, APRESENTOU MOMENTOS DE CONFUSÃO MENTAL, PUPILAS ISOFOTO, CORADO E HIDRATADO, EM AR AMBIENTE. MUCOSA ORAL ÚMIDA, ACUIDADE VISUAL E AUDITIVA PRESERVADA. DIETOTERAPIA LÍQUIDA PASTOSA VO COM POUCA ACEITAÇÃO. TÓRAX SIMÉTRICO, CVC EM SUB ESQ. AC BRNF EM 2T, CPP MV BILATERAL DIMINUÍDOS Á ESQ. DRENO DE TÓRAX Á ESQ, COM DÉBITO SEROHEMÁTICO. CATETER EPIDURAL COM ANALGESIA CONTÍNUA FENTA + NOVABUPI 4 ML/H. ABDOME FLÁCIDO COM RHA NORMOATIVOS. MMSS COM PAM EM RADIAL D. MMII SEM DEMAIS PARTICULARIDADES. GENITÁLIA MASCLINA COM SVD COM DÉBITO LÍMPIDO DE COLORAÇÃO AMARELO CITRINO. SEGUE SOB CUIDADOS INTENSIVOS. ",
  "entities": {
    "Paciente ou Grupo com Deficiência": [
      "paciente",
      "CLIENTE"
    ],
    "Procedimento Terapêutico ou Preventivo": [
      "medicado",
      "SVD",
      "CVC",
      "CATETERISMO VESICAL DE DEMORA",
      "CORREÇÃO HÉRNIA DIAFRAGMÁTICA",
      "CATETER PERIDURAL",
      "DIETOTERAPIA LÍQUIDA PASTOSA VO",
      "DRENO DE TÓRAX",
      "CATETER EPIDURAL",
      "ANALGESIA CONTÍNUA"
    ],
    "Produto Intelectual": [
      "prescrição"
    ],
    "Atividade de Assistência à Saúde": [
      "prescrição",
      "SOLICITADO",
      "CUIDADOS INTENSIVOS"
    ],
    "Dispositivo Médico": [
      "MATERIAL",
      "SVD",
      "CVC",
      "CATETERISMO VESICAL DE DEMORA",
      "CATETER PERIDURAL",
      "DRENO DE TÓRAX",
      "CATETER EPIDURAL"
    ],
    "Abreviação": [
      "PO",
      "UTI",
      "SVD",
      "GSW14",
      "CVC",
      "AC",
      "CPP",
      "ESQ",
      "FENTA",
      "NOVABUPI",
      "MMSS",
      "PAM",
      "MMII",
      "TC CRÂNIO",
      "ARRANCOU SNE",
      "DIETOTERAPIA LÍQUIDA PASTOSA VO",
      "SUB ESQ",
      "BRNF EM 2T",
      "RHA NORMOATIVOS",
      "RADIAL D"
    ],
    "Conceito Temporal": [
      "PO"
    ],
    "Organização Relacionada à Saúde": [
      "UTI"
    ],
    "Conceito Espacial": [
      "E",
      "ESQ"
    ],
    "Procedimento Diagnóstico": [
      "EXAME",
      "AC",
      "PAM",
      "TC CRÂNIO"
    ],
    "Sinal ou Sintoma": [
      "GSW14",
      "PARTICULARIDADES",
      "PERIODO DE AGITAÇÃO",
      "MOMENTOS DE CONFUSÃO MENTAL",
      "DIMINUÍDOS",
      "DÉBITO SEROHEMÁTICO"
    ],
    "Achado": [
      "CORADO",
      "HIDRATADO",
      "PUPILAS ISOFOTO",
      "EM AR AMBIENTE",
      "MUCOSA ORAL ÚMIDA",
      "ACUIDADE VISUAL E AUDITIVA PRESERVADA",
      "TÓRAX SIMÉTRICO",
      "BRNF EM 2T",
      "RHA NORMOATIVOS",
      "COLORAÇÃO AMARELO CITRINO"
    ],
    "Substância Farmacológica": [
      "FENTA",
      "NOVABUPI"
    ],
    "Substância Química Orgânica": [
      "FENTA"
    ],
    "Localização ou Região Corporal": [
      "ABDOME",
      "MMSS",
      "MMII"
    ],
    "Função Fisiológica": [
      "DÉBITO"
    ],
    "Conceito Quantitativo": [
      "242 mg/dl",
      "4 ML/H"
    ],
    "Parte do Corpo, Órgão ou Componente Orgânico": [
      "SUB ESQ",
      "RADIAL D",
      "GENITÁLIA MASCLINA"
    ]
  },
  "labels": {
    "tórax simétrico": {
      "capitulo": "12"
    },
    "diminuídos": {
      "capitulo": "21"
    },
    "periodo de agitação": {
      "capitulo": "06"
    },
    "pupilas isofoto": {
      "capitulo": "08"
    },
    "débito serohemático": {
      "capitulo": "12"
    },
    "momentos de confusão mental": {
      "capitulo": "06"
    },
    "particularidades": {
      "capitulo": "21"
    },
    "coloração amarelo citrino": {
      "capitulo": "14"
    },
    "brnf em 2t": {
      "capitulo": "11"
    },
    "gsw14": {
      "capitulo": "21"
    }
  }
}