{
  "prontuario_id": 268,
  "text": "Às 18:50H: RETORNA DO CC POR FIXAÇÃO EXTERNA DE FEMUR DIREITO SOB MONITOR E RESPIRADOR DE TRANSPORTE. ## INICIO SG 0,5% EM 1 AMP DE MIDAZOLAM E 1 AMP DE FENTANIL. ENF Florence Nightingale, COREN XXXX. DOR ABDOMINAL E PELVICA. Às 15:30: Acordado, afebril, confuso, agitado, com necessidade de contenção. Uso de O2 em nevoa umida, FO em região cervical E com sangramento leve, trocado curativo do local. mantendo jejum, contato do dra Alice que virá para liberar dieta. aguardo.... Enf Florence Nightingale. ANEURISMA DA ARTERIA CAROTIDA. Às 02:45h: encontra-se consciente, pouco confusa, acamada, ssvv dentro dos parametros de normalidade, mantem acesso venoso periférico em MSE permeavel salinizado no momento, apresenta rush cutâneo corporal + prurido, curativo em MID limpo e seco externamente, refere boa aceitação alimentar, eliminações fisiologicas presentes, segue sob cuidados de enfermagem. Enf Florence Nightingale. FRATURA DO FEMUR.",
  "entities": {
    "Abreviação": [
      "CC",
      "SG",
      "ENF",
      "FO",
      "Enf",
      "MSE",
      "MID",
      "1 AMP",
      "região cervical E",
      "ssvv dentro dos parametros de normalidade"
    ],
    "Organização Relacionada à Saúde": [
      "CC"
    ],
    "Dispositivo Médico": [
      "MONITOR",
      "curativo",
      "RESPIRADOR DE TRANSPORTE",
      "acesso venoso periférico"
    ],
    "Substância Farmacológica": [
      "SG",
      "MIDAZOLAM",
      "FENTANIL"
    ],
    "Substância Química Orgânica": [
      "FENTANIL"
    ],
    "Grupo Profissional ou Ocupacional": [
      "ENF",
      "Enf"
    ],
    "Achado": [
      "Acordado",
      "afebril",
      "consciente",
      "acamada",
      "permeavel",
      "salinizado",
      "limpo",
      "seco",
      "ssvv dentro dos parametros de normalidade",
      "boa aceitação alimentar",
      "eliminações fisiologicas presentes"
    ],
    "Negação": [
      "afebril"
    ],
    "Sinal ou Sintoma": [
      "confuso",
      "agitado",
      "prurido",
      "pouco confusa",
      "rush cutâneo corporal"
    ],
    "Procedimento Terapêutico ou Preventivo": [
      "contenção",
      "jejum",
      "salinizado",
      "curativo",
      "FIXAÇÃO EXTERNA",
      "O2 em nevoa umida",
      "trocado curativo",
      "acesso venoso periférico"
    ],
    "Lesão ou Envenenamento": [
      "FO",
      "FRATURA DO FEMUR"
    ],
    "Alimento": [
      "dieta"
    ],
    "Localização ou Região Corporal": [
      "MSE",
      "MID",
      "região cervical E"
    ],
    "Conceito Espacial": [
      "externamente"
    ],
    "Parte do Corpo, Órgão ou Componente Orgânico": [
      "FEMUR DIREITO"
    ],
    "Doença ou Síndrome": [
      "DOR ABDOMINAL E PELVICA",
      "ANEURISMA DA ARTERIA CAROTIDA"
    ],
    "Função Fisiológica": [
      "eliminações fisiologicas presentes"
    ],
    "Atividade de Assistência à Saúde": [
      "cuidados de enfermagem"
    ]
  },
  "labels": {
    "acordado": {
      "capitulo": "06"
    },
    "pouco confusa": {
      "capitulo": "06"
    },
    "seco": {
      "capitulo": "14"
    },
    "limpo": {
      "capitulo": "14"
    },
    "dor abdominal e pelvica": {
      "capitulo": "13"
    },
    "confuso": {
      "capitulo": "06"
    },
    "permeavel": {
      "capitulo": "11"
    },
    "consciente": {
      "capitulo": "06"
    },
    "fratura do femur": {
      "capitulo": "15"
    },
    "rush cutâneo corporal": {
      "capitulo": "21"
    },
    "salinizado": {
      "capitulo": "11"
    },
    "fo": {
      "capitulo": "09"
    },
    "acamada": {
      "capitulo": "06"
    },
    "aneurisma da arteria carotida": {
      "capitulo": "11"
    },
    "agitado": {
      "capitulo": "06"
    },
    "prurido": {
      "capitulo": "14"
    }
  }
}