{
  "prontuario_id": 292,
  "text": "Pcte com cultura de Aspirado Traqueal do dia 15/01/08, com crescimento de Acinetobacter baumannii PAN Resistente. Instaurar Precaução de Contato até alta hospitalar. NEOPLASIA MALIGNA DA BASE DA LINGUA. Às 09:45 horas: Hipotenso, bradicárdico, períodos de dessaturação; pupilas mióticas isocóricas, reage pouco a estímulos táteis e de aspiração; sonda nasogástrica aberta sem débito; monitorização cardíaca, pressão arterial, saturação e respiração; em régua. FRATURA DE OUTRAS PARTES DA PERNA. Às 10:00: Paciente não referindo queixas, consciente, orientado, calmo, comunicativo, restrito ao leito, aceitando bem dieta VO, com acesso venoso periférico MSD, curativo + fixador externo de pelve com presença de moderada quantidade de exsudato sanguinolen. TRAUMATISMOS MULTIPLOS NAO ESPECIFICADOS.",
  "entities": {
    "Abreviação": [
      "Pcte",
      "MSD",
      "aceitando bem dieta VO"
    ],
    "Paciente ou Grupo com Deficiência": [
      "Pcte",
      "Paciente"
    ],
    "Sinal ou Sintoma": [
      "Hipotenso",
      "bradicárdico",
      "mióticas",
      "queixas",
      "períodos de dessaturação"
    ],
    "Parte do Corpo, Órgão ou Componente Orgânico": [
      "pupilas"
    ],
    "Achado": [
      "isocóricas",
      "consciente",
      "orientado",
      "calmo",
      "comunicativo",
      "sonda nasogástrica aberta",
      "restrito ao leito",
      "aceitando bem dieta VO",
      "exsudato sanguinolen"
    ],
    "Procedimento Terapêutico ou Preventivo": [
      "aspiração",
      "curativo",
      "Precaução de Contato",
      "sonda nasogástrica aberta",
      "restrito ao leito",
      "acesso venoso periférico",
      "fixador externo"
    ],
    "Substância Corporal": [
      "débito"
    ],
    "Procedimento Diagnóstico": [
      "saturação",
      "respiração",
      "monitorização cardíaca",
      "pressão arterial"
    ],
    "Função de Organismo": [
      "respiração"
    ],
    "Dispositivo Médico": [
      "régua",
      "curativo",
      "sonda nasogástrica aberta",
      "acesso venoso periférico",
      "fixador externo"
    ],
    "Localização ou Região Corporal": [
      "MSD",
      "pelve"
    ],
    "Procedimento Laboratorial": [
      "cultura de Aspirado Traqueal"
    ],
    "Bactéria": [
      "crescimento de Acinetobacter baumannii PAN Resistente"
    ],
    "Resultado Laboratorial ou de Teste": [
      "crescimento de Acinetobacter baumannii PAN Resistente"
    ],
    "Atividade de Assistência à Saúde": [
      "alta hospitalar"
    ],
    "Processo Neoplásico": [
      "NEOPLASIA MALIGNA DA BASE DA LINGUA"
    ],
    "Conceito Qualitativo": [
      "reage pouco",
      "moderada quantidade"
    ],
    "Lesão ou Envenenamento": [
      "FRATURA DE OUTRAS PARTES DA PERNA",
      "TRAUMATISMOS MULTIPLOS"
    ]
  },
  "labels": {
    "bradicárdico": {
      "capitulo": "11"
    },
    "isocóricas": {
      "capitulo": "09"
    },
    "exsudato sanguinolen": {
      "capitulo": "14"
    },
    "neoplasia maligna da base da lingua": {
      "capitulo": "02"
    },
    "sonda nasogástrica aberta": {
      "capitulo": "22"
    },
    "fratura de outras partes da perna": {
      "capitulo": "15"
    },
    "restrito ao leito": {
      "capitulo": "21"
    },
    "crescimento de acinetobacter baumannii pan resistente": {
      "capitulo": "01"
    },
    "períodos de dessaturação": {
      "capitulo": "11"
    },
    "mióticas": {
      "capitulo": "09"
    },
    "traumatismos multiplos": {
      "capitulo": "22"
    },
    "queixas": {
      "capitulo": "21"
    },
    "hipotenso": {
      "capitulo": "11"
    }
  }
}