{
  "prontuario_id": 425,
  "text": "Às 16H: CONSCIENTE, LÚCIDA, ORIENTADA, COMUNICATIVA, DEAMBULA COM AUXÍLIO, AFEBRIL, EUPNÉICA, NORMOCORADA, AVP EM MSD, ACEITA DIETA VO, FOI RETIRADO SVD, NÃO APRESENTOU MICÇÃO ESPONTANEA NO PERÍODO DA TARDE, EVACUAÇÃO AUSENTE, DRENO DE PENROSE NO ABDOMEN COM CALCULOSE DA VESICULA BILIAR COM OUTRAS FORMAS DE COLECISTITE. Às 02:00: Chamado plantão novamente pela dor que o cliente referia, houve pedido que lavassemos a sonda, a mesma não possuia sistema de irrigação, conversado com Dr Vital Brasil, que pediu avaliação da Urologia, ele conversou com Dr Vital Brasil e decidiram que o Dr. TRAUMATISMOS MULTIPLOS NAO ESPECIFICADOS. Às 16:20: PCTE ENCONTRA-SE NA HEMODIALISE. ULCERA GASTRICA CRONICA OU NAO ESPECIFICADA COM HEMORRAGIA. PROVENIENTE DO CC ÀS 09:00. LUCIDA, ORIENTADA, REFERINDO LEVE ALGIA ABDOMINAL. APRESENTA SNG FECHADA (SOLICITO FRASCO), CURATIVO ENFAIXADO EM REGIÃO ABDOMINAL DE ASPECTO SECO EXTERNAMENTE, DRENO DE SUCTOR COM DÉBITO SANGUINOLENTO, SVD COM DÉBITO. MANTÉM A HERNIA INGUINAL.",
  "entities": {
    "Achado": [
      "CONSCIENTE",
      "LÚCIDA",
      "ORIENTADA",
      "COMUNICATIVA",
      "AFEBRIL",
      "EUPNÉICA",
      "NORMOCORADA",
      "EVACUAÇÃO",
      "LUCIDA",
      "DÉBITO",
      "DEAMBULA COM AUXÍLIO",
      "ACEITA DIETA VO",
      "MICÇÃO ESPONTANEA",
      "SNG FECHADA",
      "ASPECTO SECO",
      "DÉBITO SANGUINOLENTO"
    ],
    "Negação": [
      "AFEBRIL",
      "AUSENTE"
    ],
    "Procedimento Terapêutico ou Preventivo": [
      "AVP",
      "HEMODIALISE",
      "SVD",
      "RETIRADO SVD",
      "DRENO DE PENROSE",
      "lavassemos a sonda",
      "SNG FECHADA",
      "CURATIVO ENFAIXADO",
      "DRENO DE SUCTOR"
    ],
    "Abreviação": [
      "AVP",
      "MSD",
      "Dr",
      "PCTE",
      "CC",
      "SVD",
      "ACEITA DIETA VO",
      "RETIRADO SVD",
      "SNG FECHADA"
    ],
    "Dispositivo Médico": [
      "AVP",
      "SVD",
      "DRENO DE PENROSE",
      "CURATIVO ENFAIXADO",
      "DRENO DE SUCTOR"
    ],
    "Localização ou Região Corporal": [
      "MSD",
      "ABDOMINAL",
      "NO ABDOMEN",
      "REGIÃO ABDOMINAL"
    ],
    "Função Fisiológica": [
      "EVACUAÇÃO",
      "DÉBITO",
      "MICÇÃO ESPONTANEA"
    ],
    "Organização Relacionada à Saúde": [
      "plantão",
      "Urologia",
      "CC"
    ],
    "Sinal ou Sintoma": [
      "dor",
      "COM HEMORRAGIA"
    ],
    "Paciente ou Grupo com Deficiência": [
      "cliente",
      "PCTE"
    ],
    "Atividade de Assistência à Saúde": [
      "avaliação"
    ],
    "Conceito Espacial": [
      "EXTERNAMENTE"
    ],
    "Doença ou Síndrome": [
      "CALCULOSE DA VESICULA BILIAR",
      "ULCERA GASTRICA CRONICA"
    ],
    "Lesão ou Envenenamento": [
      "TRAUMATISMOS MULTIPLOS"
    ],
    "Substância Corporal": [
      "DÉBITO SANGUINOLENTO"
    ],
    "Anormalidade Anatômica": [
      "HERNIA INGUINAL"
    ]
  },
  "labels": {
    "calculose da vesicula biliar": {
      "capitulo": "13"
    },
    "sng fechada": {
      "capitulo": "X"
    },
    "ulcera gastrica cronica": {
      "capitulo": "13"
    },
    "débito": {
      "capitulo": "21"
    },
    "débito sanguinolento": {
      "capitulo": "22"
    },
    "evacuação": {
      "capitulo": "21"
    },
    "aspecto seco": {
      "capitulo": "X"
    },
    "com hemorragia": {
      "capitulo": "13"
    },
    "hernia inguinal": {
      "capitulo": "15"
    },
    "traumatismos multiplos": {
      "capitulo": "22"
    },
    "dor": {
      "capitulo": "21"
    },
    "micção espontanea": {
      "capitulo": "21"
    }
  }
}