{
  "prontuario_id": 345,
  "text": "Às 9h: Relatou forte algia em flanco esquerdo ao respirar, PA 120/70 mmHg, Dextro 120. comunicado Alice da geral, que virá avaliar. Acesso venoso periférico em mão esquerda, apresenta curativo em região abdominal limpo, seco externamente, diurese presente. Enfª Florence Nightingale. APENDICITE AGUDA COM PERITONITE GENERALIZADA. Às 15:00: REALIZADO TROCA DO CURATIVO EM REGIÃO ABDOMINAL, COM PRESENÇA DE SECREÇAO EM GRANDE QUANTIDADE, COM ODOR FETIDO; DOR ABDOMINAL E PELVICA. Às 16:00: PVC INSTALADA NO MOMENTO, 27 cm/H2O; CIRROSE HEPATICA ALCOOLICA. Às 09:00 horas: Abertura ocular, sem contactuar. DVE com débito; saturação satisfatória; recebendo dieta por sonda nasoenteral e SF 0,9%; traqueostomizado, em névoa a 3 l/m; secreção em média quantidade; roncos raros a ausculta; abdomen flácido; diurese efetiva; precaução de contato por VRE. DISPARO DE OUTRA ARMA DE FOGO E DE ARMA DE FOGO NAO ESPECIFICADA, INTENCAO NAO DETERMINADA, AREAS INDUSTRIAIS E EM CONSTRUCAO.",
  "entities": {
    "Atributo Clínico": [
      "PA"
    ],
    "Abreviação": [
      "PA",
      "geral",
      "Enfª",
      "PVC",
      "DVE",
      "SF 0 , 9%"
    ],
    "Conceito Quantitativo": [
      "120",
      "120/70 mmHg",
      "27 cm/H2O",
      "3 l/m"
    ],
    "Dispositivo Médico": [
      "curativo",
      "Acesso venoso periférico"
    ],
    "Procedimento Terapêutico ou Preventivo": [
      "curativo",
      "DVE",
      "traqueostomizado",
      "névoa",
      "Acesso venoso periférico",
      "TROCA DO CURATIVO",
      "sonda nasoenteral",
      "precaução de contato"
    ],
    "Achado": [
      "limpo",
      "seco",
      "contactuar",
      "traqueostomizado",
      "diurese presente",
      "Abertura ocular",
      "saturação satisfatória",
      "abdomen flácido",
      "diurese efetiva"
    ],
    "Grupo Profissional ou Ocupacional": [
      "Enfª"
    ],
    "Sinal ou Sintoma": [
      "DOR",
      "forte algia",
      "ODOR FETIDO",
      "roncos raros"
    ],
    "Localização ou Região Corporal": [
      "ABDOMINAL",
      "PELVICA",
      "flanco esquerdo",
      "região abdominal",
      "REGIÃO ABDOMINAL"
    ],
    "Negação": [
      "sem"
    ],
    "Substância Corporal": [
      "secreção"
    ],
    "Procedimento Diagnóstico": [
      "ausculta"
    ],
    "Parte do Corpo, Órgão ou Componente Orgânico": [
      "mão esquerda"
    ],
    "Função Fisiológica": [
      "diurese presente",
      "diurese efetiva"
    ],
    "Doença ou Síndrome": [
      "APENDICITE AGUDA COM PERITONITE GENERALIZADA",
      "CIRROSE HEPATICA ALCOOLICA"
    ],
    "Atividade de Assistência à Saúde": [
      "TROCA DO CURATIVO"
    ],
    "Conceito Qualitativo": [
      "GRANDE QUANTIDADE",
      "média quantidade"
    ],
    "Substância Farmacológica": [
      "SF 0 , 9%"
    ]
  },
  "labels": {
    "roncos raros": {
      "capitulo": "12"
    },
    "seco": {
      "capitulo": "14"
    },
    "limpo": {
      "capitulo": "14"
    },
    "abdomen flácido": {
      "capitulo": "13"
    },
    "forte algia": {
      "capitulo": "11"
    },
    "apendicite aguda com peritonite generalizada": {
      "capitulo": "13"
    },
    "traqueostomizado": {
      "capitulo": "12"
    },
    "dor": {
      "capitulo": "21"
    },
    "odor fetido": {
      "capitulo": "13"
    },
    "cirrose hepatica alcoolica": {
      "capitulo": "11"
    }
  }
}