{
  "prontuario_id": 745,
  "text": "Às 14:20h: Pancreatite, Consciente, orientada, comunicativa. Refere eliminações intestinais e urinárias presentes e boa aceitação da dieta. Mantem acesso venoso periférico em membro superior esquerdo, com fluidoterapia em curso. Ac Florence Nightingale. PANCREATITE AGUDA. ENCAMINHADO PARA TAC DE CRÂNIO. RECEBEU ALTA DA UTI. NEOPLASIA MALIGNA DO CEREBRO EXCETO LOBOS E VENTRICULOS. Tentativa de nova punção em subclávia D, sem sucesso, pelo Dr Vital Brasil, feito pedido para cx geral para possível flebotomia. Até avaliação e procedimento, manter em uso acesso central E. HEMORRAGIA SUBARACNOIDE PROVENIENTE DA ARTERIA CEREBRAL MEDIA. Às 16:23: ORIENTADA, COMUNICATIVA, SEM QUEIXAS ALGICAS, ACESSO VENOSO PERIFERICO EM MSE, ACEITANDO DIETA, ELIMINAÇÕES FISIOLOGICAS PRESENTES. CALCULOSE DE VIA BILIAR COM COLANGITE. Às 12:20: 1º PO FX RÁDIO E. EVOLUI SEM QUEIXAS ÁLGICAS. MANTÉM-SE ALERTA, ORIENTADO E COMUNICATIVO. HEMATOMA PERIORBITAL BILATERAL + HIPEREMIA EM CONJUNTIVA E. ACEITANDO BEM DIETA VO. AVP EM MSD, PÉRVIO, SEM SINAIS FLOGÍSTICOS. TALA GESSADA + CURATIVO LIMPO. FRATURA DA EXTREMIDADE DISTAL DO RADIO. Em 30/09/2006, 13 HORAS: VÍTIMA DE COLISÃO AUTO-AUTO, COM TRAUMA TORACOABDOMINAL CONTUSO, COM FRATURA ESCALONADA DE COSTELAS A ESQUERDA, PNEUMOTÓRAX E LESÃO DE BAÇO. FOI SUBMETIDA A DRENAGEM DE TÓRAX E E LAPAROTOMIA COM ESPLENECTOMIA E DRENO DE PENROSE EM. TRAUMATISMOS MULTIPLOS NAO ESPECIFICADOS.",
  "entities": {
    "Doença ou Síndrome": [
      "Pancreatite",
      "PNEUMOTÓRAX",
      "PANCREATITE AGUDA",
      "HEMORRAGIA SUBARACNOIDE",
      "CALCULOSE DE VIA BILIAR COM COLANGITE"
    ],
    "Achado": [
      "Consciente",
      "orientada",
      "comunicativa",
      "sucesso",
      "ORIENTADA",
      "COMUNICATIVA",
      "ALERTA",
      "ORIENTADO",
      "COMUNICATIVO",
      "PÉRVIO",
      "LIMPO",
      "boa aceitação da dieta",
      "QUEIXAS ALGICAS",
      "ACEITANDO DIETA",
      "ELIMINAÇÕES FISIOLOGICAS PRESENTES",
      "ACEITANDO BEM DIETA VO"
    ],
    "Atividade de Assistência à Saúde": [
      "ALTA"
    ],
    "Organização Relacionada à Saúde": [
      "UTI",
      "cx geral"
    ],
    "Abreviação": [
      "UTI",
      "Dr",
      "MSE",
      "PO",
      "AVP",
      "MSD",
      "TAC DE CRÂNIO",
      "cx geral",
      "CONJUNTIVA E",
      "ACEITANDO BEM DIETA VO"
    ],
    "Negação": [
      "EXCETO",
      "sem",
      "SEM"
    ],
    "Parte do Corpo, Órgão ou Componente Orgânico": [
      "LOBOS",
      "VENTRICULOS",
      "ARTERIA CEREBRAL MEDIA",
      "CONJUNTIVA E"
    ],
    "Procedimento Terapêutico ou Preventivo": [
      "flebotomia",
      "procedimento",
      "AVP",
      "CURATIVO",
      "LAPAROTOMIA",
      "ESPLENECTOMIA",
      "acesso venoso periférico",
      "fluidoterapia em curso",
      "ACESSO VENOSO PERIFERICO",
      "TALA GESSADA",
      "DRENAGEM DE TÓRAX",
      "DRENO DE PENROSE"
    ],
    "Conceito Espacial": [
      "E"
    ],
    "Localização ou Região Corporal": [
      "MSE",
      "MSD",
      "membro superior esquerdo"
    ],
    "Conceito Temporal": [
      "PO"
    ],
    "Sinal ou Sintoma": [
      "HIPEREMIA",
      "QUEIXAS ALGICAS",
      "QUEIXAS ÁLGICAS",
      "HEMATOMA PERIORBITAL BILATERAL",
      "SINAIS FLOGÍSTICOS"
    ],
    "Dispositivo Médico": [
      "AVP",
      "CURATIVO",
      "acesso venoso periférico",
      "acesso central",
      "ACESSO VENOSO PERIFERICO",
      "TALA GESSADA",
      "DRENO DE PENROSE"
    ],
    "Paciente ou Grupo com Deficiência": [
      "VÍTIMA"
    ],
    "Procedimento Diagnóstico": [
      "TAC DE CRÂNIO"
    ],
    "Processo Neoplásico": [
      "NEOPLASIA MALIGNA DO CEREBRO"
    ],
    "Função Fisiológica": [
      "ELIMINAÇÕES FISIOLOGICAS PRESENTES"
    ],
    "Lesão ou Envenenamento": [
      "FRATURA DA EXTREMIDADE DISTAL DO RADIO",
      "COLISÃO AUTO-AUTO",
      "TRAUMA TORACOABDOMINAL CONTUSO",
      "LESÃO DE BAÇO",
      "TRAUMATISMOS MULTIPLOS"
    ]
  },
  "labels": {
    "orientado": {
      "capitulo": "06"
    },
    "fratura da extremidade distal do radio": {
      "capitulo": "15"
    },
    "sinais flogísticos": {
      "capitulo": "21"
    },
    "neoplasia maligna do cerebro": {
      "capitulo": "02"
    },
    "pancreatite": {
      "capitulo": "13"
    },
    "hematoma periorbital bilateral": {
      "capitulo": "15"
    },
    "pancreatite aguda": {
      "capitulo": "13"
    },
    "comunicativo": {
      "capitulo": "06"
    },
    "limpo": {
      "capitulo": "21"
    },
    "colisão auto-auto": {
      "capitulo": "22"
    },
    "lesão de baço": {
      "capitulo": "03"
    },
    "traumatismos multiplos": {
      "capitulo": "22"
    },
    "alerta": {
      "capitulo": "06"
    },
    "sucesso": {
      "capitulo": "21"
    },
    "hemorragia subaracnoide": {
      "capitulo": "08"
    },
    "comunicativa": {
      "capitulo": "06"
    },
    "calculose de via biliar com colangite": {
      "capitulo": "13"
    },
    "pneumotórax": {
      "capitulo": "12"
    },
    "pérvio": {
      "capitulo": "21"
    },
    "orientada": {
      "capitulo": "06"
    },
    "hiperemia": {
      "capitulo": "15"
    },
    "trauma toracoabdominal contuso": {
      "capitulo": "22"
    }
  }
}