{
  "prontuario_id": 130,
  "text": "Às 8:00Hrs: Cliente em glasgow 7, pupilas iso / foto +, traqueostomizado, respiração espontânea em aa com auxilio de oxigenoterapia em nevoa umida 4 L/min, eupneico, face corada, mucosa oral hidratada, boa perfusão periferica, no leito com cabeceira elevada á 45°. Mantem com monitorização de multiparametros, ECG, PNI, SpO2, SNE aberta com dietaterapia em curso BI 75 ml/hr, acesso venoso periferico em MIe com srt em curso gravitacional. Apresenta ausculta cardiaca ritmica e normofonetica, ausculta pulmonar MV + com roncos difusos, abdomen distendido e RHA hipoativos, edemas em MMSS e II cacifo II, UP em região sacra-coccigeana estagio II. Faz uso de SVD aberta com debito diuretico presente ++, eliminação fecal presente ++, de aspecto pastoso. Segue cuidados intensivos de enfermagem, em precaução de contato por acinetobacter baumannii.   Enf° Florence Nightingale, Coren XXXX. EDEMA PULMONAR NAO ESPECIFICADO DE OUTRA FORMA. Às 18h: hx de luxação ombro D, acordado, lucido, comunicativo, eupneico, normotenso, normocorado, aceitando dieta oferecido, acesso venoso periferico em MSE sem sinais flogisticos e salinizado, edema + hematoma em ombro D com tipoia de malha, hiperemia em regiao axilar D, refere eliminações presentes e leve algia em ombro D, realizada medidas de conforto, segue sob cuidados.  Enf Florence Nightingale. LUXACAO DA ARTICULACAO DO TORNOZELO.",
  "entities": {
    "Paciente ou Grupo com Deficiência": [
      "Cliente"
    ],
    "Parte do Corpo, Órgão ou Componente Orgânico": [
      "pupilas",
      "ombro D"
    ],
    "Achado": [
      "traqueostomizado",
      "eupneico",
      "ritmica",
      "normofonetica",
      "acordado",
      "lucido",
      "comunicativo",
      "normotenso",
      "normocorado",
      "salinizado",
      "respiração espontânea em aa",
      "face corada",
      "mucosa oral hidratada",
      "boa perfusão periferica",
      "SNE aberta",
      "MV +",
      "cacifo II",
      "SVD aberta",
      "debito diuretico presente",
      "eliminação fecal presente",
      "aspecto pastoso",
      "aceitando dieta",
      "eliminações presentes"
    ],
    "Procedimento Terapêutico ou Preventivo": [
      "traqueostomizado",
      "salinizado",
      "nevoa umida",
      "cabeceira elevada á 45°",
      "SNE aberta",
      "dietaterapia em curso",
      "acesso venoso periferico",
      "srt em curso gravitacional",
      "SVD aberta",
      "precaução de contato",
      "tipoia de malha",
      "medidas de conforto"
    ],
    "Abreviação": [
      "ECG",
      "PNI",
      "SpO2",
      "BI",
      "MIe",
      "MMSS",
      "II",
      "UP",
      "Enf°",
      "hx",
      "MSE",
      "Enf",
      "respiração espontânea em aa",
      "SNE aberta",
      "srt em curso gravitacional",
      "MV +",
      "RHA hipoativos",
      "SVD aberta",
      "ombro D",
      "regiao axilar D"
    ],
    "Procedimento Diagnóstico": [
      "ECG",
      "PNI",
      "monitorização de multiparametros",
      "ausculta cardiaca",
      "ausculta pulmonar"
    ],
    "Dispositivo de Administração de Medicamento": [
      "BI"
    ],
    "Localização ou Região Corporal": [
      "MIe",
      "abdomen",
      "MMSS",
      "II",
      "MSE",
      "região sacra-coccigeana",
      "regiao axilar D"
    ],
    "Função Patológica": [
      "edemas",
      "edema",
      "hematoma"
    ],
    "Sinal ou Sintoma": [
      "edemas",
      "edema",
      "hematoma",
      "hiperemia",
      "glasgow 7",
      "roncos difusos",
      "RHA hipoativos",
      "aspecto pastoso",
      "sinais flogisticos",
      "leve algia"
    ],
    "Doença ou Síndrome": [
      "UP",
      "EDEMA PULMONAR"
    ],
    "Grupo Profissional ou Ocupacional": [
      "Enf°",
      "Enf"
    ],
    "Negação": [
      "sem"
    ],
    "Atividade de Assistência à Saúde": [
      "cuidados",
      "cuidados intensivos de enfermagem"
    ],
    "Conceito Quantitativo": [
      "4 L/min",
      "75 ml/hr"
    ],
    "Dispositivo Médico": [
      "SNE aberta",
      "acesso venoso periferico",
      "SVD aberta",
      "tipoia de malha"
    ],
    "Conceito Qualitativo": [
      "cacifo II",
      "estagio II"
    ],
    "Função Fisiológica": [
      "debito diuretico presente",
      "eliminação fecal presente",
      "eliminações presentes"
    ],
    "Bactéria": [
      "acinetobacter baumannii"
    ],
    "Lesão ou Envenenamento": [
      "luxação ombro",
      "LUXACAO DA ARTICULACAO DO TORNOZELO"
    ]
  },
  "labels": {
    "rha hipoativos": {
      "capitulo": "08"
    },
    "edemas": {
      "capitulo": "15"
    },
    "traqueostomizado": {
      "capitulo": "12"
    },
    "leve algia": {
      "capitulo": "21"
    },
    "eliminação fecal presente": {
      "capitulo": "13"
    },
    "glasgow 7": {
      "capitulo": "21"
    },
    "hematoma": {
      "capitulo": "22"
    },
    "debito diuretico presente": {
      "capitulo": "11"
    },
    "mv +": {
      "capitulo": "12"
    },
    "svd aberta": {
      "capitulo": "13"
    },
    "sinais flogisticos": {
      "capitulo": "22"
    },
    "luxacao da articulacao do tornozelo": {
      "capitulo": "15"
    },
    "roncos difusos": {
      "capitulo": "12"
    },
    "acinetobacter baumannii": {
      "capitulo": "01"
    },
    "up": {
      "capitulo": "21"
    },
    "aspecto pastoso": {
      "capitulo": "13"
    },
    "luxação ombro": {
      "capitulo": "15"
    },
    "edema": {
      "capitulo": "15"
    },
    "respiração espontânea em aa": {
      "capitulo": "12"
    },
    "sne aberta": {
      "capitulo": "13"
    },
    "edema pulmonar": {
      "capitulo": "12"
    },
    "hiperemia": {
      "capitulo": "15"
    },
    "eliminações presentes": {
      "capitulo": "21"
    },
    "cacifo ii": {
      "capitulo": "21"
    }
  }
}