{
  "prontuario_id": 983,
  "text": "Em 09/12/2007, 09:30 HORAS: PERMANECE SEDADA, DISCRETAMENTE DESCORADA, VM VIA TOT COM FiO2 50%, PCV, PI 24 cmH2O, PEEP 6 cmH2O, F 16 mrpm, SPO2 91%. ABDOMEM GLOBOSO, FLÁCIDO. COM DIETA POR SNG Á 40 ML/H. HEMODINAMICAMENTE ESTÁVEL, COM DESMAME DOPAMINA, NO MOMENTO. ANEURISMA DA AORTA ABDOMINAL ROTO. Paciente 6º PO HIM perna D, consciente, orientado, calmo, comunicativo, hipocorado, referindo dor a mobilização em MID, em jejum para realização de procedimento cirúrgico hoje, com sinais vitais estáveis, acesso venoso periférico MSE com soroterapia, cura. FRATURA DA DIAFISE DA TIBIA. Lucida, orientada, comunicativa, sinais vitais estáveis, mantém repouso no leito, boa ingesta alimentar VO, boa ingesta hidrica, refere nucalgia, acesso venoso periférico em MIE salinizado, diurese e evacuação presente no período. Segue cuidados de enferm. PNEUMONIA NAO ESPECIFICADA. Às 16:45HRS: CONSCIENTE, ORIENTADA, ALERTA, VERBALIZANDO. ACEITANDO BEM A DIETA VO. AVP EM MSE SALINIZADO. CURATIVO NA REGIAO LOMBAR COM PEQUENA PRESENÇA EXSUDATO HEMATIVO; FOI TROCADO NOVAMENTE O CURATIVO NO PERIODO DA TARDE. PERMANECE COM DRENO DE SUCTOR C. INSTABILIDADES DA COLUNA VERTEBRAL.",
  "entities": {
    "Achado": [
      "SEDADA",
      "FLÁCIDO",
      "consciente",
      "orientado",
      "calmo",
      "comunicativo",
      "Lucida",
      "orientada",
      "comunicativa",
      "salinizado",
      "CONSCIENTE",
      "ORIENTADA",
      "ALERTA",
      "VERBALIZANDO",
      "SALINIZADO",
      "HEMODINAMICAMENTE ESTÁVEL",
      "sinais vitais estáveis",
      "sinais vitais",
      "repouso no leito",
      "boa ingesta alimentar VO",
      "boa ingesta hidrica",
      "diurese e evacuação presente",
      "ACEITANDO BEM"
    ],
    "Procedimento Terapêutico ou Preventivo": [
      "SEDADA",
      "FiO2",
      "PCV",
      "PI",
      "PEEP",
      "SPO2",
      "DESMAME",
      "jejum",
      "soroterapia",
      "salinizado",
      "AVP",
      "SALINIZADO",
      "CURATIVO",
      "DIETA POR SNG",
      "procedimento cirúrgico",
      "acesso venoso periférico",
      "repouso no leito",
      "DRENO DE SUCTOR"
    ],
    "Dispositivo Médico": [
      "TOT",
      "AVP",
      "CURATIVO",
      "acesso venoso periférico",
      "DRENO DE SUCTOR"
    ],
    "Abreviação": [
      "FiO2",
      "PCV",
      "PI",
      "PEEP",
      "F",
      "SPO2",
      "PO",
      "MID",
      "MSE",
      "MIE",
      "AVP",
      "DIETA POR SNG",
      "perna",
      "boa ingesta alimentar VO",
      "cuidados de enferm",
      "ACEITANDO BEM"
    ],
    "Conceito Quantitativo": [
      "50%",
      "91%",
      "24 cmH2O",
      "6 cmH2O",
      "16 mrpm",
      "40 ML/H"
    ],
    "Localização ou Região Corporal": [
      "ABDOMEM",
      "MID",
      "MSE",
      "MIE",
      "REGIAO LOMBAR"
    ],
    "Sinal ou Sintoma": [
      "GLOBOSO",
      "hipocorado",
      "nucalgia",
      "DISCRETAMENTE DESCORADA",
      "dor a mobilização",
      "EXSUDATO HEMATIVO"
    ],
    "Substância Química Orgânica": [
      "DOPAMINA"
    ],
    "Substância Farmacológica": [
      "DOPAMINA"
    ],
    "Paciente ou Grupo com Deficiência": [
      "Paciente"
    ],
    "Conceito Temporal": [
      "PO"
    ],
    "Parte do Corpo, Órgão ou Componente Orgânico": [
      "perna"
    ],
    "Lesão ou Envenenamento": [
      "FRATURA DA DIAFISE DA TIBIA"
    ],
    "Atributo Clínico": [
      "sinais vitais"
    ],
    "Função Fisiológica": [
      "diurese e evacuação presente"
    ],
    "Atividade de Assistência à Saúde": [
      "cuidados de enferm"
    ],
    "Conceito Qualitativo": [
      "ACEITANDO BEM"
    ],
    "Doença ou Síndrome": [
      "INSTABILIDADES DA COLUNA VERTEBRAL"
    ]
  },
  "labels": {
    "orientado": {
      "capitulo": "06"
    },
    "flácido": {
      "capitulo": "08"
    },
    "instabilidades da coluna vertebral": {
      "capitulo": "11"
    },
    "discretamente descorada": {
      "capitulo": "12"
    },
    "nucalgia": {
      "capitulo": "15"
    },
    "comunicativo": {
      "capitulo": "06"
    },
    "fratura da diafise da tibia": {
      "capitulo": "15"
    },
    "verbalizando": {
      "capitulo": "06"
    },
    "exsudato hemativo": {
      "capitulo": "21"
    },
    "alerta": {
      "capitulo": "06"
    },
    "dor a mobilização": {
      "capitulo": "21"
    },
    "sedada": {
      "capitulo": "08"
    },
    "comunicativa": {
      "capitulo": "06"
    },
    "consciente": {
      "capitulo": "06"
    },
    "hipocorado": {
      "capitulo": "21"
    },
    "globoso": {
      "capitulo": "15"
    },
    "calmo": {
      "capitulo": "06"
    }
  }
}