{
  "prontuario_id": 101,
  "text": "13:00 Apos passagem plantão, enfermeira Florence Nightingale comunica que paciente apresenta prurido em torax e mmss apos a primeira dose esquema RIPE; entro contato com DR Vital Brasil e mesmo vem avaliar paciente e suspende a segunda dose de RIPE, pois paciente apresenta reacão alergica. avalia paciente e orienta mesma, e preenche Gerenciamento de Riscos. Segue em observacão. Às 13hrs: Encaminhado a tomografia de emergencia, sem intercorrencias no transporte e intercorrencias. Às 8:50: SOLICITO RAIO-X PARA AVALIAÇÃO DA POSIÇÃO DA SNE. Em 20/03/2012, 09:00hs: 7º DI por injesta de gasolina em pescoço e MMSS, 6ª PO de Cervicotomia + Fasciotomia de MMSS, 4º D de acesso venoso central em jugular interna E, trocado curativo em 20/03/12, 8º D de SVD. PA: 149/76, P: 84, FR: 30, SpO2 97%, Glasgow 15, pupilas isocóricas fotorreagentes, respiração espontânea em ar ambiente, acesso venoso central em jugular E com plano básico de hidratação, incisão cirúrgica em região cervical com pouca drenagem de secreção serosa, monitorizado, estável hemodinamicamente, MV + sem R/A, MMSS edemaciados com curativo oclusivo limpo e seco, abdome plano, flácido, indolor a palpação, RHA +, SVD com diurese efetiva, evacuação ausente, extremidades bem perfundidas, higienizado e sentado no leito, pele íntegra. ## Mantendo jejum, plano de debridamento cirúrgico de MMSS para a tarde. ##",
  "entities": {
    "Atividade de Assistência à Saúde": [
      "plantão",
      "observacão"
    ],
    "Organização Relacionada à Saúde": [
      "plantão"
    ],
    "Grupo Profissional ou Ocupacional": [
      "enfermeira"
    ],
    "Paciente ou Grupo com Deficiência": [
      "paciente"
    ],
    "Sinal ou Sintoma": [
      "prurido",
      "reacão alergica"
    ],
    "Localização ou Região Corporal": [
      "torax",
      "mmss",
      "MMSS",
      "região cervical"
    ],
    "Abreviação": [
      "mmss",
      "DR",
      "MMSS",
      "PO",
      "SVD",
      "PA",
      "P",
      "FR",
      "SpO2",
      "R/A",
      "suspende a segunda dose de RIPE",
      "POSIÇÃO DA SNE",
      "jugular interna E",
      "jugular E",
      "MV +",
      "RHA +"
    ],
    "Procedimento Diagnóstico": [
      "RAIO-X",
      "monitorizado",
      "tomografia de emergencia"
    ],
    "Parte do Corpo, Órgão ou Componente Orgânico": [
      "pescoço",
      "pupilas",
      "jugular interna E",
      "jugular E"
    ],
    "Conceito Temporal": [
      "PO"
    ],
    "Procedimento Terapêutico ou Preventivo": [
      "Cervicotomia",
      "Fasciotomia",
      "curativo",
      "SVD",
      "higienizado",
      "jejum",
      "suspende a segunda dose de RIPE",
      "acesso venoso central",
      "plano básico de hidratação",
      "curativo oclusivo",
      "debridamento cirúrgico"
    ],
    "Dispositivo Médico": [
      "curativo",
      "SVD",
      "acesso venoso central",
      "curativo oclusivo"
    ],
    "Atributo Clínico": [
      "PA",
      "P",
      "FR",
      "SpO2"
    ],
    "Conceito Quantitativo": [
      "149/76",
      "84",
      "30",
      "97%"
    ],
    "Negação": [
      "sem",
      "ausente"
    ],
    "Achado": [
      "R/A",
      "limpo",
      "seco",
      "flácido",
      "evacuação",
      "higienizado",
      "Glasgow 15",
      "respiração espontânea em ar ambiente",
      "estável hemodinamicamente",
      "MV +",
      "RHA +",
      "diurese efetiva",
      "extremidades bem perfundidas",
      "pele íntegra"
    ],
    "Função Fisiológica": [
      "evacuação",
      "diurese efetiva"
    ],
    "Lesão ou Envenenamento": [
      "injesta de gasolina",
      "incisão cirúrgica"
    ]
  },
  "labels": {
    "pele íntegra": {
      "capitulo": "14"
    },
    "higienizado": {
      "capitulo": "24"
    },
    "flácido": {
      "capitulo": "15"
    },
    "evacuação": {
      "capitulo": "21"
    },
    "glasgow 15": {
      "capitulo": "21"
    },
    "incisão cirúrgica": {
      "capitulo": "13"
    },
    "seco": {
      "capitulo": "14"
    },
    "estável hemodinamicamente": {
      "capitulo": "11"
    },
    "limpo": {
      "capitulo": "24"
    },
    "r/a": {
      "capitulo": "21"
    },
    "injesta de gasolina": {
      "capitulo": "22"
    },
    "extremidades bem perfundidas": {
      "capitulo": "15"
    },
    "respiração espontânea em ar ambiente": {
      "capitulo": "12"
    },
    "prurido": {
      "capitulo": "14"
    },
    "reacão alergica": {
      "capitulo": "04"
    }
  }
}