{
  "prontuario_id": 125,
  "text": "Às 18HS: PACIENTE APRESENTA PA ELEVADA, 200/120, AVISADO DR VITAL BRASIL, DA ORTOPEDIA, QUE PRESCREVEU CAPTOPRIL 50 MG VO, SEGUE SOB OS CUIDADOS DE ENFERMAGEM. ENFER FLORENCE NIGHTINGALE, [COREN XXXX]. FRATURA DA DIAFISE DA TIBIA. ÀS 10:40H: PACIENTE LUCIDA, ORIENTADA, COMUNICATIVA. REFERE ALGIA EM MEMBRO INFERIOR DIREITO AO DEAMBULAR, O MESMO ENCONTRA-SE AVERMELHADO E EDEMASIADO. PERDEU ACESSO VENOSO, DIFICULDADE EM NOVA PUNCÃO. BOA ACEITACÃO DA DIETA. ELIMINACÕES FISIOLOGICAS PRESENTES. ENFa FLORENCE NIGHTINGALE, COREN XXXX. OUTRAS AFECCOES LOCALIZADAS DO TECIDO CONJUNTIVO ESPECIFICADAS. Às 12:30HS: ALERTA, COMUNICATIVO, PUPLAS ISOCORICAS FOTORREAGENTES. TRAQUEOSTOMIZADO, EUPINEICO EM AR AMBIENTE, MANTEM NÉVOA PARA FACILITAR A ASPIRAÇÃO DA TRAQUEOSTOMIA, ASPIRADO MEDIA QUANTIDADE DE SECREÇÃO FLUIDIFICADA. DIURESE ESPONTANEA EM UROPEN. USO DE FRALDA. PACIENTE RETIROU SOG, NÃO REPASSADO, POIS A FONO AVALIOU E LIBEROU DIETA LIQUIDA PASTOSA ASSISTIDA. BOA ACEITAÇÃO DA DIETA SEM SINAIS DE ASPIRAÇÃO. ENFERMEIRA FLORENCE NIGHTINGALE (COREN XXXX). TRAUMATISMO INTRACRANIANO.",
  "entities": {
    "Paciente ou Grupo com Deficiência": [
      "PACIENTE"
    ],
    "Conceito Quantitativo": [
      "200/120",
      "50 MG"
    ],
    "Abreviação": [
      "DR",
      "VO",
      "ENFER",
      "ENFa",
      "FONO",
      "PA ELEVADA",
      "RETIROU SOG"
    ],
    "Organização Relacionada à Saúde": [
      "ORTOPEDIA"
    ],
    "Aminoácido, Peptídeo ou Proteína": [
      "CAPTOPRIL"
    ],
    "Substância Farmacológica": [
      "CAPTOPRIL"
    ],
    "Grupo Profissional ou Ocupacional": [
      "ENFER",
      "ENFa",
      "ENFERMEIRA"
    ],
    "Achado": [
      "LUCIDA",
      "ORIENTADA",
      "COMUNICATIVA",
      "DEAMBULAR",
      "ALERTA",
      "COMUNICATIVO",
      "TRAQUEOSTOMIZADO",
      "DIFICULDADE EM NOVA PUNCÃO",
      "BOA ACEITACÃO DA DIETA",
      "ELIMINACÕES FISIOLOGICAS PRESENTES",
      "EUPINEICO EM AR AMBIENTE",
      "SECREÇÃO FLUIDIFICADA",
      "DIURESE ESPONTANEA",
      "BOA ACEITAÇÃO DA DIETA"
    ],
    "Sinal ou Sintoma": [
      "ALGIA",
      "PA ELEVADA",
      "AVERMELHADO E EDEMASIADO",
      "SINAIS DE ASPIRAÇÃO"
    ],
    "Parte do Corpo, Órgão ou Componente Orgânico": [
      "PUPLAS",
      "MEMBRO INFERIOR DIREITO"
    ],
    "Procedimento Terapêutico ou Preventivo": [
      "TRAQUEOSTOMIZADO",
      "NÉVOA",
      "FRALDA",
      "REPASSADO",
      "ACESSO VENOSO",
      "ASPIRAÇÃO DA TRAQUEOSTOMIA",
      "RETIROU SOG",
      "DIETA LIQUIDA PASTOSA ASSISTIDA"
    ],
    "Dispositivo Médico": [
      "UROPEN",
      "FRALDA",
      "ACESSO VENOSO"
    ],
    "Objeto Manufaturado": [
      "FRALDA"
    ],
    "Negação": [
      "SEM"
    ],
    "Atividade de Assistência à Saúde": [
      "CUIDADOS DE ENFERMAGEM"
    ],
    "Lesão ou Envenenamento": [
      "FRATURA DA DIAFISE DA TIBIA",
      "TRAUMATISMO INTRACRANIANO"
    ],
    "Função Fisiológica": [
      "ELIMINACÕES FISIOLOGICAS PRESENTES",
      "DIURESE ESPONTANEA"
    ],
    "Conceito Qualitativo": [
      "MEDIA QUANTIDADE"
    ]
  },
  "labels": {
    "diurese espontanea": {
      "capitulo": "11"
    },
    "secreção fluidificada": {
      "capitulo": "12"
    },
    "traqueostomizado": {
      "capitulo": "22"
    },
    "deambular": {
      "capitulo": "21"
    },
    "eupineico em ar ambiente": {
      "capitulo": "21"
    },
    "sinais de aspiração": {
      "capitulo": "21"
    },
    "traumatismo intracraniano": {
      "capitulo": "08"
    },
    "comunicativo": {
      "capitulo": "21"
    },
    "avermelhado e edemasiado": {
      "capitulo": "15"
    },
    "fratura da diafise da tibia": {
      "capitulo": "15"
    },
    "alerta": {
      "capitulo": "21"
    },
    "pa elevada": {
      "capitulo": "11"
    },
    "algia": {
      "capitulo": "15"
    },
    "dificuldade em nova puncão": {
      "capitulo": "22"
    }
  }
}