{
  "prontuario_id": 466,
  "text": "Às 16:55h: 6º DI investigação de sangramento em TGI. Consciente, orientado, tranquilo, comunicativo e deambulando. Aguardando conduta médica. Enf Florence Nightingale. ABDOME AGUDO. HSA. Às 14:10: PACIENTE LÚCIDO, ORIENTADO, COMUNICATIVO, PUPILAS ISO E FOTO, DEAMBULANDO, REFERE LEVE CEFALEIA, AVP EM MSD SALINIZADO, ACEITANDO BEM A DIETA,  ANSIOSO QUANTO A ALTA , SEGUE EM OBSERVAÇÃO. TRAUMATISMOS MULTIPLOS NAO ESPECIFICADOS. Às 09:46h: Acordada, alerta, responsiva, corada, hidratada. Mantém SNE para alimentação por bomba infusora. Apresenta abdome plano, flácido, indolor à palpação, RHA +. Diurese limpida em bom volume, não evacuou. FRATURA DO COLO DO FEMUR. Às 15:00: PACIENTE LUCIDO, ORIENTADO, MANTEM REPOUSO NO LEITO, RELATA ALGIA MODERADA EM REGIAO LOMBAR E MMII, SENDO MEDICADO CONFORME PRESCRIÇAO MEDICA. ACEITANDO BEM A DIETA E FF NORMAIS. LUMBAGO COM CIATICA. Às 10:59 HS: CONSCIENTE, ORIENTADO, REFERINDO ALGIA MODERADA, AVP EM MSD SALINIZADO, DRENO DE TÓRAX À DIREITA COM DÉBITO HEMÁTICO, SVD COM ASPECTO NORMAL, CTVO EM REGIÃO LOMBAR LIMPO E SECO. MANTER REPOUSO ATÉ SEGUNDA ORDEM, PODE SENTAR NO LEITO. REALIZADO RX; FRATURA DA COLUNA LOMBAR E DA PELVE. PACIENTE JOVEM PROCURA ATENDIMENTO POR QUEIXA DE DOR INTERNÁDEGAS, COM PRESENÇA DE CISTO PILONIDAL AO EXAME FISÍCO. INTERNA AOS CUIDADOS DA CX GERAL, APÓS REALIZAÇÃO DE EXAMES LABORATORIAIS E ECG. CC AVISADO. EM JEJUM, SENDO A ÚLTIMA REFEIÇÃO ÀS 12:30. CO CISTO PILONIDAL SEM ABSCESSO.",
  "entities": {
    "Sinal ou Sintoma": [
      "sangramento",
      "LEVE CEFALEIA",
      "ALGIA MODERADA",
      "DÉBITO HEMÁTICO",
      "DOR INTERNÁDEGAS"
    ],
    "Parte do Corpo, Órgão ou Componente Orgânico": [
      "TGI",
      "PUPILAS",
      "PELVE",
      "COLUNA LOMBAR"
    ],
    "Achado": [
      "Consciente",
      "orientado",
      "tranquilo",
      "comunicativo",
      "deambulando",
      "LÚCIDO",
      "ORIENTADO",
      "COMUNICATIVO",
      "DEAMBULANDO",
      "SALINIZADO",
      "Acordada",
      "alerta",
      "responsiva",
      "corada",
      "hidratada",
      "flácido",
      "evacuou",
      "LUCIDO",
      "CONSCIENTE",
      "LIMPO",
      "SECO",
      "ACEITANDO BEM",
      "ANSIOSO QUANTO A ALTA",
      "RHA +",
      "Diurese limpida",
      "bom volume",
      "REPOUSO NO LEITO",
      "FF NORMAIS",
      "SVD COM ASPECTO NORMAL"
    ],
    "Abreviação": [
      "Enf",
      "HSA",
      "AVP",
      "MSD",
      "MMII",
      "CTVO",
      "RX",
      "ECG",
      "CC",
      "SNE para alimentação",
      "RHA +",
      "FF NORMAIS",
      "SVD COM ASPECTO NORMAL",
      "CX GERAL"
    ],
    "Grupo Profissional ou Ocupacional": [
      "Enf"
    ],
    "Doença ou Síndrome": [
      "HSA",
      "ABDOME AGUDO"
    ],
    "Paciente ou Grupo com Deficiência": [
      "PACIENTE"
    ],
    "Dispositivo Médico": [
      "AVP",
      "CTVO",
      "bomba infusora",
      "DRENO DE TÓRAX"
    ],
    "Procedimento Terapêutico ou Preventivo": [
      "AVP",
      "SALINIZADO",
      "MEDICADO",
      "CTVO",
      "REPOUSO",
      "JEJUM",
      "SNE para alimentação",
      "REPOUSO NO LEITO",
      "DRENO DE TÓRAX",
      "PODE SENTAR NO LEITO"
    ],
    "Localização ou Região Corporal": [
      "MSD",
      "abdome",
      "MMII",
      "REGIAO LOMBAR",
      "REGIÃO LOMBAR"
    ],
    "Atividade de Assistência à Saúde": [
      "OBSERVAÇÃO",
      "CUIDADOS",
      "PRESCRIÇAO MEDICA"
    ],
    "Negação": [
      "indolor",
      "não",
      "SEM"
    ],
    "Procedimento Diagnóstico": [
      "palpação",
      "RX",
      "ECG"
    ],
    "Função Fisiológica": [
      "evacuou",
      "Diurese limpida"
    ],
    "Conceito Espacial": [
      "DIREITA"
    ],
    "Organização Relacionada à Saúde": [
      "CC",
      "CX GERAL"
    ],
    "Alimento": [
      "REFEIÇÃO"
    ],
    "Lesão ou Envenenamento": [
      "TRAUMATISMOS MULTIPLOS",
      "FRATURA DO COLO DO FEMUR"
    ],
    "Dispositivo de Administração de Medicamento": [
      "bomba infusora"
    ],
    "Conceito Qualitativo": [
      "bom volume"
    ],
    "Substância Corporal": [
      "DÉBITO HEMÁTICO"
    ],
    "Procedimento Laboratorial": [
      "EXAMES LABORATORIAIS"
    ]
  },
  "labels": {
    "orientado": {
      "capitulo": "06"
    },
    "débito hemático": {
      "capitulo": "22"
    },
    "flácido": {
      "capitulo": "15"
    },
    "tranquilo": {
      "capitulo": "06"
    },
    "sangramento": {
      "capitulo": "13"
    },
    "dor internádegas": {
      "capitulo": "21"
    },
    "seco": {
      "capitulo": "21"
    },
    "comunicativo": {
      "capitulo": "06"
    },
    "deambulando": {
      "capitulo": "06"
    },
    "leve cefaleia": {
      "capitulo": "21"
    },
    "limpo": {
      "capitulo": "21"
    },
    "traumatismos multiplos": {
      "capitulo": "22"
    },
    "alerta": {
      "capitulo": "06"
    },
    "algia moderada": {
      "capitulo": "15"
    },
    "acordada": {
      "capitulo": "06"
    },
    "corada": {
      "capitulo": "06"
    },
    "evacuou": {
      "capitulo": "21"
    },
    "lúcido": {
      "capitulo": "06"
    },
    "consciente": {
      "capitulo": "06"
    },
    "repouso no leito": {
      "capitulo": "21"
    },
    "fratura do colo do femur": {
      "capitulo": "15"
    },
    "abdome agudo": {
      "capitulo": "13"
    },
    "lucido": {
      "capitulo": "06"
    },
    "ansioso quanto a alta": {
      "capitulo": "21"
    },
    "hsa": {
      "capitulo": "22"
    },
    "responsiva": {
      "capitulo": "06"
    }
  }
}