{
  "prontuario_id": 25,
  "text": "Às 19H: Paciente sedada ramsay 6, mantendo CVC em jugular interna E para noradrenalina e NPT, e jugular externa com sedação em curso, SNG aberta sem debito, gastrostomia com drenagem em pouco debito com aspecto bilioso e dreno de penrose com debito seroso de aspecto amarelo claro, pele friavel com equimose e flictemas rompidos, PAM com bom fluxo e refluxo, porem instavel. Quadro instavel e prognostico reservado. Segue sob cuidados. Às 14:00: NORMOCORADO, GLASGOW 15, PUPILAS ISOFOTO, SNE COM DIETA EM CURSO, MUCOSA ORAL HIGIENIZADA, VM VIA TQT PARAMETROS: PS 12, PEEP 5, FR 16, FIO2 29%, VOL 400 ML. MMSS AQUECIDOS, FIXADORES EXTERNOS EM MSE, ABDOMEN FLÁCIDO, RHA +, OSTOMA FUNCIONANTE, DIURESE VIA URUPEM EFETIVA CONCENTRADA, MMII COM EXTREMIDADES AQUECIDAS E PELE RESSECADA; SEM EDEMA, AVP EM MID COM SOROTERAPIA EM CURSO. REALIZADA HIGIENE CORPORAL, ORAL E MEDIDAS DE CONFORTO. Às 23:50H: CLIENTE NÃO APRESENTOU DIURESE ESPONTÂNEA ATÉ O MOMENTO, REALIZADO CATETERISMO VESICAL DE ALÍVIO. NIVEL DE CONSCIENCIA REBAIXADO, SENDO NESCESSARIO REALIZAR INTUBAÇÃO OROTRAQUEAL COM TOT 8.0, PERMANECE EM RIMA 24, MODO PCV, PEEP 5, FIO2 50, FREQ 18, SPO2 100%, INICIA COM PROPOFOL A 10 ML/H, APRESENTANDO HIPOTENSÃO, COM BOA RESPOSTA A VOLUME, REALIZADO PUNÇÃO DE CATETER VENOSO CENTRAL DUPLO-LUMEN EM SUBCLAVIA DIREITA, INSTALADO MONITORIZAÇÃO DE PVC, TENTADO PUNÇÃO DE PAM RADIAL UMA VEZ, SEM SUCESSO, SOLICITO ARTERIAL PARA PAM FEMURAL. SEGUE EM DIALISE POR PROGRAMAÇÃO DE QUATRO HORAS PARA RETIRADA DE DOIS LITROS.",
  "entities": {
    "Paciente ou Grupo com Deficiência": [
      "Paciente",
      "CLIENTE"
    ],
    "Procedimento Terapêutico ou Preventivo": [
      "sedada",
      "CVC",
      "NPT",
      "sedação",
      "gastrostomia",
      "VM",
      "TQT",
      "PS",
      "PEEP",
      "FIO2",
      "AVP",
      "SOROTERAPIA",
      "SPO2",
      "DIALISE",
      "SNG aberta",
      "dreno de penrose",
      "SNE COM DIETA",
      "FIXADORES EXTERNOS",
      "HIGIENE CORPORAL",
      "MEDIDAS DE CONFORTO",
      "CATETERISMO VESICAL DE ALÍVIO",
      "INTUBAÇÃO OROTRAQUEAL",
      "MODO PCV",
      "CATETER VENOSO CENTRAL DUPLO-LUMEN",
      "PUNÇÃO DE PAM RADIAL"
    ],
    "Achado": [
      "sedada",
      "debito",
      "NORMOCORADO",
      "DIURESE",
      "EFETIVA",
      "CONCENTRADA",
      "SUCESSO",
      "ramsay 6",
      "SNG aberta",
      "debito seroso",
      "amarelo claro",
      "bom fluxo",
      "GLASGOW 15",
      "PUPILAS ISOFOTO",
      "MUCOSA ORAL HIGIENIZADA",
      "MMSS AQUECIDOS",
      "ABDOMEN FLÁCIDO",
      "RHA +",
      "OSTOMA FUNCIONANTE",
      "EXTREMIDADES AQUECIDAS",
      "PELE RESSECADA",
      "DIURESE ESPONTÂNEA",
      "BOA RESPOSTA A VOLUME"
    ],
    "Abreviação": [
      "CVC",
      "NPT",
      "PAM",
      "VM",
      "TQT",
      "PS",
      "PEEP",
      "FR",
      "FIO2",
      "VOL",
      "MSE",
      "MMII",
      "AVP",
      "MID",
      "FREQ",
      "SPO2",
      "jugular interna E",
      "SNG aberta",
      "PUPILAS ISOFOTO",
      "SNE COM DIETA",
      "MMSS AQUECIDOS",
      "RHA +",
      "TOT 8",
      "MODO PCV",
      "MONITORIZAÇÃO DE PVC",
      "PUNÇÃO DE PAM RADIAL",
      "PAM FEMURAL"
    ],
    "Dispositivo Médico": [
      "CVC",
      "URUPEM",
      "AVP",
      "SNG aberta",
      "dreno de penrose",
      "FIXADORES EXTERNOS",
      "TOT 8",
      "CATETER VENOSO CENTRAL DUPLO-LUMEN"
    ],
    "Substância Farmacológica": [
      "noradrenalina",
      "PROPOFOL"
    ],
    "Hormônio": [
      "noradrenalina"
    ],
    "Negação": [
      "sem",
      "SEM"
    ],
    "Substância Corporal": [
      "debito",
      "debito seroso"
    ],
    "Sinal ou Sintoma": [
      "equimose",
      "instavel",
      "EDEMA",
      "HIPOTENSÃO",
      "aspecto bilioso",
      "pele friavel",
      "flictemas rompidos",
      "Quadro instavel",
      "NIVEL DE CONSCIENCIA REBAIXADO"
    ],
    "Procedimento Diagnóstico": [
      "PAM",
      "MONITORIZAÇÃO DE PVC",
      "PAM FEMURAL"
    ],
    "Atividade de Assistência à Saúde": [
      "cuidados"
    ],
    "Conceito Quantitativo": [
      "12",
      "5",
      "16",
      "29%",
      "24",
      "50",
      "18",
      "100%",
      "400 ML",
      "10 ML/H",
      "QUATRO HORAS"
    ],
    "Localização ou Região Corporal": [
      "MSE",
      "MMII",
      "MID"
    ],
    "Função Fisiológica": [
      "DIURESE",
      "DIURESE ESPONTÂNEA"
    ],
    "Função Patológica": [
      "EDEMA"
    ],
    "Parte do Corpo, Órgão ou Componente Orgânico": [
      "RIMA",
      "jugular interna E",
      "jugular externa",
      "SUBCLAVIA DIREITA"
    ],
    "Substância Química Orgânica": [
      "PROPOFOL"
    ]
  },
  "labels": {
    "instavel": {
      "capitulo": "22"
    },
    "nivel de consciencia rebaixado": {
      "capitulo": "06"
    },
    "debito": {
      "capitulo": "13"
    },
    "extremidades aquecidas": {
      "capitulo": "V"
    },
    "aspecto bilioso": {
      "capitulo": "13"
    },
    "concentrada": {
      "capitulo": "16"
    },
    "pupilas isofoto": {
      "capitulo": "08"
    },
    "flictemas rompidos": {
      "capitulo": "14"
    },
    "amarelo claro": {
      "capitulo": "14"
    },
    "sucesso": {
      "capitulo": "22"
    },
    "sedada": {
      "capitulo": "06"
    },
    "quadro instavel": {
      "capitulo": "22"
    },
    "diurese espontânea": {
      "capitulo": "16"
    },
    "bom fluxo": {
      "capitulo": "12"
    },
    "diurese": {
      "capitulo": "16"
    },
    "mmss aquecidos": {
      "capitulo": "V"
    },
    "pele ressecada": {
      "capitulo": "14"
    },
    "edema": {
      "capitulo": "15"
    },
    "pele friavel": {
      "capitulo": "14"
    },
    "hipotensão": {
      "capitulo": "11"
    },
    "abdomen flácido": {
      "capitulo": "15"
    },
    "boa resposta a volume": {
      "capitulo": "22"
    },
    "sng aberta": {
      "capitulo": "13"
    },
    "debito seroso": {
      "capitulo": "13"
    },
    "efetiva": {
      "capitulo": "16"
    },
    "equimose": {
      "capitulo": "14"
    }
  }
}