{
  "prontuario_id": 273,
  "text": "Às 15:00H: SEGUE ACAMADO. REALIZOU BRONCO HOJE PELA MANHÃ E FECHOU TRAQUEO. SEGUE EM AA COM RESPIRAÇÃO CONFORTAVEL. DIETA VIA GASTROSTOMIA EM BI A 75 ML/ H. MANTEM AVP EM MSD SALINIZADO. DIURESE E EVACUAÇÃO PRESENTES POR FRALDA. SEGUE AOS CUIDADOS, AGUARDANDO LIBERAÇÃO PARA HOME CARE. Às 15HS: ORIENTADA, CALMA, POUCO COMUNICATIVA, EUPNEICA EM AR AMBIENTE, ACEITOU POUCA DIETA OFERTADA, ACESSO VENOSO PERIFERICO EM ANTEBRAÇO DIREITO SALINIZADO, REALIZADO AVALIAÇÃO E BIOPSIA PELO DR VITAL BRASIL, DA VASCULAR, EM FERIDA DE MEMBRO INFERIOR ESQUERDO E ENCAMINHADO PARA LABORATÓRIO, DIURESE DE COLORAÇÃO CITRICA, segue sob cuidados. Às 17:40HR: Rawsay 6, pupilas anisocorica D > E, escleras e conjuntivas normocoradas, CNE com dieta 40 ml\\h, boca higienizada. CVC em jugular interna D com fenta 25 ml\\h, dormo 25 ml\\h, sitio da punção sem sinais flogisticos, CVC em subclavia D exclusiva para hemodialise. TOT + VM (Pi 22, peep 5, Fio2 30%) uso continuo de filtro de barreira, aspiração sistema aberto com media quantidade de secreção mucopurulenta, dreno de torax D sem oscilação, crepitação em bases. BCRNF. Abdome plano, flacido, RHA diminuidos. PAM em arteria radial D. CVD anurico. Higienizado e mobilizado no leito, cabeceira elevada 45º, monitorização por multiplos parametros. SEGUE CUIDADOS.",
  "entities": {
    "Achado": [
      "ACAMADO",
      "SALINIZADO",
      "ORIENTADA",
      "CALMA",
      "BCRNF",
      "flacido",
      "RESPIRAÇÃO CONFORTAVEL",
      "DIURESE E EVACUAÇÃO PRESENTES",
      "POUCO COMUNICATIVA",
      "EUPNEICA EM AR AMBIENTE",
      "ACESSO VENOSO PERIFERICO",
      "DIURESE DE COLORAÇÃO CITRICA",
      "Rawsay 6",
      "escleras e conjuntivas normocoradas",
      "boca higienizada"
    ],
    "Sinal ou Sintoma": [
      "ACAMADO",
      "oscilação",
      "ACEITOU POUCA DIETA",
      "pupilas anisocorica",
      "sinais flogisticos",
      "media quantidade de secreção mucopurulenta",
      "crepitação em bases",
      "RHA diminuidos",
      "CVD anurico"
    ],
    "Abreviação": [
      "BRONCO",
      "AVP",
      "MSD",
      "DR",
      "CVC",
      "fenta",
      "dormo",
      "TOT",
      "VM",
      "Pi",
      "peep",
      "Fio2",
      "BCRNF",
      "PAM",
      "FECHOU TRAQUEO",
      "D &gt; E",
      "CNE com dieta",
      "jugular interna D",
      "subclavia D",
      "RHA diminuidos",
      "arteria radial D",
      "CVD anurico"
    ],
    "Procedimento Diagnóstico": [
      "BRONCO",
      "BIOPSIA",
      "PAM",
      "monitorização por multiplos parametros"
    ],
    "Dispositivo Médico": [
      "BI",
      "AVP",
      "FRALDA",
      "CVC",
      "TOT",
      "ACESSO VENOSO PERIFERICO",
      "filtro de barreira",
      "dreno de torax"
    ],
    "Procedimento Terapêutico ou Preventivo": [
      "AVP",
      "SALINIZADO",
      "CVC",
      "hemodialise",
      "TOT",
      "VM",
      "Pi",
      "peep",
      "Fio2",
      "FECHOU TRAQUEO",
      "ACESSO VENOSO PERIFERICO",
      "CNE com dieta",
      "filtro de barreira",
      "aspiração sistema aberto",
      "dreno de torax",
      "Higienizado e mobilizado no leito",
      "cabeceira elevada 45º"
    ],
    "Localização ou Região Corporal": [
      "MSD",
      "Abdome",
      "MEMBRO INFERIOR ESQUERDO"
    ],
    "Objeto Manufaturado": [
      "FRALDA"
    ],
    "Atividade de Assistência à Saúde": [
      "CUIDADOS",
      "cuidados",
      "HOME CARE"
    ],
    "Organização Relacionada à Saúde": [
      "VASCULAR",
      "LABORATÓRIO"
    ],
    "Lesão ou Envenenamento": [
      "FERIDA"
    ],
    "Substância Farmacológica": [
      "fenta",
      "dormo"
    ],
    "Substância Química Orgânica": [
      "fenta",
      "dormo"
    ],
    "Negação": [
      "sem"
    ],
    "Conceito Quantitativo": [
      "22",
      "5",
      "30%",
      "75 ML/ H",
      "40 ml\\h",
      "25 ml\\h"
    ],
    "Função Fisiológica": [
      "DIURESE E EVACUAÇÃO PRESENTES",
      "DIURESE DE COLORAÇÃO CITRICA"
    ],
    "Parte do Corpo, Órgão ou Componente Orgânico": [
      "ANTEBRAÇO DIREITO",
      "jugular interna D",
      "subclavia D",
      "arteria radial D"
    ]
  },
  "labels": {
    "rha diminuidos": {
      "capitulo": "15"
    },
    "acesso venoso periferico": {
      "capitulo": "11"
    },
    "rawsay 6": {
      "capitulo": "08"
    },
    "diurese de coloração citrica": {
      "capitulo": "21"
    },
    "media quantidade de secreção mucopurulenta": {
      "capitulo": "12"
    },
    "crepitação em bases": {
      "capitulo": "12"
    },
    "cvd anurico": {
      "capitulo": "16"
    },
    "sinais flogisticos": {
      "capitulo": "22"
    },
    "ferida": {
      "capitulo": "15"
    },
    "pupilas anisocorica": {
      "capitulo": "08"
    },
    "aceitou pouca dieta": {
      "capitulo": "13"
    },
    "bcrnf": {
      "capitulo": "12"
    },
    "salinizado": {
      "capitulo": "11"
    },
    "oscilação": {
      "capitulo": "22"
    },
    "orientada": {
      "capitulo": "06"
    },
    "pouco comunicativa": {
      "capitulo": "06"
    }
  }
}