{
  "prontuario_id": 890,
  "text": "Maria, 68 anos, procedente de Curitiba\n\nPaciente relata tremor em cabeça  há 10 anos e dor cervical e cefaleia esquerda, relata piora progressiva nos ultimos anos.\nRefere que iniciou com cefaleia importante aos 40 anos após ultimo parto, continua com crises fortes de cefaleia desde então. \nRefere que tremor melhora quando está calma e relaxada, e piora em momentos de estresse. \n\nAMP: HAS - não utiliza medicações de uso contínuo, histerectomia há 1,5 anos. Em uso de gabapentina 300 mg 8/8 horas por dor lombar com irradiação para MMII, trajeto de L5.\n\nAo exame: tremor (tipo não-não) e rigidez cervical, com desvio da cabeça para direita, \nsem deficit de força, sem rigidez em membros, sem bradicinesia, sem alterações de pares cranianos.\nHipertrofia de trapézio.\n\nRM (325/07/2014): angioma venoso na região parietal esquerda.\nTC cervical: exame dentro dos padrões da normalidade, exceto por osteofitos marginais nos corpos vertebrais. \n\nCONDUTA: \nExplico quanto a natureza benigna e idiopática do quadro.\nSugiro aplicação de toxina botulínica em musculatura cervical, paciente concorda com procedimento.",
  "entities": {
    "Paciente ou Grupo com Deficiência": [
      "Paciente",
      "paciente"
    ],
    "Sinal ou Sintoma": [
      "cefaleia",
      "tremor",
      "bradicinesia",
      "tremor em cabeça",
      "dor cervical",
      "piora progressiva",
      "cefaleia importante",
      "crises fortes de cefaleia",
      "dor lombar",
      "irradiação para MMII",
      "rigidez cervical",
      "desvio da cabeça para direita",
      "deficit de força",
      "rigidez em membros",
      "alterações de pares cranianos",
      "Hipertrofia de trapézio"
    ],
    "Procedimento Terapêutico ou Preventivo": [
      "parto",
      "histerectomia",
      "procedimento"
    ],
    "Doença ou Síndrome": [
      "HAS"
    ],
    "Abreviação": [
      "HAS",
      "L5",
      "RM",
      "irradiação para MMII",
      "TC cervical"
    ],
    "Negação": [
      "não",
      "sem"
    ],
    "Substância Química Orgânica": [
      "gabapentina"
    ],
    "Substância Farmacológica": [
      "gabapentina",
      "medicações de uso contínuo",
      "toxina botulínica"
    ],
    "Parte do Corpo, Órgão ou Componente Orgânico": [
      "L5",
      "musculatura cervical"
    ],
    "Procedimento Diagnóstico": [
      "exame",
      "RM",
      "TC cervical"
    ],
    "Atividade de Assistência à Saúde": [
      "CONDUTA"
    ],
    "Conceito Qualitativo": [
      "tipo não-não"
    ],
    "Resultado Laboratorial ou de Teste": [
      "angioma venoso na região parietal esquerda",
      "dentro dos padrões da normalidade",
      "osteofitos marginais nos corpos vertebrais"
    ],
    "Aminoácido, Peptídeo ou Proteína": [
      "toxina botulínica"
    ]
  },
  "labels": {
    "crises fortes de cefaleia": {
      "capitulo": "08"
    },
    "bradicinesia": {
      "capitulo": "08"
    },
    "alterações de pares cranianos": {
      "capitulo": "08"
    },
    "rigidez cervical": {
      "capitulo": "15"
    },
    "hipertrofia de trapézio": {
      "capitulo": "15"
    },
    "cefaleia importante": {
      "capitulo": "08"
    },
    "rigidez em membros": {
      "capitulo": "08"
    },
    "tremor em cabeça": {
      "capitulo": "08"
    },
    "dor lombar": {
      "capitulo": "13"
    },
    "desvio da cabeça para direita": {
      "capitulo": "21"
    },
    "tremor": {
      "capitulo": "08"
    },
    "irradiação para mmii": {
      "capitulo": "11"
    },
    "dor cervical": {
      "capitulo": "15"
    },
    "cefaleia": {
      "capitulo": "08"
    },
    "deficit de força": {
      "capitulo": "08"
    }
  }
}