{
  "prontuario_id": 576,
  "text": "13:01 HS RETORNOU CENTRO CIRUGICO ÁS 12:30 , EM MACA , TRAQUEOSTOMIZADO , EUPNEICO, ABERTURA OCULAR , CURATIVO TIPO CAPACETE ,CURATIVO REGIÃO ABDOMINAL ,LIMPO E SECO EXTERNAMENTE, ACESSO VENOSO PERIFÉRICO SALINIZADO EM MSD, SONDA NASOENTERAL FECHADA ,SEM FÁCIES DE DOR  DURANTE O PERIODO, SEM FÁCIES DE DOR DURANTE O PERIODO, MANTEM PRECAUÇÃO DE CONTATO. ENF FLORENCE NIGHTINGLAE COREN XXXX. DOENCA DE HUNTINGTON. 12:40hrs paciente com momentos de confusão mental, acordada, comunicativa, eupneica em aa, não se alimenta via oral, emagrecida com jejunostomia com soro glicosado em bomba infusora, curativo limpo e seco, diurese presnete em svd. SEPTICEMIA NAO ESPECIFICADA. 18:10hrs paciente acordado, respondendo a comandos verbais, sne com dieta em curso traqueostomizado eupneico em aa curativos especial em região sacra + calcaneo  diurese presente, seguem cuidados de enfermagem. ACIDENTE VASCULAR CEREBRAL NAO ESPECIFICADO COMO HEMORRAGICO OU ISQUEMICO.",
  "entities": {
    "Dispositivo Médico": [
      "MACA",
      "CURATIVO",
      "curativo",
      "CURATIVO TIPO CAPACETE",
      "ACESSO VENOSO PERIFÉRICO SALINIZADO",
      "SONDA NASOENTERAL FECHADA",
      "bomba infusora",
      "curativos especial"
    ],
    "Procedimento Terapêutico ou Preventivo": [
      "TRAQUEOSTOMIZADO",
      "CURATIVO",
      "jejunostomia",
      "curativo",
      "traqueostomizado",
      "CURATIVO TIPO CAPACETE",
      "ACESSO VENOSO PERIFÉRICO SALINIZADO",
      "SONDA NASOENTERAL FECHADA",
      "PRECAUÇÃO DE CONTATO",
      "alimenta via oral",
      "soro glicosado",
      "sne com dieta",
      "curativos especial"
    ],
    "Achado": [
      "TRAQUEOSTOMIZADO",
      "EUPNEICO",
      "LIMPO",
      "SECO",
      "acordada",
      "comunicativa",
      "emagrecida",
      "limpo",
      "seco",
      "acordado",
      "traqueostomizado",
      "ABERTURA OCULAR",
      "eupneica em aa",
      "diurese presnete em svd",
      "respondendo a comandos verbais",
      "eupneico em aa",
      "diurese presente"
    ],
    "Conceito Espacial": [
      "EXTERNAMENTE"
    ],
    "Abreviação": [
      "MSD",
      "ENF",
      "eupneica em aa",
      "diurese presnete em svd",
      "sne com dieta",
      "eupneico em aa"
    ],
    "Localização ou Região Corporal": [
      "MSD",
      "REGIÃO ABDOMINAL",
      "região sacra"
    ],
    "Negação": [
      "SEM",
      "não"
    ],
    "Grupo Profissional ou Ocupacional": [
      "ENF"
    ],
    "Paciente ou Grupo com Deficiência": [
      "paciente"
    ],
    "Parte do Corpo, Órgão ou Componente Orgânico": [
      "calcaneo"
    ],
    "Organização Relacionada à Saúde": [
      "CENTRO CIRUGICO"
    ],
    "Sinal ou Sintoma": [
      "FÁCIES DE DOR",
      "momentos de confusão mental"
    ],
    "Doença ou Síndrome": [
      "DOENCA DE HUNTINGTON",
      "ACIDENTE VASCULAR CEREBRAL"
    ],
    "Substância Farmacológica": [
      "soro glicosado"
    ],
    "Dispositivo de Administração de Medicamento": [
      "bomba infusora"
    ],
    "Função Fisiológica": [
      "diurese presnete em svd",
      "diurese presente"
    ],
    "Atividade de Assistência à Saúde": [
      "cuidados de enfermagem"
    ]
  },
  "labels": {
    "comunicativa": {
      "capitulo": "06"
    },
    "diurese presente": {
      "capitulo": "11"
    },
    "seco": {
      "capitulo": "13"
    },
    "acordado": {
      "capitulo": "06"
    },
    "limpo": {
      "capitulo": "13"
    },
    "respondendo a comandos verbais": {
      "capitulo": "06"
    },
    "fácies de dor": {
      "capitulo": "21"
    },
    "acidente vascular cerebral": {
      "capitulo": "08"
    },
    "emagrecida": {
      "capitulo": "15"
    },
    "traqueostomizado": {
      "capitulo": "12"
    },
    "abertura ocular": {
      "capitulo": "09"
    },
    "eupneica em aa": {
      "capitulo": "12"
    },
    "momentos de confusão mental": {
      "capitulo": "06"
    },
    "doenca de huntington": {
      "capitulo": "06"
    },
    "acordada": {
      "capitulo": "06"
    },
    "eupneico": {
      "capitulo": "12"
    },
    "eupneico em aa": {
      "capitulo": "12"
    }
  }
}