{
  "prontuario_id": 333,
  "text": "12:15HS. CONSCIENTE. COMUNICATIVA. EUPINEICA. NÃO APRESENTA QUEIXAS. ACEITOU A DIETA OFERECIDA. EVACUAÇÃO E DIURESE PRESENTE. LIBERADO PEDIDO DE ARTERIOGRAFIA. ASSINADO AUTORIZAÇÃ PELO FAMILIAR E ENCAMINHADO PARA O SETOR DE ARTERIOGRAFA. ENFERMEIRA FLORENCE NIGHTINGALE (COREN XXXX). ALOPECIA ANDROGENICA. 1 DI COM HX DE HEMEPLEGIA A D. ALERTA, RESPONDENDO A COMANDOS. DESORIENTADA, COM PERIODOS DE CONFUSÃO. COM DESVIO DE RIMA, DISASTRICA. RESPIRAÇÃO ESPONTÂNEA EM AR AMBIENTE.  PACIENTE COM ARRITMIA CARDIACA, COMUNICADO R1 LUCAS. ACESSO VENOSO PERIFERICO EM MSE. PUPILAS ISO E FOTO. NEGA ALGIA. DIURESE PRESENTE. LIBEREADO DIETA ASSISTIDA, ORIENTO EQUIPE PARA MANTER CABECEIRA ELEVADA. AGUARDA TRANSFERÊNCIA UI ACIDENTE VASCULAR CEREBRAL NAO ESPECIFICADO COMO HEMORRAGICO OU ISQUEMICO. 08:50hs- Glasgow 14, pupilas isocóricas fotorreagentes, SNE com dieta a 75ml/h, respiração espontânea em návoa úmida a 5l/m, SpO2 95%, apresenta tosse produtiva com expectoração amarela em grande quantidade, acesso venoso central D com plano básico de hidratação, monitorizado, estável hemodinamicamente, MV+ com roncos esparsos, SVD com diurese efetiva, evacuação ausente, úlcera grau III em região sacra, extremidades quentes e bem perfundidas, higienizado e sentado na poltrona. Enfª FLORENCE NIGHTINGALE XXXX. OUTRAS DOENCAS DAS VIAS AEREAS SUPERIORES.",
  "entities": {
    "Achado": [
      "CONSCIENTE",
      "COMUNICATIVA",
      "EUPINEICA",
      "EVACUAÇÃO",
      "ALERTA",
      "ISO",
      "FOTO",
      "isocóricas",
      "fotorreagentes",
      "MV+",
      "ACEITOU A DIETA",
      "DIURESE PRESENTE",
      "RESPONDENDO A COMANDOS",
      "RESPIRAÇÃO ESPONTÂNEA EM AR AMBIENTE",
      "respiração espontânea",
      "estável hemodinamicamente",
      "SVD com diurese efetiva",
      "extremidades quentes",
      "bem perfundidas",
      "sentado na poltrona"
    ],
    "Negação": [
      "NÃO",
      "NEGA",
      "ausente"
    ],
    "Sinal ou Sintoma": [
      "QUEIXAS",
      "DESORIENTADA",
      "DISASTRICA",
      "ALGIA",
      "HEMEPLEGIA A D",
      "PERIODOS DE CONFUSÃO",
      "DESVIO DE RIMA",
      "ARRITMIA CARDIACA",
      "Glasgow 14",
      "tosse produtiva",
      "expectoração amarela em grande quantidade",
      "roncos esparsos"
    ],
    "Função Fisiológica": [
      "EVACUAÇÃO",
      "evacuação",
      "DIURESE PRESENTE",
      "SVD com diurese efetiva"
    ],
    "Procedimento Diagnóstico": [
      "ARTERIOGRAFIA",
      "monitorizado"
    ],
    "Grupo Familiar": [
      "FAMILIAR"
    ],
    "Grupo Profissional ou Ocupacional": [
      "ENFERMEIRA",
      "R1",
      "EQUIPE",
      "Enfª"
    ],
    "Paciente ou Grupo com Deficiência": [
      "PACIENTE"
    ],
    "Abreviação": [
      "R1",
      "MSE",
      "ISO",
      "FOTO",
      "UI",
      "SpO2",
      "MV+",
      "Enfª",
      "HEMEPLEGIA A D",
      "SNE com dieta",
      "acesso venoso central D",
      "SVD com diurese efetiva"
    ],
    "Localização ou Região Corporal": [
      "MSE",
      "região sacra"
    ],
    "Parte do Corpo, Órgão ou Componente Orgânico": [
      "PUPILAS",
      "pupilas"
    ],
    "Alimento": [
      "DIETA"
    ],
    "Procedimento Terapêutico ou Preventivo": [
      "DIETA",
      "higienizado",
      "ACESSO VENOSO PERIFERICO",
      "CABECEIRA ELEVADA",
      "SNE com dieta",
      "návoa úmida",
      "acesso venoso central D",
      "plano básico de hidratação",
      "sentado na poltrona"
    ],
    "Organização Relacionada à Saúde": [
      "UI",
      "SETOR DE ARTERIOGRAFA"
    ],
    "Conceito Quantitativo": [
      "75ml/h",
      "5l/m",
      "95%"
    ],
    "Atributo Clínico": [
      "SpO2"
    ],
    "Doença ou Síndrome": [
      "ALOPECIA ANDROGENICA",
      "ACIDENTE VASCULAR CEREBRAL",
      "úlcera grau III",
      "DOENCAS DAS VIAS AEREAS SUPERIORES"
    ],
    "Dispositivo Médico": [
      "ACESSO VENOSO PERIFERICO",
      "acesso venoso central D"
    ]
  },
  "labels": {
    "foto": {
      "capitulo": "09"
    },
    "disastrica": {
      "capitulo": "06"
    },
    "doencas das vias aereas superiores": {
      "capitulo": "12"
    },
    "iso": {
      "capitulo": "08"
    },
    "estável hemodinamicamente": {
      "capitulo": "11"
    },
    "desvio de rima": {
      "capitulo": "09"
    },
    "roncos esparsos": {
      "capitulo": "12"
    },
    "respiração espontânea": {
      "capitulo": "12"
    },
    "alerta": {
      "capitulo": "06"
    },
    "arritmia cardiaca": {
      "capitulo": "11"
    },
    "alopecia androgenica": {
      "capitulo": "14"
    },
    "fotorreagentes": {
      "capitulo": "09"
    },
    "desorientada": {
      "capitulo": "06"
    },
    "glasgow 14": {
      "capitulo": "08"
    },
    "expectoração amarela em grande quantidade": {
      "capitulo": "12"
    },
    "periodos de confusão": {
      "capitulo": "06"
    },
    "respondendo a comandos": {
      "capitulo": "06"
    },
    "isocóricas": {
      "capitulo": "08"
    },
    "tosse produtiva": {
      "capitulo": "12"
    },
    "hemeplegia a d": {
      "capitulo": "08"
    },
    "acidente vascular cerebral": {
      "capitulo": "22"
    },
    "respiração espontânea em ar ambiente": {
      "capitulo": "12"
    },
    "úlcera grau iii": {
      "capitulo": "14"
    }
  }
}