{
  "prontuario_id": 538,
  "text": "03:21 Paciente consciente, lúcido, orientado, comunicativo, normotenso, normocorado, afebril, deambulando. MAntém acesso venoso salinizado em MSE. Permanece com gesso em MSD. Apresenta leve edema facial. Nega algias no momento. Segue sob cuidados. EXAME MEDICO GERAL. 00:24 Paciente consciente, lúcido, orientado, comunicativo, em repouso no leito. Mantém acesso venoso salinizado no momento. Permanece com curativo em MMII, com saídad e secreção em moderada quantidade e odor fétido. Realizada terceira troca do ctvo durante o período. Segue sob cuidados. VARIZES DOS MEMBROS INFERIORES COM ULCERA E INFLAMACAO. 03:14 em repouso no leito, sob névoa umida, dispneica, confusa,  edema em MMSS e MMII, faz uso de fraldas, eliminações intestinais presente, apresentou hipertenção 210/60 comunicado plantão Dra Maria, prescreveu captopril. Segue sob cuidados multiprofissionais. FLORENCE NIGHTINGALE, XXXX. DERRAME PLEURAL NAO CLASSIFICADO EM OUTRA PARTE.",
  "entities": {
    "Paciente ou Grupo com Deficiência": [
      "Paciente"
    ],
    "Achado": [
      "consciente",
      "lúcido",
      "orientado",
      "comunicativo",
      "normotenso",
      "normocorado",
      "afebril",
      "deambulando",
      "repouso no leito",
      "eliminações intestinais presente"
    ],
    "Negação": [
      "afebril",
      "Nega"
    ],
    "Abreviação": [
      "MSE",
      "MSD",
      "MMII",
      "MMSS",
      "Dra",
      "troca do ctvo"
    ],
    "Localização ou Região Corporal": [
      "MSE",
      "MSD",
      "MMII",
      "MMSS"
    ],
    "Dispositivo Médico": [
      "gesso",
      "curativo",
      "acesso venoso salinizado"
    ],
    "Procedimento Terapêutico ou Preventivo": [
      "gesso",
      "curativo",
      "acesso venoso salinizado",
      "repouso no leito",
      "troca do ctvo",
      "sob névoa umida"
    ],
    "Sinal ou Sintoma": [
      "algias",
      "dispneica",
      "confusa",
      "edema",
      "hipertenção",
      "leve edema facial",
      "odor fétido"
    ],
    "Atividade de Assistência à Saúde": [
      "cuidados",
      "EXAME MEDICO GERAL",
      "cuidados multiprofissionais"
    ],
    "Substância Corporal": [
      "secreção"
    ],
    "Função Patológica": [
      "edema"
    ],
    "Objeto Manufaturado": [
      "fraldas"
    ],
    "Conceito Quantitativo": [
      "210/60"
    ],
    "Organização Relacionada à Saúde": [
      "plantão"
    ],
    "Aminoácido, Peptídeo ou Proteína": [
      "captopril"
    ],
    "Substância Farmacológica": [
      "captopril"
    ],
    "Procedimento Diagnóstico": [
      "EXAME MEDICO GERAL"
    ],
    "Conceito Qualitativo": [
      "moderada quantidade"
    ],
    "Doença ou Síndrome": [
      "VARIZES DOS MEMBROS INFERIORES COM ULCERA E INFLAMACAO",
      "DERRAME PLEURAL"
    ],
    "Função Fisiológica": [
      "eliminações intestinais presente"
    ]
  },
  "labels": {
    "eliminações intestinais presente": {
      "capitulo": "13"
    },
    "algias": {
      "capitulo": "21"
    },
    "derrame pleural": {
      "capitulo": "12"
    },
    "dispneica": {
      "capitulo": "12"
    },
    "deambulando": {
      "capitulo": "15"
    },
    "normotenso": {
      "capitulo": "11"
    },
    "varizes dos membros inferiores com ulcera e inflamacao": {
      "capitulo": "15"
    },
    "confusa": {
      "capitulo": "06"
    },
    "repouso no leito": {
      "capitulo": "21"
    },
    "edema": {
      "capitulo": "15"
    },
    "odor fétido": {
      "capitulo": "14"
    },
    "leve edema facial": {
      "capitulo": "14"
    },
    "hipertenção": {
      "capitulo": "11"
    }
  }
}