{
  "prontuario_id": 231,
  "text": "18:20 APRESENTANDO GLICEMIA CAPILAR DE 59 MG/DL, REALIZADO MEDICAÇÃO CONFORME PRESCRIÇÃO MÉDICA. ENF FLORENCE NIGHTINGALE XXXX. EXAME GERAL E INVESTIGACAO DE PESSOAS SEM QUEIXAS OU DIAGNOSTICO RELATADO. 15:10 - REALIZOU TOMOGRAFIA DE TORAX COM SUCESSO; SINDROME DO DESCONFORTO RESPIRATORIO DO ADULTO. 02:15 H CLIENTE ACAMADA, POUCO RESPONSIVA, AFEBRIL, USO DE O2 SOB CATETER NASAL TIPO OCULOS. RECEBE DIETA VIA SNE POR BI 60 ML/H. MANTEM ACESSO PERIFERICO EM MID REGIÃO DE PÉ COM PLANO DE SORO EM CURSO. APRESENTA EDEMA DE MMSS. DIURESE EM SVD FUNCIONANTE. REALIZADO MUDANÇA DE  DECUBITO E MEDIDAS DE CONFORTO PELA EQUIPE DE ENFERMAGEM. SEGUE EM OBSERVAÇÃO E CUIDADOS. ENFª FLORENCE NIGHTINGALE, COREN XXXX. ABSCESSO URETRAL. 12:00 2ºDI COM HX AVEi. MONITORIZADA NA SALA DE EMERGENCIA, PA 221/127, FC 81. ABERTURA OCULAR ESPONTANEA, PUPILAS ISO E FOTO, RESPONDE A COMANDOS, SONOLENTA, EUPNEICA, SNG ABERTA SEM DEBITO NO MOMENTO, MANTEM MASCARA TRANSPARENTE DE O2 3 L/MIN, ACESSO VENOSO EM MSD COM MANITOL EM CURSO, SVD COM 200 ML DEBITO AMARELO CLARO. HEMIPLEGIA D. MANTEM JEJUM. AGUARDA VAGA EM UTI. FAMILIA PRESENTE NO HORARIO DE VISITA. ENF FLORENCE NIGHTINGALE. ACIDENTE VASCULAR CEREBRAL NAO ESPECIFICADO COMO HEMORRAGICO OU ISQUEMICO.",
  "entities": {
    "Substância Farmacológica": [
      "MEDICAÇÃO",
      "MANITOL"
    ],
    "Grupo Profissional ou Ocupacional": [
      "ENF",
      "ENFª",
      "EQUIPE DE ENFERMAGEM"
    ],
    "Abreviação": [
      "ENF",
      "O2",
      "MID",
      "MMSS",
      "ENFª",
      "AVEi",
      "PA",
      "FC",
      "ISO",
      "FOTO",
      "MSD",
      "SVD",
      "UTI",
      "DIURESE EM SVD FUNCIONANTE",
      "SNG ABERTA",
      "HEMIPLEGIA D"
    ],
    "Negação": [
      "SEM",
      "AFEBRIL"
    ],
    "Sinal ou Sintoma": [
      "QUEIXAS",
      "EDEMA",
      "SONOLENTA",
      "POUCO RESPONSIVA",
      "HEMIPLEGIA D"
    ],
    "Achado": [
      "SUCESSO",
      "ACAMADA",
      "AFEBRIL",
      "ISO",
      "FOTO",
      "EUPNEICA",
      "DEBITO",
      "DIURESE EM SVD FUNCIONANTE",
      "ABERTURA OCULAR ESPONTANEA",
      "RESPONDE A COMANDOS",
      "SNG ABERTA",
      "DEBITO AMARELO CLARO"
    ],
    "Paciente ou Grupo com Deficiência": [
      "CLIENTE"
    ],
    "Dispositivo Médico": [
      "BI",
      "SVD",
      "CATETER NASAL TIPO OCULOS",
      "ACESSO PERIFERICO",
      "MASCARA TRANSPARENTE DE O2",
      "ACESSO VENOSO"
    ],
    "Localização ou Região Corporal": [
      "MID",
      "MMSS",
      "MSD",
      "REGIÃO DE PÉ"
    ],
    "Atividade de Assistência à Saúde": [
      "OBSERVAÇÃO",
      "CUIDADOS",
      "PRESCRIÇÃO MÉDICA"
    ],
    "Doença ou Síndrome": [
      "AVEi",
      "SINDROME DO DESCONFORTO RESPIRATORIO DO ADULTO",
      "ABSCESSO URETRAL",
      "ACIDENTE VASCULAR CEREBRAL"
    ],
    "Procedimento Diagnóstico": [
      "MONITORIZADA",
      "TOMOGRAFIA DE TORAX"
    ],
    "Atributo Clínico": [
      "PA",
      "FC"
    ],
    "Conceito Quantitativo": [
      "221/127",
      "81",
      "60 ML/H",
      "200 ML"
    ],
    "Parte do Corpo, Órgão ou Componente Orgânico": [
      "PUPILAS"
    ],
    "Substância Química Orgânica": [
      "MANITOL"
    ],
    "Procedimento Terapêutico ou Preventivo": [
      "SVD",
      "JEJUM",
      "ACESSO PERIFERICO",
      "PLANO DE SORO EM CURSO",
      "MUDANÇA DE DECUBITO",
      "MEDIDAS DE CONFORTO",
      "SNG ABERTA",
      "MASCARA TRANSPARENTE DE O2",
      "ACESSO VENOSO"
    ],
    "Organização Relacionada à Saúde": [
      "UTI",
      "SALA DE EMERGENCIA"
    ],
    "Grupo Familiar": [
      "FAMILIA"
    ],
    "Produto Intelectual": [
      "PRESCRIÇÃO MÉDICA"
    ],
    "Função Fisiológica": [
      "DIURESE EM SVD FUNCIONANTE"
    ]
  },
  "labels": {
    "diurese em svd funcionante": {
      "capitulo": "11"
    },
    "foto": {
      "capitulo": "09"
    },
    "debito": {
      "capitulo": "22"
    },
    "abscesso uretral": {
      "capitulo": "16"
    },
    "queixas": {
      "capitulo": "21"
    },
    "iso": {
      "capitulo": "08"
    },
    "pouco responsiva": {
      "capitulo": "06"
    },
    "debito amarelo claro": {
      "capitulo": "22"
    },
    "sucesso": {
      "capitulo": "09"
    },
    "eupneica": {
      "capitulo": "12"
    },
    "acamada": {
      "capitulo": "21"
    },
    "edema": {
      "capitulo": "15"
    },
    "abertura ocular espontanea": {
      "capitulo": "09"
    },
    "sonolenta": {
      "capitulo": "07"
    },
    "hemiplegia d": {
      "capitulo": "08"
    },
    "acidente vascular cerebral": {
      "capitulo": "08"
    },
    "sng aberta": {
      "capitulo": "12"
    },
    "sindrome do desconforto respiratorio do adulto": {
      "capitulo": "12"
    },
    "avei": {
      "capitulo": "21"
    },
    "responde a comandos": {
      "capitulo": "06"
    }
  }
}