{
  "prontuario_id": 691,
  "text": "9:40 H CONSCIENTE, ORIENTADA, VERBALIZANDO, MOBILIZANDO ATIVAMENTE OS MEMBROS. EUPNEICA EM NÉVOA ÚMIDA 2 L/MIN, MV DIFUSOS, SOROTERAPIA EM ACESSO PERIFÉRICO EM MSD, SENDO INFUNDIDO SF 0,9, DRENO DE TÓRAX COM DRENAGEM ESBRANQUIÇADA EM PEQUENA QUANTIDADE.  ABDOME SEMI GLOBOSO, INCISÃO MEDIANA COM PRESENÇA DE PUS, DRENANDO NA REGIÃO DO UMBIGO, SVD URINA EFETIVA. ACEITOU DIETA LIQUIDA RESTRITA. PRECAUÇÃO POR MRSA. EDEMA CEREBRAL. 2 DI, pciente internado pela ortopedia. Vitima colisão auto x moto. Consciente, orientado, verbalizando. Ao exame físico: couro cabeludo integro, sem presença de sujidades. Corado, pupilas isocóricas, ecoriação em região nasal, eupneico, em mascara  O2 5 ml/min, jejum.  Relata que o O2 provoca tosse. Tórax simétrico, algia em região esternal. Adbome globoso, indolor a palpação. Acesso venoso em MSE, com soroterapia em curso. Escoriação em região de metacarpo E, região de rotuliana  e anterior da perna bilateral. MMII com edema. Eliminações fisiológicas ausentes no período. Acadêmica de Enfermagem da XXXX FLORENCE NIGHTINGALE. FERIMENTO DE OUTRAS PARTES DO TORAX.",
  "entities": {
    "Achado": [
      "CONSCIENTE",
      "ORIENTADA",
      "VERBALIZANDO",
      "EUPNEICA",
      "Consciente",
      "orientado",
      "verbalizando",
      "Corado",
      "eupneico",
      "MOBILIZANDO ATIVAMENTE OS MEMBROS",
      "MV DIFUSOS",
      "URINA EFETIVA",
      "ACEITOU DIETA LIQUIDA RESTRITA",
      "couro cabeludo integro",
      "presença de sujidades",
      "pupilas isocóricas",
      "Tórax simétrico",
      "indolor a palpação",
      "Eliminações fisiológicas"
    ],
    "Abreviação": [
      "MSD",
      "SVD",
      "pciente",
      "MSE",
      "MMII",
      "MV DIFUSOS",
      "SF 0 , 9",
      "mascara O2",
      "região de metacarpo E"
    ],
    "Localização ou Região Corporal": [
      "MSD",
      "Adbome",
      "MSE",
      "MMII",
      "REGIÃO DO UMBIGO",
      "região nasal",
      "região esternal",
      "região de metacarpo E",
      "região de rotuliana"
    ],
    "Procedimento Terapêutico ou Preventivo": [
      "SVD",
      "jejum",
      "NÉVOA ÚMIDA",
      "SOROTERAPIA EM",
      "ACESSO PERIFÉRICO",
      "DRENO DE TÓRAX",
      "ACEITOU DIETA LIQUIDA RESTRITA",
      "mascara O2",
      "Acesso venoso",
      "soroterapia em curso"
    ],
    "Dispositivo Médico": [
      "SVD",
      "ACESSO PERIFÉRICO",
      "DRENO DE TÓRAX",
      "Acesso venoso"
    ],
    "Paciente ou Grupo com Deficiência": [
      "pciente",
      "Vitima"
    ],
    "Grupo Profissional ou Ocupacional": [
      "ortopedia"
    ],
    "Negação": [
      "sem",
      "ausentes"
    ],
    "Sinal ou Sintoma": [
      "ecoriação",
      "algia",
      "Escoriação",
      "edema",
      "DRENAGEM ESBRANQUIÇADA",
      "ABDOME SEMI GLOBOSO",
      "PRESENÇA DE PUS"
    ],
    "Lesão ou Envenenamento": [
      "ecoriação",
      "Escoriação",
      "INCISÃO MEDIANA",
      "colisão auto x moto",
      "FERIMENTO DE OUTRAS PARTES DO TORAX"
    ],
    "Conceito Quantitativo": [
      "2 L/MIN",
      "PEQUENA QUANTIDADE",
      "5 ml/min"
    ],
    "Substância Farmacológica": [
      "SF 0 , 9"
    ],
    "Função Fisiológica": [
      "URINA EFETIVA",
      "Eliminações fisiológicas"
    ],
    "Doença ou Síndrome": [
      "EDEMA CEREBRAL"
    ],
    "Procedimento Diagnóstico": [
      "exame físico"
    ]
  },
  "labels": {
    "edema cerebral": {
      "capitulo": "08"
    },
    "ecoriação": {
      "capitulo": "22"
    },
    "mv difusos": {
      "capitulo": "12"
    },
    "ferimento de outras partes do torax": {
      "capitulo": "12"
    },
    "incisão mediana": {
      "capitulo": "15"
    },
    "abdome semi globoso": {
      "capitulo": "15"
    },
    "escoriação": {
      "capitulo": "22"
    },
    "tórax simétrico": {
      "capitulo": "12"
    },
    "mobilizando ativamente os membros": {
      "capitulo": "15"
    },
    "eupneico": {
      "capitulo": "12"
    },
    "aceitou dieta liquida restrita": {
      "capitulo": "24"
    },
    "drenagem esbranquiçada": {
      "capitulo": "22"
    },
    "algia": {
      "capitulo": "21"
    },
    "colisão auto x moto": {
      "capitulo": "23"
    },
    "presença de pus": {
      "capitulo": "15"
    },
    "edema": {
      "capitulo": "15"
    }
  }
}