{
  "prontuario_id": 593,
  "text": "Paciente com DM 2;  HAS;  artrite reumatóide em acompanhamento no ambulatório de reumatologia do XXXX. Vem à emergencia em 28/07 encaminhada do ambulatório da reumato por pré-síncope e dor em ardência em região esternal direita, sem irradiação, de curta duração, em repouso. Relata ter tido outro episódio de pré-síncope há aprox. 2 meses, porém é a primeira vez que teve dor torácica. ECG com hemibloqueio anterior esquerdo, pobre progressão da onda R em V1 e V2, porém sem alterações isquêmicas agudas. Não houve alteração de enzimas cardíacas. Realizou cintilo miocárdica para estratificação de risco, cujo resultado foi normal, sem isquemia. Recebe alta assintomática, com receita das medicações em uso e orientação de procurar seu médico (posto de saúde) para ajuste da dose de  hipoglicemiantes para melhor controle do DM. Retorno a emergência se necessário. PACIENTE COM FIBRILAÇÃO ATRIAL, DUPLA LESÃO AÓRTICA, I MITRAL LEVE, COM ÚLTIMA ECO TRANSESOFÁGICA, OPTADO POR ADIAR CIRURGIA  E SEGUIR TRATAMENTO MEDICAMENTOSO. PACIENTE EM USO ANTICOAGULANTES, COM HISTÓRIA DE DOENÇA DIVERTICULAR, INTERNA COM QUADRO DE MELENA E INSTABILIDADE HEMODINÂMICA, ENCAMINHADO DO XXXX, APÓS TRANSFUSÃO DE 2 CHADS E ESTABILIZAÇÃO. PACIENTE PERMANECEU ESTÁVEL , COM CONTROLE HT / HB. REALIZADA AVALIAÇÃO COM GASTRO, ENDOSCOPIA DIGESTIVA ALTA COM GASTRITE ENDOSCÓPICA ANTRAL. RECEBE ALTA SEM ANTICOAGULAÇÃO, EM USO DE OMEPRAZOL, COM SEGUIMENTO AMBULATORIAL E DISCUTIR REINTRODUÇÃO ATC  APÓS.",
  "entities": {
    "Paciente ou Grupo com Deficiência": [
      "Paciente",
      "PACIENTE"
    ],
    "Doença ou Síndrome": [
      "HAS",
      "DM",
      "DM 2",
      "artrite reumatóide",
      "FIBRILAÇÃO ATRIAL",
      "DOENÇA DIVERTICULAR",
      "GASTRITE ENDOSCÓPICA ANTRAL"
    ],
    "Abreviação": [
      "HAS",
      "ECG",
      "DM",
      "GASTRO",
      "ATC",
      "DM 2",
      "ambulatório da reumato",
      "cintilo miocárdica",
      "CONTROLE HT / HB"
    ],
    "Atividade de Assistência à Saúde": [
      "acompanhamento",
      "encaminhada",
      "alta",
      "receita",
      "orientação",
      "Retorno",
      "INTERNA",
      "ALTA"
    ],
    "Organização Relacionada à Saúde": [
      "emergencia",
      "emergência",
      "ambulatório de reumatologia",
      "ambulatório da reumato",
      "posto de saúde"
    ],
    "Sinal ou Sintoma": [
      "pré-síncope",
      "irradiação",
      "dor em ardência",
      "em repouso",
      "dor torácica",
      "DUPLA LESÃO AÓRTICA",
      "INSTABILIDADE HEMODINÂMICA"
    ],
    "Negação": [
      "sem",
      "Não",
      "SEM"
    ],
    "Procedimento Diagnóstico": [
      "ECG",
      "cintilo miocárdica",
      "ECO TRANSESOFÁGICA",
      "ENDOSCOPIA DIGESTIVA ALTA"
    ],
    "Produto Intelectual": [
      "receita"
    ],
    "Substância Farmacológica": [
      "medicações",
      "hipoglicemiantes",
      "ANTICOAGULANTES",
      "OMEPRAZOL",
      "ATC"
    ],
    "Grupo Profissional ou Ocupacional": [
      "médico",
      "GASTRO"
    ],
    "Procedimento Terapêutico ou Preventivo": [
      "CIRURGIA",
      "TRANSFUSÃO",
      "ESTABILIZAÇÃO",
      "ANTICOAGULAÇÃO",
      "estratificação de risco",
      "TRATAMENTO MEDICAMENTOSO"
    ],
    "Função Patológica": [
      "MELENA"
    ],
    "Achado": [
      "ESTÁVEL"
    ],
    "Substância Química Orgânica": [
      "OMEPRAZOL"
    ],
    "Localização ou Região Corporal": [
      "região esternal direita"
    ],
    "Resultado Laboratorial ou de Teste": [
      "hemibloqueio anterior esquerdo",
      "pobre progressão da onda R em V1 e V2",
      "alterações isquêmicas agudas",
      "resultado foi normal",
      "GASTRITE ENDOSCÓPICA ANTRAL"
    ]
  },
  "labels": {
    "melena": {
      "capitulo": "22"
    },
    "gastrite endoscópica antral": {
      "capitulo": "13"
    },
    "dor em ardência": {
      "capitulo": "21"
    },
    "has": {
      "capitulo": "11"
    },
    "instabilidade hemodinâmica": {
      "capitulo": "22"
    },
    "dupla lesão aórtica": {
      "capitulo": "11"
    },
    "artrite reumatóide": {
      "capitulo": "15"
    },
    "fibrilação atrial": {
      "capitulo": "11"
    },
    "dor torácica": {
      "capitulo": "21"
    },
    "irradiação": {
      "capitulo": "21"
    },
    "doença diverticular": {
      "capitulo": "13"
    },
    "dm": {
      "capitulo": "5"
    },
    "dm 2": {
      "capitulo": "5"
    },
    "pré-síncope": {
      "capitulo": "21"
    }
  }
}