{
  "prontuario_id": 153,
  "text": "PACIENTE CARDIOPATA ISQUÊMICO COM SEVERA DISFUNÇÃO VENTRICULAR E, INTERNA COM QUADRO DE DOR EPIGÁSTRICA E IC CLASSE II - III. HISTÓRIA DE HEMORRAGIA DIGESTIVA POR UP GÁSTRICA EM VIGÊNCIA DE ACO NO MÊS DE MAIO/03. NÃO REALIZOU TTO ADEQUADO PARA UP E HP +, SENDO REALIZADA NOVA EDA DE AMB COM RETORNO AGENDADO NA GASTRO PARA VER RESULTADO E INSTITUIR NOVO TTO, SE NECESSÁRIO. IC COMPENSADA COM USO DE DIURÉTICO EV E VASODILATADORES VO. INÍCIADO OMEPRAZOL COM MELHORA DOS SÍNTOMAS GÁSTRICOS. APÓS TTO DE DÇ PÉPTICA DEVERÁ SER REINICIADA ACO NO AMB DE CARDIOLOGIA. Realizada pericardiocentese, sem complicações; retirados 650 ml de líquido pericárdico sero-hemático. # HAS HÁ 3 ANOS, # DM 2 HÁ 15 ANOS,  # CI. PCT VEM A EMERGENCIA DIA 08.10 POR ANGINA DE FORTE INTENSIDADE QUANDO CAMINHAVA PELO CORREDOR DO HOSPITAL (SEU MARIDO ESTÁ INTERNADO AQUI TRATANDO UMA ENDOCARDITE). RELATAVA EPISODIOS SEMELHANTES SO QUE DE MENOR INTENSIDADE, HÁ 15 DIAS. HOUVE ELEVAÇÃO DE MARCADORES CARDIACO E ECG REVELAVA INFRA-ST EM PAREDE ANTERO-SEPTAL. FOI MANEJADA COM SCA SSST SENDO FEITA ESTRATIFICAÇÃO NAO-INVASIVA COM CM 11.1006 QUE MOSTROU ISQUEMIA MIOCARDICA NAS PAREDES INFERO-LATERAL, ANTERO-SEPTAL E ANTERIOR DEVIDO A DILATAÇÃO ISQUEMICA TRANSITORIA, A POSSIBILIDADE DE ISQUEMIA DE TRES VASOS E/OU ISQUEMIA SUBENDOCARDICA DEVERIA SER CONSIDERADA. FOI  FEITO CAT EM 13.10 QUE MOSTROU DA COM LESÃO SEGMENTAR SEVERA PROX, 1 DG COM ATEROMATOSE SEVERA PROX, CX OCLUIDA DISTAL, 2 MG COM LESÃO SUBOCLUSIVA E CD SEM LESÕES. NO DIA SEGUINTE (14.10.06), A PCT APRESENTOU MELENA ENA EGD DE URGENCIA VERIFICOU-SE ULCERA PRE-PILORICA POREJANTE SENDO FEITA ESCLEROTERAPIA E COLOCAÇÃO DE CLIPE METÁLICO. APOS PROCEDIMENTO, PCT APRESENTOU NOVA SCA SSST COM ELEVAÇÃO DE MARCADORES CARDIACOS. O CASO FOI DISCUTIDO NA REUNIÃO DA CARDIO ENTRE A OPÇÃO PERCUTANEA (ALTO RISCO DE ESTENOSE DA ADA QUE É UMA LESÃO GRANDE) E CIRURGICA (IDEAL, MAS QUE SOFRE RESSALVAS CONSIDERANDO A IDADE DA PCT, TER DM E IRC, COM EURO SCORE DE 10 % DE MORTALIDADE). A PROF MARIA OPTOU POR ESTRATEGIA CONSERVADORA. NO DIA 19.10,0 A PCT APRESENTOU ENTERORRAGIA SENDO FEITA NOVA EGD (ULCERA CICATRIZADA) E COLONO (27/10 - DIVERTICULOS). NO DIA 28.10 APOS HIDRATAÇÃO LEVE DA COLONO A PCT TEVE QUADRO DE EAP, NECESSITANDO DE VM, VINDO PARA O ANDAR HJ (31.10). AMANHÃ IRÁ FAZER A ACTP DA ADA CONFORME COMBINADO. REALIZOU ACTP + STENT DE DAE, SEM INTERCORRENCIAS, BOM RESULTADO ANGIOGRÁFICO. SEM ANGINA OU DISPNEIA. EXAME SEM SINAIS DE ICC. NO DIA PREVISTO PARA ALTA APRESENTOU QUADRO DE FARMACODERMIA PROVAVEL PELO USO DE DIPIRONA. ALTA ADIADA PARA VER EVOLUCAO DAS LESOES TIPO URTICARIA  E RESPOSTA A MANEJO SINTOMATICA. ORIENTADA A PROCURAR MEDICO ASSISTENTE E MANTER MEDICACAO EM USO. No dia seguinte ao adiamento da alta, apresentava melhora das lesões cutâneas. Alta hospitalar em 04/11/2006.",
  "entities": {
    "Paciente ou Grupo com Deficiência": [
      "PACIENTE",
      "PCT"
    ],
    "Negação": [
      "NÃO",
      "SEM"
    ],
    "Abreviação": [
      "UP",
      "EDA",
      "GASTRO",
      "AMB",
      "HAS",
      "CI",
      "PCT",
      "ECG",
      "CAT",
      "DA",
      "CD",
      "EGD",
      "CARDIO",
      "DM",
      "IRC",
      "COLONO",
      "EAP",
      "VM",
      "ACTP",
      "ADA",
      "SEVERA DISFUNÇÃO VENTRICULAR E",
      "IC CLASSE II - III",
      "UP GÁSTRICA",
      "TTO ADEQUADO",
      "HP +",
      "DM 2",
      "SCA SSST",
      "LESÃO SEGMENTAR SEVERA PROX",
      "DG COM ATEROMATOSE SEVERA PROX",
      "ALTO RISCO DE ESTENOSE DA ADA",
      "STENT DE DAE",
      "SINAIS DE ICC"
    ],
    "Doença ou Síndrome": [
      "UP",
      "HAS",
      "DM",
      "IRC",
      "DIVERTICULOS",
      "EAP",
      "CARDIOPATA ISQUÊMICO",
      "IC CLASSE II - III",
      "UP GÁSTRICA",
      "DM 2",
      "UMA ENDOCARDITE",
      "SCA SSST",
      "ISQUEMIA DE TRES VASOS",
      "ISQUEMIA SUBENDOCARDICA",
      "ULCERA PRE-PILORICA POREJANTE",
      "ULCERA CICATRIZADA"
    ],
    "Procedimento Diagnóstico": [
      "EDA",
      "ECG",
      "CAT",
      "EGD",
      "COLONO",
      "EXAME"
    ],
    "Organização Relacionada à Saúde": [
      "GASTRO",
      "AMB",
      "EMERGENCIA",
      "CARDIO"
    ],
    "Grupo Profissional ou Ocupacional": [
      "GASTRO",
      "CARDIO",
      "MEDICO"
    ],
    "Grupo Familiar": [
      "MARIDO"
    ],
    "Procedimento Terapêutico ou Preventivo": [
      "CAT",
      "ESCLEROTERAPIA",
      "PROCEDIMENTO",
      "VM",
      "ACTP",
      "ESTRATIFICAÇÃO NAO-INVASIVA",
      "COLOCAÇÃO DE",
      "CLIPE METÁLICO",
      "OPÇÃO PERCUTANEA",
      "E CIRURGICA",
      "ESTRATEGIA CONSERVADORA",
      "HIDRATAÇÃO LEVE",
      "STENT DE DAE"
    ],
    "Parte do Corpo, Órgão ou Componente Orgânico": [
      "CD",
      "ADA",
      "PAREDES INFERO-LATERAL"
    ],
    "Função Patológica": [
      "MELENA",
      "HEMORRAGIA DIGESTIVA",
      "DILATAÇÃO ISQUEMICA TRANSITORIA"
    ],
    "Sinal ou Sintoma": [
      "MELENA",
      "ENTERORRAGIA",
      "INTERCORRENCIAS",
      "ANGINA",
      "DISPNEIA",
      "FARMACODERMIA",
      "DOR EPIGÁSTRICA",
      "ANGINA DE FORTE INTENSIDADE",
      "QUANDO CAMINHAVA",
      "EPISODIOS SEMELHANTES",
      "SINAIS DE ICC",
      "LESOES TIPO URTICARIA"
    ],
    "Atributo Clínico": [
      "IDADE"
    ],
    "Resultado Laboratorial ou de Teste": [
      "DIVERTICULOS",
      "HP +",
      "ELEVAÇÃO DE MARCADORES CARDIACO",
      "INFRA-ST EM PAREDE ANTERO-SEPTAL",
      "LESÃO SEGMENTAR SEVERA PROX",
      "DG COM ATEROMATOSE SEVERA PROX",
      "CX OCLUIDA DISTAL",
      "2 MG COM LESÃO SUBOCLUSIVA",
      "ULCERA PRE-PILORICA POREJANTE",
      "ELEVAÇÃO DE MARCADORES CARDIACOS",
      "ULCERA CICATRIZADA"
    ],
    "Atividade de Assistência à Saúde": [
      "ALTA",
      "ORIENTADA",
      "alta",
      "Alta hospitalar"
    ],
    "Substância Química Orgânica": [
      "DIPIRONA"
    ],
    "Substância Farmacológica": [
      "DIPIRONA",
      "MEDICACAO"
    ],
    "Dispositivo Médico": [
      "CLIPE METÁLICO"
    ],
    "Achado": [
      "ULCERA CICATRIZADA",
      "BOM RESULTADO ANGIOGRÁFICO",
      "melhora das lesões cutâneas"
    ]
  },
  "labels": {
    "cardiopata isquêmico": {
      "capitulo": "11"
    },
    "ulcera pre-pilorica porejante": {
      "capitulo": "13"
    },
    "hemorragia digestiva": {
      "capitulo": "13"
    },
    "dm 2": {
      "capitulo": "05"
    },
    "episodios semelhantes": {
      "capitulo": "21"
    },
    "isquemia subendocardica": {
      "capitulo": "11"
    },
    "angina de forte intensidade": {
      "capitulo": "11"
    },
    "angina": {
      "capitulo": "11"
    },
    "uma endocardite": {
      "capitulo": "11"
    },
    "dilatação isquemica transitoria": {
      "capitulo": "11"
    },
    "enterorragia": {
      "capitulo": "13"
    },
    "melena": {
      "capitulo": "13"
    },
    "dor epigástrica": {
      "capitulo": "13"
    },
    "eap": {
      "capitulo": "21"
    },
    "farmacodermia": {
      "capitulo": "14"
    },
    "lesoes tipo urticaria": {
      "capitulo": "14"
    },
    "dispneia": {
      "capitulo": "11"
    },
    "sinais de icc": {
      "capitulo": "21"
    },
    "sca ssst": {
      "capitulo": "21"
    },
    "ic classe ii - iii": {
      "capitulo": "11"
    },
    "has": {
      "capitulo": "05"
    },
    "ulcera cicatrizada": {
      "capitulo": "13"
    },
    "diverticulos": {
      "capitulo": "13"
    },
    "isquemia de tres vasos": {
      "capitulo": "11"
    },
    "dm": {
      "capitulo": "05"
    }
  }
}