{
  "prontuario_id": 472,
  "text": "Paciente apresentando nódulo com cerca de 6 cm em lobo direito da tireóide, com exame de aspiração por agulha (PAAF) sugestiva de carcinoma de células de hürthle. Submetido à tireoidectomia total em 14/06/2007. Apresentou boa evolução pós-operatória, com sinais vitais dentro da normalidade, afebril, sem intercorrências. Fonação preservada, sem sinais clínicos de hipocalcemia. Nível sérico de cálcio dentro da normalidade no controle pós-operatório. Recebe alta em bom estado geral, com boa tolerância alimentar, ferida operatória em bom aspecto. Retorna para acompanhamento ambulatorial, conforme agendamento anexo. Consulta para acompanhamento na endocrinologia, conforme consultoria realizada durante a internação, dia 17/07/2007, na sala XXXX, zona XX do ambulatório do XXXX, primeiro turno. PACIENTE COM DM, TABAGISTA PESADO, INTERNA ELETIVAMENTE PARA REALIZAÇÃO DE ACTP + STENT EM ARTÉRIA ILÍACA DIREITA. PACIENTE COM AMPUTAÇÃO SUPRACONDILIANA DE MIE HÁ 1 MÊS E APRESENTANDO ISQUEMIA CRÍTICA DISTAL EM MID. PROCEDIMENTO REALIZADO SEM INTERCORRÊNCIAS, COM SUCESSO ANGIOGRÁFICO. PACIENTE RECEBEU DOSE DE ATAQUE DE CLOPIDOGREL. RECEBE ALTA COM RECOMENDAÇÃO DE: - RETORNO BREVE AO SEU MÉDICO ASSISTENTE, - MANTER USO DE: CLOPIDOGREL 75 MG POR 30 DIAS, AAS 100 MG, SINVASTATINA 40 MG, PROCURAR A EMERGÊNCIA EM CASO DE INTERCORRÊNCIA. ",
  "entities": {
    "Paciente ou Grupo com Deficiência": [
      "Paciente",
      "PACIENTE"
    ],
    "Anormalidade Adquirida": [
      "nódulo"
    ],
    "Abreviação": [
      "PAAF",
      "DM",
      "ACTP",
      "MIE",
      "MID",
      "AAS"
    ],
    "Achado": [
      "afebril",
      "boa evolução pós-operatória",
      "sinais vitais dentro da normalidade",
      "Fonação preservada",
      "Nível sérico de cálcio dentro da normalidade",
      "bom estado geral",
      "boa tolerância alimentar",
      "bom aspecto",
      "SUCESSO ANGIOGRÁFICO"
    ],
    "Negação": [
      "afebril",
      "sem",
      "SEM"
    ],
    "Sinal ou Sintoma": [
      "intercorrências",
      "INTERCORRÊNCIAS",
      "INTERCORRÊNCIA",
      "cerca de 6 cm",
      "sinais clínicos de hipocalcemia"
    ],
    "Conceito Temporal": [
      "pós-operatório"
    ],
    "Atividade de Assistência à Saúde": [
      "alta",
      "Consulta",
      "ALTA",
      "RETORNO",
      "acompanhamento ambulatorial"
    ],
    "Doença ou Síndrome": [
      "DM",
      "TABAGISTA PESADO"
    ],
    "Procedimento Terapêutico ou Preventivo": [
      "ACTP",
      "STENT",
      "PROCEDIMENTO",
      "exame de aspiração por agulha",
      "tireoidectomia total",
      "acompanhamento na endocrinologia",
      "AMPUTAÇÃO SUPRACONDILIANA",
      "DOSE DE ATAQUE"
    ],
    "Dispositivo Médico": [
      "STENT"
    ],
    "Localização ou Região Corporal": [
      "MIE",
      "MID"
    ],
    "Substância Química Orgânica": [
      "CLOPIDOGREL",
      "AAS",
      "SINVASTATINA"
    ],
    "Substância Farmacológica": [
      "CLOPIDOGREL",
      "AAS",
      "SINVASTATINA"
    ],
    "Organização Relacionada à Saúde": [
      "EMERGÊNCIA"
    ],
    "Conceito Quantitativo": [
      "cerca de 6 cm",
      "DOSE DE ATAQUE",
      "75 MG",
      "100 MG",
      "40 MG"
    ],
    "Parte do Corpo, Órgão ou Componente Orgânico": [
      "lobo direito da tireóide",
      "ARTÉRIA ILÍACA DIREITA"
    ],
    "Processo Neoplásico": [
      "carcinoma de células de hürthle"
    ],
    "Resultado Laboratorial ou de Teste": [
      "carcinoma de células de hürthle",
      "Nível sérico de cálcio dentro da normalidade"
    ],
    "Lesão ou Envenenamento": [
      "ferida operatória"
    ],
    "Grupo Profissional ou Ocupacional": [
      "MÉDICO ASSISTENTE"
    ],
    "Conceito Qualitativo": [
      "75 MG",
      "100 MG",
      "40 MG"
    ]
  },
  "labels": {
    "sinais clínicos de hipocalcemia": {
      "capitulo": "05"
    },
    "nódulo": {
      "capitulo": "02"
    },
    "sucesso angiográfico": {
      "capitulo": "11"
    },
    "carcinoma de células de hürthle": {
      "capitulo": "02"
    },
    "ferida operatória": {
      "capitulo": "15"
    },
    "intercorrência": {
      "capitulo": "22"
    },
    "intercorrências": {
      "capitulo": "22"
    },
    "tabagista pesado": {
      "capitulo": "24"
    },
    "dm": {
      "capitulo": "05"
    }
  }
}