{
  "prontuario_id": 116,
  "text": "Paciente HAS, cardiopatia isquêmica, com CRM em 1993. Lesão em ponte de safena para CD com tentativa de ACTP sem sucesso em 08/2000, mas com ACTP + stent em segmento proximal de CD, bem como ACTP em segmentos médio e distal da CD nativa com sucesso. SCA sem supra ST em 10/2004. CAT com lesão em Cx, sendo realizado tentativa de ACTP neste vaso no dia 25/10/04, sem sucesso por dissecção. Posteriormente marcadores cardíacos revelaram IAM peri-ACTP. Nova tentativa de CATP em CX em 29/10/04, também sem sucesso. Permaneceu assintomático após as referidas tentativas, com controle da pressão e estabilidade hemodinâmica. Recebe alta com sinais vitais estáveis e com orientações de retorno ao seu médico para acompanhamento e revisão. Medicações em uso conforme receita anexa a este sumário de alta. Orientação quanto aos critérios de procurar atendimento médico de emergência. ",
  "entities": {
    "Paciente ou Grupo com Deficiência": [
      "Paciente"
    ],
    "Doença ou Síndrome": [
      "HAS",
      "cardiopatia isquêmica",
      "SCA sem supra ST"
    ],
    "Abreviação": [
      "HAS",
      "CRM",
      "ACTP",
      "CAT",
      "Cx",
      "CX",
      "tentativa de ACTP",
      "segmento proximal de CD",
      "SCA sem supra ST",
      "IAM peri-ACTP",
      "tentativa de CATP"
    ],
    "Procedimento Terapêutico ou Preventivo": [
      "CRM",
      "ACTP",
      "stent",
      "CAT",
      "tentativa de ACTP",
      "tentativa de CATP"
    ],
    "Negação": [
      "sem",
      "assintomático"
    ],
    "Achado": [
      "sucesso",
      "assintomático",
      "controle da pressão",
      "estabilidade hemodinâmica",
      "sinais vitais estáveis"
    ],
    "Dispositivo Médico": [
      "stent"
    ],
    "Conceito Espacial": [
      "distal",
      "segmentos médio"
    ],
    "Procedimento Diagnóstico": [
      "CAT"
    ],
    "Parte do Corpo, Órgão ou Componente Orgânico": [
      "Cx",
      "CX",
      "ponte de safena",
      "segmento proximal de CD"
    ],
    "Atividade de Assistência à Saúde": [
      "alta",
      "orientações",
      "retorno",
      "acompanhamento",
      "revisão",
      "receita",
      "Orientação"
    ],
    "Grupo Profissional ou Ocupacional": [
      "médico"
    ],
    "Substância Farmacológica": [
      "Medicações"
    ],
    "Produto Intelectual": [
      "receita",
      "sumário de alta"
    ],
    "Procedimento Laboratorial": [
      "marcadores cardíacos"
    ]
  },
  "labels": {
    "cardiopatia isquêmica": {
      "capitulo": "11"
    },
    "sca sem supra st": {
      "capitulo": "08"
    },
    "sucesso": {
      "capitulo": "21"
    }
  }
}