{
  "prontuario_id": 124,
  "text": "Paciente G2 C1, IG de 41 sem, TS A +, com sorologias de 1º trimestre normais, é admitida no CO por gestação prolongada. Teste rápido para HIV negativo. Solicitados exames de 3º trimestre. Induzido trabalho de parto sob monitorização cardiotocográfica. Evoluiu para Cesárea em 30/05/2007 às 15:33 hs (por condição fetal não tranquilizadora + suspeita de ruptura uterina, a qual não se confirmou no trans-operatório). RN com APGAR 8/9, FEM, 3645 G. Apresentou boa evolução puerperal, recebendo alta em boas condições gerais, com sinais vitais estáveis, mamas lactantes, útero contraído, lóquios fisiológicos, abdome inocente e cicatriz operatória com bom aspecto, sendo orientada a seguir às recomendações abaixo. Exames: - HIV: nr, - HbsAg: n, - VDRL: nr. Paciente interna para procedimento cirúrgico. Realizado sem intercorrências. Boa evolução no pós-operatório. Recebe alta em bom estado geral, com orientações, analgesia e retorno em ambulatório. PACTE INTERNA PARA INVESTIGAÇÃO DE MASSA PELVICA. TEM ECOS ANTERIORES COM MIOMA UTERINO COM CERCA DE 4 CM. APRESENTOU DOR EM BV, SANGRAMENTO VAGINAL E AUMENTO DO MIOMA. REALIZOU PANHISTERECTOMIA. ABERTURA DA PEÇA COM DEGENERAÇÃO DE MIOMA E ENDOMETRIO LIVRE. AGUARDA AP.",
  "entities": {
    "Paciente ou Grupo com Deficiência": [
      "Paciente",
      "PACTE"
    ],
    "Abreviação": [
      "G2",
      "C1",
      "IG",
      "TS",
      "CO",
      "RN",
      "FEM",
      "PACTE",
      "ECOS",
      "41 sem",
      "HIV : nr",
      "HbsAg : n",
      "VDRL : nr",
      "DOR EM BV"
    ],
    "Atributo Clínico": [
      "IG",
      "TS"
    ],
    "Atividade de Assistência à Saúde": [
      "admitida",
      "trans-operatório",
      "alta",
      "orientada",
      "recomendações",
      "interna",
      "orientações",
      "retorno",
      "INTERNA",
      "INVESTIGAÇÃO"
    ],
    "Organização Relacionada à Saúde": [
      "CO",
      "ambulatório"
    ],
    "Procedimento Terapêutico ou Preventivo": [
      "Cesárea",
      "analgesia",
      "PANHISTERECTOMIA",
      "Induzido trabalho de parto",
      "procedimento cirúrgico"
    ],
    "Negação": [
      "não",
      "sem"
    ],
    "Achado": [
      "tranquilizadora",
      "boa evolução puerperal",
      "boas condições gerais",
      "sinais vitais estáveis",
      "mamas lactantes",
      "útero contraído",
      "lóquios fisiológicos",
      "abdome inocente",
      "bom aspecto",
      "Boa evolução",
      "bom estado geral",
      "ENDOMETRIO LIVRE"
    ],
    "Conceito Temporal": [
      "trans-operatório",
      "pós-operatório",
      "ANTERIORES"
    ],
    "Grupo Populacional": [
      "RN"
    ],
    "Grupo Etário": [
      "RN"
    ],
    "Atributo de Organismo": [
      "FEM"
    ],
    "Resultado Laboratorial ou de Teste": [
      "Exames",
      "sorologias de 1º trimestre normais",
      "Teste rápido para HIV negativo",
      "HIV : nr",
      "HbsAg : n",
      "VDRL : nr",
      "MIOMA UTERINO"
    ],
    "Procedimento Laboratorial": [
      "Exames",
      "exames de 3º trimestre"
    ],
    "Sinal ou Sintoma": [
      "intercorrências",
      "ruptura uterina",
      "DOR EM BV",
      "SANGRAMENTO VAGINAL"
    ],
    "Procedimento Diagnóstico": [
      "ECOS",
      "AP",
      "exames de 3º trimestre",
      "monitorização cardiotocográfica",
      "ABERTURA DA PEÇA"
    ],
    "Função Patológica": [
      "ruptura uterina"
    ],
    "Conceito Quantitativo": [
      "3645 G"
    ]
  },
  "labels": {
    "lóquios fisiológicos": {
      "capitulo": "18"
    },
    "mamas lactantes": {
      "capitulo": "18"
    },
    "útero contraído": {
      "capitulo": "18"
    },
    "endometrio livre": {
      "capitulo": "22"
    },
    "intercorrências": {
      "capitulo": "21"
    },
    "dor em bv": {
      "capitulo": "16"
    },
    "sangramento vaginal": {
      "capitulo": "16"
    },
    "ruptura uterina": {
      "capitulo": "18"
    }
  }
}