{
  "prontuario_id": 246,
  "text": "Paciente previamente hígido procura a emergencia do XXXX por palpitações iniciadas há poucas horas. ECG com fibrilação atrial. Solicitados exames lab sem evidencia de alteração eletrolítica. Iniciado com amiodarona EV. Em cerca de 12h houve reversão para ritmo sinusal. Ecocardiograma normal. Tem alta hospitalar assintomático, em ritmo cardiaco regular, com orientação de procurar a emergencia se necessário. PACIENTE COM CARDIOPATIA ISQUEMICA, INTERNA PARA TENTATIVA DE ACTP CD - OCLUSÃO CRÔNICA. NÃO FOI POSSÍVEL ULTRAPASSAR A LESÃO C/ GUIA. RECEBE ALTA EM USO DAS MEDICAÇÕES ABAIXO E RETORNO AO SEU MÉDICO PARA SEGUIMENTO. Cardiopatia isquêmica = ACTP com stent em segmento médio da ACX em 02/04/07. Pcte internou de forma eletiva para realização do procedimento descrito acima, o qual foi realizado sem intercorrências.  Apresentou boa evolução clínica, sem complicações importantes. Tem alta em bom estado geral, sem sintomas anginosos.  RECOMENDAÇÕES: - AAS 200 mg ao dia CONTINUO, - Sinvastatina 20 mg ao dia CONTINUO, - Ticlopidina 250 mg 12/12h pelo menos por 1 mês, - Reavaliação breve com médico assistente (7 a 10 dias), - Demais medicamentos conforme médico assistente.",
  "entities": {
    "Paciente ou Grupo com Deficiência": [
      "Paciente",
      "PACIENTE",
      "Pcte"
    ],
    "Achado": [
      "hígido",
      "normal",
      "assintomático",
      "ritmo sinusal",
      "ritmo cardiaco regular",
      "boa evolução clínica",
      "bom estado geral"
    ],
    "Sinal ou Sintoma": [
      "palpitações",
      "intercorrências",
      "OCLUSÃO CRÔNICA",
      "sintomas anginosos"
    ],
    "Conceito Temporal": [
      "horas",
      "12h",
      "dia",
      "CONTINUO",
      "mês",
      "breve",
      "dias"
    ],
    "Abreviação": [
      "ECG",
      "EV",
      "12h",
      "ACTP",
      "CD",
      "Pcte",
      "AAS",
      "exames lab",
      "ACTP com stent",
      "segmento médio da ACX"
    ],
    "Procedimento Diagnóstico": [
      "ECG",
      "Ecocardiograma"
    ],
    "Negação": [
      "sem",
      "assintomático",
      "NÃO"
    ],
    "Substância Química Orgânica": [
      "amiodarona",
      "AAS",
      "Ticlopidina"
    ],
    "Procedimento Terapêutico ou Preventivo": [
      "EV",
      "ACTP",
      "ULTRAPASSAR",
      "procedimento",
      "ACTP com stent"
    ],
    "Resultado Laboratorial ou de Teste": [
      "normal",
      "fibrilação atrial",
      "alteração eletrolítica"
    ],
    "Atividade de Assistência à Saúde": [
      "orientação",
      "INTERNA",
      "ALTA",
      "RETORNO",
      "SEGUIMENTO",
      "internou",
      "alta",
      "RECOMENDAÇÕES",
      "Reavaliação",
      "alta hospitalar"
    ],
    "Parte do Corpo, Órgão ou Componente Orgânico": [
      "CD",
      "segmento médio da ACX"
    ],
    "Dispositivo Médico": [
      "GUIA"
    ],
    "Substância Farmacológica": [
      "MEDICAÇÕES",
      "AAS",
      "Sinvastatina",
      "Ticlopidina",
      "medicamentos"
    ],
    "Grupo Profissional ou Ocupacional": [
      "MÉDICO",
      "médico assistente"
    ],
    "Doença ou Síndrome": [
      "fibrilação atrial",
      "CARDIOPATIA ISQUEMICA",
      "Cardiopatia isquêmica"
    ],
    "Procedimento Laboratorial": [
      "exames lab"
    ],
    "Conceito Quantitativo": [
      "200 mg",
      "20 mg",
      "250 mg"
    ]
  },
  "labels": {
    "boa evolução clínica": {
      "capitulo": "11"
    },
    "sintomas anginosos": {
      "capitulo": "11"
    },
    "cardiopatia isquêmica": {
      "capitulo": "11"
    },
    "oclusão crônica": {
      "capitulo": "11"
    },
    "ritmo sinusal": {
      "capitulo": "21"
    },
    "cardiopatia isquemica": {
      "capitulo": "11"
    },
    "intercorrências": {
      "capitulo": "21"
    },
    "fibrilação atrial": {
      "capitulo": "11"
    },
    "palpitações": {
      "capitulo": "11"
    },
    "ritmo cardiaco regular": {
      "capitulo": "21"
    }
  }
}