{
  "prontuario_id": 142,
  "text": "INTERNA PARA ACTP + STENT DAE SEGMENTO DISTAL, SEM INTERCORRÊNCIAS E COM SUCESSO ANGIOGRÁFICO. RECEBE ALTA COM AS SEGUINTES ORIENTAÇÕES: CLOPIDOGREL 75 MG VO 1 X/D POR 30 DIAS, AAS 100 MG VO 1 X/D. MANTER DEMAIS MEDICAÇÕES DE USO PRÉVIO, REVISÃO CLÍNICA COM SEU MÉDICO EM 7-10 DIAS. PACIENTE PORTADORA DE VÁLVULA MITRAL BIOLÓGICA HÁ 3 ANOS, INTERNOU PARA INVESTIGAÇÃO DE DISPNÉIA. NÃO FORAM ENCONTRADAS QUAISQUER ALTERAÇÕES NAS FUNÇÕES PULMONAR E CARDÍACA, ALÉM DAS JÁ PREEXISTENTES. RECEBE ALTA EM BOM ESTADO GERAL E PERSISTE EM ACOMPANHAMENTO AMBULATORIAL NESTE HOSPITAL. DURANTE A INTERNAÇÃO, PASSOU A APRESENTAR LESÕES CUTÂNEAS COMPATÍVEIS E SUGESTIVAS DE ESCABIOSE, PARA QUAL INSTITUIU-SE O TRATAMENTO A SER REALIZADO EM SEU DOMICÍLIO. INVESTIGAÇÃO CARDIOLÓGICA RECENTE NÃO MOSTROU PIORA DA FUNÇÃO DA PRÓTESE, NÃO SENDO PROVÁVEL SER A DISPNÉIA ATRIBUÍVEL A ESTA CAUSA. REALIZADA ANGIOPLASTIA CORONARIANA COM IMPLANTE DE STENT EM TERÇO PROXIMAL DE ARTERIA DIAGONALIS. PROCEDIMENTO TRANSCORREU SEM INTERCORRENCIAS. PACIENTE COM SINDROME DO PANICO, EM INVESTIGAÇAO DE DOR TORACICA, REALIZOU CATETERISMO CARDÍACO, SENDO OBSERVADA LESÃO SEVERA NA EMERGÊNCIA DE GRANDE RAMO MARGINAL. REALIZADA ACTP + STENT COM SUCESSO ANGIOGRAFICO E SEM INTERCORRêNCIAS. RECEBE ALTA EM BOAS CONDIÇÕES, SEGUE ACOMPANHAMENTO NO AMBULATÓRIO - MEI. ORIENTAÇÃO PARA USAR TICLOPIDINA 250 MG 12/12 H POR 30 DIAS, AAS 100 MG/D E ATENOLOL 50 MG/D. DEMAIS A CRITÉRIO MÉDICO ASSISTENTE.",
  "entities": {
    "Procedimento Terapêutico ou Preventivo": [
      "ACTP",
      "STENT",
      "MEDICAÇÕES",
      "PROCEDIMENTO",
      "O TRATAMENTO",
      "ANGIOPLASTIA CORONARIANA COM IMPLANTE DE STENT",
      "CATETERISMO CARDÍACO"
    ],
    "Abreviação": [
      "ACTP",
      "VO",
      "AAS",
      "H",
      "DAE SEGMENTO DISTAL"
    ],
    "Dispositivo Médico": [
      "STENT"
    ],
    "Negação": [
      "SEM",
      "NÃO"
    ],
    "Sinal ou Sintoma": [
      "INTERCORRÊNCIAS",
      "DISPNÉIA",
      "INTERCORRENCIAS",
      "INTERCORRêNCIAS",
      "DOR TORACICA"
    ],
    "Atividade de Assistência à Saúde": [
      "ALTA",
      "ORIENTAÇÕES",
      "INTERNAÇÃO",
      "REVISÃO CLÍNICA",
      "ACOMPANHAMENTO AMBULATORIAL",
      "ACOMPANHAMENTO NO AMBULATÓRIO"
    ],
    "Substância Farmacológica": [
      "CLOPIDOGREL",
      "AAS",
      "MEDICAÇÕES",
      "TICLOPIDINA",
      "ATENOLOL"
    ],
    "Conceito Temporal": [
      "DIAS",
      "PRÉVIO",
      "ANOS",
      "H"
    ],
    "Substância Química Orgânica": [
      "AAS",
      "TICLOPIDINA",
      "ATENOLOL"
    ],
    "Grupo Profissional ou Ocupacional": [
      "MÉDICO",
      "MÉDICO ASSISTENTE"
    ],
    "Paciente ou Grupo com Deficiência": [
      "PACIENTE"
    ],
    "Função de Órgão ou Tecido": [
      "CARDÍACA",
      "FUNÇÕES PULMONAR"
    ],
    "Organização Relacionada à Saúde": [
      "HOSPITAL"
    ],
    "Doença ou Síndrome": [
      "ESCABIOSE",
      "SINDROME DO PANICO"
    ],
    "Parte do Corpo, Órgão ou Componente Orgânico": [
      "DAE SEGMENTO DISTAL",
      "TERÇO PROXIMAL DE ARTERIA DIAGONALIS"
    ],
    "Achado": [
      "SUCESSO ANGIOGRÁFICO",
      "BOM ESTADO GERAL",
      "SUCESSO ANGIOGRAFICO",
      "BOAS CONDIÇÕES"
    ],
    "Procedimento Diagnóstico": [
      "INVESTIGAÇÃO CARDIOLÓGICA",
      "CATETERISMO CARDÍACO"
    ]
  },
  "labels": {
    "sucesso angiográfico": {
      "capitulo": "11"
    },
    "sindrome do panico": {
      "capitulo": "06"
    },
    "dor toracica": {
      "capitulo": "12"
    },
    "dispnéia": {
      "capitulo": "11"
    },
    "intercorrências": {
      "capitulo": "22"
    },
    "sucesso angiografico": {
      "capitulo": "11"
    },
    "escabiose": {
      "capitulo": "14"
    },
    "intercorrencias": {
      "capitulo": "22"
    }
  }
}