{
  "prontuario_id": 204,
  "text": "PACIENTE COM HISTÓRIA DE HIPERTENSÃO ARTERIAL GRAVE , INICIOU COM DOR TORÁCICA COM IRRADIAÇÃO PARA DORSO E ABDÔMEN EM 12/10 , DE FORTE INTENSIDADE . RX DE TÓRAX COM ALARGAMENTO DE MEDIASTINO . TC DE TÓRAX E ABDÔMEN COM DISSECÇÃO DE AORTA DESCENDENTE A PARTIR DA EMERGÊNCIA DA SUBCLÁVIA ESQUERDA . ECO TRANSESOFÁGICO NÃO EVIDENCIOU DISSECÇÃO DE AORTA ASCENDENTE. EVOLUIU COM PERDA DE FUNÇÃO RENAL E ANÚRIA , PERDA FUNCIONAL DO MIE . AVALIADO PELA CIRURGIA VASCULAR , QUE CONTRA INDICOU CIRURGIA EM VIRTUDE DA EXTREMA GRAVIDADE DO CASO E AUSÊNCIA DE OPÇÃO TERAPÊUTIC CIRÚRGICA EM VIGÊNCIA DE COMPLICAÇÕES JÁ ESTABELECIDAS . EVOLUIU A ASSISTOLIA E ÓBITO EM 13/120 ÀS 9H35MIN .",
  "entities": {
    "Paciente ou Grupo com Deficiência": [
      "PACIENTE"
    ],
    "Localização ou Região Corporal": [
      "DORSO",
      "ABDÔMEN",
      "TÓRAX"
    ],
    "Procedimento Diagnóstico": [
      "TC",
      "RX DE TÓRAX",
      "ECO TRANSESOFÁGICO"
    ],
    "Abreviação": [
      "TC",
      "RX DE TÓRAX",
      "ECO TRANSESOFÁGICO",
      "PERDA FUNCIONAL DO MIE"
    ],
    "Negação": [
      "NÃO",
      "AUSÊNCIA"
    ],
    "Doença ou Síndrome": [
      "ASSISTOLIA",
      "HIPERTENSÃO ARTERIAL GRAVE",
      "DISSECÇÃO DE AORTA DESCENDENTE"
    ],
    "Função de Organismo": [
      "ÓBITO"
    ],
    "Sinal ou Sintoma": [
      "DOR TORÁCICA",
      "PERDA FUNCIONAL DO MIE"
    ],
    "Conceito Qualitativo": [
      "FORTE INTENSIDADE"
    ],
    "Resultado Laboratorial ou de Teste": [
      "ALARGAMENTO DE MEDIASTINO",
      "DISSECÇÃO DE AORTA DESCENDENTE",
      "PARTIR DA EMERGÊNCIA DA SUBCLÁVIA ESQUERDA",
      "EVIDENCIOU DISSECÇÃO DE AORTA ASCENDENTE"
    ],
    "Grupo Profissional ou Ocupacional": [
      "CIRURGIA VASCULAR"
    ],
    "Organização Relacionada à Saúde": [
      "CIRURGIA VASCULAR"
    ],
    "Procedimento Terapêutico ou Preventivo": [
      "TERAPÊUTIC CIRÚRGICA"
    ]
  },
  "labels": {
    "assistolia": {
      "capitulo": "22"
    },
    "dor torácica": {
      "capitulo": "11"
    },
    "hipertensão arterial grave": {
      "capitulo": "11"
    },
    "dissecção de aorta descendente": {
      "capitulo": "11"
    },
    "perda funcional do mie": {
      "capitulo": "16"
    }
  }
}