{
  "prontuario_id": 537,
  "text": "PACIENTE DE 11 ANOS COM DIAGNÓSTICO DE ADRENOLEUCODISTROFIA , COM MANIFESTAÇÃO NEUROLÓGICA , EM USO DE FLUDROCORTISONA 0,05MG /DIA E PREDNISOLONA 4,8MG /DIA + RISPERIDONA 0,75MG /DIA . ACOMPANHA COM ENDÓCRINO E COM NEURO . INICIOU HOJE AO MEIO DIA (AO ACORDAR) COM PROSTRAÇÃO E VÔMITOS . LEVADO AO PRONTO ATENDIMENTO DA ULBRA , ONDE CHEGOU COM FEBRE DE 39,5 , PERFUSÃO RUIM , TREMORES E DESIDRATAÇÃO ( HGT 120 ) . FEZ PUSH DE SF 1000ML . RX DE TÓRAX NORMAL . ENCAMINHADO AO HCPA PARA AVALIAÇÃO . MÃE NEGA CRISE CONVULSIVA . APRESENTANDO PLACAS PURULENTAS NA AMIGDALA , RECEBEU PENICILINA BENZATINA E RECEBEU ALTA COM DOSE DOBRADA DA PREDNISOLONA POR MAIS 3 DIAS E SINTOMÁTICOS ENQUANTO SINTOMAS .  ",
  "entities": {
    "Paciente ou Grupo com Deficiência": [
      "PACIENTE"
    ],
    "Doença ou Síndrome": [
      "ADRENOLEUCODISTROFIA",
      "DESIDRATAÇÃO"
    ],
    "Hormônio": [
      "FLUDROCORTISONA"
    ],
    "Substância Farmacológica": [
      "FLUDROCORTISONA",
      "PREDNISOLONA",
      "RISPERIDONA",
      "SF",
      "SINTOMÁTICOS",
      "PENICILINA BENZATINA"
    ],
    "Substância Química Orgânica": [
      "FLUDROCORTISONA",
      "PREDNISOLONA",
      "RISPERIDONA",
      "PENICILINA BENZATINA"
    ],
    "Abreviação": [
      "ENDÓCRINO",
      "NEURO",
      "HGT",
      "RX DE TÓRAX"
    ],
    "Grupo Profissional ou Ocupacional": [
      "ENDÓCRINO",
      "NEURO"
    ],
    "Sinal ou Sintoma": [
      "PROSTRAÇÃO",
      "VÔMITOS",
      "FEBRE",
      "TREMORES",
      "DESIDRATAÇÃO",
      "SINTOMAS",
      "MANIFESTAÇÃO NEUROLÓGICA",
      "PERFUSÃO RUIM",
      "CRISE CONVULSIVA",
      "PLACAS PURULENTAS"
    ],
    "Procedimento Laboratorial": [
      "HGT"
    ],
    "Resultado Laboratorial ou de Teste": [
      "120",
      "NORMAL"
    ],
    "Conceito Quantitativo": [
      "1000ML",
      "0 , 05MG",
      "4 , 8MG",
      "0 , 75MG",
      "39 , 5",
      "DOSE DOBRADA"
    ],
    "Conceito Qualitativo": [
      "1000ML"
    ],
    "Achado": [
      "NORMAL"
    ],
    "Grupo Familiar": [
      "MÃE"
    ],
    "Negação": [
      "NEGA"
    ],
    "Parte do Corpo, Órgão ou Componente Orgânico": [
      "AMIGDALA"
    ],
    "Atividade de Assistência à Saúde": [
      "ALTA"
    ],
    "Organização Relacionada à Saúde": [
      "PRONTO ATENDIMENTO"
    ],
    "Procedimento Diagnóstico": [
      "RX DE TÓRAX"
    ],
    "Antibiótico": [
      "PENICILINA BENZATINA"
    ]
  },
  "labels": {
    "febre": {
      "capitulo": "22"
    },
    "sintomas": {
      "capitulo": "21"
    },
    "adrenoleucodistrofia": {
      "capitulo": "05"
    },
    "tremores": {
      "capitulo": "08"
    },
    "desidratação": {
      "capitulo": "11"
    },
    "prostração": {
      "capitulo": "06"
    },
    "manifestação neurológica": {
      "capitulo": "08"
    },
    "vômitos": {
      "capitulo": "13"
    },
    "placas purulentas": {
      "capitulo": "14"
    },
    "crise convulsiva": {
      "capitulo": "06"
    },
    "perfusão ruim": {
      "capitulo": "22"
    }
  }
}