{
  "prontuario_id": 702,
  "text": "PACIENTE COM HAS , COM DM , CRM PRÁVIA , COM ANGIOPLASTIA COM STENT EM PONTE DE SAFENA SEQUENCIAL PARA CX E CD EM NOVEMBRO DE 2005 , COM NECESSIDADE DE ANGIOPLASTIA INTRA STENT POR ANGINA EM JUNHO DE 2006 . RETORNA PARA NOVO CATETERISMO DIAGNÓSTICO POR ANGINA DE CARÁTER PROGRESSIVO , COM DOR AO REPOUSO NOS DIAS PRECEDENTES AO EXAME . DURANTE O PROCEDIMENTO , DOR PRECORDIAL IMPORTANTE , COM NECESSIDADE DE NTG EV PARA CONTROLE DA DOR . REALIZADA ENTÃO NOVAMENTE ANGIOPLASTIA INTRA STENT , COM MELHORA CLÍNICA . SEM ALTERAÇÕES ELETROCARDIOGRÁFICAS SUGESTIVAS DE ISQUEMIA AGUDA .  RECEBE ALTA EM BOM ESTADO GERAL , OM ORIENTAÇÃO DE MANTER MEDICAÇÕES EM USO PRÉVIO E MANTER ACOMPANHAMENTO COM SEU MÉDICO ASSISTENTE .",
  "entities": {
    "Paciente ou Grupo com Deficiência": [
      "PACIENTE"
    ],
    "Abreviação": [
      "HAS",
      "DM",
      "CRM",
      "CX",
      "CD"
    ],
    "Doença ou Síndrome": [
      "HAS",
      "DM",
      "ANGINA",
      "ALTERAÇÕES ELETROCARDIOGRÁFICAS SUGESTIVAS DE ISQUEMIA AGUDA"
    ],
    "Procedimento Terapêutico ou Preventivo": [
      "CRM",
      "PROCEDIMENTO",
      "ANGIOPLASTIA INTRA STENT",
      "CONTROLE DA DOR"
    ],
    "Conceito Temporal": [
      "PRÁVIA",
      "DURANTE",
      "DIAS PRECEDENTES",
      "USO PRÉVIO"
    ],
    "Dispositivo Médico": [
      "STENT"
    ],
    "Conceito Qualitativo": [
      "SEQUENCIAL"
    ],
    "Parte do Corpo, Órgão ou Componente Orgânico": [
      "CX",
      "CD",
      "PONTE DE SAFENA"
    ],
    "Sinal ou Sintoma": [
      "ANGINA",
      "ANGINA DE CARÁTER PROGRESSIVO",
      "DOR AO REPOUSO",
      "DOR PRECORDIAL IMPORTANTE",
      "ALTERAÇÕES ELETROCARDIOGRÁFICAS SUGESTIVAS DE ISQUEMIA AGUDA"
    ],
    "Atividade de Assistência à Saúde": [
      "RETORNA",
      "ALTA",
      "ORIENTAÇÃO",
      "MANTER ACOMPANHAMENTO"
    ],
    "Procedimento Diagnóstico": [
      "EXAME",
      "PROCEDIMENTO",
      "CATETERISMO DIAGNÓSTICO"
    ],
    "Substância Farmacológica": [
      "NTG",
      "MEDICAÇÕES"
    ],
    "Substância Química Orgânica": [
      "NTG"
    ],
    "Conceito Funcional": [
      "EV"
    ],
    "Negação": [
      "SEM"
    ],
    "Achado": [
      "MELHORA CLÍNICA",
      "ALTERAÇÕES ELETROCARDIOGRÁFICAS SUGESTIVAS DE ISQUEMIA AGUDA",
      "BOM ESTADO GERAL"
    ],
    "Grupo Profissional ou Ocupacional": [
      "MÉDICO ASSISTENTE"
    ]
  },
  "labels": {
    "has": {
      "capitulo": "11"
    },
    "angina de caráter progressivo": {
      "capitulo": "11"
    },
    "dor ao repouso": {
      "capitulo": "21"
    },
    "melhora clínica": {
      "capitulo": "21"
    },
    "dor precordial importante": {
      "capitulo": "21"
    },
    "angina": {
      "capitulo": "11"
    },
    "dm": {
      "capitulo": "05"
    },
    "alterações eletrocardiográficas sugestivas de isquemia aguda": {
      "capitulo": "21"
    }
  }
}