{
  "prontuario_id": 970,
  "text": "DERMATOLOGIA\n\n1° Consulta\n\nQP : alteração ungueal mão direita\n\nS) Refere há 1 ano iniciou com dor , eritema e edema em periungueal em  4° dedo e que após hoje crescimento da unha com distrofia . Refere que há cerca de 9 meses houve inicio do mesmo quadro em 2° dedo mão direita .\n\nRelata mancha hipercrômica em dorso nasal há cerca de 8 meses, assintomatica .\n\nHMP : Refere uso de fluoxetina devido depressão\nUso de ACO\nNega hx de ca de pele pessoal ou familiar\n\nO)  edema e eritema peringueal em 2° e 4° quirodáctilos da mão direita\nonicodistrofia em 2° e 4° quirodáctilos mão direita\nmancha hipercrômica em dorso nasal \n\nA) Liquen plano ungueal ? Psoriase ungueal ? Onicomicose ?\nMelanose solar ? Melasma ?\n\nP) Solicito deixar as unhas crescerem para realizar clipping ungueal no retorno\nPrescrevo hormoskin 1 x à noite até o retorno\nRetorno em 22/09/15 tarde\n\nR1 Beatriz\nDoutor Vital Brazil ",
  "entities": {
    "Organização Relacionada à Saúde": [
      "DERMATOLOGIA"
    ],
    "Atividade de Assistência à Saúde": [
      "Consulta",
      "O",
      "retorno",
      "Prescrevo",
      "Retorno"
    ],
    "Abreviação": [
      "QP",
      "S",
      "HMP",
      "ACO",
      "O",
      "A",
      "P",
      "R1",
      "ca de pele"
    ],
    "Achado": [
      "S",
      "assintomatica",
      "HMP"
    ],
    "Sinal ou Sintoma": [
      "eritema",
      "edema",
      "alteração ungueal",
      "iniciou com dor",
      "mesmo quadro",
      "mancha hipercrômica"
    ],
    "Localização ou Região Corporal": [
      "periungueal",
      "peringueal",
      "dorso nasal"
    ],
    "Negação": [
      "assintomatica",
      "Nega"
    ],
    "Substância Química Orgânica": [
      "fluoxetina"
    ],
    "Substância Farmacológica": [
      "fluoxetina",
      "ACO"
    ],
    "Doença ou Síndrome": [
      "depressão",
      "onicodistrofia",
      "Onicomicose",
      "Melasma",
      "unha com distrofia",
      "Liquen plano ungueal",
      "Psoriase ungueal",
      "Melanose solar"
    ],
    "Procedimento Diagnóstico": [
      "A",
      "clipping ungueal"
    ],
    "Produto Intelectual": [
      "P"
    ],
    "Medicamento Clínico": [
      "hormoskin"
    ],
    "Grupo Profissional ou Ocupacional": [
      "R1"
    ],
    "Parte do Corpo, Órgão ou Componente Orgânico": [
      "mão direita",
      "4° dedo",
      "2° dedo mão direita",
      "2° e 4° quirodáctilos da mão direita",
      "2° e 4° quirodáctilos mão direita"
    ],
    "Conceito Temporal": [
      "após hoje"
    ],
    "Conceito Funcional": [
      "uso de",
      "Uso de"
    ],
    "Processo Neoplásico": [
      "ca de pele"
    ],
    "Função Fisiológica": [
      "unhas crescerem"
    ]
  },
  "labels": {
    "liquen plano ungueal": {
      "capitulo": "14"
    },
    "unha com distrofia": {
      "capitulo": "14"
    },
    "alteração ungueal": {
      "capitulo": "14"
    },
    "edema": {
      "capitulo": "21"
    },
    "melasma": {
      "capitulo": "14"
    },
    "eritema": {
      "capitulo": "14"
    },
    "psoriase ungueal": {
      "capitulo": "14"
    },
    "onicodistrofia": {
      "capitulo": "14"
    },
    "ca de pele": {
      "capitulo": "14"
    },
    "melanose solar": {
      "capitulo": "14"
    },
    "onicomicose": {
      "capitulo": "14"
    },
    "depressão": {
      "capitulo": "06"
    },
    "mancha hipercrômica": {
      "capitulo": "14"
    }
  }
}