{
  "prontuario_id": 467,
  "text": "PACEINTE RETORNA PARA REAVLIAÇÃO DEVIDO A SUSPITA DE GLAUCOMA\n\nDM HA 2 ANOS EM USO DE INSULINA ( DESCONTROLADA - SIC)\nHAS TRATADA\nNEGA CX E TRAUMA OCULARES\nNEGA HISTÓRICO FAMILIAR DE GLAUCOMA OU CEGUEIRA\n\n#EXAME FISICO\n\nAVSC\n20/20P\n20/25P\n\nBIO\nAO : PT NASAL GRAU 1 , PUPILAS ISO/FOTORREAGENTES , CA CALMA , CORNEA CLARA E TRANSPARENTE\n\nPIO\n14/13\n\nFO\nOD ESCAVAÇAO 0,5-0,6, ESCAVAÇÃO PROFUNDA, DO MÉDIO , CAMADA DE FIBRAS NERVOSAS NROMAL\nOD ESCAVAÇAO 0,5-0,6, ESCAVAÇÃO PROFUNDA, DO MÉDIO , CAMADA DE FIBRAS NERVOSAS NROMAL\n\n#AF (03/02/15):\nAO DO RÓSEO COM AUMENTO DA ESCAVAÇÃO , SEM ALTERAÇÕES NO DECORRER DO EXAME . ÁREA DE ATROFIA/HIPERTROFIA DE EPR ( CICATRIZ PIGMETARES CORIORRETINIANAS ) ESPARSAS NO POLO POSTERIOR . MÁCULA E VASOS RETINIANOS SEM ALTERAÇÕES . QUADRO SUGESTIVO DE COROIDITE MULTIFOCAL , INATIVA NO MOMENTO .\n-SUGERIDO ACOMPANHAMENTO SEMESTRAL\n\n# TRIAGEM GLAUCOMA :\n\nPAQUI (13/03/15:\n554\n550\n\nCV (18/03/15)\nOD CONFIABILIDADE BOA , LIMIAR FOVEAL 37 , GHT NORMAL , MD 2,24 , PSD 1,17\nOE CONFIABILIDADE BOA , LIMIAR FOVEAL 34 , GHT ALTERADO , ESCOTOMAS RELATIVSO PERIFÉRICO , MD -1,81\n\n# CONDUTA\nMANTENHO PACIENTE SEM COLÍRIOS\nPRESCREVO LUBRIFICANTE OCULAR\nSOLICITO NOVO CAMPO VISUAL E AGENDO RETORNO EM 6 MESES\nORIENTO PACIENTE A DIRIGIR-SE AO HUC CASO APRESENTE QUALQUER ALTERAÇÃO AGUDA DA SAÚDE OCULAR\n\n\nR2 Vital Brazil\nDoutor Vital Brazil .\n \n \n \n ",
  "entities": {
    "Paciente ou Grupo com Deficiência": [
      "PACEINTE",
      "PACIENTE"
    ],
    "Atividade de Assistência à Saúde": [
      "REAVLIAÇÃO",
      "CONDUTA",
      "MANTENHO",
      "PRESCREVO",
      "SOLICITO",
      "ORIENTO",
      "EXAME FISICO",
      "ACOMPANHAMENTO SEMESTRAL",
      "AGENDO RETORNO"
    ],
    "Doença ou Síndrome": [
      "GLAUCOMA",
      "DM",
      "HAS TRATADA",
      "PT NASAL GRAU 1",
      "ESCAVAÇAO 0 , 5-0 , 6",
      "ESCAVAÇÃO PROFUNDA , DO MÉDIO",
      "COROIDITE MULTIFOCAL"
    ],
    "Abreviação": [
      "DM",
      "SIC",
      "CX",
      "AVSC",
      "BIO",
      "AO",
      "ISO/FOTORREAGENTES",
      "PIO",
      "FO",
      "OD",
      "AF",
      "EPR",
      "PAQUI",
      "CV",
      "MD",
      "PSD",
      "OE",
      "R2",
      "HAS TRATADA",
      "PT NASAL GRAU 1",
      "CA CALMA"
    ],
    "Substância Farmacológica": [
      "INSULINA",
      "COLÍRIOS",
      "LUBRIFICANTE OCULAR"
    ],
    "Aminoácido, Peptídeo ou Proteína": [
      "INSULINA"
    ],
    "Hormônio": [
      "INSULINA"
    ],
    "Achado": [
      "DESCONTROLADA",
      "CEGUEIRA",
      "ISO/FOTORREAGENTES",
      "CA CALMA",
      "CONFIABILIDADE BOA",
      "ESCOTOMAS RELATIVSO PERIFÉRICO"
    ],
    "Conceito Qualitativo": [
      "DESCONTROLADA",
      "ESPARSAS",
      "INATIVA"
    ],
    "Negação": [
      "NEGA",
      "SEM"
    ],
    "Procedimento Terapêutico ou Preventivo": [
      "CX",
      "ACOMPANHAMENTO SEMESTRAL"
    ],
    "Atributo Clínico": [
      "AVSC",
      "PIO",
      "GHT",
      "MD",
      "PSD",
      "LIMIAR FOVEAL"
    ],
    "Conceito Quantitativo": [
      "20/20P",
      "20/25P",
      "14/13",
      "37",
      "34",
      "2 , 24",
      "1 , 17",
      "-1 , 81"
    ],
    "Parte do Corpo, Órgão ou Componente Orgânico": [
      "AO",
      "PUPILAS",
      "CORNEA",
      "FO",
      "OD",
      "EPR",
      "MÁCULA",
      "OE",
      "VASOS RETINIANOS"
    ],
    "Resultado Laboratorial ou de Teste": [
      "14/13",
      "NORMAL",
      "ALTERADO",
      "ESCAVAÇAO 0 , 5-0 , 6",
      "ESCAVAÇÃO PROFUNDA , DO MÉDIO",
      "CAMADA DE FIBRAS NERVOSAS NROMAL",
      "AUMENTO DA ESCAVAÇÃO",
      "ALTERAÇÕES NO DECORRER DO EXAME"
    ],
    "Procedimento Diagnóstico": [
      "AF",
      "PAQUI",
      "EXAME FISICO",
      "TRIAGEM GLAUCOMA",
      "CAMPO VISUAL"
    ],
    "Conceito Espacial": [
      "ESPARSAS"
    ],
    "Sinal ou Sintoma": [
      "ALTERAÇÕES",
      "ALTERAÇÕES NO DECORRER DO EXAME",
      "ALTERAÇÃO AGUDA DA SAÚDE OCULAR"
    ],
    "Produto Intelectual": [
      "CONDUTA"
    ],
    "Grupo Profissional ou Ocupacional": [
      "R2"
    ],
    "Lesão ou Envenenamento": [
      "TRAUMA OCULARES"
    ],
    "Localização ou Região Corporal": [
      "ÁREA DE ATROFIA/HIPERTROFIA",
      "POLO POSTERIOR"
    ],
    "Anormalidade Anatômica": [
      "CICATRIZ PIGMETARES CORIORRETINIANAS"
    ]
  },
  "labels": {
    "alterações": {
      "capitulo": "09"
    },
    "cicatriz pigmetares coriorretinianas": {
      "capitulo": "09"
    },
    "escavaçao 0 , 5-0 , 6": {
      "capitulo": "09"
    },
    "descontrolada": {
      "capitulo": "05"
    },
    "trauma oculares": {
      "capitulo": "09"
    },
    "coroidite multifocal": {
      "capitulo": "09"
    },
    "alteração aguda da saúde ocular": {
      "capitulo": "21"
    },
    "cegueira": {
      "capitulo": "09"
    },
    "alterações no decorrer do exame": {
      "capitulo": "21"
    },
    "escotomas relativso periférico": {
      "capitulo": "09"
    },
    "escavação profunda , do médio": {
      "capitulo": "09"
    },
    "dm": {
      "capitulo": "05"
    },
    "glaucoma": {
      "capitulo": "09"
    }
  }
}