{
  "prontuario_id": 665,
  "text": "PACIENTE , 21 ANOS\n\nFOLICULITE QUELOIDEANA\nACNE GRAU III\nSD DOWN\n\nUSO DE: TRIANCIL + FRADEMICINA ( 0,75 / 0,25 )\nJÁ USOU ISOTRETINOÍNA , SUSPENSA POR AUMENTO DE TRIGLICERÍDEOS\n\nMÃE ACHA QUE O PACIENTE ESTÁ APRESENTANDO MELHORA EM COURO CABELUDO . PERSISTE COM ACNE NA FACE .\nNÃO FEZ USO DA TETRACICLINA PRESCRITA NA CONSULTA ANTERIOR .\n\nEF : PLACA ERITEMATOSA, CICATRICIAL , COM ÁREAS DE POLITRIQUIA E PÚSTULAS .\nPÁPULAS ERITEMATOSAS EM MENTO .\n\nTRAZ EXAMES LAB : COLEST T : 169 ;  TRIGL: 124 ; LDL: 103 ; HDL: 41\n\nCD: MANTENHO INFILTRAÇÃO COM TRIANCIL E FRADEMICINA\nTETRACICLINA 1G  /DIA 30 DIAS E 500 MG  /DIA POR 30 DIAS\nCLINDOXYL CONTROL\nORIENTO A MÂE\nRETORNO 2 MESES\n \n \n \n ",
  "entities": {
    "Paciente ou Grupo com Deficiência": [
      "PACIENTE"
    ],
    "Medicamento Clínico": [
      "TRIANCIL",
      "FRADEMICINA"
    ],
    "Substância Farmacológica": [
      "TRIANCIL",
      "FRADEMICINA",
      "ISOTRETINOÍNA",
      "TETRACICLINA",
      "CLINDOXYL"
    ],
    "Substância Química Orgânica": [
      "ISOTRETINOÍNA",
      "TETRACICLINA"
    ],
    "Atividade de Assistência à Saúde": [
      "SUSPENSA",
      "PRESCRITA",
      "CONSULTA",
      "EF",
      "CD",
      "MANTENHO",
      "ORIENTO",
      "RETORNO"
    ],
    "Grupo Familiar": [
      "MÃE",
      "MÂE"
    ],
    "Sinal ou Sintoma": [
      "ACNE",
      "PÚSTULAS",
      "AUMENTO DE TRIGLICERÍDEOS",
      "PLACA ERITEMATOSA",
      "ÁREAS DE POLITRIQUIA",
      "PÁPULAS ERITEMATOSAS"
    ],
    "Localização ou Região Corporal": [
      "FACE",
      "MENTO"
    ],
    "Negação": [
      "NÃO"
    ],
    "Antibiótico": [
      "TETRACICLINA"
    ],
    "Abreviação": [
      "EF",
      "TRIGL",
      "LDL",
      "HDL",
      "SD DOWN",
      "EXAMES LAB",
      "COLEST T"
    ],
    "Achado": [
      "CICATRICIAL",
      "MELHORA EM COURO CABELUDO",
      "PÁPULAS ERITEMATOSAS"
    ],
    "Conceito Quantitativo": [
      "169",
      "124",
      "103",
      "41",
      "1G",
      "0 , 75 / 0 , 25",
      "500 MG"
    ],
    "Atributo Clínico": [
      "TRIGL",
      "LDL",
      "HDL",
      "COLEST T"
    ],
    "Procedimento Laboratorial": [
      "TRIGL",
      "LDL",
      "HDL",
      "EXAMES LAB",
      "COLEST T"
    ],
    "Produto Intelectual": [
      "CD"
    ],
    "Procedimento Terapêutico ou Preventivo": [
      "INFILTRAÇÃO"
    ],
    "Doença ou Síndrome": [
      "FOLICULITE QUELOIDEANA",
      "ACNE GRAU III",
      "SD DOWN"
    ],
    "Resultado Laboratorial ou de Teste": [
      "AUMENTO DE TRIGLICERÍDEOS"
    ],
    "Parte do Corpo, Órgão ou Componente Orgânico": [
      "MELHORA EM COURO CABELUDO"
    ],
    "Conceito Temporal": [
      "30 DIAS"
    ]
  },
  "labels": {
    "placa eritematosa": {
      "capitulo": "14"
    },
    "pápulas eritematosas": {
      "capitulo": "14"
    },
    "pústulas": {
      "capitulo": "14"
    },
    "acne": {
      "capitulo": "14"
    },
    "áreas de politriquia": {
      "capitulo": "14"
    },
    "acne grau iii": {
      "capitulo": "14"
    },
    "foliculite queloideana": {
      "capitulo": "14"
    },
    "aumento de triglicerídeos": {
      "capitulo": "05"
    },
    "sd down": {
      "capitulo": "20"
    }
  }
}