{
  "prontuario_id": 810,
  "text": "primeira consulta ; encaminhada pelo ambu cardio ( Doutor Vital Brazil )\n\npaciente , 67 anos , casada , 4 filhos , trabalhava em restaurante , aposentada ha 7 anos , natural de ibaiti PR , procedente de curitiba .\n\nPaciente refere dispepsia após o almoço ha 4 anos , com sensação de estufamento ( chega a desabotoar a calça ) , sem relação com ooconteudo ingerido , acompanhado de sufocamento , dor em queimação em epigastrio , e sensação de refluxo e nausea . \nRefere disfagia a solidos - ela associa a tireoidite . Nega associacao de vomitos e diarreia .\nRefere mudança no hábito intestinal  era constipada , agora vai 1x/dia .\nNega despertarnoturno com sintomas . \nInicio de sintomas proximos ao evento de falecimento da irma  r3efere ser muito nervosa e ansiosa\n\nEXAME COMPLEMENTAR :\nEDA de 22/03/2014\ndx: hérnia hiatal de pequeno volume , gastrite enantematosa antral discreta , duodenite enantematosa, teste de urease \nDoença Dispéptica\nDRGE\nca de intestino - irma\nca osseo- pai\nca estomago-vó\nIC , tratada com \nLosartana 50 mg\nCarvedilol 25 mg\nApresolina 50mg\nFurosemida 40mg\nOmeprazol 20mg\nMonocordil 20 mg\n\nHipotireoidismo tratado com \nlevotiroxina 100mcg\n\nAsma , tratada com \nAlenia  ( formoterol + budesonida )\n\nVarizes tratadas com \nDiosmin ( 1 envelope )\n\nPaciente foi submetida a colocação de Marca Passo\nPaciente faz uso de Sulfato Ferroso , devido a presença de Sangue nao visivel nas fezes\n ",
  "entities": {
    "Conceito Temporal": [
      "primeira",
      "1x/dia",
      "Inicio",
      "após o almoço"
    ],
    "Atividade de Assistência à Saúde": [
      "consulta",
      "encaminhada",
      "EXAME COMPLEMENTAR"
    ],
    "Paciente ou Grupo com Deficiência": [
      "paciente",
      "Paciente"
    ],
    "Achado": [
      "casada",
      "aposentada",
      "nervosa",
      "ansiosa",
      "relação com ooconteudo ingerido",
      "mudança no hábito intestinal",
      "falecimento da irma"
    ],
    "Grupo Familiar": [
      "filhos",
      "irma",
      "pai"
    ],
    "Grupo Profissional ou Ocupacional": [
      "aposentada"
    ],
    "Negação": [
      "sem",
      "Nega"
    ],
    "Localização ou Região Corporal": [
      "epigastrio"
    ],
    "Sinal ou Sintoma": [
      "nausea",
      "vomitos",
      "diarreia",
      "constipada",
      "ansiosa",
      "sensação de estufamento",
      "relação com ooconteudo ingerido",
      "dor em queimação",
      "sensação de refluxo",
      "disfagia a solidos"
    ],
    "Doença ou Síndrome": [
      "tireoidite",
      "DRGE",
      "IC",
      "Hipotireoidismo",
      "Asma",
      "Varizes",
      "gastrite enantematosa antral discreta",
      "duodenite enantematosa",
      "Doença Dispéptica"
    ],
    "Disfunção Mental ou Comportamental": [
      "despertarnoturno"
    ],
    "Abreviação": [
      "EDA",
      "DRGE",
      "IC",
      "ambu cardio",
      "ca de intestino",
      "ca osseo-",
      "ca estomago-vó",
      "50 mg",
      "25 mg"
    ],
    "Procedimento Diagnóstico": [
      "EDA",
      "teste de urease"
    ],
    "Resultado Laboratorial ou de Teste": [
      "dx",
      "hérnia hiatal de pequeno volume",
      "gastrite enantematosa antral discreta",
      "duodenite enantematosa",
      "teste de urease",
      "Doença Dispéptica",
      "Sangue nao visivel nas fezes"
    ],
    "Procedimento Terapêutico ou Preventivo": [
      "tratada",
      "colocação de Marca Passo"
    ],
    "Substância Química Inorgânica": [
      "Losartana",
      "Sulfato Ferroso"
    ],
    "Substância Farmacológica": [
      "Losartana",
      "Carvedilol",
      "Apresolina",
      "Furosemida",
      "Omeprazol",
      "Monocordil",
      "Alenia",
      "formoterol",
      "budesonida",
      "Diosmin",
      "Sulfato Ferroso"
    ],
    "Substância Química Orgânica": [
      "Carvedilol",
      "Furosemida",
      "Omeprazol",
      "Diosmin"
    ],
    "Medicamento Clínico": [
      "Apresolina",
      "Monocordil",
      "Alenia"
    ],
    "Conceito Quantitativo": [
      "50mg",
      "40mg",
      "20mg",
      "100mcg",
      "50 mg",
      "25 mg",
      "20 mg"
    ],
    "Organização Relacionada à Saúde": [
      "ambu cardio"
    ],
    "Atividade Ocupacional": [
      "trabalhava em restaurante"
    ],
    "Comportamento Individual": [
      "desabotoar a calça"
    ],
    "Anormalidade Anatômica": [
      "hérnia hiatal de pequeno volume"
    ],
    "Conceito Qualitativo": [
      "hérnia hiatal de pequeno volume"
    ],
    "Processo Neoplásico": [
      "ca de intestino",
      "ca osseo-",
      "ca estomago-vó"
    ]
  },
  "labels": {
    "despertarnoturno": {
      "capitulo": "07"
    },
    "falecimento da irma": {
      "capitulo": "24"
    },
    "sensação de estufamento": {
      "capitulo": "13"
    },
    "disfagia a solidos": {
      "capitulo": "13"
    },
    "ansiosa": {
      "capitulo": "06"
    },
    "ic": {
      "capitulo": "13"
    },
    "hipotireoidismo": {
      "capitulo": "05"
    },
    "dor em queimação": {
      "capitulo": "13"
    },
    "drge": {
      "capitulo": "13"
    },
    "nervosa": {
      "capitulo": "06"
    },
    "ca de intestino": {
      "capitulo": "24"
    },
    "mudança no hábito intestinal": {
      "capitulo": "13"
    },
    "vomitos": {
      "capitulo": "13"
    },
    "hérnia hiatal de pequeno volume": {
      "capitulo": "13"
    },
    "asma": {
      "capitulo": "12"
    },
    "doença dispéptica": {
      "capitulo": "13"
    },
    "ca osseo-": {
      "capitulo": "24"
    },
    "tireoidite": {
      "capitulo": "05"
    },
    "nausea": {
      "capitulo": "13"
    },
    "varizes": {
      "capitulo": "14"
    },
    "duodenite enantematosa": {
      "capitulo": "13"
    },
    "sensação de refluxo": {
      "capitulo": "13"
    },
    "diarreia": {
      "capitulo": "13"
    },
    "ca estomago-vó": {
      "capitulo": "24"
    }
  }
}