{
  "prontuario_id": 442,
  "text": "LUCAS, MASC, 57 ANOS.  DOR EM DORSO E FLANCO D, COM IRRADIACAO EM FAIXA EPIGASTRICA, HA DOIS DIAS. DOR EM APERTO, DE MEDIA A FORTE INTENSIDADE, ITERMITENTE NAO ASSOCIADA A MEDICACAO. NEGA DISURIA, HEMATURIA. NÃO CONSEGUE URINAR TUDO O QUE PRECISA. URINA EM MEDIA 5 X/DIA E 3 X/NOITE.  COMORBIDADES - DM2 HA 24 ANOS - HAS HA 12 ANOS - DOENCA VASC PERIFERICA - VARIZES EM MMII - DISLIPIDEMIA - TB, PNEUMONIA - PLEURITE - OBESIDADE - SEDENTARIO - HPB EM TTO - HEMORROIDAS - IMPOTENCIA SEXUAL HA 8 ANOS - RETINOPATIA DIABETICA - NEFROPATIA DIABETICA.  HMP - EX-TABAGISTA HA 12 ANOS - HERNIA INGUINAL OPERADA - INTERNADO PELA ULTIMA VEZ HA 3 ANOS POR PNEUMONIA.  MEDICAMENTOS - INSULINA NHP 40U DE MANHA E 20U HA NOITE / ANLODIPINO 25 12/12H / AAS 100MG / SINVASTATINA 20MG.  EXAMES LAB 7/6/13 - RELACAO ALBUMINA-CREATININA URINARIA 1405 / VOLUME DE URINA EM 24H 2550 / MICROALBUMINURIA 3766,1 / UR 66 / DIPSTICK: DENSIDADE 1020, LEU +, PROT +++, GLI ++++ / HB 15,5 / HT 44,7 / LEU 12.490 / HBA1C 12,36 / K 4,6 / NA 145 / PU - PROT 100, GLI +++ / CR 2,6 / UR 66 / CKD-EPI 37.  EXAME FISICO - PA 167/96 - FC 60 - EDEMA MMII ++/4 - PESO 102 - ALTURA 1,72 - IMC 34,5 - HEMORROIDAS.  CONDUTA: ENALAPRIL 10MG 12/12  - AUMENTAMOS A NHP DA MANHA PARA 50U E 30U A NOITE,",
  "entities": {
    "Abreviação": [
      "MASC",
      "DM2",
      "HAS",
      "MMII",
      "TB",
      "HPB",
      "TTO",
      "AAS",
      "PA",
      "FC",
      "FLANCO D",
      "DOENCA VASC PERIFERICA",
      "UR 66",
      "LEU +",
      "PROT +++",
      "GLI ++++",
      "HB 15 , 5",
      "HT 44 , 7",
      "LEU 12",
      "HBA1C 12 , 36",
      "K 4 , 6",
      "NA 145",
      "PROT 100",
      "GLI +++",
      "CR 2 , 6",
      "CKD-EPI 37"
    ],
    "Sinal ou Sintoma": [
      "DOR",
      "DISURIA",
      "HEMATURIA",
      "IRRADIACAO EM FAIXA EPIGASTRICA",
      "DOR EM APERTO"
    ],
    "Localização ou Região Corporal": [
      "DORSO",
      "MMII",
      "FLANCO D"
    ],
    "Negação": [
      "NAO",
      "NEGA",
      "NÃO"
    ],
    "Doença ou Síndrome": [
      "DM2",
      "HAS",
      "DISLIPIDEMIA",
      "TB",
      "PNEUMONIA",
      "PLEURITE",
      "OBESIDADE",
      "HPB",
      "HEMORROIDAS",
      "DOENCA VASC PERIFERICA",
      "IMPOTENCIA SEXUAL",
      "RETINOPATIA DIABETICA",
      "NEFROPATIA DIABETICA"
    ],
    "Achado": [
      "EX-TABAGISTA",
      "ASSOCIADA A MEDICACAO",
      "CONSEGUE URINAR",
      "HERNIA INGUINAL OPERADA"
    ],
    "Atividade de Assistência à Saúde": [
      "INTERNADO"
    ],
    "Substância Farmacológica": [
      "ANLODIPINO",
      "SINVASTATINA",
      "ENALAPRIL",
      "INSULINA NHP"
    ],
    "Conceito Quantitativo": [
      "25",
      "100MG",
      "20MG",
      "167/96",
      "60",
      "102",
      "5 X/DIA",
      "3 X/NOITE",
      "1 , 72"
    ],
    "Atributo Clínico": [
      "PA",
      "FC"
    ],
    "Conceito Qualitativo": [
      "DE MEDIA A FORTE INTENSIDADE"
    ],
    "Aminoácido, Peptídeo ou Proteína": [
      "INSULINA NHP"
    ],
    "Hormônio": [
      "INSULINA NHP"
    ],
    "Resultado Laboratorial ou de Teste": [
      "ALBUMINA-CREATININA URINARIA 1405",
      "VOLUME DE URINA EM 24H 2550",
      "MICROALBUMINURIA 3766",
      "UR 66",
      "DENSIDADE 1020",
      "LEU +",
      "PROT +++",
      "GLI ++++",
      "HB 15 , 5",
      "HT 44 , 7",
      "LEU 12",
      "HBA1C 12 , 36",
      "K 4 , 6",
      "NA 145",
      "PROT 100",
      "GLI +++",
      "CR 2 , 6",
      "CKD-EPI 37",
      "IMC 34 , 5"
    ],
    "Procedimento Diagnóstico": [
      "EXAME FISICO"
    ]
  },
  "labels": {
    "tb": {
      "capitulo": "01"
    },
    "ex-tabagista": {
      "capitulo": "24"
    },
    "doenca vasc periferica": {
      "capitulo": "11"
    },
    "hemorroidas": {
      "capitulo": "14"
    },
    "dor em aperto": {
      "capitulo": "21"
    },
    "impotencia sexual": {
      "capitulo": "17"
    },
    "dm2": {
      "capitulo": "05"
    },
    "nefropatia diabetica": {
      "capitulo": "16"
    },
    "dislipidemia": {
      "capitulo": "05"
    },
    "pneumonia": {
      "capitulo": "12"
    },
    "has": {
      "capitulo": "11"
    },
    "irradiacao em faixa epigastrica": {
      "capitulo": "13"
    },
    "dor": {
      "capitulo": "21"
    },
    "retinopatia diabetica": {
      "capitulo": "09"
    },
    "pleurite": {
      "capitulo": "12"
    },
    "obesidade": {
      "capitulo": "24"
    },
    "hernia inguinal operada": {
      "capitulo": "15"
    }
  }
}