{
  "prontuario_id": 380,
  "text": "# 61 # professora.  # QP: controlar a PA e DM para cx coluna. pcte relata ter cistite cronica há 40 anos - urupol. # pcte relata dispnéia aos pequenos esforcos, dor na nuca, sensação de sufocamento, palpitaçoes, visão turva devido a PA; aferiu a PA hoje pela manha: 260/180 mmHg. Exames alterados:  glicose: 128 mg/dl, colesterol total: 272 mg/dl, triglicerideos: 406 mg/dl, Parcial de urina: proteinas 30 mg/dl, hemacias: 1000 /ml,  microaluminuria: creatinina 83 mg/dl,  microalbuminuria urinaria: 453,2 mg/L. conduta: exames para investigar insuficiencia cardiaca;   receitado: enalapril 10mg, sinvastatina 20mg, anlodipina 5mg e metformina 850 mg. Pai e mae falecidos de infarto, irmao falecido com 57 anos. HAS: anlodipina 1 x por dia. pcte nao sabe dizer, DM 2 há 2 anos: metformina e insulina - pela manha. ex fumante 3 meses 40 maços /ano. Dois AVE um há 1 ano e outro 2 anos. duas gravidez tubarias.",
  "entities": {
    "Grupo Profissional ou Ocupacional": [
      "professora"
    ],
    "Achado": [
      "QP",
      "falecidos",
      "falecido",
      "ex fumante"
    ],
    "Abreviação": [
      "QP",
      "DM",
      "pcte",
      "PA",
      "HAS",
      "AVE",
      "cx coluna",
      "aferiu a PA",
      "DM 2"
    ],
    "Função de Organismo": [
      "PA"
    ],
    "Doença ou Síndrome": [
      "DM",
      "infarto",
      "HAS",
      "AVE",
      "cistite cronica",
      "insuficiencia cardiaca",
      "DM 2",
      "gravidez tubarias"
    ],
    "Paciente ou Grupo com Deficiência": [
      "pcte"
    ],
    "Substância Farmacológica": [
      "urupol",
      "enalapril",
      "sinvastatina",
      "anlodipina",
      "metformina",
      "insulina"
    ],
    "Sinal ou Sintoma": [
      "dor",
      "palpitaçoes",
      "dispnéia aos pequenos esforcos",
      "sensação de sufocamento",
      "visão turva"
    ],
    "Procedimento Laboratorial": [
      "Exames",
      "Parcial de urina"
    ],
    "Atividade de Assistência à Saúde": [
      "conduta",
      "investigar",
      "receitado",
      "aferiu a PA"
    ],
    "Produto Intelectual": [
      "conduta"
    ],
    "Procedimento Diagnóstico": [
      "exames"
    ],
    "Aminoácido, Peptídeo ou Proteína": [
      "enalapril",
      "insulina"
    ],
    "Conceito Quantitativo": [
      "10mg",
      "20mg",
      "5mg",
      "Dois",
      "duas",
      "260/180 mmHg",
      "850 mg",
      "1 x por dia",
      "40 maços /ano"
    ],
    "Substância Química Orgânica": [
      "sinvastatina",
      "anlodipina",
      "metformina"
    ],
    "Grupo Familiar": [
      "Pai",
      "mae",
      "irmao"
    ],
    "Negação": [
      "nao"
    ],
    "Hormônio": [
      "insulina"
    ],
    "Procedimento Terapêutico ou Preventivo": [
      "cx coluna"
    ],
    "Resultado Laboratorial ou de Teste": [
      "glicose : 128 mg/dl",
      "colesterol total : 272 mg/dl",
      "triglicerideos : 406 mg/dl",
      "proteinas 30 mg/dl",
      "hemacias : 1000 /ml",
      "microaluminuria : creatinina 83 mg/dl",
      "microalbuminuria urinaria : 453 , 2 mg/L"
    ]
  },
  "labels": {
    "infarto": {
      "capitulo": "11"
    },
    "palpitaçoes": {
      "capitulo": "11"
    },
    "dispnéia aos pequenos esforcos": {
      "capitulo": "12"
    },
    "sensação de sufocamento": {
      "capitulo": "12"
    },
    "visão turva": {
      "capitulo": "09"
    },
    "has": {
      "capitulo": "11"
    },
    "falecido": {
      "capitulo": "24"
    },
    "falecidos": {
      "capitulo": "24"
    },
    "dm": {
      "capitulo": "05"
    },
    "gravidez tubarias": {
      "capitulo": "18"
    },
    "cistite cronica": {
      "capitulo": "16"
    },
    "dm 2": {
      "capitulo": "05"
    },
    "ave": {
      "capitulo": "21"
    },
    "dor": {
      "capitulo": "15"
    },
    "ex fumante": {
      "capitulo": "24"
    },
    "insuficiencia cardiaca": {
      "capitulo": "11"
    }
  }
}