{
  "prontuario_id": 932,
  "text": "LUCAS, 55 ANOS, RETORNO PARA AVALIAÇÃO DE EXAMES,  EM ACOMPANHAMENTO HÁ 3 ANOS POR DM 2, EM USO INSULINA NPH 16 U ANTES DE DORMIR E METFORMINA 850 MG 2 VEZES AO DIA, REFERE CONTROLE DA DOENÇA  CARDIOMIOPATIA ISQUEMICA COM HISTORICO DE CX PARA REVASCULARIZAÇÃO (3 POSTES SAFENA) EM 2011, HIPERTENSO EM USO DE ENALAPRIL 1 CP A NOITE,  DISLIPIDEMICO EM USO DE SINVASTATINA 60 MG,  EM USO DE AAS 100 MG, EM USO DE CLOPRIM 75 MG.  EXAMES: HMG - HB 12,5; HT 35,9; PLAQUETAS 217000;   CR 1 MG/DL, CKD-EPI 84 ML/ MIN, GLICOSE 113 MG/DL, HEMO GLICADA 6,03%; AC URICO 8;   TG 171; HDL 46; CT 197; LDL 117; TGP 17; TGO 27;  ACIDO FOLICO 20; MICROALBUMINURIA EM AMOSTRA ISOLADA 5,88 MG/G DE CREATININA.  SINAIS VITAIS  110/ 70 MMHG, PULSO  76.  CONDUTA: VYTORIN 10/40 MG 1 COMPRIMIDO AO DIA, NO LUGAR DE SINVASTATINA 60 MG. SOLICITADO RETORNO EM MARÇO DE 2015, COM EXAMES.",
  "entities": {
    "Atividade de Assistência à Saúde": [
      "RETORNO",
      "ACOMPANHAMENTO",
      "SOLICITADO RETORNO"
    ],
    "Substância Farmacológica": [
      "METFORMINA",
      "ENALAPRIL",
      "SINVASTATINA",
      "AAS",
      "CLOPRIM",
      "VYTORIN",
      "INSULINA NPH"
    ],
    "Substância Química Orgânica": [
      "METFORMINA",
      "SINVASTATINA",
      "AAS",
      "CLOPRIM",
      "VYTORIN"
    ],
    "Achado": [
      "HIPERTENSO",
      "DISLIPIDEMICO"
    ],
    "Doença ou Síndrome": [
      "HIPERTENSO",
      "DISLIPIDEMICO",
      "DM 2",
      "DOENÇA CARDIOMIOPATIA ISQUEMICA"
    ],
    "Aminoácido, Peptídeo ou Proteína": [
      "ENALAPRIL"
    ],
    "Abreviação": [
      "AAS",
      "DM 2",
      "CX PARA REVASCULARIZAÇÃO",
      "AC URICO 8"
    ],
    "Procedimento Laboratorial": [
      "EXAMES",
      "HMG"
    ],
    "Atributo Clínico": [
      "PULSO",
      "SINAIS VITAIS"
    ],
    "Conceito Quantitativo": [
      "76",
      "16 U",
      "850 MG",
      "2 VEZES AO DIA",
      "1 CP A NOITE",
      "60 MG",
      "100 MG",
      "75 MG",
      "110/ 70 MMHG",
      "10/40 MG",
      "1 COMPRIMIDO AO DIA"
    ],
    "Produto Intelectual": [
      "CONDUTA"
    ],
    "Conceito Temporal": [
      "ANTES DE DORMIR"
    ],
    "Procedimento Terapêutico ou Preventivo": [
      "CX PARA REVASCULARIZAÇÃO",
      "POSTES SAFENA"
    ],
    "Resultado Laboratorial ou de Teste": [
      "HB 12 , 5",
      "HT 35 , 9",
      "PLAQUETAS 217000",
      "CR 1 MG/DL",
      "CKD-EPI 84 ML/ MIN",
      "GLICOSE 113 MG/DL",
      "HEMO GLICADA 6 , 03%",
      "AC URICO 8",
      "TG 171",
      "HDL 46",
      "CT 197",
      "LDL 117",
      "TGP 17",
      "TGO 27",
      "ACIDO FOLICO 20",
      "MICROALBUMINURIA EM AMOSTRA ISOLADA 5",
      "88 MG/G DE CREATININA"
    ]
  },
  "labels": {
    "dislipidemico": {
      "capitulo": "11"
    },
    "doença cardiomiopatia isquemica": {
      "capitulo": "11"
    },
    "dm 2": {
      "capitulo": "05"
    },
    "hipertenso": {
      "capitulo": "11"
    }
  }
}