{
  "prontuario_id": 441,
  "text": "Lucas, 58 anos.  QP: retorno para apresentar exames. HMA:  DM 2 e HAS em uso de: - AAS 100 mg, 1 x/dia - Enalapril 10 mg, 12/12 h - Selozok (metoprolol) 100 mg, 1 cp/manhã - Clopidogrel 75 mg, 1 cp/dia - Metformina 850 mg, 3 x/dia - Atorvastatina 20 mg, 2 cp/dia - Bezofibrato 200 mg, 1 cp/noite. - Insulina NPH 40 U pela manhã, 20 UI pela noite. - Fluoxetina. Fez 3 angioplastias. Em uma das vezes iniciou com episódio de dispneia. Diagnóstico de hérnia de disco, mas perdeu o seguimento da ortopedia no XXXX. Visão turva.  CHV: Alimentação: - Café da manhã: pão e algo salgado (peixe, salsicha, queijo, presunto). - Almoço: arroz, carne, salada. - Noite: pão, peixe, o que sobrou do almoço. Come doces. Ex-tabagista há 9 anos. Nega etilismo.  Exames lab: BEG, LOTE, AAA Sat: 93 em AA, FC: 83 bpm, FR: 18 ipm, PA: 140/80, Peso: 97, Altura: 1,75; IMC: 31,7; Tórax sem particularidades. Presença de FTV. Complacência normal. Presença de sons claros pulmonares. MV + bilateralmente, sem RA. BRCNF em 2T sem sopros. Abdome globoso, sem cicatrizes e visceromegalias. Presença de RHA. Fígado não palpável. Sem facies de dor a palpação. Membros inferiores sem edemas. Pulsos presentes, cheios e filiformes.  Exames laboratoriais: HMG normal, Cr: 1,4; Glicemia de jejum: 193, Ureia: 82, Tgs: 226, HDL: 28, Colesterol total: 204, LDL: 130, TSH: 1,15; T4: 0,99; CKD-EPI: 55.",
  "entities": {
    "Abreviação": [
      "QP",
      "HMA",
      "HAS",
      "AAS",
      "CHV",
      "BEG",
      "LOTE",
      "AAA",
      "Sat",
      "FC",
      "FR",
      "PA",
      "IMC",
      "RA",
      "DM 2",
      "Exames lab",
      "MV + bilateralmente",
      "Presença de RHA",
      "HMG normal",
      "Cr : 1 , 4",
      "Tgs : 226"
    ],
    "Atividade de Assistência à Saúde": [
      "retorno"
    ],
    "Procedimento Laboratorial": [
      "exames",
      "Exames lab",
      "Exames laboratoriais"
    ],
    "Doença ou Síndrome": [
      "HAS",
      "etilismo",
      "DM 2",
      "hérnia de disco"
    ],
    "Substância Química Orgânica": [
      "AAS",
      "Metformina"
    ],
    "Substância Farmacológica": [
      "AAS",
      "Enalapril",
      "Selozok",
      "metoprolol",
      "Clopidogrel",
      "Metformina",
      "Atorvastatina",
      "Bezofibrato",
      "Fluoxetina",
      "Insulina NPH"
    ],
    "Aminoácido, Peptídeo ou Proteína": [
      "Enalapril"
    ],
    "Procedimento Terapêutico ou Preventivo": [
      "angioplastias"
    ],
    "Sinal ou Sintoma": [
      "dispneia",
      "particularidades",
      "FTV",
      "RA",
      "sopros",
      "globoso",
      "cicatrizes",
      "visceromegalias",
      "edemas",
      "Visão turva",
      "facies de dor"
    ],
    "Organização Relacionada à Saúde": [
      "ortopedia"
    ],
    "Grupo Profissional ou Ocupacional": [
      "ortopedia"
    ],
    "Alimento": [
      "Alimentação",
      "pão",
      "salgado",
      "peixe",
      "salsicha",
      "queijo",
      "presunto",
      "Almoço",
      "arroz",
      "carne",
      "salada",
      "doces"
    ],
    "Peixe": [
      "peixe"
    ],
    "Achado": [
      "Ex-tabagista",
      "BEG",
      "LOTE",
      "palpável",
      "presentes",
      "cheios",
      "filiformes",
      "Complacência normal",
      "sons claros pulmonares",
      "MV + bilateralmente",
      "Presença de RHA"
    ],
    "Negação": [
      "Nega",
      "sem",
      "não",
      "Sem"
    ],
    "Atributo Clínico": [
      "Sat",
      "FC",
      "FR",
      "PA",
      "Peso",
      "Altura",
      "IMC",
      "Pulsos"
    ],
    "Conceito Quantitativo": [
      "93",
      "140/80",
      "97",
      "100 mg",
      "1 x/dia",
      "10 mg",
      "1 cp/manhã",
      "75 mg",
      "1 cp/dia",
      "850 mg",
      "3 x/dia",
      "20 mg",
      "2 cp/dia",
      "200 mg",
      "1 cp/noite",
      "20 UI pela noite",
      "83 bpm",
      "18 ipm",
      "1 , 75",
      "31 , 7"
    ],
    "Localização ou Região Corporal": [
      "Tórax",
      "Abdome",
      "Membros inferiores"
    ],
    "Parte do Corpo, Órgão ou Componente Orgânico": [
      "Fígado"
    ],
    "Procedimento Diagnóstico": [
      "palpação"
    ],
    "Função Patológica": [
      "edemas"
    ],
    "Hormônio": [
      "Insulina NPH"
    ],
    "Resultado Laboratorial ou de Teste": [
      "HMG normal",
      "Cr : 1 , 4",
      "Glicemia de jejum : 193",
      "Ureia : 82",
      "Tgs : 226",
      "HDL : 28",
      "Colesterol total : 204",
      "LDL : 130",
      "TSH : 1 , 15",
      "T4 : 0 , 99",
      "CKD-EPI : 55"
    ]
  },
  "labels": {
    "ra": {
      "capitulo": "04"
    },
    "edemas": {
      "capitulo": "12"
    },
    "ftv": {
      "capitulo": "11"
    },
    "dm 2": {
      "capitulo": "05"
    },
    "cicatrizes": {
      "capitulo": "14"
    },
    "visão turva": {
      "capitulo": "09"
    },
    "palpável": {
      "capitulo": "13"
    },
    "mv + bilateralmente": {
      "capitulo": "08"
    },
    "particularidades": {
      "capitulo": "09"
    },
    "hérnia de disco": {
      "capitulo": "15"
    },
    "filiformes": {
      "capitulo": "11"
    },
    "presença de rha": {
      "capitulo": "16"
    },
    "facies de dor": {
      "capitulo": "21"
    },
    "dispneia": {
      "capitulo": "12"
    },
    "visceromegalias": {
      "capitulo": "13"
    },
    "has": {
      "capitulo": "05"
    },
    "beg": {
      "capitulo": "09"
    },
    "sopros": {
      "capitulo": "11"
    },
    "globoso": {
      "capitulo": "15"
    },
    "cheios": {
      "capitulo": "11"
    },
    "sons claros pulmonares": {
      "capitulo": "12"
    },
    "lote": {
      "capitulo": "21"
    }
  }
}