{
  "prontuario_id": 679,
  "text": "59 a. Comorbidades: DM tipo 2 ( há mais de 10 anos, insulinodependente há 5 anos), hipotireoidismo (após tireoidectomia ), HAS (há mais de 10 anos), glaucoma. Medicamentos diários: Insulina NPH (20U pela manhã e 16U à noite), regular (16U pela manhã e 8U à noite), puran (100mcg), metformina 850mg, AAS (100mg), enalapril (20mg). Retorno com exames laboratoriais: Cr = 0,8; TFG CKD-EPI 79,3 ml/min/1,73 m2 ; glicose = 193, triglicerídeos = 117, HbA1c = 8,42%, TSH = 0,85, T4 livre = 1,33 ; microalbuminúria: 3,18mg/24hrs.  CONDUTA: NPH 24U + regular 16U pela manhã, NPH 16U  + regular 8U à noite. Medicamentos sintomáticos para IVAS. Retorno em 3 meses.",
  "entities": {
    "Achado": [
      "insulinodependente"
    ],
    "Doença ou Síndrome": [
      "hipotireoidismo",
      "HAS",
      "glaucoma",
      "IVAS",
      "DM tipo 2"
    ],
    "Procedimento Terapêutico ou Preventivo": [
      "tireoidectomia"
    ],
    "Abreviação": [
      "HAS",
      "regular",
      "AAS",
      "NPH",
      "DM tipo 2"
    ],
    "Substância Farmacológica": [
      "Medicamentos",
      "regular",
      "puran",
      "metformina",
      "AAS",
      "enalapril",
      "NPH",
      "Insulina NPH"
    ],
    "Conceito Temporal": [
      "diários",
      "pela manhã",
      "à noite"
    ],
    "Substância Química Orgânica": [
      "regular",
      "puran",
      "metformina",
      "AAS",
      "NPH"
    ],
    "Conceito Quantitativo": [
      "100mcg",
      "850mg",
      "100mg",
      "20mg",
      "24U",
      "16U"
    ],
    "Atividade de Assistência à Saúde": [
      "Retorno"
    ],
    "Produto Intelectual": [
      "CONDUTA"
    ],
    "Procedimento Laboratorial": [
      "exames laboratoriais"
    ],
    "Resultado Laboratorial ou de Teste": [
      "Cr = 0 , 8",
      "TFG CKD-EPI 79 , 3 ml/min/1 , 73 m2",
      "glicose = 193",
      "triglicerídeos = 117",
      "HbA1c = 8 , 42%",
      "TSH = 0 , 85",
      "T4 livre = 1 , 33",
      "microalbuminúria : 3 , 18mg/24hrs"
    ]
  },
  "labels": {
    "has": {
      "capitulo": "11"
    },
    "ivas": {
      "capitulo": "22"
    },
    "dm tipo 2": {
      "capitulo": "05"
    },
    "hipotireoidismo": {
      "capitulo": "05"
    },
    "glaucoma": {
      "capitulo": "09"
    }
  }
}