{
  "prontuario_id": 244,
  "text": "01/02/12 Às 17h. Internou na UTI - IV, proveniente do CC ., PO de tocacotomia exploradora, consciente, comunicativo, pupilas isocóricas fotoreagentes. Respiração espontânea, em névoa úmida 3l. MV diminuído em ápice E e bibasalmente. Apresenta hematoma em região torácica E, dreno de tórax anterior e posterior em tórax E, com débito hemático. Abdomen flácido. RHA hiperativo. Apresenta escoriação em região abdominal, sem presença de exsudato. Curativo em MIE com tala gessada. Monitorizado, e colocada medidas de conforto. Enfermeira Florence Nightingale . EXAME GERAL E INVESTIGACAO DE PESSOAS SEM QUEIXAS OU DIAGNOSTICO RELATADO",
  "entities": {
    "Atividade de Assistência à Saúde": [
      "Internou",
      "Monitorizado",
      "EXAME GERAL"
    ],
    "Abreviação": [
      "UTI",
      "CC",
      "PO",
      "MIE",
      "MV diminuído",
      "ápice E",
      "região torácica E",
      "tórax E",
      "RHA hiperativo"
    ],
    "Organização Relacionada à Saúde": [
      "UTI",
      "CC"
    ],
    "Conceito Temporal": [
      "PO"
    ],
    "Achado": [
      "consciente",
      "comunicativo",
      "isocóricas",
      "fotoreagentes",
      "Respiração espontânea",
      "Abdomen flácido"
    ],
    "Parte do Corpo, Órgão ou Componente Orgânico": [
      "pupilas"
    ],
    "Conceito Quantitativo": [
      "3l"
    ],
    "Conceito Espacial": [
      "bibasalmente",
      "anterior",
      "posterior"
    ],
    "Função Patológica": [
      "hematoma"
    ],
    "Lesão ou Envenenamento": [
      "escoriação"
    ],
    "Negação": [
      "sem",
      "SEM"
    ],
    "Substância Corporal": [
      "exsudato",
      "débito hemático"
    ],
    "Sinal ou Sintoma": [
      "exsudato",
      "QUEIXAS",
      "MV diminuído",
      "débito hemático",
      "RHA hiperativo"
    ],
    "Procedimento Terapêutico ou Preventivo": [
      "Curativo",
      "tocacotomia exploradora",
      "névoa úmida",
      "dreno de tórax",
      "tala gessada",
      "medidas de conforto"
    ],
    "Dispositivo Médico": [
      "Curativo",
      "dreno de tórax",
      "tala gessada"
    ],
    "Localização ou Região Corporal": [
      "MIE",
      "ápice E",
      "região torácica E",
      "tórax E",
      "região abdominal"
    ],
    "Procedimento Diagnóstico": [
      "Monitorizado",
      "INVESTIGACAO DE PESSOAS"
    ],
    "Grupo Profissional ou Ocupacional": [
      "Enfermeira"
    ],
    "Função de Organismo": [
      "Respiração espontânea"
    ]
  },
  "labels": {
    "mv diminuído": {
      "capitulo": "11"
    },
    "hematoma": {
      "capitulo": "22"
    },
    "débito hemático": {
      "capitulo": "22"
    },
    "abdomen flácido": {
      "capitulo": "13"
    },
    "respiração espontânea": {
      "capitulo": "12"
    },
    "queixas": {
      "capitulo": "21"
    },
    "rha hiperativo": {
      "capitulo": "03"
    },
    "escoriação": {
      "capitulo": "14"
    }
  }
}