{
  "prontuario_id": 342,
  "text": "PTE CI GRAVE, COM ANGINA REFRATARIA A TTO CLINICO REINTEERNA COM DOR TORACICA TIPICA, NO REPOUSO, ( CLASSE 3 ). tEM CRM PREVIA E IMPLANTE DE STENT EM ACD (2) COM REESTENOSE INTRA STENT E ACTPS. EM UMA ULTIMA  INTERNACAO (AGO/2003) APRESENTAVA NOVOS EPISODIOS DE ANGINA TENDO REALIZADO ACTP DE OSTIO DE ACD ( SEM STENT ) COM ENXERTO DE MAMARIA PARA ADA PERVIO. NESTA INTERNACAO FOI PROPOSTO PRE-TRATAMENTO COM RAPAMICINA VO COMO TERAPEUTICA PARA EVITAR REESTENOSE. CINTILOGRAFICA MIOCARDICA POSITIVA PARA ISQUEMIA EM TERRITORIO DE ACD. NO ESTUDO HEMODINAMICO EVIDENCIOU-SE ESTENOSE SIGNIFICATICVA DO OSTIO DE ACD, PROCEDENDO-SE A IMPLANTE DE STENT NESTE LOCAL. SEGUE COM ADMINISTRACAO DE SIROLIMUS ( RAPAMICINA ) VO DURANTE 30 DIAS. ALTA EM BOAS CONDICOES, ASSINTOMATICO.",
  "entities": {
    "Paciente ou Grupo com Deficiência": [
      "PTE"
    ],
    "Abreviação": [
      "PTE",
      "CRM",
      "ACD",
      "ACTPS",
      "ACTP",
      "VO",
      "CI GRAVE",
      "TTO CLINICO",
      "OSTIO DE ACD",
      "POSITIVA PARA ISQUEMIA EM TERRITORIO DE ACD",
      "ESTENOSE SIGNIFICATICVA DO OSTIO DE ACD"
    ],
    "Atividade de Assistência à Saúde": [
      "REINTEERNA",
      "REALIZADO",
      "PROPOSTO",
      "TERAPEUTICA",
      "ADMINISTRACAO",
      "ALTA"
    ],
    "Procedimento Terapêutico ou Preventivo": [
      "CRM",
      "ACTPS",
      "ACTP",
      "PRE-TRATAMENTO",
      "TERAPEUTICA",
      "TTO CLINICO"
    ],
    "Conceito Temporal": [
      "PREVIA",
      "PRE-TRATAMENTO"
    ],
    "Dispositivo Médico": [
      "STENT"
    ],
    "Parte do Corpo, Órgão ou Componente Orgânico": [
      "ACD",
      "MAMARIA",
      "ADA",
      "OSTIO DE ACD"
    ],
    "Sinal ou Sintoma": [
      "ANGINA",
      "ANGINA REFRATARIA",
      "DOR TORACICA TIPICA",
      "NO REPOUSO",
      "REESTENOSE INTRA STENT"
    ],
    "Negação": [
      "SEM",
      "EVITAR"
    ],
    "Achado": [
      "PERVIO",
      "ASSINTOMATICO",
      "BOAS CONDICOES"
    ],
    "Substância Farmacológica": [
      "SIROLIMUS",
      "RAPAMICINA"
    ],
    "Doença ou Síndrome": [
      "CI GRAVE"
    ],
    "Procedimento Diagnóstico": [
      "CINTILOGRAFICA MIOCARDICA",
      "ESTUDO HEMODINAMICO"
    ],
    "Resultado Laboratorial ou de Teste": [
      "POSITIVA PARA ISQUEMIA EM TERRITORIO DE ACD",
      "ESTENOSE SIGNIFICATICVA DO OSTIO DE ACD"
    ]
  },
  "labels": {
    "angina refrataria": {
      "capitulo": "11"
    },
    "pervio": {
      "capitulo": "18"
    },
    "dor toracica tipica": {
      "capitulo": "21"
    },
    "reestenose intra stent": {
      "capitulo": "11"
    },
    "no repouso": {
      "capitulo": "21"
    },
    "angina": {
      "capitulo": "11"
    },
    "ci grave": {
      "capitulo": "11"
    }
  }
}