{
  "prontuario_id": 411,
  "text": "# Lucas , 64 anos  # QP : acompanhamento ambulatorial  # Relata polaciúria, frequencia urinária a cada 30min, noctúria.  # Medicamentos - carbamazepina 200mg - 3x / dia - carbonato de lítio - 2x / dia - haldol 5mg - 1x / dia - diazepan - 1x / dia - losartana 50mg - 1 cp 12/12hs - HCTZ 25mg - 1x manhã - atenolol 50mg - 1x manhã - AAS 100mg - 1 cp após o almoço  # 20/05/13 Cr 1,1 CKD 71 Hb 16,5 Ht : 49,3% Leuc : 8380 K 3,9 Na 140   conduta : soliito microalbuminuria  para investigacao de DRC  repito : losartana 50mg - 1 cp 12/12hs - HCTZ 25mg - 1x manhã - atenolol 50mg - 1x manhã - AAS 100mg - 1 cp após o almoço. # HAS há 2 anos # Nega DM, cardiopatia ? e dislipidemia  # ex-tabagista durante 5 anos de 20cig / dia nega etilismo refere internações prévias por causas psiquiátricas.",
  "entities": {
    "Sinal ou Sintoma": [
      "polaciúria",
      "noctúria",
      "causas psiquiátricas"
    ],
    "Substância Farmacológica": [
      "Medicamentos",
      "carbamazepina",
      "haldol",
      "diazepan",
      "losartana",
      "HCTZ",
      "atenolol",
      "AAS",
      "carbonato de lítio"
    ],
    "Substância Química Orgânica": [
      "haldol",
      "diazepan",
      "HCTZ"
    ],
    "Conceito Temporal": [
      "12/12hs",
      "manhã",
      "prévias",
      "a cada 30min",
      "3x / dia",
      "2x / dia",
      "1x / dia",
      "após o almoço",
      "há 2 anos",
      "5 anos"
    ],
    "Abreviação": [
      "HCTZ",
      "AAS",
      "DRC",
      "HAS",
      "DM",
      "1 cp",
      "Cr 1 , 1",
      "Hb 16 , 5",
      "Ht : 49 , 3%",
      "Leuc : 8380",
      "K 3 , 9",
      "Na 140"
    ],
    "Produto Intelectual": [
      "conduta"
    ],
    "Atividade de Assistência à Saúde": [
      "conduta",
      "investigacao",
      "internações",
      "acompanhamento ambulatorial"
    ],
    "Resultado Laboratorial ou de Teste": [
      "microalbuminuria",
      "Cr 1 , 1",
      "CKD 71",
      "Hb 16 , 5",
      "Ht : 49 , 3%",
      "Leuc : 8380",
      "K 3 , 9",
      "Na 140"
    ],
    "Procedimento Diagnóstico": [
      "investigacao"
    ],
    "Doença ou Síndrome": [
      "DRC",
      "HAS",
      "DM",
      "cardiopatia",
      "dislipidemia",
      "etilismo"
    ],
    "Negação": [
      "Nega",
      "nega"
    ],
    "Achado": [
      "ex-tabagista",
      "frequencia urinária"
    ],
    "Comportamento Individual": [
      "etilismo"
    ],
    "Grupo Etário": [
      "64 anos"
    ],
    "Função de Organismo": [
      "frequencia urinária"
    ],
    "Conceito Quantitativo": [
      "3x / dia",
      "2x / dia",
      "1x / dia",
      "1 cp",
      "100mg -"
    ],
    "Substância Química Inorgânica": [
      "carbonato de lítio"
    ]
  },
  "labels": {
    "polaciúria": {
      "capitulo": "16"
    },
    "has": {
      "capitulo": "06"
    },
    "etilismo": {
      "capitulo": "24"
    },
    "ex-tabagista": {
      "capitulo": "24"
    },
    "frequencia urinária": {
      "capitulo": "21"
    },
    "drc": {
      "capitulo": "11"
    },
    "cardiopatia": {
      "capitulo": "11"
    },
    "noctúria": {
      "capitulo": "16"
    },
    "dm": {
      "capitulo": "05"
    },
    "causas psiquiátricas": {
      "capitulo": "06"
    },
    "dislipidemia": {
      "capitulo": "05"
    }
  }
}