{
  "prontuario_id": 251,
  "text": "# HAS # DM # EX-TABAGISTA # EOSINOFILIA NÃO INVESTIGADA  PACIENTE VEM ENCAMINHADOAO HCPA POR INFARTO AGUDO DO MIOCÁRDIO COM SUPRA DE ST EM V2 - V3 + ALTERAÇÕES ENZIMATICAS. PACIENTE APRESENTAVA DOR TORÁCICA HÁ UMA SEMANA E PROCURAVA ATENDIMENTO MÉDICO RECEBENDO TRATAMENTO COM ANALGESIAS. NO DIA 21/03 PACIENTE APRESENTOU DOR TORÁCICA COM CIANOSE, SUDORESE SENDO ENTÃO ENCAMINHADO PARA O HCPA. NO HCPA REALIZOU-SE UMA ACTP QUE MOSTROU LESÃO EM DAE ( COLOCADO STENT COM SUCESSO ), ALÉM DE OUTRAS LESÕES EM CX ( DISCRETA IRREG ). E CD ( ATEROMATOSE DIFUSA ). NA INTERNAÇÃO PACIENTE APRESENTOU UMA HIPOTENSÃO COM O USO DE BETA BLOQUEADOR E O MESMO FOI SUSPENSO TEMPORARIAMENTE.",
  "entities": {
    "Abreviação": [
      "HAS",
      "DM",
      "ACTP",
      "CD",
      "LESÃO EM DAE"
    ],
    "Doença ou Síndrome": [
      "HAS",
      "DM",
      "INFARTO AGUDO DO MIOCÁRDIO",
      "ATEROMATOSE DIFUSA"
    ],
    "Achado": [
      "EX-TABAGISTA"
    ],
    "Negação": [
      "NÃO"
    ],
    "Atividade de Assistência à Saúde": [
      "INVESTIGADA",
      "RECEBENDO",
      "ENCAMINHADO",
      "REALIZOU-SE",
      "INTERNAÇÃO",
      "SUSPENSO"
    ],
    "Procedimento Diagnóstico": [
      "INVESTIGADA",
      "ACTP"
    ],
    "Paciente ou Grupo com Deficiência": [
      "PACIENTE"
    ],
    "Localização ou Região Corporal": [
      "TORÁCICA"
    ],
    "Grupo Profissional ou Ocupacional": [
      "MÉDICO"
    ],
    "Procedimento Terapêutico ou Preventivo": [
      "TRATAMENTO",
      "ANALGESIAS",
      "ACTP",
      "CX"
    ],
    "Substância Farmacológica": [
      "ANALGESIAS",
      "BETA BLOQUEADOR"
    ],
    "Sinal ou Sintoma": [
      "CIANOSE",
      "SUDORESE",
      "HIPOTENSÃO",
      "ALTERAÇÕES ENZIMATICAS",
      "ATEROMATOSE DIFUSA"
    ],
    "Organização Relacionada à Saúde": [
      "HCPA"
    ],
    "Dispositivo Médico": [
      "STENT"
    ],
    "Parte do Corpo, Órgão ou Componente Orgânico": [
      "CD"
    ],
    "Conceito Temporal": [
      "TEMPORARIAMENTE",
      "UMA SEMANA"
    ],
    "Resultado Laboratorial ou de Teste": [
      "ALTERAÇÕES ENZIMATICAS",
      "LESÃO EM DAE",
      "ATEROMATOSE DIFUSA"
    ],
    "Lesão ou Envenenamento": [
      "OUTRAS LESÕES"
    ]
  },
  "labels": {
    "has": {
      "capitulo": "11"
    },
    "alterações enzimaticas": {
      "capitulo": "05"
    },
    "hipotensão": {
      "capitulo": "11"
    },
    "sudorese": {
      "capitulo": "22"
    },
    "infarto agudo do miocárdio": {
      "capitulo": "11"
    },
    "ateromatose difusa": {
      "capitulo": "11"
    },
    "cianose": {
      "capitulo": "22"
    },
    "outras lesões": {
      "capitulo": "21"
    },
    "dm": {
      "capitulo": "05"
    }
  }
}