{
  "prontuario_id": 901,
  "text": "paciente interna com quadro de hemorragia digestiva alta, endoscopia de urgencia mostrou 2 ulceras, 1 com sangramento, colocado clip metalico. não apresentou mais sangramento, mas descompensou da angina, com muitos episódios de dor. Hematócrito estava 9,3, optou-se por transfundir 2 ui CHAD para melhora do controle dos sintomas. Realizou endoscopia de controle 72 horas apos, com resultado favorável das ulceras, em fase de cicatrização, sem evidencia de sangramento. Alta em condições estáveis, com o mesmo perfil de angina dos ultimos meses. Orientado para manter medicação prescrita e acompanhamento com equipe da dor e psiquiatria.",
  "entities": {
    "Paciente ou Grupo com Deficiência": [
      "paciente"
    ],
    "Atividade de Assistência à Saúde": [
      "interna",
      "colocado",
      "controle",
      "Alta",
      "Orientado",
      "prescrita",
      "acompanhamento"
    ],
    "Procedimento Terapêutico ou Preventivo": [
      "endoscopia",
      "transfundir",
      "clip metalico",
      "endoscopia de controle"
    ],
    "Procedimento Diagnóstico": [
      "endoscopia",
      "endoscopia de controle"
    ],
    "Resultado Laboratorial ou de Teste": [
      "ulceras",
      "9 , 3",
      "resultado favorável",
      "em fase de cicatrização",
      "evidencia de sangramento"
    ],
    "Função Patológica": [
      "sangramento"
    ],
    "Negação": [
      "não",
      "sem"
    ],
    "Sinal ou Sintoma": [
      "sangramento",
      "descompensou",
      "angina",
      "sintomas"
    ],
    "Doença ou Síndrome": [
      "angina",
      "hemorragia digestiva alta"
    ],
    "Procedimento Laboratorial": [
      "Hematócrito"
    ],
    "Substância Farmacológica": [
      "CHAD",
      "medicação"
    ],
    "Abreviação": [
      "CHAD"
    ],
    "Grupo Profissional ou Ocupacional": [
      "psiquiatria",
      "equipe da dor"
    ],
    "Dispositivo Médico": [
      "clip metalico"
    ],
    "Conceito Quantitativo": [
      "muitos episódios",
      "9 , 3",
      "2 ui"
    ],
    "Conceito Temporal": [
      "72 horas apos",
      "ultimos meses"
    ],
    "Achado": [
      "resultado favorável",
      "condições estáveis"
    ],
    "Função de Organismo": [
      "em fase de cicatrização"
    ]
  },
  "labels": {
    "sangramento": {
      "capitulo": "13"
    },
    "hemorragia digestiva alta": {
      "capitulo": "13"
    },
    "sintomas": {
      "capitulo": "21"
    },
    "descompensou": {
      "capitulo": "13"
    },
    "angina": {
      "capitulo": "11"
    }
  }
}