{
  "prontuario_id": 622,
  "text": "23:20H Glasgow 15 , face corada, pupilas iso / foto. SNE em narina D com infusao  de  dieta 75ml / hr.Traqueostomizado, sob suporte de nevoa umida 3L/min,ausculta pulmonar com MV com roncos difusos em apice,aspirado media quantidade de secreçao muco-purulenta.Acesso periferico MSD com infusao de sf 0,9% gravitacional. Mantem cabeceira do leito 45 graus. Extremidades aquecidas, perfusao periferica preservada.Abdomen  flacido palpaçao, rha + . Hiperemia reg sacra .Diurese  por SVD presente em coletor  amarelo citrico. Monitorizado continuamente com cardioscopico + oximetria de pulso + pam nao invasiva. Enfermeira Florence Nightingale. EDEMA CEREBRAL TRAUMATICO",
  "entities": {
    "Parte do Corpo, Órgão ou Componente Orgânico": [
      "pupilas",
      "narina D"
    ],
    "Achado": [
      "iso",
      "foto",
      "MV",
      "Glasgow 15",
      "face corada",
      "Extremidades aquecidas",
      "perfusao periferica preservada",
      "rha +",
      "amarelo citrico"
    ],
    "Abreviação": [
      "iso",
      "foto",
      "SNE",
      "MV",
      "MSD",
      "SVD",
      "narina D",
      "rha +",
      "reg sacra",
      "pam nao invasiva"
    ],
    "Dispositivo Médico": [
      "SNE",
      "SVD",
      "Acesso periferico"
    ],
    "Conceito Quantitativo": [
      "3L/min",
      "75ml / hr"
    ],
    "Procedimento Terapêutico ou Preventivo": [
      "aspirado",
      "infusao de dieta",
      "suporte de nevoa umida",
      "Acesso periferico",
      "infusao de sf 0 , 9% gravitacional",
      "cabeceira do leito 45 graus"
    ],
    "Atividade de Assistência à Saúde": [
      "aspirado"
    ],
    "Função de Organismo": [
      "Diurese"
    ],
    "Espaço ou Junção Corporal": [
      "narina D"
    ],
    "Alimento": [
      "infusao de dieta"
    ],
    "Procedimento Diagnóstico": [
      "ausculta pulmonar",
      "oximetria de pulso",
      "pam nao invasiva"
    ],
    "Sinal ou Sintoma": [
      "roncos difusos"
    ],
    "Substância Corporal": [
      "secreçao muco-purulenta"
    ],
    "Atributo Clínico": [
      "perfusao periferica preservada"
    ],
    "Localização ou Região Corporal": [
      "reg sacra"
    ],
    "Lesão ou Envenenamento": [
      "EDEMA CEREBRAL TRAUMATICO"
    ]
  },
  "labels": {
    "glasgow 15": {
      "capitulo": "22"
    },
    "roncos difusos": {
      "capitulo": "12"
    },
    "extremidades aquecidas": {
      "capitulo": "15"
    },
    "mv": {
      "capitulo": "12"
    },
    "edema cerebral traumatico": {
      "capitulo": "22"
    },
    "amarelo citrico": {
      "capitulo": "21"
    },
    "face corada": {
      "capitulo": "21"
    }
  }
}