{
  "prontuario_id": 918,
  "text": "Lucas, 66 anos # vem encaminhado por alteração da função renal. Cr 1,2 => ClCr 47ml/min # HAS há 5 anos, em uso de losartana 50mg, HCTZ 25mg # DM há 25 anos, insulino-dependente há 15 anos. Em uso de NPH  26 /_/ 36 e regular 10 UI # hipotireoidismo, em uso de 50mg # DLP, em uso de sinvastatina 20mg e AAS 100mg # G 3 C 3, apendicectomia. Nega vícios, nega alergia a medicamentos Exame físico : Peso 73kg, Alt 150cm, IMC 32 PA 130 x 70mmHg, FC 80. MV sem RA. PC : bulhas rítmicas sem sopros Abdomen globoso, flácido, cicatriz mediana Exames mostram : Hb glicada 8,9%, LDFL 109, Cr 1,2  relação albumina / creatinina 759mg/g  CT 187  TGL 110  HDL 56  K 5,1TSH 5,1  Hb 13,6  PU com proteínas 25mg/dl  sem hematúria",
  "entities": {
    "Atividade de Assistência à Saúde": [
      "encaminhado"
    ],
    "Doença ou Síndrome": [
      "HAS",
      "DM",
      "hipotireoidismo",
      "DLP",
      "vícios",
      "hematúria"
    ],
    "Abreviação": [
      "HAS",
      "HCTZ",
      "DM",
      "NPH",
      "DLP",
      "AAS",
      "Alt",
      "IMC",
      "PA",
      "FC",
      "MV",
      "RA",
      "PU",
      "Cr 1 , 2",
      "Hb glicada 8 , 9%",
      "CT 187",
      "TGL 110",
      "Hb 13 , 6"
    ],
    "Substância Farmacológica": [
      "losartana",
      "HCTZ",
      "NPH",
      "regular",
      "sinvastatina",
      "AAS"
    ],
    "Conceito Quantitativo": [
      "50mg",
      "25mg",
      "26",
      "36",
      "20mg",
      "100mg",
      "3",
      "73kg",
      "150cm",
      "32",
      "80",
      "10 UI",
      "130 x 70mmHg"
    ],
    "Substância Química Orgânica": [
      "HCTZ",
      "sinvastatina",
      "AAS"
    ],
    "Sinal ou Sintoma": [
      "insulino-dependente",
      "RA",
      "sopros",
      "globoso",
      "hematúria",
      "alteração da função renal",
      "alergia a medicamentos"
    ],
    "Hormônio": [
      "NPH",
      "regular"
    ],
    "Aminoácido, Peptídeo ou Proteína": [
      "NPH",
      "regular"
    ],
    "Atributo Clínico": [
      "G",
      "Peso",
      "Alt",
      "IMC",
      "PA",
      "FC"
    ],
    "Procedimento Terapêutico ou Preventivo": [
      "apendicectomia"
    ],
    "Negação": [
      "Nega",
      "nega",
      "sem"
    ],
    "Disfunção Mental ou Comportamental": [
      "vícios"
    ],
    "Achado": [
      "MV",
      "flácido",
      "bulhas rítmicas"
    ],
    "Localização ou Região Corporal": [
      "Abdomen"
    ],
    "Procedimento Laboratorial": [
      "Exames"
    ],
    "Função Patológica": [
      "alteração da função renal",
      "alergia a medicamentos"
    ],
    "Resultado Laboratorial ou de Teste": [
      "Cr 1 , 2",
      "ClCr 47ml/min",
      "Hb glicada 8 , 9%",
      "LDFL 109",
      "relação albumina / creatinina 759mg/g",
      "CT 187",
      "TGL 110",
      "HDL 56",
      "Hb 13 , 6",
      "proteínas 25mg/dl"
    ],
    "Conceito Temporal": [
      "há 5 anos",
      "há 25 anos",
      "há 15 anos"
    ],
    "Procedimento Diagnóstico": [
      "Exame físico"
    ]
  },
  "labels": {
    "dlp": {
      "capitulo": "11"
    },
    "hematúria": {
      "capitulo": "21"
    },
    "insulino-dependente": {
      "capitulo": "05"
    },
    "flácido": {
      "capitulo": "15"
    },
    "has": {
      "capitulo": "11"
    },
    "sopros": {
      "capitulo": "09"
    },
    "globoso": {
      "capitulo": "14"
    },
    "alteração da função renal": {
      "capitulo": "11"
    },
    "hipotireoidismo": {
      "capitulo": "05"
    },
    "dm": {
      "capitulo": "05"
    },
    "bulhas rítmicas": {
      "capitulo": "09"
    }
  }
}