{
  "prontuario_id": 480,
  "text": "64 anos, Natural de Curitiba, trabalha com Artesanato Acompamento de Nefropatia diabetica há 6 meses Encaminhada da unidade de saude da Vila São Paulo Diabetica há 20 anos Insulino dependente há 15 anos Relata dor lombar com irradiação para coxa direita. Sem alivio, uso de gabapentina 300mg  de 8/8h NPH 38 U de manha, 10U no almoço e 16U a noite Regular 22U pela manha, 14 U no almoço e 4U a noite Meformina 850mg  8/8h  Medicamentos NPH 38 U de manha, 10U no almoço e 16U a noite Regular 22U pela manha, 14 U no almoço e 4U a noite Meformina 850mg  8/8h Fenofibrato 250mg 1x ao dia de noite AAS 100mg  Enalapril 10mg : 2 cp 12/12h Anlodipino 5mg : 1 cp 12/12h Hidroclorotiazda 25mg: 1x ao dia Gabapentina 300g : 8/8h Genfibrozila 900 mg  Exames : Creatinina : 0,5  CKD-EPI CREATININE (2009)  105 Glicose de Jejum : 159 hemoglobina Glicada 8,36% Colesterol Total : 155 LDL : 83 Triglicerideos : 162 HDL : 40 Potassio : 4,6 Ureia : 27 Microalbuminuria  142,8mg / 24h Hemograma; Serie Vermelha normal, Serie Branca:  Leucocitose com linfocitose  Parcial de Urina : Glicosuria ++++/4. Nega diabetes e HAS na familia. HAS há 6 anos Trigliceridemia isolada Fratura de vertebra lombar ( L1 ) há 1 ano e 5 meses Cirurgia de Catarata há 1 ano Colecistectomia há 20 anos ITU há 1 ano, tratamento com antibioticoterapia por 7 dias Nega tabagismo e etilismo",
  "entities": {
    "Atividade Ocupacional": [
      "Artesanato"
    ],
    "Atividade de Assistência à Saúde": [
      "Acompamento",
      "Encaminhada",
      "tratamento"
    ],
    "Sinal ou Sintoma": [
      "Diabetica",
      "irradiação",
      "Insulino dependente"
    ],
    "Doença ou Síndrome": [
      "Diabetica",
      "diabetes",
      "HAS",
      "Trigliceridemia",
      "ITU",
      "tabagismo",
      "etilismo",
      "Nefropatia diabetica"
    ],
    "Localização ou Região Corporal": [
      "lombar"
    ],
    "Negação": [
      "Sem",
      "Nega"
    ],
    "Achado": [
      "alivio",
      "Serie Vermelha normal"
    ],
    "Substância Química Orgânica": [
      "gabapentina",
      "Meformina",
      "Fenofibrato",
      "AAS",
      "Anlodipino",
      "Gabapentina"
    ],
    "Substância Farmacológica": [
      "gabapentina",
      "NPH",
      "Regular",
      "Meformina",
      "Medicamentos",
      "Fenofibrato",
      "AAS",
      "Enalapril",
      "Anlodipino",
      "Hidroclorotiazda",
      "Gabapentina",
      "Genfibrozila"
    ],
    "Conceito Temporal": [
      "8/8h",
      "manha",
      "almoço",
      "noite",
      "12/12h",
      "há 6 meses",
      "há 20 anos",
      "há 15 anos",
      "1x ao dia",
      "há 6 anos",
      "há 1 ano e 5 meses",
      "há 1 ano",
      "20 anos"
    ],
    "Aminoácido, Peptídeo ou Proteína": [
      "NPH",
      "Regular",
      "Enalapril"
    ],
    "Hormônio": [
      "NPH",
      "Regular"
    ],
    "Abreviação": [
      "NPH",
      "AAS",
      "HAS",
      "ITU",
      "1 cp"
    ],
    "Conceito Quantitativo": [
      "100mg",
      "10mg",
      "5mg",
      "38 U",
      "14 U",
      "2 cp",
      "1 cp",
      "900 mg"
    ],
    "Procedimento Laboratorial": [
      "Exames",
      "Hemograma"
    ],
    "Grupo Familiar": [
      "familia"
    ],
    "Conceito Qualitativo": [
      "isolada"
    ],
    "Procedimento Terapêutico ou Preventivo": [
      "Colecistectomia",
      "antibioticoterapia",
      "Cirurgia de Catarata"
    ],
    "Disfunção Mental ou Comportamental": [
      "tabagismo",
      "etilismo"
    ],
    "Organização Relacionada à Saúde": [
      "unidade de saude"
    ],
    "Parte do Corpo, Órgão ou Componente Orgânico": [
      "coxa direita"
    ],
    "Resultado Laboratorial ou de Teste": [
      "Creatinina : 0 , 5",
      "CKD-EPI CREATININE ( 2009 ) 105",
      "Glicose de Jejum : 159",
      "hemoglobina Glicada 8 , 36%",
      "Colesterol Total : 155",
      "LDL : 83",
      "Triglicerideos : 162",
      "HDL",
      "Potassio : 4 , 6",
      "Ureia : 27",
      "Microalbuminuria 142 , 8mg / 24h",
      "Serie Vermelha normal",
      "Serie Branca : Leucocitose com linfocitose",
      "Glicosuria ++++/4"
    ],
    "Procedimento Diagnóstico": [
      "Parcial de Urina"
    ],
    "Função Patológica": [
      "Glicosuria ++++/4"
    ]
  },
  "labels": {
    "trigliceridemia": {
      "capitulo": "11"
    },
    "has": {
      "capitulo": "11"
    },
    "diabetes": {
      "capitulo": "05"
    },
    "glicosuria ++++/4": {
      "capitulo": "21"
    },
    "itu": {
      "capitulo": "22"
    },
    "irradiação": {
      "capitulo": "08"
    },
    "insulino dependente": {
      "capitulo": "05"
    },
    "nefropatia diabetica": {
      "capitulo": "16"
    }
  }
}