{
  "prontuario_id": 673,
  "text": "Homem, 69 anos, retorno com exames. HMP : DM há 10 anos, HAS há 10 anos e dislipidemia. Faz uso de sinvastatina 30 mg, Ferro 250 mg, Diovan 160 mg, Metformina 850 mg, AAS 1 cp no almoço. Cx de prótese de quadril em março de 2013 e cx para correçao de fratura em calâneo há 10 anos. Nega pé diabético, nega edema. HMF : Pai hipertenso, tio com CA de estômago CHV : ex tabagista 45 anos / maço ( parou há 10 anos ) RS : Dificuldade para controlar esfíncter - não controla evacuação.   Exame físico : BEG, LOTE, corado, hidratado PA : 139/75 mmHg FC : 75 bpm Peso; 79 Kg Altura : 1,63 m  Exames : Creatinina : 1,5 Uréia : 66 CKD/EPI : 47 Hemoglobina : 10,8 Ht : 33,4% Leucócitos : 13050 Glicemia : 90 Calcio ionico : 1,28 Fosforo : 4,3 Potassio : 4,8 Sodio : 138 Ácido Úrico : 7,1  Conduta : pedidos exames - HbA1c - Glicemia - Relação albumina / creatinina em amostra de urina isolada - Ferritina - IRST - PTH - 25O H vitamina D - Lipidograma",
  "entities": {
    "Atributo Clínico": [
      "Homem",
      "PA",
      "FC",
      "Peso",
      "Altura"
    ],
    "Atividade de Assistência à Saúde": [
      "retorno",
      "pedidos"
    ],
    "Resultado Laboratorial ou de Teste": [
      "exames",
      "Creatinina : 1 , 5",
      "Uréia : 66",
      "CKD/EPI : 47",
      "Hemoglobina : 10 , 8",
      "Ht : 33 , 4%",
      "Leucócitos : 13050",
      "Glicemia : 90",
      "Calcio ionico : 1 , 28",
      "Fosforo : 4 , 3",
      "Potassio : 4 , 8",
      "Sodio : 138",
      "Ácido Úrico : 7 , 1"
    ],
    "Procedimento Diagnóstico": [
      "exames",
      "Exame físico"
    ],
    "Achado": [
      "HMP",
      "HMF",
      "CHV",
      "RS",
      "BEG",
      "LOTE",
      "corado",
      "hidratado",
      "ex tabagista",
      "controla evacuação"
    ],
    "Abreviação": [
      "HMP",
      "DM",
      "HAS",
      "AAS",
      "cx",
      "HMF",
      "CHV",
      "RS",
      "BEG",
      "LOTE",
      "PA",
      "FC",
      "IRST",
      "1 cp",
      "Cx de prótese de quadril",
      "CA de estômago",
      "Ht : 33 , 4%"
    ],
    "Doença ou Síndrome": [
      "DM",
      "HAS",
      "dislipidemia",
      "hipertenso",
      "pé diabético"
    ],
    "Substância Farmacológica": [
      "sinvastatina",
      "Ferro",
      "Diovan",
      "Metformina",
      "AAS"
    ],
    "Substância Química Orgânica": [
      "sinvastatina",
      "Diovan",
      "Metformina",
      "AAS"
    ],
    "Elemento, Íon ou Isótopo": [
      "Ferro"
    ],
    "Substância Biologicamente Ativa": [
      "Ferro"
    ],
    "Conceito Temporal": [
      "almoço",
      "há 10 anos"
    ],
    "Procedimento Terapêutico ou Preventivo": [
      "cx",
      "correçao",
      "Cx de prótese de quadril"
    ],
    "Negação": [
      "Nega",
      "nega",
      "não"
    ],
    "Sinal ou Sintoma": [
      "edema",
      "pé diabético",
      "Dificuldade para controlar esfíncter"
    ],
    "Função Patológica": [
      "edema"
    ],
    "Grupo Familiar": [
      "Pai",
      "tio"
    ],
    "Evento": [
      "parou"
    ],
    "Procedimento Laboratorial": [
      "Exames",
      "exames",
      "HbA1c",
      "Glicemia",
      "Ferritina",
      "IRST",
      "PTH",
      "Lipidograma",
      "Relação albumina / creatinina em amostra de urina isolada",
      "25O H vitamina D"
    ],
    "Produto Intelectual": [
      "Conduta"
    ],
    "Conceito Quantitativo": [
      "30 mg",
      "250 mg",
      "160 mg",
      "850 mg",
      "1 cp",
      "45 anos / maço",
      "139/75 mmHg",
      "75 bpm",
      "79 Kg",
      "1 , 63 m"
    ],
    "Lesão ou Envenenamento": [
      "fratura em calâneo"
    ],
    "Processo Neoplásico": [
      "CA de estômago"
    ]
  },
  "labels": {
    "ca de estômago": {
      "capitulo": "02"
    },
    "fratura em calâneo": {
      "capitulo": "15"
    },
    "dificuldade para controlar esfíncter": {
      "capitulo": "21"
    },
    "chv": {
      "capitulo": "06"
    },
    "hmp": {
      "capitulo": "05"
    },
    "controla evacuação": {
      "capitulo": "21"
    },
    "rs": {
      "capitulo": "06"
    },
    "hmf": {
      "capitulo": "05"
    },
    "dislipidemia": {
      "capitulo": "11"
    },
    "hipertenso": {
      "capitulo": "11"
    },
    "has": {
      "capitulo": "05"
    },
    "dm": {
      "capitulo": "05"
    }
  }
}