{
  "prontuario_id": 870,
  "text": "Lucas, 61 ANOS\n# IC ETIOLOGIA ISQUEMICA\n# IAM EM 27/08/2010\n# POT ATC C STENT\n# POT RVM 2011 MIE - DA / SF - DIAG\n# EM USO DE:\n- CARVEDILOL 25MG 12/12HS\n- ROSUVA 10\n- VALSARTAN 320\n- FURO 40\n- APRESOLINA 50MG 12/12HS\n- ESPIRO 25\n- AAS 100\n- MONOC 20MG NOITE\n- MTF 850 3X\n- LEVOTIROX 50\n- INDAPAMIDA 1,5\nS # RELATA DISPNEIA PARA GRANDES ESFORÇOS. NEGA DOR PRECORDIAL, EDEMA DE MMII, ORTOPNEIA E DPN.\n- CINTILO (06/10/14): HIPOPERFUSÃO PERSISTENTE ( FIBROSE ) DE GRANDE EXTENSÃO, NO SEGMENTO MEDIOAPICAL DA PAREDE ANTERIOR E ÁPICE\nDE VE, EM GRAU DISCRETO NA PAREDE ANTEROSSEPTAL. FE REPOUSO 49%\n- ECO 17/09/15: AE 42, VD 26, SE 10, PP 9, DD 55, DS 46, FE 34%, PSAP 49 MMHG. VE ACINESIA ANTERO-SEPTAL E ANTERIOR MEDIO-APICAL E APICAL.\nO # PA 110/70, FC 80 SAT 96%\nCORADO, HIDRATADO, EUPNEICO\nBCRNFSS2T\nMV+ SIM BILART SRA\nABD SP \nMMII S EDEMA\nA # IC ISQUEMICA\nP # MANTENHO MEDICAÇÕES\n- SOLICITO NOVOS EXAMES LABORATORIAIS E ECOCARDIO TT\n- RETORNO 8 MESES\n E4 CARDIO Doutor Vital Brazil \n \n \n \n ",
  "entities": {
    "Abreviação": [
      "IAM",
      "POT",
      "ATC",
      "RVM",
      "MIE",
      "DA",
      "SF",
      "DIAG",
      "12/12HS",
      "ROSUVA",
      "FURO",
      "ESPIRO",
      "AAS",
      "MONOC",
      "MTF",
      "3X",
      "LEVOTIROX",
      "MMII",
      "DPN",
      "CINTILO",
      "ECO",
      "PA",
      "FC",
      "BCRNFSS2T",
      "SRA",
      "S",
      "CARDIO",
      "IC ETIOLOGIA ISQUEMICA",
      "SEGMENTO MEDIOAPICAL DA PAREDE ANTERIOR E ÁPICE DE VE",
      "FE REPOUSO 49%",
      "AE 42",
      "VD 26",
      "SE 10",
      "PP 9",
      "DD 55",
      "DS 46",
      "FE 34%",
      "PSAP 49 MMHG",
      "VE ACINESIA ANTERO-SEPTAL E ANTERIOR MEDIO-APICAL E APICAL",
      "MV+ SIM BILART",
      "IC ISQUEMICA",
      "ECOCARDIO TT"
    ],
    "Doença ou Síndrome": [
      "IAM",
      "IC ETIOLOGIA ISQUEMICA",
      "IC ISQUEMICA"
    ],
    "Conceito Temporal": [
      "POT",
      "12/12HS",
      "NOITE",
      "3X",
      "MESES"
    ],
    "Procedimento Terapêutico ou Preventivo": [
      "ATC",
      "STENT",
      "RVM",
      "MEDICAÇÕES"
    ],
    "Dispositivo Médico": [
      "STENT"
    ],
    "Localização ou Região Corporal": [
      "MIE",
      "MMII",
      "ABD"
    ],
    "Parte do Corpo, Órgão ou Componente Orgânico": [
      "DA",
      "SF",
      "DIAG"
    ],
    "Substância Química Orgânica": [
      "CARVEDILOL",
      "ROSUVA",
      "VALSARTAN",
      "FURO",
      "APRESOLINA",
      "ESPIRO",
      "AAS",
      "MONOC",
      "MTF",
      "INDAPAMIDA"
    ],
    "Substância Farmacológica": [
      "CARVEDILOL",
      "ROSUVA",
      "VALSARTAN",
      "FURO",
      "APRESOLINA",
      "ESPIRO",
      "AAS",
      "MONOC",
      "MTF",
      "LEVOTIROX",
      "INDAPAMIDA",
      "MEDICAÇÕES"
    ],
    "Conceito Quantitativo": [
      "25MG",
      "12/12HS",
      "10",
      "320",
      "40",
      "50MG",
      "25",
      "100",
      "20MG",
      "850",
      "3X",
      "50",
      "110/70",
      "80",
      "96%",
      "8",
      "1 , 5"
    ],
    "Hormônio": [
      "LEVOTIROX"
    ],
    "Negação": [
      "NEGA",
      "SRA",
      "SP",
      "S"
    ],
    "Sinal ou Sintoma": [
      "EDEMA",
      "ORTOPNEIA",
      "DPN",
      "DISPNEIA PARA GRANDES ESFORÇOS",
      "DOR PRECORDIAL"
    ],
    "Procedimento Diagnóstico": [
      "CINTILO",
      "ECO",
      "ECOCARDIO TT"
    ],
    "Atributo Clínico": [
      "PA",
      "FC",
      "SAT"
    ],
    "Achado": [
      "CORADO",
      "HIDRATADO",
      "EUPNEICO",
      "BCRNFSS2T",
      "SRA",
      "MV+ SIM BILART"
    ],
    "Atividade de Assistência à Saúde": [
      "MANTENHO",
      "SOLICITO",
      "RETORNO"
    ],
    "Resultado Laboratorial ou de Teste": [
      "HIPOPERFUSÃO PERSISTENTE ( FIBROSE ) DE GRANDE EXTENSÃO",
      "SEGMENTO MEDIOAPICAL DA PAREDE ANTERIOR E ÁPICE DE VE",
      "GRAU DISCRETO NA PAREDE ANTEROSSEPTAL",
      "FE REPOUSO 49%",
      "AE 42",
      "VD 26",
      "SE 10",
      "PP 9",
      "DD 55",
      "DS 46",
      "FE 34%",
      "PSAP 49 MMHG",
      "VE ACINESIA ANTERO-SEPTAL E ANTERIOR MEDIO-APICAL E APICAL"
    ],
    "Procedimento Laboratorial": [
      "EXAMES LABORATORIAIS"
    ]
  },
  "labels": {
    "ortopneia": {
      "capitulo": "11"
    },
    "edema": {
      "capitulo": "14"
    },
    "sra": {
      "capitulo": "X"
    },
    "dor precordial": {
      "capitulo": "21"
    },
    "dpn": {
      "capitulo": "21"
    },
    "dispneia para grandes esforços": {
      "capitulo": "12"
    },
    "iam": {
      "capitulo": "11"
    },
    "ic etiologia isquemica": {
      "capitulo": "11"
    },
    "ic isquemica": {
      "capitulo": "11"
    }
  }
}