{
  "prontuario_id": 75,
  "text": "Lucas, 63 ANOS\nCOMORBIDADES:\n# MCP DILATADA / CHAGAS\n# HAS\n# DISLIPIDEMIA\n# MARCA-PASSO HÁ 5 ANOS --> 11 MESES DE BATERIA\n# DAC FAMILIAR\n# CHV: EX-TABAGISTA DE 38 MAÇOS-ANO\nLucas, 63 ANOS\nCOMORBIDADES:\n# MCP DILATADA/CHAGAS\n# HAS\n# DISLIPIDEMIA\n# MARCA-PASSO HÁ 5 ANOS --> 11 MESES DE BATERIA\n# DAC FAMILIAR\n# CHV: EX-TABAGISTA DE 38 MAÇOS-ANO\nCATE DO DIA 29/07/2014: PROTOCOLO PRÉ - TRANSPLANTE CARDÍACO REALIZADO COM SUCESSO; RVP WOOD POSITIVA: CANDIDATO A TRANSPLANTE\nS # MANTEM-SE EM CLASSE FUNCIONAL III. RELATA EDEMA DE MMII. NEGA PRECORDIALGIA. \nMEDICAMENTOS:\n# ENALAPRIL 10 MG; 1/2 CP DE 12/12 HORAS\n# APRESOLINA 50 MG 1 CP DE 8/8 HORAS\n# MONOCORDL 20 MG 1 CP AS 8 E OUTRO AS 14 HORAS\n# ESPIRONOLACTONA 25 MG 1 CP AO DIA\n# FUROSEMIDA 40 MG 1 CP AS 8 E OUTRO AS 14 HORAS\n# CARVEDILOL 25 MG 1 CP DE 12/12 HORAS\n# SINVASTATINA 20 MG 1 CP A NOITE\nExame Físico\nPA 90/70 mmHG FC 76bpm, FR 18bpm\nACV: BCRNF SS EM FOCO TRICUSPIDE 3+ / 6+, SS EM FOCO MITRLA 2+ / 6+\nAP: MV+ BILAT, SEM RA\nABD: GLOBOSO, FLÁCIDO, PIPAROTE +\nEdema em MMII ++/++++\nA # IC CF III\nP # AUMENTO FSM PARA 80MG / 40MG\n-  DEMAIS MANTISO\nR4 CARDIO Doutor Vital Brazil ",
  "entities": {
    "Doença ou Síndrome": [
      "COMORBIDADES",
      "CHAGAS",
      "HAS",
      "DISLIPIDEMIA",
      "DAC",
      "MCP DILATADA",
      "MCP DILATADA/CHAGAS",
      "IC CF III"
    ],
    "Abreviação": [
      "HAS",
      "DAC",
      "CHV",
      "CATE",
      "MMII",
      "PA",
      "FC",
      "FR",
      "ACV",
      "BCRNF",
      "SS",
      "AP",
      "RA",
      "ABD",
      "FSM",
      "MCP DILATADA",
      "MCP DILATADA/CHAGAS",
      "RVP WOOD POSITIVA",
      "1/2 CP",
      "1 CP",
      "MV+ BILAT",
      "PIPAROTE +",
      "IC CF III"
    ],
    "Dispositivo Médico": [
      "MARCA-PASSO"
    ],
    "Procedimento Terapêutico ou Preventivo": [
      "MARCA-PASSO",
      "CATE",
      "TRANSPLANTE CARDÍACO"
    ],
    "Grupo Familiar": [
      "FAMILIAR"
    ],
    "Achado": [
      "CHV",
      "EX-TABAGISTA",
      "SUCESSO",
      "BCRNF",
      "SS",
      "FLÁCIDO",
      "MV+ BILAT"
    ],
    "Procedimento Diagnóstico": [
      "CATE",
      "Exame Físico"
    ],
    "Conceito Temporal": [
      "PRÉ",
      "12/12 HORAS",
      "8/8 HORAS",
      "A NOITE"
    ],
    "Atividade de Assistência à Saúde": [
      "REALIZADO",
      "AUMENTO"
    ],
    "Sinal ou Sintoma": [
      "EDEMA",
      "PRECORDIALGIA",
      "SS",
      "RA",
      "GLOBOSO",
      "Edema",
      "RVP WOOD POSITIVA",
      "PIPAROTE +"
    ],
    "Localização ou Região Corporal": [
      "MMII",
      "ABD",
      "FOCO TRICUSPIDE",
      "FOCO MITRLA"
    ],
    "Negação": [
      "NEGA",
      "SEM"
    ],
    "Substância Farmacológica": [
      "MEDICAMENTOS",
      "ENALAPRIL",
      "APRESOLINA",
      "MONOCORDL",
      "ESPIRONOLACTONA",
      "FUROSEMIDA",
      "CARVEDILOL",
      "SINVASTATINA",
      "FSM"
    ],
    "Aminoácido, Peptídeo ou Proteína": [
      "ENALAPRIL"
    ],
    "Atributo Clínico": [
      "PA",
      "FC",
      "FR",
      "ACV",
      "AP"
    ],
    "Conceito Quantitativo": [
      "76bpm",
      "18bpm",
      "++/++++",
      "80MG",
      "40MG",
      "38 MAÇOS-ANO",
      "10 MG",
      "1/2 CP",
      "50 MG",
      "1 CP",
      "20 MG",
      "25 MG",
      "40 MG",
      "90/70 mmHG",
      "3+ / 6+",
      "2+ / 6+"
    ],
    "Sistema Corporal": [
      "ACV"
    ],
    "Resultado Laboratorial ou de Teste": [
      "++/++++",
      "CANDIDATO A TRANSPLANTE",
      "FOCO TRICUSPIDE",
      "PIPAROTE +"
    ],
    "Conceito Qualitativo": [
      "CLASSE FUNCIONAL III"
    ]
  },
  "labels": {
    "ra": {
      "capitulo": "11"
    },
    "flácido": {
      "capitulo": "11"
    },
    "ic cf iii": {
      "capitulo": "V"
    },
    "rvp wood positiva": {
      "capitulo": "11"
    },
    "chagas": {
      "capitulo": "03"
    },
    "mv+ bilat": {
      "capitulo": "08"
    },
    "chv": {
      "capitulo": "17"
    },
    "ex-tabagista": {
      "capitulo": "24"
    },
    "piparote +": {
      "capitulo": "21"
    },
    "mcp dilatada/chagas": {
      "capitulo": "03"
    },
    "precordialgia": {
      "capitulo": "11"
    },
    "ss": {
      "capitulo": "08"
    },
    "dac": {
      "capitulo": "16"
    },
    "comorbidades": {
      "capitulo": "24"
    },
    "bcrnf": {
      "capitulo": "08"
    },
    "dislipidemia": {
      "capitulo": "05"
    },
    "edema": {
      "capitulo": "11"
    },
    "has": {
      "capitulo": "04"
    },
    "globoso": {
      "capitulo": "21"
    },
    "mcp dilatada": {
      "capitulo": "03"
    }
  }
}