{
  "prontuario_id": 889,
  "text": "50 ANOS.\n# HAS.\n# ULCERA PEPTICA.\n# MUD: ATENOLOL 25mg 3X / DIA.\n# PALPITAÇÃO AOS MODERADOS ESFORÇOS, DURAÇÃO DE  POUCOS MINUTOS, 3 EPISODIOS POR DIA, MELHORA ESPONTANEA. \nMELHORA DAS DEMAIS QUEIXAS - DISPNEIA AOS MODERADOS ESFORÇOS ASSOCIADA A QUEIMAÇÃO DA REGIÃO CERVICAL. \n# HMF + PARA DAC ( MÃE IAM AOS 45 ANOS ).\n# LAB (03/10/14): HDL 64, LDL 119, TRIGL 203, TSH 2,5, CT 224, CREATININA 0,94, GLICEMIA 74, HB 13,4, PLAQ 325,000.\n# ECG (04/02/14): RITMO SINUSAL, FC: 63 BPM, INTERVALO PR MÉDIO DE 160 mseg, EIXO +60 GRAUS.\nECOCARDIO 04/10/14: DENTRO DOS LIMITES DA NORMALIDADE, AE 36, VD 16, SEPTO 8, PPVE 8, VE 42 X 22, FE 79%.\nECG DE REPOUSO 12/09/14: TAQUICARDIA PAROXÍSTICA SUPRA VENTRICULAR.\n# PCTE EM BEG, NORMOCORADA, HIDRATADA.\nPA: 145/90mmHg.\nFC: 68bpm.\nBCRNF SS.\nCPP LIVRES.\nEDEMA DISCRETO EM MMII.\n# PLANO: SOLICITADO HOLTER 24HRS PARA AVALIAR FC EM 24 HRS.\nAUMENTADO DOSE DE ATENOLO PARA 100MG / DIA, OBSERVAR RELAÇÃO COM SINTOMAS PEO HOLTER.\nRETORNO EM 06 MESES.\n\n\n \n \n \n ",
  "entities": {
    "Abreviação": [
      "HAS",
      "MUD",
      "DAC",
      "IAM",
      "LAB",
      "ECG",
      "FC",
      "ECOCARDIO",
      "PCTE",
      "BEG",
      "PA",
      "BCRNF",
      "SS",
      "MMII",
      "HMF +",
      "TRIGL 203",
      "CT 224",
      "PLAQ 325 , 000",
      "AE 36",
      "VD 16",
      "PPVE 8",
      "VE 42 X 22",
      "FE 79%",
      "ECG DE REPOUSO",
      "CPP LIVRES",
      "HOLTER 24HRS"
    ],
    "Doença ou Síndrome": [
      "HAS",
      "DAC",
      "IAM",
      "ULCERA PEPTICA",
      "TAQUICARDIA PAROXÍSTICA SUPRA VENTRICULAR"
    ],
    "Substância Farmacológica": [
      "ATENOLOL",
      "ATENOLO"
    ],
    "Substância Química Orgânica": [
      "ATENOLOL",
      "ATENOLO"
    ],
    "Achado": [
      "MELHORA",
      "BEG",
      "NORMOCORADA",
      "HIDRATADA",
      "BCRNF",
      "SS",
      "MELHORA ESPONTANEA",
      "HMF +",
      "RITMO SINUSAL",
      "CPP LIVRES"
    ],
    "Sinal ou Sintoma": [
      "QUEIXAS",
      "QUEIMAÇÃO",
      "SINTOMAS",
      "PALPITAÇÃO AOS MODERADOS ESFORÇOS",
      "DISPNEIA AOS MODERADOS ESFORÇOS",
      "EDEMA DISCRETO"
    ],
    "Grupo Familiar": [
      "MÃE"
    ],
    "Procedimento Laboratorial": [
      "LAB"
    ],
    "Resultado Laboratorial ou de Teste": [
      "LAB",
      "HDL 64",
      "LDL 119",
      "TRIGL 203",
      "TSH 2 , 5",
      "CT 224",
      "CREATININA 0 , 94",
      "GLICEMIA 74",
      "HB 13 , 4",
      "PLAQ 325 , 000",
      "RITMO SINUSAL",
      "INTERVALO PR MÉDIO DE 160 mseg",
      "EIXO +60 GRAUS",
      "DENTRO DOS LIMITES DA NORMALIDADE",
      "AE 36",
      "VD 16",
      "SEPTO 8",
      "PPVE 8",
      "VE 42 X 22",
      "FE 79%",
      "TAQUICARDIA PAROXÍSTICA SUPRA VENTRICULAR"
    ],
    "Procedimento Diagnóstico": [
      "ECG",
      "ECOCARDIO",
      "HOLTER",
      "ECG DE REPOUSO",
      "HOLTER 24HRS"
    ],
    "Atributo Clínico": [
      "FC",
      "PA"
    ],
    "Conceito Quantitativo": [
      "145/90mmHg",
      "68bpm",
      "DOSE",
      "25mg 3X / DIA",
      "3 EPISODIOS POR DIA",
      "100MG / DIA"
    ],
    "Parte do Corpo, Órgão ou Componente Orgânico": [
      "MMII"
    ],
    "Atividade de Assistência à Saúde": [
      "PLANO",
      "SOLICITADO",
      "AVALIAR",
      "AUMENTADO",
      "OBSERVAR",
      "RETORNO"
    ],
    "Localização ou Região Corporal": [
      "REGIÃO CERVICAL"
    ]
  },
  "labels": {
    "melhora espontanea": {
      "capitulo": "06"
    },
    "ritmo sinusal": {
      "capitulo": "08"
    },
    "queixas": {
      "capitulo": "21"
    },
    "taquicardia paroxística supra ventricular": {
      "capitulo": "11"
    },
    "palpitação aos moderados esforços": {
      "capitulo": "11"
    },
    "ulcera peptica": {
      "capitulo": "13"
    },
    "dac": {
      "capitulo": "06"
    },
    "sintomas": {
      "capitulo": "21"
    },
    "queimação": {
      "capitulo": "14"
    },
    "edema discreto": {
      "capitulo": "15"
    },
    "iam": {
      "capitulo": "18"
    },
    "dispneia aos moderados esforços": {
      "capitulo": "12"
    },
    "has": {
      "capitulo": "06"
    },
    "melhora": {
      "capitulo": "06"
    },
    "hmf +": {
      "capitulo": "05"
    }
  }
}