{
  "prontuario_id": 939,
  "text": "Lucas, 51 anos\n# HAS\n# Ex-tabagista ( parou ha 23 anos) - 2 anos/maço.\n# Acompanha por taquicardia supra - ventricular paroxicistica.\nSubjetivo:\nPaciente relata que segue tendo ainda alguns episódios de palpitações. A sensação de palpitação se localiza em regiçao de epigastro. Ultimamente está com astenia, dispneia quando deambula 1 qua Doutor Vital Brazil pré - cordialgia. Nega dispneia paroxistica noturna. Hábitos fisiológicos preservados. Sono preservado.\nMedicamentos em uso: Atenolol 25 mg 2cp de 12/12h.\nHOLTER: arritmia ventricular complexa , com episodio de taquicardia ventricular não sustentada.\nObjetivo:\nBEG, LOC, MUC - acianótica.\nSem sopro carotideo.\nPA: 140/80,      FC: 72.\nAC; RR, 2t, BNF, sem sopro.\nAP: MVUD, sem ruidos adventicios.\nExt aquecidas, bem perfundidas, sem edema.\nImpressão:\nTVNS - sintomas esporádicos.\nConduta:\nSolicito estudo eletrofisiológicos. Aviso paciente da necessidade de parar atenolol 7 dias antes do exame.\nDoutor Vital Brazil ",
  "entities": {
    "Abreviação": [
      "HAS",
      "BEG",
      "LOC",
      "MUC",
      "PA",
      "FC",
      "AC",
      "RR",
      "2t",
      "BNF",
      "AP",
      "MVUD",
      "TVNS",
      "deambula 1 qua",
      "Ext aquecidas"
    ],
    "Doença ou Síndrome": [
      "HAS",
      "TVNS",
      "taquicardia supra - ventricular paroxicistica",
      "arritmia ventricular complexa"
    ],
    "Achado": [
      "Ex-tabagista",
      "BEG",
      "LOC",
      "MUC",
      "RR",
      "2t",
      "BNF",
      "MVUD",
      "deambula 1 qua",
      "Hábitos fisiológicos preservados",
      "Sono preservado",
      "Ext aquecidas",
      "bem perfundidas"
    ],
    "Atividade de Assistência à Saúde": [
      "Acompanha",
      "Conduta",
      "Solicito"
    ],
    "Conceito Temporal": [
      "episódios",
      "episodio",
      "antes",
      "parou ha 23 anos"
    ],
    "Sinal ou Sintoma": [
      "palpitações",
      "astenia",
      "dispneia",
      "acianótica",
      "sopro",
      "edema",
      "sensação de palpitação",
      "pré - cordialgia",
      "dispneia paroxistica noturna",
      "sopro carotideo",
      "ruidos adventicios",
      "sintomas esporádicos"
    ],
    "Grupo Profissional ou Ocupacional": [
      "Doutor"
    ],
    "Negação": [
      "Nega",
      "acianótica",
      "Sem",
      "sem"
    ],
    "Procedimento Terapêutico ou Preventivo": [
      "Medicamentos"
    ],
    "Substância Farmacológica": [
      "Medicamentos",
      "Atenolol",
      "atenolol"
    ],
    "Substância Química Orgânica": [
      "Atenolol",
      "atenolol"
    ],
    "Procedimento Diagnóstico": [
      "HOLTER",
      "AC",
      "AP",
      "exame",
      "estudo eletrofisiológicos"
    ],
    "Atributo Clínico": [
      "PA",
      "FC"
    ],
    "Conceito Quantitativo": [
      "140/80",
      "72",
      "2 anos/maço",
      "25 mg 2cp"
    ],
    "Localização ou Região Corporal": [
      "regiçao de epigastro"
    ],
    "Resultado Laboratorial ou de Teste": [
      "arritmia ventricular complexa",
      "taquicardia ventricular não sustentada"
    ]
  },
  "labels": {
    "deambula 1 qua": {
      "capitulo": "11"
    },
    "muc": {
      "capitulo": "14"
    },
    "sopro carotideo": {
      "capitulo": "11"
    },
    "dispneia paroxistica noturna": {
      "capitulo": "11"
    },
    "mvud": {
      "capitulo": "09"
    },
    "acianótica": {
      "capitulo": "14"
    },
    "ex-tabagista": {
      "capitulo": "24"
    },
    "arritmia ventricular complexa": {
      "capitulo": "08"
    },
    "tvns": {
      "capitulo": "21"
    },
    "sintomas esporádicos": {
      "capitulo": "21"
    },
    "taquicardia supra - ventricular paroxicistica": {
      "capitulo": "11"
    },
    "sopro": {
      "capitulo": "09"
    },
    "astenia": {
      "capitulo": "06"
    },
    "pré - cordialgia": {
      "capitulo": "08"
    },
    "loc": {
      "capitulo": "06"
    },
    "palpitações": {
      "capitulo": "21"
    },
    "dispneia": {
      "capitulo": "12"
    },
    "ruidos adventicios": {
      "capitulo": "11"
    },
    "edema": {
      "capitulo": "14"
    },
    "has": {
      "capitulo": "24"
    },
    "beg": {
      "capitulo": "06"
    },
    "sensação de palpitação": {
      "capitulo": "21"
    }
  }
}