{
  "prontuario_id": 179,
  "text": "Lucas, 77 ANOS\nCATETERISMO COM ANGIOPLASTIA EM 19/ABRIL/13\nHISTORIA DE HEMATURIA EM 2012\nSONDA DESDE JANEIRO. NAO CONSEGUE FICAR SEM SONDA - NAO CONSEGUE URINAR\nVEM À CONSULTA PARA AVALIAÇÃO PRÉ-OP. UROLOGISTA PEDE AVALIAÇÃO PARA CX DE \nCOMORBIDADES:\n\tDM\n\tHAS\n\tHIPOTIREOIDISMO\n\tDISLIPIDEMIA\nEM USO DE:\n\tAAS 100MG\n\tCLOPIDOGREL 75MG\n\tSINVASTATINA 40MG\n\tLOSARTANA 50MG\n\tSELOZOK 50MG\n\tLEVOTIROXINA 125MCG\n\tFINASTERIDA 5MG\n\tINSULINA\nNEGA ANGINA, NEGA DISPINEIA.\nNEGA TABAGISMO. EX-ETILISTA, PAROU HÁ MAIS DE 10 ANOS\nREFERE BOA ALIMENTAÇAO\nREFERE HABITO INTESTINAL MAIS RESSECADO. EVACUA A CADA 2 DIAS\nHX DE HEMORROIDA, SEM SANGRAMENTO RECENTES\nHX DE TUBERCULOSE HÁ MAIS DE 10 ANOS\nREFERE AMORTECIMENTO DE MEMBROS SUPERIORES\nAPENDICECTOMIA PREVIA HÁ MUITOS ANOS ( JUVENTUDE )\nEXAMES (15/08): LDL 47; HBA1C 7,6%; GLICOSE 71; UREIA 62; CREATININA 2; COLESTEROL TOTAL 138; TG 234; HDL 44; PROT TOTAIS 6,90; ALBUMINA 3,90; GLOBULINA 3,0; TSH 0,14; HB 15,5; PLAQUETAS 186,000\nAO EXAME:\nPA 170/100\nFC 66\nFR 22\nMV + , SEM RA\nBCRNFSS\nMEMBROS COM EDEMA +/4\nCONDUTA:\nSOLICITO CINTILOGRAFIA MIOCÁRDICA PARA AVALIAÇÃO DE RISCO CIRURGICO\nELETRONEUROMIOGRAFIA DE MEMBROS SUPERIORES\nRETORNO COM EXAMES\n \n \n \n ",
  "entities": {
    "Sinal ou Sintoma": [
      "HEMATURIA",
      "ANGINA",
      "DISPINEIA",
      "RESSECADO",
      "AMORTECIMENTO",
      "RA",
      "SANGRAMENTO RECENTES",
      "EDEMA +/4"
    ],
    "Dispositivo Médico": [
      "SONDA"
    ],
    "Negação": [
      "NAO",
      "SEM",
      "NEGA"
    ],
    "Função Fisiológica": [
      "URINAR",
      "HABITO INTESTINAL"
    ],
    "Atividade de Assistência à Saúde": [
      "CONSULTA",
      "AVALIAÇÃO",
      "SOLICITO",
      "RETORNO",
      "AVALIAÇÃO DE RISCO CIRURGICO"
    ],
    "Grupo Profissional ou Ocupacional": [
      "UROLOGISTA"
    ],
    "Abreviação": [
      "DM",
      "HAS",
      "AAS",
      "PA",
      "FC",
      "FR",
      "RA",
      "BCRNFSS",
      "AVALIAÇÃO PRÉ-OP",
      "CX DE COMORBIDADES",
      "LDL 47",
      "HBA1C 7 , 6%",
      "TG 234",
      "HDL 44",
      "PROT TOTAIS 6 , 90",
      "TSH 0 , 14",
      "HB 15 , 5",
      "MV +"
    ],
    "Doença ou Síndrome": [
      "DM",
      "HAS",
      "HIPOTIREOIDISMO",
      "DISLIPIDEMIA",
      "TABAGISMO"
    ],
    "Substância Farmacológica": [
      "AAS",
      "CLOPIDOGREL",
      "SINVASTATINA",
      "LOSARTANA",
      "SELOZOK",
      "LEVOTIROXINA",
      "FINASTERIDA",
      "INSULINA"
    ],
    "Substância Química Orgânica": [
      "AAS",
      "CLOPIDOGREL",
      "SINVASTATINA",
      "LOSARTANA",
      "SELOZOK",
      "LEVOTIROXINA",
      "FINASTERIDA"
    ],
    "Conceito Quantitativo": [
      "100MG",
      "75MG",
      "40MG",
      "50MG",
      "125MCG",
      "5MG",
      "170/100",
      "66",
      "22"
    ],
    "Hormônio": [
      "LEVOTIROXINA",
      "INSULINA"
    ],
    "Aminoácido, Peptídeo ou Proteína": [
      "LEVOTIROXINA"
    ],
    "Achado": [
      "EX-ETILISTA",
      "BCRNFSS",
      "BOA ALIMENTAÇAO",
      "EVACUA A CADA 2 DIAS",
      "HX DE TUBERCULOSE",
      "MV +"
    ],
    "Procedimento Terapêutico ou Preventivo": [
      "APENDICECTOMIA",
      "CATETERISMO COM ANGIOPLASTIA",
      "AVALIAÇÃO PRÉ-OP",
      "CX DE COMORBIDADES"
    ],
    "Procedimento Laboratorial": [
      "EXAMES"
    ],
    "Atributo Clínico": [
      "PA",
      "FC"
    ],
    "Resultado Laboratorial ou de Teste": [
      "EXAMES",
      "LDL 47",
      "HBA1C 7 , 6%",
      "GLICOSE 71",
      "UREIA 62",
      "CREATININA 2",
      "COLESTEROL TOTAL 138",
      "TG 234",
      "HDL 44",
      "PROT TOTAIS 6 , 90",
      "ALBUMINA 3 , 90",
      "GLOBULINA 3 , 0",
      "TSH 0 , 14",
      "HB 15 , 5",
      "PLAQUETAS 186"
    ],
    "Conceito Temporal": [
      "DESDE JANEIRO",
      "HÁ MAIS DE 10 ANOS",
      "HÁ MUITOS ANOS"
    ],
    "Procedimento Diagnóstico": [
      "AVALIAÇÃO PRÉ-OP",
      "CINTILOGRAFIA MIOCÁRDICA",
      "ELETRONEUROMIOGRAFIA DE MEMBROS SUPERIORES"
    ]
  },
  "labels": {
    "amortecimento": {
      "capitulo": "11"
    },
    "hipotireoidismo": {
      "capitulo": "05"
    },
    "ressecado": {
      "capitulo": "13"
    },
    "hx de tuberculose": {
      "capitulo": "01"
    },
    "mv +": {
      "capitulo": "11"
    },
    "edema +/4": {
      "capitulo": "15"
    },
    "bcrnfss": {
      "capitulo": "21"
    },
    "dislipidemia": {
      "capitulo": "05"
    },
    "evacua a cada 2 dias": {
      "capitulo": "13"
    },
    "hematuria": {
      "capitulo": "16"
    },
    "has": {
      "capitulo": "11"
    },
    "sangramento recentes": {
      "capitulo": "16"
    },
    "dm": {
      "capitulo": "11"
    }
  }
}