{
  "prontuario_id": 1000,
  "text": "IRC EM DIALISE NA SANTA CASA DE PONTA GROSSA\nFEZ TTO ATÉ 30/10 PARA ENDOCARDITE BACTERIANA ( LOCAL DA FAV )\nCDL EM JUGULAR INTERNA DIREITA HÁ 35 DIAS\nTEMPO DE 4H - PESO SECO 64KG\nEM USO DE RENAL GEL, CACO 3\nEF: \nFAV PROXIMA EM MMSS ESQUERDO HÁ 26 DIAS - COM DEISCENCIA DE 1 PONTO.\nPA 110*70\nPC BCRNF SS FTRI.\nMMII EDEMA +/4\nA: RETORNA COM EXAMES CARDIACOS\nCATETERISMO CARDIACO: 10/2013 CIRCULACAO COLATERAL SEM LESAO OBSTRUTIVA COM IRREGULARIDADE PAREITAL DIFUSA, VE C/ HIPOCINESIA DIFUSA DE GRAU MODERADO A SEVERO. IMi SEVERA.\nECOCARDIO 09 E 10/2013 REGURGITACAP ,OTRAÇ E TRICUSPIDE SEVERA, AUMENTO DE VE, V MITRAL COM VEGETAÇÃO HIPOCINESIA DIFUSA DO VE\nHVE E ACINESIA DA PÁREDE SEPTAL FUNCOA SISTOLICA PRESERVADA H PULMONAR. SEPTO 16 FE 48% EP25%. MASSA VE 534\nDOPPLER DE ILIACAS SEM ALTERACAO\nTE INEFICAZ\nUS: ASCITE DISCRETA. DEMAIS OK\nCMV IGG E IGM POS, TOXO E EBV IGG POS\nTTO DE ENDOCARDITE EM SETEMBRO AINDA COM VEGETACAO NO ECOCARDIO DE CONTROLE\nSEM EXAMES DA DIALISE\nCMV IGM: POSITIVO MAS ASSINTOMATICO\nP: AVALIAÇAO E LIBERACAO DA CARDIO\nAGUARDO LIBERACAO PARA ATIVAR EM LISTA\n \n \n \n ",
  "entities": {
    "Abreviação": [
      "IRC",
      "TTO",
      "FAV",
      "CDL",
      "EF",
      "PA",
      "PC",
      "BCRNF",
      "SS",
      "FTRI",
      "MMII",
      "HVE",
      "EP25%",
      "TE",
      "US",
      "TOXO",
      "ECOCARDIO",
      "CARDIO",
      "CACO 3",
      "VE C/ HIPOCINESIA DIFUSA DE GRAU MODERADO A SEVERO",
      "IMi SEVERA",
      "AUMENTO DE VE",
      "V MITRAL COM VEGETAÇÃO",
      "HIPOCINESIA DIFUSA DO VE",
      "H PULMONAR",
      "FE 48%",
      "MASSA VE 534",
      "CMV IGG E IGM",
      "EBV IGG",
      "CMV IGM : POSITIVO"
    ],
    "Doença ou Síndrome": [
      "IRC",
      "ENDOCARDITE",
      "ENDOCARDITE BACTERIANA",
      "IMi SEVERA"
    ],
    "Procedimento Terapêutico ou Preventivo": [
      "DIALISE",
      "TTO",
      "FAV",
      "CATETERISMO CARDIACO"
    ],
    "Anormalidade Anatômica": [
      "FAV"
    ],
    "Dispositivo Médico": [
      "CDL"
    ],
    "Conceito Quantitativo": [
      "64KG",
      "110*70"
    ],
    "Atributo Clínico": [
      "PA",
      "PC",
      "PESO SECO"
    ],
    "Achado": [
      "BCRNF",
      "DEISCENCIA DE 1 PONTO"
    ],
    "Negação": [
      "SS",
      "SEM",
      "ASSINTOMATICO"
    ],
    "Sinal ou Sintoma": [
      "SS",
      "ALTERACAO",
      "ASSINTOMATICO",
      "EDEMA +/4"
    ],
    "Parte do Corpo, Órgão ou Componente Orgânico": [
      "MMII",
      "JUGULAR INTERNA DIREITA"
    ],
    "Atividade de Assistência à Saúde": [
      "RETORNA",
      "AVALIAÇAO",
      "AGUARDO",
      "LIBERACAO",
      "ATIVAR EM LISTA"
    ],
    "Procedimento Diagnóstico": [
      "ECOCARDIO",
      "TE",
      "US",
      "CATETERISMO CARDIACO",
      "DOPPLER DE ILIACAS"
    ],
    "Resultado Laboratorial ou de Teste": [
      "REGURGITACAP",
      "HVE",
      "EP25%",
      "INEFICAZ",
      "CIRCULACAO COLATERAL SEM LESAO OBSTRUTIVA COM IRREGULARIDADE PAREITAL DIFUSA",
      "VE C/ HIPOCINESIA DIFUSA DE GRAU MODERADO A SEVERO",
      "OTRAÇ E TRICUSPIDE SEVERA",
      "AUMENTO DE VE",
      "V MITRAL COM VEGETAÇÃO",
      "HIPOCINESIA DIFUSA DO VE",
      "ACINESIA DA PÁREDE SEPTAL",
      "FUNCOA SISTOLICA PRESERVADA",
      "H PULMONAR",
      "SEPTO 16",
      "FE 48%",
      "MASSA VE 534",
      "ASCITE DISCRETA",
      "EXAMES DA DIALISE",
      "CMV IGM : POSITIVO"
    ],
    "Procedimento Laboratorial": [
      "TOXO",
      "EXAMES CARDIACOS",
      "CMV IGG E IGM",
      "EBV IGG"
    ],
    "Conceito Temporal": [
      "HÁ 35 DIAS",
      "HÁ 26 DIAS"
    ],
    "Substância Química Orgânica": [
      "RENAL GEL"
    ],
    "Substância Farmacológica": [
      "RENAL GEL",
      "CACO 3"
    ],
    "Substância Química Inorgânica": [
      "CACO 3"
    ]
  },
  "labels": {
    "irc": {
      "capitulo": "11"
    },
    "endocardite": {
      "capitulo": "11"
    },
    "imi severa": {
      "capitulo": "08"
    },
    "fav": {
      "capitulo": "21"
    },
    "alteracao": {
      "capitulo": "21"
    },
    "edema +/4": {
      "capitulo": "15"
    },
    "bcrnf": {
      "capitulo": "05"
    },
    "endocardite bacteriana": {
      "capitulo": "11"
    },
    "deiscencia de 1 ponto": {
      "capitulo": "21"
    },
    "ss": {
      "capitulo": "V"
    }
  }
}