{
  "prontuario_id": 410,
  "text": "PACIENTE EM PRIMEIRA CONSULTA ENCAMINHADA PARA CX DE CATARATA DE OE \nREFERE BAV PROGRESSIVA DE OE \nJÁ REALIZADO CX DE CATARATA EM OD EM 2005 NO HOSPITAL DE CLINICAS \nHAS HÁ 8 ANOS EM TTO CONTROLADA \nNEGA DM \nREFERE ARRITMIA CARDIACA FA EM ACOMPANHAMENTO \nECOGRAFIA DE OE 03/09/2013\nRETINA COLADA CENTRAL E PERIFERICAMENTE COM CAVIDADE VITREA SEM ALTERAÇÕES E MUSCULATURA OCULAR NORMAIS \nAV : 20/80 // VÊ VULTOS \nESQ: +1,00 ESF // DIFICIL DEVIDO OPACIDADE \nTOL: SEM MELHORA DA AV E PACIENTE NÃO COLABORATIVA \nBIO: OD LIO TOPICA COM CA CALMA E BEM FORMADA AO COM PUPILAS FOTOREAGENTES BILATERAL E SIMETRIACMENTE AO ; OE CATARATA IMPORTANTE \nFO: OD: PAPILA E MACULA NORMAIS \nOE : NÃO VISUALIZADO DEVIDO OPACIDADE DE MEIOS \nPIO: 15/16\nBIO:\nOE: CATARATA CAPSULAR ANTERIOR 4+/4 COM NUCLEAR 3+/4+ \nMR: DIFICL DEVIDO OPACIDADE DE MEIOS \nCDTA: PREENCHO APAC E SOLICITO EXAMES LABORATORIAIS . NO RETORNO REALIZAR NOVA CLASSIFICAÇÃO DE CATARATA EXTRA ??\nR1 Vital Brasil \nR3 Vital Brasil \n\n\n \n \n \n ",
  "entities": {
    "Paciente ou Grupo com Deficiência": [
      "PACIENTE"
    ],
    "Atividade de Assistência à Saúde": [
      "CONSULTA",
      "ENCAMINHADA",
      "ACOMPANHAMENTO",
      "CDTA",
      "PREENCHO",
      "SOLICITO",
      "RETORNO",
      "REALIZAR"
    ],
    "Parte do Corpo, Órgão ou Componente Orgânico": [
      "OE",
      "OD"
    ],
    "Abreviação": [
      "HAS",
      "TTO",
      "DM",
      "AV",
      "ESQ",
      "TOL",
      "BIO",
      "OD",
      "AO",
      "OE",
      "FO",
      "PIO",
      "MR",
      "CDTA",
      "APAC",
      "R1",
      "R3",
      "BAV PROGRESSIVA DE OE",
      "CX DE CATARATA EM OD",
      "ARRITMIA CARDIACA",
      "ECOGRAFIA DE OE",
      "+1 , 00 ESF",
      "MELHORA DA AV",
      "LIO TOPICA COM CA CALMA E BEM FORMADA"
    ],
    "Doença ou Síndrome": [
      "HAS",
      "DM",
      "CATARATA",
      "ARRITMIA CARDIACA"
    ],
    "Procedimento Terapêutico ou Preventivo": [
      "TTO",
      "CX DE CATARATA EM OD"
    ],
    "Conceito Qualitativo": [
      "CONTROLADA",
      "COLABORATIVA",
      "MELHORA DA AV"
    ],
    "Negação": [
      "NEGA",
      "SEM",
      "NÃO"
    ],
    "Procedimento Diagnóstico": [
      "AV",
      "ESQ",
      "TOL",
      "BIO",
      "FO",
      "PIO",
      "MR",
      "ECOGRAFIA DE OE"
    ],
    "Conceito Quantitativo": [
      "20/80",
      "15/16",
      "+1 , 00 ESF"
    ],
    "Sinal ou Sintoma": [
      "VULTOS",
      "DIFICIL DEVIDO OPACIDADE"
    ],
    "Regulamento ou Lei": [
      "APAC"
    ],
    "Grupo Profissional ou Ocupacional": [
      "R1",
      "R3"
    ],
    "Achado": [
      "BAV PROGRESSIVA DE OE"
    ],
    "Conceito Temporal": [
      "HÁ 8 ANOS"
    ],
    "Resultado Laboratorial ou de Teste": [
      "RETINA COLADA CENTRAL E PERIFERICAMENTE COM CAVIDADE VITREA SEM ALTERAÇÕES",
      "MUSCULATURA OCULAR NORMAIS",
      "LIO TOPICA COM CA CALMA E BEM FORMADA",
      "PUPILAS FOTOREAGENTES BILATERAL E SIMETRIACMENTE",
      "CATARATA IMPORTANTE",
      "PAPILA E MACULA NORMAIS",
      "NÃO VISUALIZADO DEVIDO OPACIDADE DE MEIOS",
      "CATARATA CAPSULAR ANTERIOR 4+/4 COM NUCLEAR 3+/4+",
      "DIFICL DEVIDO OPACIDADE DE MEIOS"
    ],
    "Procedimento Laboratorial": [
      "EXAMES LABORATORIAIS"
    ]
  },
  "labels": {
    "bav progressiva de oe": {
      "capitulo": "09"
    },
    "dificil devido opacidade": {
      "capitulo": "21"
    },
    "catarata": {
      "capitulo": "09"
    },
    "arritmia cardiaca": {
      "capitulo": "11"
    },
    "dm": {
      "capitulo": "05"
    }
  }
}