{
  "prontuario_id": 522,
  "text": "# Lucas, 58 anos\n# Comorbidades: HAS, Dislipidemia, Tabagismo 115 maços/ano\n# HMA: IAM ST - Killip I em 10 de junho de 2013. Realizado ATC com stent em DA com sucesso\n# Em uso de:\nAAS 100 mg - 1cp ao dia\nEnalapril 10 mg - 1 cp de 12/12h\nBrilinta 90 mg - 1 cp de 12/12h\nSelozok 50 mg - 2 cp ao dia\nSinvastatina 40 mg - 1 cp ao dia\nEspironolactona 25 mg- 1 cp ao dia\n# S: dispneia paroxística noturna e dispneia durante o dia também. angina leve\n# O:\nP = 84 bpm\nPA = 110x80 mmHg\nEstetores finos\n# A: paciente pós IAM evoluiu com dispneia paroxística noturna\n# P: Furosemida 40 mg - 1 cp ao dia\n       Ecocardiograma transtorácico\n       Espirometria\n \n \n \n ",
  "entities": {
    "Abreviação": [
      "HAS",
      "AAS",
      "1cp",
      "12/12h",
      "P",
      "PA",
      "IAM",
      "IAM ST",
      "1 cp",
      "2 cp",
      "84 bpm"
    ],
    "Doença ou Síndrome": [
      "HAS",
      "Dislipidemia",
      "Tabagismo",
      "IAM",
      "IAM ST",
      "angina leve"
    ],
    "Dispositivo Médico": [
      "stent"
    ],
    "Parte do Corpo, Órgão ou Componente Orgânico": [
      "DA"
    ],
    "Substância Farmacológica": [
      "AAS",
      "Enalapril",
      "Brilinta",
      "Selozok",
      "Sinvastatina",
      "Espironolactona",
      "Furosemida"
    ],
    "Substância Química Orgânica": [
      "AAS",
      "Enalapril",
      "Selozok",
      "Sinvastatina",
      "Espironolactona",
      "Furosemida"
    ],
    "Conceito Quantitativo": [
      "1cp",
      "115 maços/ano",
      "100 mg",
      "10 mg",
      "1 cp",
      "90 mg",
      "50 mg",
      "2 cp",
      "40 mg",
      "25 mg-",
      "84 bpm",
      "110x80 mmHg"
    ],
    "Conceito Temporal": [
      "dia",
      "12/12h",
      "pós"
    ],
    "Aminoácido, Peptídeo ou Proteína": [
      "Enalapril"
    ],
    "Ácido Nucleico, Nucleosídeo ou Nucleotídeo": [
      "Brilinta"
    ],
    "Sinal ou Sintoma": [
      "dispneia",
      "dispneia paroxística noturna",
      "angina leve",
      "Estetores finos"
    ],
    "Atributo Clínico": [
      "P",
      "PA"
    ],
    "Paciente ou Grupo com Deficiência": [
      "paciente"
    ],
    "Procedimento Diagnóstico": [
      "Espirometria",
      "Ecocardiograma transtorácico"
    ],
    "Classificação": [
      "Killip I"
    ]
  },
  "labels": {
    "has": {
      "capitulo": "11"
    },
    "iam": {
      "capitulo": "11"
    },
    "iam st": {
      "capitulo": "11"
    },
    "dispneia paroxística noturna": {
      "capitulo": "12"
    },
    "estetores finos": {
      "capitulo": "21"
    },
    "tabagismo": {
      "capitulo": "24"
    },
    "dispneia": {
      "capitulo": "12"
    },
    "angina leve": {
      "capitulo": "11"
    },
    "dislipidemia": {
      "capitulo": "05"
    }
  }
}