{
  "prontuario_id": 371,
  "text": "Lucas, 60 ANOS\n# HAS\n# DSLP\n# MIOCARDIOPATIA ISQUEMICA\n# 06/2013: IAMCSST - KILLIP I => ATC DA COM STENT COM SUCESSO\n# EX-TABAGISTA: 45MAÇOS/ANO PAROU QUANDO INFARTOU\n# EM USO DE: AAS 100MG, ENALAPRIL 10MG 12/12H; BRILINTA 90MG 12/12H; SELOZOK 150MG; SINVASTATINA 40MG / D; ESPIRONOLACTONA 25MG / D\n# ECOCARDIO 24/10/13: AE 44 // VD 25 // SEPTO 10 // VE 64 // FE 40% *\nVE AUMENTADO EM GRAU DISCRETO, PADRÃO DE HIPERTROFIA EXCENTRICA, DISFUNÇÃO SISTOLICA MODERADA. CONTRAÇÃO SEGMENTAR DO VE\nALTERADA. DISFUNÇÃO DIASTÓLICA GRAU II DO VE - RESTRITIVO AE AUMENTADO EM GRAU DISCRETO. INSUFICIENCIA MITRAL DISCRETA\nS # REFERE MELHORA DA DISPNEIA.\nAO EXAME:\nBEG, LOTE\nPA 140X80 MMHG FC 65\nAP  MVB+, DIFUSAMENTE DIMINUIDO, S RA\nAC BCRNF SS\nMMII SP\nEX LAB:\nCREAT 1,3; UR 71\nA # DAC IC ETIOLOGIA ISQUEMICA\nP #  ",
  "entities": {
    "Abreviação": [
      "HAS",
      "DSLP",
      "IAMCSST",
      "AAS",
      "12/12H",
      "D",
      "ECOCARDIO",
      "BEG",
      "LOTE",
      "PA",
      "FC",
      "AP",
      "MVB+",
      "S",
      "RA",
      "AC",
      "BCRNF",
      "SS",
      "MMII",
      "SP",
      "DAC",
      "ATC DA COM STENT",
      "AE 44",
      "VD 25",
      "VE 64",
      "FE 40%",
      "VE AUMENTADO EM GRAU DISCRETO",
      "CONTRAÇÃO SEGMENTAR DO VE ALTERADA",
      "DISFUNÇÃO DIASTÓLICA GRAU II DO VE - RESTRITIVO",
      "AE AUMENTADO EM GRAU DISCRETO",
      "EX LAB",
      "CREAT 1 , 3",
      "UR 71",
      "IC ETIOLOGIA ISQUEMICA"
    ],
    "Doença ou Síndrome": [
      "HAS",
      "DSLP",
      "IAMCSST",
      "INFARTOU",
      "DAC",
      "MIOCARDIOPATIA ISQUEMICA",
      "IC ETIOLOGIA ISQUEMICA"
    ],
    "Achado": [
      "EX-TABAGISTA",
      "MELHORA",
      "BEG",
      "LOTE",
      "MVB+",
      "BCRNF"
    ],
    "Conceito Quantitativo": [
      "45MAÇOS/ANO",
      "100MG",
      "10MG",
      "90MG",
      "150MG",
      "40MG",
      "25MG",
      "65",
      "140X80 MMHG"
    ],
    "Substância Farmacológica": [
      "AAS",
      "ENALAPRIL",
      "BRILINTA",
      "SELOZOK",
      "SINVASTATINA",
      "ESPIRONOLACTONA"
    ],
    "Substância Química Orgânica": [
      "AAS",
      "ENALAPRIL",
      "BRILINTA",
      "SELOZOK",
      "SINVASTATINA",
      "ESPIRONOLACTONA"
    ],
    "Aminoácido, Peptídeo ou Proteína": [
      "ENALAPRIL"
    ],
    "Conceito Temporal": [
      "12/12H",
      "D"
    ],
    "Ácido Nucleico, Nucleosídeo ou Nucleotídeo": [
      "BRILINTA"
    ],
    "Procedimento Diagnóstico": [
      "ECOCARDIO"
    ],
    "Sinal ou Sintoma": [
      "DISPNEIA",
      "RA",
      "SS",
      "SP",
      "DIFUSAMENTE DIMINUIDO"
    ],
    "Atributo Clínico": [
      "PA",
      "FC",
      "AP",
      "AC"
    ],
    "Negação": [
      "S",
      "SS",
      "SP"
    ],
    "Parte do Corpo, Órgão ou Componente Orgânico": [
      "MMII"
    ],
    "Classificação": [
      "KILLIP I"
    ],
    "Procedimento Terapêutico ou Preventivo": [
      "ATC DA COM STENT"
    ],
    "Resultado Laboratorial ou de Teste": [
      "AE 44",
      "VD 25",
      "SEPTO 10",
      "VE 64",
      "FE 40%",
      "VE AUMENTADO EM GRAU DISCRETO",
      "PADRÃO DE HIPERTROFIA EXCENTRICA",
      "DISFUNÇÃO SISTOLICA MODERADA",
      "CONTRAÇÃO SEGMENTAR DO VE ALTERADA",
      "DISFUNÇÃO DIASTÓLICA GRAU II DO VE - RESTRITIVO",
      "AE AUMENTADO EM GRAU DISCRETO",
      "INSUFICIENCIA MITRAL DISCRETA",
      "CREAT 1 , 3",
      "UR 71"
    ],
    "Procedimento Laboratorial": [
      "EX LAB"
    ]
  },
  "labels": {
    "dac": {
      "capitulo": "11"
    },
    "ss": {
      "capitulo": "V"
    },
    "iamcsst": {
      "capitulo": "11"
    },
    "ra": {
      "capitulo": "09"
    },
    "mvb+": {
      "capitulo": "08"
    },
    "has": {
      "capitulo": "21"
    },
    "difusamente diminuido": {
      "capitulo": "21"
    },
    "miocardiopatia isquemica": {
      "capitulo": "11"
    },
    "beg": {
      "capitulo": "V"
    },
    "dslp": {
      "capitulo": "06"
    },
    "ex-tabagista": {
      "capitulo": "24"
    },
    "bcrnf": {
      "capitulo": "09"
    },
    "sp": {
      "capitulo": "08"
    },
    "lote": {
      "capitulo": "X"
    },
    "ic etiologia isquemica": {
      "capitulo": "11"
    },
    "dispneia": {
      "capitulo": "12"
    }
  }
}