{
  "prontuario_id": 424,
  "text": "Lucas, 68 ANOS\nS # Primeira consulta.Paciente encaminhada po Doutor Vital Brazil cardiologista. Paciente realizou angiopplastia apos IAM há cerca de 01 mês. Refere sintomas depressivos, que segundo paciente, já existiam, no entanto exacerbaram desde então. Refere humor deprimido, choro facil,anedonia, avolia, ideação passiva de morte. Relata tratamento prévio por episodio depressivo há cerca de 04 anos - tomou fluoxetina 40 mg / dia e amitriptilina 25 mg / dia,e parou por conta propria.Refere diminuiçao do apetite e insonia intermediaria. Situação social complicada, é casada há 51 anos e esposo é alcoolatra e agride fisica e verbalmente a esposa \" ele nao da suporte nenhum,nem foi me ver no hospital \"( sic ).Tem dois filhos e alguns netos, que a ajudam. Nega episodio de hiperativção.\nCDTA # Prescrevo escitalopram 10 mg (1 - 0 - 0 )- forneço amostra de exodus, oriento iniciar com 1/2 cp ao dia e aumenta para 01 cp após uma semana. Retorno em janeiro para reavaliação.\nEEM # Asseada,cooperayiva, orientada alo e auto, normovigil, normotenaz, sem alt de sensopercepçao, humor hipotimico afeto congruente, critica e insght preservados.\n ",
  "entities": {
    "Atividade de Assistência à Saúde": [
      "consulta",
      "encaminhada",
      "CDTA",
      "Prescrevo",
      "forneço",
      "oriento",
      "aumenta",
      "Retorno",
      "reavaliação"
    ],
    "Paciente ou Grupo com Deficiência": [
      "Paciente",
      "paciente"
    ],
    "Grupo Profissional ou Ocupacional": [
      "Doutor",
      "cardiologista"
    ],
    "Doença ou Síndrome": [
      "IAM",
      "alcoolatra"
    ],
    "Conceito Qualitativo": [
      "exacerbaram",
      "facil",
      "preservados"
    ],
    "Sinal ou Sintoma": [
      "choro",
      "anedonia",
      "avolia",
      "hiperativção",
      "sintomas depressivos",
      "ideação passiva de morte",
      "episodio depressivo",
      "diminuiçao do apetite",
      "insonia intermediaria",
      "alt de sensopercepçao",
      "humor hipotimico"
    ],
    "Disfunção Mental ou Comportamental": [
      "anedonia",
      "avolia",
      "ideação passiva de morte",
      "episodio depressivo",
      "alt de sensopercepçao",
      "humor hipotimico"
    ],
    "Substância Farmacológica": [
      "fluoxetina",
      "amitriptilina",
      "escitalopram",
      "exodus"
    ],
    "Substância Química Orgânica": [
      "fluoxetina",
      "amitriptilina",
      "escitalopram",
      "exodus"
    ],
    "Conceito Temporal": [
      "dia",
      "há cerca de 01 mês",
      "há cerca de 04 anos",
      "após uma semana"
    ],
    "Grupo Familiar": [
      "esposo",
      "netos"
    ],
    "Negação": [
      "Nega",
      "sem"
    ],
    "Abreviação": [
      "CDTA",
      "EEM",
      "1/2 cp",
      "01 cp",
      "orientada alo e auto",
      "alt de sensopercepçao"
    ],
    "Substância Química Inorgânica": [
      "exodus"
    ],
    "Atributo Clínico": [
      "EEM"
    ],
    "Achado": [
      "Asseada",
      "cooperayiva",
      "normovigil",
      "normotenaz",
      "humor deprimido",
      "parou por conta propria",
      "diminuiçao do apetite",
      "Situação social complicada",
      "orientada alo e auto",
      "afeto congruente"
    ],
    "Processo Mental": [
      "critica",
      "insght"
    ],
    "Procedimento Terapêutico ou Preventivo": [
      "tratamento prévio"
    ],
    "Conceito Quantitativo": [
      "40 mg",
      "25 mg",
      "10 mg",
      "1 - 0 - 0",
      "1/2 cp",
      "01 cp"
    ],
    "Lesão ou Envenenamento": [
      "agride fisica e verbalmente"
    ]
  },
  "labels": {
    "alcoolatra": {
      "capitulo": "24"
    },
    "sintomas depressivos": {
      "capitulo": "06"
    },
    "hiperativção": {
      "capitulo": "06"
    },
    "insonia intermediaria": {
      "capitulo": "07"
    },
    "agride fisica e verbalmente": {
      "capitulo": "22"
    },
    "diminuiçao do apetite": {
      "capitulo": "21"
    },
    "humor deprimido": {
      "capitulo": "06"
    },
    "episodio depressivo": {
      "capitulo": "06"
    },
    "orientada alo e auto": {
      "capitulo": "24"
    },
    "iam": {
      "capitulo": "11"
    },
    "humor hipotimico": {
      "capitulo": "06"
    },
    "avolia": {
      "capitulo": "06"
    },
    "choro": {
      "capitulo": "06"
    },
    "parou por conta propria": {
      "capitulo": "24"
    },
    "situação social complicada": {
      "capitulo": "24"
    },
    "alt de sensopercepçao": {
      "capitulo": "21"
    },
    "anedonia": {
      "capitulo": "06"
    },
    "ideação passiva de morte": {
      "capitulo": "06"
    }
  }
}