{
  "prontuario_id": 811,
  "text": "Lucas, 65 ANOS\n# MCP dilatada - IDIOPÁTICA\nCF II-III OSCILANTE.\n** PROTOCOLO DE TX CARDIACO - INDICE CARDIACO 3,44 **\n*** Em uso de: Omeprazol 20mg / d, AAS 100mg / d, Losartan 50mg 12/12hs, Espironolactona 25mg / d, Hidralazina 100mg 12/12hs, Carvedilol 12,5mg 12/12hs\n# Exames:\nCAT 09/06/2014: ausência de coronariopatia obstrutiva crítica\nIC 3,449 pré / 3,602 pós\nRVP em woods 0,217 pré / 0,147 pós\nS # Dispnéia CF II. Nega dor torácica. Nega palpitação e síncope. Há cerca de 2 semanas suspendeu losartan por hipotensão sintomática (PAS 70-80). Atendimento na UPA por tosse seca e dor torácica precordial em queimação, duração de horas, sem relação com esforço físico ( ECG BRE, tropo negativa ). \nAo exame:\nPte em BEG, eupneico, corado, hidratado\nPA 100/60 mmHg\ndiscreta estase jugular a 45º\nMV+ bilateral sem RA\nRCR 2t SS ictus desviado \nSem VCM\nSem edema MMII\nBoa perfusão periférica\nA # MCP dilatada - CF II \nP # Oriento voltar com losartan e reduzo hidralazina 50 12/12hs. Retorno com lab em fev/15. \nE4 cardio Doutor Vital Brazil ",
  "entities": {
    "Substância Farmacológica": [
      "Omeprazol",
      "AAS",
      "Losartan",
      "Espironolactona",
      "Hidralazina",
      "Carvedilol",
      "losartan",
      "hidralazina"
    ],
    "Substância Química Orgânica": [
      "Omeprazol",
      "AAS",
      "Losartan",
      "Espironolactona",
      "Hidralazina",
      "Carvedilol",
      "losartan",
      "hidralazina"
    ],
    "Conceito Quantitativo": [
      "20mg",
      "100mg",
      "50mg",
      "25mg",
      "70-80",
      "50",
      "12 , 5mg",
      "100/60 mmHg"
    ],
    "Conceito Temporal": [
      "d",
      "12/12hs",
      "Há cerca de 2 semanas",
      "duração de horas"
    ],
    "Abreviação": [
      "d",
      "AAS",
      "12/12hs",
      "CAT",
      "PAS",
      "ECG",
      "BRE",
      "BEG",
      "PA",
      "VCM",
      "MMII",
      "lab",
      "cardio",
      "MCP dilatada - IDIOPÁTICA CF II-III OSCILANTE",
      "IC 3 , 449",
      "RVP em woods",
      "tropo negativa",
      "MV+ bilateral",
      "RCR 2t",
      "MCP dilatada - CF II"
    ],
    "Resultado Laboratorial ou de Teste": [
      "Exames",
      "BRE",
      "lab",
      "INDICE CARDIACO 3 , 44",
      "ausência de coronariopatia obstrutiva crítica",
      "IC 3 , 449",
      "RVP em woods",
      "0 , 217 pré / 0 , 147 pós",
      "tropo negativa"
    ],
    "Procedimento Diagnóstico": [
      "CAT",
      "ECG"
    ],
    "Sinal ou Sintoma": [
      "Dispnéia",
      "palpitação",
      "síncope",
      "RA",
      "SS",
      "VCM",
      "edema",
      "dor dor torácica torácica",
      "hipotensão sintomática",
      "tosse seca",
      "discreta estase jugular a 45º",
      "ictus desviado"
    ],
    "Negação": [
      "Nega",
      "sem",
      "SS",
      "Sem"
    ],
    "Atividade de Assistência à Saúde": [
      "suspendeu",
      "Oriento",
      "reduzo",
      "Retorno"
    ],
    "Localização ou Região Corporal": [
      "precordial"
    ],
    "Conceito Qualitativo": [
      "queimação"
    ],
    "Doença ou Síndrome": [
      "BRE",
      "MCP dilatada - IDIOPÁTICA CF II-III OSCILANTE",
      "MCP dilatada - CF II"
    ],
    "Paciente ou Grupo com Deficiência": [
      "Pte"
    ],
    "Achado": [
      "BEG",
      "eupneico",
      "corado",
      "hidratado",
      "MV+ bilateral",
      "RCR 2t",
      "Boa Boa perfusão perfusão periférica periférica"
    ],
    "Atributo Clínico": [
      "PA"
    ],
    "Parte do Corpo, Órgão ou Componente Orgânico": [
      "MMII"
    ],
    "Procedimento Laboratorial": [
      "lab"
    ],
    "Grupo Profissional ou Ocupacional": [
      "E4",
      "cardio",
      "Doutor"
    ],
    "Produto Intelectual": [
      "PROTOCOLO DE TX CARDIACO"
    ],
    "Função Patológica": [
      "hipotensão sintomática"
    ],
    "Atividade Diária ou Recreativa": [
      "esforço físico"
    ]
  },
  "labels": {
    "ra": {
      "capitulo": "11"
    },
    "discreta estase jugular a 45º": {
      "capitulo": "11"
    },
    "mcp dilatada - idiopática cf ii-iii oscilante": {
      "capitulo": "11"
    },
    "mcp dilatata - cf ii": {
      "capitulo": "11"
    },
    "mv+ bilateral": {
      "capitulo": "11"
    },
    "vcm": {
      "capitulo": "21"
    },
    "tosse seca": {
      "capitulo": "13"
    },
    "ss": {
      "capitulo": "21"
    },
    "dor dor torácica torácica": {
      "capitulo": "11"
    },
    "rcr 2t": {
      "capitulo": "21"
    },
    "palpitação": {
      "capitulo": "11"
    },
    "edema": {
      "capitulo": "15"
    },
    "dispnéia": {
      "capitulo": "11"
    },
    "ictus desviado": {
      "capitulo": "08"
    },
    "síncope": {
      "capitulo": "11"
    },
    "hipotensão sintomática": {
      "capitulo": "11"
    }
  }
}