{
  "prontuario_id": 670,
  "text": "Lucas, 65 ANOS\n\n# IC CF III EM ACOMPANHAMENTO COM Doutor Vital Brazil.\n# NEGA DM, DSLP, TABAGISMO, IAM´S PRÉVIOS\n# EM USO DE LST 50MG 12/12 H, CARVEDILOL 12,5MG 12/12 HORAS, APRESOLINA 50MG 8/8H, ESPIRONOLACTONA 25MG / DIA, OMP 20\n# ECOCARDIO COM STRESS (03/02/14): AUMENTO DE CABIDADES ESQUERDA COM FUNÇÃO DE VE REDUZIDA, REFLUXO MITRAL MODERADO / IMPORTANTES, REFLUXO AORTICO MODERADO, REFLUXO TRICUSPIDE DISCRETO. NÃO HOUVE AVALIAÇÃO DA ISQUEMIA POR DISFUNÇÃO SEVERA DO VE.\n# ECG COM PADRÃO DE BRE.\n# AVALIAÇÃO PRÉ-TRANSPLANTE.\n# DOPPLER CAROTIDAS + VERTEBRAIS: CERVICAL D: CAROTIDA: ESTENOSE 20-30% NA BIFURCAÇÃO CAROTÍDEA;\nPACIENTE SEM QUEIXAS. \nCATE 16/06/15: PRÉ: RVP 2,19 // RVS 24\n\t      PÓS: RVP 2,08 // RVS 12,59\nEXAMES LAB 21/07/15: NA 141; K 5; CREAT 1; GLI 89; UREIA 32; CPK 81; AC URICO 4,9; TG 102; TGP 36; HDL 41; TGO 23; CT 156; LDL 95; HMG OK; TSH 1,83; T4L 1,23; EQU NORMAL\nP: AMNTIDO TTO CLINICO\n \n \n \n ",
  "entities": {
    "Atividade de Assistência à Saúde": [
      "ACOMPANHAMENTO",
      "AMNTIDO",
      "AVALIAÇÃO DA ISQUEMIA"
    ],
    "Grupo Profissional ou Ocupacional": [
      "Doutor"
    ],
    "Negação": [
      "NEGA",
      "NÃO",
      "SEM"
    ],
    "Doença ou Síndrome": [
      "DM",
      "DSLP",
      "TABAGISMO",
      "IAM´S",
      "IC CF III"
    ],
    "Abreviação": [
      "DM",
      "DSLP",
      "IAM´S",
      "LST",
      "8/8H",
      "OMP",
      "ECG",
      "CATE",
      "IC CF III",
      "12/12 H",
      "ECOCARDIO COM STRESS",
      "AUMENTO DE CABIDADES ESQUERDA COM FUNÇÃO DE VE REDUZIDA",
      "PADRÃO DE BRE",
      "CERVICAL D",
      "RVP 2 , 19",
      "RVS 24",
      "RVP 2 , 08",
      "RVS 12 , 59",
      "EXAMES LAB",
      "NA 141",
      "K 5",
      "CREAT 1",
      "GLI 89",
      "CPK 81",
      "AC URICO 4 , 9",
      "TG 102",
      "TGP 36",
      "HDL 41",
      "TGO 23",
      "CT 156",
      "LDL 95",
      "HMG OK",
      "TSH 1 , 83",
      "T4L 1 , 23",
      "EQU NORMAL",
      "TTO CLINICO"
    ],
    "Substância Farmacológica": [
      "LST",
      "CARVEDILOL",
      "APRESOLINA",
      "ESPIRONOLACTONA",
      "OMP"
    ],
    "Substância Química Orgânica": [
      "LST",
      "CARVEDILOL",
      "APRESOLINA",
      "ESPIRONOLACTONA",
      "OMP"
    ],
    "Conceito Quantitativo": [
      "50MG",
      "8/8H",
      "25MG",
      "20",
      "12/12 H",
      "12 , 5MG",
      "12/12 HORAS"
    ],
    "Conceito Temporal": [
      "8/8H",
      "DIA",
      "PRÉ",
      "PÓS",
      "12/12 H",
      "12/12 HORAS"
    ],
    "Procedimento Diagnóstico": [
      "ECG",
      "CATE",
      "ECOCARDIO COM STRESS",
      "AVALIAÇÃO PRÉ-TRANSPLANTE",
      "DOPPLER CAROTIDAS + VERTEBRAIS"
    ],
    "Parte do Corpo, Órgão ou Componente Orgânico": [
      "CAROTIDA",
      "CERVICAL D"
    ],
    "Paciente ou Grupo com Deficiência": [
      "PACIENTE"
    ],
    "Sinal ou Sintoma": [
      "QUEIXAS",
      "DISFUNÇÃO SEVERA DO VE"
    ],
    "Resultado Laboratorial ou de Teste": [
      "AUMENTO DE CABIDADES ESQUERDA COM FUNÇÃO DE VE REDUZIDA",
      "REFLUXO MITRAL MODERADO / IMPORTANTES",
      "REFLUXO AORTICO MODERADO",
      "REFLUXO TRICUSPIDE DISCRETO",
      "PADRÃO DE BRE",
      "ESTENOSE 20-30% NA BIFURCAÇÃO CAROTÍDEA",
      "RVP 2 , 19",
      "RVS 24",
      "RVP 2 , 08",
      "RVS 12 , 59",
      "EXAMES LAB",
      "NA 141",
      "K 5",
      "CREAT 1",
      "GLI 89",
      "UREIA 32",
      "CPK 81",
      "AC URICO 4 , 9",
      "TG 102",
      "TGP 36",
      "HDL 41",
      "TGO 23",
      "CT 156",
      "LDL 95",
      "HMG OK",
      "TSH 1 , 83",
      "T4L 1 , 23",
      "EQU NORMAL"
    ],
    "Procedimento Terapêutico ou Preventivo": [
      "AVALIAÇÃO PRÉ-TRANSPLANTE",
      "TTO CLINICO"
    ],
    "Procedimento Laboratorial": [
      "EXAMES LAB"
    ]
  },
  "labels": {
    "ic cf iii": {
      "capitulo": "11"
    },
    "disfunção severa do ve": {
      "capitulo": "08"
    },
    "queixas": {
      "capitulo": "21"
    }
  }
}