{
  "prontuario_id": 867,
  "text": "Lucas, 65 ANOS\n\n# PO DE TX CARDÍACO (23/10/15)  -  ( IC DILATADA IDIOPÁTICA)\n# EM USO DE : CICLOSPORINA 150MG 12/12H, MICOFENOLATO 720MG 8/8H, PREDNISONA 20MG / DIA\nAAS 100MG / DIA, OMZ 20MG / DIA. \n- EXAMES - AVALIAÇÃO PRÉ - TRANSPLANTE:\n# DOPPLER CAROTIDAS + VERTEBRAIS: CERVICAL D: CAROTIDA: ESTENOSE 20-30% NA BIFURCAÇÃO CAROTÍDEA;\n# CATE 16/06/15: PRÉ: RVP 2,19 // RVS 24, PÓS: RVP 2,08 // RVS 12,59\n# ECOTT 28/8/15 AE 46 / VD 26 / S / PP 10 / 10 VE 81 / 66 FE 37%. VE DILATADO COM HIPOCONTRATIBILIDADE DIFUSA MODERADA / I\nAO LEVE / IMI LEVE AMODERADA / PSAP 39 MMHG.\nS #  SENTE BEM, DOR NA FO SOMENTE AOS MOVIMENTOS E AO TOSSIR. NEGA DISPNÉIA. RELATA QUE FO ESTÁ SECA, SEM SINAIS FLOGÍSTICOS. \nNEGA FEBRE. \nO # BEG, HIPOCORADO +/4+, EUPNEICO, AFEBRIL\nPA: 110X70 // FC: 80\nCV: BRNF SS\nCPP: MV+ BILATERAL, SEM RA\nFO LIMPA E SECA, SEM PRESENÇA DE SECREÇÃO\nABD: RHA+, INDOLOR\nMMII: SEM EDEMA OU EMPASTAMENTO\nA # PO DE TX CARDIACO (23/10/15)\nP # MANTIDO RETORNO EM 30 DIAS\n \n \n \n ",
  "entities": {
    "Conceito Temporal": [
      "PO",
      "12/12H",
      "8/8H",
      "DIA",
      "PRÉ",
      "PÓS"
    ],
    "Substância Farmacológica": [
      "CICLOSPORINA",
      "MICOFENOLATO",
      "PREDNISONA",
      "AAS",
      "OMZ"
    ],
    "Aminoácido, Peptídeo ou Proteína": [
      "CICLOSPORINA"
    ],
    "Substância Química Orgânica": [
      "CICLOSPORINA",
      "MICOFENOLATO",
      "PREDNISONA",
      "AAS",
      "OMZ"
    ],
    "Conceito Quantitativo": [
      "150MG",
      "12/12H",
      "720MG",
      "8/8H",
      "20MG",
      "100MG",
      "110X70",
      "80",
      "30"
    ],
    "Abreviação": [
      "12/12H",
      "8/8H",
      "AAS",
      "OMZ",
      "CATE",
      "ECOTT",
      "FO",
      "BEG",
      "PA",
      "FC",
      "CV",
      "CPP",
      "RA",
      "ABD",
      "RHA+",
      "MMII",
      "TX CARDÍACO",
      "IC DILATADA IDIOPÁTICA",
      "CERVICAL D",
      "RVP 2 , 19",
      "RVS 24",
      "RVP 2 , 08",
      "RVS 12 , 59",
      "AE 46",
      "VD 26",
      "PP 10 / 10",
      "VE 81 / 66",
      "FE 37%",
      "VE DILATADO COM HIPOCONTRATIBILIDADE DIFUSA MODERADA",
      "I AO LEVE",
      "IMI LEVE AMODERADA",
      "PSAP 39 MMHG",
      "MV+ BILATERAL",
      "TX CARDIACO"
    ],
    "Hormônio": [
      "PREDNISONA"
    ],
    "Parte do Corpo, Órgão ou Componente Orgânico": [
      "CAROTIDA",
      "MMII",
      "CERVICAL D"
    ],
    "Procedimento Diagnóstico": [
      "CATE",
      "ECOTT",
      "AVALIAÇÃO PRÉ - TRANSPLANTE",
      "DOPPLER CAROTIDAS + VERTEBRAIS"
    ],
    "Procedimento Terapêutico ou Preventivo": [
      "CATE",
      "TX CARDÍACO",
      "TX CARDIACO"
    ],
    "Lesão ou Envenenamento": [
      "FO"
    ],
    "Função Fisiológica": [
      "MOVIMENTOS",
      "TOSSIR"
    ],
    "Negação": [
      "NEGA",
      "SEM",
      "AFEBRIL",
      "SS",
      "INDOLOR"
    ],
    "Sinal ou Sintoma": [
      "DISPNÉIA",
      "FEBRE",
      "AFEBRIL",
      "SS",
      "RA",
      "INDOLOR",
      "EDEMA",
      "EMPASTAMENTO",
      "SINAIS FLOGÍSTICOS",
      "HIPOCORADO +/4+"
    ],
    "Achado": [
      "SECA",
      "BEG",
      "EUPNEICO",
      "LIMPA",
      "RHA+",
      "SENTE BEM",
      "MV+ BILATERAL"
    ],
    "Atributo Clínico": [
      "PA",
      "FC",
      "CV",
      "CPP"
    ],
    "Localização ou Região Corporal": [
      "MMII"
    ],
    "Atividade de Assistência à Saúde": [
      "RETORNO",
      "AVALIAÇÃO PRÉ - TRANSPLANTE"
    ],
    "Doença ou Síndrome": [
      "IC DILATADA IDIOPÁTICA"
    ],
    "Resultado Laboratorial ou de Teste": [
      "ESTENOSE 20-30% NA BIFURCAÇÃO CAROTÍDEA",
      "RVP 2 , 19",
      "RVS 24",
      "RVP 2 , 08",
      "RVS 12 , 59",
      "AE 46",
      "VD 26",
      "PP 10 / 10",
      "VE 81 / 66",
      "FE 37%",
      "VE DILATADO COM HIPOCONTRATIBILIDADE DIFUSA MODERADA",
      "I AO LEVE",
      "IMI LEVE AMODERADA",
      "PSAP 39 MMHG"
    ]
  },
  "labels": {
    "ra": {
      "capitulo": "11"
    },
    "ic dilatada idiopática": {
      "capitulo": "11"
    },
    "sinais flogísticos": {
      "capitulo": "21"
    },
    "febre": {
      "capitulo": "21"
    },
    "mv+ bilateral": {
      "capitulo": "21"
    },
    "ss": {
      "capitulo": "11"
    },
    "fo": {
      "capitulo": "21"
    },
    "edema": {
      "capitulo": "21"
    },
    "beg": {
      "capitulo": "21"
    },
    "dispnéia": {
      "capitulo": "21"
    },
    "empastamento": {
      "capitulo": "21"
    }
  }
}