{
  "prontuario_id": 895,
  "text": "PACIENTE QUEIXA-SE DE EMBAÇAMENTO AO, PIOR EM OE.\nEM USO DE: AAS, CARVEDILOL, FUROSEMIDA, SINVASTATINA, ENALAPRIL.\nNEGA CIRURGIAS E TRAUMAS OCULARES.\nREFERE QUE HA MAIS DE 5 ANOS, DEITOU NA MACA PARA INICIO DE CIRURGIA DE CATARATA POREM NAO REALIZOU PROCEDIMENTO.\nNEGA HF DE GLAUCOMA E CEGUEIRA.\n\nAV:\n20/40\nMM\n\nFO:\nVISUALIZAÇÃO DIFICIL POR OPACIDADE DE MEIOS AO.\n\nBIO:\nCATARATA AO.\n\nPIO: 12/12.\n\nCD:\nORIENTO PACIENTE SOBRE CATARATA, PACIENTE INDECISO SOBRE OPERAR, MAS SOLICITA QUE DEIXE AGENDADO RECONSULTA PARA TER TEMPO PARA DECIDIR.\nRETORNO PARA MR AO E CLASSIFICAÇÃO DE CATARATA OE DIA 07/05/15.\n\nR1 LUCAS\n \n \n \n ",
  "entities": {
    "Paciente ou Grupo com Deficiência": [
      "PACIENTE"
    ],
    "Sinal ou Sintoma": [
      "QUEIXA-SE",
      "EMBAÇAMENTO"
    ],
    "Abreviação": [
      "AO",
      "OE",
      "AAS",
      "HF",
      "AV",
      "FO",
      "BIO",
      "PIO",
      "CD",
      "VISUALIZAÇÃO DIFICIL POR OPACIDADE DE MEIOS AO",
      "CATARATA AO",
      "MR AO",
      "CLASSIFICAÇÃO DE CATARATA OE"
    ],
    "Parte do Corpo, Órgão ou Componente Orgânico": [
      "AO",
      "OE"
    ],
    "Conceito Qualitativo": [
      "PIOR"
    ],
    "Substância Farmacológica": [
      "AAS",
      "CARVEDILOL",
      "FUROSEMIDA",
      "SINVASTATINA",
      "ENALAPRIL"
    ],
    "Substância Química Orgânica": [
      "AAS",
      "CARVEDILOL",
      "FUROSEMIDA",
      "SINVASTATINA"
    ],
    "Aminoácido, Peptídeo ou Proteína": [
      "ENALAPRIL"
    ],
    "Negação": [
      "NEGA",
      "NAO"
    ],
    "Procedimento Terapêutico ou Preventivo": [
      "CIRURGIAS",
      "PROCEDIMENTO",
      "CIRURGIA DE CATARATA"
    ],
    "Achado": [
      "HF",
      "INDECISO SOBRE OPERAR"
    ],
    "Doença ou Síndrome": [
      "GLAUCOMA",
      "CATARATA",
      "CATARATA AO"
    ],
    "Função Patológica": [
      "CEGUEIRA"
    ],
    "Procedimento Diagnóstico": [
      "AV",
      "FO",
      "BIO",
      "PIO",
      "CLASSIFICAÇÃO DE CATARATA OE"
    ],
    "Atributo Clínico": [
      "PIO"
    ],
    "Conceito Quantitativo": [
      "12/12"
    ],
    "Resultado Laboratorial ou de Teste": [
      "12/12",
      "20/40 MM",
      "VISUALIZAÇÃO DIFICIL POR OPACIDADE DE MEIOS AO"
    ],
    "Produto Intelectual": [
      "CD"
    ],
    "Atividade de Assistência à Saúde": [
      "CD",
      "ORIENTO",
      "RECONSULTA",
      "RETORNO"
    ],
    "Lesão ou Envenenamento": [
      "TRAUMAS OCULARES"
    ]
  },
  "labels": {
    "indeciso sobre operar": {
      "capitulo": "09"
    },
    "catarata ao": {
      "capitulo": "09"
    },
    "traumas oculares": {
      "capitulo": "21"
    },
    "embaçamento": {
      "capitulo": "09"
    },
    "cegueira": {
      "capitulo": "09"
    },
    "catarata": {
      "capitulo": "09"
    },
    "glaucoma": {
      "capitulo": "09"
    }
  }
}