{
  "prontuario_id": 32,
  "text": "LUCAS, 18 anos.\n\n# HF -  cardiopatia.\n\nEm uso de : Diclin  (ACO).\n\nHMA: Pcte relata síncope inicio em janeiro mais com o calor.\npródromos: tontura e sudorese e escurecimento visual.\nRefere exacerbação dos sintomas com nervosismo.\nDuração de segundos há 3 minutos.\nNega confusão mental ou salivação após.\nNega uso de medicação.\nNega outros sintomas.\nRefere que continua apresentando sintomas, com ultimo ha 1 semana, durante atividades domesticas.\n\nEcocardio 18/02/15: RA 20, AE 26, VD 17, Septo 08, PP 08, VE 39, FE 63%. Exame dentro da normalidade.\nTeste ergometrico: Resposta cardiovascular normal ao esforço fisico, atingiu 11 METS.\nECG: DCRD.\n\nHF - p cardiopatia.\n\nBEG, hidratada, normocorada, acianotica.\nFC 80, FR 18, PA: 120/70, SAT 98%AA.\nAC bnf em 2t e ss,\nAP mv+ simetrico s ra,\nAbd sp.\nmmii s edema,\n\nVaso vagal?\n\nA: Aguarda holter.\nRetorno com exames.\n \n \n \n ",
  "entities": {
    "Achado": [
      "HF",
      "HMA",
      "BEG",
      "hidratada",
      "normocorada",
      "Exame dentro da normalidade",
      "bnf em 2t",
      "mv+ simetrico"
    ],
    "Abreviação": [
      "HF",
      "ACO",
      "HMA",
      "Pcte",
      "Ecocardio",
      "ECG",
      "DCRD",
      "p",
      "BEG",
      "FC",
      "FR",
      "PA",
      "AC",
      "AP",
      "s",
      "ra",
      "Abd",
      "sp",
      "mmii",
      "A",
      "RA 20",
      "AE 26",
      "VD 17",
      "PP 08",
      "VE 39",
      "FE 63%",
      "bnf em 2t",
      "mv+ simetrico"
    ],
    "Doença ou Síndrome": [
      "cardiopatia",
      "Vaso vagal"
    ],
    "Substância Farmacológica": [
      "Diclin",
      "ACO",
      "medicação"
    ],
    "Substância Química Orgânica": [
      "Diclin"
    ],
    "Paciente ou Grupo com Deficiência": [
      "Pcte"
    ],
    "Sinal ou Sintoma": [
      "síncope",
      "tontura",
      "sudorese",
      "nervosismo",
      "salivação",
      "sintomas",
      "acianotica",
      "ra",
      "sp",
      "edema",
      "escurecimento visual",
      "exacerbação dos sintomas",
      "confusão mental",
      "outros sintomas",
      "Vaso vagal"
    ],
    "Negação": [
      "Nega",
      "acianotica",
      "ss",
      "s",
      "sp"
    ],
    "Conceito Temporal": [
      "após",
      "durante atividades domesticas"
    ],
    "Procedimento Diagnóstico": [
      "Ecocardio",
      "ECG",
      "AC",
      "AP",
      "A",
      "holter",
      "exames",
      "Teste ergometrico"
    ],
    "Resultado Laboratorial ou de Teste": [
      "DCRD",
      "RA 20",
      "AE 26",
      "VD 17",
      "Septo 08",
      "PP 08",
      "VE 39",
      "FE 63%",
      "Resposta cardiovascular normal ao esforço fisico",
      "atingiu 11 METS"
    ],
    "Atributo Clínico": [
      "FC",
      "FR",
      "PA",
      "SAT"
    ],
    "Conceito Quantitativo": [
      "80",
      "18",
      "120/70",
      "98%AA"
    ],
    "Parte do Corpo, Órgão ou Componente Orgânico": [
      "Abd",
      "mmii"
    ],
    "Função Patológica": [
      "edema"
    ]
  },
  "labels": {
    "escurecimento visual": {
      "capitulo": "09"
    },
    "ra": {
      "capitulo": "11"
    },
    "sp": {
      "capitulo": "15"
    },
    "bnf em 2t": {
      "capitulo": "X"
    },
    "hma": {
      "capitulo": "21"
    },
    "sudorese": {
      "capitulo": "21"
    },
    "acianotica": {
      "capitulo": "11"
    },
    "hf": {
      "capitulo": "11"
    },
    "cardiopatia": {
      "capitulo": "11"
    },
    "sintomas": {
      "capitulo": "21"
    },
    "vaso vagal": {
      "capitulo": "21"
    },
    "nervosismo": {
      "capitulo": "06"
    },
    "mv+ simetrico": {
      "capitulo": "15"
    },
    "exacerbação dos sintomas": {
      "capitulo": "21"
    },
    "edema": {
      "capitulo": "15"
    },
    "beg": {
      "capitulo": "11"
    },
    "síncope": {
      "capitulo": "21"
    },
    "tontura": {
      "capitulo": "21"
    }
  }
}