{
  "prontuario_id": 521,
  "text": "Paciente em acompanhamento com a cardiologia devido a 2 IAM previos ( em 2004  e 2012).\nEm uso de  : carvediol 6, 25 mg , AAS 100 mg , furosemida 40 mg , losartana 100 mg, atorvstatina 20 mg , omeprazol 20 mg.\nPaciente relata dispnéia e cansaço aos minimos esforços. Paciente relata parestesias em pé direito , dores musculares na panturrilha.\nComorbidades : HAS, ICC , dislipidemia.\nEventos: 2 CATs e 3 angioplastias.\nNa ultima consulta foi trocada sinvastatina por atorvastatina mas o paciente continua em uso de sinvastatina. \nPaciente nao traz exames.\nEF:\nPA: 120/80 mmhg.\nBCRNF.\nPulso MMII pedioso poplíteo e femoral presentes.\nConduta : troco sinvastatina por atorvastatina e solicito exames de sangue ( CT, LDL, HDL, TG ); mantenho as demais medicações.\n \n \n \n ",
  "entities": {
    "Paciente ou Grupo com Deficiência": [
      "Paciente",
      "paciente"
    ],
    "Atividade de Assistência à Saúde": [
      "acompanhamento",
      "trocada",
      "Conduta",
      "troco",
      "mantenho"
    ],
    "Grupo Profissional ou Ocupacional": [
      "cardiologia"
    ],
    "Conceito Quantitativo": [
      "2",
      "3",
      "6 , 25 mg",
      "100 mg",
      "40 mg",
      "20 mg",
      "120/80 mmhg"
    ],
    "Abreviação": [
      "IAM",
      "AAS",
      "HAS",
      "ICC",
      "CATs",
      "EF",
      "PA",
      "BCRNF",
      "MMII",
      "CT"
    ],
    "Doença ou Síndrome": [
      "IAM",
      "HAS",
      "ICC",
      "dislipidemia"
    ],
    "Conceito Temporal": [
      "previos"
    ],
    "Substância Farmacológica": [
      "carvediol",
      "AAS",
      "furosemida",
      "losartana",
      "atorvstatina",
      "omeprazol",
      "sinvastatina",
      "atorvastatina",
      "medicações"
    ],
    "Substância Química Orgânica": [
      "carvediol",
      "AAS",
      "furosemida",
      "losartana",
      "atorvstatina",
      "omeprazol",
      "sinvastatina",
      "atorvastatina"
    ],
    "Sinal ou Sintoma": [
      "dispnéia",
      "parestesias",
      "cansaço aos minimos esforços",
      "dores musculares"
    ],
    "Procedimento Terapêutico ou Preventivo": [
      "CATs",
      "angioplastias"
    ],
    "Negação": [
      "nao"
    ],
    "Procedimento Diagnóstico": [
      "EF"
    ],
    "Atributo Clínico": [
      "PA",
      "Pulso"
    ],
    "Achado": [
      "BCRNF",
      "presentes"
    ],
    "Parte do Corpo, Órgão ou Componente Orgânico": [
      "MMII",
      "pedioso",
      "poplíteo",
      "femoral",
      "pé direito"
    ],
    "Produto Intelectual": [
      "Conduta"
    ],
    "Procedimento Laboratorial": [
      "CT",
      "LDL",
      "HDL",
      "TG",
      "exames de sangue"
    ]
  },
  "labels": {
    "icc": {
      "capitulo": "04"
    },
    "parestesias": {
      "capitulo": "08"
    },
    "cansaço aos minimos esforços": {
      "capitulo": "11"
    },
    "has": {
      "capitulo": "11"
    },
    "dispnéia": {
      "capitulo": "12"
    },
    "iam": {
      "capitulo": "11"
    },
    "dores musculares": {
      "capitulo": "15"
    },
    "dislipidemia": {
      "capitulo": "05"
    }
  }
}