{
  "prontuario_id": 853,
  "text": "LUCAS, 48 ANOS \n\n# HAS HÁ 10 ANOS\n# DSLP \n# HIPOTIREOIDISMO HÁ  8 MESES EM USO DE PURA T4 25 MCG /DIA \n# DEPRESSÃO, EM USO DE FLUOXETINA 20 MG /DIAS \n# CAT EM JUNHO/2011: SEM INDICAÇÃO CIRÚRGICA \n# HÉRNIA DE DISCO HÁ 3 ANOS \n# CINTILOGRAFIA MIOCÁRDICA COM DIPIRIDAMOL EM 2011: HIPOCAPTAÇÃO APICAL, DO SEGMENTO ANTERIOR (TRANSITÓRIO) E BASAL DO SEGMENTO ANTERO-SEPTAL.\n# DEMAIS MEDICAÇÕES: ENALAPRIL 20 MG 1 CP 12/12H, AAS 100MG /DIA, CARVEDILOL 6,25 MG 2 CP 12/12 HORAS, SINVASTATINA 20 MG 2 CP/NOITE, HCTZ 25 MG /DIA, SUSTRATE 100 MG SE DOR PRECORDIAL , COMPLEXO B 1 CP APÓS ALMOÇO., PURAN 25 mcg 1 x dia, fFLUXETINA 20 mg 1 x dia, HIDROXIDOCLOROQUINA  400mg 1 x dia, COLCHICINA 0,5 mg 2x dia.\n\nPACIENTE REFERE EPISÓDIOS INTERMINTES DE PALPITAÇÕES E DOR PRECORDIAL (1-2 X/SEMANA), COM  RELAÇÃO COM EXERCICÍO FÍSICO OU COM O ESTRESSE. SEM OUTROS SINTOMAS ASSSOCIADOS. NEGA QUEIXAS RESPIRATÓRIAS, URINÁRIAS OU GASTROINTESTINAIS. \n\nSINDORME X.\n \n \n \n ",
  "entities": {
    "Abreviação": [
      "HAS",
      "DSLP",
      "CAT",
      "AAS",
      "HCTZ",
      "PURAN",
      "PURA T4"
    ],
    "Doença ou Síndrome": [
      "HAS",
      "DSLP",
      "HIPOTIREOIDISMO",
      "DEPRESSÃO",
      "HÉRNIA DE DISCO",
      "SINDORME X"
    ],
    "Disfunção Mental ou Comportamental": [
      "DEPRESSÃO"
    ],
    "Substância Farmacológica": [
      "FLUOXETINA",
      "DIPIRIDAMOL",
      "ENALAPRIL",
      "AAS",
      "CARVEDILOL",
      "SINVASTATINA",
      "HCTZ",
      "SUSTRATE",
      "PURAN",
      "fFLUXETINA",
      "HIDROXIDOCLOROQUINA",
      "COLCHICINA",
      "PURA T4",
      "COMPLEXO B"
    ],
    "Substância Química Orgânica": [
      "FLUOXETINA",
      "DIPIRIDAMOL",
      "AAS",
      "CARVEDILOL",
      "SINVASTATINA",
      "HCTZ",
      "PURAN",
      "fFLUXETINA",
      "HIDROXIDOCLOROQUINA",
      "COLCHICINA",
      "PURA T4",
      "COMPLEXO B"
    ],
    "Procedimento Terapêutico ou Preventivo": [
      "CAT",
      "MEDICAÇÕES",
      "INDICAÇÃO CIRÚRGICA"
    ],
    "Procedimento Diagnóstico": [
      "CAT",
      "CINTILOGRAFIA MIOCÁRDICA"
    ],
    "Negação": [
      "SEM",
      "NEGA"
    ],
    "Aminoácido, Peptídeo ou Proteína": [
      "ENALAPRIL"
    ],
    "Hormônio": [
      "PURAN"
    ],
    "Sinal ou Sintoma": [
      "PALPITAÇÕES",
      "ESTRESSE",
      "DOR PRECORDIAL",
      "SINTOMAS ASSSOCIADOS"
    ],
    "Função de Organismo": [
      "RESPIRATÓRIAS",
      "URINÁRIAS",
      "GASTROINTESTINAIS"
    ],
    "Conceito Quantitativo": [
      "25 MCG /DIA",
      "20 MG /DIAS",
      "20 MG 1 CP 12/12H",
      "100MG /DIA",
      "6 , 25 MG 2 CP 12/12 HORAS",
      "20 MG 2 CP/NOITE",
      "25 MG /DIA",
      "100 MG",
      "1 CP",
      "25 mcg 1 x dia",
      "20 mg 1 x dia",
      "400mg 1 x dia"
    ],
    "Atividade de Assistência à Saúde": [
      "INDICAÇÃO CIRÚRGICA"
    ],
    "Resultado Laboratorial ou de Teste": [
      "HIPOCAPTAÇÃO APICAL"
    ],
    "Localização ou Região Corporal": [
      "SEGMENTO ANTERIOR ( TRANSITÓRIO"
    ],
    "Vitamina": [
      "COMPLEXO B"
    ],
    "Conceito Temporal": [
      "APÓS ALMOÇO",
      "EPISÓDIOS INTERMINTES"
    ],
    "Atividade Diária ou Recreativa": [
      "EXERCICÍO FÍSICO"
    ]
  },
  "labels": {
    "hérnia de disco": {
      "capitulo": "15"
    },
    "sindorme x": {
      "capitulo": "06"
    },
    "dor precordial": {
      "capitulo": "08"
    },
    "dslp": {
      "capitulo": "05"
    },
    "sintomas asssociados": {
      "capitulo": "21"
    },
    "palpitações": {
      "capitulo": "11"
    },
    "hipotireoidismo": {
      "capitulo": "05"
    },
    "depressão": {
      "capitulo": "06"
    },
    "estresse": {
      "capitulo": "06"
    }
  }
}