{
  "prontuario_id": 97,
  "text": "LUCAS, 65 anos. \n\n2007 IAM, RM, desenvolveu arritmia após RM, em 2010 fez angioplastia,\nTem sentido palpitação um dia sim, dia não, costuma durar pelo menos uma hora, ocasionalmente dura a noite inteira, associada a dispneia, aperto no peito e dor nas costas, mal estar, depois da angioplastia.\nem 2010 não teve mais síncope,\nHAS, coronariopatia, arritmia, catarata, hipertireoidismo.\nProstatectomia, RM, angioplastia, trauma (pedaço de ferro entrou no peito),\nHMF: ave, câncer (mãe e irmãs),\nMedicamentos: tapazol 10 mg, enalapril 10 mg, selozok 50 mg, sinvastatina 40 mg, xarelto 20 mg,\nEF: FC 60 bpm, bcrnf, demais spp.\nacrescentou-se 25 mg de selozok.\nretorno em 60 dias.\n \n \n \n ",
  "entities": {
    "Abreviação": [
      "IAM",
      "RM",
      "HAS",
      "HMF",
      "ave",
      "EF",
      "FC",
      "bcrnf",
      "spp"
    ],
    "Doença ou Síndrome": [
      "IAM",
      "HAS",
      "coronariopatia",
      "catarata",
      "hipertireoidismo",
      "ave"
    ],
    "Procedimento Terapêutico ou Preventivo": [
      "RM",
      "angioplastia",
      "Prostatectomia"
    ],
    "Achado": [
      "arritmia",
      "HMF",
      "bcrnf",
      "entrou no peito"
    ],
    "Conceito Temporal": [
      "após",
      "2010",
      "ocasionalmente",
      "depois",
      "um dia sim , dia não"
    ],
    "Sinal ou Sintoma": [
      "palpitação",
      "dispneia",
      "síncope",
      "durar pelo menos uma hora",
      "dura a noite inteira",
      "aperto no peito",
      "dor nas costas",
      "mal estar"
    ],
    "Negação": [
      "não",
      "spp"
    ],
    "Função Patológica": [
      "arritmia"
    ],
    "Lesão ou Envenenamento": [
      "trauma"
    ],
    "Processo Neoplásico": [
      "câncer"
    ],
    "Grupo Familiar": [
      "mãe",
      "irmãs"
    ],
    "Substância Farmacológica": [
      "Medicamentos",
      "tapazol",
      "enalapril",
      "selozok",
      "sinvastatina",
      "xarelto"
    ],
    "Substância Química Orgânica": [
      "tapazol",
      "selozok",
      "sinvastatina",
      "xarelto"
    ],
    "Aminoácido, Peptídeo ou Proteína": [
      "enalapril"
    ],
    "Procedimento Diagnóstico": [
      "EF"
    ],
    "Atributo Clínico": [
      "FC"
    ],
    "Atividade de Assistência à Saúde": [
      "acrescentou-se"
    ],
    "Conceito Quantitativo": [
      "durar pelo menos uma hora",
      "10 mg",
      "50 mg",
      "40 mg",
      "20 mg",
      "60 bpm",
      "25 mg"
    ],
    "Objeto Manufaturado": [
      "pedaço de ferro"
    ]
  },
  "labels": {
    "aperto no peito": {
      "capitulo": "11"
    },
    "coronariopatia": {
      "capitulo": "11"
    },
    "arritmia": {
      "capitulo": "11"
    },
    "hipertireoidismo": {
      "capitulo": "05"
    },
    "mal estar": {
      "capitulo": "21"
    },
    "dor nas costas": {
      "capitulo": "15"
    },
    "câncer": {
      "capitulo": "02"
    },
    "iam": {
      "capitulo": "22"
    },
    "catarata": {
      "capitulo": "09"
    },
    "ave": {
      "capitulo": "24"
    },
    "entrou no peito": {
      "capitulo": "22"
    },
    "hmf": {
      "capitulo": "24"
    },
    "dispneia": {
      "capitulo": "12"
    },
    "palpitação": {
      "capitulo": "11"
    },
    "dura a noite inteira": {
      "capitulo": "21"
    },
    "has": {
      "capitulo": "24"
    },
    "durar pelo menos uma hora": {
      "capitulo": "21"
    },
    "síncope": {
      "capitulo": "22"
    },
    "trauma": {
      "capitulo": "22"
    }
  }
}