{
  "prontuario_id": 719,
  "text": "DAC  INCIPIENTE .\nHAS.\n09-14 - CATE:   DA  PIM  COM OBSRUÇÃO SISTOLE   >  50 % -- LEDSAO   MODERADA  1/3   PROXIMAL  CD.\nUSA  HCT,  ATL,  AAS,  CLOPIDOGREL, SVT,    VERAPAMIL  80 D.\nS:   SEM QX  CARDIOLOGICAS    ATUAIS -  DOR   DIM,INUI  EM INMTENSIDADE  E FREQUENCIOA.\nO: 27-2-15  - FE  53,  EP 39, AE  42,  FÇAO SIST    LIMITROFE   E  DIAST   PRESERVADA,    AE  LIMITROFE,     INSUF MI DISCRETA   , HSAP 42.\n31-3-15 -  HB  15, HT  89,    CRE 1,1;   GLI  88,    U  30 ,  TRI 72, HDL  47 , NA   137 , LDL 121 , K  4,4 ;   COL    182.\nP:  AUMENMTO  SVT  40 MG N.\nCINTILO / RETORNO.\nCARDIO    GERAL.\n \n \n \n ",
  "entities": {
    "Abreviação": [
      "HAS",
      "CATE",
      "DA",
      "HCT",
      "ATL",
      "AAS",
      "SVT",
      "D",
      "S",
      "O",
      "P",
      "CINTILO",
      "DAC INCIPIENTE",
      "LEDSAO MODERADA 1/3 PROXIMAL CD",
      "QX CARDIOLOGICAS",
      "FE 53",
      "EP 39",
      "AE 42",
      "FÇAO SIST LIMITROFE",
      "DIAST PRESERVADA",
      "AE LIMITROFE",
      "INSUF MI DISCRETA",
      "HSAP 42",
      "HB 15",
      "HT 89",
      "CRE 1 , 1",
      "GLI 88",
      "U 30",
      "TRI 72",
      "COL 182",
      "CARDIO GERAL"
    ],
    "Doença ou Síndrome": [
      "HAS",
      "DAC INCIPIENTE"
    ],
    "Procedimento Terapêutico ou Preventivo": [
      "CATE"
    ],
    "Substância Farmacológica": [
      "HCT",
      "ATL",
      "AAS",
      "CLOPIDOGREL",
      "SVT",
      "VERAPAMIL"
    ],
    "Substância Química Orgânica": [
      "HCT",
      "ATL",
      "AAS",
      "CLOPIDOGREL",
      "SVT",
      "VERAPAMIL"
    ],
    "Conceito Temporal": [
      "D",
      "ATUAIS"
    ],
    "Achado": [
      "S",
      "DIM , INUI EM INMTENSIDADE E FREQUENCIOA"
    ],
    "Negação": [
      "SEM"
    ],
    "Sinal ou Sintoma": [
      "DOR",
      "QX CARDIOLOGICAS"
    ],
    "Produto Intelectual": [
      "P"
    ],
    "Procedimento Diagnóstico": [
      "CINTILO"
    ],
    "Atividade de Assistência à Saúde": [
      "RETORNO"
    ],
    "Resultado Laboratorial ou de Teste": [
      "PIM COM OBSRUÇÃO SISTOLE &gt; 50 %",
      "LEDSAO MODERADA 1/3 PROXIMAL CD",
      "FE 53",
      "EP 39",
      "AE 42",
      "FÇAO SIST LIMITROFE",
      "DIAST PRESERVADA",
      "AE LIMITROFE",
      "INSUF MI DISCRETA",
      "HSAP 42",
      "HB 15",
      "HT 89",
      "CRE 1 , 1",
      "GLI 88",
      "U 30",
      "TRI 72",
      "HDL 47",
      "NA 137",
      "LDL 121",
      "K 4 , 4",
      "COL 182"
    ],
    "Conceito Quantitativo": [
      "40 MG"
    ]
  },
  "labels": {
    "dac incipiente": {
      "capitulo": "11"
    },
    "dor": {
      "capitulo": "21"
    },
    "dim , inui em inmtensidade e frequencioa": {
      "capitulo": "21"
    },
    "qx cardiologicas": {
      "capitulo": "11"
    }
  }
}