{
  "prontuario_id": 359,
  "text": "DAC INCIPIENTE,\nHAS.\n\n09-14 CATE : DA Ponte Intra Miocárdica COM OBSRUÇÃO SISTOLE > 50 % --LEDSAO MODERADA 1/3 PROXIMAL CD.\n\n#  HCTZ 25, ATL50, AAS100, SVT 40, VERAPAMIL 80 D.\n\nECO 27-2-15: FE 53, EP 39, AE 42, FÇAO SIST LIMITROFE E DIAST PRESERVADA, AE LIMITROFE, INSUF MI DISCRETA, HSAP 42.\n\n31-3-15: HB 15, HT 89, CRE 1,1; GLI 88, U 30, TRI 72, HDL 47, NA 137, LDL 121, K 4,4; COL 182.\n\nCintilografia miocárdica: FE 59%, negativa para isquemia.\n\n\nPA 140/80,\n\nEF: BEG, M corado, hidratado, uepencio, acianotico, anciterico.\nMV +, s/ RA,\nBRNF 2 t, s/ sorpso.\n\nmembros perufndidos, sem edemas.\n\nCD : mantidas demais condutas.\nlipidgrama.\n \n \n \n ",
  "entities": {
    "Abreviação": [
      "HAS",
      "CATE",
      "DA",
      "HCTZ",
      "ATL50",
      "AAS100",
      "SVT",
      "D",
      "ECO",
      "PA",
      "EF",
      "BEG",
      "s/",
      "RA",
      "CD",
      "DAC INCIPIENTE",
      "--LEDSAO MODERADA 1/3 PROXIMAL CD",
      "FE 53",
      "EP 39",
      "AE 42",
      "FÇAO SIST LIMITROFE",
      "DIAST PRESERVADA",
      "AE LIMITROFE",
      "INSUF MI DISCRETA",
      "HSAP 42",
      "HT 89",
      "CRE 1 , 1",
      "GLI 88",
      "U 30",
      "TRI 72",
      "COL 182",
      "FE 59%",
      "MV +",
      "BRNF 2 t"
    ],
    "Doença ou Síndrome": [
      "HAS",
      "DAC INCIPIENTE"
    ],
    "Procedimento Terapêutico ou Preventivo": [
      "CATE"
    ],
    "Parte do Corpo, Órgão ou Componente Orgânico": [
      "DA"
    ],
    "Substância Farmacológica": [
      "HCTZ",
      "ATL50",
      "AAS100",
      "SVT",
      "VERAPAMIL"
    ],
    "Substância Química Orgânica": [
      "HCTZ",
      "AAS100",
      "SVT",
      "VERAPAMIL"
    ],
    "Conceito Quantitativo": [
      "25",
      "40",
      "140/80"
    ],
    "Substância Química Inorgânica": [
      "ATL50"
    ],
    "Conceito Temporal": [
      "D"
    ],
    "Procedimento Diagnóstico": [
      "ECO",
      "EF",
      "Cintilografia miocárdica"
    ],
    "Negação": [
      "negativa",
      "acianotico",
      "anciterico",
      "s/",
      "sem"
    ],
    "Atributo Clínico": [
      "PA"
    ],
    "Achado": [
      "BEG",
      "corado",
      "hidratado",
      "uepencio",
      "MV +",
      "BRNF 2 t",
      "membros perufndidos"
    ],
    "Sinal ou Sintoma": [
      "acianotico",
      "anciterico",
      "RA",
      "sorpso",
      "edemas"
    ],
    "Função Patológica": [
      "edemas"
    ],
    "Produto Intelectual": [
      "CD"
    ],
    "Atividade de Assistência à Saúde": [
      "CD",
      "mantidas demais condutas"
    ],
    "Procedimento Laboratorial": [
      "lipidgrama"
    ],
    "Resultado Laboratorial ou de Teste": [
      "Ponte Intra Miocárdica COM OBSRUÇÃO SISTOLE &gt; 50 %",
      "--LEDSAO MODERADA 1/3 PROXIMAL CD",
      "FE 53",
      "EP 39",
      "AE 42",
      "FÇAO SIST LIMITROFE",
      "DIAST PRESERVADA",
      "AE LIMITROFE",
      "INSUF MI DISCRETA",
      "HSAP 42",
      "HB 15",
      "HT 89",
      "CRE 1 , 1",
      "GLI 88",
      "U 30",
      "TRI 72",
      "HDL 47",
      "NA 137",
      "LDL 121",
      "K 4 , 4",
      "COL 182",
      "FE 59%"
    ]
  },
  "labels": {
    "dac incipiente": {
      "capitulo": "11"
    },
    "ra": {
      "capitulo": "22"
    },
    "has": {
      "capitulo": "21"
    },
    "membros perufndidos": {
      "capitulo": "15"
    },
    "edemas": {
      "capitulo": "14"
    },
    "brnf 2 t": {
      "capitulo": "22"
    },
    "mv +": {
      "capitulo": "11"
    }
  }
}