{
  "prontuario_id": 950,
  "text": "HAS / DLP.\nBronquite,\nObesidade,\n\n# Tosse com captopril.\n# Losartana 100 /12h, anlodipino 5 / 12h , HCTZ 25, Alenia 6/6h, \n\nQueixa de dor em MSE e irradiação para região precordial duração de 15 minutos, com dificuldade para mexer o braço.\nDispnéia aos esforços (400 / 500 metros).\n\nEF: BEG, corada, hidratada, eupneica, acinaotioca, anicterica.\ns/ sopro carotideo.\nMV + c/ sibilos expiratorios;\nBR2t s/ sopros;\nmembors perfundidos, sem edemas, dermatite ocre.\n\n\n\nECO (26587/ 25/03/15 ):\nAE 29,  Vd 22, S 10, PP 09, FE 69%.\n  remodelamento concentrioc.\n  PSAP 26.\n\n\nHb 14,5; Ht 45,7; Leuco 7950; Eo 1; Lf 30; Mo 10; Sg 58;\nCr 0,7; Glicose 101;  U 34; Mg 1,8; FA 161; GGT 50;  Ác úrico 6,5; Na 141; PK 4,1; \n\nCT 181; LDL 94; HDL 38;  Tg 247;\nTSH 5,74;\n\nPA 160/110.\n\nEF; BEG, corado, hidratado, eupenico, acianotico, anciterica.\nMV + s/ Ra;\nBRNF 2 t s/ sopros;\nabd globoso dep indolor.\nmembros perufndido, s sem edenas.\n\n\nCD:\n Aguarda novo TE (solicito novamente, perdeu o outro).\n Nova glicemia Hb glicada.\n \n \n \n ",
  "entities": {
    "Abreviação": [
      "HAS",
      "DLP",
      "HCTZ",
      "MSE",
      "EF",
      "BEG",
      "s/",
      "BR2t",
      "ECO",
      "PA",
      "Ra",
      "CD",
      "TE",
      "MV +",
      "AE 29",
      "Vd 22",
      "S 10",
      "PP 09",
      "FE 69%",
      "remodelamento concentrioc",
      "PSAP 26",
      "Hb 14 , 5",
      "Ht 45 , 7",
      "Leuco 7950",
      "Eo 1",
      "Lf 30",
      "Mo 10",
      "Sg 58",
      "Cr 0 , 7",
      "U 34",
      "Mg 1 , 8",
      "FA 161",
      "GGT 50",
      "Ác úrico 6 , 5",
      "CT 181",
      "Tg 247",
      "BRNF 2 t",
      "abd globoso",
      "Hb glicada"
    ],
    "Doença ou Síndrome": [
      "HAS",
      "DLP",
      "Bronquite",
      "Obesidade",
      "dermatite ocre"
    ],
    "Substância Farmacológica": [
      "Losartana",
      "anlodipino",
      "HCTZ",
      "Alenia"
    ],
    "Substância Química Orgânica": [
      "Losartana",
      "anlodipino",
      "HCTZ",
      "Alenia"
    ],
    "Conceito Temporal": [
      "/12h",
      "12h",
      "6/6h",
      "duração de 15 minutos"
    ],
    "Conceito Quantitativo": [
      "25",
      "6/6h",
      "160/110",
      "400 / 500 metros"
    ],
    "Sinal ou Sintoma": [
      "Queixa",
      "dor",
      "irradiação",
      "acinaotioca",
      "anicterica",
      "sopros",
      "edemas",
      "acianotico",
      "anciterica",
      "Ra",
      "indolor",
      "edenas",
      "dificuldade para mexer",
      "Dispnéia aos esforços",
      "sopro carotideo",
      "sibilos expiratorios"
    ],
    "Localização ou Região Corporal": [
      "MSE",
      "região precordial"
    ],
    "Procedimento Diagnóstico": [
      "EF",
      "ECO",
      "TE"
    ],
    "Achado": [
      "BEG",
      "corada",
      "hidratada",
      "eupneica",
      "BR2t",
      "corado",
      "hidratado",
      "eupenico",
      "Tosse com captopril",
      "duração de 15 minutos",
      "MV +",
      "membors perfundidos",
      "BRNF 2 t",
      "membros perufndido"
    ],
    "Negação": [
      "acinaotioca",
      "anicterica",
      "s/",
      "sem",
      "acianotico",
      "anciterica",
      "indolor"
    ],
    "Função Patológica": [
      "edemas",
      "edenas"
    ],
    "Atributo Clínico": [
      "PA"
    ],
    "Produto Intelectual": [
      "CD"
    ],
    "Atividade de Assistência à Saúde": [
      "solicito"
    ],
    "Procedimento Laboratorial": [
      "glicemia",
      "Hb glicada"
    ],
    "Resultado Laboratorial ou de Teste": [
      "AE 29",
      "Vd 22",
      "S 10",
      "PP 09",
      "FE 69%",
      "remodelamento concentrioc",
      "PSAP 26",
      "Hb 14 , 5",
      "Ht 45 , 7",
      "Leuco 7950",
      "Eo 1",
      "Lf 30",
      "Mo 10",
      "Sg 58",
      "Cr 0 , 7",
      "Glicose 101",
      "U 34",
      "Mg 1 , 8",
      "FA 161",
      "GGT 50",
      "Ác úrico 6 , 5",
      "Na 141",
      "PK 4 , 1",
      "CT 181",
      "LDL 94",
      "HDL 38",
      "Tg 247",
      "TSH 5 , 74"
    ]
  },
  "labels": {
    "ra": {
      "capitulo": "08"
    },
    "sopro carotideo": {
      "capitulo": "08"
    },
    "bronquite": {
      "capitulo": "12"
    },
    "dermatite ocre": {
      "capitulo": "14"
    },
    "sibilos expiratorios": {
      "capitulo": "12"
    },
    "queixa": {
      "capitulo": "21"
    },
    "irradiação": {
      "capitulo": "21"
    },
    "mv +": {
      "capitulo": "08"
    },
    "tosse com captopril": {
      "capitulo": "12"
    },
    "brnf 2 t": {
      "capitulo": "21"
    },
    "dispnéia aos esforços": {
      "capitulo": "12"
    },
    "dlp": {
      "capitulo": "11"
    },
    "br2t": {
      "capitulo": "21"
    },
    "has": {
      "capitulo": "11"
    },
    "sopros": {
      "capitulo": "12"
    },
    "dor": {
      "capitulo": "08"
    },
    "obesidade": {
      "capitulo": "05"
    },
    "dificuldade para mexer": {
      "capitulo": "08"
    }
  }
}