{
  "prontuario_id": 937,
  "text": "QP; INCHAÇO NO ROSTO;\nS; INICIO HA 5 MESES, EM FACE E CORPO DE MANDIBULA DIR, INDOLOR, NEGA DISFAGIA, NEGA DISFAGIA, NEGA PARESIAS OU OPARESTESIAS EM FACE; NEGA TABAGISMO; NEGA ALERGIAS, HAS EM TTO, TRANSPLANTADA RENAL ESQ HA 03 ANOS, EM USO DE IMUNODEPRESSORES (SIC); REFERE EPISTAXES EVENTUAIS APOS TRANSPLANTE RENAL;\nO; OTO; CERUMEN BILAT; RINO; PRESENÇA DE COAGULOS BILATERIAS.; ORO; EDENTULISMO SUP E INF; PRESENÇA DE MASSA ENDURECIDA EM CORPO E RAMO DIREITOS DE MANDIBULA , INDOLOR Á PALPAÇÃO; 8 X 8 CM; LINGUA E ASSOALHO LIVRES; C/P? LIVRE (TALVEZ ESPESSAMENTO DE FEIXE VASCULONERVOSO FACIAL DIREITA, SOB A LESÃO CITADA);\nrefere rx feito no HUC, mas não truxe;\na; tumor odontogenico (cisto dentigero, ameloblastoma, tu marrom? sarcoma de mandibula?)\nc; solicito tc de pescoço com contraste;  rx panoramico de mandibula;\nretorno com exames;\n\nr2 Lucas\n \n \n ",
  "entities": {
    "Achado": [
      "QP",
      "S",
      "LIVRE",
      "TRANSPLANTADA RENAL ESQ",
      "CERUMEN BILAT",
      "PRESENÇA DE COAGULOS BILATERIAS",
      "LINGUA E ASSOALHO LIVRES"
    ],
    "Abreviação": [
      "QP",
      "S",
      "O",
      "OTO",
      "RINO",
      "ORO",
      "C/P",
      "rx",
      "a",
      "c",
      "TRANSPLANTADA RENAL ESQ",
      "CERUMEN BILAT",
      "SUP E INF",
      "tu marrom",
      "tc de pescoço com contraste",
      "rx panoramico de mandibula"
    ],
    "Sinal ou Sintoma": [
      "INCHAÇO",
      "INDOLOR",
      "DISFAGIA",
      "PARESIAS",
      "OPARESTESIAS",
      "EPISTAXES",
      "ESPESSAMENTO",
      "PRESENÇA DE MASSA ENDURECIDA"
    ],
    "Localização ou Região Corporal": [
      "ROSTO",
      "FACE"
    ],
    "Parte do Corpo, Órgão ou Componente Orgânico": [
      "FACE",
      "MANDIBULA DIR",
      "CORPO E RAMO DIREITOS DE MANDIBULA",
      "FEIXE VASCULONERVOSO FACIAL DIREITA"
    ],
    "Negação": [
      "INDOLOR",
      "NEGA",
      "não"
    ],
    "Doença ou Síndrome": [
      "TABAGISMO",
      "ALERGIAS",
      "HAS",
      "EDENTULISMO",
      "cisto dentigero"
    ],
    "Procedimento Terapêutico ou Preventivo": [
      "TTO",
      "TRANSPLANTADA RENAL ESQ",
      "TRANSPLANTE RENAL"
    ],
    "Substância Farmacológica": [
      "IMUNODEPRESSORES"
    ],
    "Conceito Temporal": [
      "APOS"
    ],
    "Procedimento Diagnóstico": [
      "OTO",
      "RINO",
      "ORO",
      "rx",
      "exames",
      "tc de pescoço com contraste",
      "rx panoramico de mandibula"
    ],
    "Lesão ou Envenenamento": [
      "LESÃO"
    ],
    "Organização Relacionada à Saúde": [
      "HUC"
    ],
    "Processo Neoplásico": [
      "ameloblastoma",
      "tumor odontogenico",
      "tu marrom",
      "sarcoma de mandibula"
    ],
    "Produto Intelectual": [
      "c"
    ],
    "Atividade de Assistência à Saúde": [
      "solicito"
    ],
    "Resultado Laboratorial ou de Teste": [
      "CERUMEN BILAT",
      "PRESENÇA DE COAGULOS BILATERIAS"
    ],
    "Conceito Espacial": [
      "SUP E INF"
    ],
    "Conceito Quantitativo": [
      "8 X 8 CM"
    ]
  },
  "labels": {
    "qp": {
      "capitulo": "22"
    },
    "lesão": {
      "capitulo": "22"
    },
    "inchaço": {
      "capitulo": "10"
    },
    "espessamento": {
      "capitulo": "15"
    },
    "paresias": {
      "capitulo": "21"
    },
    "oparestesias": {
      "capitulo": "21"
    },
    "sarcoma de mandibula": {
      "capitulo": "02"
    },
    "disfagia": {
      "capitulo": "21"
    },
    "presença de massa endurecida": {
      "capitulo": "15"
    },
    "tu marrom": {
      "capitulo": "21"
    },
    "presença de coagulos bilaterias": {
      "capitulo": "03"
    },
    "cisto dentigero": {
      "capitulo": "02"
    },
    "cerumen bilat": {
      "capitulo": "10"
    },
    "ameloblastoma": {
      "capitulo": "02"
    },
    "tumor odontogenico": {
      "capitulo": "02"
    },
    "edentulismo": {
      "capitulo": "21"
    },
    "s": {
      "capitulo": "22"
    },
    "epistaxes": {
      "capitulo": "10"
    }
  }
}