{
  "prontuario_id": 450,
  "text": "22/04/2012    19:45h     # Colisão moto X auto + Fratura expoxta de femur e tibia E  + TCE grave    # 3° TQT    # 9° SOG    # 10° SVD.     Paciente 18 anos, traqueostomizado sob VM PSV, SOG com plano de dieta em curso, pele integra, mantendo curativo em fixador externo seco e limpo externamente em MIE, SVD com diurese efetiva, AVP em MSE com soroterapia em curso, PAM radial E com bom fluxo e refluxo, capacete sem sinais de sujidade externa, FC 62, PA 103/49, SAT 100%. Segue com resposta aos estimulos porém não à comandos. Segue sob cuidados e estavel. Enfermeira Florence Nightingale . FRATURA DO FEMUR.",
  "entities": {
    "Parte do Corpo, Órgão ou Componente Orgânico": [
      "femur",
      "MIE",
      "MSE",
      "FEMUR",
      "radial"
    ],
    "Conceito Espacial": [
      "E",
      "externamente"
    ],
    "Conceito Quantitativo": [
      "3°",
      "9°",
      "10°",
      "62",
      "103/49",
      "100%"
    ],
    "Procedimento Terapêutico ou Preventivo": [
      "TQT",
      "SOG",
      "SVD",
      "curativo",
      "AVP",
      "VM PSV",
      "plano de dieta em curso",
      "fixador externo",
      "soroterapia em curso"
    ],
    "Abreviação": [
      "TQT",
      "SOG",
      "SVD",
      "MIE",
      "AVP",
      "MSE",
      "FC",
      "PA",
      "Colisão moto X auto",
      "TCE grave",
      "VM PSV",
      "radial",
      "E"
    ],
    "Dispositivo Médico": [
      "SOG",
      "SVD",
      "curativo",
      "AVP",
      "VM PSV",
      "fixador externo"
    ],
    "Paciente ou Grupo com Deficiência": [
      "Paciente"
    ],
    "Achado": [
      "traqueostomizado",
      "seco",
      "limpo",
      "pele integra",
      "diurese efetiva",
      "bom fluxo e refluxo",
      "sinais de sujidade externa",
      "resposta aos estimulos"
    ],
    "Conceito Qualitativo": [
      "seco",
      "limpo"
    ],
    "Objeto Manufaturado": [
      "capacete"
    ],
    "Negação": [
      "sem",
      "não"
    ],
    "Atributo Clínico": [
      "FC",
      "PA",
      "SAT"
    ],
    "Atividade de Assistência à Saúde": [
      "cuidados"
    ],
    "Grupo Profissional ou Ocupacional": [
      "Enfermeira"
    ],
    "Lesão ou Envenenamento": [
      "FRATURA",
      "Colisão moto X auto",
      "Fratura expoxta",
      "TCE grave"
    ]
  },
  "labels": {
    "colisão moto x auto": {
      "capitulo": "22"
    },
    "tce grave": {
      "capitulo": "12"
    },
    "fratura": {
      "capitulo": "15"
    },
    "seco": {
      "capitulo": "14"
    },
    "limpo": {
      "capitulo": "14"
    },
    "fratura expoxta": {
      "capitulo": "15"
    },
    "pele integra": {
      "capitulo": "14"
    },
    "traqueostomizado": {
      "capitulo": "22"
    },
    "sinais de sujidade externa": {
      "capitulo": "21"
    },
    "resposta aos estimulos": {
      "capitulo": "21"
    }
  }
}