{
  "prontuario_id": 227,
  "text": "21:55h Responsivo a estimulos, mas periodos de agitaçao psicomotora, face corada, pupilas iso / foto. SNE com infusao de dieta 50ml/hr. Intubado,sob vm  em modo PCV com 50% FIO, PEEP 5, PL 18, FR  16, ausculta pulmonar com sibilos difusos, aspirado com media quantidade de secreçao, em uso de filtro bacteriologico. Acesso periferico jugular E com infusao de dormonid 15ml/hr + fentanil 8ml/hr. Extremidades edemaciadas, perfusao periferica preservada. Abdomen flacido, palpaçao, rha +. Hiperemia reg dorsal + reg glutea. Diurese por SVD presente em coletro amarelo citrico. Mantem monitorizada continuamente com cardioscopico + oximetria de pulso + pam nao invasiva. Enfermeira Florence Nightingale. SINDROME DO DESCONFORTO RESPIRATORIO DO ADULTO.",
  "entities": {
    "Conceito Temporal": [
      "periodos"
    ],
    "Parte do Corpo, Órgão ou Componente Orgânico": [
      "pupilas",
      "Abdomen"
    ],
    "Abreviação": [
      "iso",
      "foto",
      "SNE",
      "vm",
      "FIO",
      "PEEP",
      "PL",
      "FR",
      "SVD",
      "pam",
      "rha +",
      "reg dorsal",
      "reg glutea"
    ],
    "Achado": [
      "iso",
      "foto",
      "flacido",
      "Responsivo a estimulos",
      "face corada",
      "perfusao periferica preservada",
      "rha +"
    ],
    "Dispositivo Médico": [
      "SNE",
      "SVD"
    ],
    "Procedimento Terapêutico ou Preventivo": [
      "SNE",
      "Intubado",
      "vm",
      "PCV",
      "aspirado",
      "SVD"
    ],
    "Atividade de Assistência à Saúde": [
      "infusao",
      "monitorizada continuamente"
    ],
    "Conceito Quantitativo": [
      "50ml/hr",
      "50%",
      "5",
      "18",
      "16",
      "15ml/hr",
      "media quantidade"
    ],
    "Atributo Clínico": [
      "FIO",
      "PEEP",
      "PL",
      "FR"
    ],
    "Substância Corporal": [
      "aspirado"
    ],
    "Sinal ou Sintoma": [
      "secreçao",
      "Hiperemia",
      "agitaçao psicomotora",
      "sibilos difusos",
      "Extremidades edemaciadas"
    ],
    "Substância Química Orgânica": [
      "dormonid",
      "fentanil"
    ],
    "Substância Farmacológica": [
      "dormonid",
      "fentanil"
    ],
    "Procedimento Diagnóstico": [
      "palpaçao",
      "cardioscopico",
      "ausculta pulmonar",
      "oximetria de pulso"
    ],
    "Função de Organismo": [
      "Diurese"
    ],
    "Negação": [
      "nao"
    ],
    "Conceito Qualitativo": [
      "invasiva"
    ],
    "Grupo Profissional ou Ocupacional": [
      "Enfermeira"
    ],
    "Objeto Manufaturado": [
      "filtro bacteriologico"
    ],
    "Localização ou Região Corporal": [
      "reg dorsal",
      "reg glutea"
    ],
    "Doença ou Síndrome": [
      "SINDROME DO DESCONFORTO RESPIRATORIO DO ADULTO"
    ]
  },
  "labels": {
    "responsivo a estimulos": {
      "capitulo": "06"
    },
    "flacido": {
      "capitulo": "21"
    },
    "secreçao": {
      "capitulo": "13"
    },
    "sibilos difusos": {
      "capitulo": "12"
    },
    "extremidades edemaciadas": {
      "capitulo": "15"
    },
    "agitaçao psicomotora": {
      "capitulo": "06"
    },
    "sindrome do desconforto respiratorio do adulto": {
      "capitulo": "12"
    },
    "hiperemia": {
      "capitulo": "21"
    },
    "face corada": {
      "capitulo": "21"
    }
  }
}