{
  "prontuario_id": 527,
  "text": "02:25h: Paciente encaminhado ao centro cirúrgico as 20h, retornando as 23:45h no POI de transplantectomia, acomodado no leito, apresentando-se sonolento, mantem SSVV estáveis : PA : 150x70 mmhg, Temp: 36,2° C, P: 105, FR: 19, Spo2: 90 %, instalado névoa umida a 3l/mim, porém paciente recusa-se a permanecer por muito tempo com o oxigênio, mantem acesso venoso periférico pérvio em MSD , curativo em flanco inferior direito limpo e seco externamente, não refere queixas álgicas. Iniciou com transfusão de 1 unidade de concentrados de hemáceas a 01:40h, até o momento sem intercorrências, segue sob cuidados de enfermagem. Enfermeira Florence Nightingale . EXAME GERAL E INVESTIGACAO DE PESSOAS SEM QUEIXAS OU DIAGNOSTICO RELATADO.",
  "entities": {
    "Atividade de Assistência à Saúde": [
      "encaminhado",
      "cuidados",
      "EXAME GERAL"
    ],
    "Abreviação": [
      "POI",
      "PA",
      "Temp",
      "P",
      "FR",
      "Spo2",
      "MSD",
      "SSVV estáveis"
    ],
    "Conceito Temporal": [
      "POI",
      "momento"
    ],
    "Sinal ou Sintoma": [
      "sonolento",
      "intercorrências",
      "QUEIXAS",
      "queixas álgicas"
    ],
    "Atributo Clínico": [
      "PA",
      "Temp",
      "P",
      "FR",
      "Spo2"
    ],
    "Conceito Quantitativo": [
      "105",
      "19",
      "3l/mim",
      "150x70 mmhg",
      "36 , 2° C",
      "90 %"
    ],
    "Procedimento Terapêutico ou Preventivo": [
      "oxigênio",
      "curativo",
      "névoa umida",
      "acesso venoso periférico",
      "transfusão de 1 unidade de concentrados de hemáceas"
    ],
    "Conceito Qualitativo": [
      "pérvio",
      "limpo"
    ],
    "Parte do Corpo, Órgão ou Componente Orgânico": [
      "MSD"
    ],
    "Dispositivo Médico": [
      "curativo",
      "acesso venoso periférico"
    ],
    "Conceito Espacial": [
      "externamente"
    ],
    "Negação": [
      "não",
      "sem",
      "SEM"
    ],
    "Organização Relacionada à Saúde": [
      "enfermagem",
      "centro cirúrgico"
    ],
    "Grupo Profissional ou Ocupacional": [
      "enfermagem",
      "Enfermeira"
    ],
    "Doença ou Síndrome": [
      "QUEIXAS",
      "DIAGNOSTICO RELATADO"
    ],
    "Achado": [
      "acomodado no leito",
      "SSVV estáveis"
    ],
    "Localização ou Região Corporal": [
      "flanco inferior direito"
    ],
    "Procedimento Diagnóstico": [
      "INVESTIGACAO DE PESSOAS"
    ]
  },
  "labels": {
    "diagnostico relatado": {
      "capitulo": "21"
    },
    "intercorrências": {
      "capitulo": "22"
    },
    "sonolento": {
      "capitulo": "07"
    },
    "ssvv estáveis": {
      "capitulo": "11"
    },
    "queixas": {
      "capitulo": "21"
    }
  }
}