{
  "prontuario_id": 573,
  "text": "18:20HR PROVENIENTE DO HOSPITAL DIA EM POI DE EMBOLIZAÇÃO DE ANEURISMA. PA 116/67 MMHGM, FC 78 BPM, SPO2 98%. SEM QUEIXAS AGICAS, ASPECTO DE CONFORTO E BEM ESTAR. GLASGOW 15, PUPILAS IS \\ FOTO, ESCLERAS E CONJUNTIVAS  NORMOCORADAS, BOCA HIGIENIZADA. RESPIRAÇÃO TORACICA, AMPLITUDE PROFUNDA, AR AMBIENTE, CPP LIVRES DE RA. BCRNF. ABDOME GLOBOSO POR ACUMULO DE TECIDO ADIPOSO, RHA NORMOATIVOS. PUNÇÃO VENOSA EM MSD COM SF 0,9% EM PLANO BASICO DE HIDRATÇÃO EM CURSO. CURATIVO OCLUSIVO EM REGIÃO INGUINAL D. DIURESE EM COMADRE. SEGUE SOB OS CUIDADOS DA ENFERMAGEM. Enfermeira Florence Nightingale.  TRAUMATISMO INTRACRANIANO.",
  "entities": {
    "Organização Relacionada à Saúde": [
      "HOSPITAL",
      "ENFERMAGEM"
    ],
    "Abreviação": [
      "POI",
      "PA",
      "FC",
      "SPO2",
      "IS",
      "FOTO",
      "RA",
      "BCRNF",
      "MSD",
      "CPP LIVRES",
      "RHA NORMOATIVOS",
      "REGIÃO INGUINAL D"
    ],
    "Conceito Temporal": [
      "POI"
    ],
    "Atributo Clínico": [
      "PA",
      "FC",
      "SPO2"
    ],
    "Conceito Quantitativo": [
      "98%",
      "116/67 MMHGM",
      "78 BPM"
    ],
    "Negação": [
      "SEM"
    ],
    "Parte do Corpo, Órgão ou Componente Orgânico": [
      "PUPILAS",
      "ESCLERAS",
      "CONJUNTIVAS",
      "MSD"
    ],
    "Achado": [
      "IS",
      "FOTO",
      "NORMOCORADAS",
      "BCRNF",
      "ASPECTO DE CONFORTO",
      "BEM ESTAR",
      "GLASGOW 15",
      "BOCA HIGIENIZADA",
      "RESPIRAÇÃO TORACICA",
      "CPP LIVRES",
      "ABDOME GLOBOSO",
      "RHA NORMOATIVOS"
    ],
    "Sinal ou Sintoma": [
      "RA",
      "QUEIXAS AGICAS",
      "AMPLITUDE PROFUNDA",
      "ACUMULO DE TECIDO ADIPOSO"
    ],
    "Substância Farmacológica": [
      "SF"
    ],
    "Procedimento Terapêutico ou Preventivo": [
      "HIDRATÇÃO",
      "PUNÇÃO VENOSA",
      "CURATIVO OCLUSIVO"
    ],
    "Função de Organismo": [
      "DIURESE"
    ],
    "Objeto Físico": [
      "COMADRE"
    ],
    "Atividade de Assistência à Saúde": [
      "CUIDADOS",
      "PLANO BASICO"
    ],
    "Grupo Profissional ou Ocupacional": [
      "Enfermeira"
    ],
    "Doença ou Síndrome": [
      "EMBOLIZAÇÃO DE ANEURISMA",
      "TRAUMATISMO INTRACRANIANO"
    ],
    "Dispositivo Médico": [
      "PUNÇÃO VENOSA",
      "CURATIVO OCLUSIVO"
    ],
    "Localização ou Região Corporal": [
      "REGIÃO INGUINAL D"
    ]
  },
  "labels": {
    "traumatismo intracraniano": {
      "capitulo": "08"
    },
    "embolização de aneurisma": {
      "capitulo": "11"
    },
    "abdome globoso": {
      "capitulo": "15"
    },
    "acumulo de tecido adiposo": {
      "capitulo": "15"
    },
    "respiração toracica": {
      "capitulo": "12"
    },
    "glasgow 15": {
      "capitulo": "08"
    },
    "foto": {
      "capitulo": "X"
    },
    "queixas agicas": {
      "capitulo": "21"
    }
  }
}