{
  "prontuario_id": 164,
  "text": "S - PROVENIENTE PS ÀS 20h30. # HX BRONCOASPIRAÇÃO APÓS ALIMENTAÇÃO, SENDO LEVADA PARA XXXX, SEGUNDO INFORMAÇÃO FAMILIAR. # PNEUMONIA ASPIRATIVA.   * AVCs / DPOC.  O - CHEGA COM RAMSAY: 06, PUPILAS ISOMIÓTICAS RFM +, INTUBADO SOB VM: VCV: 470, PEEP: 5, FR: 15, FIO2: 0,5%, MANTEM FILTRO BARREIRA BACTERIOLOGICO, SNG FECHADA, CATETER VENOSO PERIFERICO EM JUGULAR EXTERNA À ESQUERDA COM SG 5% EM CURSO, CATETER VENOSO PERIFÉRICO EM ANTEBRAÇO DIREITO COM DOPAMINA À 30ML/H, FENTANIL À 20ML/H, DORMONID À 30ML/H EM BI, MMSS E MMII LIVRES DE EDEMA E EXTREMIDADE COM PERFUSÃO PRESERVADA, AC: BCRNF, AP: CPL, ABD: RHA+, PLANO E FLACIDO, SVD COM DIURESE EFETIVA AMARELO OURO. REGIÃO SACRA E CALCANEOS COM ULCERA POR PRESSÃO ESTAGIO II. REALIZADO COLETA DE 2 AMOSTRA DE HEMOCULTURA E UROCULTURA NO PS POR Enfermeira Florence Nightingale.  HEMORRAGIA GASTROINTESTINAL SEM OUTRA ESPECIFICACAO.",
  "entities": {
    "Abreviação": [
      "S",
      "PS",
      "HX",
      "AVCs",
      "DPOC",
      "O",
      "VM",
      "VCV",
      "PEEP",
      "FR",
      "FIO2",
      "BI",
      "MMSS",
      "MMII",
      "AC",
      "BCRNF",
      "AP",
      "CPL",
      "ABD",
      "RHA+",
      "SVD",
      "RFM +",
      "SNG FECHADA"
    ],
    "Organização Relacionada à Saúde": [
      "PS"
    ],
    "Conceito Temporal": [
      "APÓS"
    ],
    "Alimento": [
      "ALIMENTAÇÃO"
    ],
    "Doença ou Síndrome": [
      "AVCs",
      "DPOC",
      "PNEUMONIA ASPIRATIVA",
      "ULCERA POR PRESSÃO ESTAGIO II",
      "HEMORRAGIA GASTROINTESTINAL"
    ],
    "Parte do Corpo, Órgão ou Componente Orgânico": [
      "PUPILAS",
      "MMSS",
      "MMII",
      "CALCANEOS",
      "JUGULAR EXTERNA À ESQUERDA",
      "ANTEBRAÇO DIREITO"
    ],
    "Sinal ou Sintoma": [
      "ISOMIÓTICAS",
      "EDEMA",
      "RAMSAY : 06"
    ],
    "Procedimento Terapêutico ou Preventivo": [
      "INTUBADO",
      "VM",
      "SVD",
      "SNG FECHADA",
      "CATETER VENOSO PERIFERICO",
      "CATETER VENOSO PERIFÉRICO"
    ],
    "Conceito Quantitativo": [
      "470",
      "5",
      "15",
      "5%",
      "20ML/H",
      "30ML/H",
      "0 , 5%",
      "2 AMOSTRA"
    ],
    "Atributo Clínico": [
      "PEEP",
      "FR",
      "FIO2"
    ],
    "Substância Farmacológica": [
      "SG",
      "DOPAMINA",
      "FENTANIL",
      "DORMONID"
    ],
    "Substância Biologicamente Ativa": [
      "DOPAMINA"
    ],
    "Substância Química Orgânica": [
      "DOPAMINA",
      "FENTANIL",
      "DORMONID"
    ],
    "Dispositivo de Administração de Medicamento": [
      "BI"
    ],
    "Negação": [
      "LIVRES",
      "SEM"
    ],
    "Procedimento Diagnóstico": [
      "AC",
      "AP",
      "HEMOCULTURA",
      "UROCULTURA"
    ],
    "Achado": [
      "BCRNF",
      "CPL",
      "RHA+",
      "PLANO",
      "FLACIDO",
      "RFM +",
      "EXTREMIDADE COM PERFUSÃO PRESERVADA",
      "DIURESE EFETIVA",
      "AMARELO OURO"
    ],
    "Dispositivo Médico": [
      "SVD",
      "FILTRO BARREIRA BACTERIOLOGICO",
      "SNG FECHADA",
      "CATETER VENOSO PERIFERICO",
      "CATETER VENOSO PERIFÉRICO"
    ],
    "Atividade de Assistência à Saúde": [
      "COLETA"
    ],
    "Grupo Profissional ou Ocupacional": [
      "Enfermeira"
    ],
    "Resultado Laboratorial ou de Teste": [
      "RFM +"
    ],
    "Função de Organismo": [
      "DIURESE EFETIVA"
    ],
    "Conceito Qualitativo": [
      "AMARELO OURO"
    ],
    "Localização ou Região Corporal": [
      "REGIÃO SACRA"
    ]
  },
  "labels": {
    "ramsay : 06": {
      "capitulo": "08"
    },
    "avcs / dpoc": {
      "capitulo": "08"
    },
    "edema": {
      "capitulo": "15"
    },
    "pneumonia aspirativa": {
      "capitulo": "12"
    },
    "ulcera por pressão estagio ii": {
      "capitulo": "15"
    },
    "hemorragia gastrointestinal": {
      "capitulo": "12"
    }
  }
}