{
  "prontuario_id": 350,
  "text": "10:00hs - POI de nefrectomia e esplenectomia, glasglow 15, pupilas isocóricas e fotoreagentes, respiração espontanea com suporte de névoa ´mida saturando 100%, AVPMSE com soroterapia gravitacional em curso, SVD com diurese presente. Monitorizado com PNI: 120x90 mmHg, cardioscopia com Fc: 75 bpm e oximetria depulso, mucosa coradas, AP: MV presentes e roncos esparsos com tosse efetiv, abdomen flácido , doloroso a palpação com RH presente, curativo de laparotomia com um ponto pouco sangrante, DTF a esquerda pouco hemático e sem fuga aerea, extremidades aquecidas e bem perfundidas. Enfermeira Florence Nightingale. TRAUMATISMO DE REGIAO NAO ESPECIFICADA DO CORPO.",
  "entities": {
    "Conceito Temporal": [
      "POI"
    ],
    "Abreviação": [
      "POI",
      "AVPMSE",
      "SVD",
      "PNI",
      "Fc",
      "AP",
      "DTF",
      "75 bpm",
      "MV presentes",
      "RH presente"
    ],
    "Procedimento Terapêutico ou Preventivo": [
      "nefrectomia",
      "esplenectomia",
      "AVPMSE",
      "SVD",
      "PNI",
      "DTF",
      "suporte de névoa ´mida",
      "soroterapia gravitacional",
      "curativo de laparotomia"
    ],
    "Parte do Corpo, Órgão ou Componente Orgânico": [
      "pupilas",
      "abdomen"
    ],
    "Achado": [
      "isocóricas",
      "fotoreagentes",
      "flácido",
      "glasglow 15",
      "respiração espontanea",
      "saturando 100%",
      "mucosa coradas",
      "MV presentes",
      "RH presente",
      "extremidades aquecidas",
      "bem perfundidas"
    ],
    "Dispositivo Médico": [
      "AVPMSE",
      "SVD"
    ],
    "Atividade de Assistência à Saúde": [
      "Monitorizado"
    ],
    "Procedimento Diagnóstico": [
      "PNI",
      "cardioscopia",
      "AP",
      "palpação",
      "oximetria depulso"
    ],
    "Atributo Clínico": [
      "Fc"
    ],
    "Sinal ou Sintoma": [
      "doloroso",
      "hemático",
      "roncos esparsos",
      "tosse efetiv",
      "ponto pouco sangrante",
      "fuga aerea"
    ],
    "Conceito Espacial": [
      "esquerda"
    ],
    "Negação": [
      "sem"
    ],
    "Grupo Profissional ou Ocupacional": [
      "Enfermeira"
    ],
    "Função de Organismo": [
      "diurese presente"
    ],
    "Conceito Quantitativo": [
      "120x90 mmHg",
      "75 bpm"
    ]
  },
  "labels": {
    "isocóricas": {
      "capitulo": "11"
    },
    "flácido": {
      "capitulo": "15"
    },
    "fuga aerea": {
      "capitulo": "22"
    },
    "respiração espontanea": {
      "capitulo": "12"
    },
    "hemático": {
      "capitulo": "16"
    },
    "doloroso": {
      "capitulo": "15"
    },
    "mv presentes": {
      "capitulo": "11"
    },
    "fotoreagentes": {
      "capitulo": "09"
    },
    "roncos esparsos": {
      "capitulo": "21"
    },
    "ponto pouco sangrante": {
      "capitulo": "22"
    },
    "tosse efetiv": {
      "capitulo": "21"
    },
    "mucosa coradas": {
      "capitulo": "14"
    }
  }
}