{
  "prontuario_id": 709,
  "text": "15h - Glasgow 10, pupilas iso / foto +, traqueostomizado, traqueo de plastico, suporte de O² sob nevoa a 2l/min, aspirado pouca quantidade de secreção de aspecto seroso, puncionado novo acesso em dorso mao D com abocath 22, mantem soroterapia em curso, abdomen globoso e flacido, gastrostomia com dieta a 75 ml/h em BI, apresentando globo vesical, tentativa de cateterismo de alivio sem sucesso, chamado plantao da urologia, Doutor Vital Brazil realizou passagem de sonda vesical de demora nº 16, diurese presente de coloração citrina, edema em MMII e MMSS cacifo ++/IV, lesoes em MMII, uso de fralda para eliminações, realizada medidas de conforto, segue sob cuidados e observação. Mantem precaução por contato.  Enfermeira Florence Nightingale. SEPTICEMIA NAO ESPECIFICADA.",
  "entities": {
    "Parte do Corpo, Órgão ou Componente Orgânico": [
      "pupilas",
      "abdomen",
      "MMII",
      "MMSS"
    ],
    "Abreviação": [
      "iso",
      "foto",
      "BI",
      "MMII",
      "MMSS",
      "traqueo de plastico",
      "dorso mao D"
    ],
    "Achado": [
      "iso",
      "foto",
      "globoso",
      "flacido",
      "sucesso",
      "diurese presente"
    ],
    "Procedimento Terapêutico ou Preventivo": [
      "traqueostomizado",
      "aspirado",
      "soroterapia",
      "traqueo de plastico",
      "suporte de O² sob nevoa",
      "sonda vesical de demora",
      "medidas de conforto",
      "precaução por contato"
    ],
    "Conceito Quantitativo": [
      "2l/min",
      "75 ml/h",
      "nº 16"
    ],
    "Dispositivo Médico": [
      "acesso",
      "fralda",
      "traqueo de plastico",
      "abocath 22",
      "sonda vesical de demora"
    ],
    "Dispositivo de Administração de Medicamento": [
      "BI"
    ],
    "Negação": [
      "sem"
    ],
    "Grupo Profissional ou Ocupacional": [
      "Doutor",
      "Enfermeira",
      "plantao da urologia"
    ],
    "Sinal ou Sintoma": [
      "edema",
      "Glasgow 10",
      "globo vesical"
    ],
    "Lesão ou Envenenamento": [
      "lesoes"
    ],
    "Objeto Manufaturado": [
      "fralda",
      "traqueo de plastico"
    ],
    "Função de Organismo": [
      "eliminações",
      "diurese presente"
    ],
    "Atividade de Assistência à Saúde": [
      "cuidados",
      "observação",
      "cateterismo de alivio",
      "medidas de conforto"
    ],
    "Conceito Qualitativo": [
      "aspecto seroso",
      "coloração citrina"
    ],
    "Localização ou Região Corporal": [
      "dorso mao D"
    ],
    "Resultado Laboratorial ou de Teste": [
      "cacifo ++/IV"
    ]
  },
  "labels": {
    "flacido": {
      "capitulo": "15"
    },
    "edema": {
      "capitulo": "11"
    },
    "foto": {
      "capitulo": "09"
    },
    "lesoes": {
      "capitulo": "21"
    },
    "globoso": {
      "capitulo": "13"
    },
    "glasgow 10": {
      "capitulo": "08"
    },
    "globo vesical": {
      "capitulo": "16"
    },
    "iso": {
      "capitulo": "09"
    }
  }
}