{
  "prontuario_id": 992,
  "text": "8:10Hrs - 2° DI  UTI / Dx: DpOC, derrame pleural DIR. # 2° IOT + VM. # 2° D SNG em narina DIR. # 2° AV JEE + MSD. # 2° SVD.  Cliente em ramsay 6, pupilas iso / foto +, IOT + VM. Mantem com monitorização de multiparametros ECG, PNI, SpO2,   SNG aberta com estase gastrica presente ++ de aspecto biliosa, acesso venoso JEE com srt + acesso venoso pereiferico em MSD com dormonid 40ml/hr, fentanil 20ml/hr em curso BI. Apresenta ausculta pulmonar MV + com roncos difusos, abdomem plano e flacido com RHA +, hiperemia em região sacra-coccigeana. Faz uso de SVD aberta com debito diuretico presente ++ de coloração amarelo-claro, eliminação fecal ausente. Segue cuidados intensivos de enfermagem.  Enfermeira Florence Nightingale . OUTRAS DOENCAS PULMONARES OBSTRUTIVAS CRONICAS.",
  "entities": {
    "Abreviação": [
      "UTI",
      "Dx",
      "DpOC",
      "IOT",
      "VM",
      "SNG",
      "AV",
      "JEE",
      "MSD",
      "SVD",
      "iso",
      "ECG",
      "PNI",
      "SpO2",
      "srt",
      "BI",
      "narina DIR",
      "foto +",
      "SNG aberta",
      "MV +",
      "RHA +",
      "SVD aberta"
    ],
    "Organização Relacionada à Saúde": [
      "UTI",
      "enfermagem"
    ],
    "Procedimento Diagnóstico": [
      "Dx",
      "ECG",
      "PNI",
      "SpO2",
      "ausculta pulmonar"
    ],
    "Doença ou Síndrome": [
      "DpOC",
      "derrame pleural DIR",
      "DOENCAS PULMONARES OBSTRUTIVAS CRONICAS"
    ],
    "Procedimento Terapêutico ou Preventivo": [
      "IOT",
      "VM",
      "SNG",
      "AV",
      "SVD",
      "PNI",
      "SpO2",
      "srt",
      "SNG aberta",
      "acesso venoso",
      "acesso venoso pereiferico",
      "SVD aberta"
    ],
    "Dispositivo Médico": [
      "SNG",
      "AV",
      "SVD",
      "IOT",
      "SNG aberta",
      "acesso venoso",
      "acesso venoso pereiferico",
      "SVD aberta"
    ],
    "Parte do Corpo, Órgão ou Componente Orgânico": [
      "JEE",
      "MSD",
      "pupilas",
      "abdomem"
    ],
    "Achado": [
      "iso",
      "plano",
      "flacido",
      "foto +",
      "MV +",
      "RHA +",
      "debito diuretico presente"
    ],
    "Substância Química Orgânica": [
      "dormonid",
      "fentanil"
    ],
    "Substância Farmacológica": [
      "dormonid",
      "fentanil"
    ],
    "Conceito Quantitativo": [
      "40ml/hr",
      "20ml/hr"
    ],
    "Dispositivo de Administração de Medicamento": [
      "BI"
    ],
    "Sinal ou Sintoma": [
      "hiperemia",
      "ramsay 6",
      "estase gastrica presente ++",
      "aspecto biliosa",
      "roncos difusos"
    ],
    "Negação": [
      "ausente"
    ],
    "Grupo Profissional ou Ocupacional": [
      "Enfermeira"
    ],
    "Conceito Temporal": [
      "2° DI"
    ],
    "Atividade de Assistência à Saúde": [
      "monitorização de multiparametros",
      "cuidados intensivos"
    ],
    "Conceito Qualitativo": [
      "aspecto biliosa",
      "coloração amarelo-claro"
    ],
    "Localização ou Região Corporal": [
      "região sacra-coccigeana"
    ],
    "Função de Organismo": [
      "debito diuretico presente",
      "eliminação fecal"
    ]
  },
  "labels": {
    "doencas pulmonares obstrutivas cronicas": {
      "capitulo": "12"
    },
    "aspecto biliosa": {
      "capitulo": "13"
    },
    "roncos difusos": {
      "capitulo": "12"
    },
    "dpoc": {
      "capitulo": "03"
    },
    "mv +": {
      "capitulo": "12"
    },
    "derrame pleural dir": {
      "capitulo": "12"
    },
    "hiperemia": {
      "capitulo": "15"
    },
    "estase gastrica presente ++": {
      "capitulo": "13"
    }
  }
}