{
  "prontuario_id": 259,
  "text": "          Paciente HAS, asmática em uso crônico de presdnisona, com história de episódios de pré-síncope; consultou na XXXX,  realizando ECG que mostrou BAV total com posteior  escape em TV (27/06/02). Realizado avaliação enzimática sugestica de IAM não Q + persistência de isquemia lateral ao ECG.           Realizou CAT em 02/06/02 mostrando oclusão total em 1/3 médio de CD, onde foi realizado ACTP + colocação de stent com boa revascularização (TIMI 3).            Apresenta boa evolução após o procedimento, sem sinais ou sintomas de isquemia. Recebe alta em bom estado geral, com orientações de retorno ao ambulatório de cardiologia para revisão. ",
  "entities": {
    "Abreviação": [
      "HAS",
      "ECG",
      "CAT",
      "BAV total com posteior escape em TV",
      "IAM não Q",
      "1/3 médio de CD",
      "realizado ACTP"
    ],
    "Doença ou Síndrome": [
      "HAS",
      "asmática",
      "IAM não Q",
      "oclusão total"
    ],
    "Conceito Temporal": [
      "crônico",
      "episódios",
      "persistência",
      "após"
    ],
    "Substância Química Orgânica": [
      "presdnisona"
    ],
    "Hormônio": [
      "presdnisona"
    ],
    "Substância Farmacológica": [
      "presdnisona"
    ],
    "Sinal ou Sintoma": [
      "pré-síncope",
      "sinais ou sintomas de isquemia"
    ],
    "Atividade de Assistência à Saúde": [
      "consultou",
      "colocação",
      "alta",
      "retorno",
      "revisão"
    ],
    "Procedimento Diagnóstico": [
      "ECG",
      "CAT",
      "procedimento"
    ],
    "Procedimento Terapêutico ou Preventivo": [
      "CAT",
      "procedimento",
      "realizado ACTP"
    ],
    "Dispositivo Médico": [
      "stent"
    ],
    "Negação": [
      "sem",
      "IAM não Q"
    ],
    "Resultado Laboratorial ou de Teste": [
      "BAV total com posteior escape em TV",
      "isquemia lateral",
      "oclusão total"
    ],
    "Procedimento Laboratorial": [
      "avaliação enzimática"
    ],
    "Parte do Corpo, Órgão ou Componente Orgânico": [
      "1/3 médio de CD"
    ],
    "Achado": [
      "boa revascularização",
      "boa evolução",
      "bom estado geral"
    ],
    "Organização Relacionada à Saúde": [
      "ambulatório de cardiologia"
    ]
  },
  "labels": {
    "sinais ou sintomas de isquemia": {
      "capitulo": "11"
    },
    "asmática": {
      "capitulo": "12"
    },
    "iam não q": {
      "capitulo": "08"
    },
    "oclusão total": {
      "capitulo": "11"
    },
    "boa revascularização": {
      "capitulo": "11"
    },
    "pré-síncope": {
      "capitulo": "06"
    }
  }
}