{
  "prontuario_id": 826,
  "text": "PACIENTE SUBMETIDO A ANGIOPLASTIA CORONARIANA COM IMPLANTE DE STENT EM ADA E DIAGONAL EM 14 /04/2003. INTERNOU PARA INVESTIGAR DOR PRECORDIAL ATIPICA; REALIZADO VARIOS ECG(S) E SERIE DE ENZIMAS QUE RESULTARAM NORMAIS; FEZ CINTILOGRAFIA MIOCARDICA COM ESTRESSE FARMACOLÓGICO QUE EVIDENCIOU PERFUSÃO NORMAL; DURANTE A INTERNAÇÃO AUMENTOU-SE A DOSE DE NITRATO E ADMNISTROU-SE ENOXAPARINA. MELHOROU DOS SINTOMAS, MAS AINDA PERSISTE COM EPISIDIOS DE DOR PRECORDIAL ATIPICA, DE LEVE INTENSIDADE E ESPORADICA;  RECEBE ALTA HOSPITALAR COM A ORIENTAÇÃO DE CONSULTAR COM MEDICO ASSISTENTE E COM PLANO DE REALIZAR CINTILOGRAFIA MIOCARDICA DE ESFORÇO;",
  "entities": {
    "Atividade de Assistência à Saúde": [
      "SUBMETIDO",
      "INTERNOU",
      "INVESTIGAR",
      "REALIZADO",
      "INTERNAÇÃO",
      "ADMNISTROU-SE",
      "ORIENTAÇÃO",
      "REALIZAR",
      "ALTA HOSPITALAR"
    ],
    "Parte do Corpo, Órgão ou Componente Orgânico": [
      "ADA",
      "DIAGONAL"
    ],
    "Abreviação": [
      "ADA",
      "ECG"
    ],
    "Procedimento Diagnóstico": [
      "ECG",
      "CINTILOGRAFIA MIOCARDICA COM ESTRESSE FARMACOLÓGICO",
      "CINTILOGRAFIA MIOCARDICA DE ESFORÇO"
    ],
    "Achado": [
      "NORMAIS",
      "PERFUSÃO NORMAL",
      "MELHOROU DOS SINTOMAS"
    ],
    "Conceito Quantitativo": [
      "DOSE"
    ],
    "Substância Farmacológica": [
      "NITRATO",
      "ENOXAPARINA"
    ],
    "Substância Química Orgânica": [
      "ENOXAPARINA"
    ],
    "Conceito Temporal": [
      "EPISIDIOS",
      "ESPORADICA"
    ],
    "Procedimento Terapêutico ou Preventivo": [
      "ANGIOPLASTIA CORONARIANA",
      "IMPLANTE IMPLANTE DE DE STENT STENT"
    ],
    "Sinal ou Sintoma": [
      "DOR PRECORDIAL ATIPICA"
    ],
    "Procedimento Laboratorial": [
      "SERIE DE ENZIMAS"
    ],
    "Resultado Laboratorial ou de Teste": [
      "PERFUSÃO NORMAL"
    ],
    "Conceito Qualitativo": [
      "LEVE INTENSIDADE"
    ],
    "Grupo Profissional ou Ocupacional": [
      "MEDICO ASSISTENTE"
    ]
  },
  "labels": {
    "melhorou dos sintomas": {
      "capitulo": "11"
    },
    "dor precordial atipica": {
      "capitulo": "11"
    }
  }
}