{
  "prontuario_id": 45,
  "text": "R2 LUCAS\nEQUIPE DA RETINA.\n\nLUCAS, 52A.\n\n# BAV OD NPL E PTOSE DESDE TRAUMA CONTUSO OD APÓS QUEDA DE ESCADA EM 28/05/15, COM MÚLTIPLAS FRATURAS DE ÓRBITA, SUBMETIDO A CX DE FACE (MANTÉM ACOMPANHAMENTO).\n# ATENDIDO NO HUC, REALIZOU TC DE CRÂNIO NA OCASIÃO (NÃO ESTÁ NO SISTEMA).\n# DM HÁ >10A, EM USO DE MTF, GLIBENCLAMIDA E ACARBOSE, SEM HX DE FOTOCOAGULAÇÃO PRÉVIA + HAS EM USO DE LOSARTAN.\n\nVEIO PARA AVALIAÇÃO DE HV OD E TRAZER US SOLICITADO.\n\nUS (17/06/15): DIÂMETRO AP DIMINUÍDO, CAVIDADE VÍTREA PREENCHIDA POR ECOS DE ALTA REFLETIVIDADE, FORMANDO MBNS CONTÍNUAS, IMAGEM SUGESTIVA DE ? E HV, CORÓIDE EM POSIÇÃO.\n\nAV:\nOD S/C NPL.\nOE C/C 20/30P.\n\nBIO:\nOD PTOSE, RCA 2+, CATARATA, SEM NVI, HV, CÓRNEA CLARA, PIGMENTOS DE ÍRIS EM ENDOTÉLIO, PUPILA POUCO REAGENTE.\nOE VH 4, SEM NVI, CÓRNEA E CRISTALINO CLAROS.\n\nPIO: 13 / 13.\n\nMR:\nOD HV MACIÇO + DR.\nOE RD PRÉ-PROLIFERATIVA.\n\nP # NÃO INDICADO VVPP OD POR PROGNÓSTICO RUIM, PCT NPL DESDE O TRAUMA, PROVÁVEL LESÃO DE N ÓPTICO.\n     ORIENTO PEGAR TOMOGRAFIA REALIZADA NO INTERNAMENTO E TRAZER NA PRÓXIMA CONSULTA.\n     MANTENHO PREDFORT E MYD 12/12H ATÉ O RETORNO.\n     SOLICITO PANFOTO OE POR RD PRÉ PROLIFERATIVA E AF PÓS FOTO 45 - 60 DIAS APÓS.\n     RETORNO EM 15/09/15.\n \n \n \n ",
  "entities": {
    "Abreviação": [
      "R2",
      "DM",
      "MTF",
      "HAS",
      "HV",
      "OD",
      "US",
      "AV",
      "S/C",
      "NPL",
      "OE",
      "C/C",
      "BIO",
      "NVI",
      "PIO",
      "MR",
      "DR",
      "VVPP",
      "PCT",
      "MYD",
      "PANFOTO",
      "TC DE CRÂNIO",
      "DIÂMETRO AP DIMINUÍDO",
      "RCA 2+",
      "VH 4",
      "HV MACIÇO",
      "RD PRÉ-PROLIFERATIVA",
      "N ÓPTICO",
      "RD PRÉ PROLIFERATIVA",
      "PÓS FOTO"
    ],
    "Grupo Profissional ou Ocupacional": [
      "R2",
      "EQUIPE DA RETINA"
    ],
    "Atividade de Assistência à Saúde": [
      "ATENDIDO",
      "AVALIAÇÃO",
      "SOLICITADO",
      "INDICADO",
      "ORIENTO",
      "INTERNAMENTO",
      "CONSULTA",
      "MANTENHO",
      "RETORNO",
      "SOLICITO"
    ],
    "Negação": [
      "NÃO",
      "SEM",
      "S/C",
      "NPL"
    ],
    "Doença ou Síndrome": [
      "DM",
      "HAS",
      "DR",
      "RD PRÉ-PROLIFERATIVA",
      "RD PRÉ PROLIFERATIVA"
    ],
    "Substância Farmacológica": [
      "MTF",
      "GLIBENCLAMIDA",
      "ACARBOSE",
      "LOSARTAN",
      "PREDFORT",
      "MYD"
    ],
    "Substância Química Orgânica": [
      "MTF",
      "GLIBENCLAMIDA",
      "ACARBOSE",
      "LOSARTAN"
    ],
    "Procedimento Terapêutico ou Preventivo": [
      "FOTOCOAGULAÇÃO",
      "VVPP",
      "PANFOTO"
    ],
    "Conceito Temporal": [
      "PRÉVIA",
      "DESDE",
      "PRÓXIMA",
      "ATÉ",
      "APÓS",
      "PÓS FOTO",
      "45 - 60 DIAS"
    ],
    "Parte do Corpo, Órgão ou Componente Orgânico": [
      "OD",
      "OE",
      "CÓRNEA",
      "CRISTALINO",
      "N ÓPTICO"
    ],
    "Procedimento Diagnóstico": [
      "US",
      "AV",
      "BIO",
      "PIO",
      "MR",
      "TOMOGRAFIA",
      "TC DE CRÂNIO"
    ],
    "Sinal ou Sintoma": [
      "NPL",
      "PTOSE",
      "PIGMENTOS DE ÍRIS EM ENDOTÉLIO",
      "PUPILA POUCO REAGENTE"
    ],
    "Conceito Quantitativo": [
      "20/30P",
      "12/12H",
      "13 / 13"
    ],
    "Anormalidade Adquirida": [
      "CATARATA"
    ],
    "Função Patológica": [
      "NVI",
      "HV",
      "HV MACIÇO"
    ],
    "Conceito Qualitativo": [
      "CLAROS"
    ],
    "Achado": [
      "CLAROS",
      "IMAGEM SUGESTIVA",
      "CORÓIDE EM POSIÇÃO",
      "CÓRNEA CLARA"
    ],
    "Lesão ou Envenenamento": [
      "TRAUMA",
      "LESÃO"
    ],
    "Organização Relacionada à Saúde": [
      "EQUIPE DA RETINA"
    ],
    "Resultado Laboratorial ou de Teste": [
      "DIÂMETRO AP DIMINUÍDO",
      "CAVIDADE VÍTREA PREENCHIDA POR ECOS DE ALTA REFLETIVIDADE",
      "IMAGEM SUGESTIVA",
      "RCA 2+",
      "VH 4"
    ]
  },
  "labels": {
    "claros": {
      "capitulo": "09"
    },
    "rd pré-proliferativa": {
      "capitulo": "08"
    },
    "ptose": {
      "capitulo": "09"
    },
    "hv maciço": {
      "capitulo": "09"
    },
    "pigmentos de íris em endotélio": {
      "capitulo": "09"
    },
    "lesão": {
      "capitulo": "22"
    },
    "córnea clara": {
      "capitulo": "09"
    },
    "npl": {
      "capitulo": "09"
    },
    "hv": {
      "capitulo": "09"
    },
    "pupila pouco reagente": {
      "capitulo": "09"
    },
    "imagem sugestiva": {
      "capitulo": "21"
    },
    "catarata": {
      "capitulo": "09"
    },
    "coróide em posição": {
      "capitulo": "09"
    },
    "dr": {
      "capitulo": "11"
    },
    "has": {
      "capitulo": "05"
    },
    "nvi": {
      "capitulo": "09"
    },
    "dm": {
      "capitulo": "05"
    },
    "trauma": {
      "capitulo": "22"
    }
  }
}