{
  "prontuario_id": 664,
  "text": "# QP: BAV EM OD PROGRESSVIA E INSIDIOSA HÁ 1 ANO E MEIO. NEGA OUTRAS QUEIXAS OCULARES.\n# DM HÁ 5 ANOS - EM TRATAMENTO VO - GJ 150 - 200\n# NEGA HAS / CIRURGIA E TRAUMA OCULAR\n# NEGA HF DE GLAUCOMA E AMAUROSE\nAVSC:\n20 / 400\n20 / 200\nAVCC:\n20 / 200\n20 / 70\nÓCULOS EM USO:\n- 2,00 ESF\n- 1,50 - 0,50 135\nAD: + 3,00\nT:\n- 3,50 - 1,00 60 // 20 / 60\n- 1,50 - 0,50 135 // 20 / 50\nAD: + 3,00\nJ1\nBIO:\nCATARATA + BUT REDUZIDO AO\nMR: MA'S E MH'S. ATROFIA DE EPR AO.\nCLASSIFICAÇÃO DE CATARA:\nOD: ANTERIOR: 1+ / NUCLEAR 2+ / POSTERIOR 2+.\nOE:\nANTERIOR 1+ / NUCLEAR 1-2+ / POSTERIOR 2+\nCD: PRESCREVO: - 3,00 - 0,75 60 // - 1,50 - 0,50 135 // AD: + 3,00\nOBS: SOLICITO EXAMES ( PRE OP DE FACO + ANGIOGRAFIA PORÉM PACIENTE NÃO DESEJA REALIZAR).\nRETORNO ANUAL VIA UBS.\nR1: Dr Vital Brasil\nR2: Dr Vital Brasil\n \n \n \n ",
  "entities": {
    "Sinal ou Sintoma": [
      "QP",
      "BAV",
      "REDUZIDO",
      "QUEIXAS OCULARES",
      "20 / 400",
      "20 / 200",
      "20 / 70"
    ],
    "Abreviação": [
      "QP",
      "BAV",
      "OD",
      "DM",
      "VO",
      "GJ",
      "HAS",
      "HF",
      "AVSC",
      "AVCC",
      "ESF",
      "AD",
      "T",
      "BIO",
      "BUT",
      "AO",
      "MR",
      "MA'S",
      "MH'S",
      "OE",
      "CD",
      "UBS",
      "R1",
      "Dr",
      "R2",
      "ATROFIA DE EPR",
      "PRE OP"
    ],
    "Parte do Corpo, Órgão ou Componente Orgânico": [
      "OD",
      "OE"
    ],
    "Negação": [
      "NEGA",
      "NÃO"
    ],
    "Doença ou Síndrome": [
      "DM",
      "HAS",
      "GLAUCOMA",
      "AMAUROSE",
      "CATARATA",
      "MH'S",
      "CATARA"
    ],
    "Procedimento Terapêutico ou Preventivo": [
      "TRATAMENTO",
      "CIRURGIA"
    ],
    "Atributo Clínico": [
      "AVSC",
      "AVCC"
    ],
    "Dispositivo Médico": [
      "ÓCULOS"
    ],
    "Procedimento Diagnóstico": [
      "BIO",
      "BUT",
      "MR",
      "EXAMES",
      "ANGIOGRAFIA"
    ],
    "Conceito Qualitativo": [
      "REDUZIDO"
    ],
    "Atividade de Assistência à Saúde": [
      "CD",
      "PRESCREVO",
      "AD",
      "SOLICITO",
      "RETORNO"
    ],
    "Procedimento Laboratorial": [
      "EXAMES"
    ],
    "Paciente ou Grupo com Deficiência": [
      "PACIENTE"
    ],
    "Conceito Temporal": [
      "ANUAL",
      "HÁ 1 ANO E MEIO",
      "HÁ 5 ANOS"
    ],
    "Organização Relacionada à Saúde": [
      "UBS"
    ],
    "Grupo Profissional ou Ocupacional": [
      "R1",
      "Dr",
      "R2"
    ],
    "Resultado Laboratorial ou de Teste": [
      "150 - 200",
      "20 / 400",
      "20 / 200",
      "20 / 70"
    ],
    "Lesão ou Envenenamento": [
      "TRAUMA OCULAR"
    ]
  },
  "labels": {
    "bav": {
      "capitulo": "09"
    },
    "queixas oculares": {
      "capitulo": "21"
    },
    "trauma ocular": {
      "capitulo": "22"
    },
    "amaurose": {
      "capitulo": "09"
    },
    "catarata": {
      "capitulo": "09"
    },
    "catara": {
      "capitulo": "09"
    },
    "qp": {
      "capitulo": "09"
    },
    "dm": {
      "capitulo": "11"
    },
    "glaucoma": {
      "capitulo": "09"
    }
  }
}