{
  "prontuario_id": 894,
  "text": "Lucas, 26 anos\nTRM CERVICAL POR COLISÃO AUTO X AUTO (MAIO/2014) SÍNCOPES DE REPETIÇÃO (JUNHO/14) C/ TRAUMA CRÂNIOCERVICAL APÓS QUEDA #\nINVAGINAÇÃO BASILAR / PLATIBASIA / FUSÃO C1 - C2 # TETRAPARESIA ESPÁSTICA (MIELOPATIA CERVICAL ALTA PÓS -TRM)\nPO DESCOMPRESSÃO MICROCIRÚRGICA DE JUNÇÃO CRANIOCERVICAL VIA POSTERIOR (RESSECÇÃO SUBOCCIPITAL + ARCO POSTERIOR DE C1\nASSIMILADO AO CRANIO) PARA CORREÇÃO DE ESTENOSE CRANIOCERVICAL CONSEQUENTE À INVAGINAÇÃO BASILAR (18/12/14)\nPaciente afirma melhora importante do quadro de força motora. Sem queixas álgicas (melhora completa da dor cervical prévia). Nega alteração de controle\nesfincteriano. Nega febre, vertigem e síncope. Realizando FST 2 x / semana.\nExame Físico 01/09/15: Tetraparesia espástica, de predomínio em hemicorpo à direita ( FM: MSD = 4-, MSE = 4+, MID = 4, MIE = 4+) Hiperreflexia à direita com aumento de\nárea reflexógena, com clônus esgotável à direita e Hoffman presente à direita Babinski bilateral. Sem alteração de sensibilidade ao exame comparado, incluindo\nproprioceptiva; Marcha protopática e disbasia, hemiparética\nCD: Discuto com Doutor Vital Brazil . AIH sem rota para artodese occipito - cervical 3 níveis via posterior + tratamento cirúrgico de Chiari. A ser discutido posteriormente\nressecção de ondontoíde via transoral (em 2 tempo)\n \n \n \n ",
  "entities": {
    "Lesão ou Envenenamento": [
      "TRM",
      "-TRM",
      "TRAUMA CRÂNIOCERVICAL"
    ],
    "Abreviação": [
      "TRM",
      "-TRM",
      "PO",
      "FST",
      "FM",
      "CD",
      "AIH",
      "MSD = 4-",
      "MSE = 4+",
      "MID = 4",
      "MIE = 4+"
    ],
    "Localização ou Região Corporal": [
      "CERVICAL",
      "cervical",
      "hemicorpo à direita",
      "área reflexógena"
    ],
    "Evento": [
      "QUEDA",
      "COLISÃO AUTO X AUTO"
    ],
    "Anormalidade Congênita": [
      "PLATIBASIA",
      "INVAGINAÇÃO BASILAR"
    ],
    "Conceito Temporal": [
      "PÓS"
    ],
    "Conceito Qualitativo": [
      "melhora"
    ],
    "Negação": [
      "Sem",
      "Nega",
      "sem"
    ],
    "Sinal ou Sintoma": [
      "febre",
      "vertigem",
      "síncope",
      "disbasia",
      "hemiparética",
      "SÍNCOPES DE REPETIÇÃO",
      "FUSÃO C1 - C2",
      "queixas álgicas",
      "alteração de controle esfincteriano",
      "Tetraparesia espástica",
      "MSD = 4-",
      "MSE = 4+",
      "MID = 4",
      "MIE = 4+",
      "Hiperreflexia à direita",
      "clônus esgotável à direita",
      "Babinski bilateral",
      "alteração de sensibilidade",
      "Marcha protopática"
    ],
    "Atividade de Assistência à Saúde": [
      "FST",
      "CD",
      "Discuto",
      "AIH"
    ],
    "Procedimento Terapêutico ou Preventivo": [
      "FST",
      "DESCOMPRESSÃO MICROCIRÚRGICA DE JUNÇÃO CRANIOCERVICAL VIA POSTERIOR",
      "RESSECÇÃO SUBOCCIPITAL",
      "ARCO POSTERIOR DE C1 ASSIMILADO AO CRANIO",
      "artodese occipito - cervical",
      "tratamento cirúrgico de Chiari",
      "ressecção de ondontoíde via transoral"
    ],
    "Conceito Espacial": [
      "direita"
    ],
    "Grupo Profissional ou Ocupacional": [
      "Doutor"
    ],
    "Doença ou Síndrome": [
      "INVAGINAÇÃO BASILAR",
      "FUSÃO C1 - C2",
      "TETRAPARESIA ESPÁSTICA",
      "MIELOPATIA CERVICAL ALTA",
      "ESTENOSE CRANIOCERVICAL"
    ],
    "Conceito Quantitativo": [
      "2 x / semana"
    ],
    "Resultado Laboratorial ou de Teste": [
      "MSD = 4-",
      "MSE = 4+",
      "MID = 4",
      "MIE = 4+"
    ]
  },
  "labels": {
    "vertigem": {
      "capitulo": "08"
    },
    "disbasia": {
      "capitulo": "15"
    },
    "mse = 4+": {
      "capitulo": "08"
    },
    "alteração de controle esfincteriano": {
      "capitulo": "21"
    },
    "fusão c1 - c2": {
      "capitulo": "15"
    },
    "estenose craniocervical": {
      "capitulo": "08"
    },
    "msd = 4-": {
      "capitulo": "08"
    },
    "trm": {
      "capitulo": "22"
    },
    "síncopes de repetição": {
      "capitulo": "22"
    },
    "clônus esgotável à direita": {
      "capitulo": "08"
    },
    "trauma crâniocervical": {
      "capitulo": "22"
    },
    "platibasia": {
      "capitulo": "15"
    },
    "tetraparesia espástica": {
      "capitulo": "08"
    },
    "babinski bilateral": {
      "capitulo": "08"
    },
    "mielopatia cervical alta": {
      "capitulo": "08"
    },
    "hemiparética": {
      "capitulo": "15"
    },
    "mie = 4+": {
      "capitulo": "08"
    },
    "mid = 4": {
      "capitulo": "08"
    },
    "alteração de sensibilidade": {
      "capitulo": "21"
    },
    "hiperreflexia à direita": {
      "capitulo": "08"
    },
    "síncope": {
      "capitulo": "22"
    },
    "marcha protopática": {
      "capitulo": "15"
    },
    "invaginação basilar": {
      "capitulo": "15"
    }
  }
}