{
  "prontuario_id": 543,
  "text": "LUCAS, 66 anos\n# Multiplos CBC's (face - dorso nasal, supra labial, frontal, cervical, dorso, ombro).\n# CEC in situ malar 05/2013\n# QA's\ns: sem queixas. Usou efurix por 7 dias apenas devido a irritação.\no: Lesão tipo placa pouco deprimida de aprox 1 cm em dorso superior.\nLesões eritemato-crostosas não infiltradas em face e dorso de \nmãos (pouca quantidade).\na: ceratoses actínicas em face e dorso de mãos\n   lesão suspeita em dorso superior: CBC superficial? Bowen?\np: agendo bx de lesão em dorso e shaving + ect de lesão\nde verruga viral em sulco paranasal D\ncriocx em ceratoses actínicas\nr1 doutor Vital Brazil\n \n \n \n ",
  "entities": {
    "Processo Neoplásico": [
      "CBC's",
      "CEC in situ",
      "CBC superficial"
    ],
    "Abreviação": [
      "CBC's",
      "bx",
      "ect",
      "criocx",
      "r1",
      "CEC in situ",
      "CBC superficial",
      "sulco paranasal D"
    ],
    "Localização ou Região Corporal": [
      "face",
      "frontal",
      "cervical",
      "dorso",
      "ombro",
      "malar",
      "shaving",
      "dorso nasal",
      "supra labial",
      "dorso superior",
      "dorso de mãos",
      "sulco paranasal D"
    ],
    "Negação": [
      "sem"
    ],
    "Sinal ou Sintoma": [
      "queixas",
      "irritação",
      "lesão",
      "lesão de verruga viral"
    ],
    "Substância Farmacológica": [
      "efurix"
    ],
    "Ácido Nucleico, Nucleosídeo ou Nucleotídeo": [
      "efurix"
    ],
    "Doença ou Síndrome": [
      "Bowen",
      "ceratoses actínicas"
    ],
    "Atividade de Assistência à Saúde": [
      "agendo"
    ],
    "Procedimento Diagnóstico": [
      "bx"
    ],
    "Procedimento Terapêutico ou Preventivo": [
      "shaving",
      "ect",
      "criocx"
    ],
    "Grupo Profissional ou Ocupacional": [
      "r1",
      "doutor"
    ],
    "Conceito Temporal": [
      "7 dias"
    ],
    "Conceito Qualitativo": [
      "pouco deprimida",
      "pouca quantidade"
    ],
    "Conceito Quantitativo": [
      "1 cm"
    ],
    "Lesão ou Envenenamento": [
      "Lesões eritemato-crostosas"
    ]
  },
  "labels": {
    "cec in situ": {
      "capitulo": "02"
    },
    "lesões eritemato-crostosas": {
      "capitulo": "14"
    },
    "cbc's": {
      "capitulo": "22"
    },
    "lesão de verruga viral": {
      "capitulo": "14"
    },
    "ceratoses actínicas": {
      "capitulo": "14"
    },
    "cbc superficial": {
      "capitulo": "22"
    },
    "lesão": {
      "capitulo": "21"
    },
    "bowen": {
      "capitulo": "02"
    }
  }
}