{
  "prontuario_id": 752,
  "text": "56 ANOS\nPACIENTE COMPARECE ENCAMINHADA DEVIDO A IDENTIFICAÇÃO DE IMAGEM POLIPOIDE EM COLO UTERINO. NEGA SINTOMATOLOGIA. NEGA SINUSIORRAGIA.\nNEGA SANGRAMENTOS APOS A MENOPAUSA.\nMENOPAUSA: AOS 45 ANOS\nG 2 C 2 A 0\nNEGA USO DE TH.\nAMAMENTOU OS FILOHS AO SEIO CERCA DE 1-2 ANOS.\nAM: NEGA PATOLOGIAS.\nAF: NEGA HISTORIA FAMILIAR DE NEOPLASIA.\nNAO TRAZ EXAMES COMPLEMENTARES.\nAO EXAME:\nPA 120X80\nPESO 74,9\nCA 94\nVULVA HIPOTROFICA, SEM LESÕES. COLO EPITELIZADO, COM POLIPO ENDOCERVICAL VISUALIZADO PELO ORIFICIO EXTERNO DO COLO, COM PEDICULO PARECENDO VIR DO INTERIOR CAVIDADE UTERINA. REALIZADO RETIRADA POR TORÇÃO DO PEDICULO DO POLIPO ENDOCERVICAL.\nREVISÃO DE HEMOSTASIA.\nMATERIAL ENVIADO PARA AP\nAO TOQUE UTERO DE VOLUME NORMAL, MOVEL, REGULAR. ANEXOS NAO PALPAVEIS.\nCD: RETORNO EM 45 DIAS.\nORIENTO PACIENTE.\nDoutor Vital Brazil R3 \n \n \n \n ",
  "entities": {
    "Paciente ou Grupo com Deficiência": [
      "PACIENTE"
    ],
    "Atividade de Assistência à Saúde": [
      "ENCAMINHADA",
      "REVISÃO",
      "CD",
      "RETORNO",
      "ORIENTO"
    ],
    "Negação": [
      "NEGA",
      "NAO",
      "SEM"
    ],
    "Sinal ou Sintoma": [
      "SINTOMATOLOGIA",
      "SINUSIORRAGIA",
      "SANGRAMENTOS",
      "PATOLOGIAS",
      "LESÕES",
      "VULVA HIPOTROFICA"
    ],
    "Conceito Temporal": [
      "APOS"
    ],
    "Função Fisiológica": [
      "MENOPAUSA",
      "AMAMENTOU"
    ],
    "Função de Organismo": [
      "G"
    ],
    "Conceito Quantitativo": [
      "2",
      "0",
      "120X80",
      "94",
      "45",
      "74 , 9"
    ],
    "Procedimento Terapêutico ou Preventivo": [
      "C",
      "HEMOSTASIA",
      "RETIRADA POR TORÇÃO"
    ],
    "Abreviação": [
      "TH",
      "AM",
      "AF",
      "AP",
      "CD",
      "R3"
    ],
    "Grupo Familiar": [
      "FILOHS"
    ],
    "Processo Neoplásico": [
      "NEOPLASIA"
    ],
    "Procedimento Diagnóstico": [
      "AP",
      "AO TOQUE"
    ],
    "Parte do Corpo, Órgão ou Componente Orgânico": [
      "UTERO",
      "COLO UTERINO",
      "ORIFICIO EXTERNO DO COLO"
    ],
    "Achado": [
      "MOVEL",
      "REGULAR",
      "VOLUME NORMAL"
    ],
    "Grupo Profissional ou Ocupacional": [
      "Doutor",
      "R3"
    ],
    "Resultado Laboratorial ou de Teste": [
      "IMAGEM POLIPOIDE",
      "EXAMES COMPLEMENTARES",
      "COLO EPITELIZADO",
      "POLIPO ENDOCERVICAL",
      "PEDICULO PARECENDO VIR DO INTERIOR CAVIDADE UTERINA"
    ],
    "Grupo Etário": [
      "45 ANOS"
    ]
  },
  "labels": {
    "sangramentos": {
      "capitulo": "22"
    },
    "patologias": {
      "capitulo": "02"
    },
    "sintomatologia": {
      "capitulo": "21"
    },
    "vulva hipotrofica": {
      "capitulo": "15"
    },
    "sinusiorragia": {
      "capitulo": "22"
    },
    "neoplasia": {
      "capitulo": "02"
    },
    "lesões": {
      "capitulo": "22"
    }
  }
}