{
  "prontuario_id": 936,
  "text": "# Lucas, 34 anos, trabalha como cuidadora\n# Hernia Incisional\n# Paciente relata que há 2 anos e meio realizou Cx bariátrica e há aproximadamente 1 ano observou abaulamento na regiao da cicatriz, aumento progressivo de tamanho. Aumento de tamanho pós prandial. Relata também dor na regiao, tipo compressiva, associada a vomitos.\n- relata episodios diarios de vomito quando alimenta-se em excesso ou come muito doce.\n- nega DM, HAS, dislipidemia. \n- alergia a pen Benzatina.\n# Exame físico\nBRNF2T ss\nAbdomen flacido, indolor a palpacao profunda e superficial, RHA+, sem alteracao na percussâo. Fraqueza em parede em regiao inferior da cicatriz.\n# exames complementares:\n- exames laboratoriais ( calcio, ferro, ferritina, zinco., B12, vitamina D, glicemia, Proteinas total e fração, hemograma e ácido fólico) sem alteração;\nDiscuto caso com Doutro Vital Brazil. Solicito ECG, Raio x de torax Ap+P, solicito demais exames laboratoriais.\n \n \n \n ",
  "entities": {
    "Paciente ou Grupo com Deficiência": [
      "Paciente"
    ],
    "Sinal ou Sintoma": [
      "dor",
      "vomitos",
      "vomito",
      "indolor",
      "alteracao",
      "alteração",
      "abaulamento na regiao da cicatriz",
      "aumento progressivo de tamanho"
    ],
    "Conceito Qualitativo": [
      "excesso"
    ],
    "Conceito Quantitativo": [
      "muito"
    ],
    "Alimento": [
      "doce"
    ],
    "Negação": [
      "nega",
      "ss",
      "indolor",
      "sem"
    ],
    "Abreviação": [
      "DM",
      "HAS",
      "RHA+",
      "ECG",
      "Cx bariátrica",
      "pen Benzatina"
    ],
    "Doença ou Síndrome": [
      "DM",
      "HAS",
      "dislipidemia",
      "Hernia Incisional"
    ],
    "Localização ou Região Corporal": [
      "Abdomen",
      "parede em regiao inferior"
    ],
    "Achado": [
      "flacido",
      "RHA+"
    ],
    "Procedimento Diagnóstico": [
      "palpacao",
      "percussâo",
      "ECG",
      "Raio x de torax Ap+P"
    ],
    "Função Patológica": [
      "cicatriz"
    ],
    "Procedimento Laboratorial": [
      "calcio",
      "ferro",
      "ferritina",
      "zinco",
      "B12",
      "glicemia",
      "hemograma",
      "exames complementares",
      "exames laboratoriais",
      "vitamina D",
      "Proteinas total e fração",
      "ácido fólico"
    ],
    "Atividade de Assistência à Saúde": [
      "Discuto",
      "Solicito",
      "solicito"
    ],
    "Grupo Profissional ou Ocupacional": [
      "Doutro"
    ],
    "Conceito Temporal": [
      "há 2 anos e meio",
      "pós prandial"
    ],
    "Procedimento Terapêutico ou Preventivo": [
      "Cx bariátrica"
    ],
    "Antibiótico": [
      "pen Benzatina"
    ],
    "Substância Química Orgânica": [
      "pen Benzatina"
    ]
  },
  "labels": {
    "flacido": {
      "capitulo": "13"
    },
    "alteração": {
      "capitulo": "21"
    },
    "vomito": {
      "capitulo": "22"
    },
    "alteracao": {
      "capitulo": "21"
    },
    "cicatriz": {
      "capitulo": "15"
    },
    "vomitos": {
      "capitulo": "22"
    },
    "abaulamento na regiao da cicatriz": {
      "capitulo": "13"
    },
    "dor": {
      "capitulo": "21"
    },
    "aumento progressivo de tamanho": {
      "capitulo": "13"
    },
    "hernia incisional": {
      "capitulo": "15"
    }
  }
}