{
  "prontuario_id": 780,
  "text": "# QP: MOSCAS VOLANTES EM OD HÁ 2 MESES. REFERE BAV DE AO HÁ 7 ANOS ( REFERE DX PRÉVIO DE TOXO E ATROFIA DE NERVO ÓPTICO EM AO - SIC )\n\n# HMA: PACIENTE REFERE HIPEREMIA CONJUNTIVAL, PRURIDO E LACRIMEJAMENTO. NÃO FAZ USO DE ÓCULOS, NÃO FAZ USO DE NENHUM COLÍRIO\n\n# HMP: COMORBIDADES: HIV EM USO DE TARV ( CONTROLADA - SIC ). NEGA TRAUMAS OU CIRURGIAS OCULARES\n\n# HMF: NEGA HISTÓRICO FAMILIAR DE GLAUCOMA OU CEGUEIRA\n\n# EXAME FÍSICO:\n\n- AVsc: OD 20/200 \tOE CD 30 CM\n\n- ESQ: OD -0,75 -0,75 180 \n\t    OE -1,00 -1,50 180\n\n- TOL: AO NÃO MELHORA\n\n- BIO: AO CA CALMA E BEM FORMADA, PUPILAS FOTORREAGENTES, CÓRNEA CLARA, HIPEREMIA PERILIMBAR E BLEFARITE ANTERIOR E POSTERIOR\n\n- PIO: 14/14\n\n- MR: OD ATROFIA DE NERVO ÓPTICO, MACULA NORMAL\n\tOE ATROFIA DE NERVO ÓPTICO, CICATRIZ DE CORIO EM FEIXE PAPILA MACULAR\n\n# CONDUTA: PRESCREVO VIGADEXA COLÍRIO DE 4/4H POR 7 DIAS + DOXICILCINA VO DE 12/12H POR 10 DIAS + LUBRIFICANTE OCULAR. ORIENTO PACIENTE A DIRIGIR-SE AO HUC CASO APRESENTE QUALQUER ALTERAÇÃO AGUDA DA SAÚDE OCUALR. RETORNO ANUAL VIA UBS\n\nR1 Doutor Vital Brazil\n \n \n \n ",
  "entities": {
    "Sinal ou Sintoma": [
      "QP",
      "PRURIDO",
      "LACRIMEJAMENTO",
      "MOSCAS VOLANTES",
      "HIPEREMIA CONJUNTIVAL",
      "HIPEREMIA PERILIMBAR",
      "ALTERAÇÃO AGUDA DA SAÚDE OCUALR"
    ],
    "Abreviação": [
      "QP",
      "OD",
      "TOXO",
      "HIV",
      "TARV",
      "OE",
      "CD",
      "ESQ",
      "TOL",
      "BIO",
      "PIO",
      "MR",
      "4/4H",
      "VO",
      "12/12H",
      "UBS",
      "R1",
      "DX PRÉVIO",
      "CA CALMA"
    ],
    "Parte do Corpo, Órgão ou Componente Orgânico": [
      "OD",
      "AO",
      "OE"
    ],
    "Conceito Quantitativo": [
      "2",
      "20/200",
      "14/14",
      "4/4H",
      "7",
      "12/12H",
      "10",
      "30 CM",
      "-0 , 75 -0 , 75 180",
      "-1 , 00 -1 , 50 180"
    ],
    "Doença ou Síndrome": [
      "TOXO",
      "HIV",
      "GLAUCOMA",
      "CEGUEIRA",
      "ATROFIA DE NERVO ÓPTICO EM AO"
    ],
    "Paciente ou Grupo com Deficiência": [
      "PACIENTE"
    ],
    "Negação": [
      "NÃO",
      "NEGA"
    ],
    "Dispositivo Médico": [
      "ÓCULOS"
    ],
    "Substância Farmacológica": [
      "COLÍRIO",
      "VIGADEXA COLÍRIO",
      "LUBRIFICANTE OCULAR"
    ],
    "Vírus": [
      "HIV"
    ],
    "Conceito Qualitativo": [
      "CONTROLADA",
      "MELHORA"
    ],
    "Lesão ou Envenenamento": [
      "TRAUMAS"
    ],
    "Atributo Clínico": [
      "AVsc"
    ],
    "Procedimento Diagnóstico": [
      "CD",
      "ESQ",
      "TOL",
      "BIO",
      "PIO",
      "MR"
    ],
    "Resultado Laboratorial ou de Teste": [
      "14/14",
      "CA CALMA",
      "BEM FORMADA",
      "PUPILAS FOTORREAGENTES",
      "CÓRNEA CLARA",
      "HIPEREMIA PERILIMBAR",
      "BLEFARITE ANTERIOR E POSTERIOR",
      "ATROFIA DE NERVO ÓPTICO",
      "MACULA NORMAL",
      "CICATRIZ DE CORIO EM FEIXE PAPILA MACULAR"
    ],
    "Atividade de Assistência à Saúde": [
      "CONDUTA",
      "PRESCREVO",
      "ORIENTO",
      "RETORNO",
      "DX PRÉVIO"
    ],
    "Antibiótico": [
      "DOXICILCINA",
      "VIGADEXA COLÍRIO"
    ],
    "Substância Química Orgânica": [
      "DOXICILCINA",
      "VIGADEXA COLÍRIO"
    ],
    "Conceito Funcional": [
      "VO"
    ],
    "Conceito Temporal": [
      "ANUAL",
      "HÁ 7 ANOS"
    ],
    "Organização Relacionada à Saúde": [
      "UBS"
    ],
    "Grupo Profissional ou Ocupacional": [
      "R1",
      "Doutor"
    ],
    "Procedimento Terapêutico ou Preventivo": [
      "CIRURGIAS OCULARES"
    ],
    "Achado": [
      "HISTÓRICO FAMILIAR",
      "CÓRNEA CLARA"
    ],
    "Medicamento Clínico": [
      "LUBRIFICANTE OCULAR"
    ]
  },
  "labels": {
    "atrofia de nervo óptico em ao": {
      "capitulo": "09"
    },
    "hiperemia perilimbar": {
      "capitulo": "09"
    },
    "lacrimejamento": {
      "capitulo": "09"
    },
    "toxo": {
      "capitulo": "01"
    },
    "hiv": {
      "capitulo": "04"
    },
    "alteração aguda da saúde ocualr": {
      "capitulo": "21"
    },
    "traumas": {
      "capitulo": "22"
    },
    "cegueira": {
      "capitulo": "09"
    },
    "moscas volantes": {
      "capitulo": "09"
    },
    "prurido": {
      "capitulo": "09"
    },
    "glaucoma": {
      "capitulo": "09"
    },
    "hiperemia conjuntival": {
      "capitulo": "09"
    }
  }
}