{
  "prontuario_id": 234,
  "text": "ACOMPANHAMENTO COM Doutor Vital Brazil POR TRATAMENTO CONSERVADOR  DE HEMANGIOBLASTOMA CEREBELAR ESQ\n\nPO DESCOMPRESSÃO CERVICAL + ARTRODESE CERVICAL PARA TTO. DE MALFORMAÇÃO DE CHIARI E SIRINGOMIELIA C4-C7.\nPACIENTE MELHOROU DE DEFICITS PREVIOS, EMBORA PERISTINDO COM ALGUMAS SEQUELAS NEUROLOGICAS: HIPOESTESIA EM DIMIDIO DIR +\nPARESIA EM MSD PRINCIPALMENTE.\nSEM NOVAS QUEIXAS E SEM PIROA CLINICA\n\nRETORNA HOJE COM RM DE CRANIO E COLUNAS CERVICAL E LOMBAR, SEM PIORA DA SIRINGOMIELIA E SEM COMPLICAÇÕES DA FIXAÇÃO /\nDESCOMPRESSÃO CERVICAL.\nSIRINGOMIELIA MANTÉM-SE NOS MESMOS NIVEIS E DIMENSOES. SEM NOVAS ALTERAÇÕES.\n\nALIVIO DAS DORES IMPORTANTE COM AMITRIPTILINA.\n\nP # SOLICITO NOVA RM DE CRANIO \nRETORNO COM Doutor Vital Brazil COM EXAME\n \n \n \n ",
  "entities": {
    "Atividade de Assistência à Saúde": [
      "ACOMPANHAMENTO",
      "SOLICITO",
      "RETORNO"
    ],
    "Grupo Profissional ou Ocupacional": [
      "Doutor"
    ],
    "Conceito Temporal": [
      "PO"
    ],
    "Abreviação": [
      "PO",
      "TTO",
      "HEMANGIOBLASTOMA CEREBELAR ESQ",
      "DIMIDIO DIR",
      "PARESIA EM MSD",
      "RM DE CRANIO E COLUNAS CERVICAL E LOMBAR",
      "RM DE CRANIO"
    ],
    "Procedimento Terapêutico ou Preventivo": [
      "TTO",
      "TRATAMENTO CONSERVADOR",
      "DESCOMPRESSÃO CERVICAL",
      "ARTRODESE CERVICAL",
      "FIXAÇÃO / DESCOMPRESSÃO CERVICAL"
    ],
    "Paciente ou Grupo com Deficiência": [
      "PACIENTE"
    ],
    "Negação": [
      "SEM"
    ],
    "Sinal ou Sintoma": [
      "QUEIXAS",
      "COMPLICAÇÕES",
      "ALTERAÇÕES",
      "SEQUELAS NEUROLOGICAS",
      "PARESIA EM MSD",
      "PIROA CLINICA",
      "PIORA DA SIRINGOMIELIA"
    ],
    "Doença ou Síndrome": [
      "SIRINGOMIELIA",
      "HEMANGIOBLASTOMA CEREBELAR ESQ",
      "MALFORMAÇÃO DE CHIARI",
      "SIRINGOMIELIA C4-C7"
    ],
    "Substância Química Orgânica": [
      "AMITRIPTILINA"
    ],
    "Substância Farmacológica": [
      "AMITRIPTILINA"
    ],
    "Procedimento Diagnóstico": [
      "EXAME",
      "RM DE CRANIO E COLUNAS CERVICAL E LOMBAR",
      "RM DE CRANIO"
    ],
    "Achado": [
      "MELHOROU DE DEFICITS PREVIOS",
      "ALIVIO DAS DORES"
    ],
    "Parte do Corpo, Órgão ou Componente Orgânico": [
      "DIMIDIO DIR"
    ]
  },
  "labels": {
    "alterações": {
      "capitulo": "08"
    },
    "hemangioblastoma cerebelar esq": {
      "capitulo": "02"
    },
    "siringomielia c4-c7": {
      "capitulo": "08"
    },
    "siringomielia": {
      "capitulo": "08"
    },
    "paresia em msd": {
      "capitulo": "08"
    },
    "sequelas neurologicas": {
      "capitulo": "08"
    },
    "piora da siringomielia": {
      "capitulo": "08"
    },
    "complicações": {
      "capitulo": "22"
    },
    "malformação de chiari": {
      "capitulo": "02"
    }
  }
}