{
  "prontuario_id": 247,
  "text": "1 CONSULTA\n\nPACIENTE ENCAMINHADA DA UBS DEVIDO A USG DE ABDOME ( 17/0614): DEMONSTRANDO FIGADO AUMENTADO COM TUMORAÇÕES NODULARES- FIGADO METASTAATICO??\nCOLECISTOPATIA CALCULOSA CRONICA. \nPACIENTE REFERE QUE INICIOU HA 6 MESES INICIOU COM DORES ESPORADICAS EM REGIAO EPIGASTRICA, CONTINUA, SEM IRRADIAÇÃO, COM MELHORA ESPOTANEA. HA 3 SEMANAS INICIOU COM NAUSEAS E VOMITOS ASOCIADOS. NEGA EMAGRECIMENTO. NEGA ICTERICIA. NEGA FEBRE. NEGA DISFAGIA. REFERE NUNCA TER APRESENTADO COLICA BILIAR. NEGA HISTORIA DE CA FAMLIAR. DIURESE E FEZES SEM ALTERAÇÕES.\nNEGA INGESTAO DE BEBIDA ALCOOLICA, NAO FUMA.\nNAO TOMA MEDICAÇÕES DE USO CONTINUO.\n\nEXAME FISICO:\nBEG, CORADA, HIDRATADA, ANICTERICA, AFEBRIL\nDADOS VITAIS ESTAVEIS\nC/P: AUSENCIA DE LINFONODO MEGALIAS\nBCRNFSS\nMV+ SEM RA\nABDOME FLACIDO, RHA+, DOR A PALPAÇÃO EM HD, MASSA PALPAVEL DE APROXIMADAMENTE 5CM, FIXA, ENDURECISA EM HD, AUSENCIA DE IRRITAÇÃO PERITNEAL\nMAMAS: PRESENÇA DE NODULO DE 1 CM EM MAMA ESQUERDA AS 15HS, FIBROELASTICO, MOVEL, INDOLOR\nMMIS:SP\n\nEXAMES LAB: \nHB 11,6\nVG 33,8%\nRESTANTE OK\n\nCD #\nSOLICITO TAC DE ABDOME\nSOLICITO RX DE TORAX\nMARCADORES NEOPLASICOS\nECG E EXAMES PRE OP.\nPROVAS DE HEPATITE\nRETORNO COM EXAMES VIA ROTA.\n \n \n \n ",
  "entities": {
    "Atividade de Assistência à Saúde": [
      "CONSULTA",
      "ENCAMINHADA",
      "CD",
      "SOLICITO",
      "RETORNO",
      "ROTA"
    ],
    "Paciente ou Grupo com Deficiência": [
      "PACIENTE"
    ],
    "Organização Relacionada à Saúde": [
      "UBS"
    ],
    "Abreviação": [
      "UBS",
      "BEG",
      "C/P",
      "BCRNFSS",
      "MV+",
      "RA",
      "RHA+",
      "HD",
      "15HS",
      "MMIS",
      "SP",
      "CD",
      "ECG",
      "USG DE ABDOME",
      "EXAMES LAB",
      "HB 11 , 6",
      "VG 33 , 8%",
      "TAC DE ABDOME",
      "EXAMES PRE OP"
    ],
    "Localização ou Região Corporal": [
      "EPIGASTRICA",
      "HD"
    ],
    "Negação": [
      "SEM",
      "NEGA",
      "NUNCA",
      "NAO",
      "ANICTERICA",
      "AFEBRIL",
      "AUSENCIA",
      "INDOLOR"
    ],
    "Sinal ou Sintoma": [
      "IRRADIAÇÃO",
      "NAUSEAS",
      "VOMITOS",
      "EMAGRECIMENTO",
      "ICTERICIA",
      "FEBRE",
      "DISFAGIA",
      "ALTERAÇÕES",
      "ANICTERICA",
      "AFEBRIL",
      "RA",
      "ENDURECISA",
      "INDOLOR",
      "DORES ESPORADICAS",
      "COLICA BILIAR",
      "LINFONODO MEGALIAS",
      "IRRITAÇÃO PERITNEAL"
    ],
    "Grupo Familiar": [
      "FAMLIAR"
    ],
    "Substância Corporal": [
      "FEZES"
    ],
    "Achado": [
      "FUMA",
      "BEG",
      "CORADA",
      "HIDRATADA",
      "BCRNFSS",
      "MV+",
      "RHA+",
      "FIXA",
      "FIBROELASTICO",
      "MOVEL",
      "SP",
      "MELHORA ESPOTANEA",
      "DADOS VITAIS ESTAVEIS",
      "ABDOME FLACIDO"
    ],
    "Comportamento Individual": [
      "FUMA"
    ],
    "Procedimento Diagnóstico": [
      "PALPAÇÃO",
      "ECG",
      "USG DE ABDOME",
      "TAC DE ABDOME",
      "RX DE TORAX",
      "EXAMES PRE OP"
    ],
    "Conceito Quantitativo": [
      "5CM"
    ],
    "Parte do Corpo, Órgão ou Componente Orgânico": [
      "MMIS"
    ],
    "Resultado Laboratorial ou de Teste": [
      "EXAMES",
      "FIGADO AUMENTADO COM TUMORAÇÕES NODULARES- FIGADO METASTAATICO",
      "HB 11 , 6",
      "VG 33 , 8%"
    ],
    "Doença ou Síndrome": [
      "COLECISTOPATIA CALCULOSA CRONICA"
    ],
    "Conceito Temporal": [
      "HA 6 MESES",
      "HA 3 SEMANAS"
    ],
    "Substância": [
      "BEBIDA ALCOOLICA"
    ],
    "Procedimento Terapêutico ou Preventivo": [
      "MEDICAÇÕES DE USO CONTINUO"
    ],
    "Procedimento Laboratorial": [
      "EXAMES LAB",
      "MARCADORES NEOPLASICOS",
      "PROVAS DE HEPATITE"
    ],
    "Substância Biologicamente Ativa": [
      "MARCADORES NEOPLASICOS"
    ]
  },
  "labels": {
    "alterações": {
      "capitulo": "21"
    },
    "fixa": {
      "capitulo": "21"
    },
    "colecistopatia calculosa cronica": {
      "capitulo": "13"
    },
    "irradiação": {
      "capitulo": "21"
    },
    "nauseas": {
      "capitulo": "21"
    },
    "endurecisa": {
      "capitulo": "13"
    },
    "irritação peritneal": {
      "capitulo": "21"
    },
    "dores esporadicas": {
      "capitulo": "21"
    },
    "vomitos": {
      "capitulo": "21"
    },
    "linfonodo megalias": {
      "capitulo": "21"
    },
    "abdome flacido": {
      "capitulo": "13"
    }
  }
}