{
  "prontuario_id": 471,
  "text": "Lucas , 70 ANOS\n\nS: ACOMPANHA NO AMBULATORIO POR PROLAPSO GENITAL DE SEGUNDO GRAU , COM RETENÇAÕ URINARIA NEGA INCONTINENCIA, TROUXE PRE OPERATORIOS E AVALIACAO LIBERADA PELO CARDIOLOGISTA\nRX TORAX: 19/04/13 ECTASIA DIFUSA DA AORTA CALCIFICAÇOES ATEROMATOSAS NA AORTA ESPONDILOSE , HEMG 07/05/13 : HB 13,9 HT 42,8 LEUCOCITOS 7810 PLA 272000 KPTT 24,7 TAP 11,4 RNI 1,01 CR 0,7  GLICOSE 178\nO: UREIA 43 TGP 27 TGO 18 PU NORMAL\nECG 01/11/13: FC 69 SINUSAL\nUSTV: UETRO RVF HETEROGENIO DOIS NNODULOS INTRAMURAIS 1,4X1,7X1,8CM E OUTRO DE 0,8X0,4X0,6 CM VOL 33 CM 3 ENDOMETRIO 2,8 MM OVARIOS NORMAIS\n\nEXAME FISICO: PROLAPSO UTERO GENITAL DE SEGUNDO GRAU SEM PERDA URINARIA A MANOBRA DE VALSALVA\n\nP: LIBERO AIH E SOLICITO NOVOS EXAMES LABORATORIAIS E CARTA PRO ANESTESISTA\nRETORNO EM 04/04/14\nR1  Doutor Vital Brazil ",
  "entities": {
    "Atividade de Assistência à Saúde": [
      "ACOMPANHA",
      "LIBERO",
      "AIH",
      "SOLICITO",
      "RETORNO",
      "AVALIACAO LIBERADA"
    ],
    "Organização Relacionada à Saúde": [
      "AMBULATORIO"
    ],
    "Negação": [
      "NEGA",
      "SEM"
    ],
    "Grupo Profissional ou Ocupacional": [
      "CARDIOLOGISTA",
      "ANESTESISTA",
      "R1",
      "Doutor"
    ],
    "Resultado Laboratorial ou de Teste": [
      "ESPONDILOSE",
      "ECTASIA DIFUSA DA AORTA",
      "CALCIFICAÇOES ATEROMATOSAS NA AORTA",
      "HB 13 , 9",
      "HT 42 , 8",
      "LEUCOCITOS 7810",
      "PLA 272000",
      "KPTT 24 , 7",
      "TAP 11 , 4",
      "RNI 1 , 01",
      "CR 0 , 7",
      "GLICOSE 178",
      "UREIA 43",
      "TGP 27",
      "TGO 18",
      "PU NORMAL",
      "UETRO RVF HETEROGENIO",
      "DOIS NNODULOS INTRAMURAIS",
      "1 , 4X1 , 7X1 , 8CM",
      "0 , 8X0 , 4X0 , 6 CM",
      "VOL 33 CM 3",
      "ENDOMETRIO 2 , 8 MM",
      "OVARIOS NORMAIS"
    ],
    "Abreviação": [
      "HEMG",
      "ECG",
      "FC",
      "USTV",
      "AIH",
      "R1",
      "RX TORAX",
      "HB 13 , 9",
      "HT 42 , 8",
      "PLA 272000",
      "KPTT 24 , 7",
      "TAP 11 , 4",
      "RNI 1 , 01",
      "CR 0 , 7",
      "TGP 27",
      "TGO 18",
      "PU NORMAL",
      "UETRO RVF HETEROGENIO",
      "VOL 33 CM 3"
    ],
    "Procedimento Laboratorial": [
      "HEMG",
      "EXAMES LABORATORIAIS"
    ],
    "Procedimento Diagnóstico": [
      "ECG",
      "USTV",
      "PRE OPERATORIOS",
      "RX TORAX",
      "MANOBRA DE VALSALVA"
    ],
    "Atributo Clínico": [
      "FC"
    ],
    "Conceito Quantitativo": [
      "69",
      "1 , 4X1 , 7X1 , 8CM",
      "0 , 8X0 , 4X0 , 6 CM"
    ],
    "Conceito Qualitativo": [
      "SINUSAL"
    ],
    "Doença ou Síndrome": [
      "PROLAPSO GENITAL DE SEGUNDO GRAU",
      "RETENÇAÕ URINARIA",
      "PROLAPSO UTERO GENITAL DE SEGUNDO GRAU"
    ],
    "Sinal ou Sintoma": [
      "RETENÇAÕ URINARIA",
      "PERDA URINARIA"
    ],
    "Procedimento Terapêutico ou Preventivo": [
      "PRE OPERATORIOS"
    ]
  },
  "labels": {
    "retenção urinária": {
      "capitulo": "16"
    },
    "prolapso utero genital de segundo grau": {
      "capitulo": "16"
    },
    "prolapso genital de segundo grau": {
      "capitulo": "16"
    }
  }
}