{
  "prontuario_id": 139,
  "text": "PCTE RETORNA APOS EXAME DE USG \n\nAPRESENTA ABAULAMENTO EM TORAX A DIREITA \nSEM VAZAMENTO DE SECREÇÕES OU SINIAS FLOGISTICOS\nNEGA COMORBIDADES\nAPRESENTOU TADF A DIREITA POR DERRAME PLEURAL PARAPNEUMONICO HÁ 3 ANOS\nSEM OUTRAS CIRURGIAS\n\nAO EF: ABAULAMENTO DE 3X3 CMS EM FACE ANTERIOR DE TORAX A DIREITA, NÃO TEM RELAÇÃO COM CICATRIZ CIRURGICA PREVIA, SEM SINAIS\nFLOGISTICOS, SEM SECREÇÕES\n\nUSG 22/02/2016:\n- Nódulo sólido no tecido celular subcutâneo do hemitórax direito de provável origem lipomatosa\nNódulo sólido bem definido discretamente hiperecogênico com ecotextura semelhante a gordura, sem\nfluxo ao exame com Doppler colorido, localizado no tecido celular subcutâneo do hemitórax direito,\ndistando 0,3 cm da pele e medindo aproximadamente 3,4 x 0,6 x 3,0 cm (L x AP x T) (vol 3,7 cm³).\n- Ausência de massas ou coleções organizadas. \n\nEXPLICO CASO PARA PCTE QUE NAO REFERE DESEJO DE EXERESE DA LESAO\nORIENTO CUIDADOS E SINAIS DE ALERTA\nNAO DESEJA RETORNO PARA REAVALIAÇÃO\nALTA AMBULATORIAL\n\nR2 Doutor Vital Brazil\n \n \n \n ",
  "entities": {
    "Abreviação": [
      "PCTE",
      "USG",
      "EF",
      "R2",
      "TADF A DIREITA",
      "L x AP x T",
      "vol 3 , 7 cm³"
    ],
    "Paciente ou Grupo com Deficiência": [
      "PCTE"
    ],
    "Atividade de Assistência à Saúde": [
      "RETORNA",
      "EXPLICO",
      "RETORNO",
      "REAVALIAÇÃO",
      "ORIENTO CUIDADOS",
      "ALTA AMBULATORIAL"
    ],
    "Procedimento Diagnóstico": [
      "USG"
    ],
    "Sinal ou Sintoma": [
      "ABAULAMENTO",
      "VAZAMENTO DE SECREÇÕES",
      "SINIAS FLOGISTICOS",
      "SINAIS FLOGISTICOS",
      "SINAIS DE ALERTA"
    ],
    "Negação": [
      "SEM",
      "NEGA",
      "NÃO",
      "sem",
      "Ausência",
      "NAO"
    ],
    "Procedimento Terapêutico ou Preventivo": [
      "CIRURGIAS",
      "CIRURGICA",
      "TADF A DIREITA",
      "EXERESE DA LESAO"
    ],
    "Conceito Qualitativo": [
      "RELAÇÃO"
    ],
    "Função Patológica": [
      "CICATRIZ"
    ],
    "Substância Corporal": [
      "SECREÇÕES"
    ],
    "Grupo Profissional ou Ocupacional": [
      "R2",
      "Doutor"
    ],
    "Parte do Corpo, Órgão ou Componente Orgânico": [
      "TORAX A DIREITA"
    ],
    "Doença ou Síndrome": [
      "DERRAME PLEURAL PARAPNEUMONICO"
    ],
    "Conceito Temporal": [
      "HÁ 3 ANOS"
    ],
    "Conceito Quantitativo": [
      "3X3 CMS",
      "L x AP x T"
    ],
    "Resultado Laboratorial ou de Teste": [
      "Nódulo sólido no tecido celular subcutâneo do hemitórax direito",
      "origem lipomatosa",
      "Nódulo sólido bem definido discretamente",
      "hiperecogênico",
      "com ecotextura semelhante a gordura",
      "fluxo ao exame com Doppler colorido",
      "localizado no tecido celular subcutâneo do hemitórax direito",
      "distando 0 , 3 cm da pele",
      "vol 3 , 7 cm³",
      "massas ou coleções organizadas"
    ],
    "Ideia ou Conceito": [
      "SINAIS DE ALERTA"
    ]
  },
  "labels": {
    "abaulamento": {
      "capitulo": "12"
    },
    "derrame pleural parapneumonico": {
      "capitulo": "12"
    },
    "cicatriz": {
      "capitulo": "14"
    }
  }
}