{
  "prontuario_id": 352,
  "text": "Às 17:52hs: Paciente de alta da UTI-3 para ALA-A leito 5, acompanhado dos familiares e da Enfermagem. Às 17h: Paciente admitida do CC pos-craniotomia, lucida, orientada, comunicativa, com curativo cefalico tipo capacete seco e limpo externamente, eupneica com suporte de nevoa umida continua, AVP em MSD com soroterapia em curso, PNI estavel, mobilidade preservada, pupilas isocoricas, liberado dieta VO e SSVV estaveis. Segue sob cuidados. À 01:43: Paciente POI de cx de mse, lucido, verbalizando, eupneico, afebril, mantendo boa perfusão distal, permanece com efeito anestesico. Mantem tala mais enfaixamento em mse. Às 16h: Realizou RX, SNE bem localizada, libero Medicamento e Dieta. Às 10H30MIN: ADMINISTRADO MIDAZOLAN E ENCAMINHADO AO CENTRO CIRÚRGICO ACOMPANHADO PELA ENFERMAGEM. Às 18h: Consciente, comunicativa, eupneica, deambulando sem auxilio, aceitando dieta oferecida, acesso venoso periferico em MSD sem sinais flogisticos e salinizado, fistula em MMSS, abdomen globoso e flacido, indolor a palpação, refere eliminações presentes, nega queixas algicas, segue sob cuidados. Em 13/06/11, 21:30 HRS: PACIENTE SEGUE EM SALA DE POLI VÍTIMA DE FAF EM CRANIO, MANTENDO MONITORIZAÇÃO CARDÍACA + OXIMETRIA DE PULSO + PNI, CONSCIENTE, LÚCIDO, ORIENTADO, GLASGOW 15, REFERINDO CEFALÉIA. APRESENTA HEMATOMA EM REGIÃO PERIORBITAL E, OE EM REGIAO AURICULAR E, OS EM PALPEBRA E, PUPILA D MÉDIA FOTORREAGENTE, PUPILA E MIDRIÁTICA, BCRNF, RESPIRAÇÃO ESPONTANEA, EUPNEICO EM AR AMBIENTE, MV +, ABDOME SP, ELIMINAÇÕES ESPONTANEAS, AVP EM MSD. ENCAMINHADO PEDIDO DE UTI. REPASSO PEDIDOS DE CONSULTA (OTORRINO, OFTALMO, FACE). SEGUE AOS CUIDADOS DA ENFERMAGEM.",
  "entities": {
    "Paciente ou Grupo com Deficiência": [
      "Paciente",
      "PACIENTE",
      "VÍTIMA"
    ],
    "Atividade de Assistência à Saúde": [
      "alta",
      "cuidados",
      "libero",
      "CONSULTA",
      "CUIDADOS DA ENFERMAGEM"
    ],
    "Abreviação": [
      "UTI-3",
      "CC",
      "AVP",
      "MSD",
      "POI",
      "mse",
      "RX",
      "PNI",
      "OE",
      "OS",
      "BCRNF",
      "UTI",
      "OTORRINO",
      "OFTALMO",
      "PNI estavel",
      "SSVV estaveis",
      "cx de mse",
      "SNE bem localizada",
      "fistula em MMSS",
      "SALA DE POLI",
      "REGIAO AURICULAR E",
      "MV +",
      "ABDOME SP"
    ],
    "Organização Relacionada à Saúde": [
      "UTI-3",
      "Enfermagem",
      "CC",
      "ENFERMAGEM",
      "UTI",
      "OTORRINO",
      "OFTALMO",
      "CENTRO CIRÚRGICO",
      "SALA DE POLI"
    ],
    "Objeto Manufaturado": [
      "leito"
    ],
    "Conceito Quantitativo": [
      "5"
    ],
    "Grupo Familiar": [
      "familiares"
    ],
    "Grupo Profissional ou Ocupacional": [
      "Enfermagem",
      "ENFERMAGEM"
    ],
    "Conceito Temporal": [
      "pos-craniotomia",
      "POI"
    ],
    "Procedimento Terapêutico ou Preventivo": [
      "pos-craniotomia",
      "AVP",
      "tala",
      "enfaixamento",
      "Medicamento",
      "Dieta",
      "salinizado",
      "curativo cefalico tipo capacete",
      "suporte de nevoa umida continua",
      "soroterapia em curso",
      "cx de mse",
      "efeito anestesico",
      "acesso venoso periferico",
      "fistula em MMSS"
    ],
    "Achado": [
      "lucida",
      "orientada",
      "comunicativa",
      "seco",
      "limpo",
      "eupneica",
      "lucido",
      "verbalizando",
      "eupneico",
      "afebril",
      "Consciente",
      "salinizado",
      "flacido",
      "CONSCIENTE",
      "LÚCIDO",
      "ORIENTADO",
      "BCRNF",
      "PNI estavel",
      "mobilidade preservada",
      "pupilas isocoricas",
      "SSVV estaveis",
      "boa perfusão distal",
      "SNE bem localizada",
      "deambulando sem auxilio",
      "aceitando dieta",
      "eliminações presentes",
      "GLASGOW 15",
      "RESPIRAÇÃO ESPONTANEA",
      "EUPNEICO EM AR AMBIENTE",
      "MV +",
      "ABDOME SP",
      "ELIMINAÇÕES ESPONTANEAS"
    ],
    "Dispositivo Médico": [
      "AVP",
      "tala",
      "enfaixamento",
      "curativo cefalico tipo capacete",
      "acesso venoso periferico"
    ],
    "Localização ou Região Corporal": [
      "MSD",
      "mse",
      "abdomen",
      "REGIAO AURICULAR E"
    ],
    "Negação": [
      "afebril",
      "indolor"
    ],
    "Procedimento Diagnóstico": [
      "RX",
      "palpação",
      "PNI",
      "MONITORIZAÇÃO CARDÍACA",
      "OXIMETRIA DE PULSO"
    ],
    "Alimento": [
      "Dieta"
    ],
    "Substância Farmacológica": [
      "MIDAZOLAN"
    ],
    "Sinal ou Sintoma": [
      "globoso",
      "CEFALÉIA",
      "MIDRIÁTICA",
      "sinais flogisticos",
      "queixas algicas"
    ],
    "Parte do Corpo, Órgão ou Componente Orgânico": [
      "CRANIO"
    ],
    "Função Fisiológica": [
      "eliminações presentes"
    ],
    "Objeto Físico": [
      "ELIMINAÇÕES ESPONTANEAS"
    ]
  },
  "labels": {}
}