{
  "prontuario_id": 985,
  "text": "Às 7:58Hrs: Cliente em glasgow 9/10, pupilas iso / foto +, traqueostomizado, VM nos parametros PSV (12), peep 5 cmH2O, FR 14, FiO2 35%, face corada, mucosa oral hidratada, boa perfuão periferica, no leito com cabeceira elevada á 45°. Mantem com monitorização de multiparametros, ECG, PNI, SpO2, SNE aberta com dietoterapia em curso BI 60 ml/hr, acesso venoso periferico em JED com srt em curso gravitacional, DVE aberta com debito seroso ++, ctvo região craniana limpo e seco. Apresenta ausculta cardiaca ritmica e normofonetica, ausculta pulmonar MV + com roncos esparsos, abdomem plano e flacido com RHA +, UP região craniana occipital estagio I/II. Faz uso de SVD aberta com debito diuretico presente ++ de coloração amarelo claro, eliminação fecal ausente. segue cuidados. Às 14:30: PROVENIENTE DO HD, POI OTOPLASTIA, SONOLENTA, VERBALIZA, AFEBRIL, EUPNEICA EM AR AMBIENTE, NORMOCORADA, SEM QUEIXAS, COM ACESSO VENOSO PERIFERICO EM MSE SALINIZADO, SEM SINAIS FLOGISTICOS, LIBERADO DIETA APÓS AS 16:00 HRS, CAPACETE DE CREPE + CURATIVO EXTERNAMENTE LIMPO E SECO. Às 16h: Consciente, comunicativa, eupneica, em ar ambiente, normotensa, hipocorada, aceitando dieta trazida pelos familiares, acesso venoso central em subclavia E com curativo transparente, sitio de inserção sem sinais flogisticos, com soroterapia em curso, abdomen globoso e flacido, indolor a palpação, curativo em regiao lombar de aspecto limpo e seco externamente, deambulando com auxilio, nega queixas algicas, refere diurese presente, realizada medidas de conforto, segue sob cuidados. Mantem precauções de contato.   ",
  "entities": {
    "Paciente ou Grupo com Deficiência": [
      "Cliente"
    ],
    "Parte do Corpo, Órgão ou Componente Orgânico": [
      "pupilas",
      "JED",
      "subclavia E"
    ],
    "Achado": [
      "traqueostomizado",
      "limpo",
      "seco",
      "plano",
      "flacido",
      "VERBALIZA",
      "AFEBRIL",
      "NORMOCORADA",
      "SALINIZADO",
      "LIMPO",
      "SECO",
      "Consciente",
      "comunicativa",
      "eupneica",
      "normotensa",
      "face corada",
      "mucosa oral hidratada",
      "boa perfuão periferica",
      "SNE aberta",
      "debito seroso",
      "MV +",
      "RHA +",
      "SVD aberta",
      "debito diuretico presente",
      "coloração amarelo claro",
      "eliminação fecal",
      "EUPNEICA EM AR AMBIENTE",
      "aceitando dieta",
      "deambulando com auxilio",
      "diurese presente"
    ],
    "Procedimento Terapêutico ou Preventivo": [
      "traqueostomizado",
      "VM",
      "PSV",
      "peep",
      "FiO2",
      "ctvo",
      "OTOPLASTIA",
      "SALINIZADO",
      "CURATIVO",
      "soroterapia",
      "curativo",
      "cabeceira elevada á 45°",
      "SNE aberta",
      "com dietoterapia",
      "acesso venoso periferico",
      "srt em curso gravitacional",
      "DVE aberta",
      "SVD aberta",
      "ACESSO VENOSO PERIFERICO",
      "CAPACETE DE CREPE",
      "acesso venoso central",
      "curativo transparente",
      "medidas de conforto",
      "precauções de contato"
    ],
    "Abreviação": [
      "VM",
      "PSV",
      "peep",
      "FR",
      "FiO2",
      "ECG",
      "PNI",
      "SpO2",
      "BI",
      "JED",
      "ctvo",
      "UP",
      "HD",
      "POI",
      "MSE",
      "SNE aberta",
      "com dietoterapia",
      "srt em curso gravitacional",
      "DVE aberta",
      "MV +",
      "RHA +",
      "SVD aberta",
      "subclavia E"
    ],
    "Conceito Quantitativo": [
      "12",
      "14",
      "35%",
      "5 cmH2O",
      "60 ml/hr"
    ],
    "Procedimento Diagnóstico": [
      "ECG",
      "PNI",
      "SpO2",
      "palpação",
      "monitorização de multiparametros",
      "ausculta cardiaca",
      "ausculta pulmonar"
    ],
    "Dispositivo de Administração de Medicamento": [
      "BI"
    ],
    "Dispositivo Médico": [
      "ctvo",
      "CURATIVO",
      "curativo",
      "SNE aberta",
      "acesso venoso periferico",
      "SVD aberta",
      "ACESSO VENOSO PERIFERICO",
      "CAPACETE DE CREPE",
      "acesso venoso central",
      "curativo transparente"
    ],
    "Localização ou Região Corporal": [
      "abdomem",
      "MSE",
      "abdomen",
      "região craniana",
      "região craniana occipital",
      "regiao lombar"
    ],
    "Doença ou Síndrome": [
      "UP"
    ],
    "Negação": [
      "ausente",
      "AFEBRIL",
      "SEM",
      "sem",
      "indolor",
      "nega"
    ],
    "Atividade de Assistência à Saúde": [
      "cuidados"
    ],
    "Organização Relacionada à Saúde": [
      "HD"
    ],
    "Conceito Temporal": [
      "POI"
    ],
    "Sinal ou Sintoma": [
      "SONOLENTA",
      "QUEIXAS",
      "hipocorada",
      "glasgow 9/10",
      "debito seroso",
      "roncos esparsos",
      "SINAIS FLOGISTICOS",
      "sinais flogisticos",
      "queixas algicas"
    ],
    "Alimento": [
      "DIETA"
    ],
    "Conceito Espacial": [
      "EXTERNAMENTE",
      "externamente"
    ],
    "Grupo Familiar": [
      "familiares"
    ],
    "Função Fisiológica": [
      "debito diuretico presente",
      "eliminação fecal",
      "diurese presente"
    ]
  },
  "labels": {}
}