{
  "prontuario_id": 299,
  "text": "75 anos, natural de ibitinga-SP, residente em curitiba, trabalhou na roça, como tecelã e agora trabalha em casa, casada.\n\nQP: veio para acompanhamento.\n\nHMA: paciente refere DM há 8 anos, toma metformina 850 mg 2x por dia. Descobriu ao acaso durante um exame de sangue. Paciente tem hipertireoidismo há mais de 5 anos descoberto em exame. Toma tapazol 10mg 2 x/dia. Paciente refere cansaço nos MMII final da tarde e nega edema. Refere dor no braço E, há muitos anos que começou com piora há 2 anos e melhora com fisioterapia e paracetamol.\n \nMãe faleceu de CA no fígado e pai faleceu de pneumonia. Tios tiveram CA de estômago ou fígado.\nHAS há 20 anos aproximadamente controlada com medicamentos.\nfez 3 cx de glaucoma e catarata, a última há 5 anos e faz acompanhamento com oftalmologista.\nfez apendicectomia com 14 anos.\npcte refere arritmia e distúrbio de coagulação acompanhado com cardiologista.\n\nG 8 P 8 C 0 A 0 . menopausa com 45 anos, nega metrorragia. nega reposição hormonal.\n\ndigoxina 0,25mg.\nhidroclorotiazida 25mg.\nespironolactona 25mg.\nomeprazol 20mg.\ncarvedilol 25mg.\nsinvastatina 20mg 2cp a noite.\njanuvia 100mg 1cp no café.\nvalsartana 320mg.\nmarevan 5mg.\nmetformina 850mg.\ntapazol 10mg.\n\nexames:\ncreatinina 1,2.\nGJ 113.\nCPK 90.\ncalcio total: 8,9.\nTG 302.\nHDL 24.\ncolesterol total 167.\nLDL 83.\nTSH 4,07.\nT4 0,68.\nvit D 36,1.\nHbA1C 7,30%.\nGlicose pós-prandial 119.\n ",
  "entities": {
    "Abreviação": [
      "QP",
      "HMA",
      "DM",
      "MMII",
      "HAS",
      "pcte",
      "C",
      "braço E",
      "CA no fígado",
      "GJ 113",
      "TG 302",
      "vit D 36 , 1",
      "HbA1C 7 , 30%"
    ],
    "Achado": [
      "QP",
      "HMA",
      "melhora",
      "faleceu",
      "menopausa"
    ],
    "Paciente ou Grupo com Deficiência": [
      "paciente",
      "Paciente",
      "pcte"
    ],
    "Doença ou Síndrome": [
      "DM",
      "hipertireoidismo",
      "pneumonia",
      "HAS",
      "glaucoma",
      "catarata",
      "arritmia",
      "distúrbio de coagulação"
    ],
    "Substância Química Orgânica": [
      "metformina",
      "tapazol",
      "paracetamol",
      "digoxina",
      "hidroclorotiazida",
      "espironolactona",
      "omeprazol",
      "carvedilol",
      "sinvastatina",
      "valsartana",
      "marevan"
    ],
    "Substância Farmacológica": [
      "metformina",
      "tapazol",
      "paracetamol",
      "digoxina",
      "hidroclorotiazida",
      "espironolactona",
      "omeprazol",
      "carvedilol",
      "sinvastatina",
      "januvia",
      "valsartana",
      "marevan"
    ],
    "Procedimento Diagnóstico": [
      "exame",
      "exame de sangue"
    ],
    "Conceito Quantitativo": [
      "10mg",
      "8",
      "0",
      "25mg",
      "20mg",
      "100mg",
      "320mg",
      "5mg",
      "850mg",
      "850 mg",
      "2 x/dia",
      "0 , 25mg"
    ],
    "Sinal ou Sintoma": [
      "cansaço",
      "edema",
      "dor",
      "metrorragia"
    ],
    "Parte do Corpo, Órgão ou Componente Orgânico": [
      "MMII",
      "estômago",
      "fígado",
      "braço E"
    ],
    "Negação": [
      "nega"
    ],
    "Função Patológica": [
      "edema",
      "arritmia"
    ],
    "Procedimento Terapêutico ou Preventivo": [
      "fisioterapia",
      "apendicectomia",
      "reposição hormonal"
    ],
    "Grupo Familiar": [
      "Mãe",
      "pai",
      "Tios"
    ],
    "Atividade de Assistência à Saúde": [
      "acompanhamento"
    ],
    "Grupo Profissional ou Ocupacional": [
      "oftalmologista",
      "cardiologista"
    ],
    "Função de Organismo": [
      "G"
    ],
    "Atributo Clínico": [
      "G"
    ],
    "Função Fisiológica": [
      "menopausa"
    ],
    "Procedimento Laboratorial": [
      "exames"
    ],
    "Conceito Temporal": [
      "2x por dia",
      "2 x/dia",
      "há 2 anos",
      "há 20 anos",
      "com 45 anos",
      "2cp a noite",
      "1cp no café"
    ],
    "Processo Neoplásico": [
      "CA no fígado"
    ],
    "Resultado Laboratorial ou de Teste": [
      "creatinina 1 , 2",
      "GJ 113",
      "CPK 90",
      "calcio total : 8 , 9",
      "TG 302",
      "HDL 24",
      "colesterol total 167",
      "LDL 83",
      "TSH 4 , 07",
      "T4 0 , 68",
      "vit D 36 , 1",
      "HbA1C 7 , 30%",
      "Glicose pós-prandial 119"
    ]
  },
  "labels": {}
}