{
  "prontuario_id": 455,
  "text": "Às 15:50: 1° DI COM HX DE DPOC + HEMIPARESIA A ESQUERDA. NO MOMENTO, CONSCIENTE, ORIENTADO, POUCO DISPNEICO, VERBALIZANDO COM DIFICULDADE, EM REPOUSO NO LEITO, O2 CONTÍNUO SOB UMIDIFICADOR, MANTÉM JEJUM, SEM QUEIXAS ÁLGICAS, ELIMINAÇÕES PRESENTES. ENF. FLORENCE NIGHTINGALE. ACIDENTE VASCULAR CEREBRAL NAO ESPECIFICADO COMO HEMORRAGICO OU ISQUEMICO. 3° DI COM HX DE DIVERTICULITE. CONSCIENTE, ORIENTADA, VERBALIZANDO. EM REPOUSO NO LEITO. COM CABECEIRA 45 GRAUS. PUPILAS ISO E FOTO. OXIMETRIA DE PULSO COM FC: 75, SAT DE O2: 93%. COM CVC À D. RESPIRAÇÃO ESPONTÂNEA COM AUXILIO DE O2 EM NÉVOA ÚMIDA à 6 L/MIN. DIVERTICULO DO ESOFAGO ADQUIRIDO. Às 5h: Paciente em preparo para Colonoscopia. Apesar de apresentar episódio de vômito, efeito intestinal satisfatório aparentemente. OUTRAS FORMAS DE OBSTRUCAO INTESTINAL E AS NAO ESPECIFICADAS. À 01:00: # precaução de contato. # Crise convulsiva. Abertura ocular espontanea, não responsivo. Traqueostomizado com O2 em névoa, sendo necessário aspiração intermitente, acesso venoso central em subclavia E com NPT em BI + medicação. Eliminações presentes. INTOXICACAO POR OUTRAS DROGAS MEDICAMENTOS E SUBSTANCIAS BIOLOGICAS E AS NAO ESPECIFICADAS.",
  "entities": {
    "Abreviação": [
      "DI",
      "ENF",
      "FC",
      "CVC",
      "D",
      "NPT",
      "BI",
      "HX DE DPOC",
      "HX DE DIVERTICULITE",
      "PUPILAS ISO E FOTO",
      "SAT DE O2",
      "subclavia E"
    ],
    "Sinal ou Sintoma": [
      "HEMIPARESIA",
      "DISPNEICO",
      "vômito",
      "VERBALIZANDO COM DIFICULDADE",
      "Crise convulsiva",
      "não responsivo"
    ],
    "Achado": [
      "CONSCIENTE",
      "ORIENTADO",
      "JEJUM",
      "ORIENTADA",
      "VERBALIZANDO",
      "FC",
      "REPOUSO NO LEITO",
      "ELIMINAÇÕES PRESENTES",
      "PUPILAS ISO E FOTO",
      "RESPIRAÇÃO ESPONTÂNEA",
      "efeito intestinal satisfatório",
      "Abertura ocular espontanea",
      "Eliminações presentes"
    ],
    "Grupo Profissional ou Ocupacional": [
      "ENF"
    ],
    "Atributo Clínico": [
      "FC",
      "SAT DE O2"
    ],
    "Conceito Quantitativo": [
      "75",
      "93%"
    ],
    "Procedimento Terapêutico ou Preventivo": [
      "CVC",
      "NPT",
      "REPOUSO NO LEITO",
      "O2 CONTÍNUO SOB UMIDIFICADOR",
      "CABECEIRA 45 GRAUS",
      "O2 EM NÉVOA ÚMIDA",
      "preparo para Colonoscopia",
      "precaução de contato",
      "aspiração intermitente",
      "acesso venoso central"
    ],
    "Conceito Espacial": [
      "D"
    ],
    "Paciente ou Grupo com Deficiência": [
      "Paciente"
    ],
    "Dispositivo Médico": [
      "BI",
      "acesso venoso central"
    ],
    "Substância Farmacológica": [
      "medicação"
    ],
    "Doença ou Síndrome": [
      "HX DE DPOC",
      "ACIDENTE VASCULAR CEREBRAL",
      "HX DE DIVERTICULITE",
      "DIVERTICULO DO ESOFAGO ADQUIRIDO",
      "OBSTRUCAO INTESTINAL"
    ],
    "Conceito Temporal": [
      "NO MOMENTO"
    ],
    "Função Fisiológica": [
      "ELIMINAÇÕES PRESENTES",
      "Eliminações presentes"
    ],
    "Procedimento Diagnóstico": [
      "OXIMETRIA DE PULSO"
    ],
    "Negação": [
      "NAO ESPECIFICADAS",
      "não responsivo"
    ],
    "Parte do Corpo, Órgão ou Componente Orgânico": [
      "subclavia E"
    ],
    "Lesão ou Envenenamento": [
      "INTOXICACAO POR OUTRAS DROGAS MEDICAMENTOS E SUBSTANCIAS BIOLOGICAS"
    ]
  },
  "labels": {}
}