{
  "prontuario_id": 815,
  "text": "ACEITOU BEM A DIETA ORAL. SENTADO NA POLTRONA. ESTENOSE SUBGLOTICA POS-PROCEDIMENTO. João, 78 anos, 1 dia de UTI. # S: Paciente admitido na UTI proveniente do PS, quadro de dispneia, HSA, paciente relata dor em região epigástrica. # O: Paciente em BEG, estável hemodinamicamente, afebril, boa saturação, pupilas isofoto, suporte de O2 névoa úmida, auscuta pulmonar RA ausente, MV diminuido em base direita, acesso venoso periférico em MSE, abdomen globoso, RHA + , região dorsal e sacra íntegra, SVD com baixo débito urinário, realizado medidas de conforto. # A: BEG, estável hemodinamicamente, eupneico no periodo.  # P: Manter monitorização cardíaca e oximetria de pulso continua, suporte de O2, cuidados intensivos, seguir prescriçoes multidisciplinares. INSUFICIENCIA CARDIACA CONGESTIVA. PACTE LÚCIDO, COMUNICATIVO, EUPNÉICO, NORMOCORADO, COM HEMATOMA EM OLHO DIREITO, CURATIVO OCLUSIVO EM MSD COM USO DE TIPÓIA, AVP EM MSE PÉRVIO, DIURESE ESPONTÃNEA PRESENTE, ACEITANDO BEM A DIETA ALIMENTAR OFERECIDA. SEM QUEIXAS ÁLGICAS, MANTENDO SSVV ESTÁVEIS, SEGUE SOB CUIDADOS DE ENFERMAGEM. ENFª FLORENCE NIGHTINGALE XXXX. TRAUMATISMO INTRACRANIANO NAO ESPECIFICADO. Às 00:30h: Retornou do CC apos realizar Laparotomia + esplenectomia + gastrorrafia e jejunostomia, face hipocorada, pupilas isomioticas / bradifotorreagentes. SNG em narina E fechada conforme orientaçoes plantao. Intubada, sob vm em modo CMV com 43% FIO2, PEEP 9, VC 350 ml, ausculta pulmonar com MV diminuidos  em base E, em uso de filtro bacteriologico + trach care. Acesso central E com infusao de NPT 63 ml/hr + dormonid 30 ml/hr + fentanil ml/hr. Extremidades edemaciadas, perfusao periferica diminuida. Dreno de torax hemitorax E com debito purulento, dreno em cavidade abdominal aberto sem presença de selo agua, conforme orientaçoes cirurgia geral, com debito sanguinolento + gastro aberta sem debito quantitativo no momento + jejuno fechada + FO aparentemente limpa. Diurese por SVD presente em coletor, amarelo citrico. Monitorizada continuamente com cardioscopio + oximetria de pulso + pam nao invasiva. Enfermeira Florence Nightingale. EDEMA CEREBRAL.",
  "entities": {
    "Conceito Qualitativo": [
      "BEM",
      "fechada"
    ],
    "Organização Relacionada à Saúde": [
      "UTI",
      "PS",
      "CC",
      "cirurgia geral"
    ],
    "Abreviação": [
      "UTI",
      "PS",
      "HSA",
      "BEG",
      "RA",
      "MSE",
      "SVD",
      "MSD",
      "AVP",
      "ENFª",
      "CC",
      "SNG",
      "E",
      "vm",
      "FIO2",
      "PEEP",
      "VC",
      "FO",
      "pupilas isofoto",
      "MV diminuido",
      "RHA +",
      "suporte de O2",
      "SSVV ESTÁVEIS",
      "modo CMV",
      "MV diminuidos",
      "infusao de NPT",
      "gastro aberta",
      "jejuno fechada"
    ],
    "Paciente ou Grupo com Deficiência": [
      "Paciente",
      "paciente"
    ],
    "Sinal ou Sintoma": [
      "dispneia",
      "dor",
      "RA",
      "globoso",
      "HEMATOMA",
      "MV diminuido",
      "QUEIXAS ÁLGICAS",
      "face hipocorada",
      "MV diminuidos",
      "Extremidades edemaciadas",
      "perfusao periferica diminuida",
      "debito purulento"
    ],
    "Achado": [
      "BEG",
      "afebril",
      "íntegra",
      "eupneico",
      "LÚCIDO",
      "COMUNICATIVO",
      "EUPNÉICO",
      "NORMOCORADO",
      "PÉRVIO",
      "Intubada",
      "limpa",
      "Monitorizada",
      "SENTADO NA POLTRONA",
      "estável hemodinamicamente",
      "boa saturação",
      "pupilas isofoto",
      "RHA +",
      "DIURESE ESPONTÃNEA PRESENTE",
      "SSVV ESTÁVEIS",
      "amarelo citrico"
    ],
    "Negação": [
      "afebril",
      "ausente",
      "sem",
      "nao"
    ],
    "Conceito Espacial": [
      "direita",
      "DIREITO",
      "E"
    ],
    "Localização ou Região Corporal": [
      "MSE",
      "abdomen",
      "sacra",
      "MSD",
      "região epigástrica",
      "região dorsal"
    ],
    "Dispositivo Médico": [
      "SVD",
      "TIPÓIA",
      "AVP",
      "SNG",
      "dreno",
      "coletor",
      "cardioscopio",
      "acesso venoso periférico",
      "oximetria de pulso",
      "CURATIVO OCLUSIVO",
      "filtro bacteriologico",
      "trach care",
      "Acesso central",
      "Dreno de torax"
    ],
    "Procedimento Terapêutico ou Preventivo": [
      "SVD",
      "TIPÓIA",
      "AVP",
      "Laparotomia",
      "esplenectomia",
      "gastrorrafia",
      "jejunostomia",
      "SNG",
      "Intubada",
      "vm",
      "dreno",
      "pam",
      "invasiva",
      "DIETA ORAL",
      "SENTADO NA POLTRONA",
      "névoa úmida",
      "acesso venoso periférico",
      "medidas de conforto",
      "suporte de O2",
      "CURATIVO OCLUSIVO",
      "DIETA ALIMENTAR",
      "filtro bacteriologico",
      "trach care",
      "Acesso central",
      "infusao de NPT",
      "Dreno de torax",
      "gastro aberta",
      "jejuno fechada"
    ],
    "Conceito Temporal": [
      "continua",
      "apos",
      "continuamente",
      "no periodo",
      "no momento"
    ],
    "Função Patológica": [
      "HEMATOMA",
      "EDEMA CEREBRAL"
    ],
    "Parte do Corpo, Órgão ou Componente Orgânico": [
      "OLHO",
      "pupilas"
    ],
    "Conceito Funcional": [
      "USO",
      "uso"
    ],
    "Atividade de Assistência à Saúde": [
      "orientaçoes",
      "plantao",
      "cuidados intensivos",
      "CUIDADOS DE ENFERMAGEM"
    ],
    "Conceito Quantitativo": [
      "43%",
      "9",
      "350 ml",
      "63 ml/hr",
      "30 ml/hr"
    ],
    "Substância Química Orgânica": [
      "dormonid",
      "fentanil"
    ],
    "Substância Farmacológica": [
      "dormonid",
      "fentanil"
    ],
    "Função Fisiológica": [
      "Diurese",
      "baixo débito urinário",
      "DIURESE ESPONTÃNEA PRESENTE"
    ],
    "Procedimento Diagnóstico": [
      "Monitorizada",
      "cardioscopio",
      "auscuta pulmonar",
      "monitorização cardíaca",
      "oximetria de pulso",
      "ausculta pulmonar"
    ],
    "Doença ou Síndrome": [
      "ESTENOSE SUBGLOTICA POS-PROCEDIMENTO",
      "INSUFICIENCIA CARDIACA CONGESTIVA"
    ],
    "Lesão ou Envenenamento": [
      "TRAUMATISMO INTRACRANIANO NAO ESPECIFICADO"
    ],
    "Espaço ou Junção Corporal": [
      "cavidade abdominal"
    ]
  },
  "labels": {}
}