{
  "prontuario_id": 528,
  "text": "ÀS 15:29: CORADO, ALERTA, AFEBRIL, ACAMADO, COM RESPOSTA OCULAR, EM REPOUSO NO LEITO, DIETA VIA SNE EM BOMBA INFUSORA, AVP EM MSE SALINIZADO, COM TRAQUEO E PRESENÇA DE SECREÇÃO AMARELA, ELIMINAÇÕES FISIOLOGICAS PRESENTES E ESPONTANEAS, SEGUE SOB CUIDADOS DE ENFERMAGEM. HEMORRAGIA INTRACEREBRAL HEMISFERICA SUBCORTICAL. Lucida, orientada, porém apresenta períodos de agitação motora, Respiração espontanea, sob névoa úmida, sat 95%, hemodinamicamente estável, abdome globoso, Rha + , permanece com fixador pelvico com discreta secreção sanguinolenta em inserçaõ á direita e, TRAUMATISMOS MULTIPLOS NAO ESPECIFICADOS. Às 9:30h: Alerta, orientado, verbalizando, em repouso no leito. Mantém colar cervical ajustado, aguarda chegada de colar cervical Philadelphia já solicitado pelos médicos. Nega algias ou outras queixas. Boa aceitação alimentar. Aguarda realização de RNM, agu. FRATURA DA PRIMEIRA VERTEBRA CERVICAL. ÀS 16:30 HS: CONSCIENTE. NEGA ALGIA. EM JEJUM PARA REALIZAÇÃO DE ARTERIOGRAFIA. DIURESE ESPONTÂNEA. TALA GESSADA EM MSE, LIMPA E SECA EXTERNAMENTE. ENFAIXAMENTO EM MID, LIMPO E SECO EXTERNAMENTE. AUSÊNCIA DE EDEMA DISTAL. BOA PERFUSÃO PERIFÉRICA. ACESSO VEN. TRAUMATISMOS MULTIPLOS NAO ESPECIFICADOS.",
  "entities": {
    "Achado": [
      "CORADO",
      "ALERTA",
      "AFEBRIL",
      "ACAMADO",
      "Lucida",
      "orientada",
      "Alerta",
      "orientado",
      "verbalizando",
      "CONSCIENTE",
      "JEJUM",
      "LIMPA",
      "SECA",
      "LIMPO",
      "SECO",
      "RESPOSTA OCULAR",
      "REPOUSO NO LEITO",
      "ELIMINAÇÕES FISIOLOGICAS",
      "Respiração espontanea",
      "hemodinamicamente estável",
      "Rha",
      "+",
      "repouso no",
      "leito",
      "aceitação",
      "alimentar",
      "DIURESE",
      "ESPONTÂNEA",
      "BOA PERFUSÃO",
      "PERIFÉRICA"
    ],
    "Negação": [
      "AFEBRIL",
      "Nega",
      "AUSÊNCIA"
    ],
    "Dispositivo Médico": [
      "AVP",
      "fixador",
      "pelvico",
      "colar cervical Philadelphia",
      "TALA",
      "GESSADA",
      "ACESSO"
    ],
    "Procedimento Terapêutico ou Preventivo": [
      "AVP",
      "TRAQUEO",
      "JEJUM",
      "ENFAIXAMENTO",
      "REPOUSO NO LEITO",
      "DIETA VIA SNE",
      "névoa úmida",
      "fixador pelvico",
      "repouso leito",
      "no",
      "colar cervical ajustado",
      "TALA",
      "GESSADA"
    ],
    "Abreviação": [
      "AVP",
      "MSE",
      "TRAQUEO",
      "RNM",
      "MID",
      "DIETA VIA SNE",
      "sat 95%",
      "Rha +",
      "ACESSO",
      "VEN"
    ],
    "Localização ou Região Corporal": [
      "MSE",
      "abdome",
      "MID"
    ],
    "Conceito Qualitativo": [
      "PRESENTES",
      "ESPONTANEAS",
      "Boa"
    ],
    "Sinal ou Sintoma": [
      "globoso",
      "algias",
      "queixas",
      "ALGIA",
      "EDEMA",
      "SECREÇÃO AMARELA",
      "agitação motora"
    ],
    "Conceito Espacial": [
      "direita",
      "EXTERNAMENTE"
    ],
    "Grupo Profissional ou Ocupacional": [
      "médicos"
    ],
    "Procedimento Diagnóstico": [
      "RNM",
      "ARTERIOGRAFIA"
    ],
    "Substância Corporal": [
      "SECREÇÃO AMARELA"
    ],
    "Função Fisiológica": [
      "ELIMINAÇÕES FISIOLOGICAS",
      "DIURESE",
      "ESPONTÂNEA"
    ],
    "Atividade de Assistência à Saúde": [
      "CUIDADOS DE ENFERMAGEM"
    ],
    "Doença ou Síndrome": [
      "HEMORRAGIA INTRACEREBRAL HEMISFERICA SUBCORTICAL"
    ],
    "Lesão ou Envenenamento": [
      "TRAUMATISMOS NAO ESPECIFICADOS",
      "MULTIPLOS",
      "FRATURA DA PRIMEIRA VERTEBRA CERVICAL",
      "TRAUMATISMOS MULTIPLOS NAO",
      "ESPECIFICADOS"
    ],
    "Alimento": [
      "aceitação",
      "alimentar"
    ]
  },
  "labels": {}
}