{
  "prontuario_id": 349,
  "text": "Às 07:58Hrs: Cliente em glw 15, pupilas iso / foto + , respiração espontânea em aa, eupneica, face corada, mucosa oral hidratada, boa perfusão periferica, no leito com cabeceira elevada á 30°. Jejum para procedimento cx. Mantem com monitorização de multiparametros, ECG, PNI, SpO2, acesso venoso periferico em MSE com srt em curso gravitacional. Apresenta ausculta cardiaca ritmica e normofonetica, ausculta pulmonar MV +, sem R/A, abdomen plano e flacido, com RHA + . Faz uso de SVD aberta com debito diuretico presente ++ de coloração amarelo claro, eliminação fecal ausente. segue cuidados. Às 10:20hs: Boa aceitação de dieta líquida pastosa VO. Sentado na poltrona. Ás 23:00h, encaminhado de ambulância para o X-Leme para realizar RNM, sob cuidados da aux de enfermagem, retorno por volta das 01:30h, exame realizado sem intercorrências. Laudo da RNM mantido juntamente como prontuário do pcte. Aguarda reavaliação e conduta médica.",
  "entities": {
    "Paciente ou Grupo com Deficiência": [
      "Cliente",
      "pcte"
    ],
    "Achado": [
      "eupneica",
      "ritmica",
      "normofonetica",
      "plano",
      "flacido",
      "glw 15",
      "pupilas iso / foto +",
      "respiração espontânea em aa",
      "face corada",
      "mucosa oral hidratada",
      "boa perfusão periferica",
      "MV +",
      "RHA +",
      "debito diuretico presente",
      "coloração amarelo claro",
      "eliminação fecal",
      "Boa aceitação de dieta líquida pastosa VO"
    ],
    "Procedimento Terapêutico ou Preventivo": [
      "Jejum",
      "SpO2",
      "cabeceira elevada á 30°",
      "procedimento cx",
      "acesso venoso periferico",
      "srt em curso gravitacional",
      "SVD aberta"
    ],
    "Procedimento Diagnóstico": [
      "ECG",
      "PNI",
      "RNM",
      "monitorização de multiparametros",
      "ausculta cardiaca",
      "ausculta pulmonar"
    ],
    "Abreviação": [
      "ECG",
      "PNI",
      "SpO2",
      "MSE",
      "R/A",
      "RNM",
      "pcte",
      "glw 15",
      "pupilas iso / foto +",
      "respiração espontânea em aa",
      "procedimento cx",
      "srt em curso gravitacional",
      "MV +",
      "RHA +",
      "SVD aberta",
      "Boa aceitação de dieta líquida pastosa VO",
      "aux de enfermagem",
      "Laudo da RNM"
    ],
    "Localização ou Região Corporal": [
      "MSE",
      "abdomen"
    ],
    "Negação": [
      "sem",
      "ausente"
    ],
    "Sinal ou Sintoma": [
      "R/A",
      "intercorrências"
    ],
    "Conceito Funcional": [
      "uso"
    ],
    "Atividade de Assistência à Saúde": [
      "cuidados",
      "exame"
    ],
    "Dispositivo Médico": [
      "ambulância",
      "acesso venoso periferico",
      "SVD aberta"
    ],
    "Produto Intelectual": [
      "prontuário"
    ],
    "Função Fisiológica": [
      "debito diuretico presente",
      "eliminação fecal"
    ],
    "Grupo Profissional ou Ocupacional": [
      "aux de enfermagem"
    ],
    "Resultado Laboratorial ou de Teste": [
      "Laudo da RNM"
    ]
  },
  "labels": {}
}