{
  "prontuario_id": 746,
  "text": "Às 13:30HS: ORIENTADO, CALMO, COMUNICATIVO, EUPNEICO EM AR AMBIENTE, CORADO, MEDICO DA ORTOPEDIA ORIENTOU PARA JEJUM APÓS ALMOÇO, PARA PROCEDIMENTO NO CENTRO CIRURGICO, ACESSO VENOSO PERIFERICO EM ANTEBRAÇO DIREITO SALINIZADO NO MOMENTO, CURATIVO + FIXADOR EXTERNO, EM MEMBRO INFERIOR ESQUERDO, APRESENTA FLICTENAS EM DORSO DO PÉ, RELATA ALGIA; FOI MEDICADO CONFORME PRESCRIÇÃO MÉDICA. SONDA VESICAL DE DEMORA COM DÉBITO CITRINO, segue sob cuidados. # AVC ISQUEMICO. # S: SEM QUEIXAS NO PERIODO. # O: GLASGOW ESTIMADO EM 14, PUPILAS ISOFOTO, AFEBRIL, NORMOCÁRDICA, NORMOTENSA, SNE DIETA EM CURSO 75 ML/H EM BOMBA INFUSORA, ACESSO VENOSO PERIFÉRICO EM MSD SALINIZADO, ABDOMEN PLANO, PALPÁVEL, REGIÃO DORSAL E SACRA ÍNTEGRA, EXTREMIDADES AQUECIDAS E PERFUNDIDAS, REALZIADO MEDIDAS DE HIGIENE E CONFORTO. # A: BEG. # P: SEGUIR PRESCRIÇÃO DE ENFERMAGEM E MULTIDISCIPLINAR. OBS: COMUNICO SERVIÇO SOCIAL PARA SOLICITAR A PRESENÇA DA FAMÍLIA PARA ORIENTAÇÕES DE ALTA, AGUARDO CONTATO.",
  "entities": {
    "Achado": [
      "ORIENTADO",
      "CALMO",
      "COMUNICATIVO",
      "CORADO",
      "SALINIZADO",
      "AFEBRIL",
      "NORMOCÁRDICA",
      "NORMOTENSA",
      "PLANO",
      "PALPÁVEL",
      "ÍNTEGRA",
      "AQUECIDAS",
      "BEG",
      "EUPNEICO EM AR AMBIENTE",
      "DÉBITO CITRINO",
      "PUPILAS ISOFOTO",
      "E PERFUNDIDAS"
    ],
    "Grupo Profissional ou Ocupacional": [
      "MEDICO",
      "SERVIÇO SOCIAL"
    ],
    "Organização Relacionada à Saúde": [
      "ORTOPEDIA",
      "CENTRO CIRURGICO",
      "SERVIÇO SOCIAL"
    ],
    "Procedimento Terapêutico ou Preventivo": [
      "JEJUM",
      "PROCEDIMENTO",
      "SALINIZADO",
      "CURATIVO",
      "MEDICADO",
      "SNE",
      "ACESSO VENOSO PERIFERICO",
      "FIXADOR EXTERNO",
      "SONDA VESICAL DE DEMORA",
      "DIETA EM CURSO",
      "ACESSO VENOSO PERIFÉRICO",
      "MEDIDAS DE HIGIENE E CONFORTO"
    ],
    "Dispositivo Médico": [
      "CURATIVO",
      "SNE",
      "ACESSO VENOSO PERIFERICO",
      "FIXADOR EXTERNO",
      "SONDA VESICAL DE DEMORA",
      "ACESSO VENOSO PERIFÉRICO"
    ],
    "Sinal ou Sintoma": [
      "FLICTENAS",
      "ALGIA",
      "QUEIXAS",
      "GLASGOW ESTIMADO EM 14"
    ],
    "Atividade de Assistência à Saúde": [
      "MEDICADO",
      "cuidados",
      "ALTA",
      "PRESCRIÇÃO MÉDICA",
      "PRESCRIÇÃO DE ENFERMAGEM"
    ],
    "Negação": [
      "AFEBRIL"
    ],
    "Abreviação": [
      "SNE",
      "MSD",
      "BEG",
      "AVC ISQUEMICO"
    ],
    "Localização ou Região Corporal": [
      "MSD",
      "ABDOMEN",
      "REGIÃO",
      "DORSAL",
      "SACRA",
      "EXTREMIDADES",
      "MEMBRO INFERIOR ESQUERDO",
      "DORSO DO PÉ"
    ],
    "Grupo Familiar": [
      "FAMÍLIA"
    ],
    "Parte do Corpo, Órgão ou Componente Orgânico": [
      "ANTEBRAÇO DIREITO"
    ],
    "Produto Intelectual": [
      "PRESCRIÇÃO MÉDICA",
      "PRESCRIÇÃO DE ENFERMAGEM"
    ],
    "Doença ou Síndrome": [
      "AVC ISQUEMICO"
    ],
    "Conceito Quantitativo": [
      "75 ML/H"
    ],
    "Dispositivo de Administração de Medicamento": [
      "BOMBA INFUSORA"
    ]
  },
  "labels": {}
}