{
  "prontuario_id": 500,
  "text": "Às 06:30: Paciente consciente, lúcido, orientado, comunicativo, normotenso, normocorado, afebril, deambulando. MAntém acesso venoso em MSD, salinizado no momento; permanece com curativo oclusivo em mão E, limpo e seco. PAciente mantém agora, curativo em coxa E, região de pele doadora para enxertia. Relata não conseguir esticar a perna e leve algia. Mantém boa aceitação da dieta oferecida; eliminações presentes. Segue sob cuidados. FRATURA DE OUTROS OSSOS DO CARPO. Às 18:55hrs: Realizo passagem de SNE em narina DIR, procedimento sem intercorrencia, aguarda RX de controle para iniciar dietaterapia. Enf° Florence Nightingale, Coren XXXX. OSTEOMIELITE AGUDA HEMATOGENICA. Às 12:45: CONSCIENTE, ORIENTADO, VERBALIZA, DEAMBULA, NO MOMENTO REPOUSO NO LEITO, AFEBRIL, EUPNEICO EM AR AMBIENTE, SEM QUEIXAS ALGICAS, SEM ACESSO VENOSO, ACEITANDO DIETA OFERECIDA, MANTEM TALA GESSADA + CURATIVO EM MSE EXTERNAMENTE LIMPO E SECO, MOVIMENTAÇÃO PRESERVADA, DIURESE ESPONTANEA, EVACUAÇÃO PRESENTE. ENF Florence Nightingale, XXXX. FRATURA DE OUTROS DEDOS.",
  "entities": {
    "Paciente ou Grupo com Deficiência": [
      "Paciente",
      "PAciente"
    ],
    "Achado": [
      "consciente",
      "lúcido",
      "orientado",
      "comunicativo",
      "normotenso",
      "normocorado",
      "afebril",
      "deambulando",
      "salinizado",
      "limpo",
      "seco",
      "CONSCIENTE",
      "ORIENTADO",
      "VERBALIZA",
      "DEAMBULA",
      "AFEBRIL",
      "LIMPO",
      "SECO",
      "boa aceitação da dieta",
      "eliminações presentes",
      "REPOUSO NO LEITO",
      "EUPNEICO EM AR AMBIENTE",
      "ACEITANDO DIETA",
      "MOVIMENTAÇÃO PRESERVADA",
      "DIURESE ESPONTANEA",
      "EVACUAÇÃO PRESENTE"
    ],
    "Negação": [
      "afebril",
      "AFEBRIL"
    ],
    "Abreviação": [
      "MSD",
      "Enf°",
      "MSE",
      "ENF",
      "mão E",
      "coxa E",
      "passagem de SNE",
      "narina DIR",
      "RX de controle"
    ],
    "Localização ou Região Corporal": [
      "MSD",
      "MSE",
      "coxa E",
      "região de pele"
    ],
    "Procedimento Terapêutico ou Preventivo": [
      "salinizado",
      "curativo",
      "enxertia",
      "procedimento",
      "dietaterapia",
      "CURATIVO",
      "acesso venoso",
      "curativo oclusivo",
      "passagem de SNE",
      "REPOUSO NO LEITO",
      "ACESSO VENOSO",
      "TALA GESSADA"
    ],
    "Dispositivo Médico": [
      "curativo",
      "CURATIVO",
      "acesso venoso",
      "curativo oclusivo",
      "ACESSO VENOSO",
      "TALA GESSADA"
    ],
    "Atividade de Assistência à Saúde": [
      "cuidados"
    ],
    "Grupo Profissional ou Ocupacional": [
      "Enf°",
      "ENF"
    ],
    "Conceito Espacial": [
      "EXTERNAMENTE"
    ],
    "Parte do Corpo, Órgão ou Componente Orgânico": [
      "mão E"
    ],
    "Sinal ou Sintoma": [
      "leve algia",
      "QUEIXAS ALGICAS"
    ],
    "Função Fisiológica": [
      "eliminações presentes",
      "DIURESE ESPONTANEA",
      "EVACUAÇÃO PRESENTE"
    ],
    "Lesão ou Envenenamento": [
      "FRATURA DE OUTROS OSSOS DO CARPO",
      "FRATURA DE OUTROS DEDOS"
    ],
    "Espaço ou Junção Corporal": [
      "narina DIR"
    ],
    "Procedimento Diagnóstico": [
      "RX de controle"
    ],
    "Doença ou Síndrome": [
      "OSTEOMIELITE AGUDA HEMATOGENICA"
    ]
  },
  "labels": {}
}