{
  "prontuario_id": 642,
  "text": "Às 15:30: ENCAMINHADA PARA REALIZAÇÃO DE ESPIROMETRIA, DEAMBULANDO, ACOMPANHADA PELA ENFERMAGEM. Às 10:00Hrs: Cliente hemodinamicamente estavel, encaminhada ao centro cirurgico. Às 12:35HS: CONSCIENTE, COMUNICATIVO, DEAMBULANDO, EUPINEICO. NÃO REFERE ALGIA. ACEITOU BEM A DIETA OFERECIDA. CURATIVO LIMPO E SECO EXTERNAMENTE. SEGUE CUIDADOS. Às 9H15MIN: ADMINISTRADO MIDAZOLAN E ENCAMINHADO AO CENTRO CIRÚRGICO ACOMPANHADO PELA ENFERMAGEM. Em 10/04/12, 16:00: 8º do na uti por ave i + tu cerebral. # 6º D TQT EM VM MODO PSV, PS 9, FIO2 30%, VC 400, PEEP 5. # 6º D SNE COM DIETA 50 ML/H. # 6º D SVD DIURESE EFETIVA. # PROGNÓSTICO RESERVADO. SAV C. GLASGOW 6T, PUPILAS ISOMIÓTICAS, SEM AVP, MEDICAÇÃO VO, REALIZADO TROCA DE CÂNULA DE TQT PELO médico, TQT NUM 08. PROCEDIMENTO SEM INTERCORRÊNCIAS. ",
  "entities": {
    "Procedimento Diagnóstico": [
      "ESPIROMETRIA"
    ],
    "Achado": [
      "DEAMBULANDO",
      "CONSCIENTE",
      "COMUNICATIVO",
      "EUPINEICO",
      "LIMPO",
      "SECO",
      "hemodinamicamente estavel",
      "ACEITOU BEM A DIETA",
      "DIURESE EFETIVA"
    ],
    "Grupo Profissional ou Ocupacional": [
      "ENFERMAGEM",
      "médico"
    ],
    "Organização Relacionada à Saúde": [
      "ENFERMAGEM",
      "uti",
      "centro cirurgico",
      "CENTRO CIRÚRGICO"
    ],
    "Paciente ou Grupo com Deficiência": [
      "Cliente"
    ],
    "Sinal ou Sintoma": [
      "ALGIA",
      "GLASGOW 6T"
    ],
    "Dispositivo Médico": [
      "CURATIVO",
      "SVD",
      "AVP",
      "TQT NUM 08"
    ],
    "Procedimento Terapêutico ou Preventivo": [
      "CURATIVO",
      "TQT",
      "VM",
      "FIO2",
      "PEEP",
      "SVD",
      "AVP",
      "PROCEDIMENTO",
      "MODO PSV",
      "SNE COM DIETA",
      "TROCA DE CÂNULA DE TQT"
    ],
    "Conceito Espacial": [
      "EXTERNAMENTE"
    ],
    "Atividade de Assistência à Saúde": [
      "CUIDADOS"
    ],
    "Substância Farmacológica": [
      "MIDAZOLAN",
      "MEDICAÇÃO VO"
    ],
    "Abreviação": [
      "uti",
      "TQT",
      "VM",
      "PS",
      "FIO2",
      "VC",
      "PEEP",
      "SVD",
      "AVP",
      "ave i",
      "tu cerebral",
      "MODO PSV",
      "SNE COM DIETA",
      "SAV C",
      "MEDICAÇÃO VO",
      "TROCA DE CÂNULA DE TQT"
    ],
    "Conceito Quantitativo": [
      "9",
      "30%",
      "400",
      "5",
      "50 ML/H"
    ],
    "Doença ou Síndrome": [
      "ave i"
    ],
    "Processo Neoplásico": [
      "tu cerebral"
    ],
    "Função Fisiológica": [
      "DIURESE EFETIVA"
    ]
  },
  "labels": {}
}