{
  "prontuario_id": 851,
  "text": "Às 24:30h: Consciente, orientada no tempo e espaço, comunicativa. Aceita bem dieta oferecida, refere dormir bem e fazer bastante \"xixi\", relata algia em fêmur D. Ao exame físico, ausculta pulmonar com MV diminuídos bilateralmente. BCRNF s/ s. Abdomen globoso e flácido. Acesso venoso periférico em mão D, hematoma em MMSS. Incisão cirúrgica em região de fêmur D com curativo limpo e seco. Ac de enfermagem Florence e Maria. FRATURA DO FEMUR. Às 11:58h: Realizo passagem de SNE para alimentação; procedimento realizado sem intercorrência; Solicto RX de abdome simples no leito para 14h. Aguarda realização de RX para liberação da dieta. EXAME GERAL E INVESTIGACAO DE PESSOAS SEM QUEIXAS OU DIAGNOSTICO RELATADO.",
  "entities": {
    "Achado": [
      "Consciente",
      "comunicativa",
      "BCRNF",
      "flácido",
      "limpo",
      "seco",
      "orientada no tempo e espaço",
      "Aceita bem dieta",
      "dormir bem"
    ],
    "Sinal ou Sintoma": [
      "algia",
      "globoso",
      "hematoma",
      "MV diminuídos bilateralmente"
    ],
    "Abreviação": [
      "BCRNF",
      "MMSS",
      "RX",
      "fêmur D",
      "MV diminuídos bilateralmente",
      "mão D",
      "região de fêmur D",
      "RX de abdome simples"
    ],
    "Localização ou Região Corporal": [
      "Abdomen",
      "MMSS",
      "região de fêmur D"
    ],
    "Função Patológica": [
      "hematoma"
    ],
    "Dispositivo Médico": [
      "curativo",
      "Acesso venoso periférico"
    ],
    "Procedimento Terapêutico ou Preventivo": [
      "curativo",
      "procedimento",
      "Acesso venoso periférico"
    ],
    "Organização Relacionada à Saúde": [
      "enfermagem"
    ],
    "Grupo Profissional ou Ocupacional": [
      "enfermagem"
    ],
    "Procedimento Diagnóstico": [
      "RX",
      "exame físico",
      "ausculta pulmonar",
      "RX de abdome simples"
    ],
    "Alimento": [
      "dieta"
    ],
    "Parte do Corpo, Órgão ou Componente Orgânico": [
      "fêmur D",
      "mão D"
    ],
    "Lesão ou Envenenamento": [
      "Incisão cirúrgica",
      "FRATURA DO FEMUR"
    ]
  },
  "labels": {}
}