{
  "prontuario_id": 789,
  "text": "Em 29/05/2012, 06:00hrs: Paciente 3º PO de drenagem de HSD, responsiva, com periodos de confusão, Gls 13-14, respiração espontanea com auxilio de névoa úmida, SSVV estaveis, afebril, eupneico, pupilas isofotorreagentes, MV + bilateral, sem ra, dvs, bcrnf 2t ss, ab flacido, indolor a palpação, sem vmg palpaveis, MMII sem edemas. SNG com dieta em BI acesso venoso central. Em 25/05/2012, em subclavia direita com srt gravitacional, MCPM, ctvo cefálico limpo e seco, FO em região cefálica sem sinais flogisticos, encaminhado paciente para TAC de cranio de controle, conforme pedido da neurocx, realizado banho de leito, troca de curativos, SVD em 25/05/2012 com débito citrico, mantendo cuidados de UTI. Enfº Florence Nightingale. Às 12H: PROVENIENTE DA UTI 3, CALMA, COMUNICATIVA, EUPNEICA, ACEITA DIETA OFERECIDA. REFERE USO DE OXIGENOTERAPIA INTERMITENTE. ACESSO VENOSO PERIFÉRICO SALINIZADO EM MSD. O MESMO PÉRVIO, SEM SINAIS FLOGISTICOS. DIURESE PRESENTE ESPONTANEAMENTE. EVACUAÇÃO AUSENTE. SEGUE SOB CUIDADOS DE ENFERMAGEM. Às 09:50HS: GLASGOW 3. INCISÃO CIRURGICA SEM SINAIS FLOGISTICOS. SNE COM DIETA EM CURSO. TRAQUEOSTOMIZA COM POUCA QUANTIDADE DE SECREÇÃO FLUIDIFICADA. EUPINEICO COM SUPORTE DE NEVOA UMIDA. ULCERA POR PRESSÃO EM REGIAO SACRA, COM TECIDO NECROTICO. ULCERA POR PRESSÃO EM CALCANEOS. DIURESE ESPONTANEA EM FRALDA.  ",
  "entities": {
    "Paciente ou Grupo com Deficiência": [
      "Paciente",
      "paciente"
    ],
    "Abreviação": [
      "PO",
      "ra",
      "dvs",
      "ab",
      "MMII",
      "MCPM",
      "FO",
      "neurocx",
      "SVD",
      "Enfº",
      "UTI",
      "MSD",
      "drenagem de HSD",
      "Gls 13-14",
      "SSVV estaveis",
      "MV + bilateral",
      "vmg palpaveis",
      "srt gravitacional",
      "ctvo cefálico",
      "TAC de cranio",
      "cuidados de UTI",
      "SNE COM DIETA"
    ],
    "Conceito Temporal": [
      "PO"
    ],
    "Achado": [
      "responsiva",
      "afebril",
      "eupneico",
      "flacido",
      "limpo",
      "seco",
      "CALMA",
      "COMUNICATIVA",
      "EUPNEICA",
      "SALINIZADO",
      "PÉRVIO",
      "EVACUAÇÃO",
      "TRAQUEOSTOMIZA",
      "EUPINEICO",
      "respiração espontanea",
      "SSVV estaveis",
      "pupilas isofotorreagentes",
      "MV + bilateral",
      "débito citrico",
      "ACEITA DIETA",
      "DIURESE PRESENTE ESPONTANEAMENTE",
      "SECREÇÃO FLUIDIFICADA",
      "DIURESE ESPONTANEA",
      "EM FRALDA"
    ],
    "Negação": [
      "afebril",
      "sem",
      "ss",
      "indolor",
      "SEM",
      "AUSENTE"
    ],
    "Sinal ou Sintoma": [
      "ra",
      "ss",
      "edemas",
      "periodos de confusão",
      "Gls 13-14",
      "vmg palpaveis",
      "sinais flogisticos",
      "SINAIS FLOGISTICOS",
      "GLASGOW 3"
    ],
    "Localização ou Região Corporal": [
      "ab",
      "MMII",
      "MSD",
      "região cefálica",
      "REGIAO SACRA"
    ],
    "Procedimento Diagnóstico": [
      "palpação",
      "TAC de cranio"
    ],
    "Função Patológica": [
      "edemas"
    ],
    "Lesão ou Envenenamento": [
      "FO",
      "INCISÃO CIRURGICA"
    ],
    "Procedimento Terapêutico ou Preventivo": [
      "SVD",
      "TRAQUEOSTOMIZA",
      "drenagem de HSD",
      "névoa úmida",
      "acesso venoso central",
      "srt gravitacional",
      "ctvo cefálico",
      "banho de leito",
      "troca de curativos",
      "OXIGENOTERAPIA INTERMITENTE",
      "ACESSO VENOSO PERIFÉRICO",
      "SNE COM DIETA",
      "SUPORTE DE NEVOA UMIDA"
    ],
    "Dispositivo Médico": [
      "SVD",
      "acesso venoso central",
      "ctvo cefálico",
      "ACESSO VENOSO PERIFÉRICO"
    ],
    "Grupo Profissional ou Ocupacional": [
      "Enfº"
    ],
    "Organização Relacionada à Saúde": [
      "UTI"
    ],
    "Função Fisiológica": [
      "EVACUAÇÃO",
      "débito citrico",
      "DIURESE PRESENTE ESPONTANEAMENTE",
      "DIURESE ESPONTANEA"
    ],
    "Parte do Corpo, Órgão ou Componente Orgânico": [
      "CALCANEOS",
      "subclavia direita"
    ],
    "Atividade de Assistência à Saúde": [
      "cuidados de UTI",
      "CUIDADOS DE ENFERMAGEM"
    ],
    "Conceito Qualitativo": [
      "POUCA QUANTIDADE"
    ],
    "Substância Corporal": [
      "SECREÇÃO FLUIDIFICADA"
    ],
    "Doença ou Síndrome": [
      "ULCERA POR PRESSÃO"
    ]
  },
  "labels": {}
}