{
  "prontuario_id": 427,
  "text": "S: 2º DI na UTI. # 2º PO APENDICECTOMIA AGUDA + COLECTOMIA COM ILEOTRANSVERSOANASTOMOSE. O: ECG 14, EC 0, PUPILAS ISOMIOTICAS RFM +, ESCLERA OCULAR EDEMACIADA, SNG COM DIETA À 20 ML/H EM BI, INTUBADO SOB VM: PS 14, PEEP 5, FIO2 0,3%. MANTEM FILTRO BARREIRA BACTERIOLOGICO, PAM EM ARTÉRIA RADIAL ESQUERDA PERMEÁVEL, CVC EM SUBCLAVIA DIREITA COM SF 0,9% À 21 ML/H, NORADRENALINA À 5 ML/H EM BI, CONTROLE PVC, CONTIDO NO LEITO PARA PREVENÇÃO DE ACIDENTES COM DISPOSITIVOS, AC: BCRNF, AP: PRESENÇA DE RONCOS ESPARÇOS BILATERAL, ABD: RHA +, DISTENDIDO E RIGIDO, INCISÃO CIRURGICA COM CURATIVO LIMPO E SECO, DRENO SUCTOR COM DEBITO SEROSO EM PEQUENA QUANTIDADE, SVD COM BAIXO FLUXO URINÁRIO AMARELO OURO CONCENTRADO, REGIÃO DORSAL COM PELE INTEGRA. MONITORIZAÇÃO MULTIPARAMETRICO. A: RISCO PARA INFECÇÃO; PADRÃO RESPIRATÓRIO INEFICAZ; DESOBSTRUÇÃO INEFICAZ DE VIAS AEREAS; RISCO PARA DESEQUILIBRIO NUTRICIONAL; RISCO PARA INTEGRIDADE DA PELE PREJUDICADA. P: SEGUE PRESCRIÇÃO DE ENFERMAGEM EM ANEXO. À 01:00 H: CLIENTE CONSCIENTE, POUCO CONTACTUANTE, SE COMUNICA POR GESTOS, ABERTURA OCULAR ESPONTANEA, OBEDECE COMANDOS COM DIFICULDADE, REPOUSO, AFEBRIL, EUPNEICA. RECEBE DIETA VIA SNE POR BI 30 ML/H. MANTEM ACESSO PERIFERICO COM PLANO DE HIDRATAÇÃO EM CURSO. APRESENTA ÚLCERA EM MIE, REGIÃO DE PÉ, COM ASPECTO SECO E LIMPO EXTERNAMENTE. ELIMINAÇÕES EM FRALDA. SEGUE EM OBSERVAÇÃO E CUIDADOS.  ",
  "entities": {
    "Organização Relacionada à Saúde": [
      "UTI"
    ],
    "Abreviação": [
      "UTI",
      "PO",
      "BI",
      "VM",
      "PS",
      "PEEP",
      "FIO2",
      "PAM",
      "CVC",
      "AC",
      "BCRNF",
      "AP",
      "ABD",
      "SVD",
      "MIE",
      "ECG 14",
      "EC 0",
      "RFM +",
      "SNG COM DIETA",
      "SF 0 , 9%",
      "CONTROLE PVC",
      "RHA +",
      "DIETA VIA SNE"
    ],
    "Conceito Temporal": [
      "PO"
    ],
    "Dispositivo de Administração de Medicamento": [
      "BI"
    ],
    "Achado": [
      "INTUBADO",
      "PERMEÁVEL",
      "BCRNF",
      "LIMPO",
      "SECO",
      "CONSCIENTE",
      "REPOUSO",
      "AFEBRIL",
      "EUPNEICA",
      "EC 0",
      "RFM +",
      "CONTIDO NO LEITO",
      "RHA +",
      "PEQUENA QUANTIDADE",
      "PELE INTEGRA",
      "RISCO PARA INFECÇÃO",
      "DESOBSTRUÇÃO INEFICAZ DE VIAS AEREAS",
      "RISCO PARA DESEQUILIBRIO NUTRICIONAL",
      "ABERTURA OCULAR ESPONTANEA",
      "OBEDECE COMANDOS COM DIFICULDADE",
      "ASPECTO SECO"
    ],
    "Procedimento Terapêutico ou Preventivo": [
      "INTUBADO",
      "VM",
      "PS",
      "PEEP",
      "FIO2",
      "CVC",
      "CURATIVO",
      "SVD",
      "REPOUSO",
      "APENDICECTOMIA AGUDA",
      "COLECTOMIA COM ILEOTRANSVERSOANASTOMOSE",
      "SNG COM DIETA",
      "FILTRO BARREIRA BACTERIOLOGICO",
      "CONTIDO NO LEITO",
      "PREVENÇÃO DE ACIDENTES COM DISPOSITIVOS",
      "DRENO SUCTOR",
      "DIETA VIA SNE",
      "ACESSO PERIFERICO",
      "PLANO DE HIDRATAÇÃO"
    ],
    "Conceito Quantitativo": [
      "14",
      "5",
      "20 ML/H",
      "0 , 3%",
      "21 ML/H",
      "5 ML/H",
      "30 ML/H"
    ],
    "Procedimento Diagnóstico": [
      "PAM",
      "AC",
      "AP",
      "CONTROLE PVC",
      "MONITORIZAÇÃO MULTIPARAMETRICO"
    ],
    "Dispositivo Médico": [
      "CVC",
      "BI",
      "CURATIVO",
      "SVD",
      "FILTRO BARREIRA BACTERIOLOGICO",
      "DRENO SUCTOR",
      "ACESSO PERIFERICO"
    ],
    "Substância Farmacológica": [
      "NORADRENALINA",
      "SF 0 , 9%"
    ],
    "Hormônio": [
      "NORADRENALINA"
    ],
    "Localização ou Região Corporal": [
      "ABD",
      "MIE",
      "REGIÃO DORSAL"
    ],
    "Parte do Corpo, Órgão ou Componente Orgânico": [
      "ABD",
      "PÉ",
      "ARTÉRIA RADIAL ESQUERDA",
      "SUBCLAVIA DIREITA"
    ],
    "Paciente ou Grupo com Deficiência": [
      "CLIENTE"
    ],
    "Negação": [
      "AFEBRIL"
    ],
    "Doença ou Síndrome": [
      "ÚLCERA"
    ],
    "Conceito Espacial": [
      "EXTERNAMENTE"
    ],
    "Objeto Manufaturado": [
      "FRALDA"
    ],
    "Atividade de Assistência à Saúde": [
      "OBSERVAÇÃO",
      "CUIDADOS",
      "PRESCRIÇÃO DE ENFERMAGEM"
    ],
    "Sinal ou Sintoma": [
      "ECG 14",
      "PUPILAS ISOMIOTICAS",
      "ESCLERA OCULAR EDEMACIADA",
      "RONCOS ESPARÇOS BILATERAL",
      "DISTENDIDO E RIGIDO",
      "DEBITO SEROSO",
      "BAIXO FLUXO URINÁRIO",
      "PADRÃO RESPIRATÓRIO INEFICAZ",
      "POUCO CONTACTUANTE",
      "OBEDECE COMANDOS COM DIFICULDADE"
    ],
    "Lesão ou Envenenamento": [
      "INCISÃO CIRURGICA"
    ],
    "Conceito Qualitativo": [
      "PEQUENA QUANTIDADE"
    ],
    "Produto Intelectual": [
      "PRESCRIÇÃO DE ENFERMAGEM"
    ]
  },
  "labels": {}
}