{
  "prontuario_id": 298,
  "text": "9:47 H CONSCIENTE, ORIENTADO, VERBALIZANDO, MOBILIZANDO ATIVAMENTE OS MEMBROS.  DISPNEICO AOS ESFORÇOS, MV DIFUSOS,  82 NASAL 2 L/MIN. SOROTERAPIA EM ACESSO VENOSO SENDO INFUNDIDO  SF 0,9 21 ML/H, PUNCIONADO NOVO ACESSO VENOSO DEVIDO HIPEREMIA.  ABDOME GLOBOSO, RHA PRESENTES, URINANDO ESPONTANEAMENTE NO BANHEIRO. MONITORIZADO, OXIMETRIA DE PULSO, HEMODINAMICAMENTE ESTÁVEL. INSUFICIENCIA CARDIACA CONGESTIVA. PCTE PROVENIENTE DO INTERNAMENTO PARA PROCEDIMENTO CIRÚRGICO AMANHÃ. CHEGOU LÚCIDO, COMUNICATIVO, NORMOCORADO, EUPNÉICO, RESTRITO AO LEITO, RELATANDO ELIMINAÇÕES FISIOLÓGICAS PRESENTES E BOA ACEINTAÇÃO DA DIETA ALIMENTAR. RELATOU FORTE ALGI EM MSE, PORÉM PCTE NÃO POSSUIA PRESCRIÇÃO MÉDICA. COMUNICADO DR VITAL BRASIL, PORÉM O MESMO NÃO SE ENCONTRAVA NO HOSPITAL. DR VITAL BRASIL AVALIOU O PCTE E SOLICITOU RAIO-X E REALIZOU PRESCRIÇÃO MÉDICA, E ASSIM QUE REALIZADO COMUNICAR DR VITAL BRASIL (PLANTÃO DA ORTOPEDIA). ORIENTANDO A REALIZAR JEJUM ORAL APÓS ÀS 24 HORAS. SEGUE SOB CUIDADOS DE ENFERMAGEM. ENFª FLORENCE NIGHTINGALE XXXX. FRATURA DE MANDIBULA.",
  "entities": {
    "Achado": [
      "CONSCIENTE",
      "ORIENTADO",
      "VERBALIZANDO",
      "MONITORIZADO",
      "LÚCIDO",
      "COMUNICATIVO",
      "NORMOCORADO",
      "EUPNÉICO",
      "MOBILIZANDO ATIVAMENTE OS MEMBROS",
      "MV DIFUSOS",
      "RHA PRESENTES",
      "URINANDO ESPONTANEAMENTE",
      "HEMODINAMICAMENTE ESTÁVEL",
      "RESTRITO AO LEITO",
      "ELIMINAÇÕES FISIOLÓGICAS PRESENTES",
      "BOA ACEINTAÇÃO DA DIETA ALIMENTAR"
    ],
    "Procedimento Terapêutico ou Preventivo": [
      "SOROTERAPIA",
      "ACESSO VENOSO",
      "PUNCIONADO NOVO",
      "PROCEDIMENTO CIRÚRGICO",
      "RESTRITO AO LEITO",
      "BOA ACEINTAÇÃO DA DIETA ALIMENTAR",
      "JEJUM ORAL"
    ],
    "Sinal ou Sintoma": [
      "HIPEREMIA",
      "DISPNEICO AOS ESFORÇOS",
      "ABDOME GLOBOSO",
      "FORTE ALGI"
    ],
    "Procedimento Diagnóstico": [
      "MONITORIZADO",
      "RAIO-X",
      "OXIMETRIA DE PULSO"
    ],
    "Abreviação": [
      "PCTE",
      "MSE",
      "DR",
      "ENFª",
      "MV DIFUSOS",
      "SF 0 , 9",
      "RHA PRESENTES"
    ],
    "Paciente ou Grupo com Deficiência": [
      "PCTE"
    ],
    "Localização ou Região Corporal": [
      "MSE"
    ],
    "Negação": [
      "NÃO"
    ],
    "Organização Relacionada à Saúde": [
      "HOSPITAL",
      "PLANTÃO DA ORTOPEDIA"
    ],
    "Grupo Profissional ou Ocupacional": [
      "ENFª"
    ],
    "Conceito Quantitativo": [
      "2 L/MIN",
      "21 ML/H"
    ],
    "Dispositivo Médico": [
      "ACESSO VENOSO"
    ],
    "Substância Farmacológica": [
      "SF 0 , 9"
    ],
    "Função Fisiológica": [
      "URINANDO ESPONTANEAMENTE",
      "ELIMINAÇÕES FISIOLÓGICAS PRESENTES"
    ],
    "Doença ou Síndrome": [
      "INSUFICIENCIA CARDIACA CONGESTIVA"
    ],
    "Atividade de Assistência à Saúde": [
      "PRESCRIÇÃO MÉDICA",
      "CUIDADOS DE ENFERMAGEM"
    ],
    "Produto Intelectual": [
      "PRESCRIÇÃO MÉDICA"
    ],
    "Lesão ou Envenenamento": [
      "FRATURA DE MANDIBULA"
    ]
  },
  "labels": {}
}