{
  "prontuario_id": 852,
  "text": "05:35 HORAS. PACIENTE TRAZIDA AO PRONTO ATENDIMENTO POR REMOÇÃO PARTICULAR. POR CRISE CONVULSIVA. CHEGA EM CRISE ENCAMINHADA PARA SALA DE EMERGÊNCIA, PUNCIONADO ACESSO VENOSO PERÍFERICO PACIENTE DE DIFÍCIL ACESSO. COLOCADA EM SUPORTE DE 02 SOB MÁSCARA DE VENTURI EM 6 L/MIN E MONITORIZAÇÃO CARDÍACA E OXÍMETRIA DE PULSO CONTÍNUA - SSVV ESTÁVEIS. PERMANECE EM REPOUSO NO LEITO, CABECEIRA ELEVADA 45°C. APRESENTOU NOVO EPISÓDIO SEGUIDA DE VÔMITOS - MEDICADA CONFORME PRESCRIÇÃO. ENCAMINHADA PARA TOMOGRAFIA DE CRÂNIO - TRASPORTE SEM INTERCORRÊNCIAS. RETORNA PARA SALA DE EMERGÊNCIA, REALIZADA PASSAGEM DE SVD COM DÉBITO CLARO E PASSAGEM DE SNG SEM DÉBITO. PERMANECERÁ NO PRONTO ATENDIMENTO AGUARDANDO VAGA DE UTI. SEGUE SOB OS CUIDADOS DA EQUIPE MULTIPROFISSIONAL. ESTADO DE MAL EPILEPTICO. 02:37 Em repouso no leito, em ar ambiente, refeindo algia em halux D, diurese presente, evacução ausente, aceita a dieta oferecida , apresentou dextro 225 administrado 4 UI conforme esquema. Segue sob cuidados multiprofissionais. FLORENCE NIGHTINGALE XXXX. EXPOSICAO A OUTROS FATORES AMBIENTAIS ARTIFICIAIS E AOS NAO ESPECIFICADOS LOCAL NAO ESPECIFICADO.",
  "entities": {
    "Paciente ou Grupo com Deficiência": [
      "PACIENTE"
    ],
    "Sinal ou Sintoma": [
      "VÔMITOS",
      "algia",
      "CRISE CONVULSIVA"
    ],
    "Procedimento Terapêutico ou Preventivo": [
      "MEDICADA",
      "SVD",
      "SNG",
      "PUNCIONADO ACESSO VENOSO PERÍFERICO",
      "SUPORTE DE 02",
      "REPOUSO NO LEITO",
      "CABECEIRA ELEVADA 45°C",
      "repouso no leito"
    ],
    "Produto Intelectual": [
      "PRESCRIÇÃO"
    ],
    "Atividade de Assistência à Saúde": [
      "PRESCRIÇÃO",
      "CUIDADOS DA EQUIPE MULTIPROFISSIONAL",
      "cuidados multiprofissionais"
    ],
    "Negação": [
      "SEM",
      "ausente"
    ],
    "Achado": [
      "INTERCORRÊNCIAS",
      "DÉBITO",
      "evacução",
      "DIFÍCIL ACESSO",
      "SSVV ESTÁVEIS",
      "REPOUSO NO LEITO",
      "DÉBITO CLARO",
      "repouso no leito",
      "ar ambiente",
      "diurese presente",
      "aceita a dieta"
    ],
    "Abreviação": [
      "SVD",
      "SNG",
      "UTI",
      "SSVV ESTÁVEIS",
      "halux D",
      "4 UI"
    ],
    "Dispositivo Médico": [
      "SVD",
      "SNG",
      "PUNCIONADO ACESSO VENOSO PERÍFERICO",
      "MÁSCARA DE VENTURI"
    ],
    "Organização Relacionada à Saúde": [
      "UTI",
      "PRONTO ATENDIMENTO",
      "SALA DE EMERGÊNCIA"
    ],
    "Função Fisiológica": [
      "evacução",
      "diurese presente"
    ],
    "Conceito Quantitativo": [
      "225",
      "6 L/MIN"
    ],
    "Procedimento Diagnóstico": [
      "MONITORIZAÇÃO CARDÍACA",
      "OXÍMETRIA DE PULSO CONTÍNUA",
      "TOMOGRAFIA DE CRÂNIO"
    ],
    "Doença ou Síndrome": [
      "ESTADO DE MAL EPILEPTICO"
    ],
    "Parte do Corpo, Órgão ou Componente Orgânico": [
      "halux D"
    ]
  },
  "labels": {}
}