{
  "prontuario_id": 423,
  "text": "08:40hs Repassado SNE e realizado testes, aguarda RX para confirmar posicionamento. Enf FLORENCE NIGHTINGALE. 09:00hs Glasglow 4, pupilas levemente anisocóricas, TQT em VM modo controlado VC: 660, PEEP: 8, FiO2: 60%, AVCSE com noradrenalina: 30 ml/h, SNE repassada aguarda RX para confirmar posicionamento, SNG aberta com estase gástrica, FO abdominal  com saida discreta de secreção serosanguinolenta, SVD com diurese concentrada. Monitorização PAM radial esquerda: 100 mmHg, FC: 126 bpm, SpO2: 97%, asculta cardíaca: BRNF SS, asculta pulmonar: MV presente e roncos difusos, abdomen flácido e RH presente, extremidades bem perfundidas e aquecidas, segue aos cuidados intensivos de enfermagem. Enf FLORENCE NIGHTINGALE. SEPTICEMIA NAO ESPECIFICADA. 00:36 Lucida, comunicativa, em repouso no leito, referindo mal estar gastrico, realizado troca de curativo em MIE, ferida sanguinolenta, com pouca secreçao serosa, extremidade aquecida, referindo algia intensa no local, foi medicada, aceita dieta, diurese presente, segue cuidados. VARIZES DOS MEMBROS INFERIORES COM ULCERA.",
  "entities": {
    "Abreviação": [
      "RX",
      "Enf",
      "TQT",
      "VM",
      "VC",
      "PEEP",
      "FiO2",
      "AVCSE",
      "FO",
      "FC",
      "bpm",
      "SpO2",
      "MIE",
      "Repassado SNE",
      "SNE repassada",
      "SNG aberta com estase gástrica",
      "SVD com diurese concentrada",
      "Monitorização PAM",
      "BRNF SS",
      "MV presente",
      "RH presente"
    ],
    "Procedimento Diagnóstico": [
      "RX",
      "Monitorização PAM",
      "asculta cardíaca",
      "asculta pulmonar"
    ],
    "Grupo Profissional ou Ocupacional": [
      "Enf"
    ],
    "Procedimento Terapêutico ou Preventivo": [
      "TQT",
      "VM",
      "PEEP",
      "FiO2",
      "AVCSE",
      "medicada",
      "Repassado SNE",
      "modo controlado",
      "SNE repassada",
      "SNG aberta com estase gástrica",
      "repouso no leito",
      "troca de curativo"
    ],
    "Conceito Quantitativo": [
      "660",
      "8",
      "60%",
      "126",
      "97%",
      "30 ml/h",
      "100 mmHg"
    ],
    "Dispositivo Médico": [
      "AVCSE"
    ],
    "Substância Farmacológica": [
      "noradrenalina"
    ],
    "Hormônio": [
      "noradrenalina"
    ],
    "Substância Química Orgânica": [
      "noradrenalina"
    ],
    "Lesão ou Envenenamento": [
      "FO"
    ],
    "Localização ou Região Corporal": [
      "abdominal",
      "abdomen",
      "extremidades",
      "MIE"
    ],
    "Atributo Clínico": [
      "FC",
      "SpO2"
    ],
    "Achado": [
      "Lucida",
      "comunicativa",
      "BRNF SS",
      "MV presente",
      "RH presente",
      "bem perfundidas",
      "repouso no leito",
      "extremidade aquecida",
      "aceita dieta",
      "diurese presente"
    ],
    "Conceito Qualitativo": [
      "pouca"
    ],
    "Atividade de Assistência à Saúde": [
      "cuidados",
      "cuidados intensivos de enfermagem"
    ],
    "Sinal ou Sintoma": [
      "Glasglow 4",
      "pupilas levemente anisocóricas",
      "SNG aberta com estase gástrica",
      "discreta de secreção serosanguinolenta",
      "roncos difusos",
      "mal estar gastrico",
      "algia intensa"
    ],
    "Função Fisiológica": [
      "SVD com diurese concentrada",
      "diurese presente"
    ],
    "Parte do Corpo, Órgão ou Componente Orgânico": [
      "radial esquerda"
    ],
    "Substância Corporal": [
      "secreçao serosa"
    ],
    "Doença ou Síndrome": [
      "VARIZES DOS MEMBROS INFERIORES COM ULCERA"
    ]
  },
  "labels": {}
}