{
  "prontuario_id": 837,
  "text": "15:30HRS Conforme orientação da plantonista Dra Maria, foi suspensa alta da UTI por instabilidade hemodinâmica. Segue cuidados intensivos de enfermagem. Enf° FLORENCE NIGHTINGALE, Coren XXXX. INSUFICIENCIA RESPIRATORIA AGUDA. 19:30 GLASGOW = 15, ACORDDA, COMUNICATIVA, COLABORATIVA APRESENTANDO PERÍODOS DE CONFUSÃO, PERMANECE EUPNEICA SATURANDO 97% (19:15 CAPACETE CEFÁLICO TROCADO PELO DR VITAL BRASIL), NORMOTENSA (109/60), NORMOCÁRDICA (65 bpm), NORMOCORADA, AUSCULTA PULMONAR COM RAROS RONCOS, ACESSO VENOSO EM FACE EXTERNA DE ANTEBRAÇO MSD RECEBENDO PLANO BÁSICO DE HIDRATAÇÃO, ABDOMEM FLÁCIDO SEM MASSA PALPÁVEL, INDOLOR A PALPAÇÃO, DLE ABERTA PELO DR VITAL BRASIL COM DÉBITO TOTAL DE 175 ML ATÉ O MOMENTO, PELE ÍNTEGRA EM SACRA, SVD COM DIURESE EFETIVA (BALANÇO + 708), HEMODINAMICAMENTE ESTÁVEL EM MONITORIZAÇÃO DE ECG, PA, OXIMETRIA DE PULSO, PRECAUÇÃO DE CONTATO PROFILÁTICO, SEGUE SOB CUIDADOS DE ENFERMAGEM. EXAME GERAL E INVESTIGACAO DE PESSOAS SEM QUEIXAS OU DIAGNOSTICO RELATADO.",
  "entities": {
    "Grupo Profissional ou Ocupacional": [
      "plantonista",
      "Enf°"
    ],
    "Abreviação": [
      "Dra",
      "UTI",
      "Enf°",
      "DR",
      "MSD",
      "ECG",
      "PA",
      "DLE ABERTA",
      "SVD COM DIURESE EFETIVA"
    ],
    "Atividade de Assistência à Saúde": [
      "alta",
      "cuidados intensivos de enfermagem",
      "CUIDADOS DE ENFERMAGEM"
    ],
    "Organização Relacionada à Saúde": [
      "UTI"
    ],
    "Achado": [
      "ACORDDA",
      "COMUNICATIVA",
      "COLABORATIVA",
      "EUPNEICA",
      "NORMOTENSA",
      "NORMOCÁRDICA",
      "NORMOCORADA",
      "FLÁCIDO",
      "GLASGOW = 15",
      "MASSA PALPÁVEL",
      "PELE ÍNTEGRA",
      "SVD COM DIURESE EFETIVA",
      "HEMODINAMICAMENTE ESTÁVEL"
    ],
    "Atributo Clínico": [
      "SATURANDO"
    ],
    "Conceito Quantitativo": [
      "97%",
      "109/60",
      "65 bpm",
      "175 ML"
    ],
    "Localização ou Região Corporal": [
      "MSD",
      "ABDOMEM",
      "SACRA",
      "FACE EXTERNA DE ANTEBRAÇO"
    ],
    "Negação": [
      "SEM",
      "INDOLOR"
    ],
    "Procedimento Diagnóstico": [
      "PALPAÇÃO",
      "MONITORIZAÇÃO",
      "ECG",
      "AUSCULTA PULMONAR",
      "OXIMETRIA DE PULSO"
    ],
    "Sinal ou Sintoma": [
      "QUEIXAS",
      "instabilidade hemodinâmica",
      "PERÍODOS DE CONFUSÃO",
      "RAROS RONCOS"
    ],
    "Doença ou Síndrome": [
      "INSUFICIENCIA RESPIRATORIA AGUDA"
    ],
    "Dispositivo Médico": [
      "CAPACETE CEFÁLICO",
      "ACESSO VENOSO"
    ],
    "Procedimento Terapêutico ou Preventivo": [
      "CAPACETE CEFÁLICO",
      "ACESSO VENOSO",
      "PLANO BÁSICO DE HIDRATAÇÃO",
      "DLE ABERTA",
      "PRECAUÇÃO DE CONTATO PROFILÁTICO"
    ],
    "Função Fisiológica": [
      "SVD COM DIURESE EFETIVA"
    ]
  },
  "labels": {}
}