{
  "prontuario_id": 202,
  "text": "FERNANDA  # OSTEOGêNESE IMPERFEITA  PACIENTE TRANSFERIDA DE URUGUAIANA PARA INVESTIGAÇÃO DE OSTEOGÊNESE IMPERFEITA. NASCIDA DE PV, SEM PEDIATRA NA SALA DE PARTO, PRÉ NATAL: ECO OBSTÉTRICA COM ALTERAÇÃO DE FÊMUR. CHEGA AO HOSPITAL COM TRAÇÃO DE MEMBROS INFERIORES, AVALIADA PELA GENÉTICA QUE SUGERE INICIAR PAMIDRONATO (TRATAMENTO OSTEOGENESE IMPERFEITA TIPO 3) E SOLICITAR EXAMES PRÉVIOS. 31/05 SOLICITO EXAMES PRÉ PAMIDRONATO E CONSULTORIA PARA PATOLOGIA CLÍNICA (SOLICITO DOSAGEM DE N-TELO PEPTÍDEO). 01/06 COLETANDO URINA DE 24 HORAS. DISCUTIDO EM ROUND: INICIAR PAMIDRONATO NA SEGUNDA FEIRA. 04/06 INICIADO PAMIDRONATO, REALIZADO CONTROLES PRÉ E POS PAMIDRONATO. 05/06 INICIADO COM FEBRE PERSISTENTE E PROSTRAÇÃO, HEMOGRAMA NÃO INFECCIOSO. 06/06 INICIADO VANCO E AMICA, NOVO HEMOGRAMA SEM ALTERAÇÃO, PCR 51, HMC: NEGATIVA. RETIRADO TRAÇÃO DE MMI PELA TRAUMATO, RX DE CORPO INTEIRO. FRATURA MMSSD RECOLOCADA TALA. COMPLETOU 10 DIAS  DE ANTIBIÓTICOS SENDO SUSPENSO EM 17/06. RX DE CORPO INTEIRO CONFORME ORIENTADO PELA TRAUMATO. 21/06 IMOBILIZADO MMSS D PELA TRAUMATO, QUE NECESSITOU SER RECOLOCADO NA SEGUNDA-FEIRA, POIS HAVIA SAÍDO DO LUGAR.MANTÉM-SE ESTÁVEL E EM BOM ESTADO GERAL. REAVALIADA PELA ORTOPEDIA EM 26/06/07  QUE DÁ ALTA À PACIENTE E RETORNO EM AGOSTO PARA REAVALIAÇÃO. REAVALIADA PELA GENÉTICA EM 27/06/07, DE ONDE TAMBÉM RECEBE ALTA COM PLANO DE REINTERNAÇÃO EM AGOSTO PARA REALIZAÇÃO DE PAMIDRONATO. TEM ALTA EM BOM ESTADO GERAL, AFEBRIL, COM MEMBRO SUPERIOR DIREITO IMOBILIZADO, ACEITANDO BEM VO E COM PRESCRIÇÃO DE VITAMINA A + D.   PLANO: # RETORNO COM TRAUMATO EM AGOSTO PARA CONTINUAÇÃO DO ACOMPANHAMENTO. # RETORNO COM A GENÉTICA EM AGOSTO COM PLANO DE INTERNAÇÃO PARA A REALIZAÇÃO DE PAMIDRONATO. # MANUSEIO MÍNIMO. # PRESCREVO VITAMINA A + D. # RETORNO À EMERGÊNCIA EM CASO DE INTERCORRÊNCIAS.",
  "entities": {
    "Paciente ou Grupo com Deficiência": [
      "PACIENTE"
    ],
    "Atividade de Assistência à Saúde": [
      "INVESTIGAÇÃO",
      "REAVALIADA",
      "ALTA",
      "RETORNO",
      "REAVALIAÇÃO",
      "PRESCRIÇÃO",
      "ACOMPANHAMENTO"
    ],
    "Abreviação": [
      "PV",
      "VANCO",
      "AMICA",
      "TRAUMATO",
      "ECO OBSTÉTRICA",
      "HMC : NEGATIVA",
      "RETIRADO TRAÇÃO DE MMI",
      "RX DE CORPO INTEIRO",
      "FRATURA MMSSD",
      "ACEITANDO BEM VO",
      "VITAMINA A + D"
    ],
    "Procedimento Terapêutico ou Preventivo": [
      "PV",
      "IMOBILIZADO",
      "TRAÇÃO DE MEMBROS INFERIORES",
      "TRATAMENTO OSTEOGENESE IMPERFEITA TIPO 3",
      "RETIRADO TRAÇÃO DE MMI",
      "RECOLOCADA TALA",
      "NECESSITOU SER RECOLOCADO",
      "PLANO DE REINTERNAÇÃO"
    ],
    "Negação": [
      "SEM",
      "AFEBRIL"
    ],
    "Grupo Profissional ou Ocupacional": [
      "PEDIATRA",
      "GENÉTICA",
      "TRAUMATO",
      "ORTOPEDIA",
      "PATOLOGIA CLÍNICA"
    ],
    "Organização Relacionada à Saúde": [
      "HOSPITAL",
      "EMERGÊNCIA",
      "SALA DE PARTO"
    ],
    "Substância Farmacológica": [
      "PAMIDRONATO",
      "ANTIBIÓTICOS",
      "DE PAMIDRONATO",
      "VITAMINA A + D"
    ],
    "Substância Química Orgânica": [
      "PAMIDRONATO",
      "AMICA",
      "VITAMINA A + D"
    ],
    "Procedimento Diagnóstico": [
      "EXAMES",
      "ECO OBSTÉTRICA",
      "RX DE CORPO INTEIRO"
    ],
    "Procedimento Laboratorial": [
      "EXAMES",
      "DOSAGEM DE N-TELO PEPTÍDEO",
      "URINA DE 24 HORAS"
    ],
    "Conceito Temporal": [
      "PRÉ",
      "POS",
      "PRÉ NATAL"
    ],
    "Sinal ou Sintoma": [
      "PROSTRAÇÃO",
      "INTERCORRÊNCIAS",
      "FEBRE PERSISTENTE"
    ],
    "Aminoácido, Peptídeo ou Proteína": [
      "VANCO"
    ],
    "Antibiótico": [
      "VANCO",
      "AMICA",
      "ANTIBIÓTICOS"
    ],
    "Achado": [
      "ESTÁVEL",
      "AFEBRIL",
      "BOM ESTADO GERAL",
      "ACEITANDO BEM VO"
    ],
    "Produto Intelectual": [
      "PRESCRIÇÃO"
    ],
    "Anormalidade Congênita": [
      "OSTEOGêNESE IMPERFEITA",
      "TRATAMENTO OSTEOGENESE IMPERFEITA TIPO 3"
    ],
    "Doença ou Síndrome": [
      "OSTEOGêNESE IMPERFEITA",
      "TRATAMENTO OSTEOGENESE IMPERFEITA TIPO 3"
    ],
    "Resultado Laboratorial ou de Teste": [
      "ALTERAÇÃO DE FÊMUR",
      "PCR 51",
      "HMC : NEGATIVA"
    ],
    "Lesão ou Envenenamento": [
      "FRATURA MMSSD"
    ],
    "Localização ou Região Corporal": [
      "MEMBRO SUPERIOR DIREITO"
    ],
    "Vitamina": [
      "VITAMINA A + D"
    ]
  },
  "labels": {}
}