{
  "prontuario_id": 132,
  "text": "Paciente com nefrolitíase, interna para NPC, procedimento sem intercorrências. Apresenta adequada evolução pós-operatória, recebe alta em BEG, retirada sonda de nefrostomia, com RX de controle sem evidencia de litiase residual. MENOR ADMITIDO NO D11 PÓS-QT (SEM 31) COM NEUTROPENIA FEBRIL. HEMOCULTURA COM ESTAFILOCOCOS COAGULASE NEG, USOU VANCOMICINA POR 07 DIAS.  RECEBE ALTA COM CLAVULIN POR 03 DIAS. RETORNAR EM 02/07 PARA ÚLTIMA QT. Paciente internou para realização de revisão de mastoidectomia. Procedimento realizado sem intercorrências. Paciente recebe alta em bom estado geral, sem paralisia facial ou cofose, com orientações de cuidados domiciliares, analgesia, antibioticoterapia e acompanhamento ambulatorial ou a emergencia se sinais de gravidade orientados. G2 C1, IG de 39 sem, TS: B +. INTERNA PARA REALIZAR PARTO CESARIA POR FETO EM APRESENTAÇÃO PÉLVICA. EVOLUI PARA Cesárea em 16/06/2007, 20:29 hs, RN APGAR 9 / 10, FEM, 3310 G, VDRL: nr, TOXO IGG e IGM: nr. RECEBE ALTA EM BOM ESTADO GERAL, SINAIS VITAIS ESTÁVEIS, MAMAS LACTANTES, LÓQUIOS FISIOLÓGICOS, ÚTERO CONTRAÍDO, FERIDA OPERATÓRIA SEM PARTICULARIDADES.",
  "entities": {
    "Paciente ou Grupo com Deficiência": [
      "Paciente"
    ],
    "Doença ou Síndrome": [
      "nefrolitíase",
      "litiase",
      "NEUTROPENIA FEBRIL",
      "paralisia facial"
    ],
    "Procedimento Terapêutico ou Preventivo": [
      "NPC",
      "procedimento",
      "QT",
      "Procedimento",
      "analgesia",
      "antibioticoterapia",
      "Cesárea",
      "retirada sonda de nefrostomia",
      "revisão de mastoidectomia",
      "acompanhamento ambulatorial",
      "PARTO CESARIA"
    ],
    "Abreviação": [
      "NPC",
      "BEG",
      "PÓS-QT",
      "QT",
      "G2",
      "C1",
      "IG",
      "TS",
      "RN",
      "FEM",
      "RX de controle",
      "ESTAFILOCOCOS COAGULASE NEG",
      "39 sem",
      "VDRL : nr",
      "TOXO IGG e IGM : nr"
    ],
    "Negação": [
      "sem",
      "SEM"
    ],
    "Sinal ou Sintoma": [
      "intercorrências",
      "cofose",
      "PARTICULARIDADES",
      "sinais de gravidade"
    ],
    "Atividade de Assistência à Saúde": [
      "alta",
      "ALTA",
      "RETORNAR",
      "internou",
      "orientações",
      "INTERNA",
      "cuidados domiciliares"
    ],
    "Achado": [
      "BEG",
      "PARTICULARIDADES",
      "adequada evolução",
      "bom estado geral",
      "APRESENTAÇÃO PÉLVICA",
      "BOM ESTADO GERAL",
      "SINAIS VITAIS ESTÁVEIS",
      "MAMAS LACTANTES",
      "LÓQUIOS FISIOLÓGICOS",
      "ÚTERO CONTRAÍDO"
    ],
    "Conceito Temporal": [
      "PÓS-QT",
      "DIAS",
      "ÚLTIMA"
    ],
    "Procedimento Laboratorial": [
      "HEMOCULTURA"
    ],
    "Aminoácido, Peptídeo ou Proteína": [
      "VANCOMICINA"
    ],
    "Antibiótico": [
      "VANCOMICINA",
      "CLAVULIN"
    ],
    "Substância Química Orgânica": [
      "CLAVULIN"
    ],
    "Organização Relacionada à Saúde": [
      "emergencia"
    ],
    "Atributo Clínico": [
      "IG",
      "TS"
    ],
    "Grupo Populacional": [
      "RN"
    ],
    "Atributo de Organismo": [
      "FEM"
    ],
    "Procedimento Diagnóstico": [
      "RX de controle"
    ],
    "Bactéria": [
      "ESTAFILOCOCOS COAGULASE NEG"
    ],
    "Resultado Laboratorial ou de Teste": [
      "ESTAFILOCOCOS COAGULASE NEG",
      "VDRL : nr",
      "TOXO IGG e IGM : nr"
    ],
    "Conceito Quantitativo": [
      "3310 G"
    ],
    "Lesão ou Envenenamento": [
      "FERIDA OPERATÓRIA"
    ]
  },
  "labels": {}
}