{
  "prontuario_id": 535,
  "text": "PACIENTE INTERNA COM QUADRO DE ANGINA INSTÁVEL. REALIZADA ANGIOPLASTIA COM IMPLANTE DE STENT EM CD, PROCEDIMENTO REALIZADO SEM INTERCORRÊNCIAS, COM SUCESSO ANGIOGRÁFICO. STENT PRÉVIAMENTE IMPLANTADO EM DAE LIVRE DE REESTENOSE. Realiza angioplastia com implante de stent em artéria renal direita. Procedimento transcorreu sem intercorrências. Paciente interna com quadro de IC, com sinais de congestao intensa pulmonar e sistemica. Rx Tórax com grande derrame pleural bilateral. Ecocardiograma mostra disfunção ventricular difusa leve, e movimento anômalo septal. Revisão do marcasso com Dr Vital Brasil mostra funcionamento adequado do dispositivo. Implementadas medidas farmacológicas e não farmacologicas com boa evolução clinica. Durante a internação apresentou episódio de dor torácica posterior intensa, contínua, que necessitou de esquema analgésico contínuo, atribuída a absorção de derrame pleural. pte veio ao xxxx com dor atipica ao esforco. Internou por teste de esforco com infra st maior q 1 mm, ja assintomatica. Realizou portanto, cintilografia de esforco que foi normal, sem deficits de perfusao ou hipocinesia em teste livre de drogas. Tem alta em bom estado geral e estratificada do ponto de vista cardiaco como sendo de minimo (bx) risco para dor isquemica, sendo o teste de esforco provavelmente um falso positivo. Segue ao seu medico para investigar origem da dor (osteomuscular, dispepsia, espasmo esof). Sem medicaçoes prescritas.",
  "entities": {
    "Paciente ou Grupo com Deficiência": [
      "PACIENTE",
      "Paciente",
      "pte"
    ],
    "Atividade de Assistência à Saúde": [
      "INTERNA",
      "interna",
      "internação",
      "Internou",
      "alta"
    ],
    "Procedimento Terapêutico ou Preventivo": [
      "ANGIOPLASTIA",
      "PROCEDIMENTO",
      "angioplastia",
      "Procedimento",
      "IMPLANTE DE STENT",
      "implante de stent",
      "esquema analgésico contínuo"
    ],
    "Parte do Corpo, Órgão ou Componente Orgânico": [
      "CD",
      "DAE",
      "artéria renal direita"
    ],
    "Abreviação": [
      "CD",
      "DAE",
      "IC",
      "Dr",
      "pte",
      "Rx Tórax",
      "espasmo esof"
    ],
    "Negação": [
      "SEM",
      "sem",
      "não",
      "assintomatica",
      "Sem"
    ],
    "Sinal ou Sintoma": [
      "INTERCORRÊNCIAS",
      "intercorrências",
      "assintomatica",
      "dor",
      "dispepsia",
      "ANGINA INSTÁVEL",
      "sinais de congestao intensa pulmonar e sistemica",
      "dor torácica posterior intensa",
      "dor atipica ao esforco",
      "dor isquemica"
    ],
    "Dispositivo Médico": [
      "STENT"
    ],
    "Função Patológica": [
      "REESTENOSE"
    ],
    "Doença ou Síndrome": [
      "IC",
      "derrame pleural",
      "espasmo esof"
    ],
    "Procedimento Diagnóstico": [
      "Ecocardiograma",
      "Rx Tórax",
      "Revisão do marcasso",
      "teste de esforco",
      "cintilografia de esforco"
    ],
    "Substância Farmacológica": [
      "farmacologicas",
      "medicaçoes",
      "medidas farmacológicas"
    ],
    "Conceito Temporal": [
      "contínua"
    ],
    "Achado": [
      "assintomatica",
      "SUCESSO ANGIOGRÁFICO",
      "funcionamento adequado do dispositivo",
      "boa evolução clinica",
      "bom estado geral",
      "falso positivo"
    ],
    "Resultado Laboratorial ou de Teste": [
      "normal",
      "grande derrame pleural bilateral",
      "disfunção ventricular difusa leve",
      "movimento anômalo septal",
      "funcionamento adequado do dispositivo",
      "infra st maior q 1 mm",
      "hipocinesia em teste livre de drogas",
      "falso positivo"
    ],
    "Grupo Profissional ou Ocupacional": [
      "medico"
    ],
    "Sistema Corporal": [
      "osteomuscular"
    ]
  },
  "labels": {}
}