{
  "prontuario_id": 388,
  "text": "12:16 horas. Paciente proveniente do CMUM Cajuru (4 dias de permanência), com Hx de dor abdominal a aproximadamente 15 dias associada a vomitos. Com SNG aberta em frasco com 300 ml de estase gástrica biliosa, consciente, lucida, respondendo ao comando verbal, pele e mucosa corada e hidratada, eupneica em ar ambiente. AVP em MSD para venóclise. Ausculta pulmonar livre, abdomen flácido, doloroso a palpação. RHA diminuídos. Diurese espontânea, eliminação intestinal ausente a aproximadamente 15 dias (SIC). Relata ainda que realizou ontem enema, porem, sem eficacia. Nega alergia medicamentosa. Afirma que interrompeu o tratamento de infecção urinaria. Paciente segue sobre avaliação medica. OUTRAS DOENÇAS ESPECIFICADAS DO PANCREAS",
  "entities": {
    "Paciente ou Grupo com Deficiência": [
      "Paciente"
    ],
    "Dispositivo Médico": [
      "frasco",
      "AVP"
    ],
    "Achado": [
      "consciente",
      "lucida",
      "corada",
      "hidratada",
      "eficacia",
      "respondendo ao comando verbal",
      "eupneica em ar ambiente",
      "Ausculta pulmonar livre",
      "Diurese espontânea",
      "eliminação intestinal"
    ],
    "Parte do Corpo, Órgão ou Componente Orgânico": [
      "pele",
      "mucosa"
    ],
    "Procedimento Terapêutico ou Preventivo": [
      "AVP",
      "venóclise",
      "SNG aberta",
      "tratamento de infecção urinaria"
    ],
    "Abreviação": [
      "AVP",
      "MSD",
      "SNG aberta",
      "RHA diminuídos"
    ],
    "Localização ou Região Corporal": [
      "MSD",
      "abdomen"
    ],
    "Negação": [
      "ausente",
      "sem",
      "Nega"
    ],
    "Procedimento Diagnóstico": [
      "enema"
    ],
    "Sinal ou Sintoma": [
      "dor abdominal",
      "associada a vomitos",
      "estase gástrica biliosa",
      "doloroso a palpação",
      "RHA diminuídos",
      "alergia medicamentosa"
    ],
    "Conceito Quantitativo": [
      "300 ml"
    ],
    "Função Fisiológica": [
      "Diurese espontânea",
      "eliminação intestinal"
    ],
    "Doença ou Síndrome": [
      "tratamento de infecção urinaria",
      "DOENÇAS ESPECIFICADAS DO PANCREAS"
    ],
    "Atividade de Assistência à Saúde": [
      "avaliação medica"
    ]
  },
  "labels": {}
}