{
  "prontuario_id": 963,
  "text": "22h - Pós procedimento de embolização, pré cirúrgico de neurocirurgia, consciente, orientada, comunicativa, em repouso no leito, afebril, normoceálica, normocorada, pupilas isocórica, fotorreagentes com abertura ocular espontânea, mucosas íntegras e úmidas, em ar ambiente, tórax plano com simetria de expansibilidade, ausculta pulmonar com murmúrios vesiculares, ausculta cardíaca normofonética com bulhas regulares e rítmicas, abdômen globoso, flácido, indolor e flácido, RHA +, mantém AVP em MSE com soroterapia em curso, diurese presente em SVD em grande quantidade, permanece com CTVO compressivo em RID para retirar 18/01 às 14:30h. Enfermeiro Florence Nightingale Coren xxxx . NEOPLASIA DE COMPORTAMENTO INCERTO OU DESCONHECIDO DO ENCEFALO SUPRATENTORIAL",
  "entities": {
    "Grupo Profissional ou Ocupacional": [
      "neurocirurgia",
      "Enfermeiro"
    ],
    "Achado": [
      "consciente",
      "orientada",
      "comunicativa",
      "afebril",
      "normoceálica",
      "normocorada",
      "isocórica",
      "fotorreagentes",
      "íntegras",
      "úmidas",
      "plano",
      "normofonética",
      "rítmicas",
      "flácido",
      "repouso no leito",
      "abertura ocular espontânea",
      "simetria de expansibilidade",
      "murmúrios vesiculares",
      "bulhas regulares",
      "RHA +",
      "diurese presente",
      "grande quantidade"
    ],
    "Negação": [
      "afebril",
      "indolor"
    ],
    "Parte do Corpo, Órgão ou Componente Orgânico": [
      "pupilas",
      "mucosas",
      "ENCEFALO SUPRATENTORIAL"
    ],
    "Localização ou Região Corporal": [
      "tórax",
      "abdômen",
      "MSE"
    ],
    "Sinal ou Sintoma": [
      "globoso"
    ],
    "Abreviação": [
      "MSE",
      "SVD",
      "RID",
      "RHA +",
      "mantém AVP",
      "CTVO compressivo"
    ],
    "Dispositivo Médico": [
      "SVD",
      "mantém AVP",
      "CTVO compressivo"
    ],
    "Procedimento Terapêutico ou Preventivo": [
      "SVD",
      "Pós procedimento",
      "repouso no leito",
      "mantém AVP",
      "soroterapia em curso",
      "CTVO compressivo"
    ],
    "Processo Neoplásico": [
      "NEOPLASIA"
    ],
    "Conceito Temporal": [
      "Pós procedimento",
      "pré cirúrgico"
    ],
    "Procedimento Diagnóstico": [
      "ausculta pulmonar",
      "ausculta cardíaca"
    ],
    "Função Fisiológica": [
      "diurese presente"
    ],
    "Conceito Qualitativo": [
      "grande quantidade"
    ]
  },
  "labels": {}
}