{
  "prontuario_id": 897,
  "text": "Pcte com RNM de crânio agendada para hoje às 23:00h. Por volta das 21:00h pcte apresentou quadro de confusão mental , seguida de crise convulsiva generalizada , prontamente atendido na sala de poli , com MCC + oximetria digital de pulso + PNI contínuos . Instalado O2 , medicado CPM e  mantido em observação no leito . Hidantalizado pela R1 Vital Brasil da neurocirurgia , procedimento realizado sem intercorrências . Pcte bastante sonolento , mantido em sala de poli e suspenso RNM por hora . Diurese espontânea , com controle através de uropen . SSVV às 05:45h PA = 133/74mmhg , FC = 114bpm, SpO2 = 93% .  Conforme orientação da neurocirurgia , mantém observação na sala de poli sob cuidados intensivos de enfermagem .  Florence Nightingale Coren xxxx  CHOQUE NAO ESPECIFICADO",
  "entities": {
    "Paciente ou Grupo com Deficiência": [
      "Pcte",
      "pcte"
    ],
    "Abreviação": [
      "Pcte",
      "pcte",
      "MCC",
      "CPM",
      "R1",
      "RNM",
      "SSVV",
      "PA",
      "FC",
      "SpO2",
      "RNM de crânio",
      "sala de poli",
      "PNI contínuos"
    ],
    "Procedimento Diagnóstico": [
      "MCC",
      "RNM",
      "RNM de crânio",
      "oximetria digital de pulso",
      "PNI contínuos"
    ],
    "Procedimento Terapêutico ou Preventivo": [
      "medicado",
      "Hidantalizado",
      "procedimento",
      "Instalado O2"
    ],
    "Atividade de Assistência à Saúde": [
      "medicado",
      "suspenso",
      "orientação",
      "observação no leito",
      "cuidados intensivos de enfermagem"
    ],
    "Grupo Profissional ou Ocupacional": [
      "R1",
      "neurocirurgia"
    ],
    "Organização Relacionada à Saúde": [
      "neurocirurgia",
      "sala de poli"
    ],
    "Negação": [
      "sem"
    ],
    "Sinal ou Sintoma": [
      "intercorrências",
      "confusão mental",
      "crise convulsiva generalizada",
      "bastante sonolento"
    ],
    "Dispositivo Médico": [
      "uropen"
    ],
    "Atributo Clínico": [
      "SSVV",
      "PA",
      "FC",
      "SpO2"
    ],
    "Conceito Quantitativo": [
      "133/74mmhg",
      "114bpm",
      "93%"
    ],
    "Doença ou Síndrome": [
      "CHOQUE"
    ],
    "Achado": [
      "Diurese espontânea"
    ],
    "Função Fisiológica": [
      "Diurese espontânea"
    ]
  },
  "labels": {}
}