{
  "prontuario_id": 899,
  "text": "# LUCAS, 78 ANOS. SEGUNDA CONSULTA. RETORNO COM EXAMES.  # REFERE INCONTINENCIA URINARIA AOS ESFORÇOS. NEGA DEMAIS QUEIXAS URINARIAS.  # HAS HA 20 ANOS, DM HA 20 ANOS, DSLP. HISTERECTOMIZADA AOS 45 ANOS, RETIROU OVARIO DIR AOS 19 ANOS. G 1 C 1 A 0. NEGA ALERGIA A MEDICAMENTOS.  # AAS 100 MG; LEVOTIROXINA 25MCG; METFORMINA 850MG 1 CP; OMEPRAZOL 20MG 1 CP; LOSARTANA 50MG 12/12; BEZAFIBRATO 200MG; PREMARIN 0,3MG; CITRATO DE CALCIO 600MG; COLECALCIFEROL. # MAE FALECEU AOS 54 POR IAM, PAI FACELEU DE CA PROSTATA AOS 74 ANOS.  # LAB: CREAT 1,4; U 68; CKD-EPI 35,9; GLICEMIA 128; K 5,2; URINA LEVEMENTE TURVA, PH 7, LEUC 29; GASO VEN: PH 7,36; PCO2 52,60; HCO3 29.  # BEG, LOTE, NORMOCORADA, HIDRATADA. PULMONAR SP. CARDIACO SP. MMII: VARIZES BILAT MAIS PRONUNCIADAS EM MIE. PA 130/80, FC 72.  # PEÇO US DE RINS E VIAS URINARIAS, PEÇO LAB, RETORNO EM 6 MESES.",
  "entities": {
    "Atividade de Assistência à Saúde": [
      "CONSULTA",
      "RETORNO"
    ],
    "Procedimento Diagnóstico": [
      "EXAMES",
      "US DE RINS E VIAS URINARIAS"
    ],
    "Negação": [
      "NEGA",
      "SP"
    ],
    "Abreviação": [
      "HAS",
      "DM",
      "DSLP",
      "G",
      "C",
      "A",
      "AAS",
      "CP",
      "IAM",
      "LAB",
      "BEG",
      "LOTE",
      "SP",
      "MMII",
      "MIE",
      "PA",
      "FC",
      "RETIROU OVARIO DIR",
      "CA PROSTATA",
      "CREAT 1 , 4",
      "U 68",
      "CKD-EPI 35 , 9",
      "K 5 , 2",
      "PH 7",
      "LEUC 29",
      "GASO VEN",
      "PCO2 52 , 60",
      "HCO3 29",
      "VARIZES BILAT",
      "US DE RINS E VIAS URINARIAS"
    ],
    "Doença ou Síndrome": [
      "HAS",
      "DM",
      "DSLP",
      "IAM",
      "INCONTINENCIA URINARIA AOS ESFORÇOS",
      "ALERGIA A MEDICAMENTOS",
      "VARIZES BILAT"
    ],
    "Atributo Clínico": [
      "G",
      "C",
      "A",
      "PULMONAR",
      "CARDIACO",
      "PA",
      "FC"
    ],
    "Conceito Quantitativo": [
      "1",
      "0",
      "25MCG",
      "200MG",
      "600MG",
      "130/80",
      "72",
      "100 MG",
      "0 , 3MG"
    ],
    "Procedimento Terapêutico ou Preventivo": [
      "C",
      "RETIROU OVARIO DIR"
    ],
    "Substância Química Orgânica": [
      "AAS",
      "LEVOTIROXINA",
      "METFORMINA",
      "OMEPRAZOL",
      "LOSARTANA",
      "BEZAFIBRATO",
      "PREMARIN",
      "COLECALCIFEROL",
      "CITRATO DE CALCIO"
    ],
    "Substância Farmacológica": [
      "AAS",
      "LEVOTIROXINA",
      "METFORMINA",
      "OMEPRAZOL",
      "LOSARTANA",
      "BEZAFIBRATO",
      "PREMARIN",
      "COLECALCIFEROL",
      "CITRATO DE CALCIO"
    ],
    "Conceito Temporal": [
      "12/12"
    ],
    "Vitamina": [
      "COLECALCIFEROL"
    ],
    "Grupo Familiar": [
      "MAE",
      "PAI"
    ],
    "Achado": [
      "FALECEU",
      "FACELEU",
      "BEG",
      "LOTE",
      "NORMOCORADA",
      "HIDRATADA",
      "SP",
      "HISTERECTOMIZADA AOS 45 ANOS",
      "RETIROU OVARIO DIR"
    ],
    "Localização ou Região Corporal": [
      "CARDIACO",
      "MMII",
      "MIE"
    ],
    "Sinal ou Sintoma": [
      "QUEIXAS URINARIAS"
    ],
    "Processo Neoplásico": [
      "CA PROSTATA"
    ],
    "Resultado Laboratorial ou de Teste": [
      "CREAT 1 , 4",
      "U 68",
      "CKD-EPI 35 , 9",
      "GLICEMIA 128",
      "K 5 , 2",
      "URINA LEVEMENTE TURVA",
      "PH 7",
      "LEUC 29",
      "PH 7 , 36",
      "PCO2 52 , 60",
      "HCO3 29"
    ],
    "Procedimento Laboratorial": [
      "GASO VEN"
    ],
    "Conceito Qualitativo": [
      "MAIS PRONUNCIADAS"
    ]
  },
  "labels": {}
}