{
  "prontuario_id": 418,
  "text": "LUCAS, 65 ANOS.  # COMORBIDADES: - HÉRNIA INGUINAL BILATERAL (CANCELADA CIRURGIA AGENDA POR HIPERTENSÃO DESCONTROLADA) - HAS,  - HPB, - COLECISTECTOMIA HÁ ANOS - NEGA ETILISMO / TABAGISMO - MUC: ATENOLOL 25MG 12/12 H; LOSARTANA 50MG 12/12 H; DOXAZOSINA 2MG /D  # S PACIENTE VEM PARA VERIFICAR CONTROLE DA PA + MOSTRAR LABORATORIAIS COLETADOS.  # O : BEG. PA BRAÇO DIREITO 180x100 / PA BRAÇO ESQ 170x90, FC 56, ACV RR 2T BNF, AP MVUD.  -> LABORATORIAIS 14/06: Cr 1,26 -> TFG CKD-EPI 59,5 ML/MIN, U 40;   Na 147; K 5,0; Glicemia de jejum 146  (glicemia de jejum prévia 05/2016: 140).  # A HAS SEM CONTROLE ADEQUADO, DM TIPO 2 SEM DX PRÉVIO.  # CD: INICIO METFORMINA 500MG 2 X/DIA, OTIMIZO TRATAMENTO ANTI-HAS: ACRESCENTO HIDROCLOROTIAZIDA 25MG /D, SOLICITO HBA1C. RETORNO EM 2 MESES.  R1D FLORENCE DR VITAL BRASIL.",
  "entities": {
    "Negação": [
      "CANCELADA",
      "NEGA",
      "SEM"
    ],
    "Procedimento Terapêutico ou Preventivo": [
      "CIRURGIA",
      "COLECISTECTOMIA"
    ],
    "Abreviação": [
      "HAS",
      "HPB",
      "MUC",
      "S",
      "O",
      "BEG",
      "PA",
      "FC",
      "ACV",
      "AP",
      "MVUD",
      "CD",
      "ANTI-HAS",
      "HBA1C",
      "BRAÇO ESQ",
      "RR 2T BNF",
      "Cr 1 , 26",
      "U 40",
      "Na 147",
      "K 5 , 0",
      "DM TIPO 2"
    ],
    "Doença ou Síndrome": [
      "HAS",
      "HPB",
      "ETILISMO",
      "TABAGISMO",
      "DM TIPO 2"
    ],
    "Substância Farmacológica": [
      "MUC",
      "ATENOLOL",
      "LOSARTANA",
      "DOXAZOSINA",
      "METFORMINA",
      "ANTI-HAS",
      "HIDROCLOROTIAZIDA"
    ],
    "Substância Química Orgânica": [
      "ATENOLOL",
      "LOSARTANA",
      "DOXAZOSINA",
      "METFORMINA",
      "HIDROCLOROTIAZIDA"
    ],
    "Achado": [
      "S",
      "BEG",
      "MVUD",
      "MOSTRAR LABORATORIAIS COLETADOS",
      "RR 2T BNF",
      "CONTROLE ADEQUADO"
    ],
    "Paciente ou Grupo com Deficiência": [
      "PACIENTE"
    ],
    "Atividade de Assistência à Saúde": [
      "VERIFICAR",
      "RETORNO"
    ],
    "Atributo Clínico": [
      "PA",
      "FC"
    ],
    "Função de Organismo": [
      "PA"
    ],
    "Conceito Quantitativo": [
      "180x100",
      "170x90",
      "56",
      "2 X/DIA",
      "25MG /D"
    ],
    "Parte do Corpo, Órgão ou Componente Orgânico": [
      "ACV",
      "AP",
      "BRAÇO DIREITO",
      "BRAÇO ESQ"
    ],
    "Procedimento Laboratorial": [
      "LABORATORIAIS",
      "HBA1C",
      "glicemia de jejum prévia"
    ],
    "Procedimento Diagnóstico": [
      "DX"
    ],
    "Sinal ou Sintoma": [
      "HIPERTENSÃO DESCONTROLADA"
    ],
    "Conceito Temporal": [
      "12/12 H"
    ],
    "Resultado Laboratorial ou de Teste": [
      "Cr 1 , 26",
      "TFG CKD-EPI 59 , 5 ML/MIN",
      "U 40",
      "Na 147",
      "K 5 , 0",
      "Glicemia de jejum 146",
      "glicemia de jejum prévia"
    ]
  },
  "labels": {}
}