{
  "prontuario_id": 865,
  "text": "AVALIAÇÃO NEFRO GERAL. IRC - CR 1,5 / CKD 58 PROTEINURIA 3152MG / 24H - PRÉVIO SÓ COM MICROALBUMINURIA - GESF SECUNDARIA ? IGA ? TEM HEMATURIA HAS NAO COMPENSADA HIPERCALEMIA. ROBERTO, 57 ANOS  # HAS HÁ 10 ANOS # IRC - CR 1,5 # TABAGISTA - 40 ANOS - MAÇO # LOMBALGIA   TROUXA LAB : 2012 - CR 1,7 / 2014 - 1,8 MICROALBUMINURIA 2014  717,21 TE NEGATIVO  EXAMES DE AGORA - AGO/2015 US - RIM DIREITO DIMINUIDO (8,1X4  , 8X4,5), RIM E 9,1X4,8X4,5 US ABDOMEN - PLACAS ATEROMATOSAS EM AORTA ECOCARDIO - NORMAL ( AE 31 / SEPTO 1,0, FE 0,69) CR 1,5, K 5,7 GLICOSE 110 CALCIO 10,4 ALB 4,1 PU  D 1020, PROT 1000, LEUC 7000/HEM 92000  - PROTEINURIA 24H - 3152MG  HB 17,4 ELETROFORESE SEM PICO GAMA GLOBULINA PSA 5,12  AO EXAME : PA 150/100 MV POSITIVO, SIMETRICO BCRNF ABDOMEN FLACIDO, SEM MASSAS, RHA POSITIVOS MEMBROS SEM EDEMA",
  "entities": {
    "Atividade de Assistência à Saúde": [
      "AVALIAÇÃO"
    ],
    "Abreviação": [
      "IRC",
      "IGA",
      "HAS",
      "LAB",
      "TE",
      "US",
      "ECOCARDIO",
      "PU",
      "PA",
      "BCRNF",
      "NEFRO GERAL",
      "CR 1 , 5",
      "GESF SECUNDARIA",
      "HAS NAO COMPENSADA",
      "CR 1 , 7",
      "AE 31",
      "FE 0 , 69",
      "K 5 , 7",
      "ALB 4 , 1",
      "PROT 1000",
      "HB 17 , 4",
      "MV POSITIVO",
      "RHA POSITIVOS"
    ],
    "Doença ou Síndrome": [
      "IRC",
      "MICROALBUMINURIA",
      "HAS",
      "TABAGISTA",
      "GESF SECUNDARIA",
      "HAS NAO COMPENSADA"
    ],
    "Conceito Temporal": [
      "PRÉVIO",
      "AGORA",
      "HÁ 10 ANOS"
    ],
    "Procedimento Laboratorial": [
      "MICROALBUMINURIA",
      "LAB",
      "EXAMES"
    ],
    "Sinal ou Sintoma": [
      "HEMATURIA",
      "HIPERCALEMIA",
      "LOMBALGIA",
      "MASSAS",
      "EDEMA"
    ],
    "Disfunção Mental ou Comportamental": [
      "TABAGISTA"
    ],
    "Procedimento Diagnóstico": [
      "TE",
      "EXAMES",
      "US",
      "ECOCARDIO",
      "EXAME"
    ],
    "Conceito Quantitativo": [
      "DIMINUIDO",
      "150/100",
      "40 ANOS - MAÇO",
      "717 , 21"
    ],
    "Achado": [
      "NORMAL",
      "SIMETRICO",
      "BCRNF",
      "FLACIDO",
      "MV POSITIVO",
      "RHA POSITIVOS"
    ],
    "Atributo Clínico": [
      "PA"
    ],
    "Localização ou Região Corporal": [
      "ABDOMEN",
      "MEMBROS"
    ],
    "Negação": [
      "SEM"
    ],
    "Grupo Profissional ou Ocupacional": [
      "NEFRO GERAL"
    ],
    "Resultado Laboratorial ou de Teste": [
      "CR 1 , 5",
      "CKD 58",
      "PROTEINURIA 3152MG / 24H",
      "CR 1 , 7",
      "RIM E 9 , 1X4 , 8X4 , 5",
      "PLACAS ATEROMATOSAS EM AORTA",
      "AE 31",
      "SEPTO 1 , 0",
      "FE 0 , 69",
      "K 5 , 7",
      "GLICOSE 110",
      "CALCIO 10 , 4",
      "ALB 4 , 1",
      "PROT 1000",
      "LEUC 7000/HEM 92000",
      "PROTEINURIA 24H - 3152MG",
      "HB 17 , 4",
      "ELETROFORESE SEM PICO GAMA GLOBULINA",
      "PSA 5 , 12"
    ],
    "Grupo Etário": [
      "57 ANOS"
    ],
    "Parte do Corpo, Órgão ou Componente Orgânico": [
      "RIM DIREITO"
    ]
  },
  "labels": {}
}