{
  "prontuario_id": 637,
  "text": "Paciente retorna com exames de controle.   Refere ITU crônica há 1 ano ( 5 episódios no último ano ). Refere estar com disúria e ardência no momento. Nega febre, refere dor em região lombar bilateralmente.  Exames: Parcial de urina com 150mg/dL de proteínas, pH de 5,0, 1034 leucócitos e 7578 cel bacterianas/uL. Cultura de urina com E. Coli superior a 100.000 UFC/ml. Antibiograma resistente a Ciprofloxacino, Nitrofurantoina, Bactrim, Ac. Nalidixico e Ampicilina. Sensivel a Clavulin, Cefalotina, Cefuroxima, Ceftriaxona, Cefepime, Ertapenem, Meropenem, Amicacina e Gentamicina. Proteinúria de 24h : 150. Microalbuminuria : 40,9 mg/dL. Creatinina urinária : 41,8 mg/dL Relaçao albumina / creatinina na urina : 978,47 Colonoscopia : Diverticulose acentuada de cólon sigmoide. Uretrocistografia miccional : Residuo pos miccional significativo, fratura de ramo isquiopubico. HbA1C: 6,5% Ác. Urico: 5 mg/dL Cálcio: 8,13 mg/dL Potássio: 5,9 mEq/L Creatinina: 1,1 mg/dL Sódio: 134 mEq/L Ureia: 64 mg/dL Fosforo sérico: 5,28 mg/dL PTH : 46,4 pg/mL USG abdominal: Dilatação de ducto hepatocoledoco e de forma discreta da arvore biliar intrahepatica. Rins com morfologia, topografia, dimensões e ecotextura preservadas. Sem cálculos, crescimentos expansivos ou sinais de uropatia obstrutiva. Paciente portadora de DM2 há 10 anos. Portadora de HAS há 20 anos. Portadora de Hipotireoidismo. Em uso de: Gliclazida 30mg 1x ao dia, Metformina 850mg 2x ao dia, Omeprazol 20 mg, Levotiroxina 50 mcg  1x ao dia, Valsartana 80 mg, AAS 100 mg, Atenolol 50 mg 2x ao dia, Rosivastatina 20 mg.",
  "entities": {
    "Paciente ou Grupo com Deficiência": [
      "Paciente"
    ],
    "Sinal ou Sintoma": [
      "disúria",
      "ardência",
      "febre",
      "dor"
    ],
    "Negação": [
      "Nega"
    ],
    "Procedimento Laboratorial": [
      "Exames",
      "Antibiograma",
      "exames de controle",
      "Parcial de urina",
      "Cultura de urina"
    ],
    "Antibiótico": [
      "Ciprofloxacino",
      "Nitrofurantoina",
      "Bactrim",
      "Ampicilina",
      "Clavulin",
      "Cefalotina",
      "Cefuroxima",
      "Ceftriaxona",
      "Cefepime",
      "Ertapenem",
      "Meropenem",
      "Amicacina",
      "Gentamicina"
    ],
    "Substância Química Orgânica": [
      "Ciprofloxacino",
      "Nitrofurantoina",
      "Bactrim",
      "Ampicilina",
      "Clavulin",
      "Cefalotina",
      "Cefuroxima",
      "Ceftriaxona",
      "Cefepime",
      "Ertapenem",
      "Meropenem",
      "Amicacina",
      "Gentamicina",
      "Metformina",
      "Valsartana",
      "Rosivastatina"
    ],
    "Procedimento Diagnóstico": [
      "Colonoscopia",
      "Uretrocistografia miccional",
      "USG abdominal"
    ],
    "Doença ou Síndrome": [
      "Diverticulose",
      "DM2",
      "HAS",
      "Hipotireoidismo",
      "ITU crônica"
    ],
    "Conceito Quantitativo": [
      "acentuada",
      "2x ao dia",
      "20 mg",
      "80 mg",
      "100 mg",
      "50 mg"
    ],
    "Abreviação": [
      "DM2",
      "HAS",
      "AAS",
      "ITU crônica",
      "USG abdominal"
    ],
    "Substância Farmacológica": [
      "Gliclazida",
      "Metformina",
      "Omeprazol",
      "Levotiroxina",
      "Valsartana",
      "AAS",
      "Atenolol",
      "Rosivastatina"
    ],
    "Aminoácido, Peptídeo ou Proteína": [
      "Levotiroxina"
    ],
    "Hormônio": [
      "Levotiroxina"
    ],
    "Localização ou Região Corporal": [
      "região lombar bilateralmente"
    ],
    "Resultado Laboratorial ou de Teste": [
      "150mg/dL de proteínas",
      "pH de 5 , 0",
      "1034 leucócitos",
      "7578 cel bacterianas/uL",
      "Proteinúria de 24h : 150",
      "Microalbuminuria : 40 , 9 mg/dL",
      "Creatinina urinária : 41 , 8 mg/dL",
      "albumina / creatinina na urina : 978 , 47",
      "Residuo pos miccional significativo",
      "fratura de ramo isquiopubico",
      "HbA1C : 6 , 5%",
      "Cálcio : 8 , 13 mg/dL",
      "Potássio : 5 , 9 mEq/L",
      "Creatinina : 1 , 1 mg/dL",
      "Sódio : 134 mEq/L",
      "Ureia : 64 mg/dL",
      "Fosforo sérico : 5 , 28 mg/dL",
      "PTH : 46 , 4 pg/mL",
      "Dilatação de ducto hepatocoledoco",
      "forma discreta da arvore biliar intrahepatica",
      "Rins com morfologia , topografia , dimensões e ecotextura preservadas",
      "Sem cálculos , crescimentos expansivos ou sinais de uropatia obstrutiva"
    ],
    "Lesão ou Envenenamento": [
      "fratura de ramo isquiopubico"
    ]
  },
  "labels": {}
}