{
  "prontuario_id": 14,
  "text": "LUCAS , 55 ANOS, RETORNO PARA AVALIAÇÃO DE EXAMES  EM ACOMPANHAMENTO POR DM 2, EM USO METFORMINA 850 MG 2 CP AO DIA  DISLIPIDEMICO EM USO DE ROVASTATINA 10 MG, FIBRATO 100 MG HIPERTENSO EM USO DE LOSARTANA 100 MG, ENALAPRIL 25 MG, AAS 100 MG ( AUTO MEDICAÇÃO ) GOTA EM USO DE ALOPURINOL 300 MG NEGA INTERNAMENTOS ANTERIORES, MAS RELATA DOIS EPISODIOS ALERGICOS DE FORTE INTENSIDADE COM EDEMA DE GLOTE   NEGA CXS  HMP : PAIS FALECIDOS PO CA ( NAO SOUBE ESPECIFICAR ) E IRMA POR CA DE BAÇO FILHOS SAUDAVEIS, O MAIS VELHO ALERGICO   EXAMES : 17/10/2014  HMG  HB 15 HT 45,2 LEUCOCITOS 7800 PLAQUETAS 248000  CR 1,1 CKD EPI 84 UREIA 37 ACIDO URICO 5,6  HDL 45 CT 213 TG 407 LDL  CALCULO SBC 86,6  GLICOSE 83  HB GLICADA 6,09% INSULINA BASAL 3,2 M UI/ML  GAMA GT 43  CPK 170  U/L  SINAIS VITAIS  PA 110/ 80 PULSO 80   AUSCULTA PULMONAR SP AUSCULTA CARDIACA DESDOBRAMENTO DE B2 CAROTIDAS AUSCULTA SEM ANORMALIDADES    CONDUTA: MANTIDOS TODAS AS MEDICAÇOES",
  "entities": {
    "Atividade de Assistência à Saúde": [
      "RETORNO",
      "ACOMPANHAMENTO",
      "INTERNAMENTOS",
      "PO",
      "MANTIDOS",
      "AVALIAÇÃO DE EXAMES"
    ],
    "Substância Química Orgânica": [
      "METFORMINA",
      "ROVASTATINA",
      "FIBRATO",
      "AAS",
      "ALOPURINOL"
    ],
    "Substância Farmacológica": [
      "METFORMINA",
      "ROVASTATINA",
      "FIBRATO",
      "LOSARTANA",
      "ENALAPRIL",
      "AAS",
      "ALOPURINOL",
      "ALERGICO",
      "MEDICAÇOES"
    ],
    "Abreviação": [
      "CP",
      "AAS",
      "CXS",
      "HMP",
      "PO",
      "CA",
      "HMG",
      "PA",
      "SP",
      "DM 2",
      "CA DE BAÇO",
      "HB 15",
      "HT 45 , 2",
      "CR 1 , 1",
      "CT 213",
      "TG 407",
      "HB GLICADA 6 , 09%"
    ],
    "Doença ou Síndrome": [
      "DISLIPIDEMICO",
      "HIPERTENSO",
      "GOTA",
      "CA",
      "DM 2"
    ],
    "Aminoácido, Peptídeo ou Proteína": [
      "ENALAPRIL"
    ],
    "Negação": [
      "NEGA",
      "NAO",
      "SP",
      "SEM"
    ],
    "Conceito Temporal": [
      "ANTERIORES",
      "PO"
    ],
    "Procedimento Terapêutico ou Preventivo": [
      "CXS",
      "MEDICAÇOES"
    ],
    "Achado": [
      "HMP",
      "FALECIDOS",
      "SAUDAVEIS",
      "SP"
    ],
    "Grupo Familiar": [
      "PAIS",
      "IRMA",
      "FILHOS"
    ],
    "Procedimento Laboratorial": [
      "EXAMES"
    ],
    "Procedimento Diagnóstico": [
      "HMG",
      "AUSCULTA PULMONAR",
      "AUSCULTA CARDIACA",
      "CAROTIDAS AUSCULTA"
    ],
    "Atributo Clínico": [
      "PA",
      "PULSO",
      "SINAIS VITAIS",
      "AUSCULTA PULMONAR",
      "AUSCULTA CARDIACA"
    ],
    "Conceito Quantitativo": [
      "80",
      "850 MG",
      "10 MG",
      "100 MG",
      "25 MG",
      "300 MG",
      "110/ 80"
    ],
    "Sinal ou Sintoma": [
      "ANORMALIDADES",
      "AUTO MEDICAÇÃO",
      "EPISODIOS ALERGICOS DE FORTE INTENSIDADE",
      "EDEMA DE GLOTE",
      "DESDOBRAMENTO DE B2"
    ],
    "Produto Intelectual": [
      "CONDUTA"
    ],
    "Comportamento Individual": [
      "AUTO MEDICAÇÃO"
    ],
    "Função Patológica": [
      "EPISODIOS ALERGICOS DE FORTE INTENSIDADE"
    ],
    "Processo Neoplásico": [
      "CA DE BAÇO"
    ],
    "Resultado Laboratorial ou de Teste": [
      "HB 15",
      "HT 45 , 2",
      "LEUCOCITOS 7800",
      "PLAQUETAS 248000",
      "CR 1 , 1",
      "CKD EPI 84",
      "UREIA 37",
      "ACIDO URICO 5 , 6",
      "HDL 45",
      "CT 213",
      "TG 407",
      "LDL CALCULO SBC 86 , 6",
      "GLICOSE 83",
      "HB GLICADA 6 , 09%",
      "INSULINA BASAL 3 , 2 M UI/ML",
      "GAMA GT 43",
      "CPK 170 U/L"
    ]
  },
  "labels": {}
}