{
  "prontuario_id": 152,
  "text": "Lucas , 63 anos.  QP : retorno para mostragem de exames.  HMA : DM2 diagnosticado há 6 anos. Em uso de metformina 850mg 3x ao dia; glicazida 30mg ( 1 comprimido pela manha ); e insulina NPH 10U a noite. Controle glicêmico com glicemia em jejum abaixo de 100 ( não costuma anotar ). Refere poliúria e nictúria (4 - 5x) há 6 meses; nega polidipsia. Nega outros sintomas. Interrompeu caminhada por quadros de dispneia (Novembro) - antes caminhada 30min por dia. Má - aderência a dieta.   HMP : HAS tratado (em uso de nifedipino 30mg 1 cp por dia; losartana 50mg 1 cp de 8/8h; ticagrelor 90mg 1 cp 12/12h); ICC ( carvedilol 6,25mg 1 cp 12/12h ). IAM ( 2 episodios - 2009 e 2012 - em uso de AAS 100mg 1 cp apos o almoço ). Cirurgia RVM (2009), angioplastia (2012), marcapasso (2012).  CHV : ex-tabagista (60 maços / anos - parou há 12 anos); etilista ocasional (finais de semana - cerca de 2 cervejas); nega drogadição.  RS : sem outras queixas.  EXAMES (03/02/2015) TSH 3.78 Glicose 120 HbA1C : 6.1% Acido urico 8.7 TG : 309 CT : 185 LDL : 86 HDL : 37 K : 4.1 Relação creatinina / albumina : 27mg/g",
  "entities": {
    "Atividade de Assistência à Saúde": [
      "retorno",
      "diagnosticado",
      "anotar",
      "tratado"
    ],
    "Procedimento Diagnóstico": [
      "exames"
    ],
    "Resultado Laboratorial ou de Teste": [
      "exames",
      "EXAMES",
      "abaixo de 100",
      "TSH 3",
      "Glicose 120",
      "HbA1C : 6",
      "Acido urico 8",
      "TG : 309",
      "CT : 185",
      "LDL : 86",
      "HDL : 37",
      "K : 4",
      "Relação creatinina / albumina : 27mg/g"
    ],
    "Procedimento Laboratorial": [
      "exames",
      "EXAMES",
      "Controle glicêmico",
      "glicemia em jejum"
    ],
    "Abreviação": [
      "DM2",
      "NPH",
      "HAS",
      "ICC",
      "IAM",
      "AAS",
      "RVM",
      "CHV",
      "3x ao dia",
      "4 - 5x",
      "1 cp",
      "TG : 309",
      "CT : 185"
    ],
    "Doença ou Síndrome": [
      "DM2",
      "HAS",
      "ICC",
      "IAM"
    ],
    "Substância Química Orgânica": [
      "metformina",
      "insulina",
      "nifedipino",
      "losartana",
      "carvedilol",
      "AAS"
    ],
    "Substância Farmacológica": [
      "metformina",
      "glicazida",
      "nifedipino",
      "losartana",
      "ticagrelor",
      "carvedilol",
      "AAS"
    ],
    "Conceito Quantitativo": [
      "30mg",
      "30min",
      "3x ao dia",
      "1 comprimido",
      "4 - 5x",
      "1 cp",
      "6 , 25mg",
      "60 maços / anos"
    ],
    "Conceito Temporal": [
      "manha",
      "noite",
      "antes",
      "8/8h",
      "12/12h",
      "episodios",
      "apos",
      "6 meses",
      "finais de semana"
    ],
    "Negação": [
      "não",
      "nega",
      "Nega",
      "sem"
    ],
    "Sinal ou Sintoma": [
      "poliúria",
      "nictúria",
      "polidipsia",
      "sintomas",
      "dispneia",
      "queixas",
      "Má - aderência a dieta",
      "etilista ocasional"
    ],
    "Atividade Diária ou Recreativa": [
      "caminhada"
    ],
    "Ácido Nucleico, Nucleosídeo ou Nucleotídeo": [
      "ticagrelor"
    ],
    "Procedimento Terapêutico ou Preventivo": [
      "Cirurgia",
      "RVM",
      "angioplastia",
      "marcapasso"
    ],
    "Dispositivo Médico": [
      "marcapasso"
    ],
    "Achado": [
      "CHV",
      "ex-tabagista"
    ],
    "Disfunção Mental ou Comportamental": [
      "drogadição"
    ]
  },
  "labels": {}
}