{
  "prontuario_id": 104,
  "text": "DRC ESTAGIO 5\nFALENCIA ENXERTO RENAL POR TROMBOSE ENXERTO RENAL\nASMA COM USO DE ALENIA, JÁ INTERNADA EM CRISE DE BRONCOESPASMO PÓS HD E EM USO DE ALENIA\nS : AVALIAÇÃO PSICO: PENDENTE\nAVALIAÇÃO PNEUMO: PENDENTE\nPARECER DA VASCULAR E/OU NEFROLOGISTA SOBRE DIFICULDADE DE ACESSO VASCULAR: PENDENTE\n* RELATA USO DE CDL E PERMCATH S/E COM INFECÇÃO E PERDA\n* FAV CONFECCIONADAS E SEM FUNÇÃO INICIAL\n* FAV PROFUNDA, DE DIFICIL PUNÇÃO COM INFILTRAÇÃO PREVIA E IMPOSSIBILIDADE DE SUPERFICIALIZAÇÃO. INTERCORRENCIAS COM INFILTRAÇÃO E DOR, JÁ COM AVALIAÇÃO NO SERVIÇO DE NEFROLOGIA INTERVENCIONISTA E ORIENTAÇÃO SOBRE \" ULTIMO ACESSO VIÁVEL\" SEGUNDO A PACIENTE\nDRC ESTAGIO 5\nFALENCIA ENXERTO RENAL POR TROMBOSE ENXERTO RENAL\nASMA COM USO DE ALENIA, JÁ INTERNADA EM CRISE DE BRONCOESPASMO PÓS HD E EM USO DE ALENIA\nS : AVALIAÇÃO PSICO: PENDENTE\nAVALIAÇÃO PNEUMO: PENDENTE\nPARECER DA VASCULAR E/OU NEFROLOGISTA SOBRE DI\n \n \n ",
  "entities": {
    "Doença ou Síndrome": [
      "ASMA",
      "DRC ESTAGIO 5",
      "TROMBOSE ENXERTO RENAL"
    ],
    "Substância Farmacológica": [
      "ALENIA",
      "CDL"
    ],
    "Atividade de Assistência à Saúde": [
      "INTERNADA",
      "AVALIAÇÃO",
      "ORIENTAÇÃO",
      "PARECER",
      "AVALIAÇÃO PSICO",
      "AVALIAÇÃO PNEUMO",
      "PENDENTE PARECER"
    ],
    "Procedimento Terapêutico ou Preventivo": [
      "HD",
      "FAV CONFECCIONADAS"
    ],
    "Achado": [
      "PENDENTE",
      "DIFICULDADE DE ACESSO VASCULAR",
      "DIFICIL PUNÇÃO",
      "ULTIMO ACESSO VIÁVEL\""
    ],
    "Grupo Profissional ou Ocupacional": [
      "VASCULAR",
      "NEFROLOGISTA"
    ],
    "Abreviação": [
      "CDL",
      "DRC ESTAGIO 5",
      "AVALIAÇÃO PSICO",
      "AVALIAÇÃO PNEUMO",
      "FAV CONFECCIONADAS",
      "FAV PROFUNDA"
    ],
    "Dispositivo Médico": [
      "PERMCATH"
    ],
    "Negação": [
      "SEM"
    ],
    "Sinal ou Sintoma": [
      "INFILTRAÇÃO",
      "INTERCORRENCIAS",
      "DOR",
      "FALENCIA ENXERTO RENAL",
      "CRISE DE BRONCOESPASMO",
      "FAV PROFUNDA",
      "IMPOSSIBILIDADE DE SUPERFICIALIZAÇÃO"
    ],
    "Paciente ou Grupo com Deficiência": [
      "PACIENTE"
    ],
    "Organização Relacionada à Saúde": [
      "SERVIÇO DE NEFROLOGIA INTERVENCIONISTA"
    ]
  },
  "labels": {}
}