{
  "prontuario_id": 71,
  "text": "# Lucas, 78 ANOS\n\n# FAC EM ANTICOAGULAÇÃO\n# MP DESDE 2002 ( HOSP CAJURU ) - EQUIPE Doutor Vital Brazil \n# HIPOTIREOIDISMO\n# NEGA IAM PRÉVIO\n# DEPRESSÃO\n# EX-ETILISTA\n# EX-TABAGISTA\n# NEGA ALERGIA A MEDICAMENTOS\n# EM USO DE: MAREVAN 5MG ( CONFORME TAP) E LEVOTIROXONA 50 MCG / DIA\n# US ABDOME (16/11): VESÍCULA BILIAR COM LAMA BILIAR E MICROCÁLCULOS\n# ECOCARDIOGRAMA TT (19/11):  FE 31% -\n# ECOCARDIOGRAMA TT (27/11/15): FEVE 28%\n# CATE (01/12): LESAO 80% TCE DISTAL , 40% CD\nS # INTERNAMENTO PRÉVIO POR PANCRETATITE BILIAR, PORÉM NÃO REALIZADA CX DEVIDO NECESSIDADE DA REALIZAÇÃO DE CAT, ENCAMINHADO DEVIDO NODULO PROSTATICO. REFERE URGE INCONTINENCIA URINÁRIA. JATO MICCIONAL FRACO\nO # TR: 60 G, FE, NODULO ÀS 5 HORAS\nA # HPB ? CA ?\nP # SOLICITO LAB E USG\n     PRESCREVO DOXAZOSINA 2MG\n     RETORNO COM EXAMES\n \n \n \n ",
  "entities": {
    "Doença ou Síndrome": [
      "FAC",
      "MP",
      "HIPOTIREOIDISMO",
      "IAM",
      "DEPRESSÃO",
      "HPB",
      "PANCRETATITE BILIAR"
    ],
    "Abreviação": [
      "FAC",
      "MP",
      "IAM",
      "CATE",
      "CX",
      "CAT",
      "TR",
      "FE",
      "HPB",
      "CA",
      "LAB",
      "USG",
      "US ABDOME",
      "ECOCARDIOGRAMA TT",
      "FE 31%",
      "FEVE 28%",
      "40% CD"
    ],
    "Função Patológica": [
      "FAC"
    ],
    "Procedimento Terapêutico ou Preventivo": [
      "ANTICOAGULAÇÃO",
      "CATE",
      "CX",
      "CAT"
    ],
    "Negação": [
      "NEGA",
      "NÃO"
    ],
    "Conceito Temporal": [
      "PRÉVIO"
    ],
    "Achado": [
      "EX-ETILISTA",
      "EX-TABAGISTA"
    ],
    "Sinal ou Sintoma": [
      "ALERGIA",
      "NODULO",
      "URGE INCONTINENCIA URINÁRIA",
      "JATO MICCIONAL FRACO"
    ],
    "Substância Farmacológica": [
      "MEDICAMENTOS",
      "MAREVAN",
      "LEVOTIROXONA",
      "DOXAZOSINA"
    ],
    "Conceito Quantitativo": [
      "5MG",
      "2MG",
      "50 MCG / DIA"
    ],
    "Procedimento Laboratorial": [
      "TAP",
      "LAB",
      "EXAMES"
    ],
    "Procedimento Diagnóstico": [
      "CATE",
      "CAT",
      "USG",
      "EXAMES",
      "US ABDOME",
      "ECOCARDIOGRAMA TT"
    ],
    "Atividade de Assistência à Saúde": [
      "INTERNAMENTO",
      "REALIZADA",
      "SOLICITO",
      "PRESCREVO"
    ],
    "Processo Neoplásico": [
      "NODULO",
      "HPB",
      "CA",
      "NODULO PROSTATICO"
    ],
    "Resultado Laboratorial ou de Teste": [
      "VESÍCULA BILIAR COM LAMA BILIAR",
      "FE 31%",
      "FEVE 28%",
      "LESAO 80% TCE DISTAL",
      "40% CD"
    ]
  },
  "labels": {}
}