{
  "prontuario_id": 121,
  "text": "Lucas, 62 ANOS\nCOMORBIDADES:\n# MCP DILATADA / CHAGAS\n# HAS\n# DISLIPIDEMIA\n# MARCA-PASSO HÁ 5 ANOS\n# DAC FAMILIAR\nCHV: EX-TABAGISTA DE 38 MAÇOS-ANO\nHMA: \n# PACIENTE COM ICC CLASSE FUNCIONAL II RETORNA COM RESULTADO DO CAT SOLICITADO NA ÚLTIMA CONSULTA; RELATA MELHORA DO EDEMA DESDE A ÚLTIMA CONSULTA/ \nCAT: DO DIA 29/07/2014: PROTOCOLO PRÉ - TRANSPLANTE CARDÍACO REALIZADO COM SUCESSO; RVP WOOD POSITIVA: CANDIDATO ATRANSPLANTE;\nMEDICAMENTOS:\n# ENALAPRIL 10 MG; 1/2 CP DE 12/12 HORAS\n# APRESOLINA 25 MG 1 CP DE 8/8 HORAS\n# MONOCORDL 20 MG 1 CP AS 8 E OUTRO AS 14 HORAS\n# ESPIRONOLACTONA 25 MG 1 CP AO DIA\n#  FUROSEMIDA 40 MG 1 CP AS 8 E OUTRO AS 14 HORAS\n#  CARVEDILOL 25 MG 1 CP DE 12/12 HORAS\n#  SINVASTATINA 20 MG 1 CP A NOITE\nCONDUTA: SOLICITADO INTERNAMENTO COM MONITORIZAÇÃO PARA REALIZAÇÃO DE TRANSPLANTE;\n \n \n \n ",
  "entities": {
    "Doença ou Síndrome": [
      "COMORBIDADES",
      "CHAGAS",
      "HAS",
      "DISLIPIDEMIA",
      "DAC",
      "MCP DILATADA",
      "ICC CLASSE FUNCIONAL II"
    ],
    "Abreviação": [
      "HAS",
      "DAC",
      "CHV",
      "HMA",
      "CAT",
      "MCP DILATADA",
      "ICC CLASSE FUNCIONAL II",
      "RVP WOOD POSITIVA",
      "1/2 CP",
      "1 CP"
    ],
    "Procedimento Terapêutico ou Preventivo": [
      "MARCA-PASSO",
      "CAT",
      "TRANSPLANTE CARDÍACO",
      "REALIZAÇÃO DE TRANSPLANTE"
    ],
    "Dispositivo Médico": [
      "MARCA-PASSO"
    ],
    "Grupo Familiar": [
      "FAMILIAR"
    ],
    "Achado": [
      "CHV",
      "EX-TABAGISTA",
      "HMA",
      "MELHORA",
      "SUCESSO"
    ],
    "Paciente ou Grupo com Deficiência": [
      "PACIENTE"
    ],
    "Resultado Laboratorial ou de Teste": [
      "RESULTADO"
    ],
    "Procedimento Diagnóstico": [
      "CAT",
      "MONITORIZAÇÃO"
    ],
    "Atividade de Assistência à Saúde": [
      "SOLICITADO",
      "CONSULTA",
      "CONSULTA/",
      "REALIZADO",
      "CONDUTA",
      "INTERNAMENTO"
    ],
    "Função Patológica": [
      "EDEMA"
    ],
    "Sinal ou Sintoma": [
      "EDEMA"
    ],
    "Conceito Temporal": [
      "PRÉ",
      "12/12 HORAS",
      "8/8 HORAS",
      "A NOITE"
    ],
    "Substância Farmacológica": [
      "MEDICAMENTOS",
      "ENALAPRIL",
      "APRESOLINA",
      "MONOCORDL",
      "ESPIRONOLACTONA",
      "FUROSEMIDA",
      "CARVEDILOL",
      "SINVASTATINA"
    ],
    "Conceito Quantitativo": [
      "38 MAÇOS-ANO",
      "10 MG",
      "1/2 CP",
      "25 MG",
      "1 CP",
      "8/8 HORAS",
      "20 MG",
      "AO DIA",
      "40 MG"
    ]
  },
  "labels": {}
}