{
  "prontuario_id": 631,
  "text": "# Lucas, 55 ANOS\n# NATURAL DE ALAGOAS, RESIDENTE EM CURITIBA.\n# DÇ DE CHAGAS\n# BAVT\n# MARCA-PASSO DUPLACAMARA EM DDD 50-60 DESDE 2007\n# PACIENTE ENCAMINHADO DO AMBULATÓRIO DE ARRITMIAS.\nPACIENTE NEGA DISPNEIA, NEGA ORTOPNEIA, NEGA DPN.\nSEM OUTRAS QUEIXAS\n# NEGA HX DE HAS, DM, DISLIPIDEMIA E TIREOIDOPATIAS.\n# MÃE FALECIDA POR CARDIOPATIA ( IAM ?), 65 ANOS.\n# CX DE APENDICITE E HERNIAS PARAMEDIANAS HÁ > 20 ANOS\n# EM USO DE:\nMETOPROLOL 50MG 12/12HS\nENALAPRIL 10 MG 12/12HS\nESPIRONO 25\nSVT 20\nEXAMES LAB 11/11: CREAT 1; UR 58; GLI 71; TG 88; HDL 52; CT 160; LDL 90; Na 140; K 5,2; Hb 14,8/ Ht 46,6/LEUC 5150\nEF # BEG, LOTE, CORADO E HIDRATADO.\nPA: 90/60MMHG; P: 72\nAUSENCIA DE TURGÊNCIA JUGULAR\nICTUS PALPÁVEL EM 7º EIC EM LINHA HEMIAXILAR E\nBCRNF 2T SS\nAUSCULTA PULMONAR SEM ALTERAÇÕES.\nABDOME INOCENTE.\nSEM EDEMA EM MMII. PULSOS + BL, SIMÉTRICOS.\nA: DÇA CHAGAS\nP: MANTENHO MEDICAÇÕES\nSOLICITO ECOCARDIO\nRETORNO EM 3 MESES\n \n \n \n ",
  "entities": {
    "Abreviação": [
      "BAVT",
      "DPN",
      "HAS",
      "DM",
      "IAM",
      "12/12HS",
      "ESPIRONO",
      "SVT",
      "EF",
      "BEG",
      "LOTE",
      "PA",
      "P",
      "BCRNF",
      "MMII",
      "ECOCARDIO",
      "DÇ DE CHAGAS",
      "CX DE APENDICITE",
      "EXAMES LAB",
      "CREAT 1",
      "UR 58",
      "GLI 71",
      "TG 88",
      "CT 160",
      "Na 140",
      "K 5 , 2",
      "Hb 14 , 8/",
      "Ht 46",
      "+ BL",
      "DÇA CHAGAS"
    ],
    "Doença ou Síndrome": [
      "BAVT",
      "HAS",
      "DM",
      "DISLIPIDEMIA",
      "TIREOIDOPATIAS",
      "CARDIOPATIA",
      "IAM",
      "DÇ DE CHAGAS",
      "DÇA CHAGAS"
    ],
    "Dispositivo Médico": [
      "MARCA-PASSO"
    ],
    "Procedimento Terapêutico ou Preventivo": [
      "MARCA-PASSO",
      "MEDICAÇÕES",
      "CX DE APENDICITE"
    ],
    "Paciente ou Grupo com Deficiência": [
      "PACIENTE"
    ],
    "Atividade de Assistência à Saúde": [
      "ENCAMINHADO",
      "MANTENHO",
      "SOLICITO"
    ],
    "Negação": [
      "NEGA",
      "SEM",
      "AUSENCIA",
      "SS"
    ],
    "Sinal ou Sintoma": [
      "DISPNEIA",
      "ORTOPNEIA",
      "DPN",
      "QUEIXAS",
      "ALTERAÇÕES",
      "EDEMA",
      "TURGÊNCIA JUGULAR"
    ],
    "Grupo Familiar": [
      "MÃE"
    ],
    "Substância Farmacológica": [
      "METOPROLOL",
      "ENALAPRIL",
      "ESPIRONO",
      "SVT",
      "MEDICAÇÕES"
    ],
    "Conceito Quantitativo": [
      "50MG",
      "12/12HS",
      "25",
      "20",
      "90/60MMHG",
      "72",
      "10 MG"
    ],
    "Conceito Temporal": [
      "12/12HS"
    ],
    "Aminoácido, Peptídeo ou Proteína": [
      "ENALAPRIL"
    ],
    "Procedimento Diagnóstico": [
      "EF",
      "ECOCARDIO",
      "AUSCULTA PULMONAR"
    ],
    "Achado": [
      "BEG",
      "LOTE",
      "CORADO",
      "HIDRATADO",
      "BCRNF",
      "SIMÉTRICOS",
      "PALPÁVEL EM 7º EIC EM LINHA HEMIAXILAR",
      "ABDOME INOCENTE",
      "+ BL"
    ],
    "Atributo Clínico": [
      "PA",
      "P",
      "PULSOS",
      "AUSCULTA PULMONAR"
    ],
    "Localização ou Região Corporal": [
      "ICTUS",
      "MMII"
    ],
    "Organização Relacionada à Saúde": [
      "AMBULATÓRIO DE ARRITMIAS"
    ],
    "Procedimento Laboratorial": [
      "EXAMES LAB"
    ],
    "Resultado Laboratorial ou de Teste": [
      "CREAT 1",
      "UR 58",
      "GLI 71",
      "TG 88",
      "HDL 52",
      "CT 160",
      "LDL 90",
      "Na 140",
      "K 5 , 2",
      "Hb 14 , 8/",
      "Ht 46"
    ]
  },
  "labels": {}
}