{
  "prontuario_id": 193,
  "text": "ABLAÇÃO DE TAQUICARDIA ATRIAL 2009 E A SEGUNDA EM 2010.\nHAS, NEGA DM, DLPD, TABAGISMO, ALERGIA MEDICAMENTOSA.\nCATETERISMO COM AUSENCIA DE CORONARIOPATIA.\nFAZ USO DE ATENOLOL 100MG 12/12H, DILTIAZEN 60MG 12/12H, ENALAPRIL 10MG 12/12H, HCTZ  25MG, MAREVAN 5MG.\nHOLTER COM PRESENCA DE EV E ESV RARAS COM EPISODIOS NAO SUSTENTADOS DE TAQUICARDIA ATRIAL SEM PRESENCA DE SINTOMAS.\n# PACIENTE REFERE ESTAR SE SENTINDO BEM COM AS MEDICAÇÕES. NEGA SINTOMAS DE PALPITAÇÕES. RELATA DISPNEIA AOS GRANDES ESFORCOS, COM MELHORA COM REPOUSO. RELATA QUE APRESENTOU 1 EPISODIO DE HIPOTENSAO. RELATA CEFALEIA.\n# BEG, PA 120/80MMHG,   FC 70.\nC/P : SEM ALT.\nCORAÇÃO: BRNF 2T, SEM SOPRO.\nPULMAO: MV+, SEM RA.\nCD: MEDICAÇÃO MANTIDA. SOLICITO NOVO HOLTER E ECOCARDIO.\n \n \n \n ",
  "entities": {
    "Abreviação": [
      "HAS",
      "DM",
      "DLPD",
      "HCTZ",
      "BEG",
      "PA",
      "FC",
      "C/P",
      "ALT",
      "MV+",
      "RA",
      "CD",
      "ECOCARDIO",
      "PRESENCA DE EV E ESV RARAS COM EPISODIOS",
      "BRNF 2T"
    ],
    "Doença ou Síndrome": [
      "HAS",
      "DM",
      "DLPD",
      "TABAGISMO",
      "CORONARIOPATIA",
      "ALERGIA MEDICAMENTOSA"
    ],
    "Negação": [
      "NEGA",
      "AUSENCIA",
      "NAO",
      "SEM"
    ],
    "Procedimento Terapêutico ou Preventivo": [
      "CATETERISMO",
      "ABLAÇÃO DE TAQUICARDIA ATRIAL"
    ],
    "Substância Farmacológica": [
      "ATENOLOL",
      "DILTIAZEN",
      "ENALAPRIL",
      "HCTZ",
      "MAREVAN",
      "MEDICAÇÕES"
    ],
    "Substância Química Orgânica": [
      "ATENOLOL",
      "DILTIAZEN",
      "HCTZ",
      "MAREVAN"
    ],
    "Conceito Quantitativo": [
      "100MG",
      "60MG",
      "10MG",
      "25MG",
      "5MG",
      "120/80MMHG",
      "70",
      "1 EPISODIO"
    ],
    "Conceito Temporal": [
      "12/12H"
    ],
    "Aminoácido, Peptídeo ou Proteína": [
      "ENALAPRIL"
    ],
    "Procedimento Diagnóstico": [
      "HOLTER",
      "ECOCARDIO"
    ],
    "Paciente ou Grupo com Deficiência": [
      "PACIENTE"
    ],
    "Sinal ou Sintoma": [
      "SINTOMAS",
      "PALPITAÇÕES",
      "HIPOTENSAO",
      "CEFALEIA",
      "ALT",
      "SOPRO",
      "RA",
      "DISPNEIA AOS GRANDES ESFORCOS"
    ],
    "Achado": [
      "BEG",
      "MV+",
      "SENTINDO BEM",
      "MELHORA COM REPOUSO",
      "BRNF 2T"
    ],
    "Atributo Clínico": [
      "PA",
      "FC"
    ],
    "Parte do Corpo, Órgão ou Componente Orgânico": [
      "C/P",
      "CORAÇÃO",
      "PULMAO"
    ],
    "Atividade de Assistência à Saúde": [
      "CD",
      "SOLICITO",
      "MEDICAÇÃO MANTIDA"
    ],
    "Produto Intelectual": [
      "CD"
    ],
    "Resultado Laboratorial ou de Teste": [
      "PRESENCA DE EV E ESV RARAS COM EPISODIOS",
      "SUSTENTADOS DE TAQUICARDIA ATRIAL",
      "PRESENCA DE SINTOMAS"
    ]
  },
  "labels": {}
}