{
  "prontuario_id": 434,
  "text": "QP:\nDores articulares em cotovelos e região lombar. \nCom piora à movimentação e melhora ao repouso. Relata início das dores à fratura de coluna e piora quando iniciou profilaxia para febre reumática.\nRelata piora importante da dor a início de problemas familiares recentes.\n- Dor lombar cronica de origem mecânica\n- História de doença reumática na família, não soube explicar\n- Hitória de miocardiopatia na família\n- História de câncer  ( irmão )\nHMP: \n- Iniciou profilaxia para febre reumática há 3 anos, associou início das dores à profilaxia com penicilina benzatina\n- Há 10 anos Homoenxerto aórtico + revascularização ( estenose aórtica + ICO )\n- Hx de trabalho levantando peso (almoxarifado), aposentado há 10 anos por invalidez\n- Hx de neurocisticercose em uso de fenitoína\n- História de fratura, não quis relatar a data nem mecanismo da fratura: T8 e T11, tratamento conservador. \nREMÉDIOS EM USO:\nAAS 100mg \nLosartana 50mg\nAtenolol 25mg\nFurosemida 40mg\nAtorvastatina 20mg\nEzetimib 10mg\nOmeprazol 20mg\nFenitoína 100mg\nCHV:\n- Faz caminhadas diárias\n- Relata alimentação saudável\n- Rx de tórax e coluna lombar\n- Hemograma, creatinina, VHS, PCR, eletroforese de proteínas, cálcio, vitamina D",
  "entities": {
    "Sinal ou Sintoma": [
      "QP",
      "dores",
      "dor",
      "Dores articulares",
      "Dor lombar"
    ],
    "Abreviação": [
      "QP",
      "ICO",
      "AAS",
      "Rx",
      "VHS",
      "PCR"
    ],
    "Localização ou Região Corporal": [
      "lombar"
    ],
    "Conceito Qualitativo": [
      "piora",
      "melhora ao repouso"
    ],
    "Conceito Temporal": [
      "cronica",
      "data",
      "há 3 anos",
      "Há 10 anos",
      "há 10 anos"
    ],
    "Fenômeno ou Processo": [
      "mecânica"
    ],
    "Grupo Familiar": [
      "família",
      "irmão"
    ],
    "Doença ou Síndrome": [
      "miocardiopatia",
      "câncer",
      "ICO",
      "neurocisticercose",
      "febre reumática",
      "doença reumática",
      "estenose aórtica"
    ],
    "Procedimento Terapêutico ou Preventivo": [
      "profilaxia",
      "revascularização",
      "REMÉDIOS",
      "Homoenxerto aórtico",
      "tratamento conservador"
    ],
    "Grupo Profissional ou Ocupacional": [
      "aposentado"
    ],
    "Achado": [
      "invalidez",
      "problemas familiares recentes",
      "alimentação saudável"
    ],
    "Substância Farmacológica": [
      "fenitoína",
      "AAS",
      "Losartana",
      "Atenolol",
      "Furosemida",
      "Atorvastatina",
      "Ezetimib",
      "Omeprazol",
      "Fenitoína"
    ],
    "Substância Química Orgânica": [
      "fenitoína",
      "AAS",
      "Losartana",
      "Atenolol",
      "Furosemida",
      "Atorvastatina",
      "Ezetimib",
      "Omeprazol",
      "Fenitoína",
      "penicilina benzatina"
    ],
    "Lesão ou Envenenamento": [
      "fratura",
      "fratura de coluna",
      "mecanismo da fratura"
    ],
    "Negação": [
      "não",
      "nem"
    ],
    "Conceito Quantitativo": [
      "100mg",
      "50mg",
      "25mg",
      "40mg",
      "20mg",
      "10mg"
    ],
    "Atividade Diária ou Recreativa": [
      "caminhadas"
    ],
    "Parte do Corpo, Órgão ou Componente Orgânico": [
      "tórax",
      "T8 e T11",
      "coluna lombar"
    ],
    "Procedimento Laboratorial": [
      "Hemograma",
      "creatinina",
      "VHS",
      "PCR",
      "cálcio",
      "eletroforese de proteínas",
      "vitamina D"
    ],
    "Antibiótico": [
      "penicilina benzatina"
    ],
    "Atividade Ocupacional": [
      "trabalho levantando peso"
    ]
  },
  "labels": {}
}