{
  "prontuario_id": 145,
  "text": "LUCAS, 61 ANOS\n\n# HAS\n# IC\n# HIPOTIREOIDISMO\n# MIOCARDIOPATIA DILATADA\n# IMPLANTE DE MP + CDI EM NOV/13\n\nEM USO: CARVEDILOL 50 MG 2X/D + MONONITRATO DE ISOSSORBITA 20 MG 2X/D + ANCORON 200 MG 2X/D + ALDACTONE 25 MG /D + FUROSEMIDA 40 MG 2X/D + LOSARTAN 50 MG 2X/D + DIGOXINA 0,25 MG /D + SINVASTATINA 40 MG /D + LEVOTIROXINA 50 MCG /D + RIVOTRIL 2 MG /D + PROCIMAX.\n\nPACIENTE REFERE QUE HÁ 6 MESES VEM APRESENTANDO EPISÓDIOS DE DOR TORÁCICA EM APERTO, COM DURAÇÃO DE 10 A 30 MINUTOS, EM REPOUSO, MAS COM PIORA AOS ESFORÇOS. \nRELATA AINDA DISPNÉIA / CANSAÇO AOS MODERADOS ESFORÇOS. NEGA ORTOPNEIA OU DPN.\nHÁ 2 MESES NÃO FAZ REVISÃO DO MP.\n\nAO EXAME:\nBEG, EUPNEICA, AFEBRIL.\nAC: RCR 2T BNF SS.\nAP: MV +, SEM RA.\nABD: FLÁCIDO, INDOLOR.\nMMII: SEM EDEMA, PANTURRILHAS LIVRES.\n\nLAB 29/04/15: TSH 15,  T4L 0,97.\n\nCD: PRESCREVO HIDRALAZINA,\n      SOLICITO ECOTT E ECOSTRESS,\n      ENCAMINHO PARA AVALIAÇÃO DO MP,\n      SOLICITO LAB,\n      AUMENTO PURAN PARA 75 MCG /D,\n      RETORNO EM 3 MESES OU COM RESULTADO DE ECOSTRESS ANTES,\n\nR4 CARDIO XX LUCAS \n \n \n ",
  "entities": {
    "Abreviação": [
      "HAS",
      "IC",
      "CDI",
      "DPN",
      "MP",
      "BEG",
      "AC",
      "AP",
      "RA",
      "ABD",
      "MMII",
      "LAB",
      "CD",
      "ECOTT",
      "ECOSTRESS",
      "CARDIO",
      "IMPLANTE DE MP",
      "MV +"
    ],
    "Doença ou Síndrome": [
      "HAS",
      "IC",
      "HIPOTIREOIDISMO",
      "DPN",
      "MIOCARDIOPATIA DILATADA"
    ],
    "Procedimento Terapêutico ou Preventivo": [
      "CDI",
      "IMPLANTE DE MP"
    ],
    "Dispositivo Médico": [
      "CDI"
    ],
    "Substância Farmacológica": [
      "CARVEDILOL",
      "ANCORON",
      "ALDACTONE",
      "FUROSEMIDA",
      "LOSARTAN",
      "DIGOXINA",
      "SINVASTATINA",
      "LEVOTIROXINA",
      "RIVOTRIL",
      "PROCIMAX",
      "HIDRALAZINA",
      "PURAN",
      "MONONITRATO DE ISOSSORBITA"
    ],
    "Substância Química Orgânica": [
      "CARVEDILOL",
      "ANCORON",
      "FUROSEMIDA",
      "LOSARTAN",
      "DIGOXINA",
      "SINVASTATINA",
      "LEVOTIROXINA",
      "PROCIMAX",
      "HIDRALAZINA",
      "PURAN",
      "MONONITRATO DE ISOSSORBITA"
    ],
    "Conceito Quantitativo": [
      "2X/D",
      "50 MG",
      "20 MG",
      "200 MG",
      "25 MG",
      "40 MG",
      "0 , 25 MG",
      "50 MCG",
      "2 MG",
      "75 MCG"
    ],
    "Conceito Temporal": [
      "2X/D",
      "/D",
      "HÁ 6 MESES"
    ],
    "Paciente ou Grupo com Deficiência": [
      "PACIENTE"
    ],
    "Sinal ou Sintoma": [
      "REPOUSO",
      "DISPNÉIA",
      "ORTOPNEIA",
      "AFEBRIL",
      "SS",
      "RA",
      "INDOLOR",
      "EDEMA",
      "DOR TORÁCICA",
      "PIORA AOS ESFORÇOS",
      "CANSAÇO AOS MODERADOS ESFORÇOS"
    ],
    "Negação": [
      "NEGA",
      "NÃO",
      "AFEBRIL",
      "SS",
      "SEM",
      "INDOLOR"
    ],
    "Procedimento Diagnóstico": [
      "EXAME",
      "AC",
      "AP",
      "ECOTT",
      "ECOSTRESS"
    ],
    "Achado": [
      "BEG",
      "EUPNEICA",
      "FLÁCIDO",
      "MV +",
      "PANTURRILHAS LIVRES"
    ],
    "Parte do Corpo, Órgão ou Componente Orgânico": [
      "ABD",
      "MMII"
    ],
    "Função Patológica": [
      "EDEMA"
    ],
    "Procedimento Laboratorial": [
      "LAB"
    ],
    "Produto Intelectual": [
      "CD"
    ],
    "Atividade de Assistência à Saúde": [
      "PRESCREVO",
      "SOLICITO",
      "ENCAMINHO",
      "AUMENTO"
    ],
    "Conceito Qualitativo": [
      "EM APERTO"
    ],
    "Resultado Laboratorial ou de Teste": [
      "TSH 15",
      "T4L 0 , 97",
      "RESULTADO DE ECOSTRESS ANTES"
    ]
  },
  "labels": {}
}