{
  "prontuario_id": 256,
  "text": "Lucas, 68 ANOS.\n\nCAT EM 2008.\nVALVOPLASTIA AÓRTICA EM 2008. VALVA BIOLÓGICA.\n40 DIAS DE ARRITMIA. CARDIOVERSAO, FICOU BOM.\nQUEIXA DE CANSAÇO ANTES DA CX - PNEUMONIA (SIC).\nFUMANTE POR 40 ANOS, 25 CIGARROS POR DIA.\n\nREFERE ESTAR SEM SINTOMAS CARDIOVASC.\nULTIMA CONSULTA HÁ 1 ANO.\nPA BAIXA (SIC).\n\nEM USO DE:\n- ENALAPRIL 10 - 12/12;\n- CARVEDILOL 6,25 - 12/12;\n- AAS 100;\n- ATORVASTATINA 20 - 2 A NOITE.\n\nEXAME FISICO:\nFC 80,\tPA 150/100,\tFR 16;\nBCRNF COM SOPRO SISTÓLICO EM FOCO AORTICO,\nMV+ BILATERAL, SEM RA.\nRH+, SEM VISCEROMEGALIA OU DOR A PALPAÇÃO. HERNIA UMBULICAL, ANEL HERNIÁRIO DE 5CM, REDUTÍVEL.\n \n \n \n ",
  "entities": {
    "Abreviação": [
      "CAT",
      "SIC",
      "AAS",
      "FC",
      "PA",
      "FR",
      "BCRNF",
      "RA",
      "RH+",
      "SINTOMAS CARDIOVASC",
      "PA BAIXA",
      "MV+ BILATERAL"
    ],
    "Procedimento Terapêutico ou Preventivo": [
      "CAT",
      "CARDIOVERSAO",
      "CX",
      "VALVOPLASTIA AÓRTICA"
    ],
    "Doença ou Síndrome": [
      "ARRITMIA",
      "PNEUMONIA"
    ],
    "Disfunção Mental ou Comportamental": [
      "FUMANTE"
    ],
    "Negação": [
      "SEM"
    ],
    "Substância Farmacológica": [
      "ENALAPRIL",
      "CARVEDILOL",
      "AAS",
      "ATORVASTATINA"
    ],
    "Aminoácido, Peptídeo ou Proteína": [
      "ENALAPRIL"
    ],
    "Conceito Quantitativo": [
      "10",
      "12/12",
      "100",
      "20",
      "80",
      "150/100",
      "16",
      "5CM",
      "25 CIGARROS POR DIA",
      "6 , 25"
    ],
    "Conceito Temporal": [
      "12/12",
      "40 DIAS",
      "POR 40 ANOS",
      "2 A NOITE"
    ],
    "Substância Química Orgânica": [
      "CARVEDILOL",
      "AAS",
      "ATORVASTATINA"
    ],
    "Atributo Clínico": [
      "FC",
      "PA",
      "FR"
    ],
    "Achado": [
      "BCRNF",
      "RH+",
      "VALVA BIOLÓGICA",
      "FICOU BOM",
      "PA BAIXA",
      "MV+ BILATERAL"
    ],
    "Sinal ou Sintoma": [
      "RA",
      "VISCEROMEGALIA",
      "QUEIXA DE CANSAÇO",
      "SINTOMAS CARDIOVASC",
      "SOPRO SISTÓLICO EM FOCO AORTICO"
    ],
    "Procedimento Diagnóstico": [
      "PALPAÇÃO",
      "EXAME FISICO"
    ],
    "Conceito Qualitativo": [
      "REDUTÍVEL"
    ],
    "Dispositivo Médico": [
      "VALVA BIOLÓGICA"
    ],
    "Anormalidade Anatômica": [
      "HERNIA UMBULICAL",
      "ANEL HERNIÁRIO"
    ]
  },
  "labels": {}
}