{
  "prontuario_id": 882,
  "text": "PACIENTE QUEIXA-SE DE BAV PARA PERTO.\nNEGA USO DE OCULOS, NEGA USO DE COLIRIO.\nHAS EM TTO. NEGA DM\nREFERE TRANSPLANTE RENAL, HA 2 ANOS, NAO SABE REFERIR BEM A CAUSA.\nNEGA CIRURGIAS E TRAUMAS OCULARES.\nNEGA HF DE GLAUCOMA E CEGUEIRA.\n\nAV:\n20/25\n20/20\n\nTOL:\nPL ESF 20/25.\nPL ESF 20/30.\nAD +2,75; LE J2\n\nBIO: \nBLEFARITE ANTERIOR AO.\nCATARATA INCIPIENTE AO.\n\nFO:\nPAPILA E MACULA NORMAL AO.\n\nPIO:12/12\n\n**EXAME OFTALMOLOGICO DE DIFICIL REALIZAÇÃO, PACIENTE NAO COMPREENDE BEM EXAME. COGNITIVO BAIXO\n\nCD:\nPRESCREVO OCULOS PARA PERTO CONFORME TOLERANCIA A PÉDIDO DO PACIENTE\nPRESCREVO TTO BLEFARITE ANTERIOR\nALTA COM RETORNO ANUAL VIA UBS\n\n\nR1 CAROLINA\n \n \n \n ",
  "entities": {
    "Paciente ou Grupo com Deficiência": [
      "PACIENTE"
    ],
    "Sinal ou Sintoma": [
      "QUEIXA-SE",
      "BAV PARA PERTO"
    ],
    "Negação": [
      "NEGA",
      "NAO"
    ],
    "Doença ou Síndrome": [
      "HAS",
      "DM",
      "GLAUCOMA",
      "CEGUEIRA",
      "BLEFARITE ANTERIOR AO",
      "CATARATA INCIPIENTE",
      "BLEFARITE ANTERIOR"
    ],
    "Procedimento Terapêutico ou Preventivo": [
      "TTO",
      "CIRURGIAS",
      "TRANSPLANTE RENAL"
    ],
    "Abreviação": [
      "DM",
      "HF",
      "BIO",
      "AO",
      "FO",
      "PIO",
      "UBS",
      "BAV PARA PERTO",
      "AV : 20/25 20/20",
      "TOL : PL ESF 20/25",
      "PL ESF 20/30",
      "AD +2 , 75",
      "BLEFARITE ANTERIOR AO",
      "PAPILA E MACULA NORMAL AO"
    ],
    "Achado": [
      "HF",
      "COMPREENDE BEM",
      "COGNITIVO BAIXO"
    ],
    "Parte do Corpo, Órgão ou Componente Orgânico": [
      "AO"
    ],
    "Procedimento Diagnóstico": [
      "FO",
      "PIO",
      "EXAME",
      "**EXAME OFTALMOLOGICO"
    ],
    "Atributo Clínico": [
      "PIO"
    ],
    "Conceito Quantitativo": [
      "12/12"
    ],
    "Conceito Qualitativo": [
      "DIFICIL"
    ],
    "Atividade de Assistência à Saúde": [
      "REALIZAÇÃO",
      "ALTA",
      "RETORNO ANUAL"
    ],
    "Produto Intelectual": [
      "CD"
    ],
    "Organização Relacionada à Saúde": [
      "UBS"
    ],
    "Lesão ou Envenenamento": [
      "TRAUMAS OCULARES"
    ],
    "Resultado Laboratorial ou de Teste": [
      "AV : 20/25 20/20",
      "TOL : PL ESF 20/25",
      "PL ESF 20/30",
      "AD +2 , 75",
      "PAPILA E MACULA NORMAL AO"
    ]
  },
  "labels": {}
}