{
  "prontuario_id": 744,
  "text": "LUCAS, 59 ANOS\n\n# S: PACIENTE EM ACOMPANHAMENTO POR TUMORAÇÃO EM MANDÍBULA.\nINICIO HA CERCA DE 7 MESES, EM FACE E CORPO DE MANDIBULA DIR, INDOLOR. NAO AUMENTA O VOLUME HA 3 MESES.\nNEGA DISFAGIA, NEGA PARESIAS OU PARESTESIAS EM FACE. \nNEGA TABAGISMO; NEGA ALERGIAS,\nEPISTAXE FREQUENTE (2 A 3 X/SEMANA).\n\nHMP: HAS EM TTO, TRANSPLANTADA RENAL ESQ HA 03 ANOS, EM USO DE IMUNODEPRESSORES (SIC);\n\n# O: ORO: EDENTULISMO SUP E INF; PRESENÇA DE MASSA ENDURECIDA EM CORPO E RAMO DIREITOS DE MANDIBULA , INDOLOR Á PALPAÇÃO; 8 X 8 CM;\nLINGUA E ASSOALHO LIVRES;\n-C/P: LIVRE.\n- PERFURAÇÃO SEPTAL PEQUENA ANTERIOR COM CROSTAS.\n\nTC DO PERSCOÇO (11/12/2015): LESÃO ÓSSEA NA MANDIBULA DIREITA, COM SINAIS DE MODERADA AGRESSIVIDADE LOCAL . CONSIDERAR AS POSSIBILIDADES DE LESÃO PRIMARIA (AMELOBLASTOMA?TCG?), \nOU MENOS PROVAVELMENTE SECUNDÁRIA. SUGERE-SE CORRELAÇÃO COM ESTUDO ANATOMOPATOLÓGICO.\n-BÓCIO TIREOIDIANO NODULAR.\n\n# A: LESÃO OSSEA DA MANDIBULA DIREITA (cisto dentigero, ameloblastoma, tu marrom ? sarcoma de mandibula ?).\n\n# P: RETORNO EM 2 SEMANAS (17/02/2016) EM VISITA.\nNÃO REALIZADO BIOPSIA SEPTAL HOJE POR FALTA DE MATERIAL ADEQUADO.\nBIOPSIAR SEPTO PROXIMA CONSULTA.\n \n \n \n ",
  "entities": {
    "Abreviação": [
      "S",
      "HMP",
      "O",
      "ORO",
      "-C/P",
      "A",
      "P",
      "MANDIBULA DIR",
      "TRANSPLANTADA RENAL ESQ",
      "SUP E INF",
      "TC DO PERSCOÇO",
      "tu marrom"
    ],
    "Achado": [
      "S",
      "HMP",
      "LIVRE",
      "TRANSPLANTADA RENAL ESQ",
      "LINGUA E ASSOALHO LIVRES"
    ],
    "Paciente ou Grupo com Deficiência": [
      "PACIENTE"
    ],
    "Atividade de Assistência à Saúde": [
      "ACOMPANHAMENTO",
      "O",
      "RETORNO"
    ],
    "Parte do Corpo, Órgão ou Componente Orgânico": [
      "MANDÍBULA",
      "FACE",
      "MANDIBULA DIR"
    ],
    "Sinal ou Sintoma": [
      "INDOLOR",
      "DISFAGIA",
      "PARESIAS",
      "PARESTESIAS",
      "EPISTAXE",
      "AUMENTA O VOLUME",
      "PRESENÇA DE MASSA ENDURECIDA"
    ],
    "Negação": [
      "INDOLOR",
      "NAO",
      "NEGA",
      "NÃO"
    ],
    "Doença ou Síndrome": [
      "TABAGISMO",
      "ALERGIAS",
      "HAS",
      "EDENTULISMO",
      "-BÓCIO TIREOIDIANO NODULAR",
      "cisto dentigero"
    ],
    "Substância Farmacológica": [
      "IMUNODEPRESSORES"
    ],
    "Procedimento Diagnóstico": [
      "ORO",
      "A",
      "TC DO PERSCOÇO",
      "ESTUDO ANATOMOPATOLÓGICO",
      "BIOPSIA SEPTAL"
    ],
    "Processo Neoplásico": [
      "AMELOBLASTOMA",
      "ameloblastoma",
      "tu marrom",
      "sarcoma de mandibula"
    ],
    "Produto Intelectual": [
      "P"
    ],
    "Localização ou Região Corporal": [
      "SEPTO"
    ],
    "Procedimento Terapêutico ou Preventivo": [
      "TRANSPLANTADA RENAL ESQ"
    ],
    "Conceito Espacial": [
      "SUP E INF"
    ],
    "Conceito Quantitativo": [
      "8 X 8 CM"
    ],
    "Resultado Laboratorial ou de Teste": [
      "LESÃO ÓSSEA NA MANDIBULA DIREITA",
      "COM SINAIS DE MODERADA AGRESSIVIDADE LOCAL"
    ],
    "Lesão ou Envenenamento": [
      "LESÃO OSSEA DA MANDIBULA DIREITA"
    ]
  },
  "labels": {}
}