{
  "prontuario_id": 610,
  "text": "07:40 - Paciente acordada, lúcida e orientada, contactuante, mais ativa hoje, glasgow de 15. Hipocorada, mucosas úmidas. Pele íntegra com hiperemia em região axilar. Traqueostomizada sob VM PSV, FIO2 30%, PEEP 6, P 10, F 16, eupneica, mantendo boa saturação, ausculta pulmonar com MV+ com roncos bilateral. Normocardica e normotensa. Abdome globoso e flácido, RHA +, com SNE recebendo dienta à 75 ml/h. Mantém CVC em subclávia D infundindo soro gravitacional. Diurese presente em SVD clara. Evacuação presente. Boa perfusão periférica. FLORENCE NIGHTINGALE. Coren xxxx  DOR TORACICA NAO ESPECIFICADA.",
  "entities": {
    "Achado": [
      "acordada",
      "lúcida",
      "orientada",
      "contactuante",
      "eupneica",
      "MV+",
      "Normocardica",
      "normotensa",
      "globoso",
      "flácido",
      "mais ativa hoje",
      "glasgow de 15",
      "mucosas úmidas",
      "Pele íntegra",
      "boa saturação",
      "RHA +",
      "Diurese presente",
      "Evacuação presente",
      "Boa perfusão periférica"
    ],
    "Sinal ou Sintoma": [
      "Hipocorada",
      "hiperemia",
      "globoso",
      "roncos bilateral"
    ],
    "Procedimento Terapêutico ou Preventivo": [
      "Traqueostomizada",
      "VM",
      "PSV",
      "SNE",
      "dienta",
      "CVC",
      "SVD"
    ],
    "Abreviação": [
      "VM",
      "PSV",
      "FIO2",
      "PEEP",
      "P",
      "F",
      "MV+",
      "SNE",
      "CVC",
      "SVD",
      "RHA +",
      "subclávia D"
    ],
    "Atributo Clínico": [
      "FIO2",
      "PEEP",
      "P",
      "F"
    ],
    "Conceito Quantitativo": [
      "30%",
      "6",
      "10",
      "16",
      "75 ml/h"
    ],
    "Parte do Corpo, Órgão ou Componente Orgânico": [
      "Abdome",
      "subclávia D"
    ],
    "Dispositivo Médico": [
      "SNE",
      "CVC",
      "SVD"
    ],
    "Conceito Qualitativo": [
      "clara"
    ],
    "Localização ou Região Corporal": [
      "região axilar"
    ],
    "Procedimento Diagnóstico": [
      "ausculta pulmonar"
    ],
    "Função de Organismo": [
      "Diurese presente",
      "Evacuação presente"
    ],
    "Doença ou Síndrome": [
      "DOR TORACICA"
    ]
  },
  "labels": {}
}