{
  "prontuario_id": 650,
  "text": "Interna para angioplastia seguida de implante de stent Driver em terço médio de coronária direita e stent Cypher em artéria segunda marginal. Procedimento realizado em 06/12/04 pelo Doutor Vital Brazil, sem intercorrências e com sucesso angiográfico. Recebe alta em bom estado geral, afebril, sinais vitais estáveis, sem sinais de hematoma ou pseudoaneurisma em local de punção e com boa perfusão de membros inferiores. Orientado a: - retorno à emergência se necessário. - retorno ao médico assistente em uma semana. - orientações gerais. - manter medicações em uso (orientado a usar plavix 75mg xdia por mais 3 meses e manter uso por tempo indefinido de AAS, angipress e medicações para dislipidemia).",
  "entities": {
    "Atividade de Assistência à Saúde": [
      "Interna",
      "alta",
      "Orientado",
      "retorno",
      "orientado",
      "orientações gerais",
      "manter medicações em uso",
      "manter uso"
    ],
    "Procedimento Terapêutico ou Preventivo": [
      "angioplastia",
      "Procedimento",
      "implante de stent Driver",
      "stent Cypher"
    ],
    "Grupo Profissional ou Ocupacional": [
      "Doutor",
      "médico médico assistente assistente"
    ],
    "Negação": [
      "sem",
      "afebril"
    ],
    "Sinal ou Sintoma": [
      "intercorrências",
      "afebril",
      "sinais",
      "hematoma"
    ],
    "Função Patológica": [
      "pseudoaneurisma"
    ],
    "Organização Relacionada à Saúde": [
      "emergência"
    ],
    "Substância Química Orgânica": [
      "plavix",
      "AAS"
    ],
    "Substância Farmacológica": [
      "plavix",
      "AAS",
      "angipress"
    ],
    "Abreviação": [
      "AAS"
    ],
    "Dispositivo Médico": [
      "stent Cypher"
    ],
    "Parte do Corpo, Órgão ou Componente Orgânico": [
      "artéria segunda marginal",
      "membros inferiores"
    ],
    "Achado": [
      "sucesso angiográfico",
      "bom bom estado estado geral geral",
      "sinais vitais estáveis",
      "boa perfusão"
    ],
    "Conceito Temporal": [
      "uma semana",
      "tempo indefinido"
    ],
    "Conceito Quantitativo": [
      "75mg xdia"
    ]
  },
  "labels": {}
}