{
  "prontuario_id": 555,
  "text": "Paciente G 2  C 1, TS A+, IG de 39 sem 3 dia(s), INTERNA COM PRÓDROMOS DE TP, HISTÓRIA DE CESÁREA PRÉVIA HÁ MENOS DE 2 ANOS. EVOLUI PARA  Cesárea POR RISCO DE RUPTURA UTERINA  em 02/06/2007 AS 05:25 hs. NASCE RN APGAR 8 / 9, MASC, 3605 G.  EXAMES:  VDRL NR, PN OK.  Apresenta boa evolução puereperal, mamas lactantes, lóquios fisiológicos, útero contraído, SV estáveis. Em condições de alta.  ORIENTAÇÕES:  # AMAMENTAÇÃO EXCLUSIVA POR 6 MESES. # TOMAR AS MEDICAÇÕES PRESCRITAS (SULFATO FERROSO 300MG 3X/DIA LONGE DAS REFEIÇÕES, PREFERENCIALMENTE COM SUCO DE LARANJA OU LIMÃO, POR 90 DIAS - PARACETAMOL 500MG 1-2 CP VO DE 6/6 HS SE DOR). # REAVALIAÇÃO COM GINECOLOGISTA EM 30 DIAS. # LAVAR FERIDA OPERATÓRIA 3X/DIA COM ÁGUA E SABÃO NEUTRO. # RETIRAR OS PONTOS EM 10 DIAS. # RETORNAR À EMERGÊNCIA DESTE HOSPITAL SE SANGRAMENTO AUMENTADO, FEBRE,DOR FORTE OU OUTRAS INTERCORRÊNCIAS. ",
  "entities": {
    "Conceito Quantitativo": [
      "2",
      "1",
      "3X/DIA",
      "3605 G",
      "300MG 3X/DIA",
      "500MG 1-2 CP",
      "6/6 HS"
    ],
    "Abreviação": [
      "IG",
      "RN",
      "VO",
      "TS A+",
      "39 sem 3 dia",
      "3605 G",
      "VDRL NR",
      "PN OK",
      "SV estáveis"
    ],
    "Atributo Clínico": [
      "IG"
    ],
    "Atividade de Assistência à Saúde": [
      "INTERNA",
      "alta",
      "ORIENTAÇÕES",
      "REAVALIAÇÃO",
      "LAVAR",
      "RETIRAR",
      "RETORNAR",
      "TOMAR AS MEDICAÇÕES PRESCRITAS"
    ],
    "Função de Organismo": [
      "TP",
      "AMAMENTAÇÃO"
    ],
    "Procedimento Terapêutico ou Preventivo": [
      "CESÁREA",
      "Cesárea"
    ],
    "Conceito Temporal": [
      "PRÉVIA",
      "EVOLUI",
      "39 sem 3 dia",
      "6 MESES",
      "LONGE DAS REFEIÇÕES",
      "90 DIAS",
      "EM 30 DIAS",
      "10 DIAS"
    ],
    "Grupo Etário": [
      "RN"
    ],
    "Achado": [
      "MASC",
      "3605 G",
      "boa evolução puereperal",
      "mamas lactantes",
      "lóquios fisiológicos",
      "útero contraído",
      "SV estáveis"
    ],
    "Resultado Laboratorial ou de Teste": [
      "EXAMES",
      "TS A+",
      "APGAR 8 / 9",
      "VDRL NR",
      "PN OK"
    ],
    "Procedimento Diagnóstico": [
      "EXAMES"
    ],
    "Substância Química Orgânica": [
      "PARACETAMOL"
    ],
    "Substância Farmacológica": [
      "PARACETAMOL",
      "SULFATO FERROSO"
    ],
    "Sinal ou Sintoma": [
      "DOR",
      "FEBRE",
      "INTERCORRÊNCIAS",
      "SANGRAMENTO AUMENTADO",
      "DOR FORTE"
    ],
    "Grupo Profissional ou Ocupacional": [
      "GINECOLOGISTA"
    ],
    "Substância Química Inorgânica": [
      "ÁGUA",
      "SULFATO FERROSO"
    ],
    "Objeto Manufaturado": [
      "PONTOS",
      "HOSPITAL",
      "SABÃO NEUTRO"
    ],
    "Organização Relacionada à Saúde": [
      "EMERGÊNCIA",
      "HOSPITAL"
    ],
    "Função Patológica": [
      "RUPTURA UTERINA"
    ],
    "Alimento": [
      "SUCO DE LARANJA OU LIMÃO"
    ],
    "Lesão ou Envenenamento": [
      "FERIDA OPERATÓRIA"
    ]
  },
  "labels": {}
}