{
  "prontuario_id": 995,
  "text": "# INSUFICIÊNCIA CARDÍACA DIASTÓLICA. # ACFA. # HAS. # INSUFICIÊNCIA VENOSA CRÔNICA. # EX-TABAGISTA.  PACIENTE COM MÚLTIPLAS INTERNAÇÕES POR EXACERBAÇÃO DE INSUFICIÊNCIA CARDÍACA SECUNDÁRIAS A FIBRILAÇÃO ATRIAL COM ALTA RESPOSTA E A MÁ ADERÊNCIA AO TRATAMENTO, COM DIFICULDADE DE COMPREENSÃO E AFASIA DE EXPRESSÃO. TRAZIDA A EMERGÊNCIA POR PIORA PROGRESSIVA DE DIPNÉIA, ORTOPNÉIA E EDEMA. INSTITUÍDO TRATAMENTO PARA INSUFICIÊNCIA CARDÍACA DESCOMPENSADA, APRESENTANDO MELHORA DOS SINTOMAS. DEVIDO ÀS MÚLTIPLAS INTERNAÇÕES POR EXACERBAÇÃO SECUNDÁRIA A FIBRILAÇÃO ATRIAL FOI OPTADO POR REALIZAR ABLAÇÃO DE NODO AV. A PACIENTE FOI SUBMETIDA A COLOCAÇÃO DE MARCAPASSO DEFINITIVO E UM DIA APÓS, FOI REALIZADA A  ABLAÇÃO DE NODO AV. O PROCEDIMENTO OCOREU SEM INTERCORRÊNCIAS. ANTES DA ALTA FOI AVALIADO FUNCIONAMENTO DO MARCA-PASSO, QUE FICOU PROGRAMADO PARA 80 BPM. RECEBE ALTA HEMODINAMICAMENTE ESTÁVEL, SEM DISPNÉIA OU DOR TORÁCICA, COM AUSCULTA PULMONAR LIMPA E SEM EDEMA. RECEBEU ENCAMINHAMENTO PARA CONSULTA AMBULATORIAL NESSE HOSPITAL E RECEITA DAS MEDICAÇÕES QUE DEVERÁ SEGUIR TOMANDO.  MEDICAÇÕES: * CAPTOPRIL 25 MG - TOMAR 02 CP VO DE 12/12 HORAS. * FUROSEMIDA 40 MG - TOMAR 01 CP VO ÁS 8H E ÁS 14 H. * OMEPRAZOL 20 MG - TOMAR 01 CP VO PELA MANHÃ. * SINVASTATINA 40 MG - TOMAR 01 CP VO À NOITE. * AAS 100 MG - TOMAR 02 CP VO NO ALMOÇO.",
  "entities": {
    "Resultado Laboratorial ou de Teste": [
      "ACFA"
    ],
    "Abreviação": [
      "ACFA",
      "HAS",
      "AAS",
      "ABLAÇÃO DE NODO AV",
      "80 BPM",
      "TOMAR 02 CP VO",
      "TOMAR 01 CP VO"
    ],
    "Doença ou Síndrome": [
      "ACFA",
      "HAS",
      "INSUFICIÊNCIA CARDÍACA DIASTÓLICA",
      "INSUFICIÊNCIA VENOSA CRÔNICA",
      "FIBRILAÇÃO ATRIAL COM ALTA RESPOSTA",
      "INSUFICIÊNCIA CARDÍACA DESCOMPENSADA",
      "FIBRILAÇÃO ATRIAL"
    ],
    "Achado": [
      "EX-TABAGISTA",
      "LIMPA",
      "MÚLTIPLAS INTERNAÇÕES",
      "MÁ ADERÊNCIA",
      "MELHORA DOS SINTOMAS",
      "HEMODINAMICAMENTE ESTÁVEL"
    ],
    "Procedimento Terapêutico ou Preventivo": [
      "TRATAMENTO",
      "PROCEDIMENTO",
      "ABLAÇÃO DE NODO AV",
      "COLOCAÇÃO DE MARCAPASSO DEFINITIVO",
      "TOMAR 02 CP VO",
      "TOMAR 01 CP VO"
    ],
    "Organização Relacionada à Saúde": [
      "EMERGÊNCIA",
      "HOSPITAL",
      "CONSULTA AMBULATORIAL"
    ],
    "Sinal ou Sintoma": [
      "ORTOPNÉIA",
      "EDEMA",
      "INTERCORRÊNCIAS",
      "DISPNÉIA",
      "EXACERBAÇÃO DE INSUFICIÊNCIA CARDÍACA",
      "DIFICULDADE DE COMPREENSÃO",
      "PIORA PROGRESSIVA DE DIPNÉIA",
      "DOR TORÁCICA"
    ],
    "Atividade de Assistência à Saúde": [
      "REALIZAR",
      "SUBMETIDA",
      "ALTA",
      "ENCAMINHAMENTO",
      "RECEITA DAS MEDICAÇÕES"
    ],
    "Procedimento Diagnóstico": [
      "PROCEDIMENTO",
      "AUSCULTA PULMONAR"
    ],
    "Negação": [
      "SEM"
    ],
    "Conceito Temporal": [
      "ANTES",
      "MANHÃ",
      "NOITE",
      "ALMOÇO",
      "ÁS 8H",
      "14 H"
    ],
    "Conceito Qualitativo": [
      "LIMPA"
    ],
    "Objeto Manufaturado": [
      "HOSPITAL"
    ],
    "Substância Farmacológica": [
      "MEDICAÇÕES",
      "CAPTOPRIL",
      "FUROSEMIDA",
      "OMEPRAZOL",
      "SINVASTATINA",
      "AAS"
    ],
    "Aminoácido, Peptídeo ou Proteína": [
      "CAPTOPRIL"
    ],
    "Substância Química Orgânica": [
      "FUROSEMIDA",
      "OMEPRAZOL",
      "SINVASTATINA",
      "AAS"
    ],
    "Disfunção Mental ou Comportamental": [
      "DIFICULDADE DE COMPREENSÃO",
      "AFASIA DE EXPRESSÃO"
    ],
    "Atividade de Máquina": [
      "FUNCIONAMENTO DO MARCA-PASSO"
    ],
    "Conceito Quantitativo": [
      "80 BPM",
      "25 MG",
      "12/12 HORAS",
      "40 MG",
      "20 MG",
      "100 MG"
    ]
  },
  "labels": {}
}