{
  "prontuario_id": 62,
  "text": "LUCAS, 56 ANOS\n\n# PACIENTE EM ACOMPANHAMENTO POR INCONTINENCIA URINARIA DE URGENCIA LEVE (QUE MELHOROU COM TRATAMENTO DA ITU)\n\nS: PACIENTE CONFUSA, RETORNA HOJE APOS TRATAMENTO DE ITU COM MELHORA DAS QUEIXAS DE URGENCIA MICCIONAL, NEGA PERDA A URGENCIA. TROUXE EXAME DE URINA APOS TRATAMENTO. NEGA USO DE RETEMIC (NÃO SENTIU NECESSIDADE DE USAR E FICOU COM MEDO DOS EFEITOS COLATERAIS). MANTEM DIFICULDADE PARA TER RELAÇÃO SEXUAL.\n\nHMP: HA 10 ANO FEZ HISTERECTOMIA TOTAL (DEIXOU 1 OVÁRIO), HA 10 ANOS COM CPP ASSOCIADA.\nFAZ USO DE: RIVOTRIL, TOPIRAMATO.\nFAZ TRATAMENTO PARA ESQUIZOFRENIA E BIPOLARIDADE.\nG 2   P 2   A 0.\nFAZ MAMOGRAFIA A CADA DOIS ANOS (ÚLTIMA ANO PASSADO).\nFAZ PREVENTIVO NO POSTO DE SAÚDE.\n\nEXAME FÍSICO NA ULTIMA CONSULTA:\nINSPEÇÃO: PILIFICAÇÃO E TROFISMO NORMAIS PARA A IDADE SEM PERDA URINARIA A MANOBRA DE VALSALVA.\nEXAME ESPECULAR: VAGINA ROSEA E RUGOSA, SEM PRESENÇA DE LEUCORREIA PATOLÓGICA. PRESENÇA DE CISTOCELE GRAU 1 (-2) SEM PROLAPSO DE CUPULA.\nTOQUE VAGINAL: SEM ALTERAÇÃO.\n\nLABORATORIAIS (01/06/16): PARCIAL DE URINA NORMAL, UROCULTURA NEGATIVA.\n\nCONDUTA:\nORIENTADO PACIENTE SOBRE CONDIÇÃO DE BEXIGA HIPERATIVA (DIFICIL COMPREENSÃO SOBRE DIAGNOSTICO).\nPRESCREVO STELE E ORIENTO.\n\nR3 LUCAS\nDoutor Vital Brazil ",
  "entities": {
    "Atividade de Assistência à Saúde": [
      "ACOMPANHAMENTO",
      "RETORNA",
      "CONSULTA",
      "CONDUTA",
      "ORIENTADO",
      "PRESCREVO",
      "ORIENTO"
    ],
    "Achado": [
      "MELHOROU",
      "MELHORA",
      "ROSEA",
      "RUGOSA",
      "NECESSIDADE DE USAR"
    ],
    "Procedimento Terapêutico ou Preventivo": [
      "TRATAMENTO",
      "PREVENTIVO",
      "HISTERECTOMIA TOTAL"
    ],
    "Abreviação": [
      "ITU",
      "CPP",
      "R3"
    ],
    "Doença ou Síndrome": [
      "ITU",
      "DIAGNOSTICO",
      "INCONTINENCIA URINARIA DE URGENCIA LEVE",
      "CISTOCELE GRAU 1 ( -2 )",
      "PROLAPSO DE CUPULA",
      "BEXIGA HIPERATIVA ("
    ],
    "Sinal ou Sintoma": [
      "CONFUSA",
      "QUEIXAS",
      "ALTERAÇÃO",
      "URGENCIA MICCIONAL",
      "PERDA A URGENCIA",
      "DIFICULDADE PARA TER RELAÇÃO SEXUAL",
      "PERDA URINARIA",
      "LEUCORREIA PATOLÓGICA",
      "PROLAPSO DE CUPULA"
    ],
    "Conceito Temporal": [
      "HOJE",
      "APOS",
      "CADA DOIS ANOS"
    ],
    "Negação": [
      "NEGA",
      "NÃO",
      "SEM"
    ],
    "Substância Farmacológica": [
      "RETEMIC",
      "RIVOTRIL",
      "TOPIRAMATO",
      "STELE"
    ],
    "Processo Mental": [
      "MEDO",
      "COMPREENSÃO"
    ],
    "Parte do Corpo, Órgão ou Componente Orgânico": [
      "OVÁRIO",
      "VAGINA"
    ],
    "Substância Química Orgânica": [
      "RIVOTRIL",
      "TOPIRAMATO"
    ],
    "Disfunção Mental ou Comportamental": [
      "ESQUIZOFRENIA",
      "BIPOLARIDADE"
    ],
    "Conceito Quantitativo": [
      "2",
      "0"
    ],
    "Procedimento Diagnóstico": [
      "MAMOGRAFIA",
      "INSPEÇÃO",
      "EXAME FÍSICO",
      "MANOBRA DE VALSALVA",
      "EXAME ESPECULAR",
      "TOQUE VAGINAL"
    ],
    "Função de Organismo": [
      "PILIFICAÇÃO",
      "TROFISMO"
    ],
    "Atributo de Organismo": [
      "IDADE"
    ],
    "Atributo Clínico": [
      "IDADE"
    ],
    "Procedimento Laboratorial": [
      "LABORATORIAIS",
      "EXAME DE URINA"
    ],
    "Conceito Qualitativo": [
      "DIFICIL"
    ],
    "Grupo Profissional ou Ocupacional": [
      "R3",
      "Doutor"
    ],
    "Função Patológica": [
      "EFEITOS COLATERAIS"
    ],
    "Organização Relacionada à Saúde": [
      "POSTO DE SAÚDE"
    ],
    "Resultado Laboratorial ou de Teste": [
      "PARCIAL DE URINA NORMAL",
      "UROCULTURA NEGATIVA"
    ]
  },
  "labels": {}
}