{
  "prontuario_id": 166,
  "text": "# VEM APRA AVALIAÇÃO DA RETINA\n# REFERE LASER OD HÁ 2 ANOS\n# BAV OE HÁ 9 MESES\n# RDP AO FOTOCOAGULADA\nECOGRAFIA 27/8/14 OE\nDAP NORMAL // CAVIDADE VITREA PREENCHIDA POR ECOS DEW ALTA REFLETIVIDADE, FORMANDO MEMBRANAS CONTINUAS POUCO MOVEIS, FORMANDO IMAGGEM SUSGESTIVA DE Doutor Vital Brazil , CORÓIDE APARENTEMENTE EM POSIÇAO.\nAVSC\nOD 20/40\nOE MM\nMR\nOD RPD FOTOCOAGULADA, COM HV HV ANTIGOINFERIOR, BOAS AMRCAS DE LASER\nOE OPACIFICAÇÃO VITREA, PROVAVEL HV ANTIGO\nPIO\nOD 15\nOE 16\nBIO\nOD CATARATA\nOE CATARATA\nCD: SOLICITO PRE OP, VVPP DE OE.\nORIENTO SOB RISCOS DA CIRURGIA, DESEJA OPERAR\nRETORNO EM 26/11/2014 COM EXAMES\nR2 Doutor Vital Brazil ",
  "entities": {
    "Parte do Corpo, Órgão ou Componente Orgânico": [
      "RETINA",
      "OD",
      "OE",
      "AO",
      "CORÓIDE"
    ],
    "Procedimento Terapêutico ou Preventivo": [
      "LASER",
      "FOTOCOAGULADA",
      "VVPP",
      "CIRURGIA",
      "OPERAR"
    ],
    "Abreviação": [
      "OD",
      "BAV",
      "OE",
      "RDP",
      "AO",
      "AVSC",
      "MM",
      "MR",
      "RPD",
      "HV",
      "PIO",
      "BIO",
      "CD",
      "VVPP",
      "R2",
      "PRE OP"
    ],
    "Sinal ou Sintoma": [
      "BAV",
      "20/40",
      "HV",
      "OPACIFICAÇÃO VITREA"
    ],
    "Doença ou Síndrome": [
      "RDP",
      "RPD",
      "HV",
      "CATARATA"
    ],
    "Procedimento Diagnóstico": [
      "ECOGRAFIA",
      "AVSC",
      "PIO",
      "BIO"
    ],
    "Grupo Profissional ou Ocupacional": [
      "Doutor",
      "R2"
    ],
    "Conceito Espacial": [
      "ANTIGOINFERIOR"
    ],
    "Conceito Quantitativo": [
      "15",
      "16"
    ],
    "Atividade de Assistência à Saúde": [
      "CD",
      "SOLICITO",
      "ORIENTO",
      "RETORNO"
    ],
    "Procedimento Laboratorial": [
      "EXAMES"
    ],
    "Conceito Temporal": [
      "HÁ 2 ANOS",
      "HÁ 9 MESES"
    ],
    "Resultado Laboratorial ou de Teste": [
      "CAVIDADE VITREA PREENCHIDA POR ECOS DEW ALTA REFLETIVIDADE",
      "MEMBRANAS CONTINUAS POUCO MOVEIS"
    ]
  },
  "labels": {}
}