{
  "prontuario_id": 880,
  "text": "Lucas, 42 ANOS, SERVENTE, \n# PO RETIRADA DE ILIZAROV MID DIA 11/01/16\n# PSA TIBIA\n# OSTEOMIELITE TIBIA\n# FX TIBIA DIREITA - 2005\n# TTO COM FX EST POR 2X EM OUTRO SERVICO E 1X SANTA CASA\n# ALONGAMENTO OSSEO MID REALIZADO EM 10/2013 E RETIRADA MATERIAL EM 06/2014\n# NOVO ILIZAROV - 12/2014\n# COLISÃO MOTO x MOTO COM FRATURA DE TÍBIA HÁ 10 ANOS,TRATAMENTO COM FIXADOR EXTERNO POR 3 MESES, RETIRADA E RECOLOCAÇÃO POR 3X, 2X EM OUTRO SERVIÇO E 1X NA SANTA CASA. ALONGAMENTO ÓSSEO MID REALIZADO EM 10/2013 E RETIRADO 6/2014, FEZ USO DE ROBOFOOT. EM 15/12/14 NOVO ILIZAROV.\n\nS # PACIENTE SEM QUEIXAS. EM USO DE ROBOFOOT. \nO # FO LIMPA SECA E SEM SINAIS FLOGISTICOS\nA # PSA TIBIA DIREITA\nP # MANTER ROBOFOOT, CARGA PARCIAL, RETORNO EM 45 DIAS  COM NOVO RX\n\nR1 Doutor Vital Brazil\n \n \n ",
  "entities": {
    "Conceito Temporal": [
      "PO",
      "HÁ 10 ANOS",
      "45 DIAS"
    ],
    "Abreviação": [
      "PO",
      "MID",
      "TTO",
      "FO",
      "RX",
      "R1",
      "PSA TIBIA",
      "FX EST",
      "ALONGAMENTO OSSEO MID",
      "ALONGAMENTO ÓSSEO",
      "PSA TIBIA DIREITA"
    ],
    "Parte do Corpo, Órgão ou Componente Orgânico": [
      "MID",
      "TIBIA DIREITA"
    ],
    "Procedimento Terapêutico ou Preventivo": [
      "TTO",
      "ILIZAROV",
      "TRATAMENTO",
      "RETIRADA DE ILIZAROV",
      "ALONGAMENTO OSSEO MID",
      "RETIRADA MATERIAL",
      "ALONGAMENTO ÓSSEO"
    ],
    "Atividade de Assistência à Saúde": [
      "REALIZADO",
      "RETIRADA",
      "RECOLOCAÇÃO",
      "RETIRADO",
      "RETORNO"
    ],
    "Dispositivo Médico": [
      "ROBOFOOT",
      "ILIZAROV",
      "FX EST",
      "FIXADOR EXTERNO"
    ],
    "Paciente ou Grupo com Deficiência": [
      "PACIENTE"
    ],
    "Negação": [
      "SEM"
    ],
    "Sinal ou Sintoma": [
      "QUEIXAS",
      "SINAIS FLOGISTICOS"
    ],
    "Lesão ou Envenenamento": [
      "FO",
      "COLISÃO MOTO x MOTO",
      "FRATURA DE TÍBIA"
    ],
    "Achado": [
      "LIMPA",
      "SECA"
    ],
    "Procedimento Diagnóstico": [
      "RX"
    ],
    "Grupo Profissional ou Ocupacional": [
      "R1",
      "Doutor"
    ],
    "Doença ou Síndrome": [
      "OSTEOMIELITE TIBIA"
    ]
  },
  "labels": {}
}