{
  "prontuario_id": 520,
  "text": "Lucas, 52\n\nQP: PACIENTE RELATA BAV PARA PERTO, GRADUAL E PROGRESSIVA. FAZ USO DE ÓCULOS PARA PERTO E LONGE. \nNEGA OUTRAS QUEIXAS.\nNEGA USO DE COLIRIO.\n\nHMP: NEGA COMORBIDADES.\nNEGA CX OU TRAUMA OCULAR PRÉVIO.\n\nHF. NEGA FAMILIARES COM GLAUCOMA OU CEGUEIRA.\n\nÓCULOS\tOD +2,50 -1,00 110\n\t        OE +2,25 ESF\n\t        AD +2,25\n\nAVSC AO 20/20\n\nAVCC J1\n\nTOL\tOD +2,50 -1,00 110 / 20/20\n\tOE +2,25 ESF // 20/20\n\tAD +2,25 / J1\n\nBIO\tAO CA CALMA E FORMADA, PUPILAS FR, BUT <5S\n\nPIO\t12/12\n\nFO\tAO PAPILA E MÁCULA NORMAIS\n\nCD\nNÃO PRESCREVO ÓCULOS.\nPRESCREVO LACRIFILM\nORIENTO IR AO HUC SE ALTERAÇÃO AGUDA DA VISAO.\nORIENTO RETORNO ANUAL VIA UBS.\n\nR1 Doutor Vital Brazil\n \n \n \n ",
  "entities": {
    "Paciente ou Grupo com Deficiência": [
      "PACIENTE"
    ],
    "Sinal ou Sintoma": [
      "BAV",
      "QUEIXAS"
    ],
    "Abreviação": [
      "BAV",
      "CX",
      "OD",
      "OE",
      "AVSC",
      "AO",
      "AVCC",
      "J1",
      "TOL",
      "BIO",
      "FR",
      "BUT",
      "&lt;5S",
      "PIO",
      "FO",
      "CD",
      "UBS",
      "R1",
      "CA CALMA E FORMADA"
    ],
    "Conceito Qualitativo": [
      "GRADUAL",
      "PROGRESSIVA"
    ],
    "Dispositivo Médico": [
      "ÓCULOS",
      "PRESCREVO ÓCULOS"
    ],
    "Negação": [
      "NEGA",
      "NÃO"
    ],
    "Substância Farmacológica": [
      "COLIRIO",
      "LACRIFILM"
    ],
    "Procedimento Terapêutico ou Preventivo": [
      "CX"
    ],
    "Grupo Familiar": [
      "FAMILIARES"
    ],
    "Doença ou Síndrome": [
      "GLAUCOMA"
    ],
    "Achado": [
      "CEGUEIRA",
      "FR"
    ],
    "Parte do Corpo, Órgão ou Componente Orgânico": [
      "OD",
      "OE",
      "AO",
      "PUPILAS"
    ],
    "Resultado Laboratorial ou de Teste": [
      "ESF",
      "12/12",
      "CA CALMA E FORMADA",
      "PAPILA E MÁCULA NORMAIS"
    ],
    "Atividade de Assistência à Saúde": [
      "AD",
      "CD",
      "PRESCREVO",
      "ORIENTO",
      "RETORNO",
      "PRESCREVO ÓCULOS"
    ],
    "Procedimento Diagnóstico": [
      "AVSC",
      "AVCC",
      "TOL",
      "BIO",
      "BUT",
      "PIO",
      "FO"
    ],
    "Atributo Clínico": [
      "AVSC",
      "AVCC"
    ],
    "Conceito Quantitativo": [
      "20/20",
      "&lt;5S",
      "+2 , 50 -1 , 00 110",
      "+2 , 50 -1 , 00 110 / 20/20",
      "+2 , 25"
    ],
    "Conceito Temporal": [
      "ANUAL"
    ],
    "Organização Relacionada à Saúde": [
      "UBS"
    ],
    "Grupo Profissional ou Ocupacional": [
      "R1",
      "Doutor"
    ],
    "Lesão ou Envenenamento": [
      "TRAUMA OCULAR"
    ]
  },
  "labels": {}
}