{
  "prontuario_id": 562,
  "text": "S # PCTE ENCAMINHADO POR RONCOPATIA; REFERE CANSAÇO E SONOLÊNCIA DIURNA, COCHILA QUANDO SENTA-SE E SONOLÊNCIA ENQUANTO DIRIGE; NEGA HISTÓRIA REFERIDA POR TERCEIROS DE APNÉIA DURANTE O SONO; NEGA HAS; REFERE SINTOMAS DE RA, PRURIDO NASAL, OBSTRUÇÃO, ENTRE OUTROS; NEGA USO DE MEDICAÇÕES, ALERGIAS E OUTROS\n\nO # RINO: DS DIREITO ANTERIOR, DS ESQUERDO ALTO, HCCI;\nORO: AMIGDALAS G1, MALLAMPATI 3-4\nOTO: NDN\nIMC < 27\n\nPOLISSONOGRAFIA (11/03/2015)\n\nLATENCIA NORMAL PARA O SONO E PARA O SONO REM\nEFICIENCIA DO SONO ADEQUADA\nARQUITETURA DO SONO MOSTRA AUMENTO DE ESTAGIO N1 E N3 E DIMINUIÇÃO DE ESTAGIO N2 E DE SONO REM\nINDICE DE DESPERTARES AUMENTADO RELACIONADO A EVENTOS RESPIRATÓRIOS.\nSINDROME DE APNEIA OBSTRUTIVA DO SONO DE GRAU MODERADO (IAH 28,4/H) COM DESSATURAÇÃO DA OXI-HEMOGLOBINA\nPRESENÇA DE RONCOS\n\nEE MAIOR QUE 10\n\nCD # AGENDO SEPTOPLASTIA METZ PARA DIA 19/06/15. ORIENTO RISCOS E BENEFICIOS DA CIRURGIA. SOLICITO A+I\n\nR1 Doutor Vital Brazil ",
  "entities": {
    "Paciente ou Grupo com Deficiência": [
      "PCTE"
    ],
    "Abreviação": [
      "PCTE",
      "HAS",
      "RINO",
      "HCCI",
      "ORO",
      "OTO",
      "NDN",
      "CD",
      "R1",
      "SINTOMAS DE RA",
      "DS DIREITO ANTERIOR",
      "DS ESQUERDO ALTO",
      "IMC &lt; 27"
    ],
    "Atividade de Assistência à Saúde": [
      "ENCAMINHADO",
      "CD",
      "AGENDO",
      "ORIENTO"
    ],
    "Doença ou Síndrome": [
      "RONCOPATIA",
      "HAS",
      "HCCI",
      "APNÉIA DURANTE O SONO",
      "SINDROME DE APNEIA OBSTRUTIVA DO SONO DE GRAU MODERADO"
    ],
    "Sinal ou Sintoma": [
      "CANSAÇO",
      "SONOLÊNCIA",
      "OBSTRUÇÃO",
      "SONOLÊNCIA DIURNA",
      "SINTOMAS DE RA",
      "PRURIDO NASAL",
      "DESSATURAÇÃO DA OXI-HEMOGLOBINA"
    ],
    "Negação": [
      "NEGA"
    ],
    "Substância Farmacológica": [
      "MEDICAÇÕES"
    ],
    "Função Patológica": [
      "ALERGIAS"
    ],
    "Procedimento Diagnóstico": [
      "RINO",
      "ORO",
      "OTO",
      "POLISSONOGRAFIA"
    ],
    "Resultado Laboratorial ou de Teste": [
      "HCCI",
      "NDN",
      "DS DIREITO ANTERIOR",
      "DS ESQUERDO ALTO",
      "AMIGDALAS G1",
      "MALLAMPATI 3-4",
      "LATENCIA NORMAL PARA O SONO E PARA O SONO REM",
      "EFICIENCIA DO SONO ADEQUADA",
      "ARQUITETURA DO SONO MOSTRA AUMENTO DE ESTAGIO N1 E N3",
      "DIMINUIÇÃO DE ESTAGIO N2 E DE SONO REM",
      "INDICE DE DESPERTARES AUMENTADO RELACIONADO A EVENTOS RESPIRATÓRIOS"
    ],
    "Achado": [
      "BENEFICIOS",
      "COCHILA QUANDO SENTA-SE",
      "IMC &lt; 27"
    ],
    "Procedimento Terapêutico ou Preventivo": [
      "CIRURGIA",
      "SEPTOPLASTIA METZ"
    ],
    "Grupo Profissional ou Ocupacional": [
      "R1",
      "Doutor"
    ],
    "Conceito Quantitativo": [
      "MAIOR QUE 10"
    ]
  },
  "labels": {}
}