{
  "prontuario_id": 938,
  "text": "Lucas, 51 ANOS, DONA DE CASA, CASADA, PROCEDENTE DE CURITIBA\nQP: \" HERNIA INCISIONAL E EXCESSO DE PELE PÓS BARIÁTRICA \"\nPACIENTE RELATA QUE HA 4 ANOS REALIZOU CX BARIÁTRICA E HÁ UM ANO NOTOU APARECIMENTO DE UMA HERNIA NA CICATRIZ BARIÁTRICA. NEGA DOR E PRURIDO, MAS RELATA MUITO DESCONFORTO MESMO USANDO A CINTA DIARIAMENTE. PACIENTE RELATA TAMBÉM DESCONFORTO PELO EXCESSO DE PELE EM BRAÇO E BARRIGA APÓS A CIRURGIA BARIÁTRICA.\nEF: HÉRNIA INCISIONAL PÓS BARIÁTRICA EM MESOGASTRIO (PARTE DISTAL DA INCISÃO), NAO PULSÁTIL, SIMÉTRICA QUE AUMENTA COM A MANOBRA DE VALSALVA. ABDOME COM EXCESSO DE PELE  E ESTRIAS.\n \n \n \n ",
  "entities": {
    "Sinal ou Sintoma": [
      "QP",
      "DOR",
      "PRURIDO",
      "DESCONFORTO",
      "PULSÁTIL",
      "EXCESSO DE PELE"
    ],
    "Abreviação": [
      "QP",
      "BARIÁTRICA",
      "EF",
      "CX BARIÁTRICA"
    ],
    "Conceito Temporal": [
      "PÓS",
      "DIARIAMENTE",
      "APÓS",
      "HA 4 ANOS",
      "HÁ UM ANO"
    ],
    "Procedimento Terapêutico ou Preventivo": [
      "BARIÁTRICA",
      "INCISÃO",
      "CX BARIÁTRICA",
      "CIRURGIA BARIÁTRICA"
    ],
    "Paciente ou Grupo com Deficiência": [
      "PACIENTE"
    ],
    "Função Patológica": [
      "CICATRIZ"
    ],
    "Negação": [
      "NEGA",
      "NAO"
    ],
    "Dispositivo Médico": [
      "CINTA"
    ],
    "Parte do Corpo, Órgão ou Componente Orgânico": [
      "BRAÇO",
      "BARRIGA",
      "ABDOME"
    ],
    "Localização ou Região Corporal": [
      "MESOGASTRIO"
    ],
    "Conceito Espacial": [
      "DISTAL"
    ],
    "Achado": [
      "SIMÉTRICA",
      "EXCESSO DE PELE"
    ],
    "Anormalidade Adquirida": [
      "ESTRIAS"
    ],
    "Procedimento Diagnóstico": [
      "MANOBRA DE VALSALVA"
    ]
  },
  "labels": {}
}