{
  "prontuario_id": 975,
  "text": "02:19: lúcida, chorosa, disfásica, em repouso no leito, apresenta edema em região craniana, hemiparesia à direita, afebril até o momento, sem queixas álgicas, aceita dieta via oral, diurese presente, seguem cuidados. Sem acompanhante. NEOPLASIA BENIGNA DO ENCÉFALO INFRATENTORIAL. 08:30: PROVENIENTE DO INTERNAMENTO, ACOMPANHADO PELA FAMILIAR, CONSCIENTE, ORIENTADO, VERBALIZA, DEAMBULA, AFEBRIL, EUPNÉICO, SEM QUEIXAS, REFERE HIPERTENSÃO E DIABETES EM USO DE INSULINA. INTERNA PARA REALIZAÇÃO DE COLONOSCOPIA E EDA, AGENDADOS PARA DIA 24/08/2010. AGUARDA CONDUTA MÉDICA. ENF FLORENCE. OUTROS TRANSTORNOS DO APARELHO DIGESTIVO PÓS-CIRÚRGICOS NÃO CLASSIFICADOS EM OUTRA PARTE. 18:20: REALIZADA NOVA TROCA DE RESPIRADOR. APRESENTOU PROBLEMAS. ENFER FLORENCE, COREN XXXX. SEPTICEMIA POR STAPHYLOCOCCUS AUREUS. 14:25h: Glagsow 6, pupilas isocóricas fotorreagentes. SNE com infusão de dieta 75ml/h. Suporte de O2 sob traqueostomia, aspiração de secreção amarelada em média quantidade. Presença de soluços. CPP com roncos difusos. Abdômem flácido, RHA+. Acesso venoso em MSE com infusão de soroterapia. SVD com diurese efetiva, evacuação ausente. Lesão em região sacra estágio I. Uso de colchão de ar. Flictenas em região de calcâneos. Extremidades aquecidas e bem perfundidas, edema em membros Cacifo +3/+. Monitorizado continuamente com parâmetros de PA não invasiva, cardioscopia e oximetria de pulso. Segue sob cuidados intensivos. Enfª Florence. INSUFICIÊNCIA RESPIRATÓRIA AGUDA.",
  "entities": {
    "Achado": [
      "lúcida",
      "chorosa",
      "afebril",
      "CONSCIENTE",
      "ORIENTADO",
      "VERBALIZA",
      "DEAMBULA",
      "AFEBRIL",
      "EUPNÉICO",
      "RHA+",
      "repouso no leito",
      "sem queixas álgicas",
      "diurese presente",
      "SEM QUEIXAS",
      "pupilas isocóricas fotorreagentes",
      "diurese efetiva",
      "evacuação ausente",
      "Extremidades aquecidas",
      "bem perfundidas"
    ],
    "Sinal ou Sintoma": [
      "disfásica",
      "edema",
      "hemiparesia",
      "PROBLEMAS",
      "soluços",
      "Flictenas",
      "Glagsow 6",
      "roncos difusos",
      "Cacifo +3/+"
    ],
    "Negação": [
      "afebril",
      "Sem",
      "AFEBRIL",
      "NÃO",
      "sem queixas álgicas",
      "SEM QUEIXAS",
      "evacuação ausente",
      "não invasiva"
    ],
    "Atividade de Assistência à Saúde": [
      "cuidados",
      "INTERNAMENTO",
      "INTERNA",
      "cuidados intensivos"
    ],
    "Grupo Populacional": [
      "acompanhante"
    ],
    "Grupo Familiar": [
      "acompanhante",
      "FAMILIAR"
    ],
    "Doença ou Síndrome": [
      "HIPERTENSÃO",
      "DIABETES",
      "SEPTICEMIA",
      "TRANSTORNOS DO APARELHO DIGESTIVO",
      "INSUFICIÊNCIA RESPIRATÓRIA AGUDA"
    ],
    "Conceito Funcional": [
      "USO",
      "Uso"
    ],
    "Substância Farmacológica": [
      "INSULINA"
    ],
    "Hormônio": [
      "INSULINA"
    ],
    "Aminoácido, Peptídeo ou Proteína": [
      "INSULINA"
    ],
    "Procedimento Diagnóstico": [
      "COLONOSCOPIA",
      "EDA",
      "Monitorizado",
      "cardioscopia",
      "oximetria de pulso"
    ],
    "Abreviação": [
      "EDA",
      "ENF",
      "ENFER",
      "SNE",
      "CPP",
      "RHA+",
      "MSE",
      "SVD",
      "PA",
      "Suporte de O2"
    ],
    "Conceito Temporal": [
      "PÓS-CIRÚRGICOS",
      "continuamente"
    ],
    "Procedimento Terapêutico ou Preventivo": [
      "SNE",
      "traqueostomia",
      "aspiração",
      "SVD",
      "dieta via oral",
      "TROCA DE RESPIRADOR",
      "infusão de dieta 75ml/h",
      "Suporte de O2",
      "Acesso venoso",
      "infusão de soroterapia"
    ],
    "Localização ou Região Corporal": [
      "Abdômem",
      "MSE",
      "membros",
      "região craniana",
      "região sacra",
      "região de calcâneos"
    ],
    "Dispositivo Médico": [
      "SVD",
      "Acesso venoso",
      "colchão de ar"
    ],
    "Lesão ou Envenenamento": [
      "Lesão",
      "Flictenas"
    ],
    "Parte do Corpo, Órgão ou Componente Orgânico": [
      "membros"
    ],
    "Processo Neoplásico": [
      "NEOPLASIA BENIGNA DO ENCÉFALO INFRATENTORIAL"
    ],
    "Bactéria": [
      "STAPHYLOCOCCUS AUREUS"
    ],
    "Resultado Laboratorial ou de Teste": [
      "Glagsow 6"
    ],
    "Substância Corporal": [
      "secreção amarelada"
    ],
    "Conceito Quantitativo": [
      "média quantidade"
    ]
  },
  "labels": {
    "bem perfundidas": {
      "capitulo": "15.100"
    },
    "acompanhante": {
      "capitulo": "24.400"
    },
    "lesão": {
      "capitulo": "22.100"
    },
    "interna": {
      "capitulo": "24.400"
    },
    "evacuação ausente": {
      "capitulo": "13.100"
    },
    "edema": {
      "capitulo": "15.100"
    },
    "sne": {
      "capitulo": "12.100"
    },
    "aspiração": {
      "capitulo": "12.100"
    },
    "neoplasia benigna do encéfalo infratentorial": {
      "capitulo": "02.100"
    },
    "membros": {
      "capitulo": "15.100"
    },
    "sem queixas álgicas": {
      "capitulo": "21.800"
    },
    "abdômem": {
      "capitulo": "13.100"
    },
    "diabetes": {
      "capitulo": "05.100"
    },
    "svd": {
      "capitulo": "13.100"
    },
    "roncos difusos": {
      "capitulo": "12.100"
    },
    "infusão de dieta 75ml/h": {
      "capitulo": "24.400"
    },
    "cacifo +3/+": {
      "capitulo": "15.100"
    },
    "orientado": {
      "capitulo": "21.800"
    },
    "verbaliza": {
      "capitulo": "21.800"
    },
    "disfásica": {
      "capitulo": "21.800"
    },
    "transtornos do aparelho digestivo": {
      "capitulo": "13.100"
    },
    "sem queixas": {
      "capitulo": "21.800"
    },
    "hipertensão": {
      "capitulo": "11.500"
    },
    "pós-cirúrgicos": {
      "capitulo": "22.100"
    },
    "enf": {
      "capitulo": "24.400"
    },
    "cardioscopia": {
      "capitulo": "12.100"
    },
    "diurese efetiva": {
      "capitulo": "13.100"
    },
    "colonoscopia": {
      "capitulo": "13.100"
    },
    "mse": {
      "capitulo": "24.400"
    },
    "pa": {
      "capitulo": "11.500"
    },
    "continuamente": {
      "capitulo": "21.800"
    },
    "não invasiva": {
      "capitulo": "21.800"
    },
    "acesso venoso": {
      "capitulo": "11.500"
    },
    "pupilas isocóricas fotorreagentes": {
      "capitulo": "09.800"
    },
    "deambula": {
      "capitulo": "21.800"
    },
    "troca de respirador": {
      "capitulo": "22.100"
    },
    "traqueostomia": {
      "capitulo": "12.100"
    },
    "média quantidade": {
      "capitulo": "21.800"
    },
    "cuidados intensivos": {
      "capitulo": "24.400"
    },
    "repouso no leito": {
      "capitulo": "21.800"
    },
    "cpp": {
      "capitulo": "12.100"
    },
    "região craniana": {
      "capitulo": "08.100"
    },
    "oximetria de pulso": {
      "capitulo": "12.100"
    },
    "chorosa": {
      "capitulo": "21.800"
    },
    "insuficiência respiratória aguda": {
      "capitulo": "12.100"
    },
    "lúcida": {
      "capitulo": "21.800"
    },
    "extremidades aquecidas": {
      "capitulo": "15.100"
    },
    "rha+": {
      "capitulo": "15.100"
    },
    "uso": {
      "capitulo": "24.400"
    },
    "familiar": {
      "capitulo": "24.400"
    },
    "cuidados": {
      "capitulo": "24.400"
    },
    "suporte de o2": {
      "capitulo": "12.100"
    },
    "flictenas": {
      "capitulo": "14.100"
    },
    "insulina": {
      "capitulo": "05.100"
    },
    "glagsow 6": {
      "capitulo": "21.800"
    },
    "região sacra": {
      "capitulo": "08.100"
    },
    "dieta via oral": {
      "capitulo": "24.400"
    },
    "região de calcâneos": {
      "capitulo": "14.100"
    },
    "colchão de ar": {
      "capitulo": "22.100"
    },
    "consciente": {
      "capitulo": "21.800"
    }
  }
}