{
  "prontuario_id": 297,
  "text": "16/05/2007, 08:56h: Sonolento, pouco responsivo. Mantém SOG para alimentação por bomba infusora. À ausculta abdominal, RHA+. Abdome plano, flácido, indolor à palpação. CONCUSSÃO CEREBRAL. Paciente consciente, orientado, comunicativo, deambulando. Nega queixas. Aviso Dr Vital Brasil, da Otorrino, sobre PC. Florence. TRAUMATISMOS MÚLTIPLOS NÃO ESPECIFICADOS. Refere diurese presente com hematúria (SIC). CUIDADO MÉDICO NÃO ESPECIFICADO. 15:02: CORADA, ALERTA, COMUNICATIVA, ORIENTADA, EM REPOUSO NO LEITO, MANTÉM JEJUM PARA NOVA COLONOSCOPIA, POIS A MESMA FOI REALIZADA SEM SUCESSO, A MESMA FICOU PARA QUINTA-FEIRA. 13/09/07, ÀS 15:20, ORIENTADA A PCTE SOBRE O PROCEDIMANTO, AVP EM MSD SALINIZADO, SSV. NEOPLASIA MALIGNA DO CÉREBRO EXCETO LOBOS E VENTRÍCULOS. Pcte com cultura de Secreção Tibial do dia 06/07/07, com crescimento de MRSA. Instaurar Precaução de Contato até cultura negativa. AUSÊNCIA DE CONSOLIDAÇÃO DA FRATURA PSEUDOARTROSE. 10:20: TORPOROSA, NÃO COMUNICATIVA, SNE 50ML/H EM BI, TRAQUEOSTOMIA COM NÉVOA ÚMIDA, ASPIRAÇÃO EM TRAQUEO, ACESSO CENTRAL EM SUBCLÁVIA ESQ, SVD 100ML, EVACUAÇÕES AUSENTES. SEGUEM CUIDADOS. HEMORRAGIA SUBARACNÓIDE PROVENIENTE DA ARTÉRIA CEREBRAL MÉDIA.",
  "entities": {
    "Sinal ou Sintoma": [
      "Sonolento",
      "hematúria",
      "TORPOROSA",
      "pouco responsivo"
    ],
    "Abreviação": [
      "SOG",
      "RHA+",
      "PC",
      "PCTE",
      "PROCEDIMANTO",
      "AVP",
      "MSD",
      "SSV",
      "Pcte",
      "SNE",
      "50ML/H",
      "BI",
      "SVD",
      "crescimento de MRSA"
    ],
    "Dispositivo Médico": [
      "SOG",
      "AVP",
      "SNE",
      "BI",
      "SVD",
      "bomba infusora",
      "ACESSO CENTRAL"
    ],
    "Procedimento Terapêutico ou Preventivo": [
      "SOG",
      "JEJUM",
      "AVP",
      "SALINIZADO",
      "SNE",
      "SVD",
      "Precaução de Contato",
      "ASPIRAÇÃO EM TRAQUEO",
      "ACESSO CENTRAL"
    ],
    "Achado": [
      "RHA+",
      "flácido",
      "consciente",
      "orientado",
      "comunicativo",
      "deambulando",
      "hematúria",
      "CORADA",
      "ALERTA",
      "COMUNICATIVA",
      "ORIENTADA",
      "JEJUM",
      "diurese presente",
      "REPOUSO NO LEITO"
    ],
    "Localização ou Região Corporal": [
      "Abdome",
      "MSD"
    ],
    "Procedimento Diagnóstico": [
      "palpação",
      "COLONOSCOPIA",
      "ausculta abdominal"
    ],
    "Paciente ou Grupo com Deficiência": [
      "Paciente",
      "PCTE",
      "Pcte"
    ],
    "Ocupação ou Disciplina Biomédica": [
      "Otorrino"
    ],
    "Negação": [
      "SEM",
      "NÃO ESPECIFICADOS",
      "NÃO ESPECIFICADO",
      "EXCETO LOBOS E VENTRÍCULOS",
      "EVACUAÇÕES AUSENTES"
    ],
    "Doença ou Síndrome": [
      "PSEUDOARTROSE",
      "HEMORRAGIA SUBARACNÓIDE"
    ],
    "Parte do Corpo, Órgão ou Componente Orgânico": [
      "SUBCLÁVIA",
      "EXCETO LOBOS E VENTRÍCULOS",
      "ARTÉRIA CEREBRAL MÉDIA"
    ],
    "Conceito Espacial": [
      "ESQ"
    ],
    "Atividade de Assistência à Saúde": [
      "CUIDADOS",
      "CUIDADO MÉDICO"
    ],
    "Lesão ou Envenenamento": [
      "CONCUSSÃO CEREBRAL",
      "TRAUMATISMOS MÚLTIPLOS"
    ],
    "Processo Neoplásico": [
      "NEOPLASIA MALIGNA DO CÉREBRO"
    ],
    "Resultado Laboratorial ou de Teste": [
      "cultura negativa"
    ]
  },
  "labels": {
    "abdome": {
      "capitulo": "13"
    },
    "artéria cerebral média": {
      "capitulo": "08"
    },
    "aspiração em traqueo": {
      "capitulo": "08"
    },
    "ausculta abdominal": {
      "capitulo": "13"
    },
    "bomba infusora": {
      "capitulo": "05"
    },
    "colonoscopia": {
      "capitulo": "13"
    },
    "concussão cerebral": {
      "capitulo": "08"
    },
    "crescimento de mrsa": {
      "capitulo": "01"
    },
    "cultura negativa": {
      "capitulo": "01"
    },
    "cuidado médico": {
      "capitulo": "08"
    },
    "cuidados": {
      "capitulo": "08"
    },
    "deambulando": {
      "capitulo": "21"
    },
    "diurese presente": {
      "capitulo": "13"
    },
    "evacuações ausentes": {
      "capitulo": "21"
    },
    "exceto lobos e ventrículos": {
      "capitulo": "02"
    },
    "flácido": {
      "capitulo": "15"
    },
    "hematúria": {
      "capitulo": "13"
    },
    "hemorragia subaracnóide": {
      "capitulo": "08"
    },
    "jejum": {
      "capitulo": "05"
    },
    "não especificados": {
      "capitulo": "21"
    },
    "não especificado": {
      "capitulo": "21"
    },
    "orientada": {
      "capitulo": "21"
    },
    "orientado": {
      "capitulo": "21"
    },
    "otorrino": {
      "capitulo": "10"
    },
    "palpação": {
      "capitulo": "15"
    },
    "pc": {
      "capitulo": "08"
    },
    "pcte": {
      "capitulo": "08"
    },
    "precaução de contato": {
      "capitulo": "21"
    },
    "pseudoartrose": {
      "capitulo": "15"
    },
    "repouso no leito": {
      "capitulo": "21"
    },
    "salinizado": {
      "capitulo": "05"
    },
    "sne": {
      "capitulo": "08"
    },
    "sonolento": {
      "capitulo": "21"
    },
    "ssv": {
      "capitulo": "01"
    },
    "subclávia": {
      "capitulo": "11"
    },
    "torporosa": {
      "capitulo": "21"
    }
  }
}