{
  "prontuario_id": 306,
  "text": "ÀS 17:59 HR: CONSCIENTE, ORIENTADO, VERBALIZANDO, EM REPOUSO NO LEITO. SEM QUEIXAS ÁLGICAS NO MOMENTO. REFERE BOA ACEITAÇÃO DA DIETA VO. MANTÉM ACESSO VENOSO PERIFÉRICO EM MSE HEPARINIZADO. APRESENTA ÚLCERA DE PRESSÃO EM REGIÃO SACRA SEM PRESENÇA DE SECREÇÃO. FRATURA DA EXTREMIDADE DISTAL DO FEMUR. Às 7h: Paciente apresenta grande quantidade de secrecão traqueobrônquica, de aspecto espesso; aspirada com frequência. INFECCAO DO TRATO URINARIO DE LOCALIZACAO NAO ESPECIFICADA. Às 11:04: 5° DI COM HX DE ICC + DM + HAS + COLECISTITE. NO MOMENTO, CONSCIENTE, ORIENTADA, CALMA, EUPNEICA, RESPIRANDO EM AR AMBIENTE, COMUNICATIVA, DEAMBULANDO, REFERE ALGIA EM REGIÃO GLÚTEA APÓS QUEDA, ACEITANDO BEM A DIETA, ELIMINAÇÕES PRESENTES, SEM QUEIXAS MA. INSUFICIENCIA CARDIACA CONGESTIVA. Às 12:05: Paciente 1º PO FX fêmur E, referindo algia moderada MIE, consciente, orientado, calmo, comunicativo, restrito ao leito, fazendo uso de colar cervical ajustado, aceitando bem dieta VO, hipocorado, eupneico, normotenso, normocardico, afebril, com aces. TRAUMATISMOS MULTIPLOS NAO ESPECIFICADOS.",
  "entities": {
    "Achado": [
      "CONSCIENTE",
      "ORIENTADO",
      "VERBALIZANDO",
      "ORIENTADA",
      "CALMA",
      "EUPNEICA",
      "COMUNICATIVA",
      "DEAMBULANDO",
      "QUEDA",
      "consciente",
      "orientado",
      "calmo",
      "comunicativo",
      "hipocorado",
      "eupneico",
      "normotenso",
      "normocardico",
      "afebril",
      "REPOUSO NO LEITO",
      "PRESENÇA DE SECREÇÃO",
      "RESPIRANDO EM AR AMBIENTE",
      "ACEITANDO BEM A DIETA",
      "ELIMINAÇÕES PRESENTES",
      "restrito ao leito"
    ],
    "Localização ou Região Corporal": [
      "MSE",
      "MIE",
      "REGIÃO SACRA",
      "REGIÃO GLÚTEA"
    ],
    "Abreviação": [
      "MSE",
      "DI",
      "DM",
      "HAS",
      "PO",
      "MIE",
      "aces",
      "DIETA",
      "HX DE ICC",
      "QUEIXAS MA",
      "dieta VO"
    ],
    "Procedimento Terapêutico ou Preventivo": [
      "HEPARINIZADO",
      "aces",
      "REPOUSO NO LEITO",
      "DIETA",
      "ACESSO VENOSO PERIFÉRICO",
      "restrito ao leito",
      "colar cervical ajustado",
      "dieta VO"
    ],
    "Conceito Qualitativo": [
      "HEPARINIZADO",
      "aspecto espesso"
    ],
    "Paciente ou Grupo com Deficiência": [
      "Paciente"
    ],
    "Conceito Quantitativo": [
      "frequência",
      "grande quantidade"
    ],
    "Doença ou Síndrome": [
      "DM",
      "HAS",
      "COLECISTITE",
      "ÚLCERA DE PRESSÃO",
      "INFECCAO DO TRATO URINARIO",
      "HX DE ICC",
      "INSUFICIENCIA CARDIACA CONGESTIVA"
    ],
    "Sinal ou Sintoma": [
      "ALGIA",
      "QUEIXAS ÁLGICAS",
      "algia moderada"
    ],
    "Conceito Temporal": [
      "APÓS",
      "PO",
      "NO MOMENTO"
    ],
    "Conceito Funcional": [
      "uso"
    ],
    "Negação": [
      "afebril"
    ],
    "Dispositivo Médico": [
      "aces",
      "ACESSO VENOSO PERIFÉRICO"
    ],
    "Alimento": [
      "DIETA"
    ],
    "Lesão ou Envenenamento": [
      "FRATURA DA EXTREMIDADE DISTAL DO FEMUR",
      "FX fêmur E",
      "TRAUMATISMOS MULTIPLOS"
    ],
    "Substância Corporal": [
      "secrecão traqueobrônquica"
    ],
    "Função Fisiológica": [
      "ELIMINAÇÕES PRESENTES"
    ]
  },
  "labels": {
    "secrecão traqueobrônquica": {
      "capitulo": "12"
    },
    "fratura da extremidade distal do femur": {
      "capitulo": "15"
    },
    "colecistite": {
      "capitulo": "13"
    },
    "traumatismos multiplos": {
      "capitulo": "22"
    },
    "infeccao do trato urinario": {
      "capitulo": "16"
    },
    "has": {
      "capitulo": "15"
    },
    "di": {
      "capitulo": "21"
    },
    "hx de icc": {
      "capitulo": "11"
    },
    "dieta vo": {
      "capitulo": "24"
    },
    "mse": {
      "capitulo": "21"
    },
    "aceitando bem a dieta": {
      "capitulo": "24"
    },
    "heparinizado": {
      "capitulo": "21"
    },
    "paciente": {
      "capitulo": "21"
    },
    "queixas álgicas": {
      "capitulo": "21"
    },
    "no momento": {
      "capitulo": "21"
    },
    "região sacra": {
      "capitulo": "15"
    },
    "região glútea": {
      "capitulo": "15"
    },
    "mie": {
      "capitulo": "21"
    },
    "algia moderada": {
      "capitulo": "21"
    },
    "po": {
      "capitulo": "21"
    },
    "fx fêmur e": {
      "capitulo": "15"
    },
    "queda": {
      "capitulo": "22"
    },
    "grande quantidade": {
      "capitulo": "21"
    },
    "presença de secreção": {
      "capitulo": "21"
    },
    "repouso no leito": {
      "capitulo": "21"
    },
    "frequência": {
      "capitulo": "21"
    },
    "aspecto espesso": {
      "capitulo": "21"
    },
    "acesso venoso periférico": {
      "capitulo": "21"
    },
    "orientada": {
      "capitulo": "21"
    },
    "eupneico": {
      "capitulo": "21"
    },
    "normotenso": {
      "capitulo": "21"
    },
    "normocardico": {
      "capitulo": "21"
    },
    "afebril": {
      "capitulo": "21"
    },
    "comunicativa": {
      "capitulo": "21"
    },
    "calma": {
      "capitulo": "21"
    },
    "eupneica": {
      "capitulo": "21"
    },
    "hipocorado": {
      "capitulo": "21"
    },
    "dieta": {
      "capitulo": "24"
    },
    "colar cervical ajustado": {
      "capitulo": "21"
    },
    "restrito ao leito": {
      "capitulo": "21"
    },
    "eliminações presentes": {
      "capitulo": "21"
    }
  }
}