{
  "prontuario_id": 416,
  "text": "Às 00:03: Paciente referindo dificuldade para respirar, consciente, orientado, calmo, comunicativo, em repouso no leito, recebendo oxigênio por catéter nasal a 4 l/min, aceitando pouco dieta VO, acesso venoso periférico MSE salinizado, eliminações fisiológicas. ENFISEMA. Consciente, orientada, ansiosa pela alta, refere lombalgia e algia em MID. Segue sob cuidados de enfermagem. DOR LOMBAR BAIXA. Às 20:00h: Consciente, comunicativo, lucido , orientado, eupneico, afebril, mantêm repouso, até momento sem prescrição médica, comunicado plantão ortopedia. TRAUMATISMOS MULTIPLOS NAO ESPECIFICADOS. Às 10:54 HS: CONSCIENTE, ORIENTADO, LÚCIDO E COMUNICATIVO, POUCO DISPNEICO, PASSOU PARTE DA NOITE EM AR AMBIENTE, SEGUNDO A ESPOSA, SEM ALTERAÇÕES, O2 CONTÍNUO EM CATETER NASAL. AVP EM MSD COM SRT, BOA ACEITAÇÃO ALIMENTAR, RETIRADO SVD. BANHO DE ASPERSÃO E RE. OUTRAS DOENCAS PULMONARES OBSTRUTIVAS CRONICAS.",
  "entities": {
    "Paciente ou Grupo com Deficiência": [
      "Paciente"
    ],
    "Achado": [
      "consciente",
      "orientado",
      "calmo",
      "comunicativo",
      "Consciente",
      "orientada",
      "lucido",
      "eupneico",
      "afebril",
      "repouso",
      "CONSCIENTE",
      "ORIENTADO",
      "LÚCIDO",
      "COMUNICATIVO",
      "AVP",
      "repouso no leito",
      "eliminações fisiológicas",
      "ACEITAÇÃO ALIMENTAR"
    ],
    "Substância Farmacológica": [
      "oxigênio"
    ],
    "Localização ou Região Corporal": [
      "MSE",
      "MID",
      "MSD"
    ],
    "Abreviação": [
      "MSE",
      "MID",
      "AVP",
      "MSD",
      "SRT",
      "4 l/min",
      "dieta VO",
      "RETIRADO SVD"
    ],
    "Procedimento Terapêutico ou Preventivo": [
      "salinizado",
      "AVP",
      "SRT",
      "dieta VO",
      "acesso venoso periférico",
      "O2 CONTÍNUO",
      "RETIRADO SVD",
      "BANHO DE ASPERSÃO E RE"
    ],
    "Conceito Qualitativo": [
      "salinizado",
      "BOA"
    ],
    "Função Patológica": [
      "ENFISEMA"
    ],
    "Doença ou Síndrome": [
      "ENFISEMA",
      "DOENCAS PULMONARES OBSTRUTIVAS CRONICAS"
    ],
    "Atividade de Assistência à Saúde": [
      "alta",
      "cuidados de enfermagem",
      "prescrição médica"
    ],
    "Sinal ou Sintoma": [
      "lombalgia",
      "algia",
      "afebril",
      "DISPNEICO",
      "ALTERAÇÕES",
      "dificuldade para respirar",
      "DOR LOMBAR BAIXA"
    ],
    "Negação": [
      "afebril",
      "sem"
    ],
    "Conceito Quantitativo": [
      "POUCO",
      "4 l/min"
    ],
    "Grupo Familiar": [
      "ESPOSA"
    ],
    "Dispositivo Médico": [
      "AVP",
      "acesso venoso periférico"
    ],
    "Função Fisiológica": [
      "eliminações fisiológicas"
    ],
    "Produto Intelectual": [
      "prescrição médica"
    ],
    "Lesão ou Envenenamento": [
      "TRAUMATISMOS MULTIPLOS"
    ]
  },
  "labels": {
    "lucido": {
      "capitulo": "06.41.10"
    },
    "srt": {
      "capitulo": "05.89.80"
    },
    "boa": {
      "capitulo": "05.89.80"
    },
    "enfisema": {
      "capitulo": "12.09.10"
    },
    "dispneico": {
      "capitulo": "12.09.10"
    },
    "oxigênio": {
      "capitulo": "12.09.10"
    },
    "esposa": {
      "capitulo": "24.84.01"
    },
    "paciente": {
      "capitulo": "24.84.01"
    },
    "doencas pulmonares obstrutivas cronicas": {
      "capitulo": "12.09.10"
    },
    "prescrição médica": {
      "capitulo": "24.84.01"
    },
    "o2 contínuo": {
      "capitulo": "12.09.10"
    },
    "eupneico": {
      "capitulo": "12.09.10"
    },
    "alta": {
      "capitulo": "24.84.01"
    },
    "orientado": {
      "capitulo": "06.41.10"
    },
    "traumatismos multiplos": {
      "capitulo": "22.44.01"
    },
    "salinizado": {
      "capitulo": "24.84.01"
    },
    "calmo": {
      "capitulo": "06.41.10"
    },
    "mse": {
      "capitulo": "24.84.01"
    },
    "dieta vo": {
      "capitulo": "24.84.01"
    },
    "dor lombar baixa": {
      "capitulo": "15.50.10"
    },
    "repouso no leito": {
      "capitulo": "24.84.01"
    },
    "cuidados de enfermagem": {
      "capitulo": "24.84.01"
    },
    "avp": {
      "capitulo": "24.84.01"
    },
    "eliminações fisiológicas": {
      "capitulo": "24.84.01"
    },
    "lúcido": {
      "capitulo": "06.41.10"
    },
    "msd": {
      "capitulo": "24.84.01"
    },
    "dificuldade para respirar": {
      "capitulo": "12.09.10"
    },
    "comunicativo": {
      "capitulo": "06.41.10"
    },
    "repouso": {
      "capitulo": "24.84.01"
    },
    "consciente": {
      "capitulo": "06.41.10"
    },
    "alterações": {
      "capitulo": "24.84.01"
    },
    "pouco": {
      "capitulo": "24.84.01"
    },
    "aceitação alimentar": {
      "capitulo": "24.84.01"
    },
    "lombalgia": {
      "capitulo": "15.50.10"
    },
    "banho de aspersão e re": {
      "capitulo": "24.84.01"
    },
    "4 l/min": {
      "capitulo": "24.84.01"
    },
    "retirado svd": {
      "capitulo": "24.84.01"
    },
    "acesso venoso periférico": {
      "capitulo": "24.84.01"
    },
    "sem": {
      "capitulo": "24.84.01"
    },
    "orientada": {
      "capitulo": "06.41.10"
    },
    "afebril": {
      "capitulo": "05.89.80"
    },
    "mid": {
      "capitulo": "24.84.01"
    },
    "algia": {
      "capitulo": "15.50.10"
    }
  }
}