{
  "prontuario_id": 163,
  "text": "ÀS 15:30: PROVENIENTE DO PS, CONSCIENTE, COMUNICATIVA, ABSCESSO COURO CABELUDO E ORELHA DIREITA, REFERE CEFALEIA, SOLICITADO LIGAÇÃO PARA DR VITAL BRASIL SEM SUCESSO, ENTRADO PLANTÃO DA CLINICA MEDICA. DR VITAL BRASIL PRESCREVEU PARACETAMOL.  MEDICADA, AGUARDO MELHORA. ÀS 18:26: CLIENTE REFERE DOR LEVE EM MID, CONSCIENTE, COMUNICATIVO, EUPNEICO, REPOUSO NO LEITO, ACEITANDO BEM A DIETA, ACESSO PERIFÉRICO EM MSD SALINIZADO, CTVO LIMPO E SECO EM MID, APRESENTANDO MELHORA NO EDEMA, ABDOMEN PLANO E FLÁCIDO, MICÇÃO PRESENTE. ORIENTADO A ENTRAR EM JEJUM A PARTIR DAS 24:00, PARA PROCEDIMENTO CIRURGICO AMANHA, 26/05. ÀS 15:05: CONSCIENTE, COMUNICATIVO, REPOUSO NO LEITO, SSVV ESTAVEIS, REFERE ACEITAR POUCO A DIETA HOSPITALAR, CATÉTER PERIDURAL ANALGESIA. ACESSO VENOSO ANTECUBITAL ESQUERDO SALINIZADO, SEM SINAIS FLOGISTICO. CURATIVO NA REGIÃO INGUINAL ESQUERDA, PÉ COM SECREÇÃO SEROSA POUCA  QUANTIDADE, MANTENDO BOTAS DE ALGODÃO, SVD COM DÉBITO LIMPIDO. SEM QUEIXAS ALGICAS NO MOMENTO. XXXX.",
  "entities": {
    "Abreviação": [
      "PS",
      "MID",
      "MSD",
      "CTVO",
      "SVD",
      "SSVV ESTAVEIS"
    ],
    "Organização Relacionada à Saúde": [
      "PS",
      "PLANTÃO DA CLINICA MEDICA"
    ],
    "Achado": [
      "CONSCIENTE",
      "COMUNICATIVA",
      "COMUNICATIVO",
      "EUPNEICO",
      "LIMPO",
      "SECO",
      "PLANO",
      "FLÁCIDO",
      "REPOUSO NO LEITO",
      "ACEITANDO BEM A DIETA",
      "MELHORA NO EDEMA",
      "MICÇÃO PRESENTE",
      "SSVV ESTAVEIS",
      "DÉBITO LIMPIDO"
    ],
    "Parte do Corpo, Órgão ou Componente Orgânico": [
      "ORELHA",
      "PÉ",
      "COURO CABELUDO"
    ],
    "Conceito Espacial": [
      "DIREITA",
      "ESQUERDO",
      "ESQUERDA"
    ],
    "Sinal ou Sintoma": [
      "CEFALEIA",
      "DOR LEVE",
      "ACEITAR POUCO A DIETA HOSPITALAR",
      "SINAIS FLOGISTICO",
      "QUEIXAS ALGICAS"
    ],
    "Substância Química Orgânica": [
      "PARACETAMOL"
    ],
    "Substância Farmacológica": [
      "PARACETAMOL"
    ],
    "Atividade de Assistência à Saúde": [
      "MEDICADA",
      "ORIENTADO"
    ],
    "Paciente ou Grupo com Deficiência": [
      "CLIENTE"
    ],
    "Localização ou Região Corporal": [
      "MID",
      "MSD",
      "ABDOMEN",
      "ANTECUBITAL"
    ],
    "Conceito Qualitativo": [
      "SALINIZADO",
      "POUCA QUANTIDADE"
    ],
    "Procedimento Terapêutico ou Preventivo": [
      "CTVO",
      "JEJUM",
      "SALINIZADO",
      "CURATIVO",
      "SVD",
      "REPOUSO NO LEITO",
      "ACESSO PERIFÉRICO",
      "PROCEDIMENTO CIRURGICO",
      "CATÉTER PERIDURAL ANALGESIA",
      "ACESSO VENOSO",
      "BOTAS DE ALGODÃO"
    ],
    "Dispositivo Médico": [
      "CTVO",
      "CURATIVO",
      "SVD",
      "ACESSO PERIFÉRICO",
      "CATÉTER PERIDURAL ANALGESIA",
      "ACESSO VENOSO",
      "BOTAS DE ALGODÃO"
    ],
    "Conceito Temporal": [
      "AMANHA",
      "NO MOMENTO"
    ],
    "Função Fisiológica": [
      "MICÇÃO PRESENTE",
      "DÉBITO LIMPIDO"
    ],
    "Substância Corporal": [
      "SECREÇÃO SEROSA"
    ]
  },
  "labels": {
    "flácido": {
      "capitulo": "01"
    },
    "orelha": {
      "capitulo": "14"
    },
    "repouso no leito": {
      "capitulo": "21"
    },
    "curativo": {
      "capitulo": "21"
    },
    "débito limpido": {
      "capitulo": "21"
    },
    "comunicativa": {
      "capitulo": "21"
    },
    "consciente": {
      "capitulo": "21"
    },
    "botas de algodão": {
      "capitulo": "21"
    },
    "catéter peridural analgesia": {
      "capitulo": "21"
    },
    "melhora no edema": {
      "capitulo": "21"
    },
    "couro cabeludo": {
      "capitulo": "21"
    },
    "msd": {
      "capitulo": "21"
    },
    "queixas algicas": {
      "capitulo": "21"
    },
    "amanha": {
      "capitulo": "21"
    },
    "ctvo": {
      "capitulo": "21"
    },
    "salinizado": {
      "capitulo": "21"
    },
    "svd": {
      "capitulo": "21"
    },
    "acesso periférico": {
      "capitulo": "21"
    },
    "paracetamol": {
      "capitulo": "21"
    },
    "dor leve": {
      "capitulo": "21"
    },
    "plano": {
      "capitulo": "21"
    },
    "medicada": {
      "capitulo": "21"
    },
    "pouca quantidade": {
      "capitulo": "21"
    },
    "acesso venoso": {
      "capitulo": "21"
    },
    "cefaleia": {
      "capitulo": "21"
    },
    "jejum": {
      "capitulo": "21"
    },
    "mid": {
      "capitulo": "21"
    },
    "secreção serosa": {
      "capitulo": "21"
    },
    "limpo": {
      "capitulo": "21"
    },
    "abdomen": {
      "capitulo": "21"
    },
    "direita": {
      "capitulo": "21"
    },
    "antecubital": {
      "capitulo": "21"
    },
    "aceitando bem a dieta": {
      "capitulo": "21"
    },
    "ps": {
      "capitulo": "21"
    },
    "sinais flogistico": {
      "capitulo": "21"
    },
    "esquerdo": {
      "capitulo": "21"
    },
    "cliente": {
      "capitulo": "21"
    },
    "aceitar pouco a dieta hospitalar": {
      "capitulo": "21"
    },
    "micção presente": {
      "capitulo": "21"
    },
    "no momento": {
      "capitulo": "21"
    },
    "eupneico": {
      "capitulo": "21"
    },
    "procedimento cirurgico": {
      "capitulo": "21"
    },
    "esquerda": {
      "capitulo": "21"
    },
    "orientado": {
      "capitulo": "21"
    },
    "seco": {
      "capitulo": "21"
    },
    "comunicativo": {
      "capitulo": "21"
    },
    "pé": {
      "capitulo": "21"
    }
  }
}