{
  "prontuario_id": 405,
  "text": "ÀS 03:50 H: CLIENTE REALIZOU RNM DE CRANIO NO CEDIP, SEGUNDO INFORMAÇÕES RECEBIDAS PELA FUNCIONÁRIA MARIA, QUE ACOMPANHOU CLIENTE NA REMOÇÃO, QUADRO DA CLIENTE GRAVE, SENDO COMUNICADO DRº VITAL BRASIL, DA NEURO. FILMES NA UNIDADE, SEM LAUDO. SEGUE LUCIDA, COMUNICATIVA, REPOUSO, EUPNEICA, AFEBRIL. NEGA CEFALEIA, EMESE. SEGUE EM OBSERVAÇÃO E CUIDADOS. Às 11:30h: Dormindo, repouso no leito, febril, sudoreico, traqueostomizado, ar ambiente, aspirado media quantidade de secreção de aspecto purulento, gastrostomia funcionante com dietoterapia, acesso venoso em MSD com SRT em curso, uso de fralda para eliminações, precaução por contato. Às 16:03: 1° di com hx de agressão + fx de orbita esquerda. No momento, consciente, orientado, calmo, eupneico, respirando em ar ambiente, comunicativo, em repouso no leito, acesso venoso em mse com soroterapia em curso, apresenta hematoma + edema em região orbital bilateral, sutura e curativo em região orbital esquerda, refere algia no local, refere algia também em hemitórax esquerdo, aceitando bem a dieta, eliminações ausentes até o momento, segue sob cuidados. ",
  "entities": {
    "Paciente ou Grupo com Deficiência": [
      "CLIENTE"
    ],
    "Organização Relacionada à Saúde": [
      "CEDIP",
      "NEURO",
      "UNIDADE"
    ],
    "Abreviação": [
      "NEURO",
      "MSD",
      "hx",
      "mse",
      "RNM DE CRANIO",
      "SRT em curso",
      "fx de orbita esquerda"
    ],
    "Resultado Laboratorial ou de Teste": [
      "LAUDO"
    ],
    "Achado": [
      "LUCIDA",
      "COMUNICATIVA",
      "REPOUSO",
      "EUPNEICA",
      "AFEBRIL",
      "Dormindo",
      "traqueostomizado",
      "consciente",
      "orientado",
      "calmo",
      "eupneico",
      "comunicativo",
      "repouso no leito",
      "ar ambiente",
      "respirando em ar ambiente",
      "aceitando bem"
    ],
    "Procedimento Terapêutico ou Preventivo": [
      "REPOUSO",
      "traqueostomizado",
      "aspirado",
      "sutura",
      "curativo",
      "repouso no leito",
      "gastrostomia funcionante com dietoterapia",
      "acesso venoso",
      "SRT em curso",
      "precaução por contato",
      "soroterapia em curso"
    ],
    "Negação": [
      "AFEBRIL",
      "NEGA",
      "ausentes"
    ],
    "Sinal ou Sintoma": [
      "CEFALEIA",
      "EMESE",
      "febril",
      "sudoreico",
      "hematoma",
      "edema",
      "algia",
      "aspecto purulento"
    ],
    "Atividade de Assistência à Saúde": [
      "OBSERVAÇÃO",
      "CUIDADOS",
      "cuidados"
    ],
    "Substância Corporal": [
      "secreção"
    ],
    "Localização ou Região Corporal": [
      "MSD",
      "mse",
      "local",
      "hemitórax"
    ],
    "Objeto Manufaturado": [
      "fralda"
    ],
    "Lesão ou Envenenamento": [
      "agressão",
      "fx de orbita esquerda"
    ],
    "Função Patológica": [
      "hematoma",
      "edema"
    ],
    "Dispositivo Médico": [
      "curativo",
      "acesso venoso"
    ],
    "Conceito Espacial": [
      "esquerda",
      "esquerdo"
    ],
    "Função Fisiológica": [
      "eliminações"
    ],
    "Procedimento Diagnóstico": [
      "RNM DE CRANIO"
    ],
    "Conceito Qualitativo": [
      "media quantidade"
    ],
    "Conceito Temporal": [
      "No momento",
      "até o momento"
    ]
  },
  "labels": {
    "soroterapia em curso": {
      "capitulo": "24"
    },
    "rnm de cranio": {
      "capitulo": "21"
    },
    "aceitando bem": {
      "capitulo": "21"
    },
    "sudoreico": {
      "capitulo": "21"
    },
    "dormindo": {
      "capitulo": "21"
    },
    "ausentes": {
      "capitulo": "21"
    },
    "lucida": {
      "capitulo": "21"
    },
    "edema": {
      "capitulo": "21"
    },
    "unidade": {
      "capitulo": "21"
    },
    "esquerdo": {
      "capitulo": "21"
    },
    "no momento": {
      "capitulo": "21"
    },
    "neuro": {
      "capitulo": "21"
    },
    "eupneico": {
      "capitulo": "21"
    },
    "srt em curso": {
      "capitulo": "24"
    },
    "orientado": {
      "capitulo": "21"
    },
    "comunicativa": {
      "capitulo": "21"
    },
    "mse": {
      "capitulo": "21"
    },
    "calmo": {
      "capitulo": "21"
    },
    "agressão": {
      "capitulo": "23"
    },
    "respirando em ar ambiente": {
      "capitulo": "21"
    },
    "acesso venoso": {
      "capitulo": "21"
    },
    "esquerda": {
      "capitulo": "21"
    },
    "media quantidade": {
      "capitulo": "21"
    },
    "nega": {
      "capitulo": "21"
    },
    "gastrostomia funcionante com dietoterapia": {
      "capitulo": "13"
    },
    "sutura": {
      "capitulo": "15"
    },
    "curativo": {
      "capitulo": "15"
    },
    "cefaleia": {
      "capitulo": "08"
    },
    "aspecto purulento": {
      "capitulo": "01"
    },
    "traqueostomizado": {
      "capitulo": "08"
    },
    "fralda": {
      "capitulo": "24"
    },
    "cliente": {
      "capitulo": "24"
    },
    "hemitórax": {
      "capitulo": "08"
    },
    "fx de orbita esquerda": {
      "capitulo": "09"
    },
    "hematoma": {
      "capitulo": "22"
    },
    "msd": {
      "capitulo": "21"
    },
    "emese": {
      "capitulo": "21"
    },
    "cedip": {
      "capitulo": "24"
    },
    "observação": {
      "capitulo": "24"
    },
    "repouso no leito": {
      "capitulo": "21"
    },
    "laudo": {
      "capitulo": "21"
    },
    "consciente": {
      "capitulo": "21"
    },
    "hx": {
      "capitulo": "21"
    },
    "aspirado": {
      "capitulo": "21"
    },
    "até o momento": {
      "capitulo": "21"
    },
    "eliminações": {
      "capitulo": "21"
    },
    "precaução por contato": {
      "capitulo": "24"
    },
    "eupneica": {
      "capitulo": "21"
    },
    "afebril": {
      "capitulo": "01"
    },
    "secreção": {
      "capitulo": "01"
    },
    "algia": {
      "capitulo": "21"
    }
  }
}