{
  "prontuario_id": 31,
  "text": "Às 16:20 HS: EVOLUI CONSCIENTE, RESPONDE AOS COMANDOS VERBAIS. TRAQUEOSTOMIZADO, COM NÉVOA ÚMIDA A 6 L/MIN, APRESENTOU SECREÇÃO DE ASPIRAÇÃO TRAQUEAL SANGUINOLENTA APÓS REALIZAÇÃO DE BRONCOSCOPIA. COM DIETA POR GASTROSTOMIA A 75 ML/H, CURATIVO DE GASTRO COM. NEOPLASIA MALIGNA DA LINGUA COM LESAO INVASIVA. Em 03-09-2007, 15:00: Consciente, orientado, alerta, verbalizando. Púpilas Isocóricas e fotorreagentes. Corado, hidratado e afebril. Respirando em ar ambiente. Hemodinamicamente estável, eupnéico, saturando acima de 95%. Ausculta pulmonar com MV presente bil. NEOPLASIA MALIGNA DOS OSSOS DO CRANIO E DA FACE. Às 17:03: Paciente apresentando-se sonolenta no período da manhã e tarde, gemente, recebendo dieta via SNE a 75 ml/h por BI, eupneica, normotensa, normocardica, afebril, acesso venoso periférico MSD, apresentando edema em MMSS, SVD com débito colúrico. PNEUMONIA NAO ESPECIFICADA.",
  "entities": {
    "Achado": [
      "CONSCIENTE",
      "TRAQUEOSTOMIZADO",
      "SANGUINOLENTA",
      "Consciente",
      "orientado",
      "alerta",
      "verbalizando",
      "Corado",
      "hidratado",
      "afebril",
      "eupnéico",
      "eupneica",
      "normotensa",
      "normocardica",
      "RESPONDE AOS COMANDOS VERBAIS",
      "Púpilas Isocóricas e fotorreagentes",
      "Respirando em ar ambiente",
      "Hemodinamicamente estável",
      "saturando acima de 95%",
      "MV presente bil"
    ],
    "Procedimento Terapêutico ou Preventivo": [
      "TRAQUEOSTOMIZADO",
      "SVD",
      "NÉVOA ÚMIDA",
      "DE BRONCOSCOPIA",
      "DIETA POR GASTROSTOMIA",
      "CURATIVO DE GASTRO",
      "dieta via SNE",
      "acesso venoso periférico"
    ],
    "Negação": [
      "afebril"
    ],
    "Paciente ou Grupo com Deficiência": [
      "Paciente"
    ],
    "Sinal ou Sintoma": [
      "sonolenta",
      "gemente",
      "edema em MMSS",
      "débito colúrico"
    ],
    "Abreviação": [
      "BI",
      "MSD",
      "SVD",
      "CURATIVO DE GASTRO",
      "MV presente bil",
      "dieta via SNE",
      "edema em MMSS"
    ],
    "Dispositivo de Administração de Medicamento": [
      "BI"
    ],
    "Localização ou Região Corporal": [
      "MSD"
    ],
    "Dispositivo Médico": [
      "SVD",
      "CURATIVO DE GASTRO",
      "acesso venoso periférico"
    ],
    "Conceito Quantitativo": [
      "6 L/MIN",
      "75 ML/H",
      "75 ml/h"
    ],
    "Processo Neoplásico": [
      "NEOPLASIA MALIGNA DA LINGUA COM LESAO INVASIVA",
      "NEOPLASIA MALIGNA DOS OSSOS DO CRANIO E DA FACE"
    ],
    "Procedimento Diagnóstico": [
      "Ausculta pulmonar"
    ]
  },
  "labels": {
    "sonolenta": {
      "capitulo": "06"
    },
    "responde aos comandos verbais": {
      "capitulo": "06"
    },
    "débito colúrico": {
      "capitulo": "05"
    },
    "gemente": {
      "capitulo": "06"
    },
    "sanguinolenta": {
      "capitulo": "05"
    },
    "paciente": {
      "capitulo": "21"
    },
    "hemodinamicamente estável": {
      "capitulo": "21"
    },
    "6 l/min": {
      "capitulo": "21"
    },
    "verbalizando": {
      "capitulo": "06"
    },
    "neoplasia maligna da lingua com lesao invasiva": {
      "capitulo": "02"
    },
    "svd": {
      "capitulo": "05"
    },
    "orientado": {
      "capitulo": "06"
    },
    "névoa úmida": {
      "capitulo": "05"
    },
    "dieta via sne": {
      "capitulo": "05"
    },
    "respirando em ar ambiente": {
      "capitulo": "05"
    },
    "dieta por gastrostomia": {
      "capitulo": "05"
    },
    "normocardica": {
      "capitulo": "08"
    },
    "neoplasia maligna dos ossos do cranio e da face": {
      "capitulo": "02"
    },
    "75 ml/h": {
      "capitulo": "21"
    },
    "mv presente bil": {
      "capitulo": "21"
    },
    "traqueostomizado": {
      "capitulo": "05"
    },
    "púpilas isocóricas e fotorreagentes": {
      "capitulo": "08"
    },
    "bi": {
      "capitulo": "21"
    },
    "edema em mmss": {
      "capitulo": "15"
    },
    "corado": {
      "capitulo": "05"
    },
    "msd": {
      "capitulo": "21"
    },
    "ausculta pulmonar": {
      "capitulo": "12"
    },
    "consciente": {
      "capitulo": "06"
    },
    "curativo de gastro": {
      "capitulo": "05"
    },
    "eupnéico": {
      "capitulo": "05"
    },
    "alerta": {
      "capitulo": "06"
    },
    "saturando acima de 95%": {
      "capitulo": "05"
    },
    "de broncoscopia": {
      "capitulo": "05"
    },
    "hidratado": {
      "capitulo": "05"
    },
    "acesso venoso periférico": {
      "capitulo": "21"
    },
    "normotensa": {
      "capitulo": "08"
    },
    "eupneica": {
      "capitulo": "05"
    },
    "afebril": {
      "capitulo": "05"
    }
  }
}