{
  "prontuario_id": 213,
  "text": "EM 01/07/2012, 10:30h:  # Plicatura de eventração diafragmática. # D2 UTI. # D2 DTFE. # D2 AVP MSD. Paciente glasgow 15, eupneico em ar ambiente, AVP com soroterapia em curso, mantendo dreno de torax E com pouco debito sanguinolento e sem oscilação, aceitando bem a dieta VO, sem queixas algicas, mobilizado fora do leito, mantendo SSVV estaveis e segue de alta para o POSTO 2, sem intercorrencias. SUPERVISÃO NOTURNA: REF: 15/09/2011: PERMANECE TRAQUEOSTOMIZADA EM NÉVOA UMIDA, SATURANDO SATISFATORIAMENTE NO MOMENTO, PUPILAS ISOFOTO, GLASGOW ESTIMADO EM 14, AUSCULTA PULMONAR MV DIMINUIDOS EM BASES. ABDOMEN FLACIDO, RHA +, SNE COM DIETA 60 ML/H (iniciar jejum após 0 hora), PARA TROCA DE CANULA EM 16/09, AS 13:30h. ACESSO VENOSO PERIFERICO EM MSD COM PLANO BASICO DE HIDRATAÇÃO. HEMODINAMICAMENTE ESTAVEL. ULCERA POR PRESSÃO ESTAGIO INDEFINIDO POR APRESENTAR AREA DE NECROSE. MONITORIZAÇÃO DE MULTIPLOS PARAMETROS CONFORME ROTINA DA UTI.",
  "entities": {
    "Abreviação": [
      "UTI",
      "DTFE",
      "AVP",
      "MSD",
      "aceitando bem a dieta VO",
      "SSVV estaveis",
      "PUPILAS ISOFOTO",
      "MV DIMINUIDOS EM BASES",
      "RHA +",
      "SNE COM DIETA"
    ],
    "Organização Relacionada à Saúde": [
      "UTI",
      "POSTO 2"
    ],
    "Dispositivo Médico": [
      "DTFE",
      "AVP",
      "dreno de torax",
      "ACESSO VENOSO PERIFERICO"
    ],
    "Procedimento Terapêutico ou Preventivo": [
      "DTFE",
      "AVP",
      "jejum",
      "Plicatura de eventração diafragmática",
      "soroterapia em curso",
      "dreno de torax",
      "mobilizado fora do leito",
      "NÉVOA UMIDA",
      "SNE COM DIETA",
      "TROCA DE CANULA",
      "ACESSO VENOSO PERIFERICO",
      "PLANO BASICO DE HIDRATAÇÃO"
    ],
    "Localização ou Região Corporal": [
      "MSD",
      "ABDOMEN"
    ],
    "Paciente ou Grupo com Deficiência": [
      "Paciente"
    ],
    "Sinal ou Sintoma": [
      "oscilação",
      "intercorrencias",
      "queixas algicas",
      "GLASGOW ESTIMADO EM 14",
      "MV DIMINUIDOS EM BASES"
    ],
    "Atividade de Assistência à Saúde": [
      "alta"
    ],
    "Achado": [
      "TRAQUEOSTOMIZADA",
      "glasgow 15",
      "eupneico em ar ambiente",
      "aceitando bem a dieta VO",
      "mobilizado fora do leito",
      "SSVV estaveis",
      "SATURANDO SATISFATORIAMENTE",
      "PUPILAS ISOFOTO",
      "RHA +",
      "HEMODINAMICAMENTE ESTAVEL"
    ],
    "Procedimento Diagnóstico": [
      "AUSCULTA PULMONAR",
      "MONITORIZAÇÃO DE MULTIPLOS PARAMETROS"
    ],
    "Conceito Quantitativo": [
      "60 ML/H"
    ],
    "Doença ou Síndrome": [
      "ULCERA POR PRESSÃO"
    ]
  },
  "labels": {
    "ssvv estaveis": {
      "capitulo": "15"
    },
    "plicatura de eventração diafragmática": {
      "capitulo": "15"
    },
    "glasgow estimado em 14": {
      "capitulo": "06"
    },
    "sne com dieta": {
      "capitulo": "13"
    },
    "hemodinamicamente estavel": {
      "capitulo": "24"
    },
    "dreno de torax": {
      "capitulo": "12"
    },
    "avp": {
      "capitulo": "11"
    },
    "aceitando bem a dieta vo": {
      "capitulo": "24"
    },
    "pupilas isofoto": {
      "capitulo": "08"
    },
    "névoa umida": {
      "capitulo": "24"
    },
    "plano basico de hidratação": {
      "capitulo": "24"
    }
  }
}