{
  "prontuario_id": 584,
  "text": "À 00h: Admitido nesta unidade, proveniente do CC, apos realizar POI Artrodese de T11 + L3 + HX: Queda de nivel (+/-10 M). Na admissao, glasgow 14, face hipocorada, pupilas iso / foto. Hiperemia reg queixo. Respiraçao espontanea em ar ambiente com ausculta pulmonar com MV +, S/ RA, saturando 98%. Cabeceira do leito \"ZERO GRAUS E MOBILIZAR EM BLOCO \", conforme orientaçoes neuro + plantao. Acesso periferico MSD / E, com infusao de sf 0,9% gravitacional. PAM radial E permeavel + extremidades frias, perfusao periferica diminuida. Abdomen flacido, rha +. FO reg lombar com curativo especial + dreno de suctor com baixo debito sanguinolento. Diurese por SVD presente em coletor amarelo citrico. Monitorizado continuamente com cardioscopico + oximetria de pulso + pam nao invasiva. Orientado pela neuro RX de controle as 06H, agendo com RX.  Às 10:50: REALIZADO PASSAGEM DE SNE, SEM INTERCORRÊNCIA NO PROCEDIMENTO. AUSCULTA ABDOMINAL POSITIVA, RETIRO FIO GUIA. SOLICITO RAIO-X PARA AVALIAÇÃO DA POSIÇÃO. Às 16:00: Paciente acamada, traqueostomizada com canula plastica, pouco agitada. Respirando com suporte de O2 em nevoa, realizado aspiração traqueal com saida de secreção esbranquiçada pouco quantidade, Abdome flacido sem dor a palpação, dieta via gastrostomia. AP: presença de roncos + sibilos. MM com edemas. Diurese efetiva em fralda, pele integra para ulcera por pressão. Agendada broncoscopia para 20/10 - Jejum a partir das 00:00 - passo em plantão. Segue cuidados. ",
  "entities": {
    "Abreviação": [
      "CC",
      "POI",
      "T11",
      "L3",
      "HX",
      "S/",
      "RA",
      "neuro",
      "MSD",
      "E",
      "PAM",
      "FO",
      "RX",
      "AP",
      "reg queixo",
      "MV +",
      "radial E",
      "rha +",
      "reg lombar",
      "Diurese por SVD presente",
      "RX de controle",
      "PASSAGEM DE SNE",
      "MM com edemas"
    ],
    "Organização Relacionada à Saúde": [
      "CC",
      "neuro",
      "plantao",
      "plantão"
    ],
    "Conceito Temporal": [
      "POI"
    ],
    "Parte do Corpo, Órgão ou Componente Orgânico": [
      "T11",
      "L3",
      "pupilas",
      "radial E"
    ],
    "Sinal ou Sintoma": [
      "Hiperemia",
      "RA",
      "INTERCORRÊNCIA",
      "roncos",
      "sibilos",
      "glasgow 14",
      "face hipocorada",
      "extremidades frias",
      "perfusao periferica diminuida",
      "pouco agitada",
      "MM com edemas"
    ],
    "Negação": [
      "S/"
    ],
    "Atividade de Assistência à Saúde": [
      "orientaçoes",
      "plantao",
      "plantão",
      "cuidados"
    ],
    "Conceito Espacial": [
      "E"
    ],
    "Achado": [
      "permeavel",
      "acamada",
      "flacido",
      "Respiraçao espontanea em ar ambiente",
      "MV +",
      "saturando 98%",
      "rha +",
      "baixo debito sanguinolento",
      "Diurese por SVD presente",
      "amarelo citrico",
      "AUSCULTA ABDOMINAL POSITIVA",
      "pele integra"
    ],
    "Localização ou Região Corporal": [
      "Abdomen",
      "Abdome",
      "reg queixo",
      "reg lombar"
    ],
    "Lesão ou Envenenamento": [
      "FO",
      "Queda de nivel"
    ],
    "Dispositivo Médico": [
      "coletor",
      "cardioscopico",
      "Acesso periferico",
      "curativo especial",
      "dreno de suctor"
    ],
    "Procedimento Diagnóstico": [
      "cardioscopico",
      "RAIO-X",
      "palpação",
      "AP",
      "broncoscopia",
      "ausculta pulmonar",
      "Monitorizado continuamente",
      "oximetria de pulso",
      "RX de controle"
    ],
    "Procedimento Terapêutico ou Preventivo": [
      "PROCEDIMENTO",
      "broncoscopia",
      "Jejum",
      "Cabeceira do leito \"ZERO GRAUS",
      "MOBILIZAR EM BLOCO",
      "Acesso periferico",
      "curativo especial",
      "dreno de suctor",
      "PASSAGEM DE SNE",
      "RETIRO FIO GUIA",
      "traqueostomizada com canula plastica",
      "O2 em nevoa",
      "aspiração traqueal",
      "dieta via gastrostomia"
    ],
    "Paciente ou Grupo com Deficiência": [
      "Paciente"
    ],
    "Objeto Manufaturado": [
      "fralda"
    ],
    "Substância Corporal": [
      "secreção esbranquiçada"
    ],
    "Conceito Qualitativo": [
      "pouco quantidade"
    ],
    "Doença ou Síndrome": [
      "ulcera por pressão"
    ]
  },
  "labels": {
    "rx": {
      "capitulo": "26.1.10.010"
    },
    "hiperemia": {
      "capitulo": "26.1.10.010"
    },
    "dreno de suctor": {
      "capitulo": "26.1.10.010"
    },
    "l3": {
      "capitulo": "26.1.10.010"
    },
    "t11": {
      "capitulo": "26.1.10.010"
    },
    "diurese por svd presente": {
      "capitulo": "26.1.10.010"
    },
    "s/": {
      "capitulo": "26.1.10.010"
    },
    "acamada": {
      "capitulo": "26.1.10.010"
    },
    "extremidades frias": {
      "capitulo": "26.1.10.010"
    },
    "abdome": {
      "capitulo": "26.1.10.010"
    },
    "paciente": {
      "capitulo": "26.1.10.010"
    },
    "e": {
      "capitulo": "26.1.10.010"
    },
    "mv +": {
      "capitulo": "26.1.10.010"
    },
    "jejum": {
      "capitulo": "26.1.10.010"
    },
    "intercorrência": {
      "capitulo": "26.1.10.010"
    },
    "neuro": {
      "capitulo": "26.1.10.010"
    },
    "ausculta abdominal positiva": {
      "capitulo": "26.1.10.010"
    },
    "retiro fio guia": {
      "capitulo": "26.1.10.010"
    },
    "raio-x": {
      "capitulo": "26.1.10.010"
    },
    "passagem de sne": {
      "capitulo": "26.1.10.010"
    },
    "ausculta pulmonar": {
      "capitulo": "26.1.10.010"
    },
    "sibilos": {
      "capitulo": "26.1.10.010"
    },
    "mm com edemas": {
      "capitulo": "26.1.10.010"
    },
    "glasgow 14": {
      "capitulo": "26.1.10.010"
    },
    "ra": {
      "capitulo": "26.1.10.010"
    },
    "dieta via gastrostomia": {
      "capitulo": "26.1.10.010"
    },
    "palpação": {
      "capitulo": "26.1.10.010"
    },
    "fralda": {
      "capitulo": "26.1.10.010"
    },
    "monitorizado continuamente": {
      "capitulo": "26.1.10.010"
    },
    "cardioscopico": {
      "capitulo": "26.1.10.010"
    },
    "rx de controle": {
      "capitulo": "26.1.10.010"
    },
    "mobilizar em bloco": {
      "capitulo": "26.1.10.010"
    }
  }
}