{
  "prontuario_id": 874,
  "text": "PA 130/80 mmHg / FC 100 bpm / TEMP 36.3º C / FR 16. FRATURA DO COLO DO FEMUR. Às 17:10H: Passado SNE conforme orientação médica, sem intercorrências. Aguarda RX de controle. Enfª Florence Nightingale, COREN XXXX. FRATURA DA COLUNA LOMBAR E DA PELVE. Às 16:09: paciente encaminhado para uti 1. enf Florence Nightingale. SEPTICEMIA NAO ESPECIFICADA. Às 01:55HS: PCTE LUCIDO, CONFUSO, COMUNICATIVO, EUPNEICO EM AR AMBIENTE, PRESENÇA DE EDEMA EM OLHO ESQUERDO, CONTIDO NO LEITO, ACESSO VENOSO PERIFÉRICO EM MSD SALINIZADO, URUPEN C/ DIURESE PRESENTE, SEGUE SOB CUIDADOS. ACIDENTE VASCULAR CEREBRAL NAO ESPECIFICADO COMO HEMORRAGICO OU ISQUEMICO. Às 21:39h: Responsivo, colaborativo, face corada, pupilas iso / foto. Aceitando liquidos VO. Respiraçao espontanea em ar ambiente com saturaçao de 94%. Acesso central D com infusao de ancoron 11 ml/hr + insulina 8 ml/hr. Extremidades edemaciadas, perfusao periferica preservada. Abdomen globoso, rha +. Diurese espontanea em fralda, solicito uropen. No momento, nao relata queixas algicas. Monitorizado continuamente com cardioscopico + oximetria de pulso + pam nao invasiva. Enfermeira Florence Nightingale. MELENA. Às 22H: PERMANECE INSTÁVEL HEMODINAMICAMENTE, FAZENDO USO DE DVA EM ALTAS VAZÕES. MANTIDA EM VM COM FILTRO DE BARREIRA, EM MODO PCV, COM PI DE 3O CM DE H2O, FIO2 EM 0,30%, FR 22 CM DE H2O. MONITORADA COM PAM, CARDIOSCOPIA E OXIMETRIA DE PULSO. APRESENTA RAMSAY 6, PUPILAS MÉDIO-FIXAS, ANASARCA, MUCOSAS ICTÉRICAS +++/4, TOT EM RIMA LABIAL EM 24 CM, SECREÇÃO TRAQUEOBRÔNQUICA AMARELADA EM MÉDIA QUANTIDADE DE SECREÇÃO, AUSCULTA PULMONAR COM RONCOS E CREPITAÇÕES DIFUSAS, CVC EM JUGULAR INTERNA DIREITA COM NORADRENALINA 42 ML/H, DOPAMINA 42 ML/H, MIDAZOLAN 20 ML/H, SEDAÇÃO 20 ML/H, CURATIVO EM REGIÃO ABDOMINAL LIMPO E SECO, PAM EM ARTÉRIA RADIAL D PERMEÁVEL, DRENO DE SUCTOR ABDOMINAL COM POUCA QUANTIDADE DE DÉBITO HEMÁTICO, RHA AUSENTES, ABDOME DISTENDIDO, SVD COM OLIGOANÚRIA. INSUFICIENCIA RESPIRATORIA AGUDA.",
  "entities": {
    "Atributo Clínico": [
      "PA",
      "FC",
      "TEMP",
      "FR"
    ],
    "Abreviação": [
      "PA",
      "mmHg",
      "FC",
      "bpm",
      "TEMP",
      "FR",
      "Enfª",
      "uti",
      "enf",
      "PCTE",
      "MSD",
      "D",
      "DVA",
      "PI",
      "FIO2",
      "PAM",
      "+++/4",
      "TOT",
      "CVC",
      "RHA",
      "Passado SNE",
      "RX de controle",
      "Aceitando liquidos VO",
      "rha +",
      "MODO PCV",
      "ARTÉRIA RADIAL D",
      "SVD COM OLIGOANÚRIA"
    ],
    "Conceito Quantitativo": [
      "130/80",
      "100",
      "36",
      "16",
      "30%",
      "22",
      "3º C",
      "11 ml/hr",
      "8 ml/hr",
      "3O CM DE H2O",
      "24 CM",
      "42 ML/H",
      "20 ML/H"
    ],
    "Sinal ou Sintoma": [
      "intercorrências",
      "CONFUSO",
      "EDEMA",
      "MELENA",
      "ANASARCA",
      "RONCOS",
      "Extremidades edemaciadas",
      "queixas algicas",
      "INSTÁVEL HEMODINAMICAMENTE",
      "PUPILAS MÉDIO-FIXAS",
      "MUCOSAS ICTÉRICAS",
      "CREPITAÇÕES DIFUSAS",
      "DÉBITO HEMÁTICO",
      "SVD COM OLIGOANÚRIA"
    ],
    "Grupo Profissional ou Ocupacional": [
      "Enfª",
      "enf",
      "Enfermeira"
    ],
    "Paciente ou Grupo com Deficiência": [
      "paciente",
      "PCTE"
    ],
    "Organização Relacionada à Saúde": [
      "uti"
    ],
    "Achado": [
      "LUCIDO",
      "COMUNICATIVO",
      "SALINIZADO",
      "Responsivo",
      "colaborativo",
      "LIMPO",
      "SECO",
      "PERMEÁVEL",
      "RHA",
      "EUPNEICO EM AR AMBIENTE",
      "CONTIDO NO LEITO",
      "DIURESE PRESENTE",
      "face corada",
      "Aceitando liquidos VO",
      "Respiraçao espontanea em ar ambiente",
      "saturaçao de 94%",
      "perfusao periferica preservada",
      "rha +",
      "RAMSAY 6"
    ],
    "Função Patológica": [
      "EDEMA"
    ],
    "Localização ou Região Corporal": [
      "MSD",
      "Abdomen",
      "ABDOMINAL",
      "ABDOME",
      "REGIÃO ABDOMINAL"
    ],
    "Procedimento Terapêutico ou Preventivo": [
      "SALINIZADO",
      "PI",
      "FIO2",
      "TOT",
      "CVC",
      "SEDAÇÃO",
      "CURATIVO",
      "Passado SNE",
      "ACESSO VENOSO PERIFÉRICO",
      "Acesso central",
      "FILTRO DE BARREIRA",
      "MODO PCV",
      "DRENO DE SUCTOR"
    ],
    "Dispositivo Médico": [
      "URUPEN",
      "uropen",
      "cardioscopico",
      "TOT",
      "CVC",
      "CURATIVO",
      "ACESSO VENOSO PERIFÉRICO",
      "Acesso central",
      "FILTRO DE BARREIRA",
      "DRENO DE SUCTOR"
    ],
    "Atividade de Assistência à Saúde": [
      "CUIDADOS",
      "infusao",
      "solicito",
      "orientação médica"
    ],
    "Parte do Corpo, Órgão ou Componente Orgânico": [
      "pupilas",
      "OLHO ESQUERDO",
      "JUGULAR INTERNA DIREITA",
      "ARTÉRIA RADIAL D"
    ],
    "Conceito Espacial": [
      "D"
    ],
    "Substância Farmacológica": [
      "ancoron",
      "insulina",
      "NORADRENALINA",
      "DOPAMINA",
      "MIDAZOLAN"
    ],
    "Hormônio": [
      "insulina",
      "NORADRENALINA"
    ],
    "Objeto Manufaturado": [
      "fralda"
    ],
    "Procedimento Diagnóstico": [
      "cardioscopico",
      "MONITORADA",
      "PAM",
      "CARDIOSCOPIA",
      "RX de controle",
      "Monitorizado continuamente",
      "oximetria de pulso",
      "OXIMETRIA DE PULSO",
      "AUSCULTA PULMONAR"
    ],
    "Substância Química Orgânica": [
      "DOPAMINA"
    ],
    "Negação": [
      "AUSENTES"
    ],
    "Lesão ou Envenenamento": [
      "FRATURA DO COLO DO FEMUR",
      "FRATURA DA COLUNA LOMBAR E DA PELVE"
    ],
    "Função Fisiológica": [
      "DIURESE PRESENTE"
    ],
    "Doença ou Síndrome": [
      "ACIDENTE VASCULAR CEREBRAL",
      "INSUFICIENCIA RESPIRATORIA AGUDA"
    ],
    "Substância Corporal": [
      "SECREÇÃO TRAQUEOBRÔNQUICA",
      "MÉDIA QUANTIDADE DE SECREÇÃO"
    ],
    "Conceito Qualitativo": [
      "POUCA QUANTIDADE"
    ]
  },
  "labels": {
    "uropen": {
      "capitulo": "16.11"
    },
    "mmhg": {
      "capitulo": "11.10"
    },
    "pupilas médio-fixas": {
      "capitulo": "08.41"
    },
    "abdome": {
      "capitulo": "13.10"
    },
    "paciente": {
      "capitulo": "21.11"
    },
    "cardioscopico": {
      "capitulo": "21.11"
    },
    "pam": {
      "capitulo": "11.10"
    },
    "pupilas": {
      "capitulo": "08.41"
    },
    "urupen": {
      "capitulo": "16.11"
    },
    "enfermeira": {
      "capitulo": "21.11"
    },
    "insuficiencia respiratoria aguda": {
      "capitulo": "12.10"
    },
    "média quantidade de secreção": {
      "capitulo": "12.10"
    },
    "dva": {
      "capitulo": "22.11"
    },
    "rha +": {
      "capitulo": "16.11"
    },
    "100": {
      "capitulo": "21.11"
    },
    "colaborativo": {
      "capitulo": "21.11"
    },
    "3º c": {
      "capitulo": "21.11"
    },
    "tot": {
      "capitulo": "15.11"
    },
    "fratura da coluna lombar e da pelve": {
      "capitulo": "15.11"
    },
    "comunicativo": {
      "capitulo": "21.11"
    },
    "8 ml/hr": {
      "capitulo": "21.11"
    },
    "acidente vascular cerebral": {
      "capitulo": "11.10"
    },
    "enf": {
      "capitulo": "21.11"
    },
    "36": {
      "capitulo": "21.11"
    },
    "ancoron": {
      "capitulo": "21.11"
    },
    "bpm": {
      "capitulo": "11.10"
    },
    "eupneico em ar ambiente": {
      "capitulo": "12.10"
    },
    "fc": {
      "capitulo": "11.10"
    },
    "fralda": {
      "capitulo": "21.11"
    },
    "face corada": {
      "capitulo": "21.11"
    },
    "monitorizado continuamente": {
      "capitulo": "21.11"
    },
    "saturaçao de 94%": {
      "capitulo": "21.11"
    },
    "região abdominal": {
      "capitulo": "13.10"
    },
    "permeável": {
      "capitulo": "21.11"
    },
    "cvc": {
      "capitulo": "11.10"
    },
    "20 ml/h": {
      "capitulo": "21.11"
    },
    "solicito": {
      "capitulo": "21.11"
    },
    "perfusao periferica preservada": {
      "capitulo": "11.10"
    },
    "fio2": {
      "capitulo": "21.11"
    },
    "débito hemático": {
      "capitulo": "21.11"
    },
    "anasarca": {
      "capitulo": "14.11"
    },
    "sedação": {
      "capitulo": "21.11"
    },
    "dreno de suctor": {
      "capitulo": "21.11"
    },
    "pouca quantidade": {
      "capitulo": "21.11"
    },
    "orientação médica": {
      "capitulo": "21.11"
    },
    "abdominal": {
      "capitulo": "13.10"
    },
    "temp": {
      "capitulo": "15.11"
    },
    "ausentes": {
      "capitulo": "21.11"
    },
    "3o cm de h2o": {
      "capitulo": "21.11"
    },
    "30%": {
      "capitulo": "21.11"
    },
    "ramsay 6": {
      "capitulo": "21.11"
    },
    "modo pcv": {
      "capitulo": "21.11"
    },
    "seco": {
      "capitulo": "21.11"
    },
    "noradrenalina": {
      "capitulo": "11.10"
    },
    "roncos": {
      "capitulo": "12.10"
    },
    "cuidados": {
      "capitulo": "21.11"
    },
    "mucosas ictéricas": {
      "capitulo": "14.11"
    },
    "extremidades edemaciadas": {
      "capitulo": "14.11"
    },
    "uti": {
      "capitulo": "21.11"
    },
    "crepitações difusas": {
      "capitulo": "12.10"
    },
    "infusao": {
      "capitulo": "21.11"
    },
    "diurese presente": {
      "capitulo": "16.11"
    },
    "monitorada": {
      "capitulo": "21.11"
    },
    "limpo": {
      "capitulo": "21.11"
    },
    "jugular interna direita": {
      "capitulo": "11.10"
    },
    "respiraçao espontanea em ar ambiente": {
      "capitulo": "12.10"
    },
    "confuso": {
      "capitulo": "21.11"
    },
    "instável hemodinamicamente": {
      "capitulo": "21.11"
    },
    "acesso central": {
      "capitulo": "11.10"
    },
    "cardioscopia": {
      "capitulo": "21.11"
    },
    "pa": {
      "capitulo": "11.10"
    },
    "22": {
      "capitulo": "21.11"
    },
    "curativo": {
      "capitulo": "21.11"
    },
    "oximetria de pulso": {
      "capitulo": "21.11"
    },
    "16": {
      "capitulo": "21.11"
    },
    "42 ml/h": {
      "capitulo": "21.11"
    },
    "11 ml/hr": {
      "capitulo": "21.11"
    },
    "dopamina": {
      "capitulo": "11.10"
    },
    "melena": {
      "capitulo": "13.10"
    },
    "msd": {
      "capitulo": "21.11"
    },
    "insulina": {
      "capitulo": "21.11"
    },
    "24 cm": {
      "capitulo": "21.11"
    },
    "contido no leito": {
      "capitulo": "21.11"
    },
    "artéria radial d": {
      "capitulo": "11.10"
    }
  }
}