{
  "prontuario_id": 542,
  "text": "Às 02:58H: CLIENTE 16 ANOS, VÍTIMA DE MULTIPLOS FAFS, PROVENIENTE DO PS ÀS 20:40H DE ONTÉM. NO MOMENTO, CONSCIENTE, VERBALIZANDO, PUPILAS IFR, EUPNÊICO EM AR AMBIENTE, MANTÉM ACESSO VENOSO PERIFÉRICO EM MSD SALINIZADO, ACEITANDO DIETA VO, SVD COM DIURESE PRESENTE, LIBERADO ACOMPANHANTE DEVIDO IDADE DO CLIENTE. Às 16:15: RETORNOU DO CENTRO CIRURGICO, ENCAMINHADA PARA REALIZAÇÃO DE TOMOGRAFIA DE QUADRIL, ACORDADA, VERBALIZANDO, AFEBRIL, EUPNEICA, NORMOCORADO, SEM QUEIXAS ALGICAS, ACESSO VENOSO PERIFERICO EM MSE SALINIZADO, SEM SINAIS FLOGISTICOS, CURATIVO EM REGIÃO DE FÊMUR ESQUERDO EXTERNAMENTE LIMPO E SECO, DIETA LIBERADO APÓS 18:00 HRS. Às 18:55: CLIENTE CONSCIENTE, PUPILAS ISOCORICAS FOTORREAGENTES, POUCO COMUNICATIVA, EUPNEICA, REPOUSO NO LEITO, ACEITANDO POUCO A DIETA, TENTADO PUNCIONAR NOVO ACESSO PERIFÉRICO, POREM SEM SUCESSO, APRESENTANDO EDEMA EM MIE, MANTENDO MEIAS PNEUMATICAS, REALIZADO CATETERISMO PARA COLETA DE PARCIAL DE URINA, ENCAMINHADO PARA LABORATÓRIO. ORIENTADO A ENTRAR EM JEJUM A PARTIR DAS 24:00 PARA PROCEDIMENTO CIRURGICO AMANHA, 14/10. Às 00:22h: Orientado a manter jejum após as 24h para procedimento cirúrgico em 11/08, as 15:30h, conforme mapa de cirurgias eletivas. Às 22h: Realizado punçao de PAM em radial D pelo plantao, apos algumas tentativas por pulso filiforme. Instalado PVC em transdutor por haver 2 abertos no box. PVC 9 mmhg, comunicado plantao.",
  "entities": {
    "Paciente ou Grupo com Deficiência": [
      "CLIENTE",
      "VÍTIMA"
    ],
    "Abreviação": [
      "PS",
      "IFR",
      "MSD",
      "SVD",
      "MSE",
      "MIE",
      "PVC",
      "MULTIPLOS FAFS",
      "ACEITANDO DIETA VO",
      "punçao de PAM",
      "radial D",
      "PVC em transdutor"
    ],
    "Organização Relacionada à Saúde": [
      "PS",
      "LABORATÓRIO",
      "plantao",
      "CENTRO CIRURGICO"
    ],
    "Achado": [
      "CONSCIENTE",
      "VERBALIZANDO",
      "IFR",
      "SALINIZADO",
      "ACORDADA",
      "AFEBRIL",
      "EUPNEICA",
      "NORMOCORADO",
      "LIMPO",
      "SECO",
      "ISOCORICAS",
      "FOTORREAGENTES",
      "SUCESSO",
      "EUPNÊICO EM AR AMBIENTE",
      "ACEITANDO DIETA VO",
      "DIURESE PRESENTE",
      "REPOUSO NO LEITO"
    ],
    "Parte do Corpo, Órgão ou Componente Orgânico": [
      "PUPILAS",
      "radial D"
    ],
    "Localização ou Região Corporal": [
      "MSD",
      "MSE",
      "MIE",
      "REGIÃO DE FÊMUR ESQUERDO"
    ],
    "Procedimento Terapêutico ou Preventivo": [
      "SALINIZADO",
      "SVD",
      "CURATIVO",
      "PUNCIONAR",
      "CATETERISMO",
      "JEJUM",
      "jejum",
      "ACESSO VENOSO PERIFÉRICO",
      "ACESSO VENOSO PERIFERICO",
      "REPOUSO NO LEITO",
      "ACESSO PERIFÉRICO",
      "MEIAS PNEUMATICAS",
      "PROCEDIMENTO CIRURGICO",
      "procedimento cirúrgico",
      "cirurgias eletivas",
      "punçao de PAM"
    ],
    "Dispositivo Médico": [
      "SVD",
      "CURATIVO",
      "ACESSO VENOSO PERIFÉRICO",
      "ACESSO VENOSO PERIFERICO",
      "MEIAS PNEUMATICAS"
    ],
    "Grupo Populacional": [
      "ACOMPANHANTE"
    ],
    "Negação": [
      "AFEBRIL"
    ],
    "Conceito Espacial": [
      "EXTERNAMENTE"
    ],
    "Alimento": [
      "DIETA"
    ],
    "Sinal ou Sintoma": [
      "EDEMA",
      "QUEIXAS ALGICAS",
      "SINAIS FLOGISTICOS",
      "pulso filiforme"
    ],
    "Função Patológica": [
      "EDEMA"
    ],
    "Atributo Clínico": [
      "PVC"
    ],
    "Conceito Temporal": [
      "16 ANOS"
    ],
    "Lesão ou Envenenamento": [
      "MULTIPLOS FAFS"
    ],
    "Função Fisiológica": [
      "DIURESE PRESENTE"
    ],
    "Procedimento Diagnóstico": [
      "TOMOGRAFIA DE QUADRIL"
    ],
    "Procedimento Laboratorial": [
      "COLETA DE PARCIAL DE URINA"
    ],
    "Conceito Quantitativo": [
      "9 mmhg"
    ]
  },
  "labels": {
    "sinais flogisticos": {
      "capitulo": "21"
    },
    "queixas algicas": {
      "capitulo": "21"
    },
    "acompanhante": {
      "capitulo": "24"
    },
    "limpo": {
      "capitulo": "21"
    },
    "meias pneumaticas": {
      "capitulo": "21"
    },
    "9 mmhg": {
      "capitulo": "21"
    },
    "acordada": {
      "capitulo": "21"
    },
    "cateterismo": {
      "capitulo": "21"
    },
    "externamente": {
      "capitulo": "21"
    },
    "edema": {
      "capitulo": "21"
    },
    "radial d": {
      "capitulo": "21"
    },
    "jejum": {
      "capitulo": "24"
    },
    "verbalizando": {
      "capitulo": "21"
    },
    "laboratório": {
      "capitulo": "21"
    },
    "pupilas": {
      "capitulo": "21"
    },
    "svd": {
      "capitulo": "04"
    },
    "salinizado": {
      "capitulo": "21"
    },
    "mse": {
      "capitulo": "21"
    },
    "ps": {
      "capitulo": "21"
    },
    "16 anos": {
      "capitulo": "21"
    },
    "fotorreagentes": {
      "capitulo": "21"
    },
    "coleta de parcial de urina": {
      "capitulo": "21"
    },
    "pvc em transdutor": {
      "capitulo": "21"
    },
    "centro cirurgico": {
      "capitulo": "21"
    },
    "repouso no leito": {
      "capitulo": "21"
    },
    "aceitando dieta vo": {
      "capitulo": "21"
    },
    "eupnêico em ar ambiente": {
      "capitulo": "21"
    },
    "curativo": {
      "capitulo": "21"
    },
    "vítima": {
      "capitulo": "21"
    },
    "seco": {
      "capitulo": "21"
    },
    "puncionar": {
      "capitulo": "21"
    },
    "cliente": {
      "capitulo": "21"
    },
    "acesso venoso periferico": {
      "capitulo": "21"
    },
    "procedimento cirúrgico": {
      "capitulo": "21"
    },
    "mie": {
      "capitulo": "21"
    },
    "cirurgias eletivas": {
      "capitulo": "21"
    },
    "msd": {
      "capitulo": "21"
    },
    "multiplos fafs": {
      "capitulo": "21"
    },
    "pvc": {
      "capitulo": "21"
    },
    "normocorado": {
      "capitulo": "21"
    },
    "punçao de pam": {
      "capitulo": "21"
    },
    "consciente": {
      "capitulo": "21"
    },
    "região de fêmur esquerdo": {
      "capitulo": "21"
    },
    "plantao": {
      "capitulo": "21"
    },
    "diurese presente": {
      "capitulo": "21"
    },
    "ifr": {
      "capitulo": "21"
    },
    "tomografia de quadril": {
      "capitulo": "21"
    },
    "dieta": {
      "capitulo": "21"
    },
    "isocoricas": {
      "capitulo": "21"
    },
    "pulso filiforme": {
      "capitulo": "21"
    },
    "acesso venoso periférico": {
      "capitulo": "21"
    },
    "sucesso": {
      "capitulo": "21"
    },
    "eupneica": {
      "capitulo": "21"
    },
    "afebril": {
      "capitulo": "21"
    },
    "acesso periférico": {
      "capitulo": "21"
    }
  }
}