{
  "prontuario_id": 102,
  "text": "DI; 42. Às 14H: Glasgom 14, hipocorado, mucosa oral integra, SNE dieta 75 ml/h, traqueostomizado em Vm modo PSVcom VC 380 ml, Peep 5 cmH2, Fio2 40%. Torax simetrico, MV diminuido basalmente, BCRNF s/ s. Abdomen distendido, ostomia com alças intestinal corada sem sinais de lesões, debito amarelo escuro em flanco E. Fixador externo em braço e antebraço E. Diurese amarelo escuro por SVD. Acesso venoso sem sinais flogisticos em posterior do pé E, SF 0,9% 21 ml/h, gravitacional. Extremidades aquecidas, pulso pedioso ritimico. S: 7º DI na UTI. # DPOC DESCOMPENSADO. # SEPSE DE FOCO PULMONAR. *COMORBIDADE: HAS / DM / ICC. O: ECG: 15, EC: 0, PUPILAS ISOMIÓTICAS RFM +, INTUBADA SOB VM: PS 14, PEEP 8, FIO2: 0,45%, FR 10, MANTEM FILTRO BARREIRA BACTERIOLOGICO, SNE COM DIETA À 40 ML/H, EM BI, CVC EM JID COM SG 5% EM CURSO, AC: BCRNF, AP: CPL, ABD: RHA +, GLOBOSO E FLACIDO, MMSS E MMII EDEMACIADO (CACIFO ++), REGIÃO INGUINAL COM ASSADURA IMPORTANTE, SENDO APLICADO NISTATINA, APRESENTANDO VARIOS EPISÓDIOS DE FEZES LIQUIDAS AMARELADO, REGIÃO SACRA COM ULCERA POR PRESSÃO COM TECIDO NECROTICO. MONITORIZAÇÃO MULTIPARAMETRICO. A: RISCO PARA INFECÇÃO; PADRÃO RESPIRATÓRIO INEFICAZ; DESOBSTRUÇÃO INEFICAZ DE VIAS AEREAS; RISCO PARA DESEQUILIBRIO NUTRICIONAL; INTEGRIDADE DA PELE PREJUDICADA; MOBILIDADE FISICA PREJUDICADA. P: SEGUE PRESCRIÇÃO DE ENFERMAGEM EM ANEXO.",
  "entities": {
    "Sinal ou Sintoma": [
      "hipocorado",
      "GLOBOSO",
      "EDEMACIADO",
      "Glasgom 14",
      "MV diminuido basalmente",
      "Abdomen distendido",
      "sinais de lesões",
      "debito amarelo escuro",
      "sinais flogisticos",
      "ASSADURA IMPORTANTE",
      "FEZES LIQUIDAS AMARELADO",
      "ULCERA POR PRESSÃO COM TECIDO NECROTICO",
      "PADRÃO RESPIRATÓRIO INEFICAZ"
    ],
    "Procedimento Terapêutico ou Preventivo": [
      "traqueostomizado",
      "Vm",
      "VC",
      "Peep",
      "Fio2",
      "SVD",
      "INTUBADA",
      "VM",
      "PEEP",
      "FIO2",
      "CVC",
      "SNE dieta",
      "Fixador externo",
      "Acesso venoso",
      "SF 0 , 9%",
      "FILTRO BARREIRA BACTERIOLOGICO",
      "SNE COM DIETA"
    ],
    "Achado": [
      "traqueostomizado",
      "BCRNF",
      "corada",
      "INTUBADA",
      "FLACIDO",
      "mucosa oral integra",
      "Torax simetrico",
      "debito amarelo escuro",
      "Extremidades aquecidas",
      "pulso pedioso ritimico",
      "ECG : 15",
      "RFM +",
      "RHA +",
      "CACIFO ++",
      "RISCO PARA INFECÇÃO",
      "DESOBSTRUÇÃO INEFICAZ DE VIAS AEREAS",
      "RISCO PARA DESEQUILIBRIO NUTRICIONAL",
      "INTEGRIDADE DA PELE PREJUDICADA",
      "MOBILIDADE FISICA PREJUDICADA"
    ],
    "Abreviação": [
      "Vm",
      "PSVcom",
      "VC",
      "Peep",
      "Fio2",
      "BCRNF",
      "E",
      "SVD",
      "UTI",
      "HAS",
      "DM",
      "ICC",
      "O",
      "EC",
      "VM",
      "PS",
      "PEEP",
      "FIO2",
      "FR",
      "BI",
      "CVC",
      "JID",
      "AC",
      "AP",
      "CPL",
      "ABD",
      "MMSS",
      "MMII",
      "SNE dieta",
      "MV diminuido basalmente",
      "s/ s",
      "flanco E",
      "posterior do pé E",
      "SF 0 , 9%",
      "ECG : 15",
      "RFM +",
      "SG 5%",
      "RHA +"
    ],
    "Conceito Quantitativo": [
      "5",
      "40%",
      "14",
      "8",
      "10",
      "75 ml/h",
      "380 ml",
      "21 ml/h",
      "0 , 45%",
      "40 ML/H"
    ],
    "Parte do Corpo, Órgão ou Componente Orgânico": [
      "braço",
      "antebraço",
      "PUPILAS",
      "JID",
      "alças intestinal"
    ],
    "Conceito Espacial": [
      "E"
    ],
    "Dispositivo Médico": [
      "SVD",
      "CVC",
      "SNE dieta",
      "Fixador externo",
      "FILTRO BARREIRA BACTERIOLOGICO"
    ],
    "Organização Relacionada à Saúde": [
      "UTI"
    ],
    "Doença ou Síndrome": [
      "HAS",
      "DM",
      "ICC",
      "DPOC DESCOMPENSADO",
      "SEPSE DE FOCO PULMONAR",
      "ULCERA POR PRESSÃO COM TECIDO NECROTICO"
    ],
    "Dispositivo de Administração de Medicamento": [
      "BI"
    ],
    "Procedimento Diagnóstico": [
      "AC",
      "AP",
      "MONITORIZAÇÃO MULTIPARAMETRICO"
    ],
    "Localização ou Região Corporal": [
      "ABD",
      "MMSS",
      "MMII",
      "flanco E",
      "posterior do pé E",
      "REGIÃO INGUINAL",
      "REGIÃO SACRA"
    ],
    "Função Patológica": [
      "EDEMACIADO"
    ],
    "Substância Farmacológica": [
      "NISTATINA",
      "SF 0 , 9%",
      "SG 5%"
    ],
    "Substância Corporal": [
      "debito amarelo escuro"
    ],
    "Função Fisiológica": [
      "Diurese amarelo escuro"
    ],
    "Conceito Qualitativo": [
      "CACIFO ++"
    ],
    "Produto Intelectual": [
      "PRESCRIÇÃO DE ENFERMAGEM"
    ]
  },
  "labels": {
    "debito amarelo escuro": {
      "capitulo": "125.40"
    },
    "sf 0 , 9%": {
      "capitulo": "125.40"
    },
    "ec": {
      "capitulo": "125.40"
    },
    "40 ml/h": {
      "capitulo": "125.40"
    },
    "pupilas": {
      "capitulo": "085.01"
    },
    "mmss": {
      "capitulo": "085.01"
    },
    "svd": {
      "capitulo": "085.01"
    },
    "sne dieta": {
      "capitulo": "085.01"
    },
    "ap": {
      "capitulo": "085.01"
    },
    "rha +": {
      "capitulo": "085.01"
    },
    "abd": {
      "capitulo": "085.01"
    }
  }
}