{
  "prontuario_id": 741,
  "text": "Púpilas isocóricas e fotorreagentes. Responsiva a estímulos dolorosos e aspirativos. Abertura ocular espontânea, obedece a comandos verbais simples. Traqueostomizado, em ventilação mecânica PCV, PI 24, Peep 5, FiO2 43%. Hemodinamicamente estável, normocá. SINDROME DE GUILLAIN BARRE. Em 08/10/2006, 08:45 HORAS: EM PRIMEIRO PO DE RESSECÇÃO DE TU CEREBRAL, APRESENTA-SE ACORDADA, ATENDENDO AOS COMANDOS VERBAIS SIMPLES, COM PERÍODOS DE AGITAÇÃO INTENSA, CHOROSA. PRESENÇA DE EDEMA PERIPALPEBRAL BILATERAL. RESPIRAÇÃO ESPONTÂNEA EM AR AMBIENTE. HIDROCEFALIA. Às 15:55HRS: SEGUE CONSCIENTE, ORIENTADO, COMUNICATIVO. EUPNEICO COM SUPORTE DE O2 SOB NEVOA UMIDA, AFEBRIL, NORMOTENSO, NORMOCARDICO. ACEITANDO BEM A DIETA VO. APRESENTA HIPEREMIA MODERADA GENERALIZADA. REFERE CEFALEIA. MANTEM REPOUSO NO LEITO. ELIMINAÇÕES. FRATURA DE COSTELA. Às 13:00: Permanece sonolento, com abertura ocular espontânea, pupilas isocóricas e fotorreagentes, responsivo a estímulos aspirativos e dolorosos, afebril, corado, traqueostomizado com suporte de névoa úmida contínua saturando a 98%. Apresenta média quantid. FRATURA DA DIAFISE DO FEMUR.",
  "entities": {
    "Parte do Corpo, Órgão ou Componente Orgânico": [
      "Púpilas",
      "pupilas"
    ],
    "Achado": [
      "isocóricas",
      "fotorreagentes",
      "Traqueostomizado",
      "normocá",
      "ACORDADA",
      "CHOROSA",
      "CONSCIENTE",
      "ORIENTADO",
      "COMUNICATIVO",
      "EUPNEICO",
      "AFEBRIL",
      "NORMOTENSO",
      "NORMOCARDICO",
      "ELIMINAÇÕES",
      "afebril",
      "corado",
      "traqueostomizado",
      "Responsiva a estímulos dolorosos e aspirativos",
      "Abertura ocular espontânea",
      "obedece a comandos verbais simples",
      "Hemodinamicamente estável",
      "ATENDENDO AOS COMANDOS VERBAIS SIMPLES",
      "RESPIRAÇÃO ESPONTÂNEA EM AR AMBIENTE",
      "ACEITANDO BEM A DIETA VO",
      "REPOUSO NO LEITO",
      "abertura ocular espontânea",
      "responsivo a estímulos aspirativos e dolorosos"
    ],
    "Procedimento Terapêutico ou Preventivo": [
      "Traqueostomizado",
      "PCV",
      "PI",
      "Peep",
      "FiO2",
      "traqueostomizado",
      "ventilação mecânica",
      "RESSECÇÃO DE TU CEREBRAL",
      "SUPORTE DE O2 SOB NEVOA UMIDA",
      "REPOUSO NO LEITO",
      "suporte de névoa úmida contínua"
    ],
    "Abreviação": [
      "PCV",
      "PI",
      "Peep",
      "FiO2",
      "normocá",
      "PO",
      "RESSECÇÃO DE TU CEREBRAL",
      "ACEITANDO BEM A DIETA VO"
    ],
    "Conceito Quantitativo": [
      "24",
      "5",
      "43%",
      "98%"
    ],
    "Conceito Temporal": [
      "PO"
    ],
    "Doença ou Síndrome": [
      "HIDROCEFALIA",
      "SINDROME DE GUILLAIN BARRE"
    ],
    "Negação": [
      "AFEBRIL",
      "afebril"
    ],
    "Sinal ou Sintoma": [
      "CEFALEIA",
      "sonolento",
      "PERÍODOS DE AGITAÇÃO INTENSA",
      "EDEMA PERIPALPEBRAL BILATERAL",
      "HIPEREMIA MODERADA GENERALIZADA"
    ],
    "Função Fisiológica": [
      "ELIMINAÇÕES"
    ],
    "Lesão ou Envenenamento": [
      "FRATURA DE COSTELA",
      "FRATURA DA DIAFISE DO FEMUR"
    ],
    "Conceito Qualitativo": [
      "média quantid"
    ]
  },
  "labels": {
    "sonolento": {
      "capitulo": "01"
    },
    "isocóricas": {
      "capitulo": "14"
    },
    "po": {
      "capitulo": "14"
    },
    "responsivo a estímulos aspirativos e dolorosos": {
      "capitulo": "14"
    },
    "43%": {
      "capitulo": "98%"
    },
    "abertura ocular espontânea": {
      "capitulo": "05"
    },
    "pcv": {
      "capitulo": "14"
    },
    "ventilação mecânica": {
      "capitulo": "14"
    },
    "sindrome de guillain barre": {
      "capitulo": "06"
    },
    "repouso no leito": {
      "capitulo": "14"
    },
    "afebril": {
      "capitulo": "01"
    },
    "hidrocefalia": {
      "capitulo": "07"
    },
    "atendendo aos comandos verbais simples": {
      "capitulo": "14"
    },
    "suporte de névoa úmida contínua": {
      "capitulo": "14"
    },
    "consciente": {
      "capitulo": "01"
    },
    "hiperemia moderada generalizada": {
      "capitulo": "14"
    },
    "aceitando bem a dieta vo": {
      "capitulo": "14"
    },
    "peep": {
      "capitulo": "14"
    },
    "púpilas": {
      "capitulo": "05"
    },
    "normocardico": {
      "capitulo": "01"
    },
    "24": {
      "capitulo": "98%"
    },
    "acordada": {
      "capitulo": "01"
    },
    "fotorreagentes": {
      "capitulo": "14"
    },
    "corado": {
      "capitulo": "14"
    },
    "fratura da diafise do femur": {
      "capitulo": "12"
    },
    "respiração espontânea em ar ambiente": {
      "capitulo": "05"
    },
    "edema peripalpebral bilateral": {
      "capitulo": "14"
    },
    "5": {
      "capitulo": "98%"
    },
    "fio2": {
      "capitulo": "14"
    },
    "eliminações": {
      "capitulo": "14"
    },
    "ressecção de tu cerebral": {
      "capitulo": "07"
    },
    "obedece a comandos verbais simples": {
      "capitulo": "14"
    },
    "cefaleia": {
      "capitulo": "21"
    },
    "pi": {
      "capitulo": "14"
    },
    "média quantid": {
      "capitulo": "14"
    },
    "fratura de costela": {
      "capitulo": "12"
    },
    "98%": {
      "capitulo": "98%"
    },
    "períodos de agitação intensa": {
      "capitulo": "06"
    },
    "normotenso": {
      "capitulo": "01"
    },
    "normocá": {
      "capitulo": "01"
    },
    "traqueostomizado": {
      "capitulo": "14"
    },
    "pupilas": {
      "capitulo": "05"
    },
    "hemodinamicamente estável": {
      "capitulo": "01"
    },
    "chorosa": {
      "capitulo": "14"
    },
    "eupneico": {
      "capitulo": "05"
    },
    "responsiva a estímulos dolorosos e aspirativos": {
      "capitulo": "14"
    },
    "orientado": {
      "capitulo": "14"
    },
    "comunicativo": {
      "capitulo": "14"
    },
    "suporte de o2 sob nevoa umida": {
      "capitulo": "14"
    }
  }
}