{
  "prontuario_id": 173,
  "text": "Eupneico, mantendo-se com névoa úmida, saturação satisfatória; pupilas mióticas isocóricas; sonolento; respondendo a estímulos verbais quando solicitado; capacete cefálico seco e limpo; recebendo por acesso venoso periférico em MSE, plano básico de hidra. TRAUMATISMOS MULTIPLOS NAO ESPECIFICADOS. Às 18:33hrs: Paciente admitido na unidade, no periodo da tarde, para a realização do procedimento cirurgico de enxerto composto. Entrara em jejum a partir da 00hrs. Consciente, comunicativa, orientada. Segue cuidados de enfermagem. NEOPLASIA MALIGNA DA PELE COM LESAO INVASIVA. PCTE PROVENIENTE DO POSTO 02, PORTADORA DE HIV, PRÉ-CIRÚRGICO DE BIÓPSIA CEREBRAL. ÀS 07:30HS, 13/06/07: CONSCIENTE, RESPONDENDO A ESTÍMULOS VERBAIS. APRESENTA PERÍODOS DE CONFUSÃO, NECESSITANDO CONTENÇÃO DE MMSS, EUPNEICA, COLOCADA EM NÉVOA ÚMIDA, AUSCULTA C/ P. SINDROME DA ARTERIA VERTEBRO BASILAR. PACIENTE COM QUEIXA DE DOR EM LOCAL DE DRENO DE TORAX, CHAMADO DR VITAL BRASIL PARA AVALIAR SE DRENO ESTAVA LOCADO. SOMENTE FOI REALIZADO NOVO CURATIVO, QUE DEVE SER TROCADO SOMENTE NO DOMINGO. ENF FLORENCE NIGHTIGALE. PNEUMOTORAX TRAUMATICO.",
  "entities": {
    "Achado": [
      "Eupneico",
      "isocóricas",
      "seco",
      "limpo",
      "Consciente",
      "comunicativa",
      "orientada",
      "CONSCIENTE",
      "EUPNEICA",
      "saturação satisfatória",
      "respondendo a estímulos verbais",
      "RESPONDENDO A ESTÍMULOS VERBAIS"
    ],
    "Parte do Corpo, Órgão ou Componente Orgânico": [
      "pupilas"
    ],
    "Sinal ou Sintoma": [
      "sonolento",
      "DOR",
      "PERÍODOS DE CONFUSÃO"
    ],
    "Localização ou Região Corporal": [
      "MSE",
      "LOCAL DE DRENO DE TORAX"
    ],
    "Abreviação": [
      "MSE",
      "PCTE",
      "DR",
      "ENF",
      "plano básico de hidra",
      "CONTENÇÃO DE MMSS",
      "C/ P"
    ],
    "Paciente ou Grupo com Deficiência": [
      "Paciente",
      "PCTE",
      "PACIENTE"
    ],
    "Organização Relacionada à Saúde": [
      "unidade",
      "POSTO"
    ],
    "Procedimento Terapêutico ou Preventivo": [
      "jejum",
      "névoa úmida",
      "capacete cefálico",
      "acesso venoso periférico",
      "plano básico de hidra",
      "procedimento cirurgico de enxerto composto",
      "BIÓPSIA CEREBRAL",
      "CONTENÇÃO DE MMSS",
      "NÉVOA ÚMIDA",
      "REALIZADO NOVO CURATIVO"
    ],
    "Conceito Temporal": [
      "PRÉ-CIRÚRGICO"
    ],
    "Procedimento Diagnóstico": [
      "AUSCULTA",
      "BIÓPSIA CEREBRAL"
    ],
    "Grupo Profissional ou Ocupacional": [
      "ENF"
    ],
    "Dispositivo Médico": [
      "capacete cefálico",
      "acesso venoso periférico"
    ],
    "Lesão ou Envenenamento": [
      "TRAUMATISMOS MULTIPLOS",
      "PNEUMOTORAX TRAUMATICO"
    ],
    "Atividade de Assistência à Saúde": [
      "cuidados de enfermagem"
    ],
    "Processo Neoplásico": [
      "NEOPLASIA MALIGNA DA PELE COM LESAO INVASIVA"
    ],
    "Doença ou Síndrome": [
      "SINDROME DA ARTERIA VERTEBRO BASILAR",
      "PNEUMOTORAX TRAUMATICO"
    ]
  },
  "labels": {}
}