{
  "prontuario_id": 473,
  "text": "Às 03:47: Paciente consciente, lúcida, orientada, comunicativa, normotensa, normocorada, afebril, em repouso no leito. Mantém curativo em região abdominal, limpo e seco + curativo em perna D, também com aspecto seco. Apresenta diurese em SVD + fralda, porém sem evacuação no período. No início do plantão, paciente queixou-se de prurido intenso pelo corpo, o qual associa á reação medicamentosa do ATB. Feito Fenergan ás 21 horas (SNC), conforme prescrição médica. Logo após a realização da medicação, paciente começa a apresentar agitação motora, seguida  de ansiedade intensa, porém paciente mantém SSVV. Comunico DRa Alice. A filha da paciente, bastante aflita com o quadro que a mãe estava apresentando, entra em contato com Dr Vital Brasil, da cx geral, que logo após vem avaliar a paciente, e acrescenta mais medicação. Após ser medicada, paciente apresenta melhora do quadro de agitação e ansiedade. Segue em observação. AFECCOES DA PELE E DO TECIDO SUBCUTANEO NAO ESPECIFICADOS.",
  "entities": {
    "Paciente ou Grupo com Deficiência": [
      "Paciente",
      "paciente"
    ],
    "Achado": [
      "consciente",
      "lúcida",
      "orientada",
      "comunicativa",
      "normotensa",
      "normocorada",
      "afebril",
      "limpo",
      "seco",
      "evacuação",
      "repouso no leito",
      "aspecto seco",
      "mantém SSVV"
    ],
    "Negação": [
      "afebril",
      "sem"
    ],
    "Dispositivo Médico": [
      "curativo",
      "SVD",
      "fralda"
    ],
    "Procedimento Terapêutico ou Preventivo": [
      "curativo",
      "SVD",
      "medicação",
      "medicada",
      "repouso no leito"
    ],
    "Objeto Manufaturado": [
      "fralda"
    ],
    "Função Fisiológica": [
      "evacuação"
    ],
    "Atividade de Assistência à Saúde": [
      "plantão",
      "observação",
      "prescrição médica"
    ],
    "Antibiótico": [
      "ATB"
    ],
    "Substância Farmacológica": [
      "Fenergan",
      "medicação"
    ],
    "Abreviação": [
      "SNC",
      "DRa",
      "Dr",
      "perna D",
      "mantém SSVV",
      "cx geral"
    ],
    "Grupo Familiar": [
      "filha"
    ],
    "Sinal ou Sintoma": [
      "agitação",
      "prurido intenso",
      "agitação motora",
      "ansiedade intensa"
    ],
    "Localização ou Região Corporal": [
      "região abdominal"
    ],
    "Parte do Corpo, Órgão ou Componente Orgânico": [
      "perna D"
    ],
    "Produto Intelectual": [
      "prescrição médica"
    ],
    "Organização Relacionada à Saúde": [
      "cx geral"
    ],
    "Doença ou Síndrome": [
      "AFECCOES DA PELE E DO TECIDO SUBCUTANEO"
    ]
  },
  "labels": {
    "prurido intenso": {
      "capitulo": "11"
    }
  }
}