{
  "prontuario_id": 585,
  "text": "Às 18:35h: ASPECTO GERAL: EMAGRECIDO, HIDRATADO, CORADO, POLIÚRICO, ESTÁVEL HEMODINAMICAMENTE, COM USO DE DVA. NEUROLÓGICO: PÚPILAS ISOCÓRICAS, MIÓTICAS E FOTORREAGENTES, REAGE APENAS A DOR E ASPIRAÇÃO. RESPIRATÓRIO: INTUBADO, EM VM PCV COM 20 PI, 40% FIO2, 3 PEEP. PNEUMOCISTOSE. Paciente agitado, mesmo em uso de Haldol, contido ao leito e com luvas de contenção, confuso, em uso de SNE com dieta, AVP, diurese positiva em uropen. Provavel alta amanha. PNEUMOCISTOSE. Em 26/12/2007, 18 HORAS: PERMANECE SEDADO, PUPILAS ISOMIÓTICAS BRADIFOTORREAGENTES, COM EDEMA DE ESCLERAS E PERIORBITÁRIO BILATERAL, DESCORADO. COM CAPACETE CEFÁLICO LIMPO E SECO, COM FO LIMPA E SECA. MANTENDO CATETER PARA M-PIC OSCILANDO ENTRE 5-25 mmHg. TRAUMATISMOS MULTIPLOS NAO ESPECIFICADOS. Às 17:45HRS: CONSCIENTE, ORIENTADA, ALERTA, COMUNICATIVA. ACEITANDO BEM A DIETA VO. AVP EM MSD SALINIZADO. REFERE ALGIA NA REGIAO ABDOMINAL. APRESENTA TOSSE PRODUTIVA SEM EXPECTORAÇÃO. MANTEM REPOUSO. DIURESE PRESENTE. SSVV ESTAVEIS. SEGUE SOB CUIDADOS DE EN. PNEUMONIA POR MICROORGANISMO NAO ESPECIFICADA. PCTE HIPOTENSA, BRADICÁRDICA, EVOLUINDO PARA PCR. REALIZADO MANOBRAS DE REANIMAÇÃO S/ SUCESSO, EVOLUIU PARA ÓBITO AS 0:30HS. FRATURA PERTROCANTERICA.",
  "entities": {
    "Sinal ou Sintoma": [
      "EMAGRECIDO",
      "POLIÚRICO",
      "MIÓTICAS",
      "agitado",
      "confuso",
      "EDEMA",
      "DESCORADO",
      "ALGIA",
      "EXPECTORAÇÃO",
      "HIPOTENSA",
      "BRADICÁRDICA",
      "REAGE APENAS A DOR E ASPIRAÇÃO",
      "TOSSE PRODUTIVA"
    ],
    "Achado": [
      "HIDRATADO",
      "CORADO",
      "FOTORREAGENTES",
      "INTUBADO",
      "SEDADO",
      "LIMPO",
      "SECO",
      "LIMPA",
      "SECA",
      "OSCILANDO",
      "CONSCIENTE",
      "ORIENTADA",
      "ALERTA",
      "COMUNICATIVA",
      "SALINIZADO",
      "REPOUSO",
      "SUCESSO",
      "ESTÁVEL HEMODINAMICAMENTE",
      "ACEITANDO BEM A DIETA VO",
      "DIURESE PRESENTE",
      "SSVV ESTAVEIS"
    ],
    "Parte do Corpo, Órgão ou Componente Orgânico": [
      "PÚPILAS",
      "PUPILAS",
      "ESCLERAS"
    ],
    "Procedimento Terapêutico ou Preventivo": [
      "INTUBADO",
      "VM",
      "PCV",
      "PI",
      "FIO2",
      "PEEP",
      "AVP",
      "SEDADO",
      "SALINIZADO",
      "REPOUSO",
      "contido ao leito",
      "SNE com dieta",
      "CAPACETE CEFÁLICO",
      "CATETER PARA M-PIC",
      "MANOBRAS DE REANIMAÇÃO"
    ],
    "Abreviação": [
      "VM",
      "PCV",
      "PI",
      "FIO2",
      "PEEP",
      "AVP",
      "FO",
      "MSD",
      "PCTE",
      "PCR",
      "S/",
      "SNE com dieta",
      "CATETER PARA M-PIC",
      "ACEITANDO BEM A DIETA VO",
      "SSVV ESTAVEIS",
      "CUIDADOS DE EN"
    ],
    "Conceito Quantitativo": [
      "20",
      "40%",
      "3",
      "ENTRE 5-25 mmHg"
    ],
    "Doença ou Síndrome": [
      "PNEUMOCISTOSE"
    ],
    "Paciente ou Grupo com Deficiência": [
      "Paciente",
      "PCTE"
    ],
    "Substância Farmacológica": [
      "Haldol"
    ],
    "Dispositivo Médico": [
      "AVP",
      "uropen",
      "luvas de contenção",
      "CAPACETE CEFÁLICO",
      "CATETER PARA M-PIC"
    ],
    "Atividade de Assistência à Saúde": [
      "alta",
      "CUIDADOS DE EN"
    ],
    "Função Patológica": [
      "EDEMA"
    ],
    "Localização ou Região Corporal": [
      "PERIORBITÁRIO",
      "MSD",
      "REGIAO ABDOMINAL"
    ],
    "Conceito Espacial": [
      "BILATERAL"
    ],
    "Lesão ou Envenenamento": [
      "FO",
      "TRAUMATISMOS MULTIPLOS",
      "FRATURA PERTROCANTERICA"
    ],
    "Negação": [
      "SEM",
      "S/"
    ],
    "Substância Corporal": [
      "EXPECTORAÇÃO"
    ],
    "Função de Organismo": [
      "ÓBITO"
    ],
    "Função Fisiológica": [
      "DIURESE PRESENTE"
    ]
  },
  "labels": {
    "mióticas": {
      "capitulo": "08.11"
    },
    "poliúrico": {
      "capitulo": "05.89"
    },
    "pneumocistose": {
      "capitulo": "12.09"
    },
    "fratura pertrocanterica": {
      "capitulo": "15.11"
    },
    "hipotensa": {
      "capitulo": "11.59"
    },
    "peep": {
      "capitulo": "08.11"
    },
    "fotorreagentes": {
      "capitulo": "08.11"
    },
    "bradicárdica": {
      "capitulo": "08.11"
    },
    "pcv": {
      "capitulo": "08.11"
    },
    "vm": {
      "capitulo": "08.11"
    },
    "fio2": {
      "capitulo": "08.11"
    },
    "tosse produtiva": {
      "capitulo": "13.10"
    },
    "algia": {
      "capitulo": "13.10"
    }
  }
}