{
  "prontuario_id": 785,
  "text": "Às 15:10h: Encaminhada para o centro cirúrgico. Enf Florence Nightingale. FRATURA DO MEMBRO INFERIOR NIVEL NAO ESPECIFICADO. Às 11h40min: Realizado sondagem vesical de demora, conforme solicitação médica. Enfª Florence Nightingale, COREN XXXX. FRATURA DO FEMUR. Às 18h: Consciente, pouco comunicativo, sonolento, eupneico, em ar ambiente, normotenso, hipocorado, aceitando pouco dieta oferecida, cateter para hemodialise em jugular interna D, acesso venoso periferico em MSE com soroterapia em curso, abdomen globoso e semi-flacido, indolor a palpação, cistostomia com diurese presente em pequena quantidade de coloração amarelo escuro, UP regiao sacra estagio II, apresentando tecido roseo e sem exsudato, realizado curativo com placa de  hidrocoloide, nao trocar curativo por sete dias, trocar apenas curativo secundario, nega queixas algicas, realizada medidas de conforto, segue sob cuidados. Enf Florence Nightingale. EXAME GERAL E INVESTIGACAO DE PESSOAS SEM QUEIXAS OU DIAGNOSTICO RELATADO. Às 15:30H S: DEPENDENTE DE DVA, INTUBADO EM VM, DISCRETA ABERTURA OCULAR, HIPOTERMICO. O: 12º DI NO HOSPITAL, 8º DI DE UTI, COURO CABELUDO INTEGRO, DISCRETA ABERTURA OCULAR, PUPILAS ISOCORICAS FOTORREAGENTES, HIPOTERMICO (35,8 c), NORMOCARDICO (69 bpm), INTUBADO VIA TOT 7.5 RIMA 24, AUSCULTA COM RONCOS DIFUSOS, APRESENTANDO AUMENTO DA SECREÇÃO, LESÃO EM PAVILHÃO AURICULAR A DIREITA, CATETER VENOSO CENTRAL DUPLO-LUMEM VIA JUGULAR ESQUERDA INFUNDINDO NORADRENALINA (48 mg) 10 ML/H E PLANO BASICO DE HIDRATAÇÃO, ABDOMEM FLACIDO, RHA PRESENTES, SNE COM DIETA, EDEMA DOS MEMBROS, CACIFO ++/4, EXTREMIDADES AQUECIDAS REGULARMENTE PERFUNDIDAS, SVD COM DIURESE AMARELO OURO, UP SACRA SANGRANTE, UP COM TECIDO NECROSA EM CALCANEO ESQUERDO. SOLICITO AO INTENSIVISTA IRUXOL, REALIZADO CURATIVO COM ATADURA DE CREPE E GAZE, REALIZADO MEDIDAS DE HIGIENE, CONFORTO E MUDANÇA DE DECUBITO, SEGUE EM REPOUSO NO LEITO SOB COLCHÃO DE AR, MONITORADO EM CUIDADOS INTENSIVOS. A: MONITORAR PRESSÃO ARTERIAL, VERIFICAR POSSIBILIDADE DE DESMAME DA DVA, REALIZAR MUDANÇA DE DECUBITO 2/2, OBSERVAR NIVEL DE CONSCIENCIA. P: CONFORME PRESCRIÇÃO. ENF FLORENCE NIGHTINGALE, COREN XXXX. BRONCOPNEUMONIA NAO ESPECIFICADA.",
  "entities": {
    "Abreviação": [
      "Enf",
      "Enfª",
      "MSE",
      "UP",
      "VM",
      "UTI",
      "SVD",
      "ENF",
      "jugular interna D",
      "DEPENDENTE DE DVA",
      "RHA PRESENTES",
      "SNE COM DIETA",
      "MUDANÇA DE DECUBITO 2/2"
    ],
    "Grupo Profissional ou Ocupacional": [
      "Enf",
      "Enfª",
      "INTENSIVISTA",
      "ENF"
    ],
    "Achado": [
      "Consciente",
      "eupneico",
      "normotenso",
      "INTUBADO",
      "NORMOCARDICO",
      "SANGRANTE",
      "MONITORADO",
      "diurese presente",
      "pequena quantidade",
      "amarelo escuro",
      "tecido roseo",
      "DEPENDENTE DE DVA",
      "COURO CABELUDO INTEGRO",
      "DISCRETA ABERTURA OCULAR",
      "RHA PRESENTES",
      "REGULARMENTE PERFUNDIDAS",
      "AMARELO OURO",
      "REPOUSO NO LEITO"
    ],
    "Sinal ou Sintoma": [
      "sonolento",
      "hipocorado",
      "globoso",
      "semi-flacido",
      "exsudato",
      "HIPOTERMICO",
      "EDEMA",
      "tecido roseo",
      "queixas algicas",
      "DISCRETA ABERTURA OCULAR",
      "RONCOS DIFUSOS",
      "AUMENTO DA SECREÇÃO"
    ],
    "Localização ou Região Corporal": [
      "MSE",
      "abdomen",
      "MEMBROS",
      "SACRA",
      "regiao sacra"
    ],
    "Negação": [
      "indolor",
      "sem",
      "nao",
      "nega",
      "SEM"
    ],
    "Procedimento Diagnóstico": [
      "palpação",
      "AUSCULTA"
    ],
    "Procedimento Terapêutico ou Preventivo": [
      "cistostomia",
      "INTUBADO",
      "VM",
      "INFUNDINDO",
      "SVD",
      "sondagem vesical de demora",
      "cateter para hemodialise",
      "acesso venoso periferico",
      "soroterapia em curso",
      "curativo com placa de hidrocoloide",
      "curativo secundario",
      "medidas de conforto",
      "CATETER VENOSO CENTRAL DUPLO-LUMEM",
      "PLANO BASICO DE HIDRATAÇÃO",
      "SNE COM DIETA",
      "MEDIDAS DE HIGIENE",
      "MUDANÇA DE DECUBITO",
      "REPOUSO NO LEITO",
      "MUDANÇA DE DECUBITO 2/2"
    ],
    "Doença ou Síndrome": [
      "UP"
    ],
    "Substância Corporal": [
      "exsudato"
    ],
    "Atividade de Assistência à Saúde": [
      "cuidados",
      "PRESCRIÇÃO",
      "CUIDADOS INTENSIVOS",
      "OBSERVAR NIVEL DE CONSCIENCIA"
    ],
    "Organização Relacionada à Saúde": [
      "HOSPITAL",
      "UTI",
      "centro cirúrgico"
    ],
    "Dispositivo Médico": [
      "TOT",
      "SVD",
      "cateter para hemodialise",
      "acesso venoso periferico",
      "curativo com placa de hidrocoloide",
      "curativo secundario",
      "CATETER VENOSO CENTRAL DUPLO-LUMEM",
      "ATADURA DE CREPE",
      "COLCHÃO DE AR"
    ],
    "Conceito Quantitativo": [
      "7",
      "24",
      "sete dias",
      "35 , 8 c",
      "69 bpm",
      "48 mg",
      "10 ML/H"
    ],
    "Parte do Corpo, Órgão ou Componente Orgânico": [
      "RIMA",
      "jugular interna D",
      "PAVILHÃO AURICULAR A DIREITA",
      "JUGULAR ESQUERDA",
      "CALCANEO ESQUERDO"
    ],
    "Hormônio": [
      "NORADRENALINA"
    ],
    "Substância Farmacológica": [
      "NORADRENALINA",
      "IRUXOL"
    ],
    "Função Patológica": [
      "EDEMA"
    ],
    "Produto Intelectual": [
      "PRESCRIÇÃO"
    ],
    "Lesão ou Envenenamento": [
      "FRATURA DO MEMBRO INFERIOR",
      "FRATURA DO FEMUR"
    ],
    "Função Fisiológica": [
      "diurese presente"
    ],
    "Conceito Qualitativo": [
      "pequena quantidade",
      "estagio II",
      "CACIFO ++/4"
    ],
    "Conceito Temporal": [
      "sete dias"
    ],
    "Atributo Clínico": [
      "PRESSÃO ARTERIAL"
    ]
  },
  "labels": {
    "cacifo ++/4": {
      "capitulo": "15"
    },
    "tecido roseo": {
      "capitulo": "14"
    },
    "nao": {
      "capitulo": "21"
    },
    "medidas de higiene": {
      "capitulo": "21"
    },
    "ausculta": {
      "capitulo": "08"
    },
    "svd": {
      "capitulo": "16"
    },
    "dependente de dva": {
      "capitulo": "24"
    },
    "monitorado": {
      "capitulo": "24"
    },
    "mudança de decubito 2/2": {
      "capitulo": "15"
    },
    "semi-flacido": {
      "capitulo": "15"
    },
    "sne com dieta": {
      "capitulo": "13"
    },
    "tot": {
      "capitulo": "08"
    },
    "globoso": {
      "capitulo": "13"
    },
    "prescrição": {
      "capitulo": "24"
    },
    "calcaneo esquerdo": {
      "capitulo": "15"
    },
    "palpação": {
      "capitulo": "08"
    },
    "pequena quantidade": {
      "capitulo": "21"
    },
    "curativo secundario": {
      "capitulo": "15"
    },
    "queixas algicas": {
      "capitulo": "21"
    },
    "rima": {
      "capitulo": "10"
    },
    "edema": {
      "capitulo": "15"
    },
    "iruxol": {
      "capitulo": "25"
    },
    "cateter venoso central duplo-lumem": {
      "capitulo": "11"
    },
    "cistostomia": {
      "capitulo": "16"
    },
    "membros": {
      "capitulo": "11"
    },
    "jugular interna d": {
      "capitulo": "11"
    },
    "pavilhão auricular a direita": {
      "capitulo": "10"
    },
    "aumento da secreção": {
      "capitulo": "12"
    },
    "enf": {
      "capitulo": "06"
    },
    "jugular esquerda": {
      "capitulo": "11"
    },
    "mudança de decubito": {
      "capitulo": "15"
    },
    "normocardico": {
      "capitulo": "08"
    },
    "normotenso": {
      "capitulo": "11"
    },
    "cuidados intensivos": {
      "capitulo": "24"
    },
    "sonolento": {
      "capitulo": "06"
    },
    "vm": {
      "capitulo": "08"
    },
    "couro cabeludo integro": {
      "capitulo": "14"
    },
    "discreta abertura ocular": {
      "capitulo": "09"
    },
    "consciente": {
      "capitulo": "06"
    },
    "fratura do femur": {
      "capitulo": "15"
    },
    "69 bpm": {
      "capitulo": "08"
    },
    "regiao sacra": {
      "capitulo": "16"
    },
    "nega": {
      "capitulo": "21"
    },
    "hospital": {
      "capitulo": "24"
    },
    "sangrante": {
      "capitulo": "16"
    },
    "noradrenalina": {
      "capitulo": "11"
    },
    "cuidados": {
      "capitulo": "24"
    },
    "uti": {
      "capitulo": "24"
    },
    "regularmente perfundidas": {
      "capitulo": "15"
    },
    "diurese presente": {
      "capitulo": "16"
    },
    "indolor": {
      "capitulo": "08"
    },
    "fratura do membro inferior": {
      "capitulo": "15"
    },
    "sem": {
      "capitulo": "21"
    },
    "colchão de ar": {
      "capitulo": "24"
    },
    "48 mg": {
      "capitulo": "25"
    },
    "hipotermico": {
      "capitulo": "05"
    }
  }
}