{
  "prontuario_id": 728,
  "text": "Em 20/03/12, Às 09:40h: # 9º DI UTI-II. # 6º DI SNE. # 2º DI Traqueostomia. Sonolenta, glasgow 06, pupilas anisocóricas D>E fotorreagentes. SNE com dieta em curso à 75 ml/h. Traqueotomizada, em névoa úmida 3l. Acesso periférico em antebraço D, salinizado. Micção espontânea, aspecto amarelo escuro em grande quantidade. Decubitada. Às 18h: Paciente glasgow 10, pupilas isofotorreagentes, traqueostomizado sob névoa umida continua, SNE com plano de dieta em curso, diurese espontanea e em uropen, pele com flictemas, principalmente em MMSS, AVP em MSE com soroterapia em curso, realizou EEG durante à tarde, ainda sem laudo, média quantidade de secreção traqueal de aspecto fluidificado, SSVV estaveis e segue sob cuidados. 5º DI vítima de FAF em crânio, 4º PO de drenagem de HIC + HED + retirada de projétil alojado em crânio + correção de fístula liquórica + MPIC, 5º D de cateter de PIC, 5º D de SNG, 5º D de TOT + VM, 5º D de acesso venoso central em subclávia D - troca de curativo em 10/4/12, 4º D de cateter de PAM em artéria radial E, 6º D de SVD. SSVV: PA: 144/68, FC: 71, FR: 20, T: 37,1º C, SpO2: 100%. Ao exame: Ramsay 6, pupilas isomióticas, curativo cefálico limpo e seco, monitorização de PIC 19-22 mmHg, SNG com dieta a 60 ml/h, entubado com TOT 8, rima 24, em ventilação mecânica modo VCV, Vc 500 ml, PEEP 5, FiO2 30%, secreção traqueobrônquica mucosa em média quantidade, acesso venoso central em subclávia D com Dormonid 20 ml/h + Fentanil 12 ml/h + Propofol 10 ml/h + Noradrenalina 6 ml/h, monitorizado, estável hemodinamicamente, cateter de PAM em artéria radial E, flictema em dorso de mão D, abdome globoso, flácido, RHA +, SVD com diurese efetiva, evacuação ausente, mantendo curativo compressivo em região inguinal D, extremidades quentes e bem perfundidas, higienizado e sentado no leito, pele íntegra. ",
  "entities": {
    "Abreviação": [
      "UTI-II",
      "SNE",
      "MMSS",
      "AVP",
      "MSE",
      "EEG",
      "PO",
      "HED",
      "MPIC",
      "SNG",
      "TOT",
      "VM",
      "SVD",
      "SSVV",
      "PA",
      "FC",
      "FR",
      "T",
      "SpO2",
      "Vc",
      "PEEP",
      "FiO2",
      "SNE com dieta",
      "antebraço D",
      "SSVV estaveis",
      "FAF em crânio",
      "drenagem de HIC",
      "cateter de PIC",
      "subclávia D",
      "cateter de PAM",
      "artéria radial E",
      "monitorização de PIC",
      "SNG com dieta",
      "modo VCV",
      "dorso de mão D",
      "RHA +",
      "SVD com diurese efetiva",
      "região inguinal D"
    ],
    "Organização Relacionada à Saúde": [
      "UTI-II"
    ],
    "Dispositivo Médico": [
      "SNE",
      "uropen",
      "AVP",
      "SNG",
      "TOT",
      "SVD",
      "Acesso periférico",
      "cateter de PIC",
      "acesso venoso central",
      "cateter de PAM",
      "curativo cefálico",
      "curativo compressivo"
    ],
    "Procedimento Terapêutico ou Preventivo": [
      "SNE",
      "Traqueostomia",
      "Traqueotomizada",
      "salinizado",
      "Decubitada",
      "traqueostomizado",
      "AVP",
      "soroterapia",
      "HED",
      "MPIC",
      "SNG",
      "TOT",
      "VM",
      "SVD",
      "entubado",
      "PEEP",
      "FiO2",
      "higienizado",
      "SNE com dieta",
      "névoa úmida",
      "Acesso periférico",
      "névoa umida continua",
      "drenagem de HIC",
      "retirada de projétil alojado em crânio",
      "correção de fístula liquórica",
      "cateter de PIC",
      "acesso venoso central",
      "troca de curativo",
      "cateter de PAM",
      "curativo cefálico",
      "SNG com dieta",
      "ventilação mecânica",
      "modo VCV",
      "curativo compressivo"
    ],
    "Sinal ou Sintoma": [
      "Sonolenta",
      "mucosa",
      "flictema",
      "globoso",
      "glasgow 06",
      "glasgow 10",
      "pupilas isomióticas"
    ],
    "Parte do Corpo, Órgão ou Componente Orgânico": [
      "pupilas",
      "pele",
      "antebraço D",
      "subclávia D",
      "artéria radial E"
    ],
    "Achado": [
      "fotorreagentes",
      "Traqueotomizada",
      "salinizado",
      "Decubitada",
      "traqueostomizado",
      "SVD",
      "limpo",
      "seco",
      "entubado",
      "flácido",
      "evacuação",
      "quentes",
      "Micção espontânea",
      "aspecto amarelo escuro",
      "pupilas isofotorreagentes",
      "diurese espontanea",
      "aspecto fluidificado",
      "SSVV estaveis",
      "Ramsay 6",
      "estável hemodinamicamente",
      "RHA +",
      "SVD com diurese efetiva",
      "bem perfundidas",
      "sentado no leito",
      "pele íntegra"
    ],
    "Conceito Quantitativo": [
      "3l",
      "144/68",
      "71",
      "20",
      "100%",
      "8",
      "24",
      "5",
      "30%",
      "75 ml/h",
      "37 , 1º C",
      "19-22 mmHg",
      "60 ml/h",
      "500 ml",
      "20 ml/h",
      "12 ml/h",
      "10 ml/h",
      "6 ml/h"
    ],
    "Paciente ou Grupo com Deficiência": [
      "Paciente",
      "vítima"
    ],
    "Localização ou Região Corporal": [
      "MMSS",
      "MSE",
      "abdome",
      "extremidades",
      "dorso de mão D",
      "região inguinal D"
    ],
    "Procedimento Diagnóstico": [
      "EEG",
      "exame",
      "monitorizado",
      "monitorização de PIC"
    ],
    "Atividade de Assistência à Saúde": [
      "cuidados"
    ],
    "Conceito Temporal": [
      "PO"
    ],
    "Doença ou Síndrome": [
      "HED"
    ],
    "Atributo Clínico": [
      "SSVV",
      "PA",
      "FC",
      "FR",
      "T",
      "SpO2"
    ],
    "Substância Química Orgânica": [
      "Dormonid",
      "Fentanil",
      "Propofol"
    ],
    "Substância Farmacológica": [
      "Dormonid",
      "Fentanil",
      "Propofol",
      "Noradrenalina",
      "névoa úmida"
    ],
    "Hormônio": [
      "Noradrenalina"
    ],
    "Função Fisiológica": [
      "evacuação",
      "Micção espontânea",
      "diurese espontanea"
    ],
    "Negação": [
      "ausente"
    ],
    "Conceito Qualitativo": [
      "grande quantidade",
      "média quantidade",
      "bem perfundidas"
    ],
    "Substância Corporal": [
      "secreção traqueal",
      "secreção traqueobrônquica"
    ],
    "Lesão ou Envenenamento": [
      "FAF em crânio"
    ]
  },
  "labels": {
    "abdome": {
      "capitulo": "08"
    },
    "artéria radial e": {
      "capitulo": "14"
    },
    "aspecto amarelo escuro": {
      "capitulo": "07"
    },
    "ausente": {
      "capitulo": "09"
    },
    "cateter de pam": {
      "capitulo": "15"
    },
    "cateter de pic": {
      "capitulo": "16"
    },
    "correção de fístula liquórica": {
      "capitulo": "17"
    },
    "curativo cefálico": {
      "capitulo": "18"
    },
    "curativo compressivo": {
      "capitulo": "19"
    },
    "dorso de mão d": {
      "capitulo": "20"
    },
    "entubado": {
      "capitulo": "21"
    },
    "extremidades": {
      "capitulo": "22"
    },
    "flictema": {
      "capitulo": "23"
    },
    "fotorreagentes": {
      "capitulo": "24"
    },
    "glásgow 10": {
      "capitulo": "25"
    },
    "glásgow 06": {
      "capitulo": "26"
    },
    "hed": {
      "capitulo": "27"
    },
    "higienizado": {
      "capitulo": "28"
    },
    "limpo": {
      "capitulo": "29"
    },
    "micção espontânea": {
      "capitulo": "30"
    },
    "mpic": {
      "capitulo": "31"
    },
    "mucosa": {
      "capitulo": "32"
    },
    "névoa úmida": {
      "capitulo": "33"
    },
    "pele íntegra": {
      "capitulo": "34"
    },
    "peep": {
      "capitulo": "35"
    },
    "pupilas isofotorreagentes": {
      "capitulo": "36"
    },
    "pupilas isomióticas": {
      "capitulo": "37"
    },
    "rha +": {
      "capitulo": "38"
    },
    "salinizado": {
      "capitulo": "39"
    },
    "secreção traqueal": {
      "capitulo": "40"
    },
    "secreção traqueobrônquica": {
      "capitulo": "41"
    },
    "sentado no leito": {
      "capitulo": "42"
    },
    "sng com dieta": {
      "capitulo": "43"
    },
    "spo2": {
      "capitulo": "44"
    },
    "ssvv estaveis": {
      "capitulo": "45"
    },
    "subclávia d": {
      "capitulo": "46"
    },
    "svd com diurese efetiva": {
      "capitulo": "47"
    },
    "traqueostomia": {
      "capitulo": "48"
    },
    "traqueotomizada": {
      "capitulo": "49"
    },
    "traqueostomizado": {
      "capitulo": "50"
    },
    "vcv": {
      "capitulo": "51"
    }
  }
}