{
  "prontuario_id": 821,
  "text": "Às 14:18 HS: CONSCIENTE, ORIENTADA, EUPNEICA, ACEITA DIETA, CATETER EM JUGULAR ESQ PARA HEMODIÁLISE, ABDOME PLANO, FLÁCIDO, INDOLOR A PALPAÇÃO, DIURESE POUCO VOLUME, EVACUAÇÃO NORMAL, SEM QUEIXAS ALGICAS, SEM FORÇA MUSCULAR EM MMII, MANTEM PRECAUÇÃO DE CONTATO. Às 15:13: CLIENTE REFERE DOR MODERADA EM JOELHO D, CONSCIENTE, COMUNICATIVA, EUPNEICA, REPOUSO NO LEITO, ACEITANDO BEM A DIETA, ACESSO PERIFÉRICO EM MSE SALINIZADO, ABDOMEN GLOBOSO E FLÁCIDO, MANTENDO CATETER PERIDURAL PARA ANALGESIA, CTVO LIMPO E SECO EM MID, PERFUSÃO DISTAL PRESERVADA, MICÇÃO PRESENTE. Às 16:32: FOI DIMINUIDO O GOTEJAMENTO DA NPT EM BI PARA 40 ML/H, CONFORME ORIENTAÇÃO DO DRº VITAL BRASIL. Às 18:16hs: Estavel hemodinamicamente, segue de alta para ala b-16-2 acompanhado dos familiares e a enfermagem. Às 00:18h: encontra-se consciente, orientada, pouco comunicativa, ssvv dentro dos parametros de normalidade, mantendo acesso venoso periférico em MSD permeavel, salinizado no momento, mantem colar cervical, apresenta escoriações em face, sem queixas álgicas, SEGUE CUIDADOS.  ",
  "entities": {
    "Achado": [
      "CONSCIENTE",
      "ORIENTADA",
      "EUPNEICA",
      "FLÁCIDO",
      "COMUNICATIVA",
      "SALINIZADO",
      "LIMPO",
      "SECO",
      "consciente",
      "orientada",
      "permeavel",
      "salinizado",
      "ACEITA DIETA",
      "POUCO VOLUME",
      "EVACUAÇÃO NORMAL",
      "REPOUSO NO LEITO",
      "ACEITANDO BEM",
      "PERFUSÃO DISTAL PRESERVADA",
      "MICÇÃO PRESENTE",
      "Estavel hemodinamicamente",
      "pouco comunicativa",
      "ssvv dentro dos parametros de normalidade"
    ],
    "Dispositivo Médico": [
      "CATETER",
      "CTVO",
      "ACESSO PERIFÉRICO",
      "CATETER PERIDURAL",
      "acesso venoso periférico",
      "colar cervical"
    ],
    "Procedimento Terapêutico ou Preventivo": [
      "CATETER",
      "HEMODIÁLISE",
      "SALINIZADO",
      "CTVO",
      "salinizado",
      "PRECAUÇÃO DE CONTATO",
      "REPOUSO NO LEITO",
      "ACESSO PERIFÉRICO",
      "DIMINUIDO O GOTEJAMENTO DA NPT",
      "acesso venoso periférico",
      "colar cervical"
    ],
    "Localização ou Região Corporal": [
      "ABDOME",
      "MSE",
      "ABDOMEN",
      "MSD",
      "face"
    ],
    "Negação": [
      "INDOLOR",
      "SEM",
      "sem"
    ],
    "Procedimento Diagnóstico": [
      "PALPAÇÃO"
    ],
    "Função Fisiológica": [
      "DIURESE",
      "EVACUAÇÃO NORMAL",
      "MICÇÃO PRESENTE"
    ],
    "Paciente ou Grupo com Deficiência": [
      "CLIENTE"
    ],
    "Abreviação": [
      "MSE",
      "CTVO",
      "BI",
      "DRº",
      "MSD",
      "JUGULAR ESQ",
      "JOELHO D",
      "EM MID",
      "DIMINUIDO O GOTEJAMENTO DA NPT",
      "ssvv dentro dos parametros de normalidade"
    ],
    "Atividade de Assistência à Saúde": [
      "alta",
      "CUIDADOS"
    ],
    "Grupo Familiar": [
      "familiares"
    ],
    "Grupo Profissional ou Ocupacional": [
      "enfermagem"
    ],
    "Lesão ou Envenenamento": [
      "escoriações"
    ],
    "Parte do Corpo, Órgão ou Componente Orgânico": [
      "JUGULAR ESQ",
      "JOELHO D"
    ],
    "Sinal ou Sintoma": [
      "QUEIXAS ALGICAS",
      "DOR MODERADA",
      "queixas álgicas"
    ],
    "Função de Órgão ou Tecido": [
      "FORÇA MUSCULAR"
    ],
    "Conceito Quantitativo": [
      "40 ML/H"
    ]
  },
  "labels": {
    "acesso venoso periférico": {
      "capitulo": "01"
    },
    "diurese": {
      "capitulo": "14"
    },
    "alta": {
      "capitulo": "21"
    },
    "diminuido o gotejamento da npt": {
      "capitulo": "05"
    },
    "flácido": {
      "capitulo": "07"
    },
    "palpação": {
      "capitulo": "09"
    },
    "repouso no leito": {
      "capitulo": "10"
    },
    "joelho d": {
      "capitulo": "11"
    },
    "escoriações": {
      "capitulo": "12"
    },
    "enfermagem": {
      "capitulo": "13"
    },
    "mse": {
      "capitulo": "14"
    },
    "eupneica": {
      "capitulo": "15"
    },
    "comunicativa": {
      "capitulo": "16"
    },
    "consciente": {
      "capitulo": "17"
    },
    "aceita dieta": {
      "capitulo": "18"
    },
    "40 ml/h": {
      "capitulo": "19"
    },
    "perfusão distal preservada": {
      "capitulo": "20"
    },
    "queixas algicas": {
      "capitulo": "21"
    },
    "msd": {
      "capitulo": "22"
    },
    "indolor": {
      "capitulo": "23"
    },
    "em mid": {
      "capitulo": "24"
    },
    "ctvo": {
      "capitulo": "25"
    },
    "salinizado": {
      "capitulo": "26"
    },
    "permeavel": {
      "capitulo": "27"
    },
    "abdome": {
      "capitulo": "28"
    },
    "dor moderada": {
      "capitulo": "29"
    },
    "pouco volume": {
      "capitulo": "30"
    },
    "pouco comunicativa": {
      "capitulo": "31"
    },
    "ssvv dentro dos parametros de normalidade": {
      "capitulo": "32"
    },
    "aceitando bem": {
      "capitulo": "33"
    },
    "cateter": {
      "capitulo": "34"
    },
    "acesso periférico": {
      "capitulo": "35"
    },
    "bi": {
      "capitulo": "36"
    },
    "sem": {
      "capitulo": "37"
    },
    "orientada": {
      "capitulo": "38"
    },
    "face": {
      "capitulo": "39"
    },
    "queixas álgicas": {
      "capitulo": "40"
    },
    "limpo": {
      "capitulo": "41"
    },
    "cateter peridural": {
      "capitulo": "42"
    },
    "cuidados": {
      "capitulo": "43"
    },
    "familiares": {
      "capitulo": "44"
    },
    "precaução de contato": {
      "capitulo": "45"
    },
    "colar cervical": {
      "capitulo": "46"
    },
    "cliente": {
      "capitulo": "47"
    },
    "força muscular": {
      "capitulo": "48"
    },
    "micção presente": {
      "capitulo": "49"
    },
    "hemodiálise": {
      "capitulo": "50"
    },
    "jugular esq": {
      "capitulo": "51"
    },
    "evacuação normal": {
      "capitulo": "52"
    },
    "drº": {
      "capitulo": "53"
    },
    "seco": {
      "capitulo": "54"
    },
    "abdomen": {
      "capitulo": "55"
    },
    "estavel hemodinamicamente": {
      "capitulo": "56"
    }
  }
}