{
  "prontuario_id": 402,
  "text": "12H Glasgow 10 (O 4 + V 1 + M 5), pupilas isocóricas fotorreagentes. Em VM modo PCV, Peep 8, PI 24, FiO2 41%. Traqueostomizado, uso contínuo de filtro de barreira e aspiração via sistema aberto de secreção espessa hemática. Acesso central monolumem em subclávia D com curativo de filme transparente infundindo soroterapia. CPP com roncos difusos. Gastrostomia com infusão contínua de dieta à 40 ml/h. Abdomem flácido, RHA +. SVD com diurese presente e de aspecto amarelo-claro, evacuação ausente. Múltiplas úlceras por pressão em protuberâncias ósseas, uso de colchão de ar. Mantém com luvas e botas de aquecimento. Pele hipocorada, extremidades frias e cianóticas, perfusão periférica diminuída. Monitorizado contínuamente com parâmetros de PA não invasiva, cardioscopia e oximetria de pulso. Segue sob cuidados intensivos e precaução de contato para Pseudomonas aeruginosa. Enfª FLORENCE NIGHTINGALE. # Apresentou hipotensão severa por volta das 11h, infundido 1000 ml de voluvem + 01 unidade de concentrado de hemácias, iniciado noradrenalina (24 mg) à 100 ml/h.  # Solicitado materias para punção de PAM em região de femural. FRATURAS ENVOLVENDO MULTIPLAS REGIOES DO CORPO. 00:30h: Encontra-se consciente, orientado , ansioso, em repouso no leito, ssvv dentro dos parametros de normalidade, mantem acesso venoso periférico em  MSD permeavel salinizado no momento, apresenta tala gessada em MIE , curativo limpo e seco , refere baixa aceitação alimentar, eliminações fisiologicas presentes, segue sob cuidados de enfermagem. Enf FLORENCE NIGHTINGALE. FRATURA DO CALCANEO.",
  "entities": {
    "Parte do Corpo, Órgão ou Componente Orgânico": [
      "pupilas",
      "subclávia D"
    ],
    "Achado": [
      "isocóricas",
      "fotorreagentes",
      "Traqueostomizado",
      "consciente",
      "orientado",
      "permeavel",
      "salinizado",
      "limpo",
      "seco",
      "RHA +",
      "diurese presente",
      "aspecto amarelo-claro",
      "repouso no leito",
      "ssvv dentro dos parametros de normalidade",
      "eliminações fisiologicas presentes"
    ],
    "Procedimento Terapêutico ou Preventivo": [
      "VM",
      "Peep",
      "PI",
      "FiO2",
      "Traqueostomizado",
      "soroterapia",
      "Gastrostomia",
      "SVD",
      "salinizado",
      "curativo",
      "modo PCV",
      "filtro de barreira",
      "aspiração via sistema aberto",
      "Acesso central monolumem",
      "curativo de filme transparente",
      "infusão contínua de dieta",
      "colchão de ar",
      "luvas e botas de aquecimento",
      "precaução de contato",
      "concentrado de hemácias",
      "punção de PAM",
      "repouso no leito",
      "acesso venoso periférico",
      "tala gessada"
    ],
    "Abreviação": [
      "VM",
      "Peep",
      "PI",
      "FiO2",
      "CPP",
      "SVD",
      "Enfª",
      "MSD",
      "MIE",
      "Enf",
      "modo PCV",
      "subclávia D",
      "RHA +",
      "PA não invasiva",
      "punção de PAM",
      "ssvv dentro dos parametros de normalidade"
    ],
    "Conceito Quantitativo": [
      "8",
      "24",
      "41%",
      "40 ml/h",
      "1000 ml",
      "01 unidade",
      "24 mg",
      "100 ml/h"
    ],
    "Localização ou Região Corporal": [
      "CPP",
      "Abdomem",
      "extremidades",
      "MSD",
      "MIE",
      "protuberâncias ósseas",
      "região de femural"
    ],
    "Dispositivo Médico": [
      "SVD",
      "materias",
      "curativo",
      "filtro de barreira",
      "Acesso central monolumem",
      "curativo de filme transparente",
      "colchão de ar",
      "luvas e botas de aquecimento",
      "acesso venoso periférico",
      "tala gessada"
    ],
    "Função Fisiológica": [
      "evacuação",
      "diurese presente",
      "eliminações fisiologicas presentes"
    ],
    "Negação": [
      "ausente"
    ],
    "Procedimento Diagnóstico": [
      "cardioscopia",
      "Monitorizado contínuamente",
      "PA não invasiva",
      "oximetria de pulso"
    ],
    "Grupo Profissional ou Ocupacional": [
      "Enfª",
      "Enf"
    ],
    "Substância Farmacológica": [
      "voluvem",
      "noradrenalina"
    ],
    "Substância Química Orgânica": [
      "noradrenalina"
    ],
    "Hormônio": [
      "noradrenalina"
    ],
    "Sinal ou Sintoma": [
      "ansioso",
      "Glasgow 10",
      "secreção espessa hemática",
      "roncos difusos",
      "Pele hipocorada",
      "perfusão periférica diminuída",
      "hipotensão severa",
      "baixa aceitação alimentar"
    ],
    "Substância Corporal": [
      "secreção espessa hemática"
    ],
    "Doença ou Síndrome": [
      "Múltiplas úlceras por pressão"
    ],
    "Objeto Manufaturado": [
      "colchão de ar"
    ],
    "Atividade de Assistência à Saúde": [
      "cuidados intensivos",
      "cuidados de enfermagem"
    ],
    "Bactéria": [
      "Pseudomonas aeruginosa"
    ],
    "Lesão ou Envenenamento": [
      "FRATURAS ENVOLVENDO MULTIPLAS REGIOES DO CORPO",
      "FRATURA DO CALCANEO"
    ]
  },
  "labels": {}
}