{
  "prontuario_id": 686,
  "text": "EVOLUÇAO DIA 02/02/10: Acordada, responsiva, eupneica, em repouso no leito e com relato de discreta algia em mie ao se mobilizar. Acesso venoso periferico MSD salinizado, relata aceitaçao alimentar e diurese presente. Enfermeira Florence Nightingale. EMBOLIA E TROMBOSE DE ARTERIAS DOS MEMBROS INFERIORES. À 01:40 H: CLIENTE CONSCIENTE, COMUNICATIVO, ANSIOSO, REPOUSO, AFEBRIL, EUPNEICO, ORIENTADO. ACEITA DIETA OFERECIDA. MANTEM ACESSO PERIFERICO EM MSE SALINIZADO. APRESENTA CURATIVO OCLUSIVO EM REGIÃO DE MIE ASPECTO SECO E LIMPO EXTERNAMENTE. ELIMINAÇÕES NORMAIS. SEGUE EM OBSERVAÇÃO E CUIDADOS. ENFª FLORENCE NIGHTINGALE, COREN XXXX. FRATURA DO PE EXCETO DO TORNOZELO. Em 07/04/2010, 12 hs: Consciente, comunicativa, corada. Sem queixas. Tosse produtiva. Refere mal estar quando administrada a medicacao (ansia). Diurese e evacuacao presentes. Visita controlada. Ac de Enfermagem Florence, sob supervisao da prof Florence Nightingale. PNEUMONIA BACTERIANA NAO ESPECIFICADA. Às 06:11 h: Paciente retirou a SNE, em teste com agua apresenta boa deglutição VO, passo em plantão a necessidade de avaliação da fonoaudiologia para verificar a permanencia da sonda. Enf Florence Nightingale. TRAUMATISMO INTRACRANIANO. Às 7h30min: Encaminhado para o Raio-X para realizar fistulografia. Enfª Florence Nightingale, COREN XX  XXXX. OSTEOMIELITE.",
  "entities": {
    "Achado": [
      "Acordada",
      "responsiva",
      "eupneica",
      "salinizado",
      "CONSCIENTE",
      "COMUNICATIVO",
      "ANSIOSO",
      "REPOUSO",
      "AFEBRIL",
      "EUPNEICO",
      "ORIENTADO",
      "SALINIZADO",
      "SECO",
      "LIMPO",
      "Consciente",
      "comunicativa",
      "corada",
      "Diurese",
      "evacuacao",
      "presentes",
      "repouso no leito",
      "Acesso venoso periferico",
      "aceitaçao alimentar",
      "diurese presente",
      "ACEITA DIETA OFERECIDA",
      "ELIMINAÇÕES NORMAIS",
      "boa deglutição VO"
    ],
    "Localização ou Região Corporal": [
      "mie",
      "MSD",
      "MSE",
      "REGIÃO DE MIE"
    ],
    "Abreviação": [
      "mie",
      "MSD",
      "MSE",
      "ENFª",
      "Enf",
      "Enfª",
      "REGIÃO DE MIE",
      "retirou a SNE",
      "boa deglutição VO"
    ],
    "Procedimento Terapêutico ou Preventivo": [
      "salinizado",
      "SALINIZADO",
      "repouso no leito",
      "Acesso venoso periferico",
      "ACESSO PERIFERICO",
      "CURATIVO OCLUSIVO",
      "Visita controlada",
      "retirou a SNE"
    ],
    "Grupo Profissional ou Ocupacional": [
      "Enfermeira",
      "ENFª",
      "Enfermagem",
      "Enf",
      "Enfª"
    ],
    "Paciente ou Grupo com Deficiência": [
      "CLIENTE",
      "Paciente"
    ],
    "Sinal ou Sintoma": [
      "ANSIOSO",
      "queixas",
      "ansia",
      "discreta algia",
      "Tosse produtiva",
      "mal estar"
    ],
    "Negação": [
      "AFEBRIL",
      "EXCETO",
      "Sem"
    ],
    "Conceito Espacial": [
      "EXTERNAMENTE"
    ],
    "Atividade de Assistência à Saúde": [
      "OBSERVAÇÃO",
      "CUIDADOS",
      "avaliação da fonoaudiologia"
    ],
    "Parte do Corpo, Órgão ou Componente Orgânico": [
      "TORNOZELO"
    ],
    "Substância Farmacológica": [
      "medicacao"
    ],
    "Função Fisiológica": [
      "Diurese",
      "evacuacao",
      "diurese presente",
      "ELIMINAÇÕES NORMAIS"
    ],
    "Organização Relacionada à Saúde": [
      "plantão"
    ],
    "Procedimento Diagnóstico": [
      "Raio-X",
      "fistulografia"
    ],
    "Doença ou Síndrome": [
      "OSTEOMIELITE",
      "PNEUMONIA BACTERIANA"
    ],
    "Dispositivo Médico": [
      "Acesso venoso periferico",
      "ACESSO PERIFERICO",
      "CURATIVO OCLUSIVO"
    ],
    "Lesão ou Envenenamento": [
      "FRATURA DO PE",
      "TRAUMATISMO INTRACRANIANO"
    ]
  },
  "labels": {
    "aceita dieta oferecida": {
      "capitulo": "05.11.10"
    },
    "visita controlada": {
      "capitulo": "05.11.10"
    },
    "queixas": {
      "capitulo": "21.89.11"
    },
    "limpo": {
      "capitulo": "14.01.10"
    },
    "acordada": {
      "capitulo": "21.89.11"
    },
    "paciente": {
      "capitulo": "21.89.11"
    },
    "externamente": {
      "capitulo": "14.01.10"
    },
    "eliminações normais": {
      "capitulo": "14.01.10"
    },
    "avaliação da fonoaudiologia": {
      "capitulo": "21.89.11"
    },
    "aceitaçao alimentar": {
      "capitulo": "05.11.10"
    },
    "osteomielite": {
      "capitulo": "11.10.10"
    },
    "curativo oclusivo": {
      "capitulo": "14.01.10"
    },
    "enfª": {
      "capitulo": "21.89.11"
    },
    "eupneico": {
      "capitulo": "12.00.10"
    },
    "acesso venoso periferico": {
      "capitulo": "11.10.10"
    },
    "enfermeira": {
      "capitulo": "21.89.11"
    },
    "responsiva": {
      "capitulo": "21.89.11"
    },
    "orientado": {
      "capitulo": "21.89.11"
    },
    "presentes": {
      "capitulo": "21.89.11"
    },
    "boa deglutição vo": {
      "capitulo": "21.89.11"
    },
    "salinizado": {
      "capitulo": "11.10.10"
    },
    "medicacao": {
      "capitulo": "21.89.11"
    },
    "fratura do pe": {
      "capitulo": "15.01.10"
    },
    "enf": {
      "capitulo": "21.89.11"
    },
    "ansioso": {
      "capitulo": "21.89.11"
    },
    "comunicativa": {
      "capitulo": "21.89.11"
    },
    "mse": {
      "capitulo": "11.10.10"
    },
    "ansia": {
      "capitulo": "21.89.11"
    },
    "diurese": {
      "capitulo": "13.01.10"
    },
    "fistulografia": {
      "capitulo": "21.89.11"
    },
    "retirou a sne": {
      "capitulo": "21.89.11"
    },
    "corada": {
      "capitulo": "21.89.11"
    },
    "traumatismo intracraniano": {
      "capitulo": "08.50.10"
    },
    "seco": {
      "capitulo": "14.01.10"
    },
    "cliente": {
      "capitulo": "21.89.11"
    },
    "mie": {
      "capitulo": "13.01.10"
    },
    "exceto": {
      "capitulo": "21.89.11"
    },
    "msd": {
      "capitulo": "11.10.10"
    },
    "discreta algia": {
      "capitulo": "15.01.10"
    },
    "cuidados": {
      "capitulo": "21.89.11"
    },
    "comunicativo": {
      "capitulo": "21.89.11"
    },
    "repouso no leito": {
      "capitulo": "15.01.10"
    },
    "consciente": {
      "capitulo": "21.89.11"
    },
    "raio-x": {
      "capitulo": "21.89.11"
    },
    "tornozelo": {
      "capitulo": "15.01.10"
    },
    "diurese presente": {
      "capitulo": "13.01.10"
    },
    "enfermagem": {
      "capitulo": "21.89.11"
    },
    "evacuacao": {
      "capitulo": "13.01.10"
    },
    "tosse produtiva": {
      "capitulo": "12.00.10"
    },
    "sem": {
      "capitulo": "21.89.11"
    },
    "eupneica": {
      "capitulo": "12.00.10"
    },
    "afebril": {
      "capitulo": "12.00.10"
    },
    "plantão": {
      "capitulo": "21.89.11"
    }
  }
}