{
  "prontuario_id": 505,
  "text": "22:40h Encaminhada para TAC Cranio sem intercorrencias no trajeto, mantem TOT + VM + pupilas com discoria D. Enfermeira FLORENCE NIGHTINGALE, ACIDENTE VASCULAR CEREBRAL NAO ESPECIFICADO COMO HEMORRAGICO OU ISQUEMICO.   Paciente vinda do XXXX após contato prévio , com história de HAS , uso irregular de Enalapril.    Há 3 meses apresentando mal estar , epigastralgia e náuseas.   Realizou USG , que segundo o relato do filho , mostrou um \"probleminha no rim\" , e EDA com gastrite aguda (medicamentosa?). Segundo o filho , apresentava Cr = 2,6 na época , mas não chegou a levar ao médico que a acompanha.    Foi prescrito Omeprazol, com alguma melhora do quadro, mas há 4 dias confusa , desorientada e \"muito parada\" , sendo levada ao XXXX , onde doram realizados exames de lab. que revelaram Cr = 30  Ureia = 399 , K = 7,0 e anemia.       Sem outras alterações agudas.     História de Insuficiencia venosa cronica , com úlcera de repetição em MMII , em uso de Capilarema.    Colecistectomia há mais de 15 anos.    G = V  P = II ( 1 cesária ; 1 prematuro natimorto)  A = III.    Nega alergia a drogas e outras patologias.     Hipocorada, desidratada , taquipneica, afebril.  Pulsos periféricos simétricos , de amplitude diminuída.  Sem TJV.   Nuca livre.   Isocoria fotorreagente.  Sem deficit motor aparente.   AP = MV audíveis em AHT , crepitação em bases.   AC = RCR 2 t Irregular.    Abdomem = NDN    MMII = panturrilhas livres.  Dermatite ócrea.    PA = 134 x 98   FC = 76   SatO2 = 96  FR = 28   Dextro = 124   ECG = BRE   RX de torax com aumento de área cardíaca e congestão leve.     CD = Internação aos cuidados do Dr VITAL BRASIL ( nefro)             Exames.     Dra MARIA (XXXX) INSUFICIENCIA RENAL NAO ESPECIFICADA.",
  "entities": {
    "Atividade de Assistência à Saúde": [
      "Encaminhada",
      "Internação",
      "cuidados"
    ],
    "Negação": [
      "sem",
      "Sem",
      "Nega",
      "afebril"
    ],
    "Sinal ou Sintoma": [
      "intercorrencias",
      "epigastralgia",
      "náuseas",
      "confusa",
      "desorientada",
      "Hipocorada",
      "desidratada",
      "taquipneica",
      "pupilas com discoria D",
      "mal estar",
      "\"muito parada\"",
      "alterações agudas",
      "amplitude diminuída",
      "deficit motor",
      "crepitação em bases"
    ],
    "Dispositivo Médico": [
      "TOT"
    ],
    "Procedimento Terapêutico ou Preventivo": [
      "TOT",
      "VM",
      "Colecistectomia",
      "cesária"
    ],
    "Abreviação": [
      "TOT",
      "VM",
      "HAS",
      "USG",
      "EDA",
      "Cr",
      "K",
      "MMII",
      "G",
      "P",
      "A",
      "TJV",
      "AP",
      "AC",
      "NDN",
      "PA",
      "FC",
      "SatO2",
      "FR",
      "ECG",
      "BRE",
      "CD",
      "Dr",
      "nefro",
      "Dra",
      "TAC Cranio",
      "pupilas com discoria D",
      "exames de lab",
      "MV audíveis",
      "2 t",
      "RX de torax"
    ],
    "Grupo Profissional ou Ocupacional": [
      "Enfermeira",
      "médico",
      "nefro"
    ],
    "Paciente ou Grupo com Deficiência": [
      "Paciente"
    ],
    "Doença ou Síndrome": [
      "HAS",
      "anemia",
      "patologias",
      "BRE",
      "ACIDENTE VASCULAR CEREBRAL",
      "gastrite aguda",
      "Insuficiencia venosa cronica",
      "úlcera de repetição",
      "Dermatite ócrea",
      "INSUFICIENCIA RENAL"
    ],
    "Aminoácido, Peptídeo ou Proteína": [
      "Enalapril"
    ],
    "Substância Farmacológica": [
      "Enalapril",
      "Omeprazol",
      "Capilarema"
    ],
    "Procedimento Diagnóstico": [
      "USG",
      "EDA",
      "AP",
      "AC",
      "ECG",
      "Exames",
      "TAC Cranio",
      "RX de torax"
    ],
    "Grupo Familiar": [
      "filho"
    ],
    "Procedimento Laboratorial": [
      "Cr",
      "Ureia",
      "K",
      "Exames",
      "exames de lab"
    ],
    "Substância Química Orgânica": [
      "Omeprazol"
    ],
    "Localização ou Região Corporal": [
      "MMII",
      "Nuca",
      "Abdomem"
    ],
    "Conceito Quantitativo": [
      "V",
      "II",
      "1",
      "III",
      "76",
      "96",
      "28",
      "134 x 98"
    ],
    "Achado": [
      "afebril",
      "livre",
      "Isocoria",
      "fotorreagente",
      "RCR",
      "melhora do quadro",
      "prematuro natimorto",
      "MV audíveis",
      "2 t",
      "panturrilhas livres"
    ],
    "Atributo Clínico": [
      "PA",
      "FC",
      "SatO2",
      "FR"
    ],
    "Resultado Laboratorial ou de Teste": [
      "BRE",
      "gastrite aguda",
      "aumento de área cardíaca",
      "congestão leve"
    ],
    "Função Patológica": [
      "alergia a drogas"
    ]
  },
  "labels": {
    "gastrite aguda": {
      "capitulo": "13.10"
    },
    "encaminhada": {
      "capitulo": "24.10"
    },
    "dermatite ócrea": {
      "capitulo": "14.0"
    },
    "ureia": {
      "capitulo": "21.10"
    },
    "enalapril": {
      "capitulo": "24.10"
    },
    "omeprazol": {
      "capitulo": "24.10"
    },
    "enfermeira": {
      "capitulo": "24.10"
    },
    "alergia a drogas": {
      "capitulo": "24.10"
    },
    "melhora do quadro": {
      "capitulo": "24.10"
    },
    "insuficiencia renal": {
      "capitulo": "16.10"
    },
    "nefro": {
      "capitulo": "16.10"
    },
    "alterações agudas": {
      "capitulo": "21.10"
    },
    "rx de torax": {
      "capitulo": "21.10"
    },
    "cr": {
      "capitulo": "21.10"
    },
    "panturrilhas livres": {
      "capitulo": "15.0"
    },
    "desorientada": {
      "capitulo": "21.10"
    },
    "deficit motor": {
      "capitulo": "21.10"
    },
    "tot": {
      "capitulo": "21.10"
    },
    "insuficiencia venosa cronica": {
      "capitulo": "15.0"
    },
    "ii": {
      "capitulo": "21.10"
    },
    "desidratada": {
      "capitulo": "21.10"
    },
    "p": {
      "capitulo": "21.10"
    },
    "livre": {
      "capitulo": "21.10"
    },
    "congestão leve": {
      "capitulo": "21.10"
    },
    "patologias": {
      "capitulo": "21.10"
    },
    "cesária": {
      "capitulo": "21.10"
    },
    "acidente vascular cerebral": {
      "capitulo": "145.0"
    },
    "usg": {
      "capitulo": "21.10"
    },
    "náuseas": {
      "capitulo": "21.10"
    },
    "rcr": {
      "capitulo": "21.10"
    },
    "pupilas com discoria d": {
      "capitulo": "21.10"
    },
    "2 t": {
      "capitulo": "21.10"
    },
    "28": {
      "capitulo": "21.10"
    },
    "cd": {
      "capitulo": "21.10"
    },
    "fc": {
      "capitulo": "21.10"
    },
    "134 x 98": {
      "capitulo": "21.10"
    },
    "intercorrencias": {
      "capitulo": "21.10"
    },
    "96": {
      "capitulo": "21.10"
    },
    "anemia": {
      "capitulo": "21.10"
    },
    "dra": {
      "capitulo": "24.10"
    },
    "filho": {
      "capitulo": "24.10"
    },
    "vm": {
      "capitulo": "21.10"
    },
    "confusa": {
      "capitulo": "21.10"
    },
    "abdomem": {
      "capitulo": "21.10"
    },
    "úlcera de repetição": {
      "capitulo": "15.0"
    },
    "exames": {
      "capitulo": "21.10"
    },
    "fotorreagente": {
      "capitulo": "21.10"
    },
    "taquipneica": {
      "capitulo": "21.10"
    },
    "k": {
      "capitulo": "21.10"
    },
    "hipocorada": {
      "capitulo": "21.10"
    },
    "fr": {
      "capitulo": "21.10"
    },
    "sato2": {
      "capitulo": "21.10"
    },
    "nega": {
      "capitulo": "24.10"
    },
    "g": {
      "capitulo": "21.10"
    },
    "mv audíveis": {
      "capitulo": "21.10"
    },
    "aumento de área cardíaca": {
      "capitulo": "21.10"
    },
    "isocoria": {
      "capitulo": "21.10"
    },
    "epigastralgia": {
      "capitulo": "21.10"
    },
    "cuidados": {
      "capitulo": "24.10"
    },
    "has": {
      "capitulo": "24.10"
    },
    "colecistectomia": {
      "capitulo": "21.10"
    },
    "eda": {
      "capitulo": "21.10"
    },
    "v": {
      "capitulo": "21.10"
    },
    "prematuro natimorto": {
      "capitulo": "21.10"
    },
    "internação": {
      "capitulo": "24.10"
    },
    "1": {
      "capitulo": "21.10"
    },
    "nuca": {
      "capitulo": "21.10"
    },
    "a": {
      "capitulo": "21.10"
    },
    "sem": {
      "capitulo": "21.10"
    },
    "afebril": {
      "capitulo": "21.10"
    },
    "mmii": {
      "capitulo": "21.10"
    },
    "crepitação em bases": {
      "capitulo": "21.10"
    },
    "amplitude diminuída": {
      "capitulo": "21.10"
    },
    "ecg": {
      "capitulo": "21.10"
    },
    "pa": {
      "capitulo": "21.10"
    },
    "tac cranio": {
      "capitulo": "21.10"
    },
    "mal estar": {
      "capitulo": "21.10"
    },
    "exames de lab": {
      "capitulo": "21.10"
    },
    "iii": {
      "capitulo": "21.10"
    },
    "capilarema": {
      "capitulo": "24.10"
    },
    "bre": {
      "capitulo": "21.10"
    },
    "ac": {
      "capitulo": "21.10"
    },
    "ndn": {
      "capitulo": "21.10"
    }
  }
}