{
  "prontuario_id": 618,
  "text": "# HAS, # Tabagista, # DM, # Claudicação Prévia Msis. Paciente interna proveniente do ambulatório devido à úlceras extensas em MIE secundário a vasculopatia periférica com inviabilidade do membro. Paciente foi submetida a amputação SC MIE sob anestesia raquidiana. Não apresentou intercorrências no trans-operatório. Apresentou boa evolução pós-op e tem alta em bom estado geral, com orientações e retorno para Fisiatria e Cir vascular. Paciente portadora de carcinoma medular de tireoide internou para realização de linfadenectomia cervical bilateral. Intra e pós-operatórios sem intercorrências. Com sequelas de cirurgia prévia apresentando paralisia de prega vocal esquerda e hipoparatireoidismo que mantiveram-se inalterados com o atual procedimento. Paciente com IRC, ICC, vem ao XXXX por inapetência, tosse e escarro. Rx de tórax sem consolidações. Prescrevo amoxicilina para tratamento de infecção respiratória alta. Hidrato EV. Paciente G3 P1 A1, Tipo Sang Mãe AB -, IG de 40 sem 4 dia(s), vem com queixa de contrações fortes e dolorosas. Interna com diagnóstico de trabalho de parto e apresentação pélvica. Cesárea por apresentação pélvica em 14/06/2007, as 11:10 hs. RN APGAR 9/10, MASC, 4170 G. Puerpério evolui sem intercorrências. Solicito VDRL não reag,  TOXO IGG não reag e IGM não reag, HBsAg negativo, anti-HIV não reag ,CI negativo e TSRN B +. Administrado Rhogan. Recebe alta em bom estado geral, sinais vitais estáveis e orientações gerais.",
  "entities": {
    "Abreviação": [
      "HAS",
      "DM",
      "MIE",
      "pós-op",
      "Fisiatria",
      "IRC",
      "ICC",
      "G3",
      "P1",
      "A1",
      "IG",
      "RN",
      "MASC",
      "Cir vascular",
      "Rx de tórax",
      "Hidrato EV",
      "Tipo Sang Mãe AB -",
      "40 sem 4 dia",
      "VDRL não reag",
      "TOXO IGG não reag",
      "IGM não reag",
      "HBsAg negativo",
      "anti-HIV não reag",
      "CI negativo",
      "TSRN B +"
    ],
    "Doença ou Síndrome": [
      "HAS",
      "Tabagista",
      "DM",
      "hipoparatireoidismo",
      "IRC",
      "ICC",
      "vasculopatia periférica",
      "infecção respiratória alta"
    ],
    "Paciente ou Grupo com Deficiência": [
      "Paciente"
    ],
    "Organização Relacionada à Saúde": [
      "ambulatório",
      "Fisiatria",
      "Cir vascular"
    ],
    "Localização ou Região Corporal": [
      "MIE"
    ],
    "Procedimento Terapêutico ou Preventivo": [
      "amputação",
      "procedimento",
      "anestesia raquidiana",
      "linfadenectomia cervical bilateral",
      "Hidrato EV",
      "Cesárea por apresentação pélvica"
    ],
    "Negação": [
      "Não",
      "sem"
    ],
    "Sinal ou Sintoma": [
      "intercorrências",
      "inapetência",
      "tosse",
      "escarro",
      "queixa",
      "dolorosas",
      "Claudicação Prévia",
      "TSRN B +"
    ],
    "Conceito Temporal": [
      "trans-operatório",
      "pós-op",
      "prévia",
      "Intra e pós-operatórios"
    ],
    "Atividade de Assistência à Saúde": [
      "alta",
      "orientações",
      "retorno"
    ],
    "Grupo Profissional ou Ocupacional": [
      "Fisiatria",
      "Cir vascular"
    ],
    "Função Patológica": [
      "sequelas"
    ],
    "Substância Corporal": [
      "escarro"
    ],
    "Substância Química Orgânica": [
      "amoxicilina"
    ],
    "Antibiótico": [
      "amoxicilina"
    ],
    "Achado": [
      "G3",
      "P1",
      "A1",
      "inviabilidade do membro",
      "boa evolução",
      "bom estado geral",
      "apresentação pélvica",
      "Cesárea por apresentação pélvica",
      "sinais vitais estáveis"
    ],
    "Atributo Clínico": [
      "IG"
    ],
    "Grupo Etário": [
      "RN"
    ],
    "Atributo de Organismo": [
      "MASC"
    ],
    "Substância Farmacológica": [
      "Rhogan"
    ],
    "Processo Neoplásico": [
      "carcinoma medular de tireoide"
    ],
    "Procedimento Diagnóstico": [
      "Rx de tórax"
    ],
    "Resultado Laboratorial ou de Teste": [
      "Tipo Sang Mãe AB -",
      "VDRL não reag",
      "TOXO IGG não reag",
      "IGM não reag",
      "HBsAg negativo",
      "anti-HIV não reag",
      "CI negativo",
      "TSRN B +"
    ],
    "Conceito Quantitativo": [
      "40 sem 4 dia",
      "4170 G"
    ]
  },
  "labels": {
    "apresentação pélvica": {
      "capitulo": "18.11"
    },
    "rhogan": {
      "capitulo": "24.11"
    },
    "claudicação prévia": {
      "capitulo": "11.11"
    },
    "ig": {
      "capitulo": "21.11"
    },
    "linfadenectomia cervical bilateral": {
      "capitulo": "15.11"
    },
    "infecção respiratória alta": {
      "capitulo": "12.11"
    },
    "hbsag negativo": {
      "capitulo": "21.11"
    },
    "ambulatório": {
      "capitulo": "24.11"
    },
    "paciente": {
      "capitulo": "24.11"
    },
    "amoxicilina": {
      "capitulo": "21.11"
    },
    "carcinoma medular de tireoide": {
      "capitulo": "02.11"
    },
    "cir vascular": {
      "capitulo": "11.11"
    },
    "escarro": {
      "capitulo": "12.11"
    },
    "sequelas": {
      "capitulo": "21.11"
    },
    "hidrato ev": {
      "capitulo": "24.11"
    },
    "amputação": {
      "capitulo": "22.11"
    },
    "g3": {
      "capitulo": "20.11"
    },
    "anestesia raquidiana": {
      "capitulo": "08.11"
    },
    "masc": {
      "capitulo": "21.11"
    },
    "anti-hiv não reag": {
      "capitulo": "21.11"
    },
    "vasculopatia periférica": {
      "capitulo": "11.11"
    },
    "tabagista": {
      "capitulo": "24.11"
    },
    "alta": {
      "capitulo": "24.11"
    },
    "inviabilidade do membro": {
      "capitulo": "22.11"
    },
    "retorno": {
      "capitulo": "24.11"
    },
    "irc": {
      "capitulo": "21.11"
    },
    "sem": {
      "capitulo": "21.11"
    },
    "p1": {
      "capitulo": "20.11"
    },
    "hipoparatireoidismo": {
      "capitulo": "05.11"
    },
    "4170 g": {
      "capitulo": "20.11"
    },
    "rx de tórax": {
      "capitulo": "21.11"
    },
    "procedimento": {
      "capitulo": "21.11"
    },
    "cesárea por apresentação pélvica": {
      "capitulo": "18.11"
    },
    "40 sem 4 dia": {
      "capitulo": "21.11"
    },
    "igm não reag": {
      "capitulo": "21.11"
    },
    "toxo igg não reag": {
      "capitulo": "21.11"
    },
    "sinais vitais estáveis": {
      "capitulo": "21.11"
    },
    "ci negativo": {
      "capitulo": "21.11"
    },
    "mie": {
      "capitulo": "12.11"
    },
    "boa evolução": {
      "capitulo": "21.11"
    },
    "tsrn b +": {
      "capitulo": "21.11"
    },
    "trans-operatório": {
      "capitulo": "21.11"
    },
    "rn": {
      "capitulo": "20.11"
    },
    "intra e pós-operatórios": {
      "capitulo": "21.11"
    },
    "has": {
      "capitulo": "21.11"
    },
    "dm": {
      "capitulo": "05.11"
    },
    "inapetência": {
      "capitulo": "21.11"
    },
    "queixa": {
      "capitulo": "21.11"
    },
    "a1": {
      "capitulo": "20.11"
    },
    "tosse": {
      "capitulo": "12.11"
    },
    "dolorosas": {
      "capitulo": "21.11"
    },
    "fisiatria": {
      "capitulo": "24.11"
    },
    "pós-op": {
      "capitulo": "21.11"
    },
    "bom estado geral": {
      "capitulo": "21.11"
    },
    "prévia": {
      "capitulo": "21.11"
    },
    "intercorrências": {
      "capitulo": "21.11"
    },
    "não": {
      "capitulo": "21.11"
    },
    "orientações": {
      "capitulo": "24.11"
    },
    "tipo sang mãe ab -": {
      "capitulo": "21.11"
    },
    "vdrl não reag": {
      "capitulo": "21.11"
    },
    "icc": {
      "capitulo": "21.11"
    }
  }
}