{
  "prontuario_id": 959,
  "text": "16:00: permanece em sala de poli, intubada em VM sob modo PCV FR: 15, PEEP: 6 e PL: 22, hipocorada,  enegrecida, sedada com plano de Dormo 20 ml/h, Fenta 10 ml/h. Com cabeceira elevada 45º. Permanece monitorizada com oximetria de pulso, controle de PA não invasiva e monitorização cardíaca SSVV no momento: FC: 62  bpm, PA: 128x74 mmHg e mantendo Sat O2 > 97%. Com Acesso venoso central em subclávia D. Com presença de equimose em MMSS. Com SNG recebendo dieta em BI 30ml/h. Com SVD com débito de 75 ml de aspecto alaranjado e com presença de grumos. Evacuação ausente. Aguarda vaga de UTI.  Florence Nightingale Coren xxxx  EXAME GERAL E INVESTIGAÇÃO DE PESSOAS SEM QUEIXAS OU DIAGNOSTICO RELATADO",
  "entities": {
    "Procedimento Terapêutico ou Preventivo": [
      "intubada",
      "VM",
      "PEEP",
      "sedada",
      "SNG",
      "SVD",
      "modo PCV",
      "cabeceira elevada 45º",
      "Acesso venoso central",
      "dieta em BI"
    ],
    "Achado": [
      "intubada",
      "sedada",
      "Evacuação",
      "com débito",
      "aspecto alaranjado"
    ],
    "Abreviação": [
      "VM",
      "FR",
      "PEEP",
      "PL",
      "Dormo",
      "Fenta",
      "SSVV",
      "FC",
      "PA",
      "MMSS",
      "SNG",
      "30ml/h",
      "SVD",
      "UTI",
      "sala de poli",
      "modo PCV",
      "controle de PA não invasiva",
      "Sat O2",
      "subclávia D",
      "dieta em BI"
    ],
    "Atributo Clínico": [
      "FR",
      "SSVV",
      "FC",
      "PA",
      "Sat O2"
    ],
    "Conceito Quantitativo": [
      "15",
      "6",
      "22",
      "30ml/h",
      "20 ml/h",
      "10 ml/h",
      "62 bpm",
      "128x74 mmHg",
      "&gt; 97%",
      "75 ml"
    ],
    "Sinal ou Sintoma": [
      "hipocorada",
      "enegrecida",
      "equimose",
      "presença de grumos"
    ],
    "Substância Farmacológica": [
      "Dormo",
      "Fenta"
    ],
    "Substância Química Orgânica": [
      "Dormo",
      "Fenta"
    ],
    "Procedimento Diagnóstico": [
      "monitorizada",
      "oximetria de pulso",
      "controle de PA não invasiva",
      "monitorização cardíaca"
    ],
    "Localização ou Região Corporal": [
      "MMSS"
    ],
    "Dispositivo Médico": [
      "SNG",
      "SVD",
      "Acesso venoso central"
    ],
    "Função Fisiológica": [
      "Evacuação"
    ],
    "Negação": [
      "ausente"
    ],
    "Organização Relacionada à Saúde": [
      "UTI",
      "sala de poli"
    ],
    "Parte do Corpo, Órgão ou Componente Orgânico": [
      "subclávia D"
    ]
  },
  "labels": {
    "enegrecida": {
      "capitulo": "14"
    },
    "mmss": {
      "capitulo": "14"
    },
    "hipocorada": {
      "capitulo": "14"
    },
    "svd": {
      "capitulo": "13"
    },
    "aspecto alaranjado": {
      "capitulo": "13"
    },
    "equimose": {
      "capitulo": "14"
    },
    "pl": {
      "capitulo": "11"
    },
    "pa": {
      "capitulo": "11"
    },
    "intubada": {
      "capitulo": "21"
    },
    "peep": {
      "capitulo": "11"
    },
    "evacuação": {
      "capitulo": "13"
    },
    "vm": {
      "capitulo": "21"
    },
    "oximetria de pulso": {
      "capitulo": "11"
    },
    "fc": {
      "capitulo": "21"
    },
    "sng": {
      "capitulo": "13"
    },
    "128x74 mmhg": {
      "capitulo": "11"
    },
    "sat o2": {
      "capitulo": "11"
    },
    "controle de pa não invasiva": {
      "capitulo": "11"
    },
    "presença de grumos": {
      "capitulo": "13"
    },
    "uti": {
      "capitulo": "25"
    },
    "com débito": {
      "capitulo": "22"
    },
    "sala de poli": {
      "capitulo": "22"
    },
    "monitorização cardíaca": {
      "capitulo": "11"
    },
    "monitorizada": {
      "capitulo": "21"
    },
    "cabeceira elevada 45º": {
      "capitulo": "21"
    },
    "modo pcv": {
      "capitulo": "11"
    },
    "ssvv": {
      "capitulo": "11"
    },
    "ausente": {
      "capitulo": "21"
    }
  }
}