{
  "prontuario_id": 963,
  "text": "22h - Pós procedimento de embolização, pré cirúrgico de neurocirurgia, consciente, orientada, comunicativa, em repouso no leito, afebril, normoceálica, normocorada, pupilas isocórica, fotorreagentes com abertura ocular espontânea, mucosas íntegras e úmidas, em ar ambiente, tórax plano com simetria de expansibilidade, ausculta pulmonar com murmúrios vesiculares, ausculta cardíaca normofonética com bulhas regulares e rítmicas, abdômen globoso, flácido, indolor e flácido, RHA +, mantém AVP em MSE com soroterapia em curso, diurese presente em SVD em grande quantidade, permanece com CTVO compressivo em RID para retirar 18/01 às 14:30h. Enfermeiro Florence Nightingale Coren xxxx . NEOPLASIA DE COMPORTAMENTO INCERTO OU DESCONHECIDO DO ENCEFALO SUPRATENTORIAL",
  "entities": {
    "Grupo Profissional ou Ocupacional": [
      "neurocirurgia",
      "Enfermeiro"
    ],
    "Achado": [
      "consciente",
      "orientada",
      "comunicativa",
      "afebril",
      "normoceálica",
      "normocorada",
      "isocórica",
      "fotorreagentes",
      "íntegras",
      "úmidas",
      "plano",
      "normofonética",
      "rítmicas",
      "flácido",
      "repouso no leito",
      "abertura ocular espontânea",
      "simetria de expansibilidade",
      "murmúrios vesiculares",
      "bulhas regulares",
      "RHA +",
      "diurese presente",
      "grande quantidade"
    ],
    "Negação": [
      "afebril",
      "indolor"
    ],
    "Parte do Corpo, Órgão ou Componente Orgânico": [
      "pupilas",
      "mucosas",
      "ENCEFALO SUPRATENTORIAL"
    ],
    "Localização ou Região Corporal": [
      "tórax",
      "abdômen",
      "MSE"
    ],
    "Sinal ou Sintoma": [
      "globoso"
    ],
    "Abreviação": [
      "MSE",
      "SVD",
      "RID",
      "RHA +",
      "mantém AVP",
      "CTVO compressivo"
    ],
    "Dispositivo Médico": [
      "SVD",
      "mantém AVP",
      "CTVO compressivo"
    ],
    "Procedimento Terapêutico ou Preventivo": [
      "SVD",
      "Pós procedimento",
      "repouso no leito",
      "mantém AVP",
      "soroterapia em curso",
      "CTVO compressivo"
    ],
    "Processo Neoplásico": [
      "NEOPLASIA"
    ],
    "Conceito Temporal": [
      "Pós procedimento",
      "pré cirúrgico"
    ],
    "Procedimento Diagnóstico": [
      "ausculta pulmonar",
      "ausculta cardíaca"
    ],
    "Função Fisiológica": [
      "diurese presente"
    ],
    "Conceito Qualitativo": [
      "grande quantidade"
    ]
  },
  "labels": {
    "soroterapia em curso": {
      "capitulo": "05"
    },
    "mucosas": {
      "capitulo": "14"
    },
    "rid": {
      "capitulo": "08"
    },
    "pós procedimento": {
      "capitulo": "22"
    },
    "pupilas": {
      "capitulo": "08"
    },
    "bulhas regulares": {
      "capitulo": "08"
    },
    "svd": {
      "capitulo": "13"
    },
    "úmidas": {
      "capitulo": "14"
    },
    "pré cirúrgico": {
      "capitulo": "22"
    },
    "normofonética": {
      "capitulo": "08"
    },
    "comunicativa": {
      "capitulo": "06"
    },
    "rha +": {
      "capitulo": "08"
    },
    "mse": {
      "capitulo": "06"
    },
    "ctvo compressivo": {
      "capitulo": "08"
    },
    "fotorreagentes": {
      "capitulo": "08"
    },
    "tórax": {
      "capitulo": "12"
    },
    "grande quantidade": {
      "capitulo": "22"
    },
    "ausculta cardíaca": {
      "capitulo": "08"
    },
    "repouso no leito": {
      "capitulo": "22"
    },
    "normoceálica": {
      "capitulo": "08"
    },
    "isocórica": {
      "capitulo": "08"
    },
    "plano": {
      "capitulo": "22"
    },
    "neoplasia": {
      "capitulo": "02"
    },
    "flácido": {
      "capitulo": "15"
    },
    "afebril": {
      "capitulo": "08"
    },
    "mantém avp": {
      "capitulo": "08"
    },
    "murmúrios vesiculares": {
      "capitulo": "12"
    },
    "abdômen": {
      "capitulo": "13"
    },
    "normocorada": {
      "capitulo": "08"
    },
    "enfermeiro": {
      "capitulo": "24"
    },
    "ausculta pulmonar": {
      "capitulo": "12"
    },
    "globoso": {
      "capitulo": "13"
    },
    "consciente": {
      "capitulo": "06"
    },
    "rítmicas": {
      "capitulo": "08"
    },
    "abertura ocular espontânea": {
      "capitulo": "08"
    },
    "neurocirurgia": {
      "capitulo": "08"
    },
    "encefalo supratentorial": {
      "capitulo": "08"
    },
    "diurese presente": {
      "capitulo": "13"
    },
    "indolor": {
      "capitulo": "15"
    }
  }
}