{
  "prontuario_id": 652,
  "text": "HAS  DM2 # Cardiopatia Isquemica - CRM XXXX ( SAF para DA e CX ) -  ACTP CD EM 1998 # Último CAT (2001) : DAE / Cx ocluídas prox ; PS para Dg pérvia e com fluxo retrógrado para DAE ; PS para Cx pérvia ; CD com estenoses proximal de 50 e 40% # IRC - hipercalemia # AITs repetição # Estenose aórtica -  grad max 38 # Hipotireoidismo  Paciente é encaminhado de Sto Antonio da Patrulha por angina instável , sem alteração de ECG ou enzimas cardíacas . Novo cateterismo mostrou progressão da lesão em coronária direita estando com lesão crítica em segmento proximal . Realizada colocação de stent com estabelecimento de bom fluxo . Tem alta em bom estado geral , assintomático . Orientações gerais . Retorno à emergência se necessário . Medicações prescritas : Metoprolol 100mg 2x/dia ; AAS 100 mg 2cp 1x/dia ; Ticlopidina 250mg 12/12 Hs ; Isossorbida 10mg 3X/dia ; Sinvastatina 40mg à noite ; Insulina NPH 12 UI AC e 12 AJ ; Euthyrox 50mg 1c 1x/dia.",
  "entities": {
    "Doença ou Síndrome": [
      "HAS",
      "DM2",
      "IRC",
      "Hipotireoidismo",
      "Cardiopatia Isquemica",
      "AITs repetição",
      "Estenose aórtica",
      "angina instável"
    ],
    "Abreviação": [
      "HAS",
      "DM2",
      "SAF",
      "DA",
      "CX",
      "ACTP",
      "CD",
      "CAT",
      "IRC",
      "AAS",
      "AC",
      "AJ",
      "DAE / Cx ocluídas prox",
      "PS para Dg pérvia e com fluxo retrógrado para DAE",
      "PS para Cx pérvia",
      "CD com estenoses proximal de 50 e 40%",
      "AITs repetição",
      "grad max 38",
      "alteração de ECG"
    ],
    "Parte do Corpo, Órgão ou Componente Orgânico": [
      "DA",
      "CX",
      "CD"
    ],
    "Procedimento Terapêutico ou Preventivo": [
      "ACTP",
      "CAT",
      "cateterismo",
      "colocação de stent"
    ],
    "Procedimento Diagnóstico": [
      "CAT",
      "cateterismo"
    ],
    "Sinal ou Sintoma": [
      "hipercalemia"
    ],
    "Paciente ou Grupo com Deficiência": [
      "Paciente"
    ],
    "Negação": [
      "sem",
      "assintomático"
    ],
    "Atividade de Assistência à Saúde": [
      "alta",
      "Retorno",
      "Orientações gerais"
    ],
    "Achado": [
      "assintomático",
      "estabelecimento de bom fluxo",
      "bom estado geral"
    ],
    "Organização Relacionada à Saúde": [
      "emergência"
    ],
    "Substância Farmacológica": [
      "Medicações",
      "Metoprolol",
      "AAS",
      "Ticlopidina",
      "Isossorbida",
      "Sinvastatina",
      "Euthyrox",
      "Insulina NPH"
    ],
    "Substância Química Orgânica": [
      "Metoprolol",
      "AAS",
      "Ticlopidina",
      "Isossorbida",
      "Sinvastatina",
      "Euthyrox"
    ],
    "Conceito Quantitativo": [
      "100mg",
      "250mg",
      "10mg",
      "40mg",
      "50mg",
      "100 mg",
      "12 UI"
    ],
    "Resultado Laboratorial ou de Teste": [
      "DAE / Cx ocluídas prox",
      "PS para Dg pérvia e com fluxo retrógrado para DAE",
      "PS para Cx pérvia",
      "CD com estenoses proximal de 50 e 40%",
      "enzimas cardíacas",
      "progressão da lesão em coronária direita",
      "lesão crítica em segmento proximal"
    ],
    "Procedimento Laboratorial": [
      "enzimas cardíacas"
    ],
    "Aminoácido, Peptídeo ou Proteína": [
      "Insulina NPH"
    ],
    "Hormônio": [
      "Insulina NPH"
    ]
  },
  "labels": {
    "hipercalemia": {
      "capitulo": "05.1.1"
    },
    "progressão da lesão em coronária direita": {
      "capitulo": "11.51"
    },
    "alteração de ecg": {
      "capitulo": "08.1"
    },
    "hipotireoidismo": {
      "capitulo": "05.1.1"
    },
    "cateterismo": {
      "capitulo": "22.1.1"
    },
    "paciente": {
      "capitulo": "24.1.1"
    },
    "da": {
      "capitulo": "11.51"
    },
    "isossorbida": {
      "capitulo": "11.51"
    },
    "dm2": {
      "capitulo": "05.1.1"
    },
    "saf": {
      "capitulo": "24.1.1"
    },
    "ps para cx pérvia": {
      "capitulo": "11.51"
    },
    "ps para dg pérvia e com fluxo retrógrado para dae": {
      "capitulo": "11.51"
    },
    "emergência": {
      "capitulo": "23.1.1"
    },
    "medicações": {
      "capitulo": "24.1.1"
    },
    "insulina nph": {
      "capitulo": "05.1.1"
    },
    "euthyrox": {
      "capitulo": "05.1.1"
    },
    "50mg": {
      "capitulo": "20.1.1"
    },
    "aas": {
      "capitulo": "11.51"
    },
    "cardiopatia isquemica": {
      "capitulo": "11.51"
    },
    "colocação de stent": {
      "capitulo": "22.1.1"
    },
    "assintomático": {
      "capitulo": "21.1.1"
    },
    "alta": {
      "capitulo": "24.1.1"
    },
    "retorno": {
      "capitulo": "24.1.1"
    },
    "irc": {
      "capitulo": "05.1.1"
    },
    "12 ui": {
      "capitulo": "20.1.1"
    },
    "enzimas cardíacas": {
      "capitulo": "08.1"
    },
    "sem": {
      "capitulo": "21.1.1"
    },
    "grad max 38": {
      "capitulo": "20.1.1"
    },
    "10mg": {
      "capitulo": "20.1.1"
    },
    "angina instável": {
      "capitulo": "11.51"
    },
    "ac": {
      "capitulo": "24.1.1"
    },
    "ticlopidina": {
      "capitulo": "11.51"
    },
    "100 mg": {
      "capitulo": "20.1"
    },
    "orientações gerais": {
      "capitulo": "24.1.1"
    },
    "metoprolol": {
      "capitulo": "11.51"
    },
    "dae / cx ocluídas prox": {
      "capitulo": "11.51"
    },
    "bom estado geral": {
      "capitulo": "21.1.1"
    },
    "250mg": {
      "capitulo": "20.1.1"
    },
    "aj": {
      "capitulo": "05.1.1"
    },
    "has": {
      "capitulo": "24.1.1"
    },
    "actp": {
      "capitulo": "24.1.1"
    },
    "cat": {
      "capitulo": "24.1.1"
    },
    "sinvastatina": {
      "capitulo": "11.51"
    },
    "40mg": {
      "capitulo": "20.1.1"
    },
    "aits repetição": {
      "capitulo": "21.1.1"
    },
    "cd": {
      "capitulo": "11.51"
    },
    "cx": {
      "capitulo": "11.51"
    },
    "cd com estenoses proximal de 50 e 40%": {
      "capitulo": "11.51"
    }
  }
}