{
  "prontuario_id": 454,
  "text": "avaliação nefrologia geral. HAS - MAU CONTROLE, DM - MAU CONTROLE, AVC PRÉVIO - RISCO CV ALTO! LUCAS, 63 ANOS. S # ENCAMINHAMENTO POR DIABETES. # PORTADORA DE DM COM DIAGNÓSTICO HÁ CERCA DE 15 ANOS, COM RETINOPATIA DIABÉTICA - USO DE INSULINA R 8 / 0 / 8, NPH 20 / 0 / 20, MTF 850 X 2. # HAS - TAMBÉM DE LONGA DATA - USO DE: ENALAPRIL 40MG /DIA, PROPRANOLOL 40MG 12/12 H. # DSLP - SVT 40. #  AVC HA CERCA DE 15 ANOS TAMBÉM. # HIPERTIREODISMO - USO DE TAPAZOL, TIREOIDECTOMIA PARCIAL POR NODULO. # G 2 C 2  # CHV: NEGA TABAGISMO, NEGA ETILISMO. # HMF: IRMÃO COM DOENÇA RENAL, DOIS SOBRINHOS COM NEFROPATIA TRANSPLANTADOS, TODOS OS IRMÃOS COM DM, MÃE  - OBITO POR CARDIOPATIA AOS 84 ANOS; MAIO/2014: RELAÇÃO ALBUMINA/CREATININA 451,34 MG/G; CR 0,6; PU - BACTERIURIA, PROTEINA, - LDL 133! HBA1C 8,7;  O #  BEG, CORADA, HIDRATADA, PA 160/100,  P 65, MV POSITIVO, SIMETRICO, BCRNF, ABDOMEN GLOBOSO, FLACIDO, SEM MASSAS, RHA POSITIVOS, MEMBROS - SEM EDEMA.",
  "entities": {
    "Atividade de Assistência à Saúde": [
      "avaliação",
      "ENCAMINHAMENTO"
    ],
    "Abreviação": [
      "HAS",
      "DM",
      "AVC",
      "S",
      "NPH",
      "MTF",
      "DSLP",
      "SVT",
      "G",
      "C",
      "CHV",
      "HMF",
      "PU",
      "O",
      "BEG",
      "PA",
      "P",
      "BCRNF",
      "RISCO CV ALTO",
      "INSULINA R",
      "CR 0 , 6",
      "HBA1C 8 , 7",
      "MV POSITIVO",
      "RHA POSITIVOS"
    ],
    "Doença ou Síndrome": [
      "HAS",
      "DM",
      "AVC",
      "DIABETES",
      "DSLP",
      "HIPERTIREODISMO",
      "TABAGISMO",
      "ETILISMO",
      "NEFROPATIA",
      "RETINOPATIA DIABÉTICA",
      "DOENÇA RENAL"
    ],
    "Conceito Temporal": [
      "PRÉVIO",
      "12/12 H"
    ],
    "Achado": [
      "S",
      "CHV",
      "HMF",
      "BEG",
      "CORADA",
      "HIDRATADA",
      "SIMETRICO",
      "BCRNF",
      "FLACIDO",
      "MAU CONTROLE",
      "MV POSITIVO",
      "RHA POSITIVOS"
    ],
    "Produto Intelectual": [
      "DIAGNÓSTICO"
    ],
    "Substância Farmacológica": [
      "NPH",
      "MTF",
      "ENALAPRIL",
      "PROPRANOLOL",
      "SVT",
      "TAPAZOL",
      "INSULINA R"
    ],
    "Substância Química Orgânica": [
      "MTF",
      "PROPRANOLOL",
      "SVT",
      "TAPAZOL"
    ],
    "Aminoácido, Peptídeo ou Proteína": [
      "ENALAPRIL"
    ],
    "Conceito Quantitativo": [
      "40",
      "2",
      "DOIS",
      "TODOS",
      "160/100",
      "65",
      "8 / 0 / 8",
      "20 / 0 / 20",
      "X 2",
      "40MG /DIA"
    ],
    "Processo Neoplásico": [
      "NODULO"
    ],
    "Sinal ou Sintoma": [
      "NODULO",
      "GLOBOSO",
      "MASSAS",
      "EDEMA"
    ],
    "Atributo Clínico": [
      "G",
      "C",
      "PA",
      "P"
    ],
    "Negação": [
      "NEGA",
      "SEM"
    ],
    "Grupo Familiar": [
      "IRMÃO",
      "SOBRINHOS",
      "IRMÃOS",
      "MÃE"
    ],
    "Procedimento Terapêutico ou Preventivo": [
      "TRANSPLANTADOS",
      "TIREOIDECTOMIA PARCIAL"
    ],
    "Resultado Laboratorial ou de Teste": [
      "BACTERIURIA",
      "PROTEINA",
      "ALBUMINA/CREATININA 451 , 34 MG/G",
      "CR 0 , 6",
      "LDL 133",
      "HBA1C 8 , 7"
    ],
    "Localização ou Região Corporal": [
      "ABDOMEN"
    ],
    "Função Patológica": [
      "EDEMA"
    ]
  },
  "labels": {
    "bacteriuria": {
      "capitulo": "01"
    },
    "diabetes": {
      "capitulo": "05"
    },
    "doença renal": {
      "capitulo": "05"
    },
    "encaminhamento": {
      "capitulo": "05"
    },
    "enalapril": {
      "capitulo": "05"
    },
    "etilismo": {
      "capitulo": "05"
    },
    "flacido": {
      "capitulo": "05"
    },
    "globoso": {
      "capitulo": "05"
    },
    "hipertireodismo": {
      "capitulo": "05"
    },
    "insulina r": {
      "capitulo": "05"
    },
    "irmãos": {
      "capitulo": "05"
    },
    "ldl 133": {
      "capitulo": "05"
    },
    "massas": {
      "capitulo": "05"
    },
    "mv positivo": {
      "capitulo": "05"
    },
    "nefropatia": {
      "capitulo": "05"
    },
    "nega": {
      "capitulo": "05"
    },
    "nodulo": {
      "capitulo": "05"
    },
    "propranolol": {
      "capitulo": "05"
    },
    "retinopatia diabética": {
      "capitulo": "05"
    },
    "risco cv alto": {
      "capitulo": "05"
    },
    "rha positivos": {
      "capitulo": "05"
    },
    "sobrinhos": {
      "capitulo": "05"
    },
    "tabagismo": {
      "capitulo": "05"
    },
    "tireoidectomia parcial": {
      "capitulo": "05"
    },
    "transplantados": {
      "capitulo": "05"
    }
  }
}