{
  "prontuario_id": 533,
  "text": "Acompanhamento do DM2.  S : Paciente sem queixas referente ao DM. Acompanhamento oftalmológico. Em uso de metformina (3 x 850mg) e glicazida (4 x 30mg), Losartana 50mg 2 x ao dia. Caminhada 50 min 3 vezes por semana.  O : P :69,7 kg, A : 1,54m. IMC : 29,38. CA: ,FC : 68 bpm, FR : 19 mrpm, PA :130/80,  BEG, LOTE, corada, hidratada, acianótica, anicterica, afebril. PC : tórax atípico sem cicatrizes, abaulamentos ou circulação colateral, RCR 2 tempos (B1 e B2), BRNFSS, CPP : livre, expansivo bilateralmente, som claro pulmonar, murmúrios vesiculares presentes, sem ruídos adventíceos. Abdome: globoso, com estrias esbranquiçadas em baixo ventre e cicatriz de colecistectomia e de cesárea. RHA presentes, sem sopros, som timpânico a percussão, sem dor a palpação, presença de hérnia umbilical.  Espaço de Traube livre. Fígado de 9 cm pela hepatimetria. MMII : Sensibilidade presente, sem edema, micose entre terceiro e quarto dedo do pé esquerdo.  A : Exames (03/10/14) :  Glicose : 150, Hb glicada : 8,63%; TG : 255; HDL : 36; LDL : 71; CT : 158; K : 4,8; microalbuminúria de 24 horas: 18; Cl creat calculado  = 98 ml /min;  DM2 não controlado.  P : Adicionar terceiro antidiabético oral.   Encaminhar ao nutricionista.",
  "entities": {
    "Atividade de Assistência à Saúde": [
      "Acompanhamento",
      "Encaminhar",
      "Acompanhamento oftalmológico"
    ],
    "Achado": [
      "S",
      "BEG",
      "LOTE",
      "corada",
      "hidratada",
      "BRNFSS",
      "livre",
      "Caminhada 50 min 3 vezes por semana",
      "expansivo bilateralmente",
      "som claro pulmonar",
      "murmúrios vesiculares presentes",
      "RHA presentes",
      "som timpânico",
      "Espaço de Traube livre",
      "Sensibilidade presente"
    ],
    "Abreviação": [
      "S",
      "DM",
      "O",
      "P",
      "A",
      "IMC",
      "CA",
      "FC",
      "FR",
      "PA",
      "BEG",
      "LOTE",
      "BRNFSS",
      "CPP",
      "MMII",
      "RHA presentes"
    ],
    "Paciente ou Grupo com Deficiência": [
      "Paciente"
    ],
    "Negação": [
      "sem",
      "acianótica",
      "anicterica",
      "afebril",
      "não"
    ],
    "Sinal ou Sintoma": [
      "queixas",
      "acianótica",
      "anicterica",
      "afebril",
      "cicatrizes",
      "abaulamentos",
      "globoso",
      "cicatriz",
      "sopros",
      "edema",
      "circulação colateral",
      "ruídos adventíceos",
      "estrias esbranquiçadas"
    ],
    "Doença ou Síndrome": [
      "DM",
      "micose",
      "DM2"
    ],
    "Substância Química Orgânica": [
      "metformina",
      "glicazida",
      "Losartana"
    ],
    "Substância Farmacológica": [
      "metformina",
      "glicazida",
      "Losartana",
      "antidiabético oral"
    ],
    "Atributo Clínico": [
      "P",
      "A",
      "IMC",
      "CA",
      "FC",
      "FR",
      "PA"
    ],
    "Função de Organismo": [
      "PA"
    ],
    "Conceito Quantitativo": [
      "130/80",
      "69 , 7 kg",
      "1 , 54m",
      "29 , 38",
      "68 bpm",
      "19 mrpm"
    ],
    "Parte do Corpo, Órgão ou Componente Orgânico": [
      "CPP",
      "Abdome",
      "terceiro e quarto dedo do pé esquerdo"
    ],
    "Procedimento Terapêutico ou Preventivo": [
      "colecistectomia",
      "cesárea"
    ],
    "Procedimento Diagnóstico": [
      "percussão",
      "palpação",
      "hepatimetria",
      "A"
    ],
    "Localização ou Região Corporal": [
      "MMII"
    ],
    "Função Patológica": [
      "edema"
    ],
    "Procedimento Laboratorial": [
      "Exames"
    ],
    "Produto Intelectual": [
      "P"
    ],
    "Organização Relacionada à Saúde": [
      "nutricionista"
    ],
    "Grupo Profissional ou Ocupacional": [
      "nutricionista"
    ],
    "Resultado Laboratorial ou de Teste": [
      "Fígado de 9",
      "Glicose : 150",
      "Hb glicada : 8 , 63%",
      "TG : 255",
      "HDL : 36",
      "LDL : 71",
      "CT : 158",
      "K : 4 , 8",
      "microalbuminúria de 24 horas : 18",
      "Cl creat calculado = 98 ml /min"
    ]
  },
  "labels": {
    "dm": {
      "capitulo": "02"
    },
    "rha presentes": {
      "capitulo": "14"
    },
    "sopros": {
      "capitulo": "23"
    },
    "hdl": {
      "capitulo": "11"
    },
    "mmii": {
      "capitulo": "13"
    },
    "palpação": {
      "capitulo": "07"
    },
    "cicatriz": {
      "capitulo": "09"
    },
    "som timpânico": {
      "capitulo": "08"
    },
    "ca": {
      "capitulo": "15"
    },
    "acianótica": {
      "capitulo": "16"
    },
    "colecistectomia": {
      "capitulo": "52"
    },
    "circulação colateral": {
      "capitulo": "45"
    },
    "microalbuminúria de 24 horas": {
      "capitulo": "18"
    },
    "cl creat calculado": {
      "capitulo": "23"
    },
    "hidratada": {
      "capitulo": "09"
    },
    "hb glicada": {
      "capitulo": "21"
    },
    "cpp": {
      "capitulo": "07"
    },
    "percussão": {
      "capitulo": "08"
    },
    "som claro pulmonar": {
      "capitulo": "23"
    },
    "tg": {
      "capitulo": "11"
    },
    "antidiabético oral": {
      "capitulo": "05"
    },
    "fígado de 9": {
      "capitulo": "52"
    },
    "abaulamentos": {
      "capitulo": "16"
    },
    "ruídos adventíceos": {
      "capitulo": "25"
    },
    "glicose": {
      "capitulo": "21"
    },
    "ldl": {
      "capitulo": "11"
    },
    "murmúrios vesiculares presentes": {
      "capitulo": "23"
    },
    "losartana": {
      "capitulo": "07"
    },
    "micose": {
      "capitulo": "09"
    },
    "cesárea": {
      "capitulo": "52"
    },
    "k": {
      "capitulo": "17"
    }
  }
}