{
  "prontuario_id": 680,
  "text": "Paciente em tratamento para ICC diastólica há cerca de 5 a com melhora importante dos sintomas após início do tratamento. Hoje relata dispneia aos moderados esforços, nega disnpneía paroxística notrna, dorme com apenas 1 travesseiro. Nega precordialgia aos moderados esforços. Nega episódios anginosos. Nega outras queixas.  Rsultado de exames:  1- Microalbuminúria 12/04: 10.64 / G de creatinina 2- US abdome total : rins com alterações tróficas 3- ECG 19/03/14: isquemia subepicárdica anterior, alteração de repolarização ventricular infero-lateral 4- Laboratoriais 12/04/14: K 5.1,  clearence creatinina 57  Ao EF: PA 170x100mmHg (relata PA normal quando em ambiente não hospitalar), FC 63bpm AR: mv sem RA ACV : rcr em 2T sem sopros, com hipofonese de bulhas AD: abdome globos, normotenso, indolor, ausência de massas ou visceromegalias MMII sem edema  HD :  - ICC diastólica classe III - HAS - DMII - Dislipidemia  CD:  - mantenho medicação - retorno em 6 m com exames laboratoriais + ECG. ICC classe III HAS, em uso de atenolol 100mg / dia, AAS, 100mg / dia, furosemida 40mg 1cp 12/12h,anlodipino 5mg 1/2 cp à noite, losartana 50mg 12/12h DMII, metformina 850mg 12/12h Dislipidemia, faz uso de sinvastatina 20mg 02 cp à noite",
  "entities": {
    "Paciente ou Grupo com Deficiência": [
      "Paciente"
    ],
    "Procedimento Terapêutico ou Preventivo": [
      "tratamento"
    ],
    "Sinal ou Sintoma": [
      "sintomas",
      "queixas",
      "RA",
      "sopros",
      "globos",
      "massas",
      "visceromegalias",
      "edema",
      "dispneia aos moderados esforços",
      "precordialgia aos moderados esforços",
      "episódios anginosos",
      "hipofonese de bulhas"
    ],
    "Negação": [
      "nega",
      "Nega",
      "sem",
      "indolor",
      "ausência"
    ],
    "Objeto Manufaturado": [
      "travesseiro"
    ],
    "Conceito Quantitativo": [
      "10",
      "170x100mmHg",
      "63bpm",
      "64 / G",
      "100mg / dia",
      "40mg 1cp 12/12h",
      "5mg 1/2 cp",
      "50mg 12/12h",
      "850mg 12/12h",
      "20mg 02 cp"
    ],
    "Abreviação": [
      "ECG",
      "PA",
      "FC",
      "AR",
      "mv",
      "RA",
      "ACV",
      "AD",
      "MMII",
      "HD",
      "HAS",
      "DMII",
      "CD",
      "AAS",
      "ICC diastólica",
      "US abdome total",
      "rcr em 2T",
      "ICC diastólica classe III",
      "ICC classe III"
    ],
    "Procedimento Diagnóstico": [
      "ECG",
      "EF",
      "HD",
      "Rsultado de exames",
      "US abdome total",
      "exames laboratoriais"
    ],
    "Procedimento Laboratorial": [
      "Laboratoriais",
      "exames laboratoriais"
    ],
    "Atributo Clínico": [
      "PA",
      "FC",
      "AR",
      "ACV",
      "AD"
    ],
    "Organização Relacionada à Saúde": [
      "hospitalar"
    ],
    "Sistema Corporal": [
      "AR",
      "ACV",
      "AD"
    ],
    "Achado": [
      "mv",
      "normotenso",
      "indolor",
      "melhora importante",
      "rcr em 2T"
    ],
    "Localização ou Região Corporal": [
      "abdome",
      "MMII"
    ],
    "Doença ou Síndrome": [
      "HAS",
      "DMII",
      "Dislipidemia",
      "ICC diastólica",
      "disnpneía paroxística notrna",
      "ICC diastólica classe III",
      "ICC classe III"
    ],
    "Produto Intelectual": [
      "CD"
    ],
    "Atividade de Assistência à Saúde": [
      "mantenho",
      "retorno"
    ],
    "Substância Farmacológica": [
      "medicação",
      "atenolol",
      "AAS",
      "furosemida",
      "anlodipino",
      "losartana",
      "metformina",
      "sinvastatina"
    ],
    "Conceito Qualitativo": [
      "noite"
    ],
    "Conceito Temporal": [
      "após início"
    ],
    "Resultado Laboratorial ou de Teste": [
      "Rsultado de exames",
      "rins com alterações tróficas",
      "isquemia subepicárdica anterior",
      "alteração de repolarização ventricular infero-lateral",
      "K 5",
      "clearence creatinina 57"
    ]
  },
  "labels": {
    "mmii": {
      "capitulo": "04"
    },
    "anlodipino": {
      "capitulo": "11"
    },
    "64 / g": {
      "capitulo": "05"
    },
    "hipofonese de bulhas": {
      "capitulo": "08"
    },
    "queixas": {
      "capitulo": "21"
    },
    "metformina": {
      "capitulo": "05"
    },
    "abdome": {
      "capitulo": "13"
    },
    "paciente": {
      "capitulo": "24"
    },
    "edema": {
      "capitulo": "15"
    },
    "disnpneía paroxística notrna": {
      "capitulo": "12"
    },
    "precordialgia aos moderados esforços": {
      "capitulo": "11"
    },
    "rins com alterações tróficas": {
      "capitulo": "16"
    },
    "us abdome total": {
      "capitulo": "13"
    },
    "isquemia subepicárdica anterior": {
      "capitulo": "11"
    },
    "clearence creatinina 57": {
      "capitulo": "05"
    },
    "850mg 12/12h": {
      "capitulo": "05"
    },
    "rsultado de exames": {
      "capitulo": "21"
    },
    "aas": {
      "capitulo": "11"
    },
    "20mg 02 cp": {
      "capitulo": "05"
    },
    "atenolol": {
      "capitulo": "11"
    },
    "alteração de repolarização ventricular infero-lateral": {
      "capitulo": "08"
    },
    "após início": {
      "capitulo": "21"
    },
    "melhora importante": {
      "capitulo": "21"
    },
    "tratamento": {
      "capitulo": "21"
    },
    "170x100mmhg": {
      "capitulo": "11"
    },
    "ecg": {
      "capitulo": "08"
    },
    "pa": {
      "capitulo": "11"
    },
    "retorno": {
      "capitulo": "21"
    },
    "rcr em 2t": {
      "capitulo": "16"
    },
    "mantenho": {
      "capitulo": "21"
    },
    "sopros": {
      "capitulo": "08"
    },
    "nega": {
      "capitulo": "21"
    },
    "50mg 12/12h": {
      "capitulo": "05"
    },
    "normotenso": {
      "capitulo": "11"
    },
    "travesseiro": {
      "capitulo": "21"
    },
    "dispneia aos moderados esforços": {
      "capitulo": "12"
    },
    "ad": {
      "capitulo": "13"
    },
    "dislipidemia": {
      "capitulo": "05"
    },
    "ar": {
      "capitulo": "13"
    },
    "fc": {
      "capitulo": "11"
    },
    "visceromegalias": {
      "capitulo": "13"
    },
    "exames laboratoriais": {
      "capitulo": "05"
    },
    "noite": {
      "capitulo": "21"
    },
    "icc diastólica": {
      "capitulo": "11"
    },
    "furosemida": {
      "capitulo": "11"
    },
    "sinvastatina": {
      "capitulo": "05"
    },
    "mv": {
      "capitulo": "11"
    },
    "cd": {
      "capitulo": "11"
    },
    "hd": {
      "capitulo": "11"
    },
    "icc classe iii": {
      "capitulo": "11"
    },
    "has": {
      "capitulo": "11"
    },
    "dmii": {
      "capitulo": "05"
    }
  }
}