{
  "prontuario_id": 506,
  "text": "ID : Lucas, 79 anos, viuvo, cobrador de ônibus aposentado, 6 filhos.  # Medicações em uso : - losartana 50 mg 12/12 h - AAS 100 mg - captopril ? 1 x ao dia -hidroclorotiazida 25 mg 1 x ao dia -flutamida 250 mg 8/8 h # Comorbidades : HAS, Ca de Prostata em acompanhamento há 2 anos.  S : retorno com exames Acompanha na cardiologia desde 2014 devido hipertensão arterial ( descoberta devido a medida casual ). Nega tontura, dispneia, dor no peito, cansaço, ou outras queixas desde a consulta anterior. Tabagista de 78 maços / ano por 65 anos ( cigarro de palha ). Nega etilismo. Faz exercícios físicos regularmente. Dieta   O : # Exames laboratoriais (09/06) - Creatinina: 1,2 mg/dL -- TFG: 64,95 mL/min ( estádio II de DRC ) - Glicose em jejum : 101 mg/dL - Ureia : 30 mg/dL -Triglicerideos : 81 mg/dL - HDL : 36 mg/dL - Na : 142 mmol/L - K:4,8 mmol/L - Colesterol Total : 137 mg/dL - Colesterol LDL : 85 md/dL - Glicose TOTG : 125 mg/dL - Eritrocitos : 4,19 mi/mm3 - Hb glicada : 5,39% -Microalbuminuria / creatinina : 8,2 mg/ g creatinina  # ETT : VE com dimensões normais, hipertrofia concentrica discreta, contratilidade segmentar e função sistólica global preservadas e disfunção diastólica. AE e camaras direitas normais. Valvas cardíacas normais.  # EF : Altura : 1,72 m Peso: 92 kg IMC : 31,9 kg/m2 PA : 105/80 mmHg Pulso : 59 bpm FR : 18 mrpm BEG, LOTE, anictérico, hidratado, aciánotico. Ausculta pulmonar: crepitação em região interscapular. Exame cardiovascular: Bulhas não audíveis, ictus não palpável e não visível. Abdominal: Abdomen globoso, flácido, indolor a palpação, RHA presentes, sem visceromegalias.  A : HAS controlada com medicação Síndrome metabólica. HAS sd metabolica ca prostata.",
  "entities": {
    "Substância Farmacológica": [
      "losartana",
      "AAS",
      "captopril",
      "-hidroclorotiazida",
      "-flutamida",
      "medicação"
    ],
    "Abreviação": [
      "AAS",
      "HAS",
      "S",
      "ETT",
      "EF",
      "IMC",
      "PA",
      "FR",
      "BEG",
      "LOTE",
      "A",
      "Ca de Prostata",
      "estádio II de DRC",
      "Na : 142 mmol/L",
      "K : 4 , 8 mmol/L",
      "VE com dimensões normais",
      "AE e camaras direitas normais",
      "RHA presentes",
      "HAS controlada",
      "sd metabolica",
      "ca prostata"
    ],
    "Doença ou Síndrome": [
      "Comorbidades",
      "HAS",
      "Tabagista",
      "etilismo",
      "Ca de Prostata",
      "hipertensão arterial",
      "estádio II de DRC",
      "HAS controlada",
      "Síndrome metabólica",
      "sd metabolica"
    ],
    "Ideia ou Conceito": [
      "Comorbidades"
    ],
    "Atividade de Assistência à Saúde": [
      "acompanhamento",
      "retorno",
      "Acompanha",
      "consulta anterior"
    ],
    "Achado": [
      "S",
      "BEG",
      "LOTE",
      "anictérico",
      "hidratado",
      "aciánotico",
      "audíveis",
      "flácido",
      "exercícios físicos regularmente",
      "RHA presentes"
    ],
    "Procedimento Diagnóstico": [
      "exames",
      "ETT",
      "EF",
      "A",
      "Ausculta pulmonar",
      "Exame cardiovascular"
    ],
    "Procedimento Laboratorial": [
      "exames",
      "Exames laboratoriais"
    ],
    "Organização Relacionada à Saúde": [
      "cardiologia"
    ],
    "Negação": [
      "Nega",
      "anictérico",
      "aciánotico",
      "não",
      "sem"
    ],
    "Sinal ou Sintoma": [
      "tontura",
      "dispneia",
      "cansaço",
      "queixas",
      "crepitação",
      "palpável",
      "visível",
      "globoso",
      "visceromegalias"
    ],
    "Localização ou Região Corporal": [
      "peito",
      "ictus",
      "Abdominal",
      "Abdomen",
      "região interscapular"
    ],
    "Disfunção Mental ou Comportamental": [
      "Tabagista"
    ],
    "Comportamento Individual": [
      "etilismo",
      "exercícios físicos regularmente"
    ],
    "Alimento": [
      "Dieta"
    ],
    "Atributo Clínico": [
      "Altura",
      "Peso",
      "IMC",
      "PA",
      "Pulso",
      "FR",
      "Bulhas",
      "ictus"
    ],
    "Procedimento Terapêutico ou Preventivo": [
      "medicação"
    ],
    "Grupo Etário": [
      "79 anos"
    ],
    "Grupo Profissional ou Ocupacional": [
      "cobrador de ônibus"
    ],
    "Conceito Quantitativo": [
      "50 mg",
      "100 mg",
      "25 mg",
      "250 mg",
      "78 maços / ano por 65 anos",
      "1 , 72 m",
      "92 kg",
      "31 , 9 kg/m2",
      "105/80 mmHg",
      "59 bpm",
      "18 mrpm"
    ],
    "Conceito Temporal": [
      "12/12 h",
      "1 x ao dia",
      "8/8 h",
      "há 2 anos",
      "consulta anterior"
    ],
    "Processo Neoplásico": [
      "Ca de Prostata",
      "ca prostata"
    ],
    "Objeto Manufaturado": [
      "cigarro de palha"
    ],
    "Resultado Laboratorial ou de Teste": [
      "Creatinina : 1 , 2 mg/dL",
      "TFG : 64 , 95 mL/min",
      "Glicose em jejum : 101 mg/dL",
      "Ureia : 30 mg/dL",
      "-Triglicerideos : 81 mg/dL",
      "HDL : 36 mg/dL",
      "Na : 142 mmol/L",
      "K : 4 , 8 mmol/L",
      "Colesterol Total : 137 mg/dL",
      "Colesterol LDL : 85 md/dL",
      "Glicose TOTG : 125 mg/dL",
      "Eritrocitos : 4 , 19 mi/mm3",
      "Hb glicada : 5 , 39%",
      "-Microalbuminuria / creatinina : 8 , 2 mg/ g creatinina",
      "VE com dimensões normais",
      "hipertrofia concentrica discreta",
      "contratilidade segmentar",
      "função sistólica global preservadas",
      "disfunção diastólica",
      "AE e camaras direitas normais",
      "Valvas cardíacas normais"
    ],
    "Função Patológica": [
      "disfunção diastólica"
    ]
  },
  "labels": {
    "cobrador de ônibus": {
      "capitulo": "24"
    },
    "disfunção diastólica": {
      "capitulo": "08"
    },
    "79 anos": {
      "capitulo": "20"
    },
    "há 2 anos": {
      "capitulo": "20"
    },
    "tabagista": {
      "capitulo": "24"
    },
    "retorno": {
      "capitulo": "24"
    },
    "ca de prostata": {
      "capitulo": "02"
    },
    "hb glicada : 5 , 39%": {
      "capitulo": "05"
    },
    "sd metabolica": {
      "capitulo": "05"
    },
    "síndrome metabólica": {
      "capitulo": "05"
    },
    "31 , 9 kg/m2": {
      "capitulo": "05"
    },
    "função sistólica global preservadas": {
      "capitulo": "08"
    },
    "crepitação": {
      "capitulo": "09"
    },
    "12/12 h": {
      "capitulo": "07"
    },
    "visível": {
      "capitulo": "09"
    },
    "etilismo": {
      "capitulo": "24"
    },
    "aciánotico": {
      "capitulo": "09"
    },
    "-triglicerideos : 81 mg/dl": {
      "capitulo": "05"
    },
    "globoso": {
      "capitulo": "09"
    },
    "pulso": {
      "capitulo": "08"
    },
    "cardiologia": {
      "capitulo": "08"
    },
    "altura": {
      "capitulo": "05"
    },
    "dieta": {
      "capitulo": "05"
    },
    "eritrocitos : 4 , 19 mi/mm3": {
      "capitulo": "03"
    },
    "anictérico": {
      "capitulo": "09"
    },
    "queixas": {
      "capitulo": "06"
    },
    "comorbidades": {
      "capitulo": "03"
    },
    "dispneia": {
      "capitulo": "09"
    },
    "imc": {
      "capitulo": "05"
    },
    "ett": {
      "capitulo": "08"
    },
    "peso": {
      "capitulo": "05"
    },
    "59 bpm": {
      "capitulo": "08"
    },
    "região interscapular": {
      "capitulo": "09"
    },
    "105/80 mmhg": {
      "capitulo": "11"
    },
    "-microalbuminuria / creatinina : 8 , 2 mg/ g creatinina": {
      "capitulo": "16"
    },
    "glicose em jejum : 101 mg/dl": {
      "capitulo": "05"
    },
    "rha presentes": {
      "capitulo": "09"
    },
    "-flutamida": {
      "capitulo": "05"
    },
    "colesterol ldl : 85 md/dl": {
      "capitulo": "11"
    },
    "hipertrofia concentrica discreta": {
      "capitulo": "08"
    },
    "8/8 h": {
      "capitulo": "07"
    },
    "ca prostata": {
      "capitulo": "02"
    },
    "abdominal": {
      "capitulo": "09"
    },
    "beg": {
      "capitulo": "08"
    },
    "contratilidade segmentar": {
      "capitulo": "08"
    },
    "100 mg": {
      "capitulo": "05"
    },
    "bulhas": {
      "capitulo": "08"
    },
    "ictus": {
      "capitulo": "08"
    },
    "ae e camaras direitas normais": {
      "capitulo": "08"
    },
    "valvas cardíacas normais": {
      "capitulo": "08"
    },
    "ureia : 30 mg/dl": {
      "capitulo": "11"
    },
    "hdl : 36 mg/dl": {
      "capitulo": "11"
    },
    "na : 142 mmol/l": {
      "capitulo": "11"
    },
    "colesterol total : 137 mg/dl": {
      "capitulo": "11"
    },
    "glicose totg : 125 mg/dl": {
      "capitulo": "05"
    }
  }
}