{
  "prontuario_id": 616,
  "text": "09:00 CONSCIENTE, ORIENTADO, VERBALIZA, EM REPOUSO NO LEITO, AFEBRIL, EUPNEICO EM AR AMBIENTE, SEM QUEIXAS ALGICAS, RELATA DIFICULDADE A MASTIGAÇÃO DEVIDO A SECREÇÃO ESBRANQUIÇADA EM REGIÃO DE GENGIVA, ODOR FETIDO, ACESSO VENOSO PERIFERICO EM MSE SALINIZADO SEM SINAIS FLOGISTICOS, HEMATOMA EM REGIÃO ORBITAL ESQUERDA, TALA + CURATIVO EXTERNAMENTE SECO E LIMPO EM MIE, PERFUSÃO DISTAL PRESERVADA, PULSO PALPAVEL, DIURESE ESPONTANEA. Doutor Vital Brazil MAEDA SOLICITOU AVALIAÇÃO DA CX. FACE, Doutor Vital Brazil AVALIOU E SOLICITOU AVALIAÇÃO CX. PLASTICA  O MESMO ORIENTOU APENAS HIGIENE ORAL, AGUARDA RESULTADO TAC DE JOELHO PARA AVALIAÇÃO ORTO. Enfermeira Florence Nightingale. TRAUMATISMO INTRACRANIANO NAO ESPECIFICADO",
  "entities": {
    "Achado": [
      "CONSCIENTE",
      "ORIENTADO",
      "VERBALIZA",
      "AFEBRIL",
      "SECO",
      "LIMPO",
      "EUPNEICO EM AR AMBIENTE",
      "PERFUSÃO DISTAL PRESERVADA",
      "PULSO PALPAVEL",
      "DIURESE ESPONTANEA"
    ],
    "Negação": [
      "AFEBRIL",
      "SEM"
    ],
    "Localização ou Região Corporal": [
      "MSE",
      "MIE",
      "REGIÃO DE GENGIVA",
      "REGIÃO ORBITAL ESQUERDA"
    ],
    "Abreviação": [
      "MSE",
      "MIE",
      "ORTO"
    ],
    "Procedimento Terapêutico ou Preventivo": [
      "SALINIZADO",
      "TALA",
      "CURATIVO",
      "REPOUSO NO LEITO",
      "ACESSO VENOSO PERIFERICO",
      "HIGIENE ORAL"
    ],
    "Sinal ou Sintoma": [
      "HEMATOMA",
      "QUEIXAS ALGICAS",
      "DIFICULDADE A MASTIGAÇÃO",
      "ODOR FETIDO",
      "SINAIS FLOGISTICOS"
    ],
    "Dispositivo Médico": [
      "TALA",
      "CURATIVO",
      "ACESSO VENOSO PERIFERICO"
    ],
    "Conceito Espacial": [
      "EXTERNAMENTE"
    ],
    "Atividade de Assistência à Saúde": [
      "AVALIOU",
      "ORIENTOU",
      "AVALIAÇÃO",
      "SOLICITOU AVALIAÇÃO"
    ],
    "Parte do Corpo, Órgão ou Componente Orgânico": [
      "JOELHO"
    ],
    "Grupo Profissional ou Ocupacional": [
      "ORTO"
    ],
    "Substância Corporal": [
      "SECREÇÃO ESBRANQUIÇADA"
    ],
    "Atributo Clínico": [
      "PERFUSÃO DISTAL PRESERVADA"
    ],
    "Função de Organismo": [
      "DIURESE ESPONTANEA"
    ],
    "Lesão ou Envenenamento": [
      "TRAUMATISMO INTRACRANIANO"
    ]
  },
  "labels": {
    "sinais flogisticos": {
      "capitulo": "21"
    },
    "queixas algicas": {
      "capitulo": "21"
    },
    "limpo": {
      "capitulo": "21"
    },
    "diurese espontanea": {
      "capitulo": "11"
    },
    "orto": {
      "capitulo": "21"
    },
    "externamente": {
      "capitulo": "21"
    },
    "perfusão distal preservada": {
      "capitulo": "11"
    },
    "orientou": {
      "capitulo": "21"
    },
    "joelho": {
      "capitulo": "15"
    },
    "solicitou avaliação": {
      "capitulo": "21"
    },
    "orientado": {
      "capitulo": "21"
    },
    "verbaliza": {
      "capitulo": "21"
    },
    "salinizado": {
      "capitulo": "11"
    },
    "mse": {
      "capitulo": "11"
    },
    "avaliou": {
      "capitulo": "21"
    },
    "região de gengiva": {
      "capitulo": "13"
    },
    "repouso no leito": {
      "capitulo": "18"
    },
    "secreção esbranquiçada": {
      "capitulo": "13"
    },
    "eupneico em ar ambiente": {
      "capitulo": "12"
    },
    "curativo": {
      "capitulo": "14"
    },
    "traumatismo intracraniano": {
      "capitulo": "22"
    },
    "acesso venoso periferico": {
      "capitulo": "11"
    },
    "seco": {
      "capitulo": "14"
    },
    "avaliação": {
      "capitulo": "21"
    },
    "mie": {
      "capitulo": "11"
    },
    "região orbital esquerda": {
      "capitulo": "9"
    },
    "hematoma": {
      "capitulo": "14"
    },
    "higiene oral": {
      "capitulo": "13"
    },
    "odor fetido": {
      "capitulo": "13"
    },
    "consciente": {
      "capitulo": "21"
    },
    "pulso palpavel": {
      "capitulo": "11"
    },
    "dificuldade a mastigação": {
      "capitulo": "13"
    },
    "sem": {
      "capitulo": "21"
    },
    "afebril": {
      "capitulo": "11"
    },
    "tala": {
      "capitulo": "14"
    }
  }
}