{
  "prontuario_id": 509,
  "text": "L.O., 58 a. DM diagnosticada há 5 anos, em uso de Metformina 850mg 3x / dia e Glicazida 2x / dia ( sem tomar há 2 meses ) HAS há 14 anos, em uso de Enalapril, Losartana (sem tomar há 2 dias), Hidroclorotiazida e Alondipino. Em uso de Doxasozina 4mg, para HPB. Refere cx na bexiga devido a tumor ( sic ) em 2013.  Sem queixas associadas, encaminhado para acompanhamento de DM2. Nega alterações de urina ou de visão.  Refere dor em calcanhar direito, sem presença de lesões.  Refere dieta adequada, sem consumo excessivo de doces ou gorduras.  Sedentario. Refere emagrecimento de 17 kgs em 2,5 anos. Nega etilismo. Ex-tabagista, 23 maços / ano, parou há 20 anos. Refere alergia a AAS.  HF : Tias com DM. Mãe HAS.  Lab (07/05/15): Hemograma sem alterações Cr 0,9 Glicose 241 Acido Urico 7,3 Transaminase piruvica 42 HDL 30 K 4,2 Transaminase oxalacetica 26 CT 244 TSH 1,55 Hb1ac : 11% Microalbuminuria 24h : 177mg ( 2500mL ) TG : 657mg/dL  Ex Fisico :  PA: 180/130 FC : 80 FR: 18 SatO2 : 93 Peso : 101,70kg Altura : 1,63m IMC : 38,28 CA : 121cm  Precordio : BCRNFSS Pulmonar : MV + , sem RA Abdome : globoso, flacido, RHA+ , indolor a palpação MMII : Sem edema, sem lesões em pés   CD : Prescrevo Insulina NPH 20U a noite, Metformina 850mg 3x / dia e Glibenclamida 5mg 2x / dia. Enalapril 10mg 2x / dia, Anlodipino 5mg 2x / dia, Hidroclorotiazida 25mg 1x / dia, Sinvastatina 20mg 1x / dia Solicito exames laboratoriais",
  "entities": {
    "Abreviação": [
      "DM",
      "HAS",
      "HPB",
      "DM2",
      "AAS",
      "Lab",
      "PA",
      "FC",
      "FR",
      "IMC",
      "CA",
      "BCRNFSS",
      "RA",
      "RHA+",
      "MMII",
      "CD",
      "NPH",
      "cx na bexiga",
      "Cr 0 , 9",
      "CT 244",
      "TG : 657mg/dL",
      "Ex Fisico",
      "MV +"
    ],
    "Doença ou Síndrome": [
      "DM",
      "HAS",
      "HPB",
      "DM2",
      "etilismo"
    ],
    "Produto Intelectual": [
      "diagnosticada",
      "CD"
    ],
    "Substância Farmacológica": [
      "Metformina",
      "Glicazida",
      "Enalapril",
      "Losartana",
      "Hidroclorotiazida",
      "Alondipino",
      "Doxasozina",
      "AAS",
      "Glibenclamida",
      "Anlodipino",
      "Sinvastatina"
    ],
    "Substância Química Orgânica": [
      "Metformina",
      "Hidroclorotiazida",
      "Alondipino",
      "Doxasozina",
      "AAS",
      "Anlodipino",
      "Sinvastatina"
    ],
    "Negação": [
      "sem",
      "Sem",
      "Nega"
    ],
    "Procedimento Terapêutico ou Preventivo": [
      "tomar",
      "cx na bexiga"
    ],
    "Aminoácido, Peptídeo ou Proteína": [
      "Enalapril",
      "Insulina",
      "NPH"
    ],
    "Conceito Quantitativo": [
      "4mg",
      "180/130",
      "80",
      "18",
      "93",
      "121cm",
      "3x / dia",
      "2x / dia",
      "17 kgs",
      "23 maços / ano",
      "101 , 70kg",
      "1 , 63m",
      "38 , 28",
      "1x / dia"
    ],
    "Processo Neoplásico": [
      "tumor"
    ],
    "Sinal ou Sintoma": [
      "queixas",
      "alterações",
      "dor",
      "lesões",
      "Sedentario",
      "emagrecimento",
      "RA",
      "globoso",
      "edema",
      "consumo excessivo de doces ou gorduras"
    ],
    "Atividade de Assistência à Saúde": [
      "encaminhado",
      "acompanhamento",
      "Prescrevo",
      "Solicito"
    ],
    "Substância Corporal": [
      "urina"
    ],
    "Função de Organismo": [
      "visão"
    ],
    "Lesão ou Envenenamento": [
      "lesões"
    ],
    "Comportamento Individual": [
      "etilismo"
    ],
    "Disfunção Mental ou Comportamental": [
      "etilismo"
    ],
    "Achado": [
      "Ex-tabagista",
      "HF",
      "BCRNFSS",
      "flacido",
      "RHA+",
      "dieta adequada",
      "MV +"
    ],
    "Função Patológica": [
      "alergia"
    ],
    "Grupo Familiar": [
      "Tias",
      "Mãe"
    ],
    "Procedimento Laboratorial": [
      "Lab",
      "Hemograma",
      "exames laboratoriais"
    ],
    "Resultado Laboratorial ou de Teste": [
      "alterações",
      "Cr 0 , 9",
      "Glicose 241",
      "Acido Urico 7 , 3",
      "Transaminase piruvica 42",
      "HDL 30",
      "K 4 , 2",
      "Transaminase oxalacetica 26",
      "CT 244",
      "TSH 1 , 55",
      "Hb1ac : 11%",
      "Microalbuminuria 24h : 177mg",
      "TG : 657mg/dL"
    ],
    "Atributo Clínico": [
      "PA",
      "FC",
      "FR",
      "SatO2",
      "Peso",
      "Altura",
      "IMC",
      "CA"
    ],
    "Parte do Corpo, Órgão ou Componente Orgânico": [
      "Precordio",
      "pés"
    ],
    "Sistema Corporal": [
      "Pulmonar"
    ],
    "Localização ou Região Corporal": [
      "Pulmonar",
      "Abdome",
      "MMII",
      "calcanhar direito"
    ],
    "Procedimento Diagnóstico": [
      "palpação",
      "Ex Fisico"
    ],
    "Hormônio": [
      "Insulina",
      "NPH"
    ],
    "Conceito Temporal": [
      "noite",
      "há 5 anos",
      "3x / dia",
      "2x / dia",
      "há 2 meses",
      "há 14 anos",
      "há 20 anos",
      "1x / dia"
    ]
  },
  "labels": {
    "metformina": {
      "capitulo": "L011"
    },
    "tsh 1 , 55": {
      "capitulo": "E030"
    },
    "abdome": {
      "capitulo": "K80"
    },
    "17 kgs": {
      "capitulo": "Z64"
    },
    "nph": {
      "capitulo": "L011"
    },
    "enalapril": {
      "capitulo": "I10"
    },
    "dieta adequada": {
      "capitulo": "Z64"
    },
    "pulmonar": {
      "capitulo": "K40"
    },
    "microalbuminuria 24h : 177mg": {
      "capitulo": "I12"
    },
    "acido urico 7 , 3": {
      "capitulo": "T85"
    },
    "93": {
      "capitulo": "Z64"
    },
    "23 maços / ano": {
      "capitulo": "Z64"
    },
    "etilismo": {
      "capitulo": "Z64"
    },
    "globoso": {
      "capitulo": "K80"
    },
    "1 , 63m": {
      "capitulo": "Z64"
    },
    "há 5 anos": {
      "capitulo": "Z64"
    },
    "4mg": {
      "capitulo": "Z64"
    },
    "hf": {
      "capitulo": "I10"
    },
    "hpb": {
      "capitulo": "K80"
    },
    "urina": {
      "capitulo": "K80"
    },
    "cd": {
      "capitulo": "Z64"
    },
    "fc": {
      "capitulo": "Z64"
    },
    "noite": {
      "capitulo": "Z64"
    },
    "dor": {
      "capitulo": "Z71"
    },
    "glicose 241": {
      "capitulo": "E11.9"
    },
    "glicazida": {
      "capitulo": "L011"
    },
    "solicito": {
      "capitulo": "Z64"
    },
    "há 2 meses": {
      "capitulo": "Z64"
    },
    "tomar": {
      "capitulo": "Z64"
    },
    "80": {
      "capitulo": "Z64"
    },
    "sedentario": {
      "capitulo": "Z64"
    },
    "dm2": {
      "capitulo": "E11.2.9"
    },
    "18": {
      "capitulo": "Z64"
    },
    "há 14 anos": {
      "capitulo": "Z64"
    },
    "aas": {
      "capitulo": "Z64"
    },
    "38 , 28": {
      "capitulo": "Z64"
    },
    "fr": {
      "capitulo": "Z64"
    },
    "sato2": {
      "capitulo": "Z64"
    },
    "nega": {
      "capitulo": "Z64"
    },
    "lesões": {
      "capitulo": "Z71"
    },
    "3x / dia": {
      "capitulo": "Z64"
    },
    "precordio": {
      "capitulo": "K40"
    },
    "sinvastatina": {
      "capitulo": "L011"
    },
    "hb1ac : 11%": {
      "capitulo": "E11.9"
    },
    "transaminase oxalacetica 26": {
      "capitulo": "T85"
    },
    "ct 244": {
      "capitulo": "T85"
    },
    "121cm": {
      "capitulo": "Z64"
    },
    "ex-tabagista": {
      "capitulo": "Z64"
    }
  }
}