{
  "prontuario_id": 250,
  "text": "ID: Lucas, 55 ANOS, PROCEDENCIA CURITIBA, NATURAL DE SIQUEIRA CAMPOS, NÃO TRABALHA\nHMA : PALPITAÇÕES E TAQUICARDIA AO REPOUSO.\nFA CRONICA\n# 2CX DE TROCA DE MITRAL + ATRIOSEPTOPLASTIA (2006)\n# 23/09/14 PROTESE METALICA EM POSIÇÃO MITRAL NORMOFUNCIONANTE. VE APRESENTA DIMENSÕES NORMAIS COM FUNÇÃO SISTOLICA PRESERVADA. VENTRICULO DIREITO APRESENTA DIMENSÕES AUMENTADAS E FUNÇÃO SISTOLICA COMPROMETIDA DISCRETAMENTE. REGURGITAÇÃO TRICUSPIDE DISCRETA. PSAP ESTIMADA EM 45MMHG. ATRIO ESQUERDO E DIREITO DILATADOS.\n# MEDICAMENTOS EM USO: \nWARFARIM 5MG\nSELOKEN 100MG\nDIGOXINA 0,25MG\n* NÃO ESTÁ UTILIZANDO PENICILINA BENZATINA FALTA NA UNIDADE DE SAÚDE\n# RNI 14/03: 3,27\n13/06 2,68\n12/09 4,01 ( TROCOU MARCA DO REMEDIO )\nFC 72 \nPA 100X60MMHG\nCONDUTA :\nSUBSTITUIR SELOKEN POR SELOZOK\n \n \n \n ",
  "entities": {
    "Sinal ou Sintoma": [
      "PALPITAÇÕES",
      "DILATADOS",
      "TAQUICARDIA AO REPOUSO",
      "DIMENSÕES AUMENTADAS",
      "FUNÇÃO SISTOLICA COMPROMETIDA DISCRETAMENTE",
      "REGURGITAÇÃO TRICUSPIDE DISCRETA"
    ],
    "Procedimento Terapêutico ou Preventivo": [
      "ATRIOSEPTOPLASTIA",
      "2CX DE TROCA DE MITRAL"
    ],
    "Abreviação": [
      "VE",
      "PSAP",
      "FC",
      "PA",
      "FA CRONICA",
      "2CX DE TROCA DE MITRAL"
    ],
    "Parte do Corpo, Órgão ou Componente Orgânico": [
      "VE",
      "VENTRICULO DIREITO"
    ],
    "Atributo Clínico": [
      "PSAP",
      "FC",
      "PA"
    ],
    "Conceito Quantitativo": [
      "45MMHG",
      "5MG",
      "100MG",
      "72",
      "100X60MMHG",
      "0 , 25MG",
      "3 , 27",
      "2 , 68",
      "4 , 01"
    ],
    "Conceito Espacial": [
      "ESQUERDO",
      "DIREITO"
    ],
    "Substância Farmacológica": [
      "MEDICAMENTOS",
      "WARFARIM",
      "SELOKEN",
      "DIGOXINA",
      "SELOZOK",
      "PENICILINA BENZATINA"
    ],
    "Negação": [
      "NÃO",
      "FALTA"
    ],
    "Procedimento Laboratorial": [
      "RNI"
    ],
    "Resultado Laboratorial ou de Teste": [
      "RNI"
    ],
    "Atividade de Assistência à Saúde": [
      "TROCOU",
      "CONDUTA",
      "SUBSTITUIR"
    ],
    "Produto Intelectual": [
      "CONDUTA"
    ],
    "Doença ou Síndrome": [
      "FA CRONICA"
    ],
    "Dispositivo Médico": [
      "PROTESE METALICA"
    ],
    "Achado": [
      "POSIÇÃO MITRAL NORMOFUNCIONANTE",
      "DIMENSÕES NORMAIS",
      "FUNÇÃO SISTOLICA PRESERVADA"
    ],
    "Anormalidade Adquirida": [
      "FUNÇÃO SISTOLICA COMPROMETIDA DISCRETAMENTE"
    ],
    "Anormalidade Anatômica": [
      "REGURGITAÇÃO TRICUSPIDE DISCRETA"
    ],
    "Antibiótico": [
      "PENICILINA BENZATINA"
    ],
    "Organização Relacionada à Saúde": [
      "UNIDADE DE SAÚDE"
    ],
    "Medicamento Clínico": [
      "MARCA DO REMEDIO"
    ]
  },
  "labels": {
    "protese metalica": {
      "capitulo": "11"
    },
    "esquerdo": {
      "capitulo": "11"
    },
    "dimensões aumentadas": {
      "capitulo": "11"
    },
    "pa": {
      "capitulo": "11"
    },
    "função sistolica preservada": {
      "capitulo": "11"
    },
    "2cx de troca de mitral": {
      "capitulo": "11"
    },
    "fa cronica": {
      "capitulo": "11"
    },
    "45mmhg": {
      "capitulo": "11"
    },
    "taquicardia ao repouso": {
      "capitulo": "11"
    },
    "100mg": {
      "capitulo": "11"
    },
    "regurgitação tricuspide discreta": {
      "capitulo": "11"
    },
    "posição mitral normofuncionante": {
      "capitulo": "11"
    },
    "seloken": {
      "capitulo": "11"
    },
    "dimensões normais": {
      "capitulo": "11"
    },
    "função sistolica comprometida discretamente": {
      "capitulo": "11"
    },
    "palpitações": {
      "capitulo": "11"
    },
    "marca do remedio": {
      "capitulo": "24"
    },
    "ventriculo direito": {
      "capitulo": "11"
    },
    "fc": {
      "capitulo": "11"
    },
    "dilatados": {
      "capitulo": "11"
    },
    "digoxina": {
      "capitulo": "11"
    },
    "falta": {
      "capitulo": "21"
    },
    "direito": {
      "capitulo": "11"
    },
    "conduta": {
      "capitulo": "24"
    },
    "selozok": {
      "capitulo": "11"
    },
    "psap": {
      "capitulo": "11"
    },
    "72": {
      "capitulo": "21"
    },
    "substituir": {
      "capitulo": "24"
    },
    "atrioseptoplastia": {
      "capitulo": "11"
    },
    "rni": {
      "capitulo": "11"
    },
    "trocou": {
      "capitulo": "24"
    },
    "100x60mmhg": {
      "capitulo": "11"
    },
    "não": {
      "capitulo": "21"
    },
    "warfarim": {
      "capitulo": "11"
    },
    "5mg": {
      "capitulo": "11"
    }
  }
}