{
  "prontuario_id": 75,
  "text": "Lucas, 63 ANOS\nCOMORBIDADES:\n# MCP DILATADA / CHAGAS\n# HAS\n# DISLIPIDEMIA\n# MARCA-PASSO HÁ 5 ANOS --> 11 MESES DE BATERIA\n# DAC FAMILIAR\n# CHV: EX-TABAGISTA DE 38 MAÇOS-ANO\nLucas, 63 ANOS\nCOMORBIDADES:\n# MCP DILATADA/CHAGAS\n# HAS\n# DISLIPIDEMIA\n# MARCA-PASSO HÁ 5 ANOS --> 11 MESES DE BATERIA\n# DAC FAMILIAR\n# CHV: EX-TABAGISTA DE 38 MAÇOS-ANO\nCATE DO DIA 29/07/2014: PROTOCOLO PRÉ - TRANSPLANTE CARDÍACO REALIZADO COM SUCESSO; RVP WOOD POSITIVA: CANDIDATO A TRANSPLANTE\nS # MANTEM-SE EM CLASSE FUNCIONAL III. RELATA EDEMA DE MMII. NEGA PRECORDIALGIA. \nMEDICAMENTOS:\n# ENALAPRIL 10 MG; 1/2 CP DE 12/12 HORAS\n# APRESOLINA 50 MG 1 CP DE 8/8 HORAS\n# MONOCORDL 20 MG 1 CP AS 8 E OUTRO AS 14 HORAS\n# ESPIRONOLACTONA 25 MG 1 CP AO DIA\n# FUROSEMIDA 40 MG 1 CP AS 8 E OUTRO AS 14 HORAS\n# CARVEDILOL 25 MG 1 CP DE 12/12 HORAS\n# SINVASTATINA 20 MG 1 CP A NOITE\nExame Físico\nPA 90/70 mmHG FC 76bpm, FR 18bpm\nACV: BCRNF SS EM FOCO TRICUSPIDE 3+ / 6+, SS EM FOCO MITRLA 2+ / 6+\nAP: MV+ BILAT, SEM RA\nABD: GLOBOSO, FLÁCIDO, PIPAROTE +\nEdema em MMII ++/++++\nA # IC CF III\nP # AUMENTO FSM PARA 80MG / 40MG\n-  DEMAIS MANTISO\nR4 CARDIO Doutor Vital Brazil ",
  "entities": {
    "Doença ou Síndrome": [
      "COMORBIDADES",
      "CHAGAS",
      "HAS",
      "DISLIPIDEMIA",
      "DAC",
      "MCP DILATADA",
      "MCP DILATADA/CHAGAS",
      "IC CF III"
    ],
    "Abreviação": [
      "HAS",
      "DAC",
      "CHV",
      "CATE",
      "MMII",
      "PA",
      "FC",
      "FR",
      "ACV",
      "BCRNF",
      "SS",
      "AP",
      "RA",
      "ABD",
      "FSM",
      "MCP DILATADA",
      "MCP DILATADA/CHAGAS",
      "RVP WOOD POSITIVA",
      "1/2 CP",
      "1 CP",
      "MV+ BILAT",
      "PIPAROTE +",
      "IC CF III"
    ],
    "Dispositivo Médico": [
      "MARCA-PASSO"
    ],
    "Procedimento Terapêutico ou Preventivo": [
      "MARCA-PASSO",
      "CATE",
      "TRANSPLANTE CARDÍACO"
    ],
    "Grupo Familiar": [
      "FAMILIAR"
    ],
    "Achado": [
      "CHV",
      "EX-TABAGISTA",
      "SUCESSO",
      "BCRNF",
      "SS",
      "FLÁCIDO",
      "MV+ BILAT"
    ],
    "Procedimento Diagnóstico": [
      "CATE",
      "Exame Físico"
    ],
    "Conceito Temporal": [
      "PRÉ",
      "12/12 HORAS",
      "8/8 HORAS",
      "A NOITE"
    ],
    "Atividade de Assistência à Saúde": [
      "REALIZADO",
      "AUMENTO"
    ],
    "Sinal ou Sintoma": [
      "EDEMA",
      "PRECORDIALGIA",
      "SS",
      "RA",
      "GLOBOSO",
      "Edema",
      "RVP WOOD POSITIVA",
      "PIPAROTE +"
    ],
    "Localização ou Região Corporal": [
      "MMII",
      "ABD",
      "FOCO TRICUSPIDE",
      "FOCO MITRLA"
    ],
    "Negação": [
      "NEGA",
      "SEM"
    ],
    "Substância Farmacológica": [
      "MEDICAMENTOS",
      "ENALAPRIL",
      "APRESOLINA",
      "MONOCORDL",
      "ESPIRONOLACTONA",
      "FUROSEMIDA",
      "CARVEDILOL",
      "SINVASTATINA",
      "FSM"
    ],
    "Aminoácido, Peptídeo ou Proteína": [
      "ENALAPRIL"
    ],
    "Atributo Clínico": [
      "PA",
      "FC",
      "FR",
      "ACV",
      "AP"
    ],
    "Conceito Quantitativo": [
      "76bpm",
      "18bpm",
      "++/++++",
      "80MG",
      "40MG",
      "38 MAÇOS-ANO",
      "10 MG",
      "1/2 CP",
      "50 MG",
      "1 CP",
      "20 MG",
      "25 MG",
      "40 MG",
      "90/70 mmHG",
      "3+ / 6+",
      "2+ / 6+"
    ],
    "Sistema Corporal": [
      "ACV"
    ],
    "Resultado Laboratorial ou de Teste": [
      "++/++++",
      "CANDIDATO A TRANSPLANTE",
      "FOCO TRICUSPIDE",
      "PIPAROTE +"
    ],
    "Conceito Qualitativo": [
      "CLASSE FUNCIONAL III"
    ]
  },
  "labels": {
    "mmii": {
      "capitulo": "15"
    },
    "mcp dilatada": {
      "capitulo": "15"
    },
    "ss": {
      "capitulo": "21"
    },
    "38 maços-ano": {
      "capitulo": "23"
    },
    "comorbidades": {
      "capitulo": "24"
    },
    "medicamentos": {
      "capitulo": "24"
    },
    "chv": {
      "capitulo": "24"
    },
    "mcp dilatada/chagas": {
      "capitulo": "15"
    },
    "edema": {
      "capitulo": "15"
    },
    "dac": {
      "capitulo": "15"
    },
    "3+ / 6+": {
      "capitulo": "21"
    },
    "rvp wood positiva": {
      "capitulo": "11"
    },
    "enalapril": {
      "capitulo": "24"
    },
    "1/2 cp": {
      "capitulo": "24"
    },
    "realizado": {
      "capitulo": "24"
    },
    "piparote +": {
      "capitulo": "21"
    },
    "20 mg": {
      "capitulo": "21"
    },
    "fr": {
      "capitulo": "21"
    },
    "10 mg": {
      "capitulo": "21"
    },
    "18bpm": {
      "capitulo": "21"
    },
    "ap": {
      "capitulo": "24"
    },
    "pa": {
      "capitulo": "24"
    },
    "espironolactona": {
      "capitulo": "24"
    },
    "++/++++": {
      "capitulo": "21"
    },
    "fsm": {
      "capitulo": "21"
    },
    "a noite": {
      "capitulo": "24"
    },
    "foco mitrla": {
      "capitulo": "21"
    },
    "76bpm": {
      "capitulo": "21"
    },
    "nega": {
      "capitulo": "21"
    },
    "bcrnf": {
      "capitulo": "21"
    },
    "1 cp": {
      "capitulo": "24"
    },
    "dislipidemia": {
      "capitulo": "05"
    },
    "pré": {
      "capitulo": "24"
    },
    "chagas": {
      "capitulo": "15"
    },
    "monocordl": {
      "capitulo": "24"
    },
    "furosemida": {
      "capitulo": "24"
    },
    "sinvastatina": {
      "capitulo": "05"
    },
    "40mg": {
      "capitulo": "21"
    },
    "fc": {
      "capitulo": "21"
    },
    "aumento": {
      "capitulo": "21"
    },
    "80mg": {
      "capitulo": "21"
    },
    "mv+ bilat": {
      "capitulo": "21"
    },
    "sem": {
      "capitulo": "21"
    },
    "flácido": {
      "capitulo": "21"
    },
    "carvedilol": {
      "capitulo": "24"
    },
    "12/12 horas": {
      "capitulo": "24"
    },
    "40 mg": {
      "capitulo": "21"
    },
    "familiar": {
      "capitulo": "24"
    },
    "has": {
      "capitulo": "24"
    },
    "apresolina": {
      "capitulo": "24"
    },
    "precordialgia": {
      "capitulo": "21"
    },
    "50 mg": {
      "capitulo": "21"
    },
    "globoso": {
      "capitulo": "21"
    },
    "2+ / 6+": {
      "capitulo": "21"
    },
    "marca-passo": {
      "capitulo": "21"
    },
    "candidato a transplante": {
      "capitulo": "24"
    },
    "classe funcional iii": {
      "capitulo": "25"
    },
    "ic cf iii": {
      "capitulo": "25"
    },
    "cate": {
      "capitulo": "24"
    },
    "90/70 mmhg": {
      "capitulo": "21"
    },
    "exame físico": {
      "capitulo": "24"
    },
    "ra": {
      "capitulo": "24"
    },
    "transplante cardíaco": {
      "capitulo": "24"
    },
    "abd": {
      "capitulo": "24"
    },
    "ex-tabagista": {
      "capitulo": "24"
    }
  }
}