{
  "prontuario_id": 763,
  "text": "TX RENAL.\n\nEM USO DE PRED 5, MS 2 / 2, TACROLIMO 2 / 2; OMEPRAZOL - PAROU E VOLTOU, CVDL 25 1X, AAS - PAROU POR CONTA, ENALAPRIL 5 - PAROU HOJE, ACICLOVIR, FLUCONAZOL E CETOCONAZOL. \n\n\nS # IVAS HÁ 1 MES , \nLESÕES ''ALERGICAS'' EM TRONCO, EM USO DE FLUCONAZOL E CETOCONAZOL, MAS SEM MELHORA\nDIARRÉIA. \n\nO # PESO 80.\nPA 120/80.\nEXAME FISICO :  LESÕES HIPEREMIADAS EM COLO E ABDOME>> SUGERE DERMATITE DE CONTATO, PROVÁVEL SABONETE ANTISSEPTICO.\nCPP LIVRES.\n \nSUSPENDO ACICLOVIR, REDUZO MS.\nSUSPENDO FLUCONAZOL E CETOCONAZOL.\nCIPRO 7 DIAS.\nTX RENAL CR 1,1, TACROLIMO 5.\nLESÕES DE PELE /  DERMATITE CONTATO ?\nHAS COMPENSADO.\nDISPEPSIA.\nIVAS : EXACERBAÇÃO AGUDA DE BRONQUITE CRONICA\n ",
  "entities": {
    "Substância Farmacológica": [
      "PRED",
      "TACROLIMO",
      "OMEPRAZOL",
      "CVDL",
      "AAS",
      "ENALAPRIL",
      "ACICLOVIR",
      "FLUCONAZOL",
      "CETOCONAZOL",
      "MS",
      "CIPRO"
    ],
    "Abreviação": [
      "PRED",
      "MS",
      "CVDL",
      "AAS",
      "S",
      "IVAS",
      "O",
      "PA",
      "CIPRO",
      "HAS",
      "TX RENAL",
      "CPP LIVRES",
      "CR 1 , 1"
    ],
    "Substância Química Orgânica": [
      "PRED",
      "MS",
      "TACROLIMO",
      "OMEPRAZOL",
      "CVDL",
      "AAS",
      "ACICLOVIR",
      "FLUCONAZOL",
      "CETOCONAZOL",
      "CIPRO"
    ],
    "Conceito Quantitativo": [
      "5",
      "2",
      "25",
      "1X",
      "80",
      "120/80"
    ],
    "Achado": [
      "S",
      "MELHORA",
      "COMPENSADO",
      "TX RENAL",
      "PAROU E VOLTOU",
      "PAROU POR CONTA",
      "PAROU HOJE",
      "CPP LIVRES"
    ],
    "Doença ou Síndrome": [
      "IVAS",
      "HAS",
      "DISPEPSIA",
      "DERMATITE DE CONTATO",
      "DERMATITE CONTATO",
      "BRONQUITE CRONICA"
    ],
    "Parte do Corpo, Órgão ou Componente Orgânico": [
      "TRONCO",
      "ABDOME&gt;&gt;"
    ],
    "Negação": [
      "SEM"
    ],
    "Sinal ou Sintoma": [
      "DIARRÉIA",
      "LESÕES ''ALERGICAS''",
      "LESÕES HIPEREMIADAS"
    ],
    "Procedimento Diagnóstico": [
      "O",
      "EXAME FISICO"
    ],
    "Atributo de Organismo": [
      "PESO"
    ],
    "Atributo Clínico": [
      "PA"
    ],
    "Localização ou Região Corporal": [
      "COLO"
    ],
    "Atividade de Assistência à Saúde": [
      "SUSPENDO",
      "REDUZO"
    ],
    "Procedimento Terapêutico ou Preventivo": [
      "TX RENAL"
    ],
    "Resultado Laboratorial ou de Teste": [
      "CR 1 , 1"
    ],
    "Lesão ou Envenenamento": [
      "LESÕES DE PELE"
    ]
  },
  "labels": {
    "doença cardíaca": {
      "capitulo": "03"
    },
    "hipertensão arterial": {
      "capitulo": "04"
    },
    "doenças do sistema nervoso": {
      "capitulo": "06"
    },
    "doenças do aparelho respiratório": {
      "capitulo": "07"
    },
    "doenças do aparelho circulatório": {
      "capitulo": "08"
    },
    "doenças do aparelho digestivo": {
      "capitulo": "09"
    },
    "doenças do aparelho geniturinário": {
      "capitulo": "10"
    },
    "doenças endócrinas": {
      "capitulo": "11"
    },
    "doenças do sistema músculo-esquelético": {
      "capitulo": "12"
    },
    "doenças do tecido conjuntivo": {
      "capitulo": "13"
    },
    "doenças infecciosas e parasitárias": {
      "capitulo": "14"
    },
    "neoplasias": {
      "capitulo": "15"
    },
    "lesões externas": {
      "capitulo": "16"
    },
    "transtornos mentais e comportamentais": {
      "capitulo": "17"
    },
    "transtornos do desenvolvimento": {
      "capitulo": "18"
    },
    "transtornos orgânicos da mente": {
      "capitulo": "19"
    },
    "transtornos relacionados ao uso de substâncias": {
      "capitulo": "20"
    },
    "transtornos mentais e comportamentais desencadeados por fatores externos": {
      "capitulo": "21"
    }
  }
}