{
  "prontuario_id": 29,
  "text": "# IAM 2013 + ATC\n# HAS\n# DM\n# TBG ATIVA\n \n \n# S: Refere dispneia a medios/grandes esforços,\nrefere edema de membros inferiores, com piora no final do dia.\nrefere palpitaçoes esporádicas.\n nega ortopneia ou dispneia paroxistica, nega dor toracica.\n\nrelata caminhar bastante e andar de bicicleta.\n\n\n\n# ECOCARDIO 17/12/15: VE com dimensões normais e função sistólica global diminuída de grau moderado (FE simpson 42%). Alteração de contratilidade segmentar. Disfunção diastólica grau I. àtrio esquerdo e Câmaras direitas normais. Refluxo mitral discreto.\n\n# CINTILO FIBROSE PERSISTENTE APICE E MEDIO APICAL DA P ANTERIOR E ANTERO SEPTAL DISCRETA ISQUEMIA ASSOCIADA\nFE 23-28%.\n# CINTILOGRAFIA 16/01/15: HIPOPERFUSÃO ACENTUADA E PERSISTENTE NO APICE E MEDIO APICAL PAREDE ANTERIOR E ANTERO SEPTAL VE.\nHIPOCINESIA DIFUSA DAS PAREDES DO VE, ANTERIOR E APICAL. FE 23---28%.\n# TESTE ESFORÇO 16/01/15: AUSENCIA DE MANIFESTAÇÕES ELETROCARDIOGRAFICAS SUJESTIVAS DE ISQUEMIA MIOCARDICA.\n\n\nEM USO DE: AAS 100MG DIA, CARVEDILOL 12,5G 2x DIA, ENALAPRIL 10MG 1/2CP 2X DIA, METFORMINA 850MG 1CP AO DIA, SINVASTATINA 80MG A NOITE, ESPIRONOLACTONA 25MG (refere não utilizar corretamente pois causa cefaleia).\n\nO: P 70, PA 120/80.\nBEG, LOTE, normocorada, hidratada.\nBRNF SS.\nMV+ bilateralmente S RA.\nMMII edema +/++++ em membro direito.\n\n\nP: adiciono furosemida 40mg, aumento carvedilol para 25 2x ao dia, substituo sinvastatina por atorvastatina 80mg (LDL 122).\n ",
  "entities": {
    "Abreviação": [
      "IAM",
      "ATC",
      "HAS",
      "DM",
      "S",
      "ECOCARDIO",
      "CINTILO",
      "AAS",
      "O",
      "P",
      "PA",
      "BEG",
      "LOTE",
      "BRNF",
      "SS",
      "RA",
      "MMII",
      "TBG ATIVA",
      "VE com dimensões normais",
      "FE simpson 42%",
      "FE 23-28%",
      "PAREDE ANTERIOR E ANTERO SEPTAL VE",
      "HIPOCINESIA DIFUSA DAS PAREDES DO VE",
      "FE 23---28%",
      "1CP AO DIA"
    ],
    "Doença ou Síndrome": [
      "IAM",
      "HAS",
      "DM",
      "TBG ATIVA"
    ],
    "Achado": [
      "IAM",
      "HAS",
      "DM",
      "S",
      "BEG",
      "LOTE",
      "normocorada",
      "hidratada",
      "BRNF",
      "piora no final do dia",
      "caminhar bastante e",
      "andar",
      "utilizar corretamente"
    ],
    "Conceito Temporal": [
      "2013",
      "DIA",
      "2x DIA",
      "1/2CP 2X DIA",
      "1CP AO DIA",
      "NOITE",
      "2x ao dia"
    ],
    "Procedimento Terapêutico ou Preventivo": [
      "ATC",
      "aumento"
    ],
    "Sinal ou Sintoma": [
      "edema",
      "ortopneia",
      "cefaleia",
      "SS",
      "RA",
      "dispneia a medios/grandes esforços",
      "piora no final do dia",
      "palpitaçoes esporádicas",
      "dispneia paroxistica",
      "dor toracica"
    ],
    "Função Patológica": [
      "edema"
    ],
    "Negação": [
      "nega",
      "não",
      "SS",
      "S"
    ],
    "Procedimento Diagnóstico": [
      "ECOCARDIO",
      "CINTILO",
      "CINTILOGRAFIA",
      "TESTE ESFORÇO"
    ],
    "Substância Química Orgânica": [
      "AAS",
      "CARVEDILOL",
      "METFORMINA",
      "SINVASTATINA",
      "ESPIRONOLACTONA",
      "furosemida",
      "carvedilol"
    ],
    "Substância Farmacológica": [
      "AAS",
      "CARVEDILOL",
      "ENALAPRIL",
      "METFORMINA",
      "SINVASTATINA",
      "ESPIRONOLACTONA",
      "furosemida",
      "carvedilol",
      "sinvastatina",
      "atorvastatina"
    ],
    "Conceito Quantitativo": [
      "100MG",
      "10MG",
      "850MG",
      "80MG",
      "25MG",
      "70",
      "120/80",
      "40mg",
      "25",
      "80mg",
      "12 , 5G"
    ],
    "Aminoácido, Peptídeo ou Proteína": [
      "ENALAPRIL"
    ],
    "Atividade de Assistência à Saúde": [
      "O",
      "adiciono",
      "aumento",
      "substituo"
    ],
    "Atributo Clínico": [
      "P",
      "PA"
    ],
    "Conceito Espacial": [
      "bilateralmente"
    ],
    "Parte do Corpo, Órgão ou Componente Orgânico": [
      "MMII",
      "membros inferiores"
    ],
    "Produto Intelectual": [
      "P"
    ],
    "Resultado Laboratorial ou de Teste": [
      "VE com dimensões normais",
      "função sistólica global diminuída de grau moderado",
      "FE simpson 42%",
      "Alteração de contratilidade segmentar",
      "Disfunção diastólica grau I",
      "àtrio esquerdo e Câmaras direitas normais",
      "Refluxo mitral discreto",
      "FIBROSE PERSISTENTE APICE E MEDIO APICAL DA P ANTERIOR",
      "ANTERO SEPTAL DISCRETA ISQUEMIA ASSOCIADA",
      "FE 23-28%",
      "HIPOPERFUSÃO ACENTUADA E PERSISTENTE NO APICE E MEDIO APICAL",
      "PAREDE ANTERIOR E ANTERO SEPTAL VE",
      "HIPOCINESIA DIFUSA DAS PAREDES DO VE",
      "ANTERIOR E APICAL",
      "FE 23---28%",
      "AUSENCIA DE MANIFESTAÇÕES ELETROCARDIOGRAFICAS SUJESTIVAS DE ISQUEMIA MIOCARDICA",
      "+/++++"
    ]
  },
  "labels": {
    "metformina": {
      "capitulo": "05.1.10.000"
    },
    "enalapril": {
      "capitulo": "11.50.10.000"
    },
    "alteração de contratilidade segmentar": {
      "capitulo": "21.1.10.000"
    },
    "ortopneia": {
      "capitulo": "11.50.10.000"
    },
    "hipocinesia difusa das paredes do ve": {
      "capitulo": "11.50.10.000"
    },
    "iam": {
      "capitulo": "11.50.10.000"
    },
    "furosemida": {
      "capitulo": "11.50.10.000"
    },
    "função sistólica global diminuída de grau moderado": {
      "capitulo": "11.50.10.000"
    },
    "40mg": {
      "capitulo": "21.1.10.000"
    },
    "fe 23-28%": {
      "capitulo": "21.1.10.000"
    },
    "1/2cp 2x dia": {
      "capitulo": "21.1.10.000"
    },
    "tbg ativa": {
      "capitulo": "05.1.10.000"
    },
    "aumento": {
      "capitulo": "21.1.10.000"
    },
    "1cp ao dia": {
      "capitulo": "21.1.10.000"
    },
    "2x ao dia": {
      "capitulo": "21.1.10.000"
    },
    "normocorada": {
      "capitulo": "21.1.10.000"
    },
    "andar": {
      "capitulo": "21.1.10.000"
    },
    "dispneia a medios/grandes esforços": {
      "capitulo": "11.50.10.000"
    },
    "membros inferiores": {
      "capitulo": "11.50.10.000"
    },
    "70": {
      "capitulo": "21.1.10.000"
    },
    "cintilografia": {
      "capitulo": "21.1.10.000"
    },
    "p": {
      "capitulo": "21.1.10.000"
    },
    "atorvastatina": {
      "capitulo": "05.1.10.000"
    },
    "adiciono": {
      "capitulo": "21.1.10.000"
    },
    "edema": {
      "capitulo": "11.50.10.000"
    },
    "teste esforço": {
      "capitulo": "21.1.10.000"
    },
    "fe 23---28%": {
      "capitulo": "21.1.10.000"
    },
    "anterior e apical": {
      "capitulo": "11.50.10.000"
    },
    "não": {
      "capitulo": "21.1.10.000"
    },
    "noite": {
      "capitulo": "21.1.10.000"
    },
    "carvedilol": {
      "capitulo": "11.50.10.000"
    },
    "120/80": {
      "capitulo": "21.1.10.000"
    },
    "atc": {
      "capitulo": "21.1.10.000"
    },
    "substituo": {
      "capitulo": "21.1.10.000"
    },
    "cintilo": {
      "capitulo": "21.1.10.000"
    },
    "ss": {
      "capitulo": "21.1.10.000"
    },
    "dor toracica": {
      "capitulo": "11.50.10.000"
    },
    "àtrio esquerdo e câmaras direitas normais": {
      "capitulo": "11.50.10.000"
    },
    "s": {
      "capitulo": "21.1.10.000"
    },
    "ve com dimensões normais": {
      "capitulo": "11.50.10.000"
    },
    "850mg": {
      "capitulo": "21.1.10.000"
    },
    "ecocardio": {
      "capitulo": "11.50.10.000"
    },
    "antero septal discreta isquemia associada": {
      "capitulo": "11.50.10.000"
    },
    "aas": {
      "capitulo": "11.50.10.000"
    },
    "25": {
      "capitulo": "21.1.10.000"
    },
    "parede anterior e antero septal ve": {
      "capitulo": "11.50.10.000"
    },
    "disfunção diastólica grau i": {
      "capitulo": "11.50.10.000"
    },
    "nega": {
      "capitulo": "21.1.10.000"
    },
    "100mg": {
      "capitulo": "21.1.10.000"
    },
    "has": {
      "capitulo": "21.1.10.000"
    },
    "bilateralmente": {
      "capitulo": "11.50.10.000"
    },
    "fe simpson 42%": {
      "capitulo": "21.1.10.000"
    },
    "refluxo mitral discreto": {
      "capitulo": "11.50.10.000"
    }
  }
}