{
  "prontuario_id": 417,
  "text": "RETORNO\n\n# S: PACIENTE EM ACOMPANHAMENTO POR TUMORAÇÃO EM MANDÍBULA.\nINICIO HA CERCA DE 7 MESES, EM FACE E CORPO DE MANDIBULA DIR, INDOLOR. NAO AUMENTA O VOLUME HA 3 MESES.\nNEGA DISFAGIA, NEGA PARESIAS OU PARESTESIAS EM FACE.\nNEGA TABAGISMO; NEGA ALERGIAS,\nEPISTAXE FREQUENTE (2 A 3 X / SEMANA).\n\nHMP: HAS EM TTO, TRANSPLANTADA RENAL ESQ HA 03 ANOS, EM USO DE IMUNODEPRESSORES (SIC);\n\n# O: ORO: EDENTULISMO SUP E INF; PRESENÇA DE MASSA ENDURECIDA EM CORPO E RAMO DIREITOS DE MANDIBULA , INDOLOR Á PALPAÇÃO; 8 X 8CM;\nLINGUA E ASSOALHO LIVRES;\nC/P: LIVRE.\nRINO: PERFURAÇÃO SEPTAL PEQUENA ANTERIOR COM CROSTAS.\n\n# TC DO PERSCOÇO (11/12/2015): LESÃO ÓSSEA NA MANDIBULA DIREITA, COM SINAIS DE MODERADA AGRESSIVIDADE LOCAL . CONSIDERAR AS POSSIBILIDADES DE LESÃO PRIMARIA (AMELOBLASTOMA ? TCG ?) OU MENOS PROVAVELMENTE SECUNDÁRIA. SUGERE-SE CORRELAÇÃO COM ESTUDO ANATOMOPATOLÓGICO\nBÓCIO TIREOIDIANO NODULAR.\n\n# A: LESÃO OSSEA DA MANDIBULA DIREITA (cisto dentigero, ameloblastoma, tu marrom ? sarcoma de mandibula ?)\n\n# P: SOLICITO AVALIAÇÃO DA NEFRO E CARDIO PARA LIBERAÇÃO CX,\nRETORNO APÓS AVALIAÇÃO.\nNO RETORNO COM AS LIBERAÇÕES AGENDAR HEMIMANDIBULECTOMIA DIREITA INTRA ORAL + LEVAR DRILL E CANETA.\nNÃO REALIZADO BIOPSIA SEPTAL HOJE POR FALTA DE MATERIAL ADEQUADO.\nBIOPSIAR SEPTO PROXIMA CONSULTA.\n\nR1 LUcas\nR2 Lucas\nR3 Lucas\nDoutor Vital Brazil ",
  "entities": {
    "Atividade de Assistência à Saúde": [
      "RETORNO",
      "ACOMPANHAMENTO",
      "O",
      "AVALIAÇÃO",
      "REALIZADO",
      "SOLICITO AVALIAÇÃO",
      "LIBERAÇÃO CX"
    ],
    "Abreviação": [
      "S",
      "HMP",
      "O",
      "ORO",
      "RINO",
      "TCG",
      "A",
      "P",
      "NEFRO",
      "CARDIO",
      "CORPO DE MANDIBULA DIR",
      "TRANSPLANTADA RENAL ESQ",
      "SUP E INF",
      "TC DO PERSCOÇO",
      "tu marrom",
      "LIBERAÇÃO CX"
    ],
    "Achado": [
      "S",
      "HMP",
      "LIVRE",
      "TRANSPLANTADA RENAL ESQ",
      "LINGUA E ASSOALHO LIVRES"
    ],
    "Paciente ou Grupo com Deficiência": [
      "PACIENTE"
    ],
    "Processo Neoplásico": [
      "TUMORAÇÃO",
      "AMELOBLASTOMA",
      "ameloblastoma",
      "tu marrom",
      "sarcoma de mandibula"
    ],
    "Parte do Corpo, Órgão ou Componente Orgânico": [
      "MANDÍBULA",
      "FACE",
      "CORPO DE MANDIBULA DIR",
      "CORPO E RAMO DIREITOS DE MANDIBULA"
    ],
    "Negação": [
      "INDOLOR",
      "NAO",
      "NEGA",
      "NÃO"
    ],
    "Sinal ou Sintoma": [
      "INDOLOR",
      "DISFAGIA",
      "PARESIAS",
      "PARESTESIAS",
      "EPISTAXE",
      "AUMENTA O VOLUME",
      "PRESENÇA DE MASSA ENDURECIDA"
    ],
    "Localização ou Região Corporal": [
      "FACE"
    ],
    "Doença ou Síndrome": [
      "TABAGISMO",
      "ALERGIAS",
      "HAS",
      "EDENTULISMO",
      "BÓCIO TIREOIDIANO NODULAR",
      "cisto dentigero"
    ],
    "Substância Farmacológica": [
      "IMUNODEPRESSORES"
    ],
    "Procedimento Diagnóstico": [
      "ORO",
      "RINO",
      "A",
      "TC DO PERSCOÇO",
      "ESTUDO ANATOMOPATOLÓGICO",
      "BIOPSIA SEPTAL"
    ],
    "Produto Intelectual": [
      "P"
    ],
    "Grupo Profissional ou Ocupacional": [
      "NEFRO",
      "CARDIO"
    ],
    "Conceito Temporal": [
      "APÓS"
    ],
    "Função Patológica": [
      "AUMENTA O VOLUME"
    ],
    "Procedimento Terapêutico ou Preventivo": [
      "TRANSPLANTADA RENAL ESQ",
      "HEMIMANDIBULECTOMIA DIREITA INTRA ORAL"
    ],
    "Conceito Espacial": [
      "SUP E INF"
    ],
    "Conceito Quantitativo": [
      "8 X 8CM"
    ],
    "Resultado Laboratorial ou de Teste": [
      "PERFURAÇÃO SEPTAL PEQUENA ANTERIOR COM CROSTAS",
      "LESÃO ÓSSEA NA MANDIBULA DIREITA",
      "SINAIS DE MODERADA AGRESSIVIDADE LOCAL",
      "BÓCIO TIREOIDIANO NODULAR"
    ],
    "Lesão ou Envenenamento": [
      "LESÃO OSSEA DA MANDIBULA DIREITA"
    ]
  },
  "labels": {
    "sarcoma de mandibula": {
      "capitulo": "02"
    },
    "lesão ossea da mandibula direita": {
      "capitulo": "02"
    }
  }
}