{
  "prontuario_id": 646,
  "text": "7:30 - 1º DI POR DISPNÉIA. PORTADOR DE FIBROSE PULMONAR.  CONSCIENTE, ORIENTADO, DISPNÉICO AOS ESFORÇOS, VERBALIZANDO, MANTENDO REPOUSO EM SEMI-FOLWER E AUXÍLIO DE O2 (5L/MIN)  EM MÁSCARA FACIAL. BCRNF, AP MV + BILATERAL, COM RONCOS EM BASE BILATERAL. ABDOMEN GLOBOSO, DEPRESSÍVEL, COM PERISTALTISMO PRESENTE. DIURESE ESPONTÂNEA PRESENTE. REFERE EVACUAÇÃO AUSENTE HÁ UM DIA. USO DE FRALDA DESCARTÁVEL. ORIENTO SOBRE REPOUSO NO LEITO. ACEITA DIETA OFERECIDA.  MANTÉM OXÍMETRO COM 91% SAT O2, 98 bpm, 140/90 mmHg, TEMP 35,9ºC.  SEGUE SOB CUIDADOS DA EQUIPE MULTIPROFISSIONAL. AGUARDA VAGA EM UI. SINDROME DO DESCONFORTO RESPIRATORIO DO ADULTO.",
  "entities": {
    "Sinal ou Sintoma": [
      "DISPNÉIA",
      "RONCOS",
      "DISPNÉICO AOS ESFORÇOS"
    ],
    "Achado": [
      "CONSCIENTE",
      "ORIENTADO",
      "VERBALIZANDO",
      "BCRNF",
      "GLOBOSO",
      "DEPRESSÍVEL",
      "PERISTALTISMO PRESENTE",
      "DIURESE ESPONTÂNEA PRESENTE"
    ],
    "Conceito Quantitativo": [
      "5L/MIN",
      "91%",
      "98 bpm",
      "140/90 mmHg",
      "35 , 9ºC"
    ],
    "Abreviação": [
      "BCRNF",
      "AP",
      "TEMP",
      "UI",
      "98 bpm"
    ],
    "Procedimento Diagnóstico": [
      "AP",
      "OXÍMETRO"
    ],
    "Conceito Espacial": [
      "BILATERAL"
    ],
    "Parte do Corpo, Órgão ou Componente Orgânico": [
      "ABDOMEN"
    ],
    "Função de Organismo": [
      "EVACUAÇÃO"
    ],
    "Negação": [
      "AUSENTE"
    ],
    "Procedimento Terapêutico ou Preventivo": [
      "DIETA",
      "REPOUSO EM SEMI-FOLWER",
      "AUXÍLIO DE O2",
      "REPOUSO NO LEITO"
    ],
    "Atributo Clínico": [
      "TEMP",
      "SAT O2"
    ],
    "Atividade de Assistência à Saúde": [
      "CUIDADOS"
    ],
    "Organização Relacionada à Saúde": [
      "UI",
      "EQUIPE MULTIPROFISSIONAL"
    ],
    "Doença ou Síndrome": [
      "FIBROSE PULMONAR",
      "SINDROME DO DESCONFORTO RESPIRATORIO DO ADULTO"
    ],
    "Dispositivo Médico": [
      "MÁSCARA FACIAL",
      "FRALDA DESCARTÁVEL"
    ],
    "Localização ou Região Corporal": [
      "BASE BILATERAL"
    ],
    "Conceito Temporal": [
      "UM DIA"
    ],
    "Objeto Manufaturado": [
      "FRALDA DESCARTÁVEL"
    ]
  },
  "labels": {
    "peristaltismo presente": {
      "capitulo": "01"
    },
    "fralda descartável": {
      "capitulo": "14"
    },
    "auxílio de o2": {
      "capitulo": "21"
    },
    "dieta": {
      "capitulo": "05"
    },
    "verbalizando": {
      "capitulo": "09"
    },
    "ui": {
      "capitulo": "07"
    },
    "repouso no leito": {
      "capitulo": "21"
    },
    "98 bpm": {
      "capitulo": "11"
    },
    "roncos": {
      "capitulo": "15"
    },
    "bilateral": {
      "capitulo": "16"
    },
    "base bilateral": {
      "capitulo": "17"
    },
    "sindrome do desconforto respiratorio do adulto": {
      "capitulo": "18"
    },
    "consciente": {
      "capitulo": "19"
    },
    "temp": {
      "capitulo": "20"
    },
    "máscara facial": {
      "capitulo": "21"
    },
    "depressível": {
      "capitulo": "22"
    },
    "oxímetro": {
      "capitulo": "23"
    },
    "dispnéico aos esforços": {
      "capitulo": "24"
    },
    "repouso em semi-folwer": {
      "capitulo": "25"
    },
    "globoso": {
      "capitulo": "26"
    },
    "140/90 mmhg": {
      "capitulo": "27"
    },
    "fibrose pulmonar": {
      "capitulo": "28"
    },
    "diurese espontânea presente": {
      "capitulo": "29"
    },
    "bcrnf": {
      "capitulo": "30"
    },
    "equipe multiprofissional": {
      "capitulo": "31"
    },
    "5l/min": {
      "capitulo": "32"
    },
    "35": {
      "capitulo": "33"
    },
    "9ºc": {
      "capitulo": "34"
    },
    "sat o2": {
      "capitulo": "35"
    },
    "evacuação": {
      "capitulo": "36"
    },
    "cuidados": {
      "capitulo": "37"
    },
    "ausente": {
      "capitulo": "38"
    },
    "dispnéia": {
      "capitulo": "39"
    },
    "ap": {
      "capitulo": "40"
    },
    "orientado": {
      "capitulo": "41"
    },
    "91%": {
      "capitulo": "42"
    },
    "abdomen": {
      "capitulo": "43"
    },
    "um dia": {
      "capitulo": "44"
    }
  }
}