{
  "prontuario_id": 677,
  "text": "8:30 - 3ºDI COM HX QUEDA DE NIVEL. INTERNA AOS CUIDADOS DA CLINICA MEDICA POR PA ELEVADA. FX 3ª COSTELA E. MANTEM REPOUSO NO LEITO, CALMA, CONFUSA, CORADA, EUPNEICA, MANTEM CATETER TIPO OCULOS 2 L/MIN, COMUNICATIVA, MANTEM CURATIVO EM REGIAO TEMPORAL E LIMPO E SECO EXTERNAMENTE. JUGULAR EXTERNA D COM  MEDICACAO EM CURSO, TRIDIL EM BI (1) 8ML/H. APRESENTA HIPEREMIA EM REGIAO CLAVICULAR E, PLEGIA MSE. SVD COM 100 ML DEBITO SEM GRUMOS. PARESIA MIE. RELATA ALGIA EM TORAX E E OMBRO E. BOA ACEITACAO ALIMENTAR. SEGUE SOB CUIDADOS E MONITORIZACAO CONTINUA. AGUARDO SOLITACAO DE VAGA DE UTI. Enfermeira Florence Nightingale. HIPERTENSAO ESSENCIAL PRIMARIA.",
  "entities": {
    "Conceito Temporal": [
      "3ºDI"
    ],
    "Abreviação": [
      "HX",
      "E",
      "BI",
      "MSE",
      "SVD",
      "MIE",
      "UTI",
      "PA ELEVADA",
      "FX 3ª COSTELA E",
      "JUGULAR EXTERNA D",
      "REGIAO CLAVICULAR E",
      "TORAX E",
      "OMBRO E"
    ],
    "Atividade de Assistência à Saúde": [
      "INTERNA",
      "CUIDADOS",
      "MONITORIZACAO CONTINUA"
    ],
    "Achado": [
      "CALMA",
      "CORADA",
      "EUPNEICA",
      "COMUNICATIVA",
      "LIMPO",
      "SECO",
      "REPOUSO NO LEITO",
      "BOA ACEITACAO ALIMENTAR"
    ],
    "Sinal ou Sintoma": [
      "CONFUSA",
      "HIPEREMIA",
      "PLEGIA",
      "GRUMOS",
      "PARESIA",
      "ALGIA",
      "PA ELEVADA"
    ],
    "Procedimento Terapêutico ou Preventivo": [
      "CURATIVO",
      "SVD",
      "REPOUSO NO LEITO",
      "CATETER TIPO OCULOS"
    ],
    "Dispositivo Médico": [
      "CURATIVO",
      "SVD",
      "CATETER TIPO OCULOS"
    ],
    "Conceito Espacial": [
      "E",
      "EXTERNAMENTE"
    ],
    "Conceito Qualitativo": [
      "LIMPO",
      "SECO"
    ],
    "Substância Farmacológica": [
      "MEDICACAO",
      "TRIDIL"
    ],
    "Substância Química Orgânica": [
      "TRIDIL"
    ],
    "Dispositivo de Administração de Medicamento": [
      "BI"
    ],
    "Parte do Corpo, Órgão ou Componente Orgânico": [
      "MSE",
      "MIE",
      "JUGULAR EXTERNA D"
    ],
    "Função de Organismo": [
      "DEBITO"
    ],
    "Negação": [
      "SEM"
    ],
    "Organização Relacionada à Saúde": [
      "VAGA",
      "UTI",
      "CLINICA MEDICA"
    ],
    "Grupo Profissional ou Ocupacional": [
      "Enfermeira"
    ],
    "Lesão ou Envenenamento": [
      "QUEDA DE NIVEL",
      "FX 3ª COSTELA E"
    ],
    "Conceito Quantitativo": [
      "2 L/MIN",
      "1 ) 8ML/H",
      "100 ML"
    ],
    "Localização ou Região Corporal": [
      "REGIAO TEMPORAL",
      "REGIAO CLAVICULAR E",
      "TORAX E",
      "OMBRO E"
    ],
    "Doença ou Síndrome": [
      "HIPERTENSAO ESSENCIAL PRIMARIA"
    ]
  },
  "labels": {
    "pa elevada": {
      "capitulo": "08.1"
    },
    "mse": {
      "capitulo": "06.1"
    },
    "corada": {
      "capitulo": "06.1"
    },
    "calma": {
      "capitulo": "06.1"
    },
    "confusa": {
      "capitulo": "06.1"
    },
    "eupneica": {
      "capitulo": "08.1"
    },
    "grumos": {
      "capitulo": "08.1"
    },
    "mie": {
      "capitulo": "08.1"
    },
    "paresia": {
      "capitulo": "08.1"
    },
    "queda de nivel": {
      "capitulo": "08.1"
    },
    "curativo": {
      "capitulo": "08.1"
    },
    "cateter tipo oculos": {
      "capitulo": "08.1"
    },
    "fx 3ª costela e": {
      "capitulo": "08.1"
    },
    "1 ) 8ml/h": {
      "capitulo": "08.1"
    },
    "100 ml": {
      "capitulo": "08.1"
    },
    "hipertensao essencial primaria": {
      "capitulo": "04.1"
    },
    "tridil": {
      "capitulo": "04.1"
    },
    "debito": {
      "capitulo": "08.1"
    },
    "regiao temporal": {
      "capitulo": "08.1"
    },
    "uti": {
      "capitulo": "04.1"
    },
    "hx": {
      "capitulo": "04.1"
    },
    "seco": {
      "capitulo": "04.1"
    },
    "limpo": {
      "capitulo": "04.1"
    },
    "vaga": {
      "capitulo": "04.1"
    },
    "monitorizacao continua": {
      "capitulo": "04.1"
    },
    "medicacao": {
      "capitulo": "04.1"
    },
    "enfermeira": {
      "capitulo": "06.1"
    },
    "comunicativa": {
      "capitulo": "06.1"
    },
    "boa aceitacao alimentar": {
      "capitulo": "05.8"
    }
  }
}