{
  "prontuario_id": 650,
  "text": "Interna para angioplastia seguida de implante de stent Driver em terço médio de coronária direita e stent Cypher em artéria segunda marginal. Procedimento realizado em 06/12/04 pelo Doutor Vital Brazil, sem intercorrências e com sucesso angiográfico. Recebe alta em bom estado geral, afebril, sinais vitais estáveis, sem sinais de hematoma ou pseudoaneurisma em local de punção e com boa perfusão de membros inferiores. Orientado a: - retorno à emergência se necessário. - retorno ao médico assistente em uma semana. - orientações gerais. - manter medicações em uso (orientado a usar plavix 75mg xdia por mais 3 meses e manter uso por tempo indefinido de AAS, angipress e medicações para dislipidemia).",
  "entities": {
    "Atividade de Assistência à Saúde": [
      "Interna",
      "alta",
      "Orientado",
      "retorno",
      "orientado",
      "orientações gerais",
      "manter medicações em uso",
      "manter uso"
    ],
    "Procedimento Terapêutico ou Preventivo": [
      "angioplastia",
      "Procedimento",
      "implante de stent Driver",
      "stent Cypher"
    ],
    "Grupo Profissional ou Ocupacional": [
      "Doutor",
      "médico médico assistente assistente"
    ],
    "Negação": [
      "sem",
      "afebril"
    ],
    "Sinal ou Sintoma": [
      "intercorrências",
      "afebril",
      "sinais",
      "hematoma"
    ],
    "Função Patológica": [
      "pseudoaneurisma"
    ],
    "Organização Relacionada à Saúde": [
      "emergência"
    ],
    "Substância Química Orgânica": [
      "plavix",
      "AAS"
    ],
    "Substância Farmacológica": [
      "plavix",
      "AAS",
      "angipress"
    ],
    "Abreviação": [
      "AAS"
    ],
    "Dispositivo Médico": [
      "stent Cypher"
    ],
    "Parte do Corpo, Órgão ou Componente Orgânico": [
      "artéria segunda marginal",
      "membros inferiores"
    ],
    "Achado": [
      "sucesso angiográfico",
      "bom bom estado estado geral geral",
      "sinais vitais estáveis",
      "boa perfusão"
    ],
    "Conceito Temporal": [
      "uma semana",
      "tempo indefinido"
    ],
    "Conceito Quantitativo": [
      "75mg xdia"
    ]
  },
  "labels": {
    "doutor": {
      "capitulo": "08.1"
    },
    "uma semana": {
      "capitulo": ""
    },
    "angioplastia": {
      "capitulo": "11.50.10.010"
    },
    "interna": {
      "capitulo": "24.40.10.010"
    },
    "membros inferiores": {
      "capitulo": "11.50.10.010"
    },
    "sinais": {
      "capitulo": "21.890.10.010"
    },
    "manter uso": {
      "capitulo": "24.40.10.010"
    },
    "emergência": {
      "capitulo": "24.40.10.010"
    },
    "implante de stent driver": {
      "capitulo": "11.50.10.010"
    },
    "alta": {
      "capitulo": "24.40.10.010"
    },
    "orientado": {
      "capitulo": "24.40.10.010"
    },
    "aas": {
      "capitulo": "24.40.10.010"
    },
    "retorno": {
      "capitulo": "24.40.10.010"
    },
    "75mg xdia": {
      "capitulo": "24.40.10.010"
    },
    "bom bom estado estado geral geral": {
      "capitulo": "21.890.10.010"
    },
    "médico médico assistente assistente": {
      "capitulo": "08.1"
    },
    "tempo indefinido": {
      "capitulo": "24.40.10.010"
    },
    "boa perfusão": {
      "capitulo": "11.50.10.010"
    },
    "sucesso angiográfico": {
      "capitulo": "11.50.10.010"
    },
    "procedimento": {
      "capitulo": "11.50.10.010"
    },
    "sinais vitais estáveis": {
      "capitulo": "11.50.10.010"
    },
    "hematoma": {
      "capitulo": "11.50.10.010"
    },
    "manter medicações em uso": {
      "capitulo": "24.40.10.010"
    },
    "orientações gerais": {
      "capitulo": "24.40.10.010"
    },
    "pseudoaneurisma": {
      "capitulo": "11.50.10.010"
    },
    "stent cypher": {
      "capitulo": "11.50.10.010"
    },
    "plavix": {
      "capitulo": "24.40.10.010"
    },
    "artéria segunda marginal": {
      "capitulo": "11.50.10.010"
    },
    "angipress": {
      "capitulo": "24.40.10.010"
    },
    "intercorrências": {
      "capitulo": "24.40.10.010"
    },
    "sem": {
      "capitulo": "24.40.10.010"
    },
    "afebril": {
      "capitulo": "21.890.10.010"
    }
  }
}