{
  "prontuario_id": 106,
  "text": "LUCAS, 57 anos.\n# IAM ântero-lateral 02/02: SK sem sucesso, disfunção ventricular e angina pós-infarto.\n # 2 IAMs prévios.\n # HAS .\n# DPOC.\n # DM2.\n # IC (FE 49% agosto/06).\n # Tabagista.\n Paciente interna para realização de cateterismo cardíaco pós IAM lateral no dia 02/02. Disfunção sistólica e angina pós-infarto. Exame mostrou e lesões severas em terço proximal e médio da ADA e lesão grave na ACD. Foi realizada ACTP + 2 stents no terço proximal e médio da ADA, e 1 stent no terço médio da ACD, sem intercorrências, com sucesso angiográfico fluxo TIMI III. Vinha em uso de ticlopidina prescrito pelo médico assistente. Após o procedimento, apresentou quadro de congestão pulmonar, recebendo diurético EV com boa resposta. Recebe alta após 24h de observação, em bom estado geral, assintomático, com recomendação de: - manter uso de ticlopidina 250mg de 12/12h por 30 dias - AAS 200mg /dia - sinvastatina 20mg /dia. Retorno em breve a seu médico assistente. Procurar a emergência em caso de intercorrência.",
  "entities": {
    "Substância Farmacológica": [
      "SK",
      "ticlopidina",
      "AAS",
      "sinvastatina",
      "diurético EV"
    ],
    "Abreviação": [
      "SK",
      "HAS",
      "DPOC",
      "DM2",
      "IC",
      "ADA",
      "ACD",
      "ACTP",
      "AAS",
      "IAM ântero-lateral",
      "FE 49%",
      "IAM lateral",
      "diurético EV"
    ],
    "Aminoácido, Peptídeo ou Proteína": [
      "SK"
    ],
    "Enzima": [
      "SK"
    ],
    "Negação": [
      "sem",
      "assintomático"
    ],
    "Achado": [
      "sucesso",
      "sucesso angiográfico",
      "boa resposta",
      "bom bom estado estado geral geral"
    ],
    "Sinal ou Sintoma": [
      "angina",
      "intercorrências",
      "quadro",
      "assintomático",
      "intercorrência"
    ],
    "Conceito Temporal": [
      "pós-infarto",
      "prévios",
      "Após",
      "após",
      "30 dias",
      "em breve"
    ],
    "Doença ou Síndrome": [
      "HAS",
      "DPOC",
      "DM2",
      "IC",
      "Tabagista",
      "IAM ântero-lateral",
      "IAM lateral",
      "Disfunção sistólica",
      "congestão pulmonar"
    ],
    "Atividade de Assistência à Saúde": [
      "interna",
      "realizada",
      "prescrito",
      "alta",
      "observação",
      "recomendação",
      "manter",
      "Retorno",
      "Procurar"
    ],
    "Procedimento Diagnóstico": [
      "Exame",
      "procedimento",
      "cateterismo cardíaco"
    ],
    "Parte do Corpo, Órgão ou Componente Orgânico": [
      "ADA",
      "ACD"
    ],
    "Procedimento Terapêutico ou Preventivo": [
      "ACTP",
      "procedimento",
      "cateterismo cardíaco"
    ],
    "Dispositivo Médico": [
      "stents",
      "stent"
    ],
    "Substância Química Orgânica": [
      "ticlopidina",
      "AAS",
      "sinvastatina"
    ],
    "Organização Relacionada à Saúde": [
      "emergência"
    ],
    "Resultado Laboratorial ou de Teste": [
      "disfunção ventricular",
      "FE 49%",
      "fluxo TIMI III"
    ],
    "Função Patológica": [
      "disfunção ventricular",
      "Disfunção sistólica"
    ],
    "Lesão ou Envenenamento": [
      "lesões severas",
      "lesão grave"
    ],
    "Classificação": [
      "fluxo TIMI III"
    ],
    "Grupo Profissional ou Ocupacional": [
      "médico assistente"
    ],
    "Conceito Quantitativo": [
      "200mg /dia",
      "20mg /dia"
    ]
  },
  "labels": {
    "iam lateral": {
      "capitulo": "110100-0"
    },
    "dpoc": {
      "capitulo": "120000-0"
    },
    "dm2": {
      "capitulo": "051000-0"
    },
    "ic": {
      "capitulo": "115100-0"
    },
    "tabagista": {
      "capitulo": "255000-0"
    },
    "cateterismo cardíaco": {
      "capitulo": "224000-0"
    },
    "stent": {
      "capitulo": "224000-0"
    },
    "lesões severas": {
      "capitulo": "224000-0"
    },
    "boa resposta": {
      "capitulo": "224000-0"
    },
    "interna": {
      "capitulo": "224000-0"
    },
    "disfunção ventricular": {
      "capitulo": "115100-0"
    },
    "angina": {
      "capitulo": "110100-0"
    },
    "congestão pulmonar": {
      "capitulo": "120000-0"
    },
    "diurético ev": {
      "capitulo": "224000-0"
    },
    "alta": {
      "capitulo": "224000-0"
    },
    "assintomático": {
      "capitulo": "224000-0"
    },
    "recomendação": {
      "capitulo": "224000-0"
    },
    "prescrito": {
      "capitulo": "224000-0"
    },
    "retorno": {
      "capitulo": "224000-0"
    },
    "médico assistente": {
      "capitulo": "224000-0"
    },
    "procurar": {
      "capitulo": "224000-0"
    },
    "em breve": {
      "capitulo": "224000-0"
    },
    "30 dias": {
      "capitulo": "224000-0"
    }
  }
}