{
  "prontuario_id": 995,
  "text": "# INSUFICIÊNCIA CARDÍACA DIASTÓLICA. # ACFA. # HAS. # INSUFICIÊNCIA VENOSA CRÔNICA. # EX-TABAGISTA.  PACIENTE COM MÚLTIPLAS INTERNAÇÕES POR EXACERBAÇÃO DE INSUFICIÊNCIA CARDÍACA SECUNDÁRIAS A FIBRILAÇÃO ATRIAL COM ALTA RESPOSTA E A MÁ ADERÊNCIA AO TRATAMENTO, COM DIFICULDADE DE COMPREENSÃO E AFASIA DE EXPRESSÃO. TRAZIDA A EMERGÊNCIA POR PIORA PROGRESSIVA DE DIPNÉIA, ORTOPNÉIA E EDEMA. INSTITUÍDO TRATAMENTO PARA INSUFICIÊNCIA CARDÍACA DESCOMPENSADA, APRESENTANDO MELHORA DOS SINTOMAS. DEVIDO ÀS MÚLTIPLAS INTERNAÇÕES POR EXACERBAÇÃO SECUNDÁRIA A FIBRILAÇÃO ATRIAL FOI OPTADO POR REALIZAR ABLAÇÃO DE NODO AV. A PACIENTE FOI SUBMETIDA A COLOCAÇÃO DE MARCAPASSO DEFINITIVO E UM DIA APÓS, FOI REALIZADA A  ABLAÇÃO DE NODO AV. O PROCEDIMENTO OCOREU SEM INTERCORRÊNCIAS. ANTES DA ALTA FOI AVALIADO FUNCIONAMENTO DO MARCA-PASSO, QUE FICOU PROGRAMADO PARA 80 BPM. RECEBE ALTA HEMODINAMICAMENTE ESTÁVEL, SEM DISPNÉIA OU DOR TORÁCICA, COM AUSCULTA PULMONAR LIMPA E SEM EDEMA. RECEBEU ENCAMINHAMENTO PARA CONSULTA AMBULATORIAL NESSE HOSPITAL E RECEITA DAS MEDICAÇÕES QUE DEVERÁ SEGUIR TOMANDO.  MEDICAÇÕES: * CAPTOPRIL 25 MG - TOMAR 02 CP VO DE 12/12 HORAS. * FUROSEMIDA 40 MG - TOMAR 01 CP VO ÁS 8H E ÁS 14 H. * OMEPRAZOL 20 MG - TOMAR 01 CP VO PELA MANHÃ. * SINVASTATINA 40 MG - TOMAR 01 CP VO À NOITE. * AAS 100 MG - TOMAR 02 CP VO NO ALMOÇO.",
  "entities": {
    "Resultado Laboratorial ou de Teste": [
      "ACFA"
    ],
    "Abreviação": [
      "ACFA",
      "HAS",
      "AAS",
      "ABLAÇÃO DE NODO AV",
      "80 BPM",
      "TOMAR 02 CP VO",
      "TOMAR 01 CP VO"
    ],
    "Doença ou Síndrome": [
      "ACFA",
      "HAS",
      "INSUFICIÊNCIA CARDÍACA DIASTÓLICA",
      "INSUFICIÊNCIA VENOSA CRÔNICA",
      "FIBRILAÇÃO ATRIAL COM ALTA RESPOSTA",
      "INSUFICIÊNCIA CARDÍACA DESCOMPENSADA",
      "FIBRILAÇÃO ATRIAL"
    ],
    "Achado": [
      "EX-TABAGISTA",
      "LIMPA",
      "MÚLTIPLAS INTERNAÇÕES",
      "MÁ ADERÊNCIA",
      "MELHORA DOS SINTOMAS",
      "HEMODINAMICAMENTE ESTÁVEL"
    ],
    "Procedimento Terapêutico ou Preventivo": [
      "TRATAMENTO",
      "PROCEDIMENTO",
      "ABLAÇÃO DE NODO AV",
      "COLOCAÇÃO DE MARCAPASSO DEFINITIVO",
      "TOMAR 02 CP VO",
      "TOMAR 01 CP VO"
    ],
    "Organização Relacionada à Saúde": [
      "EMERGÊNCIA",
      "HOSPITAL",
      "CONSULTA AMBULATORIAL"
    ],
    "Sinal ou Sintoma": [
      "ORTOPNÉIA",
      "EDEMA",
      "INTERCORRÊNCIAS",
      "DISPNÉIA",
      "EXACERBAÇÃO DE INSUFICIÊNCIA CARDÍACA",
      "DIFICULDADE DE COMPREENSÃO",
      "PIORA PROGRESSIVA DE DIPNÉIA",
      "DOR TORÁCICA"
    ],
    "Atividade de Assistência à Saúde": [
      "REALIZAR",
      "SUBMETIDA",
      "ALTA",
      "ENCAMINHAMENTO",
      "RECEITA DAS MEDICAÇÕES"
    ],
    "Procedimento Diagnóstico": [
      "PROCEDIMENTO",
      "AUSCULTA PULMONAR"
    ],
    "Negação": [
      "SEM"
    ],
    "Conceito Temporal": [
      "ANTES",
      "MANHÃ",
      "NOITE",
      "ALMOÇO",
      "ÁS 8H",
      "14 H"
    ],
    "Conceito Qualitativo": [
      "LIMPA"
    ],
    "Objeto Manufaturado": [
      "HOSPITAL"
    ],
    "Substância Farmacológica": [
      "MEDICAÇÕES",
      "CAPTOPRIL",
      "FUROSEMIDA",
      "OMEPRAZOL",
      "SINVASTATINA",
      "AAS"
    ],
    "Aminoácido, Peptídeo ou Proteína": [
      "CAPTOPRIL"
    ],
    "Substância Química Orgânica": [
      "FUROSEMIDA",
      "OMEPRAZOL",
      "SINVASTATINA",
      "AAS"
    ],
    "Disfunção Mental ou Comportamental": [
      "DIFICULDADE DE COMPREENSÃO",
      "AFASIA DE EXPRESSÃO"
    ],
    "Atividade de Máquina": [
      "FUNCIONAMENTO DO MARCA-PASSO"
    ],
    "Conceito Quantitativo": [
      "80 BPM",
      "25 MG",
      "12/12 HORAS",
      "40 MG",
      "20 MG",
      "100 MG"
    ]
  },
  "labels": {
    "afasia de expressão": {
      "capitulo": "08"
    },
    "consulta ambulatorial": {
      "capitulo": "24"
    },
    "fibrilação atrial": {
      "capitulo": "11"
    },
    "captopril": {
      "capitulo": "24"
    },
    "edema": {
      "capitulo": "11"
    },
    "melhora dos sintomas": {
      "capitulo": "24"
    },
    "hemodinamicamente estável": {
      "capitulo": "24"
    },
    "encaminhamento": {
      "capitulo": "24"
    },
    "manhã": {
      "capitulo": "24"
    },
    "omeprazol": {
      "capitulo": "24"
    },
    "emergência": {
      "capitulo": "24"
    },
    "limpa": {
      "capitulo": "24"
    },
    "medicações": {
      "capitulo": "24"
    },
    "20 mg": {
      "capitulo": "24"
    },
    "aas": {
      "capitulo": "24"
    },
    "alta": {
      "capitulo": "24"
    },
    "funcionamento do marca-passo": {
      "capitulo": "24"
    },
    "tratamento": {
      "capitulo": "24"
    },
    "dispnéia": {
      "capitulo": "12"
    },
    "dificuldade de compreensão": {
      "capitulo": "08"
    },
    "80 bpm": {
      "capitulo": "11"
    },
    "fibrilação atrial com alta resposta": {
      "capitulo": "11"
    },
    "múltiplas internações": {
      "capitulo": "24"
    },
    "ablação de nodo av": {
      "capitulo": "11"
    },
    "hospital": {
      "capitulo": "24"
    },
    "insuficiência venosa crônica": {
      "capitulo": "11"
    },
    "procedimento": {
      "capitulo": "24"
    },
    "ortopnéia": {
      "capitulo": "12"
    },
    "furosemida": {
      "capitulo": "11"
    },
    "má aderência": {
      "capitulo": "24"
    },
    "colocação de marcapasso definitivo": {
      "capitulo": "11"
    },
    "sinvastatina": {
      "capitulo": "24"
    },
    "insuficiência cardíaca descompensada": {
      "capitulo": "11"
    },
    "acfa": {
      "capitulo": "24"
    },
    "antes": {
      "capitulo": "24"
    },
    "noite": {
      "capitulo": "24"
    },
    "12/12 horas": {
      "capitulo": "24"
    },
    "submetida": {
      "capitulo": "24"
    },
    "40 mg": {
      "capitulo": "24"
    },
    "exacerbação de insuficiência cardíaca": {
      "capitulo": "11"
    },
    "has": {
      "capitulo": "24"
    },
    "insuficiência cardíaca diastólica": {
      "capitulo": "11"
    },
    "receita das medicações": {
      "capitulo": "24"
    },
    "ausculta pulmonar": {
      "capitulo": "24"
    },
    "ás 8h": {
      "capitulo": "24"
    },
    "tomar 02 cp vo": {
      "capitulo": "24"
    },
    "100 mg": {
      "capitulo": "24"
    },
    "tomar 01 cp vo": {
      "capitulo": "24"
    },
    "25 mg": {
      "capitulo": "24"
    },
    "intercorrências": {
      "capitulo": "24"
    },
    "dor torácica": {
      "capitulo": "12"
    },
    "ex-tabagista": {
      "capitulo": "24"
    },
    "sem": {
      "capitulo": "24"
    },
    "realizar": {
      "capitulo": "24"
    },
    "almoço": {
      "capitulo": "24"
    }
  }
}