{
  "prontuario_id": 370,
  "text": "Lucas, 70 ANOS\n# EM ACOMPANHAMENTO POR DSCC E FACE\nS # PACIENTE RELATA PRURIDO E DESCAMAÇÃO EM COURO CABELUDO. HÁ 1 MÊS NÃO USA O SHAMPOO DE CETOCONAZOL\nESTÁ EM USO DE SHAMPOO QUE COMPRA NA FARMÁCIA (CLEAR ANTICASPA). NEGA OUTRAS QUEIXAS.\nO # \n1- PEQUENAS PLACAS ERITEMATO DESCAMATIVAS EM BRAÇOS E MÃOS\n2- POUCA DESCAMAÇÃO EM COURO CABELUDO.\nSEM OUTRAS LESÕES SUSPEITAS\nA # \n1- CERATOSES ACTÍNICAS\n2- DSCC\nP # \nCRIO NAS CERATOSES ACTINICAS DE MÃOS E BRAÇOS.\nTHERAPSOR SOLUÇÃO 8 GOTAS NO COURO CABELUDO 1 X POR SEMANA\nCETOCONAZOL SHAMPOO 2% 3X SEMANA\nORIENTO FPS 3X DIA.\nRETORNO EM 4 MESES.\n\nESTAGIÁRIA Lucas\nDoutor Vital Brazil \n \n \n \n ",
  "entities": {
    "Atividade de Assistência à Saúde": [
      "ACOMPANHAMENTO",
      "USA",
      "ORIENTO",
      "RETORNO"
    ],
    "Abreviação": [
      "DSCC",
      "CRIO",
      "FPS",
      "1 X POR SEMANA",
      "3X SEMANA"
    ],
    "Paciente ou Grupo com Deficiência": [
      "PACIENTE"
    ],
    "Sinal ou Sintoma": [
      "PRURIDO",
      "DESCAMAÇÃO",
      "QUEIXAS",
      "PLACAS ERITEMATO DESCAMATIVAS",
      "LESÕES SUSPEITAS"
    ],
    "Negação": [
      "NÃO",
      "NEGA",
      "SEM"
    ],
    "Substância": [
      "SHAMPOO"
    ],
    "Organização Relacionada à Saúde": [
      "FARMÁCIA"
    ],
    "Substância Farmacológica": [
      "ANTICASPA",
      "SHAMPOO DE CETOCONAZOL",
      "THERAPSOR SOLUÇÃO",
      "CETOCONAZOL SHAMPOO 2%"
    ],
    "Conceito Qualitativo": [
      "PEQUENAS",
      "POUCA"
    ],
    "Parte do Corpo, Órgão ou Componente Orgânico": [
      "BRAÇOS",
      "MÃOS"
    ],
    "Procedimento Terapêutico ou Preventivo": [
      "CRIO"
    ],
    "Conceito Temporal": [
      "MESES"
    ],
    "Grupo Profissional ou Ocupacional": [
      "ESTAGIÁRIA"
    ],
    "Localização ou Região Corporal": [
      "COURO CABELUDO"
    ],
    "Substância Química Orgânica": [
      "SHAMPOO DE CETOCONAZOL",
      "THERAPSOR SOLUÇÃO",
      "CETOCONAZOL SHAMPOO 2%"
    ],
    "Doença ou Síndrome": [
      "CERATOSES ACTÍNICAS",
      "CERATOSES ACTINICAS"
    ],
    "Conceito Quantitativo": [
      "1 X POR SEMANA",
      "3X SEMANA"
    ]
  },
  "labels": {
    "ceratoses actinicas": {
      "capitulo": "14.0"
    },
    "dscc": {
      "capitulo": "14.0"
    },
    "queixas": {
      "capitulo": "24.1"
    },
    "couro cabeludo": {
      "capitulo": "14.0"
    },
    "paciente": {
      "capitulo": "24.1"
    },
    "pouca": {
      "capitulo": "21.1"
    },
    "pequenas": {
      "capitulo": "21.1"
    },
    "cetoconazol shampoo 2%": {
      "capitulo": "14.0"
    },
    "ceratoses actínicas": {
      "capitulo": "14.0"
    },
    "acompanhamento": {
      "capitulo": "24.1"
    },
    "mãos": {
      "capitulo": "14.0"
    },
    "crio": {
      "capitulo": "24.1"
    },
    "braços": {
      "capitulo": "14.0"
    },
    "prurido": {
      "capitulo": "21.1"
    },
    "descamação": {
      "capitulo": "21.1"
    },
    "placas eritemato descamativas": {
      "capitulo": "21.1"
    },
    "shampoo de cetoconazol": {
      "capitulo": "14.0"
    },
    "anticaspa": {
      "capitulo": "24.1"
    },
    "therapsor solução": {
      "capitulo": "24.1"
    },
    "fps": {
      "capitulo": "24.1"
    },
    "retorno": {
      "capitulo": "24.1"
    }
  }
}