{
  "prontuario_id": 869,
  "text": "1a CONSULTA\nPaciente com história, há 3 anos, de cefaleia hemicraniana D contínua intensa \" em aperto \" em trajeto de nervo occipital D, com piora há 2 anos. Relata uso de toxina butolínica de 3 em 3 meses, há 1 ano, em acompanhamento no HC.\nRefere que cefaleia se acompanha de crises convulsivas mistas, eventualmente.\nMae relata quadros frequentes de crises (convulsivas ?) com quedas frequentes da propria altura, associado a comportamentos estranhos\n(engolir moeda, enfiar agulha) e crises de memória.\nFicou internada, há 2 meses, no HUC para investigação de Epilepsia, resultando em diagnóstico de Crise Psicogênica. EEG não compatível com epilepsia.\nEm acompanhamento com o serviço de neurologia e Psiquiatria do HC.\n- Cx aos 7 anos por cardiopatia\n- Nega alterações na família\n- FIbromialgia\n- MUC: Frizium 20mg 0-0-1; Topiramato 50mg 1/2-0-/12; Gabapentina 300mg 2-2-2; Indometacina 50mg 1-1-1; Fluoxetina 20mg 1-0-1;\nTramadol 50mg 1-1-1; Ciclo 21; Clorpromazina 25mg 12/12hrs\n# Ao exame:\n- LOTE, Glasgow 15, sem alt de linguagem\n- Dor a palpação de Nervo Occipital Menor, com síncope a toque superficial.\n- NC sem alts\n- Forca grau 5 global; hiperreflexia global; cutano-plantar indiferente\n- Coordenação, equilibrio e marcha sem alts\nConduta: \n1: Realizado Bloqueio de Nervo Occipital Maior D com Dexametasona 1ml + Lidocaína 2ml. Paciente responde com hipoestesia local, sem melhora significativa da cefaleia.\n2: Pacient não candidata a procedimento cirúrgico (Doutor Vital Brazil contacta Doutor Vital Brazil).\n3: Alta do serviço de Neurocirurgia.\n \n \n \n ",
  "entities": {
    "Atividade de Assistência à Saúde": [
      "CONSULTA",
      "acompanhamento",
      "internada",
      "investigação",
      "Conduta",
      "Realizado",
      "Alta"
    ],
    "Paciente ou Grupo com Deficiência": [
      "Paciente",
      "Pacient"
    ],
    "Conceito Qualitativo": [
      "intensa",
      "frequentes",
      "melhora"
    ],
    "Sinal ou Sintoma": [
      "cefaleia",
      "quedas",
      "alterações",
      "síncope",
      "alts",
      "hipoestesia",
      "crises ( convulsivas",
      "comportamentos estranhos",
      "crises de memória",
      "hiperreflexia global"
    ],
    "Grupo Familiar": [
      "Mae",
      "família"
    ],
    "Organização Relacionada à Saúde": [
      "HUC",
      "HC"
    ],
    "Doença ou Síndrome": [
      "Epilepsia",
      "epilepsia",
      "cardiopatia",
      "FIbromialgia",
      "cefaleia",
      "cefaleia hemicraniana D",
      "crises convulsivas mistas",
      "Crise Psicogênica"
    ],
    "Abreviação": [
      "EEG",
      "HC",
      "Cx",
      "MUC",
      "LOTE",
      "NC",
      "alts",
      "cefaleia hemicraniana D",
      "nervo occipital D",
      "Bloqueio de Nervo Occipital Maior D"
    ],
    "Procedimento Diagnóstico": [
      "EEG",
      "palpação"
    ],
    "Negação": [
      "não",
      "Nega",
      "sem"
    ],
    "Grupo Profissional ou Ocupacional": [
      "neurologia",
      "Psiquiatria",
      "Doutor",
      "Neurocirurgia"
    ],
    "Procedimento Terapêutico ou Preventivo": [
      "Cx",
      "cirúrgico",
      "Bloqueio de Nervo Occipital Maior D"
    ],
    "Substância Química Orgânica": [
      "Frizium",
      "Topiramato",
      "Gabapentina",
      "Indometacina",
      "Fluoxetina",
      "Tramadol",
      "Clorpromazina",
      "Lidocaína"
    ],
    "Substância Farmacológica": [
      "Frizium",
      "Topiramato",
      "Gabapentina",
      "Indometacina",
      "Fluoxetina",
      "Tramadol",
      "Clorpromazina",
      "Lidocaína",
      "toxina butolínica",
      "Ciclo 21"
    ],
    "Conceito Quantitativo": [
      "20mg",
      "50mg",
      "300mg",
      "25mg",
      "1ml",
      "2ml"
    ],
    "Achado": [
      "LOTE",
      "linguagem",
      "Coordenação",
      "equilibrio",
      "marcha",
      "Glasgow 15",
      "Forca grau 5 global",
      "cutano-plantar indiferente"
    ],
    "Parte do Corpo, Órgão ou Componente Orgânico": [
      "NC",
      "nervo occipital D",
      "Nervo Occipital Menor"
    ],
    "Conceito Espacial": [
      "local"
    ],
    "Conceito Temporal": [
      "há 3 anos",
      "há 2 anos",
      "3 em 3 meses",
      "há 1 ano",
      "há 2 meses"
    ],
    "Aminoácido, Peptídeo ou Proteína": [
      "toxina butolínica"
    ],
    "Disfunção Mental ou Comportamental": [
      "comportamentos estranhos",
      "engolir moeda",
      "enfiar agulha"
    ]
  },
  "labels": {
    "crise psicogênica": {
      "capitulo": "6A40"
    },
    "epilepsia": {
      "capitulo": "6A03"
    },
    "engolir moeda": {
      "capitulo": "25.84.81"
    },
    "paciente": {
      "capitulo": "25.84.81"
    },
    "bloqueio de nervo occipital maior d": {
      "capitulo": "850.01"
    },
    "pacient": {
      "capitulo": "25.84.81"
    },
    "fibromialgia": {
      "capitulo": "6A40"
    },
    "consulta": {
      "capitulo": "25.84.81"
    },
    "melhora": {
      "capitulo": "25.84.81"
    },
    "toxina butolínica": {
      "capitulo": "25.84.81"
    },
    "20mg": {
      "capitulo": "25.84.81"
    },
    "topiramato": {
      "capitulo": "25.84.81"
    },
    "3 em 3 meses": {
      "capitulo": "25.84.81"
    },
    "alterações": {
      "capitulo": "25.84.81"
    },
    "neurocirurgia": {
      "capitulo": "25.84.81"
    },
    "2ml": {
      "capitulo": "25.84.81"
    },
    "palpação": {
      "capitulo": "25.84.81"
    },
    "frizium": {
      "capitulo": "25.84.81"
    },
    "investigação": {
      "capitulo": "25.84.81"
    },
    "doutor": {
      "capitulo": "25.84.81"
    },
    "cefaleia hemicraniana d": {
      "capitulo": "850.01"
    },
    "coordenação": {
      "capitulo": "25.84.81"
    },
    "intensa": {
      "capitulo": "25.84.81"
    },
    "realizado": {
      "capitulo": "25.84.81"
    },
    "clorpromazina": {
      "capitulo": "25.84.81"
    },
    "hipoestesia": {
      "capitulo": "25.84.81"
    },
    "tramadol": {
      "capitulo": "25.84.81"
    },
    "comportamentos estranhos": {
      "capitulo": "25.84.81"
    },
    "cutano-plantar indiferente": {
      "capitulo": "25.84.81"
    },
    "indometacina": {
      "capitulo": "25.84.81"
    },
    "não": {
      "capitulo": "25.84.81"
    },
    "forca grau 5 global": {
      "capitulo": "25.84.81"
    },
    "lidocaína": {
      "capitulo": "25.84.81"
    },
    "gabapentina": {
      "capitulo": "25.84.81"
    },
    "marcha": {
      "capitulo": "25.84.81"
    },
    "hiperreflexia global": {
      "capitulo": "25.84.81"
    },
    "enfiar agulha": {
      "capitulo": "25.84.81"
    },
    "muc": {
      "capitulo": "25.84.81"
    },
    "há 2 meses": {
      "capitulo": "25.84.81"
    },
    "nervo occipital d": {
      "capitulo": "850.01"
    },
    "huc": {
      "capitulo": "25.84.81"
    },
    "300mg": {
      "capitulo": "25.84.81"
    },
    "equilibrio": {
      "capitulo": "25.84.81"
    },
    "quedas": {
      "capitulo": "25.84.81"
    },
    "ciclo 21": {
      "capitulo": "25.84.81"
    },
    "cx": {
      "capitulo": "25.84.81"
    },
    "cefaleia": {
      "capitulo": "850.01"
    },
    "lote": {
      "capitulo": "25.84.81"
    },
    "nervo occipital menor": {
      "capitulo": "850.01"
    },
    "psiquiatria": {
      "capitulo": "25.84.81"
    },
    "há 1 ano": {
      "capitulo": "25.84.81"
    },
    "internada": {
      "capitulo": "25.84.81"
    },
    "nc": {
      "capitulo": "25.84.81"
    },
    "glasgow 15": {
      "capitulo": "25.84.81"
    },
    "eeg": {
      "capitulo": "25.84.81"
    },
    "1ml": {
      "capitulo": "25.84.81"
    }
  }
}