{
  "prontuario_id": 820,
  "text": "# Lucas, 80 anos\n# HAS / HIPOTIREOIDISMO\n# PCTE EM ACOMPANHAMENTO POR QUADRO DE TINEA PEDIS + ONICOMICOSE\n   - EM USO DE URÉIA 40% NAS UNHAS E FENTIZOL CREME NOS PÉS\n** NAO TROUXE EXAMES LAB ***\n# PCTE NEGA MELHORA DO QUADRO. \n   REFERE SURGIMENTO DE LESÕES HIPOCRÔMICAS EM MMSS E DORSO, COM DESCAMAÇÃO FINA SUPERFICIAL. \n# AO EXAME:\nDESCAMAÇÃO SUPERFICIAL COURO CABELUDO\nMÁCULAS HIPOCRÔMICAS EM DORSO E MMSS, COM DESCAMAÇÃO SUPERFICIAL. ZILERI POSITIVO\nDESCAMAÇÃO PLANTAR E MACERAÇÃO INTERDIGITAL BILATERAL\nHIPERCERATOSE UNGUEAL, ONICODISTROFIA, ONICOLISE DISTAL, UNHAS AMARELADAS\n# A: PTIRIASE VERSICOLOR\n   TINEA PEDIS + ONICOMICOSE\n# P: CETOCONAZOL 2% SHAMPOO + ICADEN SPRAY PARA PV\n  UREIA 35% + AC SALICILICO 2% + CREME 50GR NAS UNHAS\n  CETOC 2% + MANT KARITE + UREIA 10% EM CREME PARA OS PÉS\n  RET EM 3 MESES COM LAB. \n\n \n \n \n ",
  "entities": {
    "Doença ou Síndrome": [
      "HIPOTIREOIDISMO",
      "HIPERCERATOSE",
      "ONICODISTROFIA"
    ],
    "Paciente ou Grupo com Deficiência": [
      "PCTE"
    ],
    "Abreviação": [
      "PCTE",
      "MMSS",
      "AC SALICILICO"
    ],
    "Atividade de Assistência à Saúde": [
      "ACOMPANHAMENTO"
    ],
    "Parte do Corpo, Órgão ou Componente Orgânico": [
      "PÉS",
      "COURO CABELUDO"
    ],
    "Negação": [
      "NAO",
      "NEGA"
    ],
    "Conceito Qualitativo": [
      "MELHORA"
    ],
    "Localização ou Região Corporal": [
      "MMSS",
      "DORSO",
      "PLANTAR",
      "UNGUEAL"
    ],
    "Sinal ou Sintoma": [
      "ONICOLISE",
      "LESÕES HIPOCRÔMICAS",
      "DESCAMAÇÃO FINA SUPERFICIAL",
      "DESCAMAÇÃO SUPERFICIAL",
      "MÁCULAS HIPOCRÔMICAS",
      "UNHAS AMARELADAS"
    ],
    "Conceito Espacial": [
      "DISTAL"
    ],
    "Substância Farmacológica": [
      "CREME",
      "FENTIZOL CREME",
      "ICADEN SPRAY",
      "AC SALICILICO"
    ],
    "Conceito Quantitativo": [
      "3"
    ],
    "Conceito Temporal": [
      "MESES"
    ],
    "Procedimento Laboratorial": [
      "LAB"
    ],
    "Substância Química Orgânica": [
      "FENTIZOL CREME",
      "ICADEN SPRAY"
    ]
  },
  "labels": {
    "pés": {
      "capitulo": "14.1"
    },
    "couro cabeludo": {
      "capitulo": "14.1"
    },
    "hipotireoidismo": {
      "capitulo": "05.1"
    },
    "descamação superficial": {
      "capitulo": "14.1"
    },
    "lab": {
      "capitulo": "21.1"
    },
    "nao": {
      "capitulo": "21.1"
    },
    "mmss": {
      "capitulo": "14.1"
    },
    "descamação fina superficial": {
      "capitulo": "14.1"
    },
    "unhas amareladas": {
      "capitulo": "14.1"
    },
    "ac salicilico": {
      "capitulo": "14.1"
    },
    "plantar": {
      "capitulo": "14.1"
    },
    "fentizol creme": {
      "capitulo": "14.1"
    },
    "pcte": {
      "capitulo": "21.1"
    },
    "melhora": {
      "capitulo": "21.1"
    },
    "nega": {
      "capitulo": "21.1"
    },
    "hiperceratose": {
      "capitulo": "14.1"
    },
    "onicodistrofia": {
      "capitulo": "14.1"
    },
    "3": {
      "capitulo": "21.1"
    }
  }
}