{
  "prontuario_id": 149,
  "text": "# RETORNO\n# 84 ANOS \n# TONTURA + HIPOACUSIA BILATERAL\n\nPACIENTE REFERE TONTURA E HIPOACUSIA BILTERAL EVOLUTIVA (HÁ MAIS DE 20 ANOS) \n\nEXAMES: \n1) AUDIOMETRIA: PERDA AUDITIVA SENSORIAL DE GRAU MODERADO / SEVERA A DIREITA E DE GRAU MODERADO A ESQUERDA, DESCENDENTE BILATERALMENTE\n2) TRIGLICERIDEO: 183 (<150)\n3) CT: 217 (<200)\n\nMEDICAMETOS EM USO:\n1) SERTRALINA\n2) SULPIRIDA\n3) ATENOLOL \n4) VIT D\n\nHD: \n1) PRESBIACUSIA\n2) TONTURA ORTOSTATICA ( CARDIOLÓGICA ?)\n \nCD:\n1) CONTROLE COLESTEROL\n2) PROTESE AUDITIVA (ESTÍMULO) \n3) AVALIAR USO DE ATENOLOL EM POSTO DE SAUDE ( TONTURA )\n4) TREINAMENTO TONTURA \n\nREAVALIAR EM RETORNO:\n1) MELHORA DA TONTURA, TINITUS E SE ESTÁ USANDO A PROTESE CONSTATEMENTE. \n\nR2 Doutor Vital Brazil\n \n \n \n ",
  "entities": {
    "Atividade de Assistência à Saúde": [
      "RETORNO",
      "CD",
      "CONTROLE",
      "AVALIAR",
      "TREINAMENTO",
      "REAVALIAR"
    ],
    "Sinal ou Sintoma": [
      "TONTURA",
      "TINITUS",
      "HIPOACUSIA BILATERAL",
      "HIPOACUSIA BILTERAL"
    ],
    "Paciente ou Grupo com Deficiência": [
      "PACIENTE"
    ],
    "Conceito Temporal": [
      "EVOLUTIVA"
    ],
    "Procedimento Diagnóstico": [
      "EXAMES",
      "AUDIOMETRIA"
    ],
    "Procedimento Laboratorial": [
      "EXAMES",
      "TRIGLICERIDEO",
      "CT"
    ],
    "Conceito Quantitativo": [
      "183",
      "217"
    ],
    "Abreviação": [
      "CT",
      "CD",
      "R2",
      "VIT D HD"
    ],
    "Substância Farmacológica": [
      "MEDICAMETOS",
      "SERTRALINA",
      "SULPIRIDA",
      "ATENOLOL",
      "VIT D HD"
    ],
    "Substância Química Orgânica": [
      "SERTRALINA",
      "SULPIRIDA",
      "ATENOLOL",
      "COLESTEROL",
      "VIT D HD"
    ],
    "Função Patológica": [
      "PRESBIACUSIA"
    ],
    "Substância Biologicamente Ativa": [
      "COLESTEROL"
    ],
    "Dispositivo Médico": [
      "PROTESE",
      "PROTESE AUDITIVA"
    ],
    "Grupo Profissional ou Ocupacional": [
      "R2",
      "Doutor"
    ],
    "Resultado Laboratorial ou de Teste": [
      "PERDA AUDITIVA SENSORIAL DE GRAU MODERADO",
      "SEVERA A DIREITA",
      "GRAU MODERADO A ESQUERDA",
      "DESCENDENTE BILATERALMENTE",
      "VIT D HD"
    ],
    "Vitamina": [
      "VIT D HD"
    ],
    "Doença ou Síndrome": [
      "TONTURA ORTOSTATICA"
    ],
    "Organização Relacionada à Saúde": [
      "POSTO DE SAUDE"
    ]
  },
  "labels": {
    "triglicerideo": {
      "capitulo": "25.1.10.1000"
    },
    "protese auditiva": {
      "capitulo": "10.1.10.1000"
    },
    "doutor": {
      "capitulo": "21.1.10.1000"
    },
    "hipoacusia bilateral": {
      "capitulo": "10.1.10.1000"
    },
    "colesterol": {
      "capitulo": "25.1.10.1000"
    },
    "paciente": {
      "capitulo": "21.1.10.1000"
    },
    "evolutiva": {
      "capitulo": "21.1.10.1000"
    },
    "controle": {
      "capitulo": "21.1.10.1000"
    },
    "audiometria": {
      "capitulo": "10.1.10.1000"
    },
    "ct": {
      "capitulo": "21.1.10.1000"
    },
    "perda auditiva sensorial de grau moderado": {
      "capitulo": "10.1.10.1000"
    },
    "sertralina": {
      "capitulo": "21.1.10.1000"
    },
    "atenolol": {
      "capitulo": "21.1.10.1000"
    },
    "retorno": {
      "capitulo": "21.1.10.1000"
    },
    "treinamento": {
      "capitulo": "21.1.10.1000"
    },
    "reavaliar": {
      "capitulo": "21.1.10.1000"
    },
    "descendente bilateralmente": {
      "capitulo": "21.1.10.1000"
    },
    "tontura": {
      "capitulo": "21.1.10.1000"
    },
    "vit d hd": {
      "capitulo": "21.1.10.1000"
    },
    "posto de saude": {
      "capitulo": "21.1.10.1000"
    },
    "cd": {
      "capitulo": "21.1.10.1000"
    },
    "presbiacusia": {
      "capitulo": "21.1.10.1000"
    },
    "avaliar": {
      "capitulo": "21.1.10.1000"
    },
    "grau moderado a esquerda": {
      "capitulo": "21.1.10.1000"
    },
    "217": {
      "capitulo": "21.1.10.1000"
    },
    "183": {
      "capitulo": "21.1.10.1000"
    },
    "tinitus": {
      "capitulo": "21.1.10.1000"
    },
    "sulpirida": {
      "capitulo": "21.1.10.1000"
    },
    "protese": {
      "capitulo": "21.1.10.1000"
    },
    "tontura ortostatica": {
      "capitulo": "21.1.10.1000"
    },
    "severa a direita": {
      "capitulo": "21.1.10.1000"
    },
    "r2": {
      "capitulo": "21.1.10.1000"
    }
  }
}