{
  "prontuario_id": 596,
  "text": "QP: Retorno com exames + dores osteomusculares ( joelho e cervical )\nPaciente alega cefaleia forte (9) anoite, quase todos os dias, nega fatores de melhora ou piora, em região frontal, associada a nauseas,  vômitos e lacrimejamento.\nAfirma ter dor em articulações  (joelhos e ombros), piora com movimentação, associado a edema MMII bilateral (inicio de manhã com piora final do dia).\nAlega sofrer queda de cabelo, constipação, poliuria e boca seca.\n \nmãe falecida aos 32 anos devido Chagas, pai falecido aos 70 anos devido AVC, irmão com lesões (polipos) em intestino.\n- Colesterol total 207mg/dL\n- HDL 47 mg/dL\n\n# Normais\n- Glicose em jejum 84mg/dL\n- CPK: 121 U/L\n- Transaminase pirúvica:   27 U/L\n- Transaminase oxalacetica: 24 U/L\n- HDL 47 mg/dL\n- TSH ultra sensivel 2,21 \n- T4 livre 1,22 ng/dL \n\nInternamentos:\ncolecistectomia ha 5 anos\nCx henia de disco\n\nGO: \nG 2  C 2  P 0 A 0\nmenopausa ha 6 anos sem reposição hormonal\n\nAlergia a iogo e frutos do mar\nTG, HDL, colesterol total, T4 livre, TSH.",
  "entities": {
    "Sinal ou Sintoma": [
      "QP",
      "nauseas",
      "vômitos",
      "lacrimejamento",
      "constipação",
      "poliuria",
      "polipos",
      "dores osteomusculares",
      "cefaleia forte",
      "dor em articulações",
      "piora com movimentação",
      "queda de cabelo",
      "boca seca"
    ],
    "Abreviação": [
      "QP",
      "AVC",
      "HDL",
      "CPK",
      "GO",
      "iogo",
      "TG",
      "TSH",
      "MMII bilateral",
      "TSH ultra sensivel",
      "Cx henia de disco"
    ],
    "Atividade de Assistência à Saúde": [
      "Retorno",
      "Internamentos"
    ],
    "Procedimento Laboratorial": [
      "exames",
      "TG",
      "HDL",
      "TSH",
      "colesterol total",
      "T4 livre"
    ],
    "Parte do Corpo, Órgão ou Componente Orgânico": [
      "joelho",
      "joelhos",
      "ombros",
      "intestino",
      "MMII bilateral"
    ],
    "Localização ou Região Corporal": [
      "cervical",
      "região frontal"
    ],
    "Paciente ou Grupo com Deficiência": [
      "Paciente"
    ],
    "Conceito Temporal": [
      "anoite",
      "ha 5 anos",
      "ha 6 anos"
    ],
    "Negação": [
      "nega",
      "sem"
    ],
    "Grupo Familiar": [
      "mãe",
      "pai",
      "irmão"
    ],
    "Doença ou Síndrome": [
      "Chagas",
      "AVC"
    ],
    "Conceito Quantitativo": [
      "207mg/dL",
      "84mg/dL",
      "2",
      "0",
      "47 mg/dL",
      "121 U/L",
      "24 U/L",
      "1 , 22 ng/dL"
    ],
    "Resultado Laboratorial ou de Teste": [
      "Normais",
      "Colesterol total",
      "Glicose em jejum",
      "Transaminase pirúvica : 27 U/L",
      "Transaminase oxalacetica",
      "TSH ultra sensivel",
      "2 , 21",
      "T4 livre"
    ],
    "Procedimento Terapêutico ou Preventivo": [
      "colecistectomia",
      "C",
      "Cx henia de disco",
      "reposição hormonal"
    ],
    "Função de Organismo": [
      "G",
      "P"
    ],
    "Função Fisiológica": [
      "menopausa"
    ],
    "Alimento": [
      "iogo",
      "frutos do mar"
    ],
    "Achado": [
      "fatores de melhora ou piora"
    ],
    "Hormônio": [
      "reposição hormonal"
    ],
    "Substância Química Orgânica": [
      "reposição hormonal"
    ],
    "Substância Farmacológica": [
      "reposição hormonal"
    ]
  },
  "labels": {
    "poliuria": {
      "capitulo": "16.1"
    },
    "mmii bilateral": {
      "capitulo": "15.1"
    },
    "polipos": {
      "capitulo": "02.1"
    },
    "anoite": {
      "capitulo": "21.1"
    },
    "paciente": {
      "capitulo": "21.1"
    },
    "pai": {
      "capitulo": "21.1"
    },
    "exames": {
      "capitulo": "21.1"
    },
    "mãe": {
      "capitulo": "21.1"
    },
    "colesterol total": {
      "capitulo": "11.1"
    },
    "cefaleia forte": {
      "capitulo": "21.1"
    },
    "joelho": {
      "capitulo": "15.1"
    },
    "intestino": {
      "capitulo": "13.1"
    },
    "c": {
      "capitulo": "21.1"
    },
    "tsh": {
      "capitulo": "05.1"
    },
    "lacrimejamento": {
      "capitulo": "21.1"
    },
    "ombros": {
      "capitulo": "15.1"
    },
    "retorno": {
      "capitulo": "21.1"
    },
    "frutos do mar": {
      "capitulo": "21.1"
    },
    "hdl": {
      "capitulo": "11.1"
    },
    "dor em articulações": {
      "capitulo": "15.1"
    },
    "menopausa": {
      "capitulo": "05.1"
    },
    "84mg/dl": {
      "capitulo": "21.1"
    },
    "207mg/dl": {
      "capitulo": "21.1"
    },
    "nega": {
      "capitulo": "21.1"
    },
    "cervical": {
      "capitulo": "15.1"
    },
    "0": {
      "capitulo": "21.1"
    },
    "ha 5 anos": {
      "capitulo": "21.1"
    },
    "região frontal": {
      "capitulo": "21.1"
    },
    "queda de cabelo": {
      "capitulo": "21.1"
    },
    "g": {
      "capitulo": "21.1"
    },
    "chagas": {
      "capitulo": "01.1"
    },
    "irmão": {
      "capitulo": "21.1"
    },
    "2": {
      "capitulo": "21.1"
    },
    "piora com movimentação": {
      "capitulo": "21.1"
    },
    "avc": {
      "capitulo": "08.1"
    },
    "iogo": {
      "capitulo": "21.1"
    },
    "t4 livre": {
      "capitulo": "05.1"
    },
    "121 u/l": {
      "capitulo": "21.1"
    },
    "vômitos": {
      "capitulo": "21.1"
    },
    "qp": {
      "capitulo": "21.1"
    },
    "boca seca": {
      "capitulo": "21.1"
    },
    "tg": {
      "capitulo": "21.1"
    },
    "reposição hormonal": {
      "capitulo": "21.1"
    },
    "24 u/l": {
      "capitulo": "21.1"
    },
    "ha 6 anos": {
      "capitulo": "21.1"
    },
    "glicose em jejum": {
      "capitulo": "05.1"
    },
    "colecistectomia": {
      "capitulo": "05.1"
    },
    "tsh ultra sensivel": {
      "capitulo": "05.1"
    },
    "normais": {
      "capitulo": "21.1"
    },
    "transaminase oxalacetica": {
      "capitulo": "13.1"
    },
    "cpk": {
      "capitulo": "15.1"
    },
    "fatores de melhora ou piora": {
      "capitulo": "21.1"
    },
    "cx henia de disco": {
      "capitulo": "15.1"
    },
    "joelhos": {
      "capitulo": "15.1"
    },
    "go": {
      "capitulo": "21.1"
    },
    "internamentos": {
      "capitulo": "21.1"
    },
    "sem": {
      "capitulo": "21.1"
    },
    "dores osteomusculares": {
      "capitulo": "15.1"
    }
  }
}