{
  "prontuario_id": 329,
  "text": "# Lucas, 47 ANOS\n\n# QUADRO CLÍNICO: PACIENTE COMPARECE EM CONSULTA DE ROTINA, SEM QUEIXA ESPECÍFICA. JÁ USUÁRIA DE ÓCULOS.\n- NEGA COMORBIDADES\n- NEGA CX TRAUMA OCULAR\n- HMF NEGATIVA PARA GLAUCOMA/CEGUEIRA\n- CORIORRETINITE POR TOXOPLASMOSE HÁ 12 ANOS EM OE\n\n# EXAME FÍSICO\nAV SC\n20/20\n20/200\n\nAV CC\n20/20\n20/200\nJ1\n\nÓCULOS\n-0,25  -0,75  10º\n-0,75  ESF\n\nPIO 11/12\n\nBIO\nOD: CA CALMA E BEM FORMADA, CÓRNEA CRISTALINO TRANSPARENTE, PUPILA FOTORREAGENTE.\nOE: CA CALMA E BEM FORMADA, CÓRNEA CRISTALINO TRANSPARENTE, PUPILA FOTORREAGENTE.\n\nFO\nOD: PAPILA E MÁCULA NORMAIS.\nOE: CICATRIZ TOXOPLASMOSE ENTRE PAPILA E DO.\n\n# HD\nCICATRIZ POR TOXOPLASMOSE EM OE\n\n# CD\nORIENTO RETORNO NO DIA 06/08 PARA MR (SEM ACOMPANHANTE HOJE)\n\nR1 Doutor Vital Brazil\n \n \n \n ",
  "entities": {
    "Paciente ou Grupo com Deficiência": [
      "PACIENTE"
    ],
    "Negação": [
      "SEM",
      "NEGA",
      "NEGATIVA"
    ],
    "Dispositivo Médico": [
      "ÓCULOS"
    ],
    "Procedimento Terapêutico ou Preventivo": [
      "CX"
    ],
    "Abreviação": [
      "CX",
      "HMF",
      "OE",
      "J1",
      "PIO",
      "BIO",
      "OD",
      "FO",
      "HD",
      "CD",
      "MR",
      "R1",
      "AV SC",
      "AV CC",
      "10º -0 , 75 ESF",
      "CA CALMA E BEM FORMADA",
      "ENTRE PAPILA E DO"
    ],
    "Doença ou Síndrome": [
      "GLAUCOMA/CEGUEIRA",
      "CORIORRETINITE",
      "TOXOPLASMOSE"
    ],
    "Parte do Corpo, Órgão ou Componente Orgânico": [
      "OE",
      "OD",
      "PAPILA",
      "MÁCULA"
    ],
    "Achado": [
      "J1"
    ],
    "Procedimento Diagnóstico": [
      "PIO",
      "BIO",
      "FO",
      "MR",
      "AV SC",
      "AV CC"
    ],
    "Resultado Laboratorial ou de Teste": [
      "11/12",
      "CA CALMA E BEM FORMADA",
      "CÓRNEA CRISTALINO TRANSPARENTE",
      "PUPILA FOTORREAGENTE"
    ],
    "Conceito Quantitativo": [
      "11/12",
      "20/20 20/200",
      "-0 , 25 -0 , 75",
      "10º -0 , 75 ESF"
    ],
    "Função Patológica": [
      "CICATRIZ"
    ],
    "Atividade de Assistência à Saúde": [
      "CD",
      "ORIENTO",
      "RETORNO",
      "CONSULTA DE ROTINA"
    ],
    "Grupo Profissional ou Ocupacional": [
      "R1",
      "Doutor"
    ],
    "Atributo Clínico": [
      "QUADRO CLÍNICO"
    ],
    "Sinal ou Sintoma": [
      "QUEIXA ESPECÍFICA"
    ],
    "Lesão ou Envenenamento": [
      "TRAUMA OCULAR"
    ],
    "Conceito Temporal": [
      "HÁ 12 ANOS"
    ],
    "Conceito Espacial": [
      "ENTRE PAPILA E DO"
    ]
  },
  "labels": {
    "cicatriz": {
      "capitulo": "21"
    },
    "doutor": {
      "capitulo": "21"
    },
    "20/20 20/200": {
      "capitulo": "21"
    },
    "11/12": {
      "capitulo": "21"
    },
    "paciente": {
      "capitulo": "21"
    },
    "-0 , 25 -0 , 75": {
      "capitulo": "21"
    },
    "quadro clínico": {
      "capitulo": "21"
    },
    "papila": {
      "capitulo": "21"
    },
    "queixa específica": {
      "capitulo": "21"
    },
    "óculos": {
      "capitulo": "21"
    },
    "ca calma e bem formada": {
      "capitulo": "21"
    },
    "10º -0 , 75 esf": {
      "capitulo": "21"
    },
    "retorno": {
      "capitulo": "21"
    },
    "pio": {
      "capitulo": "21"
    },
    "há 12 anos": {
      "capitulo": "21"
    },
    "nega": {
      "capitulo": "21"
    },
    "toxoplasmose": {
      "capitulo": "21"
    },
    "mácula": {
      "capitulo": "21"
    },
    "trauma ocular": {
      "capitulo": "21"
    },
    "av sc": {
      "capitulo": "21"
    },
    "cd": {
      "capitulo": "21"
    },
    "cx": {
      "capitulo": "21"
    },
    "j1": {
      "capitulo": "21"
    },
    "fo": {
      "capitulo": "21"
    },
    "av cc": {
      "capitulo": "21"
    },
    "r1": {
      "capitulo": "21"
    },
    "bio": {
      "capitulo": "21"
    },
    "oe": {
      "capitulo": "21"
    },
    "od": {
      "capitulo": "21"
    },
    "hd": {
      "capitulo": "21"
    },
    "coriorretinite": {
      "capitulo": "21"
    },
    "negativa": {
      "capitulo": "21"
    },
    "consulta de rotina": {
      "capitulo": "21"
    },
    "pupila fotorreagente": {
      "capitulo": "21"
    },
    "glaucoma/cegueira": {
      "capitulo": "21"
    },
    "sem": {
      "capitulo": "21"
    }
  }
}