{
  "prontuario_id": 874,
  "text": "PA 130/80 mmHg / FC 100 bpm / TEMP 36.3º C / FR 16. FRATURA DO COLO DO FEMUR. Às 17:10H: Passado SNE conforme orientação médica, sem intercorrências. Aguarda RX de controle. Enfª Florence Nightingale, COREN XXXX. FRATURA DA COLUNA LOMBAR E DA PELVE. Às 16:09: paciente encaminhado para uti 1. enf Florence Nightingale. SEPTICEMIA NAO ESPECIFICADA. Às 01:55HS: PCTE LUCIDO, CONFUSO, COMUNICATIVO, EUPNEICO EM AR AMBIENTE, PRESENÇA DE EDEMA EM OLHO ESQUERDO, CONTIDO NO LEITO, ACESSO VENOSO PERIFÉRICO EM MSD SALINIZADO, URUPEN C/ DIURESE PRESENTE, SEGUE SOB CUIDADOS. ACIDENTE VASCULAR CEREBRAL NAO ESPECIFICADO COMO HEMORRAGICO OU ISQUEMICO. Às 21:39h: Responsivo, colaborativo, face corada, pupilas iso / foto. Aceitando liquidos VO. Respiraçao espontanea em ar ambiente com saturaçao de 94%. Acesso central D com infusao de ancoron 11 ml/hr + insulina 8 ml/hr. Extremidades edemaciadas, perfusao periferica preservada. Abdomen globoso, rha +. Diurese espontanea em fralda, solicito uropen. No momento, nao relata queixas algicas. Monitorizado continuamente com cardioscopico + oximetria de pulso + pam nao invasiva. Enfermeira Florence Nightingale. MELENA. Às 22H: PERMANECE INSTÁVEL HEMODINAMICAMENTE, FAZENDO USO DE DVA EM ALTAS VAZÕES. MANTIDA EM VM COM FILTRO DE BARREIRA, EM MODO PCV, COM PI DE 3O CM DE H2O, FIO2 EM 0,30%, FR 22 CM DE H2O. MONITORADA COM PAM, CARDIOSCOPIA E OXIMETRIA DE PULSO. APRESENTA RAMSAY 6, PUPILAS MÉDIO-FIXAS, ANASARCA, MUCOSAS ICTÉRICAS +++/4, TOT EM RIMA LABIAL EM 24 CM, SECREÇÃO TRAQUEOBRÔNQUICA AMARELADA EM MÉDIA QUANTIDADE DE SECREÇÃO, AUSCULTA PULMONAR COM RONCOS E CREPITAÇÕES DIFUSAS, CVC EM JUGULAR INTERNA DIREITA COM NORADRENALINA 42 ML/H, DOPAMINA 42 ML/H, MIDAZOLAN 20 ML/H, SEDAÇÃO 20 ML/H, CURATIVO EM REGIÃO ABDOMINAL LIMPO E SECO, PAM EM ARTÉRIA RADIAL D PERMEÁVEL, DRENO DE SUCTOR ABDOMINAL COM POUCA QUANTIDADE DE DÉBITO HEMÁTICO, RHA AUSENTES, ABDOME DISTENDIDO, SVD COM OLIGOANÚRIA. INSUFICIENCIA RESPIRATORIA AGUDA.",
  "entities": {
    "Atributo Clínico": [
      "PA",
      "FC",
      "TEMP",
      "FR"
    ],
    "Abreviação": [
      "PA",
      "mmHg",
      "FC",
      "bpm",
      "TEMP",
      "FR",
      "Enfª",
      "uti",
      "enf",
      "PCTE",
      "MSD",
      "D",
      "DVA",
      "PI",
      "FIO2",
      "PAM",
      "+++/4",
      "TOT",
      "CVC",
      "RHA",
      "Passado SNE",
      "RX de controle",
      "Aceitando liquidos VO",
      "rha +",
      "MODO PCV",
      "ARTÉRIA RADIAL D",
      "SVD COM OLIGOANÚRIA"
    ],
    "Conceito Quantitativo": [
      "130/80",
      "100",
      "36",
      "16",
      "30%",
      "22",
      "3º C",
      "11 ml/hr",
      "8 ml/hr",
      "3O CM DE H2O",
      "24 CM",
      "42 ML/H",
      "20 ML/H"
    ],
    "Sinal ou Sintoma": [
      "intercorrências",
      "CONFUSO",
      "EDEMA",
      "MELENA",
      "ANASARCA",
      "RONCOS",
      "Extremidades edemaciadas",
      "queixas algicas",
      "INSTÁVEL HEMODINAMICAMENTE",
      "PUPILAS MÉDIO-FIXAS",
      "MUCOSAS ICTÉRICAS",
      "CREPITAÇÕES DIFUSAS",
      "DÉBITO HEMÁTICO",
      "SVD COM OLIGOANÚRIA"
    ],
    "Grupo Profissional ou Ocupacional": [
      "Enfª",
      "enf",
      "Enfermeira"
    ],
    "Paciente ou Grupo com Deficiência": [
      "paciente",
      "PCTE"
    ],
    "Organização Relacionada à Saúde": [
      "uti"
    ],
    "Achado": [
      "LUCIDO",
      "COMUNICATIVO",
      "SALINIZADO",
      "Responsivo",
      "colaborativo",
      "LIMPO",
      "SECO",
      "PERMEÁVEL",
      "RHA",
      "EUPNEICO EM AR AMBIENTE",
      "CONTIDO NO LEITO",
      "DIURESE PRESENTE",
      "face corada",
      "Aceitando liquidos VO",
      "Respiraçao espontanea em ar ambiente",
      "saturaçao de 94%",
      "perfusao periferica preservada",
      "rha +",
      "RAMSAY 6"
    ],
    "Função Patológica": [
      "EDEMA"
    ],
    "Localização ou Região Corporal": [
      "MSD",
      "Abdomen",
      "ABDOMINAL",
      "ABDOME",
      "REGIÃO ABDOMINAL"
    ],
    "Procedimento Terapêutico ou Preventivo": [
      "SALINIZADO",
      "PI",
      "FIO2",
      "TOT",
      "CVC",
      "SEDAÇÃO",
      "CURATIVO",
      "Passado SNE",
      "ACESSO VENOSO PERIFÉRICO",
      "Acesso central",
      "FILTRO DE BARREIRA",
      "MODO PCV",
      "DRENO DE SUCTOR"
    ],
    "Dispositivo Médico": [
      "URUPEN",
      "uropen",
      "cardioscopico",
      "TOT",
      "CVC",
      "CURATIVO",
      "ACESSO VENOSO PERIFÉRICO",
      "Acesso central",
      "FILTRO DE BARREIRA",
      "DRENO DE SUCTOR"
    ],
    "Atividade de Assistência à Saúde": [
      "CUIDADOS",
      "infusao",
      "solicito",
      "orientação médica"
    ],
    "Parte do Corpo, Órgão ou Componente Orgânico": [
      "pupilas",
      "OLHO ESQUERDO",
      "JUGULAR INTERNA DIREITA",
      "ARTÉRIA RADIAL D"
    ],
    "Conceito Espacial": [
      "D"
    ],
    "Substância Farmacológica": [
      "ancoron",
      "insulina",
      "NORADRENALINA",
      "DOPAMINA",
      "MIDAZOLAN"
    ],
    "Hormônio": [
      "insulina",
      "NORADRENALINA"
    ],
    "Objeto Manufaturado": [
      "fralda"
    ],
    "Procedimento Diagnóstico": [
      "cardioscopico",
      "MONITORADA",
      "PAM",
      "CARDIOSCOPIA",
      "RX de controle",
      "Monitorizado continuamente",
      "oximetria de pulso",
      "OXIMETRIA DE PULSO",
      "AUSCULTA PULMONAR"
    ],
    "Substância Química Orgânica": [
      "DOPAMINA"
    ],
    "Negação": [
      "AUSENTES"
    ],
    "Lesão ou Envenenamento": [
      "FRATURA DO COLO DO FEMUR",
      "FRATURA DA COLUNA LOMBAR E DA PELVE"
    ],
    "Função Fisiológica": [
      "DIURESE PRESENTE"
    ],
    "Doença ou Síndrome": [
      "ACIDENTE VASCULAR CEREBRAL",
      "INSUFICIENCIA RESPIRATORIA AGUDA"
    ],
    "Substância Corporal": [
      "SECREÇÃO TRAQUEOBRÔNQUICA",
      "MÉDIA QUANTIDADE DE SECREÇÃO"
    ],
    "Conceito Qualitativo": [
      "POUCA QUANTIDADE"
    ]
  },
  "labels": {}
}