{
  "prontuario_id": 913,
  "text": "ÀS 14:20: ERRATA: DESCONSIDERAR EVOLUÇÃO DE ENFERMAGEM ANTERIOR. 1º DI VÍTIMA DE QUEDA DE NÍVEL COM TRAUMA DIRETO EM MSE. CONSCIENTE, ORIENTADO, EUPNÉICO, COM RESPIRAÇÃO ESPONTÂNEA EM AR AMBIENTE, MANTENDO REPOUSO. PRESENÇA DE TALA GESSADA EM MSE. AVP EM MSD. NEGA QUEIXAS ÁLGICAS. MANTÉM JEJUM. SEGUE SOB CUIDADOS DA EQUIPE MULTIPROFISSIONAL. AGUARDA PROC CIRÚRGICO. FRATURA DA EXTREMIDADE SUPERIOR DO CUBITO ULNA. Às 17:00: 1º DI, paciente encaminhada do XXXX com hx de rebaixamento do nivel de consciencia e confusao mental. Sonolenta, eupneica, fazendo uso continuo de O2 sob uso de mascara. Pupilas Iso / Foto. Glasgow: 9. Monitorizada + oximetria de pulso: Fc = 80, PA = 162 x 79 mmhg, spo2 = 95 %. Mantem acesso venoso em periferico em jugular E, com insulina a 40 ml/h e cloreto de potassio a 42 ml/h em bomba de infusao. Apresenta SNG em narina E mantendo fechada. Abdomen flacido e globoso, indolor a palpação, RHA+ , com SVD com urina aspecto citrico. Segue aos cuidados da equipe multiprofissional e aguarda vaga de UTI. DIABETES INSIPIDO. ÀS 11:05H: ACORDADA, COLABORATIVA, TRANQUILA, CONTACTUANTE, NORMOTERMICA (38,6 c), NORMOCARDICA (84 bpm), PICO HIPERTENSIVO (154/66 MMhg), EUPNEICA SOB MASCARA DE OXIGENIO A 3L/M, SPO2 98%, CATETER VENOSO CENTRAL VIA SUBCLAVIA DIREITA PERMEAVEL INFUNDINDO PLANO BASICO DE HIDRATAÇÃO, ABDOMEM GLOBOSO E FLACIDO, INDOLOR A PALPAÇÃO, RHA PRESENTES, SNE FECHADA, AGUARDA DIETA PARA INSTALAÇÃO, DRENO DE PENROSE A DIREITA COM DEBITO SEROSO, DRENO BILIAR COM DEBITO EM MEDIA QUANTIDADE, SVD COM DIURESE CONCENTRADA, SEM PRESENÇA DE GRUMOS. ELIMINAÇÕES INTESTINAIS AUSENTES ATÉ O MOMENTO, REALIZADO MEDIDAS E HIGIENE E CONFORTO. SEGUE MONITORADA COM OXIMETRIA DE PULSO, PNI ECG EM REPOUSO NO LEITO COM CABECEIRA ELEVADA A 45º. SOB CUIDADOS INTENVOS. ENF FLORENCE NIGHTINGALE, COREN XXXX. CALCULOSE DA VESICULA BILIAR COM COLICISTITE AGUDA.",
  "entities": {
    "Produto Intelectual": [
      "ERRATA",
      "EVOLUÇÃO DE ENFERMAGEM"
    ],
    "Conceito Temporal": [
      "ANTERIOR"
    ],
    "Paciente ou Grupo com Deficiência": [
      "VÍTIMA",
      "paciente"
    ],
    "Achado": [
      "CONSCIENTE",
      "ORIENTADO",
      "EUPNÉICO",
      "eupneica",
      "Iso",
      "Foto",
      "flacido",
      "RHA+",
      "ACORDADA",
      "COLABORATIVA",
      "TRANQUILA",
      "CONTACTUANTE",
      "NORMOTERMICA",
      "NORMOCARDICA",
      "EUPNEICA",
      "PERMEAVEL",
      "FLACIDO",
      "RESPIRAÇÃO ESPONTÂNEA EM AR AMBIENTE",
      "mantendo fechada",
      "aspecto citrico",
      "RHA PRESENTES",
      "DEBITO SEROSO",
      "REPOUSO NO LEITO"
    ],
    "Abreviação": [
      "MSE",
      "AVP",
      "MSD",
      "Iso",
      "Foto",
      "Fc",
      "PA",
      "spo2",
      "SNG",
      "RHA+",
      "SVD",
      "UTI",
      "SPO2",
      "PNI",
      "ECG",
      "ENF",
      "PROC CIRÚRGICO",
      "162 x 79 mmhg",
      "jugular E",
      "narina E",
      "84 bpm",
      "RHA PRESENTES",
      "SNE FECHADA"
    ],
    "Localização ou Região Corporal": [
      "MSE",
      "MSD",
      "Abdomen",
      "ABDOMEM"
    ],
    "Procedimento Terapêutico ou Preventivo": [
      "AVP",
      "JEJUM",
      "SNG",
      "SVD",
      "SPO2",
      "INFUNDINDO",
      "MANTENDO REPOUSO",
      "TALA GESSADA",
      "PROC CIRÚRGICO",
      "acesso venoso em periferico",
      "MASCARA DE OXIGENIO",
      "CATETER VENOSO CENTRAL",
      "PLANO BASICO DE HIDRATAÇÃO",
      "SNE FECHADA",
      "DRENO DE PENROSE",
      "DRENO BILIAR",
      "MEDIDAS E HIGIENE E CONFORTO",
      "REPOUSO NO LEITO",
      "CABECEIRA ELEVADA A 45º"
    ],
    "Dispositivo Médico": [
      "AVP",
      "mascara",
      "SNG",
      "SVD",
      "TALA GESSADA",
      "acesso venoso em periferico",
      "CATETER VENOSO CENTRAL",
      "SNE FECHADA",
      "DRENO DE PENROSE",
      "DRENO BILIAR"
    ],
    "Negação": [
      "NEGA",
      "indolor",
      "INDOLOR",
      "SEM",
      "AUSENTES"
    ],
    "Atividade de Assistência à Saúde": [
      "encaminhada",
      "REALIZADO",
      "CUIDADOS DA EQUIPE MULTIPROFISSIONAL",
      "cuidados da equipe multiprofissional",
      "CUIDADOS INTENVOS"
    ],
    "Sinal ou Sintoma": [
      "Sonolenta",
      "globoso",
      "GLOBOSO",
      "INDOLOR",
      "QUEIXAS ÁLGICAS",
      "rebaixamento do nivel de consciencia",
      "confusao mental",
      "Glasgow : 9",
      "PICO HIPERTENSIVO",
      "PRESENÇA DE GRUMOS"
    ],
    "Parte do Corpo, Órgão ou Componente Orgânico": [
      "Pupilas",
      "jugular E",
      "SUBCLAVIA DIREITA"
    ],
    "Procedimento Diagnóstico": [
      "Monitorizada",
      "palpação",
      "PALPAÇÃO",
      "MONITORADA",
      "ECG",
      "oximetria de pulso",
      "OXIMETRIA DE PULSO"
    ],
    "Atributo Clínico": [
      "Fc",
      "PA",
      "spo2"
    ],
    "Conceito Quantitativo": [
      "80",
      "3L/M",
      "98%",
      "162 x 79 mmhg",
      "95 %",
      "40 ml/h",
      "42 ml/h",
      "38 , 6 c",
      "84 bpm",
      "154/66 MMhg"
    ],
    "Substância Farmacológica": [
      "insulina",
      "cloreto de potassio"
    ],
    "Hormônio": [
      "insulina"
    ],
    "Aminoácido, Peptídeo ou Proteína": [
      "insulina"
    ],
    "Substância Corporal": [
      "urina"
    ],
    "Organização Relacionada à Saúde": [
      "UTI"
    ],
    "Objeto Manufaturado": [
      "UTI"
    ],
    "Conceito Espacial": [
      "DIREITA"
    ],
    "Grupo Profissional ou Ocupacional": [
      "ENF",
      "CUIDADOS DA EQUIPE MULTIPROFISSIONAL",
      "cuidados da equipe multiprofissional"
    ],
    "Lesão ou Envenenamento": [
      "QUEDA DE NÍVEL",
      "TRAUMA DIRETO",
      "FRATURA DA EXTREMIDADE SUPERIOR DO CUBITO ULNA"
    ],
    "Substância Química Inorgânica": [
      "cloreto de potassio"
    ],
    "Dispositivo de Administração de Medicamento": [
      "bomba de infusao"
    ],
    "Espaço ou Junção Corporal": [
      "narina E"
    ],
    "Doença ou Síndrome": [
      "DIABETES INSIPIDO",
      "CALCULOSE DA VESICULA BILIAR",
      "COLICISTITE AGUDA"
    ],
    "Conceito Qualitativo": [
      "MEDIA QUANTIDADE"
    ],
    "Função Fisiológica": [
      "DIURESE CONCENTRADA",
      "ELIMINAÇÕES INTESTINAIS"
    ]
  },
  "labels": {}
}