{
  "prontuario_id": 171,
  "text": "Às 14:40HS: ENCAMINHADO DE MACA PARA CENTRO CIRURGICO, ACORDADO, COMUNICATIVO, EUPNEICO EM AR AMBIENTE. ENFER FLORENCE NIGHTINGALE, COREN XXXX. FRATURA DA ABOBADA DO CRANIO. ÀS 15:37: CONSCIENTE, ALERTA, AFEBRIL, COMUNICATIVA, EUPNÉICA EM AR AMBIENTE, RESTRITA AO LEITO, REFERIU NÃO ACEITAR DIETA VIA ORAL OFERECIDA PELO HOSPITAL. IRA RECEBER ALIMENTAÇÃO DE FORA, ACESSO VENOSO PERIFERICO SALINIZADO EM ANTEBRAÇO DIREITO, SINAIS VITAIS ESTAVÉIS, REFERE ALGIA A MOBILIZAÇÃO, MANTÉM TRAÇÃO EM MEMBRO INFERIOR ESQUERDO, DIURESE PRESENTE, SOLICITO AVALIAÇÃO DO PLANTÃO DA ORTOPEDIA PARA REAVALIAR A TRAÇÃO, SEGUE SOB CUIDADOS, ENFER FLORENCE NIGHTINGALE, COREN XXXX. FRATURA DO FEMUR. Às 09:00 Horas: Hemodinamicamente estável, reage a estímulos verbais simples, dolorosos e de aspiração; recebendo sedação intermitente (Dormonid 15 mg) quando período de agitação; sonda nasogástrica aberta sem débito; monitorização cardíaca, pressão arterial, PAM 120 mmHg, PVC 25 cmH2O, PIA 27 cmH2O; em ventilação mecânica, PSV, FIO2 40%, PEEP = 6 cmH2O; secreção brônquica em média quantidade clara; roncos difusos a ausculta; curativo torácico esquerdo seco e limpo (débito seroso em média quantidade), não oscilante e sem fuga aérea; débito seroso em hipocôndrio direito por dreno suctor em médio volume; inserção de dreno suctor (retirado) em hipocôndrio direito com débito seroso; bolsa escrotal e pênis edemaciados; curativo seco em região inguinal; orifício de saída de projétil em MID região posterior pouco sanguinolento; diurese efetiva de aspecto concentrado. *Solicitado início de dieta via enteral pela cirurgia geral, prescrevo sonda enteral. ABDOME AGUDO.",
  "entities": {
    "Dispositivo Médico": [
      "MACA",
      "curativo",
      "ACESSO VENOSO PERIFERICO",
      "sonda nasogástrica aberta",
      "dreno suctor",
      "sonda enteral"
    ],
    "Achado": [
      "ACORDADO",
      "COMUNICATIVO",
      "CONSCIENTE",
      "ALERTA",
      "AFEBRIL",
      "COMUNICATIVA",
      "clara",
      "seco",
      "limpo",
      "EUPNEICO EM AR AMBIENTE",
      "EUPNÉICA EM AR AMBIENTE",
      "RESTRITA AO LEITO",
      "SINAIS VITAIS ESTAVÉIS",
      "DIURESE PRESENTE",
      "Hemodinamicamente estável",
      "débito seroso",
      "diurese efetiva",
      "aspecto concentrado"
    ],
    "Abreviação": [
      "ENFER",
      "PVC",
      "PIA",
      "PSV",
      "FIO2",
      "PEEP",
      "MID"
    ],
    "Negação": [
      "AFEBRIL",
      "NÃO",
      "não"
    ],
    "Organização Relacionada à Saúde": [
      "HOSPITAL",
      "CENTRO CIRURGICO",
      "PLANTÃO DA ORTOPEDIA",
      "cirurgia geral"
    ],
    "Conceito Espacial": [
      "DIREITO",
      "ESQUERDO",
      "esquerdo",
      "direito"
    ],
    "Procedimento Terapêutico ou Preventivo": [
      "TRAÇÃO",
      "aspiração",
      "PVC",
      "PSV",
      "curativo",
      "RESTRITA AO LEITO",
      "DIETA VIA ORAL",
      "ACESSO VENOSO PERIFERICO",
      "sedação intermitente",
      "sonda nasogástrica aberta",
      "ventilação mecânica",
      "dreno suctor",
      "inserção de",
      "dieta via enteral",
      "sonda enteral"
    ],
    "Atividade de Assistência à Saúde": [
      "CUIDADOS",
      "REAVALIAR A TRAÇÃO"
    ],
    "Substância Química Orgânica": [
      "Dormonid"
    ],
    "Substância Farmacológica": [
      "Dormonid"
    ],
    "Conceito Temporal": [
      "período",
      "início"
    ],
    "Sinal ou Sintoma": [
      "agitação",
      "oscilante",
      "edemaciados",
      "ALGIA A MOBILIZAÇÃO",
      "roncos difusos",
      "fuga aérea"
    ],
    "Função Fisiológica": [
      "débito",
      "DIURESE PRESENTE",
      "diurese efetiva"
    ],
    "Conceito Quantitativo": [
      "40%",
      "15 mg",
      "120 mmHg",
      "25 cmH2O",
      "27 cmH2O",
      "6 cmH2O",
      "média quantidade",
      "médio volume"
    ],
    "Procedimento Diagnóstico": [
      "ausculta",
      "monitorização cardíaca"
    ],
    "Localização ou Região Corporal": [
      "torácico",
      "hipocôndrio",
      "MID",
      "MEMBRO INFERIOR",
      "região inguinal"
    ],
    "Parte do Corpo, Órgão ou Componente Orgânico": [
      "pênis",
      "bolsa escrotal"
    ],
    "Função Patológica": [
      "edemaciados"
    ],
    "Lesão ou Envenenamento": [
      "FRATURA DA ABOBADA DO CRANIO",
      "FRATURA DO FEMUR"
    ],
    "Alimento": [
      "ALIMENTAÇÃO DE FORA"
    ],
    "Substância Corporal": [
      "secreção brônquica"
    ],
    "Doença ou Síndrome": [
      "ABDOME AGUDO"
    ]
  },
  "labels": {}
}