{
  "prontuario_id": 689,
  "text": "Lucas, 65 ANOS\n# S: EM ACOMPANHAMENTO AMBULATORIAL DEVIDO HERNIA INGUINAL BILATERAL REDUTIVEL\nPLANO DE CORREÇÃO BILATERAL EM 06/01/2016 PORÉM, CIRURGIA SUSPENSA DEVIDO HIPERTENSÃO \nPACIENTE MESMO FAZENDO TRATAMENTO FAMACOLOGICO NAO ESTA RESPONDENDO AO TTO PA AFERIDA AGORA (06/05/2016) DE 200/110\n# MUC: DE HCTZ 50MG 1 - 1 - 0; LOSARATANA 50MG 1 - 0 - 1; ATENOLOL 50MG 1 - 0 - 1 E ANLODIPINO 5MG 1 - 0 - 1\nTRAZ CONTROLE PRESSORICO COM AFERIÇÕES MANTENDO MÉDIA DE 160MMG DE PAS\n# P: ORIENTO MANTER CONTROLE\nNOVA SOLICITACAO DE AGNEDAMENTO DE COSNULTA COM CLINICA MEDICA\nORIENTO ACOMPANHAMENTO VIA UBS\nRETORNO EM 30 DIAS PARA NOVA AVALIAÇÃO DOS CONTROLES PRESSÓRICOS E AVALIAÇÃO DE NOVO AGENDAMENTO CIRÚRGICO\n \n \n \n ",
  "entities": {
    "Procedimento Terapêutico ou Preventivo": [
      "CIRURGIA",
      "TTO",
      "PLANO DE CORREÇÃO BILATERAL",
      "TRATAMENTO FAMACOLOGICO",
      "AGENDAMENTO CIRÚRGICO"
    ],
    "Atividade de Assistência à Saúde": [
      "SUSPENSA",
      "ORIENTO",
      "ACOMPANHAMENTO",
      "RETORNO",
      "AVALIAÇÃO",
      "AGNEDAMENTO DE COSNULTA",
      "NOVA AVALIAÇÃO",
      "CONTROLES PRESSÓRICOS"
    ],
    "Doença ou Síndrome": [
      "HIPERTENSÃO",
      "HERNIA INGUINAL BILATERAL REDUTIVEL"
    ],
    "Paciente ou Grupo com Deficiência": [
      "PACIENTE"
    ],
    "Negação": [
      "NAO"
    ],
    "Abreviação": [
      "TTO",
      "PA",
      "MUC",
      "UBS"
    ],
    "Conceito Quantitativo": [
      "200/110",
      "50MG",
      "5MG"
    ],
    "Achado": [
      "MUC"
    ],
    "Substância Farmacológica": [
      "ANLODIPINO"
    ],
    "Substância Química Orgânica": [
      "ANLODIPINO"
    ],
    "Organização Relacionada à Saúde": [
      "UBS"
    ],
    "Anormalidade Anatômica": [
      "HERNIA INGUINAL BILATERAL REDUTIVEL"
    ],
    "Grupo Profissional ou Ocupacional": [
      "CLINICA MEDICA"
    ],
    "Conceito Temporal": [
      "30 DIAS"
    ]
  },
  "labels": {
    "BA99.0": {
      "term_original": "hipertensão",
      "capitulo": "11",
      "confidence_embedding": 0.0,
      "descricao_cid": "",
      "classification_reasoning": "A hipertensão é uma condição médica caracterizada por pressão arterial elevada, e o código BA99.0 (Representação de doença CID-11: Hipertensão arterial isolada) é a opção mais precisa para describir essa condição no contexto clínico fornecido."
    },
    "FB32.4": {
      "term_original": "hernia inguinal bilateral redutivel",
      "capitulo": "15",
      "confidence_embedding": 0.0,
      "descricao_cid": "",
      "classification_reasoning": "A hernia inguinal bilateral redutivel se encaixa no código FB32.4, que representa Representação de doença CID-11: Outra hérnia inguinal especificada"
    }
  }
}