{
  "prontuario_id": 139,
  "text": "PCTE RETORNA APOS EXAME DE USG \n\nAPRESENTA ABAULAMENTO EM TORAX A DIREITA \nSEM VAZAMENTO DE SECREÇÕES OU SINIAS FLOGISTICOS\nNEGA COMORBIDADES\nAPRESENTOU TADF A DIREITA POR DERRAME PLEURAL PARAPNEUMONICO HÁ 3 ANOS\nSEM OUTRAS CIRURGIAS\n\nAO EF: ABAULAMENTO DE 3X3 CMS EM FACE ANTERIOR DE TORAX A DIREITA, NÃO TEM RELAÇÃO COM CICATRIZ CIRURGICA PREVIA, SEM SINAIS\nFLOGISTICOS, SEM SECREÇÕES\n\nUSG 22/02/2016:\n- Nódulo sólido no tecido celular subcutâneo do hemitórax direito de provável origem lipomatosa\nNódulo sólido bem definido discretamente hiperecogênico com ecotextura semelhante a gordura, sem\nfluxo ao exame com Doppler colorido, localizado no tecido celular subcutâneo do hemitórax direito,\ndistando 0,3 cm da pele e medindo aproximadamente 3,4 x 0,6 x 3,0 cm (L x AP x T) (vol 3,7 cm³).\n- Ausência de massas ou coleções organizadas. \n\nEXPLICO CASO PARA PCTE QUE NAO REFERE DESEJO DE EXERESE DA LESAO\nORIENTO CUIDADOS E SINAIS DE ALERTA\nNAO DESEJA RETORNO PARA REAVALIAÇÃO\nALTA AMBULATORIAL\n\nR2 Doutor Vital Brazil\n \n \n \n ",
  "entities": {
    "Abreviação": [
      "PCTE",
      "USG",
      "EF",
      "R2",
      "TADF A DIREITA",
      "L x AP x T",
      "vol 3 , 7 cm³"
    ],
    "Paciente ou Grupo com Deficiência": [
      "PCTE"
    ],
    "Atividade de Assistência à Saúde": [
      "RETORNA",
      "EXPLICO",
      "RETORNO",
      "REAVALIAÇÃO",
      "ORIENTO CUIDADOS",
      "ALTA AMBULATORIAL"
    ],
    "Procedimento Diagnóstico": [
      "USG"
    ],
    "Sinal ou Sintoma": [
      "ABAULAMENTO",
      "VAZAMENTO DE SECREÇÕES",
      "SINIAS FLOGISTICOS",
      "SINAIS FLOGISTICOS",
      "SINAIS DE ALERTA"
    ],
    "Negação": [
      "SEM",
      "NEGA",
      "NÃO",
      "sem",
      "Ausência",
      "NAO"
    ],
    "Procedimento Terapêutico ou Preventivo": [
      "CIRURGIAS",
      "CIRURGICA",
      "TADF A DIREITA",
      "EXERESE DA LESAO"
    ],
    "Conceito Qualitativo": [
      "RELAÇÃO"
    ],
    "Função Patológica": [
      "CICATRIZ"
    ],
    "Substância Corporal": [
      "SECREÇÕES"
    ],
    "Grupo Profissional ou Ocupacional": [
      "R2",
      "Doutor"
    ],
    "Parte do Corpo, Órgão ou Componente Orgânico": [
      "TORAX A DIREITA"
    ],
    "Doença ou Síndrome": [
      "DERRAME PLEURAL PARAPNEUMONICO"
    ],
    "Conceito Temporal": [
      "HÁ 3 ANOS"
    ],
    "Conceito Quantitativo": [
      "3X3 CMS",
      "L x AP x T"
    ],
    "Resultado Laboratorial ou de Teste": [
      "Nódulo sólido no tecido celular subcutâneo do hemitórax direito",
      "origem lipomatosa",
      "Nódulo sólido bem definido discretamente",
      "hiperecogênico",
      "com ecotextura semelhante a gordura",
      "fluxo ao exame com Doppler colorido",
      "localizado no tecido celular subcutâneo do hemitórax direito",
      "distando 0 , 3 cm da pele",
      "vol 3 , 7 cm³",
      "massas ou coleções organizadas"
    ],
    "Ideia ou Conceito": [
      "SINAIS DE ALERTA"
    ]
  },
  "labels": {
    "CB25": {
      "term_original": "abaulamento",
      "capitulo": "12",
      "confidence_embedding": 0.7745,
      "descricao_cid": "Representação de doença CID-11: Fibrotórax. Definição: Fibrotórax resulta da fibrose da pleura visceral e se manifesta clinicamente por excursão respiratória reduzida e por fisiologia pulmonar restritiva. Existem dois mecanismos distintos que podem levar à formação do fibrotórax: 1) Mais frequentemente o fibrotórax se desenvolve como consequência de inflamação pleural em pacientes com derrames pleurais, inclusive hemotórax, derrame tuberculso ou empiema crônico; 2) Menos frequentemente, o fibrotórax resulta de doença parenquimatosa pulmonar e pode ser observado em pacientes com tuberculose, bronquiectasias ou abscesso pulmonar.",
      "classification_reasoning": "O abaulamento descrito no relatório é mais consistente com a representação de doença CID-11: Fibrotórax, uma condição que se manifesta clinicamente por excursão respiratória reduzida e por fisiologia pulmonar restritiva."
    },
    "CB27": {
      "term_original": "derrame pleural parapneumonico",
      "capitulo": "12",
      "confidence_embedding": 0.7875,
      "descricao_cid": "Representação de doença CID-11: Derrame pleural. Definição: Presença de líquido na cavidade pleural, resultante de transudação ou exsudação excessivas a partir das superfícies pleurais.",
      "classification_reasoning": "Abaulamento em torax à direita após exame de USG, apresentando nódulo sólido no tecido celular subcutâneo do hemitórax direito com ecotextura semelhante a gordura, e não há vazamento de secreções ou sinais flogísticos. O histórico de derrame pleural parapneumônico há 3 anos sugere que o abaolamento pode estar relacionado ao derrame pleural. Portanto, o código mais preciso é o CB27, representação de doença CID-11: Derrame pleural."
    },
    "EL50.1": {
      "term_original": "cicatriz",
      "capitulo": "14",
      "confidence_embedding": 0.7619,
      "descricao_cid": "Representação de doença CID-11: Cicatriz cirúrgica hipertrófica. Definição: Uma cicatriz cirúrgica elevada contendo um excesso de tecido fibroso que, em contraste com uma cicatriz queloidiana, tende a diminuir com o tempo.",
      "classification_reasoning": "A cicatriz mencionada no relatório refere-se ao processo de reparo do tecido conjuntivo após cirurgia, caracterizado pela formação excessiva de colágeno. Isso é coerente com a definição de cicatriz cirúrgica hipertrófica (EL50.1)."
    }
  }
}