{
  "prontuario_id": 773,
  "text": "ID:\nLucas, 39 anos, diarista, residente em foz do iguaçu\n\nHMA:\npaciente diz que ha 9 anos faz acompanhamento de arritmia, nao sabe especificar qual\nfez uso de atenolol por 8 anos e meio\nrefere que mesmo com a medicação sentia leve falta de ar, dor no peito,fraqueza, tontura, rouquidão e dor de cabeça\n\n- refere dispneia aos grandes esforços\n- refere dor torácica ventilatorio dependente. sintomas diários\n- vertigem noturna 2-3x / semanas nos ultimos 3 meses\n- cefaléia em regiao parietal bilateral que melhora com dipirona, sintomas diários\n- fraqueza, sente-se cansada mesmo sem grandes esforços \n\natualmente em uso de amiodarona 200mg / dia\nasmatica em uso de salbutamol e budesonida, nega outros medicamentos\nrefere mal estar com café, chas, chocolates, refrigerantes de cola\nqueixa-se de palpitações de inicio súbito e desaparecimento gradual,\n\nHMP:\nparacoccidioiomicose há 6 anos\ncx previas: 2 cesárias, amigdalectomia. herniorrafia inguinal\nnega outros internamentos\nnega alergias a medicamentos\nnega tabagismo e etilismo\nnega outras comorbidades\n\nHF: mae com 70 anos e higida. tias com cardiopatias\npai falecido com CA de garganta com menos de 40 anos\n\necocardiograma 2010:\ndiscreto prolapso de valva mitral\ncamaras cardiacas normais\nFE 74%\n\nEEF 2010:\n\nFC 82\nausculta cardiaca: BCR hipofonese de B1, discreto sopro sistólico em foco mitral\nMMII sem edema\n\nconduta:\noriento quanto a arritmias\nsolicito novo holter\npeço que paciente procure o serviço de emergencia durante uma exacerbação dos sintomas para fazer ECG\nsolicito ECG\nsolicito ecocardiograma\nretiro amiodarona e retorno em 3 semanas\n \n \n \n ",
  "entities": {
    "Paciente ou Grupo com Deficiência": [
      "paciente"
    ],
    "Atividade de Assistência à Saúde": [
      "acompanhamento",
      "internamentos",
      "conduta",
      "oriento",
      "solicito",
      "retiro"
    ],
    "Achado": [
      "arritmia",
      "higida",
      "BCR",
      "arritmias"
    ],
    "Substância Química Orgânica": [
      "atenolol",
      "dipirona",
      "amiodarona",
      "salbutamol",
      "budesonida"
    ],
    "Substância Farmacológica": [
      "atenolol",
      "medicação",
      "dipirona",
      "amiodarona",
      "salbutamol",
      "budesonida",
      "medicamentos"
    ],
    "Parte do Corpo, Órgão ou Componente Orgânico": [
      "peito",
      "MMII"
    ],
    "Sinal ou Sintoma": [
      "fraqueza",
      "tontura",
      "rouquidão",
      "edema",
      "falta de ar",
      "dor de cabeça",
      "dispneia aos grandes esforços",
      "dor torácica",
      "sintomas diários",
      "vertigem noturna",
      "mal estar",
      "palpitações de inicio súbito e desaparecimento gradual",
      "hipofonese de B1",
      "discreto sopro sistólico em foco mitral",
      "exacerbação dos sintomas"
    ],
    "Abreviação": [
      "2-3x",
      "cx",
      "EEF",
      "FC",
      "BCR",
      "MMII",
      "ECG",
      "CA de garganta",
      "FE 74%"
    ],
    "Conceito Temporal": [
      "semanas",
      "dia",
      "ha 9 anos",
      "8 anos e meio",
      "nos ultimos 3 meses",
      "há 6 anos",
      "3 semanas"
    ],
    "Conceito Quantitativo": [
      "200mg",
      "82"
    ],
    "Doença ou Síndrome": [
      "asmatica",
      "paracoccidioiomicose",
      "tabagismo",
      "etilismo",
      "cardiopatias"
    ],
    "Negação": [
      "nega",
      "sem"
    ],
    "Alimento": [
      "café",
      "chas",
      "chocolates",
      "refrigerantes de cola"
    ],
    "Procedimento Terapêutico ou Preventivo": [
      "cx",
      "cesárias",
      "amigdalectomia",
      "herniorrafia inguinal"
    ],
    "Grupo Familiar": [
      "mae",
      "tias",
      "pai"
    ],
    "Procedimento Diagnóstico": [
      "ecocardiograma",
      "EEF",
      "holter",
      "ECG"
    ],
    "Atributo Clínico": [
      "FC",
      "ausculta cardiaca"
    ],
    "Conceito Qualitativo": [
      "ventilatorio dependente"
    ],
    "Localização ou Região Corporal": [
      "parietal bilateral"
    ],
    "Função Patológica": [
      "alergias a medicamentos"
    ],
    "Processo Neoplásico": [
      "CA de garganta"
    ],
    "Resultado Laboratorial ou de Teste": [
      "prolapso de valva mitral",
      "camaras cardiacas normais",
      "FE 74%"
    ],
    "Organização Relacionada à Saúde": [
      "serviço de emergencia"
    ]
  },
  "labels": {}
}