{
  "prontuario_id": 11,
  "text": "POI DE LAVAGEM + CURETA DE TECIDO NECRÓTICO. 18:00: PACIENTE RETORNOU DO CC LÚCIDO, ORIENTADO, COMUNICATIVO; MANTEM AVP COM STP. REFERE TER APRESENTADO 01 EPISÓDIO DE EMESE NO CC. CURATIVO COM ASPECTO LIMPO E SECO. SEGUE EM OBSERVAÇÃO. OSTEOMIELITE NÃO ESPECIFICADA. INTUBADO, SOB VENTILAÇÃO MECÂNICA, MONITORIZAÇÃO CARDÍACA E OXIMETRIA DE PULSO, JUGULAR COM SOROTERAPIA EM CURSO, SNG ABERTA COM ESTASE BORRA DE CAFÉ. REALIZADO MUDANÇA DE DECÚBITO, ASPIRADO TOT COM GRANDE QUANTIDADE DE SECREÇÃO ESPESSA E PURULENTA, SVD L. INFARTO CEREBRAL DEVIDO A TROMBOSE DE ARTÉRIAS PRÉ-CEREBRAIS. 18:30: DESACORDADO, FAZ ABERTURA OCULAR ESPONTÂNEA, AGITADO. REALIZADO BANHO DE LEITO E HIGIENE ORAL, APÓS CONTIDO NO LEITO NOVAMENTE DEVIDO A AGITAÇÃO. COM HEMATOMA E EDEMA DISCRETO EM REGIÃO OCULAR À D. MEIA TALA GESSADA EM MIE E REALIZADA NOVA PUNÇÃO V. TRAUMATISMOS MÚLTIPLOS NÃO ESPECIFICADOS. 13/10/2006, 15:40 HORAS: PERMANECE EM COMA, COM PUPILAS MÉDIO-FIXAS, MANTENDO CATETER DE DVE. VM VIA TOT COM FIO2-50%, PCV, PP 25cmH20, PEEP 2cmH20, F15mrpm, SPO2 99%. AUSCULTA PULMONAR COM MV LIVRES. HEMODINAMICAMENTE ESTÁVEL. CVP EM MSD COM PLANO BÁSICO D. OUTRAS HEMORRAGIAS INTRACEREBRAIS",
  "entities": {
    "Conceito Temporal": [
      "POI"
    ],
    "Abreviação": [
      "POI",
      "CC",
      "AVP",
      "STP",
      "SNG",
      "TOT",
      "SVD",
      "L",
      "D",
      "MIE",
      "VM",
      "FIO2-50%",
      "PCV",
      "PP",
      "25cmH20",
      "PEEP",
      "2cmH20",
      "F15mrpm",
      "SPO2",
      "CVP",
      "MSD",
      "PUNÇÃO V",
      "MV LIVRES"
    ],
    "Procedimento Terapêutico ou Preventivo": [
      "LAVAGEM",
      "CURETA",
      "STP",
      "CURATIVO",
      "SOROTERAPIA",
      "SNG",
      "ASPIRADO",
      "SVD",
      "VM",
      "FIO2-50%",
      "PCV",
      "VENTILAÇÃO MECÂNICA",
      "MUDANÇA DE DECÚBITO",
      "BANHO DE LEITO",
      "HIGIENE ORAL",
      "CONTIDO NO LEITO",
      "MEIA TALA GESSADA",
      "PUNÇÃO V"
    ],
    "Paciente ou Grupo com Deficiência": [
      "PACIENTE"
    ],
    "Organização Relacionada à Saúde": [
      "CC"
    ],
    "Achado": [
      "LÚCIDO",
      "ORIENTADO",
      "COMUNICATIVO",
      "AVP",
      "LIMPO",
      "SECO",
      "INTUBADO",
      "ESPESSA",
      "L",
      "F15mrpm",
      "ABERTURA OCULAR ESPONTÂNEA",
      "MV LIVRES",
      "HEMODINAMICAMENTE ESTÁVEL"
    ],
    "Dispositivo Médico": [
      "AVP",
      "CURATIVO",
      "SNG",
      "TOT",
      "SVD",
      "CATETER",
      "CVP"
    ],
    "Sinal ou Sintoma": [
      "EMESE",
      "PURULENTA",
      "DESACORDADO",
      "AGITADO",
      "AGITAÇÃO",
      "HEMATOMA",
      "EDEMA",
      "COMA",
      "ESTASE BORRA DE CAFÉ",
      "PUPILAS MÉDIO-FIXAS"
    ],
    "Doença ou Síndrome": [
      "OSTEOMIELITE",
      "COMA",
      "INFARTO CEREBRAL",
      "TROMBOSE DE ARTÉRIAS PRÉ-CEREBRAIS",
      "HEMORRAGIAS INTRACEREBRAIS"
    ],
    "Parte do Corpo, Órgão ou Componente Orgânico": [
      "JUGULAR"
    ],
    "Substância Corporal": [
      "SECREÇÃO"
    ],
    "Conceito Qualitativo": [
      "DISCRETO"
    ],
    "Conceito Espacial": [
      "D"
    ],
    "Localização ou Região Corporal": [
      "MIE",
      "MSD",
      "REGIÃO OCULAR"
    ],
    "Conceito Quantitativo": [
      "FIO2-50%",
      "25cmH20",
      "2cmH20",
      "99%"
    ],
    "Disfunção Celular ou Molecular": [
      "TECIDO NECRÓTICO"
    ],
    "Negação": [
      "NÃO ESPECIFICADA",
      "NÃO ESPECIFICADOS"
    ],
    "Procedimento Diagnóstico": [
      "MONITORIZAÇÃO CARDÍACA",
      "OXIMETRIA DE PULSO",
      "AUSCULTA PULMONAR"
    ],
    "Lesão ou Envenenamento": [
      "TRAUMATISMOS MÚLTIPLOS"
    ]
  },
  "labels": {
    "EMLIOSE": {
      "capitulo": "01",
      "is_inferred": true
    },
    "INFARTO CEREBRAL": {
      "capitulo": "X",
      "is_inferred": true
    },
    "OSTEOMIELITE": {
      "capitulo": "V",
      "is_inferred": true
    },
    "EMESE": {
      "capitulo": "13",
      "is_inferred": true
    },
    "TROMBOSE DE ARTÉRIAS PRÉ-CEREBRAIS": {
      "capitulo": "X",
      "is_inferred": true
    },
    "HEMORRAGIAS INTRACEREBRAIS": {
      "capitulo": "X",
      "is_inferred": true
    },
    "INFARTO CEREBRAL DEVIDA A TROMBOSE DE ARTÉRIAS PRÉ-CEREBRAIS": {
      "capitulo": "05",
      "is_inferred": true
    },
    "EDEMA DISCRETO EM REGIÃO OCULAR": {
      "capitulo": "09",
      "is_inferred": true
    },
    "HEMATOMA EM REGIÃO OCULAR": {
      "capitulo": "09",
      "is_inferred": true
    },
    "ABERTURA OCULAR ESPONTÂNEA": {
      "capitulo": "09",
      "is_inferred": true
    },
    "OSTEOMIELITE NÃO ESPECIFICADA": {
      "capitulo": "X",
      "is_inferred": true
    },
    "TECIDO NECRÓTICO": {
      "capitulo": "17",
      "is_inferred": true
    },
    "INFARTO CEREBRAL DEVIDO A TROMBOSE DE ARTÉRIAS PRÉ-CEREBRAIS": {
      "capitulo": "16",
      "is_inferred": true
    },
    "PURULENTA": {
      "capitulo": "12",
      "is_inferred": true
    },
    "HEMOTÓRAX": {
      "capitulo": "12",
      "is_inferred": false
    },
    "TROMBOSE DE ARTÙRIAS PRÉ-CEREBRAIS": {
      "capitulo": "14",
      "is_inferred": true
    },
    "TRAUMATISMOS MÚLTIPLOS": {
      "capitulo": "23",
      "is_inferred": true
    },
    "INFARTO CEREBRAL DEVIDO A TROMBOSE DE ARTÙRIAS PRÉ-CEREBRAIS": {
      "capitulo": "17",
      "is_inferred": true
    },
    "HEMORRAGIAS INTRACRANIANAS": {
      "capitulo": "18",
      "is_inferred": true
    },
    "TROMBOSE DE ARTERIAS PRE-CEREBRAIS": {
      "capitulo": "18",
      "is_inferred": true
    },
    "GESTAÇÃO": {
      "capitulo": "18",
      "is_inferred": false
    },
    "TRAUMATISMOS MÚLTIPLOS NÃO ESPECIFICADOS": {
      "capitulo": "21",
      "is_inferred": true
    },
    "POI DE LAVAGEM + CURETA DE TECIDO NECRÓTICO": {
      "capitulo": "22",
      "is_inferred": true
    },
    "PÓS-OPERATIVO DE INFARTO CEREBRAL": {
      "capitulo": "23",
      "is_inferred": true
    },
    "LÚCIDO": {
      "capitulo": "24",
      "is_inferred": false
    },
    "ORIENTADO": {
      "capitulo": "24",
      "is_inferred": false
    },
    "COMUNICATIVO": {
      "capitulo": "24",
      "is_inferred": false
    },
    "ESTASE BORRA DE CAFÉ": {
      "capitulo": "24",
      "is_inferred": true
    }
  }
}