{
  "prontuario_id": 286,
  "text": "Familiares chegaram para conversar com a assistênte social, os mesmos convenceram o paciente a permanecer e continuar o tratamento, ficou um familiar para acompanha-lo durante o plantão noturno. FRATURA DOS OSSOS MALARES E MAXILARES. Às 00:44: Lucida, comunicativa, orientada, aceita dieta, em repouso no leito, apresenta curativo + tala gessada em MIE, referindo algia moderada, diurese presente, segue cuidados. MENISCO DISCOIDE CONGENITO. Em 22/12/06, Noite: Traqueostomizado, respiração espontânea com suporte de O2 em névoa úmida a 6 lts/min, saturando 98%. Consciente, comunicativo, obedece a comandos verbais, pupilas isocóricas, fotorreagentes. Cicatriz cirúrgica cefálica seca. Ausculta pulmo. NEOPLASIA MALIGNA DOS OSSOS DO CRANIO E DA FACE. ÀS 10:00: EVOLUCAO NA FICHA DE ADMISSAO DO PACIENTE. TRANSFERIDO PARA UI 02. ENF FLORENCE NIGHTINGALE. NEOPLASIA MALIGNA DO CEREBRO EXCETO LOBOS E VENTRICULOS. APRESENTANDO INSTABILIDADE HEMODINÂMICA, FEBRIL. CONFORME ORIENTAÇÃO DO DR VITAL BRASIL, ADMINISTRADO SF 0,9% E VOLUVEM EM BOLUS. ABDOME AGUDO. PACIENTE EM 10° DI COM HX DE SEPSE (FOCO PULMONAR). EM 2° PO DE TRAQUEOSTOMIA EM VM EM PSV, FIO2: 25%, PEEP: 4, FR: 9. MONITORIZADA COM FC: 80, SAT DE O2: 96%, PUPILAS ISO E POUCO FOTO. SEM SEDAÇÃO. SNE À E, AGUARDANDO RX PARA LIBERAR DIETA. COM EDEMA E EXSUDATO, FERIMENTO DO TORAX PARTE NAO ESPECIFICADA. Torporoso, taquidispneico, O2 sob névoa, grande quantidade de secreção orotraqueal. Chamado plantão. Realizada sedação e intubação endotraqueal com cânula 7,5, fixa em rima labial a 22 cm, grande quantidade de secreção espessa amarelada de odor fétido, VM, P. OUTRAS HEMORRAGIAS INTRACEREBRAIS.",
  "entities": {
    "Grupo Familiar": [
      "Familiares",
      "familiar"
    ],
    "Paciente ou Grupo com Deficiência": [
      "paciente",
      "PACIENTE"
    ],
    "Procedimento Terapêutico ou Preventivo": [
      "tratamento",
      "curativo",
      "Traqueostomizado",
      "TRAQUEOSTOMIA",
      "VM",
      "SEDAÇÃO",
      "SNE",
      "sedação",
      "repouso no leito",
      "tala gessada",
      "suporte de O2",
      "névoa úmida",
      "SF 0 , 9%",
      "O2 sob névoa"
    ],
    "Achado": [
      "Lucida",
      "comunicativa",
      "orientada",
      "Traqueostomizado",
      "Consciente",
      "comunicativo",
      "fotorreagentes",
      "MONITORIZADA",
      "FC",
      "aceita dieta",
      "repouso no leito",
      "diurese presente",
      "respiração espontânea",
      "saturando 98%",
      "obedece a comandos verbais",
      "Cicatriz cirúrgica cefálica seca"
    ],
    "Dispositivo Médico": [
      "curativo",
      "SNE",
      "tala gessada",
      "cânula 7 , 5"
    ],
    "Abreviação": [
      "MIE",
      "UI",
      "ENF",
      "DI",
      "HX",
      "PO",
      "VM",
      "PSV",
      "FIO2",
      "PEEP",
      "FR",
      "FC",
      "SNE",
      "E",
      "RX",
      "P",
      "Ausculta pulmo",
      "SF 0 , 9%",
      "SAT DE O2",
      "POUCO FOTO",
      "O2 sob névoa"
    ],
    "Localização ou Região Corporal": [
      "MIE",
      "endotraqueal"
    ],
    "Atividade de Assistência à Saúde": [
      "cuidados",
      "plantão",
      "plantão noturno",
      "ADMISSAO DO PACIENTE"
    ],
    "Parte do Corpo, Órgão ou Componente Orgânico": [
      "pupilas",
      "PUPILAS",
      "rima labial"
    ],
    "Organização Relacionada à Saúde": [
      "UI"
    ],
    "Sinal ou Sintoma": [
      "FEBRIL",
      "EDEMA",
      "EXSUDATO",
      "Torporoso",
      "taquidispneico",
      "espessa",
      "amarelada",
      "algia moderada",
      "INSTABILIDADE HEMODINÂMICA",
      "ABDOME AGUDO",
      "POUCO FOTO",
      "odor fétido"
    ],
    "Doença ou Síndrome": [
      "SEPSE",
      "MENISCO DISCOIDE CONGENITO",
      "HEMORRAGIAS INTRACEREBRAIS"
    ],
    "Conceito Temporal": [
      "PO"
    ],
    "Conceito Quantitativo": [
      "25%",
      "4",
      "9",
      "96%",
      "6 lts/min",
      "grande quantidade",
      "22 cm"
    ],
    "Procedimento Diagnóstico": [
      "MONITORIZADA",
      "RX",
      "Ausculta pulmo"
    ],
    "Atributo Clínico": [
      "FC",
      "SAT DE O2"
    ],
    "Negação": [
      "SEM"
    ],
    "Conceito Espacial": [
      "E"
    ],
    "Alimento": [
      "DIETA"
    ],
    "Função Patológica": [
      "EDEMA",
      "EXSUDATO"
    ],
    "Substância Corporal": [
      "EXSUDATO",
      "secreção",
      "secreção orotraqueal"
    ],
    "Grupo Profissional ou Ocupacional": [
      "assistênte social"
    ],
    "Lesão ou Envenenamento": [
      "FRATURA DOS OSSOS MALARES E MAXILARES",
      "FERIMENTO DO TORAX"
    ],
    "Função Fisiológica": [
      "diurese presente"
    ],
    "Processo Neoplásico": [
      "NEOPLASIA MALIGNA DOS OSSOS DO CRANIO E DA FACE",
      "NEOPLASIA MALIGNA DO CEREBRO EXCETO LOBOS E VENTRICULOS"
    ],
    "Substância Farmacológica": [
      "SF 0 , 9%"
    ],
    "Conceito Qualitativo": [
      "grande quantidade"
    ]
  },
  "labels": {
    "taquidispneico": {
      "capitulo": "22",
      "opcoes": []
    },
    "monitorizada": {
      "capitulo": "V",
      "opcoes": []
    },
    "torporoso": {
      "capitulo": "08",
      "opcoes": []
    },
    "espessa": {
      "capitulo": "21",
      "opcoes": []
    },
    "traqueostomizado": {
      "capitulo": "12",
      "opcoes": []
    },
    "pouco foto": {
      "capitulo": "21",
      "opcoes": []
    },
    "comunicativo": {
      "capitulo": "06",
      "opcoes": []
    },
    "obedece a comandos verbais": {
      "capitulo": "06",
      "opcoes": []
    },
    "fratura dos ossos malares e maxilares": {
      "capitulo": "15",
      "opcoes": []
    },
    "respiração espontânea": {
      "capitulo": "12",
      "opcoes": []
    },
    "algia moderada": {
      "capitulo": "21",
      "opcoes": []
    },
    "comunicativa": {
      "capitulo": "06",
      "opcoes": []
    },
    "amarelada": {
      "capitulo": "21",
      "opcoes": []
    },
    "instabilidade hemodinâmica": {
      "capitulo": "11",
      "opcoes": []
    },
    "fotorreagentes": {
      "capitulo": "08",
      "opcoes": []
    },
    "consciente": {
      "capitulo": "06",
      "opcoes": []
    },
    "neoplasia maligna dos ossos do cranio e da face": {
      "capitulo": "02",
      "opcoes": []
    },
    "exsudato": {
      "capitulo": "21",
      "opcoes": []
    },
    "abdome agudo": {
      "capitulo": "22",
      "opcoes": []
    },
    "edema": {
      "capitulo": "15",
      "opcoes": []
    },
    "cicatriz cirúrgica cefálica seca": {
      "capitulo": "21",
      "opcoes": []
    },
    "ferimento do torax": {
      "capitulo": "22",
      "opcoes": []
    },
    "orientada": {
      "capitulo": "06",
      "opcoes": []
    },
    "hemorragias intracerebrais": {
      "capitulo": "02",
      "opcoes": []
    },
    "odor fétido": {
      "capitulo": "21",
      "opcoes": []
    },
    "fc": {
      "capitulo": "V",
      "opcoes": []
    },
    "menisco discoide congenito": {
      "capitulo": "20",
      "opcoes": []
    },
    "sepse": {
      "capitulo": "01",
      "opcoes": []
    },
    "neoplasia maligna do cerebro exceto lobos e ventriculos": {
      "capitulo": "02",
      "opcoes": []
    }
  }
}