{
  "prontuario_id": 503,
  "text": "Às 08:25hs: Glasgow 14, pupilas isocóricas fotorreagentes, respiração espontânea, em névoa úmida 4 l/m, SpO2 92%, boa aceitação de dieta branda VO, acesso venoso central D com Amiodarona 11 ml/h + Noradrenalina 11 ml/h, monitorizada, estável hemodinamicamente, MV + sem R/A, abdome globoso, flácido, indolor a palpação, RHA + , SVD com diurese efetiva, evacuação ausente, úlcera sacra grau II, MMII pouco edemaciados, PAM em pedial E, extremidades bem perfundidas, higienizada e mobilizada no leito. ÀS 23:45: PELO ENFERMEIRO NOITE:  S: GLASGOW = 6, TRAQUEOSTOMIZADO, SUPORTADO POR DVA, SEM SEDAÇÃO MAIS DE 12 H. O: 10º DI REBAIXAMENTO DO NÍVEL DE CONSCIÊNCIA + SEPSE DE FOCO PULMONAR, CRÂNIO SIMÉTRICO, COURO CABELUDO ÍNTEGRO, FACE CORADA, PUPILAS ISOFOTORREAGENTES, D 9 SNE COM DIETA EM CURSO 75 ML/H EM BI, D 2 TRAQUEOSTOMIA APRESENTANDO DISCRETO SANGRAMENTO EM INCISÃO, EM VM MODO A/C PEEP = 5 cmH2O, FIO2 = 35%, SPO2 = 100%, SECREÇÃO TRAQUEOBRÔNQUICA SEROSSANGUINOLENTA EM POUCA QUANTIDADE, ASPIRAÇÃO COM SISTEMA FECHADO, MANTÉM CABECEIRA ELEVADA 45º, D 7 CATETER DE HD EM JID RECEBENDO PLANO DE NORADRENALINA 11 ML/H, HEPARINA 11 ML/H EM BI, MMSS EDEMACIADOS CACIFO III + LIBERAÇÃO DE TRANSUDATO EM POUCA QUANTIDADE, PAM EM ARTÉRIA ESQUERDA POSICIONAL, COM MÉDIA 160/66, FC 78 bpm, AFEBRIL 37º C, TÓRAX SIMÉTRICO, AUSCULTA PULMONAR CPP: RONCOS DIFUSOS, ABDOMEN DISTENDIDO E FLÁCIDO, SEM MASSA PALPÁVEL, RHA + , ÚLCERA SACRA ESTÁGIO III, ELIMINAÇÕES INTESTINAIS AUSENTES NO MOMENTO, SVD COM DIURESE EFETIVA COLORAÇÃO AMARELO NORMAL + PRESENÇA DE GRUMOS, BALANÇO + 872, MMII COM ÚLCERAS EM CALCÂNEO ESQUERDO, PERFUSÃO PERIFÉRICA PRESERVADA, MONITORIZADO COM ECG, PAM E OXIMETRIA DE PULSO, FAZ USO DE FILTRO DE BARREIRA / UMIDIFICADOR DE AR EM PRECAUÇÃO DE CONTATO PARA VRE, SEGUE CUIDADOS. A: DESMAME VM, DESMAME DVA. P: VIDE PRESCRIÇÃO DE ENFERMAGEM.",
  "entities": {
    "Abreviação": [
      "SpO2",
      "D",
      "R/A",
      "SVD",
      "PAM",
      "BI",
      "VM",
      "PEEP",
      "FIO2",
      "SPO2",
      "CPP",
      "MMII",
      "ECG",
      "boa aceitação de dieta branda VO",
      "MV +",
      "RHA +",
      "MMII pouco edemaciados",
      "SUPORTADO POR DVA",
      "SNE COM DIETA EM CURSO",
      "MODO A/C",
      "CATETER DE HD",
      "MMSS EDEMACIADOS",
      "BALANÇO + 872",
      "DESMAME VM",
      "DESMAME DVA"
    ],
    "Procedimento Terapêutico ou Preventivo": [
      "SpO2",
      "SVD",
      "TRAQUEOSTOMIZADO",
      "SEDAÇÃO",
      "TRAQUEOSTOMIA",
      "VM",
      "névoa úmida",
      "acesso venoso central",
      "mobilizada no leito",
      "SUPORTADO POR DVA",
      "SNE COM DIETA EM CURSO",
      "ASPIRAÇÃO COM SISTEMA FECHADO",
      "CABECEIRA ELEVADA 45º",
      "FILTRO DE BARREIRA",
      "UMIDIFICADOR DE AR",
      "PRECAUÇÃO DE CONTATO",
      "DESMAME VM",
      "DESMAME DVA"
    ],
    "Conceito Quantitativo": [
      "92%",
      "35%",
      "78",
      "4 l/m",
      "11 ml/h",
      "75 ML/H",
      "5 cmH2O",
      "POUCA QUANTIDADE",
      "11 ML/H",
      "MÉDIA 160/66",
      "37º C"
    ],
    "Conceito Espacial": [
      "D",
      "E",
      "ESQUERDA",
      "ESQUERDO"
    ],
    "Substância Química Orgânica": [
      "Amiodarona",
      "HEPARINA"
    ],
    "Substância Farmacológica": [
      "Amiodarona",
      "Noradrenalina",
      "HEPARINA",
      "PLANO DE NORADRENALINA"
    ],
    "Hormônio": [
      "Noradrenalina"
    ],
    "Achado": [
      "monitorizada",
      "flácido",
      "evacuação",
      "higienizada",
      "TRAQUEOSTOMIZADO",
      "FLÁCIDO",
      "pupilas isocóricas fotorreagentes",
      "respiração espontânea",
      "boa aceitação de dieta branda VO",
      "estável hemodinamicamente",
      "MV +",
      "RHA +",
      "diurese efetiva",
      "extremidades bem perfundidas",
      "CRÂNIO SIMÉTRICO",
      "COURO CABELUDO ÍNTEGRO",
      "FACE CORADA",
      "PUPILAS ISOFOTORREAGENTES",
      "DISCRETO SANGRAMENTO EM INCISÃO",
      "TÓRAX SIMÉTRICO",
      "MASSA PALPÁVEL",
      "DIURESE EFETIVA",
      "COLORAÇÃO AMARELO NORMAL",
      "PERFUSÃO PERIFÉRICA PRESERVADA"
    ],
    "Procedimento Diagnóstico": [
      "monitorizada",
      "palpação",
      "PAM",
      "MONITORIZADO",
      "ECG",
      "AUSCULTA PULMONAR",
      "OXIMETRIA DE PULSO"
    ],
    "Negação": [
      "sem",
      "indolor",
      "ausente",
      "SEM",
      "AUSENTES"
    ],
    "Sinal ou Sintoma": [
      "R/A",
      "globoso",
      "SEROSSANGUINOLENTA",
      "DISTENDIDO",
      "Glasgow 14",
      "MMII pouco edemaciados",
      "GLASGOW = 6",
      "REBAIXAMENTO DO NÍVEL DE CONSCIÊNCIA",
      "MMSS EDEMACIADOS",
      "LIBERAÇÃO DE TRANSUDATO",
      "RONCOS DIFUSOS",
      "PRESENÇA DE GRUMOS"
    ],
    "Localização ou Região Corporal": [
      "abdome",
      "CPP",
      "ABDOMEN",
      "MMII"
    ],
    "Dispositivo Médico": [
      "SVD",
      "BI",
      "acesso venoso central",
      "CATETER DE HD",
      "FILTRO DE BARREIRA",
      "UMIDIFICADOR DE AR"
    ],
    "Função Fisiológica": [
      "evacuação",
      "diurese efetiva",
      "ELIMINAÇÕES INTESTINAIS",
      "DIURESE EFETIVA"
    ],
    "Parte do Corpo, Órgão ou Componente Orgânico": [
      "pedial",
      "CALCÂNEO"
    ],
    "Grupo Profissional ou Ocupacional": [
      "ENFERMEIRO"
    ],
    "Conceito Temporal": [
      "NOITE",
      "NO MOMENTO"
    ],
    "Substância Biologicamente Ativa": [
      "HEPARINA"
    ],
    "Atributo Clínico": [
      "PAM"
    ],
    "Conceito Qualitativo": [
      "POSICIONAL",
      "grau II",
      "POUCA QUANTIDADE",
      "CACIFO III",
      "ESTÁGIO III"
    ],
    "Doença ou Síndrome": [
      "ÚLCERAS",
      "úlcera sacra",
      "SEPSE DE FOCO PULMONAR",
      "ÚLCERA SACRA"
    ],
    "Conceito Funcional": [
      "USO"
    ],
    "Bactéria": [
      "VRE"
    ],
    "Atividade de Assistência à Saúde": [
      "CUIDADOS",
      "PRESCRIÇÃO DE ENFERMAGEM"
    ],
    "Função de Organismo": [
      "diurese efetiva",
      "DIURESE EFETIVA"
    ],
    "Substância Corporal": [
      "SECREÇÃO TRAQUEOBRÔNQUICA"
    ],
    "Produto Intelectual": [
      "PRESCRIÇÃO DE ENFERMAGEM"
    ]
  },
  "labels": {
    "flácido": {
      "capitulo": "22",
      "opcoes": []
    },
    "distendido": {
      "capitulo": "12",
      "opcoes": []
    },
    "traqueostomizado": {
      "capitulo": "12",
      "opcoes": []
    },
    "úlcera sacra": {
      "capitulo": "14",
      "opcoes": []
    },
    "pupilas isofotorreagentes": {
      "capitulo": "21",
      "opcoes": []
    },
    "mmii pouco edemaciados": {
      "capitulo": "15",
      "opcoes": []
    },
    "evacuação": {
      "capitulo": "21",
      "opcoes": []
    },
    "massa palpável": {
      "capitulo": "21",
      "opcoes": []
    },
    "respiração espontânea": {
      "capitulo": "12",
      "opcoes": []
    },
    "pupilas isocóricas fotorreagentes": {
      "capitulo": "21",
      "opcoes": []
    },
    "glasgow = 6": {
      "capitulo": "06",
      "opcoes": []
    },
    "mv +": {
      "capitulo": "22",
      "opcoes": []
    },
    "roncos difusos": {
      "capitulo": "12",
      "opcoes": []
    },
    "sepse de foco pulmonar": {
      "capitulo": "12",
      "opcoes": []
    },
    "diurese efetiva": {
      "capitulo": "21",
      "opcoes": []
    },
    "vre": {
      "capitulo": "22",
      "opcoes": []
    },
    "glasgow 14": {
      "capitulo": "06",
      "opcoes": []
    },
    "presença de grumos": {
      "capitulo": "21",
      "opcoes": []
    },
    "serossanguinolenta": {
      "capitulo": "12",
      "opcoes": []
    },
    "liberação de transudato": {
      "capitulo": "21",
      "opcoes": []
    },
    "discreto sangramento em incisão": {
      "capitulo": "22",
      "opcoes": []
    },
    "globoso": {
      "capitulo": "15",
      "opcoes": []
    },
    "mmss edemaciados": {
      "capitulo": "15",
      "opcoes": []
    },
    "r/a": {
      "capitulo": "21",
      "opcoes": []
    },
    "úlceras": {
      "capitulo": "14",
      "opcoes": []
    },
    "rebaixamento do nível de consciência": {
      "capitulo": "06",
      "opcoes": []
    }
  }
}