{
  "prontuario_id": 336,
  "text": "Às 18:00hs: Realizado raio X de abdome, sonda posicionada, retiro o fio-guia e libero dieta. Enfª Florence Nightingale, XXXX. TRAUMATISMO INTRACRANIANO. Às 8H30: FC: 110 bpm; PA: 135/75 mmHg; SPO2 99%. Glasgow 15, pupilas isocóricas. SNE desligada para broncoscopia e religada na volta do exame. Respiração espontânea em névoa úmida a 4 l/min. Curativo em região infraclavicular limpo e seco. Fixador externo em úmero, inserção de fixador com sangramento em grande quantidade. CPP livres. FO em região abdominal limpa e seca, permanece sem curativo. Hematoma em ombro D, região lateral de tórax D, vertebral e braço D. Curativo em região vertebral com exsudato sanguinolento em média quantidade. FO em região escapular com exsudato sanguinolento. Curativo em flanco E limpo e seco externamente. Abdomen plano, RHA hiperativos. Acesso venoso periférico em dorso de pé E com infusão de SF gravitacional. Diurese em uropen 800 ml amarelo escuro. às 8h20: Retirado uropen, mantém fralda. Pele íntegra. perfusão periférica de retorno rapido. Mantém monitorização contínua. ac Florence Nightingale. TRAUMATISMOS MULTIPLOS NAO ESPECIFICADOS. Às 14:20H: CONSCIENTE, COMUNICATIVO, HIPOCORADO, DEAMBULANDO. ACEITANDO BEM DIETA VIA ORAL OFERTADA. ACESSO VENOSO PERIFÉRICO EM ANTEBRAÇO DIREITO SEM SINAIS FLOGISTICOS. ELIMINAÇÕES FISIOLÓGICAS PRESENTE. NEGA QUEIXAS ALGICAS. LIBERADA DIETA, POIS O MESMO SE ALIMENTOU PELA MANHA, NÃO FOI POSSIVEL REALIZAR ENDOSCOPIA. REAGENDADO PARA AMANHA (17/08), AS 15:20H, JEJUM A PARTIR DA MEIA-NOITE. ENFERMEIRA FLORENCE NIGHTINGALE; ESTAGIÁRIA: MARIA. MELENA.",
  "entities": {
    "Grupo Profissional ou Ocupacional": [
      "Enfª",
      "ENFERMEIRA"
    ],
    "Abreviação": [
      "Enfª",
      "FC",
      "bpm",
      "PA",
      "SPO2",
      "SNE",
      "FO",
      "CPP livres",
      "ombro D",
      "região lateral de tórax D",
      "braço D",
      "flanco E",
      "RHA hiperativos",
      "dorso de pé E",
      "infusão de SF gravitacional"
    ],
    "Atributo Clínico": [
      "FC",
      "PA",
      "SPO2"
    ],
    "Conceito Quantitativo": [
      "110",
      "99%",
      "135/75 mmHg",
      "4 l/min",
      "800 ml"
    ],
    "Dispositivo Médico": [
      "SNE",
      "Curativo",
      "curativo",
      "uropen",
      "fralda",
      "Fixador externo em úmero",
      "Acesso venoso periférico",
      "ACESSO VENOSO PERIFÉRICO"
    ],
    "Procedimento Terapêutico ou Preventivo": [
      "desligada",
      "broncoscopia",
      "religada",
      "Curativo",
      "curativo",
      "JEJUM",
      "retiro o fio-guia",
      "libero dieta",
      "névoa úmida",
      "Fixador externo em úmero",
      "Acesso venoso periférico",
      "infusão de SF gravitacional",
      "Retirado uropen",
      "ACESSO VENOSO PERIFÉRICO"
    ],
    "Procedimento Diagnóstico": [
      "broncoscopia",
      "exame",
      "ENDOSCOPIA",
      "raio X de abdome",
      "monitorização contínua"
    ],
    "Achado": [
      "limpo",
      "seco",
      "sangramento",
      "limpa",
      "seca",
      "CONSCIENTE",
      "COMUNICATIVO",
      "DEAMBULANDO",
      "sonda posicionada",
      "Glasgow 15",
      "pupilas isocóricas",
      "Respiração espontânea",
      "CPP livres",
      "amarelo escuro",
      "Pele íntegra",
      "perfusão periférica de retorno rapido",
      "ACEITANDO BEM DIETA VIA ORAL",
      "ELIMINAÇÕES FISIOLÓGICAS PRESENTE"
    ],
    "Lesão ou Envenenamento": [
      "FO",
      "TRAUMATISMO INTRACRANIANO",
      "TRAUMATISMOS MULTIPLOS"
    ],
    "Negação": [
      "sem"
    ],
    "Sinal ou Sintoma": [
      "Hematoma",
      "HIPOCORADO",
      "MELENA",
      "RHA hiperativos",
      "SINAIS FLOGISTICOS",
      "QUEIXAS ALGICAS"
    ],
    "Função Patológica": [
      "Hematoma"
    ],
    "Localização ou Região Corporal": [
      "vertebral",
      "Abdomen",
      "região infraclavicular",
      "região abdominal",
      "região lateral de tórax D",
      "região vertebral",
      "região escapular",
      "flanco E",
      "dorso de pé E"
    ],
    "Conceito Espacial": [
      "externamente"
    ],
    "Função Fisiológica": [
      "Diurese",
      "ELIMINAÇÕES FISIOLÓGICAS PRESENTE"
    ],
    "Objeto Manufaturado": [
      "fralda"
    ],
    "Alimento": [
      "DIETA"
    ],
    "Parte do Corpo, Órgão ou Componente Orgânico": [
      "ombro D",
      "braço D",
      "ANTEBRAÇO DIREITO"
    ]
  },
  "labels": {
    "queixas algicas": {
      "capitulo": "06",
      "opcoes": []
    },
    "rha hiperativos": {
      "capitulo": "21",
      "opcoes": []
    },
    "sangramento": {
      "capitulo": "22",
      "opcoes": []
    },
    "hematoma": {
      "capitulo": "22",
      "opcoes": []
    },
    "traumatismo intracraniano": {
      "capitulo": "08",
      "opcoes": []
    },
    "comunicativo": {
      "capitulo": "06",
      "opcoes": []
    },
    "deambulando": {
      "capitulo": "06",
      "opcoes": []
    },
    "traumatismos multiplos": {
      "capitulo": "22",
      "opcoes": []
    },
    "melena": {
      "capitulo": "14",
      "opcoes": []
    },
    "sinais flogisticos": {
      "capitulo": "21",
      "opcoes": []
    },
    "glasgow 15": {
      "capitulo": "08",
      "opcoes": []
    },
    "consciente": {
      "capitulo": "06",
      "opcoes": []
    },
    "hipocorado": {
      "capitulo": "06",
      "opcoes": []
    },
    "fo": {
      "capitulo": "22",
      "opcoes": []
    },
    "pupilas isocóricas": {
      "capitulo": "08",
      "opcoes": []
    }
  }
}