{
  "prontuario_id": 541,
  "text": "Às 13:26: REALIZADO PASSAGEM SONDA VESICAL DEMORA. NO MOMENTO, COM DEBITO DE 50 ML. PROCEDIMENTO SEM INTERCORRENCIAS, SEGUE EM OBSERVACÃO. Às 00:02h: Paciente com a prescrição de 30g de imunoglobulina 6 frascos, porém administrado apenas 4 frascos, segundo a farmacêutica, médico, a farmacia não dispunha da dose total na data de hoje. Às 9:30: SNE TRACIONADA RETIRADA. REPASSO SEM INTERCORRÊNCIA NO PROCEDIMENTO. RETIRO FIO-GUIA. SOLICITO RAIO-X P/ AVALIAÇÃO DA POSIÇÃO. Às 16:40H: Provinda do PS, interna para pré-operatório de hepatectomia parcial agendada para amanhã. Admissão: FC 74 bpm, FR 16 rpm, PA 122/78 (89), Sat 94%. Glasgow 15, pupilas isocóricas. Nega queixas álgicas. Em ar ambiente, boa aceitação de dieta VO leve. CPP sem RA. Abdomen flácido, RHA +. Diurese espontânea. Evacuação semi-pastosa contínua. Mobilizando ativamente 4 membros. Extremidades aquecidas e bem perfundidas, sem edemas. Instalado monitorização contínua de parâmetros de PA não invasiva, cardioscopia e oximetria de pulso. Segue sob cuidadso intensivos. # Na presença do esposo, entregue óculos, par de chinelos, próteses dentárias (superior e inferior) e roupa íntima. # Orientado para jejum absoluto após 00H. 1º DI no PS com hx de dispnéia e obesidade mórbida. Em tto pela clínica médica. Hx prévia de TEP com tto no HT. Sedado, pupilas isomióticas e fotorreagentes, intubado com cân 7,5 em RL = 24 cm, uso de filtro de barreira e trach care, em VM modo PCV 35, FiO2 = 80%, PEEP = 7, mantendo VC = 730 ml. SOG aberta com pouca estase de aspecto bilioso. Mantém MCC + oximetria digital de pulso + PNI contínuos. AP com MV +, presença de crepitantes difusos, expansão torácica simétrica. Acesso venoso periférico em fossa cubital D. com infusão contínua de sedação em BI. dormonid 40 ml/h e fentanil à 10 ml/h. Abdômen globoso e levemente distendido com discreto edema, tenso a palpação e de cor enegrecida, RHA +. SVD efetiva em poliúria (2450 ml das 19 às 03:30h) de aspecto colúrico com grumos. Edema importante de bolsa escrotal. MMII com importante hiperemia e edemaciados, extremidades aquecidas e perfundidas. Permanece em sala de poli sob cuidados intensivos de enfermagem. Aguarda vaga em UTI. # Realizou USG de abdômen na sala de poli. SSVV às 03:30h: PA = 110/58 mmhg, FC = 71 bpm, SpO2 = 93%, T = 35,9° C.",
  "entities": {
    "Função Fisiológica": [
      "DEBITO",
      "Diurese espontânea"
    ],
    "Achado": [
      "DEBITO",
      "aquecidas",
      "Sedado",
      "fotorreagentes",
      "perfundidas",
      "Glasgow 15",
      "pupilas isocóricas",
      "boa aceitação de dieta VO leve",
      "RHA +",
      "Diurese espontânea",
      "Mobilizando ativamente 4 membros",
      "bem perfundidas",
      "MV +",
      "expansão torácica simétrica",
      "SVD efetiva"
    ],
    "Procedimento Terapêutico ou Preventivo": [
      "PROCEDIMENTO",
      "Sedado",
      "VM",
      "FiO2",
      "PEEP",
      "PASSAGEM SONDA VESICAL DEMORA",
      "SNE TRACIONADA RETIRADA",
      "RETIRO FIO-GUIA",
      "hepatectomia parcial",
      "Mobilizando ativamente 4 membros",
      "filtro de barreira",
      "trach care",
      "modo PCV",
      "SOG aberta",
      "Acesso venoso periférico",
      "infusão contínua de sedação",
      "SVD efetiva"
    ],
    "Sinal ou Sintoma": [
      "INTERCORRENCIAS",
      "INTERCORRÊNCIA",
      "RA",
      "edemas",
      "dispnéia",
      "globoso",
      "poliúria",
      "grumos",
      "edemaciados",
      "queixas álgicas",
      "Evacuação semi-pastosa contínua",
      "pouca estase",
      "aspecto bilioso",
      "crepitantes difusos",
      "levemente distendido",
      "discreto edema",
      "tenso a palpação",
      "cor enegrecida",
      "aspecto colúrico",
      "importante hiperemia"
    ],
    "Atividade de Assistência à Saúde": [
      "OBSERVACÃO",
      "administrado",
      "SOLICITO",
      "cuidadso intensivos",
      "cuidados intensivos de enfermagem"
    ],
    "Paciente ou Grupo com Deficiência": [
      "Paciente"
    ],
    "Produto Intelectual": [
      "prescrição"
    ],
    "Conceito Quantitativo": [
      "30g",
      "74",
      "16",
      "122/78",
      "89",
      "94%",
      "35",
      "80%",
      "7",
      "110/58",
      "71",
      "93%",
      "50 ML",
      "6 frascos",
      "4 frascos",
      "24 cm",
      "730 ml",
      "40 ml/h",
      "10 ml/h",
      "2450 ml",
      "35 , 9° C"
    ],
    "Substância Farmacológica": [
      "imunoglobulina",
      "dormonid",
      "fentanil"
    ],
    "Aminoácido, Peptídeo ou Proteína": [
      "imunoglobulina"
    ],
    "Fator Imunológico": [
      "imunoglobulina"
    ],
    "Grupo Profissional ou Ocupacional": [
      "farmacêutica",
      "médico"
    ],
    "Organização Relacionada à Saúde": [
      "farmacia",
      "PS",
      "UTI",
      "clínica médica",
      "sala de poli"
    ],
    "Procedimento Diagnóstico": [
      "RAIO-X",
      "cardioscopia",
      "MCC",
      "AP",
      "monitorização contínua de parâmetros",
      "oximetria de pulso",
      "oximetria digital de pulso",
      "PNI contínuos",
      "USG de abdômen"
    ],
    "Abreviação": [
      "PS",
      "FC",
      "bpm",
      "FR",
      "rpm",
      "PA",
      "Sat",
      "CPP",
      "RA",
      "hx",
      "Hx",
      "TEP",
      "RL",
      "VM",
      "FiO2",
      "PEEP",
      "VC",
      "MCC",
      "AP",
      "BI",
      "MMII",
      "UTI",
      "SSVV",
      "mmhg",
      "SpO2",
      "T",
      "SNE TRACIONADA RETIRADA",
      "boa aceitação de dieta VO leve",
      "RHA +",
      "intubado com cân",
      "modo PCV",
      "SOG aberta",
      "PNI contínuos",
      "MV +",
      "fossa cubital D",
      "SVD efetiva",
      "sala de poli",
      "USG de abdômen"
    ],
    "Conceito Temporal": [
      "pré-operatório"
    ],
    "Atributo Clínico": [
      "FC",
      "FR",
      "PA",
      "Sat",
      "RL",
      "SSVV",
      "SpO2",
      "T"
    ],
    "Negação": [
      "sem"
    ],
    "Localização ou Região Corporal": [
      "Abdomen",
      "Extremidades",
      "Abdômen",
      "MMII",
      "extremidades",
      "fossa cubital D"
    ],
    "Função Patológica": [
      "edemas",
      "edemaciados"
    ],
    "Grupo Familiar": [
      "esposo"
    ],
    "Objeto Manufaturado": [
      "óculos",
      "par de chinelos",
      "próteses dentárias",
      "roupa íntima"
    ],
    "Doença ou Síndrome": [
      "TEP",
      "obesidade mórbida"
    ],
    "Parte do Corpo, Órgão ou Componente Orgânico": [
      "pupilas",
      "bolsa escrotal"
    ],
    "Dispositivo de Administração de Medicamento": [
      "BI"
    ],
    "Substância Química Orgânica": [
      "dormonid",
      "fentanil"
    ],
    "Material Biomédico ou Odontológico": [
      "próteses dentárias"
    ],
    "Dispositivo Médico": [
      "intubado com cân",
      "filtro de barreira",
      "trach care",
      "Acesso venoso periférico"
    ]
  },
  "labels": {
    "ra": {
      "capitulo": "X",
      "opcoes": []
    },
    "debito": {
      "capitulo": "11",
      "opcoes": []
    },
    "rha +": {
      "capitulo": "14",
      "opcoes": []
    },
    "edemas": {
      "capitulo": "15",
      "opcoes": []
    },
    "levemente distendido": {
      "capitulo": "13",
      "opcoes": []
    },
    "aspecto bilioso": {
      "capitulo": "08",
      "opcoes": []
    },
    "tenso a palpação": {
      "capitulo": "21",
      "opcoes": []
    },
    "grumos": {
      "capitulo": "21",
      "opcoes": []
    },
    "pouca estase": {
      "capitulo": "21",
      "opcoes": []
    },
    "discreto edema": {
      "capitulo": "15",
      "opcoes": []
    },
    "aspecto colúrico": {
      "capitulo": "21",
      "opcoes": []
    },
    "mv +": {
      "capitulo": "11",
      "opcoes": []
    },
    "tep": {
      "capitulo": "04",
      "opcoes": []
    },
    "edemaciados": {
      "capitulo": "15",
      "opcoes": []
    },
    "glasgow 15": {
      "capitulo": "06",
      "opcoes": []
    },
    "fotorreagentes": {
      "capitulo": "08",
      "opcoes": []
    },
    "obesidade mórbida": {
      "capitulo": "05",
      "opcoes": []
    },
    "poliúria": {
      "capitulo": "21",
      "opcoes": []
    },
    "expansão torácica simétrica": {
      "capitulo": "11",
      "opcoes": []
    },
    "svd efetiva": {
      "capitulo": "22",
      "opcoes": []
    },
    "evacuação semi-pastosa contínua": {
      "capitulo": "21",
      "opcoes": []
    },
    "intercorrência": {
      "capitulo": "X",
      "opcoes": []
    },
    "dispnéia": {
      "capitulo": "12",
      "opcoes": []
    },
    "globoso": {
      "capitulo": "13",
      "opcoes": []
    },
    "importante hiperemia": {
      "capitulo": "15",
      "opcoes": []
    },
    "crepitantes difusos": {
      "capitulo": "22",
      "opcoes": []
    },
    "intercorrencias": {
      "capitulo": "X",
      "opcoes": []
    },
    "sedado": {
      "capitulo": "06",
      "opcoes": []
    },
    "pupilas isocóricas": {
      "capitulo": "08",
      "opcoes": []
    },
    "cor enegrecida": {
      "capitulo": "21",
      "opcoes": []
    }
  }
}