{
  "prontuario_id": 900,
  "text": "Às 12:30HS: CONSCIENTE. COMUNICATIVO. EUPINEICO. DEAMBULANDO. NÃO REFERE ALGIA. CURATIVO EM REGIÃO FRONTAL LIMPO E SECO EXTERNAMENTE. ACEITOU A DIETA OFERECIDA. CATETER VENOSO PERIFERICO EM MSE SALINIZADO. CURATIVO EM MÃO (d) LIMPO E SECO EXTERNAMENTE. DIURESE ESPONTANEA PRESENTE. SEGUE CUIDADOS. # FAF de tórax transfixante / Antecedentes de diabetes. # 07º DI. # 06º D UTI. # 06º D IOT sob VM. # 06º PO de drenagem torácica + toracotomia com segmentação a esquerda. # Janela pericardica negativa. # 06º CNG em narina D. # 06º D CVC em JID. # 06º D PAM inguinal D. # 06º D dreno torácico posterior E, retirado anterior dia 04/03/12. SSVV PA 138/75, PAM 88, FC 90, FR 15, PVC 88. T 36,7º. Pupilas isofoto +; obedece a comandos verbais; mantém cateter nasogástrico em narina D com diéta em curso sob BI à 75 ml/h; permanece entubado dependente de VM com PEEP 5, FIO2 35%, SPO2 96%, faz uso de filtro de barreiras; secreção em TOT espessa amarelada em moderada quantidade, sistema de aspiração aberto; CPP com MV + diminuidos em bases; CVC em JID sem sinais flogisticos, protegido com curativo filme transparente, com plano básico de hidratação; dependente de Noradrenalina à 21 ml/h com plano dobrado sob BI, hemodinâmicamente instável; PAM inguinal D funcionante com sem sinais de cianose; mantém dreno torácico posterior à esquerda oscilante sem fuga aérea com débito hemático em moderada quantidade, inserção do mesmo com curativo oclusivo, incisão cx em HTE limpa em seca; abdomen globoso flácido sem massa palpável, RHA +; evacuações presentes; cateter vesical de demora com diurése efetiva de cor clara com presença discreta de grumos; pele íntegra para úlceras por pressão; perfusão periferica lentificada; monitorizado com multiparâmetros.",
  "entities": {
    "Achado": [
      "CONSCIENTE",
      "COMUNICATIVO",
      "EUPINEICO",
      "DEAMBULANDO",
      "LIMPO",
      "SECO",
      "SALINIZADO",
      "secreção",
      "funcionante",
      "limpa",
      "seca",
      "flácido",
      "ACEITOU A DIETA",
      "DIURESE ESPONTANEA PRESENTE",
      "Pupilas isofoto +",
      "obedece a comandos verbais",
      "sistema de aspiração aberto",
      "MV + diminuidos em bases",
      "massa palpável",
      "RHA +",
      "evacuações presentes",
      "diurése efetiva",
      "cor clara",
      "pele íntegra"
    ],
    "Sinal ou Sintoma": [
      "ALGIA",
      "oscilante",
      "globoso",
      "espessa amarelada",
      "MV + diminuidos em bases",
      "sinais flogisticos",
      "hemodinâmicamente instável",
      "sinais de cianose",
      "fuga aérea",
      "débito hemático",
      "presença discreta de grumos",
      "perfusão periferica lentificada"
    ],
    "Dispositivo Médico": [
      "CURATIVO",
      "CNG",
      "CVC",
      "TOT",
      "CATETER VENOSO PERIFERICO",
      "cateter nasogástrico",
      "filtro de barreiras",
      "curativo filme transparente",
      "dreno torácico posterior",
      "curativo oclusivo",
      "cateter vesical de demora"
    ],
    "Procedimento Terapêutico ou Preventivo": [
      "CURATIVO",
      "SALINIZADO",
      "IOT",
      "VM",
      "CNG",
      "CVC",
      "entubado",
      "PEEP",
      "FIO2",
      "SPO2",
      "TOT",
      "CATETER VENOSO PERIFERICO",
      "drenagem torácica",
      "toracotomia com segmentação a esquerda",
      "dreno torácico posterior",
      "cateter nasogástrico",
      "diéta em curso",
      "dependente de VM",
      "filtro de barreiras",
      "sistema de aspiração aberto",
      "curativo filme transparente",
      "plano básico de hidratação",
      "curativo oclusivo",
      "cateter vesical de demora"
    ],
    "Conceito Espacial": [
      "EXTERNAMENTE",
      "d"
    ],
    "Abreviação": [
      "MSE",
      "d",
      "UTI",
      "IOT",
      "VM",
      "PO",
      "CNG",
      "CVC",
      "JID",
      "PAM",
      "SSVV",
      "PA",
      "FC",
      "FR",
      "PVC",
      "T",
      "BI",
      "PEEP",
      "FIO2",
      "SPO2",
      "TOT",
      "CPP",
      "HTE",
      "FAF de tórax transfixante",
      "narina D",
      "inguinal D",
      "Pupilas isofoto +",
      "dependente de VM",
      "MV + diminuidos em bases",
      "incisão cx",
      "RHA +"
    ],
    "Localização ou Região Corporal": [
      "MSE",
      "CPP",
      "abdomen",
      "REGIÃO FRONTAL",
      "inguinal D"
    ],
    "Parte do Corpo, Órgão ou Componente Orgânico": [
      "MÃO",
      "JID"
    ],
    "Atividade de Assistência à Saúde": [
      "CUIDADOS",
      "retirado"
    ],
    "Doença ou Síndrome": [
      "diabetes",
      "úlceras por pressão ;"
    ],
    "Organização Relacionada à Saúde": [
      "UTI"
    ],
    "Conceito Temporal": [
      "PO"
    ],
    "Negação": [
      "negativa",
      "sem"
    ],
    "Procedimento Diagnóstico": [
      "PAM",
      "monitorizado com multiparâmetros"
    ],
    "Atributo Clínico": [
      "SSVV",
      "PA",
      "PAM",
      "FC",
      "FR",
      "PVC",
      "T"
    ],
    "Conceito Quantitativo": [
      "138/75",
      "88",
      "90",
      "15",
      "5",
      "35%",
      "96%",
      "36 , 7º",
      "75 ml/h",
      "21 ml/h"
    ],
    "Dispositivo de Administração de Medicamento": [
      "BI"
    ],
    "Substância Corporal": [
      "secreção"
    ],
    "Função Fisiológica": [
      "DIURESE ESPONTANEA PRESENTE",
      "evacuações presentes",
      "diurése efetiva"
    ],
    "Lesão ou Envenenamento": [
      "FAF de tórax transfixante",
      "incisão cx"
    ],
    "Espaço ou Junção Corporal": [
      "narina D"
    ],
    "Conceito Qualitativo": [
      "moderada quantidade"
    ],
    "Substância Farmacológica": [
      "de Noradrenalina"
    ]
  },
  "labels": {
    "pele íntegra": {
      "capitulo": "14",
      "opcoes": []
    },
    "úlceras por pressão ;": {
      "capitulo": "15",
      "opcoes": []
    },
    "flácido": {
      "capitulo": "15",
      "opcoes": []
    },
    "mv + diminuidos em bases": {
      "capitulo": "21",
      "opcoes": []
    },
    "débito hemático": {
      "capitulo": "12",
      "opcoes": []
    },
    "sistema de aspiração aberto": {
      "capitulo": "22",
      "opcoes": []
    },
    "diabetes": {
      "capitulo": "05",
      "opcoes": []
    },
    "fuga aérea": {
      "capitulo": "22",
      "opcoes": []
    },
    "oscilante": {
      "capitulo": "22",
      "opcoes": []
    },
    "evacuações presentes": {
      "capitulo": "21",
      "opcoes": []
    },
    "secreção": {
      "capitulo": "21",
      "opcoes": []
    },
    "massa palpável": {
      "capitulo": "15",
      "opcoes": []
    },
    "incisão cx": {
      "capitulo": "22",
      "opcoes": []
    },
    "perfusão periferica lentificada": {
      "capitulo": "21",
      "opcoes": []
    },
    "sinais flogisticos": {
      "capitulo": "21",
      "opcoes": []
    },
    "presença discreta de grumos": {
      "capitulo": "21",
      "opcoes": []
    },
    "sinais de cianose": {
      "capitulo": "22",
      "opcoes": []
    },
    "hemodinâmicamente instável": {
      "capitulo": "11",
      "opcoes": []
    },
    "globoso": {
      "capitulo": "15",
      "opcoes": []
    },
    "espessa amarelada": {
      "capitulo": "21",
      "opcoes": []
    },
    "faf de tórax transfixante": {
      "capitulo": "22",
      "opcoes": []
    }
  }
}