{
  "prontuario_id": 779,
  "text": "Às 17:18 HS: PROVENIENTE DO PS ÁS 16:00, DEAMBULANDO, CONSCIENTE, ORIENTADO, EUPNEICO, SEM QUEIXAS ALGICAS, AGUARDA CONDUTA MÉDICA. ENF FLORENCE NIGHTINGALE, COREN XXXX. TRAUMATISMO INTRACRANIANO NAO ESPECIFICADO. Às 16h: Encaminhado ao CC, de maca, consciente, comunicativo, eupneico, em ar ambiente, jejum, acesso venoso periferico em MSD sem sinais flogisticos e salinizado, tala tipo canadense em MSE, refere eliminações presentes, refere algia ao movimento de MSE.  Enfª Florence Nightingale. FRATURA DO OMBRO E DO BRACO. Às 15:40hs: Realizado passagem de SNE, realizado raio-X, confirmado posicionamento, retirado o guia e liberada dieta. Enfª Florence Nightingale, XXXX. ACIDENTE VASCULAR CEREBRAL NAO ESPECIFICADO COMO HEMORRAGICO OU ISQUEMICO. Às 7:40 H: ENCAMINHADA PARA TAC DE CRÂNIO, SEM INTERCORRÊNCIAS. DOR ABDOMINAL E PELVICA. Às 15H: Realizada infusão de 02 concentrados de hemácias sem intercorrências. Enfª Florence Nightingale. TRAUMATISMOS MULTIPLOS NAO ESPECIFICADOS. Pcte já encontra-se em ** Precaução de Contato **.  ** Agora, com nova cultura de Aspirado Traqueal do dia 07/06/10, com crescimento de ** Klebsiella ozaenae MR. ** ** Mantê-lo em Precaução de Contato até alta hospitalar e reforçar Higienização das Mãos. ** EDEMA CEREBRAL. Às 18:31: AGENDADO PARA AMANHA, 25/11, ÁS 13:00, TAC DE TORÁX, ORIENTADO CLIENTE A ENTRAR EM JEJUM A PARTIR DAS 24:00, RELATA NÃO SER ALÉRGICO A FRUTOS DO MAR, SE FOR NECESSÁRIO CONTRASTE. REALIZOU, NO PERIODO DA MANHA, RX DE TORÁX E AGUARDANDO LIBERAÇÃO DO CONVENIO DA ESPIROMETRIA. ENFª FLORENCE NIGHTINGALE, XXXX. DERRAME PLEURAL NAO CLASSIFICADO EM OUTRA PARTE.",
  "entities": {
    "Organização Relacionada à Saúde": [
      "PS",
      "CC",
      "CONVENIO"
    ],
    "Abreviação": [
      "PS",
      "ENF",
      "CC",
      "MSD",
      "MSE",
      "Enfª",
      "Pcte",
      "ENFª",
      "passagem de SNE",
      "TAC DE CRÂNIO",
      "02 concentrados de hemácias",
      "crescimento de ** Klebsiella ozaenae MR",
      "TAC DE TORÁX",
      "RX DE TORÁX"
    ],
    "Achado": [
      "DEAMBULANDO",
      "CONSCIENTE",
      "ORIENTADO",
      "EUPNEICO",
      "consciente",
      "comunicativo",
      "eupneico",
      "jejum",
      "eliminações presentes",
      "SER ALÉRGICO A FRUTOS DO MAR"
    ],
    "Negação": [
      "SEM",
      "sem",
      "NÃO"
    ],
    "Grupo Profissional ou Ocupacional": [
      "ENF",
      "Enfª",
      "ENFª"
    ],
    "Dispositivo Médico": [
      "maca",
      "acesso venoso periferico",
      "tala tipo canadense"
    ],
    "Procedimento Terapêutico ou Preventivo": [
      "jejum",
      "JEJUM",
      "acesso venoso periferico",
      "e salinizado",
      "tala tipo canadense",
      "passagem de SNE",
      "retirado o guia",
      "02 concentrados de hemácias",
      "Precaução de Contato",
      "Higienização das Mãos"
    ],
    "Localização ou Região Corporal": [
      "MSD",
      "MSE",
      "ABDOMINAL",
      "PELVICA"
    ],
    "Procedimento Diagnóstico": [
      "raio-X",
      "ESPIROMETRIA",
      "TAC DE CRÂNIO",
      "TAC DE TORÁX",
      "RX DE TORÁX"
    ],
    "Sinal ou Sintoma": [
      "DOR",
      "QUEIXAS ALGICAS",
      "sinais flogisticos",
      "algia ao movimento"
    ],
    "Paciente ou Grupo com Deficiência": [
      "Pcte",
      "CLIENTE"
    ],
    "Função Fisiológica": [
      "eliminações presentes"
    ],
    "Lesão ou Envenenamento": [
      "FRATURA DO OMBRO E DO BRACO",
      "TRAUMATISMOS MULTIPLOS"
    ],
    "Doença ou Síndrome": [
      "ACIDENTE VASCULAR CEREBRAL",
      "EDEMA CEREBRAL",
      "DERRAME PLEURAL"
    ],
    "Procedimento Laboratorial": [
      "cultura de Aspirado Traqueal"
    ],
    "Bactéria": [
      "crescimento de ** Klebsiella ozaenae MR"
    ],
    "Resultado Laboratorial ou de Teste": [
      "crescimento de ** Klebsiella ozaenae MR"
    ],
    "Atividade de Assistência à Saúde": [
      "alta hospitalar"
    ]
  },
  "labels": {
    "edema cerebral": {
      "capitulo": "08",
      "opcoes": []
    },
    "derrame pleural": {
      "capitulo": "12",
      "opcoes": []
    },
    "queixas algicas": {
      "capitulo": "21",
      "opcoes": []
    },
    "algia ao movimento": {
      "capitulo": "15",
      "opcoes": []
    },
    "fratura do ombro e do braco": {
      "capitulo": "15",
      "opcoes": []
    },
    "ser alérgico a frutos do mar": {
      "capitulo": "21",
      "opcoes": []
    },
    "acidente vascular cerebral": {
      "capitulo": "08",
      "opcoes": []
    },
    "dor": {
      "capitulo": "21",
      "opcoes": []
    },
    "sinais flogisticos": {
      "capitulo": "22",
      "opcoes": []
    },
    "traumatismos multiplos": {
      "capitulo": "22",
      "opcoes": []
    },
    "eliminações presentes": {
      "capitulo": "21",
      "opcoes": []
    },
    "crescimento de ** klebsiella ozaenae mr**: ": {
      "capitulo": "01",
      "opcoes": []
    }
  }
}