{
  "prontuario_id": 786,
  "text": "20:45h PERMANECE ECTÉRICO, GLASGOW 15, EM NÉVOA UMIDA, SATURANDO SATISFATORIAMENTE NO MOMENTO 95%. AUSCULTA PULMONAR MV COM RONCOS DIFUSOS. ABDOMEM FLACIDO, RHA +, SNE COM DIETA 75 ML/H. ACESSO VENOSO PERIFERICO EM MSD COM PLANO BASICO DE HIDRATAÇÃO. SVD EFETIVA COM DEBITO CONCENTRADO. MONITORIZAÇÃO DE MULTIPLOS PARAMETROS CONFORME ROTINA DA UTI. EDEMA CEREBRAL. 13:10h Realizo passagem de SNE para alimentação; procedimento realizado sem intercorrência. Solicito RX de abdome simples no leito para 14 h. Aguarda realização de RX para liberação da dieta. TRAUMATISMO NAO ESPECIFICADO. 01:12h: Paciente orientado a manter jejum após as 24h para exame de Tomografia de abdomem  com contraste em 29/07 pela manhã. Enf FLORENCE NIGHTINGALE, TRAUMATISMO INTRACRANIANO. 7:48 H CONSCIENTE, ORIENTADO, VERBALIZANDO, MOBILIZANDO ATIVAMENTE OS MEMBROS. PERMANECE COM NÉVOA ÚMIDA 5 L/MIN, CREPITAÇÕES E BOLHOSOS  DIFUSPS, SOROTERAPIA EM ACESSO VENOSO CENTRAL DIREITO SENDO INFUNDIDO SG 5% 21 ML/H, ABDOME GLOBOSO, RHA PRESENTES, SVD URINA EFETIVA. MONITORIZADO, OXIMETRIA DE PULSO, HEMODINAMICAMENTE ESTÁVEL. EXAME GERAL E INVESTIGACAO DE PESSOAS SEM QUEIXAS OU DIAGNOSTICO RELATADO. 02:10h:  Encaminhada para realização de RNM de crânio as 23h na clínica XXXX acomapnhado pela enfermagem, retornando as 02h, sem intercorrencias. Enf FLORENCE NIGHTINGALE, CEFALEIA. 03:00 H CLIENTE CONSCIENTE, EUPNEICA, AFEBRIL, REPOUSO, ORIENTADA. ACEITA DIETA OFERECIDA. MANTEM ACESSO PERIFERICO COM SOROTERAPIA. REFERE PARALISIA EM MIE. DIURESE ESPONTANEA PRESENTE.  SEGUE EM OBSERVAÇÃO E CUIDADOS.  ENFª FLORENCE NIGHTINGALE, COREN XXXX. ESCLEROSE MULTIPLA.",
  "entities": {
    "Sinal ou Sintoma": [
      "ECTÉRICO",
      "intercorrência",
      "QUEIXAS",
      "intercorrencias",
      "CEFALEIA",
      "PARALISIA",
      "RONCOS DIFUSOS",
      "CREPITAÇÕES E BOLHOSOS DIFUSPS"
    ],
    "Atributo Clínico": [
      "SATURANDO"
    ],
    "Conceito Quantitativo": [
      "95%",
      "75 ML/H",
      "5 L/MIN",
      "21 ML/H"
    ],
    "Abreviação": [
      "MV",
      "MSD",
      "UTI",
      "RX",
      "Enf",
      "SVD",
      "MIE",
      "ENFª",
      "RHA +",
      "SNE COM DIETA",
      "SVD EFETIVA",
      "RX de abdome simples",
      "SG 5%",
      "RHA PRESENTES",
      "RNM de crânio"
    ],
    "Localização ou Região Corporal": [
      "ABDOMEM",
      "MSD",
      "ABDOME",
      "MIE"
    ],
    "Organização Relacionada à Saúde": [
      "UTI",
      "clínica"
    ],
    "Dispositivo Médico": [
      "SNE",
      "SVD",
      "ACESSO VENOSO PERIFERICO",
      "ACESSO VENOSO CENTRAL DIREITO",
      "ACESSO PERIFERICO"
    ],
    "Atividade de Assistência à Saúde": [
      "procedimento",
      "manter",
      "Encaminhada",
      "OBSERVAÇÃO",
      "CUIDADOS"
    ],
    "Procedimento Terapêutico ou Preventivo": [
      "procedimento",
      "jejum",
      "SOROTERAPIA",
      "SVD",
      "REPOUSO",
      "NÉVOA UMIDA",
      "SNE COM DIETA",
      "ACESSO VENOSO PERIFERICO",
      "PLANO BASICO DE HIDRATAÇÃO",
      "liberação da dieta",
      "NÉVOA ÚMIDA",
      "ACESSO VENOSO CENTRAL DIREITO",
      "ACESSO PERIFERICO",
      "COM SOROTERAPIA"
    ],
    "Negação": [
      "sem",
      "SEM",
      "AFEBRIL"
    ],
    "Objeto Manufaturado": [
      "leito"
    ],
    "Procedimento Diagnóstico": [
      "RX",
      "MONITORIZADO",
      "AUSCULTA PULMONAR",
      "MONITORIZAÇÃO DE MULTIPLOS PARAMETROS",
      "RX de abdome simples",
      "Tomografia de abdomem com contraste",
      "OXIMETRIA DE PULSO",
      "RNM de crânio"
    ],
    "Paciente ou Grupo com Deficiência": [
      "Paciente",
      "CLIENTE"
    ],
    "Grupo Profissional ou Ocupacional": [
      "Enf",
      "enfermagem",
      "ENFª"
    ],
    "Achado": [
      "CONSCIENTE",
      "ORIENTADO",
      "VERBALIZANDO",
      "EUPNEICA",
      "AFEBRIL",
      "REPOUSO",
      "ORIENTADA",
      "GLASGOW 15",
      "RHA +",
      "DEBITO CONCENTRADO",
      "MOBILIZANDO ATIVAMENTE OS MEMBROS",
      "RHA PRESENTES",
      "URINA EFETIVA",
      "HEMODINAMICAMENTE ESTÁVEL",
      "ACEITA DIETA",
      "DIURESE ESPONTANEA PRESENTE"
    ],
    "Doença ou Síndrome": [
      "EDEMA CEREBRAL",
      "ESCLEROSE MULTIPLA"
    ],
    "Lesão ou Envenenamento": [
      "TRAUMATISMO INTRACRANIANO"
    ],
    "Substância Farmacológica": [
      "SG 5%"
    ],
    "Função Fisiológica": [
      "URINA EFETIVA",
      "DIURESE ESPONTANEA PRESENTE"
    ]
  },
  "labels": {
    "edema cerebral": {
      "capitulo": "08",
      "opcoes": []
    },
    "queixas": {
      "capitulo": "21",
      "opcoes": []
    },
    "paralisia": {
      "capitulo": "08",
      "opcoes": []
    },
    "ectérico": {
      "capitulo": "12",
      "opcoes": []
    },
    "traumatismo intracraniano": {
      "capitulo": "08",
      "opcoes": []
    },
    "debito concentrado": {
      "capitulo": "21",
      "opcoes": []
    },
    "esclerose multipla": {
      "capitulo": "08",
      "opcoes": []
    },
    "glasgow 15": {
      "capitulo": "12",
      "opcoes": []
    },
    "roncos difusos": {
      "capitulo": "21",
      "opcoes": []
    },
    "crepitações e bolhosos difusps": {
      "capitulo": "21",
      "opcoes": []
    },
    "intercorrência": {
      "capitulo": "22",
      "opcoes": []
    },
    "intercorrencias": {
      "capitulo": "22",
      "opcoes": []
    },
    "cefaleia": {
      "capitulo": "08",
      "opcoes": []
    }
  }
}