{
  "prontuario_id": 905,
  "text": "PACIENTE COM LINFOPROLIFERACAO B DE BAIXO GRAU, INTERNA POR ANEMIA SINTOMATICA PROLONGADA POS-QT (C2 DE CVP EM ABRIL 2007). RECEBEU 2 UI DE CHAD E FICOU ASSINTOMATICO. REALIZADA BMO / AMO PARA DESCARTAR INFILTRACAO PELO LINFOMA QUE SERA REVISADA COM DR VITAL BRASIL POSTERIORMENTE. NAO EXISTE EVIDENCIA CLINICA DE SGTO, OU HEMOLISE QUE JUSTIFIQUE QUADRO DE ANEMIA INEQUIVOCADAMENTE. RECEBE ALTA COM RETORNO AMBULATORIAL MARCADO. Paciente G1, com exames de pré-natal normais, é admitida no centro obstétrico em 06/06/07 com IG de 28 sem 1 dia(s) por quadro de pielonefrite aguda (febre + sintomas urinários irritativos). Solicitado, EQU, urocultura e hemograma. Avaliação de bem estar fetal na chegada sem alterações (PBF = 8/8, ILA normal). Iniciado ampicilina EV em 06/06/2007. Sem outras queixas - nega contrações, perdas Vaginais ou diminuição da movimentação fetal.  Exames XXXX: 06/06/07: creatinina 0,6,  plaquetas 269 mil, HTC 29,4%, HB 9,9,  leucócitos 10100, com 6% de bastões. EQU: esterase leucocitária + / leucócitos no sedimento:1661; VDRL NR Urocultura: E. coli >100.000 multissensível.  Exames de pré-natal: - TS: O +, -fev/07: VDRL NR, glicemia jejum 72,  toxoplasmose IgG - / IgM -,  HbsAg negativo e anti-HIV negativo. - eco obstétrica (22/02/07): 13 + 1 - eco obstétrica (12/03/07): 15 + 6, P 50, placenta baixa anterior ocluindo o OCI, LA normal, feto sp.  Paciente apresenta boa evolução, mantém sinais vitais estáveis após início do antibiótico, BCF presentes, MF presentes. Em condições de alta hospitalar. Recebe orientações.",
  "entities": {
    "Paciente ou Grupo com Deficiência": [
      "PACIENTE",
      "Paciente"
    ],
    "Atividade de Assistência à Saúde": [
      "INTERNA",
      "ALTA",
      "orientações",
      "RETORNO AMBULATORIAL",
      "alta hospitalar"
    ],
    "Conceito Temporal": [
      "POS-QT"
    ],
    "Abreviação": [
      "POS-QT",
      "CHAD",
      "BMO",
      "DR",
      "G1",
      "IG",
      "EQU",
      "EV",
      "TS",
      "EVIDENCIA CLINICA DE SGTO",
      "28 sem 1 dia",
      "ILA normal",
      "HB 9 , 9",
      "VDRL NR",
      "eco obstétrica",
      "LA normal",
      "feto sp",
      "BCF presentes",
      "MF presentes"
    ],
    "Negação": [
      "ASSINTOMATICO",
      "NAO",
      "sem",
      "Sem",
      "nega"
    ],
    "Sinal ou Sintoma": [
      "ASSINTOMATICO",
      "febre",
      "alterações",
      "queixas",
      "contrações",
      "EVIDENCIA CLINICA DE SGTO",
      "sintomas urinários irritativos",
      "perdas Vaginais",
      "diminuição da movimentação fetal"
    ],
    "Procedimento Diagnóstico": [
      "BMO",
      "Exames",
      "Avaliação de bem estar fetal",
      "Exames de pré-natal",
      "eco obstétrica"
    ],
    "Processo Neoplásico": [
      "LINFOMA"
    ],
    "Doença ou Síndrome": [
      "LINFOMA",
      "ANEMIA",
      "LINFOPROLIFERACAO B DE BAIXO GRAU",
      "ANEMIA SINTOMATICA PROLONGADA",
      "pielonefrite aguda"
    ],
    "Função Patológica": [
      "HEMOLISE"
    ],
    "Achado": [
      "G1",
      "DESCARTAR INFILTRACAO",
      "ILA normal",
      "boa evolução",
      "sinais vitais estáveis",
      "BCF presentes",
      "MF presentes"
    ],
    "Atributo Clínico": [
      "IG",
      "TS"
    ],
    "Procedimento Laboratorial": [
      "EQU",
      "urocultura",
      "hemograma",
      "Exames",
      "Urocultura",
      "Exames de pré-natal"
    ],
    "Antibiótico": [
      "ampicilina",
      "antibiótico"
    ],
    "Conceito Quantitativo": [
      "4%",
      "2 UI",
      "28 sem 1 dia"
    ],
    "Substância Farmacológica": [
      "antibiótico"
    ],
    "Resultado Laboratorial ou de Teste": [
      "exames de pré-natal normais",
      "PBF = 8/8",
      "ILA normal",
      "creatinina 0 , 6",
      "plaquetas 269 mil",
      "HTC 29",
      "HB 9 , 9",
      "leucócitos 10100",
      "6% de bastões",
      "esterase leucocitária +",
      "VDRL NR",
      "glicemia jejum 72",
      "toxoplasmose IgG - / IgM",
      "HbsAg negativo",
      "anti-HIV negativo",
      "placenta baixa anterior",
      "ocluindo o OCI",
      "LA normal",
      "feto sp"
    ],
    "Organização Relacionada à Saúde": [
      "centro obstétrico"
    ]
  },
  "labels": {
    "linfoma": {
      "capitulo": "02",
      "opcoes": []
    },
    "pielonefrite aguda": {
      "capitulo": "01",
      "opcoes": []
    },
    "alterações": {
      "capitulo": "21",
      "opcoes": []
    },
    "linfoproliferacao b de baixo grau": {
      "capitulo": "02",
      "opcoes": []
    },
    "queixas": {
      "capitulo": "21",
      "opcoes": []
    },
    "perdas vaginais": {
      "capitulo": "16",
      "opcoes": []
    },
    "febre": {
      "capitulo": "01",
      "opcoes": []
    },
    "anemia": {
      "capitulo": "03",
      "opcoes": []
    },
    "contrações": {
      "capitulo": "21",
      "opcoes": []
    },
    "descartar infiltracao": {
      "capitulo": "02",
      "opcoes": []
    },
    "anemia sintomatica prolongada": {
      "capitulo": "03",
      "opcoes": []
    },
    "diminuição da movimentação fetal": {
      "capitulo": "18",
      "opcoes": []
    },
    "sintomas urinários irritativos": {
      "capitulo": "01",
      "opcoes": []
    },
    "hemolise": {
      "capitulo": "03",
      "opcoes": []
    }
  }
}