{
  "prontuario_id": 283,
  "text": "LUCAS, 80 ANOS.\n\nDOR EM FLANCO ESQUERDO, TIPO FISGADA, ESPORADICA (15 / 15 DIAS), ALIVIO COM USO DE PARACETAMOL.\nRELATA POLACIURIA, NEGA HEMATURIA, DISURIA.\nSEM DEMAIS QUEIXAS, ENCAINHADA DA US PARA AVALIAÇAO.\n\nCOMORBIDADES: HAS, DISLIPIDEMICA, IAM + CAT HA 7 ANOS, AVC HA 7 ANOS. TVP HA 2 ANOS (?)\nCX PREVIA 3 REVASCULARIZACOES DO MIOCARDIO.\n\nEM USO: ATENOLOL, CAPTOPRIL, SINVASTATINA, OMEPRAZOL, AAS INFANTIL, NAO SABE REFERIR DEMAIS MEDICACOES.\n\nLABORATORIAL:\nCREATININA: 1,3.\nGLICOSE 107.\nUREIA: 46.\nAC. URICO: 6,5.\nTG: 259.\nHDL: 42.\nNA: 140.\nK: 5,4.\nCOLESTEROL TOTAL 257.\nLDL: 163.\n\nPARCIAL DE URINA:\nCOR: AMARELO CITRINA.\nASPECTO LEVEMENT TURVO.\nPH: 6,5.\nDENSIDADE: 1,015.\nPROTEINAS: NEGATIVO.\nGLICOSE: NEGATIVO.\nCORPOS CETONICOS: NEGATIVO.\nHB: ++.\nNITRITO: EGATIVO.\nBILIRRUBINA: NEGATIVO.\nLEUCOCITOS: 30/MICRO L.\nERITROCITOS: 50 MICRO L.\nCELULLAS EPITELIAIS RARAS.\nCILINDROS AUSENTES.\nCRISTAIS AUSENTES.\nFILAMENTO DE MUC AUSENTE.\n\nUS DE ABDOME TOTAL: REDUCAO VOLUMETRICA COM AFILAMENTO CORTICAL DO RIM DIREITO.\nRIM DIREITO COM DISCRETA REDUCAO VOLUMETRICA E COM AFILAMENTO DE SUA CORTICAL, ECOGENICIDADE PRESERVADA.\nRIM ESQUERDO COM TOPOGRAFIA E VOLUMO NORMAIS, ECOGENICIDADE PRESERVADA E ESPESSURA NORMAL DA REGIAO CORTICOMEDULAR. NAO HA EVIDENCIA DE DILATACAO DO SISTEMA COLETOR. AUSENCIAN DE IMAGEM DE LITIASE.\n\nPA: 170/100, FC: 95.\nMV+, BILATERAL, SIMETRICO, SEM RA.\nBRNF 2T SS[.\nMMII SEM EDEMA.\n\nAVALIACAO:\nDRC ESTAGIO 3B, COM CLEARACE ESTIMADO DE 38 POR NEFROESCLEROSE BENIGNA.\n\nCONDUTA:\nPRESECREVO: ATENOLOL 50MG (2 CP), ENALAPRIL 10MG (4 CP), HDTZ 25 MG, AAS 100 MG, SINVASTATINA 40 MG.\nSOLICITIO LABORATORIO.\nRETORNO EM 4 MESES.\n \n \n \n ",
  "entities": {
    "Sinal ou Sintoma": [
      "DOR",
      "POLACIURIA",
      "HEMATURIA",
      "DISURIA",
      "QUEIXAS",
      "RA",
      "EDEMA"
    ],
    "Conceito Qualitativo": [
      "FISGADA",
      "ESPORADICA"
    ],
    "Conceito Temporal": [
      "ESPORADICA",
      "PREVIA",
      "15 / 15 DIAS",
      "HA 7 ANOS",
      "HA 2 ANOS"
    ],
    "Substância Farmacológica": [
      "PARACETAMOL",
      "ATENOLOL",
      "CAPTOPRIL",
      "SINVASTATINA",
      "OMEPRAZOL",
      "MEDICACOES",
      "ENALAPRIL",
      "HDTZ",
      "AAS",
      "AAS INFANTIL"
    ],
    "Negação": [
      "NEGA",
      "SEM",
      "NAO",
      "AUSENCIAN",
      "SS["
    ],
    "Atividade de Assistência à Saúde": [
      "ENCAINHADA",
      "AVALIAÇAO",
      "CONDUTA",
      "PRESECREVO",
      "SOLICITIO",
      "RETORNO EM 4 MESES"
    ],
    "Organização Relacionada à Saúde": [
      "US"
    ],
    "Abreviação": [
      "US",
      "HAS",
      "IAM",
      "CAT",
      "AVC",
      "TVP",
      "AC",
      "PA",
      "FC",
      "MV+",
      "RA",
      "MMII",
      "HDTZ",
      "AAS",
      "AAS INFANTIL",
      "TG : 259",
      "LEVEMENT TURVO",
      "HB : ++",
      "US DE ABDOME TOTAL",
      "DRC ESTAGIO 3B",
      "2 CP",
      "10MG ( 4 CP )"
    ],
    "Doença ou Síndrome": [
      "HAS",
      "DISLIPIDEMICA",
      "IAM",
      "AVC",
      "TVP",
      "DRC ESTAGIO 3B",
      "NEFROESCLEROSE BENIGNA"
    ],
    "Achado": [
      "DISLIPIDEMICA",
      "MV+",
      "BILATERAL",
      "SIMETRICO",
      "RA"
    ],
    "Procedimento Terapêutico ou Preventivo": [
      "CAT",
      "CX",
      "REVASCULARIZACOES DO MIOCARDIO"
    ],
    "Conceito Quantitativo": [
      "3",
      "170/100",
      "95",
      "50MG (",
      "2 CP",
      "10MG ( 4 CP )",
      "25 MG",
      "100 MG",
      "40 MG"
    ],
    "Substância Química Orgânica": [
      "SINVASTATINA",
      "OMEPRAZOL",
      "ATENOLOL",
      "HDTZ",
      "AAS",
      "AAS INFANTIL"
    ],
    "Procedimento Laboratorial": [
      "LABORATORIAL",
      "LABORATORIO",
      "PARCIAL DE URINA"
    ],
    "Atributo Clínico": [
      "PA",
      "FC"
    ],
    "Conceito Espacial": [
      "BILATERAL"
    ],
    "Parte do Corpo, Órgão ou Componente Orgânico": [
      "MMII"
    ],
    "Função Patológica": [
      "EDEMA"
    ],
    "Procedimento Diagnóstico": [
      "AVALIACAO",
      "US DE ABDOME TOTAL"
    ],
    "Produto Intelectual": [
      "CONDUTA"
    ],
    "Localização ou Região Corporal": [
      "FLANCO ESQUERDO"
    ],
    "Resultado Laboratorial ou de Teste": [
      "CREATININA : 1 , 3",
      "GLICOSE 107",
      "UREIA : 46",
      "URICO : 6 , 5",
      "TG : 259",
      "HDL : 42",
      "NA : 140",
      "K : 5 , 4",
      "COLESTEROL TOTAL 257",
      "LDL : 163",
      "AMARELO CITRINA",
      "LEVEMENT TURVO",
      "PH : 6 , 5",
      "DENSIDADE : 1 , 015",
      "PROTEINAS : NEGATIVO",
      "GLICOSE : NEGATIVO",
      "CORPOS CETONICOS : NEGATIVO",
      "HB : ++",
      "NITRITO : EGATIVO",
      "BILIRRUBINA : NEGATIVO",
      "LEUCOCITOS : 30/MICRO L",
      "ERITROCITOS : 50 MICRO L",
      "CELULLAS EPITELIAIS RARAS",
      "CILINDROS AUSENTES",
      "CRISTAIS AUSENTES",
      "FILAMENTO DE MUC AUSENTE",
      "REDUCAO VOLUMETRICA COM AFILAMENTO CORTICAL DO RIM DIREITO",
      "RIM DIREITO COM DISCRETA REDUCAO VOLUMETRICA",
      "COM AFILAMENTO DE SUA CORTICAL , ECOGENICIDADE PRESERVADA",
      "RIM ESQUERDO COM TOPOGRAFIA E VOLUMO NORMAIS",
      "ECOGENICIDADE PRESERVADA E ESPESSURA NORMAL DA REGIAO CORTICOMEDULAR",
      "EVIDENCIA DE DILATACAO DO SISTEMA COLETOR",
      "CLEARACE ESTIMADO DE 38"
    ]
  },
  "labels": {
    "ra": {
      "capitulo": "16",
      "opcoes": []
    },
    "edema": {
      "capitulo": "15",
      "opcoes": []
    },
    "has": {
      "capitulo": "11",
      "opcoes": []
    },
    "drc estagio 3b": {
      "capitulo": "21",
      "opcoes": []
    },
    "iam": {
      "capitulo": "11",
      "opcoes": []
    },
    "dislipidemica": {
      "capitulo": "05",
      "opcoes": []
    },
    "avc": {
      "capitulo": "11",
      "opcoes": []
    },
    "bilateral": {
      "capitulo": "16",
      "opcoes": []
    },
    "nefroesclerose benigna": {
      "capitulo": "21",
      "opcoes": []
    },
    "tvp": {
      "capitulo": "11",
      "opcoes": []
    },
    "dor": {
      "capitulo": "15",
      "opcoes": []
    },
    "simetrico": {
      "capitulo": "16",
      "opcoes": []
    },
    "mv+": {
      "capitulo": "16",
      "opcoes": []
    }
  }
}