{
  "prontuario_id": 721,
  "text": "Segue sonolenta, respondendo a estímulos dolorosos, em oxigenoterapia sob névoa úmida. Aceitando bem dieta VO, segundo informação de acompanhante. Acamada, dependente. AVP MSE em soroterapia. Início de úlcera por pressão em calcâneo D. Orientado medidas preventivas, ressaltada importância da mudança de decúbito e proteção de proeminências ósseas. Faz uso de fralda. Sudoréica. Controle glicêmico. Apresenta dextro de 88mg/dl, medicada CPM. SEGUEM CUIDADOS. Com acompanhante. 08:20h: Glasgow 14, pupilas isocóricas fotorreagentes, curativo cefálico tipo capacete limpo e seco, SNE com dieta a 30ml/h, respiração espontânea, em névoa úmida 4l/, SPO2 95%, acesso venoso periférico em jugular externa D com plano básico de hidratação, monitorizado, estável hemodinamicamente, MV+ com roncos esparsos, abdome plano, flácido, indolor à palpação, RHA+, SVD com diurese efetiva, evacuação ausente, extremiddaes bem perfundidas, higienizado e mobilizado no leito, pele íntegra. Maria Firmino, 79 anos. # Sepse pulmonar em D8 tazocin (paciente não recebeu por 2 dias Atb). # Previamente HAS/ DM/ DPOC. # AVE há 2 anos (hemiparesia à E). # Escara em região sacral e perna E. # S: paciente nega queixas, nega dor, dispnéia. Restrita ao leito. Dieta via nasoenteral.  # O: paciente em BEG, hipocorada 2+/4, hidratada, eupnéica, afebril. Dados vitais estáveis. C/P: mucosas úmidas e hipocoradas sem lNM. CPP: MV+ simétrico bilateralmente, sem RA. Prec: BCRNF sem sopro. Abd: globoso, flácido, indolor à palpação. Ausência de VCM, massas palpáveis ou sinais de irritação peritoneal. Membros: sem edema, panturrilhas livres, escara em região sacral e perna E. # A: sepse pulmonar em D8 tazocin (não foi realizado doses de ATB por 2 dias). Disglicêmica. # P: plano de manter ATBterapia até D10, solicito exs lab, mantenho demais condutas e cuidados de enfermaria. Oriento neto João em relação ao quadro da paciente.",
  "entities": {
    "Sinal ou Sintoma": [
      "sonolenta",
      "dispnéia",
      "hipocoradas",
      "Disglicêmica",
      "roncos esparsos",
      "Restrita ao leito",
      "hipocorada 2+/4"
    ],
    "Grupo Populacional": [
      "acompanhante"
    ],
    "Achado": [
      "Acamada",
      "dependente",
      "Sudoréica",
      "limpo",
      "seco",
      "monitorizado",
      "MV+",
      "flácido",
      "RHA+",
      "higienizado",
      "BEG",
      "hidratada",
      "eupnéica",
      "afebril",
      "globoso",
      "pupilas isocóricas fotorreagentes",
      "respiração espontânea",
      "estável hemodinamicamente",
      "abdome plano",
      "indolor à palpação",
      "diurese efetiva",
      "extremiddaes bem perfundidas",
      "mobilizado no leito",
      "pele íntegra",
      "Dados vitais estáveis",
      "mucosas úmidas",
      "sem lNM",
      "simétrico bilateralmente",
      "sem RA",
      "sem sopro",
      "massas palpáveis",
      "sinais de irritação peritoneal",
      "sem edema",
      "panturrilhas livres"
    ],
    "Dispositivo Médico": [
      "AVP",
      "fralda",
      "curativo",
      "SNE",
      "SVD",
      "acesso venoso periférico"
    ],
    "Procedimento Terapêutico ou Preventivo": [
      "AVP",
      "soroterapia",
      "SNE",
      "SPO2",
      "SVD",
      "mudança de decúbito",
      "névoa úmida",
      "acesso venoso periférico",
      "via nasoenteral"
    ],
    "Abreviação": [
      "AVP",
      "MSE",
      "D",
      "CPM",
      "SNE",
      "30ml/h",
      "SPO2",
      "MV+",
      "RHA+",
      "SVD",
      "D8",
      "Atb",
      "HAS/",
      "DM/",
      "DPOC",
      "AVE",
      "E",
      "BEG",
      "C/P",
      "CPP",
      "Prec",
      "Abd",
      "ATB",
      "ATBterapia",
      "D10",
      "sem lNM",
      "sem RA",
      "exs lab"
    ],
    "Localização ou Região Corporal": [
      "MSE",
      "Abd",
      "região sacral"
    ],
    "Parte do Corpo, Órgão ou Componente Orgânico": [
      "calcâneo",
      "Membros",
      "perna E"
    ],
    "Conceito Funcional": [
      "uso"
    ],
    "Atividade de Assistência à Saúde": [
      "medicada",
      "CUIDADOS"
    ],
    "Alimento": [
      "dieta"
    ],
    "Conceito Quantitativo": [
      "30ml/h",
      "4l/",
      "95%",
      "D8",
      "2 dias",
      "2 anos"
    ],
    "Procedimento Diagnóstico": [
      "monitorizado",
      "Controle glicêmico"
    ],
    "Função Fisiológica": [
      "evacuação"
    ],
    "Negação": [
      "ausente",
      "não recebeu",
      "nega queixas",
      "nega dor",
      "sem lNM",
      "sem RA",
      "sem sopro",
      "sem edema",
      "não foi realizado"
    ],
    "Antibiótico": [
      "tazocin",
      "Atb",
      "ATB"
    ],
    "Paciente ou Grupo com Deficiência": [
      "paciente"
    ],
    "Doença ou Síndrome": [
      "HAS/",
      "DM/",
      "DPOC",
      "AVE",
      "úlcera por pressão",
      "Sepse pulmonar",
      "sepse pulmonar"
    ],
    "Conceito Espacial": [
      "E"
    ],
    "Função Patológica": [
      "Escara",
      "escara"
    ],
    "Grupo Familiar": [
      "neto"
    ],
    "Resultado Laboratorial ou de Teste": [
      "dextro de 88mg/dl"
    ],
    "Conceito Qualitativo": [
      "extremiddaes bem perfundidas"
    ],
    "Procedimento Laboratorial": [
      "exs lab"
    ]
  },
  "labels": {
    "abdome plano": {
      "capitulo": "15",
      "opcoes": []
    },
    "mucosas úmidas": {
      "capitulo": "14",
      "opcoes": []
    },
    "escara": {
      "capitulo": "14",
      "opcoes": []
    },
    "monitorizado": {
      "capitulo": "21",
      "opcoes": []
    },
    "acamada": {
      "capitulo": "21",
      "opcoes": []
    },
    "rha+": {
      "capitulo": "21",
      "opcoes": []
    },
    "respiração espontânea": {
      "capitulo": "12",
      "opcoes": []
    },
    "diurese efetiva": {
      "capitulo": "16",
      "opcoes": []
    },
    "extremiddaes bem perfundidas": {
      "capitulo": "15",
      "opcoes": []
    },
    "higienizado": {
      "capitulo": "14",
      "opcoes": []
    },
    "disglicêmica": {
      "capitulo": "05",
      "opcoes": []
    },
    "hipocoradas": {
      "capitulo": "21",
      "opcoes": []
    },
    "massas palpáveis": {
      "capitulo": "21",
      "opcoes": []
    },
    "sinais de irritação peritoneal": {
      "capitulo": "21",
      "opcoes": []
    },
    "dpoc": {
      "capitulo": "04",
      "opcoes": []
    },
    "sem edema": {
      "capitulo": "15",
      "opcoes": []
    },
    "restrita ao leito": {
      "capitulo": "21",
      "opcoes": []
    },
    "mv+": {
      "capitulo": "08",
      "opcoes": []
    },
    "seco": {
      "capitulo": "14",
      "opcoes": []
    },
    "beg": {
      "capitulo": "06",
      "opcoes": []
    },
    "dispnéia": {
      "capitulo": "12",
      "opcoes": []
    },
    "has/": {
      "capitulo": "04",
      "opcoes": []
    },
    "sepse pulmonar": {
      "capitulo": "12",
      "opcoes": []
    },
    "limpo": {
      "capitulo": "14",
      "opcoes": []
    },
    "sem sopro": {
      "capitulo": "21",
      "opcoes": []
    },
    "úlcera por pressão": {
      "capitulo": "15",
      "opcoes": []
    },
    "hipocorada 2+/4": {
      "capitulo": "06",
      "opcoes": []
    },
    "simétrico bilateralmente": {
      "capitulo": "08",
      "opcoes": []
    },
    "globoso": {
      "capitulo": "15",
      "opcoes": []
    },
    "roncos esparsos": {
      "capitulo": "12",
      "opcoes": []
    },
    "dm/": {
      "capitulo": "04",
      "opcoes": []
    },
    "pele íntegra": {
      "capitulo": "14",
      "opcoes": []
    },
    "sem ra": {
      "capitulo": "21",
      "opcoes": []
    },
    "pupilas isocóricas fotorreagentes": {
      "capitulo": "08",
      "opcoes": []
    },
    "panturrilhas livres": {
      "capitulo": "15",
      "opcoes": []
    },
    "flácido": {
      "capitulo": "15",
      "opcoes": []
    },
    "mobilizado no leito": {
      "capitulo": "21",
      "opcoes": []
    },
    "ave": {
      "capitulo": "04",
      "opcoes": []
    },
    "sonolenta": {
      "capitulo": "07",
      "opcoes": []
    },
    "sudoréica": {
      "capitulo": "06",
      "opcoes": []
    }
  }
}