{
  "prontuario_id": 561,
  "text": "ÀS 9:20 H: CONSCIENTE, DESORIENTADO NO TEMPO E ESPAÇO, MOBILIZANDO ATIVAMENTE OS MEMBROS. EUPNEICO EM NÉVOA ÚMIDA 3 L/MIN, BOLHOSOS DIFUSOS. SOROTERAPIA EM ACESSO VENOSO CENTRAL DIREITO, SENDO INFUNDIDO SG 42 ML/H, ABDOME GLOBOSO, RHA PRESENTES, SVD URINA EFETIVA. EDEMA DE MEMBROS, EQUIMOSES PEQUENAS EM TODO CORPO. MONITORIZADA, OXIMETRIA DE PULSO, HEMODINAMICAMENTE ESTÁVEL. PNEUMONIA NAO ESPECIFICADA. ÀS 21:20H: PERMANECE EM VM COM SISTEMA FECHADO DE SUCÇÃO E FILTRO DE BARREIRA EM MODO PSV, COM PS DE 20 CM DE H2O, FIO2 EM 0,40%, FR 18 RPM, PEEP 8 CM DE H2O. MONITORADO COM PVC, CARDIOSCOPIA E OXIMETRIA DE PULSO. APRESENTA PUPILAS ISOCÓRICAS E FOTORREAGENTES, GLASGOW 13-14, TETRAPLEGIA, SNE COM DIETA A 75 ML/H, TRAQUEOSTOMIZADO, SECREÇÃO TRAQUEOBRÔNQUICA MUCOPURULENTA EM MÉDIA QUANTIDADE, CVC EM SUBCLÁVIA D COM NORA 3 ML/H, SF 21 ML/H, PVC COM VALORES ENTRE 15 A 20 CM DE H2O, AUSCULTA PULMONAR COM RONCOS DIFUSOS, ABDOME GLOBOSO E FLÁCIDO, RHA PRESENTES, SVD COM DIURESE DE ASPECTO AMARELO ESCURO E BOM VOLUME, ÚLCERA POR PRESSÃO ESTÁGIO I EM REGIÃO SACRA. APRESENTA ESCAPE DE AR PELA TRAQUEOSTOMIA (CX TORÁCICA CIENTE). EDEMA CEREBRAL. Às 00:36: Paciente consciente, lúcido, orientado, comunicativo, normotenso, normocorado, afebril, em repouso no leito. Sequela de trauma raquimedular. Mantém acesso venoso salinizado no momento. Apresenta múltiplas úlceras de pressão. Realizada troca de curativo em todas. Paciente com queixa de cefaléia no início do plantão, medicado conforme prescrição médica. MAntém fralda + cistostomia funcionante, com quantidade satisfatória de débito urinário. Segue sob cuidados. CALCULOSE DA VESICULA BILIAR COM COLICISTITE AGUDA.",
  "entities": {
    "Achado": [
      "CONSCIENTE",
      "MONITORIZADA",
      "MONITORADO",
      "TRAQUEOSTOMIZADO",
      "FLÁCIDO",
      "consciente",
      "lúcido",
      "orientado",
      "comunicativo",
      "normotenso",
      "normocorado",
      "afebril",
      "MOBILIZANDO ATIVAMENTE OS MEMBROS",
      "EUPNEICO EM NÉVOA ÚMIDA",
      "RHA PRESENTES",
      "URINA EFETIVA",
      "HEMODINAMICAMENTE ESTÁVEL",
      "PUPILAS ISOCÓRICAS E FOTORREAGENTES",
      "ASPECTO AMARELO ESCURO",
      "BOM VOLUME",
      "ESCAPE DE AR",
      "repouso no leito",
      "cistostomia funcionante",
      "quantidade satisfatória de débito urinário"
    ],
    "Procedimento Terapêutico ou Preventivo": [
      "SOROTERAPIA",
      "SVD",
      "VM",
      "PS",
      "SNE",
      "DIETA",
      "TRAQUEOSTOMIZADO",
      "CVC",
      "TRAQUEOSTOMIA",
      "EUPNEICO EM NÉVOA ÚMIDA",
      "ACESSO VENOSO CENTRAL",
      "SISTEMA FECHADO DE SUCÇÃO",
      "FILTRO DE BARREIRA",
      "repouso no leito",
      "acesso venoso",
      "troca de curativo"
    ],
    "Conceito Espacial": [
      "DIREITO",
      "D"
    ],
    "Substância Farmacológica": [
      "SG",
      "NORA",
      "SF"
    ],
    "Abreviação": [
      "SG",
      "SVD",
      "VM",
      "PS",
      "FIO2",
      "FR",
      "RPM",
      "PEEP",
      "PVC",
      "SNE",
      "CVC",
      "D",
      "NORA",
      "SF",
      "RHA PRESENTES",
      "MODO PSV",
      "CM DE H2O",
      "CX TORÁCICA"
    ],
    "Localização ou Região Corporal": [
      "ABDOME",
      "TODO CORPO",
      "REGIÃO SACRA"
    ],
    "Sinal ou Sintoma": [
      "GLOBOSO",
      "TETRAPLEGIA",
      "cefaléia",
      "DESORIENTADO NO TEMPO E ESPAÇO",
      "BOLHOSOS DIFUSOS",
      "EQUIMOSES PEQUENAS",
      "GLASGOW 13-14",
      "RONCOS DIFUSOS",
      "Sequela de trauma raquimedular"
    ],
    "Dispositivo Médico": [
      "SVD",
      "SNE",
      "CVC",
      "fralda",
      "ACESSO VENOSO CENTRAL",
      "FILTRO DE BARREIRA",
      "acesso venoso"
    ],
    "Procedimento Diagnóstico": [
      "MONITORIZADA",
      "MONITORADO",
      "PVC",
      "CARDIOSCOPIA",
      "OXIMETRIA DE PULSO",
      "AUSCULTA PULMONAR"
    ],
    "Conceito Quantitativo": [
      "RPM",
      "3 L/MIN",
      "42 ML/H",
      "CM DE H2O",
      "0 , 40%",
      "75 ML/H",
      "3 ML/H",
      "21 ML/H",
      "15 A 20"
    ],
    "Alimento": [
      "DIETA"
    ],
    "Parte do Corpo, Órgão ou Componente Orgânico": [
      "SUBCLÁVIA"
    ],
    "Atributo Clínico": [
      "PVC"
    ],
    "Função Fisiológica": [
      "DIURESE",
      "URINA EFETIVA",
      "quantidade satisfatória de débito urinário"
    ],
    "Paciente ou Grupo com Deficiência": [
      "Paciente"
    ],
    "Negação": [
      "afebril"
    ],
    "Conceito Qualitativo": [
      "salinizado",
      "MÉDIA QUANTIDADE",
      "BOM VOLUME",
      "ESTÁGIO I"
    ],
    "Conceito Temporal": [
      "início",
      "no momento"
    ],
    "Atividade de Assistência à Saúde": [
      "plantão",
      "medicado",
      "cuidados",
      "prescrição médica"
    ],
    "Objeto Manufaturado": [
      "fralda"
    ],
    "Função Patológica": [
      "EDEMA DE MEMBROS",
      "EDEMA CEREBRAL"
    ],
    "Doença ou Síndrome": [
      "PNEUMONIA NAO ESPECIFICADA",
      "ÚLCERA POR PRESSÃO",
      "múltiplas úlceras de pressão",
      "CALCULOSE DA VESICULA BILIAR COM COLICISTITE AGUDA"
    ],
    "Substância Corporal": [
      "SECREÇÃO TRAQUEOBRÔNQUICA"
    ],
    "Lesão ou Envenenamento": [
      "Sequela de trauma raquimedular"
    ],
    "Produto Intelectual": [
      "prescrição médica"
    ]
  },
  "labels": {
    "desorientado no tempo e espaço": {
      "capitulo": "06",
      "opcoes": []
    },
    "glasgow 13-14": {
      "capitulo": "21",
      "opcoes": []
    },
    "escape de ar": {
      "capitulo": "22",
      "opcoes": []
    },
    "pupilas isocóricas e fotorreagentes": {
      "capitulo": "21",
      "opcoes": []
    },
    "aspecto amarelo escuro": {
      "capitulo": "21",
      "opcoes": []
    },
    "bolhosos difusos": {
      "capitulo": "12",
      "opcoes": []
    },
    "roncos difusos": {
      "capitulo": "12",
      "opcoes": []
    },
    "mobilizando ativamente os membros": {
      "capitulo": "15",
      "opcoes": []
    },
    "cefaléia": {
      "capitulo": "21",
      "opcoes": []
    },
    "múltiplas úlceras de pressão": {
      "capitulo": "14",
      "opcoes": []
    },
    "calculose da vesicula biliar com colicistite aguda": {
      "capitulo": "13",
      "opcoes": []
    },
    "equimoses pequenas": {
      "capitulo": "15",
      "opcoes": []
    },
    "edema cerebral": {
      "capitulo": "08",
      "opcoes": []
    },
    "úlcera por pressão": {
      "capitulo": "14",
      "opcoes": []
    },
    "pneumonia nao especificada": {
      "capitulo": "12",
      "opcoes": []
    },
    "globoso": {
      "capitulo": "15",
      "opcoes": []
    },
    "traqueostomizado": {
      "capitulo": "22",
      "opcoes": []
    },
    "sequela de trauma raquimedular": {
      "capitulo": "08",
      "opcoes": []
    },
    "flácido": {
      "capitulo": "15",
      "opcoes": []
    },
    "edema de membros": {
      "capitulo": "15",
      "opcoes": []
    },
    "tetraplegia": {
      "capitulo": "08",
      "opcoes": []
    }
  }
}