{
  "prontuario_id": 797,
  "text": "ÀS 10:00 HS: CONSCIENTE. COMUNICATIVA. EUPNEICA. REFERE FORTE ALGIA EM MID. ACEITOU A DIETA OFERECIDA. NÃO APRESENTOU DIURESE. REALIZADO CATETERISMO VESICAL DE ALIVIO. CURATIVO EM MID SANGUINOLENTO. MATERIAL PARA TROCA DE CURATIVO NO POSTO DE ENFERMAGEM, AGUARDANDO ORTOPEDIA PARA REALIZAR. ÀS 18:33: ÁS 18:30 CANCELADO O JEJUM PELO DRº VITAL BRASIL DEVIDO O CONVENIO NÃO TER LIBERADO O MATERIAL, ORIENTADO CLIENTE E ACOMPANHANTE. Às 10:32hs: Realizado traqueostomia pelo Dr Vital Brasil. Procedimento sem intercorrencias. ÀS 15:30H: S: GLASGOW 13, SINAIS VITAIS ESTAVEIS, AFASICA, HEMIPARESIA DIREITA, DESVIO CONJUGADO DO OLHAR PARA ESQUERDA E RIMA LABIAL A DIREITA, HIPERTENSA PREVIA COM TRATAMENTO MEDICAMENTOSO. O: 1º DI POR AVEi, PROVENIENTE DO PA, CHEGA A UTI-3 SONOLENTA, POREM OBEDECENDO COMANDOS SIMPLES, PUPILAS ISOCORICAS FOTORREAGENTES, NORMOCARDICA (82 bpm), NORMOTENSA (139/81 MMhg), EUPNEICA EM USO DE CATETER NASAL TIPO OCULOS A 3 L/M SPO2 96%, AUSCULTA PULMONAR DIMINUIDA EM BASES, ABDOMEN FLACIDO, RHA PRESENTES, EXTREMIDADES AQUECIDAS E BEM PERFUNDIDAS, CATETER VENOSO PERIFERICO EM DORSO DE MÃO ESQUERDA PERMEAVEL, INFUNDINDO PLANO BASICO DE HIDRATAÇÃO, HEMATOMA EM DORSO DE MÃO DIREITA (TENTATIVA DE PUNÇÃO?), SVD COM DIURESE AMARELADA DE ASPECTO LIMPIDO, PELE INTEGRA, REALIZADO MEDIDAS DE CONFORTO, SEGUE MONITORADA EM CUIDADOS INTENSIVOS, LIBERO FAMILIAR PARA VISITA DE ADMISSÃO E ORIENTO QUANTO AS ROTINAS. A: MANTER CABECEIRA ELEVADA, AVALIAR NIVEL DE CONSCIENCIA E SINAIS DE ESFORÇO RESPIRATORIO, ORIENTAR QUANTO OS PROCEDIMENTOS E MEDICAÇÕES, ATENTAR PARA EXPRESSÕES FACIAL DE DOR.  # CONFORME PASSADO EM PLANTÃO PELA ENF FLORENCE NIGHTINGALE, COLETADO HEMOCULTURA E URUCULTURA NO PA. # SEGUNDO INFORMAÇÕES, ESTEVE INTERNADA EM OUTRA INSTITUIÇÃO POR DOR ABDOMINAL E HERNIA HIATO EM TRATAMENTO HA 3 DIAS, COLETO SWAB RETAL CONFORME PROTOCOLO. P: CONFORME PRESCRIÇÃO.     ",
  "entities": {
    "Achado": [
      "CONSCIENTE",
      "COMUNICATIVA",
      "EUPNEICA",
      "DIURESE",
      "NORMOCARDICA",
      "NORMOTENSA",
      "AQUECIDAS",
      "PERMEAVEL",
      "ACEITOU A DIETA",
      "SINAIS VITAIS ESTAVEIS",
      "PUPILAS ISOCORICAS FOTORREAGENTES",
      "SPO2 96%",
      "RHA PRESENTES",
      "BEM PERFUNDIDAS",
      "ASPECTO LIMPIDO",
      "PELE INTEGRA"
    ],
    "Localização ou Região Corporal": [
      "MID",
      "ABDOMEN",
      "EXTREMIDADES",
      "DORSO DE MÃO"
    ],
    "Abreviação": [
      "MID",
      "AVEi",
      "PA",
      "UTI-3",
      "bpm",
      "SVD",
      "ENF",
      "SPO2 96%",
      "RHA PRESENTES"
    ],
    "Função Fisiológica": [
      "DIURESE"
    ],
    "Dispositivo Médico": [
      "CURATIVO",
      "MATERIAL",
      "SVD",
      "TROCA DE CURATIVO",
      "CATETER VENOSO PERIFERICO"
    ],
    "Procedimento Terapêutico ou Preventivo": [
      "CURATIVO",
      "JEJUM",
      "traqueostomia",
      "Procedimento",
      "SVD",
      "PROCEDIMENTOS",
      "TRATAMENTO",
      "CATETERISMO VESICAL DE ALIVIO",
      "TROCA DE CURATIVO",
      "CATETER VENOSO PERIFERICO",
      "PLANO BASICO DE HIDRATAÇÃO",
      "MEDIDAS DE CONFORTO",
      "CABECEIRA ELEVADA"
    ],
    "Sinal ou Sintoma": [
      "SANGUINOLENTO",
      "intercorrencias",
      "AFASICA",
      "SONOLENTA",
      "HEMATOMA",
      "FORTE ALGIA",
      "GLASGOW 13",
      "HEMIPARESIA DIREITA",
      "DESVIO CONJUGADO DO OLHAR PARA ESQUERDA",
      "OBEDECENDO COMANDOS SIMPLES",
      "DIMINUIDA EM BASES",
      "SINAIS DE ESFORÇO RESPIRATORIO",
      "EXPRESSÕES FACIAL DE DOR",
      "DOR ABDOMINAL"
    ],
    "Organização Relacionada à Saúde": [
      "ORTOPEDIA",
      "CONVENIO",
      "PA",
      "UTI-3",
      "INSTITUIÇÃO",
      "POSTO DE ENFERMAGEM"
    ],
    "Negação": [
      "NÃO"
    ],
    "Paciente ou Grupo com Deficiência": [
      "CLIENTE"
    ],
    "Grupo Populacional": [
      "ACOMPANHANTE"
    ],
    "Doença ou Síndrome": [
      "HIPERTENSA",
      "AVEi",
      "HERNIA HIATO"
    ],
    "Conceito Quantitativo": [
      "82",
      "139/81 MMhg",
      "3 L/M"
    ],
    "Conceito Espacial": [
      "ESQUERDA",
      "DIREITA",
      "A DIREITA"
    ],
    "Conceito Qualitativo": [
      "PERMEAVEL"
    ],
    "Função Patológica": [
      "HEMATOMA"
    ],
    "Procedimento Diagnóstico": [
      "MONITORADA",
      "AUSCULTA PULMONAR"
    ],
    "Grupo Familiar": [
      "FAMILIAR"
    ],
    "Atividade de Assistência à Saúde": [
      "AVALIAR",
      "ATENTAR",
      "PLANTÃO",
      "PRESCRIÇÃO",
      "CUIDADOS INTENSIVOS"
    ],
    "Procedimento Laboratorial": [
      "HEMOCULTURA",
      "URUCULTURA",
      "SWAB RETAL"
    ],
    "Produto Intelectual": [
      "PRESCRIÇÃO"
    ],
    "Parte do Corpo, Órgão ou Componente Orgânico": [
      "RIMA LABIAL"
    ],
    "Substância Farmacológica": [
      "E MEDICAÇÕES"
    ]
  },
  "labels": {
    "hipertensa": {
      "capitulo": "11",
      "opcoes": []
    },
    "hemiparesia direita": {
      "capitulo": "08",
      "opcoes": []
    },
    "intercorrencias": {
      "capitulo": "21",
      "opcoes": []
    },
    "pupilas isocoricas fotorreagentes": {
      "capitulo": "08",
      "opcoes": []
    },
    "hematoma": {
      "capitulo": "22",
      "opcoes": []
    },
    "sinais de esforço respiratorio": {
      "capitulo": "21",
      "opcoes": []
    },
    "expressões facial de dor": {
      "capitulo": "21",
      "opcoes": []
    },
    "sanguinolento": {
      "capitulo": "13",
      "opcoes": []
    },
    "desvio conjugado do olhar para esquerda": {
      "capitulo": "09",
      "opcoes": []
    },
    "dor abdominal": {
      "capitulo": "13",
      "opcoes": []
    },
    "avei": {
      "capitulo": "21",
      "opcoes": []
    },
    "glasgow 13": {
      "capitulo": "08",
      "opcoes": []
    },
    "diminuida em bases": {
      "capitulo": "09",
      "opcoes": []
    },
    "afasica": {
      "capitulo": "08",
      "opcoes": []
    },
    "forte algia": {
      "capitulo": "21",
      "opcoes": []
    },
    "sonolenta": {
      "capitulo": "06",
      "opcoes": []
    },
    "hernia hiato": {
      "capitulo": "19",
      "opcoes": []
    }
  }
}