{
  "prontuario_id": 902,
  "text": "ÀS 10:44 HS: ALERTA, TRAQUEOSTOMIZADO. CANULA DE PLÁSTICO, SOB NÉVOA ÚMIDA, EUPNEICO, DIETA VIA SONDA NASOENTERAL, SEM INTERCORRENCIA DURANTE A INFUSÃO, DIURESE EM UROPEN, ABDOME FLÁCIDO SEM FÁSCIES DE DOR A PALPAÇÃO, PELE INTEGRA, MANTEM PRECAUÇÃO DE CONTATO. ENF FLORENCE NIGHTINGALE, COREN XXXX. NEOPLASIA DE COMPORTAMENTO INCERTO OU DESCONHECIDO DO ENCEFALO SUPRATENTORIAL. Às 02:14: Cliente apresenta-se sonolenta, dispneica, hipocorada, aceitou dieta V.O, hemodinamicamente instável, acesso venoso em jugular permeável com soroterapia em curso, abdomen globoso, flácido, curativo em coto coxofemural direito apresenta hiperemia em virilha com lesões bolhosas, sonda vesical de demora com débito em média quantidade de aspecto amarelo escuro, apresentou hipoglicemia, esforço respiratório, chamado Plantão da clínica para avaliação, administrada medicação conforme prescrição, mantém névoa úmida contínua. OBS: A pedido dos familiares não foi realizada colocação de sonda nasoenteral. Enf Florence Nightingale. EDEMA CEREBRAL. Às 15:10H: Recebido do PS, hx de broncoespasmo por crise de asma grave. Admissão: PA 124/66 (86), FC 96 bpm, FR 14 rpm, T 35,5º C, Sat 96%. Ramsay 5, pupilas isomióticas. SNG aberta sem estase. Em ventilação mecânica modo PCV, Peep 5, PI 22 cmH2O, FiO2 50%. Intubado, rima labial de TOT em 24 cm, uso contínuo de filtro de barreira e sistema fechado de aspiração. Aspiração de secreção espessa purulenta em grande quantidade. CPP com sibilos difusos. Abdomen flácido, plano, RHA + . Acesso venoso periférico em antebraço D infundindo dormonid 30 ml/h + fentanil 15 ml/h + dopamina 10 ml/h. SVD com diurese concentrada (100 ml). Pele íntegra em região dorsal e sacra. Extremidades frias, sem edemas. Instalada monitorização contínua de parâmetros de PA não invasiva, cardioscopia e oximetria de pulso + precaução de contato profilático. Enfª Florence Nightingale. PANCREATITE AGUDA.",
  "entities": {
    "Achado": [
      "ALERTA",
      "TRAQUEOSTOMIZADO",
      "EUPNEICO",
      "permeável",
      "flácido",
      "débito",
      "FC",
      "Intubado",
      "plano",
      "DIURESE EM UROPEN",
      "PELE INTEGRA",
      "aceitou dieta V",
      "aspecto amarelo escuro",
      "Sat 96%",
      "Ramsay 5",
      "SNG aberta",
      "RHA +",
      "diurese concentrada",
      "Pele íntegra"
    ],
    "Procedimento Terapêutico ou Preventivo": [
      "TRAQUEOSTOMIZADO",
      "INFUSÃO",
      "curativo",
      "PCV",
      "Intubado",
      "Aspiração",
      "SVD",
      "NÉVOA ÚMIDA",
      "DIETA VIA SONDA NASOENTERAL",
      "PRECAUÇÃO DE CONTATO",
      "aceitou dieta V",
      "acesso venoso",
      "soroterapia em curso",
      "sonda vesical de demora",
      "névoa úmida contínua",
      "sonda nasoenteral",
      "SNG aberta",
      "ventilação mecânica",
      "filtro de barreira",
      "sistema fechado de aspiração",
      "Acesso venoso periférico",
      "precaução de contato profilático"
    ],
    "Sinal ou Sintoma": [
      "INTERCORRENCIA",
      "sonolenta",
      "dispneica",
      "hipocorada",
      "globoso",
      "hipoglicemia",
      "estase",
      "espessa",
      "purulenta",
      "frias",
      "edemas",
      "FÁSCIES DE DOR A PALPAÇÃO",
      "hemodinamicamente instável",
      "hiperemia em virilha",
      "lesões bolhosas",
      "esforço respiratório",
      "pupilas isomióticas",
      "sibilos difusos"
    ],
    "Localização ou Região Corporal": [
      "ABDOME",
      "abdomen",
      "CPP",
      "Abdomen",
      "sacra",
      "Extremidades",
      "região dorsal"
    ],
    "Negação": [
      "SEM",
      "não",
      "sem"
    ],
    "Abreviação": [
      "ENF",
      "Enf",
      "PS",
      "hx",
      "PA",
      "FC",
      "bpm",
      "FR",
      "rpm",
      "T",
      "PCV",
      "Peep",
      "PI",
      "FiO2",
      "TOT",
      "cm",
      "CPP",
      "D",
      "SVD",
      "Sat 96%",
      "SNG aberta",
      "RHA +"
    ],
    "Paciente ou Grupo com Deficiência": [
      "Cliente"
    ],
    "Parte do Corpo, Órgão ou Componente Orgânico": [
      "jugular",
      "antebraço",
      "coto coxofemural",
      "rima labial"
    ],
    "Conceito Qualitativo": [
      "permeável",
      "média quantidade",
      "grande quantidade"
    ],
    "Dispositivo Médico": [
      "curativo",
      "TOT",
      "SVD",
      "CANULA DE PLÁSTICO",
      "acesso venoso",
      "sonda vesical de demora",
      "sonda nasoenteral",
      "SNG aberta",
      "filtro de barreira",
      "Acesso venoso periférico"
    ],
    "Conceito Espacial": [
      "direito",
      "D"
    ],
    "Função Fisiológica": [
      "débito"
    ],
    "Substância Farmacológica": [
      "medicação",
      "dormonid",
      "fentanil",
      "dopamina"
    ],
    "Atividade de Assistência à Saúde": [
      "prescrição"
    ],
    "Produto Intelectual": [
      "prescrição"
    ],
    "Grupo Familiar": [
      "familiares"
    ],
    "Organização Relacionada à Saúde": [
      "PS",
      "Plantão da clínica"
    ],
    "Atributo Clínico": [
      "PA",
      "FC"
    ],
    "Conceito Quantitativo": [
      "124/66",
      "86",
      "96",
      "14",
      "5",
      "50%",
      "24",
      "35 , 5º C",
      "22 cmH2O",
      "30 ml/h",
      "15 ml/h",
      "10 ml/h",
      "100 ml"
    ],
    "Conceito Funcional": [
      "uso"
    ],
    "Conceito Temporal": [
      "contínuo"
    ],
    "Substância Corporal": [
      "secreção"
    ],
    "Substância Química Orgânica": [
      "dormonid",
      "fentanil",
      "dopamina"
    ],
    "Função Patológica": [
      "edemas",
      "EDEMA CEREBRAL"
    ],
    "Procedimento Diagnóstico": [
      "cardioscopia",
      "monitorização contínua",
      "oximetria de pulso"
    ],
    "Processo Neoplásico": [
      "NEOPLASIA DE COMPORTAMENTO INCERTO OU DESCONHECIDO DO ENCEFALO SUPRATENTORIAL"
    ],
    "Doença ou Síndrome": [
      "PANCREATITE AGUDA"
    ]
  },
  "labels": {
    "alerta": {
      "capitulo": "22",
      "opcoes": []
    },
    "edemas": {
      "capitulo": "11",
      "opcoes": []
    },
    "aspecto amarelo escuro": {
      "capitulo": "13",
      "opcoes": []
    },
    "dispneica": {
      "capitulo": "12",
      "opcoes": []
    },
    "fc": {
      "capitulo": "11",
      "opcoes": []
    },
    "hipoglicemia": {
      "capitulo": "5",
      "opcoes": []
    },
    "sng aberta": {
      "capitulo": "08",
      "opcoes": []
    },
    "pupilas isomióticas": {
      "capitulo": "08",
      "opcoes": []
    },
    "hipocorada": {
      "capitulo": "12",
      "opcoes": []
    },
    "lesões bolhosas": {
      "capitulo": "22",
      "opcoes": []
    },
    "esforço respiratório": {
      "capitulo": "21",
      "opcoes": []
    },
    "pancreatite aguda": {
      "capitulo": "13",
      "opcoes": []
    },
    "hiperemia em virilha": {
      "capitulo": "22",
      "opcoes": []
    },
    "edema cerebral": {
      "capitulo": "08",
      "opcoes": []
    },
    "permeável": {
      "capitulo": "11",
      "opcoes": []
    },
    "intubado": {
      "capitulo": "12",
      "opcoes": []
    },
    "hemodinamicamente instável": {
      "capitulo": "11",
      "opcoes": []
    },
    "fáscies de dor a palpação": {
      "capitulo": "21",
      "opcoes": []
    },
    "purulenta": {
      "capitulo": "13",
      "opcoes": []
    },
    "sibilos difusos": {
      "capitulo": "12",
      "opcoes": []
    },
    "traqueostomizado": {
      "capitulo": "22",
      "opcoes": []
    },
    "neoplasia de comportamento incerto ou desconhecido do encefalo supratentorial": {
      "capitulo": "02",
      "opcoes": []
    },
    "débito": {
      "capitulo": "13",
      "opcoes": []
    },
    "estase": {
      "capitulo": "08",
      "opcoes": []
    },
    "sonolenta": {
      "capitulo": "21",
      "opcoes": []
    }
  }
}