{
  "prontuario_id": 756,
  "text": "Realizado várias tentativas de punção de acesso central pelo Drª Vital Brasil, sem sucesso; realizado passagem de cateter vesical de demora, apresentando hematúria em grande quantidade. OUTROS TRANSTORNOS DO TRATO URINARIO. Às 14:55h: Contato telefônico com dr Vital Brasil, que solicitou não administrar as doses de heparina prescritas. Repassado para os auxiliares de enfermagem. INSUFICIENCIA RESPIRATORIA AGUDA. Às 17:45H: RAMSAY 06, DEPENDENTE DE DVA, NORMOTERMICO (36,4 c), TAQUICARDICO (125 bpm), PA 121/68 MMhg, PUPILAS ISOCORICAS BRADIFOTORREAGENTES, INTUBADO POR TOT 8.0 RIMA 24, MODO PCV, PEEP 5, FREQ 13, PI 16, SPO2 100%, AUSCULTA PULMONAR COM MV DIMINUIDO BIBASAL, CATETER VENOSO CENTRAL DUPLO-LUMEN, VIA JUGULAR DIREITA, INFUNDINDO NORADRENALINA 10 ML/H, FENTANIL 10 ML/H, MIDAZOLAN 15 ML/H, AMIODARONA 12 ML/H, ABDOME FLACIDO, RHA PRESENTES, EXTREMIDADES AQUECIDAS REGULARMENTE PERFUNDIDAS, FRAGILIDADE CUTANEA, PAM POSICIONAL EM RADIAL ESQUERDA, DIURESE EM UROPEN, MANTEM BOTAS PNEUMATICAS EM REPOUSO NO LEITO, SOB COLCHÃO DE AR. # REALIZADO TENTATIVAS SEM SUCESSO PARA SONDAGEM ENTERAL, INCLUSIVE PELOS INTENSIVSITAS, AGENDADO ENDOSCOPIA PARA AMANHA (20/07/2010). Às 13:20H: # CONFORME PASSADO EM PLANTÃO, PERMANECE COM URUPEM, POIS POR HISTORICO CLINICOS NÃO É POSSIVEL SONDAGEM VESICAL. ENF FLORENCE NIGHTINGALE, COREN XXXX. MELENA. 8H30MIN: Acordado, corado, pupilas isocóricas, eupneico em ar ambiente, aceitado dieto VO oferecida, relata algia em MSE, AVP em antebraço direito pérvio, tipóia em MSE com equimose em ombro esquerdo, eliminações presentes, aguardando cirurgia, provável 2ª-feira, segundo Dr Vital Brasil. Enfª Florence Nightingale, COREN XXXX. FRATURA DO MEMBRO SUPERIOR NIVEL NAO ESPECIFICADO.",
  "entities": {
    "Achado": [
      "sucesso",
      "NORMOTERMICO",
      "INTUBADO",
      "FLACIDO",
      "AQUECIDAS",
      "Acordado",
      "corado",
      "pérvio",
      "RAMSAY 06",
      "RHA PRESENTES",
      "REGULARMENTE PERFUNDIDAS",
      "FRAGILIDADE CUTANEA",
      "REPOUSO NO LEITO",
      "pupilas isocóricas",
      "eupneico em ar ambiente",
      "aceitado dieto VO",
      "eliminações presentes"
    ],
    "Abreviação": [
      "dr",
      "PA",
      "PEEP",
      "FREQ",
      "PI",
      "SPO2",
      "PAM",
      "ENF",
      "MSE",
      "AVP",
      "Dr",
      "Enfª",
      "DEPENDENTE DE DVA",
      "MODO PCV",
      "RHA PRESENTES",
      "aceitado dieto VO"
    ],
    "Negação": [
      "não",
      "NÃO"
    ],
    "Substância Farmacológica": [
      "heparina",
      "NORADRENALINA",
      "FENTANIL",
      "MIDAZOLAN",
      "AMIODARONA"
    ],
    "Substância Química Orgânica": [
      "heparina",
      "FENTANIL",
      "AMIODARONA"
    ],
    "Substância Biologicamente Ativa": [
      "heparina"
    ],
    "Sinal ou Sintoma": [
      "TAQUICARDICO",
      "BRADIFOTORREAGENTES",
      "algia",
      "equimose",
      "DIMINUIDO BIBASAL"
    ],
    "Atributo Clínico": [
      "PA"
    ],
    "Parte do Corpo, Órgão ou Componente Orgânico": [
      "PUPILAS",
      "RIMA",
      "JUGULAR DIREITA",
      "RADIAL ESQUERDA",
      "antebraço direito",
      "ombro esquerdo"
    ],
    "Conceito Quantitativo": [
      "24",
      "5",
      "13",
      "16",
      "100%",
      "36 , 4 c",
      "125 bpm",
      "121/68 MMhg",
      "10 ML/H",
      "15 ML/H",
      "12 ML/H"
    ],
    "Procedimento Terapêutico ou Preventivo": [
      "PEEP",
      "PI",
      "SPO2",
      "INFUNDINDO",
      "AVP",
      "tipóia",
      "cirurgia",
      "punção de",
      "acesso central",
      "passagem de cateter vesical de demora",
      "MODO PCV",
      "CATETER VENOSO CENTRAL DUPLO-LUMEN",
      "BOTAS PNEUMATICAS",
      "REPOUSO NO LEITO",
      "SONDAGEM ENTERAL",
      "SONDAGEM VESICAL"
    ],
    "Hormônio": [
      "NORADRENALINA"
    ],
    "Localização ou Região Corporal": [
      "EXTREMIDADES",
      "MSE"
    ],
    "Procedimento Diagnóstico": [
      "PAM",
      "ENDOSCOPIA",
      "AUSCULTA PULMONAR"
    ],
    "Dispositivo Médico": [
      "UROPEN",
      "URUPEM",
      "AVP",
      "tipóia",
      "acesso central",
      "CATETER VENOSO CENTRAL DUPLO-LUMEN",
      "BOTAS PNEUMATICAS",
      "COLCHÃO DE AR"
    ],
    "Grupo Profissional ou Ocupacional": [
      "INTENSIVSITAS",
      "ENF",
      "Enfª",
      "auxiliares de enfermagem"
    ],
    "Atividade de Assistência à Saúde": [
      "PLANTÃO"
    ],
    "Organização Relacionada à Saúde": [
      "PLANTÃO"
    ],
    "Conceito Qualitativo": [
      "grande quantidade"
    ],
    "Doença ou Síndrome": [
      "TRANSTORNOS DO TRATO URINARIO",
      "INSUFICIENCIA RESPIRATORIA AGUDA"
    ],
    "Objeto Manufaturado": [
      "COLCHÃO DE AR"
    ],
    "Função Fisiológica": [
      "eliminações presentes"
    ],
    "Lesão ou Envenenamento": [
      "FRATURA DO MEMBRO SUPERIOR"
    ]
  },
  "labels": {
    "pupilas isocóricas": {
      "capitulo": "08",
      "opcoes": []
    },
    "fratura do membro superior": {
      "capitulo": "15",
      "opcoes": []
    },
    "algia": {
      "capitulo": "21",
      "opcoes": []
    },
    "pérvio": {
      "capitulo": "21",
      "opcoes": []
    },
    "bradifotorreagentes": {
      "capitulo": "08",
      "opcoes": []
    },
    "ramsay 06": {
      "capitulo": "12",
      "opcoes": []
    },
    "insuficiencia respiratoria aguda": {
      "capitulo": "12",
      "opcoes": []
    },
    "fragilidade cutanea": {
      "capitulo": "15",
      "opcoes": []
    },
    "intubado": {
      "capitulo": "12",
      "opcoes": []
    },
    "equimose": {
      "capitulo": "21",
      "opcoes": []
    },
    "flacido": {
      "capitulo": "15",
      "opcoes": []
    },
    "transtornos do trato urinario": {
      "capitulo": "16",
      "opcoes": []
    },
    "diminuido bibasal": {
      "capitulo": "12",
      "opcoes": []
    },
    "taquicardico": {
      "capitulo": "11",
      "opcoes": []
    },
    "pam posicional em radial esquerda": {
      "capitulo": "21",
      "opcoes": []
    }
  }
}