{
  "prontuario_id": 310,
  "text": "Às 17h06min: CONSCIENTE, COMUNICATIVA, EM REPOUSO NO LEITO, EUPNEICA, NEGA ALGIA, ACEITA DIETA VIA ORAL, ELIMINACOES FISIOLOGICAS VESICAL E INTESTINAL PRESENTES, COM ACESSO VENOSO EM MEMBRO SUPERIOR DIREITO SALINIZADO. Florence Nightingale, AC ENF PUC. TRAUMATISMOS MULTIPLOS NAO ESPECIFICADOS. Às 14:30: ATIVA, ORINTADA NO TEMPO E NO ESPAÇO, CORADA. NEGA CEFALEIA, RESPONSIVA AOS REFLEXOS. ACESSO VENOSO EM FOSSA CUBITAL D SEM ALTERAÇOES ACIMA DO LOCAL DA PUNÇAO. DIURESE ESPONTANEA SEM ALTERAÇÃO NO ASPECTO. NÃO EVACUOU. ACADEMICA DE ENFERMAGEM FLORENCE NIGHTINGALE. CONCUSSAO CEREBRAL. Paciente com história de engasgo com espinha de peixe, a aproximadamente 7 dias. Consciente, orientado, verbalizando. Em jejum. Com acesso em MSE. aGUARDANDO CIRURGIA PELA OTORRINO. ABSCESSO RETROFARINGEO E PARAFARINGEO. Paciente lúcida, orientada, comunicativa, afebril, normotensa, normocorada. Mantém AVP em MSE salinizado. foi para exame de EDA, as 10:00. Paciente com úlcera de pressão em MID, mantendo curativo limpo e seco. refere algia em MMII, os quais se apresentam. ULCERA DOS MEMBROS INFERIORES NAO CLASSIFICADA EM OUTRA PARTE. Às 00:00: PACIENTE AGITADA, COM ABDOMEN DISTENDIDO, COM SANGRAMENTO EM REGIAO, QUEIXANDO- SE DE ALGIA NO LOCAL, CHAMADO PLANTAO MEDICO, O MESMO PRESCREVEU PASSAGEM DE SVD, MAS PACIENTE ATE O MOMENTO INSISTE EM NAO REALIZAR PROCEDIMENTO, EXPLICADO AS COMPLICAÇ. TRAUMATISMOS MULTIPLOS NAO ESPECIFICADOS. Acamado, bastante secreção de VAS. MV + bilateral, com presença de roncos em grande quantidade. Abd flácido com RHA presente. Edema em MMSS, com presença de hematomas. Dieta via gastrostomia. PNEUMONIA DEVIDA A HAEMOPHILUS INFUENZAE.",
  "entities": {
    "Achado": [
      "CONSCIENTE",
      "COMUNICATIVA",
      "EUPNEICA",
      "SALINIZADO",
      "ATIVA",
      "CORADA",
      "EVACUOU",
      "Consciente",
      "orientado",
      "verbalizando",
      "lúcida",
      "orientada",
      "comunicativa",
      "afebril",
      "normotensa",
      "normocorada",
      "salinizado",
      "limpo",
      "seco",
      "Acamado",
      "REPOUSO NO LEITO",
      "ACEITA DIETA VIA ORAL",
      "ELIMINACOES FISIOLOGICAS",
      "ORINTADA NO TEMPO E NO ESPAÇO",
      "RESPONSIVA AOS REFLEXOS",
      "DIURESE ESPONTANEA",
      "história de engasgo com espinha de peixe",
      "MV + bilateral",
      "Abd flácido",
      "RHA presente"
    ],
    "Negação": [
      "NEGA",
      "SEM",
      "NÃO",
      "afebril",
      "NAO"
    ],
    "Sinal ou Sintoma": [
      "ALGIA",
      "CEFALEIA",
      "ALTERAÇOES",
      "ALTERAÇÃO",
      "algia",
      "AGITADA",
      "SANGRAMENTO",
      "Edema",
      "hematomas",
      "ABDOMEN DISTENDIDO",
      "bastante secreção de VAS",
      "roncos em grande quantidade"
    ],
    "Procedimento Terapêutico ou Preventivo": [
      "SALINIZADO",
      "jejum",
      "acesso",
      "CIRURGIA",
      "AVP",
      "salinizado",
      "curativo",
      "REPOUSO NO LEITO",
      "ACESSO VENOSO",
      "PASSAGEM DE SVD",
      "Dieta via gastrostomia"
    ],
    "Grupo Profissional ou Ocupacional": [
      "ENF"
    ],
    "Abreviação": [
      "ENF",
      "MSE",
      "OTORRINO",
      "AVP",
      "EDA",
      "MID",
      "MMII",
      "MMSS",
      "FOSSA CUBITAL D",
      "PASSAGEM DE SVD",
      "bastante secreção de VAS",
      "MV + bilateral",
      "Abd flácido",
      "RHA presente"
    ],
    "Função Fisiológica": [
      "EVACUOU",
      "ELIMINACOES FISIOLOGICAS",
      "DIURESE ESPONTANEA"
    ],
    "Paciente ou Grupo com Deficiência": [
      "Paciente",
      "PACIENTE"
    ],
    "Dispositivo Médico": [
      "acesso",
      "AVP",
      "curativo",
      "ACESSO VENOSO"
    ],
    "Localização ou Região Corporal": [
      "MSE",
      "MID",
      "MMII",
      "MMSS",
      "MEMBRO SUPERIOR DIREITO",
      "FOSSA CUBITAL D"
    ],
    "Organização Relacionada à Saúde": [
      "OTORRINO"
    ],
    "Procedimento Diagnóstico": [
      "EDA"
    ],
    "Função Patológica": [
      "Edema",
      "hematomas"
    ],
    "Lesão ou Envenenamento": [
      "TRAUMATISMOS MULTIPLOS",
      "CONCUSSAO CEREBRAL"
    ],
    "Conceito Quantitativo": [
      "7 dias"
    ],
    "Conceito Temporal": [
      "7 dias"
    ],
    "Doença ou Síndrome": [
      "ABSCESSO RETROFARINGEO E PARAFARINGEO",
      "úlcera de pressão",
      "PNEUMONIA DEVIDA A HAEMOPHILUS INFUENZAE"
    ],
    "Substância Corporal": [
      "bastante secreção de VAS"
    ]
  },
  "labels": {
    "alteraçoes": {
      "capitulo": "21",
      "opcoes": []
    },
    "roncos em grande quantidade": {
      "capitulo": "09",
      "opcoes": []
    },
    "sangramento": {
      "capitulo": "22",
      "opcoes": []
    },
    "cefaleia": {
      "capitulo": "06",
      "opcoes": []
    },
    "hematomas": {
      "capitulo": "15",
      "opcoes": []
    },
    "abdomen distendido": {
      "capitulo": "12",
      "opcoes": []
    },
    "algia": {
      "capitulo": "06",
      "opcoes": []
    },
    "abd flácido": {
      "capitulo": "08",
      "opcoes": []
    },
    "pneumonia devida a haemophilus infuenzae": {
      "capitulo": "01",
      "opcoes": []
    },
    "mv + bilateral": {
      "capitulo": "09",
      "opcoes": []
    },
    "úlcera de pressão": {
      "capitulo": "14",
      "opcoes": []
    },
    "alteração": {
      "capitulo": "21",
      "opcoes": []
    },
    "abscesso retrofaringeo e parafaringeo": {
      "capitulo": "10",
      "opcoes": []
    },
    "ativa": {
      "capitulo": "06",
      "opcoes": []
    },
    "concussao cerebral": {
      "capitulo": "08",
      "opcoes": []
    },
    "agitada": {
      "capitulo": "21",
      "opcoes": []
    },
    "bastante secreção de vas": {
      "capitulo": "22",
      "opcoes": []
    },
    "traumatismos multiplos": {
      "capitulo": "22",
      "opcoes": []
    },
    "acamado": {
      "capitulo": "21",
      "opcoes": []
    },
    "edema": {
      "capitulo": "15",
      "opcoes": []
    }
  }
}