{
  "prontuario_id": 711,
  "text": "Às 02:10 H: CLIENTE PROVENIENTE DO CENTRO CIRURGICO, ACORDADO, CONSCIENTE, EUPNEICO, AFEBRIL, ORIENTADO, REPOUSO. MANTEM ACESSO PERIFERICO COM PLANO DE SORO EM CURSO. APRESENTA INCISÃO SECA E LIMPA EM FACE. ALGIA LOCAL, SENDO MEDICADO CPM. ELIMINAÇÕES NORMAIS. SEGUE EM OBSERVAÇÃO E CUIDADOS. ENFª FLORENCE NIGHTINGALE, COREN XXXX. TRAUMATISMOS MULTIPLOS NAO ESPECIFICADOS. Às 12:30hs: Glasgow 9, pupilas isocóricas fotorreagentes, SNE com dieta a 90 ml/h, traqueostomizado, em VM modo PSV, Ps 15, PEEP 5, FiO2 30%, secreção traqueobrônquica purulenta em média quantidade, acesso venoso central D com fentanil 10 ml/h, monitorizado, estável hemodinamicamente, MV + com roncos e bolhosos difusos, PAM em radial D, abdome globoso, flácido, RHA +, SVD com diurese efetiva, evacuação ausente, extremidades bem perfundidas, higienizado e mobilizado no leito, pele íntegra, mantendo precaução de contato por MRSA. Enfª Florence Nightingale, XXXX. EXAME GERAL E INVESTIGACAO DE PESSOAS SEM QUEIXAS OU DIAGNOSTICO RELATADO. Às 09:20hs: Glasgow 7, pupilas isocóricas fotorreagentes, SNE com dieta a 60 ml/h, traqueostomizada, em VM modo VCV, Vc 490 ml, PEEP 6, fiO2 50%, secreção traqueobrônquica purulenta em média quantidade, acesso venoso central D com plano básico de hidratação, monitorizada, estável hemodinamicamente, MV + com sibilos e roncos difusos, abdome globoso, flácido, RHA +, SVD com diurese efetiva, evacuação presente, extremidades quentes e bem perfundidas, higienizada e mobilizada no leito, mantendo precaução de contato por Acinetobacter. Enfª Florence Nightingale, XXXX. EDEMA CEREBRAL.",
  "entities": {
    "Paciente ou Grupo com Deficiência": [
      "CLIENTE"
    ],
    "Achado": [
      "ACORDADO",
      "CONSCIENTE",
      "EUPNEICO",
      "AFEBRIL",
      "ORIENTADO",
      "REPOUSO",
      "SECA",
      "LIMPA",
      "traqueostomizado",
      "flácido",
      "evacuação",
      "traqueostomizada",
      "monitorizada",
      "higienizada",
      "ELIMINAÇÕES NORMAIS",
      "estável hemodinamicamente",
      "MV +",
      "RHA +",
      "SVD com diurese efetiva",
      "extremidades bem perfundidas",
      "pele íntegra",
      "evacuação presente",
      "extremidades quentes",
      "bem perfundidas"
    ],
    "Negação": [
      "AFEBRIL",
      "ausente",
      "SEM"
    ],
    "Lesão ou Envenenamento": [
      "INCISÃO",
      "TRAUMATISMOS MULTIPLOS"
    ],
    "Localização ou Região Corporal": [
      "FACE",
      "abdome"
    ],
    "Sinal ou Sintoma": [
      "ALGIA",
      "Glasgow 9",
      "secreção traqueobrônquica purulenta",
      "roncos e bolhosos difusos",
      "Glasgow 7",
      "roncos difusos"
    ],
    "Procedimento Terapêutico ou Preventivo": [
      "MEDICADO",
      "traqueostomizado",
      "VM",
      "PEEP",
      "FiO2",
      "traqueostomizada",
      "fiO2",
      "higienizada",
      "ACESSO PERIFERICO",
      "PLANO DE SORO EM CURSO",
      "SNE com dieta",
      "modo PSV",
      "acesso venoso central",
      "mobilizado no leito",
      "precaução de contato",
      "modo VCV",
      "plano básico de hidratação",
      "mobilizada no leito"
    ],
    "Abreviação": [
      "CPM",
      "ENFª",
      "VM",
      "Ps",
      "PEEP",
      "FiO2",
      "D",
      "PAM",
      "Enfª",
      "Vc",
      "fiO2",
      "SNE com dieta",
      "modo PSV",
      "MV +",
      "radial D",
      "RHA +",
      "SVD com diurese efetiva",
      "modo VCV"
    ],
    "Atividade de Assistência à Saúde": [
      "OBSERVAÇÃO",
      "CUIDADOS"
    ],
    "Grupo Profissional ou Ocupacional": [
      "ENFª",
      "Enfª"
    ],
    "Parte do Corpo, Órgão ou Componente Orgânico": [
      "pupilas",
      "radial D"
    ],
    "Conceito Quantitativo": [
      "15",
      "5",
      "30%",
      "6",
      "50%",
      "90 ml/h",
      "média quantidade",
      "10 ml/h",
      "60 ml/h",
      "490 ml"
    ],
    "Conceito Espacial": [
      "D"
    ],
    "Substância Farmacológica": [
      "fentanil"
    ],
    "Substância Química Orgânica": [
      "fentanil"
    ],
    "Procedimento Diagnóstico": [
      "monitorizado",
      "PAM",
      "monitorizada"
    ],
    "Função Fisiológica": [
      "evacuação",
      "ELIMINAÇÕES NORMAIS",
      "evacuação presente"
    ],
    "Organização Relacionada à Saúde": [
      "CENTRO CIRURGICO"
    ],
    "Dispositivo Médico": [
      "ACESSO PERIFERICO",
      "acesso venoso central"
    ],
    "Substância Corporal": [
      "secreção traqueobrônquica purulenta"
    ],
    "Conceito Qualitativo": [
      "bem perfundidas"
    ],
    "Doença ou Síndrome": [
      "EDEMA CEREBRAL"
    ]
  },
  "labels": {
    "evacuação": {
      "capitulo": "22",
      "opcoes": []
    },
    "glasgow 7": {
      "capitulo": "21",
      "opcoes": []
    },
    "algia": {
      "capitulo": "21",
      "opcoes": []
    },
    "roncos difusos": {
      "capitulo": "12",
      "opcoes": []
    },
    "glasgow 9": {
      "capitulo": "21",
      "opcoes": []
    },
    "mv +": {
      "capitulo": "22",
      "opcoes": []
    },
    "roncos e bolhosos difusos": {
      "capitulo": "12",
      "opcoes": []
    },
    "incisão": {
      "capitulo": "14",
      "opcoes": []
    },
    "secreção traqueobrônquica purulenta": {
      "capitulo": "12",
      "opcoes": []
    },
    "edema cerebral": {
      "capitulo": "08",
      "opcoes": []
    },
    "traqueostomizado": {
      "capitulo": "22",
      "opcoes": []
    },
    "flácido": {
      "capitulo": "21",
      "opcoes": []
    },
    "traumatismos multiplos": {
      "capitulo": "22",
      "opcoes": []
    },
    "traqueostomizada": {
      "capitulo": "22",
      "opcoes": []
    }
  }
}