{
  "prontuario_id": 676,
  "text": "12:40hs- Realizado TAC de crânio, sem intercorrências durante o exame e transporte. Enfª FLORENCE NIGHTINGALE XXXX. TRAUMATISMOS MULTIPLOS NAO ESPECIFICADOS Pupilas isomióticas bradifotorreagentes; monitorizada com mulitparâmetros PA, ECG  Oximetria não invasivos; mantém cateter nasoenteral com diéta em curso sob BI à 40ml/h; respiração espontãnea dependente de VNI contínua modo \"E\" PEEP 4, FIO2 50%, SPO2 94%, uso de filtro de barreiras; CPP com MV diminuidos bibasais e roncos difusos; acesso venoso em dorso da mão \"\"D\" com SF0,9% à 21ml/h; dependente de Noradrenalina à 8ml/h (140/78), abdomem flácido sem massa palpável RHA +, hipoativos; cateter vesical de demora com diurése efetiva de cor clara sem grumos; ÚP sacra grau II, MM sem edemas, extremidas hipoaquecidas com perfusão lentificada. NEOPLASIA MALIGNA DA NASOFARINGE. 15:30 PROVINIENTE DA UTI-1  CONCIENTE COMUNICATIVO, SSVV ESTÁVEIS, ACESSO VENOSO NO ANTEBRAÇO ESQUERDO SEM SINAIS FLOGISTICO, ABDOMEN FLACIDO INDOLOR  A PALPAÇÃO, SVD COM DEBITO AMARELADO. PELE INTEGRA. SEM QUEIXAS ALGICAS NO MOMENTO. ENFª FLORENCE NIGHTINGAGLE XXXX. INSUFICIENCIA CARDIACA CONGESTIVA. 20:44 GLSAGOW 10,PUPILAS \n ISOFOTOREGAENTES, EUPINEICA, NORMOCARDICA, NORMOTENSA, NOMOCARDICA, AFEBRIL, AUSCUTA PULMONAR COM MURMURIO VISICULAR + RONCOS DIFUSOS, INTUBADA, FILTRO DE BAREIRA, SISTEMA FECHADO DE ASPIRAÇAO, VENTILAÇAO MECANICA MODO PSV, PEEP 5, FIO2 30%, ACESSO VENOSO CENTRAL EM SUBCLAVIA DIREITA, NORADRENALINA 15ML/H EM BOMBA INFUSORA, SORO GLICOSADO 126 ML/H EM BOMBA INFUSORA, EDEMA EM PALPEBRA DIREITA,, INCISÃO EM REGIAO CEFÁLICA LIMPA E SECA, ABDOMEM POUCO GLOBOSO, RHA +, SONDA VISICAL DE DEMORA COM DIURESE EFETIVA, AMARELO CLARO, EXTREMIDADES AQUECIDAS E PERFUNDIDAS, REALIZADO MEDIADS DE HIGIENE E CONFORTO, SEGUE COM OXIMETRIA DE PULSO, MONITORIZAÇO CARDIACA E CUIDADOS INTENSIVOS, PRECAUÇAO DE CONATATO PROFILATICO. SEPTICEMIA ESTREPTOCOCICA.",
  "entities": {
    "Negação": [
      "sem",
      "SEM",
      "AFEBRIL"
    ],
    "Sinal ou Sintoma": [
      "intercorrências",
      "isomióticas",
      "bradifotorreagentes",
      "hipoativos",
      "grumos",
      "edemas",
      "EDEMA",
      "dependente de VNI contínua",
      "roncos difusos",
      "extremidas hipoaquecidas",
      "perfusão lentificada",
      "SINAIS FLOGISTICO",
      "QUEIXAS ALGICAS",
      "GLSAGOW 10",
      "RONCOS DIFUSOS"
    ],
    "Procedimento Diagnóstico": [
      "exame",
      "ECG",
      "TAC de crânio",
      "monitorizada com mulitparâmetros",
      "Oximetria não invasivos",
      "AUSCUTA PULMONAR",
      "OXIMETRIA DE PULSO",
      "MONITORIZAÇO CARDIACA"
    ],
    "Abreviação": [
      "Enfª",
      "PA",
      "ECG",
      "BI",
      "PEEP",
      "FIO2",
      "SPO2",
      "CPP",
      "ÚP",
      "MM",
      "ENFª",
      "TAC de crânio",
      "dependente de VNI contínua",
      "dorso da mão \"\"D\"",
      "SF0 , 9%",
      "RHA +",
      "SSVV ESTÁVEIS",
      "SVD COM DEBITO AMARELADO",
      "MODO PSV"
    ],
    "Grupo Profissional ou Ocupacional": [
      "Enfª",
      "ENFª"
    ],
    "Parte do Corpo, Órgão ou Componente Orgânico": [
      "Pupilas",
      "ANTEBRAÇO ESQUERDO",
      "SUBCLAVIA DIREITA",
      "PALPEBRA DIREITA"
    ],
    "Dispositivo de Administração de Medicamento": [
      "BI",
      "BOMBA INFUSORA"
    ],
    "Conceito Quantitativo": [
      "40ml/h",
      "4",
      "50%",
      "94%",
      "21ml/h",
      "8ml/h",
      "5",
      "30%",
      "15ML/H",
      "126 ML/H"
    ],
    "Procedimento Terapêutico ou Preventivo": [
      "PEEP",
      "FIO2",
      "SPO2",
      "INTUBADA",
      "cateter nasoenteral",
      "modo \"E\"",
      "filtro de barreiras",
      "acesso venoso",
      "cateter vesical de demora",
      "ACESSO VENOSO",
      "SISTEMA FECHADO DE ASPIRAÇAO",
      "VENTILAÇAO MECANICA",
      "MODO PSV",
      "ACESSO VENOSO CENTRAL",
      "SONDA VISICAL DE DEMORA",
      "MEDIADS DE HIGIENE E CONFORTO",
      "PRECAUÇAO DE CONATATO PROFILATICO"
    ],
    "Conceito Qualitativo": [
      "4"
    ],
    "Substância Farmacológica": [
      "Noradrenalina",
      "NORADRENALINA",
      "SF0 , 9%",
      "SORO GLICOSADO"
    ],
    "Hormônio": [
      "Noradrenalina",
      "NORADRENALINA"
    ],
    "Substância Química Orgânica": [
      "Noradrenalina",
      "NORADRENALINA"
    ],
    "Localização ou Região Corporal": [
      "abdomem",
      "sacra",
      "MM",
      "ABDOMEN",
      "ABDOMEM",
      "EXTREMIDADES",
      "dorso da mão \"\"D\"",
      "REGIAO CEFÁLICA"
    ],
    "Doença ou Síndrome": [
      "ÚP",
      "INSUFICIENCIA CARDIACA CONGESTIVA",
      "SEPTICEMIA ESTREPTOCOCICA"
    ],
    "Função Patológica": [
      "edemas"
    ],
    "Achado": [
      "CONCIENTE",
      "COMUNICATIVO",
      "EUPINEICA",
      "NORMOCARDICA",
      "NORMOTENSA",
      "NOMOCARDICA",
      "AFEBRIL",
      "INTUBADA",
      "LIMPA",
      "SECA",
      "AQUECIDAS",
      "PERFUNDIDAS",
      "monitorizada com mulitparâmetros",
      "respiração espontãnea",
      "massa palpável",
      "RHA +",
      "diurése efetiva",
      "cor clara",
      "SSVV ESTÁVEIS",
      "PELE INTEGRA",
      "PUPILAS ISOFOTOREGAENTES",
      "MURMURIO VISICULAR",
      "DIURESE EFETIVA",
      "AMARELO CLARO"
    ],
    "Lesão ou Envenenamento": [
      "INCISÃO",
      "TRAUMATISMOS MULTIPLOS"
    ],
    "Dispositivo Médico": [
      "cateter nasoenteral",
      "filtro de barreiras",
      "acesso venoso",
      "cateter vesical de demora",
      "ACESSO VENOSO",
      "FILTRO DE BAREIRA",
      "ACESSO VENOSO CENTRAL",
      "BOMBA INFUSORA",
      "SONDA VISICAL DE DEMORA"
    ],
    "Função Fisiológica": [
      "diurése efetiva",
      "DIURESE EFETIVA"
    ],
    "Processo Neoplásico": [
      "NEOPLASIA MALIGNA DA NASOFARINGE"
    ],
    "Atividade de Assistência à Saúde": [
      "MEDIADS DE HIGIENE E CONFORTO",
      "CUIDADOS INTENSIVOS"
    ]
  },
  "labels": {
    "dependente de vni contínua": {
      "capitulo": "12",
      "opcoes": []
    },
    "úp": {
      "capitulo": "22",
      "opcoes": []
    },
    "edemas": {
      "capitulo": "16",
      "opcoes": []
    },
    "monitorizada com mulitparâmetros": {
      "capitulo": "12",
      "opcoes": []
    },
    "roncos difusos": {
      "capitulo": "11",
      "opcoes": []
    },
    "septicemia estreptococica": {
      "capitulo": "01",
      "opcoes": []
    },
    "intubada": {
      "capitulo": "12",
      "opcoes": []
    },
    "incisão": {
      "capitulo": "22",
      "opcoes": []
    },
    "sinais flogistico": {
      "capitulo": "22",
      "opcoes": []
    },
    "insuficiencia cardiaca congestiva": {
      "capitulo": "11",
      "opcoes": []
    },
    "intercorrências": {
      "capitulo": "22",
      "opcoes": []
    },
    "respiração espontânea": {
      "capitulo": "12",
      "opcoes": []
    },
    "hipoativos": {
      "capitulo": "22",
      "opcoes": []
    },
    "murmurio visicular": {
      "capitulo": "11",
      "opcoes": []
    },
    "neoplasia maligna da nasofaringe": {
      "capitulo": "02",
      "opcoes": []
    },
    "traumatismos multiplos": {
      "capitulo": "22",
      "opcoes": []
    },
    "edema": {
      "capitulo": "16",
      "opcoes": []
    }
  }
}