{
  "prontuario_id": 957,
  "text": "   PACIENTE DIABÉTICA, HIPERTENSA, CARDIOPATIA ISQ. COM IMPLANTE DE STENT EM DAE EM JUL/03 INTERNOU NO HOSP XXXX COM QUADRO DE ANGINA INSTÁVEL. TRANSFERIDA PARA O SERV DE HEMODINÂMICA DO XXXX, REALIZOU CAT SENDO SUBMETIDA A  ACTP EM LESÃO DE ÓSTIO DA SEGUNDA DIAGONAL. PROCEDIMENTO REALIZADO COM SUCESSO ANGIOGRÁFICO. RECEBE ALTA ASSINTOMÁTICA. Paciente ex-tabagista, vem à emergência com quadro de dispnéia progressiva, ortopnéia, dispnéia paroxística noturna, edema de membros inferiores, turgência jugular. Diagnóstico de insuficiência cardíaca, com classe funcional IV (NYHA) na chegada. Sem história de dor torácica. ECG da chegada sem alterações. Marcadores de necrose miocárdica normais. Manejado para insuficiência cardíaca com boa resposta clínica. Ecocardiograma demonstrando dilatação de cavidades (AE = 5,3 cm, DDVE = 7,0, DSVE = 5,8), disfunção sistólica (FEVE = 35%) por hipocinesia difusa, septo e parede posterior de 0,9 cm, insuficiência mitral e tricúspide leves e PSAP = 52 mmHg. Realizado investigação etiológica com sorologia negativa para Chagas, cintilografia demonstrando necrose apical, sem condições de discriminar isquemia. Optado então pela realização de cateterismo cardíaco, que revelou artéria circunflexa dominante e livre de lesões significativas; artéria coronária direita livre com sinais de aterosclerose, mas sem lesões significativas; artéria descendente anterior de pequeno calibre, com lesão de cerca de 60% no terço proximal e lesão crítica no terço médio. Após revisão do filme, observou-se tratar de lesão de difícil manejo percutâneo, devido à sua extensão e ao pequeno calibre da artéria descrita. Após discussão do caso, optou-se por manejo clínico devido ao fato do paciente não apresentar angina, ter respondido com sucesso à terapêutica instituída e não apresentar evidência clara de benefício atual com procedimento de revascularização. Impressão de que a lesão em DAE não explicaria a hipocinesia difusa apresentada pelo paciente, devendo ser portanto doença aterosclerótica coexistindo em um coração com miocardiopatia dilatada.  Realizado ainda espirometria que evidenciou distúrbio obstrutivo moderado. DCE estimada em 57 ml/min. Paciente recebe alta em bom estado geral, afebril, eupnéico, em otimização do tratamento para ICC (já em uso de betabloqueador, IECA e espironolactona), com plano de ajustes de doses a nível ambulatorial.   OBS: peso na alta: 76 Kg.",
  "entities": {
    "Paciente ou Grupo com Deficiência": [
      "PACIENTE",
      "Paciente",
      "paciente"
    ],
    "Doença ou Síndrome": [
      "DIABÉTICA",
      "HIPERTENSA",
      "ICC",
      "CARDIOPATIA ISQ",
      "insuficiência cardíaca",
      "doença aterosclerótica",
      "miocardiopatia dilatada"
    ],
    "Organização Relacionada à Saúde": [
      "HOSP",
      "emergência",
      "ambulatorial",
      "SERV DE HEMODINÂMICA"
    ],
    "Abreviação": [
      "HOSP",
      "CAT",
      "ECG",
      "ICC",
      "IECA",
      "CARDIOPATIA ISQ",
      "SERV DE HEMODINÂMICA",
      "AE = 5 , 3 cm",
      "DDVE = 7 , 0",
      "FEVE = 35%",
      "PSAP = 52 mmHg",
      "lesão em DAE",
      "DCE estimada"
    ],
    "Procedimento Terapêutico ou Preventivo": [
      "CAT",
      "PROCEDIMENTO",
      "manejo clínico",
      "procedimento de revascularização",
      "otimização do tratamento",
      "plano de ajustes de doses"
    ],
    "Procedimento Diagnóstico": [
      "CAT",
      "ECG",
      "Ecocardiograma",
      "cintilografia",
      "espirometria",
      "investigação etiológica",
      "cateterismo cardíaco"
    ],
    "Atividade de Assistência à Saúde": [
      "ALTA",
      "recebe alta"
    ],
    "Negação": [
      "ASSINTOMÁTICA",
      "Sem",
      "sem",
      "não",
      "afebril"
    ],
    "Achado": [
      "ASSINTOMÁTICA",
      "ex-tabagista",
      "afebril",
      "eupnéico",
      "SUCESSO ANGIOGRÁFICO",
      "boa resposta clínica",
      "lesão de difícil manejo percutâneo",
      "respondido com sucesso à terapêutica",
      "bom estado geral"
    ],
    "Sinal ou Sintoma": [
      "ortopnéia",
      "edema",
      "angina",
      "ANGINA INSTÁVEL",
      "dispnéia progressiva",
      "dispnéia paroxística noturna",
      "turgência jugular",
      "dor torácica",
      "hipocinesia difusa"
    ],
    "Parte do Corpo, Órgão ou Componente Orgânico": [
      "artéria",
      "coração"
    ],
    "Substância Farmacológica": [
      "betabloqueador",
      "IECA",
      "espironolactona"
    ],
    "Substância Química Orgânica": [
      "espironolactona"
    ],
    "Localização ou Região Corporal": [
      "membros inferiores"
    ],
    "Resultado Laboratorial ou de Teste": [
      "dilatação de cavidades",
      "AE = 5 , 3 cm",
      "DDVE = 7 , 0",
      "disfunção sistólica",
      "FEVE = 35%",
      "hipocinesia difusa",
      "septo e parede posterior de 0 , 9 cm",
      "insuficiência mitral e tricúspide leves",
      "PSAP = 52 mmHg",
      "sorologia negativa para Chagas",
      "necrose apical",
      "artéria circunflexa dominante",
      "livre de lesões significativas",
      "artéria descendente anterior de pequeno calibre",
      "lesão de cerca de 60% no terço proximal",
      "lesão crítica no terço médio",
      "lesão de difícil manejo percutâneo",
      "distúrbio obstrutivo moderado",
      "57 ml/min"
    ],
    "Procedimento Laboratorial": [
      "investigação etiológica"
    ],
    "Conceito Quantitativo": [
      "76 Kg"
    ]
  },
  "labels": {
    "hipertensa": {
      "capitulo": "11",
      "opcoes": []
    },
    "turgência jugular": {
      "capitulo": "21",
      "opcoes": []
    },
    "insuficiência cardíaca": {
      "capitulo": "11",
      "opcoes": []
    },
    "dor torácica": {
      "capitulo": "21",
      "opcoes": []
    },
    "icc": {
      "capitulo": "11",
      "opcoes": []
    },
    "miocardiopatia dilatada": {
      "capitulo": "11",
      "opcoes": []
    },
    "angina": {
      "capitulo": "11",
      "opcoes": []
    },
    "cardiopatia isq": {
      "capitulo": "11",
      "opcoes": []
    },
    "dispnéia paroxística noturna": {
      "capitulo": "21",
      "opcoes": []
    },
    "doença aterosclerótica": {
      "capitulo": "11",
      "opcoes": []
    },
    "dispnéia progressiva": {
      "capitulo": "21",
      "opcoes": []
    },
    "diabética": {
      "capitulo": "11",
      "opcoes": []
    },
    "ortopnéia": {
      "capitulo": "21",
      "opcoes": []
    },
    "lesão de difícil manejo percutâneo": {
      "capitulo": "22",
      "opcoes": []
    },
    "hipocinesia difusa": {
      "capitulo": "11",
      "opcoes": []
    },
    "angina instável": {
      "capitulo": "11",
      "opcoes": []
    },
    "edema": {
      "capitulo": "21",
      "opcoes": []
    }
  }
}