{
  "prontuario_id": 778,
  "text": " MARIA, 71 ANOS ; # OSTEOPOROSE. # HISTERECTOMIA + OOFORECTOMIA HÁ 7 ANOS -> TRH. # GLAUCOMA / CATARATA. PTE INTERNA POR IAM COM SUPRA DE ST INFERIOR (25/05/06) SENDO LEVADA À ACTP PRIMÁRIA COM STENT EM ACD COM DELTA T DE 3 HORAS. ACE LIVRE DE LESÕES. EVOLUI ASSINTOMÁTICA, SEM INTERCORRÊNCIAS. RECEBE ALTA EM BEG, COM PRESCRIÇÃO DE MEDICAMENTOS CONTÍNUOS. SE QUALQUER INTERCORRÊNCIA, RETORNAR À EMERGÊNCIA DO HOSPITAL. PACIENTE DIABÉTICA , HIPERTENSA ,EX-TABAGISTA, HISTÓRIA DE TER SOFRIDO IAM (SEM LOCALIZAÇÃO) HÁ 40 DIAS DA INTERNAÇÃO , TENDO PERMANECIDO INTERNADA POR 30 DIAS NO HOSPITAL XXXX (CIDADE XXXX). DURANTE A INTERNAÇÃO EM SUA CIDADE IMPLANTOU MARCAPASSO DEFINITIVO POR BRADIARRITMIA . ALGUNS DIAS APÓS A ALTA INICIOU COM DISPNÉIA EM REPOUSO, ORTOPNÉIA E DPN, REINTERNADA POR IC CLASSE 4. NESTA OCASIÃO APRESENTAVA ISQUEMIA CRÍTICA DE MEMBRO INFERIOR ESQUERDO QUANDO FOI TRANSFERIDA PARA O XXXX PARA REALIZAÇÃO DE DE BY PASS .REALIZOU BY PASS FEMORO-FEMORAL CRUZADO DIR-ESQ. REALIZOU TAMBÉM CINEANGIO QUE MOSTROU (15/04) DA OCLUÍDA APÓS A 1' EPTAL, CX COM LESÃO LONGA DE 50 % DISTAL, CD PEQUENA COM LESÃO SUBOCLUSIVA 99 % NO SEGMENTO MÉDIO, ACINESIA APICAL E DISCINESIA APICAL (FE: 32 %), INSUFICIÊNCIA MITRAL MODERADA. EVOLUIU SATISFATORIAMENTE, COMPENSOU DA IC, RECEBE ALTA HOSPITALAR EM CLASSE FUNCIONAL 2, PERMANECE COM FO ABERTA DEVENDO REALIZAR CURATIVOS DIÁRIOS CONFORME ORIENTAÇÃO DA CIR VASCULAR E ACOMPANHAMENTO AMBULATORIAL. DISCUTIDO CINEANGIO COM DR VITAL BRASIL, QUE ORIENTOU SOLICITAÇÃO DE CINTILO MIOCÁRDICA COM DIPIRIDAMOL PARA VER SE HÁ ISQUEMIA EM TERRITÓRIO DE DA E POSTERIOR MARCAÇÃO CIRÚRGICA. REALIZOU CINTILO COM DIPIRIDAMOL (RESULTADO DISCUTIDO COM DR VITAL BRASIL) QUE MOSTRA VIABILIDADE EM TODA PAREDE ANTERIOR E TAMBÉM EM SEPTO APICAL, ÁREA DE NECROSE EM SEPTO INFERIOR. RECEBE ALTA BEM, DEVENDO REALIZAR MARCAÇÃO CIRÚRGICA AMBULATORIALMENTE.",
  "entities": {
    "Conceito Temporal": [
      "ANOS",
      "HORAS",
      "DIAS",
      "DURANTE",
      "DIÁRIOS",
      "DELTA T"
    ],
    "Doença ou Síndrome": [
      "OSTEOPOROSE",
      "GLAUCOMA",
      "CATARATA",
      "DIABÉTICA",
      "HIPERTENSA",
      "IAM",
      "BRADIARRITMIA",
      "IC",
      "IAM COM SUPRA DE ST INFERIOR",
      "IC CLASSE 4",
      "ACINESIA APICAL",
      "DISCINESIA APICAL",
      "INSUFICIÊNCIA MITRAL"
    ],
    "Procedimento Terapêutico ou Preventivo": [
      "HISTERECTOMIA",
      "OOFORECTOMIA",
      "TRH",
      "ACTP PRIMÁRIA",
      "IMPLANTOU MARCAPASSO DEFINITIVO",
      "BY PASS",
      "MARCAÇÃO CIRÚRGICA"
    ],
    "Abreviação": [
      "TRH",
      "PTE",
      "ACD",
      "ACE",
      "BEG",
      "IAM",
      "DPN",
      "CINEANGIO",
      "DA",
      "IAM COM SUPRA DE ST INFERIOR",
      "ACTP PRIMÁRIA",
      "IC CLASSE 4",
      "( FE : 32 % )",
      "FO ABERTA",
      "CIR VASCULAR",
      "CINTILO MIOCÁRDICA"
    ],
    "Paciente ou Grupo com Deficiência": [
      "PTE",
      "PACIENTE"
    ],
    "Atividade de Assistência à Saúde": [
      "INTERNA",
      "ALTA",
      "PRESCRIÇÃO",
      "INTERNAÇÃO",
      "INTERNADA",
      "REINTERNADA",
      "ORIENTAÇÃO",
      "ALTA HOSPITALAR",
      "REALIZAR MARCAÇÃO CIRÚRGICA"
    ],
    "Dispositivo Médico": [
      "STENT"
    ],
    "Parte do Corpo, Órgão ou Componente Orgânico": [
      "ACD",
      "ACE",
      "DA",
      "CD"
    ],
    "Achado": [
      "ASSINTOMÁTICA",
      "BEG",
      "EX-TABAGISTA",
      "VIABILIDADE",
      "BEM",
      "LIVRE DE LESÕES",
      "EVOLUIU SATISFATORIAMENTE",
      "FO ABERTA"
    ],
    "Negação": [
      "ASSINTOMÁTICA",
      "SEM"
    ],
    "Sinal ou Sintoma": [
      "INTERCORRÊNCIAS",
      "INTERCORRÊNCIA",
      "ORTOPNÉIA",
      "DPN",
      "DISPNÉIA EM REPOUSO"
    ],
    "Substância Farmacológica": [
      "MEDICAMENTOS",
      "DIPIRIDAMOL"
    ],
    "Organização Relacionada à Saúde": [
      "EMERGÊNCIA",
      "HOSPITAL",
      "AMBULATORIALMENTE"
    ],
    "Objeto Manufaturado": [
      "EMERGÊNCIA",
      "HOSPITAL"
    ],
    "Conceito Espacial": [
      "LOCALIZAÇÃO",
      "DISTAL"
    ],
    "Conceito Qualitativo": [
      "CRÍTICA",
      "PEQUENA",
      "MODERADA"
    ],
    "Conceito Funcional": [
      "DIR-ESQ"
    ],
    "Procedimento Diagnóstico": [
      "CINEANGIO",
      "CINTILO MIOCÁRDICA"
    ],
    "Substância Química Orgânica": [
      "DIPIRIDAMOL"
    ],
    "Função de Órgão ou Tecido": [
      "NECROSE"
    ],
    "Localização ou Região Corporal": [
      "MEMBRO INFERIOR ESQUERDO",
      "SEGMENTO MÉDIO"
    ],
    "Conceito Quantitativo": [
      "50 %",
      "99 %"
    ],
    "Resultado Laboratorial ou de Teste": [
      "ACINESIA APICAL",
      "( FE : 32 % )",
      "SEPTO APICAL"
    ],
    "Classificação": [
      "CLASSE FUNCIONAL 2"
    ],
    "Grupo Profissional ou Ocupacional": [
      "CIR VASCULAR"
    ]
  },
  "labels": {
    "hipertensa": {
      "capitulo": "11",
      "opcoes": []
    },
    "bradiarritmia": {
      "capitulo": "03",
      "opcoes": []
    },
    "viabilidade": {
      "capitulo": "21",
      "opcoes": []
    },
    "iam": {
      "capitulo": "09",
      "opcoes": []
    },
    "discinesia apical": {
      "capitulo": "08",
      "opcoes": []
    },
    "ic": {
      "capitulo": "11",
      "opcoes": []
    },
    "ex-tabagista": {
      "capitulo": "24",
      "opcoes": []
    },
    "dpn": {
      "capitulo": "15",
      "opcoes": []
    },
    "insuficiência mitral": {
      "capitulo": "11",
      "opcoes": []
    },
    "osteoporose": {
      "capitulo": "15",
      "opcoes": []
    },
    "beg": {
      "capitulo": "24",
      "opcoes": []
    },
    "intercorrência": {
      "capitulo": "21",
      "opcoes": []
    },
    "acinesia apical": {
      "capitulo": "08",
      "opcoes": []
    },
    "intercorrências": {
      "capitulo": "21",
      "opcoes": []
    },
    "dispnéia em repouso": {
      "capitulo": "13",
      "opcoes": []
    },
    "fo aberta": {
      "capitulo": "24",
      "opcoes": []
    },
    "catarata": {
      "capitulo": "09",
      "opcoes": []
    },
    "glaucoma": {
      "capitulo": "09",
      "opcoes": []
    },
    "diabética": {
      "capitulo": "15",
      "opcoes": []
    },
    "ortopnéia": {
      "capitulo": "15",
      "opcoes": []
    },
    "ic classe 4": {
      "capitulo": "11",
      "opcoes": []
    },
    "iam com supra de st inferior": {
      "capitulo": "09",
      "opcoes": []
    }
  }
}