{
  "prontuario_id": 148,
  "text": "ID: Lucas, 74 anos, natural e procedente de Rio Branco, aposentado há 35 anos, divorciado.  QP: Retorno.  HMA: acompanhante refere que o paciente apresenta DM. Refere sr DM2 há 15 anos, realiza tratamento com insulina há cerca de 03 anos, parou de usar há cerca de 08 meses devido  a mal estar durante a madrugada (hipoglicemia). chegou a ir no hospital, sendo medicado com glicose VO. acompanhante refere nao fazer dextro em casa.  paciente refere cefaleia, holocraniana, que melhora com analgesia. sem fatores de piora.    exames  19/04/2013: creatinina 1,4; glicose 209, K 5; P 4; HbA1C 9,48%; PROTEINURIA DE 24 HRS: 2706; Cl Creatinina calculado = 50 ml / min.  13/03/2013 RETINOGRAFIA: retinopatia DM não proliferatia, fotocoagulada no OD com areas de macroperfusao. opacidade de meios.  17/10/2012: TG 163, HDL 48, CT 175, ldl 94, GLICOSE 318, HbA1C 8,52%; MICROALBUMINURIA 1,849 (VR < 30). Nega historia de CA na família. medicamentos - insulina NPH 20U à noite (aplicada antes de dormir), glicazida 30mg 2 cp no almoço, metformina 850mg 2 x/dia, sinvastatina 20mg 2 cps no jantar, losartana 50mg 2 x/dia, hidroclorotiazida 1cp pela manhã, omeprazol 20mg 1 cp pela manhã. - HAS há cerca de 15 anos, dislipidemia. - Paciente refere trauma direto em olho E, com perda de visão, ocorrido há aproximadamente 35 anos. - Nega alergias.  - refere sarampo, coqueluche, varicela, caxumba na infancia.",
  "entities": {
    "Abreviação": [
      "ID",
      "QP",
      "HMA",
      "DM",
      "DM2",
      "HAS",
      "K 5",
      "P 4",
      "HbA1C 9 , 48%",
      "PROTEINURIA DE 24 HRS : 2706",
      "Cl Creatinina calculado = 50 ml / min",
      "retinopatia DM não proliferatia",
      "fotocoagulada no OD com areas de macroperfusao",
      "TG 163",
      "HDL 48",
      "CT 175",
      "ldl 94",
      "HbA1C 8 , 52%",
      "MICROALBUMINURIA 1 , 849",
      "VR &lt; 30",
      "historia de CA na família",
      "2 cp",
      "2 cps",
      "1 cp",
      "olho E"
    ],
    "Atividade de Assistência à Saúde": [
      "Retorno"
    ],
    "Doença ou Síndrome": [
      "DM",
      "DM2",
      "hipoglicemia",
      "HAS",
      "dislipidemia",
      "alergias",
      "sarampo",
      "coqueluche",
      "varicela",
      "caxumba"
    ],
    "Organização Relacionada à Saúde": [
      "hospital"
    ],
    "Procedimento Terapêutico ou Preventivo": [
      "medicado"
    ],
    "Negação": [
      "nao",
      "sem",
      "Nega"
    ],
    "Procedimento Diagnóstico": [
      "dextro",
      "RETINOGRAFIA"
    ],
    "Sinal ou Sintoma": [
      "cefaleia",
      "mal estar",
      "fatores de piora",
      "perda de visão"
    ],
    "Substância Farmacológica": [
      "glicazida",
      "metformina",
      "sinvastatina",
      "losartana",
      "hidroclorotiazida",
      "omeprazol",
      "insulina NPH"
    ],
    "Conceito Quantitativo": [
      "20mg",
      "2 cp",
      "2 cps",
      "1 cp"
    ],
    "Conceito Temporal": [
      "durante a madrugada",
      "à noite",
      "antes de dormir",
      "no almoço",
      "2 x/dia",
      "no jantar",
      "pela manhã"
    ],
    "Resultado Laboratorial ou de Teste": [
      "creatinina 1 , 4",
      "glicose 209",
      "K 5",
      "P 4",
      "HbA1C 9 , 48%",
      "PROTEINURIA DE 24 HRS : 2706",
      "Cl Creatinina calculado = 50 ml / min",
      "fotocoagulada no OD com areas de macroperfusao",
      "opacidade de meios",
      "TG 163",
      "HDL 48",
      "CT 175",
      "ldl 94",
      "GLICOSE 318",
      "HbA1C 8 , 52%",
      "MICROALBUMINURIA 1 , 849"
    ],
    "Atributo Clínico": [
      "VR &lt; 30"
    ],
    "Achado": [
      "historia de CA na família"
    ],
    "Lesão ou Envenenamento": [
      "trauma direto"
    ],
    "Parte do Corpo, Órgão ou Componente Orgânico": [
      "olho E"
    ]
  },
  "labels": {
    "hipoglicemia": {
      "capitulo": "05",
      "opcoes": []
    },
    "dm2": {
      "capitulo": "05",
      "opcoes": []
    },
    "has": {
      "capitulo": "05",
      "opcoes": []
    },
    "dislipidemia": {
      "capitulo": "05",
      "opcoes": []
    },
    "caxumba": {
      "capitulo": "01",
      "opcoes": []
    },
    "cefaleia": {
      "capitulo": "09",
      "opcoes": []
    },
    "coqueluche": {
      "capitulo": "01",
      "opcoes": []
    },
    "mal estar": {
      "capitulo": "21",
      "opcoes": []
    },
    "trauma direto": {
      "capitulo": "22",
      "opcoes": []
    },
    "dm": {
      "capitulo": "05",
      "opcoes": []
    },
    "perda de visão": {
      "capitulo": "09",
      "opcoes": []
    },
    "sarampo": {
      "capitulo": "01",
      "opcoes": []
    },
    "varicela": {
      "capitulo": "01",
      "opcoes": []
    }
  }
}