{
  "prontuario_id": 74,
  "text": "R2 MFC Lucas.  DM2 há 6 anos, HAS há 20 anos, bócio, historia de hipotireoidismo, sem tratamento há 1 ano, por recomendação médica (sic). Artrose e desvio de coluna, devido à trauma local. Nega tabagismo, nega evento CV prévio.  Em uso de metformina 850mg 0 - 1 - 1, gliclazida 60 1 - 0, carvedilol 6,25 1 - 1, anlodipino 5 + benazepril 10 uma vez ao dia, indapamida (se edema), oxibutinina (para incontinência urinária). Última avaliação oftalmológica há 6 meses, com relato de retinopatia diabética. # S : Paciente sem queixas. Última consulta no ambulatorio há um ano. Vem para apresentar resultado de exames. Não trouxe controle glicêmico de jejum, mas relata dextro entre 80 - 140. Também relata aferições de PA domiciliar com valor mínimo de 180/100mmHg.  # O : BEG. PA 240/200mmHg (relata não ter tomado anti-hipertensivos hoje). Bócio nodular. FC 67. Alt 1,65. Peso 78,5. IMC  28.  # Lab 01/06/16: TSH < 0,1. T4 livre 2,04. Cr 0,6. Glicose 142. CT 142. LDL 77. HDL 37. TG 142. K 4,4. TGP 25. TGO 20. Normoalbuminúria. TFG 93 mL/min.  ** Hemoglobina glicada não solicitada **. # A: HAS descompensada. DM2 compensada?, Hipertireoidismo subclínico.  # P: Solicitamos USG tireoide e laboratoriais de controle. Iniciamos tapazol 5mg /dia. Modificamos prescrição para: metformina 850mg 1 - 1 - 1, gliclazida 60mg 1 - 1, losartana 50mg 1 - 1, anlodipino 5mg 1 - 1, HCTZ 25mg 1 - 0, carvedilol 6,25mg 1 - 0, tapazol 5mg /dia. Faço esquema de medicações em tabela para facilitar compreensão a administração pela paciente. Fornecemos pedido para nutricionista. Retorno dia 11/10/16. Na próxima consulta encaminhar para oftalmo.",
  "entities": {
    "Doença ou Síndrome": [
      "DM2",
      "HAS",
      "bócio",
      "hipotireoidismo",
      "Artrose",
      "tabagismo",
      "evento CV",
      "incontinência urinária",
      "retinopatia diabética",
      "Bócio nodular",
      "HAS descompensada",
      "DM2 compensada",
      "Hipertireoidismo subclínico"
    ],
    "Abreviação": [
      "DM2",
      "HAS",
      "S",
      "O",
      "BEG",
      "PA",
      "FC",
      "Alt",
      "IMC",
      "Lab",
      "A",
      "P",
      "HCTZ",
      "oftalmo",
      "evento CV",
      "aferições de PA domiciliar",
      "Cr 0 , 6",
      "CT 142",
      "TG 142",
      "K 4 , 4",
      "TFG 93 mL/min",
      "HAS descompensada",
      "DM2 compensada",
      "USG tireoide"
    ],
    "Negação": [
      "sem",
      "Nega",
      "nega",
      "Não",
      "não"
    ],
    "Procedimento Terapêutico ou Preventivo": [
      "tratamento"
    ],
    "Conceito Temporal": [
      "prévio",
      "há 6 meses"
    ],
    "Substância Química Orgânica": [
      "metformina",
      "gliclazida",
      "carvedilol",
      "anlodipino",
      "benazepril",
      "indapamida",
      "oxibutinina",
      "tapazol",
      "losartana",
      "HCTZ"
    ],
    "Substância Farmacológica": [
      "metformina",
      "gliclazida",
      "carvedilol",
      "anlodipino",
      "benazepril",
      "indapamida",
      "oxibutinina",
      "anti-hipertensivos",
      "tapazol",
      "losartana",
      "HCTZ"
    ],
    "Conceito Quantitativo": [
      "5",
      "180/100mmHg",
      "240/200mmHg",
      "67",
      "28",
      "6 , 25",
      "uma vez ao dia",
      "1 , 65",
      "78 , 5",
      "5mg /dia",
      "6 , 25mg"
    ],
    "Sinal ou Sintoma": [
      "edema",
      "queixas"
    ],
    "Achado": [
      "S",
      "BEG",
      "Normoalbuminúria",
      "HAS descompensada",
      "DM2 compensada"
    ],
    "Paciente ou Grupo com Deficiência": [
      "Paciente"
    ],
    "Atividade de Assistência à Saúde": [
      "consulta",
      "O",
      "Solicitamos",
      "Iniciamos",
      "Retorno",
      "encaminhar",
      "recomendação médica",
      "avaliação oftalmológica",
      "Modificamos prescrição",
      "Fornecemos pedido"
    ],
    "Organização Relacionada à Saúde": [
      "ambulatorio",
      "nutricionista"
    ],
    "Atributo Clínico": [
      "PA",
      "FC",
      "Alt",
      "Peso",
      "IMC"
    ],
    "Procedimento Laboratorial": [
      "Lab",
      "Hemoglobina glicada"
    ],
    "Resultado Laboratorial ou de Teste": [
      "Normoalbuminúria",
      "dextro entre 80 - 140",
      "TSH &lt; 0 , 1",
      "T4 livre 2 , 04",
      "Cr 0 , 6",
      "Glicose 142",
      "CT 142",
      "LDL 77",
      "HDL 37",
      "TG 142",
      "K 4 , 4",
      "TGP 25",
      "TGO 20",
      "TFG 93 mL/min"
    ],
    "Procedimento Diagnóstico": [
      "A",
      "controle glicêmico de jejum",
      "USG tireoide"
    ],
    "Produto Intelectual": [
      "P"
    ],
    "Grupo Profissional ou Ocupacional": [
      "nutricionista",
      "oftalmo"
    ],
    "Lesão ou Envenenamento": [
      "trauma local"
    ]
  },
  "labels": {
    "retinopatia diabética": {
      "capitulo": "11",
      "opcoes": []
    },
    "bócio nodular": {
      "capitulo": "05",
      "opcoes": []
    },
    "hipertireoidismo subclínico": {
      "capitulo": "05",
      "opcoes": []
    },
    "queixas": {
      "capitulo": "21",
      "opcoes": []
    },
    "dm2 compensada": {
      "capitulo": "05",
      "opcoes": []
    },
    "beg": {
      "capitulo": "11",
      "opcoes": []
    },
    "trauma local": {
      "capitulo": "15",
      "opcoes": []
    },
    "incontinência urinária": {
      "capitulo": "16",
      "opcoes": []
    },
    "dm2": {
      "capitulo": "05",
      "opcoes": []
    },
    "artrose": {
      "capitulo": "15",
      "opcoes": []
    },
    "has": {
      "capitulo": "11",
      "opcoes": []
    },
    "s": {
      "capitulo": "21",
      "opcoes": []
    },
    "bócio": {
      "capitulo": "05",
      "opcoes": []
    },
    "has descompensada": {
      "capitulo": "11",
      "opcoes": []
    },
    "hipotireoidismo": {
      "capitulo": "05",
      "opcoes": []
    },
    "edema": {
      "capitulo": "16",
      "opcoes": []
    }
  }
}