{
  "prontuario_id": 159,
  "text": "57 anos, casado (4 filhos), panificação. QP: \" EXAME DE ROTINA E PROBLEMA  NO ESTÔMAGO\".  HÁ 3 ANOS DESCONFORTO EM EPIGÁSTRIO (SENTE ESTUFAMENTO APÓS ALIMENTAÇÃO - QUALQUER QUANTIDADE), COM REGURGITAÇÃO E TONTURA, COM ALÍVIO APÓS 3 - 4 H. PERDEU 8 KG EM 7 MESES. USA OMEPRAZOL, E RANITIDINA. DIABÉTICO HÁ 3 ANOS, METFORMINA (3 CP /DIA - MANHÃ, TARDE E A NOITE - 850 MG), GLICAZIDA 30mg (1 CP/DIA - ANTES DO ALMOÇO), HIPERTENSO HÁ 5 ANOS, LOSARTANA, ATENOLOL.  RELATA ESTAR CUIDANDO DA ALIMENTAÇÃO: PELA MANHÃ PÃO INTEGRAL E LEITE DESNATADO, PELO ALMOÇO ARROZ, FRANGO - CARNE VERMELHA NÃO, POIS PIORA O ESTUFAMENTO -, NA JANTA ARROZ E OVO. NEGA TABAGISMO E ETILISMO. HÁBITO INTESTINAL SEM ALTERAÇÃO.   RESULTADOS  DOS EXAMES: ULTRASSONOGRÁFICO DO ABDOME (FÍGADO APRESENTANDO AUMENTO DIFUSO DA SUA ECOGENICIDADE E ATENUAÇÃO DO FEIXE SONORO DISTAL, QUE PREJUDICA PARCIALMENTE SUA AVALIAÇÃO E DA SUA VASCULARIZAÇÃO - IMPRESSÃO: SINAIS COMPATÍVEIS COM ESTEATOSE HEPÁTICA IMPORTANTE, GRAU III). GLICEMIA = 112,4; GLICOSE PÓS-PRANDIAL = 161; CT = 177,3; HDL = 41; LDL = 112,8; TG = 117,5; ÁCIDO ÚRICO = 3,92; POTÁSSIO = 3,6; TGO = 22,74; TGP = 50,16; CREATININA = 0,98; TFG CKD-EPI 84 ml/min/1.73 m2; UREIA = 35,2; TSH = 3,364, T4 = 1,12; MICROALBUMINÚRIA = 2,31; HBAC1 = 7,9. DM TIPO 2, OBESIDADE, HAS, S. METABOLICA, DISPEPSIA A ESCLARECER. MÃE DIABÉTICA MORREU DO CORAÇÃO AOS 60 ANOS, IRMÃ E IRMÃO COM DIABETES E HAS, PAI COM GLAUCOMA FALECEU AOS 90 ANOS, FILHOS SAUDÁVEIS. FEZ CIRURGA EM ANTEBRAÇO ESQUERDO HÁ 9 ANOS POR ACIDENTE DE MOTO, DESDE ENTÃO REFERE FRAQUEZA. TOMAVA BESILAPIN (TROCOU POR ATENOLOL DEVIDO A TAQUICARDIA). TEM ALERGIA A DIPIRONA E AAS. DM, DISTENSÃO ABDOMINAL.",
  "entities": {
    "Abreviação": [
      "QP",
      "HAS",
      "AAS",
      "DM",
      "CT = 177 , 3",
      "TG = 117 , 5",
      "HBAC1 = 7 , 9",
      "DM TIPO 2"
    ],
    "Achado": [
      "QP",
      "DIABÉTICO",
      "HIPERTENSO",
      "DM",
      "EXAME DE ROTINA",
      "ALÍVIO APÓS 3 - 4 H",
      "FILHOS SAUDÁVEIS"
    ],
    "Alimento": [
      "ALIMENTAÇÃO",
      "ARROZ",
      "FRANGO",
      "OVO",
      "PÃO INTEGRAL",
      "LEITE DESNATADO",
      "CARNE VERMELHA"
    ],
    "Sinal ou Sintoma": [
      "REGURGITAÇÃO",
      "TONTURA",
      "ALTERAÇÃO",
      "DISPEPSIA",
      "FRAQUEZA",
      "PROBLEMA NO ESTÔMAGO\"",
      "DESCONFORTO EM EPIGÁSTRIO",
      "PERDEU 8 KG",
      "PIORA O ESTUFAMENTO",
      "DISTENSÃO ABDOMINAL"
    ],
    "Substância Farmacológica": [
      "OMEPRAZOL",
      "RANITIDINA",
      "METFORMINA",
      "GLICAZIDA",
      "LOSARTANA",
      "ATENOLOL",
      "BESILAPIN",
      "DIPIRONA",
      "AAS"
    ],
    "Substância Química Orgânica": [
      "OMEPRAZOL",
      "RANITIDINA",
      "METFORMINA",
      "GLICAZIDA",
      "LOSARTANA",
      "ATENOLOL",
      "BESILAPIN",
      "DIPIRONA",
      "AAS"
    ],
    "Doença ou Síndrome": [
      "DIABÉTICO",
      "HIPERTENSO",
      "TABAGISMO",
      "ETILISMO",
      "OBESIDADE",
      "HAS",
      "DIABÉTICA",
      "DIABETES",
      "GLAUCOMA",
      "ALERGIA",
      "DM",
      "DM TIPO 2"
    ],
    "Procedimento Terapêutico ou Preventivo": [
      "CUIDANDO"
    ],
    "Negação": [
      "NÃO",
      "NEGA",
      "SEM"
    ],
    "Conceito Temporal": [
      "MANHÃ , TARDE E A NOITE",
      "ANTES DO ALMOÇO",
      "PELA MANHÃ",
      "PELO ALMOÇO",
      "NA JANTA"
    ],
    "Conceito Quantitativo": [
      "850 MG",
      "1 CP/DIA"
    ],
    "Resultado Laboratorial ou de Teste": [
      "RESULTADOS DOS EXAMES",
      "FÍGADO APRESENTANDO AUMENTO DIFUSO DA SUA ECOGENICIDADE",
      "ATENUAÇÃO DO FEIXE SONORO DISTAL",
      "PREJUDICA PARCIALMENTE SUA AVALIAÇÃO E DA SUA VASCULARIZAÇÃO",
      "SINAIS COMPATÍVEIS COM ESTEATOSE HEPÁTICA IMPORTANTE , GRAU III",
      "GLICEMIA = 112 , 4",
      "GLICOSE PÓS-PRANDIAL = 161",
      "CT = 177 , 3",
      "HDL = 41",
      "LDL = 112 , 8",
      "TG = 117 , 5",
      "ÁCIDO ÚRICO = 3 , 92",
      "POTÁSSIO = 3 , 6",
      "TGO = 22 , 74",
      "TGP = 50 , 16",
      "CREATININA = 0 , 98",
      "TFG CKD-EPI 84 ml/min/1",
      "UREIA = 35 , 2",
      "TSH = 3 , 364",
      "T4 = 1 , 12",
      "MICROALBUMINÚRIA = 2 , 31",
      "HBAC1 = 7 , 9"
    ],
    "Procedimento Diagnóstico": [
      "ULTRASSONOGRÁFICO DO ABDOME"
    ],
    "Parte do Corpo, Órgão ou Componente Orgânico": [
      "ANTEBRAÇO ESQUERDO"
    ],
    "Lesão ou Envenenamento": [
      "ACIDENTE DE MOTO"
    ]
  },
  "labels": {
    "tabagismo": {
      "capitulo": "24",
      "opcoes": []
    },
    "qp": {
      "capitulo": "13",
      "opcoes": []
    },
    "acidente de moto": {
      "capitulo": "22",
      "opcoes": []
    },
    "tontura": {
      "capitulo": "08",
      "opcoes": []
    },
    "obesidade": {
      "capitulo": "05",
      "opcoes": []
    },
    "diabético": {
      "capitulo": "11",
      "opcoes": []
    },
    "exame de rotina": {
      "capitulo": "13",
      "opcoes": []
    },
    "etilismo": {
      "capitulo": "24",
      "opcoes": []
    },
    "piora o estufamento": {
      "capitulo": "21",
      "opcoes": []
    },
    "problema no estômago": {
      "capitulo": "13",
      "opcoes": []
    },
    "regurgitação": {
      "capitulo": "13",
      "opcoes": []
    },
    "has": {
      "capitulo": "11",
      "opcoes": []
    },
    "glaucoma": {
      "capitulo": "09",
      "opcoes": []
    },
    "diabética": {
      "capitulo": "05",
      "opcoes": []
    },
    "alteração": {
      "capitulo": "21",
      "opcoes": []
    },
    "fraqueza": {
      "capitulo": "15",
      "opcoes": []
    },
    "hipertenso": {
      "capitulo": "11",
      "opcoes": []
    },
    "desconforto em epigástrio": {
      "capitulo": "13",
      "opcoes": []
    },
    "distensão abdominal": {
      "capitulo": "13",
      "opcoes": []
    },
    "dispepsia": {
      "capitulo": "13",
      "opcoes": []
    },
    "alergia": {
      "capitulo": "24",
      "opcoes": []
    },
    "dm tipo 2": {
      "capitulo": "05",
      "opcoes": []
    },
    "dm": {
      "capitulo": "05",
      "opcoes": []
    },
    "diabetes": {
      "capitulo": "05",
      "opcoes": []
    }
  }
}