{
  "prontuario_id": 332,
  "text": "Às 14:49h: Paciente consciente, orientado, comunicativo, em repouso no leito, afebril, em ar ambiente, eupneico, AVP em MSE salinizado, apresenta MSE edemaciado e com hematoma, aguarda procedimento cirúrgico, aceitando dieta oferecida, diurese presente, sem queixas algicas. Segue sob cuidados. FRATURA DA EXTREMIDADE SUPERIOR DO UMERO. Às 18h: Paciente segue sem prescrição médica, solicitado para o plantão prescrever, porém ainda não foi prescrito. OUTROS TRAUMATISMOS E OS NAO ESPECIFICADOS DO QUADRIL E DA COXA. Às 9:30 H: CONSCIENTE, ORIENTADO, VERBALIZANDO, MOBILIZANDO ATIVAMENTE OS MEMBROS. EUPNEICO EM AR AMBIENTE, MV DIFUSOS, SOROTERAPIA EM ACESSO VENOSO PERIFÉRICO EM MSE, SENDO INFUNDIDO SF 0,9. ABDOME GLOBOSO, RHA PRESENTES, SVD URINA EFETIVA. MONITORIZADO OXIMETRIA DE PULSO, HEMODINAMICAMENTE ESTÁVEL. DIABETES MELLITUS NAO ESPECIFICADO. Às 14:10h: Realizo passagem de SNE para alimentação; procedimento realizado sem intercorrência; Solicito RX de abdome simples no leito para 16h. Aguarda realização de RX para liberação da dieta. OUTRAS DOENCAS CEREBROVASCULARES. Às 17:20: PACIENTE ADMITIDA DO CENTRO CIRÚRGICO ÁS 17:00 HORAS, RAMSAY 6, PUPILAS ISOFOTORREAGENTES, INTUBADA (TOT) 8, RIMA LABIAL 23, NORMOCÁRDICA, NORMOTENSA, AFEBRIL, AUSCUTA PULMONAR MV +, DISCRETOS RONCOS DIFUSOS, ACESSO VENOSO CENTRAL EM SUBCLÁVIA DIREITA DUPLO-LUMEN, SEDAÇÃO EM BOMBA 30 ML/H, ACESSO VENOSO PERIFÉRICO EM MSD, MONITORIZAÇAO DE PAM, ABDOMEN DISTENDIDO, CURATIVO FECHADO + DRENO DE SUCTOR COM POUCO DÉBITO HEMÁTICO, REGIÃO DORSAL E SACRA ÍNTEGRA, EXTREMIDADES AQUECIDAS E PERFUNDIDAS, SEGUE COM OXIMETRIA DE PULSO, MONITORIZAÇÃO CARDÍACA E CUIDADOS INTENSIVOS, PRECAUÇAO DE CONTATO PROFILÁTICO. HERNIA UMBILICAL.",
  "entities": {
    "Paciente ou Grupo com Deficiência": [
      "Paciente",
      "PACIENTE"
    ],
    "Achado": [
      "consciente",
      "orientado",
      "comunicativo",
      "afebril",
      "eupneico",
      "salinizado",
      "CONSCIENTE",
      "ORIENTADO",
      "VERBALIZANDO",
      "INTUBADA",
      "NORMOCÁRDICA",
      "NORMOTENSA",
      "AFEBRIL",
      "ÍNTEGRA",
      "AQUECIDAS",
      "PERFUNDIDAS",
      "repouso no leito",
      "ar ambiente",
      "aceitando dieta",
      "diurese presente",
      "MOBILIZANDO ATIVAMENTE OS MEMBROS",
      "EUPNEICO EM AR AMBIENTE",
      "MV DIFUSOS",
      "RHA PRESENTES",
      "URINA EFETIVA",
      "HEMODINAMICAMENTE ESTÁVEL",
      "RAMSAY 6",
      "PUPILAS ISOFOTORREAGENTES",
      "MV +",
      "CURATIVO FECHADO",
      "DÉBITO HEMÁTICO"
    ],
    "Negação": [
      "afebril",
      "sem",
      "AFEBRIL"
    ],
    "Dispositivo Médico": [
      "AVP",
      "SVD",
      "TOT",
      "DUPLO-LUMEN",
      "ACESSO VENOSO PERIFÉRICO",
      "ACESSO VENOSO CENTRAL",
      "CURATIVO FECHADO",
      "DRENO DE SUCTOR"
    ],
    "Procedimento Terapêutico ou Preventivo": [
      "AVP",
      "salinizado",
      "SOROTERAPIA",
      "SVD",
      "procedimento",
      "repouso no leito",
      "procedimento cirúrgico",
      "aceitando dieta",
      "MOBILIZANDO ATIVAMENTE OS MEMBROS",
      "ACESSO VENOSO PERIFÉRICO",
      "passagem de SNE para alimentação",
      "ACESSO VENOSO CENTRAL",
      "CURATIVO FECHADO",
      "DRENO DE SUCTOR",
      "PRECAUÇAO DE CONTATO PROFILÁTICO"
    ],
    "Abreviação": [
      "AVP",
      "MSE",
      "SF",
      "SVD",
      "RX",
      "MSD",
      "MV DIFUSOS",
      "RHA PRESENTES",
      "passagem de SNE para alimentação",
      "RX de abdome simples",
      "MV +",
      "MONITORIZAÇAO DE PAM"
    ],
    "Localização ou Região Corporal": [
      "MSE",
      "ABDOME",
      "MSD",
      "EXTREMIDADES"
    ],
    "Sinal ou Sintoma": [
      "edemaciado",
      "intercorrência",
      "queixas algicas",
      "DISCRETOS RONCOS DIFUSOS",
      "ABDOMEN DISTENDIDO"
    ],
    "Função Patológica": [
      "edemaciado",
      "com hematoma"
    ],
    "Atividade de Assistência à Saúde": [
      "cuidados",
      "plantão",
      "Realizo",
      "Solicito",
      "prescrição médica",
      "CUIDADOS INTENSIVOS"
    ],
    "Procedimento Diagnóstico": [
      "MONITORIZADO",
      "RX",
      "OXIMETRIA DE PULSO",
      "RX de abdome simples",
      "AUSCUTA PULMONAR",
      "MONITORIZAÇAO DE PAM",
      "MONITORIZAÇÃO CARDÍACA"
    ],
    "Alimento": [
      "dieta"
    ],
    "Conceito Quantitativo": [
      "8",
      "23"
    ],
    "Função Fisiológica": [
      "diurese presente",
      "URINA EFETIVA"
    ],
    "Lesão ou Envenenamento": [
      "FRATURA DA EXTREMIDADE SUPERIOR DO UMERO"
    ],
    "Produto Intelectual": [
      "prescrição médica"
    ],
    "Doença ou Síndrome": [
      "DIABETES MELLITUS",
      "DOENCAS CEREBROVASCULARES"
    ],
    "Organização Relacionada à Saúde": [
      "CENTRO CIRÚRGICO"
    ],
    "Parte do Corpo, Órgão ou Componente Orgânico": [
      "RIMA LABIAL",
      "SUBCLÁVIA DIREITA"
    ],
    "Dispositivo de Administração de Medicamento": [
      "SEDAÇÃO EM BOMBA"
    ],
    "Anormalidade Anatômica": [
      "HERNIA UMBILICAL"
    ]
  },
  "labels": {}
}