{
  "prontuario_id": 581,
  "text": "10:00: AVALIADO RAIO-X, SNE MAL POSICIONADA, REPASSADA SEM INTERCORRÊNCIA NO PROCEDIMENTO. AUSCULTA ABDOMINAL POSITIVA. RETIRO FIO GUIA, SOLICITO RAIO-X PARA AVALIAÇÃO DA POSIÇÃO. 17:50: CLIENTE RELATOU CEFALÉIA NO PERÍODO DA MANHÃ E FOI MEDICADO. CONSCIENTE, PUPILAS ISOCÓRICAS FOTORREAGENTES, COMUNICATIVO, EUPNÉICO, REPOUSO NO LEITO, ACEITANDO BEM A DIETA, SEM ACESSO PERIFÉRICO, APRESENTANDO EDEMA EM OMBRO E, MANTENDO TIPÓIA DE ATADURA EM MSE, ABDÔMEN PLANO E FLÁCIDO, ELIMINAÇÕES PRESENTES. 20:50 h: Paciente com cuff furado, realizado troca de TOT, instalado TOT 7.5, VM modo controlado VC 500, PEEP 07, FIO2 a 50%. 22:30h: ESQUEMA DE SUPERVISÃO NOTURNA: TRAQUEOSTOMIZADO, EM DESMAME VENTILATÓRIO EM PS DE 17, PEEP 5, FIO2 50%. PERMANECE EXTREMAMENTE AGITADO (não responde à sedação intermitente). REINICIADO  DORMONID 7 ML/H, FENTANIL 2 ML/H (continua não respondendo). PERMANECE AGITADO, ARRANCOU SOE. ACESSO VENOSO PERIFÉRICO EM MSD COM PLANO BÁSICO DE HIDRATAÇÃO + SEDAÇÃO. POLISSECRETIVO (mantendo trach care). FO SEM SINAIS FLOGÍSTICOS EM FACE, EDEMA EM FACE LD. MONITORIZAÇÃO DE MÚLTIPLOS PARÂMETROS CONFORME ROTINA DA UTI. DIURESE EM UROPEN. 23:30 h: Retorna do CC, onde realizou relaparotomia exploradora, instalado sistema de aspiração fechado em traqueostomia (trach care) no CC, trajeto de volta do CC sem intercorrências, mantém monitorização de parâmetros, TOT nº 7,5 em rima 22, VM modo VCV 440ml, peep 6, fio2 a 40%, pupilas isocóricas fotorreagentes, SNG com débito em média quantidade de aspecto borra de café, diurese via SVD em média quantidade, sem grumos, de cor amarelo claro, PAM em radial esquerda, acesso venoso central em subclávia à direita, evacuação ausente no período.  ",
  "entities": {
    "Procedimento Diagnóstico": [
      "RAIO-X",
      "MONITORIZAÇÃO DE MÚLTIPLOS PARÂMETROS",
      "monitorização de parâmetros"
    ],
    "Abreviação": [
      "SNE",
      "MSE",
      "TOT",
      "VM",
      "VC",
      "PEEP",
      "FIO2",
      "PS",
      "ML/H",
      "SOE",
      "MSD",
      "FO",
      "LD",
      "CC",
      "peep",
      "fio2",
      "SNG",
      "PAM",
      "troca de TOT",
      "modo VCV"
    ],
    "Dispositivo Médico": [
      "SNE",
      "TOT",
      "UROPEN",
      "SNG",
      "SVD",
      "FIO GUIA",
      "ACESSO PERIFÉRICO",
      "TIPÓIA DE ATADURA",
      "cuff furado",
      "ACESSO VENOSO PERIFÉRICO",
      "acesso venoso central"
    ],
    "Atividade de Assistência à Saúde": [
      "PROCEDIMENTO",
      "SUPERVISÃO NOTURNA"
    ],
    "Paciente ou Grupo com Deficiência": [
      "CLIENTE",
      "Paciente"
    ],
    "Sinal ou Sintoma": [
      "CEFALÉIA",
      "EDEMA",
      "AGITADO",
      "POLISSECRETIVO",
      "AUSCULTA ABDOMINAL POSITIVA",
      "aspecto borra de café"
    ],
    "Procedimento Terapêutico ou Preventivo": [
      "MEDICADO",
      "VM",
      "SEDAÇÃO",
      "traqueostomia",
      "SNG",
      "ACESSO PERIFÉRICO",
      "TIPÓIA DE ATADURA",
      "troca de TOT",
      "DESMAME VENTILATÓRIO",
      "ACESSO VENOSO PERIFÉRICO",
      "PLANO BÁSICO DE HIDRATAÇÃO",
      "relaparotomia exploradora",
      "sistema de aspiração fechado",
      "modo VCV",
      "acesso venoso central"
    ],
    "Achado": [
      "CONSCIENTE",
      "COMUNICATIVO",
      "EUPNÉICO",
      "FLÁCIDO",
      "TRAQUEOSTOMIZADO",
      "PAM",
      "AUSCULTA ABDOMINAL POSITIVA",
      "PUPILAS ISOCÓRICAS FOTORREAGENTES",
      "REPOUSO NO LEITO",
      "ELIMINAÇÕES PRESENTES",
      "cuff furado",
      "pupilas isocóricas fotorreagentes",
      "sem grumos",
      "cor amarelo claro"
    ],
    "Alimento": [
      "DIETA"
    ],
    "Função Patológica": [
      "EDEMA"
    ],
    "Localização ou Região Corporal": [
      "OMBRO",
      "MSE",
      "ABDÔMEN",
      "MSD",
      "FACE",
      "rima"
    ],
    "Conceito Qualitativo": [
      "EXTREMAMENTE",
      "MAL POSICIONADA"
    ],
    "Substância Farmacológica": [
      "DORMONID",
      "FENTANIL"
    ],
    "Substância Química Orgânica": [
      "DORMONID",
      "FENTANIL"
    ],
    "Lesão ou Envenenamento": [
      "FO"
    ],
    "Doença ou Síndrome": [
      "EDEMA"
    ],
    "Organização Relacionada à Saúde": [
      "UTI",
      "CC"
    ],
    "Parte do Corpo, Órgão ou Componente Orgânico": [
      "radial",
      "subclávia"
    ],
    "Conceito Espacial": [
      "esquerda",
      "direita"
    ],
    "Negação": [
      "SEM INTERCORRÊNCIA",
      "SEM SINAIS FLOGÍSTICOS",
      "sem grumos"
    ],
    "Conceito Temporal": [
      "PERÍODO DA MANHÃ",
      "no período"
    ],
    "Conceito Quantitativo": [
      "débito em média quantidade",
      "média quantidade"
    ]
  },
  "labels": {
    "agitado": {
      "capitulo": "06"
    },
    "ausculta abdominal positiva": {
      "capitulo": "12"
    },
    "cor amarelo claro": {
      "capitulo": "21"
    },
    "cuff furado": {
      "capitulo": "22"
    },
    "sem grumos": {
      "capitulo": "21"
    },
    "cefaléia": {
      "capitulo": "06"
    },
    "pam": {
      "capitulo": "09"
    },
    "polissecretivo": {
      "capitulo": "21"
    },
    "eliminações presentes": {
      "capitulo": "13"
    },
    "traqueostomizado": {
      "capitulo": "12"
    },
    "pupilas isocóricas fotorreagentes": {
      "capitulo": "08"
    },
    "flácido": {
      "capitulo": "15"
    },
    "aspecto borra de café": {
      "capitulo": "21"
    },
    "fo": {
      "capitulo": "09"
    },
    "edema": {
      "capitulo": "14"
    }
  }
}