{
  "prontuario_id": 703,
  "text": "ÀS 12H: RETORNOU DO CENTRO CIRÚRGICO, POI FRATURA LUXAÇÃO ACETÁBULO ESQUERDO E FRATURA DE CABEÇA FEMORAL, POUCO SONOLENTA, ABERTURA OCULAR ESPONTÂNEA, PUPILAS ISOCÓRICAS, APRESENTA EQUIMOSE PERIORBITAL DIREITA, EUPNEICA EM AR AMBIENTE, ESCORIAÇÃO EM LÁBIO SUPERIOR, SEM QUEIXAS ÁLGICAS NO MOMENTO, LIBERADO DIETA CONFORME PRESCRIÇÃO MÉDICA, AVP EM ANTEBRAÇO ESQUERDO COM SOROTERAPIA EM CURSO, APRESENTA GLOBO VESICAL. SOLICITO MATERIAL PARA REALIZAÇÃO DE CATETERISMO DE ALÍVIO. CURATIVO EM FÊMUR LIMPO E SECO EXTERNAMENTE COM DRENO DE SUCTOR, POUCO DÉBITO HEMÁTICO, CURATIVO PERNA ESQUERDA LIMPO E SECO EXTERNAMENTE, BOA PERFUSÃO PERIFÉRICA. Em 07/01/2012, NOITE: Vítima de FAF pélvico com entrada por espinha ilícia ântero-posterior e saída por glúteo D. Lesão grau II em sigmóide e em bexiga. Submetido à colorrafia e cistorrafia. PO de reimplante de ureter E. PO de LE. Glasgow 15, sonolento, responsivo, pupilas isofoto. Extubado de dia, agora respiração espontânea com auxílio de névoa em máscara de O2. Monitorização cardíaca contínua, PAM e oximetria digital. HMD estável, afebril e com boa saturação. SNG aberta com pouco débito bilioso. Jejum até segunda ordem. Hipocorado, hidratado, pele íntegra em reg sacra. Dreno de suctor em QIE com débito em qtd moderada de aspecto sanguinolento; Ctvo em FO de LE limpo e seco, sem sinais flogísticos. AP: MV + e preservados. Abd plano e flácido, com dor espontãnea e difusa à palpação, RHA +. Evacuação espontânea e ausente em fralda no período. SVD com débito efetivo e colúrico, irrigação vesical contínua. Desmame de nora, agora a 4 ml/h em BI. SG em BI a 42 ml/h. AVC em JID com ctvo limpo e seco sem sinais flogísiticos. AVP em MSD pérvio e salinizado. Mantém isolamento de contato até 2ª ordem. Segue sob cuidados intensivos de UTI.  ",
  "entities": {
    "Abreviação": [
      "POI",
      "AVP",
      "FAF",
      "PO",
      "LE",
      "PAM",
      "QIE",
      "Ctvo",
      "FO",
      "AP",
      "Abd",
      "SVD",
      "BI",
      "SG",
      "AVC",
      "JID",
      "ctvo",
      "MSD",
      "saída por glúteo D",
      "reimplante de ureter E",
      "pupilas isofoto",
      "HMD estável",
      "SNG aberta",
      "reg sacra",
      "qtd moderada",
      "MV +",
      "RHA +",
      "Desmame de nora",
      "cuidados intensivos de UTI"
    ],
    "Conceito Temporal": [
      "POI",
      "PO"
    ],
    "Lesão ou Envenenamento": [
      "ESCORIAÇÃO",
      "FAF",
      "FO",
      "FRATURA LUXAÇÃO ACETÁBULO ESQUERDO",
      "FRATURA DE CABEÇA FEMORAL"
    ],
    "Procedimento Terapêutico ou Preventivo": [
      "AVP",
      "CURATIVO",
      "colorrafia",
      "cistorrafia",
      "Extubado",
      "Jejum",
      "Ctvo",
      "SVD",
      "AVC",
      "ctvo",
      "salinizado",
      "LIBERADO DIETA",
      "COM SOROTERAPIA",
      "CATETERISMO DE ALÍVIO",
      "DRENO DE SUCTOR",
      "reimplante de ureter E",
      "SNG aberta",
      "Dreno de suctor",
      "irrigação vesical contínua",
      "Desmame de nora",
      "isolamento de contato"
    ],
    "Dispositivo Médico": [
      "AVP",
      "MATERIAL",
      "CURATIVO",
      "Ctvo",
      "fralda",
      "SVD",
      "AVC",
      "ctvo",
      "DRENO DE SUCTOR",
      "Dreno de suctor"
    ],
    "Parte do Corpo, Órgão ou Componente Orgânico": [
      "FÊMUR",
      "sigmóide",
      "bexiga",
      "JID",
      "LÁBIO SUPERIOR",
      "ANTEBRAÇO ESQUERDO",
      "PERNA ESQUERDA"
    ],
    "Achado": [
      "LIMPO",
      "SECO",
      "sonolento",
      "responsivo",
      "hidratado",
      "limpo",
      "seco",
      "preservados",
      "plano",
      "flácido",
      "efetivo",
      "pérvio",
      "ABERTURA OCULAR ESPONTÂNEA",
      "PUPILAS ISOCÓRICAS",
      "EUPNEICA EM AR AMBIENTE",
      "BOA PERFUSÃO PERIFÉRICA",
      "Glasgow 15",
      "pupilas isofoto",
      "respiração espontânea",
      "HMD estável",
      "boa saturação",
      "pele íntegra",
      "MV +",
      "RHA +",
      "Evacuação espontânea"
    ],
    "Conceito Espacial": [
      "EXTERNAMENTE"
    ],
    "Paciente ou Grupo com Deficiência": [
      "Vítima"
    ],
    "Localização ou Região Corporal": [
      "pélvico",
      "QIE",
      "Abd",
      "MSD",
      "espinha ilícia ântero-posterior",
      "reg sacra"
    ],
    "Procedimento Diagnóstico": [
      "PAM",
      "AP",
      "palpação",
      "Monitorização cardíaca contínua",
      "oximetria digital"
    ],
    "Sinal ou Sintoma": [
      "afebril",
      "Hipocorado",
      "EQUIMOSE PERIORBITAL DIREITA",
      "QUEIXAS ÁLGICAS",
      "GLOBO VESICAL",
      "Lesão grau II",
      "pouco débito bilioso",
      "sinais flogísticos",
      "sinais flogísiticos"
    ],
    "Negação": [
      "afebril"
    ],
    "Objeto Manufaturado": [
      "fralda"
    ],
    "Dispositivo de Administração de Medicamento": [
      "BI"
    ],
    "Substância Farmacológica": [
      "SG"
    ],
    "Organização Relacionada à Saúde": [
      "CENTRO CIRÚRGICO"
    ],
    "Atividade de Assistência à Saúde": [
      "PRESCRIÇÃO MÉDICA",
      "cuidados intensivos de UTI"
    ],
    "Produto Intelectual": [
      "PRESCRIÇÃO MÉDICA"
    ],
    "Conceito Qualitativo": [
      "qtd moderada"
    ],
    "Função Fisiológica": [
      "Evacuação espontânea"
    ],
    "Conceito Quantitativo": [
      "4 ml/h",
      "42 ml/h"
    ]
  },
  "labels": {
    "sonolento": {
      "capitulo": "06"
    },
    "sinais flogísiticos": {
      "capitulo": "08"
    },
    "pupilas isocóricas": {
      "capitulo": "09"
    },
    "pouco débito bilioso": {
      "capitulo": "21"
    },
    "lesão grau ii": {
      "capitulo": "16"
    },
    "equimose periorbital direita": {
      "capitulo": "14"
    },
    "abertura ocular espontânea": {
      "capitulo": "09"
    },
    "mv +": {
      "capitulo": "15"
    },
    "efetivo": {
      "capitulo": "21"
    },
    "sinais flogísticos": {
      "capitulo": "08"
    },
    "pupilas isofoto": {
      "capitulo": "09"
    },
    "rha +": {
      "capitulo": "15"
    },
    "plano": {
      "capitulo": "21"
    },
    "limpo": {
      "capitulo": "21"
    },
    "globo vesical": {
      "capitulo": "16"
    },
    "fratura de cabeça femoral": {
      "capitulo": "15"
    },
    "faf": {
      "capitulo": "22"
    },
    "evacuação espontânea": {
      "capitulo": "21"
    },
    "fratura luxação acetábulo esquerdo": {
      "capitulo": "15"
    },
    "escoriação": {
      "capitulo": "14"
    },
    "flácido": {
      "capitulo": "21"
    },
    "glasgow 15": {
      "capitulo": "06"
    },
    "fo": {
      "capitulo": "21"
    },
    "seco": {
      "capitulo": "21"
    }
  }
}