{
  "prontuario_id": 41,
  "text": "ÀS 11:20HS: ALERTA. CONFUSO. EUPNEICO. DEAMBULANDO. NÃO REFERE ALGIA. TRAQUEOSTOMIA SEM PRESENÇA DE SECREÇÃO. EUPNEICO EM AR AMBIENTE. DIURESE ESPONTANEA PRESENTE. SEGUE CUIDADOS. Às 13:00hs: Ramsay 6, pupilas isocóricas fotorreagentes, SNE com dieta a 30 ml/h, traqueostomizado, em ventilação mecânica modo VCV, Vc 500 ml, PEEP 10, FiO2 80%, secreção traqueobrônquica amarela em média quantidade, acesso venoso central E com NPT a 42 ml/h, acesso venoso central D com Dormonid 15 ml + Fentanil 10 ml/h + Noradrenalina 30 ml/h + Dopamina 20 ml/h, monitorizado, estável hemodinamicamente, MV global com raros roncos, MMSS edemaciados ++/4 com drenagem de exsudato, abdome globoso, semirrígido, RHA +, SVD com diurese efetiva, evacuação ausente, úlcera sacra grau II, extremidades bem perfundidas, higienizado e mobilizado no leito, mantendo precaução de contato por Enterobacter. Às 16hs: Consciente, comunicativa, aceitando bem a dieta, sem queixas algicas, mantendo acesso venoso em antebraço esquerdo, tala gessada em MIE. Diurese presente e evacuação ausente. Às 15:20h: pcte com GLASGOW 15, lucida, orientada, comunicativa, sem queixas algicas, com tosse seca, em ar ambiente. Avaliada pelo Dr Vital Brasil, apos avaliar a TAC de cranio realizada no inicio da manha, fica suspensa a cirurgia. Liberado dieta livre, solicitado pela plantonista correr 02 CH, solicitado material para AVC, tentado em subclavia D, sem sucesso, puncionado em subclavia E, pervea, SVD com debito presente em bom volume, pele integra. AP: MV + bilateral; ABM: flacido, RHA + ; MM: MMII pulso pedial presente e com boa perfusão. Colocado as 15:30 h pcte fora do leito, sentada na cadeira. segue cuidados. ",
  "entities": {
    "Achado": [
      "ALERTA",
      "EUPNEICO",
      "DEAMBULANDO",
      "traqueostomizado",
      "amarela",
      "++/4",
      "higienizado",
      "Consciente",
      "comunicativa",
      "lucida",
      "orientada",
      "pervea",
      "flacido",
      "EUPNEICO EM AR AMBIENTE",
      "DIURESE ESPONTANEA",
      "pupilas isocóricas fotorreagentes",
      "estável hemodinamicamente",
      "MV global",
      "RHA +",
      "diurese efetiva",
      "extremidades bem perfundidas",
      "Diurese presente",
      "GLASGOW 15",
      "queixas algicas",
      "debito presente",
      "pele integra",
      "MV + bilateral",
      "pulso pedial presente",
      "boa perfusão",
      "fora do leito",
      "sentada na cadeira"
    ],
    "Sinal ou Sintoma": [
      "CONFUSO",
      "ALGIA",
      "globoso",
      "semirrígido",
      "PRESENÇA DE SECREÇÃO",
      "Ramsay 6",
      "raros roncos",
      "drenagem de exsudato",
      "queixas algicas",
      "tosse seca"
    ],
    "Procedimento Terapêutico ou Preventivo": [
      "TRAQUEOSTOMIA",
      "SNE",
      "dieta",
      "traqueostomizado",
      "NPT",
      "SVD",
      "higienizado",
      "cirurgia",
      "CH",
      "AVC",
      "puncionado",
      "ventilação mecânica",
      "acesso venoso central",
      "mobilizado no leito",
      "precaução de contato",
      "acesso venoso",
      "tala gessada",
      "dieta livre",
      "sentada na cadeira"
    ],
    "Negação": [
      "SEM",
      "sem"
    ],
    "Atividade de Assistência à Saúde": [
      "CUIDADOS",
      "avaliar",
      "cuidados"
    ],
    "Abreviação": [
      "SNE",
      "Vc",
      "PEEP",
      "FiO2",
      "E",
      "NPT",
      "D",
      "SVD",
      "MIE",
      "pcte",
      "CH",
      "AVC",
      "AP",
      "ABM",
      "MM",
      "MMII",
      "modo VCV",
      "MV global",
      "RHA +",
      "TAC de cranio",
      "MV + bilateral"
    ],
    "Dispositivo Médico": [
      "SNE",
      "SVD",
      "material",
      "AVC",
      "acesso venoso central",
      "acesso venoso",
      "tala gessada"
    ],
    "Alimento": [
      "dieta"
    ],
    "Conceito Quantitativo": [
      "10",
      "80%",
      "15",
      "02",
      "30 ml/h",
      "500 ml",
      "média quantidade",
      "42 ml/h",
      "10 ml/h",
      "20 ml/h"
    ],
    "Conceito Espacial": [
      "E",
      "D"
    ],
    "Substância Química Orgânica": [
      "Dormonid",
      "Fentanil",
      "Noradrenalina",
      "Dopamina"
    ],
    "Substância Farmacológica": [
      "Dormonid",
      "Fentanil",
      "Noradrenalina",
      "Dopamina"
    ],
    "Hormônio": [
      "Noradrenalina"
    ],
    "Procedimento Diagnóstico": [
      "monitorizado",
      "AP",
      "TAC de cranio"
    ],
    "Localização ou Região Corporal": [
      "abdome",
      "sacra",
      "MIE",
      "ABM",
      "MM",
      "MMII"
    ],
    "Doença ou Síndrome": [
      "úlcera"
    ],
    "Paciente ou Grupo com Deficiência": [
      "pcte"
    ],
    "Conceito Temporal": [
      "apos",
      "inicio da manha"
    ],
    "Grupo Profissional ou Ocupacional": [
      "plantonista"
    ],
    "Parte do Corpo, Órgão ou Componente Orgânico": [
      "subclavia",
      "antebraço esquerdo"
    ],
    "Substância Corporal": [
      "secreção traqueobrônquica",
      "drenagem de exsudato"
    ],
    "Função Fisiológica": [
      "diurese efetiva",
      "Diurese presente",
      "debito presente"
    ],
    "Conceito Qualitativo": [
      "grau II",
      "bom volume"
    ]
  },
  "labels": {
    "pulso pedial presente": {
      "capitulo": "08"
    },
    "alerta": {
      "capitulo": "22"
    },
    "higienizado": {
      "capitulo": "24"
    },
    "algia": {
      "capitulo": "21"
    },
    "mv global": {
      "capitulo": "12"
    },
    "tosse seca": {
      "capitulo": "12"
    },
    "confuso": {
      "capitulo": "06"
    },
    "úlcera": {
      "capitulo": "15"
    },
    "queixas algicas": {
      "capitulo": "21"
    },
    "mv + bilateral": {
      "capitulo": "11"
    },
    "eupneico": {
      "capitulo": "12"
    },
    "deambulando": {
      "capitulo": "12"
    },
    "orientada": {
      "capitulo": "06"
    },
    "drenagem de exsudato": {
      "capitulo": "15"
    },
    "ramsay 6": {
      "capitulo": "21"
    },
    "semirrígido": {
      "capitulo": "15"
    },
    "eupneico em ar ambiente": {
      "capitulo": "12"
    },
    "sentada na cadeira": {
      "capitulo": "24"
    },
    "presença de secreção": {
      "capitulo": "12"
    },
    "amarela": {
      "capitulo": "21"
    },
    "fora do leito": {
      "capitulo": "24"
    },
    "raros roncos": {
      "capitulo": "12"
    },
    "globoso": {
      "capitulo": "15"
    },
    "flacido": {
      "capitulo": "15"
    },
    "traqueostomizado": {
      "capitulo": "12"
    },
    "pupilas isocóricas fotorreagentes": {
      "capitulo": "21"
    },
    "pervea": {
      "capitulo": "21"
    },
    "glasgow 15": {
      "capitulo": "06"
    },
    "lucida": {
      "capitulo": "06"
    },
    "consciente": {
      "capitulo": "06"
    },
    "comunicativa": {
      "capitulo": "06"
    }
  }
}