{
  "prontuario_id": 245,
  "text": "ÀS 23:50H: PERMANECE EM VM COM FILTRO DE BARREIRA EM MODO PCV COM PI DE 18 CM DE H2O, FIO2 EM 0,605, FR 12 RPM E PEEP 5 CM DE H2O. MONITORADA COM PNI, CARDIOSCOPIA E OXIMETRIA DE PULSO. APRESENTA GLASGOW 3, PUPILA PUNTIFORMES, SNE COM DIETA A 60 ML/H, CVC EM SUBCLÁVIA D COM PLANO BÁSICO DE HIDRATAÇÃO, TRAQUEOSTOMIZADA, SECREÇÃO TRAQUEOBRÔNQUICA MUCOPURULENTA EM MÉDIA QUANTIDADE, AUSCULTA PULMONAR COM RONCOS E CREPITAÇÕES DIFUSAS E  MV DIMINUÍDOS, EDEMA CACIFO +++/4 EM MMSS E MMII, ABDOME GLOBOSO E FLÁCIDO, RHA HIPERATIVOS, APRESENTOU VÁRIOS ESPISÓDIOS DE DIARREIA. PROGNÓSTICO RESERVADO, MANTÉM HIPOTENSÃO ARTERIAL. SEPTICEMIA NAO ESPECIFICADA. Às 00:11: Lucido, verbalizando em ar ambiente, referindo diarréia 3 episodios a noite. Florence Nightingale, XXXX. EXAME GERAL E INVESTIGACAO DE PESSOAS SEM QUEIXAS OU DIAGNOSTICO RELATADO. Às 12:00 horas: Abertura ocular espontânea, respondendo a estímulos verbais simples; apresentando crosta hemática em região labial (solicitado prescrição de creme para o Dr Vital Brasil); monitorização cardíaca, pressão arterial, PAM, saturação e respiração; recebendo por acesso venoso periférico em MMSE, SF 0,9% gota a gota (desligada insulina por glicemia capilar baixa); fragilidade cutânea; edema generalizado;  traqueostomizada, em ventilação mecânica, PSV, FIO2 30%, PEEP = 5 cmH2O; secreção em média quantidade, amarela; roncos difusos a ausculta; abdomen globoso, flácido; úlcera em região sacra estágio I; secreção pouco sanguinolenta (aspecto sangue velho), cicatriz escura em coto; mantendo perfusão distal preservada em MMIE; diurese efetiva amarelo ouro; precaução de contato por MRSA. EDEMA CEREBRAL.",
  "entities": {
    "Abreviação": [
      "VM",
      "PI",
      "FIO2",
      "FR",
      "RPM",
      "PEEP",
      "PNI",
      "SNE",
      "CVC",
      "D",
      "MMSS",
      "MMII",
      "PAM",
      "MMSE",
      "PSV",
      "MMIE",
      "MODO PCV",
      "CM DE H2O",
      "MV DIMINUÍDOS",
      "RHA HIPERATIVOS",
      "SF 0 , 9% gota a gota"
    ],
    "Procedimento Terapêutico ou Preventivo": [
      "VM",
      "SNE",
      "DIETA",
      "CVC",
      "TRAQUEOSTOMIZADA",
      "traqueostomizada",
      "PSV",
      "FILTRO DE BARREIRA",
      "PLANO BÁSICO DE HIDRATAÇÃO",
      "acesso venoso periférico",
      "SF 0 , 9% gota a gota",
      "ventilação mecânica",
      "precaução de contato"
    ],
    "Conceito Quantitativo": [
      "12",
      "RPM",
      "30%",
      "CM DE H2O",
      "0 , 605",
      "60 ML/H",
      "CACIFO +++/4",
      "SF 0 , 9% gota a gota",
      "5 cmH2O",
      "média quantidade"
    ],
    "Procedimento Diagnóstico": [
      "MONITORADA",
      "PNI",
      "CARDIOSCOPIA",
      "PAM",
      "saturação",
      "ausculta",
      "OXIMETRIA DE PULSO",
      "AUSCULTA PULMONAR",
      "monitorização cardíaca",
      "pressão arterial"
    ],
    "Dispositivo Médico": [
      "SNE",
      "CVC",
      "FILTRO DE BARREIRA",
      "acesso venoso periférico"
    ],
    "Alimento": [
      "DIETA"
    ],
    "Parte do Corpo, Órgão ou Componente Orgânico": [
      "SUBCLÁVIA"
    ],
    "Conceito Espacial": [
      "D"
    ],
    "Achado": [
      "TRAQUEOSTOMIZADA",
      "FLÁCIDO",
      "Lucido",
      "traqueostomizada",
      "flácido",
      "verbalizando em ar ambiente",
      "Abertura ocular espontânea",
      "respondendo a estímulos verbais simples",
      "fragilidade cutânea",
      "cicatriz escura",
      "perfusão distal preservada",
      "diurese efetiva",
      "amarelo ouro"
    ],
    "Sinal ou Sintoma": [
      "RONCOS",
      "EDEMA",
      "GLOBOSO",
      "DIARREIA",
      "diarréia",
      "amarela",
      "globoso",
      "GLASGOW 3",
      "PUPILA PUNTIFORMES",
      "CREPITAÇÕES DIFUSAS",
      "MV DIMINUÍDOS",
      "RHA HIPERATIVOS",
      "HIPOTENSÃO ARTERIAL",
      "crosta hemática",
      "edema generalizado",
      "roncos difusos"
    ],
    "Função Patológica": [
      "EDEMA",
      "EDEMA CEREBRAL"
    ],
    "Localização ou Região Corporal": [
      "MMSS",
      "MMII",
      "ABDOME",
      "MMSE",
      "abdomen",
      "coto",
      "MMIE",
      "região labial",
      "região sacra"
    ],
    "Produto Intelectual": [
      "prescrição"
    ],
    "Substância Farmacológica": [
      "creme",
      "insulina",
      "SF 0 , 9% gota a gota"
    ],
    "Substância Corporal": [
      "secreção",
      "SECREÇÃO TRAQUEOBRÔNQUICA"
    ],
    "Doença ou Síndrome": [
      "úlcera",
      "SEPTICEMIA NAO ESPECIFICADA"
    ],
    "Conceito Qualitativo": [
      "MÉDIA QUANTIDADE",
      "estágio I"
    ],
    "Resultado Laboratorial ou de Teste": [
      "glicemia capilar baixa"
    ],
    "Função Fisiológica": [
      "diurese efetiva"
    ]
  },
  "labels": {
    "septicemia nao especificada": {
      "capitulo": "01"
    },
    "fragilidade cutânea": {
      "capitulo": "14"
    },
    "edema generalizado": {
      "capitulo": "15"
    },
    "crosta hemática": {
      "capitulo": "14"
    },
    "rha hiperativos": {
      "capitulo": "11"
    },
    "roncos difusos": {
      "capitulo": "12"
    },
    "mv diminuídos": {
      "capitulo": "08"
    },
    "úlcera": {
      "capitulo": "14"
    },
    "crepitações difusas": {
      "capitulo": "12"
    },
    "roncos": {
      "capitulo": "12"
    },
    "perfusão distal preservada": {
      "capitulo": "11"
    },
    "diarreia": {
      "capitulo": "13"
    },
    "glasgow 3": {
      "capitulo": "06"
    },
    "hipotensão arterial": {
      "capitulo": "11"
    },
    "edema cerebral": {
      "capitulo": "08"
    },
    "pupila puntiformes": {
      "capitulo": "06"
    },
    "globoso": {
      "capitulo": "15"
    },
    "diarréia": {
      "capitulo": "13"
    },
    "cicatriz escura": {
      "capitulo": "14"
    },
    "flácido": {
      "capitulo": "15"
    },
    "edema": {
      "capitulo": "15"
    },
    "traqueostomizada": {
      "capitulo": "12"
    }
  }
}