{
  "prontuario_id": 658,
  "text": "Às 15:40h: ESTA EM ALTA HOSPITALAR, AGUARDA AMBULANCIA DE CIDADELA VIR BUSCA-LO, NO FINAL DA TARDE. HEPATITE AGUDA B COM AGENTE DELTA COINFECCAO COM COMA HEPATICO. Às 23:23 hs: Intubado, em VM modo PCV, Pi 24, Peep 3, Fr 14, FiO2 55%, saturando 100%. Pupilas isocóricas, fotorreagentes, reage a estímulos. Presença de escoriações e pontos em face. Permanece com colar cervical. Fx nasal com tala gessada. Ausculta pulmonar. TRAUMATISMOS MULTIPLOS NAO ESPECIFICADOS. Às 18:05: CORADA, ALERTA, AFEBRIL, COMUNICATIVA, EM REPOUSO NO LEITO, ACEITANDO DIETA VIA ORAL HOJE, AVP EM MSE SALINIZADO, SINAIS VITAIS ESTAVÉIS, NÃO REFERIU ALGIA, MANTÉM CURATIVO MMSS, ELIMINAÇÕES FISIOLOGICAS PRESENTES E ESPONTANEAS, SEGUE SOB CUIDADOS DE ENFERMAGEM. INFARTO CEREBRAL DEVIDO A TROMBOSE DE ARTERIAS PRE-CEREBRAIS. Às 16:18: PACIENTE INTERNADO APOS QUEDA DE MOTO, LUCIDO, ORIENTADO, COMUNICATIVO, ALERTA, SUTURA QUEIXO DE ASPECTO LIMPO E SECO, EUPNEICO EM AR AMBIENTE, NORMOCARDICO, NORMOTENSO, EM USO DE ACESSO VENOSO PERIFERICO EM MSE, BOA ACEITACAO DA DIETA VO, MANTEM T. TRAUMATISMOS MULTIPLOS NAO ESPECIFICADOS. ÀS 18:23h: DOR ABDOMINAL, CONSCIENTE, ORIENTADA, TRANQUILA, COMUNICATIVA E DEAMBULANDO. AGUARDANDO PROCEDIMENTO CIRURGICO. NEOPLASIA MALIGNA DA VESICULA BILIAR. PCTE C/ FRATURA MID, AVP MSE HEP, TALA MID. CIRÚRGIA PROGRAMADA P/ 28/12/06. RESTRITO AO LEITO. FRATURA DA EXTREMIDADE PROXIMAL DA TIBIA. Às 15:40: PROVENIENTE DO CC LÚCIDO, COMUNICATIVO, MANTEM DTE HEMÁTICO, ACESSO VENOSO PERIFERICO EM MSE, CTVO EM ABD, BOLSA DE COLOSTOMIA FUNCIONANTE, SVD COM DÉBITO. TRAUMATISMO DE MULTIPLOS ORGAOS INTRA ABDOMINAIS.",
  "entities": {
    "Achado": [
      "Intubado",
      "CORADA",
      "ALERTA",
      "AFEBRIL",
      "COMUNICATIVA",
      "LUCIDO",
      "ORIENTADO",
      "COMUNICATIVO",
      "LIMPO",
      "SECO",
      "NORMOCARDICO",
      "NORMOTENSO",
      "CONSCIENTE",
      "ORIENTADA",
      "TRANQUILA",
      "DEAMBULANDO",
      "LÚCIDO",
      "DÉBITO",
      "saturando 100%",
      "reage a estímulos",
      "REPOUSO NO LEITO",
      "SINAIS VITAIS ESTAVÉIS",
      "EUPNEICO EM AR AMBIENTE",
      "RESTRITO AO LEITO",
      "BOLSA DE COLOSTOMIA FUNCIONANTE"
    ],
    "Procedimento Terapêutico ou Preventivo": [
      "Intubado",
      "pontos",
      "AVP",
      "SALINIZADO",
      "CURATIVO",
      "SUTURA",
      "TALA",
      "CIRÚRGIA",
      "CTVO",
      "SVD",
      "VM modo PCV",
      "colar cervical",
      "tala gessada",
      "REPOUSO NO LEITO",
      "DIETA VIA ORAL",
      "ACESSO VENOSO PERIFERICO",
      "PROCEDIMENTO CIRURGICO",
      "RESTRITO AO LEITO"
    ],
    "Abreviação": [
      "Pi",
      "Peep",
      "Fr",
      "FiO2",
      "AVP",
      "MSE",
      "MMSS",
      "T",
      "PCTE",
      "HEP",
      "MID",
      "CC",
      "CTVO",
      "ABD",
      "SVD",
      "VM modo PCV",
      "Fx nasal",
      "DIETA VO",
      "FRATURA MID"
    ],
    "Conceito Quantitativo": [
      "24",
      "3",
      "14",
      "55%"
    ],
    "Lesão ou Envenenamento": [
      "escoriações",
      "Fx nasal",
      "TRAUMATISMOS MULTIPLOS NAO ESPECIFICADOS",
      "QUEDA DE MOTO",
      "FRATURA MID",
      "FRATURA DA EXTREMIDADE PROXIMAL DA TIBIA",
      "TRAUMATISMO DE MULTIPLOS ORGAOS INTRA ABDOMINAIS"
    ],
    "Localização ou Região Corporal": [
      "face",
      "MSE",
      "MMSS",
      "QUEIXO",
      "MID",
      "ABD"
    ],
    "Negação": [
      "AFEBRIL",
      "NÃO"
    ],
    "Dispositivo Médico": [
      "AVP",
      "CURATIVO",
      "TALA",
      "CTVO",
      "SVD",
      "colar cervical",
      "tala gessada",
      "ACESSO VENOSO PERIFERICO"
    ],
    "Conceito Qualitativo": [
      "SALINIZADO",
      "BOA ACEITACAO"
    ],
    "Sinal ou Sintoma": [
      "ALGIA",
      "DOR ABDOMINAL"
    ],
    "Paciente ou Grupo com Deficiência": [
      "PACIENTE",
      "PCTE"
    ],
    "Conceito Temporal": [
      "APOS"
    ],
    "Conceito Funcional": [
      "USO"
    ],
    "Organização Relacionada à Saúde": [
      "CC"
    ],
    "Função Fisiológica": [
      "DÉBITO",
      "ELIMINAÇÕES FISIOLOGICAS"
    ],
    "Atividade de Assistência à Saúde": [
      "ALTA HOSPITALAR",
      "CUIDADOS DE ENFERMAGEM"
    ],
    "Doença ou Síndrome": [
      "HEPATITE AGUDA B COM AGENTE DELTA COINFECCAO COM COMA HEPATICO",
      "INFARTO CEREBRAL DEVIDO A TROMBOSE DE ARTERIAS PRE-CEREBRAIS"
    ],
    "Procedimento Diagnóstico": [
      "Ausculta pulmonar"
    ],
    "Processo Neoplásico": [
      "NEOPLASIA MALIGNA DA VESICULA BILIAR"
    ],
    "Substância Corporal": [
      "DTE HEMÁTICO"
    ]
  },
  "labels": {
    "restrito ao leito": {
      "capitulo": "22"
    },
    "alerta": {
      "capitulo": "06"
    },
    "fratura mid": {
      "capitulo": "15"
    },
    "fx nasal": {
      "capitulo": "15"
    },
    "algia": {
      "capitulo": "21"
    },
    "bolsa de colostomia funcionante": {
      "capitulo": "13"
    },
    "neoplasia maligna da vesicula biliar": {
      "capitulo": "02"
    },
    "deambulando": {
      "capitulo": "06"
    },
    "fratura da extremidade proximal da tibia": {
      "capitulo": "15"
    },
    "escoriações": {
      "capitulo": "21"
    },
    "dor abdominal": {
      "capitulo": "13"
    },
    "intubado": {
      "capitulo": "22"
    },
    "infarto cerebral devido a trombose de arterias pre-cerebrais": {
      "capitulo": "08"
    },
    "hepatite aguda b com agente delta coinfeccao com coma hepatico": {
      "capitulo": "01"
    },
    "corada": {
      "capitulo": "06"
    },
    "repouso no leito": {
      "capitulo": "22"
    },
    "traumatismo de multiplos orgaos intra abdominais": {
      "capitulo": "13"
    },
    "traumatismos multiplos nao especificados": {
      "capitulo": "22"
    },
    "comunicativo": {
      "capitulo": "06"
    },
    "comunicativa": {
      "capitulo": "06"
    },
    "queda de moto": {
      "capitulo": "22"
    }
  }
}