{
  "prontuario_id": 912,
  "text": "ÀS 17:30h: 1ª DI, VITIMA DE QUEDA DE ARVORE -+ 6 m, COM TRAUMA DIRETO EM MSE + MID. CONSCIENTE, LUCIDO, EUPNEICO, COMUNICATIVO, EM REPOUSO NO LEITO, DEAMBULA COM AUXILIO, SEM QUEIXAS ALGICAS NO MOMENTO, APRESENTA PUPILAS ISOCORICAS, PELE E MUCOSA CORADA E HIDRATADA, AUSCULTA PULMONAR COM MV + , ABDOMEN PLANO, FLACIDO, RHA +, MANTEM ACESSO VENOSO PERIFERICO SALINIZADO EM MSE, GESSO EM BRAÇO MSE, TALA GESSADA + ATADURA DE CREPE EM MID, RELATA BOA ACEITAÇAO DA DIETA OFERECIDA, DIURESE ESPONTANEA PRESENTE. AGUARDA TOMOGRAFIA DE MID. FRATURA DO PE EXCETO DO TORNOZELO. ÀS 22:30HRS: RECEBO O PLANTÃO COM O CLIENTE SEM ACESSO VENOSO PERIFERICO POR REDE VENOSA FRAGILIZADA. APÓS (VARIAS) TENTATIVAS DE PUNÇÕES E SEM SUCESSO, CONVERSO POR VIA TELEFONE COM DR VITAL BRASIL, DA NEUROCIRURGIA, QUE ORIENTA ENTRAR EM CONTATO COM PLANTÃO DA ANESTESIOLOGIA PARA PROVAVEL PROCEDIMENTO NO CC. APÓS ESSE CONTATO A ORIENTAÇÃO FOI QUE A CÇA PERMANEÇA EM JEJUM POR 8 HRS. ORIENTO A ACOMPANHANTE (MÃE) + EQUIPE DE ENFERMAGEM QUANTO AO JEJUM POR VO, E AGUARDAMOS O CC SOLICITAR O PROCEDIMENTO. ENF° FLORENCE NIGHTINGALE, COREN XXXX. HIDROCEFALIA. ÀS 16:30 Horas: Paciente, 79 anos, 5° DI por Pneumotorax hipertensivo, Sepse de Foco Pulmonar, PCR e Insuficiencia respiratoria. Permanece em sala de emergencia com VM em modo PVC FiO2 65%; FR 15; PEEP 6. Monitorizado com FC 102; PA 108/75; SpO2 96%. Pupilas discoricas, SNE em narina direita em posição gastrica apos Rx, SNG em narina esquerda sem debito. AVC em subclavia esquerda infundindo, em BI, Dormonid 20 ml/h; Norepinefrina a 35 ml/h; Fentanil a 20 ml/h. Ausculta pulmonar com roncos difusos, abdomen globoso. Dreno de torax a esquerda com drenagem empiemica em pouca quantidade. SVD com 200 ml de debito concentrado e presença de grumos. Eliminação intestinal ausente no periodo. Ulcera por pressão em região sacra estagio II. Em anasarca. Extremidades frias e cianoticas. Reposiciono SNE. Paciente aguarda vaga em leito de UTI. ABDOME AGUDO.",
  "entities": {
    "Paciente ou Grupo com Deficiência": [
      "VITIMA",
      "CLIENTE",
      "Paciente"
    ],
    "Localização ou Região Corporal": [
      "MID",
      "ABDOMEN",
      "MSE",
      "gastrica",
      "Extremidades",
      "região sacra"
    ],
    "Abreviação": [
      "MID",
      "MSE",
      "CC",
      "VO",
      "ENF°",
      "PCR",
      "VM",
      "PVC",
      "FiO2",
      "FR",
      "PEEP",
      "FC",
      "PA",
      "SpO2",
      "SNE",
      "Rx",
      "SNG",
      "AVC",
      "BI",
      "SVD",
      "UTI",
      "EM MSE",
      "MV +",
      "RHA +"
    ],
    "Achado": [
      "CONSCIENTE",
      "LUCIDO",
      "EUPNEICO",
      "COMUNICATIVO",
      "CORADA",
      "HIDRATADA",
      "PLANO",
      "FLACIDO",
      "SUCESSO",
      "concentrado",
      "REPOUSO NO LEITO",
      "DEAMBULA COM AUXILIO",
      "PUPILAS ISOCORICAS",
      "MV +",
      "RHA +",
      "DIURESE ESPONTANEA"
    ],
    "Parte do Corpo, Órgão ou Componente Orgânico": [
      "PELE",
      "MUCOSA",
      "BRAÇO",
      "subclavia esquerda"
    ],
    "Procedimento Terapêutico ou Preventivo": [
      "SALINIZADO",
      "GESSO",
      "PUNÇÕES",
      "PROCEDIMENTO",
      "JEJUM",
      "VM",
      "PVC",
      "SNE",
      "SNG",
      "AVC",
      "SVD",
      "REPOUSO NO LEITO",
      "ACESSO VENOSO PERIFERICO",
      "TALA GESSADA",
      "ATADURA DE CREPE",
      "AO JEJUM",
      "Dreno de torax"
    ],
    "Dispositivo Médico": [
      "GESSO",
      "SNE",
      "SNG",
      "AVC",
      "BI",
      "SVD",
      "ACESSO VENOSO PERIFERICO",
      "TALA GESSADA",
      "ATADURA DE CREPE",
      "Dreno de torax"
    ],
    "Alimento": [
      "DIETA"
    ],
    "Atividade de Assistência à Saúde": [
      "OFERECIDA",
      "PLANTÃO",
      "PUNÇÕES",
      "ORIENTA",
      "ORIENTAÇÃO",
      "SOLICITAR"
    ],
    "Procedimento Diagnóstico": [
      "TOMOGRAFIA",
      "Monitorizado",
      "Rx",
      "AUSCULTA PULMONAR",
      "Ausculta pulmonar"
    ],
    "Negação": [
      "EXCETO",
      "SEM",
      "ausente"
    ],
    "Conceito Temporal": [
      "APÓS",
      "anos",
      "apos",
      "periodo",
      "NO MOMENTO"
    ],
    "Conceito Quantitativo": [
      "VARIAS",
      "79",
      "65%",
      "15",
      "6",
      "102",
      "108/75",
      "96%",
      "20 ml/h",
      "35 ml/h",
      "pouca quantidade",
      "200 ml"
    ],
    "Organização Relacionada à Saúde": [
      "NEUROCIRURGIA",
      "ANESTESIOLOGIA",
      "CC",
      "UTI",
      "sala de emergencia"
    ],
    "Grupo Populacional": [
      "ACOMPANHANTE"
    ],
    "Grupo Familiar": [
      "MÃE"
    ],
    "Doença ou Síndrome": [
      "HIDROCEFALIA",
      "PCR",
      "Pneumotorax hipertensivo",
      "Sepse de Foco Pulmonar",
      "Insuficiencia respiratoria",
      "Ulcera por pressão",
      "ABDOME AGUDO"
    ],
    "Atributo Clínico": [
      "PVC",
      "FiO2",
      "FR",
      "PEEP",
      "FC",
      "PA",
      "SpO2"
    ],
    "Substância Farmacológica": [
      "Dormonid",
      "Norepinefrina",
      "Fentanil"
    ],
    "Substância Química Orgânica": [
      "Dormonid",
      "Norepinefrina",
      "Fentanil"
    ],
    "Hormônio": [
      "Norepinefrina"
    ],
    "Conceito Espacial": [
      "esquerda"
    ],
    "Sinal ou Sintoma": [
      "grumos",
      "anasarca",
      "frias",
      "cianoticas",
      "QUEIXAS ALGICAS",
      "Pupilas discoricas",
      "roncos difusos",
      "abdomen globoso",
      "drenagem empiemica"
    ],
    "Função Patológica": [
      "anasarca"
    ],
    "Lesão ou Envenenamento": [
      "QUEDA DE ARVORE",
      "TRAUMA DIRETO"
    ],
    "Grupo Profissional ou Ocupacional": [
      "EQUIPE DE ENFERMAGEM"
    ],
    "Espaço ou Junção Corporal": [
      "narina direita",
      "narina esquerda"
    ],
    "Conceito Qualitativo": [
      "pouca quantidade",
      "estagio II"
    ],
    "Função Fisiológica": [
      "Eliminação intestinal"
    ]
  },
  "labels": {
    "insuficiencia respiratoria": {
      "capitulo": "12"
    },
    "sucesso": {
      "capitulo": "22"
    },
    "trauma direto": {
      "capitulo": "22"
    },
    "pupilas discoricas": {
      "capitulo": "21"
    },
    "roncos difusos": {
      "capitulo": "12"
    },
    "abdome agudo": {
      "capitulo": "13"
    },
    "anasarca": {
      "capitulo": "14"
    },
    "queda de arvore": {
      "capitulo": "22"
    },
    "grumos": {
      "capitulo": "21"
    },
    "pneumotorax hipertensivo": {
      "capitulo": "12"
    },
    "sepse de foco pulmonar": {
      "capitulo": "12"
    },
    "drenagem empiemica": {
      "capitulo": "13"
    },
    "pcr": {
      "capitulo": "21"
    },
    "hidrocefalia": {
      "capitulo": "08"
    },
    "ulcera por pressão": {
      "capitulo": "15"
    },
    "cianoticas": {
      "capitulo": "21"
    },
    "abdomen globoso": {
      "capitulo": "13"
    }
  }
}