{
  "prontuario_id": 42,
  "text": "Às 11:00: Permanece torporosa, com abertura ocular espontânea, pupilas levemente anisocóricas E>D e bradifotorreagentes e estrabismo, responsivo a estímulos aspirativos e dolorosos, afebril, corado, traqueostomizado com suporte de névoa úmida contínua satura. HIDROCEFALIA OBSTRUTIVA. PACIENTE POUCO CONTACTUANTE, SONOLENTO, COM CURATIVO SANGUINOLENTO EXTERNAMENTE, MOBILIDADE DISTAL MMII PRESERVADA, EM USO DE FRALDA E ACESSO VENOSO EM MSD SALINIZADO. FRATURA DE OSSO SUBSEQUENTE A IMPLANTE ORTOPEDICO PROTESE ARTICULAR OU PLACA OSSEA. PCTE ACAMADO, ELIMINAÇÕES EM FRALDAS, S/ SE COMUNICAR, AVP MSD C/ SOROTERAP. REALIZADO CTVO EM ÚLCERA DE DECÚBITO, ASPIRADO SECREÇÕES OROFARINGEA S/ SE ALIMENTAR. DESNUTRIÇÃO, DESIDRATAÇÃO. DESNUTRICAO PROTEICO-CALORICA NAO ESPECIFICADA Às 01:50h: Veio de CC de maca, com ctvo oclusivo em braço esquerdo, consciente, lucido, comunicativo, orientado, eupneico, afebril, hipocorado, sob efeito de anestesico, ausência de sensibilidade mse. TRAUMATISMOS MULTIPLOS NAO ESPECIFICADOS. Às 17:09: ORIENTADA, COMUNICATIVA, REFERE ALGIA EM MIE, APRESENTA EDEMA EM MMII, HEMATOMA EM MSE, ACESSO VENOSO PERIFERICO EM MSD, ACEITANDO DIETA, ELIMINAÇÕES FISIOLOGICAS PRESENTES. FLEBITE E TROMBOFLEBITE DE OUTROS VASOS PROFUNDOS DOS MEMBROS INFERIORES. Às 09:21h: Acordado, alerta, responsivo, corado, hidratado. Mantém acesso venoso central em subclávia direita com NPT em curso por bomba infusora. Inserção de catéter central limpa e seca sem sinais flogísticos. Abdome plano, flácido, indolor á palpação, RHA. ABDOME AGUDO.",
  "entities": {
    "Sinal ou Sintoma": [
      "torporosa",
      "bradifotorreagentes",
      "SONOLENTO",
      "hipocorado",
      "ALGIA",
      "EDEMA",
      "HEMATOMA",
      "levemente anisocóricas",
      "sinais flogísticos"
    ],
    "Parte do Corpo, Órgão ou Componente Orgânico": [
      "pupilas",
      "braço esquerdo",
      "subclávia direita"
    ],
    "Doença ou Síndrome": [
      "estrabismo",
      "DESNUTRIÇÃO",
      "DESIDRATAÇÃO",
      "HIDROCEFALIA OBSTRUTIVA",
      "ÚLCERA DE DECÚBITO",
      "DESNUTRICAO PROTEICO-CALORICA",
      "ABDOME AGUDO"
    ],
    "Negação": [
      "afebril",
      "S/",
      "indolor"
    ],
    "Achado": [
      "afebril",
      "corado",
      "traqueostomizado",
      "CONTACTUANTE",
      "SANGUINOLENTO",
      "SALINIZADO",
      "ACAMADO",
      "consciente",
      "lucido",
      "comunicativo",
      "orientado",
      "eupneico",
      "ORIENTADA",
      "COMUNICATIVA",
      "Acordado",
      "alerta",
      "responsivo",
      "hidratado",
      "limpa",
      "seca",
      "plano",
      "flácido",
      "RHA",
      "abertura ocular espontânea",
      "responsivo a estímulos aspirativos e dolorosos",
      "MOBILIDADE DISTAL MMII PRESERVADA",
      "ELIMINAÇÕES EM FRALDAS",
      "ctvo oclusivo",
      "sensibilidade mse",
      "ELIMINAÇÕES FISIOLOGICAS PRESENTES"
    ],
    "Paciente ou Grupo com Deficiência": [
      "PACIENTE",
      "PCTE"
    ],
    "Procedimento Terapêutico ou Preventivo": [
      "CURATIVO",
      "SALINIZADO",
      "AVP",
      "SOROTERAP",
      "CTVO",
      "ASPIRADO",
      "Inserção",
      "névoa úmida contínua",
      "ACESSO VENOSO",
      "ctvo oclusivo",
      "ACESSO VENOSO PERIFERICO",
      "acesso venoso central",
      "NPT em curso"
    ],
    "Dispositivo Médico": [
      "CURATIVO",
      "AVP",
      "CTVO",
      "maca",
      "DE FRALDA",
      "ACESSO VENOSO",
      "ctvo oclusivo",
      "ACESSO VENOSO PERIFERICO",
      "acesso venoso central",
      "bomba infusora",
      "catéter central"
    ],
    "Conceito Espacial": [
      "EXTERNAMENTE"
    ],
    "Abreviação": [
      "MSD",
      "PCTE",
      "AVP",
      "SOROTERAP",
      "CTVO",
      "S/",
      "CC",
      "MIE",
      "MMII",
      "MSE",
      "RHA",
      "MOBILIDADE DISTAL MMII PRESERVADA",
      "ctvo oclusivo",
      "sensibilidade mse",
      "EM MSD",
      "NPT em curso"
    ],
    "Localização ou Região Corporal": [
      "MSD",
      "MIE",
      "MMII",
      "MSE",
      "Abdome"
    ],
    "Organização Relacionada à Saúde": [
      "CC"
    ],
    "Função Patológica": [
      "EDEMA",
      "HEMATOMA"
    ],
    "Procedimento Diagnóstico": [
      "palpação"
    ],
    "Função Fisiológica": [
      "ELIMINAÇÕES EM FRALDAS",
      "ELIMINAÇÕES FISIOLOGICAS PRESENTES"
    ],
    "Lesão ou Envenenamento": [
      "TRAUMATISMOS MULTIPLOS"
    ]
  },
  "labels": {
    "sonolento": {
      "capitulo": "06"
    },
    "eliminações em fraldas": {
      "capitulo": "24"
    },
    "desnutricao proteico-calorica": {
      "capitulo": "05"
    },
    "salinizado": {
      "capitulo": "11"
    },
    "algia": {
      "capitulo": "09"
    },
    "abdome agudo": {
      "capitulo": "12"
    },
    "responsivo a estímulos aspirativos e dolorosos": {
      "capitulo": "21"
    },
    "desidratação": {
      "capitulo": "05"
    },
    "ctvo oclusivo": {
      "capitulo": "22"
    },
    "bradifotorreagentes": {
      "capitulo": "08"
    },
    "torporosa": {
      "capitulo": "06"
    },
    "hematoma": {
      "capitulo": "15"
    },
    "sanguinolento": {
      "capitulo": "21"
    },
    "sinais flogísticos": {
      "capitulo": "21"
    },
    "hidrocefalia obstrutiva": {
      "capitulo": "08"
    },
    "contactuante": {
      "capitulo": "24"
    },
    "desnutrição": {
      "capitulo": "05"
    },
    "mobilidade distal mmii preservada": {
      "capitulo": "15"
    },
    "traqueostomizado": {
      "capitulo": "12"
    },
    "sensibilidade mse": {
      "capitulo": "21"
    },
    "levemente anisocóricas": {
      "capitulo": "08"
    },
    "flácido": {
      "capitulo": "15"
    },
    "acamado": {
      "capitulo": "24"
    },
    "eliminações fisiologicas presentes": {
      "capitulo": "24"
    },
    "traumatismos multiplos": {
      "capitulo": "22"
    },
    "estrabismo": {
      "capitulo": "09"
    },
    "úlcera de decúbito": {
      "capitulo": "21"
    },
    "edema": {
      "capitulo": "15"
    }
  }
}