{
  "prontuario_id": 351,
  "text": "Às 17:50H: Encaminhado para Ala B de cadeira de rodas, acompanhado por familiares. À 01:30H: CONSCIENTE, EUPNEICO EM AR A, SINAIS VITAIS ESTÁVEIS, SEM QUEIXAS ÁLGICAS, SEGUE EM REPOUSO ABSOLUTO NO LEITO, COM CABECEIRA A ZERO GRAU, MANTÉM ACESSO VENOSO PERIFÉRICO EM MSD PERMEÁVEL, DÉFICIT MOTOR EM MMII. NÃO APRESENTOU DIURESE ESPONTÂNEA, REALIZADO CAT DE ALÍVIO, DRENADO 1300 ML DE DIURESE CONCENTRADA ÀS 20:30H DO DIA 22/09. Às 18:27: CLIENTE REFERE DOR MODERADA EM MID, CONSCIENTE, COMUNICATIVA, EUPNEICA, REPOUSO NO LEITO, ACEITANDO BEM A DIETA, ACESSO PERIFÉRICO EM MSD SALINIZADO, ABDOMEN GLOBOSO E FLÁCIDO, CTVO LIMPO E SECO EM MID + FIXADOR EXTERNO, APRESENTANDO EDEMA CACIFO ++, PERFUSÃO DISTAL PRESERVADA, ABDOMEN GLOBOSO E FLÁCIDO, MICÇÃO PRESENTE. Às 18:13h: Paciente consciente, orientado, comunicativo, em repouso no leito, afebril, eupneico, AVP em MSE salinizado, curativo oclusivo em região axilar esquerda seco e limpo externamente, mantendo jejum até o momento, aguardando liberação de dieta, diurese e evacuação ausentes até o momento. Coren XXXX. Às 08:00hs: Glasgow 10, pupilas isocóricas fotorreagentes, respiração espontânea, em névoa úmida contínua a 4 l/m, SpO2 95%, secreção traqueobrônquica mucosa em pouca quantidade, acesso venoso central E com plano básico de hidratação, monitorizado, estável hemodinamicamente, MV + com roncos esparsos, abdome plano, flácido, indolor a palpação, RHA +, gastrostomia com dieta a 90 ml/h, diurese espontânea efetiva em uropen, evacuação ausente, extremidades quentes e bem perfundidas, mantendo precaução de contato por Pseudomonas.",
  "entities": {
    "Grupo Familiar": [
      "familiares"
    ],
    "Achado": [
      "CONSCIENTE",
      "PERMEÁVEL",
      "COMUNICATIVA",
      "EUPNEICA",
      "SALINIZADO",
      "FLÁCIDO",
      "LIMPO",
      "SECO",
      "consciente",
      "orientado",
      "comunicativo",
      "afebril",
      "eupneico",
      "salinizado",
      "seco",
      "limpo",
      "plano",
      "flácido",
      "quentes",
      "EUPNEICO EM AR A",
      "SINAIS VITAIS ESTÁVEIS",
      "DIURESE ESPONTÂNEA",
      "REPOUSO NO LEITO",
      "ACEITANDO BEM A DIETA",
      "PERFUSÃO DISTAL PRESERVADA",
      "MICÇÃO PRESENTE",
      "repouso no leito",
      "respiração espontânea",
      "estável hemodinamicamente",
      "MV +",
      "RHA +",
      "diurese espontânea efetiva",
      "bem perfundidas"
    ],
    "Abreviação": [
      "MSD",
      "MID",
      "CTVO",
      "AVP",
      "MSE",
      "SpO2",
      "E",
      "EUPNEICO EM AR A",
      "DÉFICIT MOTOR EM MMII",
      "CAT DE ALÍVIO",
      "MV +",
      "RHA +"
    ],
    "Localização ou Região Corporal": [
      "MSD",
      "MID",
      "ABDOMEN",
      "MSE",
      "abdome",
      "extremidades",
      "região axilar esquerda"
    ],
    "Procedimento Terapêutico ou Preventivo": [
      "DRENADO",
      "SALINIZADO",
      "CTVO",
      "AVP",
      "salinizado",
      "jejum",
      "REPOUSO ABSOLUTO NO LEITO",
      "CABECEIRA A ZERO GRAU",
      "ACESSO VENOSO PERIFÉRICO",
      "CAT DE ALÍVIO",
      "REPOUSO NO LEITO",
      "ACESSO PERIFÉRICO",
      "FIXADOR EXTERNO",
      "repouso no leito",
      "curativo oclusivo",
      "névoa úmida contínua",
      "acesso venoso central",
      "plano básico de hidratação",
      "gastrostomia com dieta",
      "precaução de contato"
    ],
    "Paciente ou Grupo com Deficiência": [
      "CLIENTE",
      "Paciente"
    ],
    "Sinal ou Sintoma": [
      "GLOBOSO",
      "EDEMA",
      "mucosa",
      "QUEIXAS ÁLGICAS",
      "DÉFICIT MOTOR EM MMII",
      "DOR MODERADA",
      "Glasgow 10",
      "roncos esparsos"
    ],
    "Dispositivo Médico": [
      "CTVO",
      "AVP",
      "uropen",
      "cadeira de rodas",
      "ACESSO VENOSO PERIFÉRICO",
      "ACESSO PERIFÉRICO",
      "FIXADOR EXTERNO",
      "curativo oclusivo",
      "acesso venoso central"
    ],
    "Função Patológica": [
      "EDEMA"
    ],
    "Negação": [
      "afebril",
      "ausentes",
      "indolor",
      "ausente"
    ],
    "Conceito Espacial": [
      "externamente"
    ],
    "Alimento": [
      "dieta"
    ],
    "Função Fisiológica": [
      "diurese",
      "evacuação",
      "DIURESE ESPONTÂNEA",
      "DIURESE CONCENTRADA",
      "MICÇÃO PRESENTE",
      "diurese espontânea efetiva"
    ],
    "Parte do Corpo, Órgão ou Componente Orgânico": [
      "pupilas"
    ],
    "Atributo Clínico": [
      "SpO2"
    ],
    "Conceito Quantitativo": [
      "95%",
      "1300 ML",
      "4 l/m",
      "90 ml/h"
    ],
    "Procedimento Diagnóstico": [
      "monitorizado",
      "palpação"
    ],
    "Bactéria": [
      "Pseudomonas"
    ],
    "Substância Corporal": [
      "secreção traqueobrônquica"
    ],
    "Conceito Qualitativo": [
      "pouca quantidade"
    ]
  },
  "labels": {
    "pseudomonas": {
      "capitulo": "01"
    },
    "respiração espontânea": {
      "capitulo": "12"
    },
    "salinizado": {
      "capitulo": "X"
    },
    "dor moderada": {
      "capitulo": "21"
    },
    "mv +": {
      "capitulo": "12"
    },
    "déficit motor em mmii": {
      "capitulo": "15"
    },
    "glasgow 10": {
      "capitulo": "21"
    },
    "micção presente": {
      "capitulo": "16"
    },
    "perfusão distal preservada": {
      "capitulo": "11"
    },
    "bem perfundidas": {
      "capitulo": "X"
    },
    "mucosa": {
      "capitulo": "14"
    },
    "plano": {
      "capitulo": "X"
    },
    "limpo": {
      "capitulo": "X"
    },
    "permeável": {
      "capitulo": "X"
    },
    "globoso": {
      "capitulo": "21"
    },
    "roncos esparsos": {
      "capitulo": "12"
    },
    "quentes": {
      "capitulo": "15"
    },
    "flácido": {
      "capitulo": "21"
    },
    "seco": {
      "capitulo": "X"
    },
    "edema": {
      "capitulo": "21"
    }
  }
}