{
  "prontuario_id": 993,
  "text": "Às 19:30H: 1º DI, VITIMA DE QUEDA DE NIVEL, COM CONTUSÃO EM COLUNA. NO MOMENTO, CONSCIENTE, COMUNICATIVO, EM REPOUSO NO LEITO EM DECUBITO DORSAL, RESPIRANDO EM AR AMBIENTE, HIPOCORADO, AUSCULTA PULMONAR COM RA DISCRETOS, ABDOMEN GLOBOSO, RHA +, MOVIMENTANDO 4. FRATURA DE VERTEBRA LOMBAR. Às 18:00: PACIENTE ACORDADA EM REPOUSO NO LEITO, REALIZOU AED PELA MANNHA, AVALIADA PELA FONO A TARDE, IRA MANTEM SNG PELO RISCO DE BRONCOASPIRAÇAO, LIBERADA DIETA VIA SONDA, SEGUE EM OBSERVAÇÃO. HIDRONEFROSE COM ESTREITAMENTO DE URETER NAO CLASSIFICADA EM OUTRA PARTE. Às 18:11: LUCIDO, ORIENTADO, EUPNÉICO, AFEBRIL, SEM QUEIXAS ÁLGICAS, ACEITA DIETA OFERECIDA. DIURESE ESPONTÂNEA EFETIVA. FRATURA DO ACETABULO. Em 28/12, 12:15: 1º DI POR TCE. ACORDADA, COMUNICATIVA, DEAMBULANDO SEM AUXILIO, ACOMPANHADA DA DIA, ENCAMINHADA AO BANHO DE ASPERSÃO, PUNCIONADO ACESSO VENOSO EM MSD COM ABOCATH 22, LIBERADO DIETA, NÃO APRESENTOU EPISODIO DE VOMITO. CONCUSSAO CEREBRAL. Às 15:00 HORAS: 3° DIA DE INTERNAMENTO. COM HISTÓRIA DE DOR TORÁCICA E DISPNÉIA + ICC + HAS, QUEDA DO ESTADO GERAL. ACORDADA, LÚCIDA E POUCO COMUNICATIVA. HIPOCORADA, APATICA COM APARÊNCIA DE DESNUTRIÇÃO, BASTANTE EMAGRECIDA, PELE FINA E FLÁCIDA COM RECECAME. INSUFICIENCIA CARDIACA NAO ESPECIFICADA. Às 02:00h: Acordado, gemente, apatico, letargico, verbaliza com dificuldade e esforço, apresenta ictericia +++/IV, ausculta pulmonar com MV +, abdomen distêndido, repassado SNE em narina direita. SEPTICEMIA POR SALMONELA.",
  "entities": {
    "Paciente ou Grupo com Deficiência": [
      "VITIMA",
      "PACIENTE"
    ],
    "Achado": [
      "CONSCIENTE",
      "COMUNICATIVO",
      "ACORDADA",
      "LUCIDO",
      "ORIENTADO",
      "EUPNÉICO",
      "AFEBRIL",
      "COMUNICATIVA",
      "LÚCIDA",
      "FINA",
      "FLÁCIDA",
      "RECECAME",
      "Acordado",
      "+++/IV",
      "RESPIRANDO EM AR AMBIENTE",
      "RHA +",
      "MOVIMENTANDO 4",
      "REPOUSO NO LEITO",
      "RISCO DE BRONCOASPIRAÇAO",
      "ACEITA DIETA OFERECIDA",
      "DIURESE ESPONTÂNEA EFETIVA",
      "DEAMBULANDO SEM AUXILIO",
      "MV +"
    ],
    "Sinal ou Sintoma": [
      "HIPOCORADO",
      "VOMITO",
      "DISPNÉIA",
      "HIPOCORADA",
      "APATICA",
      "gemente",
      "apatico",
      "letargico",
      "ictericia",
      "RA DISCRETOS",
      "QUEIXAS ÁLGICAS",
      "DOR TORÁCICA",
      "QUEDA DO ESTADO GERAL",
      "BASTANTE EMAGRECIDA",
      "verbaliza com dificuldade e esforço",
      "abdomen distêndido"
    ],
    "Localização ou Região Corporal": [
      "ABDOMEN",
      "MSD"
    ],
    "Abreviação": [
      "AED",
      "FONO",
      "SNG",
      "TCE",
      "MSD",
      "ICC",
      "HAS",
      "RECECAME",
      "SNE",
      "RA DISCRETOS",
      "RHA +",
      "MV +"
    ],
    "Procedimento Diagnóstico": [
      "AED",
      "AUSCULTA PULMONAR",
      "ausculta pulmonar"
    ],
    "Organização Relacionada à Saúde": [
      "FONO"
    ],
    "Procedimento Terapêutico ou Preventivo": [
      "SNG",
      "SNE",
      "REPOUSO NO LEITO EM DECUBITO DORSAL",
      "REPOUSO NO LEITO",
      "DIETA VIA SONDA",
      "BANHO DE ASPERSÃO",
      "ACESSO VENOSO"
    ],
    "Dispositivo Médico": [
      "SNG",
      "SNE",
      "ACESSO VENOSO",
      "ABOCATH 22"
    ],
    "Atividade de Assistência à Saúde": [
      "OBSERVAÇÃO",
      "PUNCIONADO",
      "repassado"
    ],
    "Negação": [
      "AFEBRIL"
    ],
    "Lesão ou Envenenamento": [
      "TCE",
      "QUEDA DE NIVEL",
      "CONTUSÃO EM COLUNA",
      "FRATURA DE VERTEBRA LOMBAR",
      "FRATURA DO ACETABULO",
      "CONCUSSAO CEREBRAL"
    ],
    "Alimento": [
      "DIETA"
    ],
    "Doença ou Síndrome": [
      "ICC",
      "HAS",
      "HIDRONEFROSE COM ESTREITAMENTO DE URETER",
      "INSUFICIENCIA CARDIACA",
      "SEPTICEMIA POR SALMONELA"
    ],
    "Parte do Corpo, Órgão ou Componente Orgânico": [
      "PELE"
    ],
    "Função Fisiológica": [
      "DIURESE ESPONTÂNEA EFETIVA"
    ],
    "Espaço ou Junção Corporal": [
      "narina direita"
    ]
  },
  "labels": {
    "tce": {
      "capitulo": "22"
    },
    "hidronefrose com estreitamento de ureter": {
      "capitulo": "16"
    },
    "vomito": {
      "capitulo": "21"
    },
    "ictericia": {
      "capitulo": "21"
    },
    "rececame": {
      "capitulo": "21"
    },
    "letargico": {
      "capitulo": "06"
    },
    "fratura de vertebra lombar": {
      "capitulo": "15"
    },
    "fratura do acetabulo": {
      "capitulo": "15"
    },
    "dor torácica": {
      "capitulo": "21"
    },
    "mv +": {
      "capitulo": "21"
    },
    "apatica": {
      "capitulo": "06"
    },
    "icc": {
      "capitulo": "21"
    },
    "+++/iv": {
      "capitulo": "21"
    },
    "abdomen distêndido": {
      "capitulo": "21"
    },
    "flácida": {
      "capitulo": "21"
    },
    "bastante emagrecida": {
      "capitulo": "21"
    },
    "dispnéia": {
      "capitulo": "12"
    },
    "verbaliza com dificuldade e esforço": {
      "capitulo": "06"
    },
    "has": {
      "capitulo": "21"
    },
    "queda de nivel": {
      "capitulo": "22"
    },
    "contusão em coluna": {
      "capitulo": "15"
    },
    "risco de broncoaspiraçao": {
      "capitulo": "21"
    },
    "queda do estado geral": {
      "capitulo": "06"
    },
    "fina": {
      "capitulo": "21"
    },
    "gemente": {
      "capitulo": "06"
    },
    "concussao cerebral": {
      "capitulo": "08"
    },
    "septicemia por salmonela": {
      "capitulo": "01"
    }
  }
}