{
  "prontuario_id": 27,
  "text": "Às 15:27: CLIENTE ALERTA, CONSCIENTE, PUPILAS ANISOCORICAS E ) D, COMUNICATIVA, DISCRETA DISPNEIA AOS ESFORÇOS,COM SUPORTE DE OXIGENOTERAPIA EM CATETER NASAL A 2 /L, MANTENDO OXIMETRIA DE PULSO SAT: 96 %, REPOUSO NO LEITO, ACEITANDO POUCO A DIETA, ACESSO PERIFÉRICO EM MSE SALINIZADO, ABDOMEN GLOBOSO E FLÁCIDO, APRESENTANDO HIPEREMIA EM REGIÃO SACRA, MANTENDO COLCHÃO DE AR, ELIMINAÇÕES PRESENTES. FOI ENCAMINHADA AO ELETROCARDIOGRAMA. ENFª FLORENCE NIGHTINGALE, XXXX. INSUFICIENCIA RENAL AGUDA NAO ESPECIFICADA. ÀS 20:20 h:  MANTENDO PRECAUÇÃO DE CONTATO PARA (VRE / MRSA). APRESENTANDO HIPERTENSÃO, EMESE EM JATO BILIOSO, UM EPISÓDIO EM GRANDE QUANTIDADE,  ABERTO SNE (grande quantidade de estase biliosa), COMUNICADO PLANTONISTA, PERMANECE EM JEJUM PARA CC AINDA HOJE. TRAQUEOSTOMIZADO, EM VM  MODO PSV, PS 20, PEEP 8 (mantendo trach care), FIO2 50 %, SPO2 95 %. AUSCULTA PULMONAR MV DIMINUIDOS EM BASES, COM RONCOS DIFUSOS, SECREÇÃO SEROSA EM MEDIA QUANTIDADE. ABDOMEM PERITONIOSTOMIA COM SECREÇÃO ESVERDEADA EM GRANDE QUANTIDADE, CTVO COM SUJIDADE, AGUARDANDO CC CHAMAR, MANTENDO ASPIRAÇÃO Á VÁCUO (continua). ACESSO VENOSO CENTRAL DUPLO LUMEN EM SUBCLAVIA E COM NPT EM VIA EXCLUSIVA 63 ML/H, PLANO BASICO DE HIDRATAÇÃO NA OUTRA VIA. HEMODINAMICAMENTE ESTAVEL. PELE FRAGILIZADA, COM BOLHAS + EDEMA CACIFO +++, SVD EFETIVA COM DEBITO CITRICO + EDEMA DE BOLSA ESCROTAL (mantendo elevada), MONITORIZAÇÃO CARDIOSCOPICA, OXIMETRIA DE PULSO, PNI. EDEMA CEREBRAL.",
  "entities": {
    "Paciente ou Grupo com Deficiência": [
      "CLIENTE"
    ],
    "Achado": [
      "ALERTA",
      "CONSCIENTE",
      "COMUNICATIVA",
      "SALINIZADO",
      "FLÁCIDO",
      "TRAQUEOSTOMIZADO",
      "SUJIDADE",
      "REPOUSO NO LEITO",
      "ELIMINAÇÕES PRESENTES",
      "HEMODINAMICAMENTE ESTAVEL",
      "SVD EFETIVA COM DEBITO CITRICO"
    ],
    "Atributo Clínico": [
      "SAT"
    ],
    "Abreviação": [
      "SAT",
      "MSE",
      "ENFª",
      "VRE",
      "MRSA",
      "CC",
      "VM",
      "PS",
      "PEEP",
      "FIO2",
      "SPO2",
      "CTVO",
      "NPT",
      "PNI",
      "ABERTO SNE",
      "MODO PSV",
      "MV DIMINUIDOS EM BASES",
      "SUBCLAVIA E",
      "SVD EFETIVA COM DEBITO CITRICO"
    ],
    "Localização ou Região Corporal": [
      "MSE",
      "ABDOMEN",
      "ABDOMEM",
      "REGIÃO SACRA"
    ],
    "Procedimento Terapêutico ou Preventivo": [
      "SALINIZADO",
      "JEJUM",
      "TRAQUEOSTOMIZADO",
      "VM",
      "PS",
      "PEEP",
      "FIO2",
      "SPO2",
      "PERITONIOSTOMIA",
      "CTVO",
      "NPT",
      "SUPORTE DE OXIGENOTERAPIA",
      "REPOUSO NO LEITO",
      "ACESSO PERIFÉRICO",
      "COLCHÃO DE AR",
      "PRECAUÇÃO DE CONTATO",
      "ABERTO SNE",
      "MODO PSV",
      "ASPIRAÇÃO Á VÁCUO",
      "ACESSO VENOSO CENTRAL DUPLO LUMEN",
      "PLANO BASICO DE HIDRATAÇÃO"
    ],
    "Sinal ou Sintoma": [
      "GLOBOSO",
      "HIPEREMIA",
      "HIPERTENSÃO",
      "BOLHAS",
      "PUPILAS ANISOCORICAS",
      "DISCRETA DISPNEIA AOS ESFORÇOS",
      "ACEITANDO POUCO A DIETA",
      "EMESE EM JATO BILIOSO",
      "grande quantidade de estase biliosa",
      "MV DIMINUIDOS EM BASES",
      "RONCOS DIFUSOS",
      "SECREÇÃO ESVERDEADA EM GRANDE QUANTIDADE",
      "EDEMA CACIFO +++",
      "EDEMA DE BOLSA ESCROTAL"
    ],
    "Procedimento Diagnóstico": [
      "ELETROCARDIOGRAMA",
      "PNI",
      "OXIMETRIA DE PULSO",
      "AUSCULTA PULMONAR",
      "MONITORIZAÇÃO CARDIOSCOPICA"
    ],
    "Grupo Profissional ou Ocupacional": [
      "ENFª",
      "PLANTONISTA"
    ],
    "Bactéria": [
      "VRE",
      "MRSA"
    ],
    "Organização Relacionada à Saúde": [
      "CC"
    ],
    "Conceito Quantitativo": [
      "20",
      "8",
      "96 %",
      "50 %",
      "95 %",
      "63 ML/H"
    ],
    "Dispositivo Médico": [
      "CTVO",
      "CATETER NASAL",
      "ACESSO PERIFÉRICO",
      "COLCHÃO DE AR",
      "ACESSO VENOSO CENTRAL DUPLO LUMEN"
    ],
    "Conceito Qualitativo": [
      "2 /L",
      "GRANDE QUANTIDADE",
      "grande quantidade de estase biliosa",
      "MEDIA QUANTIDADE",
      "SECREÇÃO ESVERDEADA EM GRANDE QUANTIDADE"
    ],
    "Objeto Manufaturado": [
      "COLCHÃO DE AR"
    ],
    "Função Fisiológica": [
      "ELIMINAÇÕES PRESENTES"
    ],
    "Doença ou Síndrome": [
      "INSUFICIENCIA RENAL AGUDA",
      "EDEMA CEREBRAL"
    ],
    "Parte do Corpo, Órgão ou Componente Orgânico": [
      "SUBCLAVIA E",
      "EDEMA DE BOLSA ESCROTAL"
    ],
    "Função Patológica": [
      "EDEMA CACIFO +++"
    ]
  },
  "labels": {
    "aceitando pouco a dieta": {
      "capitulo": "13"
    },
    "mv diminuidos em bases": {
      "capitulo": "12"
    },
    "alerta": {
      "capitulo": "21"
    },
    "edema cacifo +++": {
      "capitulo": "14"
    },
    "salinizado": {
      "capitulo": "13"
    },
    "emese em jato bilioso": {
      "capitulo": "13"
    },
    "discreta dispneia aos esforços": {
      "capitulo": "12"
    },
    "bolhas": {
      "capitulo": "14"
    },
    "roncos difusos": {
      "capitulo": "12"
    },
    "edema de bolsa escrotal": {
      "capitulo": "16"
    },
    "sujidade": {
      "capitulo": "21"
    },
    "hiperemia": {
      "capitulo": "21"
    },
    "vre": {
      "capitulo": "24"
    },
    "edema cerebral": {
      "capitulo": "08"
    },
    "globoso": {
      "capitulo": "13"
    },
    "traqueostomizado": {
      "capitulo": "12"
    },
    "flácido": {
      "capitulo": "15"
    },
    "pupilas anisocoricas": {
      "capitulo": "21"
    },
    "grande quantidade de estase biliosa": {
      "capitulo": "13"
    },
    "insuficiencia renal aguda": {
      "capitulo": "11"
    },
    "hipertensão": {
      "capitulo": "11"
    },
    "mrsa": {
      "capitulo": "24"
    },
    "secreção esverdeada em grande quantidade": {
      "capitulo": "21"
    },
    "svd efetiva com debito citrico": {
      "capitulo": "21"
    }
  }
}