{
  "prontuario_id": 634,
  "text": "23H PERMANECE EM V.M. COM FIFLTRO DE BARREIRA EM MODO PSV 15 CM DE H2O, FIO2 EM0,60%, FR 18 RPM, PEEP 6 CM DE H2O. MONITORADO COM PNI, CARDIOSCOPIA E OXIMETRIA DE PULSO. APRESENTA PUPILAS ISOCÓRICAS E FOTORREAGENTES, GLASGOW 14, SNE COM DIETA A 75ML/H, TRAQUEOSTOMIZADO, SECREÇÃO TRAQUEOBRÔNQUICA MUCOPURULENTA EM MÉDIA QUANTIDADE, CURATIVO OCLUSIVO EM HTE, AUSCULTA PULMONAR COM RONCOS DIFUSOS, ABDOME PLANO E FLÁCIDO, RHA PRESENTES, COLETOR URUNÁRIO COM DIURESE EM BOM VOLUME ASPECTO AMARELO ESCURO. PERMANECE COM DISCRETO DESCONFORTO RESPIRATÓRIO E PERÍODOS DE AGITAÇÃO. CONFORME ORIENTAÇÃO DO PLANTONISTA FOI AUMENTADO A FR MIN DE 8 PARA 12. SEPTICEMIA NAO ESPECIFICADA. 00:54 POI de tto cx por osteomelite em femur direito. Lucido, comunicativo, orientado, apresenta curativo em regiao femural à direita, sanguinolento, realizado reforço, referindo algia moderada no local, coto em MIE, aceita dieta oferecida, diurese presente, segue cuidados. AUSENCIA DE CONSOLIDACAO DA FRATURA PSEUDO ARTROSE. 01:30h Admitido nesta unidade proveniente do CC apos realizar POI Cervicotomia com Esofagorrafia + Jejunostomia, com HX : FAF axilar E 07/08/10 + Hemotorax E + Lesao transfixante esofago/cervical + abcesso. Na admissao PA 90/66mmhg, FC 86bpm, Sat. 96% na sequencia evolui com hipotensao severa sendo necessario realizar volume sem melhora 60/40mmhg sendo inciado com noradrenalin ano momento 30ml/hr. Face hipocorada, pupilas isomioticas / foto. Curativo em reg. cervical com debito sanguinolento. Intubado, sob vm em modo PCV com 505 FIO2, PEEP 5, PL 24, ausculta pulmoanr com MV diminuidos em base E, aspirado media quantidade de secreçao, instalado novo filtro bacteriologico. Apresentava acesso venoso em MSE + MID infiltrando sendo realziado nova punçao vensosa em MSD com jelco 18 (com infusao de dormonid 30 ml/hr + fentanil 20 ml/hr ) e MSE com jelco 20 (noradrenalina 30 ml/hr).Dreno de torax em hemitorax E com debito hematico. Abdomen flacido palpaçao, rha hipoativo. Diurese por SVD presente em coletor cor verde. PAM em pedial E permeavel. Monitorado com cardioscopico + oximetria de pulso + pam invasiva. Enfermeira FLORENCE NIGHTINGALE. HEMOPNEUMOTORAX TRAUMATICO.",
  "entities": {
    "Abreviação": [
      "FIO2",
      "FR",
      "PEEP",
      "HTE",
      "POI",
      "MIE",
      "CC",
      "FAF",
      "PA",
      "FC",
      "Sat",
      "noradrenalin",
      "foto",
      "vm",
      "PL",
      "MSE",
      "MID",
      "MSD",
      "PAM",
      "MODO PSV",
      "18 RPM",
      "MONITORADO COM PNI",
      "SNE COM DIETA",
      "RHA PRESENTES",
      "AUMENTADO A FR",
      "tto cx",
      "axilar E",
      "Hemotorax E",
      "modo PCV",
      "MV diminuidos em base E",
      "hemitorax E",
      "rha hipoativo",
      "pedial E",
      "pam invasiva"
    ],
    "Procedimento Terapêutico ou Preventivo": [
      "FIO2",
      "PEEP",
      "TRAQUEOSTOMIZADO",
      "curativo",
      "Cervicotomia",
      "Esofagorrafia",
      "Jejunostomia",
      "Curativo",
      "Intubado",
      "vm",
      "infusao",
      "SVD",
      "FIFLTRO DE BARREIRA",
      "MODO PSV",
      "SNE COM DIETA",
      "CURATIVO OCLUSIVO",
      "AUMENTADO A FR",
      "tto cx",
      "realizado reforço",
      "modo PCV",
      "aspirado media quantidade de secreçao",
      "filtro bacteriologico",
      "acesso venoso",
      "punçao vensosa",
      "Dreno de torax"
    ],
    "Conceito Quantitativo": [
      "60%",
      "75ML/H",
      "90/66mmhg",
      "86bpm",
      "96%",
      "60/40mmhg",
      "30ml/hr",
      "505",
      "5",
      "24",
      "15 CM DE H2O",
      "18 RPM",
      "6 CM DE H2O",
      "8 PARA 12",
      "30 ml/hr",
      "20 ml/hr"
    ],
    "Procedimento Diagnóstico": [
      "CARDIOSCOPIA",
      "PAM",
      "Monitorado",
      "OXIMETRIA DE PULSO",
      "AUSCULTA PULMONAR",
      "ausculta pulmoanr",
      "oximetria de pulso",
      "pam invasiva"
    ],
    "Parte do Corpo, Órgão ou Componente Orgânico": [
      "PUPILAS",
      "coto",
      "pupilas",
      "femur direito"
    ],
    "Achado": [
      "ISOCÓRICAS",
      "FOTORREAGENTES",
      "TRAQUEOSTOMIZADO",
      "PLANO",
      "FLÁCIDO",
      "Lucido",
      "comunicativo",
      "orientado",
      "foto",
      "Intubado",
      "permeavel",
      "RHA PRESENTES",
      "BOM VOLUME",
      "ASPECTO AMARELO ESCURO",
      "aceita dieta",
      "diurese presente"
    ],
    "Localização ou Região Corporal": [
      "ABDOME",
      "MIE",
      "esofago/cervical",
      "cervical",
      "MSE",
      "MID",
      "MSD",
      "Abdomen",
      "regiao femural à direita",
      "axilar E",
      "hemitorax E"
    ],
    "Função Fisiológica": [
      "DIURESE",
      "Diurese",
      "diurese presente"
    ],
    "Atividade de Assistência à Saúde": [
      "ORIENTAÇÃO",
      "cuidados"
    ],
    "Grupo Profissional ou Ocupacional": [
      "PLANTONISTA",
      "Enfermeira"
    ],
    "Conceito Temporal": [
      "POI"
    ],
    "Dispositivo Médico": [
      "curativo",
      "Curativo",
      "SVD",
      "cardioscopico",
      "FIFLTRO DE BARREIRA",
      "CURATIVO OCLUSIVO",
      "COLETOR URUNÁRIO",
      "filtro bacteriologico",
      "acesso venoso",
      "jelco 18",
      "jelco 20",
      "Dreno de torax"
    ],
    "Sinal ou Sintoma": [
      "sanguinolento",
      "isomioticas",
      "GLASGOW 14",
      "SECREÇÃO TRAQUEOBRÔNQUICA MUCOPURULENTA",
      "RONCOS DIFUSOS",
      "DESCONFORTO RESPIRATÓRIO",
      "PERÍODOS DE AGITAÇÃO",
      "algia moderada",
      "hipotensao severa",
      "Face hipocorada",
      "debito sanguinolento",
      "MV diminuidos em base E",
      "debito hematico",
      "rha hipoativo"
    ],
    "Negação": [
      "AUSENCIA"
    ],
    "Organização Relacionada à Saúde": [
      "CC"
    ],
    "Lesão ou Envenenamento": [
      "FAF",
      "Lesao transfixante",
      "HEMOPNEUMOTORAX TRAUMATICO"
    ],
    "Doença ou Síndrome": [
      "abcesso",
      "PSEUDO ARTROSE",
      "HEMOPNEUMOTORAX TRAUMATICO"
    ],
    "Atributo Clínico": [
      "PA",
      "FC",
      "Sat"
    ],
    "Substância Química Orgânica": [
      "noradrenalin",
      "dormonid",
      "fentanil",
      "noradrenalina"
    ],
    "Substância Farmacológica": [
      "noradrenalin",
      "dormonid",
      "fentanil",
      "noradrenalina"
    ],
    "Hormônio": [
      "noradrenalin",
      "noradrenalina"
    ],
    "Substância Corporal": [
      "SECREÇÃO TRAQUEOBRÔNQUICA MUCOPURULENTA"
    ],
    "Conceito Qualitativo": [
      "MÉDIA QUANTIDADE",
      "aspirado media quantidade de secreçao"
    ]
  },
  "labels": {
    "isomioticas": {
      "capitulo": "08"
    },
    "debito sanguinolento": {
      "capitulo": "22"
    },
    "aspecto amarelo escuro": {
      "capitulo": "21"
    },
    "roncos difusos": {
      "capitulo": "12"
    },
    "fotorreagentes": {
      "capitulo": "21"
    },
    "abcesso": {
      "capitulo": "01"
    },
    "rha hipoativo": {
      "capitulo": "22"
    },
    "sanguinolento": {
      "capitulo": "22"
    },
    "secreção traqueobrônquica mucopurulenta": {
      "capitulo": "12"
    },
    "hipotensao severa": {
      "capitulo": "22"
    },
    "isocóricas": {
      "capitulo": "08"
    },
    "glasgow 14": {
      "capitulo": "21"
    },
    "debito hematico": {
      "capitulo": "22"
    },
    "lesao transfixante": {
      "capitulo": "01"
    },
    "hemopneumotorax traumatico": {
      "capitulo": "12"
    },
    "intubado": {
      "capitulo": "22"
    },
    "algia moderada": {
      "capitulo": "21"
    },
    "períodos de agitação": {
      "capitulo": "06"
    },
    "foto": {
      "capitulo": "21"
    },
    "traqueostomizado": {
      "capitulo": "12"
    },
    "mv diminuidos em base e": {
      "capitulo": "21"
    },
    "face hipocorada": {
      "capitulo": "22"
    },
    "desconforto respiratório": {
      "capitulo": "12"
    },
    "pseudo artrose": {
      "capitulo": "15"
    }
  }
}