{
  "prontuario_id": 505,
  "text": "22:40h Encaminhada para TAC Cranio sem intercorrencias no trajeto, mantem TOT + VM + pupilas com discoria D. Enfermeira FLORENCE NIGHTINGALE, ACIDENTE VASCULAR CEREBRAL NAO ESPECIFICADO COMO HEMORRAGICO OU ISQUEMICO.   Paciente vinda do XXXX após contato prévio , com história de HAS , uso irregular de Enalapril.    Há 3 meses apresentando mal estar , epigastralgia e náuseas.   Realizou USG , que segundo o relato do filho , mostrou um \"probleminha no rim\" , e EDA com gastrite aguda (medicamentosa?). Segundo o filho , apresentava Cr = 2,6 na época , mas não chegou a levar ao médico que a acompanha.    Foi prescrito Omeprazol, com alguma melhora do quadro, mas há 4 dias confusa , desorientada e \"muito parada\" , sendo levada ao XXXX , onde doram realizados exames de lab. que revelaram Cr = 30  Ureia = 399 , K = 7,0 e anemia.       Sem outras alterações agudas.     História de Insuficiencia venosa cronica , com úlcera de repetição em MMII , em uso de Capilarema.    Colecistectomia há mais de 15 anos.    G = V  P = II ( 1 cesária ; 1 prematuro natimorto)  A = III.    Nega alergia a drogas e outras patologias.     Hipocorada, desidratada , taquipneica, afebril.  Pulsos periféricos simétricos , de amplitude diminuída.  Sem TJV.   Nuca livre.   Isocoria fotorreagente.  Sem deficit motor aparente.   AP = MV audíveis em AHT , crepitação em bases.   AC = RCR 2 t Irregular.    Abdomem = NDN    MMII = panturrilhas livres.  Dermatite ócrea.    PA = 134 x 98   FC = 76   SatO2 = 96  FR = 28   Dextro = 124   ECG = BRE   RX de torax com aumento de área cardíaca e congestão leve.     CD = Internação aos cuidados do Dr VITAL BRASIL ( nefro)             Exames.     Dra MARIA (XXXX) INSUFICIENCIA RENAL NAO ESPECIFICADA.",
  "entities": {
    "Atividade de Assistência à Saúde": [
      "Encaminhada",
      "Internação",
      "cuidados"
    ],
    "Negação": [
      "sem",
      "Sem",
      "Nega",
      "afebril"
    ],
    "Sinal ou Sintoma": [
      "intercorrencias",
      "epigastralgia",
      "náuseas",
      "confusa",
      "desorientada",
      "Hipocorada",
      "desidratada",
      "taquipneica",
      "pupilas com discoria D",
      "mal estar",
      "\"muito parada\"",
      "alterações agudas",
      "amplitude diminuída",
      "deficit motor",
      "crepitação em bases"
    ],
    "Dispositivo Médico": [
      "TOT"
    ],
    "Procedimento Terapêutico ou Preventivo": [
      "TOT",
      "VM",
      "Colecistectomia",
      "cesária"
    ],
    "Abreviação": [
      "TOT",
      "VM",
      "HAS",
      "USG",
      "EDA",
      "Cr",
      "K",
      "MMII",
      "G",
      "P",
      "A",
      "TJV",
      "AP",
      "AC",
      "NDN",
      "PA",
      "FC",
      "SatO2",
      "FR",
      "ECG",
      "BRE",
      "CD",
      "Dr",
      "nefro",
      "Dra",
      "TAC Cranio",
      "pupilas com discoria D",
      "exames de lab",
      "MV audíveis",
      "2 t",
      "RX de torax"
    ],
    "Grupo Profissional ou Ocupacional": [
      "Enfermeira",
      "médico",
      "nefro"
    ],
    "Paciente ou Grupo com Deficiência": [
      "Paciente"
    ],
    "Doença ou Síndrome": [
      "HAS",
      "anemia",
      "patologias",
      "BRE",
      "ACIDENTE VASCULAR CEREBRAL",
      "gastrite aguda",
      "Insuficiencia venosa cronica",
      "úlcera de repetição",
      "Dermatite ócrea",
      "INSUFICIENCIA RENAL"
    ],
    "Aminoácido, Peptídeo ou Proteína": [
      "Enalapril"
    ],
    "Substância Farmacológica": [
      "Enalapril",
      "Omeprazol",
      "Capilarema"
    ],
    "Procedimento Diagnóstico": [
      "USG",
      "EDA",
      "AP",
      "AC",
      "ECG",
      "Exames",
      "TAC Cranio",
      "RX de torax"
    ],
    "Grupo Familiar": [
      "filho"
    ],
    "Procedimento Laboratorial": [
      "Cr",
      "Ureia",
      "K",
      "Exames",
      "exames de lab"
    ],
    "Substância Química Orgânica": [
      "Omeprazol"
    ],
    "Localização ou Região Corporal": [
      "MMII",
      "Nuca",
      "Abdomem"
    ],
    "Conceito Quantitativo": [
      "V",
      "II",
      "1",
      "III",
      "76",
      "96",
      "28",
      "134 x 98"
    ],
    "Achado": [
      "afebril",
      "livre",
      "Isocoria",
      "fotorreagente",
      "RCR",
      "melhora do quadro",
      "prematuro natimorto",
      "MV audíveis",
      "2 t",
      "panturrilhas livres"
    ],
    "Atributo Clínico": [
      "PA",
      "FC",
      "SatO2",
      "FR"
    ],
    "Resultado Laboratorial ou de Teste": [
      "BRE",
      "gastrite aguda",
      "aumento de área cardíaca",
      "congestão leve"
    ],
    "Função Patológica": [
      "alergia a drogas"
    ]
  },
  "labels": {
    "desorientada": {
      "capitulo": "06"
    },
    "amplitude diminuída": {
      "capitulo": "08"
    },
    "dermatite ócrea": {
      "capitulo": "14"
    },
    "isocoria": {
      "capitulo": "09"
    },
    "mal estar": {
      "capitulo": "21"
    },
    "rcr": {
      "capitulo": "11"
    },
    "livre": {
      "capitulo": "21"
    },
    "alterações agudas": {
      "capitulo": "21"
    },
    "2 t": {
      "capitulo": "11"
    },
    "confusa": {
      "capitulo": "06"
    },
    "\"muito parada\"": {
      "capitulo": "06"
    },
    "crepitação em bases": {
      "capitulo": "08"
    },
    "insuficiencia renal": {
      "capitulo": "16"
    },
    "bre": {
      "capitulo": "08"
    },
    "epigastralgia": {
      "capitulo": "13"
    },
    "pupilas com discoria d": {
      "capitulo": "09"
    },
    "intercorrencias": {
      "capitulo": "21"
    },
    "hipocorada": {
      "capitulo": "11"
    },
    "desidratada": {
      "capitulo": "11"
    },
    "melhora do quadro": {
      "capitulo": "21"
    },
    "gastrite aguda": {
      "capitulo": "13"
    },
    "alergia a drogas": {
      "capitulo": "04"
    },
    "has": {
      "capitulo": "05"
    },
    "patologias": {
      "capitulo": "04"
    },
    "deficit motor": {
      "capitulo": "08"
    },
    "úlcera de repetição": {
      "capitulo": "14"
    },
    "mv audíveis": {
      "capitulo": "10"
    },
    "náuseas": {
      "capitulo": "13"
    },
    "fotorreagente": {
      "capitulo": "09"
    },
    "prematuro natimorto": {
      "capitulo": "20"
    },
    "panturrilhas livres": {
      "capitulo": "21"
    },
    "acidente vascular cerebral": {
      "capitulo": "08"
    },
    "anemia": {
      "capitulo": "03"
    },
    "taquipneica": {
      "capitulo": "11"
    },
    "insuficiencia venosa cronica": {
      "capitulo": "16"
    }
  }
}