{
  "prontuario_id": 190,
  "text": "08:35H Glasgow 8. SNE infundidno dieta. Em ventilação mecânica modo PSV, PS 15 cmH2O, FiO2 27%, Peep 8. Traqueostomizado, uso contínuo de filtro de barreira e sistema fechado de aspiração. Acesso central em subclávia D com curativo de filme transparente infundindo noradrenalina 10 ml/h + plano de hidratação gravitacional. CPP com roncos difusos. Abdomem globoso, flácido, RHa +. MMSS contidos. SVD com diurese efetiva. Em anasarca, apresenta descamação e fragilidade cutânea . Monitorizado contínuamente com parâmetros de PA não invasiva, cardisocopia e oximetria de pulso. Segue sob cuidados intensivos e precaução de contato profilático. Enfª FLORENCE NIGHTINGALE, COREN XXXX. OUTRAS SEPTICEMIAS. 21:30 PROVENIENTE DO PA COM QUEIXAS DE DISPNÉIA + TOSSE + INCONTINÊNCIA URINÁRIA, AO CHEGAR NA UTI GLASGOW = 15, ORIENTADO EM TEMPO E ESPAÇO, COMUNICATIVO, POUCO ANCIOSO DEVIDO PRÓPRIO INTERNAMENTO, EUPNEICO EM AR AMBIENTE SATURANDO 94%, HIPERTENSO 223/118, NORMOCÁRDICO 94 bpm, AFEBRIL 36.5º C, NORMOCORADO, ACESSO VENOSO EM MSD SALINIZADO, AUSCULTA PULMONAR POSITIVA, COM EXPANSÇÃO E COMPLACÊNCIA SIMÉTRICOS, ABDOMEM FLÁCIDO SEM MASSA PALPÁVEL INDOLOR A PALPAÇÃO, RHA HIPOATIVOS, PELE ÍNTEGRA EM SACRA, SVD COM DIURESE PRESENTE + PRESENÇA HEMATÚRIA + ARDÊNCIA NO CANAL + EXTRAVAZAMENTO E DOR AO URINAR, COMUNICADO DR VITAL BRASIL, O MESMO SOLICITA QUE RETIRE A SVD E MANTENHA COM DIURESE ESPONTÂNEA, SONDA RETIRADA SEM INTERCORRÊNCIAS, MMII LIVRES, PERFUSÃO PERIFÉRICA DIMINUÍDA, HEMODINÂMICAMENTE ESTÁVEL, INICIA COM CUIDADOS INTENSIVOS DE UTI. DOENCA PULMONAR OBSTRUTIVA CRONICA COM EXACERBACAO AGUDA NAO ESPECIFICADA.",
  "entities": {
    "Abreviação": [
      "PS",
      "FiO2",
      "Peep",
      "CPP",
      "Enfª",
      "PA",
      "UTI",
      "MSD",
      "SVD",
      "DR",
      "SNE infundidno dieta",
      "modo PSV",
      "subclávia D",
      "RHa +",
      "MMSS contidos",
      "SVD com diurese efetiva",
      "PA não invasiva",
      "RHA HIPOATIVOS",
      "RETIRE A SVD",
      "MMII LIVRES"
    ],
    "Procedimento Terapêutico ou Preventivo": [
      "PS",
      "FiO2",
      "Peep",
      "Traqueostomizado",
      "SALINIZADO",
      "SVD",
      "SNE infundidno dieta",
      "ventilação mecânica",
      "modo PSV",
      "filtro de barreira",
      "sistema fechado de aspiração",
      "Acesso central",
      "curativo de filme transparente",
      "plano de hidratação gravitacional",
      "MMSS contidos",
      "SVD com diurese efetiva",
      "precaução de contato profilático",
      "ACESSO VENOSO",
      "RETIRE A SVD",
      "SONDA RETIRADA"
    ],
    "Conceito Quantitativo": [
      "27%",
      "8",
      "94%",
      "223/118",
      "36",
      "15 cmH2O",
      "10 ml/h",
      "94 bpm"
    ],
    "Achado": [
      "Traqueostomizado",
      "flácido",
      "COMUNICATIVO",
      "NORMOCÁRDICO",
      "AFEBRIL",
      "NORMOCORADO",
      "SALINIZADO",
      "RHa +",
      "SVD com diurese efetiva",
      "GLASGOW = 15",
      "ORIENTADO EM TEMPO E ESPAÇO",
      "EUPNEICO EM AR AMBIENTE",
      "AUSCULTA PULMONAR POSITIVA",
      "EXPANSÇÃO E COMPLACÊNCIA SIMÉTRICOS",
      "MASSA PALPÁVEL",
      "PELE ÍNTEGRA",
      "DIURESE PRESENTE",
      "DIURESE ESPONTÂNEA",
      "MMII LIVRES",
      "HEMODINÂMICAMENTE ESTÁVEL"
    ],
    "Hormônio": [
      "noradrenalina"
    ],
    "Substância Farmacológica": [
      "noradrenalina"
    ],
    "Substância Química Orgânica": [
      "noradrenalina"
    ],
    "Localização ou Região Corporal": [
      "Abdomem",
      "MSD",
      "ABDOMEM",
      "SACRA"
    ],
    "Sinal ou Sintoma": [
      "globoso",
      "anasarca",
      "descamação",
      "DISPNÉIA",
      "TOSSE",
      "HIPERTENSO",
      "HEMATÚRIA",
      "EXTRAVAZAMENTO",
      "INTERCORRÊNCIAS",
      "Glasgow 8",
      "roncos difusos",
      "RHA HIPOATIVOS",
      "ARDÊNCIA NO CANAL",
      "DOR AO URINAR",
      "PERFUSÃO PERIFÉRICA DIMINUÍDA"
    ],
    "Função Patológica": [
      "anasarca"
    ],
    "Procedimento Diagnóstico": [
      "cardisocopia",
      "PALPAÇÃO",
      "Monitorizado contínuamente",
      "PA não invasiva",
      "oximetria de pulso"
    ],
    "Grupo Profissional ou Ocupacional": [
      "Enfª"
    ],
    "Doença ou Síndrome": [
      "SEPTICEMIAS",
      "DOENCA PULMONAR OBSTRUTIVA CRONICA"
    ],
    "Organização Relacionada à Saúde": [
      "PA",
      "UTI"
    ],
    "Atributo Clínico": [
      "SATURANDO"
    ],
    "Negação": [
      "AFEBRIL",
      "SEM",
      "INDOLOR"
    ],
    "Dispositivo Médico": [
      "SVD",
      "filtro de barreira",
      "Acesso central",
      "curativo de filme transparente",
      "ACESSO VENOSO"
    ],
    "Parte do Corpo, Órgão ou Componente Orgânico": [
      "subclávia D"
    ],
    "Função Fisiológica": [
      "SVD com diurese efetiva",
      "DIURESE PRESENTE",
      "DIURESE ESPONTÂNEA"
    ],
    "Atividade de Assistência à Saúde": [
      "cuidados intensivos",
      "CUIDADOS INTENSIVOS"
    ]
  },
  "labels": {
    "normocorado": {
      "capitulo": "11"
    },
    "expansção e complacência simétricos": {
      "capitulo": "12"
    },
    "doenca pulmonar obstrutiva cronica": {
      "capitulo": "12"
    },
    "ardência no canal": {
      "capitulo": "21"
    },
    "svd com diurese efetiva": {
      "capitulo": "16"
    },
    "salinizado": {
      "capitulo": "11"
    },
    "descamação": {
      "capitulo": "14"
    },
    "ausculta pulmonar positiva": {
      "capitulo": "12"
    },
    "roncos difusos": {
      "capitulo": "12"
    },
    "anasarca": {
      "capitulo": "14"
    },
    "perfusão periférica diminuída": {
      "capitulo": "11"
    },
    "glasgow = 15": {
      "capitulo": "21"
    },
    "massa palpável": {
      "capitulo": "21"
    },
    "glasgow 8": {
      "capitulo": "21"
    },
    "normocárdico": {
      "capitulo": "11"
    },
    "eupneico em ar ambiente": {
      "capitulo": "12"
    },
    "tosse": {
      "capitulo": "12"
    },
    "dispnéia": {
      "capitulo": "12"
    },
    "dor ao urinar": {
      "capitulo": "21"
    },
    "intercorrências": {
      "capitulo": "22"
    },
    "extravazamento": {
      "capitulo": "22"
    },
    "hemodinâmicamente estável": {
      "capitulo": "11"
    },
    "globoso": {
      "capitulo": "21"
    },
    "hipertenso": {
      "capitulo": "11"
    },
    "traqueostomizado": {
      "capitulo": "12"
    },
    "pele íntegra": {
      "capitulo": "14"
    },
    "flácido": {
      "capitulo": "21"
    },
    "hematúria": {
      "capitulo": "16"
    },
    "septicemias": {
      "capitulo": "01"
    }
  }
}