{
  "prontuario_id": 834,
  "text": "PACIENTE COM IAM EM 98, IMPLANTE DE STENTS EM ACD EM 11/01, INTERNA COM ANGINA INSTÁVEL. NO CATETERISMO, EVIDENCIA-SE LESÃO DE 50-60 % EM ADA E REESTENOSES DE STENTS DO SEGMENTO MÉDIO E DISTAL DA ACD. REALIZADA ACTP COM SUCESSO E SEM INTERCORRÊNCIAS, COM RESULTADO TIMI III.  PACIENTE TERÁ ALTA HOSPITALAR ASSINTOMÁTICO. João, 64 anos, # ICC (FE 40 % prévia), # DM 2, # HAS, # AVEi dez/06 sem seqüelas, # Ex-tabagista, # Claudicação intermitente. Paciente com angina estável classe II em vigência de tratamento clínico interna eletivamente para realização de ACTP + stent em lesão grave (calcificada e em curva) na ADA proximal. Durante o procedimento, ocorreu dissecção proximal em espiral da ADA, paciente evoluiu com dor precordial intensa e PCR em FV (após a abertura do vaso), prontamente revertida após um choque não sincronizado de 360 J. Foi reaberta a artéria descendente anterior em seu segmento proximal (2 stents seqüenciais), fluxo TIMI II no terço proximal e médio, o que permitiu a preservação de 2 calibrosos ramos septais com circulação colateral para a ACD (ocluída). Não foi possível abrir o terço distal da ADA a despeito de várias tentativas. Paciente foi transferido ao CTI para monitorização. Evoluiu com infarto com SST em parede ântero-septal, sem instabilidade hemodinâmica, insuficiência cardíaca ou complicações pós-infarto. Apresentou episódio de hemorragia digestiva alta, autolimitado e sem repercussão hemodinâmica. EGD mostrou 2 úlceras gástricas Forrest III. Recebeu omeprazol EV por 24 h, passado então para VO e reiniciados anti-plaquetários conforme orientação da gastro. Ecocardio realizado no dia 21/02 mostrou ventriculo esquerdo com diâmetros normais e marcado aumento das espessuras parietais. Hipocinesia da parede anterior, do ápice e dos segmentos médio e basal da parede inferior. Fração de ejeção de 52 %. Déficit de relaxamento. Foi feito doppler de membro inferior direito para avaliação de abaulamento no local da punção, descartado pseudoaneurisma. Recebe alta em bom estado geral, com a pressão arterial bem controlada, sem queixa de dor precordial, sem dispnéia ou sinais clínicos de insuficiência cardíaca. Recomendação de: - manter uso de ticlopidina 250 mg 12/12 h por 30 dias, - AAS 100 mg / dia, - sinvastatina 20 mg/dia, - captopril 50 mg 8/8 h, - HCTZ 25 mg / dia, - Isossorbida 40 mg 3 x/dia, - Metoprolol 50 mg 12/12 h, - Anlodipina 10 mg / dia, - Omeprazol 20 mg / dia. Retorno ao ambulatório de cardiologia. Procurar a emergência em caso de intercorrências.",
  "entities": {
    "Paciente ou Grupo com Deficiência": [
      "PACIENTE",
      "Paciente",
      "paciente"
    ],
    "Abreviação": [
      "IAM",
      "ACD",
      "ACTP",
      "ICC",
      "HAS",
      "AVEi",
      "ADA",
      "CTI",
      "EGD",
      "VO",
      "gastro",
      "Ecocardio",
      "AAS",
      "HCTZ",
      "LESÃO DE 50-60 % EM ADA",
      "FE 40 % prévia",
      "DM 2",
      "ADA proximal",
      "PCR em FV",
      "infarto com SST",
      "omeprazol EV"
    ],
    "Doença ou Síndrome": [
      "IAM",
      "ICC",
      "HAS",
      "AVEi",
      "DM 2",
      "PCR em FV",
      "infarto com SST",
      "insuficiência cardíaca",
      "úlceras gástricas Forrest III"
    ],
    "Parte do Corpo, Órgão ou Componente Orgânico": [
      "ACD",
      "ADA",
      "ADA proximal"
    ],
    "Procedimento Terapêutico ou Preventivo": [
      "CATETERISMO",
      "ACTP",
      "procedimento",
      "VO",
      "IMPLANTE DE STENTS",
      "tratamento clínico",
      "stent em lesão grave",
      "prontamente revertida",
      "choque não sincronizado de 360 J",
      "2 stents seqüenciais"
    ],
    "Procedimento Diagnóstico": [
      "CATETERISMO",
      "monitorização",
      "EGD",
      "Ecocardio",
      "doppler de membro inferior direito"
    ],
    "Achado": [
      "SUCESSO",
      "ASSINTOMÁTICO",
      "Ex-tabagista",
      "autolimitado",
      "RESULTADO TIMI III",
      "calcificada e em curva",
      "fluxo TIMI II no terço proximal e médio",
      "bom estado geral",
      "pressão arterial bem controlada"
    ],
    "Negação": [
      "SEM",
      "ASSINTOMÁTICO",
      "sem",
      "Não"
    ],
    "Sinal ou Sintoma": [
      "INTERCORRÊNCIAS",
      "seqüelas",
      "ocluída",
      "queixa",
      "dispnéia",
      "intercorrências",
      "ANGINA INSTÁVEL",
      "FE 40 % prévia",
      "Claudicação intermitente",
      "angina estável classe II",
      "dor precordial intensa",
      "instabilidade hemodinâmica",
      "complicações pós-infarto",
      "repercussão hemodinâmica",
      "Déficit de relaxamento",
      "dor precordial",
      "sinais clínicos de insuficiência cardíaca"
    ],
    "Conceito Quantitativo": [
      "2",
      "Fração de ejeção de 52 %",
      "250 mg",
      "100 mg",
      "20 mg/dia",
      "50 mg",
      "25 mg",
      "40 mg",
      "10 mg",
      "20 mg"
    ],
    "Organização Relacionada à Saúde": [
      "CTI",
      "emergência",
      "ambulatório de cardiologia"
    ],
    "Substância Farmacológica": [
      "anti-plaquetários",
      "ticlopidina",
      "AAS",
      "sinvastatina",
      "captopril",
      "HCTZ",
      "Isossorbida",
      "Metoprolol",
      "Anlodipina",
      "Omeprazol",
      "omeprazol EV"
    ],
    "Atividade de Assistência à Saúde": [
      "orientação",
      "alta",
      "Retorno",
      "ALTA HOSPITALAR"
    ],
    "Grupo Profissional ou Ocupacional": [
      "gastro"
    ],
    "Função Patológica": [
      "pseudoaneurisma",
      "hemorragia digestiva alta"
    ],
    "Substância Química Orgânica": [
      "ticlopidina",
      "AAS",
      "sinvastatina",
      "HCTZ",
      "Isossorbida",
      "Metoprolol",
      "Anlodipina",
      "Omeprazol"
    ],
    "Aminoácido, Peptídeo ou Proteína": [
      "captopril"
    ],
    "Resultado Laboratorial ou de Teste": [
      "LESÃO DE 50-60 % EM ADA",
      "RESULTADO TIMI III",
      "FE 40 % prévia",
      "úlceras gástricas Forrest III",
      "ventriculo esquerdo com diâmetros normais",
      "marcado aumento das espessuras parietais",
      "Fração de ejeção de 52 %"
    ],
    "Dispositivo Médico": [
      "2 stents seqüenciais"
    ],
    "Função Fisiológica": [
      "circulação colateral"
    ]
  },
  "labels": {
    "resultado timi iii": {
      "capitulo": "11"
    },
    "sucesso": {
      "capitulo": "21"
    },
    "dm 2": {
      "capitulo": "05"
    },
    "dor precordial intensa": {
      "capitulo": "11"
    },
    "repercussão hemodinâmica": {
      "capitulo": "11"
    },
    "iam": {
      "capitulo": "11"
    },
    "queixa": {
      "capitulo": "21"
    },
    "insuficiência cardíaca": {
      "capitulo": "11"
    },
    "fluxo timi ii no terço proximal e médio": {
      "capitulo": "11"
    },
    "icc": {
      "capitulo": "05"
    },
    "hemorragia digestiva alta": {
      "capitulo": "13"
    },
    "infarto com sst": {
      "capitulo": "11"
    },
    "úlceras gástricas forrest iii": {
      "capitulo": "13"
    },
    "dispnéia": {
      "capitulo": "12"
    },
    "pcr em fv": {
      "capitulo": "21"
    },
    "sinais clínicos de insuficiência cardíaca": {
      "capitulo": "11"
    },
    "intercorrências": {
      "capitulo": "21"
    },
    "has": {
      "capitulo": "05"
    },
    "déficit de relaxamento": {
      "capitulo": "08"
    },
    "dor precordial": {
      "capitulo": "11"
    },
    "calcificada e em curva": {
      "capitulo": "11"
    },
    "instabilidade hemodinâmica": {
      "capitulo": "11"
    },
    "angina estável classe ii": {
      "capitulo": "11"
    },
    "claudicação intermitente": {
      "capitulo": "15"
    },
    "ocluída": {
      "capitulo": "11"
    },
    "complicações pós-infarto": {
      "capitulo": "21"
    },
    "angina instável": {
      "capitulo": "11"
    },
    "pseudoaneurisma": {
      "capitulo": "22"
    }
  }
}