{
  "prontuario_id": 896,
  "text": "Natália, 9 anos.  # Crises convulsivas de difícil controle. # Amilase elevada - toxicidade anticonvulsivantes? Paciente com crises convulsivas desde o nascimento. Fazia acompanhamento em Portão (onde reside) e há cerca de 2 anos iniciou acompanhamento com NEI HCPA. Vinha em uso de VPA 250 mg 8/8 h e oxcarbamazepina 300 mg 12/12 h. Padrão de crises piorou este ano (quase que semanalmente). Crises são tônico-clônicas generalizadas. Hematoma em mento devido a queda durante crise convulsiva (provas de coagulação normais). Em 21/05, estava em consulta com NEI: amilase: 202. Conversado com GAI que orientou internar e solicitar Eco Abdômem. Sem sintomas abdominais ou outras queixas. Exame físico sem alterações (exceto hematoma em mento). Em 22/05, repetida amilase: 298, TGO, TGP, GGT e lipase normais. NS VPA: 71,7 (adequado). NEI aumentou oxcarba p/ 300 mg 8/8 h e reduziu VPA para 250 mg 12/12 h e iniciou topiramato 12,5 mg 12/12 h em 23/05. Em 25/05, NEI reduziu VPA para 250 mg 1 x/dia, aumentado topiramato p/ 25 mg 12/12 h e mantida dose de oxcarba. Eco Abdominal normal (exceto pequeno nódulo em lobo ---> mínimo hemangioma??). Paciente bem clinicamente. Suspendo ácido valproico dia 29/05. Reavaliada pela NEI, alteração no ENE. Necessidade de realização de RNM. Dia 30/05 apresentou crise convulsiva a noite. Aumentado dose do topiramato. Sem novas crises, realizou RNM dia 01/06: normal. Condições de alta hospitalar com as medicações em uso. Plano: acompanhamento com a neuro, manter medicações conforme receita médica.",
  "entities": {
    "Conceito Temporal": [
      "anos",
      "h",
      "ano",
      "semanalmente",
      "x/dia",
      "dia",
      "Dia",
      "noite"
    ],
    "Paciente ou Grupo com Deficiência": [
      "Paciente"
    ],
    "Substância Farmacológica": [
      "VPA",
      "oxcarbamazepina",
      "oxcarba",
      "topiramato",
      "medicações",
      "ácido valproico"
    ],
    "Substância Química Orgânica": [
      "VPA",
      "oxcarbamazepina",
      "oxcarba",
      "topiramato",
      "ácido valproico"
    ],
    "Abreviação": [
      "VPA",
      "h",
      "TGO",
      "TGP",
      "GGT",
      "oxcarba",
      "RNM",
      "neuro",
      "Eco Abdômem",
      "NS VPA : 71 , 7"
    ],
    "Conceito Qualitativo": [
      "piorou"
    ],
    "Sinal ou Sintoma": [
      "Crises",
      "queixas",
      "alterações",
      "crises convulsivas",
      "tônico-clônicas generalizadas",
      "crise convulsiva",
      "sintomas abdominais",
      "novas crises"
    ],
    "Função Patológica": [
      "Hematoma",
      "hematoma"
    ],
    "Atividade de Assistência à Saúde": [
      "consulta",
      "Suspendo",
      "Reavaliada",
      "alta hospitalar"
    ],
    "Negação": [
      "Sem"
    ],
    "Localização ou Região Corporal": [
      "mento"
    ],
    "Procedimento Laboratorial": [
      "TGO",
      "TGP",
      "GGT",
      "lipase"
    ],
    "Achado": [
      "normais",
      "normal",
      "provas de coagulação normais",
      "bem clinicamente"
    ],
    "Parte do Corpo, Órgão ou Componente Orgânico": [
      "lobo"
    ],
    "Processo Neoplásico": [
      "hemangioma"
    ],
    "Procedimento Diagnóstico": [
      "RNM",
      "Eco Abdômem",
      "Exame físico"
    ],
    "Resultado Laboratorial ou de Teste": [
      "normal",
      "Amilase elevada",
      "provas de coagulação normais",
      "amilase : 298",
      "NS VPA : 71 , 7",
      "pequeno nódulo"
    ],
    "Grupo Profissional ou Ocupacional": [
      "neuro"
    ],
    "Procedimento Terapêutico ou Preventivo": [
      "medicações"
    ],
    "Lesão ou Envenenamento": [
      "toxicidade anticonvulsivantes"
    ],
    "Produto Intelectual": [
      "receita médica"
    ]
  },
  "labels": {
    "crises convulsivas": {
      "capitulo": "08"
    },
    "tônico-clônicas generalizadas": {
      "capitulo": "08"
    },
    "hemangioma": {
      "capitulo": "14"
    },
    "crises": {
      "capitulo": "08"
    },
    "alterações": {
      "capitulo": "21"
    },
    "queixas": {
      "capitulo": "21"
    },
    "hematoma": {
      "capitulo": "22"
    },
    "crise convulsiva": {
      "capitulo": "08"
    },
    "sintomas abdominais": {
      "capitulo": "13"
    },
    "toxicidade anticonvulsivantes": {
      "capitulo": "21"
    },
    "novas crises": {
      "capitulo": "08"
    }
  }
}