{
  "prontuario_id": 823,
  "text": "# HAS # HIPOTIREIODISMO PÓS TIREOIDECTOMIA  ( BOCIO MULTINODULAR TÓXICO ) # ESTENOSE MITRAL COMISSUROTOMIA EM 1999 # ACFA ( ANTICOAGULADA ) # ECOCARDIO 2004 AE 5,4 DD 4,7 DS 2,9 FE 69% AREA VALVAL MITRAL 2  PACIENTE INTERNA NO HCPA POR EPISÓDIO DE MAL-ESTAR , SUDORESE , ESCURESCIMENTO VISUAL E PRÉ SINCOPE . NA CHEGADA AO HOSPITAL APRESENTAVA UMA BRADICARDICA , COMPATIVEL COM BAVT ( FC 36 ) A QUAL FOI ATRIBUIDA APOS INVESTIGAÇÃO LABORATORIAL E RADIOLÓGICA AS MEDICAÇÕES ( DIGOXINA + VERAPAMIL ) . COM A SUSPENSÃO DAS DROGAS E CORREÇÃO DA INSTABILIDADE HEMODINÂMICA PACIENTE APRESENTOU MELHORA SIGNIFICATIVAS DA SINTOMATOLOGIA . NA ALTA PACIENTE ENCONTRA-SE ASSINTOMÁTICA , AFEBRIL COM SINAIS VITÁIS ESTAVÉIS E RECEBE ENCAMINHAMENTO PARA AMBULATÓRIO DE CARDIOLOGIA (Doutor Vital Brazil ) PARA ACOMPANHAMENTO DO DISTÚRBIO DE CONDUÇÃO E DEMAIS COMORBIDADES. ",
  "entities": {
    "Doença ou Síndrome": [
      "HAS",
      "ACFA",
      "BAVT",
      "BOCIO MULTINODULAR TÓXICO",
      "ESTENOSE MITRAL",
      "DISTÚRBIO DE CONDUÇÃO",
      "DEMAIS COMORBIDADES"
    ],
    "Abreviação": [
      "HAS",
      "ACFA",
      "ECOCARDIO",
      "BAVT",
      "FC",
      "AE 5 , 4",
      "DD 4 , 7",
      "DS 2 , 9",
      "FE 69%"
    ],
    "Conceito Temporal": [
      "PÓS",
      "APOS"
    ],
    "Procedimento Terapêutico ou Preventivo": [
      "TIREOIDECTOMIA",
      "COMISSUROTOMIA",
      "ANTICOAGULADA",
      "SUSPENSÃO DAS DROGAS",
      "CORREÇÃO DA INSTABILIDADE HEMODINÂMICA"
    ],
    "Procedimento Diagnóstico": [
      "ECOCARDIO",
      "INVESTIGAÇÃO",
      "RADIOLÓGICA"
    ],
    "Paciente ou Grupo com Deficiência": [
      "PACIENTE"
    ],
    "Atividade de Assistência à Saúde": [
      "INTERNA",
      "ALTA",
      "ENCAMINHAMENTO",
      "ACOMPANHAMENTO",
      "SUSPENSÃO DAS DROGAS",
      "CORREÇÃO DA INSTABILIDADE HEMODINÂMICA"
    ],
    "Sinal ou Sintoma": [
      "SUDORESE",
      "BRADICARDICA",
      "EPISÓDIO DE MAL-ESTAR",
      "ESCURESCIMENTO VISUAL",
      "PRÉ SINCOPE"
    ],
    "Organização Relacionada à Saúde": [
      "HOSPITAL",
      "AMBULATÓRIO DE CARDIOLOGIA"
    ],
    "Atributo Clínico": [
      "FC"
    ],
    "Conceito Quantitativo": [
      "36"
    ],
    "Procedimento Laboratorial": [
      "LABORATORIAL"
    ],
    "Substância Farmacológica": [
      "MEDICAÇÕES",
      "DIGOXINA",
      "VERAPAMIL"
    ],
    "Substância Química Orgânica": [
      "DIGOXINA",
      "VERAPAMIL"
    ],
    "Negação": [
      "ASSINTOMÁTICA",
      "AFEBRIL"
    ],
    "Achado": [
      "ASSINTOMÁTICA",
      "AFEBRIL",
      "MELHORA SIGNIFICATIVAS DA SINTOMATOLOGIA",
      "SINAIS VITÁIS ESTAVÉIS"
    ],
    "Resultado Laboratorial ou de Teste": [
      "AE 5 , 4",
      "DD 4 , 7",
      "DS 2 , 9",
      "FE 69%",
      "AREA VALVAL MITRAL 2"
    ]
  },
  "labels": {
    "bocio multinodular tóxico": {
      "capitulo": "05"
    },
    "estenose mitral": {
      "capitulo": "11"
    },
    "distúrbio de condução": {
      "capitulo": "08"
    },
    "escurescimento visual": {
      "capitulo": "09"
    },
    "episódio de mal-estar": {
      "capitulo": "21"
    },
    "pré sincope": {
      "capitulo": "21"
    },
    "acfa": {
      "capitulo": "11"
    },
    "bradicardica": {
      "capitulo": "11"
    },
    "sudorese": {
      "capitulo": "21"
    }
  }
}