{
  "prontuario_id": 343,
  "text": "Lucas, 58 anos - DM tipo 2 - HAS.   Em uso de:  - Atenolol 25mg 12/12 h - Metformina 850mg 1 cp na hora do café da manhã e outro cp conforme HGT à tarde - Lexotam quando está nervosa.  Peso: 112kg, Altura: 1,62m; IMC: 42,67.  Paciente refere que sua glicemia se altera conforme estado emocional. Não tem feito controle de HGT pois está desempregada e não consegue comprar as fitas. Não se adaptou com a Metformina porque tem alergia na pele (sic), coça-se muito. 0  Laboratório (18/03/2015): Hb A1C 8,22%; Glicemia de jejum 129; Creatinina 0,9;  TFG CKD-EPI 70.2 ml/min/1.73 m2; Ureia 28; Sódio 138; Potássio 4,8; Bilirrubina total 0,70 (D 0,2; I 0,5); Triglicerídeos 152; Colesterol total 193;  LDL 121; HDL 42; TGP 39;  TGO 37; RNI 1,09;  TTPA 0,95; TSH ultrassensível 2,71; T4 livre 1,32; Prolactina 7,1; Testosterona total 69,3;  Testosterona livre 2,68; Microalbuminúria 10,28 mg/g; Vitamina D 15,9; Anti-microssomal 0,3;  USG de abdome total (16/03/2016): esteatose hepática e colelitíase.  Ao exame: BEG, LOC, eupneica, hidratada, corada, afebril; PA 150/100;  FC 88; AC: RCR, 2T, BNF, SS; AP: MV presente, simétrico, bilateral, sem RA.  Análise: 1) DM tipo 2 descompensado. 2) Obesidade mórbida. 3) Micose em região genital?  Plano: prescrevo Glifage XR 500mg 1 cp à noite e Nesina 25mg 1 cp/dia. Forneço encaminhamento para pegar fitas de HGT no posto. Oriento consultar com ginecologista.  R1 CM Florence, Dr Vital Brasil.",
  "entities": {
    "Doença ou Síndrome": [
      "HAS",
      "colelitíase",
      "Micose",
      "Obesidade mórbida"
    ],
    "Abreviação": [
      "HAS",
      "cp",
      "HGT",
      "IMC",
      "BEG",
      "LOC",
      "PA",
      "FC",
      "AC",
      "RCR",
      "2T",
      "BNF",
      "SS",
      "AP",
      "MV presente"
    ],
    "Substância Química Orgânica": [
      "Atenolol",
      "Metformina",
      "Lexotam",
      "Nesina"
    ],
    "Substância Farmacológica": [
      "Atenolol",
      "Metformina",
      "Lexotam",
      "Nesina"
    ],
    "Procedimento Diagnóstico": [
      "HGT",
      "exame",
      "Análise"
    ],
    "Sinal ou Sintoma": [
      "nervosa",
      "coça-se",
      "afebril",
      "RA"
    ],
    "Atributo Clínico": [
      "Peso",
      "Altura",
      "IMC",
      "PA",
      "FC"
    ],
    "Conceito Quantitativo": [
      "112kg",
      "150/100",
      "88",
      "1 , 62m",
      "42 , 67"
    ],
    "Paciente ou Grupo com Deficiência": [
      "Paciente"
    ],
    "Negação": [
      "Não",
      "não",
      "afebril",
      "sem"
    ],
    "Procedimento Terapêutico ou Preventivo": [
      "controle"
    ],
    "Conceito Qualitativo": [
      "muito"
    ],
    "Procedimento Laboratorial": [
      "Laboratório"
    ],
    "Resultado Laboratorial ou de Teste": [
      "colelitíase",
      "Glicemia de jejum 129",
      "Creatinina 0 , 9",
      "TFG CKD-EPI 70",
      "Ureia 28",
      "Potássio 4 , 8",
      "Bilirrubina total 0 , 70",
      "Triglicerídeos 152",
      "Colesterol total 193",
      "LDL 121",
      "HDL 42",
      "TGP 39",
      "TGO 37",
      "RNI 1 , 09",
      "TTPA 0 , 95",
      "TSH ultrassensível 2 , 71",
      "T4 livre 1 , 32",
      "Prolactina 7 , 1",
      "Testosterona total 69 , 3",
      "Testosterona livre 2 , 68",
      "Microalbuminúria 10 , 28 mg/g",
      "Vitamina D 15 , 9",
      "Anti-microssomal 0 , 3"
    ],
    "Achado": [
      "BEG",
      "LOC",
      "eupneica",
      "hidratada",
      "corada",
      "RCR",
      "2T",
      "BNF",
      "SS",
      "simétrico",
      "bilateral",
      "MV presente"
    ],
    "Conceito Espacial": [
      "bilateral"
    ],
    "Produto Intelectual": [
      "Plano"
    ],
    "Atividade de Assistência à Saúde": [
      "prescrevo"
    ],
    "Organização Relacionada à Saúde": [
      "posto"
    ],
    "Grupo Profissional ou Ocupacional": [
      "ginecologista"
    ]
  },
  "labels": {
    "colelitíase": {
      "capitulo": "13"
    },
    "bnf": {
      "capitulo": "V"
    },
    "coça-se": {
      "capitulo": "21"
    },
    "micose": {
      "capitulo": "14"
    },
    "2t": {
      "capitulo": "21"
    },
    "loc": {
      "capitulo": "21"
    },
    "beg": {
      "capitulo": "21"
    },
    "ss": {
      "capitulo": "21"
    },
    "simétrico": {
      "capitulo": "21"
    },
    "has": {
      "capitulo": "11"
    },
    "ra": {
      "capitulo": "15"
    },
    "mv presente": {
      "capitulo": "21"
    },
    "nervosa": {
      "capitulo": "06"
    },
    "bilateral": {
      "capitulo": "21"
    },
    "obesidade mórbida": {
      "capitulo": "15"
    }
  }
}