{
  "prontuario_id": 316,
  "text": "44 ANOS HAS DESDE OS 17 ANOS, DM TIPO 2, HÁ 5 ANOS G 4 C 4 A0 LAQUEADURA CATETERISMO CARDÍACO HÁ 2 ANOS , EM PONTA GROSSA. SEM INDICAÇÃO ANGIOPLASTIA ARRITMIA DLP MISTA EX TABAGISTA , VOLTOU TABAGISMO HÁ 2 MESES (FUMAVA DESDE 9 ANOS) NEGA ALTERAÇÃO TIRÓIDE, IAM, AVE  EM USO AAS, ATENOLOL 50 2X, INDAPAMIDA 1,5 2 CP, ANLO 5 2X, ATENSINA 0,200 2X , hoje PESO 87 PA 160/100 MUCOSAS HIPOCORADAS CPP LIVRES ABDOME SP. ABO O SOROLOGIAS ANTIHBS NEG, TOXO NEG, CMV E EBV POSITIVO; DISLIPIDEMIA MISTA ECOCARDIO HVE MODERADA ECG FC 93, SINUSAL, ALT DIFUSA REPOLARIZAÇÃO TE NEGATIVO PARA ISQUEMIA DOPPLER PELVICO SP ECOGRAFIA ABDOME TOTAL > RINS ATROFICOS RX DE TORAX HAS DESCOMP. 28/05/2014> ECOGRAFIA> SINAIS DE NEFROPATIA CRONICA BILATERAL 15/04/2014>: CR 3,2 31/03/2015: CR 2,47, CL CR 42 12/06/2015: glico 79 , na 140 , ca 9,5 , ac urico 6,5 , cr 2,92 , k 5,2 , ureia 98 , p 5,5 , ht 41 , hb 14 , ph 7,23 , bic 21 p urina l 13mil , prot 100 17/08/2015: glicose 78 , na 141, ca 9,5 , ac urico 6.6 , cr 3,1 , k 6,1 , ur 85, ct 322, hdl 33, tg 547, p 6,2, ht 41, hb 14,6, p urina prot 100, hb gli 5,1, pth 58 ECOGRAFIA URINÁRIA > SINAIS DE NEFROPATIA BILATERAL 16/09/2015: PH 7,29 , BIC 18,6 . VHS 48 , UREIA 102 , HT 10 , HB 13,8 , GLICO 103 , CR 3,7, K 5,2 , P 5,1 26/02/16: CL CR CKD EPI 13ML/MIN ; cr 4,15 ; K 5,2",
  "entities": {
    "Doença ou Síndrome": [
      "HAS",
      "ARRITMIA",
      "TABAGISMO",
      "IAM",
      "AVE",
      "DM TIPO 2",
      "DLP MISTA",
      "DISLIPIDEMIA MISTA",
      "HAS DESCOMP",
      "SINAIS DE NEFROPATIA BILATERAL"
    ],
    "Abreviação": [
      "HAS",
      "IAM",
      "AVE",
      "AAS",
      "ANLO",
      "PA",
      "CPP",
      "SP",
      "ECOCARDIO",
      "ECG",
      "FC",
      "ECOGRAFIA&gt;",
      "DM TIPO 2",
      "DLP MISTA",
      "1 , 5 2 CP",
      "ABO O",
      "SOROLOGIAS ANTIHBS NEG",
      "TOXO NEG",
      "HVE MODERADA",
      "ALT DIFUSA REPOLARIZAÇÃO",
      "RX DE TORAX",
      "HAS DESCOMP",
      "CR 3 , 2",
      "CR 2 , 47",
      "CL CR 42",
      "glico 79",
      "na 140",
      "ca 9 , 5",
      "ac urico 6 , 5",
      "cr 2 , 92",
      "k 5 , 2",
      "p 5 , 5",
      "ht 41",
      "hb 14",
      "bic 21",
      "p urina",
      "l 13mil",
      "prot 100",
      "na 141",
      "ac urico 6",
      "cr 3 , 1",
      "k 6 , 1",
      "ur 85",
      "ct 322",
      "hdl 33",
      "tg 547",
      "p 6 , 2",
      "hb 14 , 6",
      "hb gli 5 , 1",
      "BIC 18 , 6",
      "HT 10",
      "HB 13 , 8",
      "GLICO 103",
      "CR 3 , 7",
      "K 5 , 2",
      "P 5 , 1",
      "cr 4 , 15"
    ],
    "Atributo Clínico": [
      "G",
      "PESO",
      "PA",
      "CPP",
      "FC"
    ],
    "Conceito Quantitativo": [
      "4",
      "87",
      "160/100",
      "93",
      "50 2X",
      "1 , 5 2 CP",
      "5 2X",
      "0 , 200 2X"
    ],
    "Procedimento Terapêutico ou Preventivo": [
      "C",
      "LAQUEADURA",
      "ANGIOPLASTIA",
      "CATETERISMO CARDÍACO"
    ],
    "Negação": [
      "SEM",
      "NEGA",
      "SP"
    ],
    "Atividade de Assistência à Saúde": [
      "INDICAÇÃO"
    ],
    "Sinal ou Sintoma": [
      "ARRITMIA",
      "ALTERAÇÃO",
      "MUCOSAS HIPOCORADAS",
      "SINAIS DE NEFROPATIA BILATERAL"
    ],
    "Parte do Corpo, Órgão ou Componente Orgânico": [
      "TIRÓIDE"
    ],
    "Substância Farmacológica": [
      "AAS",
      "ATENOLOL",
      "INDAPAMIDA",
      "ANLO",
      "ATENSINA"
    ],
    "Achado": [
      "LIVRES",
      "SP",
      "EX TABAGISTA"
    ],
    "Localização ou Região Corporal": [
      "ABDOME"
    ],
    "Vírus": [
      "CMV"
    ],
    "Procedimento Diagnóstico": [
      "ECOCARDIO",
      "ECG",
      "ECOGRAFIA&gt;",
      "DOPPLER PELVICO",
      "ECOGRAFIA ABDOME TOTAL",
      "RX DE TORAX",
      "p urina",
      "ECOGRAFIA URINÁRIA"
    ],
    "Resultado Laboratorial ou de Teste": [
      "SINUSAL",
      "SP",
      "ABO O",
      "SOROLOGIAS ANTIHBS NEG",
      "TOXO NEG",
      "EBV POSITIVO",
      "HVE MODERADA",
      "ALT DIFUSA REPOLARIZAÇÃO",
      "TE NEGATIVO PARA ISQUEMIA",
      "RINS ATROFICOS",
      "HAS DESCOMP",
      "SINAIS DE NEFROPATIA CRONICA BILATERAL",
      "CR 3 , 2",
      "CR 2 , 47",
      "CL CR 42",
      "glico 79",
      "na 140",
      "ca 9 , 5",
      "ac urico 6 , 5",
      "cr 2 , 92",
      "k 5 , 2",
      "ureia 98",
      "p 5 , 5",
      "ht 41",
      "hb 14",
      "ph 7 , 23",
      "bic 21",
      "l 13mil",
      "prot 100",
      "glicose 78",
      "na 141",
      "ac urico 6",
      "cr 3 , 1",
      "k 6 , 1",
      "ur 85",
      "ct 322",
      "hdl 33",
      "tg 547",
      "p 6 , 2",
      "hb 14 , 6",
      "p urina",
      "hb gli 5 , 1",
      "pth 58",
      "SINAIS DE NEFROPATIA BILATERAL",
      "PH 7 , 29",
      "BIC 18 , 6",
      "VHS 48",
      "UREIA 102",
      "HT 10",
      "HB 13 , 8",
      "GLICO 103",
      "CR 3 , 7",
      "K 5 , 2",
      "P 5 , 1",
      "CL CR CKD EPI 13ML/MIN",
      "cr 4 , 15"
    ],
    "Conceito Temporal": [
      "44 ANOS",
      "HÁ 5 ANOS",
      "HÁ 2 ANOS",
      "HÁ 2 MESES",
      "9 ANOS"
    ]
  },
  "labels": {
    "cmv": {
      "capitulo": "04"
    },
    "mucosas hipocoradas": {
      "capitulo": "14"
    },
    "tabagismo": {
      "capitulo": "11"
    },
    "has descomp": {
      "capitulo": "21"
    },
    "alteração": {
      "capitulo": "21"
    },
    "dislipidemia mista": {
      "capitulo": "05"
    },
    "dm tipo 2": {
      "capitulo": "11"
    },
    "sinais de nefropatia bilateral": {
      "capitulo": "16"
    },
    "arritmia": {
      "capitulo": "08"
    },
    "dlp mista": {
      "capitulo": "21"
    }
  }
}