{
  "prontuario_id": 391,
  "text": "43 ANOS HAS DESDE OS 17 ANOS, DM TIPO 2, HÁ 5 ANOS G 4 C 4 A0 LAQUEADURA CATETERISMO CARDÍACO HÁ 2 ANOS , EM PONTA GROSSA. SEM INDICAÇÃO ANGIOPLASTIA ARRITMIA DLP MISTA EX TABAGISTA , ,PAROU HÁ 6 MESES ( FUMAVA DESDE 9 ANOS ) NEGA ALTERAÇÃO TIRÓIDE, IAM, AVE EM USO DE LST 50 2X, AAS, ATENOLOL 50 2X, FUROSEMIDA 40 2cp  hoje PESO 82 PA 170/100 MUCOSAS HIPOCORADAS CPP LIVRES ABDOME SP ECOGRAFIA 28/05/2014 > SINAIS DE NEFROPATIA CRONICA BILATERAL 15/04/2014 >: CR 3,2 31/03/2015 TFG CKD-EPI  16.7 ml/min/1.73 m2 ; CR 2,47 TFG CKD-EPI 22.9 ml/min/1.73 m2 , CL CR 42 12/06/2015: glico 79, na 140, ca 9,5, ac urico 6,5, cr 2,92 TFG CKD-EPI 18.7 ml/min/1.73 m2 , k 5,2, ureia 98, p 5,5, ht 41, hb 14, ph 7,23, bic 21 p urina l 13mil, prot 100 17/08/2015 : glicose 78, na 141, ca 9,5, ac urico 6.6, cr 3,1 TFG CKD-EPI 17.4 ml/min/1.73 m2 , k 6,1, ur 85, ct 322, hdl 33, tg 547, p 6,2, ht 41, hb 14,6,  p urina  prot 100, hb gli 5,1, pth 58          ECOGRAFIA URINÁRIA > SINAIS DE NEFROPATIA BILATERAL. SUBSTITUO LASIX POR INDAPAMIDA, ACRESCENTO ANLODIPINA E ATENSINA SUSPENDO LST RETORNO 1 MES. HAS DESCOMPENSADA DRC SEVERA > HIPERCALEMIA DM REMISSÃO DLP DESCOMPENSADO.",
  "entities": {
    "Abreviação": [
      "HAS",
      "A0",
      "IAM",
      "AVE",
      "LST",
      "AAS",
      "2cp",
      "PA",
      "CPP",
      "SP",
      "DM TIPO 2",
      "DLP MISTA",
      "CR 2 , 47",
      "glico 79",
      "na 140",
      "ca 9 , 5",
      "ac urico 6 , 5",
      "cr 2 , 92",
      "k 5 , 2",
      "p 5 , 5",
      "ht 41",
      "hb 14",
      "bic 21",
      "p urina",
      "l 13mil",
      "prot 100",
      "na 141",
      "ac urico 6",
      "cr 3 , 1",
      "k 6 , 1",
      "ur 85",
      "ct 322",
      "tg 547",
      "p 6 , 2",
      "hb 14 , 6",
      "hb gli 5 , 1",
      "HAS DESCOMPENSADA",
      "DRC SEVERA",
      "DM REMISSÃO",
      "DLP DESCOMPENSADO"
    ],
    "Doença ou Síndrome": [
      "HAS",
      "ARRITMIA",
      "IAM",
      "AVE",
      "DM TIPO 2",
      "DLP MISTA",
      "NEFROPATIA CRONICA BILATERAL",
      "HAS DESCOMPENSADA",
      "DRC SEVERA",
      "DM REMISSÃO",
      "DLP DESCOMPENSADO"
    ],
    "Atributo Clínico": [
      "G",
      "PESO",
      "PA"
    ],
    "Conceito Quantitativo": [
      "4",
      "82",
      "170/100",
      "50 2X"
    ],
    "Procedimento Terapêutico ou Preventivo": [
      "C",
      "LAQUEADURA",
      "ANGIOPLASTIA",
      "CATETERISMO CARDÍACO"
    ],
    "Achado": [
      "A0",
      "LIVRES",
      "SP",
      "EX TABAGISTA"
    ],
    "Negação": [
      "SEM",
      "NEGA",
      "SP"
    ],
    "Atividade de Assistência à Saúde": [
      "INDICAÇÃO",
      "SUBSTITUO",
      "ACRESCENTO",
      "SUSPENDO",
      "RETORNO"
    ],
    "Sinal ou Sintoma": [
      "ARRITMIA",
      "ALTERAÇÃO",
      "HIPERCALEMIA",
      "MUCOSAS HIPOCORADAS"
    ],
    "Disfunção Mental ou Comportamental": [
      "FUMAVA"
    ],
    "Parte do Corpo, Órgão ou Componente Orgânico": [
      "TIRÓIDE"
    ],
    "Substância Farmacológica": [
      "LST",
      "AAS",
      "ATENOLOL",
      "FUROSEMIDA",
      "LASIX",
      "INDAPAMIDA",
      "ANLODIPINA",
      "ATENSINA"
    ],
    "Sistema Corporal": [
      "CPP"
    ],
    "Localização ou Região Corporal": [
      "ABDOME"
    ],
    "Procedimento Diagnóstico": [
      "ECOGRAFIA",
      "p urina",
      "ECOGRAFIA URINÁRIA"
    ],
    "Grupo Etário": [
      "43 ANOS"
    ],
    "Conceito Temporal": [
      "DESDE OS 17 ANOS",
      "HÁ 5 ANOS",
      "HÁ 2 ANOS",
      "HÁ 6 MESES"
    ],
    "Resultado Laboratorial ou de Teste": [
      "NEFROPATIA CRONICA BILATERAL",
      "CR 3 , 2",
      "TFG CKD-EPI 16",
      "CR 2 , 47",
      "TFG CKD-EPI 22",
      "CL CR 42",
      "glico 79",
      "na 140",
      "ca 9 , 5",
      "ac urico 6 , 5",
      "cr 2 , 92",
      "TFG CKD-EPI 18",
      "k 5 , 2",
      "ureia 98",
      "p 5 , 5",
      "ht 41",
      "hb 14",
      "ph 7 , 23",
      "bic 21",
      "l 13mil",
      "prot 100",
      "glicose 78",
      "na 141",
      "ac urico 6",
      "cr 3 , 1",
      "TFG CKD-EPI 17",
      "k 6 , 1",
      "ur 85",
      "ct 322",
      "hdl 33",
      "tg 547",
      "p 6 , 2",
      "hb 14 , 6",
      "hb gli 5 , 1",
      "pth 58",
      "SINAIS DE NEFROPATIA BILATERAL"
    ],
    "Procedimento Laboratorial": [
      "p urina"
    ]
  },
  "labels": {
    "a0": {
      "capitulo": "11"
    },
    "arritmia": {
      "capitulo": "08"
    },
    "iam": {
      "capitulo": "04"
    },
    "ex tabagista": {
      "capitulo": "24"
    },
    "dm remissão": {
      "capitulo": "05"
    },
    "dlp mista": {
      "capitulo": "04"
    },
    "hipercalemia": {
      "capitulo": "11"
    },
    "fumava": {
      "capitulo": "24"
    },
    "has": {
      "capitulo": "21"
    },
    "dlp descompensado": {
      "capitulo": "04"
    },
    "alteração": {
      "capitulo": "21"
    },
    "mucosas hipocoradas": {
      "capitulo": "14"
    },
    "has descompensada": {
      "capitulo": "21"
    },
    "nefropatia cronica bilateral": {
      "capitulo": "16"
    },
    "drc severa": {
      "capitulo": "11"
    },
    "dm tipo 2": {
      "capitulo": "05"
    }
  }
}