{
  "prontuario_id": 597,
  "text": "HÁ 20 ANOS EM ACOMPANHAMENTO POR CARDIOPATIA ( IAM COM ANGIOPLASTIA ), HÁ 3 ANOS SUBMETIDO A 3 PONTE DE SAFENA ELETIVAMENTE, POR CANSAÇO,DOR NO PEITO DE VARIADAS INTENSIDADES, INCLUSIVE AO REPOUSO.\nATUALMENTE APRESENTA CANSAÇO QUANDO CAMINHA EM TORNO DE UMA QUADRA, ASSOCIADO A DOR EMPATURRILHA BILATERAL QUE CESSA COM O REPOUSO, COM EDEMA DE MMI, AINDA APRESENTA DOR TORÁCICA DE LEVE INTENSIDADE COM CARACTERISTICAS DIFERENTEDA ANTERIOR. REFERE ENJOO\nEXAMES:\nECOCARDIOGRAMA 27/09/13\nCONCLUSÃO: HIPERTROFIADE VENTRICULO ESQUERDO,COM DIMENSOESAUMENTADAS E FUNÇÃO SISTOLICA COMPROMETIDA DE GRAU MODERADO, ACINESIA DE PAREDE INFERIOR  E HIPOCINESIANOS DEMAIS SEGMENTOS, ALTERAÇÃO DO RELAXAMENTO VENTRICULAR ESQUERDO.\nREGURGITAÇÃO MITRAL MODERADA, ATRIO ESQUERDO DILATADO.\nLABORATORIO: \nGLICEMIA: 385MG/DL\nCT: 237\nCREATININA 1,89\nHDL: 32\nTGO: 18\nLDL: 126\nCPK: 149\nK: 4,9\nNA: 136\nTGP: 10\nUREIA: 70\nHEMOGRAMA: SEM ALTERAÇÕES\nKPTT: 51 ( CONTROL 31 )\nTAP: MAIOR QUE 70\nTSH: 4,111\nLABORATORIO 10/05/13\nMICROALBUMINURIA: 9,89\n TIO CARDIOPATA\nEM USO DE AAS 100MG, LOSARTANA 50MG 2CP PELA MANHA 1 CP A TARDE, ESPIRONOLACTONA 25MG 1 CP PELA MANHA, AMIODARONA 200MG,1/2 CP DIA,  FUROSEMIDA 40MG 1CPPELAMANHA E 1/2CP A TARDE, MAREVAN 5MG 1 CP DOMINGO, SEGUNDA, QUARTA, QUINTA E SABADO E 1 CP E MEIO, TERÇAS E QUINTAS, CONCOR 5MG  1CP DIA)\nHAS DIABETES: INSULINA NÃO LEMBRA DOSE, E OUTRAS MEDICAÇÃO.\nCX: 6 CATETERISMO, 2 ANGIOSPLATIA, 3 PONTE DE SAFENA.\nNEGA ALERGIAS\nNEGA OUTRAS CIRURGAS E INTERNAMENTOS.\nACOMPANHAMENTO",
  "entities": {
    "Atividade de Assistência à Saúde": [
      "ACOMPANHAMENTO",
      "SUBMETIDO",
      "INTERNAMENTOS"
    ],
    "Doença ou Síndrome": [
      "CARDIOPATIA",
      "IAM",
      "CARDIOPATA",
      "HAS",
      "DIABETES"
    ],
    "Abreviação": [
      "IAM",
      "MMI",
      "AAS",
      "2CP",
      "1CPPELAMANHA",
      "1/2CP",
      "1CP",
      "HAS",
      "CX",
      "CT : 237",
      "HDL : 32",
      "TGO : 18",
      "LDL : 126",
      "CPK : 149",
      "K : 4 , 9",
      "NA : 136",
      "TGP : 10",
      "KPTT : 51 ( CONTROL 31 )",
      "TAP : MAIOR QUE 70",
      "TSH : 4 , 111",
      "1 CP",
      "1/2 CP",
      "1 CP E MEIO"
    ],
    "Procedimento Terapêutico ou Preventivo": [
      "ANGIOPLASTIA",
      "CX",
      "CATETERISMO",
      "ANGIOSPLATIA",
      "CIRURGAS",
      "INTERNAMENTOS",
      "PONTE DE SAFENA"
    ],
    "Sinal ou Sintoma": [
      "CANSAÇO",
      "EDEMA",
      "ENJOO",
      "ALTERAÇÕES",
      "DOR NO PEITO",
      "CANSAÇO QUANDO CAMINHA EM TORNO DE UMA QUADRA",
      "DOR TORÁCICA"
    ],
    "Parte do Corpo, Órgão ou Componente Orgânico": [
      "MMI",
      "EMPATURRILHA BILATERAL"
    ],
    "Procedimento Diagnóstico": [
      "EXAMES",
      "ECOCARDIOGRAMA"
    ],
    "Procedimento Laboratorial": [
      "LABORATORIO",
      "HEMOGRAMA"
    ],
    "Negação": [
      "SEM",
      "NÃO",
      "NEGA"
    ],
    "Grupo Familiar": [
      "TIO"
    ],
    "Substância Farmacológica": [
      "AAS",
      "LOSARTANA",
      "ESPIRONOLACTONA",
      "AMIODARONA",
      "FUROSEMIDA",
      "MAREVAN",
      "CONCOR",
      "INSULINA",
      "MEDICAÇÃO"
    ],
    "Substância Química Orgânica": [
      "AAS",
      "LOSARTANA",
      "ESPIRONOLACTONA",
      "AMIODARONA",
      "FUROSEMIDA",
      "MAREVAN",
      "CONCOR",
      "INSULINA"
    ],
    "Conceito Quantitativo": [
      "100MG",
      "50MG",
      "2CP",
      "25MG",
      "200MG",
      "40MG",
      "1CPPELAMANHA",
      "1/2CP",
      "5MG",
      "1CP",
      "6",
      "2",
      "3",
      "1 CP",
      "1/2 CP",
      "1 CP E MEIO"
    ],
    "Conceito Temporal": [
      "MANHA",
      "DIA",
      "HÁ 20 ANOS",
      "HÁ 3 ANOS",
      "A TARDE",
      "DOMINGO , SEGUNDA , QUARTA , QUINTA E SABADO",
      "TERÇAS E QUINTAS"
    ],
    "Hormônio": [
      "INSULINA"
    ],
    "Função Patológica": [
      "ALERGIAS"
    ],
    "Conceito Qualitativo": [
      "VARIADAS INTENSIDADES",
      "LEVE INTENSIDADE",
      "FUNÇÃO SISTOLICA COMPROMETIDA DE GRAU MODERADO"
    ],
    "Achado": [
      "CARACTERISTICAS DIFERENTEDA ANTERIOR",
      "LEMBRA DOSE"
    ],
    "Resultado Laboratorial ou de Teste": [
      "HIPERTROFIADE VENTRICULO ESQUERDO , COM DIMENSOESAUMENTADAS",
      "FUNÇÃO SISTOLICA COMPROMETIDA DE GRAU MODERADO",
      "ACINESIA DE PAREDE INFERIOR E HIPOCINESIANOS DEMAIS SEGMENTOS",
      "ALTERAÇÃO DO RELAXAMENTO VENTRICULAR ESQUERDO",
      "REGURGITAÇÃO MITRAL MODERADA",
      "ATRIO ESQUERDO DILATADO",
      "GLICEMIA : 385MG/DL",
      "CT : 237",
      "CREATININA 1 , 89",
      "HDL : 32",
      "TGO : 18",
      "LDL : 126",
      "CPK : 149",
      "K : 4 , 9",
      "NA : 136",
      "TGP : 10",
      "UREIA : 70",
      "KPTT : 51 ( CONTROL 31 )",
      "TAP : MAIOR QUE 70",
      "TSH : 4 , 111",
      "MICROALBUMINURIA : 9 , 89"
    ]
  },
  "labels": {
    "cansaço quando caminha em torno de uma quadra": {
      "capitulo": "11"
    },
    "dor torácica": {
      "capitulo": "11"
    },
    "cardiopata": {
      "capitulo": "11"
    },
    "cansaço": {
      "capitulo": "11"
    },
    "enjoo": {
      "capitulo": "22"
    },
    "alterações": {
      "capitulo": "21"
    },
    "cardiopatia": {
      "capitulo": "11"
    },
    "caracteristicas diferenteda anterior": {
      "capitulo": "21"
    },
    "dor no peito": {
      "capitulo": "11"
    },
    "diabetes": {
      "capitulo": "05"
    },
    "edema": {
      "capitulo": "15"
    },
    "iam": {
      "capitulo": "11"
    }
  }
}